Workbook

Sheet Main
A1: Master
B2: ABT
B3: Price | C3: 102.98 | D3: 9/21/2026
B4: SO | C4: 1730.383 | D4: Q2'26
B5: MC | C5: =C3*C4 -> 178194.84
B6: Cash | C6: =5104+499 -> 5603 | D6: Q2'26
B7: Debt | C7: 10036 | D7: Q2'26
B8: EV | C8: =C5-C6+C7 -> 182627.84
B10: Abbott Laboratories (ABT)
B12: Founder(s): | C12: Wallace Calvin Abbott | F12: Registered Exchange: NYSE | N12: Resources:
B13: Founded: 1888 | F13: Address: | G13: 100 Abbott Park Road, Abbott Park North Chicago, IL 60064 U.S. | N13: SEC filings | Q13: https://www.sec.gov/edgar/browse/?CIK=1800&owner=exclude
B14: Headquarters: Chicago, IL | F14: Investor Relations Contact: | N14: Abbott Labs Homepage | Q14: https://www.abbott.com/
B15: Current CEO: Robert Ford | F15: Investors Relation Department | O15: Abbott Labs IR Page | R15: https://www.abbott.com/investors.html
B16: Employees: 114,000 | F16: Phone: | G16: (224) 667-6100 | I16: Email: | J16: investor.relations@abbott.com | O16: Abbott Vascular Products | R16: https://www.cardiovascular.abbott/us/en/hcp/products.html
B17: Industry: Medical Devices - Pharmaceuticals | N17: Earnings Calls | Q17: https://seekingalpha.com/symbol/ABT/earnings/transcripts
B18: Sector: Healthcare | N18: Equity Analysis | Q18: https://stockanalysis.com/stocks/abt/company/
B19: IPO: 1929 … shortly before the start of the Great Depression | N19: MacroTrends | Q19: https://www.macrotrends.net/stocks/charts/ORCL/oracle/income-statement?freq=Q
B20: Fiscal Year: [January - December] | N20: ROIC, WACC | Q20: https://www.gurufocus.com/term/wacc/ABT
N21: Godel Terminal | Q21: https://app.godelterminal.com/
A22: Company Overview:
B23: Founded in 1888 and headquartered in Abbott Park, Illinois, Abbott Laboratories is a diversified global healthcare company that discovers, develops, manufactures, and sells a broad range of healthcare products
C24: Abbott operates across diagnostics, medical devices, nutrition, and branded generic pharmaceuticals segments
B25: Business Segments:
B26: Branded Generic Pharmaceuticals (Approx. 10-15% of Revenue)
C27: Focus on emerging and international markets, offering affordable branded generics for chronic conditions
C28: Management describes a significant growth opportunity as middle-income populations expand in key regions
B29: Nutrition (Approx. 20-25% of Revenue)
C30: Includes adult and pediatric nutritional products like Ensure (meal replacements) and Similac (infant formula)
B31: Diagnostics (Approx. 20-25% of Revenue)
C32: Products include laboratory-based testing instruments and assays, point-of-care diagnostics, blood glucose monitoring (FreeStyle Libre CGM), and molecular diagnostics
D33: Market leader in point-of-care testing, including COVID-19, infectious diseases, and cardiovascular diagnostics
C34: Strong innovation pipeline and expanding global footprint … big MNC presence
B35: Medical Devices (Approx. 35-40% of Revenue)
C36: Includes cardiovascular devices (stents, catheters), neuromodulation devices, diabetes care including CGMs, thrombectomy and other minimally invasive surgical products
D37: Emphasis on implantable cardiac rhythm management and vascular access … Direct competitive overlap with PEN in the thrombectomy & embolization space
C38: Beneficiary of increasing global demand for medical technology and aging populations … large and established japanese presence … kinda the primary case study along with South Korea in reguards to the developed world aging population problem
B39: Market leadership in diagnostics and strong positioning in CGM products (Freestyle Libre platform) … competing with Dexcom
B40: Diversified portfolio across high-growth healthcare segments balancing cyclical risks
C41: Steady demand through economic cycles … especially desirable in economically uncertian times … Bond like earnings prints … evaluate equity beta
C42: Powerful global brands such as Ensure and Similac provide resilience in adverse economic conditions
B43: Strong dividend cash return program … investigate dividend yeild and sustainability
A45: Business Segments and Geographical Info:
B46: [Begin researching fundamentals / core business … begin with SEC filings, but expand and use all public resources available]

Sheet Model
B1: [Use for Graphing] | AU1: Q1 2020 | AY1: Q1 2021 | BC1: Q1 2022 | BG1: Q1 2023 | BK1: Q1 2024 | BO1: Q1 2025 | BS1: Q1 2026
B2: Quarterly
B3: Revenues | C3: {="Q"&MOD(_xlfn.SEQUENCE(1,72)-1,4)+1&" "&(2009+INT((_xlfn.SEQUENCE(1,72)-1)/4))} -> Q1 2009 | D3: Q2 2009 | E3: Q3 2009 | F3: Q4 2009 | G3: Q1 2010 | H3: Q2 2010 | I3: Q3 2010 | J3: Q4 2010 | K3: Q1 2011 | L3: Q2 2011 | M3: Q3 2011 | N3: Q4 2011 | O3: Q1 2012 | P3: Q2 2012 | Q3: Q3 2012 | R3: Q4 2012 | S3: Q1 2013 | T3: Q2 2013 | U3: Q3 2013 | V3: Q4 2013 | W3: Q1 2014 | X3: Q2 2014 | Y3: Q3 2014 | Z3: Q4 2014 | AA3: Q1 2015 | AB3: Q2 2015 | AC3: Q3 2015 | AD3: Q4 2015 | AE3: Q1 2016 | AF3: Q2 2016 | AG3: Q3 2016 | AH3: Q4 2016 | AI3: Q1 2017 | AJ3: Q2 2017 | AK3: Q3 2017 | AL3: Q4 2017 | AM3: Q1 2018 | AN3: Q2 2018 | AO3: Q3 2018 | AP3: Q4 2018 | AQ3: Q1 2019 | AR3: Q2 2019 | AS3: Q3 2019 | AT3: Q4 2019 | AU3: Q1 2020 | AV3: Q2 2020 | AW3: Q3 2020 | AX3: Q4 2020 | AY3: Q1 2021 | AZ3: Q2 2021 | BA3: Q3 2021 | BB3: Q4 2021 | BC3: Q1 2022 | BD3: Q2 2022 | BE3: Q3 2022 | BF3: Q4 2022 | BG3: Q1 2023 | BH3: Q2 2023 | BI3: Q3 2023 | BJ3: Q4 2023 | BK3: Q1 2024 | BL3: Q2 2024 | BM3: Q3 2024 | BN3: Q4 2024 | BO3: Q1 2025 | BP3: Q2 2025 | BQ3: Q3 2025 | BR3: Q4 2025 | BS3: Q1 2026 | BT3: Q2 2026 | BU3: Q3 2026 | BV3: Q4 2026 | CA3: 2009 | CB3: =CA3+1 -> 2010 | CC3: =CB3+1 -> 2011 | CD3: =CC3+1 -> 2012 | CE3: =CD3+1 -> 2013 | CF3: =CE3+1 -> 2014 | CG3: =CF3+1 -> 2015 | CH3: =CG3+1 -> 2016 | CI3: =CH3+1 -> 2017 | ... EX3: =EW3+1 -> 2084
B4: Ttl Established Pharma Product Revenues | AU4: 1044 | AV4: 1013 | AW4: 1099 | AX4: =4303-SUM(AU4:AW4) -> 1147 | AY4: 1070 | AZ4: 1180 | BA4: 1265 | BB4: =4718-SUM(AY4:BA4) -> 1203 | BC4: 1147 | BD4: =1223 -> 1223 | BE4: 1326 | BF4: =3766+1146-SUM(BC4:BE4) -> 1216 | BG4: 1189 | BH4: 1287 | BI4: 1368 | BJ4: =3807+1259-SUM(BG4:BI4) -> 1222 | BK4: 1226 | BL4: 1294 | BM4: 1406 | BN4: =3858+1336-SUM(BK4:BM4) -> 1268 | BO4: 1260 | BP4: 1383 | BQ4: 1511 | BR4: =1046+336 -> 1382 | BS4: 1426 | BT4: 1426 | CL4: =SUM(AU4:AX4) -> 4303 | CM4: =SUM(AY4:BB4) -> 4718 | CN4: =SUM(BC4:BF4) -> 4912 | CO4: =SUM(BG4:BJ4) -> 5066 | CP4: =SUM(BK4:BN4) -> 5194 | CQ4: =SUM(BO4:BR4) -> 5536 | CR4: =CQ4*(1+CR24) -> 6255.68 | CS4: =CR4*(1+CS24) -> 6943.8048 | CT4: =CS4*(1+CT24) -> 7603.4663 | CU4: =CT4*(1+CU24) -> 8211.7436 | CV4: =CU4*(1+CV24) -> 8827.6243 | CW4: =CV4*(1+CW24) -> 9445.558 | CX4: =CW4*(1+CX24) -> 10059.519 | CY4: =CX4*(1+CY24) -> 10562.495 | CZ4: =CY4*(1+CZ24) -> 11037.808
B5: Pediatric Nutritionals | AU5: 1089 | AV5: 1024 | AW5: 1006 | AX5: =4127-SUM(AU5:AW5) -> 1008 | AY5: 1066 | AZ5: 1093 | BA5: 1100 | BB5: =4298-SUM(AY5:BA5) -> 1039 | BC5: 847 | BD5: 925 | BE5: 827 | BF5: =1919+1562-SUM(BC5:BE5) -> 882 | BG5: 924 | BH5: 1024 | BI5: 1001 | BJ5: =3934-SUM(BG5:BI5) -> 985 | BK5: 1009 | BL5: 1059 | BM5: 955 | BN5: =1815+2208-SUM(BK5:BM5) -> 1000 | BO5: 1041 | BP5: 1054 | BQ5: 977 | BR5: =3974-SUM(BO5:BQ5) -> 902 | BS5: 953 | BT5: 953 | CL5: =SUM(AU5:AX5) -> 4127 | CM5: =SUM(AY5:BB5) -> 4298 | CN5: =SUM(BC5:BF5) -> 3481 | CO5: =SUM(BG5:BJ5) -> 3934 | CP5: =SUM(BK5:BN5) -> 4023 | CQ5: =SUM(BO5:BR5) -> 3974 | CR5: =CQ5*(1+CR25) -> 4343.582 | CS5: =CR5*(1+CS25) -> 3822.3522 | CT5: =CS5*(1+CT25) -> 3593.011 | CU5: =CT5*(1+CU25) -> 3413.3605 | CV5: =CU5*(1+CV25) -> 3457.7342 | CW5: =CV5*(1+CW25) -> 3502.6847 | CX5: =CW5*(1+CX25) -> 3548.2196 | CY5: =CX5*(1+CY25) -> 3590.7982 | CZ5: =CY5*(1+CZ25) -> 3633.8878
B6: Adult Nutritionals | AU6: 815 | AV6: 859 | AW6: 918 | AX6: =3520-SUM(AU6:AW6) -> 928 | AY6: 970 | AZ6: 1015 | BA6: 1008 | BB6: =3996-SUM(AY6:BA6) -> 1003 | BC6: 1047 | BD6: 1028 | BE6: 968 | BF6: =2621+1357-SUM(BC6:BE6) -> 935 | BG6: 1043 | BH6: 1052 | BI6: 1072 | BJ6: =4220-SUM(BG6:BI6) -> 1053 | BK6: 1059 | BL6: 1091 | BM6: 1111 | BN6: =2909+1481-SUM(BK6:BM6) -> 1129 | BO6: 1105 | BP6: 1158 | BQ6: 1176 | BR6: =3029+1448-SUM(BO6:BQ6) -> 1038 | BS6: 1064 | BT6: 1064 | CL6: =SUM(AU6:AX6) -> 3520 | CM6: =SUM(AY6:BB6) -> 3996 | CN6: =SUM(BC6:BF6) -> 3978 | CO6: =SUM(BG6:BJ6) -> 4220 | CP6: =SUM(BK6:BN6) -> 4390 | CQ6: =SUM(BO6:BR6) -> 4477 | CR6: =CQ6*(1+CR26) -> 4208.38 | CS6: =CR6*(1+CS26) -> 3913.7934 | CT6: =CS6*(1+CT26) -> 3718.1037 | CU6: =CT6*(1+CU26) -> 3643.7417 | CV6: =CU6*(1+CV26) -> 3680.1791 | CW6: =CV6*(1+CW26) -> 3753.7827 | CX6: =CW6*(1+CX26) -> 3922.7029 | CY6: =CX6*(1+CY26) -> 4079.611 | CZ6: =CY6*(1+CZ26) -> 4201.9993
B7: Ttl Nutritionals Revenues | AU7: =SUM(AU5:AU6) -> 1904 | AV7: =SUM(AV5:AV6) -> 1883 | AW7: =SUM(AW5:AW6) -> 1924 | AX7: =SUM(AX5:AX6) -> 1936 | AY7: =SUM(AY5:AY6) -> 2036 | AZ7: =SUM(AZ5:AZ6) -> 2108 | BA7: =SUM(BA5:BA6) -> 2108 | BB7: =SUM(BB5:BB6) -> 2042 | ... BT7: =SUM(BT5:BT6) -> 2017 | CL7: =SUM(AU7:AX7) -> 7647 | CM7: =SUM(AY7:BB7) -> 8294 | CN7: =SUM(BC7:BF7) -> 7459 | CO7: =SUM(BG7:BJ7) -> 8154 | CP7: =SUM(BK7:BN7) -> 8413 | CQ7: =SUM(BO7:BR7) -> 8451 | CR7: =SUM(CR5:CR6) -> 8551.962 | CS7: =SUM(CS5:CS6) -> 7736.1456 | CT7: =SUM(CT5:CT6) -> 7311.1148 | CU7: =SUM(CU5:CU6) -> 7057.1021 | CV7: =SUM(CV5:CV6) -> 7137.9132 | CW7: =SUM(CW5:CW6) -> 7256.4674 | CX7: =SUM(CX5:CX6) -> 7470.9225 | CY7: =SUM(CY5:CY6) -> 7670.4092 | CZ7: =SUM(CZ5:CZ6) -> 7835.8871
B8: Core Lab | AU8: 989 | AV8: 987 | AW8: 1176 | AX8: =4475-SUM(AU8:AW8) -> 1323 | AY8: 1182 | AZ8: 1306 | BA8: 1292 | BB8: =5128-SUM(AY8:BA8) -> 1348 | BC8: 1184 | BD8: 1221 | BE8: 1219 | BF8: =4888-SUM(BC8:BE8) -> 1264 | BG8: 1182 | BH8: 1293 | BI8: 1314 | BJ8: =5159-SUM(BG8:BI8) -> 1370 | BK8: 1205 | BL8: 1329 | BM8: 1314 | BN8: =5235-SUM(BK8:BM8) -> 1387 | BO8: 1177 | BP8: 1358 | BQ8: 1364 | BR8: 1461 | BS8: 1272 | BT8: 1272 | CL8: =SUM(AU8:AX8) -> 4475 | CM8: =SUM(AY8:BB8) -> 5128 | CN8: =SUM(BC8:BF8) -> 4888 | CO8: =SUM(BG8:BJ8) -> 5159 | CP8: =SUM(BK8:BN8) -> 5235 | CQ8: =SUM(BO8:BR8) -> 5360 | CR8: =CQ8*(1+CR28) -> 5547.6 | CS8: =CR8*(1+CS28) -> 5625.2664 | CT8: =CS8*(1+CT28) -> 5704.0201 | CU8: =CT8*(1+CU28) -> 5778.1724 | CV8: =CU8*(1+CV28) -> 5853.2886 | CW8: =CV8*(1+CW28) -> 5923.5281 | CX8: =CW8*(1+CX28) -> 5994.6104 | CY8: =CX8*(1+CY28) -> 6060.5511 | CZ8: =CY8*(1+CZ28) -> 6127.2172
B9: Molecular | AU9: 139 | AV9: 359 | AW9: 458 | AX9: =1438-SUM(AU9:AW9) -> 482 | AY9: 447 | AZ9: 290 | BA9: 345 | BB9: =1427-SUM(AY9:BA9) -> 345 | BC9: 420 | BD9: 212 | BE9: 183 | BF9: =995-SUM(BC9:BE9) -> 180 | BG9: 147 | BH9: 141 | BI9: 133 | BJ9: =574-SUM(BG9:BI9) -> 153 | BK9: 129 | BL9: 127 | BM9: 128 | BN9: =521-SUM(BK9:BM9) -> 137 | BO9: 122 | BP9: 123 | BQ9: 131 | BR9: 141 | BS9: 149 | BT9: 149 | CL9: =SUM(AU9:AX9) -> 1438 | CM9: =SUM(AY9:BB9) -> 1427 | CN9: =SUM(BC9:BF9) -> 995 | CO9: =SUM(BG9:BJ9) -> 574 | CP9: =SUM(BK9:BN9) -> 521 | CQ9: =SUM(BO9:BR9) -> 517 | CR9: =CQ9*(1+CR29) -> 625.57 | CS9: =CR9*(1+CS29) -> 744.4283 | CT9: =CS9*(1+CT29) -> 863.53683 | CU9: =CT9*(1+CU29) -> 993.06735 | CV9: =CU9*(1+CV29) -> 1132.0968 | CW9: =CV9*(1+CW29) -> 1279.2694 | CX9: =CW9*(1+CX29) -> 1439.178 | CY9: =CX9*(1+CY29) -> 1611.8794 | CZ9: =CY9*(1+CZ29) -> 1797.2455
B10: Point of Care | AU10: 138 | AV10: 118 | AW10: 131 | AX10: =516-SUM(AU10:AW10) -> 129 | AY10: 129 | AZ10: 137 | BA10: 135 | BB10: =536-SUM(AY10:BA10) -> 135 | BC10: 128 | BD10: 139 | BE10: 127 | BF10: =525-SUM(BC10:BE10) -> 131 | BG10: 134 | BH10: 142 | BI10: 140 | BJ10: =565-SUM(BG10:BI10) -> 149 | BK10: 139 | BL10: 156 | BM10: 146 | BN10: =588-SUM(BK10:BM10) -> 147 | BO10: 142 | BP10: 148 | BQ10: 158 | BR10: 158 | BS10: 96 | BT10: 96 | CL10: =SUM(AU10:AX10) -> 516 | CM10: =SUM(AY10:BB10) -> 536 | CN10: =SUM(BC10:BF10) -> 525 | CO10: =SUM(BG10:BJ10) -> 565 | CP10: =SUM(BK10:BN10) -> 588 | CQ10: =SUM(BO10:BR10) -> 606 | CR10: =CQ10*(1+CR30) -> 412.08 | CS10: =CR10*(1+CS30) -> 296.6976 | CT10: =CS10*(1+CT30) -> 314.49946 | CU10: =CT10*(1+CU30) -> 331.79693 | CV10: =CU10*(1+CV30) -> 349.21626 | CW10: =CV10*(1+CW30) -> 366.67708 | CX10: =CW10*(1+CX30) -> 384.09424 | CY10: =CX10*(1+CY30) -> 401.37848 | CZ10: =CY10*(1+CZ30) -> 418.43707
B11: Rapid Diagnostics | AU11: 560 | AV11: 530 | AW11: 875 | AX11: =4376-SUM(AU11:AW11) -> 2411 | AY11: 2256 | AZ11: 1514 | BA11: 2140 | BB11: =8553-SUM(AY11:BA11) -> 2643 | BC11: 3525 | BD11: 2722 | BE11: 2112 | BF11: =10061-SUM(BC11:BE11) -> 1702 | BG11: 1225 | BH11: 741 | BI11: 862 | BJ11: =3690-SUM(BG11:BI11) -> 862 | BK11: 741 | BL11: 583 | BM11: 824 | BN11: =2997-SUM(BK11:BM11) -> 849 | BO11: 613 | BP11: 544 | BQ11: 600 | BR11: 697 | BS11: 663 | BT11: 663 | CL11: =SUM(AU11:AX11) -> 4376 | CM11: =SUM(AY11:BB11) -> 8553 | CN11: =SUM(BC11:BF11) -> 10061 | CO11: =SUM(BG11:BJ11) -> 3690 | CP11: =SUM(BK11:BN11) -> 2997 | CQ11: =SUM(BO11:BR11) -> 2454 | CR11: =CQ11*(1+CR31) -> 2871.18 | CS11: =CR11*(1+CS31) -> 3474.1278 | CT11: =CS11*(1+CT31) -> 4238.4359 | CU11: =CT11*(1+CU31) -> 5001.3544 | CV11: =CU11*(1+CV31) -> 5801.5711 | CW11: =CV11*(1+CW31) -> 6671.8067 | CX11: =CW11*(1+CX31) -> 7605.8597 | CY11: =CX11*(1+CY31) -> 8594.6214 | CZ11: =CY11*(1+CZ31) -> 9625.976
B12: Ttl Diagnostics Revenues | AU12: =SUM(AU8:AU11) -> 1826 | AV12: =SUM(AV8:AV11) -> 1994 | AW12: =SUM(AW8:AW11) -> 2640 | AX12: =SUM(AX8:AX11) -> 4345 | AY12: =SUM(AY8:AY11) -> 4014 | AZ12: =SUM(AZ8:AZ11) -> 3247 | BA12: =SUM(BA8:BA11) -> 3912 | BB12: =SUM(BB8:BB11) -> 4471 | ... BT12: =SUM(BT8:BT11) -> 2180 | CL12: =SUM(AU12:AX12) -> 10805 | CM12: =SUM(AY12:BB12) -> 15644 | CN12: =SUM(BC12:BF12) -> 16469 | CO12: =SUM(BG12:BJ12) -> 9988 | CP12: =SUM(BK12:BN12) -> 9341 | CQ12: =SUM(BO12:BR12) -> 8937 | CR12: =SUM(CR8:CR11) -> 9456.43 | CS12: =SUM(CS8:CS11) -> 10140.52 | CT12: =SUM(CT8:CT11) -> 11120.492 | CU12: =SUM(CU8:CU11) -> 12104.391 | CV12: =SUM(CV8:CV11) -> 13136.173 | CW12: =SUM(CW8:CW11) -> 14241.281 | CX12: =SUM(CX8:CX11) -> 15423.742 | CY12: =SUM(CY8:CY11) -> 16668.43 | CZ12: =SUM(CZ8:CZ11) -> 17968.876
B13: Rhythm Management | AU13: 474 | AV13: 401 | AW13: 507 | AX13: =1914-SUM(AU13:AW13) -> 532 | AY13: 519 | AZ13: 567 | BA13: 571 | BB13: =2198-SUM(AY13:BA13) -> 541 | BC13: 524 | BD13: 548 | BE13: 533 | BF13: =2119-SUM(BC13:BE13) -> 514 | BG13: 527 | BH13: 583 | BI13: 563 | BJ13: =2255-SUM(BG13:BI13) -> 582 | BK13: 562 | BL13: 607 | BM13: 597 | BN13: =2390-SUM(BK13:BM13) -> 624 | BO13: 585 | BP13: 673 | BQ13: 686 | BR13: 705 | BS13: 684 | BT13: 684 | CL13: =SUM(AU13:AX13) -> 1914 | CM13: =SUM(AY13:BB13) -> 2198 | CN13: =SUM(BC13:BF13) -> 2119 | CO13: =SUM(BG13:BJ13) -> 2255 | CP13: =SUM(BK13:BN13) -> 2390 | CQ13: =SUM(BO13:BR13) -> 2649 | CR13: =CQ13*(1+CR33) -> 2999.9925 | CS13: =CR13*(1+CS33) -> 3359.9916 | CT13: =CS13*(1+CT33) -> 3729.5907 | CU13: =CT13*(1+CU33) -> 4121.1977 | CV13: =CU13*(1+CV33) -> 4492.1055 | CW13: =CV13*(1+CW33) -> 4829.0134 | CX13: =CW13*(1+CX33) -> 5118.7542 | CY13: =CX13*(1+CY33) -> 5374.6919 | CZ13: =CY13*(1+CZ33) -> 5589.6796
B14: Electrophysiology | AU14: 388 | AV14: 299 | AW14: 441 | AX14: =1578-SUM(AU14:AW14) -> 450 | AY14: 431 | AZ14: 487 | BA14: 485 | BB14: =1907-SUM(AY14:BA14) -> 504 | BC14: 485 | BD14: 486 | BE14: 469 | BF14: =1927-SUM(BC14:BE14) -> 487 | BG14: 505 | BH14: 553 | BI14: 544 | BJ14: =2195-SUM(BG14:BI14) -> 593 | BK14: 587 | BL14: 627 | BM14: 610 | BN14: =2467-SUM(BK14:BM14) -> 643 | BO14: 629 | BP14: 700 | BQ14: 705 | BR14: 730 | BS14: 788 | BT14: 788 | CL14: =SUM(AU14:AX14) -> 1578 | CM14: =SUM(AY14:BB14) -> 1907 | CN14: =SUM(BC14:BF14) -> 1927 | CO14: =SUM(BG14:BJ14) -> 2195 | CP14: =SUM(BK14:BN14) -> 2467 | CQ14: =SUM(BO14:BR14) -> 2764 | CR14: =CQ14*(1+CR34) -> 3372.08 | CS14: =CR14*(1+CS34) -> 3945.3336 | CT14: =CS14*(1+CT34) -> 4576.587 | CU14: =CT14*(1+CU34) -> 5285.958 | CV14: =CU14*(1+CV34) -> 6052.4219 | CW14: =CV14*(1+CW34) -> 6839.2367 | CX14: =CW14*(1+CX34) -> 7591.5527 | CY14: =CX14*(1+CY34) -> 8236.8347 | CZ14: =CY14*(1+CZ34) -> 8772.229
B15: Heart Failure | AU15: 203 | AV15: 158 | AW15: 190 | AX15: =740-SUM(AU15:AW15) -> 189 | AY15: 194 | AZ15: 227 | BA15: 229 | BB15: =889-SUM(AY15:BA15) -> 239 | BC15: 250 | BD15: 269 | BE15: 258 | BF15: =1035-SUM(BC15:BE15) -> 258 | BG15: 281 | BH15: 295 | BI15: 284 | BJ15: =1161-SUM(BG15:BI15) -> 301 | BK15: 305 | BL15: 321 | BM15: 322 | BN15: =1279-SUM(BK15:BM15) -> 331 | BO15: 339 | BP15: 368 | BQ15: 366 | BR15: 375 | BS15: 389 | BT15: 389 | CL15: =SUM(AU15:AX15) -> 740 | CM15: =SUM(AY15:BB15) -> 889 | CN15: =SUM(BC15:BF15) -> 1035 | CO15: =SUM(BG15:BJ15) -> 1161 | CP15: =SUM(BK15:BN15) -> 1279 | CQ15: =SUM(BO15:BR15) -> 1448 | CR15: =CQ15*(1+CR35) -> 1629 | CS15: =CR15*(1+CS35) -> 1791.9 | CT15: =CS15*(1+CT35) -> 1935.252 | CU15: =CT15*(1+CU35) -> 2051.3671 | CV15: =CU15*(1+CV35) -> 2153.9355 | CW15: =CV15*(1+CW35) -> 2240.0929 | CX15: =CW15*(1+CX35) -> 2307.2957 | CY15: =CX15*(1+CY35) -> 2353.4416 | CZ15: =CY15*(1+CZ35) -> 2388.7432
B16: Vascular | AU16: 625 | AV16: 481 | AW16: 630 | AX16: =2339-SUM(AU16:AW16) -> 603 | AY16: 635 | AZ16: 697 | BA16: 644 | BB16: =2654-SUM(AY16:BA16) -> 678 | BC16: 619 | BD16: 653 | BE16: 606 | BF16: =2483-SUM(BC16:BE16) -> 605 | BG16: 617 | BH16: 715 | BI16: 672 | BJ16: =2681-SUM(BG16:BI16) -> 677 | BK16: 689 | BL16: 724 | BM16: 699 | BN16: =2837-SUM(BK16:BM16) -> 725 | BO16: 710 | BP16: 757 | BQ16: 745 | BR16: 783 | BS16: 777 | BT16: 777 | CL16: =SUM(AU16:AX16) -> 2339 | CM16: =SUM(AY16:BB16) -> 2654 | CN16: =SUM(BC16:BF16) -> 2483 | CO16: =SUM(BG16:BJ16) -> 2681 | CP16: =SUM(BK16:BN16) -> 2837 | CQ16: =SUM(BO16:BR16) -> 2995 | CR16: =CQ16*(1+CR36) -> 3264.55 | CS16: =CR16*(1+CS36) -> 3525.714 | CT16: =CS16*(1+CT36) -> 3772.514 | CU16: =CT16*(1+CU36) -> 3998.8648 | CV16: =CU16*(1+CV36) -> 4198.8081 | CW16: =CV16*(1+CW36) -> 4366.7604 | CX16: =CW16*(1+CX36) -> 4497.7632 | CY16: =CX16*(1+CY36) -> 4587.7185 | CZ16: =CY16*(1+CZ36) -> 4633.5956
B17: Structural Heart | AU17: 318 | AV17: 223 | AW17: 353 | AX17: =1247-SUM(AU17:AW17) -> 353 | AY17: 377 | AZ17: 422 | BA17: 392 | BB17: =1610-SUM(AY17:BA17) -> 419 | BC17: 411 | BD17: 440 | BE17: 420 | BF17: =1712-SUM(BC17:BE17) -> 441 | BG17: 461 | BH17: 498 | BI17: 487 | BJ17: =1944-SUM(BG17:BI17) -> 498 | BK17: 515 | BL17: 564 | BM17: 558 | BN17: =2246-SUM(BK17:BM17) -> 609 | BO17: 577 | BP17: 636 | BQ17: 635 | BR17: 675 | BS17: 578 | BT17: 578 | CL17: =SUM(AU17:AX17) -> 1247 | CM17: =SUM(AY17:BB17) -> 1610 | CN17: =SUM(BC17:BF17) -> 1712 | CO17: =SUM(BG17:BJ17) -> 1944 | CP17: =SUM(BK17:BN17) -> 2246 | CQ17: =SUM(BO17:BR17) -> 2523 | CR17: =CQ17*(1+CR37) -> 2422.08 | CS17: =CR17*(1+CS37) -> 2397.8592 | CT17: =CS17*(1+CT37) -> 2565.7093 | CU17: =CT17*(1+CU37) -> 2796.6232 | CV17: =CU17*(1+CV37) -> 3090.2686 | CW17: =CV17*(1+CW37) -> 3368.3928 | CX17: =CW17*(1+CX37) -> 3621.0223 | CY17: =CX17*(1+CY37) -> 3838.2836 | CZ17: =CY17*(1+CZ37) -> 4011.0064
B18: Neuromodulation | AU18: 177 | AV18: 106 | AW18: 206 | AX18: =702-SUM(AU18:AW18) -> 213 | AY18: 184 | AZ18: 210 | BA18: 190 | BB18: =781-SUM(AY18:BA18) -> 197 | BC18: 179 | BD18: 197 | BE18: 192 | BF18: =770-SUM(BC18:BE18) -> 202 | BG18: 196 | BH18: 227 | BI18: 227 | BJ18: =890-SUM(BG18:BI18) -> 240 | BK18: 226 | BL18: 243 | BM18: 236 | BN18: =962-SUM(BK18:BM18) -> 257 | BO18: 228 | BP18: 254 | BQ18: 254 | BR18: 274 | BS18: 243 | BT18: 243 | CL18: =SUM(AU18:AX18) -> 702 | CM18: =SUM(AY18:BB18) -> 781 | CN18: =SUM(BC18:BF18) -> 770 | CO18: =SUM(BG18:BJ18) -> 890 | CP18: =SUM(BK18:BN18) -> 962 | CQ18: =SUM(BO18:BR18) -> 1010 | CR18: =CQ18*(1+CR38) -> 1040.3 | CS18: =CR18*(1+CS38) -> 1087.1135 | CT18: =CS18*(1+CT38) -> 1152.3403 | CU18: =CT18*(1+CU38) -> 1227.2424 | CV18: =CU18*(1+CV38) -> 1300.877 | CW18: =CV18*(1+CW38) -> 1372.4252 | CX18: =CW18*(1+CX38) -> 1434.1843 | CY18: =CX18*(1+CY38) -> 1484.3808 | CZ18: =CY18*(1+CZ38) -> 1521.4903
B19: Diabetes Care | AU19: 752 | AV19: 755 | AW19: 843 | AX19: =3267-SUM(AU19:AW19) -> 917 | AY19: 980 | AZ19: 1056 | BA19: 1121 | BB19: =4328-SUM(AY19:BA19) -> 1171 | BC19: 1126 | BD19: 1192 | BE19: 1167 | BF19: =4756-SUM(BC19:BE19) -> 1271 | BG19: 1313 | BH19: 1424 | BI19: 1472 | BJ19: =5761-SUM(BG19:BI19) -> 1552 | BK19: 1569 | BL19: 1648 | BM19: 1725 | BN19: =6805-SUM(BK19:BM19) -> 1863 | BO19: 1827 | BP19: 1981 | BQ19: 2057 | BR19: 2133 | BS19: 2080 | BT19: 2080 | CL19: =SUM(AU19:AX19) -> 3267 | CM19: =SUM(AY19:BB19) -> 4328 | CN19: =SUM(BC19:BF19) -> 4756 | CO19: =SUM(BG19:BJ19) -> 5761 | CP19: =SUM(BK19:BN19) -> 6805 | CQ19: =SUM(BO19:BR19) -> 7998 | CR19: =CQ19*(1+CR39) -> 9117.72 | CS19: =CR19*(1+CS39) -> 10713.321 | CT19: =CS19*(1+CT39) -> 12641.719 | CU19: =CT19*(1+CU39) -> 14537.977 | CV19: =CU19*(1+CV39) -> 16427.914 | CW19: =CV19*(1+CW39) -> 18234.984 | CX19: =CW19*(1+CX39) -> 19876.133 | CY19: =CX19*(1+CY39) -> 21267.462 | CZ19: =CY19*(1+CZ39) -> 22543.51
B20: Ttl Med Device Revenues | AU20: =SUM(AU13:AU19) -> 2937 | AV20: =SUM(AV13:AV19) -> 2423 | AW20: =SUM(AW13:AW19) -> 3170 | AX20: =SUM(AX13:AX19) -> 3257 | AY20: =SUM(AY13:AY19) -> 3320 | AZ20: =SUM(AZ13:AZ19) -> 3666 | BA20: =SUM(BA13:BA19) -> 3632 | BB20: =SUM(BB13:BB19) -> 3749 | ... BT20: =SUM(BT13:BT19) -> 5539 | CL20: =SUM(AU20:AX20) -> 11787 | CM20: =SUM(AY20:BB20) -> 14367 | CN20: =SUM(BC20:BF20) -> 14802 | CO20: =SUM(BG20:BJ20) -> 16887 | CP20: =SUM(BK20:BN20) -> 18986 | CQ20: =SUM(BO20:BR20) -> 21387 | CR20: =SUM(CR13:CR19) -> 23845.723 | CS20: =SUM(CS13:CS19) -> 26821.233 | CT20: =SUM(CT13:CT19) -> 30373.712 | CU20: =SUM(CU13:CU19) -> 34019.23 | CV20: =SUM(CV13:CV19) -> 37716.33 | CW20: =SUM(CW13:CW19) -> 41250.905 | CX20: =SUM(CX13:CX19) -> 44446.705 | CY20: =SUM(CY13:CY19) -> 47142.813 | CZ20: =SUM(CZ13:CZ19) -> 49460.254
B21: Other Revenues | AU21: 15 | AV21: 15 | AW21: 20 | AX21: =66-SUM(AU21:AW21) -> 16 | AY21: 16 | AZ21: 22 | BA21: 11 | BB21: =52-SUM(AY21:BA21) -> 3 | BC21: 3 | BD21: 2 | BE21: 3 | BF21: =11-SUM(BC21:BE21) -> 3 | BG21: 3 | BH21: 3 | BI21: 4 | BJ21: =14-SUM(BG21:BI21) -> 4 | BK21: 3 | BL21: 4 | BM21: 4 | BN21: =16-SUM(BK21:BM21) -> 5 | BO21: 3 | BP21: 5 | BQ21: 4 | BR21: =17-SUM(BO21:BQ21) -> 5 | BS21: 2 | BT21: 2 | CL21: =SUM(AU21:AX21) -> 66 | CM21: =SUM(AY21:BB21) -> 52 | CN21: =SUM(BC21:BF21) -> 11 | CO21: =SUM(BG21:BJ21) -> 14 | CP21: =SUM(BK21:BN21) -> 16 | CQ21: =SUM(BO21:BR21) -> 17 | CR21: =CQ21*(1+CR41) -> 8.5 | CS21: =CR21*(1+CS41) -> 9.35 | CT21: =CS21*(1+CT41) -> 10.3785 | CU21: =CT21*(1+CU41) -> 11.727705 | CV21: =CU21*(1+CV41) -> 13.486861 | CW21: =CV21*(1+CW41) -> 15.50989 | CX21: =CW21*(1+CX41) -> 17.836373 | CY21: =CX21*(1+CY41) -> 20.511829 | CZ21: =CY21*(1+CZ41) -> 23.588604
B22: Ttl Revenues | AU22: =AU21+AU20+AU12+AU7+AU4 -> 7726 | AV22: =AV21+AV20+AV12+AV7+AV4 -> 7328 | AW22: =AW21+AW20+AW12+AW7+AW4 -> 8853 | AX22: =AX21+AX20+AX12+AX7+AX4 -> 10701 | AY22: =AY21+AY20+AY12+AY7+AY4 -> 10456 | AZ22: =AZ21+AZ20+AZ12+AZ7+AZ4 -> 10223 | BA22: =BA21+BA20+BA12+BA7+BA4 -> 10928 | BB22: =BB21+BB20+BB12+BB7+BB4 -> 11468 | ... BT22: =BT21+BT20+BT12+BT7+BT4 -> 11164 | CL22: =SUM(AU22:AX22) -> 34608 | CM22: =SUM(AY22:BB22) -> 43075 | CN22: =SUM(BC22:BF22) -> 43653 | CO22: =SUM(BG22:BJ22) -> 40109 | CP22: =SUM(BK22:BN22) -> 41950 | CQ22: =SUM(BO22:BR22) -> 44328 | CR22: =CR21+CR20+CR12+CR7+CR4 -> 48118.295 | CS22: =CS21+CS20+CS12+CS7+CS4 -> 51651.053 | CT22: =CT21+CT20+CT12+CT7+CT4 -> 56419.164 | CU22: =CU21+CU20+CU12+CU7+CU4 -> 61404.194 | CV22: =CV21+CV20+CV12+CV7+CV4 -> 66831.527 | CW22: =CW21+CW20+CW12+CW7+CW4 -> 72209.722 | CX22: =CX21+CX20+CX12+CX7+CX4 -> 77418.726 | CY22: =CY21+CY20+CY12+CY7+CY4 -> 82064.66 | CZ22: =CZ21+CZ20+CZ12+CZ7+CZ4 -> 86326.413
B24: Ttl Established Pharma Product Revenue Growth Y/y | AY24: =AY4/AU4-1 -> 0.024904215 | AZ24: =AZ4/AV4-1 -> 0.16485686 | BA24: =BA4/AW4-1 -> 0.15104641 | BB24: =BB4/AX4-1 -> 0.048823017 | BC24: =BC4/AY4-1 -> 0.071962617 | BD24: =BD4/AZ4-1 -> 0.036440678 | BE24: =BE4/BA4-1 -> 0.048221344 | BF24: =BF4/BB4-1 -> 0.010806318 | ... BT24: =BT4/BP4-1 -> 0.031091829 | CM24: =CM4/CL4-1 -> 0.096444341 | CN24: =CN4/CM4-1 -> 0.041119118 | CO24: =CO4/CN4-1 -> 0.031351792 | CP24: =CP4/CO4-1 -> 0.025266482 | CQ24: 0.15 | CR24: 0.13 | CS24: 0.11 | CT24: 0.095 | CU24: 0.08 | CV24: 0.075 | CW24: 0.07 | CX24: 0.065 | CY24: 0.05 | CZ24: 0.045
B25: Pediatric Nutritionals Growth Y/y | AY25: =AY5/AU5-1 -> -0.021120294 | AZ25: =AZ5/AV5-1 -> 0.067382812 | BA25: =BA5/AW5-1 -> 0.093439364 | BB25: =BB5/AX5-1 -> 0.030753968 | BC25: =BC5/AY5-1 -> -0.2054409 | BD25: =BD5/AZ5-1 -> -0.1537054 | BE25: =BE5/BA5-1 -> -0.24818182 | BF25: =BF5/BB5-1 -> -0.15110683 | ... BT25: =BT5/BP5-1 -> -0.095825427 | CM25: =CM5/CL5-1 -> 0.041434456 | CN25: =CN5/CM5-1 -> -0.19008841 | CO25: =CO5/CN5-1 -> 0.13013502 | CP25: =CP5/CO5-1 -> 0.022623284 | CQ25: 0.016 | CR25: 0.093 | CS25: -0.12 | CT25: -0.06 | CU25: -0.05 | CV25: 0.013 | CW25: 0.013 | CX25: 0.013 | CY25: 0.012 | CZ25: 0.012
B26: Adult Nutritionals Growth Y/y | AY26: =AY6/AU6-1 -> 0.19018405 | AZ26: =AZ6/AV6-1 -> 0.18160652 | BA26: =BA6/AW6-1 -> 0.098039216 | BB26: =BB6/AX6-1 -> 0.080818966 | BC26: =BC6/AY6-1 -> 0.079381443 | BD26: =BD6/AZ6-1 -> 0.012807882 | BE26: =BE6/BA6-1 -> -0.03968254 | BF26: =BF6/BB6-1 -> -0.06779661 | ... BT26: =BT6/BP6-1 -> -0.081174439 | CM26: =CM6/CL6-1 -> 0.13522727 | CN26: =CN6/CM6-1 -> -0.0045045045 | CO26: =CO6/CN6-1 -> 0.06083459 | CP26: =CP6/CO6-1 -> 0.04028436 | CQ26: 0.045 | CR26: -0.06 | CS26: -0.07 | CT26: -0.05 | CU26: -0.02 | CV26: 0.01 | CW26: 0.02 | CX26: 0.045 | CY26: 0.04 | CZ26: 0.03
B27: Ttl Nutritionals Revenues Growth Y/y | AY27: =AY7/AU7-1 -> 0.069327731 | AZ27: =AZ7/AV7-1 -> 0.11949018 | BA27: =BA7/AW7-1 -> 0.095634096 | BB27: =BB7/AX7-1 -> 0.054752066 | BC27: =BC7/AY7-1 -> -0.069744597 | BD27: =BD7/AZ7-1 -> -0.073529412 | BE27: =BE7/BA7-1 -> -0.14848197 | BF27: =BF7/BB7-1 -> -0.11018609 | ... BT27: =BT7/BP7-1 -> -0.088155515 | CM27: =CM7/CL7-1 -> 0.084608343 | CN27: =CN7/CM7-1 -> -0.10067519 | CO27: =CO7/CN7-1 -> 0.093176029 | CP27: =CP7/CO7-1 -> 0.031763552 | CQ27: =CQ7/CP7-1 -> 0.0045168192 | CR27: =CR7/CQ7-1 -> 0.011946752 | CS27: =CS7/CR7-1 -> -0.095395237 | CT27: =CT7/CS7-1 -> -0.0549409 | ... CZ27: =CZ7/CY7-1 -> 0.021573544
B28: Core Lab Growth Y/y | AY28: =AY8/AU8-1 -> 0.19514661 | AZ28: =AZ8/AV8-1 -> 0.32320162 | BA28: =BA8/AW8-1 -> 0.098639456 | BB28: =BB8/AX8-1 -> 0.018896447 | BC28: =BC8/AY8-1 -> 0.0016920474 | BD28: =BD8/AZ8-1 -> -0.065084227 | BE28: =BE8/BA8-1 -> -0.056501548 | BF28: =BF8/BB8-1 -> -0.06231454 | ... BT28: =BT8/BP8-1 -> -0.063328424 | CM28: =CM8/CL8-1 -> 0.14592179 | CN28: =CN8/CM8-1 -> -0.046801872 | CO28: =CO8/CN8-1 -> 0.055441899 | CP28: =CP8/CO8-1 -> 0.014731537 | CQ28: 0.02 | CR28: 0.035 | CS28: 0.014 | CT28: 0.014 | CU28: 0.013 | CV28: 0.013 | CW28: 0.012 | CX28: 0.012 | CY28: 0.011 | CZ28: 0.011
B29: Molecular Growth Y/y | AY29: =AY9/AU9-1 -> 2.2158273 | AZ29: =AZ9/AV9-1 -> -0.19220056 | BA29: =BA9/AW9-1 -> -0.24672489 | BB29: =BB9/AX9-1 -> -0.28423237 | BC29: =BC9/AY9-1 -> -0.060402685 | BD29: =BD9/AZ9-1 -> -0.26896552 | BE29: =BE9/BA9-1 -> -0.46956522 | BF29: =BF9/BB9-1 -> -0.47826087 | ... BT29: =BT9/BP9-1 -> 0.21138211 | CM29: =CM9/CL9-1 -> -0.0076495132 | CN29: =CN9/CM9-1 -> -0.30273301 | CO29: =CO9/CN9-1 -> -0.42311558 | CP29: =CP9/CO9-1 -> -0.092334495 | CQ29: 0.01 | CR29: 0.21 | CS29: 0.19 | CT29: 0.16 | CU29: 0.15 | CV29: 0.14 | CW29: 0.13 | CX29: 0.125 | CY29: 0.12 | CZ29: 0.115
B30: Point of Care Growth Y/y | AY30: =AY10/AU10-1 -> -0.065217391 | AZ30: =AZ10/AV10-1 -> 0.16101695 | BA30: =BA10/AW10-1 -> 0.030534351 | BB30: =BB10/AX10-1 -> 0.046511628 | BC30: =BC10/AY10-1 -> -0.007751938 | BD30: =BD10/AZ10-1 -> 0.01459854 | BE30: =BE10/BA10-1 -> -0.059259259 | BF30: =BF10/BB10-1 -> -0.02962963 | ... BT30: =BT10/BP10-1 -> -0.35135135 | CM30: =CM10/CL10-1 -> 0.03875969 | CN30: =CN10/CM10-1 -> -0.020522388 | CO30: =CO10/CN10-1 -> 0.076190476 | CP30: =CP10/CO10-1 -> 0.040707965 | CQ30: 0.04 | CR30: -0.32 | CS30: -0.28 | CT30: 0.06 | CU30: 0.055 | CV30: 0.0525 | CW30: 0.05 | CX30: 0.0475 | CY30: 0.045 | CZ30: 0.0425
B31: Rapid Diagnostics Growth Y/y | AY31: =AY11/AU11-1 -> 3.0285714 | AZ31: =AZ11/AV11-1 -> 1.8566038 | BA31: =BA11/AW11-1 -> 1.4457143 | BB31: =BB11/AX11-1 -> 0.096225633 | BC31: =BC11/AY11-1 -> 0.5625 | BD31: =BD11/AZ11-1 -> 0.79788639 | BE31: =BE11/BA11-1 -> -0.013084112 | BF31: =BF11/BB11-1 -> -0.35603481 | ... BT31: =BT11/BP11-1 -> 0.21875 | CM31: =CM11/CL11-1 -> 0.95452468 | CN31: =CN11/CM11-1 -> 0.17631241 | CO31: =CO11/CN11-1 -> -0.63323725 | CP31: =CP11/CO11-1 -> -0.18780488 | CQ31: -0.11 | CR31: 0.17 | CS31: 0.21 | CT31: 0.22 | CU31: 0.18 | CV31: 0.16 | CW31: 0.15 | CX31: 0.14 | CY31: 0.13 | CZ31: 0.12
B32: Ttl Diagnostics Growth Y/y | AY32: =AY12/AU12-1 -> 1.1982475 | AZ32: =AZ12/AV12-1 -> 0.62838516 | BA32: =BA12/AW12-1 -> 0.48181818 | BB32: =BB12/AX12-1 -> 0.028998849 | BC32: =BC12/AY12-1 -> 0.30966617 | BD32: =BD12/AZ12-1 -> 0.32245149 | BE32: =BE12/BA12-1 -> -0.069274029 | BF32: =BF12/BB12-1 -> -0.26705435 | ... BT32: =BT12/BP12-1 -> 0.003221353 | CM32: =CM12/CL12-1 -> 0.44784822 | CN32: =CN12/CM12-1 -> 0.052735873 | CO32: =CO12/CN12-1 -> -0.39352723 | CP32: =CP12/CO12-1 -> -0.064777733 | CQ32: =CQ12/CP12-1 -> -0.043250187 | CR32: =CR12/CQ12-1 -> 0.058121293 | CS32: =CS12/CR12-1 -> 0.072341264 | CT32: =CT12/CS12-1 -> 0.096639247 | ... CZ32: =CZ12/CY12-1 -> 0.078018465
B33: Rhythm Management Growth Y/y | AY33: =AY13/AU13-1 -> 0.094936709 | AZ33: =AZ13/AV13-1 -> 0.41396509 | BA33: =BA13/AW13-1 -> 0.12623274 | BB33: =BB13/AX13-1 -> 0.016917293 | BC33: =BC13/AY13-1 -> 0.0096339114 | BD33: =BD13/AZ13-1 -> -0.0335097 | BE33: =BE13/BA13-1 -> -0.066549912 | BF33: =BF13/BB13-1 -> -0.049907579 | ... BT33: =BT13/BP13-1 -> 0.016344725 | CM33: =CM13/CL13-1 -> 0.14838036 | CN33: =CN13/CM13-1 -> -0.035941765 | CO33: =CO13/CN13-1 -> 0.064181218 | CP33: =CP13/CO13-1 -> 0.059866962 | CQ33: 0.105 | CR33: 0.1325 | CS33: 0.12 | CT33: 0.11 | CU33: 0.105 | CV33: 0.09 | CW33: 0.075 | CX33: 0.06 | CY33: 0.05 | CZ33: 0.04
B34: Electrophysiology Growth Y/y | AY34: =AY14/AU14-1 -> 0.11082474 | AZ34: =AZ14/AV14-1 -> 0.62876254 | BA34: =BA14/AW14-1 -> 0.099773243 | BB34: =BB14/AX14-1 -> 0.12 | BC34: =BC14/AY14-1 -> 0.12529002 | BD34: =BD14/AZ14-1 -> -0.0020533881 | BE34: =BE14/BA14-1 -> -0.032989691 | BF34: =BF14/BB14-1 -> -0.033730159 | ... BT34: =BT14/BP14-1 -> 0.12571429 | CM34: =CM14/CL14-1 -> 0.20849176 | CN34: =CN14/CM14-1 -> 0.010487677 | CO34: =CO14/CN14-1 -> 0.13907628 | CP34: =CP14/CO14-1 -> 0.123918 | CQ34: 0.12 | CR34: 0.22 | CS34: 0.17 | CT34: 0.16 | CU34: 0.155 | CV34: 0.145 | CW34: 0.13 | CX34: 0.11 | CY34: 0.085 | CZ34: 0.065
B35: Heart Failure Growth Y/y | AY35: =AY15/AU15-1 -> -0.044334975 | AZ35: =AZ15/AV15-1 -> 0.43670886 | BA35: =BA15/AW15-1 -> 0.20526316 | BB35: =BB15/AX15-1 -> 0.26455026 | BC35: =BC15/AY15-1 -> 0.28865979 | BD35: =BD15/AZ15-1 -> 0.18502203 | BE35: =BE15/BA15-1 -> 0.12663755 | BF35: =BF15/BB15-1 -> 0.079497908 | ... BT35: =BT15/BP15-1 -> 0.057065217 | CM35: =CM15/CL15-1 -> 0.20135135 | CN35: =CN15/CM15-1 -> 0.16422947 | CO35: =CO15/CN15-1 -> 0.12173913 | CP35: =CP15/CO15-1 -> 0.10163652 | CQ35: 0.132 | CR35: 0.125 | CS35: 0.1 | CT35: 0.08 | CU35: 0.06 | CV35: 0.05 | CW35: 0.04 | CX35: 0.03 | CY35: 0.02 | CZ35: 0.015
B36: Vascular Growth Y/y | AY36: =AY16/AU16-1 -> 0.016 | AZ36: =AZ16/AV16-1 -> 0.44906445 | BA36: =BA16/AW16-1 -> 0.022222222 | BB36: =BB16/AX16-1 -> 0.12437811 | BC36: =BC16/AY16-1 -> -0.02519685 | BD36: =BD16/AZ16-1 -> -0.06312769 | BE36: =BE16/BA16-1 -> -0.059006211 | BF36: =BF16/BB16-1 -> -0.10766962 | ... BT36: =BT16/BP16-1 -> 0.026420079 | CM36: =CM16/CL16-1 -> 0.13467294 | CN36: =CN16/CM16-1 -> -0.064431047 | CO36: =CO16/CN16-1 -> 0.079742247 | CP36: =CP16/CO16-1 -> 0.058187244 | CQ36: 0.0475 | CR36: 0.09 | CS36: 0.08 | CT36: 0.07 | CU36: 0.06 | CV36: 0.05 | CW36: 0.04 | CX36: 0.03 | CY36: 0.02 | CZ36: 0.01
B37: Structural Heart Revenue Growth Y/y | AY37: =AY17/AU17-1 -> 0.18553459 | AZ37: =AZ17/AV17-1 -> 0.89237668 | BA37: =BA17/AW17-1 -> 0.11048159 | BB37: =BB17/AX17-1 -> 0.18696884 | BC37: =BC17/AY17-1 -> 0.090185676 | BD37: =BD17/AZ17-1 -> 0.042654028 | BE37: =BE17/BA17-1 -> 0.071428571 | BF37: =BF17/BB17-1 -> 0.052505967 | ... BT37: =BT17/BP17-1 -> -0.091194969 | CM37: =CM17/CL17-1 -> 0.29109864 | CN37: =CN17/CM17-1 -> 0.063354037 | CO37: =CO17/CN17-1 -> 0.13551402 | CP37: =CP17/CO17-1 -> 0.15534979 | CQ37: 0.13 | CR37: -0.04 | CS37: -0.01 | CT37: 0.07 | CU37: 0.09 | CV37: 0.105 | CW37: 0.09 | CX37: 0.075 | CY37: 0.06 | CZ37: 0.045
B38: Neuromodulation Revenue Growth Y/y | AY38: =AY18/AU18-1 -> 0.039548023 | AZ38: =AZ18/AV18-1 -> 0.98113208 | BA38: =BA18/AW18-1 -> -0.077669903 | BB38: =BB18/AX18-1 -> -0.075117371 | BC38: =BC18/AY18-1 -> -0.027173913 | BD38: =BD18/AZ18-1 -> -0.061904762 | BE38: =BE18/BA18-1 -> 0.010526316 | BF38: =BF18/BB18-1 -> 0.025380711 | ... BT38: =BT18/BP18-1 -> -0.043307087 | CM38: =CM18/CL18-1 -> 0.11253561 | CN38: =CN18/CM18-1 -> -0.014084507 | CO38: =CO18/CN18-1 -> 0.15584416 | CP38: =CP18/CO18-1 -> 0.080898876 | CQ38: 0.04 | CR38: 0.03 | CS38: 0.045 | CT38: 0.06 | CU38: 0.065 | CV38: 0.06 | CW38: 0.055 | CX38: 0.045 | CY38: 0.035 | CZ38: 0.025
B39: Diabetes Care Revenue Growth Y/y | AY39: =AY19/AU19-1 -> 0.30319149 | AZ39: =AZ19/AV19-1 -> 0.3986755 | BA39: =BA19/AW19-1 -> 0.32977461 | BB39: =BB19/AX19-1 -> 0.27699019 | BC39: =BC19/AY19-1 -> 0.14897959 | BD39: =BD19/AZ19-1 -> 0.12878788 | BE39: =BE19/BA19-1 -> 0.04103479 | BF39: =BF19/BB19-1 -> 0.085397096 | ... BT39: =BT19/BP19-1 -> 0.04997476 | CM39: =CM19/CL19-1 -> 0.32476278 | CN39: =CN19/CM19-1 -> 0.098890943 | CO39: =CO19/CN19-1 -> 0.21131203 | CP39: =CP19/CO19-1 -> 0.18121854 | CQ39: 0.195 | CR39: 0.14 | CS39: 0.175 | CT39: 0.18 | CU39: 0.15 | CV39: 0.13 | CW39: 0.11 | CX39: 0.09 | CY39: 0.07 | CZ39: 0.06
B40: Ttl Med Device Revenues Revenue Growth Y/y | AY40: =AY20/AU20-1 -> 0.13040518 | AZ40: =AZ20/AV20-1 -> 0.51300041 | BA40: =BA20/AW20-1 -> 0.14574132 | BB40: =BB20/AX20-1 -> 0.15105926 | BC40: =BC20/AY20-1 -> 0.08253012 | BD40: =BD20/AZ20-1 -> 0.032460447 | BE40: =BE20/BA20-1 -> 0.0035792952 | BF40: =BF20/BB20-1 -> 0.0077353961 | ... BT40: =BT20/BP20-1 -> 0.031663252 | CM40: =CM20/CL20-1 -> 0.21888521 | CN40: =CN20/CM20-1 -> 0.03027772 | CO40: =CO20/CN20-1 -> 0.14085934 | CP40: =CP20/CO20-1 -> 0.1242968 | CQ40: =CQ20/CP20-1 -> 0.1264616 | CR40: =CR20/CQ20-1 -> 0.11496341 | CS40: =CS20/CR20-1 -> 0.12478173 | CT40: =CT20/CS20-1 -> 0.13245026 | ... CZ40: =CZ20/CY20-1 -> 0.04915788
B41: Other Revenues Revenue Growth Y/y | AY41: =AY21/AU21-1 -> 0.066666667 | AZ41: =AZ21/AV21-1 -> 0.46666667 | BA41: =BA21/AW21-1 -> -0.45 | BB41: =BB21/AX21-1 -> -0.8125 | BC41: =BC21/AY21-1 -> -0.8125 | BD41: =BD21/AZ21-1 -> -0.90909091 | BE41: =BE21/BA21-1 -> -0.72727273 | BF41: =BF21/BB21-1 -> 0 | ... BT41: =BT21/BP21-1 -> -0.6 | CM41: =CM21/CL21-1 -> -0.21212121 | CN41: =CN21/CM21-1 -> -0.78846154 | CO41: =CO21/CN21-1 -> 0.27272727 | CP41: =CP21/CO21-1 -> 0.14285714 | CQ41: 0.15 | CR41: -0.5 | CS41: 0.1 | CT41: 0.11 | CU41: 0.13 | CV41: 0.15 | CW41: 0.15 | CX41: 0.15 | CY41: 0.15 | CZ41: 0.15
B42: Ttl Revenues Revenue Growth Y/y | AY42: =AY22/AU22-1 -> 0.35335232 | AZ42: =AZ22/AV22-1 -> 0.39506004 | BA42: =BA22/AW22-1 -> 0.23438382 | BB42: =BB22/AX22-1 -> 0.071675544 | BC42: =BC22/AY22-1 -> 0.13762433 | BD42: =BD22/AZ22-1 -> 0.10114448 | BE42: =BE22/BA22-1 -> -0.047401171 | BF42: =BF22/BB22-1 -> -0.12007325 | ... BT42: =BT22/BP22-1 -> 0.0019745109 | CM42: =CM22/CL22-1 -> 0.24465442 | CN42: =CN22/CM22-1 -> 0.013418456 | CO42: =CO22/CN22-1 -> -0.081185715 | CP42: =CP22/CO22-1 -> 0.045899923 | CQ42: =CQ22/CP22-1 -> 0.056686532 | CR42: =CR22/CQ22-1 -> 0.085505651 | CS42: =CS22/CR22-1 -> 0.073418206 | CT42: =CT22/CS22-1 -> 0.092313907 | ... CZ42: =CZ22/CY22-1 -> 0.051931648
B44: Established Pharma Product % of Ttl Revenues | AU44: =AU4/AU22 -> 0.13512814 | AV44: =AV4/AV22 -> 0.1382369 | AW44: =AW4/AW22 -> 0.12413871 | AX44: =AX4/AX22 -> 0.10718624 | AY44: =AY4/AY22 -> 0.10233359 | AZ44: =AZ4/AZ22 -> 0.115426 | BA44: =BA4/BA22 -> 0.11575769 | BB44: =BB4/BB22 -> 0.10490059 | ... BT44: =BT4/BT22 -> 0.127732 | CL44: =CL4/CL22 -> 0.12433541 | CM44: =CM4/CM22 -> 0.10952989 | CN44: =CN4/CN22 -> 0.11252377 | CO44: =CO4/CO22 -> 0.12630582 | CP44: =CP4/CP22 -> 0.12381406 | CQ44: =CQ4/CQ22 -> 0.1248872
B45: Nutritionals Revenues % of Ttl Revenues | AU45: =AU7/AU22 -> 0.24644059 | AV45: =AV7/AV22 -> 0.25695961 | AW45: =AW7/AW22 -> 0.21732746 | AX45: =AX7/AX22 -> 0.18091767 | AY45: =AY7/AY22 -> 0.19472073 | AZ45: =AZ7/AZ22 -> 0.2062017 | BA45: =BA7/BA22 -> 0.19289898 | BB45: =BB7/BB22 -> 0.17806069 | ... BT45: =BT7/BT22 -> 0.18067001 | CL45: =CL7/CL22 -> 0.22096047 | CM45: =CM7/CM22 -> 0.19254788 | CN45: =CN7/CN22 -> 0.17087027 | CO45: =CO7/CO22 -> 0.20329602 | CP45: =CP7/CP22 -> 0.20054827 | CQ45: =CQ7/CQ22 -> 0.190647
B46: Diagnostics Revenues % of Ttl Revenues | AU46: =AU12/AU22 -> 0.23634481 | AV46: =AV12/AV22 -> 0.27210699 | AW46: =AW12/AW22 -> 0.298204 | AX46: =AX12/AX22 -> 0.40603682 | AY46: =AY12/AY22 -> 0.38389441 | AZ46: =AZ12/AZ22 -> 0.31761714 | BA46: =BA12/BA22 -> 0.3579795 | BB46: =BB12/BB22 -> 0.38986746 | ... BT46: =BT12/BT22 -> 0.19527051 | CL46: =CL12/CL22 -> 0.31221105 | CM46: =CM12/CM22 -> 0.3631805 | CN46: =CN12/CN22 -> 0.37727075 | CO46: =CO12/CO22 -> 0.24902142 | CP46: =CP12/CP22 -> 0.22266985 | CQ46: =CQ12/CQ22 -> 0.20161072
B47: Med Device Revenues % of Ttl Revenues | AU47: =AU20/AU22 -> 0.38014497 | AV47: =AV20/AV22 -> 0.33064956 | AW47: =AW20/AW22 -> 0.35807071 | AX47: =AX20/AX22 -> 0.30436408 | AY47: =AY20/AY22 -> 0.31752104 | AZ47: =AZ20/AZ22 -> 0.35860315 | BA47: =BA20/BA22 -> 0.33235725 | BB47: =BB20/BB22 -> 0.32690966 | ... BT47: =BT20/BT22 -> 0.49614833 | CL47: =CL20/CL22 -> 0.34058599 | CM47: =CM20/CM22 -> 0.33353453 | CN47: =CN20/CN22 -> 0.33908322 | CO47: =CO20/CO22 -> 0.4210277 | CP47: =CP20/CP22 -> 0.45258641 | CQ47: =CQ20/CQ22 -> 0.48247158
B48: Other Revenues % of Ttl Revenues | AU48: =AU21/AU22 -> 0.0019414962 | AV48: =AV21/AV22 -> 0.0020469432 | AW48: =AW21/AW22 -> 0.0022591212 | AX48: =AX21/AX22 -> 0.0014951874 | AY48: =AY21/AY22 -> 0.0015302219 | AZ48: =AZ21/AZ22 -> 0.0021520102 | BA48: =BA21/BA22 -> 0.0010065886 | BB48: =BB21/BB22 -> 0.00026159749 | ... BT48: =BT21/BT22 -> 0.00017914726 | CL48: =CL21/CL22 -> 0.0019070735 | CM48: =CM21/CM22 -> 0.0012071967 | CN48: =CN21/CN22 -> 0.00025198726 | CO48: =CO21/CO22 -> 0.00034904884 | CP48: =CP21/CP22 -> 0.00038140644 | CQ48: =CQ21/CQ22 -> 0.00038350478
B50: U.S. Revenues | AU50: 2856 | AV50: 2638 | AW50: 3239 | AX50: 3912 | AY50: 3838 | AZ50: 3581 | BA50: 4368 | BB50: 4565 | BC50: 4637 | BD50: 4892 | BE50: 4094 | BF50: 4002 | BG50: 3928 | BH50: 3758 | BI50: 3817 | BJ50: 3835 | BK50: 3846 | BL50: 3944 | BM50: 4202 | BN50: 4175 | BO50: 4168 | BP50: 4276 | BQ50: 4299 | BR50: 4175 | BS50: 4274 | BT50: 4274 | CL50: =SUM(AU50:AX50) -> 12645 | CM50: =SUM(AY50:BB50) -> 16352 | CN50: =SUM(BC50:BF50) -> 17625 | CO50: =SUM(BG50:BJ50) -> 15338 | CP50: =SUM(BK50:BN50) -> 16167 | CQ50: =SUM(BO50:BR50) -> 16918
B51: Internation Revenues | AU51: 4870 | AV51: 4690 | AW51: 5524 | AX51: 6789 | AY51: 6618 | AZ51: 6642 | BA51: 6560 | BB51: 6903 | BC51: 6958 | BD51: 6365 | BE51: 6316 | BF51: 6089 | BG51: 5819 | BH51: 6220 | BI51: 6326 | BJ51: 6406 | BK51: 6118 | BL51: 6433 | BM51: 6433 | BN51: 6799 | BO51: 6190 | BP51: 6866 | BQ51: 7070 | BR51: 6799 | BS51: 6890 | BT51: 6890 | CL51: =SUM(AU51:AX51) -> 21873 | CM51: =SUM(AY51:BB51) -> 26723 | CN51: =SUM(BC51:BF51) -> 25728 | CO51: =SUM(BG51:BJ51) -> 24771 | CP51: =SUM(BK51:BN51) -> 25783 | CQ51: =SUM(BO51:BR51) -> 26925
B52: Ttl Revenues | AU52: =SUM(AU50:AU51) -> 7726 | AV52: =SUM(AV50:AV51) -> 7328 | AW52: =SUM(AW50:AW51) -> 8763 | AX52: =SUM(AX50:AX51) -> 10701 | AY52: =SUM(AY50:AY51) -> 10456 | AZ52: =SUM(AZ50:AZ51) -> 10223 | BA52: =SUM(BA50:BA51) -> 10928 | BB52: =SUM(BB50:BB51) -> 11468 | ... BT52: =SUM(BT50:BT51) -> 11164 | CL52: =SUM(AU52:AX52) -> 34518 | CM52: =SUM(AY52:BB52) -> 43075 | CN52: =SUM(BC52:BF52) -> 43353 | CO52: =SUM(BG52:BJ52) -> 40109 | CP52: =SUM(BK52:BN52) -> 41950 | CQ52: =SUM(BO52:BR52) -> 43843
B54: U.S. Revenue Growth Y/y | AY54: =AY50/AU50-1 -> 0.34383754 | AZ54: =AZ50/AV50-1 -> 0.35746778 | BA54: =BA50/AW50-1 -> 0.34856437 | BB54: =BB50/AX50-1 -> 0.16692229 | BC54: =BC50/AY50-1 -> 0.20818134 | BD54: =BD50/AZ50-1 -> 0.36609886 | BE54: =BE50/BA50-1 -> -0.062728938 | BF54: =BF50/BB50-1 -> -0.12332968 | ... BT54: =BT50/BP50-1 -> -0.00046772685 | CM54: =CM50/CL50-1 -> 0.29315935 | CN54: =CN50/CM50-1 -> 0.077849804 | CO54: =CO50/CN50-1 -> -0.12975887 | CP54: =CP50/CO50-1 -> 0.054048768 | CQ54: =CQ50/CP50-1 -> 0.04645265
B55: Internation Revenue Growth Y/y | AY55: =AY51/AU51-1 -> 0.35893224 | AZ55: =AZ51/AV51-1 -> 0.41620469 | BA55: =BA51/AW51-1 -> 0.18754526 | BB55: =BB51/AX51-1 -> 0.016791869 | BC55: =BC51/AY51-1 -> 0.051375038 | BD55: =BD51/AZ51-1 -> -0.041704306 | BE55: =BE51/BA51-1 -> -0.037195122 | BF55: =BF51/BB51-1 -> -0.11791975 | ... BT55: =BT51/BP51-1 -> 0.003495485 | CM55: =CM51/CL51-1 -> 0.22173456 | CN55: =CN51/CM51-1 -> -0.037233844 | CO55: =CO51/CN51-1 -> -0.037196828 | CP55: =CP51/CO51-1 -> 0.040854225 | CQ55: =CQ51/CP51-1 -> 0.044292751
B56: Ttl Revenues Growth Y/y | AY56: =AY52/AU52-1 -> 0.35335232 | AZ56: =AZ52/AV52-1 -> 0.39506004 | BA56: =BA52/AW52-1 -> 0.24706151 | BB56: =BB52/AX52-1 -> 0.071675544 | BC56: =BC52/AY52-1 -> 0.10893267 | BD56: =BD52/AZ52-1 -> 0.10114448 | BE56: =BE52/BA52-1 -> -0.047401171 | BF56: =BF52/BB52-1 -> -0.12007325 | ... BT56: =BT52/BP52-1 -> 0.0019745109 | CM56: =CM52/CL52-1 -> 0.24789965 | CN56: =CN52/CM52-1 -> 0.0064538595 | CO56: =CO52/CN52-1 -> -0.074827578 | CP56: =CP52/CO52-1 -> 0.045899923 | CQ56: =CQ52/CP52-1 -> 0.045125149
B58: U.S. % of Revenues | AU58: =AU50/AU52 -> 0.36966089 | AV58: =AV50/AV52 -> 0.35998908 | AW58: =AW50/AW52 -> 0.36962228 | AX58: =AX50/AX52 -> 0.36557331 | AY58: =AY50/AY52 -> 0.36706197 | AZ58: =AZ50/AZ52 -> 0.35028857 | BA58: =BA50/BA52 -> 0.39970717 | BB58: =BB50/BB52 -> 0.39806418 | ... BT58: =BT50/BT52 -> 0.38283769 | CL58: =CL50/CL52 -> 0.36633061 | CM58: =CM50/CM52 -> 0.37961695 | CN58: =CN50/CN52 -> 0.40654626 | CO58: =CO50/CO52 -> 0.38240794 | CP58: =CP50/CP52 -> 0.38538737 | CQ58: =CQ50/CQ52 -> 0.38587688
B59: International % of Revenues | AU59: =AU51/AU52 -> 0.63033911 | AV59: =AV51/AV52 -> 0.64001092 | AW59: =AW51/AW52 -> 0.63037772 | AX59: =AX51/AX52 -> 0.63442669 | AY59: =AY51/AY52 -> 0.63293803 | AZ59: =AZ51/AZ52 -> 0.64971143 | BA59: =BA51/BA52 -> 0.60029283 | BB59: =BB51/BB52 -> 0.60193582 | ... BT59: =BT51/BT52 -> 0.61716231 | CL59: =CL51/CL52 -> 0.63366939 | CM59: =CM51/CM52 -> 0.62038305 | CN59: =CN51/CN52 -> 0.59345374 | CO59: =CO51/CO52 -> 0.61759206 | CP59: =CP51/CP52 -> 0.61461263 | CQ59: =CQ51/CQ52 -> 0.61412312
B61: Revenues | C61: 6718.4 | D61: 7494.9 | E61: 7761.3 | F61: 8790.1 | G61: 7698.4 | H61: 8826 | I61: 8674.5 | J61: 9967.8 | K61: 9040.8 | L61: 9616.3 | M61: 9816.7 | N61: 10377 | O61: 5283.7 | P61: 5313.3 | Q61: 5264.8 | R61: 3188.2 | S61: 5378 | T61: 5446 | U61: 4825 | V61: 4008 | W61: 4755 | X61: 5057 | Y61: 5079 | Z61: 5331 | AA61: 4897 | AB61: 5170 | AC61: 5150 | AD61: 5188 | AE61: 4885 | AF61: 5333 | AG61: 5302 | AH61: 5333 | AI61: 6335 | AJ61: 6637 | AK61: 6829 | AL61: 7589 | AM61: 7390 | AN61: 7767 | AO61: 7656 | AP61: 7765 | AQ61: 7535 | AR61: 7979 | AS61: 8076 | AT61: 8314 | AU61: =AU22 -> 7726 | AV61: =AV22 -> 7328 | AW61: =AW22 -> 8853 | AX61: =AX22 -> 10701 | AY61: =AY22 -> 10456 | AZ61: =AZ22 -> 10223 | BA61: =BA22 -> 10928 | BB61: =BB22 -> 11468 | ... BS61: =BS22 -> 11164 | BT61: 12593 | CA61: =SUM(C61:F61) -> 30764.7 | CB61: =SUM(G61:J61) -> 35166.7 | CC61: =SUM(K61:N61) -> 38850.8 | CD61: =SUM(O61:R61) -> 19050 | CE61: =SUM(S61:V61) -> 19657 | CF61: =SUM(W61:Z61) -> 20222 | CG61: =SUM(AA61:AD61) -> 20405 | CH61: =SUM(AE61:AH61) -> 20853 | CI61: =SUM(AI61:AL61) -> 27390 | CJ61: =SUM(AM61:AP61) -> 30578 | CK61: =SUM(AQ61:AT61) -> 31904 | CL61: =SUM(AU61:AX61) -> 34608 | CM61: =SUM(AY61:BB61) -> 43075 | CN61: =SUM(BC61:BF61) -> 43653 | CO61: =SUM(BG61:BJ61) -> 40109 | CP61: =SUM(BK61:BN61) -> 41950 | CQ61: =CQ22 -> 44328 | CR61: =CR22 -> 48118.295 | CS61: =CS22 -> 51651.053 | CT61: =CT22 -> 56419.164 | CU61: =CU22 -> 61404.194 | CV61: =CV22 -> 66831.527 | CW61: =CW22 -> 72209.722 | CX61: =CX22 -> 77418.726 | ... CZ61: =CZ22 -> 86326.413
B62: COGS | C62: 2935.9 | D62: 3129 | E62: 3360.2 | F62: 3784.2 | G62: 3335.1 | H62: 3543.9 | I62: 3741.1 | J62: 4045 | K62: 3859 | L62: 3870.5 | M62: 3973.2 | N62: 3838 | O62: 2359.2 | P62: 2370.1 | Q62: 2488.9 | R62: 1680.9 | S62: 2432 | T62: 2545 | U62: 2255 | V62: 1961 | W62: 2274 | X62: 2288 | Y62: 2319 | Z62: 2325 | AA62: 2081 | AB62: 2218 | AC62: 2242 | AD62: 2206 | AE62: 2140 | AF62: 2287 | AG62: 2285 | AH62: 2382 | AI62: 3062 | AJ62: 3189 | AK62: 2876 | AL62: 3282 | AM62: 3067 | AN62: 3282 | AO62: 3166 | AP62: 3191 | AQ62: 3160 | AR62: 3279 | AS62: 3358 | AT62: 3434 | AU62: 3281 | AV62: 3263 | AW62: 3966 | AX62: =15003-SUM(AU62:AW62) -> 4493 | AY62: 4401 | AZ62: 4947 | BA62: 4423 | BB62: =18537-SUM(AY62:BA62) -> 4766 | BC62: 4987 | BD62: 4933 | BE62: 4629 | BF62: =19142-SUM(BC62:BE62) -> 4593 | BG62: 4331 | BH62: 4483 | BI62: 4605 | BJ62: =17975-SUM(BG62:BI62) -> 4556 | BK62: 4463 | BL62: 4603 | BM62: 4698 | BN62: =18706-SUM(BK62:BM62) -> 4942 | BO62: 4468 | BP62: 4854 | BQ62: 5075 | BR62: 4922 | BS62: 4890 | BT62: 5325 | CA62: =SUM(C62:F62) -> 13209.3 | CB62: =SUM(G62:J62) -> 14665.1 | CC62: =SUM(K62:N62) -> 15540.7 | CD62: =SUM(O62:R62) -> 8899.1 | CE62: =SUM(S62:V62) -> 9193 | CF62: =SUM(W62:Z62) -> 9206 | CG62: =SUM(AA62:AD62) -> 8747 | CH62: =SUM(AE62:AH62) -> 9094 | CI62: =SUM(AI62:AL62) -> 12409 | CJ62: =SUM(AM62:AP62) -> 12706 | CK62: =SUM(AQ62:AT62) -> 13231 | CL62: =SUM(AU62:AX62) -> 15003 | CM62: =SUM(AY62:BB62) -> 18537 | CN62: =SUM(BC62:BF62) -> 19142 | CO62: =SUM(BG62:BJ62) -> 17975 | CP62: =SUM(BK62:BN62) -> 18706 | CQ62: =SUM(BO62:BR62) -> 19319 | CR62: =CR61*(1-CR79) -> 21412.641 | CS62: =CS61*(1-CS79) -> 22933.068 | CT62: =CT61*(1-CT79) -> 24993.69 | CU62: =CU61*(1-CU79) -> 27140.654 | CV62: =CV61*(1-CV79) -> 29472.704 | CW62: =CW61*(1-CW79) -> 31772.278 | CX62: =CX61*(1-CX79) -> 34064.239 | CY62: =CY61*(1-CY79) -> 36108.45 | CZ62: =CZ61*(1-CZ79) -> 37983.622
B63: GP | C63: =C61-C62 -> 3782.5 | D63: =D61-D62 -> 4365.9 | E63: =E61-E62 -> 4401.1 | F63: =F61-F62 -> 5005.9 | G63: =G61-G62 -> 4363.3 | H63: =H61-H62 -> 5282.1 | I63: =I61-I62 -> 4933.4 | J63: =J61-J62 -> 5922.8 | ... BT63: =BT61-BT62 -> 7268 | CA63: =SUM(C63:F63) -> 17555.4 | CB63: =SUM(G63:J63) -> 20501.6 | CC63: =SUM(K63:N63) -> 23310.1 | CD63: =SUM(O63:R63) -> 10150.9 | CE63: =SUM(S63:V63) -> 10464 | CF63: =SUM(W63:Z63) -> 11016 | CG63: =SUM(AA63:AD63) -> 11658 | CH63: =SUM(AE63:AH63) -> 11759 | CI63: =SUM(AI63:AL63) -> 14981 | CJ63: =SUM(AM63:AP63) -> 17872 | CK63: =SUM(AQ63:AT63) -> 18673 | CL63: =SUM(AU63:AX63) -> 19605 | CM63: =SUM(AY63:BB63) -> 24538 | CN63: =SUM(BC63:BF63) -> 24511 | CO63: =SUM(BG63:BJ63) -> 22134 | CP63: =SUM(BK63:BN63) -> 23244 | CQ63: =SUM(BO63:BR63) -> 25009 | CR63: =CR61-CR62 -> 26705.653 | CS63: =CS61-CS62 -> 28717.986 | CT63: =CT61-CT62 -> 31425.474 | CU63: =CU61-CU62 -> 34263.54 | CV63: =CV61-CV62 -> 37358.824 | CW63: =CW61-CW62 -> 40437.444 | CX63: =CX61-CX62 -> 43354.486 | CY63: =CY61-CY62 -> 45956.209 | CZ63: =CZ61-CZ62 -> 48342.791
B64: Ammortization of Intangibles | C64: 0 | D64: 0 | E64: 0 | F64: 0 | G64: 0 | H64: 0 | I64: 0 | J64: 0 | K64: 0 | L64: 0 | M64: 0 | N64: 0 | O64: 0 | P64: 0 | Q64: 0 | R64: 0 | S64: 0 | T64: 0 | U64: 0 | V64: 0 | W64: 0 | X64: 0 | Y64: 0 | Z64: 0 | AA64: 0 | AB64: 0 | AC64: 0 | AD64: 0 | AE64: 0 | AF64: 0 | AG64: 0 | AH64: 0 | AI64: 0 | AJ64: 0 | AK64: 0 | AL64: 0 | AM64: 0 | AN64: 0 | AO64: 0 | AP64: 0 | AQ64: 0 | AR64: 0 | AS64: 0 | AT64: 0 | AU64: 561 | AV64: 553 | AW64: 510 | AX64: =2132-SUM(AU64:AW64) -> 508 | AY64: 509 | AZ64: 504 | BA64: 520 | BB64: =2047-SUM(AY64:BA64) -> 514 | BC64: 512 | BD64: 507 | BE64: 498 | BF64: =2013-SUM(BC64:BE64) -> 496 | BG64: 491 | BH64: 498 | BI64: 496 | BJ64: =1966-SUM(BG64:BI64) -> 481 | BK64: 472 | BL64: 471 | BM64: 470 | BN64: =1878-SUM(BK64:BM64) -> 465 | BO64: 420 | BP64: 420 | BQ64: 420 | BR64: 422 | BS64: 422 | BT64: 658 | CA64: =SUM(C64:F64) -> 0 | CB64: =SUM(G64:J64) -> 0 | CC64: =SUM(K64:N64) -> 0 | CD64: =SUM(O64:R64) -> 0 | CE64: =SUM(S64:V64) -> 0 | CF64: =SUM(W64:Z64) -> 0 | CG64: =SUM(AA64:AD64) -> 0 | CH64: =SUM(AE64:AH64) -> 0 | CI64: =SUM(AI64:AL64) -> 0 | CJ64: =SUM(AM64:AP64) -> 0 | CK64: =SUM(AQ64:AT64) -> 0 | CL64: =SUM(AU64:AX64) -> 2132 | CM64: =SUM(AY64:BB64) -> 2047 | CN64: =SUM(BC64:BF64) -> 2013 | CO64: =SUM(BG64:BJ64) -> 1966 | CP64: =SUM(BK64:BN64) -> 1878 | CQ64: =SUM(BO64:BR64) -> 1682 | CR64: =CQ64*0.9 -> 1513.8 | CS64: =CR64*0.9 -> 1362.42 | CT64: =CS64*0.9 -> 1226.178 | CU64: =CT64*0.9 -> 1103.5602 | CV64: =CU64*0.9 -> 993.20418 | CW64: =CV64*0.9 -> 893.88376 | CX64: =CW64*0.9 -> 804.49539 | CY64: =CX64*0.9 -> 724.04585 | CZ64: =CY64*0.9 -> 651.64126
B65: R&D | C65: 0 | D65: 0 | E65: 0 | F65: 0 | G65: 0 | H65: 0 | I65: 0 | J65: 0 | K65: 0 | L65: 0 | M65: 0 | N65: 0 | O65: 0 | P65: 0 | Q65: 0 | R65: 0 | S65: 0 | T65: 0 | U65: 0 | V65: 0 | W65: 0 | X65: 0 | Y65: 0 | Z65: 0 | AA65: 0 | AB65: 0 | AC65: 0 | AD65: 0 | AE65: 0 | AF65: 0 | AG65: 0 | AH65: 0 | AI65: 0 | AJ65: 0 | AK65: 0 | AL65: 0 | AM65: 0 | AN65: 0 | AO65: 0 | AP65: 0 | AQ65: 0 | AR65: 0 | AS65: 0 | AT65: 0 | AU65: 578 | AV65: 564 | AW65: 580 | AX65: =2420-SUM(AU65:AW65) -> 698 | AY65: 654 | AZ65: 654 | BA65: 672 | BB65: =2742-SUM(AY65:BA65) -> 762 | BC65: 697 | BD65: 684 | BE65: 782 | BF65: =2888-SUM(BC65:BE65) -> 725 | BG65: 654 | BH65: 715 | BI65: 672 | BJ65: =2741-SUM(BG65:BI65) -> 700 | BK65: 684 | BL65: 698 | BM65: 713 | BN65: =2844-SUM(BK65:BM65) -> 749 | BO65: 716 | BP65: 725 | BQ65: 766 | BR65: 735 | BS65: 767 | BT65: 892 | CA65: =SUM(C65:F65) -> 0 | CB65: =SUM(G65:J65) -> 0 | CC65: =SUM(K65:N65) -> 0 | CD65: =SUM(O65:R65) -> 0 | CE65: =SUM(S65:V65) -> 0 | CF65: =SUM(W65:Z65) -> 0 | CG65: =SUM(AA65:AD65) -> 0 | CH65: =SUM(AE65:AH65) -> 0 | CI65: =SUM(AI65:AL65) -> 0 | CJ65: =SUM(AM65:AP65) -> 0 | CK65: =SUM(AQ65:AT65) -> 0 | CL65: =SUM(AU65:AX65) -> 2420 | CM65: =SUM(AY65:BB65) -> 2742 | CN65: =SUM(BC65:BF65) -> 2888 | CO65: =SUM(BG65:BJ65) -> 2741 | CP65: =SUM(BK65:BN65) -> 2844 | CQ65: =SUM(BO65:BR65) -> 2942 | CR65: =CR61*CR80 -> 3272.044 | CS65: =CS61*CS80 -> 3512.2716 | CT65: =CT61*CT80 -> 3780.084 | CU65: =CU61*CU80 -> 4114.081 | CV65: =CV61*CV80 -> 4410.8808 | CW65: =CW61*CW80 -> 4765.8417 | CX65: =CX61*CX80 -> 5032.2172 | CY65: =CY61*CY80 -> 5334.2029 | CZ65: =CZ61*CZ80 -> 5611.2168
B66: SG&A | C66: 0 | D66: 0 | E66: 0 | F66: 0 | G66: 0 | H66: 0 | I66: 0 | J66: 0 | K66: 0 | L66: 0 | M66: 0 | N66: 0 | O66: 0 | P66: 0 | Q66: 0 | R66: 0 | S66: 0 | T66: 0 | U66: 0 | V66: 0 | W66: 0 | X66: 0 | Y66: 0 | Z66: 0 | AA66: 0 | AB66: 0 | AC66: 0 | AD66: 0 | AE66: 0 | AF66: 0 | AG66: 0 | AH66: 0 | AI66: 0 | AJ66: 0 | AK66: 0 | AL66: 0 | AM66: 0 | AN66: 0 | AO66: 0 | AP66: 0 | AQ66: 0 | AR66: 0 | AS66: 0 | AT66: 0 | AU66: 2548 | AV66: 2276 | AW66: 2302 | AX66: =9696-SUM(AU66:AW66) -> 2570 | AY66: 2783 | AZ66: 2726 | BA66: 2767 | BB66: =11324-SUM(AY66:BA66) -> 3048 | BC66: 2787 | BD66: 2757 | BE66: 2731 | BF66: =11248-SUM(BC66:BE66) -> 2973 | BG66: 2762 | BH66: 2740 | BI66: 2723 | BJ66: =10949-SUM(BG66:BI66) -> 2724 | BK66: 2959 | BL66: 2936 | BM66: 2895 | BN66: =11697-SUM(BK66:BM66) -> 2907 | BO66: 3061 | BP66: 3091 | BQ66: 3051 | BR66: 3129 | BS66: 3740 | BT66: 4025 | CA66: =SUM(C66:F66) -> 0 | CB66: =SUM(G66:J66) -> 0 | CC66: =SUM(K66:N66) -> 0 | CD66: =SUM(O66:R66) -> 0 | CE66: =SUM(S66:V66) -> 0 | CF66: =SUM(W66:Z66) -> 0 | CG66: =SUM(AA66:AD66) -> 0 | CH66: =SUM(AE66:AH66) -> 0 | CI66: =SUM(AI66:AL66) -> 0 | CJ66: =SUM(AM66:AP66) -> 0 | CK66: =SUM(AQ66:AT66) -> 0 | CL66: =SUM(AU66:AX66) -> 9696 | CM66: =SUM(AY66:BB66) -> 11324 | CN66: =SUM(BC66:BF66) -> 11248 | CO66: =SUM(BG66:BJ66) -> 10949 | CP66: =SUM(BK66:BN66) -> 11697 | CQ66: =SUM(BO66:BR66) -> 12332 | CR66: =CR61*CR81 -> 16119.629 | CS66: =CS61*CS81 -> 16528.337 | CT66: =CT61*CT81 -> 17489.941 | CU66: =CU61*CU81 -> 18421.258 | CV66: =CV61*CV81 -> 19381.143 | CW66: =CW61*CW81 -> 20218.722 | CX66: =CX61*CX81 -> 21483.696 | CY66: =CY61*CY81 -> 22567.781 | CZ66: =CZ61*CZ81 -> 23653.437
B67: Ttl Operating Costs | C67: 2721.7 | D67: 2694.5 | E67: 2761.4 | F67: 3142.1 | G67: 2892.8 | H67: 3676.1 | I67: 3752.2 | J67: 4092.9 | K67: 3880.7 | L67: 3972.4 | M67: 5248.5 | N67: 4457 | O67: 2415.3 | P67: 2379.1 | Q67: 2465.9 | R67: 1530.8 | S67: 2331 | T67: 2274 | U67: 2097 | V67: 1629 | W67: 2116 | X67: 2092 | Y67: 2032 | Z67: 2180 | AA67: 2206 | AB67: 2223 | AC67: 2195 | AD67: 2167 | AE67: 2221 | AF67: 2230 | AG67: 2120 | AH67: 2162 | AI67: 3515 | AJ67: 3062 | AK67: 3184 | AL67: 3656 | AM67: 3715 | AN67: 3603 | AO67: 3495 | AP67: 3409 | AQ67: 3636 | AR67: 3494 | AS67: 3520 | AT67: 3491 | AU67: =SUM(AU64:AU66) -> 3687 | AV67: =SUM(AV64:AV66) -> 3393 | AW67: =SUM(AW64:AW66) -> 3392 | AX67: =SUM(AX64:AX66) -> 3776 | AY67: =SUM(AY64:AY66) -> 3946 | AZ67: =SUM(AZ64:AZ66) -> 3884 | BA67: =SUM(BA64:BA66) -> 3959 | BB67: =SUM(BB64:BB66) -> 4324 | ... BT67: =SUM(BT64:BT66) -> 5575 | CA67: =SUM(C67:F67) -> 11319.7 | CB67: =SUM(G67:J67) -> 14414 | CC67: =SUM(K67:N67) -> 17558.6 | CD67: =SUM(O67:R67) -> 8791.1 | CE67: =SUM(S67:V67) -> 8331 | CF67: =SUM(W67:Z67) -> 8420 | CG67: =SUM(AA67:AD67) -> 8791 | CH67: =SUM(AE67:AH67) -> 8733 | CI67: =SUM(AI67:AL67) -> 13417 | CJ67: =SUM(AM67:AP67) -> 14222 | CK67: =SUM(AQ67:AT67) -> 14141 | CL67: =SUM(AU67:AX67) -> 14248 | CM67: =SUM(AY67:BB67) -> 16113 | CN67: =SUM(BC67:BF67) -> 16149 | CO67: =SUM(BG67:BJ67) -> 15656 | CP67: =SUM(BK67:BN67) -> 16419 | CQ67: =SUM(BO67:BR67) -> 16956 | CR67: =SUM(CR64:CR66) -> 20905.473 | CS67: =SUM(CS64:CS66) -> 21403.029 | CT67: =SUM(CT64:CT66) -> 22496.203 | CU67: =SUM(CU64:CU66) -> 23638.899 | CV67: =SUM(CV64:CV66) -> 24785.228 | CW67: =SUM(CW64:CW66) -> 25878.448 | CX67: =SUM(CX64:CX66) -> 27320.409 | CY67: =SUM(CY64:CY66) -> 28626.03 | CZ67: =SUM(CZ64:CZ66) -> 29916.295
B68: OI | C68: =C63-C67 -> 1060.8 | D68: =D63-D67 -> 1671.4 | E68: =E63-E67 -> 1639.7 | F68: =F63-F67 -> 1863.8 | G68: =G63-G67 -> 1470.5 | H68: =H63-H67 -> 1606 | I68: =I63-I67 -> 1181.2 | J68: =J63-J67 -> 1829.9 | ... BT68: =BT63-BT67 -> 1693 | CA68: =SUM(C68:F68) -> 6235.7 | CB68: =SUM(G68:J68) -> 6087.6 | CC68: =SUM(K68:N68) -> 5751.5 | CD68: =SUM(O68:R68) -> 1359.8 | CE68: =SUM(S68:V68) -> 2133 | CF68: =SUM(W68:Z68) -> 2596 | CG68: =SUM(AA68:AD68) -> 2867 | CH68: =SUM(AE68:AH68) -> 3026 | CI68: =SUM(AI68:AL68) -> 1564 | CJ68: =SUM(AM68:AP68) -> 3650 | CK68: =SUM(AQ68:AT68) -> 4532 | CL68: =SUM(AU68:AX68) -> 5357 | CM68: =SUM(AY68:BB68) -> 8425 | CN68: =SUM(BC68:BF68) -> 8362 | CO68: =SUM(BG68:BJ68) -> 6478 | CP68: =SUM(BK68:BN68) -> 6825 | CQ68: =SUM(BO68:BR68) -> 8053 | CR68: =CR63-CR67 -> 5800.1808 | CS68: =CS63-CS67 -> 7314.957 | CT68: =CT63-CT67 -> 8929.2715 | CU68: =CU63-CU67 -> 10624.641 | CV68: =CV63-CV67 -> 12573.596 | CW68: =CW63-CW67 -> 14558.997 | CX68: =CX63-CX67 -> 16034.077 | CY68: =CY63-CY67 -> 17330.179 | CZ68: =CZ63-CZ67 -> 18426.496
B69: Interest Expenses | C69: 0 | D69: 0 | E69: 0 | F69: 0 | G69: 0 | H69: 0 | I69: 0 | J69: 0 | K69: 0 | L69: 0 | M69: 0 | N69: 0 | O69: 0 | P69: 0 | Q69: 0 | R69: 0 | S69: 0 | T69: 0 | U69: 0 | V69: 0 | W69: 0 | X69: 0 | Y69: 0 | Z69: 0 | AA69: 0 | AB69: 0 | AC69: 0 | AD69: 0 | AE69: 0 | AF69: 0 | AG69: 0 | AH69: 0 | AI69: 0 | AJ69: 0 | AK69: 0 | AL69: 0 | AM69: 0 | AN69: 0 | AO69: 0 | AP69: 0 | AQ69: 0 | AR69: 0 | AS69: 0 | AT69: 0 | AU69: 139 | AV69: 134 | AW69: 137 | AX69: =546-SUM(AU69:AW69) -> 136 | AY69: 135 | AZ69: 134 | BA69: 133 | BB69: =533-SUM(AY69:BA69) -> 131 | BC69: 131 | BD69: 132 | BE69: 141 | BF69: =558-SUM(BC69:BE69) -> 154 | BG69: 153 | BH69: 159 | BI69: 166 | BJ69: =637-SUM(BG69:BI69) -> 159 | BK69: 141 | BL69: 140 | BM69: 142 | BN69: =559-SUM(BK69:BM69) -> 136 | BO69: 131 | BP69: 121 | BQ69: 121 | BR69: 42 | BS69: 174 | BT69: 351 | CA69: =SUM(C72:F72) -> 958 | CB69: =SUM(G72:J72) -> -374.8 | CC69: =SUM(K72:N72) -> -552.6 | CD69: =SUM(O72:R72) -> -1580 | CE69: =SUM(S72:V72) -> -92 | CF69: =SUM(W72:Z72) -> -81 | CG69: =SUM(AA72:AD72) -> 316 | CH69: =SUM(AE72:AH72) -> -1613 | CI69: =SUM(AI72:AL72) -> 667 | CJ69: =SUM(AM72:AP72) -> -777 | CK69: =SUM(AQ72:AT72) -> -455 | CL69: =SUM(AU69:AX69) -> 546 | CM69: =SUM(AY69:BB69) -> 533 | CN69: =SUM(BC69:BF69) -> 558 | CO69: =SUM(BG69:BJ69) -> 637 | CP69: =SUM(BK69:BN69) -> 559 | CQ69: =SUM(BO69:BR69) -> 415 | CR69: 525 | CS69: 500 | CT69: 475 | CU69: 470 | CV69: 465 | CW69: 460 | CX69: 455 | CY69: 450 | CZ69: 445
B70: Interest Income | C70: 0 | D70: 0 | E70: 0 | F70: 0 | G70: 0 | H70: 0 | I70: 0 | J70: 0 | K70: 0 | L70: 0 | M70: 0 | N70: 0 | O70: 0 | P70: 0 | Q70: 0 | R70: 0 | S70: 0 | T70: 0 | U70: 0 | V70: 0 | W70: 0 | X70: 0 | Y70: 0 | Z70: 0 | AA70: 0 | AB70: 0 | AC70: 0 | AD70: 0 | AE70: 0 | AF70: 0 | AG70: 0 | AH70: 0 | AI70: 0 | AJ70: 0 | AK70: 0 | AL70: 0 | AM70: 0 | AN70: 0 | AO70: 0 | AP70: 0 | AQ70: 0 | AR70: 0 | AS70: 0 | AT70: 0 | AU70: -18 | AV70: -9 | AW70: -10 | AX70: =-46-SUM(AU70:AW70) -> -9 | AY70: -11 | AZ70: -11 | BA70: -10 | BB70: =-43-SUM(AY70:BA70) -> -11 | BC70: -14 | BD70: -26 | BE70: -55 | BF70: =-183-SUM(BC70:BE70) -> -88 | BG70: -101 | BH70: -98 | BI70: -97 | BJ70: =-385-SUM(BG70:BI70) -> -89 | BK70: -80 | BL70: -82 | BM70: -91 | BN70: =-344-SUM(BK70:BM70) -> -91 | BO70: -82 | BP70: -71 | BQ70: -77 | BR70: -15 | BS70: -106 | BT70: -52 | CA70: =SUM(C70:F70) -> 0 | CB70: =SUM(G70:J70) -> 0 | CC70: =SUM(K70:N70) -> 0 | CD70: =SUM(O70:R70) -> 0 | CE70: =SUM(S70:V70) -> 0 | CF70: =SUM(W70:Z70) -> 0 | CG70: =SUM(AA70:AD70) -> 0 | CH70: =SUM(AE70:AH70) -> 0 | CI70: =SUM(AI70:AL70) -> 0 | CJ70: =SUM(AM70:AP70) -> 0 | CK70: =SUM(AQ70:AT70) -> 0 | CL70: =SUM(AU70:AX70) -> -46 | CM70: =SUM(AY70:BB70) -> -43 | CN70: =SUM(BC70:BF70) -> -183 | CO70: =SUM(BG70:BJ70) -> -385 | CP70: =SUM(BK70:BN70) -> -344 | CQ70: =SUM(BO70:BR70) -> -245 | CR70: =-CQ86*($DA$89) -> -894.81 | CS70: =-CR86*($DA$89) -> -1440.1748 | CT70: =-CS86*($DA$89) -> -2156.4494 | CU70: =-CT86*($DA$89) -> -3065.6157 | CV70: =-CU86*($DA$89) -> -4188.3274 | CW70: =-CV86*($DA$89) -> -5562.4803 | CX70: =-CW86*($DA$89) -> -7211.4848 | CY70: =-CX86*($DA$89) -> -9116.4444 | CZ70: =-CY86*($DA$89) -> -11283.731
B71: ForEx (Gain) Loss | C71: 0 | D71: 0 | E71: 0 | F71: 0 | G71: 0 | H71: 0 | I71: 0 | J71: 0 | K71: 0 | L71: 0 | M71: 0 | N71: 0 | O71: 0 | P71: 0 | Q71: 0 | R71: 0 | S71: 0 | T71: 0 | U71: 0 | V71: 0 | W71: 0 | X71: 0 | Y71: 0 | Z71: 0 | AA71: 0 | AB71: 0 | AC71: 0 | AD71: 0 | AE71: 0 | AF71: 0 | AG71: 0 | AH71: 0 | AI71: 0 | AJ71: 0 | AK71: 0 | AL71: 0 | AM71: 0 | AN71: 0 | AO71: 0 | AP71: 0 | AQ71: 0 | AR71: 0 | AS71: 0 | AT71: 0 | AU71: 5 | AV71: -1 | AW71: -7 | AX71: =-8-SUM(AU71:AW71) -> -5 | AY71: 3 | AZ71: 0 | BA71: 4 | BB71: =1-SUM(AY71:BA71) -> -6 | BC71: -3 | BD71: 0 | BE71: 19 | BF71: =2-SUM(BC71:BE71) -> -14 | BG71: 6 | BH71: 21 | BI71: -10 | BJ71: =41-SUM(BG71:BI71) -> 24 | BK71: 0 | BL71: -6 | BM71: -11 | BN71: =-27-SUM(BK71:BM71) -> -10 | BO71: -7 | BP71: -11 | BQ71: -17 | BR71: 0 | BS71: -13 | BT71: 4 | CA71: =SUM(C71:F71) -> 0 | CB71: =SUM(G71:J71) -> 0 | CC71: =SUM(K71:N71) -> 0 | CD71: =SUM(O71:R71) -> 0 | CE71: =SUM(S71:V71) -> 0 | CF71: =SUM(W71:Z71) -> 0 | CG71: =SUM(AA71:AD71) -> 0 | CH71: =SUM(AE71:AH71) -> 0 | CI71: =SUM(AI71:AL71) -> 0 | CJ71: =SUM(AM71:AP71) -> 0 | CK71: =SUM(AQ71:AT71) -> 0 | CL71: =SUM(AU71:AX71) -> -8 | CM71: =SUM(AY71:BB71) -> 1 | CN71: =SUM(BC71:BF71) -> 2 | CO71: =SUM(BG71:BJ71) -> 41 | CP71: =SUM(BK71:BN71) -> -27 | CQ71: =SUM(BO71:BR71) -> -35 | CR71: 0 | CS71: 0 | CT71: 0 | CU71: 0 | CV71: 0 | CW71: 0 | CX71: 0 | CY71: 0 | CZ71: 0
B72: Other Income | C72: 871.7 | D72: -104.4 | E72: 231.6 | F72: -40.9 | G72: -148.3 | H72: -47.3 | I72: -117.1 | J72: -62.1 | K72: -232.4 | L72: -98.9 | M72: -93.3 | N72: -128 | O72: -45.8 | P72: -34.7 | Q72: -78.7 | R72: -1420.8 | S72: -61 | T72: -26 | U72: 8 | V72: -13 | W72: -24 | X72: -19 | Y72: -13 | Z72: -25 | AA72: 43 | AB72: 257 | AC72: 1 | AD72: 15 | AE72: -522 | AF72: -101 | AG72: -1076 | AH72: 86 | AI72: 978 | AJ72: -91 | AK72: -143 | AL72: -77 | AM72: -177 | AN72: -105 | AO72: -277 | AP72: -218 | AQ72: -107 | AR72: -104 | AS72: -95 | AT72: -149 | AU72: -1 | AV72: 22 | AW72: -46 | AX72: =-103-SUM(AU72:AW72) -> -78 | AY72: -61 | AZ72: -79 | BA72: -74 | BB72: =-277-SUM(AY72:BA72) -> -63 | BC72: -78 | BD72: -82 | BE72: -93 | BF72: =-321-SUM(BC72:BE72) -> -68 | BG72: -111 | BH72: -176 | BI72: -83 | BJ72: =-479-SUM(BG72:BI72) -> -109 | BK72: -111 | BL72: 10 | BM72: -121 | BN72: =-376-SUM(BK72:BM72) -> -154 | BO72: -127 | BP72: -137 | BQ72: -150 | BR72: -134 | BS72: -159 | BT72: -134 | CA72: =SUM(C72:F72) -> 958 | CB72: =SUM(G72:J72) -> -374.8 | CC72: =SUM(K72:N72) -> -552.6 | CD72: =SUM(O72:R72) -> -1580 | CE72: =SUM(S72:V72) -> -92 | CF72: =SUM(W72:Z72) -> -81 | CG72: =SUM(AA72:AD72) -> 316 | CH72: =SUM(AE72:AH72) -> -1613 | CI72: =SUM(AI72:AL72) -> 667 | CJ72: =SUM(AM72:AP72) -> -777 | CK72: =SUM(AQ72:AT72) -> -455 | CL72: =SUM(AU72:AX72) -> -103 | CM72: =SUM(AY72:BB72) -> -277 | CN72: =SUM(BC72:BF72) -> -321 | CO72: =SUM(BG72:BJ72) -> -479 | CP72: =SUM(BK72:BN72) -> -376 | CQ72: =SUM(BO72:BR72) -> -548 | CR72: =CQ72*(1.05) -> -575.4 | CS72: =CR72*(1.05) -> -604.17 | CT72: =CS72*(1.05) -> -634.3785 | CU72: =CT72*(1.05) -> -666.09743 | CV72: =CU72*(1.05) -> -699.4023 | CW72: =CV72*(1.05) -> -734.37241 | CX72: =CW72*(1.05) -> -771.09103 | CY72: =CX72*(1.05) -> -809.64558 | CZ72: =CY72*(1.05) -> -850.12786
B73: Pretax Income | C73: =C68+C72 -> 1932.5 | D73: =D68+D72 -> 1567 | E73: =E68+E72 -> 1871.3 | F73: =F68+F72 -> 1822.9 | G73: =G68+G72 -> 1322.2 | H73: =H68+H72 -> 1558.7 | I73: =I68+I72 -> 1064.1 | J73: =J68+J72 -> 1767.8 | ... AT73: =AT68+AT72 -> 1240 | AU73: =AU68-SUM(AU69:AU72) -> 633 | AV73: =AV68-SUM(AV69:AV72) -> 526 | AW73: =AW68-SUM(AW69:AW72) -> 1421 | AX73: =AX68-SUM(AX69:AX72) -> 2388 | AY73: =AY68-SUM(AY69:AY72) -> 2043 | AZ73: =AZ68-SUM(AZ69:AZ72) -> 1348 | BA73: =BA68-SUM(BA69:BA72) -> 2493 | BB73: =BB68-SUM(BB69:BB72) -> 2327 | ... BT73: =BT68-SUM(BT69:BT72) -> 1524 | CA73: =SUM(C73:F73) -> 7193.7 | CB73: =SUM(G73:J73) -> 5712.8 | CC73: =SUM(K73:N73) -> 5198.9 | CD73: =SUM(O73:R73) -> -220.2 | CE73: =SUM(S73:V73) -> 2041 | CF73: =SUM(W73:Z73) -> 2515 | CG73: =SUM(AA73:AD73) -> 3183 | CH73: =SUM(AE73:AH73) -> 1413 | CI73: =SUM(AI73:AL73) -> 2231 | CJ73: =SUM(AM73:AP73) -> 2873 | CK73: =SUM(AQ73:AT73) -> 4077 | CL73: =SUM(AU73:AX73) -> 4968 | CM73: =SUM(AY73:BB73) -> 8211 | CN73: =SUM(BC73:BF73) -> 8306 | CO73: =SUM(BG73:BJ73) -> 6664 | CP73: =SUM(BK73:BN73) -> 7013 | CQ73: =SUM(BO73:BR73) -> 8466 | CR73: =CR68-SUM(CR69:CR72) -> 6745.3908 | CS73: =CS68-SUM(CS69:CS72) -> 8859.3018 | CT73: =CT68-SUM(CT69:CT72) -> 11245.099 | CU73: =CU68-SUM(CU69:CU72) -> 13886.354 | CV73: =CV68-SUM(CV69:CV72) -> 16996.326 | CW73: =CW68-SUM(CW69:CW72) -> 20395.849 | CX73: =CX68-SUM(CX69:CX72) -> 23561.653 | CY73: =CY68-SUM(CY69:CY72) -> 26806.269 | CZ73: =CZ68-SUM(CZ69:CZ72) -> 30115.355
B74: Taxes | C74: 493.8 | D74: 278.9 | E74: 391 | F74: 284.2 | G74: 319.2 | H74: 267 | I74: 173.4 | J74: 327 | K74: 205 | L74: -268.2 | M74: 198.4 | N74: 335 | O74: 112.2 | P74: 118.7 | Q74: -107.6 | R74: -580.2 | S74: 10 | T74: 125 | U74: -163 | V74: 81 | W74: 117 | X74: 233 | Y74: 278 | Z74: 169 | AA74: 124 | AB74: 200 | AC74: 118 | AD74: 135 | AE74: -54 | AF74: 116 | AG74: 178 | AH74: 110 | AI74: 350 | AJ74: 25 | AK74: 65 | AL74: 1438 | AM74: 22 | AN74: 59 | AO74: 166 | AP74: 292 | AQ74: -40 | AR74: 96 | AS74: 143 | AT74: 191 | AU74: 69 | AV74: -11 | AW74: 189 | AX74: =497-SUM(AU74:AW74) -> 250 | AY74: 250 | AZ74: 159 | BA74: 393 | BB74: =1140-SUM(AY74:BA74) -> 338 | BC74: 429 | BD74: 334 | BE74: 323 | BF74: =1373-SUM(BC74:BE74) -> 287 | BG74: 244 | BH74: 261 | BI74: 235 | BJ74: =941-SUM(BG74:BI74) -> 201 | BK74: 211 | BL74: 305 | BM74: 294 | BN74: =-6389-SUM(BK74:BM74) -> -7199 | BO74: 453 | BP74: 371 | BQ74: 536 | BR74: 582 | BS74: 372 | BT74: 596 | CA74: =SUM(C74:F74) -> 1447.9 | CB74: =SUM(G74:J74) -> 1086.6 | CC74: =SUM(K74:N74) -> 470.2 | CD74: =SUM(O74:R74) -> -456.9 | CE74: =SUM(S74:V74) -> 53 | CF74: =SUM(W74:Z74) -> 797 | CG74: =SUM(AA74:AD74) -> 577 | CH74: =SUM(AE74:AH74) -> 350 | CI74: =SUM(AI74:AL74) -> 1878 | CJ74: =SUM(AM74:AP74) -> 539 | CK74: =SUM(AQ74:AT74) -> 390 | CL74: =SUM(AU74:AX74) -> 497 | CM74: =SUM(AY74:BB74) -> 1140 | CN74: =SUM(BC74:BF74) -> 1373 | CO74: =SUM(BG74:BJ74) -> 941 | CP74: =SUM(BK74:BN74) -> -6389 | CQ74: =SUM(BO74:BR74) -> 1942 | CR74: =CR73*CR83 -> 1551.4399 | CS74: =CS73*CS83 -> 2037.6394 | CT74: =CT73*CT83 -> 2586.3729 | CU74: =CU73*CU83 -> 3193.8614 | CV74: =CV73*CV83 -> 3909.1549 | CW74: =CW73*CW83 -> 4691.0454 | CX74: =CX73*CX83 -> 5419.1802 | CY74: =CY73*CY83 -> 6165.4419 | CZ74: =CZ73*CZ83 -> 6926.5317
B75: Net Income | C75: =C73-C74 -> 1438.7 | D75: =D73-D74 -> 1288.1 | E75: =E73-E74 -> 1480.3 | F75: =F73-F74 -> 1538.7 | G75: =G73-G74 -> 1003 | H75: =H73-H74 -> 1291.7 | I75: =I73-I74 -> 890.7 | J75: =J73-J74 -> 1440.8 | ... BT75: =BT73-BT74 -> 928 | CA75: =SUM(C75:F75) -> 5745.8 | CB75: =SUM(G75:J75) -> 4626.2 | CC75: =SUM(K75:N75) -> 4728.7 | CD75: =SUM(O75:R75) -> 236.7 | CE75: =SUM(S75:V75) -> 1988 | CF75: =SUM(W75:Z75) -> 1718 | CG75: =SUM(AA75:AD75) -> 2606 | CH75: =SUM(AE75:AH75) -> 1063 | CI75: =SUM(AI75:AL75) -> 353 | CJ75: =SUM(AM75:AP75) -> 2334 | CK75: =SUM(AQ75:AT75) -> 3687 | CL75: =SUM(AU75:AX75) -> 4471 | CM75: =SUM(AY75:BB75) -> 7071 | CN75: =SUM(BC75:BF75) -> 6933 | CO75: =SUM(BG75:BJ75) -> 5723 | CP75: =SUM(BK75:BN75) -> 13402 | CQ75: =SUM(BO75:BR75) -> 6524 | CR75: =CR73-CR74 -> 5193.9509 | CS75: =CS73-CS74 -> 6821.6624 | CT75: =CT73-CT74 -> 8658.7265 | CU75: =CU73-CU74 -> 10692.493 | CV75: =CV73-CV74 -> 13087.171 | CW75: =CW73-CW74 -> 15704.804 | CX75: =CX73-CX74 -> 18142.473 | CY75: =CY73-CY74 -> 20640.827 | CZ75: =CZ73-CZ74 -> 23188.823 | DA75: =CZ75*(1+$DA$90) -> 23304.768 | DB75: =DA75*(1+$DA$90) -> 23421.291 | DC75: =DB75*(1+$DA$90) -> 23538.398 | DD75: =DC75*(1+$DA$90) -> 23656.09 | DE75: =DD75*(1+$DA$90) -> 23774.37 | DF75: =DE75*(1+$DA$90) -> 23893.242 | DG75: =DF75*(1+$DA$90) -> 24012.708 | DH75: =DG75*(1+$DA$90) -> 24132.772 | ... EX75: =EW75*(1+$DA$90) -> 29756.497
B76: SC | C76: 1546 | D76: 1546 | E76: 1546 | F76: 1547 | G76: 1548 | H76: 1544 | I76: 1545 | J76: 1546 | K76: 1552 | L76: 1557 | M76: 1559 | N76: 1557 | O76: 1574 | P76: 1572 | Q76: 1577 | R76: 1575 | S76: 1569 | T76: 1561 | U76: 1552 | V76: 1558 | W76: 1533 | X76: 1507 | Y76: 1509 | Z76: 1516 | AA76: 1505 | AB76: 1494 | AC76: 1495 | AD76: 1496 | AE76: 1477 | AF76: 1475 | AG76: 1476 | AH76: 1477 | AI76: 1727 | AJ76: 1741 | AK76: 1744 | AL76: 1740 | AM76: 1753 | AN76: 1758 | AO76: 1760 | AP76: 1758 | AQ76: 1763 | AR76: 1769 | AS76: 1772 | AT76: 1768 | AU76: 1769 | AV76: 1773 | AW76: 1774 | AX76: 1773 | AY76: 1777 | AZ76: 1779 | BA76: 1775 | BB76: 1775 | BC76: 1762 | BD76: 1754 | BE76: 1753 | BF76: 1753 | BG76: 1742 | BH76: 1740 | BI76: 1739 | BJ76: 1740 | BK76: 1740 | BL76: 1743 | BM76: 1739 | BN76: 1740 | BO76: 1739 | BP76: 1743 | BQ76: 1742 | BR76: 1749 | BS76: 1747.07 | BT76: 1743 | CA76: =AVERAGE(C76:F76) -> 1546.25 | CB76: =AVERAGE(G76:J76) -> 1545.75 | CC76: =AVERAGE(K76:N76) -> 1556.25 | CD76: =AVERAGE(O76:R76) -> 1574.5 | CE76: =AVERAGE(S76:V76) -> 1560 | CF76: =AVERAGE(W76:Z76) -> 1516.25 | CG76: =AVERAGE(AA76:AD76) -> 1497.5 | CH76: =AVERAGE(AE76:AH76) -> 1476.25 | CI76: =AVERAGE(AI76:AL76) -> 1738 | CJ76: =AVERAGE(AM76:AP76) -> 1757.25 | CK76: =AVERAGE(AQ76:AT76) -> 1768 | CL76: =AVERAGE(AU76:AX76) -> 1772.25 | CM76: =AVERAGE(AY76:BB76) -> 1776.5 | CN76: =AVERAGE(BC76:BF76) -> 1755.5 | CO76: =AVERAGE(BG76:BJ76) -> 1740.25 | CP76: =AVERAGE(BK76:BN76) -> 1740.5 | CQ76: =AVERAGE(BO76:BR76) -> 1743.25
B77: EPS | C77: =C75/C76 -> 0.93059508 | D77: =D75/D76 -> 0.83318241 | E77: =E75/E76 -> 0.95750323 | F77: =F75/F76 -> 0.99463478 | G77: =G75/G76 -> 0.64793282 | H77: =H75/H76 -> 0.83659326 | I77: =I75/I76 -> 0.57650485 | J77: =J75/J76 -> 0.93195343 | ... BT77: =BT75/BT76 -> 0.53241538 | CA77: =SUM(C77:F77) -> 3.7159155 | CB77: =SUM(G77:J77) -> 2.9929844 | CC77: =SUM(K77:N77) -> 3.0385957 | CD77: =SUM(O77:R77) -> 0.15065213 | CE77: =SUM(S77:V77) -> 1.2745578 | CF77: =SUM(W77:Z77) -> 1.1346183 | CG77: =SUM(AA77:AD77) -> 1.7408338 | CH77: =SUM(AE77:AH77) -> 0.72008824 | CI77: =SUM(AI77:AL77) -> 0.20371485 | CJ77: =SUM(AM77:AP77) -> 1.3279518 | CK77: =SUM(AQ77:AT77) -> 2.0849378 | CL77: =SUM(AU77:AX77) -> 2.5220422 | CM77: =SUM(AY77:BB77) -> 3.9810189 | CN77: =SUM(BC77:BF77) -> 3.9471481 | CO77: =SUM(BG77:BJ77) -> 3.2886854 | CP77: =SUM(BK77:BN77) -> 7.7015549 | CQ77: =SUM(BO77:BR77) -> 3.7417664
B79: Gross Profit Margin | C79: =C63/C61 -> 0.56300607 | D79: =D63/D61 -> 0.58251611 | E79: =E63/E61 -> 0.56705707 | F79: =F63/F61 -> 0.56949295 | G79: =G63/G61 -> 0.56678011 | H79: =H63/H61 -> 0.59847043 | I79: =I63/I61 -> 0.56872442 | J79: =J63/J61 -> 0.5941933 | ... BT79: =BT63/BT61 -> 0.57714603 | CA79: =CA63/CA61 -> 0.57063453 | CB79: =CB63/CB61 -> 0.58298333 | CC79: =CC63/CC61 -> 0.59999022 | CD79: =CD63/CD61 -> 0.53285564 | CE79: =CE63/CE61 -> 0.53232945 | CF79: =CF63/CF61 -> 0.54475324 | CG79: =CG63/CG61 -> 0.57133056 | CH79: =CH63/CH61 -> 0.56389968 | ... CQ79: =CQ63/CQ61 -> 0.56418065 | CR79: 0.555 | CS79: 0.556 | CT79: 0.557 | CU79: 0.558 | CV79: 0.559 | CW79: 0.56 | CX79: 0.56 | CY79: 0.56 | CZ79: 0.56
B80: R&D as % of Revenue | C80: =C65/C61 -> 0 | D80: =D65/D61 -> 0 | E80: =E65/E61 -> 0 | F80: =F65/F61 -> 0 | G80: =G65/G61 -> 0 | H80: =H65/H61 -> 0 | I80: =I65/I61 -> 0 | J80: =J65/J61 -> 0 | ... BT80: =BT65/BT61 -> 0.070833002 | CA80: =CA65/CA61 -> 0 | CB80: =CB65/CB61 -> 0 | CC80: =CC65/CC61 -> 0 | CD80: =CD65/CD61 -> 0 | CE80: =CE65/CE61 -> 0 | CF80: =CF65/CF61 -> 0 | CG80: =CG65/CG61 -> 0 | CH80: =CH65/CH61 -> 0 | ... CQ80: =CQ65/CQ61 -> 0.066368886 | CR80: 0.068 | CS80: 0.068 | CT80: 0.067 | CU80: 0.067 | CV80: 0.066 | CW80: 0.066 | CX80: 0.065 | CY80: 0.065 | CZ80: 0.065
B81: SG&A as % of Revenue | C81: =C66/C61 -> 0 | D81: =D66/D61 -> 0 | E81: =E66/E61 -> 0 | F81: =F66/F61 -> 0 | G81: =G66/G61 -> 0 | H81: =H66/H61 -> 0 | I81: =I66/I61 -> 0 | J81: =J66/J61 -> 0 | ... BT81: =BT66/BT61 -> 0.31962201 | CA81: =CA66/CA61 -> 0 | CB81: =CB66/CB61 -> 0 | CC81: =CC66/CC61 -> 0 | CD81: =CD66/CD61 -> 0 | CE81: =CE66/CE61 -> 0 | CF81: =CF66/CF61 -> 0 | CG81: =CG66/CG61 -> 0 | CH81: =CH66/CH61 -> 0 | ... CQ81: =CQ66/CQ61 -> 0.27819888 | CR81: 0.335 | CS81: 0.32 | CT81: 0.31 | CU81: 0.3 | CV81: 0.29 | CW81: 0.28 | CX81: 0.2775 | CY81: 0.275 | CZ81: 0.274
B82: Operating Profit Margin | C82: =C68/C61 -> 0.15789474 | D82: =D68/D61 -> 0.22300498 | E82: =E68/E61 -> 0.21126615 | F82: =F68/F61 -> 0.21203399 | G82: =G68/G61 -> 0.19101372 | H82: =H68/H61 -> 0.18196238 | I82: =I68/I61 -> 0.13616923 | J82: =J68/J61 -> 0.18358113 | ... BT82: =BT68/BT61 -> 0.13443977 | CA82: =CA68/CA61 -> 0.2026901 | CB82: =CB68/CB61 -> 0.17310694 | CC82: =CC68/CC61 -> 0.14804071 | CD82: =CD68/CD61 -> 0.071380577 | CE82: =CE68/CE61 -> 0.10851096 | CF82: =CF68/CF61 -> 0.12837504 | CG82: =CG68/CG61 -> 0.14050478 | CH82: =CH68/CH61 -> 0.14511102 | ... CZ82: =CZ68/CZ61 -> 0.21345143
B83: Effective Tax Rate | C83: =C74/C73 -> 0.25552393 | D83: =D74/D73 -> 0.17798341 | E83: =E74/E73 -> 0.20894565 | F83: =F74/F73 -> 0.15590543 | G83: =G74/G73 -> 0.24141582 | H83: =H74/H73 -> 0.17129659 | I83: =I74/I73 -> 0.16295461 | J83: =J74/J73 -> 0.18497568 | ... BT83: =BT74/BT73 -> 0.39107612 | CA83: =CA74/CA73 -> 0.20127334 | CB83: =CB74/CB73 -> 0.19020445 | CC83: =CC74/CC73 -> 0.090442209 | CD83: =CD74/CD73 -> 2.0749319 | CE83: =CE74/CE73 -> 0.025967663 | CF83: =CF74/CF73 -> 0.31689861 | CG83: =CG74/CG73 -> 0.18127553 | CH83: =CH74/CH73 -> 0.24769993 | ... CQ83: =CQ74/CQ73 -> 0.22938814 | CR83: 0.23 | CS83: 0.23 | CT83: 0.23 | CU83: 0.23 | CV83: 0.23 | CW83: 0.23 | CX83: 0.23 | CY83: 0.23 | CZ83: 0.23
B84: Net Profit Margin | C84: =C75/C61 -> 0.21414325 | D84: =D75/D61 -> 0.17186353 | E84: =E75/E61 -> 0.19072836 | F84: =F75/F61 -> 0.1750492 | G84: =G75/G61 -> 0.13028681 | H84: =H75/H61 -> 0.14635169 | I84: =I75/I61 -> 0.10268027 | J84: =J75/J61 -> 0.14454544 | ... BT84: =BT75/BT61 -> 0.073691734 | CA84: =CA75/CA61 -> 0.186766 | CB84: =CB75/CB61 -> 0.13155059 | CC84: =CC75/CC61 -> 0.12171435 | CD84: =CD75/CD61 -> 0.012425197 | CE84: =CE75/CE61 -> 0.10113446 | CF84: =CF75/CF61 -> 0.084956978 | CG84: =CG75/CG61 -> 0.1277138 | CH84: =CH75/CH61 -> 0.050975879 | ... CZ84: =CZ75/CZ61 -> 0.26861794
B86: Cash & CEs | BF86: 9882 | BG86: 9161 | BH86: 7835 | BI86: 6709 | BJ86: 6896 | BK86: 6284 | BL86: 6987 | BM86: 7558 | BN86: 7616 | BO86: 6532 | BP86: 6951 | BQ86: 7511 | BR86: 8522 | BS86: 6803 | BT86: 5104 | CN86: =BF86 -> 9882 | CO86: =BJ86 -> 6896 | CP86: =BN86 -> 7616 | CQ86: =BR86 -> 8522 | CR86: =CQ86+CR75 -> 13715.951 | CS86: =CR86+CS75 -> 20537.613 | CT86: =CS86+CT75 -> 29196.34 | CU86: =CT86+CU75 -> 39888.832 | CV86: =CU86+CV75 -> 52976.003 | CW86: =CV86+CW75 -> 68680.807 | CX86: =CW86+CX75 -> 86823.28 | CY86: =CX86+CY75 -> 107464.11 | CZ86: =CY86+CZ75 -> 130652.93
B87: ST Investments | BF87: 288 | BG87: 371 | BH87: 320 | BI87: 338 | BJ87: 383 | BK87: 367 | BL87: 232 | BM87: 230 | BN87: 351 | BO87: 312 | BP87: 331 | BQ87: 222 | BR87: 417 | BS87: 492 | BT87: 499 | CN87: =BF87 -> 288 | CO87: =BJ87 -> 383 | CP87: =BN87 -> 351 | CQ87: =BR87 -> 417
B88: A/R | BF88: 6218 | BG88: 6020 | BH88: 6172 | BI88: 6499 | BJ88: 6565 | BK88: 6605 | BL88: 6854 | BM88: 7051 | BN88: 6925 | BO88: 7327 | BP88: 7972 | BQ88: 8138 | BR88: 7929 | BS88: 8210 | BT88: 8599 | CN88: =BF88 -> 6218 | CO88: =BJ88 -> 6565 | CP88: =BN88 -> 6925 | CQ88: =BR88 -> 7929
B89: Inventories | BF89: 6173 | BG89: 6673 | BH89: 6871 | BI89: 6650 | BJ89: 6570 | BK89: 6827 | BL89: 6814 | BM89: 6813 | BN89: 6194 | BO89: 6639 | BP89: 6954 | BQ89: 6708 | BR89: 6488 | BS89: 6989 | BT89: 7315 | CN89: =BF89 -> 6173 | CO89: =BJ89 -> 6570 | CP89: =BN89 -> 6194 | CQ89: =BR89 -> 6488 | CS89: Invested Capital | CV89: Avg. (2024-2025) | CX89: Projected ROIC: | CZ89: ROIC | DA89: 0.105
B90: Prepaid Expenses | BF90: 2663 | BG90: 2152 | BH90: 2307 | BI90: 2468 | BJ90: 2256 | BK90: 2293 | BL90: 2232 | BM90: 2150 | BN90: 2570 | BO90: 2343 | BP90: 2260 | BQ90: 2260 | BR90: 2640 | BS90: 3014 | BT90: 3000 | CN90: =BF90 -> 2663 | CO90: =BJ90 -> 2256 | CP90: =BN90 -> 2570 | CQ90: =BR90 -> 2640 | CS90: 2024 | CT90: 2025 | CV90: 2024-2025 | CX90: 2025 | CZ90: Terminal | DA90: 0.005
B91: LT Investments | BF91: 766 | BG91: 776 | BH91: 799 | BI91: 788 | BJ91: 799 | BK91: 818 | BL91: 877 | BM91: 912 | BN91: 886 | BO91: 907 | BP91: 958 | BQ91: 951 | BR91: 918 | BS91: 1090 | BT91: 1111 | CN91: =BF91 -> 766 | CO91: =BJ91 -> 799 | CP91: =BN91 -> 886 | CQ91: =BR91 -> 918 | CS91: =SUM(CP86:CP89)-CP98+CP92+CP94+CP93 -> 57304 | CT91: =SUM(CQ86:CQ89)-CQ98+CQ92+CQ94+CQ93 -> 60493 | CV91: =AVERAGE(CS91:CT91) -> 58898.5 | CX91: =AVERAGE(CQ68)*(1-CQ83) -> 6205.7373 | CZ91: RFR (10-year yield) | DA91: 0.0421
B92: PP&E | BF92: 9162 | BG92: 9282 | BH92: 9449 | BI92: 9552 | BJ92: 10154 | BK92: 10107 | BL92: 10233 | BM92: 10621 | BN92: 10658 | BO92: 10932 | BP92: 11395 | BQ92: 11504 | BR92: 11816 | BS92: 12377 | BT92: 12812 | CN92: =BF92 -> 9162 | CO92: =BJ92 -> 10154 | CP92: =BN92 -> 10658 | CQ92: =BR92 -> 11816 | CX92: =CX91/CV91 -> 0.10536325 | CZ92: ERP (Avg. market return - (less) RFR) | DA92: =9.5%-DA91 -> 0.0529
B93: Intangibles | BF93: 10454 | BG93: 10006 | BH93: 9834 | BI93: 9282 | BJ93: 8815 | BK93: 8296 | BL93: 7827 | BM93: 7352 | BN93: 6647 | BO93: 6261 | BP93: 5920 | BQ93: 5598 | BR93: 5526 | BS93: 17875 | BT93: 17211 | CN93: =BF93 -> 10454 | CO93: =BJ93 -> 8815 | CP93: =BN93 -> 6647 | CQ93: =BR93 -> 5526 | CS93: Capital Structure | CZ93: Equity β (1-year avg.) | DA93: ='Notes | Quant Analysis'!K279 -> 0.71
B94: Goodwill | BF94: 22799 | BG94: 22927 | BH94: 23258 | BI94: 23277 | BJ94: 23679 | BK94: 23383 | BL94: 23308 | BM94: 23658 | BN94: 23108 | BO94: 23359 | BP94: 23952 | BQ94: 23971 | BR94: 24035 | BS94: 35221 | BT94: 35244 | CN94: =BF94 -> 22799 | CO94: =BJ94 -> 23679 | CP94: =BN94 -> 23108 | CQ94: =BR94 -> 24035 | CS94: Mkt Cap | CV94: =Main!C5 -> 178194.84 | CZ94: Discount (Cost of Equity) | DA94: =+DA91+(DA92*DA93) -> 0.079659
B95: Deferred LT Taxes | BF95: 6033 | BG95: 6426 | BH95: 6509 | BI95: 6527 | BJ95: 7097 | BK95: 7487 | BL95: 7653 | BM95: 8011 | BN95: 16459 | BO95: 16836 | BP95: 17306 | BQ95: 17318 | BR95: 18422 | BS95: 18358 | BT95: 18320 | CN95: =BF95 -> 6033 | CO95: =BJ95 -> 7097 | CP95: =BN95 -> 16459 | CQ95: =BR95 -> 18422 | CS95: Debt to Ttl Mkt Cap | CV95: =Main!C7/(Main!C7+CV94) -> 0.053317511
B96: Ttl Assets | BF96: =SUM(BF86:BF95) -> 74438 | BG96: =SUM(BG86:BG95) -> 73794 | BH96: =SUM(BH86:BH95) -> 73354 | BI96: =SUM(BI86:BI95) -> 72090 | BJ96: =SUM(BJ86:BJ95) -> 73214 | BK96: =SUM(BK86:BK95) -> 72467 | BL96: =SUM(BL86:BL95) -> 73017 | BM96: =SUM(BM86:BM95) -> 74356 | ... BT96: =SUM(BT86:BT95) -> 109215 | CN96: =BF96 -> 74438 | CO96: =BJ96 -> 73214 | CP96: =BN96 -> 81414 | CQ96: =BR96 -> 86713 | CS96: Mkt Equity to Ttl Mkt Cap | CV96: =CV94/(CV94+Main!C7) -> 0.94668249 | CZ96: NPV | DA96: =NPV(DA94,CQ75:EX75) -> 218994.41
CS97: Debt / Equity | CV97: =CQ104/CQ107 -> 0.18752724 | CZ97: SC | DA97: =Main!C4 -> 1730.383
B98: A/P | BF98: 4607 | BG98: 4167 | BH98: 4211 | BI98: 3961 | BJ98: 4295 | BK98: 4178 | BL98: 4125 | BM98: 4034 | BN98: 4195 | BO98: 4214 | BP98: 4306 | BQ98: 4123 | BR98: 4240 | BS98: 4679 | BT98: 4794 | CN98: =BF98 -> 4607 | CO98: =BJ98 -> 4295 | CP98: =BN98 -> 4195 | CQ98: =BR98 -> 4240 | CZ98: FV | DA98: =DA96/DA97 -> 126.55834
B99: ST Salaries Payable | BF99: 1556 | BG99: 1098 | BH99: 1362 | BI99: 1479 | BJ99: 1597 | BK99: 1092 | BL99: 1389 | BM99: 1618 | BN99: 1701 | BO99: 1167 | BP99: 1550 | BQ99: 1735 | BR99: 1745 | BS99: 1212 | BT99: 1619 | CN99: =BF99 -> 1556 | CO99: =BJ99 -> 1597 | CP99: =BN99 -> 1701 | CQ99: =BR99 -> 1745 | CS99: Cost of Equity | CZ99: CP | DA99: =Main!C3 -> 102.98
B100: Other ST Liabilities | BF100: 5845 | BG100: 5758 | BH100: 5334 | BI100: 5347 | BJ100: 5422 | BK100: 5220 | BL100: 5071 | BM100: 5427 | BN100: 5143 | BO100: 5600 | BP100: 5656 | BQ100: 5880 | BR100: 5812 | BS100: 6379 | BT100: 6892 | CN100: =BF100 -> 5845 | CO100: =BJ100 -> 5422 | CP100: =BN100 -> 5143 | CQ100: =BR100 -> 5812 | CS100: RFR (10-year yield) | CV100: 0.0409 | CZ100: Change Δ | DA100: =DA98/DA99-1 -> 0.22896041 | DB100: =IF(DA100>0,"Upside","Downside") -> Upside
B101: Dividends Payable | BF101: 887 | BG101: 888 | BH101: 886 | BI101: 886 | BJ101: 955 | BK101: 959 | BL101: 959 | BM101: 956 | BN101: 1024 | BO101: 1032 | BP101: 1030 | BQ101: 1030 | BR101: 1097 | BS101: 1100 | BT101: 1093 | CN101: =BF101 -> 887 | CO101: =BJ101 -> 955 | CP101: =BN101 -> 1024 | CQ101: =BR101 -> 1097 | CS101: Equity β (1-year avg.) | CV101: ='Notes | Quant Analysis'!K279 -> 0.71 | CZ101: {=_xlfn.IFS(DA100>=25%,"Strong Buy",DA100>=10.00001%,"Buy",AND(DA100<=10%,DA100>=-4.9999%),"Hold",AND(DA100<=-5%,DA100>=-14.999999%),"Sell",DA100<=-15%,"Strong Sell")} -> Buy
B102: ST Taxes Payable | BF102: 343 | BG102: 334 | BH102: 273 | BI102: 318 | BJ102: 492 | BK102: 562 | BL102: 601 | BM102: 713 | BN102: 594 | BO102: 485 | BP102: 390 | BQ102: 469 | BR102: 569 | BS102: 598 | BT102: 411 | CN102: =BF102 -> 343 | CO102: =BJ102 -> 492 | CP102: =BN102 -> 594 | CQ102: =BR102 -> 569 | CS102: Market Return(1-year avg.) | CV102: 0.1433
B103: Current Portion of LT Debt | BF103: 2251 | BG103: 2285 | BH103: 2284 | BI103: 1051 | BJ103: 1080 | BK103: 2010 | BL103: 1615 | BM103: 2154 | BN103: 1500 | BO103: 506 | BP103: 507 | BQ103: 1345 | BR103: 3033 | BS103: 4409 | BT103: 3005 | CN103: =BF103 -> 2251 | CO103: =BJ103 -> 1080 | CP103: =BN103 -> 1500 | CQ103: =BR103 -> 3033 | CS103: Cost of Equity | CV103: =(CV100+CV101)*(CV102-CV100) -> 0.07689216
B104: LT Debt | BF104: 14522 | BG104: 14615 | BH104: 14562 | BI104: 14477 | BJ104: 13599 | BK104: 12576 | BL104: 13139 | BM104: 12825 | BN104: 12625 | BO104: 12736 | BP104: 12930 | BQ104: 11596 | BR104: 9896 | BS104: 29638 | BT104: 29603 | CN104: =BF104 -> 14522 | CO104: =BJ104 -> 13599 | CP104: =BN104 -> 12625 | CQ104: =BR104 -> 9896
B105: LT Salaries Payable | BF105: 7522 | BG105: 7417 | BH105: 7038 | BI105: 6877 | BJ105: 6947 | BK105: 6827 | BL105: 6558 | BM105: 6601 | BN105: 6731 | BO105: 6644 | BP105: 6801 | BQ105: 6739 | BR105: 7550 | BS105: 9713 | BT105: 10036 | CN105: =BF105 -> 7522 | CO105: =BJ105 -> 6947 | CP105: =BN105 -> 6731 | CQ105: =BR105 -> 7550 | CS105: Cost of Debt
B106: Ttl Liabilities | BF106: =SUM(BF98:BF105) -> 37533 | BG106: =SUM(BG98:BG105) -> 36562 | BH106: =SUM(BH98:BH105) -> 35950 | BI106: =SUM(BI98:BI105) -> 34396 | BJ106: =SUM(BJ98:BJ105) -> 34387 | BK106: =SUM(BK98:BK105) -> 33424 | BL106: =SUM(BL98:BL105) -> 33457 | BM106: =SUM(BM98:BM105) -> 34328 | ... BT106: =SUM(BT98:BT105) -> 57453 | CN106: =BF106 -> 37533 | CO106: =BJ106 -> 34387 | CP106: =BN106 -> 33513 | CQ106: =BR106 -> 33942 | CS106: Cost of Debt | CV106: 0.055
B107: Ttl SE | BF107: 36905 | BG107: 3723 | BH107: 37404 | BI107: 37694 | BJ107: 38827 | BK107: 39043 | BL107: 39560 | BM107: 40028 | BN107: 47901 | BO107: 49064 | BP107: 50829 | BQ107: 51264 | BR107: 52771 | BS107: 52701 | BT107: 51762 | CN107: =BF107 -> 36905 | CO107: =BJ107 -> 38827 | CP107: =BN107 -> 47901 | CQ107: =BR107 -> 52771 | CS107: Tax Rate | CV107: 0.23
B108: Ttl L + SE | BF108: =BF106+BF107 -> 74438 | BG108: =BG106+BG107 -> 40285 | BH108: =BH106+BH107 -> 73354 | BI108: =BI106+BI107 -> 72090 | BJ108: =BJ106+BJ107 -> 73214 | BK108: =BK106+BK107 -> 72467 | BL108: =BL106+BL107 -> 73017 | BM108: =BM106+BM107 -> 74356 | ... BT108: =BT106+BT107 -> 109215 | CN108: =BF108 -> 74438 | CO108: =BJ108 -> 73214 | CP108: =BN108 -> 81414 | CQ108: =BR108 -> 86713 | CS108: After Tax Cost of Debt | CV108: =CV106*(1-CV107) -> 0.04235
...

Sheet Notes | Quant Analysis
CB1: 0
H2: Employee Scope: | AE2: General Notes/Observations
I32: Notes: | J32: [X]
J33: [Y]
J34: [Z]
H36: Institutional Ownership Snapshot Q2'25
I66: Notes: | J66: [X]
J67: [Y]
J68: [Z]
AE69: Financial Stmts. Notes/Observations
H70: Revenue Breakdown by Segment | AE70: Revenues:
I102: Notes: | J102: [X]
J103: [Y]
J104: [Z]
H106: Revenue Breakdown of Diagnostics Segment | AE106: Earnings Scope:
I138: Notes: | J138: [X]
J139: [Y]
J140: [Z]
H142: Revenue Breakdown of Med-Devices Segment | AE142: Balance Sheet Scope:
I174: Notes: | J174: [X]
J175: [Y]
J176: [Z]
H178: Q/q Total Revenues, Net Income, FCF | AE178: [Equity Preformance Compared to Peers]
A192: 1256 Trading Days? (From: 9/12/2020 - 9/12/2025)
A193: Close | B193: High | C193: Low | D193: Open | E193: Volume | F193: UTC Date | G193: Change
A194: 133.73 | B194: 134.96 | C194: 131.4 | D194: 131.82 | E194: 5675032 | F194: Fri, 12 Sep 2025 00:00:00 GMT | G194: =A194/D194-1 -> 0.014489455
A195: 132.65 | B195: 132.68 | C195: 129.3975 | D195: 129.69 | E195: 5500357 | F195: Thu, 11 Sep 2025 00:00:00 GMT | G195: =A195/D195-1 -> 0.022823656
A196: 129.36 | B196: 131.85 | C196: 127.445 | D196: 131.85 | E196: 7363965 | F196: Wed, 10 Sep 2025 00:00:00 GMT | G196: =A196/D196-1 -> -0.018885097
A197: 131.95 | B197: 133.1679 | C197: 131.645 | D197: 132.3 | E197: 4635380 | F197: Tue, 09 Sep 2025 00:00:00 GMT | G197: =A197/D197-1 -> -0.0026455026
A198: 132.2 | B198: 133.09 | C198: 131.61 | D198: 132.26 | E198: 5014159 | F198: Mon, 08 Sep 2025 00:00:00 GMT | G198: =A198/D198-1 -> -0.0004536519
A199: 132.94 | B199: 134.325 | C199: 132.445 | D199: 132.515 | E199: 3225545 | F199: Fri, 05 Sep 2025 00:00:00 GMT | G199: =A199/D199-1 -> 0.0032071841
A200: 132.81 | B200: 133.84 | C200: 131.7 | D200: 132.18 | E200: 5063771 | F200: Thu, 04 Sep 2025 00:00:00 GMT | G200: =A200/D200-1 -> 0.0047662279
A201: 132.18 | B201: 132.19 | C201: 130.21 | D201: 131.15 | E201: 4753690 | F201: Wed, 03 Sep 2025 00:00:00 GMT | G201: =A201/D201-1 -> 0.0078536027
A202: 131.46 | B202: 133.395 | C202: 130.84 | D202: 132.685 | E202: 5696208 | F202: Tue, 02 Sep 2025 00:00:00 GMT | G202: =A202/D202-1 -> -0.0092323925
A203: 132.66 | B203: 132.845 | C203: 131.17 | D203: 132.015 | E203: 4426895 | F203: Fri, 29 Aug 2025 00:00:00 GMT | G203: =A203/D203-1 -> 0.0048858084
A204: 131.37 | B204: 131.635 | C204: 130.14 | D204: 130.92 | E204: 4668414 | F204: Thu, 28 Aug 2025 00:00:00 GMT | G204: =A204/D204-1 -> 0.0034372136
A205: 131.46 | B205: 131.75 | C205: 130.5616 | D205: 131.47 | E205: 4758097 | F205: Wed, 27 Aug 2025 00:00:00 GMT | G205: =A205/D205-1 -> -7.606298e-05
A206: 131.59 | B206: 132.35 | C206: 131.38 | D206: 131.86 | E206: 6076213 | F206: Tue, 26 Aug 2025 00:00:00 GMT | G206: =A206/D206-1 -> -0.0020476263
A207: 131.87 | B207: 132.96 | C207: 131.49 | D207: 132.72 | E207: 4695123 | F207: Mon, 25 Aug 2025 00:00:00 GMT | G207: =A207/D207-1 -> -0.0064044605 | I207: Notes: | J207: [X]
A208: 132.59 | B208: 133.62 | C208: 131.34 | D208: 132.77 | E208: 4130123 | F208: Fri, 22 Aug 2025 00:00:00 GMT | G208: =A208/D208-1 -> -0.001355728 | J208: [Y]
A209: 132 | B209: 133.2 | C209: 131.75 | D209: 132.12 | E209: 3980063 | F209: Thu, 21 Aug 2025 00:00:00 GMT | G209: =A209/D209-1 -> -0.00090826521 | J209: [Z]
A210: 132.44 | B210: 133.81 | C210: 131.72 | D210: 132.05 | E210: 3615370 | F210: Wed, 20 Aug 2025 00:00:00 GMT | G210: =A210/D210-1 -> 0.0029534267
A211: 131.25 | B211: 131.72 | C211: 128.68 | D211: 129.92 | E211: 4669839 | F211: Tue, 19 Aug 2025 00:00:00 GMT | G211: =A211/D211-1 -> 0.010237069 | H211: Y/y Total Revenues, Net Income, FCF
A212: 130.27 | B212: 132.3 | C212: 130.16 | D212: 131.63 | E212: 3831433 | F212: Mon, 18 Aug 2025 00:00:00 GMT | G212: =A212/D212-1 -> -0.010331991
A213: 131.75 | B213: 132.35 | C213: 129.665 | D213: 129.92 | E213: 6784760 | F213: Fri, 15 Aug 2025 00:00:00 GMT | G213: =A213/D213-1 -> 0.014085591
A214: 129.28 | B214: 130.14 | C214: 128.53 | D214: 129.105 | E214: 9688357 | F214: Thu, 14 Aug 2025 00:00:00 GMT | G214: =A214/D214-1 -> 0.0013554858
A215: 129.4 | B215: 131.65 | C215: 128.33 | D215: 131.12 | E215: 6723933 | F215: Wed, 13 Aug 2025 00:00:00 GMT | G215: =A215/D215-1 -> -0.013117755
A216: 131.02 | B216: 131.89 | C216: 129.62 | D216: 131.74 | E216: 5657521 | F216: Tue, 12 Aug 2025 00:00:00 GMT | G216: =A216/D216-1 -> -0.0054653105
A217: 131.36 | B217: 134.35 | C217: 130.55 | D217: 134.08 | E217: 7125728 | F217: Mon, 11 Aug 2025 00:00:00 GMT | G217: =A217/D217-1 -> -0.020286396
A218: 134.28 | B218: 134.71 | C218: 131.75 | D218: 131.8 | E218: 4985614 | F218: Fri, 08 Aug 2025 00:00:00 GMT | G218: =A218/D218-1 -> 0.018816388
A219: 132.06 | B219: 132.5 | C219: 130.73 | D219: 131.16 | E219: 4690729 | F219: Thu, 07 Aug 2025 00:00:00 GMT | G219: =A219/D219-1 -> 0.0068618481
A220: 130.93 | B220: 131.72 | C220: 129.81 | D220: 130.08 | E220: 5170125 | F220: Wed, 06 Aug 2025 00:00:00 GMT | G220: =A220/D220-1 -> 0.0065344403
A221: 130.69 | B221: 131.48 | C221: 129.25 | D221: 129.91 | E221: 5355471 | F221: Tue, 05 Aug 2025 00:00:00 GMT | G221: =A221/D221-1 -> 0.0060041567
A222: 129.93 | B222: 130.13 | C222: 127.45 | D222: 127.45 | E222: 5671459 | F222: Mon, 04 Aug 2025 00:00:00 GMT | G222: =A222/D222-1 -> 0.019458611
A223: 127.29 | B223: 127.77 | C223: 125.47 | D223: 125.47 | E223: 5453261 | F223: Fri, 01 Aug 2025 00:00:00 GMT | G223: =A223/D223-1 -> 0.014505459
... A239: 133.6 | B239: 135.05 | C239: 133.01 | D239: 133.73 | E239: 4849664 | F239: Thu, 10 Jul 2025 00:00:00 GMT | G239: =A239/D239-1 -> -0.00097210798
A240: 133.22 | B240: 133.77 | C240: 131.47 | D240: 133.47 | E240: 4613236 | F240: Wed, 09 Jul 2025 00:00:00 GMT | G240: =A240/D240-1 -> -0.0018730801 | I240: Notes: | J240: [X]
A241: 133.36 | B241: 134.73 | C241: 132.85 | D241: 133.24 | E241: 4779876 | F241: Tue, 08 Jul 2025 00:00:00 GMT | G241: =A241/D241-1 -> 0.00090063044 | J241: [Y]
A242: 133.7 | B242: 134.91 | C242: 132.85 | D242: 134.51 | E242: 8919815 | F242: Mon, 07 Jul 2025 00:00:00 GMT | G242: =A242/D242-1 -> -0.0060218571 | J242: [Z]
A243: 134.44 | B243: 135.2443 | C243: 133.2 | D243: 134.67 | E243: 3114330 | F243: Thu, 03 Jul 2025 00:00:00 GMT | G243: =A243/D243-1 -> -0.0017078785
A244: 134.11 | B244: 136.34 | C244: 133.8406 | D244: 135.27 | E244: 4316253 | F244: Wed, 02 Jul 2025 00:00:00 GMT | G244: =A244/D244-1 -> -0.0085754417
A245: 136.26 | B245: 137.0836 | C245: 134.81 | D245: 135.54 | E245: 5260641 | F245: Tue, 01 Jul 2025 00:00:00 GMT | G245: =A245/D245-1 -> 0.005312085
A246: 136.01 | B246: 136.26 | C246: 134 | D246: 134 | E246: 5680163 | F246: Mon, 30 Jun 2025 00:00:00 GMT | G246: =A246/D246-1 -> 0.015
A247: 134.38 | B247: 134.91 | C247: 132.88 | D247: 133.29 | E247: 9513538 | F247: Fri, 27 Jun 2025 00:00:00 GMT | G247: =A247/D247-1 -> 0.0081776577
A248: 133.67 | B248: 137.54 | C248: 132.71 | D248: 137.325 | E248: 9452900 | F248: Thu, 26 Jun 2025 00:00:00 GMT | G248: =A248/D248-1 -> -0.026615693
A249: 137.4 | B249: 138.84 | C249: 136.64 | D249: 137.87 | E249: 5507492 | F249: Wed, 25 Jun 2025 00:00:00 GMT | G249: =A249/D249-1 -> -0.0034090085
A250: 138.08 | B250: 139.06 | C250: 132.38 | D250: 133.32 | E250: 9894809 | F250: Tue, 24 Jun 2025 00:00:00 GMT | G250: =A250/D250-1 -> 0.03570357
A251: 133.26 | B251: 133.47 | C251: 132.11 | D251: 133.065 | E251: 4825049 | F251: Mon, 23 Jun 2025 00:00:00 GMT | G251: =A251/D251-1 -> 0.0014654492
A252: 132.99 | B252: 133.68 | C252: 131.99 | D252: 133.66 | E252: 11278450 | F252: Fri, 20 Jun 2025 00:00:00 GMT | G252: =A252/D252-1 -> -0.0050127188
A253: 132.41 | B253: 133.37 | C253: 131.6 | D253: 132.95 | E253: 4950836 | F253: Wed, 18 Jun 2025 00:00:00 GMT | G253: =A253/D253-1 -> -0.0040616773
A254: 132.28 | B254: 134.01 | C254: 132.15 | D254: 133.695 | E254: 5010926 | F254: Tue, 17 Jun 2025 00:00:00 GMT | G254: =A254/D254-1 -> -0.010583791
... A272: 133.05 | B272: 136.17 | C272: 133.02 | D272: 135.1 | E272: 7209230 | F272: Wed, 21 May 2025 00:00:00 GMT | G272: =A272/D272-1 -> -0.015173945
A273: 135.2 | B273: 135.83 | C273: 134.541 | D273: 135 | E273: 6455398 | F273: Tue, 20 May 2025 00:00:00 GMT | G273: =A273/D273-1 -> 0.0014814815 | J273: Min | K273: =MIN(G194:G1449) -> -0.051741218
A274: 135.55 | B274: 135.69 | C274: 134.53 | D274: 135 | E274: 8012873 | F274: Mon, 19 May 2025 00:00:00 GMT | G274: =A274/D274-1 -> 0.0040740741 | J274: Max | K274: =MAX(G194:G1449) -> 0.046359645
A275: 134.8 | B275: 135.29 | C275: 132.77 | D275: 133.145 | E275: 7129033 | F275: Fri, 16 May 2025 00:00:00 GMT | G275: =A275/D275-1 -> 0.012430057 | J275: Mean μ | K275: =AVERAGE(G194:G1449) -> 0.00035661813
A276: 133.35 | B276: 133.425 | C276: 128.85 | D276: 128.85 | E276: 8406704 | F276: Thu, 15 May 2025 00:00:00 GMT | G276: =A276/D276-1 -> 0.034924331 | J276: Median | K276: =MEDIAN(G194:G1449) -> 0.00018121908
A277: 128.56 | B277: 130.14 | C277: 128.19 | D277: 129.3 | E277: 5267034 | F277: Wed, 14 May 2025 00:00:00 GMT | G277: =A277/D277-1 -> -0.0057231245 | J277: SD σ | K277: =_xlfn.STDEV.P(G194:G1449) -> 0.01177673
A278: 129.05 | B278: 131.75 | C278: 128.92 | D278: 131.75 | E278: 6344898 | F278: Tue, 13 May 2025 00:00:00 GMT | G278: =A278/D278-1 -> -0.020493359 | J278: 3σ 1-Day Δ: ± | K278: =3*K277 -> 0.035330191 | M278: <- Sharpe Ratio (Risk Adjusted Return)
A279: 131.99 | B279: 133.66 | C279: 130.1017 | D279: 131.79 | E279: 5958544 | F279: Mon, 12 May 2025 00:00:00 GMT | G279: =A279/D279-1 -> 0.0015175658 | J279: β (1-year avg.) | K279: 0.71 | M279: <- Sortino Ratio (Downside Risk Adjusted Return)
A280: 133.24 | B280: 134.97 | C280: 133.19 | D280: 133.975 | E280: 4976167 | F280: Fri, 09 May 2025 00:00:00 GMT | G280: =A280/D280-1 -> -0.0054860982
A281: 134 | B281: 135.22 | C281: 133.08 | D281: 133.265 | E281: 5994453 | F281: Thu, 08 May 2025 00:00:00 GMT | G281: =A281/D281-1 -> 0.0055153266 | I281: n = | J281: 1256
A282: 133.95 | B282: 134.43 | C282: 132.4312 | D282: 133.5 | E282: 4925233 | F282: Wed, 07 May 2025 00:00:00 GMT | G282: =A282/D282-1 -> 0.0033707865 | I282: Histogram Data | L282: Distribution Overlay | P282: SD Lines
A283: 133.06 | B283: 133.6 | C283: 130.7 | D283: 131.95 | E283: 6290467 | F283: Tue, 06 May 2025 00:00:00 GMT | G283: =A283/D283-1 -> 0.0084122774 | I283: Bin | J283: Frequency | L283: (X) 1-Day Δ | M283: (Y) Pop. Density | P283: X | Q283: Y
A284: 132.6 | B284: 133.06 | C284: 131.45 | D284: 132.885 | E284: 5752256 | F284: Mon, 05 May 2025 00:00:00 GMT | G284: =A284/D284-1 -> -0.0021447116 | I284: -0.04 | J284: 1 | L284: -0.04 | M284: =_xlfn.NORM.DIST(L284,$K$275,$K$277,FALSE) -> 0.095481521 | O284: Mean | P284: =K275 -> 0.00035661813 | Q284: 0
A285: 132.82 | B285: 136.8 | C285: 131.33 | D285: 131.91 | E285: 9801692 | F285: Fri, 02 May 2025 00:00:00 GMT | G285: =A285/D285-1 -> 0.006898643 | I285: -0.039 | J285: 1 | L285: -0.039 | M285: =_xlfn.NORM.DIST(L285,$K$275,$K$277,FALSE) -> 0.12726978 | P285: =K275 -> 0.00035661813 | Q285: 34
A286: 130.88 | B286: 131.63 | C286: 128 | D286: 129.5 | E286: 6769116 | F286: Thu, 01 May 2025 00:00:00 GMT | G286: =A286/D286-1 -> 0.010656371 | I286: -0.038 | J286: 1 | L286: -0.038 | M286: =_xlfn.NORM.DIST(L286,$K$275,$K$277,FALSE) -> 0.1684224 | O286: -3σ | P286: =($K$277*-3)+$K$275 -> -0.034973573 | Q286: 0
A287: 130.75 | B287: 131.266 | C287: 128.68 | D287: 130.92 | E287: 8510507 | F287: Wed, 30 Apr 2025 00:00:00 GMT | G287: =A287/D287-1 -> -0.0012985029 | I287: -0.037 | J287: 0 | L287: -0.037 | M287: =_xlfn.NORM.DIST(L287,$K$275,$K$277,FALSE) -> 0.22128046 | P287: =($K$277*-3)+$K$275 -> -0.034973573 | Q287: 1
A288: 130.5 | B288: 131.27 | C288: 128.8 | D288: 128.89 | E288: 4315327 | F288: Tue, 29 Apr 2025 00:00:00 GMT | G288: =A288/D288-1 -> 0.012491272 | I288: -0.036 | J288: 0 | L288: -0.036 | M288: =_xlfn.NORM.DIST(L288,$K$275,$K$277,FALSE) -> 0.28863893 | O288: -2σ | P288: =($K$277*-2)+$K$275 -> -0.023196842 | Q288: 0
A289: 129.53 | B289: 130.12 | C289: 128.52 | D289: 129.33 | E289: 3843266 | F289: Mon, 28 Apr 2025 00:00:00 GMT | G289: =A289/D289-1 -> 0.0015464316 | I289: -0.035 | J289: 0 | L289: -0.035 | M289: =_xlfn.NORM.DIST(L289,$K$275,$K$277,FALSE) -> 0.37379661 | P289: =($K$277*-2)+$K$275 -> -0.023196842 | Q289: 5
A290: 128.85 | B290: 129.53 | C290: 127.235 | D290: 129.27 | E290: 4849389 | F290: Fri, 25 Apr 2025 00:00:00 GMT | G290: =A290/D290-1 -> -0.0032490137 | I290: -0.034 | J290: 3 | L290: -0.034 | M290: =_xlfn.NORM.DIST(L290,$K$275,$K$277,FALSE) -> 0.48060076 | O290: -1σ | P290: =($K$277*-1)+$K$275 -> -0.011420112 | Q290: 0
A291: 129.38 | B291: 130.2 | C291: 128.03 | D291: 130.02 | E291: 6595544 | F291: Thu, 24 Apr 2025 00:00:00 GMT | G291: =A291/D291-1 -> -0.0049223196 | I291: -0.033 | J291: 0 | L291: -0.033 | M291: =_xlfn.NORM.DIST(L291,$K$275,$K$277,FALSE) -> 0.61348248 | P291: =($K$277*-1)+$K$275 -> -0.011420112 | Q291: 21
A292: 129.84 | B292: 132.89 | C292: 127.13 | D292: 132.21 | E292: 8777184 | F292: Wed, 23 Apr 2025 00:00:00 GMT | G292: =A292/D292-1 -> -0.017926027 | I292: -0.032 | J292: 1 | L292: -0.032 | M292: =_xlfn.NORM.DIST(L292,$K$275,$K$277,FALSE) -> 0.7774787 | O292: 1σ | P292: =($K$277*1)+$K$275 -> 0.012133348 | Q292: 0
A293: 131.73 | B293: 132.03 | C293: 129.93 | D293: 129.93 | E293: 5837131 | F293: Tue, 22 Apr 2025 00:00:00 GMT | G293: =A293/D293-1 -> 0.013853613 | I293: -0.031 | J293: 0 | L293: -0.031 | M293: =_xlfn.NORM.DIST(L293,$K$275,$K$277,FALSE) -> 0.97823561 | P293: =($K$277*1)+$K$275 -> 0.012133348 | Q293: 21
A294: 129.89 | B294: 131.96 | C294: 128.5105 | D294: 130.97 | E294: 6046937 | F294: Mon, 21 Apr 2025 00:00:00 GMT | G294: =A294/D294-1 -> -0.0082461632 | I294: -0.03 | J294: 1 | L294: -0.03 | M294: =_xlfn.NORM.DIST(L294,$K$275,$K$277,FALSE) -> 1.2219883 | O294: 2σ | P294: =($K$277*2)+$K$275 -> 0.023910079 | Q294: 0
A295: 130.98 | B295: 132.71 | C295: 129.66 | D295: 130.375 | E295: 10474476 | F295: Thu, 17 Apr 2025 00:00:00 GMT | G295: =A295/D295-1 -> 0.0046404602 | I295: -0.029 | J295: 2 | L295: -0.029 | M295: =_xlfn.NORM.DIST(L295,$K$275,$K$277,FALSE) -> 1.5155117 | P295: =($K$277*2)+$K$275 -> 0.023910079 | Q295: 5
A296: 129.7 | B296: 134.16 | C296: 129.01 | D296: 129.695 | E296: 13483166 | F296: Wed, 16 Apr 2025 00:00:00 GMT | G296: =A296/D296-1 -> 3.8551987e-05 | I296: -0.028 | J296: 1 | L296: -0.028 | M296: =_xlfn.NORM.DIST(L296,$K$275,$K$277,FALSE) -> 1.8660365 | O296: 3σ | P296: =($K$277*3)+$K$275 -> 0.035686809 | Q296: 0
A297: 126.22 | B297: 128.49 | C297: 125.595 | D297: 127.62 | E297: 8639428 | F297: Tue, 15 Apr 2025 00:00:00 GMT | G297: =A297/D297-1 -> -0.010970067 | I297: -0.027 | J297: 5 | L297: -0.027 | M297: =_xlfn.NORM.DIST(L297,$K$275,$K$277,FALSE) -> 2.2811277 | P297: =($K$277*3)+$K$275 -> 0.035686809 | Q297: 1
A298: 127.37 | B298: 127.90741 | C298: 126.25516 | D298: 126.41443 | E298: 7021264.8 | F298: Mon, 14 Apr 2025 00:00:00 GMT | G298: =A298/D298-1 -> 0.0075590551 | I298: -0.026 | J298: 3 | L298: -0.026 | M298: =_xlfn.NORM.DIST(L298,$K$275,$K$277,FALSE) -> 2.7685202
A299: 126.29498 | B299: 127.92742 | C299: 123.46807 | D299: 125.47378 | E299: 7391098 | F299: Fri, 11 Apr 2025 00:00:00 GMT | G299: =A299/D299-1 -> 0.0065447622 | I299: -0.025 | J299: 4 | L299: -0.025 | M299: =_xlfn.NORM.DIST(L299,$K$275,$K$277,FALSE) -> 3.3359108
A300: 123.92595 | B300: 126.23526 | C300: 121.45739 | D300: 125.41904 | E300: 11140721 | F300: Thu, 10 Apr 2025 00:00:00 GMT | G300: =A300/D300-1 -> -0.011904762 | I300: -0.024 | J300: 3 | L300: -0.024 | M300: =_xlfn.NORM.DIST(L300,$K$275,$K$277,FALSE) -> 3.9907064
...

Sheet Management

Sheet M&A
B2: Abbott M&A Acquirees | G2: Announced | H2: Price (in $M) | I2: Description | W2: Abbott Subsidiaries | AD2: Description
B3: Bigfoot Biomedical | H3: – | W3: Domestic Subsidiaries: | AB3: Incorporated:
B4: Cardiovascular Systems | H4: 890
B5: Walk Vascular | H5: – | W5: Abbott Biologicals, LLC | AB5: Delaware
B6: Cephea Valve Technologies | H6: – | W6: Abbott Cardiovascular Inc. | AB6: Delaware
B7: St Jude Medical | H7: 25000 | W7: Abbott Cardiovascular Systems Inc. | AB7: California
B8: Kalila Medical | H8: – | W8: Abbott Delaware LLC | AB8: Delaware
B9: Alere | H9: 5300 | W9: Abbott Diabetes Care Inc. | AB9: Delaware
B10: Tendyne Holdings | H10: 250 | W10: Abbott Diabetes Care Sales Corporation | AB10: Delaware
B11: Veropharm | H11: 305 | W11: Abbott Diagnostics Scarborough, Inc. | AB11: Delaware
B12: Topera | H12: 250 | W12: Abbott Equity Investments LLC | AB12: Delaware
B13: Cfr Pharmaceuticals | H13: 2900 | W13: Abbott Finance LLC | AB13: Delaware
B14: Unelab | H14: – | W14: Abbott Global LLC | AB14: Delaware
B15: Idev Technologies | H15: 310 | W15: Abbott Health Products, LLC | AB15: Delaware
B16: Optimedica | H16: 400 | W16: Abbott Informatics Corporation | AB16: Florida
B17: Piramal Healthcare Solutions | H17: 3700 | W17: Abbott International LLC | AB17: Delaware
B18: Facet Biotech | H18: 450 | W18: Abbott Laboratories Inc. | AB18: Delaware
B19: Pangenetics | H19: 190 | W19: Abbott Laboratories International LLC | AB19: Illinois
B20: Solvay Pharmaceuticals | H20: 6600 | W20: Abbott Laboratories Pacific Ltd. | AB20: Illinois
B21: Evalve | H21: 410 | W21: Abbott Laboratories Residential Development Fund, Inc. | AB21: Illinois
B22: Visiogen | H22: 400 | W22: Abbott Laboratories Services LLC | AB22: Illinois
B23: Ibis Biosciences | H23: – | W23: Abbott Management LLC | AB23: Delaware
B24: Nova Science | H24: 10 | W24: Abbott Molecular Inc. | AB24: Delaware
B25: Kos Pharmaceuticals | H25: 3700 | W25: Abbott Nutrition Manufacturing Inc. | AB25: Delaware
B26: Spine Next | H26: 81 | W26: Abbott Point of Care Inc. | AB26: Delaware
B27: Experimental And Applied Sciences | H27: 320 | W27: Abbott Procurement LLC | AB27: Delaware
B28: Therasense | H28: 1200 | W28: Abbott Products Operations, LLC | AB28: Delaware
B29: I-Stat Corp | H29: 394 | W29: Abbott Rapid Diagnostics Informatics, Inc. | AB29: Virginia
B30: Integrated Vascular Systems | H30: 65 | W30: Abbott Rapid Dx North America, LLC | AB30: Delaware
B31: Zoneperfect Nutrition | H31: 160 | W31: Abbott Resources Inc. | AB31: Delaware
B32: Woodside Biomedical | H32: – | W32: Abbott Resources International Inc. | AB32: Delaware
B33: Spinal Concepts | H33: 166 | W33: Abbott Universal LLC | AB33: Delaware
B34: Vysis | H34: 362 | W34: Abbott Vascular Inc. | AB34: Delaware
B35: Abbott India | H35: 6900 | W35: Abbott Vascular Solutions Inc. | AB35: Indiana
B36: Glaxo Wellcome – Anesthesia Business | H36: 217 | W36: Abbott Ventures Inc. | AB36: Delaware
B37: Perclose Inc | H37: 680 | W37: Advanced Neuromodulation Systems, Inc. | AB37: Texas
B38: Alza Corp | H38: – | W38: AGA Medical Corporation | AB38: Minnesota
B39: International Murex Technologies | H39: 234 | W39: AGA Medical Holdings, Inc. | AB39: Delaware
B40: Sanofi – Parenteral Products Businesses | H40: 200 | W40: Alere Connect, LLC | AB40: Delaware
B41: Medisense Inc | H41: 876 | W41: Alere Holdco, Inc. | AB41: Delaware
W42: Alere Home Monitoring, Inc. | AB42: Delaware
W43: Alere Inc. | AB43: Delaware
W44: Alere International Holding Corp. | AB44: Delaware
W45: Alere Phoenix ACQ, Inc. | AB45: Delaware
W46: Alere San Diego, Inc. | AB46: Delaware
W47: Alere Toxicology Services, Inc. | AB47: Louisiana
W48: Alere Toxicology, Inc. | AB48: Florida
W49: Alere US Holdings, LLC | AB49: Delaware
W50: Amedica Biotech, Inc. | AB50: California
W51: Ameditech Inc. | AB51: California
W52: American Medical Supplies, Inc. | AB52: Florida
W53: AML Medical, LLC | AB53: Delaware
... W577: Abbott Trading Company, Inc. | AB577: Virgin Islands (U.S.)

Sheet Med-Devices
A2: Vascular
B3: Abbott expanded peripheral vascular offerings with acquisition of Walk Vascular in 2021
C4: Peripheral Thrombectomy Devices
C5: Jeti–6 Fr
D6: Mode of Operation: Internal saline jet just within the catheter tip breaks up thrombus and soft emboli while removing the thrombus through aspiration
D7: FDA Indicated Use: For all peripheral venous and arterial vasculature
C8: Jeti–8 Fr
D9: Mode of Operation: Internal saline jet just within the catheter tip breaks up thrombus and soft emboli while removing the thrombus through aspiration
D10: FDA Indicated Use: For all peripheral venous and arterial vasculature
C11: Jeti line competes directly with Penumbra's peripheral Indigo Lightning & Bolt CAVT Systems
D12: Jeti uses a "hydrodynamic" approach. It shoots a high-speed jet of saline at the tip to break up the clot before sucking it in (maceration + aspiration)
E13: This is designed to prevent clogging and reduce blood loss by breaking the clot into smaller pieces first
A18: CGMs / Diabetes Care
B19: Abbott’s diabetes franchise is a dominant growth driver in The Company's overall medical devices portfolio
B20: CGM Monitor - FreeStyle Libre
C21: FreeStyle Libre 3 System
D22: Abbott's flagship CGM product - Disposable sensor device (Libre 3 / Libre 3 Plus) and reader for viewing sensor outputs … Requires perscription from healthcare provider
D23: The Libre 3 or Libre 3 Plus sensor streams real-time glucose data every minute directly to a reader device or dedicated smartphone app via Bluetooth, with no need to scan the sensor manually
E24: Intended patients are all people with Type 1, Type 2 (on insulin), or gestational diabetes
E25: Libre 3 Plus has a 15-day wear time and is approved for children as young as 2 years old … Standard Libre 3 sensor has 14-day wear time and is approved for children 4 and older
E26: Most advanced censor technology … Includes features necessary for intensive diabetes management … alarms, data sharing with healthcare providers, compatibility with insulin pumps
F27: World's smallest and thinnest CGM sensor (size of two stacked pennies)
F28: Huge development for diabetes patients ... eliminates the need for frequent patient fingerstick pricks which have traditionally been required for blood glucose monitoring (BGM)
C29: FreeStyle Libre 2 System
D30: Abbott's Budget CGM product - Disposable sensor device (Libre 2 / Libre 2 Plus) and reader for viewing sensor outputs … Requires perscription from healthcare provider
D31: The Libre 2 or Libre 2 Plus sensor requires manual scanning ("Flash monitoring") meaning the user must actively hold a reader or smartphone near the sensor on their arm to get a current glucose reading
E32: The sensor only stores 8 hours of data. If the user does not scan at least every eight hours, there will be gaps (broken lines) in the historical glucose graph
E33: Intended patients are all people with Type 1, Type 2 (on insulin), or gestational diabetes
E34: Libre 2 Plus has a 15-day wear time and is approved for children as young as 2 years old … Standard Libre 2 sensor has 14-day wear time and is approved for children 4 and older
B35: CGM Monitor - Libre Rio
D36: Abbott's over-the-counter (OTC) continuous glucose monitoring (CGM) system - Disposable sensor device and reader for viewing sensor outputs
D37: The Libre Rio sensor streams real-time glucose data every minute directly to a reader device or dedicated smartphone app via Bluetooth, with no need to scan the sensor manually
E38: Intended for patients with type 2 diabetes who do not use insulin and manage their condition primarily through diet and lifestyle
E39: Libre Rio has a 14-day wear time and is approved for adults 18 and older
E40: Based on the FreeStyle Libre technology … Focuses on providing glucose data and personalized insights for lifestyle management … does not include certain clinical features
C41: CGM Monitor - Libre Lingo
D42: Abbott's over-the-counter (OTC) continuous glucose monitoring (CGM) system - Disposable sensor device and reader for viewing sensor outputs
D43: The Libre Lingo sensor streams real-time glucose data every minute directly to a reader device or dedicated smartphone app via Bluetooth, with no need to scan the sensor manually
E44: Intended for general consumers without diabetes (same market as DXCM's Stelo) for general health and wellness purposes
E45: Libre Lingo has a 14-day wear time and is approved for adults 18 and older
E46: Based on the FreeStyle Libre technology … Focuses on providing health oriented consumers insights into glocuse levels … data not intended / approved for medical action without consulting healthcare providers
B47: Management's strategy for CGM offerings rely on marketing The Company's proven FreeStyle Libre sensor technology across different consumer markets by tailoring the software experience and regulatory clearance for each user base
C48: Each device has a different intended target audience … relies on the same base technology, but each system uses its own dedicated app, preventing users from simply using the "wrong" software for their condition
A53: Heart Failure
A71: Structural Heart
A88: Electrophysiology
A107: Neuromodulation
A131: Rhythm Management

Sheet Diagnostics

Sheet Table Formatting
B2: [Bold Title] | G2: [Bold Title]
B3: Line Titles | G3: <-- General
B4: Line Titles | G4: <-- Info
B5: Line Titles | G5: <-- General
B6: Line Titles | G6: <-- Info
B7: Line Titles | G7: <-- General
B8: Line Titles | G8: <-- Info
