Workbook

Sheet Main
A1: Master | AP1: 1
B2: BSX
B3: Price | C3: 43.79 | D3: 46236
B4: SO | C4: 1470.2 | D4: Q2'26
B5: MC | C5: =C3*C4 -> 64380.058
B6: Cash | C6: 1453 | D6: Q2'26
B7: Debt | C7: 10988 | D7: Q2'26
B8: EV | C8: =C5-C6+C7 -> 73915.058 | O8: Resources:
O9: SEC filings | R9: https://www.sec.gov/edgar/browse/?CIK=885725&owner=exclude
B10: Boston Scientific Corp. (BSX) | O10: Boston Scientific Homepage | R10: https://www.bostonscientific.com/en-US/home.html
P11: BSX IR Page | S11: https://investors.bostonscientific.com/
B12: Founder(s): John Abele, Peter Nicholas | G12: Registered Exchange: NYSE | O12: Earnings Calls | R12: https://seekingalpha.com/symbol/BSX/earnings/transcripts
B13: Founded: 1979 | G13: Address: 300 Boston Scientific Way Marlborough, MA 01752-1234 U.S. | O13: Godel Terminal | R13: https://app.godelterminal.com/
B14: Headquarted: Marlborough, MA | G14: Investor Relations Contact: | O14: FDA Med Device Reporting's | R14: https://www.fda.gov/medical-devices
B15: Current CEO: Michael F. Mahoney (since 2012) | G15: Investors Relation Department | O15: U.S. Patent Office Search | R15: https://ppubs.uspto.gov/pubThe Companybapp/static/pages/ppubsbasic.html
B16: Employees: 53,000 (Q4'24) | G16: Phone: | J16: Email: | K16: BSXInvestorRelations@bsci.com | P16: BSX IP Catalog | S16: https://www.bostonscientific.com/content/dam/bostonscientific/corporate/patent-marking-spreadsheet-6feb-2025.pdf
B17: Sector: Healthcare | O17: Thrombecotomy News | R17: https://evtoday.com/
B18: Industry: Medical Devices | O18: MedTech News | R18: https://www.medtechdive.com/
B19: IPO: May 19, 1992 -- $1.6B valuation | O19: MacroTrends | R19: https://www.macrotrends.net/stocks/charts/BSX/boston-scientific/income-statement?freq=Q
B20: Fiscal Year: [January - December] | O20: ROIC, WACC | R20: https://www.gurufocus.com/term/wacc/BSX
A22: Overview:
B23: Boston Scientific Corporation is a global developer, manufacturer and marketer of medical devices that are used in a broad range of interventional medical specialties for both domestic and international markets
C24: The Company operates through three segments:
D25: MedSurg: | F25: Minimally invasive devices for endoscopy, urology, and pelvic health
D26: Rhythm and Neuro: | F26: Solutions for cardiac rhythm management (CRM), electrophysiology (EP), and neuromodulation
D27: Cardiovascular: | F27: Devices for interventional cardiology, peripheral interventions, and structural heart
B28: The Company states that they operate pursuant to five strategic imperatives
C29: Strengthen Category Leadership, Expand into High Growth Adjacencies, Drive Global Expansion, Fund the Journey to Fuel Growth and Develop Key Capabilities
B30: Management expects to continue to invest in our core businesses and pursue opportunities to diversify and further expand our presence in strategic, high-growth adjacencies and new global markets, including growth within the countries we define as emerging markets
C31: Maintaining and expanding our international presence is an important component of our long-term growth strategy
C32: Through our international presence, we seek to increase net sales and market share, leverage our relationships with leading physicians and their clinical research programs, accelerate the time to bring new products to market and gain access to worldwide technological developments that we can implement across our product lines
B33: Our research and development efforts are focused largely on the development of next-generation and novel technology offerings across multiple programs and all divisions
C34: !Check into R&D projects, product pipelines, and create useful life schedules for current assets!
B35: In the past several years, The Company has completed numerous acquisitions in support of its growth strategy, both strengthening the core businesses and expanding into high growth adjacent markets
A96: Product Offerings
B98: The Company's core businesses are organized into two reportable segments: MedSurg and Cardiovascular. The following describes our key product offerings and new product innovations by reportable segment and business unit
C99: Rhythm and Neuro operating segment is consolidated into the Cardiovascular segment on financial filings
B101: [Build table here]

Sheet Model
AU1: Q1 2020 | AY1: Q1 2021 | BC1: Q1 2022 | BG1: Q1 2023 | BK1: Q1 2024 | BO1: Q1 2025 | BS1: Q1 2026
B2: Quarterly | C2: Apr | D2: July | E2: Oct | F2: Jan | G2: Apr | H2: July | I2: Oct | J2: Jan | K2: Apr | L2: July | M2: Oct | N2: Jan | O2: Apr | P2: July | Q2: Oct | R2: Jan | S2: Apr | T2: July | U2: Oct | V2: Jan | W2: Apr | X2: July | Y2: Oct | Z2: Jan | AA2: Apr | AB2: July | AC2: Oct | AD2: Jan | AE2: Apr | AF2: July | AG2: Oct | AH2: Jan | AI2: Apr | AJ2: July | AK2: Oct | AL2: Jan | AM2: Apr | AN2: July | AO2: Oct | AP2: Jan | AQ2: Apr | AR2: July | AS2: Oct | AT2: Jan | AU2: Apr | AV2: July | AW2: Oct | AX2: Jan | AY2: Apr | AZ2: July | BA2: Oct | BB2: Jan | BC2: Apr | BD2: July | BE2: Oct | BF2: Jan | BG2: Apr | BH2: July | BI2: Oct | BJ2: Jan | BK2: Apr | BL2: July | BM2: Oct | BN2: Jan | BO2: Apr | BP2: July | BQ2: Oct | BR2: Jan | BS2: Apr | BT2: July | BU2: Oct | BV2: Jan
B3: Revenues | C3: {="Q"&MOD(_xlfn.SEQUENCE(1,72)-1,4)+1&" "&(2009+INT((_xlfn.SEQUENCE(1,72)-1)/4))} -> Q1 2009 | D3: Q2 2009 | E3: Q3 2009 | F3: Q4 2009 | G3: Q1 2010 | H3: Q2 2010 | I3: Q3 2010 | J3: Q4 2010 | K3: Q1 2011 | L3: Q2 2011 | M3: Q3 2011 | N3: Q4 2011 | O3: Q1 2012 | P3: Q2 2012 | Q3: Q3 2012 | R3: Q4 2012 | S3: Q1 2013 | T3: Q2 2013 | U3: Q3 2013 | V3: Q4 2013 | W3: Q1 2014 | X3: Q2 2014 | Y3: Q3 2014 | Z3: Q4 2014 | AA3: Q1 2015 | AB3: Q2 2015 | AC3: Q3 2015 | AD3: Q4 2015 | AE3: Q1 2016 | AF3: Q2 2016 | AG3: Q3 2016 | AH3: Q4 2016 | AI3: Q1 2017 | AJ3: Q2 2017 | AK3: Q3 2017 | AL3: Q4 2017 | AM3: Q1 2018 | AN3: Q2 2018 | AO3: Q3 2018 | AP3: Q4 2018 | AQ3: Q1 2019 | AR3: Q2 2019 | AS3: Q3 2019 | AT3: Q4 2019 | AU3: Q1 2020 | AV3: Q2 2020 | AW3: Q3 2020 | AX3: Q4 2020 | AY3: Q1 2021 | AZ3: Q2 2021 | BA3: Q3 2021 | BB3: Q4 2021 | BC3: Q1 2022 | BD3: Q2 2022 | BE3: Q3 2022 | BF3: Q4 2022 | BG3: Q1 2023 | BH3: Q2 2023 | BI3: Q3 2023 | BJ3: Q4 2023 | BK3: Q1 2024 | BL3: Q2 2024 | BM3: Q3 2024 | BN3: Q4 2024 | BO3: Q1 2025 | BP3: Q2 2025 | BQ3: Q3 2025 | BR3: Q4 2025 | BS3: Q1 2026 | BT3: Q2 2026 | BU3: Q3 2026 | BV3: Q4 2026 | CA3: 2009 | CB3: =CA3+1 -> 2010 | CC3: =CB3+1 -> 2011 | CD3: =CC3+1 -> 2012 | CE3: =CD3+1 -> 2013 | CF3: =CE3+1 -> 2014 | CG3: =CF3+1 -> 2015 | CH3: =CG3+1 -> 2016 | CI3: =CH3+1 -> 2017 | ... EO3: =EN3+1 -> 2075
B4: Endoscopy | AU4: 442 | AV4: 348 | AW4: 475 | AX4: =1780-SUM(AU4:AW4) -> 515 | AY4: 499 | AZ4: 551 | BA4: 533 | BB4: =2141-SUM(AY4:BA4) -> 558 | BC4: 532 | BD4: 561 | BE4: 559 | BF4: =2221-SUM(BC4:BE4) -> 569 | BG4: 577 | BH4: 630 | BI4: 629 | BJ4: =2482-SUM(BG4:BI4) -> 646 | BK4: 642 | BL4: 675 | BM4: 678 | BN4: =2687-SUM(BK4:BM4) -> 692 | BO4: 673 | BP4: 737 | BQ4: 747 | BR4: 760 | BS4: 736 | BT4: 793 | CK4: 1894 | CL4: =SUM(AU4:AX4) -> 1780 | CM4: =SUM(AY4:BB4) -> 2141 | CN4: =SUM(BC4:BF4) -> 2221 | CO4: =SUM(BG4:BJ4) -> 2482 | CP4: =SUM(BK4:BN4) -> 2687 | CQ4: =SUM(BO4:BR4) -> 2917 | CR4: =CQ4*(1+CR17) -> 3179.53 | CS4: =CR4*(1+CS17) -> 3386.1995 | CT4: =CS4*(1+CT17) -> 3562.2818 | CU4: =CT4*(1+CU17) -> 3711.8977 | CV4: =CU4*(1+CV17) -> 3860.3736 | CW4: =CV4*(1+CW17) -> 4003.2074 | CX4: =CW4*(1+CX17) -> 4143.3196 | CY4: =CX4*(1+CY17) -> 4275.9059 | ... DA4: =CZ4*(1+DA17) -> 4540.7127
B5: Urology | AU5: 332 | AV5: 228 | AW5: 350 | AX5: =1286-SUM(AU5:AW5) -> 376 | AY5: 361 | AZ5: 397 | BA5: 384 | BB5: =1583-SUM(AY5:BA5) -> 441 | BC5: 413 | BD5: 450 | BE5: 433 | BF5: =1773-SUM(BC5:BE5) -> 477 | BG5: 469 | BH5: 485 | BI5: 483 | BJ5: =1964-SUM(BG5:BI5) -> 527 | BK5: 513 | BL5: 525 | BM5: 532 | BN5: =2200-SUM(BK5:BM5) -> 630 | BO5: 633 | BP5: 676 | BQ5: 682 | BR5: 717 | BS5: 646 | BT5: 684 | CK5: 1413 | CL5: =SUM(AU5:AX5) -> 1286 | CM5: =SUM(AY5:BB5) -> 1583 | CN5: =SUM(BC5:BF5) -> 1773 | CO5: =SUM(BG5:BJ5) -> 1964 | CP5: =SUM(BK5:BN5) -> 2200 | CQ5: =SUM(BO5:BR5) -> 2708 | CR5: =CQ5*(1+CR18) -> 2870.48 | CS5: =CR5*(1+CS18) -> 2985.2992 | CT5: =CS5*(1+CT18) -> 3194.2701 | CU5: =CT5*(1+CU18) -> 3449.8118 | CV5: =CU5*(1+CV18) -> 3656.8005 | CW5: =CV5*(1+CW18) -> 3839.6405 | CX5: =CW5*(1+CX18) -> 4012.4243 | CY5: =CX5*(1+CY18) -> 4172.9213 | ... DA5: =CZ5*(1+DA18) -> 4459.3402
B6: Neuromodulation | AU6: 191 | AV6: 122 | AW6: 216 | AX6: =761-SUM(AU6:AW6) -> 232 | AY6: 198 | AZ6: 247 | BA6: 221 | BB6: =909-SUM(AY6:BA6) -> 243 | BC6: 209 | BD6: 238 | BE6: 221 | BF6: =917-SUM(BC6:BE6) -> 249 | BG6: 234 | BH6: 244 | BI6: 229 | BJ6: =976-SUM(BG6:BI6) -> 269 | BK6: 256 | BL6: 282 | BM6: 268 | BN6: =1106-SUM(BK6:BM6) -> 300 | BO6: 271 | BP6: 303 | BQ6: 293 | BR6: 332 | BS6: 319 | BT6: 341 | CK6: 873 | CL6: =SUM(AU6:AX6) -> 761 | CM6: =SUM(AY6:BB6) -> 909 | CN6: =SUM(BC6:BF6) -> 917 | CO6: =SUM(BG6:BJ6) -> 976 | CP6: =SUM(BK6:BN6) -> 1106 | CQ6: =SUM(BO6:BR6) -> 1199 | CR6: =CQ6*(1+CR19) -> 1366.86 | CS6: =CR6*(1+CS19) -> 1530.8832 | CT6: =CS6*(1+CT19) -> 1699.2804 | CU6: =CT6*(1+CU19) -> 1869.2084 | CV6: =CU6*(1+CV19) -> 2037.4371 | CW6: =CV6*(1+CW19) -> 2200.4321 | CX6: =CW6*(1+CX19) -> 2354.4624 | CY6: =CX6*(1+CY19) -> 2495.7301 | ... DA6: =CZ6*(1+DA19) -> 2725.3373
B7: MedSurg Ttl Revenues | AU7: =SUM(AU4:AU6) -> 965 | AV7: =SUM(AV4:AV6) -> 698 | AW7: =SUM(AW4:AW6) -> 1041 | AX7: =SUM(AX4:AX6) -> 1123 | AY7: =SUM(AY4:AY6) -> 1058 | AZ7: =SUM(AZ4:AZ6) -> 1195 | BA7: =SUM(BA4:BA6) -> 1138 | BB7: =SUM(BB4:BB6) -> 1242 | ... BT7: =SUM(BT4:BT6) -> 1818 | CK7: =SUM(CK4:CK6) -> 4180 | CL7: =SUM(CL4:CL6) -> 3827 | CM7: =SUM(CM4:CM6) -> 4633 | CN7: =SUM(CN4:CN6) -> 4911 | CO7: =SUM(CO4:CO6) -> 5422 | CP7: =SUM(CP4:CP6) -> 5993 | CQ7: =SUM(BO7:BR7) -> 6824 | CR7: =SUM(CR4:CR6) -> 7416.87 | CS7: =SUM(CS4:CS6) -> 7902.3818 | CT7: =SUM(CT4:CT6) -> 8455.8323 | CU7: =SUM(CU4:CU6) -> 9030.9178 | CV7: =SUM(CV4:CV6) -> 9554.6112 | CW7: =SUM(CW4:CW6) -> 10043.28 | CX7: =SUM(CX4:CX6) -> 10510.206 | CY7: =SUM(CY4:CY6) -> 10944.557 | ... DA7: =SUM(DA4:DA6) -> 11725.39
B8: Interventional Cardiology | AU8: 633 | AV8: 495 | AW8: 586 | AX8: =2299-SUM(AU8:AW8) -> 585 | AY8: 526 | AZ8: 574 | BA8: 534 | BB8: =2209-SUM(AY8:BA8) -> 575 | BC8: 544 | BD8: 574 | BE8: 549 | BF8: =2228-SUM(BC8:BE8) -> 561 | BG8: 591 | BH8: 629 | BI8: 583 | BJ8: =2417-SUM(BG8:BI8) -> 614 | BK8: 652 | BL8: 665 | BM8: 661 | BN8: =2645-SUM(BK8:BM8) -> 667 | BO8: 697 | BP8: 731 | BQ8: 686 | BR8: 732 | BS8: 764 | BT8: 833 | CK8: 2816 | CL8: =SUM(AU8:AX8) -> 2299 | CM8: =SUM(AY8:BB8) -> 2209 | CN8: =SUM(BC8:BF8) -> 2228 | CO8: =SUM(BG8:BJ8) -> 2417 | CP8: =SUM(BK8:BN8) -> 2645 | CQ8: =SUM(BO8:BR8) -> 2846 | CR8: =CQ8*(1+CR21) -> 3116.37 | CS8: =CR8*(1+CS21) -> 3459.1707 | CT8: =CS8*(1+CT21) -> 3701.3126 | CU8: =CT8*(1+CU21) -> 3886.3783 | CV8: =CU8*(1+CV21) -> 4061.2653 | CW8: =CV8*(1+CW21) -> 4223.7159 | CX8: =CW8*(1+CX21) -> 4371.546 | CY8: =CX8*(1+CY21) -> 4502.6924 | ... DA8: =CZ8*(1+DA21) -> 4719.103
B9: Watchman | AU9: 41 | AV9: 68 | AW9: 74 | AX9: =219-SUM(AU9:AW9) -> 36 | AY9: 170 | AZ9: 216 | BA9: 210 | BB9: =829-SUM(AY9:BA9) -> 233 | BC9: 226 | BD9: 250 | BE9: 262 | BF9: =1019-SUM(BC9:BE9) -> 281 | BG9: 291 | BH9: 317 | BI9: 323 | BJ9: =1274-SUM(BG9:BI9) -> 343 | BK9: 344 | BL9: 379 | BM9: 380 | BN9: =1516-SUM(BK9:BM9) -> 413 | BO9: 425 | BP9: 486 | BQ9: 512 | BR9: 541 | BS9: 506 | BT9: 507 | CK9: 81 | CL9: =SUM(AU9:AX9) -> 219 | CM9: =SUM(AY9:BB9) -> 829 | CN9: =SUM(BC9:BF9) -> 1019 | CO9: =SUM(BG9:BJ9) -> 1274 | CP9: =SUM(BK9:BN9) -> 1516 | CQ9: =SUM(BO9:BR9) -> 1964 | CR9: =CQ9*(1+CR22) -> 2278.24 | CS9: =CR9*(1+CS22) -> 2585.8024 | CT9: =CS9*(1+CT22) -> 2973.6728 | CU9: =CT9*(1+CU22) -> 3330.5135 | CV9: =CU9*(1+CV22) -> 3713.5225 | CW9: =CV9*(1+CW22) -> 4084.8748 | CX9: =CW9*(1+CX22) -> 4432.0892 | CY9: =CX9*(1+CY22) -> 4764.4958 | ... DA9: =CZ9*(1+DA22) -> 5429.3812
B10: Cardiac Rhythm | AU10: 437 | AV10: 351 | AW10: 465 | AX10: =1704-SUM(AU10:AW10) -> 451 | AY10: 469 | AZ10: 524 | BA10: 512 | BB10: =2019-SUM(AY10:BA10) -> 514 | BC10: 519 | BD10: 541 | BE10: 519 | BF10: =2100-SUM(BC10:BE10) -> 521 | BG10: 548 | BH10: 566 | BI10: 552 | BJ10: =2218-SUM(BG10:BI10) -> 552 | BK10: 575 | BL10: 576 | BM10: 561 | BN10: =2279-SUM(BK10:BM10) -> 567 | BO10: 578 | BP10: 590 | BQ10: 578 | BR10: 607 | BS10: 906 | BT10: 585 | CK10: 1939 | CL10: =SUM(AU10:AX10) -> 1704 | CM10: =SUM(AY10:BB10) -> 2019 | CN10: =SUM(BC10:BF10) -> 2100 | CO10: =SUM(BG10:BJ10) -> 2218 | CP10: =SUM(BK10:BN10) -> 2279 | CQ10: =SUM(BO10:BR10) -> 2353 | CR10: =CQ10*(1+CR23) -> 3176.55 | CS10: =CR10*(1+CS23) -> 3811.86 | CT10: =CS10*(1+CT23) -> 3926.2158 | CU10: =CT10*(1+CU23) -> 4024.3712 | CV10: =CU10*(1+CV23) -> 4114.9195 | CW10: =CV10*(1+CW23) -> 4197.2179 | CX10: =CW10*(1+CX23) -> 4270.6693 | CY10: =CX10*(1+CY23) -> 4334.7293 | ... DA10: =CZ10*(1+DA23) -> 4432.8025
B11: Electrophysiology | AU11: 74 | AV11: 51 | AW11: 76 | AX11: =287-SUM(AU11:AW11) -> 86 | AY11: 83 | AZ11: 95 | BA11: 86 | BB11: =365-SUM(AY11:BA11) -> 101 | BC11: 118 | BD11: 152 | BE11: 148 | BF11: =585-SUM(BC11:BE11) -> 167 | BG11: 177 | BH11: 193 | BI11: 190 | BJ11: =800-SUM(BG11:BI11) -> 240 | BK11: 300 | BL11: 428 | BM11: 527 | BN11: =1904-SUM(BK11:BM11) -> 649 | BO11: 729 | BP11: 840 | BQ11: 865 | BR11: 889 | BS11: 578 | BT11: 916 | CK11: 329 | CL11: =SUM(AU11:AX11) -> 287 | CM11: =SUM(AY11:BB11) -> 365 | CN11: =SUM(BC11:BF11) -> 585 | CO11: =SUM(BG11:BJ11) -> 800 | CP11: =SUM(BK11:BN11) -> 1904 | CQ11: =SUM(BO11:BR11) -> 3323 | CR11: =CQ11*(1+CR24) -> 2591.94 | CS11: =CR11*(1+CS24) -> 2332.746 | CT11: =CS11*(1+CT24) -> 2659.3304 | CU11: =CT11*(1+CU24) -> 2951.8568 | CV11: =CU11*(1+CV24) -> 3217.5239 | CW11: =CV11*(1+CW24) -> 3474.9258 | CX11: =CW11*(1+CX24) -> 3718.1706 | CY11: =CX11*(1+CY24) -> 3941.2609 | ... DA11: =CZ11*(1+DA24) -> 4303.8569
B12: Cardiology Ttl | AU12: =SUM(AU8:AU11) -> 1185 | AV12: =SUM(AV8:AV11) -> 965 | AW12: =SUM(AW8:AW11) -> 1201 | AX12: =SUM(AX8:AX11) -> 1158 | AY12: =SUM(AY8:AY11) -> 1248 | AZ12: =SUM(AZ8:AZ11) -> 1409 | BA12: =SUM(BA8:BA11) -> 1342 | BB12: =SUM(BB8:BB11) -> 1423 | ... BT12: =SUM(BT8:BT11) -> 2841 | CK12: =SUM(CK8:CK11) -> 5165 | CL12: =SUM(CL8:CL11) -> 4509 | CM12: =SUM(CM8:CM11) -> 5422 | CN12: =SUM(CN8:CN11) -> 5932 | CO12: =SUM(CO8:CO11) -> 6709 | CP12: =SUM(CP8:CP11) -> 8344 | CQ12: =SUM(BO12:BR12) -> 10486 | CR12: =SUM(CR8:CR11) -> 11163.1 | CS12: =SUM(CS8:CS11) -> 12189.579 | CT12: =SUM(CT8:CT11) -> 13260.532 | CU12: =SUM(CU8:CU11) -> 14193.12 | CV12: =SUM(CV8:CV11) -> 15107.231 | CW12: =SUM(CW8:CW11) -> 15980.734 | CX12: =SUM(CX8:CX11) -> 16792.475 | CY12: =SUM(CY8:CY11) -> 17543.178 | ... DA12: =SUM(DA8:DA11) -> 18885.144
B13: Peripheral Interventions | AU13: 393 | AV13: 340 | AW13: 417 | AX13: =1577-SUM(AU13:AW13) -> 427 | AY13: =433 -> 433 | AZ13: 473 | BA13: 452 | BB13: =1820-SUM(AY13:BA13) -> 462 | BC13: 465 | BD13: 478 | BE13: 479 | BF13: =1899-SUM(BC13:BE13) -> 477 | BG13: 502 | BH13: 535 | BI13: 538 | BJ13: =2109-SUM(BG13:BI13) -> 534 | BK13: 575 | BL13: 590 | BM13: 602 | BN13: =2410-SUM(BK13:BM13) -> 643 | BO13: 657 | BP13: 698 | BQ13: 702 | BR13: 708 | BS13: 749 | BT13: 783 | CK13: 1390 | CL13: =SUM(AU13:AX13) -> 1577 | CM13: =SUM(AY13:BB13) -> 1820 | CN13: =SUM(BC13:BF13) -> 1899 | CO13: =SUM(BG13:BJ13) -> 2109 | CP13: =SUM(BK13:BN13) -> 2410 | CQ13: =SUM(BO13:BR13) -> 2765 | CR13: =CQ13*(1+CR26) -> 3138.275 | CS13: =CR13*(1+CS26) -> 3514.868 | CT13: =CS13*(1+CT26) -> 3919.0778 | CU13: =CT13*(1+CU26) -> 4350.1764 | CV13: =CU13*(1+CV26) -> 4785.194 | CW13: =CV13*(1+CW26) -> 5215.8615 | CX13: =CW13*(1+CX26) -> 5633.1304 | CY13: =CX13*(1+CY26) -> 6027.4495 | ... DA13: =CZ13*(1+DA26) -> 6644.6604
B14: Cardiovascular Ttl Revenues | AU14: =SUM(AU12:AU13) -> 1578 | AV14: =SUM(AV12:AV13) -> 1305 | AW14: =SUM(AW12:AW13) -> 1618 | AX14: =SUM(AX12:AX13) -> 1585 | AY14: =SUM(AY12:AY13) -> 1681 | AZ14: =SUM(AZ12:AZ13) -> 1882 | BA14: =SUM(BA12:BA13) -> 1794 | BB14: =SUM(BB12:BB13) -> 1885 | ... BT14: =SUM(BT12:BT13) -> 3624 | CK14: =CK12+CK13 -> 6555 | CL14: =CL12+CL13 -> 6086 | CM14: =CM12+CM13 -> 7242 | CN14: =CN12+CN13 -> 7831 | CO14: =CO12+CO13 -> 8818 | CP14: =CP12+CP13 -> 10754 | CQ14: =SUM(BO14:BR14) -> 13251 | CR14: =CR12+CR13 -> 14301.375 | CS14: =CS12+CS13 -> 15704.447 | CT14: =CT12+CT13 -> 17179.609 | CU14: =CU12+CU13 -> 18543.296 | CV14: =CV12+CV13 -> 19892.425 | CW14: =CW12+CW13 -> 21196.596 | CX14: =CX12+CX13 -> 22425.605 | CY14: =CY12+CY13 -> 23570.628 | ... DA14: =DA12+DA13 -> 25529.804
B15: Ttl Revenues | AU15: =AU7+AU14 -> 2543 | AV15: =AV7+AV14 -> 2003 | AW15: =AW7+AW14 -> 2659 | AX15: =AX7+AX14 -> 2708 | AY15: =AY7+AY14+13 -> 2752 | AZ15: =AZ7+AZ14 -> 3077 | BA15: =BA7+BA14 -> 2932 | BB15: =BB7+BB14 -> 3127 | BC15: =BC7+BC14 -> 3026 | BD15: =BD7+BD14 -> 3244 | BE15: =BE7+BE14 -> 3170 | BF15: =BF7+BF14-60 -> 3242 | BG15: =BG7+BG14 -> 3389 | BH15: =BH7+BH14 -> 3599 | BI15: =BI7+BI14 -> 3527 | BJ15: =BJ7+BJ14 -> 3725 | BK15: =BK7+BK14 -> 3857 | BL15: =BL7+BL14 -> 4120 | BM15: =BM7+BM14 -> 4209 | BN15: =BN7+BN14 -> 4561 | ... BT15: =BT7+BT14 -> 5442 | CK15: =CK7+CK14 -> 10735 | CL15: =CL7+CL14 -> 9913 | CM15: =CM7+CM14+13 -> 11888 | CN15: =CN7+CN14-60 -> 12682 | CO15: =CO7+CO14 -> 14240 | CP15: =CP7+CP14 -> 16747 | CQ15: =SUM(BO15:BR15) -> 20075 | CR15: =CR7+CR14 -> 21718.245 | CS15: =CS7+CS14 -> 23606.829 | CT15: =CT7+CT14 -> 25635.442 | CU15: =CU7+CU14 -> 27574.214 | CV15: =CV7+CV14 -> 29447.036 | CW15: =CW7+CW14 -> 31239.876 | CX15: =CX7+CX14 -> 32935.812 | CY15: =CY7+CY14 -> 34515.185 | ... DA15: =DA7+DA14 -> 37255.194
B17: Endoscopy Growth Y/y | AY17: =AY4/AU4-1 -> 0.12895928 | AZ17: =AZ4/AV4-1 -> 0.58333333 | BA17: =BA4/AW4-1 -> 0.12210526 | BB17: =BB4/AX4-1 -> 0.083495146 | BC17: =BC4/AY4-1 -> 0.066132265 | BD17: =BD4/AZ4-1 -> 0.01814882 | BE17: =BE4/BA4-1 -> 0.048780488 | BF17: =BF4/BB4-1 -> 0.019713262 | ... BT17: =BT4/BP4-1 -> 0.075983718 | CL17: =CL4/CK4-1 -> -0.060190074 | CM17: =CM4/CL4-1 -> 0.20280899 | CN17: =CN4/CM4-1 -> 0.037365717 | CO17: =CO4/CN4-1 -> 0.11751463 | CP17: =CP4/CO4-1 -> 0.082594682 | CQ17: =CQ4/CP4-1 -> 0.08559732 | CR17: 0.09 | CS17: 0.065 | CT17: 0.052 | CU17: 0.042 | CV17: 0.04 | CW17: 0.037 | CX17: 0.035 | CY17: 0.032 | CZ17: 0.031 | DA17: 0.03
B18: Urology Growth Y/y | AY18: =AY5/AU5-1 -> 0.087349398 | AZ18: =AZ5/AV5-1 -> 0.74122807 | BA18: =BA5/AW5-1 -> 0.097142857 | BB18: =BB5/AX5-1 -> 0.17287234 | BC18: =BC5/AY5-1 -> 0.14404432 | BD18: =BD5/AZ5-1 -> 0.13350126 | BE18: =BE5/BA5-1 -> 0.12760417 | BF18: =BF5/BB5-1 -> 0.081632653 | ... BT18: =BT5/BP5-1 -> 0.01183432 | CL18: =CL5/CK5-1 -> -0.089879689 | CM18: =CM5/CL5-1 -> 0.23094868 | CN18: =CN5/CM5-1 -> 0.12002527 | CO18: =CO5/CN5-1 -> 0.10772702 | CP18: =CP5/CO5-1 -> 0.12016293 | CQ18: =CQ5/CP5-1 -> 0.23090909 | CR18: 0.06 | CS18: 0.04 | CT18: 0.07 | CU18: 0.08 | CV18: 0.06 | CW18: 0.05 | CX18: 0.045 | CY18: 0.04 | CZ18: 0.035 | DA18: 0.0325
B19: Neuro Growth Y/y | AY19: =AY6/AU6-1 -> 0.036649215 | AZ19: =AZ6/AV6-1 -> 1.0245902 | BA19: =BA6/AW6-1 -> 0.023148148 | BB19: =BB6/AX6-1 -> 0.047413793 | BC19: =BC6/AY6-1 -> 0.055555556 | BD19: =BD6/AZ6-1 -> -0.036437247 | BE19: =BE6/BA6-1 -> 0 | BF19: =BF6/BB6-1 -> 0.024691358 | ... BT19: =BT6/BP6-1 -> 0.12541254 | CL19: =CL6/CK6-1 -> -0.12829324 | CM19: =CM6/CL6-1 -> 0.19448095 | CN19: =CN6/CM6-1 -> 0.0088008801 | CO19: =CO6/CN6-1 -> 0.06434024 | CP19: =CP6/CO6-1 -> 0.13319672 | CQ19: =CQ6/CP6-1 -> 0.084086799 | CR19: 0.14 | CS19: 0.12 | CT19: 0.11 | CU19: 0.1 | CV19: 0.09 | CW19: 0.08 | CX19: 0.07 | CY19: 0.06 | CZ19: 0.05 | DA19: 0.04
B20: MedSurg Growth Y/y | AY20: =AY7/AU7-1 -> 0.096373057 | AZ20: =AZ7/AV7-1 -> 0.71203438 | BA20: =BA7/AW7-1 -> 0.093179635 | BB20: =BB7/AX7-1 -> 0.10596616 | BC20: =BC7/AY7-1 -> 0.09073724 | BD20: =BD7/AZ7-1 -> 0.045188285 | BE20: =BE7/BA7-1 -> 0.065905097 | BF20: =BF7/BB7-1 -> 0.042673108 | ... BT20: =BT7/BP7-1 -> 0.059440559 | CL20: =CL7/CK7-1 -> -0.084449761 | CM20: =CM7/CL7-1 -> 0.21060883 | CN20: =CN7/CM7-1 -> 0.060004317 | CO20: =CO7/CN7-1 -> 0.10405213 | CP20: =CP7/CO7-1 -> 0.10531169 | CQ20: =CQ7/CP7-1 -> 0.13866177 | CR20: =CR7/CQ7-1 -> 0.086880129 | CS20: =CS7/CR7-1 -> 0.065460477 | ... DA20: =DA7/CZ7-1 -> 0.03326073
B21: Interventional Growth Y/y | AY21: =AY8/AU8-1 -> -0.16903633 | AZ21: =AZ8/AV8-1 -> 0.15959596 | BA21: =BA8/AW8-1 -> -0.088737201 | BB21: =BB8/AX8-1 -> -0.017094017 | BC21: =BC8/AY8-1 -> 0.034220532 | BD21: =BD8/AZ8-1 -> 0 | BE21: =BE8/BA8-1 -> 0.028089888 | BF21: =BF8/BB8-1 -> -0.024347826 | ... BT21: =BT8/BP8-1 -> 0.13953488 | CL21: =CL8/CK8-1 -> -0.18359375 | CM21: =CM8/CL8-1 -> -0.039147455 | CN21: =CN8/CM8-1 -> 0.008601177 | CO21: =CO8/CN8-1 -> 0.084829443 | CP21: =CP8/CO8-1 -> 0.094331816 | CQ21: =CQ8/CP8-1 -> 0.075992439 | CR21: 0.095 | CS21: 0.11 | CT21: 0.07 | CU21: 0.05 | CV21: 0.045 | CW21: 0.04 | CX21: 0.035 | CY21: 0.03 | CZ21: 0.025 | DA21: 0.0225
B22: Watchman Growth Y/y | AY22: =AY9/AU9-1 -> 3.1463415 | AZ22: =AZ9/AV9-1 -> 2.1764706 | BA22: =BA9/AW9-1 -> 1.8378378 | BB22: =BB9/AX9-1 -> 5.4722222 | BC22: =BC9/AY9-1 -> 0.32941176 | BD22: =BD9/AZ9-1 -> 0.15740741 | BE22: =BE9/BA9-1 -> 0.24761905 | BF22: =BF9/BB9-1 -> 0.20600858 | ... BT22: =BT9/BP9-1 -> 0.043209877 | CL22: =CL9/CK9-1 -> 1.7037037 | CM22: =CM9/CL9-1 -> 2.7853881 | CN22: =CN9/CM9-1 -> 0.2291918 | CO22: =CO9/CN9-1 -> 0.25024534 | CP22: =CP9/CO9-1 -> 0.1899529 | CQ22: =CQ9/CP9-1 -> 0.29551451 | CR22: 0.16 | CS22: 0.135 | CT22: 0.15 | CU22: 0.12 | CV22: 0.115 | CW22: 0.1 | CX22: 0.085 | CY22: 0.075 | CZ22: 0.07 | DA22: 0.065
B23: Rhythm Growth Y/y | AY23: =AY10/AU10-1 -> 0.073226545 | AZ23: =AZ10/AV10-1 -> 0.49287749 | BA23: =BA10/AW10-1 -> 0.10107527 | BB23: =BB10/AX10-1 -> 0.13968958 | BC23: =BC10/AY10-1 -> 0.10660981 | BD23: =BD10/AZ10-1 -> 0.032442748 | BE23: =BE10/BA10-1 -> 0.013671875 | BF23: =BF10/BB10-1 -> 0.013618677 | ... BT23: =BT10/BP10-1 -> -0.0084745763 | CL23: =CL10/CK10-1 -> -0.12119649 | CM23: =CM10/CL10-1 -> 0.18485915 | CN23: =CN10/CM10-1 -> 0.040118871 | CO23: =CO10/CN10-1 -> 0.056190476 | CP23: =CP10/CO10-1 -> 0.027502254 | CQ23: =CQ10/CP10-1 -> 0.032470382 | CR23: 0.35 | CS23: 0.2 | CT23: 0.03 | CU23: 0.025 | CV23: 0.0225 | CW23: 0.02 | CX23: 0.0175 | CY23: 0.015 | CZ23: 0.0125 | DA23: 0.01
B24: Electrophysiology Growth Y/y | AY24: =AY11/AU11-1 -> 0.12162162 | AZ24: =AZ11/AV11-1 -> 0.8627451 | BA24: =BA11/AW11-1 -> 0.13157895 | BB24: =BB11/AX11-1 -> 0.1744186 | BC24: =BC11/AY11-1 -> 0.42168675 | BD24: =BD11/AZ11-1 -> 0.6 | BE24: =BE11/BA11-1 -> 0.72093023 | BF24: =BF11/BB11-1 -> 0.65346535 | ... BT24: =BT11/BP11-1 -> 0.09047619 | CL24: =CL11/CK11-1 -> -0.12765957 | CM24: =CM11/CL11-1 -> 0.271777 | CN24: =CN11/CM11-1 -> 0.60273973 | CO24: =CO11/CN11-1 -> 0.36752137 | CP24: =CP11/CO11-1 -> 1.38 | CQ24: =CQ11/CP11-1 -> 0.74527311 | CR24: -0.22 | CS24: -0.1 | CT24: 0.14 | CU24: 0.11 | CV24: 0.09 | CW24: 0.08 | CX24: 0.07 | CY24: 0.06 | CZ24: 0.05 | DA24: 0.04
B25: Cardiology Growth Y/y | AY25: =AY12/AU12-1 -> 0.053164557 | AZ25: =AZ12/AV12-1 -> 0.46010363 | BA25: =BA12/AW12-1 -> 0.11740216 | BB25: =BB12/AX12-1 -> 0.22884283 | BC25: =BC12/AY12-1 -> 0.12740385 | BD25: =BD12/AZ12-1 -> 0.076650106 | BE25: =BE12/BA12-1 -> 0.10134128 | BF25: =BF12/BB12-1 -> 0.075193254 | ... BT25: =BT12/BP12-1 -> 0.073290518 | CL25: =CL12/CK12-1 -> -0.12700871 | CM25: =CM12/CL12-1 -> 0.20248392 | CN25: =CN12/CM12-1 -> 0.094061232 | CO25: =CO12/CN12-1 -> 0.13098449 | CP25: =CP12/CO12-1 -> 0.24370249 | CQ25: =CQ12/CP12-1 -> 0.25671141 | CR25: =CR13/CQ13-1 -> 0.135 | CS25: =CS13/CR13-1 -> 0.12 | CT25: =CT13/CS13-1 -> 0.115 | CU25: =CU13/CT13-1 -> 0.11 | CV25: =CV13/CU13-1 -> 0.1 | CW25: =CW13/CV13-1 -> 0.09 | CX25: =CX13/CW13-1 -> 0.08 | CY25: =CY13/CX13-1 -> 0.07 | ... DA25: =DA13/CZ13-1 -> 0.04
B26: Peripheral Growth Y/y | AY26: =AY13/AU13-1 -> 0.10178117 | AZ26: =AZ13/AV13-1 -> 0.39117647 | BA26: =BA13/AW13-1 -> 0.083932854 | BB26: =BB13/AX13-1 -> 0.081967213 | BC26: =BC13/AY13-1 -> 0.073903002 | BD26: =BD13/AZ13-1 -> 0.010570825 | BE26: =BE13/BA13-1 -> 0.059734513 | BF26: =BF13/BB13-1 -> 0.032467532 | ... BT26: =BT13/BP13-1 -> 0.1217765 | CL26: =CL13/CK13-1 -> 0.13453237 | CM26: =CM13/CL13-1 -> 0.15409004 | CN26: =CN13/CM13-1 -> 0.043406593 | CO26: =CO13/CN13-1 -> 0.11058452 | CP26: =CP13/CO13-1 -> 0.14272167 | CQ26: =CQ13/CP13-1 -> 0.1473029 | CR26: 0.135 | CS26: 0.12 | CT26: 0.115 | CU26: 0.11 | CV26: 0.1 | CW26: 0.09 | CX26: 0.08 | CY26: 0.07 | CZ26: 0.06 | DA26: 0.04
B27: Cardiovascular Y/y | AY27: =AY14/AU14-1 -> 0.065272497 | AZ27: =AZ14/AV14-1 -> 0.44214559 | BA27: =BA14/AW14-1 -> 0.10877627 | BB27: =BB14/AX14-1 -> 0.18927445 | BC27: =BC14/AY14-1 -> 0.11362284 | BD27: =BD14/AZ14-1 -> 0.060042508 | BE27: =BE14/BA14-1 -> 0.090858417 | BF27: =BF14/BB14-1 -> 0.064721485 | ... BT27: =BT14/BP14-1 -> 0.083408072 | CL27: =CL14/CK14-1 -> -0.071548436 | CM27: =CM14/CL14-1 -> 0.18994413 | CN27: =CN14/CM14-1 -> 0.081331124 | CO27: =CO14/CN14-1 -> 0.12603754 | CP27: =CP14/CO14-1 -> 0.21955092 | CQ27: =CQ14/CP14-1 -> 0.23219267 | CR27: =CR14/CQ14-1 -> 0.079267602 | CS27: =CS14/CR14-1 -> 0.098107497 | ... DA27: =DA14/CZ14-1 -> 0.036549511
B28: Ttl Revenue Growth Y/y | AY28: =AY15/AU15-1 -> 0.082186394 | AZ28: =AZ15/AV15-1 -> 0.53619571 | BA28: =BA15/AW15-1 -> 0.10267018 | BB28: =BB15/AX15-1 -> 0.15472674 | BC28: =BC15/AY15-1 -> 0.099563953 | BD28: =BD15/AZ15-1 -> 0.054273643 | BE28: =BE15/BA15-1 -> 0.081173261 | BF28: =BF15/BB15-1 -> 0.036776463 | ... BT28: =BT15/BP15-1 -> 0.075281565 | CL28: =CL15/CK15-1 -> -0.076571961 | CM28: =CM15/CL15-1 -> 0.19923333 | CN28: =CN15/CM15-1 -> 0.06679004 | CO28: =CO15/CN15-1 -> 0.12285129 | CP28: =CP15/CO15-1 -> 0.17605337 | CQ28: =CQ15/CP15-1 -> 0.19872216 | CR28: =CR15/CQ15-1 -> 0.081855293 | CS28: =CS15/CR15-1 -> 0.086958405 | ... DA28: =DA15/CZ15-1 -> 0.035512172
B30: MedSurg % of Ttl Revenues | AU30: =AU7/AU15 -> 0.37947306 | AV30: =AV7/AV15 -> 0.34847728 | AW30: =AW7/AW15 -> 0.39150056 | AX30: =AX7/AX15 -> 0.41469719 | AY30: =AY7/AY15 -> 0.38444767 | AZ30: =AZ7/AZ15 -> 0.38836529 | BA30: =BA7/BA15 -> 0.38813097 | BB30: =BB7/BB15 -> 0.3971858 | ... BT30: =BT7/BT15 -> 0.33406836 | CK30: =CK7/CK15 -> 0.38938053 | CL30: =CL7/CL15 -> 0.38605871 | CM30: =CM7/CM15 -> 0.38972073 | CN30: =CN7/CN15 -> 0.38724176 | CO30: =CO7/CO15 -> 0.38075843 | CP30: =CP7/CP15 -> 0.35785514 | CQ30: =CQ7/CQ15 -> 0.33992528 | CR30: =CR7/CR15 -> 0.34150411 | ... DA30: =DA7/DA15 -> 0.31473169
B31: Cardiovasc % of Ttl Revenues | AU31: =AU14/AU15 -> 0.62052694 | AV31: =AV14/AV15 -> 0.65152272 | AW31: =AW14/AW15 -> 0.60849944 | AX31: =AX14/AX15 -> 0.58530281 | AY31: =AY14/AY15 -> 0.61082849 | AZ31: =AZ14/AZ15 -> 0.61163471 | BA31: =BA14/BA15 -> 0.61186903 | BB31: =BB14/BB15 -> 0.6028142 | ... BT31: =BT14/BT15 -> 0.66593164 | CK31: =CK14/CK15 -> 0.61061947 | CL31: =CL14/CL15 -> 0.61394129 | CM31: =CM14/CM15 -> 0.60918573 | CN31: =CN14/CN15 -> 0.61748935 | CO31: =CO14/CO15 -> 0.61924157 | CP31: =CP14/CP15 -> 0.64214486 | CQ31: =CQ14/CQ15 -> 0.66007472 | CR31: =CR14/CR15 -> 0.65849589 | ... DA31: =DA14/DA15 -> 0.68526831
B33: U.S. Revenues | AU33: 1452 | AV33: 1058 | AW33: 1496 | AX33: =5508-SUM(AU33:AW33) -> 1502 | AY33: 1577 | AZ33: 1800 | BA33: 1726 | BB33: =6901-SUM(AY33:BA33) -> 1798 | BC33: 1778 | BD33: 1934 | BE33: 1934 | BF33: =7632-SUM(BC33:BE33) -> 1986 | BG33: 2003 | BH33: 2110 | BI33: 2099 | BJ33: =8425-SUM(BG33:BI33) -> 2213 | BK33: 2258 | BL33: 2466 | BM33: 2593 | BN33: =10210-SUM(BK33:BM33) -> 2893 | BO33: 2960 | BP33: 3224 | BQ33: 3294 | BR33: 3385 | BS33: 3284 | BT33: 3426 | CK33: 6097 | CL33: =SUM(AU33:AX33) -> 5508 | CM33: =SUM(AY33:BB33) -> 6901 | CN33: =SUM(BC33:BF33) -> 7632 | CO33: =SUM(BG33:BJ33) -> 8425 | CP33: =SUM(BK33:BN33) -> 10210 | CQ33: =SUM(BO33:BR33) -> 12863
B34: Euro, Mid. East, Afr | AU34: 552 | AV34: 416 | AW34: 540 | AX34: =2097-SUM(AU34:AW34) -> 589 | AY34: 604 | AZ34: 662 | BA34: 590 | BB34: =2518-SUM(AY34:BA34) -> 662 | BC34: 624 | BD34: 660 | BE34: 585 | BF34: =2526-SUM(BC34:BE34) -> 657 | BG34: 712 | BH34: 723 | BI34: 671 | BJ34: =2856-SUM(BG34:BI34) -> 750 | BK34: 803 | BL34: 822 | BM34: 773 | BN34: =3228-SUM(BK34:BM34) -> 830 | BO34: 846 | BP34: 878 | BQ34: 793 | BR34: 933 | BS34: 932 | BT34: 932 | CK34: 2264 | CL34: =SUM(AU34:AX34) -> 2097 | CM34: =SUM(AY34:BB34) -> 2518 | CN34: =SUM(BC34:BF34) -> 2526 | CO34: =SUM(BG34:BJ34) -> 2856 | CP34: =SUM(BK34:BN34) -> 3228 | CQ34: =SUM(BO34:BR34) -> 3450
B35: A-Pac | AU35: 409 | AV35: 410 | AW35: 472 | AX35: =1781-SUM(AU35:AW35) -> 490 | AY35: 473 | AZ35: 520 | BA35: 517 | BB35: =2070-SUM(AY35:BA35) -> 560 | BC35: 517 | BD35: 530 | BE35: 532 | BF35: =2116-SUM(BC35:BE35) -> 537 | BG35: 548 | BH35: 626 | BI35: 611 | BJ35: =2400-SUM(BG35:BI35) -> 615 | BK35: 647 | BL35: 670 | BM35: 684 | BN35: =2686-SUM(BK35:BM35) -> 685 | BO35: 701 | BP35: 790 | BQ35: 803 | BR35: 789 | BS35: 803 | BT35: 878 | CK35: 1898 | CL35: =SUM(AU35:AX35) -> 1781 | CM35: =SUM(AY35:BB35) -> 2070 | CN35: =SUM(BC35:BF35) -> 2116 | CO35: =SUM(BG35:BJ35) -> 2400 | CP35: =SUM(BK35:BN35) -> 2686 | CQ35: =SUM(BO35:BR35) -> 3083
B36: Lat Am + Canada | AU36: 89 | AV36: 51 | AW36: 77 | AX36: =307-SUM(AU36:AW36) -> 90 | AY36: 85 | AZ36: 95 | BA36: 99 | BB36: =386-SUM(AY36:BA36) -> 107 | BC36: 107 | BD36: 120 | BE36: 119 | BF36: =469-SUM(BC36:BE36) -> 123 | BG36: 126 | BH36: 140 | BI36: 146 | BJ36: =559-SUM(BG36:BI36) -> 147 | BK36: 149 | BL36: 162 | BM36: 159 | BN36: =623-SUM(BK36:BM36) -> 153 | BO36: 156 | BP36: 169 | BQ36: 175 | BR36: 179 | BS36: 185 | BT36: 206 | CK36: 395 | CL36: =SUM(AU36:AX36) -> 307 | CM36: =SUM(AY36:BB36) -> 386 | CN36: =SUM(BC36:BF36) -> 469 | CO36: =SUM(BG36:BJ36) -> 559 | CP36: =SUM(BK36:BN36) -> 623 | CQ36: =SUM(BO36:BR36) -> 679
B37: Ttl Revenues | AU37: =SUM(AU33:AU36)+41 -> 2543 | AV37: =SUM(AV33:AV36)+68 -> 2003 | AW37: =SUM(AW33:AW36)+74 -> 2659 | AX37: =SUM(AX33:AX36)+220-41-68-74 -> 2708 | AY37: =SUM(AY33:AY36)+13 -> 2752 | AZ37: =SUM(AZ33:AZ36) -> 3077 | BA37: =SUM(BA33:BA36) -> 2932 | BB37: =SUM(BB33:BB36) -> 3127 | BC37: =SUM(BC33:BC36) -> 3026 | BD37: =SUM(BD33:BD36) -> 3244 | BE37: =SUM(BE33:BE36) -> 3170 | BF37: =SUM(BF33:BF36)-61 -> 3242 | BG37: =SUM(BG33:BG36) -> 3389 | BH37: =SUM(BH33:BH36) -> 3599 | BI37: =SUM(BI33:BI36) -> 3527 | BJ37: =SUM(BJ33:BJ36) -> 3725 | BK37: =SUM(BK33:BK36) -> 3857 | BL37: =SUM(BL33:BL36) -> 4120 | BM37: =SUM(BM33:BM36) -> 4209 | BN37: =SUM(BN33:BN36) -> 4561 | ... BT37: =SUM(BT33:BT36) -> 5442 | CK37: =SUM(CK33:CK36)+81 -> 10735 | CL37: =SUM(CL33:CL36)+220 -> 9913 | CM37: =SUM(CM33:CM36)+13 -> 11888 | CN37: =SUM(CN33:CN36)-61 -> 12682 | CO37: =SUM(CO33:CO36) -> 14240 | CP37: =SUM(CP33:CP36) -> 16747 | CQ37: =SUM(BO37:BR37) -> 20075
B39: U.S. Revenue Growth Y/y | AY39: =AY33/AU33-1 -> 0.086088154 | AZ39: =AZ33/AV33-1 -> 0.70132325 | BA39: =BA33/AW33-1 -> 0.15374332 | BB39: =BB33/AX33-1 -> 0.19707057 | BC39: =BC33/AY33-1 -> 0.1274572 | BD39: =BD33/AZ33-1 -> 0.074444444 | BE39: =BE33/BA33-1 -> 0.12050985 | BF39: =BF33/BB33-1 -> 0.10456062 | ... BT39: =BT33/BP33-1 -> 0.062655087 | CL39: =CL33/CK33-1 -> -0.096604888 | CM39: =CM33/CL33-1 -> 0.25290487 | CN39: =CN33/CM33-1 -> 0.10592668 | CO39: =CO33/CN33-1 -> 0.10390461 | CP39: =CP33/CO33-1 -> 0.21186944 | CQ39: =CQ33/CP33-1 -> 0.25984329
B40: Euro, Mid. East, Afr Revenue Growth Y/y | AY40: =AY34/AU34-1 -> 0.094202899 | AZ40: =AZ34/AV34-1 -> 0.59134615 | BA40: =BA34/AW34-1 -> 0.092592593 | BB40: =BB34/AX34-1 -> 0.12393888 | BC40: =BC34/AY34-1 -> 0.033112583 | BD40: =BD34/AZ34-1 -> -0.003021148 | BE40: =BE34/BA34-1 -> -0.0084745763 | BF40: =BF34/BB34-1 -> -0.0075528701 | ... BT40: =BT34/BP34-1 -> 0.061503417 | CL40: =CL34/CK34-1 -> -0.073763251 | CM40: =CM34/CL34-1 -> 0.20076299 | CN40: =CN34/CM34-1 -> 0.0031771247 | CO40: =CO34/CN34-1 -> 0.13064133 | CP40: =CP34/CO34-1 -> 0.1302521 | CQ40: =CQ34/CP34-1 -> 0.068773234
B41: A-Pac Revenue Growth Y/y | AY41: =AY35/AU35-1 -> 0.15647922 | AZ41: =AZ35/AV35-1 -> 0.26829268 | BA41: =BA35/AW35-1 -> 0.095338983 | BB41: =BB35/AX35-1 -> 0.14285714 | BC41: =BC35/AY35-1 -> 0.093023256 | BD41: =BD35/AZ35-1 -> 0.019230769 | BE41: =BE35/BA35-1 -> 0.02901354 | BF41: =BF35/BB35-1 -> -0.041071429 | ... BT41: =BT35/BP35-1 -> 0.11139241 | CL41: =CL35/CK35-1 -> -0.061643836 | CM41: =CM35/CL35-1 -> 0.16226839 | CN41: =CN35/CM35-1 -> 0.022222222 | CO41: =CO35/CN35-1 -> 0.1342155 | CP41: =CP35/CO35-1 -> 0.11916667 | CQ41: =CQ35/CP35-1 -> 0.14780343
B42: Lat Am + Canada Revenue Growth Y/y | AY42: =AY36/AU36-1 -> -0.04494382 | AZ42: =AZ36/AV36-1 -> 0.8627451 | BA42: =BA36/AW36-1 -> 0.28571429 | BB42: =BB36/AX36-1 -> 0.18888889 | BC42: =BC36/AY36-1 -> 0.25882353 | BD42: =BD36/AZ36-1 -> 0.26315789 | BE42: =BE36/BA36-1 -> 0.2020202 | BF42: =BF36/BB36-1 -> 0.14953271 | ... BT42: =BT36/BP36-1 -> 0.21893491 | CL42: =CL36/CK36-1 -> -0.22278481 | CM42: =CM36/CL36-1 -> 0.25732899 | CN42: =CN36/CM36-1 -> 0.21502591 | CO42: =CO36/CN36-1 -> 0.19189765 | CP42: =CP36/CO36-1 -> 0.11449016 | CQ42: =CQ36/CP36-1 -> 0.08988764
B43: Ttl Revenue Growth Y/y | AY43: =AY37/AU37-1 -> 0.082186394 | AZ43: =AZ37/AV37-1 -> 0.53619571 | BA43: =BA37/AW37-1 -> 0.10267018 | BB43: =BB37/AX37-1 -> 0.15472674 | BC43: =BC37/AY37-1 -> 0.099563953 | BD43: =BD37/AZ37-1 -> 0.054273643 | BE43: =BE37/BA37-1 -> 0.081173261 | BF43: =BF37/BB37-1 -> 0.036776463 | ... BT43: =BT37/BP37-1 -> 0.075281565 | CL43: =CL37/CK37-1 -> -0.076571961 | CM43: =CM37/CL37-1 -> 0.19923333 | CN43: =CN37/CM37-1 -> 0.06679004 | CO43: =CO37/CN37-1 -> 0.12285129 | CP43: =CP37/CO37-1 -> 0.17605337 | CQ43: =CQ37/CP37-1 -> 0.19872216
B45: U.S. % of Revenues | AU45: =AU33/AU37 -> 0.57097916 | AV45: =AV33/AV37 -> 0.52820769 | AW45: =AW33/AW37 -> 0.56261753 | AX45: =AX33/AX37 -> 0.55465288 | AY45: =AY33/AY37 -> 0.57303779 | AZ45: =AZ33/AZ37 -> 0.58498538 | BA45: =BA33/BA37 -> 0.58867667 | BB45: =BB33/BB37 -> 0.57499201 | ... BT45: =BT33/BT37 -> 0.62954796 | CK45: =CK33/CK37 -> 0.56795529 | CL45: =CL33/CL37 -> 0.55563402 | CM45: =CM33/CM37 -> 0.58050135 | CN45: =CN33/CN37 -> 0.60179782 | CO45: =CO33/CO37 -> 0.59164326 | CP45: =CP33/CP37 -> 0.60966143 | CQ45: =CQ33/CQ37 -> 0.6407472
B46: Euro, Mid. East, Afr % of Revenues | AU46: =AU34/AU37 -> 0.21706646 | AV46: =AV34/AV37 -> 0.20768847 | AW46: =AW34/AW37 -> 0.20308387 | AX46: =AX34/AX37 -> 0.21750369 | AY46: =AY34/AY37 -> 0.21947674 | AZ46: =AZ34/AZ37 -> 0.21514462 | BA46: =BA34/BA37 -> 0.20122783 | BB46: =BB34/BB37 -> 0.21170451 | ... BT46: =BT34/BT37 -> 0.17126057 | CK46: =CK34/CK37 -> 0.21089893 | CL46: =CL34/CL37 -> 0.2115404 | CM46: =CM34/CM37 -> 0.21181023 | CN46: =CN34/CN37 -> 0.19917994 | CO46: =CO34/CO37 -> 0.2005618 | CP46: =CP34/CP37 -> 0.19275094 | CQ46: =CQ34/CQ37 -> 0.17185554
B47: A-Pac % of Revenues | AU47: =AU35/AU37 -> 0.16083366 | AV47: =AV35/AV37 -> 0.20469296 | AW47: =AW35/AW37 -> 0.17751034 | AX47: =AX35/AX37 -> 0.18094535 | AY47: =AY35/AY37 -> 0.171875 | AZ47: =AZ35/AZ37 -> 0.16899578 | BA47: =BA35/BA37 -> 0.17633015 | BB47: =BB35/BB37 -> 0.17908539 | ... BT47: =BT35/BT37 -> 0.16133774 | CK47: =CK35/CK37 -> 0.17680484 | CL47: =CL35/CL37 -> 0.17966307 | CM47: =CM35/CM37 -> 0.17412517 | CN47: =CN35/CN37 -> 0.16685065 | CO47: =CO35/CO37 -> 0.16853933 | CP47: =CP35/CP37 -> 0.16038693 | CQ47: =CQ35/CQ37 -> 0.1535741
B48: Lat Am + Canada % of Revenues | AU48: =AU36/AU37 -> 0.034998034 | AV48: =AV36/AV37 -> 0.025461807 | AW48: =AW36/AW37 -> 0.028958255 | AX48: =AX36/AX37 -> 0.03323486 | AY48: =AY36/AY37 -> 0.030886628 | AZ48: =AZ36/AZ37 -> 0.030874228 | BA48: =BA36/BA37 -> 0.033765348 | BB48: =BB36/BB37 -> 0.0342181 | ... BT48: =BT36/BT37 -> 0.03785373 | CK48: =CK36/CK37 -> 0.036795529 | CL48: =CL36/CL37 -> 0.030969434 | CM48: =CM36/CM37 -> 0.032469717 | CN48: =CN36/CN37 -> 0.036981549 | CO48: =CO36/CO37 -> 0.039255618 | CP48: =CP36/CP37 -> 0.037200693 | CQ48: =CQ36/CQ37 -> 0.033823163
B50: Revenues | C50: 2010 | D50: 2074 | E50: 2025 | F50: 2079 | G50: 1960 | H50: 1928 | I50: 1916 | J50: 2002 | K50: 1925 | L50: 1975 | M50: 1874 | N50: 1848 | O50: 1866 | P50: 1828 | Q50: 1735 | R50: 1820 | S50: 1761 | T50: 1809 | U50: 1735 | V50: 1838 | W50: 1774 | X50: 1873 | Y50: 1846 | Z50: 1887 | AA50: 1768 | AB50: 1843 | AC50: 1888 | AD50: 1978 | AE50: 1964 | AF50: 2126 | AG50: 2105 | AH50: 2191 | AI50: 2160 | AJ50: 2257 | AK50: 2222 | AL50: 2409 | AM50: 2379 | AN50: 2490 | AO50: 2393 | AP50: 2561 | AQ50: 2493 | AR50: 2631 | AS50: 2707 | AT50: 2904 | AU50: =AU37 -> 2543 | AV50: =AV37 -> 2003 | AW50: =AW37 -> 2659 | AX50: =AX37 -> 2708 | AY50: =AY37 -> 2752 | AZ50: =AZ37 -> 3077 | BA50: =BA37 -> 2932 | BB50: =BB37 -> 3127 | ... BT50: =BT37 -> 5442 | CA50: =SUM(C50:F50) -> 8188 | CB50: =SUM(G50:J50) -> 7806 | CC50: =SUM(K50:N50) -> 7622 | CD50: =SUM(O50:R50) -> 7249 | CE50: =SUM(S50:V50) -> 7143 | CF50: =SUM(W50:Z50) -> 7380 | CG50: =SUM(AA50:AD50) -> 7477 | CH50: =SUM(AE50:AH50) -> 8386 | CI50: =SUM(AI50:AL50) -> 9048 | CJ50: =SUM(AM50:AP50) -> 9823 | CK50: =SUM(AQ50:AT50) -> 10735 | CL50: =SUM(AU50:AX50) -> 9913 | CM50: =SUM(AY50:BB50) -> 11888 | CN50: =SUM(BC50:BF50) -> 12682 | CO50: =SUM(BG50:BJ50) -> 14240 | CP50: =SUM(BK50:BN50) -> 16747 | CQ50: =SUM(BO50:BR50) -> 20075 | CR50: =CR15 -> 21718.245 | CS50: =CS15 -> 23606.829 | CT50: =CT15 -> 25635.442 | CU50: =CU15 -> 27574.214 | CV50: =CV15 -> 29447.036 | CW50: =CW15 -> 31239.876 | CX50: =CX15 -> 32935.812 | CY50: =CY15 -> 34515.185 | ... DA50: =DA15 -> 37255.194
B51: COGS | C51: 607 | D51: 630 | E51: 629 | F51: 710 | G51: 663 | H51: 654 | I51: 623 | J51: 659 | K51: 631 | L51: 688 | M51: 680 | N51: 660 | O51: 631 | P51: 578 | Q51: 558 | R51: 582 | S51: 578 | T51: 530 | U51: 510 | V51: 556 | W51: 537 | X51: 563 | Y51: 550 | Z51: 560 | AA51: 520 | AB51: 540 | AC51: 539 | AD51: 574 | AE51: 573 | AF51: 639 | AG51: 594 | AH51: 618 | AI51: 650 | AJ51: 632 | AK51: 637 | AL51: 674 | AM51: 672 | AN51: 739 | AO51: 672 | AP51: 730 | AQ51: 730 | AR51: 758 | AS51: 777 | AT51: 851 | AU51: 806 | AV51: 791 | AW51: 869 | AX51: =3465-SUM(AU51:AW51) -> 999 | AY51: 894 | AZ51: 945 | BA51: 900 | BB51: =3711-SUM(AY51:BA51) -> 972 | BC51: 955 | BD51: 1011 | BE51: 979 | BF51: =3956-SUM(BC51:BE51) -> 1011 | BG51: 1040 | BH51: 1058 | BI51: 1101 | BJ51: =4345-SUM(BG51:BI51) -> 1146 | BK51: 1209 | BL51: 1270 | BM51: 1312 | BN51: =5257-SUM(BK51:BM51) -> 1466 | BO51: 1453 | BP51: 1637 | BQ51: 1523 | BR51: 1608 | BS51: 1590 | BT51: 1594 | CA51: =SUM(C51:F51) -> 2576 | CB51: =SUM(G51:J51) -> 2599 | CC51: =SUM(K51:N51) -> 2659 | CD51: =SUM(O51:R51) -> 2349 | CE51: =SUM(S51:V51) -> 2174 | CF51: =SUM(W51:Z51) -> 2210 | CG51: =SUM(AA51:AD51) -> 2173 | CH51: =SUM(AE51:AH51) -> 2424 | CI51: =SUM(AI51:AL51) -> 2593 | CJ51: =SUM(AM51:AP51) -> 2813 | CK51: =SUM(AQ51:AT51) -> 3116 | CL51: =SUM(AU51:AX51) -> 3465 | CM51: =SUM(AY51:BB51) -> 3711 | CN51: =SUM(BC51:BF51) -> 3956 | CO51: =SUM(BG51:BJ51) -> 4345 | CP51: =SUM(BK51:BN51) -> 5257 | CQ51: =SUM(BO51:BR51) -> 6221 | CR51: =CR50*(1-CR74) -> 6906.4019 | CS51: =CS50*(1-CS74) -> 7200.0828 | CT51: =CT50*(1-CT74) -> 7741.9034 | CU51: =CU50*(1-CU74) -> 8272.2642 | CV51: =CV50*(1-CV74) -> 8760.4934 | CW51: =CW50*(1-CW74) -> 9215.7634 | CX51: =CX50*(1-CX74) -> 9633.7249 | CY51: =CY50*(1-CY74) -> 10009.404 | ... DA51: =DA50*(1-DA74) -> 10804.006
B52: GP | C52: =C50-C51 -> 1403 | D52: =D50-D51 -> 1444 | E52: =E50-E51 -> 1396 | F52: =F50-F51 -> 1369 | G52: =G50-G51 -> 1297 | H52: =H50-H51 -> 1274 | I52: =I50-I51 -> 1293 | J52: =J50-J51 -> 1343 | ... BT52: =BT50-BT51 -> 3848 | CA52: =SUM(C52:F52) -> 5612 | CB52: =SUM(G52:J52) -> 5207 | CC52: =SUM(K52:N52) -> 4963 | CD52: =SUM(O52:R52) -> 4900 | CE52: =SUM(S52:V52) -> 4969 | CF52: =SUM(W52:Z52) -> 5170 | CG52: =SUM(AA52:AD52) -> 5304 | CH52: =SUM(AE52:AH52) -> 5962 | CI52: =SUM(AI52:AL52) -> 6455 | CJ52: =SUM(AM52:AP52) -> 7010 | CK52: =SUM(AQ52:AT52) -> 7619 | CL52: =SUM(AU52:AX52) -> 6448 | CM52: =SUM(AY52:BB52) -> 8177 | CN52: =SUM(BC52:BF52) -> 8726 | CO52: =SUM(BG52:BJ52) -> 9895 | CP52: =SUM(BK52:BN52) -> 11490 | CQ52: =SUM(BO52:BR52) -> 13854 | CR52: =CR50-CR51 -> 14811.843 | CS52: =CS50-CS51 -> 16406.746 | CT52: =CT50-CT51 -> 17893.538 | CU52: =CU50-CU51 -> 19301.95 | CV52: =CV50-CV51 -> 20686.543 | CW52: =CW50-CW51 -> 22024.113 | CX52: =CX50-CX51 -> 23302.087 | CY52: =CY50-CY51 -> 24505.781 | ... DA52: =DA50-DA51 -> 26451.188
B53: SG&A | C53: 651 | D53: 671 | E53: 665 | F53: 648 | G53: 628 | H53: 634 | I53: 634 | J53: 686 | K53: 602 | L53: 649 | M53: 635 | N53: 608 | O53: 669 | P53: 649 | Q53: 569 | R53: 642 | S53: 608 | T53: 661 | U53: 658 | V53: 751 | W53: 666 | X53: 743 | Y53: 741 | Z53: 752 | AA53: 668 | AB53: 700 | AC53: 729 | AD53: 776 | AE53: 716 | AF53: 779 | AG53: 772 | AH53: 832 | AI53: 794 | AJ53: 815 | AK53: 800 | AL53: 885 | AM53: 860 | AN53: 886 | AO53: 870 | AP53: 953 | AQ53: 869 | AR53: 968 | AS53: 1012 | AT53: 1092 | AU53: 978 | AV53: 798 | AW53: 984 | AX53: =3787-SUM(AU53:AW53) -> 1027 | AY53: 1019 | AZ53: 1121 | BA53: 1066 | BB53: =4359-SUM(AY53:BA53) -> 1153 | BC53: 1060 | BD53: 1165 | BE53: 1132 | BF53: =4520-SUM(BC53:BE53) -> 1163 | BG53: 1215 | BH53: 1354 | BI53: 1242 | BJ53: =5190-SUM(BG53:BI53) -> 1379 | BK53: 1364 | BL53: 1446 | BM53: 1562 | BN53: =5984-SUM(BK53:BM53) -> 1612 | BO53: 1597 | BP53: 1716 | BQ53: 1741 | BR53: 1834 | BS53: 1781 | BT53: 1803 | CA53: =SUM(C53:F53) -> 2635 | CB53: =SUM(G53:J53) -> 2582 | CC53: =SUM(K53:N53) -> 2494 | CD53: =SUM(O53:R53) -> 2529 | CE53: =SUM(S53:V53) -> 2678 | CF53: =SUM(W53:Z53) -> 2902 | CG53: =SUM(AA53:AD53) -> 2873 | CH53: =SUM(AE53:AH53) -> 3099 | CI53: =SUM(AI53:AL53) -> 3294 | CJ53: =SUM(AM53:AP53) -> 3569 | CK53: =SUM(AQ53:AT53) -> 3941 | CL53: =SUM(AU53:AX53) -> 3787 | CM53: =SUM(AY53:BB53) -> 4359 | CN53: =SUM(BC53:BF53) -> 4520 | CO53: =SUM(BG53:BJ53) -> 5190 | CP53: =SUM(BK53:BN53) -> 5984 | CQ53: =SUM(BO53:BR53) -> 6888 | CR53: =CR50*CR75 -> 7623.104 | CS53: =CS50*CS75 -> 8238.7833 | CT53: =CT50*CT75 -> 8895.4983 | CU53: =CU50*CU75 -> 9540.678 | CV53: =CV50*CV75 -> 10159.228 | CW53: =CW50*CW75 -> 10746.517 | CX53: =CX50*CX75 -> 11296.983 | CY53: =CY50*CY75 -> 11804.193 | ... DA53: =DA50*DA75 -> 12666.766
B54: R&D | C54: 257 | D54: 280 | E54: 258 | F54: 261 | G54: 253 | H54: 232 | I54: 230 | J54: 224 | K54: 212 | L54: 223 | M54: 229 | N54: 231 | O54: 215 | P54: 213 | Q54: 220 | R54: 238 | S54: 204 | T54: 223 | U54: 217 | V54: 217 | W54: 191 | X54: 206 | Y54: 212 | Z54: 208 | AA54: 192 | AB54: 220 | AC54: 221 | AD54: 243 | AE54: 210 | AF54: 222 | AG54: 232 | AH54: 256 | AI54: 235 | AJ54: 244 | AK54: 254 | AL54: 264 | AM54: 261 | AN54: 275 | AO54: 289 | AP54: 288 | AQ54: 280 | AR54: 280 | AS54: 306 | AT54: 308 | AU54: 300 | AV54: 242 | AW54: 315 | AX54: =1143-SUM(AU54:AW54) -> 286 | AY54: 276 | AZ54: 298 | BA54: 310 | BB54: =1204-SUM(AY54:BA54) -> 320 | BC54: 319 | BD54: 335 | BE54: 339 | BF54: =1323-SUM(BC54:BE54) -> 330 | BG54: 337 | BH54: 359 | BI54: 356 | BJ54: =1414-SUM(BG54:BI54) -> 362 | BK54: 366 | BL54: 383 | BM54: 407 | BN54: =1615-SUM(BK54:BM54) -> 459 | BO54: 443 | BP54: 526 | BQ54: 514 | BR54: 569 | BS54: 516 | BT54: 554 | CA54: =SUM(C54:F54) -> 1056 | CB54: =SUM(G54:J54) -> 939 | CC54: =SUM(K54:N54) -> 895 | CD54: =SUM(O54:R54) -> 886 | CE54: =SUM(S54:V54) -> 861 | CF54: =SUM(W54:Z54) -> 817 | CG54: =SUM(AA54:AD54) -> 876 | CH54: =SUM(AE54:AH54) -> 920 | CI54: =SUM(AI54:AL54) -> 997 | CJ54: =SUM(AM54:AP54) -> 1113 | CK54: =SUM(AQ54:AT54) -> 1174 | CL54: =SUM(AU54:AX54) -> 1143 | CM54: =SUM(AY54:BB54) -> 1204 | CN54: =SUM(BC54:BF54) -> 1323 | CO54: =SUM(BG54:BJ54) -> 1414 | CP54: =SUM(BK54:BN54) -> 1615 | CQ54: =SUM(BO54:BR54) -> 2052 | CR54: =CR50*(CR76) -> 2258.6975 | CS54: =CS50*(CS76) -> 2549.5375 | CT54: =CT50*(CT76) -> 2819.8986 | CU54: =CU50*(CU76) -> 3088.312 | CV54: =CV50*(CV76) -> 3356.9622 | CW54: =CW50*(CW76) -> 3530.106 | CX54: =CX50*(CX76) -> 3688.8109 | CY54: =CY50*(CY76) -> 3831.1855 | ... DA54: =DA50*(DA76) -> 4060.8162
B55: Royalties | AU55: 12 | AV55: 8 | AW55: 12 | AX55: =45-SUM(AU55:AW55) -> 13 | AY55: 12 | AZ55: 12 | BA55: 14 | BB55: =49-SUM(AY55:BA55) -> 11 | BC55: 12 | BD55: 11 | BE55: 11 | BF55: =47-SUM(BC55:BE55) -> 13 | BG55: 11 | BH55: 12 | BI55: 11 | BJ55: =46-SUM(BG55:BI55) -> 12 | BK55: 10 | BL55: 9 | BM55: 5 | BN55: =33-SUM(BK55:BM55) -> 9 | BO55: 14 | BP55: 14 | BQ55: 12 | BR55: 6 | BS55: 12 | BT55: 12 | CA55: 0 | CB55: 0 | CC55: 0 | CD55: 0 | CE55: 0 | CF55: 0 | CG55: 0 | CH55: 0 | CI55: 0 | CJ55: 0 | CK55: 0 | CL55: =SUM(AU55:AX55) -> 45 | CM55: =SUM(AY55:BB55) -> 49 | CN55: =SUM(BC55:BF55) -> 47 | CO55: =SUM(BG55:BJ55) -> 46 | CP55: =SUM(BK55:BN55) -> 33 | CQ55: =SUM(BO55:BR55) -> 46 | CR55: =CQ55*1.035 -> 47.61 | CS55: =CR55*1.035 -> 49.27635 | CT55: =CS55*1.035 -> 51.001022 | CU55: =CT55*1.035 -> 52.786058 | CV55: =CU55*1.035 -> 54.63357 | CW55: =CV55*1.035 -> 56.545745 | CX55: =CW55*1.035 -> 58.524846 | CY55: =CX55*1.035 -> 60.573216 | ... DA55: =CZ55*1.035 -> 64.887543
B56: Amortization | AU56: 201 | AV56: 197 | AW56: 197 | AX56: =789-SUM(AU56:AW56) -> 194 | AY56: 185 | AZ56: 180 | BA56: 184 | BB56: =741-SUM(AY56:BA56) -> 192 | BC56: 198 | BD56: 204 | BE56: 202 | BF56: =803-SUM(BC56:BE56) -> 199 | BG56: 203 | BH56: 210 | BI56: 208 | BJ56: =828-SUM(BG56:BI56) -> 207 | BK56: 214 | BL56: 213 | BM56: 205 | BN56: =856-SUM(BK56:BM56) -> 224 | BO56: 219 | BP56: 225 | BQ56: 225 | BR56: 228 | BS56: 232 | BT56: 233 | CA56: 0 | CB56: 0 | CC56: 0 | CD56: 0 | CE56: 0 | CF56: 0 | CG56: 0 | CH56: 0 | CI56: 0 | CJ56: 0 | CK56: 0 | CL56: =SUM(AU56:AX56) -> 789 | CM56: =SUM(AY56:BB56) -> 741 | CN56: =SUM(BC56:BF56) -> 803 | CO56: =SUM(BG56:BJ56) -> 828 | CP56: =SUM(BK56:BN56) -> 856 | CQ56: =SUM(BO56:BR56) -> 897 | CR56: =CQ56*1.025 -> 919.425 | CS56: =CR56*1.025 -> 942.41062 | CT56: =CS56*1.025 -> 965.97089 | CU56: =CT56*1.025 -> 990.12016 | CV56: =CU56*1.025 -> 1014.8732 | CW56: =CV56*1.025 -> 1040.245 | CX56: =CW56*1.025 -> 1066.2511 | CY56: =CX56*1.025 -> 1092.9074 | ... DA56: =CZ56*1.025 -> 1148.2358
B57: Intangible Asset Impairment | AU57: 198 | AV57: 34 | AW57: 219 | AX57: =460-SUM(AU57:AW57) -> 9 | AY57: -6 | AZ57: 45 | BA57: 128 | BB57: =370-SUM(AY57:BA57) -> 203 | BC57: 12 | BD57: 7 | BE57: 125 | BF57: =132-SUM(BC57:BE57) -> -12 | BG57: 0 | BH57: 57 | BI57: 1 | BJ57: =58-SUM(BG57:BI57) -> 0 | BK57: 17 | BL57: 276 | BM57: 0 | BN57: =386-SUM(BK57:BM57) -> 93 | BO57: 0 | BP57: 46 | BQ57: 0 | BR57: 0 | BS57: 0 | BT57: 0 | CA57: 0 | CB57: 0 | CC57: 0 | CD57: 0 | CE57: 0 | CF57: 0 | CG57: 0 | CH57: 0 | CI57: 0 | CJ57: 0 | CK57: 0 | CL57: =SUM(AU57:AX57) -> 460 | CM57: =SUM(AY57:BB57) -> 370 | CN57: =SUM(BC57:BF57) -> 132 | CO57: =SUM(BG57:BJ57) -> 58 | CP57: =SUM(BK57:BN57) -> 386 | CQ57: =SUM(BO57:BR57) -> 46 | CR57: =CQ57*1.03 -> 47.38 | CS57: =CR57*1.03 -> 48.8014 | CT57: =CS57*1.03 -> 50.265442 | CU57: =CT57*1.03 -> 51.773405 | CV57: =CU57*1.03 -> 53.326607 | CW57: =CV57*1.03 -> 54.926406 | CX57: =CW57*1.03 -> 56.574198 | CY57: =CX57*1.03 -> 58.271424 | ... DA57: =CZ57*1.03 -> 61.820153
B58: Contingent Consideration | AU58: -108 | AV58: 0 | AW58: 6 | AX58: =-100-SUM(AU58:AW58) -> 2 | AY58: 5 | AZ58: -85 | BA58: -26 | BB58: =-136-SUM(AY58:BA58) -> -30 | BC58: 4 | BD58: 36 | BE58: 20 | BF58: =35-SUM(BC58:BE58) -> -25 | BG58: 0 | BH58: 19 | BI58: 11 | BJ58: =58-SUM(BG58:BI58) -> 28 | BK58: 0 | BL58: 2 | BM58: -23 | BN58: =-5-SUM(BK58:BM58) -> 16 | BO58: 6 | BP58: -5 | BQ58: 11 | BR58: 6 | BS58: -30 | BT58: -16 | CA58: 0 | CB58: 0 | CC58: 0 | CD58: 0 | CE58: 0 | CF58: 0 | CG58: 0 | CH58: 0 | CI58: 0 | CJ58: 0 | CK58: 0 | CL58: =SUM(AU58:AX58) -> -100 | CM58: =SUM(AY58:BB58) -> -136 | CN58: =SUM(BC58:BF58) -> 35 | CO58: =SUM(BG58:BJ58) -> 58 | CP58: =SUM(BK58:BN58) -> -5 | CQ58: =SUM(BO58:BR58) -> 18 | CR58: 0 | CS58: 0 | CT58: 0 | CU58: 0 | CV58: 0 | CW58: 0 | CX58: 0 | CY58: 0 | CZ58: 0 | DA58: 0
B59: Restructuring Charges | AU59: 10 | AV59: 4 | AW59: 2 | AX59: =52-SUM(AU59:AW59) -> 36 | AY59: 3 | AZ59: 3 | BA59: 9 | BB59: =40-SUM(AY59:BA59) -> 25 | BC59: 0 | BD59: 10 | BE59: 4 | BF59: =24-SUM(BC59:BE59) -> 10 | BG59: 11 | BH59: 16 | BI59: 15 | BJ59: =69-SUM(BG59:BI59) -> 27 | BK59: 2 | BL59: 1 | BM59: 8 | BN59: =16-SUM(BK59:BM59) -> 5 | BO59: 10 | BP59: 83 | BQ59: -9 | BR59: 16 | BS59: 2 | BT59: 8 | CA59: 0 | CB59: 0 | CC59: 0 | CD59: 0 | CE59: 0 | CF59: 0 | CG59: 0 | CH59: 0 | CI59: 0 | CJ59: 0 | CK59: 0 | CL59: =SUM(AU59:AX59) -> 52 | CM59: =SUM(AY59:BB59) -> 40 | CN59: =SUM(BC59:BF59) -> 24 | CO59: =SUM(BG59:BJ59) -> 69 | CP59: =SUM(BK59:BN59) -> 16 | CQ59: =SUM(BO59:BR59) -> 100 | CR59: 0 | CS59: 0 | CT59: 0 | CU59: 0 | CV59: 0 | CW59: 0 | CX59: 0 | CY59: 0 | CZ59: 0 | DA59: 0
B60: Litigation-Related net Charges | AU60: 0 | AV60: 0 | AW60: 260 | AX60: =278-SUM(AU60:AW60) -> 18 | AY60: -6 | AZ60: 298 | BA60: 0 | BB60: =430-SUM(AY60:BA60) -> 138 | BC60: 0 | BD60: 42 | BE60: 0 | BF60: =173-SUM(BC60:BE60) -> 131 | BG60: 20 | BH60: 0 | BI60: -111 | BJ60: =-111-SUM(BG60:BI60) -> -20 | BK60: 0 | BL60: 0 | BM60: 0 | BN60: =0-SUM(BK60:BM60) -> 0 | BO60: 0 | BP60: 0 | BQ60: 0 | BR60: 194 | BS60: 0 | BT60: 76 | CA60: 0 | CB60: 0 | CC60: 0 | CD60: 0 | CE60: 0 | CF60: 0 | CG60: 0 | CH60: 0 | CI60: 0 | CJ60: 0 | CK60: 0 | CL60: =SUM(AU60:AX60) -> 278 | CM60: =SUM(AY60:BB60) -> 430 | CN60: =SUM(BC60:BF60) -> 173 | CO60: =SUM(BG60:BJ60) -> -111 | CP60: =SUM(BK60:BN60) -> 0 | CQ60: =SUM(BO60:BR60) -> 194 | CR60: 0 | CS60: 0 | CT60: 0 | CU60: 0 | CV60: 0 | CW60: 0 | CX60: 0 | CY60: 0 | CZ60: 0 | DA60: 0
B61: Loss on Disposal of Assets | AU61: 0 | AV61: 0 | AW61: 0 | AX61: =74-SUM(AU61:AW61) -> 74 | AY61: 0 | AZ61: -2 | BA61: -40 | BB61: =-78-SUM(AY61:BA61) -> -36 | BC61: 0 | BD61: 0 | BE61: 0 | BF61: =22-SUM(BC61:BE61) -> 22 | BG61: 0 | BH61: 0 | BI61: 0 | BJ61: =0-SUM(BG61:BI61) -> 0 | BK61: 0 | BL61: 0 | BM61: 0 | BN61: =0-SUM(BK61:BM61) -> 0 | BO61: 0 | BP61: 0 | BQ61: 0 | BR61: 0 | BS61: 0 | BT61: 0 | CA61: 0 | CB61: 0 | CC61: 0 | CD61: 0 | CE61: 0 | CF61: 0 | CG61: 0 | CH61: 0 | CI61: 0 | CJ61: 0 | CK61: 0 | CL61: =SUM(AU61:AX61) -> 74 | CM61: =SUM(AY61:BB61) -> -78 | CN61: =SUM(BC61:BF61) -> 22 | CO61: =SUM(BG61:BJ61) -> 0 | CP61: =SUM(BK61:BN61) -> 0 | CQ61: =SUM(BO61:BR61) -> 0 | CR61: 0 | CS61: 0 | CT61: 0 | CU61: 0 | CV61: 0 | CW61: 0 | CX61: 0 | CY61: 0 | CZ61: 0 | DA61: 0
B62: Operating Income | C62: 11 | D62: 275 | E62: 51 | F62: -1231 | G62: -1486 | H62: 231 | I62: 251 | J62: 348 | K62: 322 | L62: 237 | M62: 174 | N62: 171 | O62: 196 | P62: -3587 | Q62: -594 | R62: 117 | S62: -330 | T62: 220 | U62: 103 | V62: 127 | W62: 197 | X62: -69 | Y62: 64 | Z62: -493 | AA62: 24 | AB62: 219 | AC62: -299 | AD62: -227 | AE62: 293 | AF62: -334 | AG62: 348 | AH62: 140 | AI62: 364 | AJ62: 225 | AK62: 377 | AL62: 319 | AM62: 407 | AN62: 392 | AO62: 388 | AP62: 319 | AQ62: 541 | AR62: 384 | AS62: 383 | AT62: 210 | AU62: =AU52-SUM(AU53:AU61) -> 146 | AV62: =AV52-SUM(AV53:AV61) -> -71 | AW62: =AW52-SUM(AW53:AW61) -> -205 | AX62: =AX52-SUM(AX53:AX61) -> 50 | AY62: =AY52-SUM(AY53:AY61) -> 370 | AZ62: =AZ52-SUM(AZ53:AZ61) -> 262 | BA62: =BA52-SUM(BA53:BA61) -> 387 | BB62: =BB52-SUM(BB53:BB61) -> 179 | ... BT62: =BT52-SUM(BT53:BT61) -> 1178 | CA62: =SUM(C62:F62) -> -894 | CB62: =SUM(G62:J62) -> -656 | CC62: =SUM(K62:N62) -> 904 | CD62: =SUM(O62:R62) -> -3868 | CE62: =SUM(S62:V62) -> 120 | CF62: =SUM(W62:Z62) -> -301 | CG62: =SUM(AA62:AD62) -> -283 | CH62: =SUM(AE62:AH62) -> 447 | CI62: =SUM(AI62:AL62) -> 1285 | CJ62: =SUM(AM62:AP62) -> 1506 | CK62: =SUM(AQ62:AT62) -> 1518 | CL62: =SUM(AU62:AX62) -> -80 | CM62: =SUM(AY62:BB62) -> 1198 | CN62: =SUM(BC62:BF62) -> 1647 | CO62: =SUM(BG62:BJ62) -> 2343 | CP62: =SUM(BK62:BN62) -> 2605 | CQ62: =SUM(BO62:BR62) -> 3613 | CR62: =CR52-SUM(CR53:CR61) -> 3915.6266 | CS62: =CS52-SUM(CS53:CS61) -> 4577.9369 | CT62: =CT52-SUM(CT53:CT61) -> 5110.9041 | CU62: =CU52-SUM(CU53:CU61) -> 5578.2801 | CV62: =CV52-SUM(CV53:CV61) -> 6047.52 | CW62: =CW52-SUM(CW53:CW61) -> 6595.7721 | CX62: =CX52-SUM(CX53:CX61) -> 7134.9423 | CY62: =CY52-SUM(CY53:CY61) -> 7658.6505 | ... DA62: =DA52-SUM(DA53:DA61) -> 8448.6621
B63: Interest Income (Expenses) | AU63: -88 | AV63: -91 | AW63: -86 | AX63: =-361-SUM(AU63:AW63) -> -96 | AY63: -82 | AZ63: -86 | BA63: -86 | BB63: =-341-SUM(AY63:BA63) -> -87 | BC63: -279 | BD63: -64 | BE63: -63 | BF63: =-470-SUM(BC63:BE63) -> -64 | BG63: -65 | BH63: -70 | BI63: -66 | BJ63: =-265-SUM(BG63:BI63) -> -64 | BK63: -69 | BL63: -77 | BM63: -79 | BN63: =-305-SUM(BK63:BM63) -> -80 | BO63: -82 | BP63: -90 | BQ63: -87 | BR63: -90 | BS63: -90 | BT63: -96 | CA63: 0 | CB63: 0 | CC63: 0 | CD63: 0 | CE63: 0 | CF63: 0 | CG63: 0 | CH63: 0 | CI63: 0 | CJ63: 0 | CK63: 0 | CL63: =SUM(AU63:AX63) -> -361 | CM63: =SUM(AY63:BB63) -> -341 | CN63: =SUM(BC63:BF63) -> -470 | CO63: =SUM(BG63:BJ63) -> -265 | CP63: =SUM(BK63:BN63) -> -305 | CQ63: =SUM(BO63:BR63) -> -349 | CR63: =-CQ98*($DF$98) -> -861.5675 | CS63: =-CR98*($DF$98) -> -794.79602 | CT63: =-CS98*($DF$98) -> -733.19933 | CU63: =-CT98*($DF$98) -> -676.37638 | CV63: =-CU98*($DF$98) -> -623.95721 | CW63: =-CV98*($DF$98) -> -575.60053 | CX63: =-CW98*($DF$98) -> -530.99149 | CY63: =-CX98*($DF$98) -> -489.83965 | ... DA63: =-CZ98*($DF$98) -> -416.8566
B64: Other Income | C64: -108 | D64: -95 | E64: -95 | F64: -116 | G64: -89 | H64: -112 | I64: -88 | J64: -118 | K64: -49 | L64: -79 | M64: -63 | N64: -71 | O64: -73 | P64: -31 | Q64: -69 | R64: -66 | S64: -64 | T64: -68 | U64: -143 | V64: -68 | W64: -51 | X64: -35 | Y64: -61 | Z64: -61 | AA64: -75 | AB64: -114 | AC64: -68 | AD64: -110 | AE64: -65 | AF64: -63 | AG64: -91 | AH64: -51 | AI64: -59 | AJ64: -134 | AK64: -68 | AL64: -92 | AM64: -84 | AN64: -45 | AO64: 68 | AP64: -24 | AQ64: -84 | AR64: -239 | AS64: -292 | AT64: -216 | AU64: -36 | AV64: -18 | AW64: 64 | AX64: =362-SUM(AU64:AW64) -> 352 | AY64: 37 | AZ64: -27 | BA64: 181 | BB64: =218-SUM(AY64:BA64) -> 27 | BC64: -31 | BD64: -14 | BE64: -50 | BF64: =-38-SUM(BC64:BE64) -> 57 | BG64: -43 | BH64: -18 | BI64: -17 | BJ64: =-93-SUM(BG64:BI64) -> -15 | BK64: 2 | BL64: -23 | BM64: 14 | BN64: =-16-SUM(BK64:BM64) -> -9 | BO64: -34 | BP64: 213 | BQ64: -22 | BR64: -35 | BS64: 151 | BT64: -22 | CA64: =SUM(C64:F64) -> -414 | CB64: =SUM(G64:J64) -> -407 | CC64: =SUM(K64:N64) -> -262 | CD64: =SUM(O64:R64) -> -239 | CE64: =SUM(S64:V64) -> -343 | CF64: =SUM(W64:Z64) -> -208 | CG64: =SUM(AA64:AD64) -> -367 | CH64: =SUM(AE64:AH64) -> -270 | CI64: =SUM(AI64:AL64) -> -353 | CJ64: =SUM(AM64:AP64) -> -85 | CK64: =SUM(AQ64:AT64) -> -831 | CL64: =SUM(AU64:AX64) -> 362 | CM64: =SUM(AY64:BB64) -> 218 | CN64: =SUM(BC64:BF64) -> -38 | CO64: =SUM(BG64:BJ64) -> -93 | CP64: =SUM(BK64:BN64) -> -16 | CQ64: =SUM(BO64:BR64) -> 122 | CR64: =CQ81*($DK$81) -> 121.125 | CS64: =CR81*($DK$81) -> 369.98006 | CT64: =CS81*($DK$81) -> 693.50818 | CU64: =CT81*($DK$81) -> 1087.3513 | CV64: =CU81*($DK$81) -> 1551.0693 | CW64: =CV81*($DK$81) -> 2089.4237 | CX64: =CW81*($DK$81) -> 2715.3831 | CY64: =CX81*($DK$81) -> 3434.7192 | ... DA64: =CZ81*($DK$81) -> 5169.9001
B65: Pretax Income | C65: =C62+C63+C64 -> -97 | D65: =D62+D63+D64 -> 180 | E65: =E62+E63+E64 -> -44 | F65: =F62+F63+F64 -> -1347 | G65: =G62+G63+G64 -> -1575 | H65: =H62+H63+H64 -> 119 | I65: =I62+I63+I64 -> 163 | J65: =J62+J63+J64 -> 230 | ... BT65: =BT62+BT63+BT64 -> 1060 | CA65: =SUM(C65:F65) -> -1308 | CB65: =SUM(G65:J65) -> -1063 | CC65: =SUM(K65:N65) -> 642 | CD65: =SUM(O65:R65) -> -4107 | CE65: =SUM(S65:V65) -> -223 | CF65: =SUM(W65:Z65) -> -509 | CG65: =SUM(AA65:AD65) -> -650 | CH65: =SUM(AE65:AH65) -> 177 | CI65: =SUM(AI65:AL65) -> 932 | CJ65: =SUM(AM65:AP65) -> 1421 | CK65: =SUM(AQ65:AT65) -> 687 | CL65: =SUM(AU65:AX65) -> -79 | CM65: =SUM(AY65:BB65) -> 1075 | CN65: =SUM(BC65:BF65) -> 1139 | CO65: =SUM(BG65:BJ65) -> 1985 | CP65: =SUM(BK65:BN65) -> 2284 | CQ65: =SUM(BO65:BR65) -> 3386 | CR65: =CR62+SUM(CR63:CR64) -> 3175.1841 | CS65: =CS62+SUM(CS63:CS64) -> 4153.121 | CT65: =CT62+SUM(CT63:CT64) -> 5071.213 | CU65: =CU62+SUM(CU63:CU64) -> 5989.255 | CV65: =CV62+SUM(CV63:CV64) -> 6974.6322 | CW65: =CW62+SUM(CW63:CW64) -> 8109.5953 | CX65: =CX62+SUM(CX63:CX64) -> 9319.3339 | CY65: =CY62+SUM(CY63:CY64) -> 10603.53 | ... DA65: =DA62+SUM(DA63:DA64) -> 13201.706
B66: Taxes | C66: -84 | D66: 22 | E66: 50 | F66: -271 | G66: 14 | H66: 21 | I66: -27 | J66: -6 | K66: 227 | L66: 12 | M66: -31 | N66: -7 | O66: 10 | P66: -40 | Q66: 1 | R66: -10 | S66: -40 | T66: 22 | U66: -35 | V66: -49 | W66: 13 | X66: -108 | Y66: -40 | Z66: -255 | AA66: -50 | AB66: 3 | AC66: -169 | AD66: -195 | AE66: 26 | AF66: -190 | AG66: 29 | AH66: -35 | AI66: 15 | AJ66: -55 | AK66: 26 | AL66: 842 | AM66: 26 | AN66: -209 | AO66: 24 | AP66: -90 | AQ66: 33 | AR66: -9 | AS66: -35 | AT66: -4002 | AU66: 11 | AV66: -33 | AW66: -72 | AX66: =2-SUM(AU66:AW66) -> 96 | AY66: -16 | AZ66: -37 | BA66: 63 | BB66: =36-SUM(AY66:BA66) -> 26 | BC66: 45 | BD66: 85 | BE66: 57 | BF66: =443-SUM(BC66:BE66) -> 256 | BG66: 130 | BH66: 156 | BI66: 106 | BJ66: =393-SUM(BG66:BI66) -> 1 | BK66: 115 | BL66: 98 | BM66: 200 | BN66: =436-SUM(BK66:BM66) -> 23 | BO66: 133 | BP66: 146 | BQ66: 184 | BR66: 30 | BS66: -177 | BT66: 155 | CA66: =SUM(C66:F66) -> -283 | CB66: =SUM(G66:J66) -> 2 | CC66: =SUM(K66:N66) -> 201 | CD66: =SUM(O66:R66) -> -39 | CE66: =SUM(S66:V66) -> -102 | CF66: =SUM(W66:Z66) -> -390 | CG66: =SUM(AA66:AD66) -> -411 | CH66: =SUM(AE66:AH66) -> -170 | CI66: =SUM(AI66:AL66) -> 828 | CJ66: =SUM(AM66:AP66) -> -249 | CK66: =SUM(AQ66:AT66) -> -4013 | CL66: =SUM(AU66:AX66) -> 2 | CM66: =SUM(AY66:BB66) -> 36 | CN66: =SUM(BC66:BF66) -> 443 | CO66: =SUM(BG66:BJ66) -> 393 | CP66: =SUM(BK66:BN66) -> 436 | CQ66: =SUM(BO66:BR66) -> 493 | CR66: =CR65*CR78 -> 555.65722 | CS66: =CS65*CS78 -> 747.56177 | CT66: =CT65*CT78 -> 925.49637 | CU66: =CU65*CU78 -> 1108.0122 | CV66: =CV65*CV78 -> 1307.7435 | CW66: =CW65*CW78 -> 1520.5491 | CX66: =CX65*CX78 -> 1747.3751 | CY66: =CY65*CY78 -> 1988.1619 | ... DA66: =DA65*DA78 -> 2475.3198
B67: Net Income | C67: =C65-C66 -> -13 | D67: =D65-D66 -> 158 | E67: =E65-E66 -> -94 | F67: =F65-F66 -> -1076 | G67: =G65-G66 -> -1589 | H67: =H65-H66 -> 98 | I67: =I65-I66 -> 190 | J67: =J65-J66 -> 236 | ... BT67: =BT65-BT66 -> 905 | CA67: =SUM(C67:F67) -> -1025 | CB67: =SUM(G67:J67) -> -1065 | CC67: =SUM(K67:N67) -> 441 | CD67: =SUM(O67:R67) -> -4068 | CE67: =SUM(S67:V67) -> -121 | CF67: =SUM(W67:Z67) -> -119 | CG67: =SUM(AA67:AD67) -> -239 | CH67: =SUM(AE67:AH67) -> 347 | CI67: =SUM(AI67:AL67) -> 104 | CJ67: =SUM(AM67:AP67) -> 1670 | CK67: =SUM(AQ67:AT67) -> 4700 | CL67: =SUM(AU67:AX67) -> -81 | CM67: =SUM(AY67:BB67) -> 1039 | CN67: =SUM(BC67:BF67) -> 696 | CO67: =SUM(BG67:BJ67) -> 1592 | CP67: =SUM(BK67:BN67) -> 1848 | CQ67: =SUM(BO67:BR67) -> 2893 | CR67: =CR65-CR66 -> 2619.5269 | CS67: =CS65-CS66 -> 3405.5592 | CT67: =CT65-CT66 -> 4145.7166 | CU67: =CU65-CU66 -> 4881.2428 | CV67: =CV65-CV66 -> 5666.8886 | CW67: =CW65-CW66 -> 6589.0462 | CX67: =CX65-CX66 -> 7571.9588 | CY67: =CY65-CY66 -> 8615.3682 | ... DA67: =DA65-DA66 -> 10726.386
B68: Preferred Stock Obligation | C68: 0 | D68: 0 | E68: 0 | F68: 0 | G68: 0 | H68: 0 | I68: 0 | J68: 0 | K68: 0 | L68: 0 | M68: 0 | N68: 0 | O68: 0 | P68: 0 | Q68: 0 | R68: 0 | S68: 0 | T68: 0 | U68: 0 | V68: 0 | W68: 0 | X68: 0 | Y68: 0 | Z68: 0 | AA68: 0 | AB68: 0 | AC68: 0 | AD68: 0 | AE68: 0 | AF68: 0 | AG68: 0 | AH68: 0 | AI68: 0 | AJ68: 0 | AK68: 0 | AL68: 0 | AM68: 0 | AN68: 0 | AO68: 0 | AP68: 0 | AQ68: 0 | AR68: 0 | AS68: 0 | AT68: 0 | AU68: 0 | AV68: -5 | AW68: -14 | AX68: =-33-SUM(AU68:AW68) -> -14 | AY68: -14 | AZ68: -14 | BA68: -14 | BB68: =-55-SUM(AY68:BA68) -> -13 | BC68: -14 | BD68: -14 | BE68: -14 | BF68: =-55-SUM(BC68:BE68) -> -13 | BG68: -14 | BH68: -9 | BI68: 0 | BJ68: =-23-SUM(BG68:BI68) -> 0 | BK68: 0 | BL68: 0 | BM68: 0 | BN68: =0-SUM(BK68:BM68) -> 0 | BO68: 0 | BP68: 0 | BQ68: 0 | BR68: 0 | BS68: 0 | BT68: 0 | CA68: 0 | CB68: 0 | CC68: 0 | CD68: 0 | CE68: 0 | CF68: 0 | CG68: 0 | CH68: 0 | CI68: 0 | CJ68: 0 | CK68: 0 | CL68: =SUM(AU68:AX68) -> -33 | CM68: =SUM(AY68:BB68) -> -55 | CN68: =SUM(BC68:BF68) -> -55 | CO68: =SUM(BG68:BJ68) -> -23 | CP68: =SUM(BK68:BN68) -> 0 | CQ68: =SUM(BO68:BR68) -> 0 | CR68: 0 | CS68: 0 | CT68: 0 | CU68: 0 | CV68: 0 | CW68: 0 | CX68: 0 | CY68: 0 | CZ68: 0 | DA68: 0
B69: Net Income Attr to Non-Cont | C69: 0 | D69: 0 | E69: 0 | F69: 0 | G69: 0 | H69: 0 | I69: 0 | J69: 0 | K69: 0 | L69: 0 | M69: 0 | N69: 0 | O69: 0 | P69: 0 | Q69: 0 | R69: 0 | S69: 0 | T69: 0 | U69: 0 | V69: 0 | W69: 0 | X69: 0 | Y69: 0 | Z69: 0 | AA69: 0 | AB69: 0 | AC69: 0 | AD69: 0 | AE69: 0 | AF69: 0 | AG69: 0 | AH69: 0 | AI69: 0 | AJ69: 0 | AK69: 0 | AL69: 0 | AM69: 0 | AN69: 0 | AO69: 0 | AP69: 0 | AQ69: 0 | AR69: 0 | AS69: 0 | AT69: 0 | AU69: 0 | AV69: 0 | AW69: 0 | AX69: 0 | AY69: 0 | AZ69: 0 | BA69: 0 | BB69: 0 | BC69: 0 | BD69: 0 | BE69: 0 | BF69: 0 | BG69: 0 | BH69: 0 | BI69: 0 | BJ69: 0 | BK69: -2 | BL69: -2 | BM69: 0 | BN69: =-4-SUM(BK69:BM69) -> 0 | BO69: -2 | BP69: -1 | BQ69: 0 | BR69: -2 | BS69: -2 | BT69: -2 | CA69: 0 | CB69: 0 | CC69: 0 | CD69: 0 | CE69: 0 | CF69: 0 | CG69: 0 | CH69: 0 | CI69: 0 | CJ69: 0 | CK69: 0 | CL69: =SUM(AU69:AX69) -> 0 | CM69: =SUM(AY69:BB69) -> 0 | CN69: =SUM(BC69:BF69) -> 0 | CO69: =SUM(BG69:BJ69) -> 0 | CP69: =SUM(BK69:BN69) -> -4 | CQ69: =SUM(BO69:BR69) -> -5 | CR69: 0 | CS69: 0 | CT69: 0 | CU69: 0 | CV69: 0 | CW69: 0 | CX69: 0 | CY69: 0 | CZ69: 0 | DA69: 0
B70: Net Income Attr to BSX | C70: =C67+C68-C69 -> -13 | D70: =D67+D68-D69 -> 158 | E70: =E67+E68-E69 -> -94 | F70: =F67+F68-F69 -> -1076 | G70: =G67+G68-G69 -> -1589 | H70: =H67+H68-H69 -> 98 | I70: =I67+I68-I69 -> 190 | J70: =J67+J68-J69 -> 236 | ... BT70: =BT67+BT68-BT69 -> 907 | CA70: =SUM(AJ70:AM70) -> 111 | CB70: =SUM(AK70:AN70) -> 521 | CC70: =SUM(AL70:AO70) -> 670 | CD70: =SUM(AM70:AP70) -> 1670 | CE70: =SUM(AN70:AQ70) -> 1797 | CF70: =SUM(AO70:AR70) -> 1395 | CG70: =SUM(AP70:AS70) -> 1089 | CH70: =SUM(AQ70:AT70) -> 4700 | ... CL70: =SUM(AU70:AX70) -> -114 | CM70: =SUM(AY70:BB70) -> 984 | CN70: =SUM(BC70:BF70) -> 641 | CO70: =SUM(BG70:BJ70) -> 1569 | CP70: =SUM(BK70:BN70) -> 1852 | CQ70: =SUM(BO70:BR70) -> 2898 | CR70: =CR67-SUM(CR68:CR69) -> 2619.5269 | CS70: =CS67-SUM(CS68:CS69) -> 3405.5592 | CT70: =CT67-SUM(CT68:CT69) -> 4145.7166 | CU70: =CU67-SUM(CU68:CU69) -> 4881.2428 | CV70: =CV67-SUM(CV68:CV69) -> 5666.8886 | CW70: =CW67-SUM(CW68:CW69) -> 6589.0462 | CX70: =CX67-SUM(CX68:CX69) -> 7571.9588 | CY70: =CY67-SUM(CY68:CY69) -> 8615.3682 | ... DA70: =DA67-SUM(DA68:DA69) -> 10726.386 | DB70: =DA70*(1+$DK$82) -> 10914.098 | DC70: =DB70*(1+$DK$82) -> 11105.094 | DD70: =DC70*(1+$DK$82) -> 11299.433 | DE70: =DD70*(1+$DK$82) -> 11497.173 | DF70: =DE70*(1+$DK$82) -> 11698.374 | DG70: =DF70*(1+$DK$82) -> 11903.096 | DH70: =DG70*(1+$DK$82) -> 12111.4 | DI70: =DH70*(1+$DK$82) -> 12323.349 | ... EO70: =EN70*(1+$DK$82) -> 21469.905
B71: SC | C71: 1504 | D71: 1507 | E71: 1509 | F71: 1507 | G71: 1515 | H71: 1516 | I71: 1519 | J71: 1517 | K71: 1527 | L71: 1529 | M71: 1514 | N71: 1509 | O71: 1445 | P71: 1423 | Q71: 1393 | R71: 1407 | S71: 1352 | T71: 1344 | U71: 1340 | V71: 1341 | W71: 1322 | X71: 1323 | Y71: 1326 | Z71: 1324 | AA71: 1334 | AB71: 1341 | AC71: 1344 | AD71: 1341 | AE71: 1350 | AF71: 1357 | AG71: 1361 | AH71: 1358 | AI71: 1365 | AJ71: 1370 | AK71: 1372 | AL71: 1370 | AM71: 1377 | AN71: 1381 | AO71: 1383 | AP71: 1381 | AQ71: 1388 | AR71: 1391 | AS71: 1393 | AT71: 1392 | AU71: 1397.4 | AV71: 1410.9 | AW71: 1430.9 | AX71: 1416.7 | AY71: 1418.7 | AZ71: 1421.3 | BA71: 1423.8 | BB71: 1422.3 | BC71: 1427.8 | BD71: 1429.7 | BE71: 1431.6 | BF71: 1430.5 | BG71: 1435.8 | BH71: 1446.2 | BI71: 1464.5 | BJ71: 1453 | BK71: 1468.4 | BL71: 1470.6 | BM71: 1472.7 | BN71: 1471.5 | BO71: 1477.2 | BP71: 1479.9 | BQ71: 1481.7 | BR71: 1482.7 | BS71: 1484.9 | BT71: 1470.2 | CA71: =F71 -> 1507 | CB71: =J71 -> 1517 | CC71: =N71 -> 1509 | CD71: =R71 -> 1407 | CE71: =V71 -> 1341 | CF71: =Z71 -> 1324 | CG71: =AD71 -> 1341 | CH71: =AH71 -> 1358 | CI71: =AL71 -> 1370 | CJ71: =AP71 -> 1381 | CK71: =AT71 -> 1392 | CL71: =AX71 -> 1416.7 | CM71: =BB71 -> 1422.3 | CN71: =BF71 -> 1430.5 | CO71: =BJ71 -> 1453 | CP71: =BN71 -> 1471.5 | CQ71: =AVERAGE(BO71:BR71) -> 1480.375
B72: EPS | C72: =C70/C71 -> -0.008643617 | D72: =D70/D71 -> 0.10484406 | E72: =E70/E71 -> -0.062292909 | F72: =F70/F71 -> -0.71400133 | G72: =G70/G71 -> -1.0488449 | H72: =H70/H71 -> 0.064643799 | I72: =I70/I71 -> 0.12508229 | J72: =J70/J71 -> 0.1555702 | ... BT72: =BT70/BT71 -> 0.61692287 | CA72: =SUM(C72:F72) -> -0.68009379 | CB72: =SUM(G72:J72) -> -0.70354859 | CC72: =SUM(K72:N72) -> 0.29031084 | CD72: =SUM(O72:R72) -> -2.8695199 | CE72: =SUM(S72:V72) -> -0.08830256 | CF72: =SUM(W72:Z72) -> -0.089773884 | CG72: =SUM(AA72:AD72) -> -0.17789954 | CH72: =SUM(AE72:AH72) -> 0.25592189 | CI72: =SUM(AI72:AL72) -> 0.076386668 | CJ72: =SUM(AM72:AP72) -> 1.209441 | CK72: =SUM(AQ72:AT72) -> 3.3773291 | CL72: =SUM(AU72:AX72) -> -0.07961869 | CM72: =SUM(AY72:BB72) -> 0.69220566 | CN72: =SUM(BC72:BF72) -> 0.44822606 | CO72: =SUM(BG72:BJ72) -> 1.080429 | CP72: =SUM(BK72:BN72) -> 1.2591655 | CQ72: =SUM(BO72:BR72) -> 1.9575956
B74: Gross Profit Margin | C74: =C52/C50 -> 0.69800995 | D74: =D52/D50 -> 0.69623915 | E74: =E52/E50 -> 0.68938272 | F74: =F52/F50 -> 0.65848966 | G74: =G52/G50 -> 0.66173469 | H74: =H52/H50 -> 0.66078838 | I74: =I52/I50 -> 0.67484342 | J74: =J52/J50 -> 0.67082917 | ... BT74: =BT52/BT50 -> 0.70709298 | CA74: =CA52/CA50 -> 0.68539326 | CB74: =CB52/CB50 -> 0.66705099 | CC74: =CC52/CC50 -> 0.65114143 | CD74: =CD52/CD50 -> 0.6759553 | CE74: =CE52/CE50 -> 0.69564609 | CF74: =CF52/CF50 -> 0.70054201 | CG74: =CG52/CG50 -> 0.70937542 | CH74: =CH52/CH50 -> 0.71094682 | ... CQ74: =CQ52/CQ50 -> 0.69011208 | CR74: 0.682 | CS74: 0.695 | CT74: 0.698 | CU74: 0.7 | CV74: 0.7025 | CW74: 0.705 | CX74: 0.7075 | CY74: 0.71 | CZ74: 0.71 | DA74: 0.71
B75: SG&A as % of Revenue | C75: =C53/C50 -> 0.3238806 | D75: =D53/D50 -> 0.32352941 | E75: =E53/E50 -> 0.32839506 | F75: =F53/F50 -> 0.31168831 | G75: =G53/G50 -> 0.32040816 | H75: =H53/H50 -> 0.32883817 | I75: =I53/I50 -> 0.3308977 | J75: =J53/J50 -> 0.34265734 | ... BT75: =BT53/BT50 -> 0.33131202 | CA75: =CA53/CA50 -> 0.32181241 | CB75: =CB53/CB50 -> 0.3307712 | CC75: =CC53/CC50 -> 0.32721071 | CD75: =CD53/CD50 -> 0.34887571 | CE75: =CE53/CE50 -> 0.3749125 | CF75: =CF53/CF50 -> 0.39322493 | CG75: =CG53/CG50 -> 0.38424502 | CH75: =CH53/CH50 -> 0.36954448 | ... CQ75: =CQ53/CQ50 -> 0.34311333 | CR75: 0.351 | CS75: 0.349 | CT75: 0.347 | CU75: 0.346 | CV75: 0.345 | CW75: 0.344 | CX75: 0.343 | CY75: 0.342 | CZ75: 0.341 | DA75: 0.34
B76: R&D as % of Revenue | C76: =C54/C50 -> 0.1278607 | D76: =D54/D50 -> 0.13500482 | E76: =E54/E50 -> 0.12740741 | F76: =F54/F50 -> 0.12554113 | G76: =G54/G50 -> 0.12908163 | H76: =H54/H50 -> 0.12033195 | I76: =I54/I50 -> 0.12004175 | J76: =J54/J50 -> 0.11188811 | ... BT76: =BT54/BT50 -> 0.10180081 | CA76: =CA54/CA50 -> 0.12896922 | CB76: =CB54/CB50 -> 0.12029208 | CC76: =CC54/CC50 -> 0.11742325 | CD76: =CD54/CD50 -> 0.12222376 | CE76: =CE54/CE50 -> 0.12053759 | CF76: =CF54/CF50 -> 0.11070461 | CG76: =CG54/CG50 -> 0.11715929 | CH76: =CH54/CH50 -> 0.10970665 | ... CQ76: =CQ54/CQ50 -> 0.10221669 | CR76: 0.104 | CS76: 0.108 | CT76: 0.11 | CU76: 0.112 | CV76: 0.114 | CW76: 0.113 | CX76: 0.112 | CY76: 0.111 | CZ76: 0.11 | DA76: 0.109
B77: Operating Profit Margin | C77: =C62/C50 -> 0.0054726368 | D77: =D62/D50 -> 0.13259402 | E77: =E62/E50 -> 0.025185185 | F77: =F62/F50 -> -0.59211159 | G77: =G62/G50 -> -0.75816327 | H77: =H62/H50 -> 0.11981328 | I77: =I62/I50 -> 0.13100209 | J77: =J62/J50 -> 0.17382617 | ... BT77: =BT62/BT50 -> 0.21646454 | CA77: =CA62/CA50 -> -0.10918417 | CB77: =CB62/CB50 -> -0.08403792 | CC77: =CC62/CC50 -> 0.11860404 | CD77: =CD62/CD50 -> -0.53359084 | CE77: =CE62/CE50 -> 0.016799664 | CF77: =CF62/CF50 -> -0.040785908 | CG77: =CG62/CG50 -> -0.037849405 | CH77: =CH62/CH50 -> 0.053303124 | ... DA77: =DA62/DA50 -> 0.2267781
B78: Effective Tax Rate | C78: =C66/C65 -> 0.86597938 | D78: =D66/D65 -> 0.12222222 | E78: =E66/E65 -> -1.1363636 | F78: =F66/F65 -> 0.20118782 | G78: =G66/G65 -> -0.0088888889 | H78: =H66/H65 -> 0.17647059 | I78: =I66/I65 -> -0.16564417 | J78: =J66/J65 -> -0.026086957 | ... BT78: =BT66/BT65 -> 0.14622642 | CA78: =CA66/CA65 -> 0.21636086 | CB78: =CB66/CB65 -> -0.0018814675 | CC78: =CC66/CC65 -> 0.31308411 | CD78: =CD66/CD65 -> 0.0094959825 | CE78: =CE66/CE65 -> 0.4573991 | CF78: =CF66/CF65 -> 0.76620825 | CG78: =CG66/CG65 -> 0.63230769 | CH78: =CH66/CH65 -> -0.96045198 | ... CQ78: =CQ66/CQ65 -> 0.14559953 | CR78: 0.175 | CS78: 0.18 | CT78: 0.1825 | CU78: 0.185 | CV78: 0.1875 | CW78: 0.1875 | CX78: 0.1875 | CY78: 0.1875 | CZ78: 0.1875 | DA78: 0.1875
B79: Net Profit Margin | C79: =C67/C50 -> -0.0064676617 | D79: =D67/D50 -> 0.076181292 | E79: =E67/E50 -> -0.046419753 | F79: =F67/F50 -> -0.51755652 | G79: =G67/G50 -> -0.81071429 | H79: =H67/H50 -> 0.050829876 | I79: =I67/I50 -> 0.099164927 | J79: =J67/J50 -> 0.11788212 | ... BT79: =BT67/BT50 -> 0.16629915 | CA79: =CA67/CA50 -> -0.12518319 | CB79: =CB67/CB50 -> -0.13643351 | CC79: =CC67/CC50 -> 0.05785883 | CD79: =CD67/CD50 -> -0.56118085 | CE79: =CE67/CE50 -> -0.016939661 | CF79: =CF67/CF50 -> -0.016124661 | CG79: =CG67/CG50 -> -0.031964692 | CH79: =CH67/CH50 -> 0.041378488 | ... DA79: =DA67/DA50 -> 0.28791652
B81: Cash & C.E.'s | AX81: 1734 | AY81: 2016 | AZ81: 2675 | BA81: 1947 | BB81: 1925 | BC81: 325 | BD81: 276 | BE81: 339 | BF81: 928 | BG81: 570 | BH81: 426 | BI81: 952 | BJ81: 866 | BK81: 2329 | BL81: 2913 | BM81: 2502 | BN81: 414 | BO81: 725 | BP81: 534 | BQ81: 1275 | BR81: 1965 | BS81: 1453 | BT81: 539 | CL81: =AX81 -> 1734 | CM81: =BB81 -> 1925 | CN81: =BF81 -> 928 | CO81: =BJ81 -> 866 | CP81: =BN81 -> 414 | CQ81: =BQ81 -> 1275 | CR81: =CQ81+CR70 -> 3894.5269 | CS81: =CR81+CS70 -> 7300.0861 | CT81: =CS81+CT70 -> 11445.803 | CU81: =CT81+CU70 -> 16327.046 | CV81: =CU81+CV70 -> 21993.934 | CW81: =CV81+CW70 -> 28582.98 | CX81: =CW81+CX70 -> 36154.939 | CY81: =CX81+CY70 -> 44770.307 | ... DA81: =CZ81+DA70 -> 65146.386 | DC81: Invested Capital | DF81: Avg. (2023-2024) | DH81: Projected ROIC: | DJ81: ROIC | DK81: 0.095
B82: A/R | AX82: 1531 | AY82: 1631 | AZ82: 1675 | BA82: 1669 | BB82: 1778 | BC82: 1866 | BD82: 1917 | BE82: 1871 | BF82: 1970 | BG82: 2076 | BH82: 2134 | BI82: 2101 | BJ82: 2229 | BK82: 2304 | BL82: 2400 | BM82: 2501 | BN82: 2558 | BO82: 2693 | BP82: 2815 | BQ82: 2828 | BR82: 2926 | BS82: 3027 | BT82: 3049 | CL82: =AX82 -> 1531 | CM82: =BB82 -> 1778 | CN82: =BF82 -> 1970 | CO82: =BJ82 -> 2229 | CP82: =BN82 -> 2558 | CQ82: =BQ82 -> 2828 | DC82: 2024 | DD82: 2025 | DF82: 2023-2024 | DH82: 2025 | DJ82: Terminal | DK82: 0.0175
B83: Inventories | AX83: 1351 | AY83: 1407 | AZ83: 1430 | BA83: 1603 | BB83: 1610 | BC83: 1736 | BD83: 1752 | BE83: 1788 | BF83: 1867 | BG83: 2050 | BH83: 2250 | BI83: 2404 | BJ83: 2484 | BK83: 2561 | BL83: 2608 | BM83: 2753 | BN83: 2810 | BO83: 2867 | BP83: 2861 | BQ83: 2921 | BR83: 2943 | BS83: 3117 | BT83: 3235 | CL83: =AX83 -> 1351 | CM83: =BB83 -> 1610 | CN83: =BF83 -> 1867 | CO83: =BJ83 -> 2484 | CP83: =BN83 -> 2810 | CQ83: =BQ83 -> 2921 | DC83: =SUM(CP81:CP84)-CP95+CP87+CP89+CP88 -> 32196 | DD83: =SUM(CQ81:CQ84)-CQ95+CQ87+CQ89+CQ88 -> 35503 | DF83: =AVERAGE(DC83:DD83) -> 33849.5 | DH83: =AVERAGE(CR62)*(1-CR78) -> 3230.392 | DJ83: RFR (10-year yield) | DK83: 0.0499
B84: Prepaid Income Taxes | AX84: 194 | AY84: 192 | AZ84: 202 | BA84: 217 | BB84: 205 | BC84: 249 | BD84: 264 | BE84: 262 | BF84: 264 | BG84: 296 | BH84: 303 | BI84: 307 | BJ84: 315 | BK84: 319 | BL84: 315 | BM84: 332 | BN84: 307 | BO84: 294 | BP84: 298 | BQ84: 310 | BR84: 299 | BS84: 358 | BT84: 390 | CL84: =AX84 -> 194 | CM84: =BB84 -> 205 | CN84: =BF84 -> 264 | CO84: =BJ84 -> 315 | CP84: =BN84 -> 307 | CQ84: =BQ84 -> 310 | DH84: =DH83/DF83 -> 0.095433964 | DJ84: ERP (Avg. market return - (less) RFR) | DK84: =10.35%-DK83 -> 0.0536
B85: Assets Held for Sale | AX85: 1133 | AY85: 0 | AZ85: 0 | BA85: 0 | BB85: 0 | BC85: 0 | BD85: 0 | BE85: 0 | BF85: 0 | BG85: 0 | BH85: 0 | BI85: 0 | BJ85: 0 | BK85: 0 | BL85: 0 | BM85: 0 | BN85: 0 | BO85: 0 | BP85: 0 | BQ85: 0 | BR85: 0 | BS85: 0 | BT85: 0 | CL85: =AX85 -> 1133 | CM85: 0 | CN85: 0 | CO85: 0 | CP85: 0 | CQ85: =BQ85 -> 0 | DC85: Capital Structure | DJ85: Equity β (1-year avg.) | DK85: ='Notes | Analysis'!K269 -> 0.73
B86: Other Current Assets | AX86: 751 | AY86: 855 | AZ86: 777 | BA86: 792 | BB86: 799 | BC86: 889 | BD86: 874 | BE86: 884 | BF86: 731 | BG86: 711 | BH86: 773 | BI86: 741 | BJ86: 621 | BK86: 671 | BL86: 756 | BM86: 674 | BN86: 831 | BO86: 756 | BP86: 613 | BQ86: 701 | BR86: 660 | BS86: 729 | BT86: 760 | CL86: =AX86 -> 751 | CM86: =BB86 -> 799 | CN86: =BF86 -> 731 | CO86: =BJ86 -> 621 | CP86: =BN86 -> 831 | CQ86: =BQ86 -> 701 | DC86: Mkt Cap | DF86: =Main!C5 -> 64380.058 | DJ86: Discount (Cost of Equity) | DK86: =+DK83+(DK84*DK85) -> 0.089028
B87: PP&E | AX87: 2084 | AY87: 2053 | AZ87: 2082 | BA87: 2109 | BB87: 2252 | BC87: 2265 | BD87: 2246 | BE87: 2273 | BF87: 2446 | BG87: 2478 | BH87: 2534 | BI87: 2635 | BJ87: 2859 | BK87: 2897 | BL87: 2951 | BM87: 3072 | BN87: 3294 | BO87: 3389 | BP87: 3461 | BQ87: 3795 | BR87: 4036 | BS87: 4063 | BT87: 4126 | CL87: =AX87 -> 2084 | CM87: =BB87 -> 2252 | CN87: =BF87 -> 2446 | CO87: =BJ87 -> 2859 | CP87: =BN87 -> 3294 | CQ87: =BQ87 -> 3795 | DC87: Debt to Ttl Mkt Cap | DF87: =Main!C7/(Main!C7+DF86) -> 0.14579121
B88: Goodwill | AX88: 9951 | AY88: 10868 | AZ88: 10874 | BA88: 11820 | BB88: 11988 | BC88: 12949 | BD88: 12883 | BE88: 12852 | BF88: 12920 | BG88: 13269 | BH88: 13659 | BI88: 13608 | BJ88: 14387 | BK88: 14361 | BL88: 14397 | BM88: 15033 | BN88: 17089 | BO88: 17340 | BP88: 18076 | BQ88: 18214 | BR88: 18282 | BS88: 18536 | BT88: 18640 | CL88: =AX88 -> 9951 | CM88: =BB88 -> 11988 | CN88: =BF88 -> 12920 | CO88: =BJ88 -> 14387 | CP88: =BN88 -> 17089 | CQ88: =BQ88 -> 18214 | DC88: Mkt Equity to Ttl Mkt Cap | DF88: =DF86/(DF86+Main!C7) -> 0.85420879 | DJ88: NPV | DK88: =NPV(DK86,CR70:EO70) -> 97916.102
B89: Other Intangibles | AX89: 5917 | AY89: 5991 | AZ89: 5788 | BA89: 6227 | BB89: 6121 | BC89: 6581 | BD89: 6349 | BE89: 6058 | BF89: 5902 | BG89: 6060 | BH89: 6063 | BI89: 5849 | BJ89: 6003 | BK89: 5839 | BL89: 5417 | BM89: 5754 | BN89: 6684 | BO89: 6566 | BP89: 7260 | BQ89: 7162 | BR89: 7019 | BS89: 7060 | BT89: 6918 | CL89: =AX89 -> 5917 | CM89: =BB89 -> 6121 | CN89: =BF89 -> 5902 | CO89: =BJ89 -> 6003 | CP89: =BN89 -> 6684 | CQ89: =BQ89 -> 7162 | DC89: LT Debt / Equity | DF89: =CQ98/CQ102 -> 0.47046128 | DJ89: SC | DK89: =Main!C4 -> 1470.2
B90: Deffered Taxes | AX90: 4210 | AY90: 4173 | AZ90: 4036 | BA90: 4049 | BB90: 4142 | BC90: 4102 | BD90: 4059 | BE90: 4018 | BF90: 3942 | BG90: 3900 | BH90: 3865 | BI90: 3840 | BJ90: 3841 | BK90: 3792 | BL90: 3801 | BM90: 3816 | BN90: 3655 | BO90: 3676 | BP90: 3778 | BQ90: 3669 | BR90: 3675 | BS90: 3953 | BT90: 3909 | CL90: =AX90 -> 4210 | CM90: =BB90 -> 4142 | CN90: =BF90 -> 3942 | CO90: =BJ90 -> 3841 | CP90: =BN90 -> 3655 | CQ90: =BQ90 -> 3669 | DJ90: FV | DK90: =DK88/DK89 -> 66.600532
B91: Other LT Assets | AX91: 1921 | AY91: 1714 | AZ91: 1629 | BA91: 1444 | BB91: 1409 | BC91: 1375 | BD91: 1569 | BE91: 1602 | BF91: 1500 | BG91: 1482 | BH91: 1595 | BI91: 1605 | BJ91: 1531 | BK91: 1596 | BL91: 1550 | BM91: 1642 | BN91: 1753 | BO91: 1834 | BP91: 1864 | BQ91: 1832 | BR91: 1866 | BS91: 2055 | BT91: =2245+1405 -> 3650 | CL91: =AX91 -> 1921 | CM91: =BB91 -> 1409 | CN91: =BF91 -> 1500 | CO91: =BJ91 -> 1531 | CP91: =BN91 -> 1753 | CQ91: =BQ91 -> 1832 | DC91: Cost of Equity | DJ91: CP | DK91: =Main!C3 -> 43.79
B92: Ttl Assets | AX92: =SUM(AX81:AX91) -> 30777 | AY92: =SUM(AY81:AY91) -> 30900 | AZ92: =SUM(AZ81:AZ91) -> 31168 | BA92: =SUM(BA81:BA91) -> 31877 | BB92: =SUM(BB81:BB91) -> 32229 | BC92: =SUM(BC81:BC91) -> 32337 | BD92: =SUM(BD81:BD91) -> 32189 | BE92: =SUM(BE81:BE91) -> 31947 | ... BT92: =SUM(BT81:BT91) -> 45216 | CL92: =AX92 -> 30777 | CM92: =BB92 -> 32229 | CN92: =BF92 -> 32470 | CO92: =BJ92 -> 35136 | CP92: =BN92 -> 39395 | CQ92: =BQ92 -> 42707 | DC92: RFR (10-year yield) | DF92: =DK83 -> 0.0499 | DJ92: Change Δ | DK92: =DK90/DK91-1 -> 0.52090732 | DL92: =IF(DK92>0,"Upside","Downside") -> Upside
DC93: Equity β (1-year avg.) | DF93: ='Notes | Analysis'!K269 -> 0.73 | DJ93: {=_xlfn.IFS(DK92>=25%,"Strong Buy",DK92>=10.00001%,"Buy",AND(DK92<=10%,DK92>=-4.9999%),"Hold",AND(DK92<=-5%,DK92>=-14.999999%),"Sell",DK92<=-15%,"Strong Sell")} -> Strong Buy
B94: Current Debt | AX94: 13 | AY94: 13 | AZ94: 262 | BA94: 261 | BB94: 260 | BC94: 238 | BD94: 170 | BE94: 20 | BF94: 20 | BG94: 510 | BH94: 559 | BI94: 513 | BJ94: 531 | BK94: 1085 | BL94: 1580 | BM94: 1652 | BN94: 1779 | BO94: 777 | BP94: 480 | BQ94: 483 | BR94: 299 | BS94: 41 | BT94: 1709 | CL94: =AX94 -> 13 | CM94: =BB94 -> 260 | CN94: =BF94 -> 20 | CO94: =BJ94 -> 531 | CP94: =BN94 -> 1779 | CQ94: =BQ94 -> 483 | DC94: Market Return(1-year avg.) | DF94: 0.14
B95: Accounts Payable | AX95: 513 | AY95: 615 | AZ95: 689 | BA95: 674 | BB95: 794 | BC95: 696 | BD95: 732 | BE95: 803 | BF95: 862 | BG95: 868 | BH95: 899 | BI95: 929 | BJ95: 943 | BK95: 921 | BL95: 906 | BM95: 908 | BN95: 960 | BO95: 1004 | BP95: 962 | BQ95: 1002 | BR95: 1144 | BS95: 1141 | BT95: 1231 | CL95: =AX95 -> 513 | CM95: =BB95 -> 794 | CN95: =BF95 -> 862 | CO95: =BJ95 -> 943 | CP95: =BN95 -> 960 | CQ95: =BQ95 -> 1002 | DC95: Cost of Equity | DF95: =(DF92+DF93)*(DF94-DF92) -> 0.07026899
B96: Accrued Expenses | AX96: 2197 | AY96: 2060 | AZ96: 2442 | BA96: 2418 | BB96: 2436 | BC96: 2306 | BD96: 2197 | BE96: 1974 | BF96: 2160 | BG96: 1918 | BH96: 2164 | BI96: 2255 | BJ96: 2646 | BK96: 2083 | BL96: 2320 | BM96: 2460 | BN96: 2773 | BO96: 2354 | BP96: 2797 | BQ96: 2981 | BR96: 3201 | BS96: 2514 | BT96: 2756 | CL96: =AX96 -> 2197 | CM96: =BB96 -> 2436 | CN96: =BF96 -> 2160 | CO96: =BJ96 -> 2646 | CP96: =BN96 -> 2773 | CQ96: =BQ96 -> 2981
B97: Other Current Liabilities | AX97: 958 | AY97: 705 | AZ97: 680 | BA97: 669 | BB97: 783 | BC97: 1034 | BD97: 784 | BE97: 752 | BF97: 761 | BG97: 787 | BH97: 940 | BI97: 882 | BJ97: 814 | BK97: 827 | BL97: 770 | BM97: 891 | BN97: 887 | BO97: 923 | BP97: 952 | BQ97: 862 | BR97: 795 | BS97: 875 | BT97: 732 | CL97: =AX97 -> 958 | CM97: =BB97 -> 783 | CN97: =BF97 -> 761 | CO97: =BJ97 -> 814 | CP97: =BN97 -> 887 | CQ97: =BQ97 -> 862 | DC97: Cost of Debt
B98: LT Debt | AX98: 9130 | AY98: 9082 | AZ98: 8847 | BA98: 8824 | BB98: 8804 | BC98: 9067 | BD98: 8802 | BE98: 8564 | BF98: 8915 | BG98: 8495 | BH98: 8494 | BI98: 8386 | BJ98: 8571 | BK98: 9534 | BL98: 8991 | BM98: 9233 | BN98: 8968 | BO98: 10532 | BP98: 11107 | BQ98: 11117 | BR98: 11137 | BS98: 10988 | BT98: 10915 | CL98: =AX98 -> 9130 | CM98: =BB98 -> 8804 | CN98: =BF98 -> 8915 | CO98: =BJ98 -> 8571 | CP98: =BN98 -> 8968 | CQ98: =BQ98 -> 11117 | CR98: =CQ98+CR63 -> 10255.433 | CS98: =CR98+CS63 -> 9460.6365 | CT98: =CS98+CT63 -> 8727.4372 | CU98: =CT98+CU63 -> 8051.0608 | CV98: =CU98+CV63 -> 7427.1036 | CW98: =CV98+CW63 -> 6851.503 | CX98: =CW98+CX63 -> 6320.5116 | CY98: =CX98+CY63 -> 5830.6719 | ... DA98: =CZ98+DA63 -> 4961.9382 | DC98: Cost of Debt | DF98: 0.0775
B99: Deferred Income Taxes | AX99: 330 | AY99: 336 | AZ99: 115 | BA99: 274 | BB99: 310 | BC99: 261 | BD99: 265 | BE99: 278 | BF99: 144 | BG99: 210 | BH99: 135 | BI99: 91 | BJ99: 134 | BK99: 132 | BL99: 132 | BM99: 138 | BN99: 155 | BO99: 158 | BP99: 226 | BQ99: 242 | BR99: 220 | BS99: 219 | BT99: 221 | CL99: =AX99 -> 330 | CM99: =BB99 -> 310 | CN99: =BF99 -> 144 | CO99: =BJ99 -> 134 | CP99: =BN99 -> 155 | CQ99: =BQ99 -> 242 | DC99: Tax Rate | DF99: 0.04
B100: Other LT Liabilities | AX100: 2309 | AY100: 2370 | AZ100: 2190 | BA100: 2296 | BB100: 2220 | BC100: 2000 | BD100: 1988 | BE100: 1916 | BF100: 2035 | BG100: 1995 | BH100: 1926 | BI100: 1858 | BJ100: 1967 | BK100: 1919 | BL100: 1800 | BM100: 1841 | BN100: 1870 | BO100: 1946 | BP100: 2383 | BQ100: 2390 | BR100: 2405 | BS100: 2469 | BT100: 2480 | CL100: =AX100 -> 2309 | CM100: =BB100 -> 2220 | CN100: =BF100 -> 2035 | CO100: =BJ100 -> 1967 | CP100: =BN100 -> 1870 | CQ100: =BQ100 -> 2390 | DC100: After Tax Cost of Debt | DF100: =DF98*(1-DF99) -> 0.0744
B101: Ttl Liabilities | AX101: =SUM(AX94:AX100) -> 15450 | AY101: =SUM(AY94:AY100) -> 15181 | AZ101: =SUM(AZ94:AZ100) -> 15225 | BA101: =SUM(BA94:BA100) -> 15416 | BB101: =SUM(BB94:BB100) -> 15607 | BC101: =SUM(BC94:BC100) -> 15602 | BD101: =SUM(BD94:BD100) -> 14938 | BE101: =SUM(BE94:BE100) -> 14307 | ... BT101: =SUM(BT94:BT100) -> 20044 | CL101: =SUM(CL94:CL100) -> 15450 | CM101: =SUM(CM94:CM100) -> 15607 | CN101: =SUM(CN94:CN100) -> 14897 | CO101: =SUM(CO94:CO100) -> 15606 | CP101: =SUM(CP94:CP100) -> 17392 | CQ101: =BQ101 -> 19077
B102: SE | AX102: 15327 | AY102: 15719 | AZ102: 15943 | BA102: 16461 | BB102: 16622 | BC102: 16735 | BD102: 17251 | BE102: 17640 | BF102: 17573 | BG102: 18109 | BH102: 18485 | BI102: 19129 | BJ102: 19530 | BK102: 20168 | BL102: 20609 | BM102: 20956 | BN102: 22003 | BO102: 22446 | BP102: 22653 | BQ102: 23630 | BR102: 24472 | BS102: 26104 | BT102: 25172 | CL102: =AX102 -> 15327 | CM102: =BB102 -> 16622 | CN102: =BF102 -> 17573 | CO102: =BJ102 -> 19530 | CP102: =BN102 -> 22003 | CQ102: =BQ102 -> 23630
B103: Ttl L + SE | AX103: =AX101+AX102 -> 30777 | AY103: =AY101+AY102 -> 30900 | AZ103: =AZ101+AZ102 -> 31168 | BA103: =BA101+BA102 -> 31877 | BB103: =BB101+BB102 -> 32229 | BC103: =BC101+BC102 -> 32337 | BD103: =BD101+BD102 -> 32189 | BE103: =BE101+BE102 -> 31947 | ... BT103: =BT101+BT102 -> 45216 | CL103: =CL101+CL102 -> 30777 | CM103: =CM101+CM102 -> 32229 | CN103: =CN101+CN102 -> 32470 | CO103: =CO101+CO102 -> 35136 | CP103: =CP101+CP102 -> 39395 | CQ103: =BQ103 -> 42707
B105: Current Ratio
B106: Quick Ratio
B107: Cash Ratio
B108: Return on Assets
B109: Return on Equity
...

Sheet PEN Acquisition
AU1: Q1 2020 | AY1: Q1 2021 | BC1: Q1 2022 | BG1: Q1 2023 | BK1: Q1 2024 | BO1: Q1 2025 | BS1: Q1 2026
B2: Quarterly | C2: Apr | D2: July | E2: Oct | F2: Jan | G2: Apr | H2: July | I2: Oct | J2: Jan | K2: Apr | L2: July | M2: Oct | N2: Jan | O2: Apr | P2: July | Q2: Oct | R2: Jan | S2: Apr | T2: July | U2: Oct | V2: Jan | W2: Apr | X2: July | Y2: Oct | Z2: Jan | AA2: Apr | AB2: July | AC2: Oct | AD2: Jan | AE2: Apr | AF2: July | AG2: Oct | AH2: Jan | AI2: Apr | AJ2: July | AK2: Oct | AL2: Jan | AM2: Apr | AN2: July | AO2: Oct | AP2: Jan | AQ2: Apr | AR2: July | AS2: Oct | AT2: Jan | AU2: Apr | AV2: July | AW2: Oct | AX2: Jan | AY2: Apr | AZ2: July | BA2: Oct | BB2: Jan | BC2: Apr | BD2: July | BE2: Oct | BF2: Jan | BG2: Apr | BH2: July | BI2: Oct | BJ2: Jan | BK2: Apr | BL2: July | BM2: Oct | BN2: Jan | BO2: Apr | BP2: July | BQ2: Oct | BR2: Jan | BS2: Apr | BT2: July | BU2: Oct | BV2: Jan
B3: Revenues | C3: {="Q"&MOD(_xlfn.SEQUENCE(1,72)-1,4)+1&" "&(2009+INT((_xlfn.SEQUENCE(1,72)-1)/4))} -> Q1 2009 | D3: Q2 2009 | E3: Q3 2009 | F3: Q4 2009 | G3: Q1 2010 | H3: Q2 2010 | I3: Q3 2010 | J3: Q4 2010 | K3: Q1 2011 | L3: Q2 2011 | M3: Q3 2011 | N3: Q4 2011 | O3: Q1 2012 | P3: Q2 2012 | Q3: Q3 2012 | R3: Q4 2012 | S3: Q1 2013 | T3: Q2 2013 | U3: Q3 2013 | V3: Q4 2013 | W3: Q1 2014 | X3: Q2 2014 | Y3: Q3 2014 | Z3: Q4 2014 | AA3: Q1 2015 | AB3: Q2 2015 | AC3: Q3 2015 | AD3: Q4 2015 | AE3: Q1 2016 | AF3: Q2 2016 | AG3: Q3 2016 | AH3: Q4 2016 | AI3: Q1 2017 | AJ3: Q2 2017 | AK3: Q3 2017 | AL3: Q4 2017 | AM3: Q1 2018 | AN3: Q2 2018 | AO3: Q3 2018 | AP3: Q4 2018 | AQ3: Q1 2019 | AR3: Q2 2019 | AS3: Q3 2019 | AT3: Q4 2019 | AU3: Q1 2020 | AV3: Q2 2020 | AW3: Q3 2020 | AX3: Q4 2020 | AY3: Q1 2021 | AZ3: Q2 2021 | BA3: Q3 2021 | BB3: Q4 2021 | BC3: Q1 2022 | BD3: Q2 2022 | BE3: Q3 2022 | BF3: Q4 2022 | BG3: Q1 2023 | BH3: Q2 2023 | BI3: Q3 2023 | BJ3: Q4 2023 | BK3: Q1 2024 | BL3: Q2 2024 | BM3: Q3 2024 | BN3: Q4 2024 | BO3: Q1 2025 | BP3: Q2 2025 | BQ3: Q3 2025 | BR3: Q4 2025 | BS3: Q1 2026 | BT3: Q2 2026 | BU3: Q3 2026 | BV3: Q4 2026 | CA3: 2009 | CB3: =CA3+1 -> 2010 | CC3: =CB3+1 -> 2011 | CD3: =CC3+1 -> 2012 | CE3: =CD3+1 -> 2013 | CF3: =CE3+1 -> 2014 | CG3: =CF3+1 -> 2015 | CH3: =CG3+1 -> 2016 | CI3: =CH3+1 -> 2017 | ... EO3: =EN3+1 -> 2075
B4: Endoscopy | AU4: 442 | AV4: 348 | AW4: 475 | AX4: =1780-SUM(AU4:AW4) -> 515 | AY4: 499 | AZ4: 551 | BA4: 533 | BB4: =2141-SUM(AY4:BA4) -> 558 | BC4: 532 | BD4: 561 | BE4: 559 | BF4: =2221-SUM(BC4:BE4) -> 569 | BG4: 577 | BH4: 630 | BI4: 629 | BJ4: =2482-SUM(BG4:BI4) -> 646 | BK4: 642 | BL4: 675 | BM4: 678 | BN4: =2687-SUM(BK4:BM4) -> 692 | BO4: 673 | BP4: 737 | BQ4: 747 | BR4: 760 | BS4: 736 | BT4: 793 | CK4: 1894 | CL4: =SUM(AU4:AX4) -> 1780 | CM4: =SUM(AY4:BB4) -> 2141 | CN4: =SUM(BC4:BF4) -> 2221 | CO4: =SUM(BG4:BJ4) -> 2482 | CP4: =SUM(BK4:BN4) -> 2687 | CQ4: =SUM(BO4:BR4) -> 2917 | CR4: =CQ4*(1+CR17) -> 3194.115 | CS4: =CR4*(1+CS17) -> 3401.7325 | CT4: =CS4*(1+CT17) -> 3578.6226 | CU4: =CT4*(1+CU17) -> 3728.9247 | CV4: =CU4*(1+CV17) -> 3878.0817 | CW4: =CV4*(1+CW17) -> 4021.5707 | CX4: =CW4*(1+CX17) -> 4162.3257 | CY4: =CX4*(1+CY17) -> 4295.5201 | ... DA4: =CZ4*(1+DA17) -> 4561.5417
B5: Urology | AU5: 332 | AV5: 228 | AW5: 350 | AX5: =1286-SUM(AU5:AW5) -> 376 | AY5: 361 | AZ5: 397 | BA5: 384 | BB5: =1583-SUM(AY5:BA5) -> 441 | BC5: 413 | BD5: 450 | BE5: 433 | BF5: =1773-SUM(BC5:BE5) -> 477 | BG5: 469 | BH5: 485 | BI5: 483 | BJ5: =1964-SUM(BG5:BI5) -> 527 | BK5: 513 | BL5: 525 | BM5: 532 | BN5: =2200-SUM(BK5:BM5) -> 630 | BO5: 633 | BP5: 676 | BQ5: 682 | BR5: 717 | BS5: 646 | BT5: 684 | CK5: 1413 | CL5: =SUM(AU5:AX5) -> 1286 | CM5: =SUM(AY5:BB5) -> 1583 | CN5: =SUM(BC5:BF5) -> 1773 | CO5: =SUM(BG5:BJ5) -> 1964 | CP5: =SUM(BK5:BN5) -> 2200 | CQ5: =SUM(BO5:BR5) -> 2708 | CR5: =CQ5*(1+CR18) -> 2789.24 | CS5: =CR5*(1+CS18) -> 2900.8096 | CT5: =CS5*(1+CT18) -> 3103.8663 | CU5: =CT5*(1+CU18) -> 3352.1756 | CV5: =CU5*(1+CV18) -> 3553.3061 | CW5: =CV5*(1+CW18) -> 3730.9714 | CX5: =CW5*(1+CX18) -> 3898.8651 | CY5: =CX5*(1+CY18) -> 4054.8197 | ... DA5: =CZ5*(1+DA18) -> 4333.1324
B6: Neuromodulation | AU6: 191 | AV6: 122 | AW6: 216 | AX6: =761-SUM(AU6:AW6) -> 232 | AY6: 198 | AZ6: 247 | BA6: 221 | BB6: =909-SUM(AY6:BA6) -> 243 | BC6: 209 | BD6: 238 | BE6: 221 | BF6: =917-SUM(BC6:BE6) -> 249 | BG6: 234 | BH6: 244 | BI6: 229 | BJ6: =976-SUM(BG6:BI6) -> 269 | BK6: 256 | BL6: 282 | BM6: 268 | BN6: =1106-SUM(BK6:BM6) -> 300 | BO6: 271 | BP6: 303 | BQ6: 293 | BR6: 332 | BS6: 319 | BT6: 341 | CK6: 873 | CL6: =SUM(AU6:AX6) -> 761 | CM6: =SUM(AY6:BB6) -> 909 | CN6: =SUM(BC6:BF6) -> 917 | CO6: =SUM(BG6:BJ6) -> 976 | CP6: =SUM(BK6:BN6) -> 1106 | CQ6: =SUM(BO6:BR6) -> 1199 | CR6: =CQ6*(1+CR19) -> 1366.86 | CS6: =CR6*(1+CS19) -> 1530.8832 | CT6: =CS6*(1+CT19) -> 1699.2804 | CU6: =CT6*(1+CU19) -> 1869.2084 | CV6: =CU6*(1+CV19) -> 2037.4371 | CW6: =CV6*(1+CW19) -> 2200.4321 | CX6: =CW6*(1+CX19) -> 2354.4624 | CY6: =CX6*(1+CY19) -> 2495.7301 | ... DA6: =CZ6*(1+DA19) -> 2725.3373
B7: MedSurg Ttl Revenues | AU7: =SUM(AU4:AU6) -> 965 | AV7: =SUM(AV4:AV6) -> 698 | AW7: =SUM(AW4:AW6) -> 1041 | AX7: =SUM(AX4:AX6) -> 1123 | AY7: =SUM(AY4:AY6) -> 1058 | AZ7: =SUM(AZ4:AZ6) -> 1195 | BA7: =SUM(BA4:BA6) -> 1138 | BB7: =SUM(BB4:BB6) -> 1242 | ... BT7: =SUM(BT4:BT6) -> 1818 | CK7: =SUM(CK4:CK6) -> 4180 | CL7: =SUM(CL4:CL6) -> 3827 | CM7: =SUM(CM4:CM6) -> 4633 | CN7: =SUM(CN4:CN6) -> 4911 | CO7: =SUM(CO4:CO6) -> 5422 | CP7: =SUM(CP4:CP6) -> 5993 | CQ7: =SUM(BO7:BR7) -> 6824 | CR7: =SUM(CR4:CR6) -> 7350.215 | CS7: =SUM(CS4:CS6) -> 7833.4253 | CT7: =SUM(CT4:CT6) -> 8381.7692 | CU7: =SUM(CU4:CU6) -> 8950.3087 | CV7: =SUM(CV4:CV6) -> 9468.825 | CW7: =SUM(CW4:CW6) -> 9952.9742 | CX7: =SUM(CX4:CX6) -> 10415.653 | CY7: =SUM(CY4:CY6) -> 10846.07 | ... DA7: =SUM(DA4:DA6) -> 11620.011
B8: Interventional Cardiology | AU8: 633 | AV8: 495 | AW8: 586 | AX8: =2299-SUM(AU8:AW8) -> 585 | AY8: 526 | AZ8: 574 | BA8: 534 | BB8: =2209-SUM(AY8:BA8) -> 575 | BC8: 544 | BD8: 574 | BE8: 549 | BF8: =2228-SUM(BC8:BE8) -> 561 | BG8: 591 | BH8: 629 | BI8: 583 | BJ8: =2417-SUM(BG8:BI8) -> 614 | BK8: 652 | BL8: 665 | BM8: 661 | BN8: =2645-SUM(BK8:BM8) -> 667 | BO8: 697 | BP8: 731 | BQ8: 686 | BR8: 732 | BS8: 764 | BT8: 833 | CK8: 2816 | CL8: =SUM(AU8:AX8) -> 2299 | CM8: =SUM(AY8:BB8) -> 2209 | CN8: =SUM(BC8:BF8) -> 2228 | CO8: =SUM(BG8:BJ8) -> 2417 | CP8: =SUM(BK8:BN8) -> 2645 | CQ8: =SUM(BO8:BR8) -> 2846 | CR8: =CQ8*(1+CR21) -> 3201.75 | CS8: =CR8*(1+CS21) -> 3457.89 | CT8: =CS8*(1+CT21) -> 3699.9423 | CU8: =CT8*(1+CU21) -> 3884.9394 | CV8: =CU8*(1+CV21) -> 4059.7617 | CW8: =CV8*(1+CW21) -> 4222.1522 | CX8: =CW8*(1+CX21) -> 4369.9275 | CY8: =CX8*(1+CY21) -> 4501.0253 | ... DA8: =CZ8*(1+DA21) -> 4717.3558
B9: Watchman | AU9: 41 | AV9: 68 | AW9: 74 | AX9: =219-SUM(AU9:AW9) -> 36 | AY9: 170 | AZ9: 216 | BA9: 210 | BB9: =829-SUM(AY9:BA9) -> 233 | BC9: 226 | BD9: 250 | BE9: 262 | BF9: =1019-SUM(BC9:BE9) -> 281 | BG9: 291 | BH9: 317 | BI9: 323 | BJ9: =1274-SUM(BG9:BI9) -> 343 | BK9: 344 | BL9: 379 | BM9: 380 | BN9: =1516-SUM(BK9:BM9) -> 413 | BO9: 425 | BP9: 486 | BQ9: 512 | BR9: 541 | BS9: 506 | BT9: 507 | CK9: 81 | CL9: =SUM(AU9:AX9) -> 219 | CM9: =SUM(AY9:BB9) -> 829 | CN9: =SUM(BC9:BF9) -> 1019 | CO9: =SUM(BG9:BJ9) -> 1274 | CP9: =SUM(BK9:BN9) -> 1516 | CQ9: =SUM(BO9:BR9) -> 1964 | CR9: =CQ9*(1+CR22) -> 2238.96 | CS9: =CR9*(1+CS22) -> 2440.4664 | CT9: =CS9*(1+CT22) -> 2806.5364 | CU9: =CT9*(1+CU22) -> 3143.3207 | CV9: =CU9*(1+CV22) -> 3504.8026 | CW9: =CV9*(1+CW22) -> 3855.2829 | CX9: =CW9*(1+CX22) -> 4182.9819 | CY9: =CX9*(1+CY22) -> 4496.7056 | ... DA9: =CZ9*(1+DA22) -> 5124.2208
B10: Cardiac Rhythm | AU10: 437 | AV10: 351 | AW10: 465 | AX10: =1704-SUM(AU10:AW10) -> 451 | AY10: 469 | AZ10: 524 | BA10: 512 | BB10: =2019-SUM(AY10:BA10) -> 514 | BC10: 519 | BD10: 541 | BE10: 519 | BF10: =2100-SUM(BC10:BE10) -> 521 | BG10: 548 | BH10: 566 | BI10: 552 | BJ10: =2218-SUM(BG10:BI10) -> 552 | BK10: 575 | BL10: 576 | BM10: 561 | BN10: =2279-SUM(BK10:BM10) -> 567 | BO10: 578 | BP10: 590 | BQ10: 578 | BR10: 607 | BS10: 906 | BT10: 585 | CK10: 1939 | CL10: =SUM(AU10:AX10) -> 1704 | CM10: =SUM(AY10:BB10) -> 2019 | CN10: =SUM(BC10:BF10) -> 2100 | CO10: =SUM(BG10:BJ10) -> 2218 | CP10: =SUM(BK10:BN10) -> 2279 | CQ10: =SUM(BO10:BR10) -> 2353 | CR10: =CQ10*(1+CR23) -> 3176.55 | CS10: =CR10*(1+CS23) -> 3430.674 | CT10: =CS10*(1+CT23) -> 3533.5942 | CU10: =CT10*(1+CU23) -> 3621.9341 | CV10: =CU10*(1+CV23) -> 3703.4276 | CW10: =CV10*(1+CW23) -> 3777.4961 | CX10: =CW10*(1+CX23) -> 3843.6023 | CY10: =CX10*(1+CY23) -> 3901.2564 | ... DA10: =CZ10*(1+DA23) -> 3989.5223
B11: Electrophysiology | AU11: 74 | AV11: 51 | AW11: 76 | AX11: =287-SUM(AU11:AW11) -> 86 | AY11: 83 | AZ11: 95 | BA11: 86 | BB11: =365-SUM(AY11:BA11) -> 101 | BC11: 118 | BD11: 152 | BE11: 148 | BF11: =585-SUM(BC11:BE11) -> 167 | BG11: 177 | BH11: 193 | BI11: 190 | BJ11: =800-SUM(BG11:BI11) -> 240 | BK11: 300 | BL11: 428 | BM11: 527 | BN11: =1904-SUM(BK11:BM11) -> 649 | BO11: 729 | BP11: 840 | BQ11: 865 | BR11: 889 | BS11: 578 | BT11: 916 | CK11: 329 | CL11: =SUM(AU11:AX11) -> 287 | CM11: =SUM(AY11:BB11) -> 365 | CN11: =SUM(BC11:BF11) -> 585 | CO11: =SUM(BG11:BJ11) -> 800 | CP11: =SUM(BK11:BN11) -> 1904 | CQ11: =SUM(BO11:BR11) -> 3323 | CR11: =CQ11*(1+CR24) -> 2591.94 | CS11: =CR11*(1+CS24) -> 2332.746 | CT11: =CS11*(1+CT24) -> 2659.3304 | CU11: =CT11*(1+CU24) -> 2951.8568 | CV11: =CU11*(1+CV24) -> 3217.5239 | CW11: =CV11*(1+CW24) -> 3474.9258 | CX11: =CW11*(1+CX24) -> 3718.1706 | CY11: =CX11*(1+CY24) -> 3941.2609 | ... DA11: =CZ11*(1+DA24) -> 4303.8569
B12: Cardiology Ttl | AU12: =SUM(AU8:AU11) -> 1185 | AV12: =SUM(AV8:AV11) -> 965 | AW12: =SUM(AW8:AW11) -> 1201 | AX12: =SUM(AX8:AX11) -> 1158 | AY12: =SUM(AY8:AY11) -> 1248 | AZ12: =SUM(AZ8:AZ11) -> 1409 | BA12: =SUM(BA8:BA11) -> 1342 | BB12: =SUM(BB8:BB11) -> 1423 | ... BT12: =SUM(BT8:BT11) -> 2841 | CK12: =SUM(CK8:CK11) -> 5165 | CL12: =SUM(CL8:CL11) -> 4509 | CM12: =SUM(CM8:CM11) -> 5422 | CN12: =SUM(CN8:CN11) -> 5932 | CO12: =SUM(CO8:CO11) -> 6709 | CP12: =SUM(CP8:CP11) -> 8344 | CQ12: =SUM(BO12:BR12) -> 10486 | CR12: =SUM(CR8:CR11) -> 11209.2 | CS12: =SUM(CS8:CS11) -> 11661.776 | CT12: =SUM(CT8:CT11) -> 12699.403 | CU12: =SUM(CU8:CU11) -> 13602.051 | CV12: =SUM(CV8:CV11) -> 14485.516 | CW12: =SUM(CW8:CW11) -> 15329.857 | CX12: =SUM(CX8:CX11) -> 16114.682 | CY12: =SUM(CY8:CY11) -> 16840.248 | ... DA12: =SUM(DA8:DA11) -> 18134.956
B13: Peripheral Interventions | AU13: 393 | AV13: 340 | AW13: 417 | AX13: =1577-SUM(AU13:AW13) -> 427 | AY13: =433 -> 433 | AZ13: 473 | BA13: 452 | BB13: =1820-SUM(AY13:BA13) -> 462 | BC13: 465 | BD13: 478 | BE13: 479 | BF13: =1899-SUM(BC13:BE13) -> 477 | BG13: 502 | BH13: 535 | BI13: 538 | BJ13: =2109-SUM(BG13:BI13) -> 534 | BK13: 575 | BL13: 590 | BM13: 602 | BN13: =2410-SUM(BK13:BM13) -> 643 | BO13: 657 | BP13: 698 | BQ13: 702 | BR13: 708 | BS13: 749 | BT13: 783 | CK13: 1390 | CL13: =SUM(AU13:AX13) -> 1577 | CM13: =SUM(AY13:BB13) -> 1820 | CN13: =SUM(BC13:BF13) -> 1899 | CO13: =SUM(BG13:BJ13) -> 2109 | CP13: =SUM(BK13:BN13) -> 2410 | CQ13: =SUM(BO13:BR13) -> 2765 | CR13: =CQ13*(1+CR26) -> 3138.275 | CS13: =CR13*(1+CS26) -> 3514.868 | CT13: =CS13*(1+CT26) -> 3919.0778 | CU13: =CT13*(1+CU26) -> 4350.1764 | CV13: =CU13*(1+CV26) -> 4785.194 | CW13: =CV13*(1+CW26) -> 5215.8615 | CX13: =CW13*(1+CX26) -> 5633.1304 | CY13: =CX13*(1+CY26) -> 6027.4495 | ... DA13: =CZ13*(1+DA26) -> 6644.6604
B14: Cardiovascular Ttl Revenues | AU14: =SUM(AU12:AU13) -> 1578 | AV14: =SUM(AV12:AV13) -> 1305 | AW14: =SUM(AW12:AW13) -> 1618 | AX14: =SUM(AX12:AX13) -> 1585 | AY14: =SUM(AY12:AY13) -> 1681 | AZ14: =SUM(AZ12:AZ13) -> 1882 | BA14: =SUM(BA12:BA13) -> 1794 | BB14: =SUM(BB12:BB13) -> 1885 | ... BT14: =SUM(BT12:BT13) -> 3624 | CK14: =CK12+CK13 -> 6555 | CL14: =CL12+CL13 -> 6086 | CM14: =CM12+CM13 -> 7242 | CN14: =CN12+CN13 -> 7831 | CO14: =CO12+CO13 -> 8818 | CP14: =CP12+CP13 -> 10754 | CQ14: =SUM(BO14:BR14) -> 13251 | CR14: =CR12+SUM(CR13:CR13) -> 14347.475 | CS14: =CS12+SUM(CS13:CS13) -> 15176.644 | CT14: =CT12+SUM(CT13:CT13) -> 16618.481 | CU14: =CU12+SUM(CU13:CU13) -> 17952.227 | CV14: =CV12+SUM(CV13:CV13) -> 19270.71 | CW14: =CW12+SUM(CW13:CW13) -> 20545.718 | CX14: =CX12+SUM(CX13:CX13) -> 21747.813 | CY14: =CY12+SUM(CY13:CY13) -> 22867.698 | ... DA14: =DA12+SUM(DA13:DA13) -> 24779.616
B15: Ttl Revenues | AU15: =AU7+AU14 -> 2543 | AV15: =AV7+AV14 -> 2003 | AW15: =AW7+AW14 -> 2659 | AX15: =AX7+AX14 -> 2708 | AY15: =AY7+AY14+13 -> 2752 | AZ15: =AZ7+AZ14 -> 3077 | BA15: =BA7+BA14 -> 2932 | BB15: =BB7+BB14 -> 3127 | BC15: =BC7+BC14 -> 3026 | BD15: =BD7+BD14 -> 3244 | BE15: =BE7+BE14 -> 3170 | BF15: =BF7+BF14-60 -> 3242 | BG15: =BG7+BG14 -> 3389 | BH15: =BH7+BH14 -> 3599 | BI15: =BI7+BI14 -> 3527 | BJ15: =BJ7+BJ14 -> 3725 | BK15: =BK7+BK14 -> 3857 | BL15: =BL7+BL14 -> 4120 | BM15: =BM7+BM14 -> 4209 | BN15: =BN7+BN14 -> 4561 | ... BT15: =BT7+BT14 -> 5442 | CK15: =CK7+CK14 -> 10735 | CL15: =CL7+CL14 -> 9913 | CM15: =CM7+CM14+13 -> 11888 | CN15: =CN7+CN14-60 -> 12682 | CO15: =CO7+CO14 -> 14240 | CP15: =CP7+CP14 -> 16747 | CQ15: =SUM(BO15:BR15) -> 20075 | CR15: =CR7+CR14 -> 21697.69 | CS15: =CS7+CS14 -> 23010.07 | CT15: =CT7+CT14 -> 25000.25 | CU15: =CU7+CU14 -> 26902.536 | CV15: =CV7+CV14 -> 28739.535 | CW15: =CW7+CW14 -> 30498.693 | CX15: =CX7+CX14 -> 32163.466 | CY15: =CY7+CY14 -> 33713.768 | ... DA15: =DA7+DA14 -> 36399.628
B17: Endoscopy Growth Y/y | AY17: =AY4/AU4-1 -> 0.12895928 | AZ17: =AZ4/AV4-1 -> 0.58333333 | BA17: =BA4/AW4-1 -> 0.12210526 | BB17: =BB4/AX4-1 -> 0.083495146 | BC17: =BC4/AY4-1 -> 0.066132265 | BD17: =BD4/AZ4-1 -> 0.01814882 | BE17: =BE4/BA4-1 -> 0.048780488 | BF17: =BF4/BB4-1 -> 0.019713262 | ... BT17: =BT4/BP4-1 -> 0.075983718 | CL17: =CL4/CK4-1 -> -0.060190074 | CM17: =CM4/CL4-1 -> 0.20280899 | CN17: =CN4/CM4-1 -> 0.037365717 | CO17: =CO4/CN4-1 -> 0.11751463 | CP17: =CP4/CO4-1 -> 0.082594682 | CQ17: =CQ4/CP4-1 -> 0.08559732 | CR17: 0.095 | CS17: 0.065 | CT17: 0.052 | CU17: 0.042 | CV17: 0.04 | CW17: 0.037 | CX17: 0.035 | CY17: 0.032 | CZ17: 0.031 | DA17: 0.03
B18: Urology Growth Y/y | AY18: =AY5/AU5-1 -> 0.087349398 | AZ18: =AZ5/AV5-1 -> 0.74122807 | BA18: =BA5/AW5-1 -> 0.097142857 | BB18: =BB5/AX5-1 -> 0.17287234 | BC18: =BC5/AY5-1 -> 0.14404432 | BD18: =BD5/AZ5-1 -> 0.13350126 | BE18: =BE5/BA5-1 -> 0.12760417 | BF18: =BF5/BB5-1 -> 0.081632653 | ... BT18: =BT5/BP5-1 -> 0.01183432 | CL18: =CL5/CK5-1 -> -0.089879689 | CM18: =CM5/CL5-1 -> 0.23094868 | CN18: =CN5/CM5-1 -> 0.12002527 | CO18: =CO5/CN5-1 -> 0.10772702 | CP18: =CP5/CO5-1 -> 0.12016293 | CQ18: =CQ5/CP5-1 -> 0.23090909 | CR18: 0.03 | CS18: 0.04 | CT18: 0.07 | CU18: 0.08 | CV18: 0.06 | CW18: 0.05 | CX18: 0.045 | CY18: 0.04 | CZ18: 0.035 | DA18: 0.0325
B19: Neuro Growth Y/y | AY19: =AY6/AU6-1 -> 0.036649215 | AZ19: =AZ6/AV6-1 -> 1.0245902 | BA19: =BA6/AW6-1 -> 0.023148148 | BB19: =BB6/AX6-1 -> 0.047413793 | BC19: =BC6/AY6-1 -> 0.055555556 | BD19: =BD6/AZ6-1 -> -0.036437247 | BE19: =BE6/BA6-1 -> 0 | BF19: =BF6/BB6-1 -> 0.024691358 | ... BT19: =BT6/BP6-1 -> 0.12541254 | CL19: =CL6/CK6-1 -> -0.12829324 | CM19: =CM6/CL6-1 -> 0.19448095 | CN19: =CN6/CM6-1 -> 0.0088008801 | CO19: =CO6/CN6-1 -> 0.06434024 | CP19: =CP6/CO6-1 -> 0.13319672 | CQ19: =CQ6/CP6-1 -> 0.084086799 | CR19: 0.14 | CS19: 0.12 | CT19: 0.11 | CU19: 0.1 | CV19: 0.09 | CW19: 0.08 | CX19: 0.07 | CY19: 0.06 | CZ19: 0.05 | DA19: 0.04
B20: MedSurg Growth Y/y | AY20: =AY7/AU7-1 -> 0.096373057 | AZ20: =AZ7/AV7-1 -> 0.71203438 | BA20: =BA7/AW7-1 -> 0.093179635 | BB20: =BB7/AX7-1 -> 0.10596616 | BC20: =BC7/AY7-1 -> 0.09073724 | BD20: =BD7/AZ7-1 -> 0.045188285 | BE20: =BE7/BA7-1 -> 0.065905097 | BF20: =BF7/BB7-1 -> 0.042673108 | ... BT20: =BT7/BP7-1 -> 0.059440559 | CL20: =CL7/CK7-1 -> -0.084449761 | CM20: =CM7/CL7-1 -> 0.21060883 | CN20: =CN7/CM7-1 -> 0.060004317 | CO20: =CO7/CN7-1 -> 0.10405213 | CP20: =CP7/CO7-1 -> 0.10531169 | CQ20: =CQ7/CP7-1 -> 0.13866177 | CR20: =CR7/CQ7-1 -> 0.077112397 | CS20: =CS7/CR7-1 -> 0.065740972 | ... DA20: =DA7/CZ7-1 -> 0.033263135
B21: Interventional Growth Y/y | AY21: =AY8/AU8-1 -> -0.16903633 | AZ21: =AZ8/AV8-1 -> 0.15959596 | BA21: =BA8/AW8-1 -> -0.088737201 | BB21: =BB8/AX8-1 -> -0.017094017 | BC21: =BC8/AY8-1 -> 0.034220532 | BD21: =BD8/AZ8-1 -> 0 | BE21: =BE8/BA8-1 -> 0.028089888 | BF21: =BF8/BB8-1 -> -0.024347826 | ... BT21: =BT8/BP8-1 -> 0.13953488 | CL21: =CL8/CK8-1 -> -0.18359375 | CM21: =CM8/CL8-1 -> -0.039147455 | CN21: =CN8/CM8-1 -> 0.008601177 | CO21: =CO8/CN8-1 -> 0.084829443 | CP21: =CP8/CO8-1 -> 0.094331816 | CQ21: =CQ8/CP8-1 -> 0.075992439 | CR21: 0.125 | CS21: 0.08 | CT21: 0.07 | CU21: 0.05 | CV21: 0.045 | CW21: 0.04 | CX21: 0.035 | CY21: 0.03 | CZ21: 0.025 | DA21: 0.0225
B22: Watchman Growth Y/y | AY22: =AY9/AU9-1 -> 3.1463415 | AZ22: =AZ9/AV9-1 -> 2.1764706 | BA22: =BA9/AW9-1 -> 1.8378378 | BB22: =BB9/AX9-1 -> 5.4722222 | BC22: =BC9/AY9-1 -> 0.32941176 | BD22: =BD9/AZ9-1 -> 0.15740741 | BE22: =BE9/BA9-1 -> 0.24761905 | BF22: =BF9/BB9-1 -> 0.20600858 | ... BT22: =BT9/BP9-1 -> 0.043209877 | CL22: =CL9/CK9-1 -> 1.7037037 | CM22: =CM9/CL9-1 -> 2.7853881 | CN22: =CN9/CM9-1 -> 0.2291918 | CO22: =CO9/CN9-1 -> 0.25024534 | CP22: =CP9/CO9-1 -> 0.1899529 | CQ22: =CQ9/CP9-1 -> 0.29551451 | CR22: 0.14 | CS22: 0.09 | CT22: 0.15 | CU22: 0.12 | CV22: 0.115 | CW22: 0.1 | CX22: 0.085 | CY22: 0.075 | CZ22: 0.07 | DA22: 0.065
B23: Rhythm Growth Y/y | AY23: =AY10/AU10-1 -> 0.073226545 | AZ23: =AZ10/AV10-1 -> 0.49287749 | BA23: =BA10/AW10-1 -> 0.10107527 | BB23: =BB10/AX10-1 -> 0.13968958 | BC23: =BC10/AY10-1 -> 0.10660981 | BD23: =BD10/AZ10-1 -> 0.032442748 | BE23: =BE10/BA10-1 -> 0.013671875 | BF23: =BF10/BB10-1 -> 0.013618677 | ... BT23: =BT10/BP10-1 -> -0.0084745763 | CL23: =CL10/CK10-1 -> -0.12119649 | CM23: =CM10/CL10-1 -> 0.18485915 | CN23: =CN10/CM10-1 -> 0.040118871 | CO23: =CO10/CN10-1 -> 0.056190476 | CP23: =CP10/CO10-1 -> 0.027502254 | CQ23: =CQ10/CP10-1 -> 0.032470382 | CR23: 0.35 | CS23: 0.08 | CT23: 0.03 | CU23: 0.025 | CV23: 0.0225 | CW23: 0.02 | CX23: 0.0175 | CY23: 0.015 | CZ23: 0.0125 | DA23: 0.01
B24: Electrophysiology Growth Y/y | AY24: =AY11/AU11-1 -> 0.12162162 | AZ24: =AZ11/AV11-1 -> 0.8627451 | BA24: =BA11/AW11-1 -> 0.13157895 | BB24: =BB11/AX11-1 -> 0.1744186 | BC24: =BC11/AY11-1 -> 0.42168675 | BD24: =BD11/AZ11-1 -> 0.6 | BE24: =BE11/BA11-1 -> 0.72093023 | BF24: =BF11/BB11-1 -> 0.65346535 | ... BT24: =BT11/BP11-1 -> 0.09047619 | CL24: =CL11/CK11-1 -> -0.12765957 | CM24: =CM11/CL11-1 -> 0.271777 | CN24: =CN11/CM11-1 -> 0.60273973 | CO24: =CO11/CN11-1 -> 0.36752137 | CP24: =CP11/CO11-1 -> 1.38 | CQ24: =CQ11/CP11-1 -> 0.74527311 | CR24: -0.22 | CS24: -0.1 | CT24: 0.14 | CU24: 0.11 | CV24: 0.09 | CW24: 0.08 | CX24: 0.07 | CY24: 0.06 | CZ24: 0.05 | DA24: 0.04
B25: Cardiology Growth Y/y | AY25: =AY12/AU12-1 -> 0.053164557 | AZ25: =AZ12/AV12-1 -> 0.46010363 | BA25: =BA12/AW12-1 -> 0.11740216 | BB25: =BB12/AX12-1 -> 0.22884283 | BC25: =BC12/AY12-1 -> 0.12740385 | BD25: =BD12/AZ12-1 -> 0.076650106 | BE25: =BE12/BA12-1 -> 0.10134128 | BF25: =BF12/BB12-1 -> 0.075193254 | ... BT25: =BT12/BP12-1 -> 0.073290518 | CL25: =CL12/CK12-1 -> -0.12700871 | CM25: =CM12/CL12-1 -> 0.20248392 | CN25: =CN12/CM12-1 -> 0.094061232 | CO25: =CO12/CN12-1 -> 0.13098449 | CP25: =CP12/CO12-1 -> 0.24370249 | CQ25: =CQ12/CP12-1 -> 0.25671141 | CR25: =CR13/CQ13-1 -> 0.135 | CS25: =CS13/CR13-1 -> 0.12 | CT25: =CT13/CS13-1 -> 0.115 | CU25: =CU13/CT13-1 -> 0.11 | CV25: =CV13/CU13-1 -> 0.1 | CW25: =CW13/CV13-1 -> 0.09 | CX25: =CX13/CW13-1 -> 0.08 | CY25: =CY13/CX13-1 -> 0.07 | ... DA25: =DA13/CZ13-1 -> 0.04
B26: Peripheral Growth Y/y | AY26: =AY13/AU13-1 -> 0.10178117 | AZ26: =AZ13/AV13-1 -> 0.39117647 | BA26: =BA13/AW13-1 -> 0.083932854 | BB26: =BB13/AX13-1 -> 0.081967213 | BC26: =BC13/AY13-1 -> 0.073903002 | BD26: =BD13/AZ13-1 -> 0.010570825 | BE26: =BE13/BA13-1 -> 0.059734513 | BF26: =BF13/BB13-1 -> 0.032467532 | ... BT26: =BT13/BP13-1 -> 0.1217765 | CL26: =CL13/CK13-1 -> 0.13453237 | CM26: =CM13/CL13-1 -> 0.15409004 | CN26: =CN13/CM13-1 -> 0.043406593 | CO26: =CO13/CN13-1 -> 0.11058452 | CP26: =CP13/CO13-1 -> 0.14272167 | CQ26: =CQ13/CP13-1 -> 0.1473029 | CR26: 0.135 | CS26: 0.12 | CT26: 0.115 | CU26: 0.11 | CV26: 0.1 | CW26: 0.09 | CX26: 0.08 | CY26: 0.07 | CZ26: 0.06 | DA26: 0.04
B27: Cardiovascular Y/y | AY27: =AY14/AU14-1 -> 0.065272497 | AZ27: =AZ14/AV14-1 -> 0.44214559 | BA27: =BA14/AW14-1 -> 0.10877627 | BB27: =BB14/AX14-1 -> 0.18927445 | BC27: =BC14/AY14-1 -> 0.11362284 | BD27: =BD14/AZ14-1 -> 0.060042508 | BE27: =BE14/BA14-1 -> 0.090858417 | BF27: =BF14/BB14-1 -> 0.064721485 | ... BT27: =BT14/BP14-1 -> 0.083408072 | CL27: =CL14/CK14-1 -> -0.071548436 | CM27: =CM14/CL14-1 -> 0.18994413 | CN27: =CN14/CM14-1 -> 0.081331124 | CO27: =CO14/CN14-1 -> 0.12603754 | CP27: =CP14/CO14-1 -> 0.21955092 | CQ27: =CQ14/CP14-1 -> 0.23219267 | CR27: =CR14/CQ14-1 -> 0.082746585 | CS27: =CS14/CR14-1 -> 0.057792009 | ... DA27: =DA14/CZ14-1 -> 0.036696955
B28: Ttl Revenue Growth Y/y | AY28: =AY15/AU15-1 -> 0.082186394 | AZ28: =AZ15/AV15-1 -> 0.53619571 | BA28: =BA15/AW15-1 -> 0.10267018 | BB28: =BB15/AX15-1 -> 0.15472674 | BC28: =BC15/AY15-1 -> 0.099563953 | BD28: =BD15/AZ15-1 -> 0.054273643 | BE28: =BE15/BA15-1 -> 0.081173261 | BF28: =BF15/BB15-1 -> 0.036776463 | ... BT28: =BT15/BP15-1 -> 0.075281565 | CL28: =CL15/CK15-1 -> -0.076571961 | CM28: =CM15/CL15-1 -> 0.19923333 | CN28: =CN15/CM15-1 -> 0.06679004 | CO28: =CO15/CN15-1 -> 0.12285129 | CP28: =CP15/CO15-1 -> 0.17605337 | CQ28: =CQ15/CP15-1 -> 0.19872216 | CR28: =CR15/CQ15-1 -> 0.080831382 | CS28: =CS15/CR15-1 -> 0.060484765 | ... DA28: =DA15/CZ15-1 -> 0.035598284
B30: MedSurg % of Ttl Revenues | AU30: =AU7/AU15 -> 0.37947306 | AV30: =AV7/AV15 -> 0.34847728 | AW30: =AW7/AW15 -> 0.39150056 | AX30: =AX7/AX15 -> 0.41469719 | AY30: =AY7/AY15 -> 0.38444767 | AZ30: =AZ7/AZ15 -> 0.38836529 | BA30: =BA7/BA15 -> 0.38813097 | BB30: =BB7/BB15 -> 0.3971858 | ... BT30: =BT7/BT15 -> 0.33406836 | CK30: =CK7/CK15 -> 0.38938053 | CL30: =CL7/CL15 -> 0.38605871 | CM30: =CM7/CM15 -> 0.38972073 | CN30: =CN7/CN15 -> 0.38724176 | CO30: =CO7/CO15 -> 0.38075843 | CP30: =CP7/CP15 -> 0.35785514 | CQ30: =CQ7/CQ15 -> 0.33992528 | CR30: =CR7/CR15 -> 0.33875565 | ... DA30: =DA7/DA15 -> 0.31923435
B31: Cardiovasc % of Ttl Revenues | AU31: =AU14/AU15 -> 0.62052694 | AV31: =AV14/AV15 -> 0.65152272 | AW31: =AW14/AW15 -> 0.60849944 | AX31: =AX14/AX15 -> 0.58530281 | AY31: =AY14/AY15 -> 0.61082849 | AZ31: =AZ14/AZ15 -> 0.61163471 | BA31: =BA14/BA15 -> 0.61186903 | BB31: =BB14/BB15 -> 0.6028142 | ... BT31: =BT14/BT15 -> 0.66593164 | CK31: =CK14/CK15 -> 0.61061947 | CL31: =CL14/CL15 -> 0.61394129 | CM31: =CM14/CM15 -> 0.60918573 | CN31: =CN14/CN15 -> 0.61748935 | CO31: =CO14/CO15 -> 0.61924157 | CP31: =CP14/CP15 -> 0.64214486 | CQ31: =CQ14/CQ15 -> 0.66007472 | CR31: =CR14/CR15 -> 0.66124435 | ... DA31: =DA14/DA15 -> 0.68076565
B33: U.S. Revenues | AU33: 1452 | AV33: 1058 | AW33: 1496 | AX33: =5508-SUM(AU33:AW33) -> 1502 | AY33: 1577 | AZ33: 1800 | BA33: 1726 | BB33: =6901-SUM(AY33:BA33) -> 1798 | BC33: 1778 | BD33: 1934 | BE33: 1934 | BF33: =7632-SUM(BC33:BE33) -> 1986 | BG33: 2003 | BH33: 2110 | BI33: 2099 | BJ33: =8425-SUM(BG33:BI33) -> 2213 | BK33: 2258 | BL33: 2466 | BM33: 2593 | BN33: =10210-SUM(BK33:BM33) -> 2893 | BO33: 2960 | BP33: 3224 | BQ33: 3294 | BR33: 3385 | BS33: 3284 | BT33: 3426 | CK33: 6097 | CL33: =SUM(AU33:AX33) -> 5508 | CM33: =SUM(AY33:BB33) -> 6901 | CN33: =SUM(BC33:BF33) -> 7632 | CO33: =SUM(BG33:BJ33) -> 8425 | CP33: =SUM(BK33:BN33) -> 10210 | CQ33: =SUM(BO33:BR33) -> 12863
B34: Euro, Mid. East, Afr | AU34: 552 | AV34: 416 | AW34: 540 | AX34: =2097-SUM(AU34:AW34) -> 589 | AY34: 604 | AZ34: 662 | BA34: 590 | BB34: =2518-SUM(AY34:BA34) -> 662 | BC34: 624 | BD34: 660 | BE34: 585 | BF34: =2526-SUM(BC34:BE34) -> 657 | BG34: 712 | BH34: 723 | BI34: 671 | BJ34: =2856-SUM(BG34:BI34) -> 750 | BK34: 803 | BL34: 822 | BM34: 773 | BN34: =3228-SUM(BK34:BM34) -> 830 | BO34: 846 | BP34: 878 | BQ34: 793 | BR34: 933 | BS34: 932 | BT34: 932 | CK34: 2264 | CL34: =SUM(AU34:AX34) -> 2097 | CM34: =SUM(AY34:BB34) -> 2518 | CN34: =SUM(BC34:BF34) -> 2526 | CO34: =SUM(BG34:BJ34) -> 2856 | CP34: =SUM(BK34:BN34) -> 3228 | CQ34: =SUM(BO34:BR34) -> 3450
B35: A-Pac | AU35: 409 | AV35: 410 | AW35: 472 | AX35: =1781-SUM(AU35:AW35) -> 490 | AY35: 473 | AZ35: 520 | BA35: 517 | BB35: =2070-SUM(AY35:BA35) -> 560 | BC35: 517 | BD35: 530 | BE35: 532 | BF35: =2116-SUM(BC35:BE35) -> 537 | BG35: 548 | BH35: 626 | BI35: 611 | BJ35: =2400-SUM(BG35:BI35) -> 615 | BK35: 647 | BL35: 670 | BM35: 684 | BN35: =2686-SUM(BK35:BM35) -> 685 | BO35: 701 | BP35: 790 | BQ35: 803 | BR35: 789 | BS35: 803 | BT35: 878 | CK35: 1898 | CL35: =SUM(AU35:AX35) -> 1781 | CM35: =SUM(AY35:BB35) -> 2070 | CN35: =SUM(BC35:BF35) -> 2116 | CO35: =SUM(BG35:BJ35) -> 2400 | CP35: =SUM(BK35:BN35) -> 2686 | CQ35: =SUM(BO35:BR35) -> 3083
B36: Lat Am + Canada | AU36: 89 | AV36: 51 | AW36: 77 | AX36: =307-SUM(AU36:AW36) -> 90 | AY36: 85 | AZ36: 95 | BA36: 99 | BB36: =386-SUM(AY36:BA36) -> 107 | BC36: 107 | BD36: 120 | BE36: 119 | BF36: =469-SUM(BC36:BE36) -> 123 | BG36: 126 | BH36: 140 | BI36: 146 | BJ36: =559-SUM(BG36:BI36) -> 147 | BK36: 149 | BL36: 162 | BM36: 159 | BN36: =623-SUM(BK36:BM36) -> 153 | BO36: 156 | BP36: 169 | BQ36: 175 | BR36: 179 | BS36: 185 | BT36: 206 | CK36: 395 | CL36: =SUM(AU36:AX36) -> 307 | CM36: =SUM(AY36:BB36) -> 386 | CN36: =SUM(BC36:BF36) -> 469 | CO36: =SUM(BG36:BJ36) -> 559 | CP36: =SUM(BK36:BN36) -> 623 | CQ36: =SUM(BO36:BR36) -> 679
B37: Ttl Revenues | AU37: =SUM(AU33:AU36)+41 -> 2543 | AV37: =SUM(AV33:AV36)+68 -> 2003 | AW37: =SUM(AW33:AW36)+74 -> 2659 | AX37: =SUM(AX33:AX36)+220-41-68-74 -> 2708 | AY37: =SUM(AY33:AY36)+13 -> 2752 | AZ37: =SUM(AZ33:AZ36) -> 3077 | BA37: =SUM(BA33:BA36) -> 2932 | BB37: =SUM(BB33:BB36) -> 3127 | BC37: =SUM(BC33:BC36) -> 3026 | BD37: =SUM(BD33:BD36) -> 3244 | BE37: =SUM(BE33:BE36) -> 3170 | BF37: =SUM(BF33:BF36)-61 -> 3242 | BG37: =SUM(BG33:BG36) -> 3389 | BH37: =SUM(BH33:BH36) -> 3599 | BI37: =SUM(BI33:BI36) -> 3527 | BJ37: =SUM(BJ33:BJ36) -> 3725 | BK37: =SUM(BK33:BK36) -> 3857 | BL37: =SUM(BL33:BL36) -> 4120 | BM37: =SUM(BM33:BM36) -> 4209 | BN37: =SUM(BN33:BN36) -> 4561 | ... BT37: =SUM(BT33:BT36) -> 5442 | CK37: =SUM(CK33:CK36)+81 -> 10735 | CL37: =SUM(CL33:CL36)+220 -> 9913 | CM37: =SUM(CM33:CM36)+13 -> 11888 | CN37: =SUM(CN33:CN36)-61 -> 12682 | CO37: =SUM(CO33:CO36) -> 14240 | CP37: =SUM(CP33:CP36) -> 16747 | CQ37: =SUM(BO37:BR37) -> 20075
B39: U.S. Revenue Growth Y/y | AY39: =AY33/AU33-1 -> 0.086088154 | AZ39: =AZ33/AV33-1 -> 0.70132325 | BA39: =BA33/AW33-1 -> 0.15374332 | BB39: =BB33/AX33-1 -> 0.19707057 | BC39: =BC33/AY33-1 -> 0.1274572 | BD39: =BD33/AZ33-1 -> 0.074444444 | BE39: =BE33/BA33-1 -> 0.12050985 | BF39: =BF33/BB33-1 -> 0.10456062 | ... BT39: =BT33/BP33-1 -> 0.062655087 | CL39: =CL33/CK33-1 -> -0.096604888 | CM39: =CM33/CL33-1 -> 0.25290487 | CN39: =CN33/CM33-1 -> 0.10592668 | CO39: =CO33/CN33-1 -> 0.10390461 | CP39: =CP33/CO33-1 -> 0.21186944 | CQ39: =CQ33/CP33-1 -> 0.25984329
B40: Euro, Mid. East, Afr Revenue Growth Y/y | AY40: =AY34/AU34-1 -> 0.094202899 | AZ40: =AZ34/AV34-1 -> 0.59134615 | BA40: =BA34/AW34-1 -> 0.092592593 | BB40: =BB34/AX34-1 -> 0.12393888 | BC40: =BC34/AY34-1 -> 0.033112583 | BD40: =BD34/AZ34-1 -> -0.003021148 | BE40: =BE34/BA34-1 -> -0.0084745763 | BF40: =BF34/BB34-1 -> -0.0075528701 | ... BT40: =BT34/BP34-1 -> 0.061503417 | CL40: =CL34/CK34-1 -> -0.073763251 | CM40: =CM34/CL34-1 -> 0.20076299 | CN40: =CN34/CM34-1 -> 0.0031771247 | CO40: =CO34/CN34-1 -> 0.13064133 | CP40: =CP34/CO34-1 -> 0.1302521 | CQ40: =CQ34/CP34-1 -> 0.068773234
B41: A-Pac Revenue Growth Y/y | AY41: =AY35/AU35-1 -> 0.15647922 | AZ41: =AZ35/AV35-1 -> 0.26829268 | BA41: =BA35/AW35-1 -> 0.095338983 | BB41: =BB35/AX35-1 -> 0.14285714 | BC41: =BC35/AY35-1 -> 0.093023256 | BD41: =BD35/AZ35-1 -> 0.019230769 | BE41: =BE35/BA35-1 -> 0.02901354 | BF41: =BF35/BB35-1 -> -0.041071429 | ... BT41: =BT35/BP35-1 -> 0.11139241 | CL41: =CL35/CK35-1 -> -0.061643836 | CM41: =CM35/CL35-1 -> 0.16226839 | CN41: =CN35/CM35-1 -> 0.022222222 | CO41: =CO35/CN35-1 -> 0.1342155 | CP41: =CP35/CO35-1 -> 0.11916667 | CQ41: =CQ35/CP35-1 -> 0.14780343
B42: Lat Am + Canada Revenue Growth Y/y | AY42: =AY36/AU36-1 -> -0.04494382 | AZ42: =AZ36/AV36-1 -> 0.8627451 | BA42: =BA36/AW36-1 -> 0.28571429 | BB42: =BB36/AX36-1 -> 0.18888889 | BC42: =BC36/AY36-1 -> 0.25882353 | BD42: =BD36/AZ36-1 -> 0.26315789 | BE42: =BE36/BA36-1 -> 0.2020202 | BF42: =BF36/BB36-1 -> 0.14953271 | ... BT42: =BT36/BP36-1 -> 0.21893491 | CL42: =CL36/CK36-1 -> -0.22278481 | CM42: =CM36/CL36-1 -> 0.25732899 | CN42: =CN36/CM36-1 -> 0.21502591 | CO42: =CO36/CN36-1 -> 0.19189765 | CP42: =CP36/CO36-1 -> 0.11449016 | CQ42: =CQ36/CP36-1 -> 0.08988764
B43: Ttl Revenue Growth Y/y | AY43: =AY37/AU37-1 -> 0.082186394 | AZ43: =AZ37/AV37-1 -> 0.53619571 | BA43: =BA37/AW37-1 -> 0.10267018 | BB43: =BB37/AX37-1 -> 0.15472674 | BC43: =BC37/AY37-1 -> 0.099563953 | BD43: =BD37/AZ37-1 -> 0.054273643 | BE43: =BE37/BA37-1 -> 0.081173261 | BF43: =BF37/BB37-1 -> 0.036776463 | ... BT43: =BT37/BP37-1 -> 0.075281565 | CL43: =CL37/CK37-1 -> -0.076571961 | CM43: =CM37/CL37-1 -> 0.19923333 | CN43: =CN37/CM37-1 -> 0.06679004 | CO43: =CO37/CN37-1 -> 0.12285129 | CP43: =CP37/CO37-1 -> 0.17605337 | CQ43: =CQ37/CP37-1 -> 0.19872216
B45: U.S. % of Revenues | AU45: =AU33/AU37 -> 0.57097916 | AV45: =AV33/AV37 -> 0.52820769 | AW45: =AW33/AW37 -> 0.56261753 | AX45: =AX33/AX37 -> 0.55465288 | AY45: =AY33/AY37 -> 0.57303779 | AZ45: =AZ33/AZ37 -> 0.58498538 | BA45: =BA33/BA37 -> 0.58867667 | BB45: =BB33/BB37 -> 0.57499201 | ... BT45: =BT33/BT37 -> 0.62954796 | CK45: =CK33/CK37 -> 0.56795529 | CL45: =CL33/CL37 -> 0.55563402 | CM45: =CM33/CM37 -> 0.58050135 | CN45: =CN33/CN37 -> 0.60179782 | CO45: =CO33/CO37 -> 0.59164326 | CP45: =CP33/CP37 -> 0.60966143 | CQ45: =CQ33/CQ37 -> 0.6407472
B46: Euro, Mid. East, Afr % of Revenues | AU46: =AU34/AU37 -> 0.21706646 | AV46: =AV34/AV37 -> 0.20768847 | AW46: =AW34/AW37 -> 0.20308387 | AX46: =AX34/AX37 -> 0.21750369 | AY46: =AY34/AY37 -> 0.21947674 | AZ46: =AZ34/AZ37 -> 0.21514462 | BA46: =BA34/BA37 -> 0.20122783 | BB46: =BB34/BB37 -> 0.21170451 | ... BT46: =BT34/BT37 -> 0.17126057 | CK46: =CK34/CK37 -> 0.21089893 | CL46: =CL34/CL37 -> 0.2115404 | CM46: =CM34/CM37 -> 0.21181023 | CN46: =CN34/CN37 -> 0.19917994 | CO46: =CO34/CO37 -> 0.2005618 | CP46: =CP34/CP37 -> 0.19275094 | CQ46: =CQ34/CQ37 -> 0.17185554
B47: A-Pac % of Revenues | AU47: =AU35/AU37 -> 0.16083366 | AV47: =AV35/AV37 -> 0.20469296 | AW47: =AW35/AW37 -> 0.17751034 | AX47: =AX35/AX37 -> 0.18094535 | AY47: =AY35/AY37 -> 0.171875 | AZ47: =AZ35/AZ37 -> 0.16899578 | BA47: =BA35/BA37 -> 0.17633015 | BB47: =BB35/BB37 -> 0.17908539 | ... BT47: =BT35/BT37 -> 0.16133774 | CK47: =CK35/CK37 -> 0.17680484 | CL47: =CL35/CL37 -> 0.17966307 | CM47: =CM35/CM37 -> 0.17412517 | CN47: =CN35/CN37 -> 0.16685065 | CO47: =CO35/CO37 -> 0.16853933 | CP47: =CP35/CP37 -> 0.16038693 | CQ47: =CQ35/CQ37 -> 0.1535741
B48: Lat Am + Canada % of Revenues | AU48: =AU36/AU37 -> 0.034998034 | AV48: =AV36/AV37 -> 0.025461807 | AW48: =AW36/AW37 -> 0.028958255 | AX48: =AX36/AX37 -> 0.03323486 | AY48: =AY36/AY37 -> 0.030886628 | AZ48: =AZ36/AZ37 -> 0.030874228 | BA48: =BA36/BA37 -> 0.033765348 | BB48: =BB36/BB37 -> 0.0342181 | ... BT48: =BT36/BT37 -> 0.03785373 | CK48: =CK36/CK37 -> 0.036795529 | CL48: =CL36/CL37 -> 0.030969434 | CM48: =CM36/CM37 -> 0.032469717 | CN48: =CN36/CN37 -> 0.036981549 | CO48: =CO36/CO37 -> 0.039255618 | CP48: =CP36/CP37 -> 0.037200693 | CQ48: =CQ36/CQ37 -> 0.033823163
B50: Revenues | C50: 2010 | D50: 2074 | E50: 2025 | F50: 2079 | G50: 1960 | H50: 1928 | I50: 1916 | J50: 2002 | K50: 1925 | L50: 1975 | M50: 1874 | N50: 1848 | O50: 1866 | P50: 1828 | Q50: 1735 | R50: 1820 | S50: 1761 | T50: 1809 | U50: 1735 | V50: 1838 | W50: 1774 | X50: 1873 | Y50: 1846 | Z50: 1887 | AA50: 1768 | AB50: 1843 | AC50: 1888 | AD50: 1978 | AE50: 1964 | AF50: 2126 | AG50: 2105 | AH50: 2191 | AI50: 2160 | AJ50: 2257 | AK50: 2222 | AL50: 2409 | AM50: 2379 | AN50: 2490 | AO50: 2393 | AP50: 2561 | AQ50: 2493 | AR50: 2631 | AS50: 2707 | AT50: 2904 | AU50: =AU37 -> 2543 | AV50: =AV37 -> 2003 | AW50: =AW37 -> 2659 | AX50: =AX37 -> 2708 | AY50: =AY37 -> 2752 | AZ50: =AZ37 -> 3077 | BA50: =BA37 -> 2932 | BB50: =BB37 -> 3127 | ... BT50: =BT37 -> 5442 | CA50: =SUM(C50:F50) -> 8188 | CB50: =SUM(G50:J50) -> 7806 | CC50: =SUM(K50:N50) -> 7622 | CD50: =SUM(O50:R50) -> 7249 | CE50: =SUM(S50:V50) -> 7143 | CF50: =SUM(W50:Z50) -> 7380 | CG50: =SUM(AA50:AD50) -> 7477 | CH50: =SUM(AE50:AH50) -> 8386 | CI50: =SUM(AI50:AL50) -> 9048 | CJ50: =SUM(AM50:AP50) -> 9823 | CK50: =SUM(AQ50:AT50) -> 10735 | CL50: =SUM(AU50:AX50) -> 9913 | CM50: =SUM(AY50:BB50) -> 11888 | CN50: =SUM(BC50:BF50) -> 12682 | CO50: =SUM(BG50:BJ50) -> 14240 | CP50: =SUM(BK50:BN50) -> 16747 | CQ50: =SUM(BO50:BR50) -> 20075 | CR50: =CR15 -> 21697.69 | CS50: =CS15 -> 23010.07 | CT50: =CT15 -> 25000.25 | CU50: =CU15 -> 26902.536 | CV50: =CV15 -> 28739.535 | CW50: =CW15 -> 30498.693 | CX50: =CX15 -> 32163.466 | CY50: =CY15 -> 33713.768 | ... DA50: =DA15 -> 36399.628
B51: COGS | C51: 607 | D51: 630 | E51: 629 | F51: 710 | G51: 663 | H51: 654 | I51: 623 | J51: 659 | K51: 631 | L51: 688 | M51: 680 | N51: 660 | O51: 631 | P51: 578 | Q51: 558 | R51: 582 | S51: 578 | T51: 530 | U51: 510 | V51: 556 | W51: 537 | X51: 563 | Y51: 550 | Z51: 560 | AA51: 520 | AB51: 540 | AC51: 539 | AD51: 574 | AE51: 573 | AF51: 639 | AG51: 594 | AH51: 618 | AI51: 650 | AJ51: 632 | AK51: 637 | AL51: 674 | AM51: 672 | AN51: 739 | AO51: 672 | AP51: 730 | AQ51: 730 | AR51: 758 | AS51: 777 | AT51: 851 | AU51: 806 | AV51: 791 | AW51: 869 | AX51: =3465-SUM(AU51:AW51) -> 999 | AY51: 894 | AZ51: 945 | BA51: 900 | BB51: =3711-SUM(AY51:BA51) -> 972 | BC51: 955 | BD51: 1011 | BE51: 979 | BF51: =3956-SUM(BC51:BE51) -> 1011 | BG51: 1040 | BH51: 1058 | BI51: 1101 | BJ51: =4345-SUM(BG51:BI51) -> 1146 | BK51: 1209 | BL51: 1270 | BM51: 1312 | BN51: =5257-SUM(BK51:BM51) -> 1466 | BO51: 1453 | BP51: 1637 | BQ51: 1523 | BR51: 1608 | BS51: 1590 | BT51: 1594 | CA51: =SUM(C51:F51) -> 2576 | CB51: =SUM(G51:J51) -> 2599 | CC51: =SUM(K51:N51) -> 2659 | CD51: =SUM(O51:R51) -> 2349 | CE51: =SUM(S51:V51) -> 2174 | CF51: =SUM(W51:Z51) -> 2210 | CG51: =SUM(AA51:AD51) -> 2173 | CH51: =SUM(AE51:AH51) -> 2424 | CI51: =SUM(AI51:AL51) -> 2593 | CJ51: =SUM(AM51:AP51) -> 2813 | CK51: =SUM(AQ51:AT51) -> 3116 | CL51: =SUM(AU51:AX51) -> 3465 | CM51: =SUM(AY51:BB51) -> 3711 | CN51: =SUM(BC51:BF51) -> 3956 | CO51: =SUM(BG51:BJ51) -> 4345 | CP51: =SUM(BK51:BN51) -> 5257 | CQ51: =SUM(BO51:BR51) -> 6221 | CR51: =CR50*(1-CR74) -> 6726.2839 | CS51: =CS50*(1-CS74) -> 7018.0713 | CT51: =CT50*(1-CT74) -> 7550.0756 | CU51: =CU50*(1-CU74) -> 8070.7608 | CV51: =CV50*(1-CV74) -> 8550.0116 | CW51: =CW50*(1-CW74) -> 8997.1143 | CX51: =CX50*(1-CX74) -> 9407.8138 | CY51: =CY50*(1-CY74) -> 9776.9926 | ... DA51: =DA50*(1-DA74) -> 10555.892
B52: GP | C52: =C50-C51 -> 1403 | D52: =D50-D51 -> 1444 | E52: =E50-E51 -> 1396 | F52: =F50-F51 -> 1369 | G52: =G50-G51 -> 1297 | H52: =H50-H51 -> 1274 | I52: =I50-I51 -> 1293 | J52: =J50-J51 -> 1343 | ... BT52: =BT50-BT51 -> 3848 | CA52: =SUM(C52:F52) -> 5612 | CB52: =SUM(G52:J52) -> 5207 | CC52: =SUM(K52:N52) -> 4963 | CD52: =SUM(O52:R52) -> 4900 | CE52: =SUM(S52:V52) -> 4969 | CF52: =SUM(W52:Z52) -> 5170 | CG52: =SUM(AA52:AD52) -> 5304 | CH52: =SUM(AE52:AH52) -> 5962 | CI52: =SUM(AI52:AL52) -> 6455 | CJ52: =SUM(AM52:AP52) -> 7010 | CK52: =SUM(AQ52:AT52) -> 7619 | CL52: =SUM(AU52:AX52) -> 6448 | CM52: =SUM(AY52:BB52) -> 8177 | CN52: =SUM(BC52:BF52) -> 8726 | CO52: =SUM(BG52:BJ52) -> 9895 | CP52: =SUM(BK52:BN52) -> 11490 | CQ52: =SUM(BO52:BR52) -> 13854 | CR52: =CR50-CR51 -> 14971.406 | CS52: =CS50-CS51 -> 15991.998 | CT52: =CT50-CT51 -> 17450.175 | CU52: =CU50-CU51 -> 18831.775 | CV52: =CV50-CV51 -> 20189.523 | CW52: =CW50-CW51 -> 21501.578 | CX52: =CX50-CX51 -> 22755.652 | CY52: =CY50-CY51 -> 23936.775 | ... DA52: =DA50-DA51 -> 25843.736
B53: SG&A | C53: 651 | D53: 671 | E53: 665 | F53: 648 | G53: 628 | H53: 634 | I53: 634 | J53: 686 | K53: 602 | L53: 649 | M53: 635 | N53: 608 | O53: 669 | P53: 649 | Q53: 569 | R53: 642 | S53: 608 | T53: 661 | U53: 658 | V53: 751 | W53: 666 | X53: 743 | Y53: 741 | Z53: 752 | AA53: 668 | AB53: 700 | AC53: 729 | AD53: 776 | AE53: 716 | AF53: 779 | AG53: 772 | AH53: 832 | AI53: 794 | AJ53: 815 | AK53: 800 | AL53: 885 | AM53: 860 | AN53: 886 | AO53: 870 | AP53: 953 | AQ53: 869 | AR53: 968 | AS53: 1012 | AT53: 1092 | AU53: 978 | AV53: 798 | AW53: 984 | AX53: =3787-SUM(AU53:AW53) -> 1027 | AY53: 1019 | AZ53: 1121 | BA53: 1066 | BB53: =4359-SUM(AY53:BA53) -> 1153 | BC53: 1060 | BD53: 1165 | BE53: 1132 | BF53: =4520-SUM(BC53:BE53) -> 1163 | BG53: 1215 | BH53: 1354 | BI53: 1242 | BJ53: =5190-SUM(BG53:BI53) -> 1379 | BK53: 1364 | BL53: 1446 | BM53: 1562 | BN53: =5984-SUM(BK53:BM53) -> 1612 | BO53: 1597 | BP53: 1716 | BQ53: 1741 | BR53: 1834 | BS53: 1781 | BT53: 1803 | CA53: =SUM(C53:F53) -> 2635 | CB53: =SUM(G53:J53) -> 2582 | CC53: =SUM(K53:N53) -> 2494 | CD53: =SUM(O53:R53) -> 2529 | CE53: =SUM(S53:V53) -> 2678 | CF53: =SUM(W53:Z53) -> 2902 | CG53: =SUM(AA53:AD53) -> 2873 | CH53: =SUM(AE53:AH53) -> 3099 | CI53: =SUM(AI53:AL53) -> 3294 | CJ53: =SUM(AM53:AP53) -> 3569 | CK53: =SUM(AQ53:AT53) -> 3941 | CL53: =SUM(AU53:AX53) -> 3787 | CM53: =SUM(AY53:BB53) -> 4359 | CN53: =SUM(BC53:BF53) -> 4520 | CO53: =SUM(BG53:BJ53) -> 5190 | CP53: =SUM(BK53:BN53) -> 5984 | CQ53: =SUM(BO53:BR53) -> 6888 | CR53: =CR50*CR75 -> 7572.4938 | CS53: =CS50*CS75 -> 7984.4942 | CT53: =CT50*CT75 -> 8650.0866 | CU53: =CU50*CU75 -> 9281.3749 | CV53: =CV50*CV75 -> 9886.4 | CW53: =CW50*CW75 -> 10461.052 | CX53: =CX50*CX75 -> 10999.905 | CY53: =CY50*CY75 -> 11496.395 | ... DA53: =DA50*DA75 -> 12375.873
B54: R&D | C54: 257 | D54: 280 | E54: 258 | F54: 261 | G54: 253 | H54: 232 | I54: 230 | J54: 224 | K54: 212 | L54: 223 | M54: 229 | N54: 231 | O54: 215 | P54: 213 | Q54: 220 | R54: 238 | S54: 204 | T54: 223 | U54: 217 | V54: 217 | W54: 191 | X54: 206 | Y54: 212 | Z54: 208 | AA54: 192 | AB54: 220 | AC54: 221 | AD54: 243 | AE54: 210 | AF54: 222 | AG54: 232 | AH54: 256 | AI54: 235 | AJ54: 244 | AK54: 254 | AL54: 264 | AM54: 261 | AN54: 275 | AO54: 289 | AP54: 288 | AQ54: 280 | AR54: 280 | AS54: 306 | AT54: 308 | AU54: 300 | AV54: 242 | AW54: 315 | AX54: =1143-SUM(AU54:AW54) -> 286 | AY54: 276 | AZ54: 298 | BA54: 310 | BB54: =1204-SUM(AY54:BA54) -> 320 | BC54: 319 | BD54: 335 | BE54: 339 | BF54: =1323-SUM(BC54:BE54) -> 330 | BG54: 337 | BH54: 359 | BI54: 356 | BJ54: =1414-SUM(BG54:BI54) -> 362 | BK54: 366 | BL54: 383 | BM54: 407 | BN54: =1615-SUM(BK54:BM54) -> 459 | BO54: 443 | BP54: 526 | BQ54: 514 | BR54: 569 | BS54: 516 | BT54: 554 | CA54: =SUM(C54:F54) -> 1056 | CB54: =SUM(G54:J54) -> 939 | CC54: =SUM(K54:N54) -> 895 | CD54: =SUM(O54:R54) -> 886 | CE54: =SUM(S54:V54) -> 861 | CF54: =SUM(W54:Z54) -> 817 | CG54: =SUM(AA54:AD54) -> 876 | CH54: =SUM(AE54:AH54) -> 920 | CI54: =SUM(AI54:AL54) -> 997 | CJ54: =SUM(AM54:AP54) -> 1113 | CK54: =SUM(AQ54:AT54) -> 1174 | CL54: =SUM(AU54:AX54) -> 1143 | CM54: =SUM(AY54:BB54) -> 1204 | CN54: =SUM(BC54:BF54) -> 1323 | CO54: =SUM(BG54:BJ54) -> 1414 | CP54: =SUM(BK54:BN54) -> 1615 | CQ54: =SUM(BO54:BR54) -> 2052 | CR54: =CR50*(CR76) -> 2256.5598 | CS54: =CS50*(CS76) -> 2485.0875 | CT54: =CT50*(CT76) -> 2750.0275 | CU54: =CU50*(CU76) -> 3013.084 | CV54: =CV50*(CV76) -> 3276.307 | CW54: =CW50*(CW76) -> 3446.3523 | CX54: =CX50*(CX76) -> 3602.3082 | CY54: =CY50*(CY76) -> 3742.2282 | ... DA54: =DA50*(DA76) -> 3967.5594
B55: Royalties | AU55: 12 | AV55: 8 | AW55: 12 | AX55: =45-SUM(AU55:AW55) -> 13 | AY55: 12 | AZ55: 12 | BA55: 14 | BB55: =49-SUM(AY55:BA55) -> 11 | BC55: 12 | BD55: 11 | BE55: 11 | BF55: =47-SUM(BC55:BE55) -> 13 | BG55: 11 | BH55: 12 | BI55: 11 | BJ55: =46-SUM(BG55:BI55) -> 12 | BK55: 10 | BL55: 9 | BM55: 5 | BN55: =33-SUM(BK55:BM55) -> 9 | BO55: 14 | BP55: 14 | BQ55: 12 | BR55: 6 | BS55: 12 | BT55: 12 | CA55: 0 | CB55: 0 | CC55: 0 | CD55: 0 | CE55: 0 | CF55: 0 | CG55: 0 | CH55: 0 | CI55: 0 | CJ55: 0 | CK55: 0 | CL55: =SUM(AU55:AX55) -> 45 | CM55: =SUM(AY55:BB55) -> 49 | CN55: =SUM(BC55:BF55) -> 47 | CO55: =SUM(BG55:BJ55) -> 46 | CP55: =SUM(BK55:BN55) -> 33 | CQ55: =SUM(BO55:BR55) -> 46 | CR55: =CQ55*1.035 -> 47.61 | CS55: =CR55*1.035 -> 49.27635 | CT55: =CS55*1.035 -> 51.001022 | CU55: =CT55*1.035 -> 52.786058 | CV55: =CU55*1.035 -> 54.63357 | CW55: =CV55*1.035 -> 56.545745 | CX55: =CW55*1.035 -> 58.524846 | CY55: =CX55*1.035 -> 60.573216 | ... DA55: =CZ55*1.035 -> 64.887543
B56: Amortization | AU56: 201 | AV56: 197 | AW56: 197 | AX56: =789-SUM(AU56:AW56) -> 194 | AY56: 185 | AZ56: 180 | BA56: 184 | BB56: =741-SUM(AY56:BA56) -> 192 | BC56: 198 | BD56: 204 | BE56: 202 | BF56: =803-SUM(BC56:BE56) -> 199 | BG56: 203 | BH56: 210 | BI56: 208 | BJ56: =828-SUM(BG56:BI56) -> 207 | BK56: 214 | BL56: 213 | BM56: 205 | BN56: =856-SUM(BK56:BM56) -> 224 | BO56: 219 | BP56: 225 | BQ56: 225 | BR56: 228 | BS56: 232 | BT56: 233 | CA56: 0 | CB56: 0 | CC56: 0 | CD56: 0 | CE56: 0 | CF56: 0 | CG56: 0 | CH56: 0 | CI56: 0 | CJ56: 0 | CK56: 0 | CL56: =SUM(AU56:AX56) -> 789 | CM56: =SUM(AY56:BB56) -> 741 | CN56: =SUM(BC56:BF56) -> 803 | CO56: =SUM(BG56:BJ56) -> 828 | CP56: =SUM(BK56:BN56) -> 856 | CQ56: =SUM(BO56:BR56) -> 897 | CR56: =CQ56*1.025 -> 919.425 | CS56: =CR56*1.025 -> 942.41062 | CT56: =CS56*1.025 -> 965.97089 | CU56: =CT56*1.025 -> 990.12016 | CV56: =CU56*1.025 -> 1014.8732 | CW56: =CV56*1.025 -> 1040.245 | CX56: =CW56*1.025 -> 1066.2511 | CY56: =CX56*1.025 -> 1092.9074 | ... DA56: =CZ56*1.025 -> 1148.2358
B57: Intangible Asset Impairment | AU57: 198 | AV57: 34 | AW57: 219 | AX57: =460-SUM(AU57:AW57) -> 9 | AY57: -6 | AZ57: 45 | BA57: 128 | BB57: =370-SUM(AY57:BA57) -> 203 | BC57: 12 | BD57: 7 | BE57: 125 | BF57: =132-SUM(BC57:BE57) -> -12 | BG57: 0 | BH57: 57 | BI57: 1 | BJ57: =58-SUM(BG57:BI57) -> 0 | BK57: 17 | BL57: 276 | BM57: 0 | BN57: =386-SUM(BK57:BM57) -> 93 | BO57: 0 | BP57: 46 | BQ57: 0 | BR57: 0 | BS57: 0 | BT57: 0 | CA57: 0 | CB57: 0 | CC57: 0 | CD57: 0 | CE57: 0 | CF57: 0 | CG57: 0 | CH57: 0 | CI57: 0 | CJ57: 0 | CK57: 0 | CL57: =SUM(AU57:AX57) -> 460 | CM57: =SUM(AY57:BB57) -> 370 | CN57: =SUM(BC57:BF57) -> 132 | CO57: =SUM(BG57:BJ57) -> 58 | CP57: =SUM(BK57:BN57) -> 386 | CQ57: =SUM(BO57:BR57) -> 46 | CR57: =CQ57*1.03 -> 47.38 | CS57: =CR57*1.03 -> 48.8014 | CT57: =CS57*1.03 -> 50.265442 | CU57: =CT57*1.03 -> 51.773405 | CV57: =CU57*1.03 -> 53.326607 | CW57: =CV57*1.03 -> 54.926406 | CX57: =CW57*1.03 -> 56.574198 | CY57: =CX57*1.03 -> 58.271424 | ... DA57: =CZ57*1.03 -> 61.820153
B58: Contingent Consideration | AU58: -108 | AV58: 0 | AW58: 6 | AX58: =-100-SUM(AU58:AW58) -> 2 | AY58: 5 | AZ58: -85 | BA58: -26 | BB58: =-136-SUM(AY58:BA58) -> -30 | BC58: 4 | BD58: 36 | BE58: 20 | BF58: =35-SUM(BC58:BE58) -> -25 | BG58: 0 | BH58: 19 | BI58: 11 | BJ58: =58-SUM(BG58:BI58) -> 28 | BK58: 0 | BL58: 2 | BM58: -23 | BN58: =-5-SUM(BK58:BM58) -> 16 | BO58: 6 | BP58: -5 | BQ58: 11 | BR58: 6 | BS58: -30 | BT58: -16 | CA58: 0 | CB58: 0 | CC58: 0 | CD58: 0 | CE58: 0 | CF58: 0 | CG58: 0 | CH58: 0 | CI58: 0 | CJ58: 0 | CK58: 0 | CL58: =SUM(AU58:AX58) -> -100 | CM58: =SUM(AY58:BB58) -> -136 | CN58: =SUM(BC58:BF58) -> 35 | CO58: =SUM(BG58:BJ58) -> 58 | CP58: =SUM(BK58:BN58) -> -5 | CQ58: =SUM(BO58:BR58) -> 18 | CR58: 0 | CS58: 0 | CT58: 0 | CU58: 0 | CV58: 0 | CW58: 0 | CX58: 0 | CY58: 0 | CZ58: 0 | DA58: 0
B59: Restructuring Charges | AU59: 10 | AV59: 4 | AW59: 2 | AX59: =52-SUM(AU59:AW59) -> 36 | AY59: 3 | AZ59: 3 | BA59: 9 | BB59: =40-SUM(AY59:BA59) -> 25 | BC59: 0 | BD59: 10 | BE59: 4 | BF59: =24-SUM(BC59:BE59) -> 10 | BG59: 11 | BH59: 16 | BI59: 15 | BJ59: =69-SUM(BG59:BI59) -> 27 | BK59: 2 | BL59: 1 | BM59: 8 | BN59: =16-SUM(BK59:BM59) -> 5 | BO59: 10 | BP59: 83 | BQ59: -9 | BR59: 16 | BS59: 2 | BT59: 8 | CA59: 0 | CB59: 0 | CC59: 0 | CD59: 0 | CE59: 0 | CF59: 0 | CG59: 0 | CH59: 0 | CI59: 0 | CJ59: 0 | CK59: 0 | CL59: =SUM(AU59:AX59) -> 52 | CM59: =SUM(AY59:BB59) -> 40 | CN59: =SUM(BC59:BF59) -> 24 | CO59: =SUM(BG59:BJ59) -> 69 | CP59: =SUM(BK59:BN59) -> 16 | CQ59: =SUM(BO59:BR59) -> 100 | CR59: 0 | CS59: 0 | CT59: 0 | CU59: 0 | CV59: 0 | CW59: 0 | CX59: 0 | CY59: 0 | CZ59: 0 | DA59: 0
B60: Litigation-Related net Charges | AU60: 0 | AV60: 0 | AW60: 260 | AX60: =278-SUM(AU60:AW60) -> 18 | AY60: -6 | AZ60: 298 | BA60: 0 | BB60: =430-SUM(AY60:BA60) -> 138 | BC60: 0 | BD60: 42 | BE60: 0 | BF60: =173-SUM(BC60:BE60) -> 131 | BG60: 20 | BH60: 0 | BI60: -111 | BJ60: =-111-SUM(BG60:BI60) -> -20 | BK60: 0 | BL60: 0 | BM60: 0 | BN60: =0-SUM(BK60:BM60) -> 0 | BO60: 0 | BP60: 0 | BQ60: 0 | BR60: 194 | BS60: 0 | BT60: 76 | CA60: 0 | CB60: 0 | CC60: 0 | CD60: 0 | CE60: 0 | CF60: 0 | CG60: 0 | CH60: 0 | CI60: 0 | CJ60: 0 | CK60: 0 | CL60: =SUM(AU60:AX60) -> 278 | CM60: =SUM(AY60:BB60) -> 430 | CN60: =SUM(BC60:BF60) -> 173 | CO60: =SUM(BG60:BJ60) -> -111 | CP60: =SUM(BK60:BN60) -> 0 | CQ60: =SUM(BO60:BR60) -> 194 | CR60: 0 | CS60: 0 | CT60: 0 | CU60: 0 | CV60: 0 | CW60: 0 | CX60: 0 | CY60: 0 | CZ60: 0 | DA60: 0
B61: Loss on Disposal of Assets | AU61: 0 | AV61: 0 | AW61: 0 | AX61: =74-SUM(AU61:AW61) -> 74 | AY61: 0 | AZ61: -2 | BA61: -40 | BB61: =-78-SUM(AY61:BA61) -> -36 | BC61: 0 | BD61: 0 | BE61: 0 | BF61: =22-SUM(BC61:BE61) -> 22 | BG61: 0 | BH61: 0 | BI61: 0 | BJ61: =0-SUM(BG61:BI61) -> 0 | BK61: 0 | BL61: 0 | BM61: 0 | BN61: =0-SUM(BK61:BM61) -> 0 | BO61: 0 | BP61: 0 | BQ61: 0 | BR61: 0 | BS61: 0 | BT61: 0 | CA61: 0 | CB61: 0 | CC61: 0 | CD61: 0 | CE61: 0 | CF61: 0 | CG61: 0 | CH61: 0 | CI61: 0 | CJ61: 0 | CK61: 0 | CL61: =SUM(AU61:AX61) -> 74 | CM61: =SUM(AY61:BB61) -> -78 | CN61: =SUM(BC61:BF61) -> 22 | CO61: =SUM(BG61:BJ61) -> 0 | CP61: =SUM(BK61:BN61) -> 0 | CQ61: =SUM(BO61:BR61) -> 0 | CR61: 0 | CS61: 0 | CT61: 0 | CU61: 0 | CV61: 0 | CW61: 0 | CX61: 0 | CY61: 0 | CZ61: 0 | DA61: 0
B62: Operating Income | C62: 11 | D62: 275 | E62: 51 | F62: -1231 | G62: -1486 | H62: 231 | I62: 251 | J62: 348 | K62: 322 | L62: 237 | M62: 174 | N62: 171 | O62: 196 | P62: -3587 | Q62: -594 | R62: 117 | S62: -330 | T62: 220 | U62: 103 | V62: 127 | W62: 197 | X62: -69 | Y62: 64 | Z62: -493 | AA62: 24 | AB62: 219 | AC62: -299 | AD62: -227 | AE62: 293 | AF62: -334 | AG62: 348 | AH62: 140 | AI62: 364 | AJ62: 225 | AK62: 377 | AL62: 319 | AM62: 407 | AN62: 392 | AO62: 388 | AP62: 319 | AQ62: 541 | AR62: 384 | AS62: 383 | AT62: 210 | AU62: =AU52-SUM(AU53:AU61) -> 146 | AV62: =AV52-SUM(AV53:AV61) -> -71 | AW62: =AW52-SUM(AW53:AW61) -> -205 | AX62: =AX52-SUM(AX53:AX61) -> 50 | AY62: =AY52-SUM(AY53:AY61) -> 370 | AZ62: =AZ52-SUM(AZ53:AZ61) -> 262 | BA62: =BA52-SUM(BA53:BA61) -> 387 | BB62: =BB52-SUM(BB53:BB61) -> 179 | ... BT62: =BT52-SUM(BT53:BT61) -> 1178 | CA62: =SUM(C62:F62) -> -894 | CB62: =SUM(G62:J62) -> -656 | CC62: =SUM(K62:N62) -> 904 | CD62: =SUM(O62:R62) -> -3868 | CE62: =SUM(S62:V62) -> 120 | CF62: =SUM(W62:Z62) -> -301 | CG62: =SUM(AA62:AD62) -> -283 | CH62: =SUM(AE62:AH62) -> 447 | CI62: =SUM(AI62:AL62) -> 1285 | CJ62: =SUM(AM62:AP62) -> 1506 | CK62: =SUM(AQ62:AT62) -> 1518 | CL62: =SUM(AU62:AX62) -> -80 | CM62: =SUM(AY62:BB62) -> 1198 | CN62: =SUM(BC62:BF62) -> 1647 | CO62: =SUM(BG62:BJ62) -> 2343 | CP62: =SUM(BK62:BN62) -> 2605 | CQ62: =SUM(BO62:BR62) -> 3613 | CR62: =CR52-SUM(CR53:CR61) -> 4127.9375 | CS62: =CS52-SUM(CS53:CS61) -> 4481.9283 | CT62: =CT52-SUM(CT53:CT61) -> 4982.8232 | CU62: =CU52-SUM(CU53:CU61) -> 5442.6366 | CV62: =CV52-SUM(CV53:CV61) -> 5903.9829 | CW62: =CW52-SUM(CW53:CW61) -> 6442.4573 | CX62: =CX52-SUM(CX53:CX61) -> 6972.0884 | CY62: =CY52-SUM(CY53:CY61) -> 7486.4 | ... DA62: =DA52-SUM(DA53:DA61) -> 8225.3593
B63: Interest Income (Expenses) | AU63: -88 | AV63: -91 | AW63: -86 | AX63: =-361-SUM(AU63:AW63) -> -96 | AY63: -82 | AZ63: -86 | BA63: -86 | BB63: =-341-SUM(AY63:BA63) -> -87 | BC63: -279 | BD63: -64 | BE63: -63 | BF63: =-470-SUM(BC63:BE63) -> -64 | BG63: -65 | BH63: -70 | BI63: -66 | BJ63: =-265-SUM(BG63:BI63) -> -64 | BK63: -69 | BL63: -77 | BM63: -79 | BN63: =-305-SUM(BK63:BM63) -> -80 | BO63: -82 | BP63: -90 | BQ63: -87 | BR63: -90 | BS63: -90 | BT63: -96 | CA63: 0 | CB63: 0 | CC63: 0 | CD63: 0 | CE63: 0 | CF63: 0 | CG63: 0 | CH63: 0 | CI63: 0 | CJ63: 0 | CK63: 0 | CL63: =SUM(AU63:AX63) -> -361 | CM63: =SUM(AY63:BB63) -> -341 | CN63: =SUM(BC63:BF63) -> -470 | CO63: =SUM(BG63:BJ63) -> -265 | CP63: =SUM(BK63:BN63) -> -305 | CQ63: =SUM(BO63:BR63) -> -349 | CR63: =-CQ98*($DF$98) -> -972.7375 | CS63: =-CR98*($DF$98) -> -2110.2375 | CT63: =-CS98*($DF$98) -> -1925.5917 | CU63: =-CT98*($DF$98) -> -1757.1024 | CV63: =-CU98*($DF$98) -> -1603.356 | CW63: =-CV98*($DF$98) -> -1463.0623 | CX63: =-CW98*($DF$98) -> -1335.0444 | CY63: =-CX98*($DF$98) -> -1218.228 | ... DA63: =-CZ98*($DF$98) -> -1014.3652
B64: Other Income | C64: -108 | D64: -95 | E64: -95 | F64: -116 | G64: -89 | H64: -112 | I64: -88 | J64: -118 | K64: -49 | L64: -79 | M64: -63 | N64: -71 | O64: -73 | P64: -31 | Q64: -69 | R64: -66 | S64: -64 | T64: -68 | U64: -143 | V64: -68 | W64: -51 | X64: -35 | Y64: -61 | Z64: -61 | AA64: -75 | AB64: -114 | AC64: -68 | AD64: -110 | AE64: -65 | AF64: -63 | AG64: -91 | AH64: -51 | AI64: -59 | AJ64: -134 | AK64: -68 | AL64: -92 | AM64: -84 | AN64: -45 | AO64: 68 | AP64: -24 | AQ64: -84 | AR64: -239 | AS64: -292 | AT64: -216 | AU64: -36 | AV64: -18 | AW64: 64 | AX64: =362-SUM(AU64:AW64) -> 352 | AY64: 37 | AZ64: -27 | BA64: 181 | BB64: =218-SUM(AY64:BA64) -> 27 | BC64: -31 | BD64: -14 | BE64: -50 | BF64: =-38-SUM(BC64:BE64) -> 57 | BG64: -43 | BH64: -18 | BI64: -17 | BJ64: =-93-SUM(BG64:BI64) -> -15 | BK64: 2 | BL64: -23 | BM64: 14 | BN64: =-16-SUM(BK64:BM64) -> -9 | BO64: -34 | BP64: 213 | BQ64: -22 | BR64: -36 | BS64: 151 | BT64: -22 | CA64: =SUM(C64:F64) -> -414 | CB64: =SUM(G64:J64) -> -407 | CC64: =SUM(K64:N64) -> -262 | CD64: =SUM(O64:R64) -> -239 | CE64: =SUM(S64:V64) -> -343 | CF64: =SUM(W64:Z64) -> -208 | CG64: =SUM(AA64:AD64) -> -367 | CH64: =SUM(AE64:AH64) -> -270 | CI64: =SUM(AI64:AL64) -> -353 | CJ64: =SUM(AM64:AP64) -> -85 | CK64: =SUM(AQ64:AT64) -> -831 | CL64: =SUM(AU64:AX64) -> 362 | CM64: =SUM(AY64:BB64) -> 218 | CN64: =SUM(BC64:BF64) -> -38 | CO64: =SUM(BG64:BJ64) -> -93 | CP64: =SUM(BK64:BN64) -> -16 | CQ64: =SUM(BO64:BR64) -> 121 | CR64: =(BS81+BS82)*($DK$81) -> 380.8 | CS64: =CR81*($DK$81) -> 405.9294 | CT64: =CS81*($DK$81) -> 613.6954 | CU64: =CT81*($DK$81) -> 882.04015 | CV64: =CU81*($DK$81) -> 1208.165 | CW64: =CV81*($DK$81) -> 1592.1278 | CX64: =CW81*($DK$81) -> 2044.5771 | CY64: =CX81*($DK$81) -> 2566.9273 | CZ64: =CY81*($DK$81) -> 3167.7141 | DA64: =CZ81*($DK$81) -> 3844.4313
B65: Pretax Income | C65: =C62+C63+C64 -> -97 | D65: =D62+D63+D64 -> 180 | E65: =E62+E63+E64 -> -44 | F65: =F62+F63+F64 -> -1347 | G65: =G62+G63+G64 -> -1575 | H65: =H62+H63+H64 -> 119 | I65: =I62+I63+I64 -> 163 | J65: =J62+J63+J64 -> 230 | ... BT65: =BT62+BT63+BT64 -> 1060 | CA65: =SUM(C65:F65) -> -1308 | CB65: =SUM(G65:J65) -> -1063 | CC65: =SUM(K65:N65) -> 642 | CD65: =SUM(O65:R65) -> -4107 | CE65: =SUM(S65:V65) -> -223 | CF65: =SUM(W65:Z65) -> -509 | CG65: =SUM(AA65:AD65) -> -650 | CH65: =SUM(AE65:AH65) -> 177 | CI65: =SUM(AI65:AL65) -> 932 | CJ65: =SUM(AM65:AP65) -> 1421 | CK65: =SUM(AQ65:AT65) -> 687 | CL65: =SUM(AU65:AX65) -> -79 | CM65: =SUM(AY65:BB65) -> 1075 | CN65: =SUM(BC65:BF65) -> 1139 | CO65: =SUM(BG65:BJ65) -> 1985 | CP65: =SUM(BK65:BN65) -> 2284 | CQ65: =SUM(BO65:BR65) -> 3385 | CR65: =CR62+SUM(CR63:CR64) -> 3536 | CS65: =CS62+SUM(CS63:CS64) -> 2777.6202 | CT65: =CT62+SUM(CT63:CT64) -> 3670.9269 | CU65: =CU62+SUM(CU63:CU64) -> 4567.5743 | CV65: =CV62+SUM(CV63:CV64) -> 5508.7919 | CW65: =CW62+SUM(CW63:CW64) -> 6571.5228 | CX65: =CX62+SUM(CX63:CX64) -> 7681.6212 | CY65: =CY62+SUM(CY63:CY64) -> 8835.0993 | ... DA65: =DA62+SUM(DA63:DA64) -> 11055.425
B66: Taxes | C66: -84 | D66: 22 | E66: 50 | F66: -271 | G66: 14 | H66: 21 | I66: -27 | J66: -6 | K66: 227 | L66: 12 | M66: -31 | N66: -7 | O66: 10 | P66: -40 | Q66: 1 | R66: -10 | S66: -40 | T66: 22 | U66: -35 | V66: -49 | W66: 13 | X66: -108 | Y66: -40 | Z66: -255 | AA66: -50 | AB66: 3 | AC66: -169 | AD66: -195 | AE66: 26 | AF66: -190 | AG66: 29 | AH66: -35 | AI66: 15 | AJ66: -55 | AK66: 26 | AL66: 842 | AM66: 26 | AN66: -209 | AO66: 24 | AP66: -90 | AQ66: 33 | AR66: -9 | AS66: -35 | AT66: -4002 | AU66: 11 | AV66: -33 | AW66: -72 | AX66: =2-SUM(AU66:AW66) -> 96 | AY66: -16 | AZ66: -37 | BA66: 63 | BB66: =36-SUM(AY66:BA66) -> 26 | BC66: 45 | BD66: 85 | BE66: 57 | BF66: =443-SUM(BC66:BE66) -> 256 | BG66: 130 | BH66: 156 | BI66: 106 | BJ66: =393-SUM(BG66:BI66) -> 1 | BK66: 115 | BL66: 98 | BM66: 200 | BN66: =436-SUM(BK66:BM66) -> 23 | BO66: 133 | BP66: 146 | BQ66: 184 | BR66: 30 | BS66: -177 | BT66: 155 | CA66: =SUM(C66:F66) -> -283 | CB66: =SUM(G66:J66) -> 2 | CC66: =SUM(K66:N66) -> 201 | CD66: =SUM(O66:R66) -> -39 | CE66: =SUM(S66:V66) -> -102 | CF66: =SUM(W66:Z66) -> -390 | CG66: =SUM(AA66:AD66) -> -411 | CH66: =SUM(AE66:AH66) -> -170 | CI66: =SUM(AI66:AL66) -> 828 | CJ66: =SUM(AM66:AP66) -> -249 | CK66: =SUM(AQ66:AT66) -> -4013 | CL66: =SUM(AU66:AX66) -> 2 | CM66: =SUM(AY66:BB66) -> 36 | CN66: =SUM(BC66:BF66) -> 443 | CO66: =SUM(BG66:BJ66) -> 393 | CP66: =SUM(BK66:BN66) -> 436 | CQ66: =SUM(BO66:BR66) -> 493 | CR66: =CR65*CR78 -> 35.36 | CS66: =CS65*CS78 -> 333.31443 | CT66: =CT65*CT78 -> 513.92977 | CU66: =CU65*CU78 -> 730.8119 | CV66: =CV65*CV78 -> 991.58254 | CW66: =CW65*CW78 -> 1248.5893 | CX66: =CX65*CX78 -> 1536.3242 | CY66: =CY65*CY78 -> 1767.0199 | ... DA66: =DA65*DA78 -> 2211.0851
B67: Net Income | C67: =C65-C66 -> -13 | D67: =D65-D66 -> 158 | E67: =E65-E66 -> -94 | F67: =F65-F66 -> -1076 | G67: =G65-G66 -> -1589 | H67: =H65-H66 -> 98 | I67: =I65-I66 -> 190 | J67: =J65-J66 -> 236 | ... BT67: =BT65-BT66 -> 905 | CA67: =SUM(C67:F67) -> -1025 | CB67: =SUM(G67:J67) -> -1065 | CC67: =SUM(K67:N67) -> 441 | CD67: =SUM(O67:R67) -> -4068 | CE67: =SUM(S67:V67) -> -121 | CF67: =SUM(W67:Z67) -> -119 | CG67: =SUM(AA67:AD67) -> -239 | CH67: =SUM(AE67:AH67) -> 347 | CI67: =SUM(AI67:AL67) -> 104 | CJ67: =SUM(AM67:AP67) -> 1670 | CK67: =SUM(AQ67:AT67) -> 4700 | CL67: =SUM(AU67:AX67) -> -81 | CM67: =SUM(AY67:BB67) -> 1039 | CN67: =SUM(BC67:BF67) -> 696 | CO67: =SUM(BG67:BJ67) -> 1592 | CP67: =SUM(BK67:BN67) -> 1848 | CQ67: =SUM(BO67:BR67) -> 2892 | CR67: =CR65-CR66 -> 3500.64 | CS67: =CS65-CS66 -> 2444.3058 | CT67: =CT65-CT66 -> 3156.9971 | CU67: =CU65-CU66 -> 3836.7625 | CV67: =CV65-CV66 -> 4517.2093 | CW67: =CW65-CW66 -> 5322.9334 | CX67: =CX65-CX66 -> 6145.2969 | CY67: =CY65-CY66 -> 7068.0795 | ... DA67: =DA65-DA66 -> 8844.3403
B68: Preferred Stock Obligation | C68: 0 | D68: 0 | E68: 0 | F68: 0 | G68: 0 | H68: 0 | I68: 0 | J68: 0 | K68: 0 | L68: 0 | M68: 0 | N68: 0 | O68: 0 | P68: 0 | Q68: 0 | R68: 0 | S68: 0 | T68: 0 | U68: 0 | V68: 0 | W68: 0 | X68: 0 | Y68: 0 | Z68: 0 | AA68: 0 | AB68: 0 | AC68: 0 | AD68: 0 | AE68: 0 | AF68: 0 | AG68: 0 | AH68: 0 | AI68: 0 | AJ68: 0 | AK68: 0 | AL68: 0 | AM68: 0 | AN68: 0 | AO68: 0 | AP68: 0 | AQ68: 0 | AR68: 0 | AS68: 0 | AT68: 0 | AU68: 0 | AV68: -5 | AW68: -14 | AX68: =-33-SUM(AU68:AW68) -> -14 | AY68: -14 | AZ68: -14 | BA68: -14 | BB68: =-55-SUM(AY68:BA68) -> -13 | BC68: -14 | BD68: -14 | BE68: -14 | BF68: =-55-SUM(BC68:BE68) -> -13 | BG68: -14 | BH68: -9 | BI68: 0 | BJ68: =-23-SUM(BG68:BI68) -> 0 | BK68: 0 | BL68: 0 | BM68: 0 | BN68: =0-SUM(BK68:BM68) -> 0 | BO68: 0 | BP68: 0 | BQ68: 0 | BR68: 0 | BS68: 0 | BT68: 0 | CA68: 0 | CB68: 0 | CC68: 0 | CD68: 0 | CE68: 0 | CF68: 0 | CG68: 0 | CH68: 0 | CI68: 0 | CJ68: 0 | CK68: 0 | CL68: =SUM(AU68:AX68) -> -33 | CM68: =SUM(AY68:BB68) -> -55 | CN68: =SUM(BC68:BF68) -> -55 | CO68: =SUM(BG68:BJ68) -> -23 | CP68: =SUM(BK68:BN68) -> 0 | CQ68: =SUM(BO68:BR68) -> 0 | CR68: 0 | CS68: 0 | CT68: 0 | CU68: 0 | CV68: 0 | CW68: 0 | CX68: 0 | CY68: 0 | CZ68: 0 | DA68: 0
B69: Net Income Attr to Non-Cont | C69: 0 | D69: 0 | E69: 0 | F69: 0 | G69: 0 | H69: 0 | I69: 0 | J69: 0 | K69: 0 | L69: 0 | M69: 0 | N69: 0 | O69: 0 | P69: 0 | Q69: 0 | R69: 0 | S69: 0 | T69: 0 | U69: 0 | V69: 0 | W69: 0 | X69: 0 | Y69: 0 | Z69: 0 | AA69: 0 | AB69: 0 | AC69: 0 | AD69: 0 | AE69: 0 | AF69: 0 | AG69: 0 | AH69: 0 | AI69: 0 | AJ69: 0 | AK69: 0 | AL69: 0 | AM69: 0 | AN69: 0 | AO69: 0 | AP69: 0 | AQ69: 0 | AR69: 0 | AS69: 0 | AT69: 0 | AU69: 0 | AV69: 0 | AW69: 0 | AX69: 0 | AY69: 0 | AZ69: 0 | BA69: 0 | BB69: 0 | BC69: 0 | BD69: 0 | BE69: 0 | BF69: 0 | BG69: 0 | BH69: 0 | BI69: 0 | BJ69: 0 | BK69: -2 | BL69: -2 | BM69: 0 | BN69: =-4-SUM(BK69:BM69) -> 0 | BO69: -2 | BP69: -1 | BQ69: 0 | BR69: -3 | BS69: -2 | BT69: -2 | CA69: 0 | CB69: 0 | CC69: 0 | CD69: 0 | CE69: 0 | CF69: 0 | CG69: 0 | CH69: 0 | CI69: 0 | CJ69: 0 | CK69: 0 | CL69: =SUM(AU69:AX69) -> 0 | CM69: =SUM(AY69:BB69) -> 0 | CN69: =SUM(BC69:BF69) -> 0 | CO69: =SUM(BG69:BJ69) -> 0 | CP69: =SUM(BK69:BN69) -> -4 | CQ69: =SUM(BO69:BR69) -> -6 | CR69: 0 | CS69: 0 | CT69: 0 | CU69: 0 | CV69: 0 | CW69: 0 | CX69: 0 | CY69: 0 | CZ69: 0 | DA69: 0
B70: Net Income Attr to BSX | C70: =C67+C68-C69 -> -13 | D70: =D67+D68-D69 -> 158 | E70: =E67+E68-E69 -> -94 | F70: =F67+F68-F69 -> -1076 | G70: =G67+G68-G69 -> -1589 | H70: =H67+H68-H69 -> 98 | I70: =I67+I68-I69 -> 190 | J70: =J67+J68-J69 -> 236 | ... BT70: =BT67+BT68-BT69 -> 907 | CA70: =SUM(AJ70:AM70) -> 111 | CB70: =SUM(AK70:AN70) -> 521 | CC70: =SUM(AL70:AO70) -> 670 | CD70: =SUM(AM70:AP70) -> 1670 | CE70: =SUM(AN70:AQ70) -> 1797 | CF70: =SUM(AO70:AR70) -> 1395 | CG70: =SUM(AP70:AS70) -> 1089 | CH70: =SUM(AQ70:AT70) -> 4700 | ... CL70: =SUM(AU70:AX70) -> -114 | CM70: =SUM(AY70:BB70) -> 984 | CN70: =SUM(BC70:BF70) -> 641 | CO70: =SUM(BG70:BJ70) -> 1569 | CP70: =SUM(BK70:BN70) -> 1852 | CQ70: =SUM(BO70:BR70) -> 2898 | CR70: =CR67-SUM(CR68:CR69) -> 3500.64 | CS70: =CS67-SUM(CS68:CS69) -> 2444.3058 | CT70: =CT67-SUM(CT68:CT69) -> 3156.9971 | CU70: =CU67-SUM(CU68:CU69) -> 3836.7625 | CV70: =CV67-SUM(CV68:CV69) -> 4517.2093 | CW70: =CW67-SUM(CW68:CW69) -> 5322.9334 | CX70: =CX67-SUM(CX68:CX69) -> 6145.2969 | CY70: =CY67-SUM(CY68:CY69) -> 7068.0795 | ... DA70: =DA67-SUM(DA68:DA69) -> 8844.3403 | DB70: =DA70*(1+$DK$82) -> 8977.0054 | DC70: =DB70*(1+$DK$82) -> 9111.6605 | DD70: =DC70*(1+$DK$82) -> 9248.3354 | DE70: =DD70*(1+$DK$82) -> 9387.0604 | DF70: =DE70*(1+$DK$82) -> 9527.8663 | DG70: =DF70*(1+$DK$82) -> 9670.7843 | DH70: =DG70*(1+$DK$82) -> 9815.8461 | DI70: =DH70*(1+$DK$82) -> 9963.0838 | ... EO70: =EN70*(1+$DK$82) -> 16043.796
B71: SC | C71: 1504 | D71: 1507 | E71: 1509 | F71: 1507 | G71: 1515 | H71: 1516 | I71: 1519 | J71: 1517 | K71: 1527 | L71: 1529 | M71: 1514 | N71: 1509 | O71: 1445 | P71: 1423 | Q71: 1393 | R71: 1407 | S71: 1352 | T71: 1344 | U71: 1340 | V71: 1341 | W71: 1322 | X71: 1323 | Y71: 1326 | Z71: 1324 | AA71: 1334 | AB71: 1341 | AC71: 1344 | AD71: 1341 | AE71: 1350 | AF71: 1357 | AG71: 1361 | AH71: 1358 | AI71: 1365 | AJ71: 1370 | AK71: 1372 | AL71: 1370 | AM71: 1377 | AN71: 1381 | AO71: 1383 | AP71: 1381 | AQ71: 1388 | AR71: 1391 | AS71: 1393 | AT71: 1392 | AU71: 1397.4 | AV71: 1410.9 | AW71: 1430.9 | AX71: 1416.7 | AY71: 1418.7 | AZ71: 1421.3 | BA71: 1423.8 | BB71: 1422.3 | BC71: 1427.8 | BD71: 1429.7 | BE71: 1431.6 | BF71: 1430.5 | BG71: 1435.8 | BH71: 1446.2 | BI71: 1464.5 | BJ71: 1453 | BK71: 1468.4 | BL71: 1470.6 | BM71: 1472.7 | BN71: 1471.5 | BO71: 1477.2 | BP71: 1479.9 | BQ71: 1481.7 | BR71: 1482.7 | BS71: 1484.9 | BT71: 1470.2 | CA71: =F71 -> 1507 | CB71: =J71 -> 1517 | CC71: =N71 -> 1509 | CD71: =R71 -> 1407 | CE71: =V71 -> 1341 | CF71: =Z71 -> 1324 | CG71: =AD71 -> 1341 | CH71: =AH71 -> 1358 | CI71: =AL71 -> 1370 | CJ71: =AP71 -> 1381 | CK71: =AT71 -> 1392 | CL71: =AX71 -> 1416.7 | CM71: =BB71 -> 1422.3 | CN71: =BF71 -> 1430.5 | CO71: =BJ71 -> 1453 | CP71: =BN71 -> 1471.5 | CQ71: =AVERAGE(BO71:BR71) -> 1480.375
B72: EPS | C72: =C70/C71 -> -0.008643617 | D72: =D70/D71 -> 0.10484406 | E72: =E70/E71 -> -0.062292909 | F72: =F70/F71 -> -0.71400133 | G72: =G70/G71 -> -1.0488449 | H72: =H70/H71 -> 0.064643799 | I72: =I70/I71 -> 0.12508229 | J72: =J70/J71 -> 0.1555702 | ... BT72: =BT70/BT71 -> 0.61692287 | CA72: =SUM(C72:F72) -> -0.68009379 | CB72: =SUM(G72:J72) -> -0.70354859 | CC72: =SUM(K72:N72) -> 0.29031084 | CD72: =SUM(O72:R72) -> -2.8695199 | CE72: =SUM(S72:V72) -> -0.08830256 | CF72: =SUM(W72:Z72) -> -0.089773884 | CG72: =SUM(AA72:AD72) -> -0.17789954 | CH72: =SUM(AE72:AH72) -> 0.25592189 | CI72: =SUM(AI72:AL72) -> 0.076386668 | CJ72: =SUM(AM72:AP72) -> 1.209441 | CK72: =SUM(AQ72:AT72) -> 3.3773291 | CL72: =SUM(AU72:AX72) -> -0.07961869 | CM72: =SUM(AY72:BB72) -> 0.69220566 | CN72: =SUM(BC72:BF72) -> 0.44822606 | CO72: =SUM(BG72:BJ72) -> 1.080429 | CP72: =SUM(BK72:BN72) -> 1.2591655 | CQ72: =SUM(BO72:BR72) -> 1.9575956
B74: Gross Profit Margin | C74: =C52/C50 -> 0.69800995 | D74: =D52/D50 -> 0.69623915 | E74: =E52/E50 -> 0.68938272 | F74: =F52/F50 -> 0.65848966 | G74: =G52/G50 -> 0.66173469 | H74: =H52/H50 -> 0.66078838 | I74: =I52/I50 -> 0.67484342 | J74: =J52/J50 -> 0.67082917 | ... BT74: =BT52/BT50 -> 0.70709298 | CA74: =CA52/CA50 -> 0.68539326 | CB74: =CB52/CB50 -> 0.66705099 | CC74: =CC52/CC50 -> 0.65114143 | CD74: =CD52/CD50 -> 0.6759553 | CE74: =CE52/CE50 -> 0.69564609 | CF74: =CF52/CF50 -> 0.70054201 | CG74: =CG52/CG50 -> 0.70937542 | CH74: =CH52/CH50 -> 0.71094682 | ... CQ74: =CQ52/CQ50 -> 0.69011208 | CR74: 0.69 | CS74: 0.695 | CT74: 0.698 | CU74: 0.7 | CV74: 0.7025 | CW74: 0.705 | CX74: 0.7075 | CY74: 0.71 | CZ74: 0.71 | DA74: 0.71
B75: SG&A as % of Revenue | C75: =C53/C50 -> 0.3238806 | D75: =D53/D50 -> 0.32352941 | E75: =E53/E50 -> 0.32839506 | F75: =F53/F50 -> 0.31168831 | G75: =G53/G50 -> 0.32040816 | H75: =H53/H50 -> 0.32883817 | I75: =I53/I50 -> 0.3308977 | J75: =J53/J50 -> 0.34265734 | ... BT75: =BT53/BT50 -> 0.33131202 | CA75: =CA53/CA50 -> 0.32181241 | CB75: =CB53/CB50 -> 0.3307712 | CC75: =CC53/CC50 -> 0.32721071 | CD75: =CD53/CD50 -> 0.34887571 | CE75: =CE53/CE50 -> 0.3749125 | CF75: =CF53/CF50 -> 0.39322493 | CG75: =CG53/CG50 -> 0.38424502 | CH75: =CH53/CH50 -> 0.36954448 | ... CQ75: =CQ53/CQ50 -> 0.34311333 | CR75: 0.349 | CS75: 0.347 | CT75: 0.346 | CU75: 0.345 | CV75: 0.344 | CW75: 0.343 | CX75: 0.342 | CY75: 0.341 | CZ75: 0.34 | DA75: 0.34
B76: R&D as % of Revenue | C76: =C54/C50 -> 0.1278607 | D76: =D54/D50 -> 0.13500482 | E76: =E54/E50 -> 0.12740741 | F76: =F54/F50 -> 0.12554113 | G76: =G54/G50 -> 0.12908163 | H76: =H54/H50 -> 0.12033195 | I76: =I54/I50 -> 0.12004175 | J76: =J54/J50 -> 0.11188811 | ... BT76: =BT54/BT50 -> 0.10180081 | CA76: =CA54/CA50 -> 0.12896922 | CB76: =CB54/CB50 -> 0.12029208 | CC76: =CC54/CC50 -> 0.11742325 | CD76: =CD54/CD50 -> 0.12222376 | CE76: =CE54/CE50 -> 0.12053759 | CF76: =CF54/CF50 -> 0.11070461 | CG76: =CG54/CG50 -> 0.11715929 | CH76: =CH54/CH50 -> 0.10970665 | ... CQ76: =CQ54/CQ50 -> 0.10221669 | CR76: 0.104 | CS76: 0.108 | CT76: 0.11 | CU76: 0.112 | CV76: 0.114 | CW76: 0.113 | CX76: 0.112 | CY76: 0.111 | CZ76: 0.11 | DA76: 0.109
B77: Operating Profit Margin | C77: =C62/C50 -> 0.0054726368 | D77: =D62/D50 -> 0.13259402 | E77: =E62/E50 -> 0.025185185 | F77: =F62/F50 -> -0.59211159 | G77: =G62/G50 -> -0.75816327 | H77: =H62/H50 -> 0.11981328 | I77: =I62/I50 -> 0.13100209 | J77: =J62/J50 -> 0.17382617 | ... BT77: =BT62/BT50 -> 0.21646454 | CA77: =CA62/CA50 -> -0.10918417 | CB77: =CB62/CB50 -> -0.08403792 | CC77: =CC62/CC50 -> 0.11860404 | CD77: =CD62/CD50 -> -0.53359084 | CE77: =CE62/CE50 -> 0.016799664 | CF77: =CF62/CF50 -> -0.040785908 | CG77: =CG62/CG50 -> -0.037849405 | CH77: =CH62/CH50 -> 0.053303124 | ... DA77: =DA62/DA50 -> 0.22597372
B78: Effective Tax Rate | C78: =C66/C65 -> 0.86597938 | D78: =D66/D65 -> 0.12222222 | E78: =E66/E65 -> -1.1363636 | F78: =F66/F65 -> 0.20118782 | G78: =G66/G65 -> -0.0088888889 | H78: =H66/H65 -> 0.17647059 | I78: =I66/I65 -> -0.16564417 | J78: =J66/J65 -> -0.026086957 | ... BT78: =BT66/BT65 -> 0.14622642 | CA78: =CA66/CA65 -> 0.21636086 | CB78: =CB66/CB65 -> -0.0018814675 | CC78: =CC66/CC65 -> 0.31308411 | CD78: =CD66/CD65 -> 0.0094959825 | CE78: =CE66/CE65 -> 0.4573991 | CF78: =CF66/CF65 -> 0.76620825 | CG78: =CG66/CG65 -> 0.63230769 | CH78: =CH66/CH65 -> -0.96045198 | ... CQ78: =CQ66/CQ65 -> 0.14564254 | CR78: 0.01 | CS78: 0.12 | CT78: 0.14 | CU78: 0.16 | CV78: 0.18 | CW78: 0.19 | CX78: 0.2 | CY78: 0.2 | CZ78: 0.2 | DA78: 0.2
B79: Net Profit Margin | C79: =C67/C50 -> -0.0064676617 | D79: =D67/D50 -> 0.076181292 | E79: =E67/E50 -> -0.046419753 | F79: =F67/F50 -> -0.51755652 | G79: =G67/G50 -> -0.81071429 | H79: =H67/H50 -> 0.050829876 | I79: =I67/I50 -> 0.099164927 | J79: =J67/J50 -> 0.11788212 | ... BT79: =BT67/BT50 -> 0.16629915 | CA79: =CA67/CA50 -> -0.12518319 | CB79: =CB67/CB50 -> -0.13643351 | CC79: =CC67/CC50 -> 0.05785883 | CD79: =CD67/CD50 -> -0.56118085 | CE79: =CE67/CE50 -> -0.016939661 | CF79: =CF67/CF50 -> -0.016124661 | CG79: =CG67/CG50 -> -0.031964692 | CH79: =CH67/CH50 -> 0.041378488 | ... DA79: =DA67/DA50 -> 0.24297887
B81: Cash & C.E.'s | AX81: 1734 | AY81: 2016 | AZ81: 2675 | BA81: 1947 | BB81: 1925 | BC81: 325 | BD81: 276 | BE81: 339 | BF81: 928 | BG81: 570 | BH81: 426 | BI81: 952 | BJ81: 866 | BK81: 2329 | BL81: 2913 | BM81: 2502 | BN81: 414 | BO81: 725 | BP81: 534 | BQ81: 1275 | BR81: 1965 | BS81: 1453 | BT81: 539 | CL81: =AX81 -> 1734 | CM81: =BB81 -> 1925 | CN81: =BF81 -> 928 | CO81: =BJ81 -> 866 | CP81: =BN81 -> 414 | CQ81: =BQ81 -> 1275 | CR81: =CQ81+CR70 -> 4775.64 | CS81: =CR81+CS70 -> 7219.9458 | CT81: =CS81+CT70 -> 10376.943 | CU81: =CT81+CU70 -> 14213.705 | CV81: =CU81+CV70 -> 18730.915 | CW81: =CV81+CW70 -> 24053.848 | CX81: =CW81+CX70 -> 30199.145 | CY81: =CX81+CY70 -> 37267.225 | ... DA81: =CZ81+DA70 -> 54072.944 | DC81: Invested Capital | DF81: Avg. (2023-2024) | DH81: Projected ROIC: | DJ81: ROIC | DK81: 0.085
B82: A/R | AX82: 1531 | AY82: 1631 | AZ82: 1675 | BA82: 1669 | BB82: 1778 | BC82: 1866 | BD82: 1917 | BE82: 1871 | BF82: 1970 | BG82: 2076 | BH82: 2134 | BI82: 2101 | BJ82: 2229 | BK82: 2304 | BL82: 2400 | BM82: 2501 | BN82: 2558 | BO82: 2693 | BP82: 2815 | BQ82: 2828 | BR82: 2926 | BS82: 3027 | BT82: 3049 | CL82: =AX82 -> 1531 | CM82: =BB82 -> 1778 | CN82: =BF82 -> 1970 | CO82: =BJ82 -> 2229 | CP82: =BN82 -> 2558 | CQ82: =BQ82 -> 2828 | DC82: 2024 | DD82: 2025 | DF82: 2023-2024 | DH82: 2025 | DJ82: Terminal | DK82: 0.015
B83: Inventories | AX83: 1351 | AY83: 1407 | AZ83: 1430 | BA83: 1603 | BB83: 1610 | BC83: 1736 | BD83: 1752 | BE83: 1788 | BF83: 1867 | BG83: 2050 | BH83: 2250 | BI83: 2404 | BJ83: 2484 | BK83: 2561 | BL83: 2608 | BM83: 2753 | BN83: 2810 | BO83: 2867 | BP83: 2861 | BQ83: 2921 | BR83: 2943 | BS83: 3117 | BT83: 3235 | CL83: =AX83 -> 1351 | CM83: =BB83 -> 1610 | CN83: =BF83 -> 1867 | CO83: =BJ83 -> 2484 | CP83: =BN83 -> 2810 | CQ83: =BQ83 -> 2921 | DC83: =SUM(CP81:CP84)-CP95+CP87+CP89+CP88 -> 32196 | DD83: =SUM(CQ81:CQ84)-CQ95+CQ87+CQ89+CQ88 -> 35503 | DF83: =AVERAGE(DC83:DD83) -> 33849.5 | DH83: =AVERAGE(CR62)*(1-CR78) -> 4086.6582 | DJ83: RFR (10-year yield) | DK83: 0.0499
B84: Prepaid Income Taxes | AX84: 194 | AY84: 192 | AZ84: 202 | BA84: 217 | BB84: 205 | BC84: 249 | BD84: 264 | BE84: 262 | BF84: 264 | BG84: 296 | BH84: 303 | BI84: 307 | BJ84: 315 | BK84: 319 | BL84: 315 | BM84: 332 | BN84: 307 | BO84: 294 | BP84: 298 | BQ84: 310 | BR84: 299 | BS84: 358 | BT84: 390 | CL84: =AX84 -> 194 | CM84: =BB84 -> 205 | CN84: =BF84 -> 264 | CO84: =BJ84 -> 315 | CP84: =BN84 -> 307 | CQ84: =BQ84 -> 310 | DH84: =DH83/DF83 -> 0.12073024 | DJ84: ERP (Avg. market return - (less) RFR) | DK84: =10.5%-DK83 -> 0.0551
B85: Assets Held for Sale | AX85: 1133 | AY85: 0 | AZ85: 0 | BA85: 0 | BB85: 0 | BC85: 0 | BD85: 0 | BE85: 0 | BF85: 0 | BG85: 0 | BH85: 0 | BI85: 0 | BJ85: 0 | BK85: 0 | BL85: 0 | BM85: 0 | BN85: 0 | BO85: 0 | BP85: 0 | BQ85: 0 | BR85: 0 | BS85: 0 | BT85: 0 | CL85: =AX85 -> 1133 | CM85: 0 | CN85: 0 | CO85: 0 | CP85: 0 | CQ85: =BQ85 -> 0 | DC85: Capital Structure | DJ85: Equity β (1-year avg.) | DK85: ='Notes | Analysis'!K269 -> 0.73
B86: Other Current Assets | AX86: 751 | AY86: 855 | AZ86: 777 | BA86: 792 | BB86: 799 | BC86: 889 | BD86: 874 | BE86: 884 | BF86: 731 | BG86: 711 | BH86: 773 | BI86: 741 | BJ86: 621 | BK86: 671 | BL86: 756 | BM86: 674 | BN86: 831 | BO86: 756 | BP86: 613 | BQ86: 701 | BR86: 660 | BS86: 729 | BT86: 760 | CL86: =AX86 -> 751 | CM86: =BB86 -> 799 | CN86: =BF86 -> 731 | CO86: =BJ86 -> 621 | CP86: =BN86 -> 831 | CQ86: =BQ86 -> 701 | DC86: Mkt Cap | DF86: =Main!C5 -> 64380.058 | DJ86: Discount (Cost of Equity) | DK86: =+DK83+(DK84*DK85) -> 0.090123
B87: PP&E | AX87: 2084 | AY87: 2053 | AZ87: 2082 | BA87: 2109 | BB87: 2252 | BC87: 2265 | BD87: 2246 | BE87: 2273 | BF87: 2446 | BG87: 2478 | BH87: 2534 | BI87: 2635 | BJ87: 2859 | BK87: 2897 | BL87: 2951 | BM87: 3072 | BN87: 3294 | BO87: 3389 | BP87: 3461 | BQ87: 3795 | BR87: 4036 | BS87: 4063 | BT87: 4126 | CL87: =AX87 -> 2084 | CM87: =BB87 -> 2252 | CN87: =BF87 -> 2446 | CO87: =BJ87 -> 2859 | CP87: =BN87 -> 3294 | CQ87: =BQ87 -> 3795 | DC87: Debt to Ttl Mkt Cap | DF87: =Main!C7/(Main!C7+DF86) -> 0.14579121
B88: Goodwill | AX88: 9951 | AY88: 10868 | AZ88: 10874 | BA88: 11820 | BB88: 11988 | BC88: 12949 | BD88: 12883 | BE88: 12852 | BF88: 12920 | BG88: 13269 | BH88: 13659 | BI88: 13608 | BJ88: 14387 | BK88: 14361 | BL88: 14397 | BM88: 15033 | BN88: 17089 | BO88: 17340 | BP88: 18076 | BQ88: 18214 | BR88: 18282 | BS88: 18536 | BT88: 18640 | CL88: =AX88 -> 9951 | CM88: =BB88 -> 11988 | CN88: =BF88 -> 12920 | CO88: =BJ88 -> 14387 | CP88: =BN88 -> 17089 | CQ88: =BQ88 -> 18214 | DC88: Mkt Equity to Ttl Mkt Cap | DF88: =DF86/(DF86+Main!C7) -> 0.85420879 | DJ88: NPV | DK88: =NPV(DK86,CR70:EO70) -> 78345.795
B89: Other Intangibles | AX89: 5917 | AY89: 5991 | AZ89: 5788 | BA89: 6227 | BB89: 6121 | BC89: 6581 | BD89: 6349 | BE89: 6058 | BF89: 5902 | BG89: 6060 | BH89: 6063 | BI89: 5849 | BJ89: 6003 | BK89: 5839 | BL89: 5417 | BM89: 5754 | BN89: 6684 | BO89: 6566 | BP89: 7260 | BQ89: 7162 | BR89: 7019 | BS89: 7060 | BT89: 6918 | CL89: =AX89 -> 5917 | CM89: =BB89 -> 6121 | CN89: =BF89 -> 5902 | CO89: =BJ89 -> 6003 | CP89: =BN89 -> 6684 | CQ89: =BQ89 -> 7162 | DC89: LT Debt / Equity | DF89: =CR98/CQ102 -> 1.0206094 | DJ89: SC | DK89: =Main!C4 -> 1470.2
B90: Deffered Taxes | AX90: 4210 | AY90: 4173 | AZ90: 4036 | BA90: 4049 | BB90: 4142 | BC90: 4102 | BD90: 4059 | BE90: 4018 | BF90: 3942 | BG90: 3900 | BH90: 3865 | BI90: 3840 | BJ90: 3841 | BK90: 3792 | BL90: 3801 | BM90: 3816 | BN90: 3655 | BO90: 3676 | BP90: 3778 | BQ90: 3669 | BR90: 3675 | BS90: 3953 | BT90: 3909 | CL90: =AX90 -> 4210 | CM90: =BB90 -> 4142 | CN90: =BF90 -> 3942 | CO90: =BJ90 -> 3841 | CP90: =BN90 -> 3655 | CQ90: =BQ90 -> 3669 | DJ90: FV | DK90: =(DK88+DK191)/DK89 -> 66.913497
B91: Other LT Assets | AX91: 1921 | AY91: 1714 | AZ91: 1629 | BA91: 1444 | BB91: 1409 | BC91: 1375 | BD91: 1569 | BE91: 1602 | BF91: 1500 | BG91: 1482 | BH91: 1595 | BI91: 1605 | BJ91: 1531 | BK91: 1596 | BL91: 1550 | BM91: 1642 | BN91: 1753 | BO91: 1834 | BP91: 1864 | BQ91: 1832 | BR91: 1866 | BS91: 2055 | BT91: =2245+1405 -> 3650 | CL91: =AX91 -> 1921 | CM91: =BB91 -> 1409 | CN91: =BF91 -> 1500 | CO91: =BJ91 -> 1531 | CP91: =BN91 -> 1753 | CQ91: =BQ91 -> 1832 | DC91: Cost of Equity | DJ91: CP | DK91: =Main!C3 -> 43.79
B92: Ttl Assets | AX92: =SUM(AX81:AX91) -> 30777 | AY92: =SUM(AY81:AY91) -> 30900 | AZ92: =SUM(AZ81:AZ91) -> 31168 | BA92: =SUM(BA81:BA91) -> 31877 | BB92: =SUM(BB81:BB91) -> 32229 | BC92: =SUM(BC81:BC91) -> 32337 | BD92: =SUM(BD81:BD91) -> 32189 | BE92: =SUM(BE81:BE91) -> 31947 | ... BT92: =SUM(BT81:BT91) -> 45216 | CL92: =AX92 -> 30777 | CM92: =BB92 -> 32229 | CN92: =BF92 -> 32470 | CO92: =BJ92 -> 35136 | CP92: =BN92 -> 39395 | CQ92: =BQ92 -> 42707 | DC92: RFR (10-year yield) | DF92: 0.0499 | DJ92: Change Δ | DK92: =DK90/DK91-1 -> 0.52805428 | DL92: =IF(DK92>0,"Upside","Downside") -> Upside
DC93: Equity β (1-year avg.) | DF93: ='Notes | Analysis'!K269 -> 0.73 | DJ93: {=_xlfn.IFS(DK92>=25%,"Strong Buy",DK92>=10.00001%,"Buy",AND(DK92<=10%,DK92>=-4.9999%),"Hold",AND(DK92<=-5%,DK92>=-14.999999%),"Sell",DK92<=-15%,"Strong Sell")} -> Strong Buy
B94: Current Debt | AX94: 13 | AY94: 13 | AZ94: 262 | BA94: 261 | BB94: 260 | BC94: 238 | BD94: 170 | BE94: 20 | BF94: 20 | BG94: 510 | BH94: 559 | BI94: 513 | BJ94: 531 | BK94: 1085 | BL94: 1580 | BM94: 1652 | BN94: 1779 | BO94: 777 | BP94: 480 | BQ94: 483 | BR94: 299 | BS94: 41 | BT94: 1709 | CL94: =AX94 -> 13 | CM94: =BB94 -> 260 | CN94: =BF94 -> 20 | CO94: =BJ94 -> 531 | CP94: =BN94 -> 1779 | CQ94: =BQ94 -> 483 | DC94: Market Return(1-year avg.) | DF94: 0.14
B95: Accounts Payable | AX95: 513 | AY95: 615 | AZ95: 689 | BA95: 674 | BB95: 794 | BC95: 696 | BD95: 732 | BE95: 803 | BF95: 862 | BG95: 868 | BH95: 899 | BI95: 929 | BJ95: 943 | BK95: 921 | BL95: 906 | BM95: 908 | BN95: 960 | BO95: 1004 | BP95: 962 | BQ95: 1002 | BR95: 1144 | BS95: 1141 | BT95: 1231 | CL95: =AX95 -> 513 | CM95: =BB95 -> 794 | CN95: =BF95 -> 862 | CO95: =BJ95 -> 943 | CP95: =BN95 -> 960 | CQ95: =BQ95 -> 1002 | DC95: Cost of Equity | DF95: =(DF92+DF93)*(DF94-DF92) -> 0.07026899
B96: Accrued Expenses | AX96: 2197 | AY96: 2060 | AZ96: 2442 | BA96: 2418 | BB96: 2436 | BC96: 2306 | BD96: 2197 | BE96: 1974 | BF96: 2160 | BG96: 1918 | BH96: 2164 | BI96: 2255 | BJ96: 2646 | BK96: 2083 | BL96: 2320 | BM96: 2460 | BN96: 2773 | BO96: 2354 | BP96: 2797 | BQ96: 2981 | BR96: 3201 | BS96: 2514 | BT96: 2756 | CL96: =AX96 -> 2197 | CM96: =BB96 -> 2436 | CN96: =BF96 -> 2160 | CO96: =BJ96 -> 2646 | CP96: =BN96 -> 2773 | CQ96: =BQ96 -> 2981
B97: Other Current Liabilities | AX97: 958 | AY97: 705 | AZ97: 680 | BA97: 669 | BB97: 783 | BC97: 1034 | BD97: 784 | BE97: 752 | BF97: 761 | BG97: 787 | BH97: 940 | BI97: 882 | BJ97: 814 | BK97: 827 | BL97: 770 | BM97: 891 | BN97: 887 | BO97: 923 | BP97: 952 | BQ97: 862 | BR97: 795 | BS97: 875 | BT97: 732 | CL97: =AX97 -> 958 | CM97: =BB97 -> 783 | CN97: =BF97 -> 761 | CO97: =BJ97 -> 814 | CP97: =BN97 -> 887 | CQ97: =BQ97 -> 862 | DC97: Cost of Debt
B98: LT Debt | AX98: 9130 | AY98: 9082 | AZ98: 8847 | BA98: 8824 | BB98: 8804 | BC98: 9067 | BD98: 8802 | BE98: 8564 | BF98: 8915 | BG98: 8495 | BH98: 8494 | BI98: 8386 | BJ98: 8571 | BK98: 9534 | BL98: 8991 | BM98: 9233 | BN98: 8968 | BO98: 10532 | BP98: 11107 | BQ98: 11117 | BR98: 11137 | BS98: 10988 | BT98: 10915 | CL98: =AX98 -> 9130 | CM98: =BB98 -> 8804 | CN98: =BF98 -> 8915 | CO98: =BJ98 -> 8571 | CP98: =BN98 -> 8968 | CQ98: =BQ98 -> 11117 | CR98: =CQ98+13000 -> 24117 | CS98: =CR98+CS63 -> 22006.763 | CT98: =CS98+CT63 -> 20081.171 | CU98: =CT98+CU63 -> 18324.068 | CV98: =CU98+CV63 -> 16720.712 | CW98: =CV98+CW63 -> 15257.65 | CX98: =CW98+CX63 -> 13922.606 | CY98: =CX98+CY63 -> 12704.378 | CZ98: =CY98+CZ63 -> 11592.745 | DA98: =CZ98+DA63 -> 10578.379 | DC98: Cost of Debt | DF98: 0.0875
B99: Deferred Income Taxes | AX99: 330 | AY99: 336 | AZ99: 115 | BA99: 274 | BB99: 310 | BC99: 261 | BD99: 265 | BE99: 278 | BF99: 144 | BG99: 210 | BH99: 135 | BI99: 91 | BJ99: 134 | BK99: 132 | BL99: 132 | BM99: 138 | BN99: 155 | BO99: 158 | BP99: 226 | BQ99: 242 | BR99: 220 | BS99: 219 | BT99: 221 | CL99: =AX99 -> 330 | CM99: =BB99 -> 310 | CN99: =BF99 -> 144 | CO99: =BJ99 -> 134 | CP99: =BN99 -> 155 | CQ99: =BQ99 -> 242 | DC99: Tax Rate | DF99: 0.04
B100: Other LT Liabilities | AX100: 2309 | AY100: 2370 | AZ100: 2190 | BA100: 2296 | BB100: 2220 | BC100: 2000 | BD100: 1988 | BE100: 1916 | BF100: 2035 | BG100: 1995 | BH100: 1926 | BI100: 1858 | BJ100: 1967 | BK100: 1919 | BL100: 1800 | BM100: 1841 | BN100: 1870 | BO100: 1946 | BP100: 2383 | BQ100: 2390 | BR100: 2405 | BS100: 2469 | BT100: 2480 | CL100: =AX100 -> 2309 | CM100: =BB100 -> 2220 | CN100: =BF100 -> 2035 | CO100: =BJ100 -> 1967 | CP100: =BN100 -> 1870 | CQ100: =BQ100 -> 2390 | DC100: After Tax Cost of Debt | DF100: =DF98*(1-DF99) -> 0.084
B101: Ttl Liabilities | AX101: =SUM(AX94:AX100) -> 15450 | AY101: =SUM(AY94:AY100) -> 15181 | AZ101: =SUM(AZ94:AZ100) -> 15225 | BA101: =SUM(BA94:BA100) -> 15416 | BB101: =SUM(BB94:BB100) -> 15607 | BC101: =SUM(BC94:BC100) -> 15602 | BD101: =SUM(BD94:BD100) -> 14938 | BE101: =SUM(BE94:BE100) -> 14307 | ... BT101: =SUM(BT94:BT100) -> 20044 | CL101: =SUM(CL94:CL100) -> 15450 | CM101: =SUM(CM94:CM100) -> 15607 | CN101: =SUM(CN94:CN100) -> 14897 | CO101: =SUM(CO94:CO100) -> 15606 | CP101: =SUM(CP94:CP100) -> 17392 | CQ101: =BQ101 -> 19077
B102: SE | AX102: 15327 | AY102: 15719 | AZ102: 15943 | BA102: 16461 | BB102: 16622 | BC102: 16735 | BD102: 17251 | BE102: 17640 | BF102: 17573 | BG102: 18109 | BH102: 18485 | BI102: 19129 | BJ102: 19530 | BK102: 20168 | BL102: 20609 | BM102: 20956 | BN102: 22003 | BO102: 22446 | BP102: 22653 | BQ102: 23630 | BR102: 24472 | BS102: 26104 | BT102: 25172 | CL102: =AX102 -> 15327 | CM102: =BB102 -> 16622 | CN102: =BF102 -> 17573 | CO102: =BJ102 -> 19530 | CP102: =BN102 -> 22003 | CQ102: =BQ102 -> 23630
B103: Ttl L + SE | AX103: =AX101+AX102 -> 30777 | AY103: =AY101+AY102 -> 30900 | AZ103: =AZ101+AZ102 -> 31168 | BA103: =BA101+BA102 -> 31877 | BB103: =BB101+BB102 -> 32229 | BC103: =BC101+BC102 -> 32337 | BD103: =BD101+BD102 -> 32189 | BE103: =BE101+BE102 -> 31947 | ... BT103: =BT101+BT102 -> 45216 | CL103: =CL101+CL102 -> 30777 | CM103: =CM101+CM102 -> 32229 | CN103: =CN101+CN102 -> 32470 | CO103: =CO101+CO102 -> 35136 | CP103: =CP101+CP102 -> 39395 | CQ103: =BQ103 -> 42707
B105: Current Ratio
B106: Quick Ratio
B107: Cash Ratio
B108: Return on Assets
B109: Return on Equity
...

Sheet Notes | Analysis
BU1: 0
H2: Employee Snapshot | AE2: Dizzying Amount of M&A
AF3: Will be important to follow up on the durability of organic revenue/earnings, Intelligent M&A is well rewarded by the market in the long run
AF4: Follow up on management scope
AF5: In the future, it's going to be necessary to build out a full cash flow statement. M&A activity demands tracking investing/financing figures just as closely as standard operating figures
AF6: [Build M&A scope]
AE8: Strong Ttl revenue growth, especially in recent years
AF9: Look for management comments/reporting's on organic vs inorganic sales
AF10: Cardiovascular is the larger business, and it is growing at a faster rate
AG11: Look into Cardiovascular vs MedSurg; see if there are any reported figures on profitability comps between segments
AF12: Research BSX market share in each of their business segments
AG13: Build list of competitors to model
AF14: Boston Scientific generates a significant portion of it's revenues (~36%) from international clients… listen into earnings call for management comments on tariff affects + potential changes to FY rev/earnings guidance
AF15: Learn more about BSX's venture arm, and the innovative products that are bought and developed internally … now driving top-line growth
AD17: Revenue Estimates:
I34: Notes: | J34: [X]
J35: [Y]
J36: [Z]
H38: Top Institutional Holders:
I70: Notes: | J70: [X]
J71: [Y]
J72: [Z]
H74: Revenue by Segment | AD74: Earnings Snapshot:
I108: Notes: | J108: Watchman and the Electrohpysiology Portfolio are worth building case studies on … Growth is incredible …
J109: Venture Capital driven … really special to see IP get commercialized so effectively
J110: [Z]
H112: Revenue by Segment | AD112: Balance Sheet Overview
A113: Close | B113: High | C113: Low | D113: Open | E113: Volume | F113: UTC Date | G113: Day change
A114: 102.74 | B114: 103.2 | C114: 101.615 | D114: 102.4 | E114: 5280884 | F114: Tue, 29 Apr 2025 00:00:00 GMT | G114: =A114/D114-1 -> 0.0033203125
A115: 102.18 | B115: 102.95 | C115: 101.5039 | D115: 102.5 | E115: 7815974 | F115: Mon, 28 Apr 2025 00:00:00 GMT | G115: =A115/D115-1 -> -0.0031219512
A116: 101.9 | B116: 102.15 | C116: 100.82 | D116: 101.39 | E116: 5380394 | F116: Fri, 25 Apr 2025 00:00:00 GMT | G116: =A116/D116-1 -> 0.0050300819
A117: 101.14 | B117: 101.675 | C117: 98.93 | D117: 99.03 | E117: 8984700 | F117: Thu, 24 Apr 2025 00:00:00 GMT | G117: =A117/D117-1 -> 0.021306675
A118: 98.92 | B118: 102.37 | C118: 98.425 | D118: 100 | E118: 12865357 | F118: Wed, 23 Apr 2025 00:00:00 GMT | G118: =A118/D118-1 -> -0.0108
A119: 95.05 | B119: 95.61 | C119: 93.35 | D119: 93.9 | E119: 8610950 | F119: Tue, 22 Apr 2025 00:00:00 GMT | G119: =A119/D119-1 -> 0.012247071
A120: 93.58 | B120: 95.18 | C120: 92.7 | D120: 95.05 | E120: 9990446 | F120: Mon, 21 Apr 2025 00:00:00 GMT | G120: =A120/D120-1 -> -0.015465544
A121: 95.12 | B121: 96.0615 | C121: 94.67 | D121: 95.6 | E121: 6673145 | F121: Thu, 17 Apr 2025 00:00:00 GMT | G121: =A121/D121-1 -> -0.0050209205
A122: 95.25 | B122: 96.69 | C122: 94.04 | D122: 94.78 | E122: 7874220 | F122: Wed, 16 Apr 2025 00:00:00 GMT | G122: =A122/D122-1 -> 0.0049588521
A123: 94.23 | B123: 95.12 | C123: 93.69 | D123: 94.66 | E123: 6615643 | F123: Tue, 15 Apr 2025 00:00:00 GMT | G123: =A123/D123-1 -> -0.0045425734
A124: 94.27 | B124: 95.63 | C124: 93.65 | D124: 95.28 | E124: 7877155 | F124: Mon, 14 Apr 2025 00:00:00 GMT | G124: =A124/D124-1 -> -0.010600336
A125: 93.67 | B125: 94.48 | C125: 91.89 | D125: 93.06 | E125: 8303735 | F125: Fri, 11 Apr 2025 00:00:00 GMT | G125: =A125/D125-1 -> 0.0065549108
... A145: 97.16 | B145: 97.385 | C145: 95.56 | D145: 96.07 | E145: 4924639 | F145: Fri, 14 Mar 2025 00:00:00 GMT | G145: =A145/D145-1 -> 0.011345894
A146: 95.37 | B146: 96.64 | C146: 94.85 | D146: 96.64 | E146: 8056893 | F146: Thu, 13 Mar 2025 00:00:00 GMT | G146: =A146/D146-1 -> -0.013141556 | I146: Notes: | J146: [X]
A147: 96.42 | B147: 98.565 | C147: 96.01 | D147: 98.04 | E147: 8790915 | F147: Wed, 12 Mar 2025 00:00:00 GMT | G147: =A147/D147-1 -> -0.016523868 | J147: [Y]
A148: 95.52 | B148: 96.27 | C148: 93.905 | D148: 94.13 | E148: 11910727 | F148: Tue, 11 Mar 2025 00:00:00 GMT | G148: =A148/D148-1 -> 0.014766812 | J148: [Z]
A149: 94.13 | B149: 97.77 | C149: 93.291 | D149: 97.765 | E149: 17009291 | F149: Mon, 10 Mar 2025 00:00:00 GMT | G149: =A149/D149-1 -> -0.037180995
A150: 100.8 | B150: 103.51 | C150: 100.5397 | D150: 103.31 | E150: 9723019 | F150: Thu, 06 Mar 2025 00:00:00 GMT | G150: =A150/D150-1 -> -0.024295809 | H150: Q/q Total Revenues, Net Income, FCF | AD150: Equity Preformance Compared to Peers
A151: 104.71 | B151: 105.21 | C151: 103.07 | D151: 103.24 | E151: 6716353 | F151: Wed, 05 Mar 2025 00:00:00 GMT | G151: =A151/D151-1 -> 0.014238667
A152: 103.61 | B152: 105.14 | C152: 102.53 | D152: 104.63 | E152: 8374524 | F152: Tue, 04 Mar 2025 00:00:00 GMT | G152: =A152/D152-1 -> -0.0097486381
A153: 104.87 | B153: 105.57 | C153: 103.83 | D153: 104.85 | E153: 6349110 | F153: Mon, 03 Mar 2025 00:00:00 GMT | G153: =A153/D153-1 -> 0.00019074869
A154: 103.79 | B154: 104.1 | C154: 101.01 | D154: 101.13 | E154: 8833246 | F154: Fri, 28 Feb 2025 00:00:00 GMT | G154: =A154/D154-1 -> 0.026302779
A155: 100.8 | B155: 103.99 | C155: 100.55 | D155: 101.64 | E155: 9010507 | F155: Thu, 27 Feb 2025 00:00:00 GMT | G155: =A155/D155-1 -> -0.0082644628
A156: 101.56 | B156: 102.815 | C156: 99.85 | D156: 100.43 | E156: 8148662 | F156: Wed, 26 Feb 2025 00:00:00 GMT | G156: =A156/D156-1 -> 0.011251618
A157: 100.72 | B157: 104.5 | C157: 97.08 | D157: 104 | E157: 18821595 | F157: Tue, 25 Feb 2025 00:00:00 GMT | G157: =A157/D157-1 -> -0.031538462
A158: 104.39 | B158: 104.95 | C158: 103.87 | D158: 104.25 | E158: 5214717 | F158: Mon, 24 Feb 2025 00:00:00 GMT | G158: =A158/D158-1 -> 0.0013429257
A159: 104.49 | B159: 105.65 | C159: 103.98 | D159: 104.64 | E159: 5513271 | F159: Fri, 21 Feb 2025 00:00:00 GMT | G159: =A159/D159-1 -> -0.0014334862
A160: 105.36 | B160: 105.48 | C160: 104.35 | D160: 105.43 | E160: 5977701 | F160: Thu, 20 Feb 2025 00:00:00 GMT | G160: =A160/D160-1 -> -0.00066394764
A161: 105.67 | B161: 105.7 | C161: 104.7637 | D161: 105.35 | E161: 4305812 | F161: Wed, 19 Feb 2025 00:00:00 GMT | G161: =A161/D161-1 -> 0.0030374941
A162: 105.35 | B162: 105.72 | C162: 102.919 | D162: 103.69 | E162: 6505711 | F162: Tue, 18 Feb 2025 00:00:00 GMT | G162: =A162/D162-1 -> 0.016009258
... A184: 96.89 | B184: 97.36 | C184: 95.37 | D184: 95.73 | E184: 5328883 | F184: Wed, 15 Jan 2025 00:00:00 GMT | G184: =A184/D184-1 -> 0.012117414
A185: 95.65 | B185: 96.25 | C185: 94.83 | D185: 95.08 | E185: 5415828 | F185: Tue, 14 Jan 2025 00:00:00 GMT | G185: =A185/D185-1 -> 0.0059949516 | I185: Notes: | J185: [X]
A186: 94.61 | B186: 95.08 | C186: 93.2035 | D186: 93.82 | E186: 4219067 | F186: Mon, 13 Jan 2025 00:00:00 GMT | G186: =A186/D186-1 -> 0.0084203795 | J186: [Y]
A187: 94.88 | B187: 96.692 | C187: 94.56 | D187: 95.475 | E187: 5944484 | F187: Fri, 10 Jan 2025 00:00:00 GMT | G187: =A187/D187-1 -> -0.0062319979 | J187: [Z]
A188: 95.95 | B188: 97.1273 | C188: 94.7501 | D188: 96.68 | E188: 10747709 | F188: Wed, 08 Jan 2025 00:00:00 GMT | G188: =A188/D188-1 -> -0.0075506827
A189: 91.99 | B189: 92.42 | C189: 90.52 | D189: 91.7 | E189: 4812189 | F189: Tue, 07 Jan 2025 00:00:00 GMT | G189: =A189/D189-1 -> 0.0031624864 | H189: Y/y Total Revenue, Net Income, FCF
A190: 91.29 | B190: 91.34 | C190: 90.43 | D190: 90.68 | E190: 4981432 | F190: Mon, 06 Jan 2025 00:00:00 GMT | G190: =A190/D190-1 -> 0.0067269519
A191: 90.69 | B191: 90.96 | C191: 89.505 | D191: 89.79 | E191: 3439787 | F191: Fri, 03 Jan 2025 00:00:00 GMT | G191: =A191/D191-1 -> 0.010023388
A192: 89.38 | B192: 90.16 | C192: 88.81 | D192: 90.02 | E192: 3369054 | F192: Thu, 02 Jan 2025 00:00:00 GMT | G192: =A192/D192-1 -> -0.0071095312
A193: 89.32 | B193: 90.21 | C193: 89.01 | D193: 89.78 | E193: 3973044 | F193: Tue, 31 Dec 2024 00:00:00 GMT | G193: =A193/D193-1 -> -0.0051236356
A194: 89.68 | B194: 90.09 | C194: 89.07 | D194: 89.66 | E194: 3411372 | F194: Mon, 30 Dec 2024 00:00:00 GMT | G194: =A194/D194-1 -> 0.00022306491
A195: 90.66 | B195: 91.5 | C195: 90.23 | D195: 90.9 | E195: 3177692 | F195: Fri, 27 Dec 2024 00:00:00 GMT | G195: =A195/D195-1 -> -0.002640264
A196: 91.45 | B196: 91.55 | C196: 90.59 | D196: 90.68 | E196: 2601931 | F196: Thu, 26 Dec 2024 00:00:00 GMT | G196: =A196/D196-1 -> 0.0084913983
A197: 91.07 | B197: 91.09 | C197: 89.66 | D197: 89.86 | E197: 1879976 | F197: Tue, 24 Dec 2024 00:00:00 GMT | G197: =A197/D197-1 -> 0.013465391
A198: 89.86 | B198: 89.988 | C198: 88.36 | D198: 89.27 | E198: 3833986 | F198: Mon, 23 Dec 2024 00:00:00 GMT | G198: =A198/D198-1 -> 0.0066091632
A199: 88.95 | B199: 89.67 | C199: 87.25 | D199: 88 | E199: 15910017 | F199: Fri, 20 Dec 2024 00:00:00 GMT | G199: =A199/D199-1 -> 0.010795455
A200: 88.66 | B200: 89.24 | C200: 87.7193 | D200: 88.04 | E200: 5620772 | F200: Thu, 19 Dec 2024 00:00:00 GMT | G200: =A200/D200-1 -> 0.0070422535
A201: 88.03 | B201: 90.21 | C201: 87.95 | D201: 90.14 | E201: 5167885 | F201: Wed, 18 Dec 2024 00:00:00 GMT | G201: =A201/D201-1 -> -0.023408032
... A223: 86.99 | B223: 87.8 | C223: 86.01 | D223: 87.12 | E223: 10230145 | F223: Fri, 15 Nov 2024 00:00:00 GMT | G223: =A223/D223-1 -> -0.0014921947
A224: 87.59 | B224: 89.09 | C224: 87.48 | D224: 88.65 | E224: 5120221 | F224: Thu, 14 Nov 2024 00:00:00 GMT | G224: =A224/D224-1 -> -0.011957135 | I224: Notes: | J224: [X]
A225: 88.77 | B225: 89.3 | C225: 88.66 | D225: 88.75 | E225: 4176533 | F225: Wed, 13 Nov 2024 00:00:00 GMT | G225: =A225/D225-1 -> 0.00022535211 | J225: [Y]
A226: 88.72 | B226: 89.005 | C226: 88.01 | D226: 88.63 | E226: 4989374 | F226: Tue, 12 Nov 2024 00:00:00 GMT | G226: =A226/D226-1 -> 0.0010154575 | J226: [Z]
A227: 88.48 | B227: 88.9 | C227: 88.21 | D227: 88.65 | E227: 4067317 | F227: Mon, 11 Nov 2024 00:00:00 GMT | G227: =A227/D227-1 -> -0.0019176537
A228: 88.25 | B228: 88.94 | C228: 87.18 | D228: 87.57 | E228: 5242205 | F228: Fri, 08 Nov 2024 00:00:00 GMT | G228: =A228/D228-1 -> 0.0077652164 | H228: BSX Historical Return Histogram (4/30/25)
A229: 86.88 | B229: 87.34 | C229: 86.11 | D229: 86.83 | E229: 4836499 | F229: Thu, 07 Nov 2024 00:00:00 GMT | G229: =A229/D229-1 -> 0.00057583784
A230: 86.44 | B230: 88.02 | C230: 85.03 | D230: 88 | E230: 6203905 | F230: Wed, 06 Nov 2024 00:00:00 GMT | G230: =A230/D230-1 -> -0.017727273
A231: 85.54 | B231: 85.69 | C231: 84.13 | D231: 84.54 | E231: 5400651 | F231: Tue, 05 Nov 2024 00:00:00 GMT | G231: =A231/D231-1 -> 0.01182872
A232: 84.72 | B232: 85.24 | C232: 83.55 | D232: 83.65 | E232: 5853107 | F232: Mon, 04 Nov 2024 00:00:00 GMT | G232: =A232/D232-1 -> 0.012791393
A233: 83.62 | B233: 84.77 | C233: 83.495 | D233: 84.33 | E233: 7051533 | F233: Fri, 01 Nov 2024 00:00:00 GMT | G233: =A233/D233-1 -> -0.0084193051
A234: 84.02 | B234: 85.25 | C234: 83.375 | D234: 83.71 | E234: 7444633 | F234: Thu, 31 Oct 2024 00:00:00 GMT | G234: =A234/D234-1 -> 0.0037032613
A235: 83.99 | B235: 84.66 | C235: 80.64 | D235: 84.51 | E235: 12004160 | F235: Wed, 30 Oct 2024 00:00:00 GMT | G235: =A235/D235-1 -> -0.006153118
A236: 84.56 | B236: 85.13 | C236: 84.37 | D236: 84.75 | E236: 7465678 | F236: Tue, 29 Oct 2024 00:00:00 GMT | G236: =A236/D236-1 -> -0.0022418879
A237: 84.76 | B237: 85.57 | C237: 84.66 | D237: 85 | E237: 8882736 | F237: Mon, 28 Oct 2024 00:00:00 GMT | G237: =A237/D237-1 -> -0.0028235294
A238: 84.73 | B238: 85.57 | C238: 83.59 | D238: 85.25 | E238: 6297105 | F238: Fri, 25 Oct 2024 00:00:00 GMT | G238: =A238/D238-1 -> -0.0060997067
A239: 85.1 | B239: 88.7 | C239: 85.03 | D239: 88.37 | E239: 10848652 | F239: Thu, 24 Oct 2024 00:00:00 GMT | G239: =A239/D239-1 -> -0.037003508
A240: 87.45 | B240: 87.58 | C240: 83.27 | D240: 85.28 | E240: 19619287 | F240: Wed, 23 Oct 2024 00:00:00 GMT | G240: =A240/D240-1 -> 0.025445591
... A262: 84 | B262: 84.71 | C262: 83.63 | D262: 84.27 | E262: 5657774 | F262: Mon, 23 Sep 2024 00:00:00 GMT | G262: =A262/D262-1 -> -0.0032039872
A263: 83.92 | B263: 84.045 | C263: 83.1 | D263: 83.56 | E263: 6968191 | F263: Fri, 20 Sep 2024 00:00:00 GMT | G263: =A263/D263-1 -> 0.0043082815 | J263: Min | K263: =MIN(G114:G2123) -> -0.071428571 | L263: The return distribution does fit a Gaussian distribution curve, but the curve is quite wide from return variability (high SD in daily avg returns), which reduces confidence in any inferences
A264: 83.71 | B264: 84.89 | C264: 83.33 | D264: 83.41 | E264: 7860788 | F264: Thu, 19 Sep 2024 00:00:00 GMT | G264: =A264/D264-1 -> 0.003596691 | J264: Max | K264: =MAX(G114:G2123) -> 0.073506412 | L264: There is slight implied upside to mean 1-day returns
A265: 82.57 | B265: 83.38 | C265: 81.82 | D265: 82.5 | E265: 7749476 | F265: Wed, 18 Sep 2024 00:00:00 GMT | G265: =A265/D265-1 -> 0.00084848485 | J265: Mean μ | K265: =AVERAGE(G114:G2123) -> 0.00017193072
A266: 82.52 | B266: 83.46 | C266: 81.54 | D266: 83.33 | E266: 7092244 | F266: Tue, 17 Sep 2024 00:00:00 GMT | G266: =A266/D266-1 -> -0.0097203888 | J266: Median | K266: =MEDIAN(G115:G2124) -> 0.00048449612
A267: 83.51 | B267: 84.005 | C267: 82.86 | D267: 83.8 | E267: 4908256 | F267: Mon, 16 Sep 2024 00:00:00 GMT | G267: =A267/D267-1 -> -0.0034606205 | J267: SD σ | K267: =_xlfn.STDEV.P(G114:G2123) -> 0.013825919
...

Sheet VC Channel

Sheet M&A Scope
A2: Noteworthy M&A
B3: MedSurg: | E3: American Medical Systems (AMS) Pelvic Health (2015) – $1.6B
F4: Men’s health (BPH/ED) & women’s pelvic floor devices
E5: EndoChoice (2016) – $210M
F6: Single-use endoscopy (complemented SpyGlass)
E7: Lumenis Surgical (2021) – $1.07B
F8: Laser solutions for urology (e.g., MOSES for kidney stones)
E9: Acotec Scientific (2022) – $523M
F10: Drug-coated balloons (DCBs) for China’s vascular market
E11: Apollo Endosurgery (2024) -- N/A
F12: Public company that has developed and commercialized endoscopic suturing devices including OverStitch™ Endoscopic Suturing Systems and X-Tack™ Endoscopic HeliX Tacking Systems and endobariatric devices including the Apollo ESG™ and Apollo REVISE™ Systems
F13: First devices authorized by the FDA for endoscopic sleeve gastroplasty and endoscopic bariatric revision procedures, as well as the Orbera Intragastric Balloon for endoscopic weight management
B15: Rhythm and Neuro: | E15: Cameron Health (2012) – $1.35B
F16: S-ICD (subcutaneous defibrillator), competing with Medtronic/Abbott
E17: Rhythmia Medical (2017) – Undisclosed
F18: High-resolution cardiac mapping (used in Farapulse ablation)
E19: Preventice (2021) – $925M
F20: Remote cardiac monitoring (competing with iRhythm)
E21: Farapulse (2021) – $295M (+ milestones)
F22: Pulsed-field ablation (PFA) for atrial fibrillation (now a $1B+ opportunity)
E23: Relievant Medsystems (2023) – $850M
F24: Privately held medical technology company that has developed and commercialized the Intracept™ Intraosseous Nerve Ablation System
G25: Only FDA-cleared system to treat vertebrogenic pain, a form of chronic low back pain
G26: Intracept (vertebral bone ablation for chronic back pain)
E27: Axonics (2024) – $3.7B (10 months after proposal due to FTC holdups … bubye Lina Khan)
F28: Publicly traded medical technology company primarily focused on the development and commercialization of devices to treat urinary and bowel dysfunction
G29: Axonics’ flagship products are sacral neuromodulation (SNM) systems for urinary incontinence
G30: The Axonics product portfolio includes the Axonics R20™ and Axonics F15™ Systems used to deliver sacral neuromodulation (SNM) therapy for the treatment of over-active bladder and fecal incontinence
F31: Competes directly with Medtronic’s InterStim, a core product in neuromodulation
B33: Cardiovascular: | E33: Guidant (2006) – $27B
F34: Acquired cardiovascular & rhythm management assets (after bidding war with J&J)
F35: Included CRMD (pacemakers/ICDs), angioplasty stents, and vascular surgery
E36: Sadra Medical (2011) – $193M (+ milestones)
F37: Added Lotus Valve (transcatheter aortic valve, later sold to Shockwave)
E38: Symetis (2017) – $435M
F39: ACURATE neo TAVR system (competed with Edwards/Medtronic in Europe)
E40: BTG plc (2019) – $4.2B
F41: Expanded peripheral interventions (e.g., EKOS ultrasound thrombectomy, Galil venous stents)
E42: Baylis Medical (2022) – $1.75B
F43: Transseptal access tools (used in left-heart procedures like Watchman)
F44: Developed the radiofrequency (RF) NRG™ and VersaCross™ Transseptal Platforms as well as a family of guidewires, sheaths and dilators used to support left heart access, which expands The Company's electrophysiology and structural heart product portfolios
F45: Received FDA 510(k) clearance for and launched the VersaCross Connect™ LAAC Access Solution (Q2'22) developed by Baylis Medical, providing safe and efficient access to the left side of the heart
E46: Obsidio (2022) – Undisclosed
F47: Privately held maker of a technology used for embolization of blood vessels
F48: Gel Embolic Material (GEM) technology for vascular occlusion
E49: Silk Road Medical (2024) -- N/A
F50: publicly traded medical device company that has developed an innovative platform of products to prevent stroke in patients with carotid artery disease through a minimally-invasive procedure called transcarotid artery revascularization
E51: Intera (2024) --- $175M
F52: Privately held medical device company that provides the Intera 3000 Hepatic Artery Infusion Pump and floxuridine – a chemotherapy drug (Full FDA approval)
F53: The Intera 3000 pump is used to administer hepatic artery infusion therapy to treat tumors in the liver primarily caused by metastatic colorectal cancer
E54: SoniVie (2025) --- $360M (+ $180M milestones), completed full stake acquisition from initial 26% equity stake
F55: Privately held medical device company that has developed the TIVUS™ Intravascular Ultrasound System
G56: An investigational technology, the TIVUS system is designed to denervate nerves surrounding blood vessels to treat a variety of hypertensive disorders, including renal artery denervation for hypertension
E57: Bolt Medical (2025) -- $516M (+ $148M milestones), completed full stake acquisition from initial 26% equity stake
F58: Intravascular lithotripsy advanced laser-based platform for the treatment of coronary and peripheral artery disease
E59: Cortex (2025) -- $239M (+$50M milestones)
F60: Privately held medical technology company focused on the development of a diagnostic mapping solution which may identify triggers and drivers outside of the pulmonary veins that are foundational to atrial fibrillation (AF)

Sheet Clinical Trial Channel

Sheet Management
B32: Notes: | C32: https://www.bostonscientific.com/en-US/about-us/leadership.html
C33: https://www.morningstar.com/stocks/xnys/bsx/executive
C34: https://www.comparably.com/companies/boston-scientific/executive-team

Sheet Debt Schedule

Sheet Portfolio | Product Lines

Sheet Interventional Cardiology
AS1: 0
A2: ANGIOJET Peripheral Thrombectomy System
B3: The AngioJet Thrombectomy System is a pharmacomechanical peripheral thrombectomy device with active aspiration and Power Pulse™ lytic delivery designed to treat the widest range of thrombosed vessels, rapidly restoring blood flow
C4: AngioJet is a console‑based rheolytic thrombectomy system composed of a mobile drive unit, a disposable pump set, and a family of single‑use catheters
C5: High‑pressure saline is pumped to jet orifices near the catheter tip; the jets exit retrograde, creating a localized low‑pressure (Venturi) zone that sucks thrombus into side windows
D6: The resulting behavior can be thought of as a high‑pressure, internal “washout” within the vessel itself
C7: Fragments and transports clot particles back through the catheter to an external collection bag, providing active aspiration while minimizing distal embolization
B8: Key features that differentiate The Company's thrombectomy offering include:
C9: Rheolytic thrombus removal (no rotating parts), suitable for fresh and subacute clot
C10: Power Pulse™ mode, allowing infusion of physician‑selected lytic agent into the thrombus followed by mechanical removal, i.e., pharmacomechanical thrombectomy
D11: Power Pulse mode is a feature of the AngioJet Thrombectomy System that combines mechanical clot disruption with simultaneous, targeted infusion of thrombolytic drugs (like tPA) directly into the thrombus
D12: Allows for delivering of medication where it's most effective to soften clots and speed up removal … offers flexibility for physicians to treat various clot burdens and restore blood flow rapidly in peripheral arteries
C13: The AngioJet Ultra platform covers arterial, venous, and arteriovenous (AV) access indications (all trad peripheral indications) … Accompaning catheter families optimized by vessel size and anatomy for optimal treatment outcomes
D14: Representative use cases in deep vein thrombosis (DVT), peripheral arteries, AV access (dialysis fistulas and grafts) and legacy coronary treatments
B15: From an industry perspective, newer aspiration‑based systems (PEN Lightning, NARI ClotTriever/FlowTriever) are driving a shift toward larger‑lumen catheters, simplified setup, and “no‑lytic” (tPA / drug assisted thrombectomy) strategies
C16: The use of larger "super-sized" bore catheters is associated with a higher aspiration force and improved clot retrieval efficacy
D17: Elsesser mentioned on a PEN conference call that enlarging catheter lumen improves aspiration force to a point … although simply maximizing lumen size yields diminishing returns due to the physics of fluid dynamics in the brain's vasculature
D18: For aspiration to work effectively, you need "flow ingestion" or the ability to suck the clot into the catheter using high-speed fluid flow …
E19: Elsesser and Penumbra have historically argued that 0.072" (1.83 mm) represents an optimal "sweet spot" for the Middle Cerebral Artery (MCA) balancing three critical factors that decline if lumen size goes larger:
E20: The Corking Effect:
F21: If a catheter is too large (e.g., "super bore" 0.088" in a 2.5mm vessel), it effectively seals the vessel like a cork … This completely stops blood flow …
G22: Without blood flow around the tip, the catheter acts like a static vacuum plug rather than a vacuum cleaner … It cannot "ingest" the clot because there is no fluid flow to sweep the thrombus into the mouth of the catheter
E23: An "Optimal Ratio":
F24: Studies and Penumbra's commentary suggest the optimal catheter-to-vessel diameter ratio is roughly 0.7 to 0.8 … Exceeding this ratio creates a seal that reduces aspiration efficiency
E25: Trackability Trade-off:
F26: Enlarging the lumen generally requires stiffer walls to prevent collapse under vacuum … Ezperts have argued that "super bore" catheters sacrifice the flexibility needed to navigate tortuous anatomy ("trackability") to reach the clot in the first place
A28: EKOS / EKOS+ Endovascular System
B29: Boston Scientific’s EKOS Endovascular System is an ultrasound‑assisted, catheter‑directed thrombolysis platform used to dissolve thrombus in pulmonary embolism (PE), deep vein thrombosis (DVT), and select peripheral arterial occlusions
C30: It is a lytic‑based therapy focused on accelerating and localizing drug effect, rather than a purely mechanical thrombectomy device
C31: The EKOS system consists of three components:
D32: An infusion catheter that delivers a thrombolytic drug (typically tPA) along the length of the clot
D33: An ultrasonic core wire that sits inside the infusion catheter and emits high‑frequency, low‑power ultrasound energy
D34: A control unit that powers and monitors the ultrasonic core
C35: Ultrasound energy mechanically unwinds and thins fibrin strands and produces “acoustic streaming,” which drives the lytic agent deeper into the thrombus and exposes more binding sites
D36: This allows effective clot dissolution with much lower lytic dose and shorter infusion times compared with standard catheter‑directed thrombolysis (CDT) or systemic thrombolysis
D37: EKOS is cleared for ultrasound‑assisted, catheter‑directed thrombolysis in pulmonary Embolism (PE), deep vein thrombosis (DVT), and Peripheral arterial occlusions (POA)
B38: EKOS is fundamentally pharmacologic plus ultrasound; it does not aspirate or physically remove clots in the way PEN, NARI, or other systems do
C39: The device serves the market as an option for patients who are poor candidates for full‑dose systemic lytics but in whom some lytic use is acceptable and as a therapy favored by some centers for intermediate‑risk PE, where data support RV function improvement with relatively low bleeding risk
C40: Mechanical thrombectomy is growing rapidly in the stroke treatment space while gaining guidline traction … there is still a place for EKOS (occupies the ultrasound‑assisted lytic niche), but market share is being taken by aspiration devices
A42: On 1/15/2026 Boston Scientific entered an agreement to acquire Penumbra at $374 dollars per share or ~$14.5B … This is Boston Scientific's largest acquisition to date and vastly exands its Thrombectomy and Embolectomy portfolios

Sheet Watchman
A2: WATCHMAN FLX
B3: The Boston Scientific Watchman FLX is a percutaneous, transcatheter left atrial appendage (LAA) closure device designed as an alternative to long-term oral anticoagulation (OAC) in patients with non-valvular atrial fibrillation (NVAF) at increased risk of stroke and systemic embolism
C4: NVAF significantly increases the risk of thromboembolic stroke due to blood stasis in the left atrial appendage (LAA)
D5: Stroke prevention in atrial fibrillation (AF) patients who either cannot take or do poorly on long‑term anticoagulants
C6: FLX is also approved for NVAF patients eligible for anticoagulation therapy aswell (wider label / patient pool)
B7: Unlike direct oral anticoagulants (DOACs) or warfarin, which carry inherent bleeding risks, the Watchman FLX mechanically excludes the LAA (primary site of thrombus formation in atrial fibrillation (AF)) ... reducing stroke risk without necessitating lifelong anticoagulant treatment
C8: WATCHMAN device was the first of its kind to receive FDA approval as a Left Atrial Appendage Closure (LAAC) device … novel device that emerged from BSX's VC arm and has since been widely adopted by the global market … incredible success story
B9: The device is implanted via a minimally invasive procedure and, following endothelialization, typically allows discontinuation of oral anticoagulants after a short-term post-implant antithrombotic regimen
C10: Large contemporary medical registries report that Watchman implant success rates are ~98-99% and result in high left atrial appendage seal rates, which has reinforced physician confidence and encouraged broader use globally
D11: Better procedural success and more consistent outcomes
B12: Compared to OACs, the Watchman FLX may be particularly advantageous for patients with contraindications to anticoagulation (ex: history of major bleeding, high fall risk, or compliance challenges), offering a durable solution with comparable stroke prevention efficacy while mitigating hemorrhagic risks
C14: Seems like a great technology for addressing risks associated with elderly patients being treated with OACs
B15: Since NVAF-related strokes often originate from the LAA, occluding the LAA (via devices like Watchman FLX) can be an effective alternative to long-term anticoagulation in eligible patients, particularly those with high bleeding risk
B17: Watchman FLX Implant:
F18: WATCHMAN (now mainly WATCHMAN FLX) is a self‑expanding nitinol frame with fixation anchors and a permeable fabric cap (polyethylene terephthalate) that sits at the opening of the left atrial appendage (LAA)
G19: It is delivered percutaneously via a trans‑septal sheath from the femoral vein, then deployed like a parachute/umbrella to plug the LAA orifice
G20: The device is recapturable and repositionable before final release offering physicians superior implant flexibility
G21: Average patient expected to heal within 45 days of the procedure … the exposed surface becomes covered with endothelial tissue, permanently sealing off the LAA so clots that form inside cannot escape into the systemic circulation
H22: Boston Scientific’s cited post-implant regimen in the FLX study was NOAC/ASA for 45 days, then clopidogrel/ASA to 6 months, then aspirin afterward … Rapidly de-risks patients from further thromboembolic stroke complications and drops need for OACs
F23: From an engineering standpoint, while WATCHMAN is 'just' a nitinol plug with fabric, clinically it hits several sweet spots in the market it serves …
G24: Solves a single, well‑characterized failure mode (LAA thrombus formation) with a localized mechanical solution
G25: Converts a chronic systemic therapy problem (lifelong anticoagulation medication ingestion) into a discrete procedural problem, which fits the incentives of hospitals, EP labs, and device companies to drive superior patient outcomes (contrary to many healthcare sceptic beliefs)
G26: BSX's R&D team has iterated quickly (2.5 -> FLX -> FLX Pro) to improve safety and endothelialization while growing the addressable anatomy range over the last few years (see most recent patient TAM numbers below)
B33: Market Position: | D33: https://www.massdevice.com/boston-scientific-farapulse-watchman-drive-2025-growth/
B34: Boston Scientific's Watchman FLX (including its latest iteration, Watchman FLX Pro) holds a commanding position in the global left atrial appendage closure (LAAC) device market, maintaining approximately 70-90% market share due to its robust clinical evidence, first-mover advantage, reimbursement support, and broad physician adoption
C36: Huge, clearly defined patient pool … growing prevelance of AF in a aging global population with a large cohort already intolerant to OACs
C37: For patients and referring physicians, the story is straightforward: “Plug the pouch where the clot forms; potentially stop blood thinners later” … That clarity drives referrals from cardiologists, neurologists, and primary care
D38: Very simple reimbursment process on the commercial side
D39: The device is a key growth engine for Boston Scientific's structural heart portfolio, with the company reporting ~20% compound annual growth rate (CAGR) for Watchman in 2025, reflecting both category expansion and significant sales momentum
C40: Boston Scientific describes WATCHMAN FLX as built on the “most studied and implanted” LAAC platform, which supports physician familiarity and adoption
B41: While Abbott’s Amplatzer Amulet is gaining share in Europe and launched in the US, Watchman’s entrenched customer base, earlier US approval, and continuous innovation enable it to maintain a substantial lead in both procedural volume and revenue
B42: In July, Boston Scientific received FDA approval expanding Watchman FLX and FLX Pro labels to include post-ablation patients, potentially adding 1-2 million patients globally to their market
C43: Expansion to potential patient population is BIG and will substantially boost procedural volumes, securing Watchman's category leadership
B44: Boston Scientific received FDA approval expanding Watchman FLX and FLX Pro labels to include post-ablation patients, potentially adding 1-2 million patients globally to their market
