Workbook

Sheet Main
B2: DIS
B3: Price | C3: 106 | D3: 2/20/26
B4: SO | C4: 1771.519 | D4: Q4'25
B5: MC | C5: =C3*C4 -> 187781.01
B6: Cash | C6: 5678 | D6: Q4'25
B7: Debt | C7: =35821+10819 -> 46640 | D7: Q4'25
B8: EV | C8: =C5-C6+C7 -> 228743.01
B10: The Walt Disney Company (DIS)
B12: Founder(s): Walt Disney & Roy Disney | G12: Registered Exchange: NYSE | N12: Resources:
B13: Founded: October 16, 1923 | G13: Address: 500 South Buena Vista Street Burbank, CA 91521 U.S. | N13: SEC filings | Q13: https://www.sec.gov/edgar/browse/?CIK=1744489&owner=exclude
B14: Headquarters: Burbank, CA | G14: Investor Relations Contact: | N14: Company Homepage | Q14: https://www.disney.com/
B15: Current CEO: Josh D'Amaro | G15: Investors Relation Department | N15: Company Homepage | Q15: https://thewaltdisneycompany.com/
B16: Employees: 231,000 | G16: Phone: | H16: (818) 560 - 1000 | J16: Email: | O16: Company IR Page | R16: https://investors.thewaltdisneycompany.com/
B17: Industry: Entertainment | N17: Earnings Calls | Q17: https://seekingalpha.com/symbol/DIS/earnings/transcripts
B18: Sector: Communication Services | N18: Equity Analysis | Q18: https://stockanalysis.com/stocks/dis/company/
B19: IPO: Nov 12th, 1957 | N19: MacroTrends | Q19: https://www.macrotrends.net/stocks/charts/DIS/disney/net-income
B20: Fiscal Year: [October - September] | N20: ROIC, WACC | Q20: https://www.gurufocus.com/term/wacc/DIS
N21: Godel Terminal | Q21: https://app.godelterminal.com/
A22: Company Overview:
B23: The Walt Disney Company operates as an entertainment company in Americas, Europe, and the Asia Pacific
C24: It operates in three segments: Entertainment (film/TV and streaming), Sports (ESPN), and Experiences (parks, resorts, cruise, and consumer products), with Disney+ as the core of its direct‑to‑consumer infrastructure strategy and Parks as its economic/cashflow engine
C25: Entertainment Segment | F25: Linear Networks: Domestic and international channels including ABC, Disney Channel, FX, Freeform, and National Geographic
F26: Direct-to-Consumer (DTC): Streaming services Disney+, Disney+ Hotstar, Hulu, and Star+
F27: Content Sales/Licensing and Other: Theatrical distribution of films (Disney, Pixar, Marvel, Lucasfilm, 20th Century Studios), licensing to third‑party TV and SVOD platforms, home entertainment, music, and production/post‑production services via Industrial Light & Magic and Skywalker Sound
C28: Sports Segment (ESPN) | F28: Domestic and international ESPN branded networks (ESPN, ESPN2, ESPNU, SEC Network, etc.), ESPN+ streaming, and sports content on Hulu
G29: ESPN is being repositioned around a long‑planned standalone ESPN streaming app, with bundling alongside Disney+ and Hulu to anchor the sports piece of the DTC portfolio
C30: Disney+ and Streaming: | F30: Disney+ sits at the center of the company’s effort to pivot from linear TV to subscription streaming
G31: Disney executives have put a great deal of time, effort, and capital into this segment in hopes of developing it into the underpinning for The Company's content distrubution
G32: The strategic objective: reach sustainable profitability in streaming while maintaining scale, shifting investor focus from net adds to ARPU and engagement
G33: Management has already signaled it will de‑emphasize subscriber numbers and instead track profitability and engagement, similar to Netflix
F34: The Company is focuesed on wider penetration with Disney+ and subsidiary distributors … There is a plan to consolidate streaming platforms (Disney+, ESPN, Hulu) into a package offering … They literally just recreated cable packages under new management (No more Dish or DirectTV)
C35: Experiences Segment: | F35: Disney’s Experiences segment is The Company’s money printing, economic powerhouse ... Generates the majority of The Firm's operating income on the financial statements … milking Disney adults is the real business driver
G36: Domestic parks in California and Florida … International parks in Paris, Hong Kong, Shanghai, and a specialized deal in Tokoyo
C37: Entertainment is ~45% of The Company's revenues, Sports is ~35% of The Company's revenues, Entertainment is ~20% of The Company's revenues
B38: The Company was founded in 1923 as the Disney Brothers Cartoon Studio; the modern company traces its start to an October 16, 1923 distribution deal for the Alice Comedies
C39: Over the decades, Disney expanded from animation into feature films, TV, consumer products, and theme parks (Disneyland 1955; Walt Disney World 1971), and later into cable networks (ABC/ESPN), studios (Pixar, Marvel, Lucasfilm, 21st Century Fox assets), and streaming
C40: Bob Iger stepped down as CEO of The Company on March 18th, 2026
A42: Business Segments and Geographical Info:

Sheet Model
B1: [Use for Graphing] | AA1: Q1 2020 | AE1: Q1 2021 | AI1: Q1 2022 | AM1: Q1 2023 | AQ1: Q1 2024 | AU1: Q1 2025 | AY1: Q1 2026
B2: Quarterly
B3: Revenues | C3: {="Q"&MOD(_xlfn.SEQUENCE(1,52)-1,4)+1&" "&(2014+INT((_xlfn.SEQUENCE(1,52)-1)/4))} -> Q1 2014 | D3: Q2 2014 | E3: Q3 2014 | F3: Q4 2014 | G3: Q1 2015 | H3: Q2 2015 | I3: Q3 2015 | J3: Q4 2015 | K3: Q1 2016 | L3: Q2 2016 | M3: Q3 2016 | N3: Q4 2016 | O3: Q1 2017 | P3: Q2 2017 | Q3: Q3 2017 | R3: Q4 2017 | S3: Q1 2018 | T3: Q2 2018 | U3: Q3 2018 | V3: Q4 2018 | W3: Q1 2019 | X3: Q2 2019 | Y3: Q3 2019 | Z3: Q4 2019 | AA3: Q1 2020 | AB3: Q2 2020 | AC3: Q3 2020 | AD3: Q4 2020 | AE3: Q1 2021 | AF3: Q2 2021 | AG3: Q3 2021 | AH3: Q4 2021 | AI3: Q1 2022 | AJ3: Q2 2022 | AK3: Q3 2022 | AL3: Q4 2022 | AM3: Q1 2023 | AN3: Q2 2023 | AO3: Q3 2023 | AP3: Q4 2023 | AQ3: Q1 2024 | AR3: Q2 2024 | AS3: Q3 2024 | AT3: Q4 2024 | AU3: Q1 2025 | AV3: Q2 2025 | AW3: Q3 2025 | AX3: Q4 2025 | AY3: Q1 2026 | AZ3: Q2 2026 | BA3: Q3 2026 | BB3: Q4 2026 | BG3: 2014 | BH3: =BG3+1 -> 2015 | BI3: =BH3+1 -> 2016 | BJ3: =BI3+1 -> 2017 | BK3: =BJ3+1 -> 2018 | BL3: =BK3+1 -> 2019 | BM3: =BL3+1 -> 2020 | BN3: =BM3+1 -> 2021 | BO3: =BN3+1 -> 2022 | ... DZ3: =DY3+1 -> 2085
B4: Entertainment | AQ4: 9981 | AR4: 9796 | AS4: 10580 | AT4: =41186-SUM(AQ4:AS4) -> 10829 | AU4: 10872 | AV4: 10682 | AW4: 10704 | AX4: =42466-SUM(AU4:AW4) -> 10208 | AY4: 11609 | BQ4: =SUM(AQ4:AT4) -> 41186 | BR4: =SUM(AU4:AX4) -> 42466 | BS4: =BR4*(1+BS9) -> 44164.64 | BT4: =BS4*(1+BT9) -> 46372.872 | BU4: =BT4*(1+BU9) -> 48227.787 | BV4: =BU4*(1+BV9) -> 49674.62 | BW4: =BV4*(1+BW9) -> 51040.673 | BX4: =BW4*(1+BX9) -> 52316.689 | BY4: =BX4*(1+BY9) -> 53493.815 | BZ4: =BY4*(1+BZ9) -> 54563.691 | ... CB4: =CA4*(1+CB9) -> 56351.334
B5: Sports | AQ5: 4835 | AR5: 4312 | AS5: 4558 | AT5: =17619-SUM(AQ5:AS5) -> 3914 | AU5: 4850 | AV5: 4534 | AW5: 4308 | AX5: =17672-SUM(AU5:AW5) -> 3980 | AY5: 4909 | BQ5: =SUM(AQ5:AT5) -> 17619 | BR5: =SUM(AU5:AX5) -> 17672 | BS5: =BR5*(1+BS10) -> 18555.6 | BT5: =BS5*(1+BT10) -> 19854.492 | BU5: =BT5*(1+BU10) -> 21045.762 | BV5: =BU5*(1+BV10) -> 22413.736 | BW5: =BV5*(1+BW10) -> 23982.698 | BX5: =BW5*(1+BX10) -> 25301.746 | BY5: =BX5*(1+BY10) -> 26566.833 | BZ5: =BY5*(1+BZ10) -> 27762.341 | ... CB5: =CA5*(1+CB10) -> 30099.93
B6: Experiences | AQ6: =9132-399 -> 8733 | AR6: =8393-418 -> 7975 | AS6: =8386-369 -> 8017 | AT6: =34151-1595-SUM(AQ6:AS6) -> 7831 | AU6: =9415-447 -> 8968 | AV6: =8889-484 -> 8405 | AW6: =9086-448 -> 8638 | AX6: =36156-1869-SUM(AU6:AW6) -> 8276 | AY6: =10006-543 -> 9463 | BQ6: =SUM(AQ6:AT6) -> 32556 | BR6: =SUM(AU6:AX6) -> 34287 | BS6: =BR6*(1+BS11) -> 36344.22 | BT6: =BS6*(1+BT11) -> 38161.431 | BU6: =BT6*(1+BU11) -> 38924.66 | BV6: =BU6*(1+BV11) -> 40092.399 | BW6: =BV6*(1+BW11) -> 40493.323 | BX6: =BW6*(1+BX11) -> 42517.99 | BY6: =BX6*(1+BY11) -> 45069.069 | BZ6: =BY6*(1+BZ11) -> 46871.832 | ... CB6: =CA6*(1+CB11) -> 49243.546
B7: Ttl Revenues | AQ7: =SUM(AQ4:AQ6) -> 23549 | AR7: =SUM(AR4:AR6) -> 22083 | AS7: =SUM(AS4:AS6) -> 23155 | AT7: =SUM(AT4:AT6) -> 22574 | AU7: =SUM(AU4:AU6) -> 24690 | AV7: =SUM(AV4:AV6) -> 23621 | AW7: =SUM(AW4:AW6) -> 23650 | AX7: =SUM(AX4:AX6) -> 22464 | AY7: =SUM(AY4:AY6) -> 25981 | BQ7: =SUM(AQ7:AT7) -> 91361 | BR7: =SUM(AU7:AX7) -> 94425 | BS7: =SUM(BS4:BS6) -> 99064.46 | BT7: =SUM(BT4:BT6) -> 104388.8 | BU7: =SUM(BU4:BU6) -> 108198.21 | BV7: =SUM(BV4:BV6) -> 112180.76 | BW7: =SUM(BW4:BW6) -> 115516.69 | BX7: =SUM(BX4:BX6) -> 120136.42 | BY7: =SUM(BY4:BY6) -> 125129.72 | BZ7: =SUM(BZ4:BZ6) -> 129197.86 | ... CB7: =SUM(CB4:CB6) -> 135694.81
B9: Entertainment Growth Y/y | AU9: =AU4/AQ4-1 -> 0.089269612 | AV9: =AV4/AR4-1 -> 0.09044508 | AW9: =AW4/AS4-1 -> 0.011720227 | AX9: =AX4/AT4-1 -> -0.057346015 | AY9: =AY4/AU4-1 -> 0.067788815 | BR9: =BR4/BQ4-1 -> 0.031078522 | BS9: 0.04 | BT9: 0.05 | BU9: 0.04 | BV9: 0.03 | BW9: 0.0275 | BX9: 0.025 | BY9: 0.0225 | BZ9: 0.02 | CA9: 0.0175 | CB9: 0.015
B10: Sports Growth Y/y | AU10: =AU5/AQ5-1 -> 0.0031023785 | AV10: =AV5/AR5-1 -> 0.05148423 | AW10: =AW5/AS5-1 -> -0.054848618 | AX10: =AX5/AT5-1 -> 0.016862545 | AY10: =AY5/AU5-1 -> 0.012164948 | BR10: =BR5/BQ5-1 -> 0.0030081162 | BS10: 0.05 | BT10: 0.07 | BU10: 0.06 | BV10: 0.065 | BW10: 0.07 | BX10: 0.055 | BY10: 0.05 | BZ10: 0.045 | CA10: 0.0425 | CB10: 0.04
B11: Experiences Growth Y/y | AU11: =AU6/AQ6-1 -> 0.026909424 | AV11: =AV6/AR6-1 -> 0.053918495 | AW11: =AW6/AS6-1 -> 0.077460397 | AX11: =AX6/AT6-1 -> 0.056825437 | AY11: =AY6/AU6-1 -> 0.055196253 | BR11: =BR6/BQ6-1 -> 0.053169923 | BS11: 0.06 | BT11: 0.05 | BU11: 0.02 | BV11: 0.03 | BW11: 0.01 | BX11: 0.05 | BY11: 0.06 | BZ11: 0.04 | CA11: 0.03 | CB11: 0.02
B12: Ttl Revenue Growth Y/y | AU12: =AU7/AQ7-1 -> 0.048452164 | AV12: =AV7/AR7-1 -> 0.069646334 | AW12: =AW7/AS7-1 -> 0.021377672 | AX12: =AX7/AT7-1 -> -0.0048728626 | AY12: =AY7/AU7-1 -> 0.052288376 | BR12: =BR7/BQ7-1 -> 0.033537286 | BS12: =BS7/BR7-1 -> 0.04913381 | BT12: =BT7/BS7-1 -> 0.053746167 | BU12: =BU7/BT7-1 -> 0.036492547 | BV12: =BV7/BU7-1 -> 0.036807891 | BW12: =BW7/BV7-1 -> 0.029737164 | BX12: =BX7/BW7-1 -> 0.039991894 | BY12: =BY7/BX7-1 -> 0.041563516 | ... CB12: =CB7/CA7-1 -> 0.02226951
B14: Entertainment % of Ttl Revenues | AQ14: =AQ4/AQ7 -> 0.42383965 | AR14: =AR4/AR7 -> 0.44359915 | AS14: =AS4/AS7 -> 0.45692075 | AT14: =AT4/AT7 -> 0.47971117 | AU14: =AU4/AU7 -> 0.44034022 | AV14: =AV4/AV7 -> 0.45222472 | AW14: =AW4/AW7 -> 0.45260042 | AX14: =AX4/AX7 -> 0.45441595 | AY14: =AY4/AY7 -> 0.44682653 | BQ14: =BQ4/BQ7 -> 0.45080505 | BR14: =BR4/BR7 -> 0.44973259 | BS14: =BS4/BS7 -> 0.4458172 | BT14: =BT4/BT7 -> 0.44423228 | BU14: =BU4/BU7 -> 0.44573554 | BV14: =BV4/BV7 -> 0.44280875 | BW14: =BW4/BW7 -> 0.44184672 | BX14: =BX4/BX7 -> 0.43547733 | ... CB14: =CB4/CB7 -> 0.41527995
B15: Sports % of Ttl Revenues | AQ15: =AQ5/AQ7 -> 0.20531657 | AR15: =AR5/AR7 -> 0.19526332 | AS15: =AS5/AS7 -> 0.19684733 | AT15: =AT5/AT7 -> 0.17338531 | AU15: =AU5/AU7 -> 0.1964358 | AV15: =AV5/AV7 -> 0.19194784 | AW15: =AW5/AW7 -> 0.18215645 | AX15: =AX5/AX7 -> 0.17717236 | AY15: =AY5/AY7 -> 0.18894577 | BQ15: =BQ5/BQ7 -> 0.19285034 | BR15: =BR5/BR7 -> 0.18715383 | BS15: =BS5/BS7 -> 0.18730834 | BT15: =BT5/BT7 -> 0.19019754 | BU15: =BU5/BU7 -> 0.19451118 | BV15: =BV5/BV7 -> 0.19980019 | BW15: =BW5/BW7 -> 0.2076124 | BX15: =BX5/BX7 -> 0.21060845 | ... CB15: =CB5/CB7 -> 0.22182079
B16: Experiences % of Ttl Revenues | AQ16: =AQ6/AQ7 -> 0.37084377 | AR16: =AR6/AR7 -> 0.36113753 | AS16: =AS6/AS7 -> 0.34623192 | AT16: =AT6/AT7 -> 0.34690352 | AU16: =AU6/AU7 -> 0.36322398 | AV16: =AV6/AV7 -> 0.35582744 | AW16: =AW6/AW7 -> 0.36524313 | AX16: =AX6/AX7 -> 0.36841168 | AY16: =AY6/AY7 -> 0.3642277 | BQ16: =BQ6/BQ7 -> 0.35634461 | BR16: =BR6/BR7 -> 0.36311358 | BS16: =BS6/BS7 -> 0.36687446 | BT16: =BT6/BT7 -> 0.36557018 | BU16: =BU6/BU7 -> 0.35975327 | BV16: =BV6/BV7 -> 0.35739106 | BW16: =BW6/BW7 -> 0.35054088 | BX16: =BX6/BX7 -> 0.35391422 | ... CB16: =CB6/CB7 -> 0.36289926
B18: Entertainment | AQ18: 874 | AR18: 781 | AS18: 1201 | AT18: =3923-SUM(AQ18:AS18) -> 1067 | AU18: 1703 | AV18: 1258 | AW18: 1201 | AX18: =4674-SUM(AU18:AW18) -> 512 | AY18: 1100 | BQ18: =SUM(AQ18:AT18) -> 3923 | BR18: =SUM(AU18:AX18) -> 4674 | BS18: =BR18*(1+BS23) -> 5562.06 | BT18: =BS18*(1+BT23) -> 6624.4135 | BU18: =BT18*(1+BU23) -> 7916.1741 | BV18: =BU18*(1+BV23) -> 9467.7442 | BW18: =BV18*(1+BW23) -> 11332.89 | BX18: =BW18*(1+BX23) -> 13599.468 | BY18: =BX18*(1+BY23) -> 16346.56 | BZ18: =BY18*(1+BZ23) -> 19681.259 | ... CB18: =CA18*(1+CB23) -> 28601.395
B19: Sports | AQ19: -103 | AR19: 778 | AS19: 802 | AT19: =2406-SUM(AQ19:AS19) -> 929 | AU19: 247 | AV19: 687 | AW19: 802 | AX19: =2882-SUM(AU19:AW19) -> 1146 | AY19: 191 | BQ19: =SUM(AQ19:AT19) -> 2406 | BR19: =SUM(AU19:AX19) -> 2882 | BS19: =BR19*(1+BS24) -> 3461.282 | BT19: =BS19*(1+BT24) -> 4167.3835 | BU19: =BT19*(1+BU24) -> 5025.8645 | BV19: =BU19*(1+BV24) -> 6071.2444 | BW19: =BV19*(1+BW24) -> 7291.5645 | BX19: =BW19*(1+BX24) -> 8786.3352 | BY19: =BX19*(1+BY24) -> 10609.5 | BZ19: =BY19*(1+BZ24) -> 12837.495 | ... CB19: =CA19*(1+CB24) -> 18842.002
B20: Experiences | AQ20: 3105 | AR20: 2286 | AS20: 2222 | AT20: =9272-SUM(AQ20:AS20) -> 1659 | AU20: 3110 | AV20: 2491 | AW20: 2222 | AX20: =9995-SUM(AU20:AW20) -> 2172 | AY20: 3309 | BQ20: =SUM(AQ20:AT20) -> 9272 | BR20: =SUM(AU20:AX20) -> 9995 | BS20: =BR20*(1+BS25) -> 10794.6 | BT20: =BS20*(1+BT25) -> 11766.114 | BU20: =BT20*(1+BU25) -> 12942.725 | BV20: =BU20*(1+BV25) -> 14301.712 | BW20: =BV20*(1+BW25) -> 15874.9 | BX20: =BW20*(1+BX25) -> 17700.513 | BY20: =BX20*(1+BY25) -> 19780.324 | BZ20: =BY20*(1+BZ25) -> 22153.962 | ... CB20: =CA20*(1+CB25) -> 27789.931
B21: Ttl Operating Income | AQ21: =SUM(AQ18:AQ20) -> 3876 | AR21: =SUM(AR18:AR20) -> 3845 | AS21: =SUM(AS18:AS20) -> 4225 | AT21: =SUM(AT18:AT20) -> 3655 | AU21: =SUM(AU18:AU20) -> 5060 | AV21: =SUM(AV18:AV20) -> 4436 | AW21: =SUM(AW18:AW20) -> 4225 | AX21: =SUM(AX18:AX20) -> 3830 | AY21: =SUM(AY18:AY20) -> 4600 | BQ21: =SUM(AQ21:AT21) -> 15601 | BR21: =SUM(AU21:AX21) -> 17551 | BS21: =SUM(BS18:BS20) -> 19817.942 | BT21: =SUM(BT18:BT20) -> 22557.911 | BU21: =SUM(BU18:BU20) -> 25884.764 | BV21: =SUM(BV18:BV20) -> 29840.7 | BW21: =SUM(BW18:BW20) -> 34499.354 | BX21: =SUM(BX18:BX20) -> 40086.316 | BY21: =SUM(BY18:BY20) -> 46736.384 | BZ21: =SUM(BZ18:BZ20) -> 54672.716 | ... CB21: =SUM(CB18:CB20) -> 75233.328
B23: Entertainment Growth Y/y | AU23: =AU18/AQ18-1 -> 0.94851259 | AV23: =AV18/AR18-1 -> 0.61075544 | AW23: =AW18/AS18-1 -> 0 | AX23: =AX18/AT18-1 -> -0.52014995 | AY23: =AY18/AU18-1 -> -0.35408103 | BR23: =BR18/BQ18-1 -> 0.19143513 | BS23: 0.19 | BT23: 0.191 | BU23: 0.195 | BV23: 0.196 | BW23: 0.197 | BX23: 0.2 | BY23: 0.202 | BZ23: 0.204 | CA23: 0.205 | CB23: 0.206
B24: Sports Growth Y/y | AU24: =AU19/AQ19-1 -> -3.3980583 | AV24: =AV19/AR19-1 -> -0.11696658 | AW24: =AW19/AS19-1 -> 0 | AX24: =AX19/AT19-1 -> 0.2335845 | AY24: =AY19/AU19-1 -> -0.22672065 | BR24: =BR19/BQ19-1 -> 0.19783874 | BS24: 0.201 | BT24: 0.204 | BU24: 0.206 | BV24: 0.208 | BW24: 0.201 | BX24: 0.205 | BY24: 0.2075 | BZ24: 0.21 | CA24: 0.211 | CB24: 0.212
B25: Experiences Growth Y/y | AU25: =AU20/AQ20-1 -> 0.001610306 | AV25: =AV20/AR20-1 -> 0.08967629 | AW25: =AW20/AS20-1 -> 0 | AX25: =AX20/AT20-1 -> 0.30922242 | AY25: =AY20/AU20-1 -> 0.063987138 | BR25: =BR20/BQ20-1 -> 0.077976704 | BS25: 0.08 | BT25: 0.09 | BU25: 0.1 | BV25: 0.105 | BW25: 0.11 | BX25: 0.115 | BY25: 0.1175 | BZ25: 0.12 | CA25: 0.12 | CB25: 0.12
B26: Ttl Operating Income Growth Y/y | AU26: =AU21/AQ21-1 -> 0.30546956 | AV26: =AV21/AR21-1 -> 0.15370611 | AW26: =AW21/AS21-1 -> 0 | AX26: =AX21/AT21-1 -> 0.047879617 | AY26: =AY21/AU21-1 -> -0.090909091 | BR26: =BR21/BQ21-1 -> 0.12499199 | BS26: =BS21/BR21-1 -> 0.12916312 | BT26: =BT21/BS21-1 -> 0.13825699 | BU26: =BU21/BT21-1 -> 0.14748055 | BV26: =BV21/BU21-1 -> 0.15282875 | BW26: =BW21/BV21-1 -> 0.15611745 | BX26: =BX21/BW21-1 -> 0.16194396 | BY26: =BY21/BX21-1 -> 0.1658937 | ... CB26: =CB21/CA21-1 -> 0.17415285
B28: Entertainment % of Operating Income | AQ28: =AQ18/AQ21 -> 0.2254902 | AR28: =AR18/AR21 -> 0.20312094 | AS28: =AS18/AS21 -> 0.28426036 | AT28: =AT18/AT21 -> 0.29192886 | AU28: =AU18/AU21 -> 0.33656126 | AV28: =AV18/AV21 -> 0.28358882 | AW28: =AW18/AW21 -> 0.28426036 | AX28: =AX18/AX21 -> 0.13368146 | AY28: =AY18/AY21 -> 0.23913043 | BQ28: =BQ18/BQ21 -> 0.25145824 | BR28: =BR18/BR21 -> 0.26630961
B29: Sports % of Operating Income | AQ29: =AQ19/AQ21 -> -0.026573787 | AR29: =AR19/AR21 -> 0.2023407 | AS29: =AS19/AS21 -> 0.18982249 | AT29: =AT19/AT21 -> 0.25417237 | AU29: =AU19/AU21 -> 0.048814229 | AV29: =AV19/AV21 -> 0.15486925 | AW29: =AW19/AW21 -> 0.18982249 | AX29: =AX19/AX21 -> 0.29921671 | AY29: =AY19/AY21 -> 0.041521739 | BQ29: =BQ19/BQ21 -> 0.15422088 | BR29: =BR19/BR21 -> 0.16420717
B30: Experiences % of Operating Income | AQ30: =AQ20/AQ21 -> 0.80108359 | AR30: =AR20/AR21 -> 0.59453836 | AS30: =AS20/AS21 -> 0.52591716 | AT30: =AT20/AT21 -> 0.45389877 | AU30: =AU20/AU21 -> 0.61462451 | AV30: =AV20/AV21 -> 0.56154193 | AW30: =AW20/AW21 -> 0.52591716 | AX30: =AX20/AX21 -> 0.56710183 | AY30: =AY20/AY21 -> 0.71934783 | BQ30: =BQ20/BQ21 -> 0.59432088 | BR30: =BR20/BR21 -> 0.56948322
B32: Americas Revenues | AQ32: 18584 | AR32: 17641 | AS32: 18293 | AT32: =72162-SUM(AQ32:AS32) -> 17644 | AU32: 19882 | AV32: 19485 | AW32: 19163 | AX32: =76430-SUM(AU32:AW32) -> 17900 | AY32: 20862 | BQ32: =SUM(AQ32:AT32) -> 72162 | BR32: =SUM(AU32:AX32) -> 76430
B33: Euro Revenues | AQ33: 2610 | AR33: 2281 | AS33: 2572 | AT33: =10279-SUM(AQ33:AS33) -> 2816 | AU33: 2855 | AV33: 2450 | AW33: 2829 | AX33: =11090-SUM(AU33:AW33) -> 2956 | AY33: 3079 | BQ33: =SUM(AQ33:AT33) -> 10279 | BR33: =SUM(AU33:AX33) -> 11090
B34: APac Revenues | AQ34: 2355 | AR34: 2161 | AS34: 2290 | AT34: =8920-SUM(AQ34:AS34) -> 2114 | AU34: 1953 | AV34: 1686 | AW34: 1658 | AX34: =6905-SUM(AU34:AW34) -> 1608 | AY34: 2040 | BQ34: =SUM(AQ34:AT34) -> 8920 | BR34: =SUM(AU34:AX34) -> 6905
B35: Ttl Revenues | AQ35: =SUM(AQ32:AQ34) -> 23549 | AR35: =SUM(AR32:AR34) -> 22083 | AS35: =SUM(AS32:AS34) -> 23155 | AT35: =SUM(AT32:AT34) -> 22574 | AU35: =SUM(AU32:AU34) -> 24690 | AV35: =SUM(AV32:AV34) -> 23621 | AW35: =SUM(AW32:AW34) -> 23650 | AX35: =SUM(AX32:AX34) -> 22464 | AY35: =SUM(AY32:AY34) -> 25981 | BQ35: =SUM(AQ35:AT35) -> 91361 | BR35: =SUM(AU35:AX35) -> 94425
B37: Americas Revenue Growth Y/y | AU37: =AU32/AQ32-1 -> 0.069845028 | AV37: =AV32/AR32-1 -> 0.10452922 | AW37: =AW32/AS32-1 -> 0.047559176 | AX37: =AX32/AT32-1 -> 0.014509182 | AY37: =AY32/AU32-1 -> 0.049290816 | BR37: =BR32/BQ32-1 -> 0.059144702
B38: Euro Revenue Growth Y/y | AU38: =AU33/AQ33-1 -> 0.093869732 | AV38: =AV33/AR33-1 -> 0.074090311 | AW38: =AW33/AS33-1 -> 0.09992224 | AX38: =AX33/AT33-1 -> 0.049715909 | AY38: =AY33/AU33-1 -> 0.078458844 | BR38: =BR33/BQ33-1 -> 0.078898726
B39: APac Revenue Growth Y/y | AU39: =AU34/AQ34-1 -> -0.17070064 | AV39: =AV34/AR34-1 -> -0.21980565 | AW39: =AW34/AS34-1 -> -0.27598253 | AX39: =AX34/AT34-1 -> -0.23935667 | AY39: =AY34/AU34-1 -> 0.044546851 | BR39: =BR34/BQ34-1 -> -0.22589686
B40: Ttl Revenue Growth Y/y | AU40: =AU35/AQ35-1 -> 0.048452164 | AV40: =AV35/AR35-1 -> 0.069646334 | AW40: =AW35/AS35-1 -> 0.021377672 | AX40: =AX35/AT35-1 -> -0.0048728626 | AY40: =AY35/AU35-1 -> 0.052288376 | BR40: =BR35/BQ35-1 -> 0.033537286
B42: U.S. % of Revenues | AQ42: =AQ32/AQ35 -> 0.78916302 | AR42: =AR32/AR35 -> 0.79884979 | AS42: =AS32/AS35 -> 0.79002375 | AT42: =AT32/AT35 -> 0.78160716 | AU42: =AU32/AU35 -> 0.80526529 | AV42: =AV32/AV35 -> 0.82490157 | AW42: =AW32/AW35 -> 0.81027484 | AX42: =AX32/AX35 -> 0.79683048 | AY42: =AY32/AY35 -> 0.8029714 | BQ42: =BQ32/BQ35 -> 0.78985563 | BR42: =BR32/BR35 -> 0.80942547
B43: Euro Revenues % of Revenues | AQ43: =AQ33/AQ35 -> 0.11083273 | AR43: =AR33/AR35 -> 0.10329213 | AS43: =AS33/AS35 -> 0.11107752 | AT43: =AT33/AT35 -> 0.12474528 | AU43: =AU33/AU35 -> 0.11563386 | AV43: =AV33/AV35 -> 0.10372126 | AW43: =AW33/AW35 -> 0.11961945 | AX43: =AX33/AX35 -> 0.13158832 | AY43: =AY33/AY35 -> 0.11850968 | BQ43: =BQ33/BQ35 -> 0.11250971 | BR43: =BR33/BR35 -> 0.11744771
B44: APac Revenues % of Revenues | AQ44: =AQ34/AQ35 -> 0.10000425 | AR44: =AR34/AR35 -> 0.097858081 | AS44: =AS34/AS35 -> 0.098898726 | AT44: =AT34/AT35 -> 0.093647559 | AU44: =AU34/AU35 -> 0.079100851 | AV44: =AV34/AV35 -> 0.071377164 | AW44: =AW34/AW35 -> 0.070105708 | AX44: =AX34/AX35 -> 0.071581197 | AY44: =AY34/AY35 -> 0.078518918 | BQ44: =BQ34/BQ35 -> 0.097634658 | BR44: =BR34/BR35 -> 0.07312682
B46: Revenues | C46: 12309 | D46: 11649 | E46: 12466 | F46: 12389 | G46: 13391 | H46: 12461 | I46: 13101 | J46: 13512 | K46: 15244 | L46: 12969 | M46: 14277 | N46: 13142 | O46: 14784 | P46: 13336 | Q46: 14238 | R46: 12779 | S46: 15351 | T46: 14548 | U46: 15229 | V46: 14306 | W46: 15303 | X46: 14922 | Y46: 20262 | Z46: 19120 | AA46: 20877 | AB46: 18025 | AC46: 11779 | AD46: 14707 | AE46: 16249 | AF46: 15613 | AG46: 17022 | AH46: 18534 | AI46: 21819 | AJ46: 19249 | AK46: 21504 | AL46: 20150 | AM46: 23512 | AN46: 21815 | AO46: 22330 | AP46: 21241 | AQ46: 23549 | AR46: 22083 | AS46: 23155 | AT46: 22574 | AU46: 24690 | AV46: 23621 | AW46: 23650 | AX46: 22464 | AY46: 25981 | BG46: =SUM(C46:F46) -> 48813 | BH46: =SUM(G46:J46) -> 52465 | BI46: =SUM(K46:N46) -> 55632 | BJ46: =SUM(O46:R46) -> 55137 | BK46: =SUM(S46:V46) -> 59434 | BL46: =SUM(W46:Z46) -> 69607 | BM46: =SUM(AA46:AD46) -> 65388 | BN46: =SUM(AE46:AH46) -> 67418 | BO46: =SUM(AI46:AL46) -> 82722 | BP46: =SUM(AM46:AP46) -> 88898 | BQ46: =SUM(AQ46:AT46) -> 91361 | BR46: =SUM(AU46:AX46) -> 94425 | BS46: =BS7 -> 99064.46 | BT46: =BT7 -> 104388.8 | BU46: =BU7 -> 108198.21 | BV46: =BV7 -> 112180.76 | BW46: =BW7 -> 115516.69 | BX46: =BX7 -> 120136.42 | BY46: =BY7 -> 125129.72 | BZ46: =BZ7 -> 129197.86 | ... CB46: =CB7 -> 135694.81
B47: COGS | C47: 7065 | D47: 5972 | E47: 6364 | F47: 7019 | G47: 7656 | H47: 6690 | I47: 6663 | J47: 7355 | K47: 8623 | L47: 6864 | M47: 7201 | N47: 7305 | O47: 8406 | P47: 6969 | Q47: 7717 | R47: 7214 | S47: 8729 | T47: 7541 | U47: 8348 | V47: 8108 | W47: 9001 | X47: 8376 | Y47: 12837 | Z47: 11847 | AA47: 13034 | AB47: 11937 | AC47: 7896 | AD47: 11013 | AE47: 11775 | AF47: 9782 | AG47: 11233 | AH47: 12341 | AI47: 14567 | AJ47: 12594 | AK47: 13682 | AL47: 13558 | AM47: 16386 | AN47: 14616 | AO47: 14471 | AP47: 13728 | AQ47: 15587 | AR47: 14172 | AS47: 14709 | AT47: 14230 | AU47: 15406 | AV47: 14810 | AW47: 14532 | AX47: 14018 | AY47: 16669 | BG47: =SUM(C47:F47) -> 26420 | BH47: =SUM(G47:J47) -> 28364 | BI47: =SUM(K47:N47) -> 29993 | BJ47: =SUM(O47:R47) -> 30306 | BK47: =SUM(S47:V47) -> 32726 | BL47: =SUM(W47:Z47) -> 42061 | BM47: =SUM(AA47:AD47) -> 43880 | BN47: =SUM(AE47:AH47) -> 45131 | BO47: =SUM(AI47:AL47) -> 54401 | BP47: =SUM(AM47:AP47) -> 59201 | BQ47: =SUM(AQ47:AT47) -> 58698 | BR47: =SUM(AU47:AX47) -> 58766 | BS47: =BS46*(1-BS65) -> 61653.397 | BT47: =BT46*(1-BT65) -> 64967.031 | BU47: =BU46*(1-BU65) -> 67337.844 | BV47: =BV46*(1-BV65) -> 69816.408 | BW47: =BW46*(1-BW65) -> 71892.55 | BX47: =BX46*(1-BX65) -> 74767.669 | BY47: =BY46*(1-BY65) -> 77875.276 | BZ47: =BZ46*(1-BZ65) -> 80407.113 | ... CB47: =CB46*(1-CB65) -> 84450.529
B48: GP | C48: =C46-C47 -> 5244 | D48: =D46-D47 -> 5677 | E48: =E46-E47 -> 6102 | F48: =F46-F47 -> 5370 | G48: =G46-G47 -> 5735 | H48: =H46-H47 -> 5771 | I48: =I46-I47 -> 6438 | J48: =J46-J47 -> 6157 | ... AY48: =AY46-AY47 -> 9312 | BG48: =SUM(C48:F48) -> 22393 | BH48: =SUM(G48:J48) -> 24101 | BI48: =SUM(K48:N48) -> 25639 | BJ48: =SUM(O48:R48) -> 24831 | BK48: =SUM(S48:V48) -> 26708 | BL48: =SUM(W48:Z48) -> 27546 | BM48: =SUM(AA48:AD48) -> 21508 | BN48: =SUM(AE48:AH48) -> 22287 | BO48: =SUM(AI48:AL48) -> 28321 | BP48: =SUM(AM48:AP48) -> 29697 | BQ48: =SUM(AQ48:AT48) -> 32663 | BR48: =SUM(AU48:AX48) -> 35659 | BS48: =BS46-BS47 -> 37411.063 | BT48: =BT46-BT47 -> 39421.764 | BU48: =BU46-BU47 -> 40860.364 | BV48: =BV46-BV47 -> 42364.348 | BW48: =BW46-BW47 -> 43624.144 | BX48: =BX46-BX47 -> 45368.756 | BY48: =BY46-BY47 -> 47254.441 | BZ48: =BZ46-BZ47 -> 48790.751 | ... CB48: =CB46-CB47 -> 51244.281
B49: SG&A | C49: 2018 | D49: 2116 | E49: 2047 | F49: 2384 | G49: 1935 | H49: 2081 | I49: 2101 | J49: 2406 | K49: 2025 | L49: 2137 | M49: 2305 | N49: 2287 | O49: 1985 | P49: 1941 | Q49: 2022 | R49: 2228 | S49: 2087 | T49: 2239 | U49: 2213 | V49: 2321 | W49: 2152 | X49: 2330 | Y49: 3368 | Z49: 3699 | AA49: 3709 | AB49: 3393 | AC49: 2455 | AD49: 2812 | AE49: 2917 | AF49: 3113 | AG49: 3168 | AH49: 4319 | AI49: 3787 | AJ49: 3768 | AK49: 4100 | AL49: 4733 | AM49: 3827 | AN49: 3614 | AO49: 3874 | AP49: 4021 | AQ49: 3783 | AR49: 3790 | AS49: 3872 | AT49: 4314 | AU49: 3930 | AV49: 3981 | AW49: 4141 | AX49: 4449 | AY49: 4121 | BG49: =SUM(C49:F49) -> 8565 | BH49: =SUM(G49:J49) -> 8523 | BI49: =SUM(K49:N49) -> 8754 | BJ49: =SUM(O49:R49) -> 8176 | BK49: =SUM(S49:V49) -> 8860 | BL49: =SUM(W49:Z49) -> 11549 | BM49: =SUM(AA49:AD49) -> 12369 | BN49: =SUM(AE49:AH49) -> 13517 | BO49: =SUM(AI49:AL49) -> 16388 | BP49: =SUM(AM49:AP49) -> 15336 | BQ49: =SUM(AQ49:AT49) -> 15759 | BR49: =SUM(AU49:AX49) -> 16501 | BS49: =BS46*BS66 -> 17336.281 | BT49: =BT46*BT66 -> 16702.207 | BU49: =BU46*BU66 -> 17041.218 | BV49: =BV46*BV66 -> 17388.017 | BW49: =BW46*BW66 -> 17789.571 | BX49: =BX46*BX66 -> 18380.873 | BY49: =BY46*BY66 -> 19019.717 | BZ49: =BZ46*BZ66 -> 19508.877 | ... CB49: =CB46*CB66 -> 20354.222
B50: Depreciation & Amortization | C50: 580 | D50: 628 | E50: 557 | F50: 663 | G50: 592 | H50: 584 | I50: 575 | J50: 656 | K50: 688 | L50: 605 | M50: 670 | N50: 720 | O50: 687 | P50: 676 | Q50: 711 | R50: 806 | S50: 757 | T50: 744 | U50: 744 | V50: 799 | W50: 732 | X50: 1490 | Y50: 1513 | Z50: 1615 | AA50: 1449 | AB50: 1479 | AC50: 6424 | AD50: 1728 | AE50: 1411 | AF50: 1686 | AG50: 1301 | AH50: 713 | AI50: 1269 | AJ50: 1482 | AK50: 1332 | AL50: 1080 | AM50: 1306 | AN50: 1310 | AO50: 1344 | AP50: 1409 | AQ50: 1243 | AR50: 1242 | AS50: 1220 | AT50: 1285 | AU50: 1276 | AV50: 1324 | AW50: 1332 | AX50: 1394 | AY50: 1316 | BG50: =SUM(C50:F50) -> 2428 | BH50: =SUM(G50:J50) -> 2407 | BI50: =SUM(K50:N50) -> 2683 | BJ50: =SUM(O50:R50) -> 2880 | BK50: =SUM(S50:V50) -> 3044 | BL50: =SUM(W50:Z50) -> 5350 | BM50: =SUM(AA50:AD50) -> 11080 | BN50: =SUM(AE50:AH50) -> 5111 | BO50: =SUM(AI50:AL50) -> 5163 | BP50: =SUM(AM50:AP50) -> 5369 | BQ50: =SUM(AQ50:AT50) -> 4990 | BR50: =SUM(AU50:AX50) -> 5326 | BS50: =BS46*BS67 -> 5587.6867 | BT50: =BT46*BT67 -> 6054.5501 | BU50: =BU46*BU67 -> 6275.4961 | BV50: =BV46*BV67 -> 6394.3031 | BW50: =BW46*BW67 -> 6584.4515 | BX50: =BX46*BX67 -> 6776.2414 | BY50: =BY46*BY67 -> 7057.8859 | BZ50: =BZ46*BZ67 -> 7287.3479 | ... CB50: =CB46*CB67 -> 7653.8052
B51: Operating Income | C51: =C48-SUM(C49:C50) -> 2646 | D51: =D48-SUM(D49:D50) -> 2933 | E51: =E48-SUM(E49:E50) -> 3498 | F51: =F48-SUM(F49:F50) -> 2323 | G51: =G48-SUM(G49:G50) -> 3208 | H51: =H48-SUM(H49:H50) -> 3106 | I51: =I48-SUM(I49:I50) -> 3762 | J51: =J48-SUM(J49:J50) -> 3095 | ... AY51: =AY48-SUM(AY49:AY50) -> 3875 | BG51: =SUM(C51:F51) -> 11400 | BH51: =SUM(G51:J51) -> 13171 | BI51: =SUM(K51:N51) -> 14202 | BJ51: =SUM(O51:R51) -> 13775 | BK51: =SUM(S51:V51) -> 14804 | BL51: =SUM(W51:Z51) -> 10647 | BM51: =SUM(AA51:AD51) -> -1941 | BN51: =SUM(AE51:AH51) -> 3659 | BO51: =SUM(AI51:AL51) -> 6770 | BP51: =SUM(AM51:AP51) -> 8992 | BQ51: =SUM(AQ51:AT51) -> 11914 | BR51: =SUM(AU51:AX51) -> 13832 | BS51: =BS48-SUM(BS49:BS50) -> 14487.095 | BT51: =BT48-SUM(BT49:BT50) -> 16665.006 | BU51: =BU48-SUM(BU49:BU50) -> 17543.65 | BV51: =BV48-SUM(BV49:BV50) -> 18582.028 | BW51: =BW48-SUM(BW49:BW50) -> 19250.121 | BX51: =BX48-SUM(BX49:BX50) -> 20211.641 | BY51: =BY48-SUM(BY49:BY50) -> 21176.838 | BZ51: =BZ48-SUM(BZ49:BZ50) -> 21994.525 | ... CB51: =CB48-SUM(CB49:CB50) -> 23236.254
B52: Restructuring & Impairment | C52: 0 | D52: 0 | E52: 0 | F52: 0 | G52: 0 | H52: 0 | I52: 0 | J52: 0 | K52: 0 | L52: 0 | M52: 0 | N52: 0 | O52: 0 | P52: 0 | Q52: 0 | R52: 0 | S52: 0 | T52: 0 | U52: 0 | V52: 0 | W52: 0 | X52: 0 | Y52: 0 | Z52: 0 | AA52: 0 | AB52: 0 | AC52: 0 | AD52: 0 | AE52: 0 | AF52: 0 | AG52: 0 | AH52: 0 | AI52: 0 | AJ52: 0 | AK52: 0 | AL52: 0 | AM52: 0 | AN52: 0 | AO52: 0 | AP52: 0 | AQ52: 0 | AR52: 0 | AS52: 0 | AT52: 0 | AU52: 0 | AV52: 0 | AW52: 0 | AX52: 0 | AY52: 0 | BG52: =SUM(C52:F52) -> 0 | BH52: =SUM(G52:J52) -> 0 | BI52: =SUM(K52:N52) -> 0 | BJ52: =SUM(O52:R52) -> 0 | BK52: =SUM(S52:V52) -> 0 | BL52: =SUM(W52:Z52) -> 0 | BM52: =SUM(AA52:AD52) -> 0 | BN52: =SUM(AE52:AH52) -> 0 | BO52: =SUM(AI52:AL52) -> 0 | BP52: =SUM(AM52:AP52) -> 0 | BQ52: =SUM(AQ52:AT52) -> 0 | BR52: =SUM(AU52:AX52) -> 0 | BS52: 0 | BT52: 0 | BU52: 0 | BV52: 0 | BW52: 0 | BX52: 0 | BY52: 0 | BZ52: 0 | CA52: 0 | CB52: 0
B53: Interest Expenses | C53: 0 | D53: 0 | E53: 0 | F53: 0 | G53: 0 | H53: 0 | I53: 0 | J53: 0 | K53: 0 | L53: 0 | M53: 0 | N53: 0 | O53: 0 | P53: 0 | Q53: 0 | R53: 0 | S53: 0 | T53: 0 | U53: 0 | V53: 0 | W53: 0 | X53: 0 | Y53: 0 | Z53: 0 | AA53: 0 | AB53: 0 | AC53: 0 | AD53: 0 | AE53: 0 | AF53: 0 | AG53: 0 | AH53: 0 | AI53: 0 | AJ53: 0 | AK53: 0 | AL53: 0 | AM53: 0 | AN53: 0 | AO53: 0 | AP53: 0 | AQ53: 0 | AR53: 0 | AS53: 0 | AT53: 0 | AU53: 0 | AV53: 0 | AW53: 0 | AX53: 0 | AY53: 0 | BG53: =SUM(C53:F53) -> 0 | BH53: =SUM(G53:J53) -> 0 | BI53: =SUM(K53:N53) -> 0 | BJ53: =SUM(O53:R53) -> 0 | BK53: =SUM(S53:V53) -> 0 | BL53: =SUM(W53:Z53) -> 0 | BM53: =SUM(AA53:AD53) -> 0 | BN53: =SUM(AE53:AH53) -> 0 | BO53: =SUM(AI53:AL53) -> 0 | BP53: =SUM(AM53:AP53) -> 0 | BQ53: =SUM(AQ53:AT53) -> 0 | BR53: =SUM(AU53:AX53) -> 0 | BS53: 0 | BT53: 0 | BU53: 0 | BV53: 0 | BW53: 0 | BX53: 0 | BY53: 0 | BZ53: 0 | CA53: 0 | CB53: 0
B54: Interest Income | C54: 294 | D54: 242 | E54: 172 | F54: 138 | G54: 154 | H54: 214 | I54: 200 | J54: 129 | K54: 450 | L54: 83 | M54: 82 | N54: 51 | O54: 19 | P54: 1 | Q54: -170 | R54: 163 | S54: -33 | T54: -96 | U54: -70 | V54: 124 | W54: 13 | X54: 4511 | Y54: -535 | Z54: -713 | AA54: -59 | AB54: -165 | AC54: 156 | AD54: 266 | AE54: -100 | AF54: 198 | AG54: -325 | AH54: -871 | AI54: -508 | AJ54: -303 | AK54: -271 | AL54: -403 | AM54: -220 | AN54: -152 | AO54: -2775 | AP54: -1076 | AQ54: -65 | AR54: -2222 | AS54: -261 | AT54: -1797 | AU54: -418 | AV54: -419 | AW54: -434 | AX54: -558 | AY54: -182 | BG54: =SUM(C54:F54) -> 846 | BH54: =SUM(G54:J54) -> 697 | BI54: =SUM(K54:N54) -> 666 | BJ54: =SUM(O54:R54) -> 13 | BK54: =SUM(S54:V54) -> -75 | BL54: =SUM(W54:Z54) -> 3276 | BM54: =SUM(AA54:AD54) -> 198 | BN54: =SUM(AE54:AH54) -> -1098 | BO54: =SUM(AI54:AL54) -> -1485 | BP54: =SUM(AM54:AP54) -> -4223 | BQ54: =SUM(AQ54:AT54) -> -4345 | BR54: =SUM(AU54:AX54) -> -1829 | BS54: =(-BR90*0.065)+(BR72*($CL$72)) -> -1768.6875 | BT54: =(-BS90*0.065)+(BS72*($CL$72)) -> -736.28062 | BU54: =(-BT90*0.065)+(BT72*($CL$72)) -> 507.27793 | BV54: =(-BU90*0.065)+(BU72*($CL$72)) -> 1896.5386 | BW54: =(-BV90*0.065)+(BV72*($CL$72)) -> 3453.5287 | BX54: =(-BW90*0.065)+(BW72*($CL$72)) -> 5164.0801 | BY54: =(-BX90*0.065)+(BX72*($CL$72)) -> 7060.2756 | BZ54: =(-BY90*0.065)+(BY72*($CL$72)) -> 9155.8333 | ... CB54: =(-CA90*0.065)+(CA72*($CL$72)) -> 13965.619
B55: Pretax Income | C55: =C51+SUM(C53:C54) -> 2940 | D55: =D51+SUM(D53:D54) -> 3175 | E55: =E51+SUM(E53:E54) -> 3670 | F55: =F51+SUM(F53:F54) -> 2461 | G55: =G51+SUM(G53:G54) -> 3362 | H55: =H51+SUM(H53:H54) -> 3320 | I55: =I51+SUM(I53:I54) -> 3962 | J55: =J51+SUM(J53:J54) -> 3224 | ... AY55: =AY51+SUM(AY53:AY54) -> 3693 | BG55: =SUM(C55:F55) -> 12246 | BH55: =SUM(G55:J55) -> 13868 | BI55: =SUM(K55:N55) -> 14868 | BJ55: =SUM(O55:R55) -> 13788 | BK55: =SUM(S55:V55) -> 14729 | BL55: =SUM(W55:Z55) -> 13923 | BM55: =SUM(AA55:AD55) -> -1743 | BN55: =SUM(AE55:AH55) -> 2561 | BO55: =SUM(AI55:AL55) -> 5285 | BP55: =SUM(AM55:AP55) -> 4769 | BQ55: =SUM(AQ55:AT55) -> 7569 | BR55: =SUM(AU55:AX55) -> 12003 | BS55: =BS51+SUM(BS52:BS54) -> 12718.408 | BT55: =BT51+SUM(BT52:BT54) -> 15928.726 | BU55: =BU51+SUM(BU52:BU54) -> 18050.928 | BV55: =BV51+SUM(BV52:BV54) -> 20478.567 | BW55: =BW51+SUM(BW52:BW54) -> 22703.65 | BX55: =BX51+SUM(BX52:BX54) -> 25375.722 | BY55: =BY51+SUM(BY52:BY54) -> 28237.114 | BZ55: =BZ51+SUM(BZ52:BZ54) -> 31150.359 | ... CB55: =CB51+SUM(CB52:CB54) -> 37201.874
B56: Taxes | C56: 1036 | D56: 1119 | E56: 1251 | F56: 836 | G56: 1118 | H56: 1092 | I56: 1323 | J56: 1483 | K56: 1448 | L56: 1170 | M56: 1471 | N56: 989 | O56: 1237 | P56: 1212 | Q56: 1144 | R56: 829 | S56: -728 | T56: 813 | U56: 795 | V56: 783 | W56: 645 | X56: 1647 | Y56: 393 | Z56: 341 | AA56: 458 | AB56: 523 | AC56: -331 | AD56: 49 | AE56: 16 | AF56: 108 | AG56: -133 | AH56: 34 | AI56: 488 | AJ56: 505 | AK56: 617 | AL56: 122 | AM56: 412 | AN56: 635 | AO56: 19 | AP56: 313 | AQ56: 720 | AR56: 441 | AS56: 251 | AT56: 384 | AU56: 1016 | AV56: -314 | AW56: -2732 | AX56: 602 | AY56: 1209 | BG56: =SUM(C56:F56) -> 4242 | BH56: =SUM(G56:J56) -> 5016 | BI56: =SUM(K56:N56) -> 5078 | BJ56: =SUM(O56:R56) -> 4422 | BK56: =SUM(S56:V56) -> 1663 | BL56: =SUM(W56:Z56) -> 3026 | BM56: =SUM(AA56:AD56) -> 699 | BN56: =SUM(AE56:AH56) -> 25 | BO56: =SUM(AI56:AL56) -> 1732 | BP56: =SUM(AM56:AP56) -> 1379 | BQ56: =SUM(AQ56:AT56) -> 1796 | BR56: =SUM(AU56:AX56) -> -1428 | BS56: =BS55*BS69 -> 2798.0497 | BT56: =BT55*BT69 -> 3663.6069 | BU56: =BU55*BU69 -> 4151.7135 | BV56: =BV55*BV69 -> 4710.0703 | BW56: =BW55*BW69 -> 5221.8395 | BX56: =BX55*BX69 -> 5836.4159 | BY56: =BY55*BY69 -> 6494.5361 | BZ56: =BZ55*BZ69 -> 7164.5825 | ... CB56: =CB55*CB69 -> 8556.4309
B57: NI from Continued Operations | C57: =C55-C56 -> 1904 | D57: =D55-D56 -> 2056 | E57: =E55-E56 -> 2419 | F57: =F55-F56 -> 1625 | G57: =G55-G56 -> 2244 | H57: =H55-H56 -> 2228 | I57: =I55-I56 -> 2639 | J57: =J55-J56 -> 1741 | ... AY57: =AY55-AY56 -> 2484 | BG57: =SUM(C57:F57) -> 8004 | BH57: =SUM(G57:J57) -> 8852 | BI57: =SUM(K57:N57) -> 9790 | BJ57: =SUM(O57:R57) -> 9366 | BK57: =SUM(S57:V57) -> 13066 | BL57: =SUM(W57:Z57) -> 10897 | BM57: =SUM(AA57:AD57) -> -2442 | BN57: =SUM(AE57:AH57) -> 2536 | BO57: =SUM(AI57:AL57) -> 3553 | BP57: =SUM(AM57:AP57) -> 3390 | BQ57: =SUM(AQ57:AT57) -> 5773 | BR57: =SUM(AU57:AX57) -> 13431 | BS57: =BS55-BS56 -> 9920.3581 | BT57: =BT55-BT56 -> 12265.119 | BU57: =BU55-BU56 -> 13899.215 | BV57: =BV55-BV56 -> 15768.496 | BW57: =BW55-BW56 -> 17481.811 | BX57: =BX55-BX56 -> 19539.306 | BY57: =BY55-BY56 -> 21742.577 | BZ57: =BZ55-BZ56 -> 23985.776 | ... CB57: =CB55-CB56 -> 28645.443 | CC57: =CB57*(1+$CL$73) -> 28717.056 | CD57: =CC57*(1+$CL$73) -> 28788.849 | CE57: =CD57*(1+$CL$73) -> 28860.821 | CF57: =CE57*(1+$CL$73) -> 28932.973 | CG57: =CF57*(1+$CL$73) -> 29005.306 | CH57: =CG57*(1+$CL$73) -> 29077.819 | CI57: =CH57*(1+$CL$73) -> 29150.513 | CJ57: =CI57*(1+$CL$73) -> 29223.39 | ... DZ57: =DY57*(1+$CL$73) -> 32454.476
B58: Loss from Discontinued Operations | C58: 0 | D58: 0 | E58: 0 | F58: 0 | G58: 0 | H58: 0 | I58: 0 | J58: 0 | K58: 0 | L58: 0 | M58: 0 | N58: 0 | O58: 0 | P58: 0 | Q58: 0 | R58: 0 | S58: 0 | T58: 0 | U58: 0 | V58: 0 | W58: 0 | X58: 0 | Y58: 0 | Z58: 0 | AA58: 0 | AB58: 0 | AC58: 0 | AD58: 0 | AE58: 0 | AF58: 0 | AG58: 0 | AH58: 0 | AI58: 0 | AJ58: 0 | AK58: 0 | AL58: 0 | AM58: 0 | AN58: 0 | AO58: 0 | AP58: 0 | AQ58: 0 | AR58: 0 | AS58: 0 | AT58: 0 | AU58: 0 | AV58: 0 | AW58: 0 | AX58: 0 | AY58: 0 | BG58: =SUM(C58:F58) -> 0 | BH58: =SUM(G58:J58) -> 0 | BI58: =SUM(K58:N58) -> 0 | BJ58: =SUM(O58:R58) -> 0 | BK58: =SUM(S58:V58) -> 0 | BL58: =SUM(W58:Z58) -> 0 | BM58: =SUM(AA58:AD58) -> 0 | BN58: =SUM(AE58:AH58) -> 0 | BO58: =SUM(AI58:AL58) -> 0 | BP58: =SUM(AM58:AP58) -> 0 | BQ58: =SUM(AQ58:AT58) -> 0 | BR58: =SUM(AU58:AX58) -> 0 | BS58: 0 | BT58: 0 | BU58: 0 | BV58: 0 | BW58: 0 | BX58: 0 | BY58: 0 | BZ58: 0 | CA58: 0 | CB58: 0
B59: NI | C59: =C57+C58 -> 1904 | D59: =D57+D58 -> 2056 | E59: =E57+E58 -> 2419 | F59: =F57+F58 -> 1625 | G59: =G57+G58 -> 2244 | H59: =H57+H58 -> 2228 | I59: =I57+I58 -> 2639 | J59: =J57+J58 -> 1741 | ... AY59: =AY57+AY58 -> 2484 | BG59: =SUM(C59:F59) -> 8004 | BH59: =SUM(G59:J59) -> 8852 | BI59: =SUM(K59:N59) -> 9790 | BJ59: =SUM(O59:R59) -> 9366 | BK59: =SUM(S59:V59) -> 13066 | BL59: =SUM(W59:Z59) -> 10897 | BM59: =SUM(AA59:AD59) -> -2442 | BN59: =SUM(AE59:AH59) -> 2536 | BO59: =SUM(AI59:AL59) -> 3553 | BP59: =SUM(AM59:AP59) -> 3390 | BQ59: =SUM(AQ59:AT59) -> 5773 | BR59: =SUM(AU59:AX59) -> 13431 | BS59: =BS57+BS58 -> 9920.3581 | BT59: =BT57+BT58 -> 12265.119 | BU59: =BU57+BU58 -> 13899.215 | BV59: =BV57+BV58 -> 15768.496 | BW59: =BW57+BW58 -> 17481.811 | BX59: =BX57+BX58 -> 19539.306 | BY59: =BY57+BY58 -> 21742.577 | BZ59: =BZ57+BZ58 -> 23985.776 | ... CB59: =CB57+CB58 -> 28645.443
B60: Noncontrolling Interests | C60: 0 | D60: 0 | E60: 0 | F60: 0 | G60: 0 | H60: 0 | I60: 0 | J60: 0 | K60: 0 | L60: 0 | M60: 0 | N60: 0 | O60: 0 | P60: 0 | Q60: 0 | R60: 0 | S60: 0 | T60: 0 | U60: 0 | V60: 0 | W60: 0 | X60: 0 | Y60: 0 | Z60: 0 | AA60: 0 | AB60: 0 | AC60: 0 | AD60: 0 | AE60: 0 | AF60: 0 | AG60: 0 | AH60: 0 | AI60: 0 | AJ60: 0 | AK60: 0 | AL60: 0 | AM60: 0 | AN60: 0 | AO60: 0 | AP60: 0 | AQ60: 0 | AR60: 0 | AS60: 0 | AT60: 0 | AU60: 0 | AV60: 0 | AW60: 0 | AX60: 0 | AY60: 0 | BG60: =SUM(C60:F60) -> 0 | BH60: =SUM(G60:J60) -> 0 | BI60: =SUM(K60:N60) -> 0 | BJ60: =SUM(O60:R60) -> 0 | BK60: =SUM(S60:V60) -> 0 | BL60: =SUM(W60:Z60) -> 0 | BM60: =SUM(AA60:AD60) -> 0 | BN60: =SUM(AE60:AH60) -> 0 | BO60: =SUM(AI60:AL60) -> 0 | BP60: =SUM(AM60:AP60) -> 0 | BQ60: =SUM(AQ60:AT60) -> 0 | BR60: =SUM(AU60:AX60) -> 0 | BS60: 0 | BT60: 0 | BU60: 0 | BV60: 0 | BW60: 0 | BX60: 0 | BY60: 0 | BZ60: 0 | CA60: 0 | CB60: 0
B61: NI to The Company | C61: =C59+C60 -> 1904 | D61: =D59+D60 -> 2056 | E61: =E59+E60 -> 2419 | F61: =F59+F60 -> 1625 | G61: =G59+G60 -> 2244 | H61: =H59+H60 -> 2228 | I61: =I59+I60 -> 2639 | J61: =J59+J60 -> 1741 | ... AY61: =AY59+AY60 -> 2484 | BG61: =SUM(C61:F61) -> 8004 | BH61: =SUM(G61:J61) -> 8852 | BI61: =SUM(K61:N61) -> 9790 | BJ61: =SUM(O61:R61) -> 9366 | BK61: =SUM(S61:V61) -> 13066 | BL61: =SUM(W61:Z61) -> 10897 | BM61: =SUM(AA61:AD61) -> -2442 | BN61: =SUM(AE61:AH61) -> 2536 | BO61: =SUM(AI61:AL61) -> 3553 | BP61: =SUM(AM61:AP61) -> 3390 | BQ61: =SUM(AQ61:AT61) -> 5773 | BR61: =SUM(AU61:AX61) -> 13431 | BS61: =BS59+BS60 -> 9920.3581 | BT61: =BT59+BT60 -> 12265.119 | BU61: =BU59+BU60 -> 13899.215 | BV61: =BV59+BV60 -> 15768.496 | BW61: =BW59+BW60 -> 17481.811 | BX61: =BX59+BX60 -> 19539.306 | BY61: =BY59+BY60 -> 21742.577 | BZ61: =BZ59+BZ60 -> 23985.776 | ... CB61: =CB59+CB60 -> 28645.443
B62: SC | C62: 1700 | D62: 1700 | E62: 1700 | F62: 1700 | G62: 1700 | H62: 1700 | I62: 1600 | J62: 1600 | K62: 1700 | L62: 1700 | M62: 1700 | N62: 1600 | O62: 1600 | P62: 1600 | Q62: 1600 | R62: 1500 | S62: 1500 | T62: 1500 | U62: 1500 | V62: 1500 | W62: 1500 | X62: 1781 | Y62: 1781 | Z62: 1781 | AA62: 1781 | AB62: 1781 | AC62: 1781 | AD62: 1781 | AE62: 1781 | AF62: 1781 | AG62: 1781 | AH62: 1781 | AI62: 1781 | AJ62: 1781 | AK62: 1781 | AL62: 1781 | AM62: 1781 | AN62: 1781 | AO62: 1781 | AP62: 1781 | AQ62: 1881 | AR62: 1873 | AS62: 1858 | AT62: 1853 | AU62: 1846 | AV62: 1837 | AW62: 1829 | AX62: 1821 | AY62: 1771 | BG62: =AVERAGE(C62:F62) -> 1700 | BH62: =AVERAGE(G62:J62) -> 1650 | BI62: =AVERAGE(K62:N62) -> 1675 | BJ62: =AVERAGE(O62:R62) -> 1575 | BK62: =AVERAGE(S62:V62) -> 1500 | BL62: =AVERAGE(W62:Z62) -> 1710.75 | BM62: =AVERAGE(AA62:AD62) -> 1781 | BN62: =AVERAGE(AE62:AH62) -> 1781 | BO62: =AVERAGE(AI62:AL62) -> 1781 | BP62: =AVERAGE(AM62:AP62) -> 1781 | BQ62: =AVERAGE(AQ62:AT62) -> 1866.25 | BR62: =AVERAGE(AU62:AX62) -> 1833.25 | BS62: 1780 | BT62: 1780 | BU62: 1780 | BV62: 1780 | BW62: 1780 | BX62: 1780 | BY62: 1780 | BZ62: 1780 | CA62: 1780 | CB62: 1780
B63: EPS | C63: =C57/C62 -> 1.12 | D63: =D57/D62 -> 1.2094118 | E63: =E57/E62 -> 1.4229412 | F63: =F57/F62 -> 0.95588235 | G63: =G57/G62 -> 1.32 | H63: =H57/H62 -> 1.3105882 | I63: =I57/I62 -> 1.649375 | J63: =J57/J62 -> 1.088125 | ... AY63: =AY57/AY62 -> 1.4025974 | BG63: =SUM(C63:F63) -> 4.7082353 | BH63: =SUM(G63:J63) -> 5.3680882 | BI63: =SUM(K63:N63) -> 5.8283824 | BJ63: =SUM(O63:R63) -> 5.9314583 | BK63: =SUM(S63:V63) -> 8.7106667 | BL63: =SUM(W63:Z63) -> 6.4115164 | BM63: =SUM(AA63:AD63) -> -1.3711398 | BN63: =SUM(AE63:AH63) -> 1.4239191 | BO63: =SUM(AI63:AL63) -> 1.9949467 | BP63: =SUM(AM63:AP63) -> 1.903425 | BQ63: =SUM(AQ63:AT63) -> 3.0928367 | BR63: =SUM(AU63:AX63) -> 7.3254125 | BS63: =BS61/BS62 -> 5.5732349 | BT63: =BT61/BT62 -> 6.8905162 | BU63: =BU61/BU62 -> 7.8085477 | BV63: =BV61/BV62 -> 8.8587057 | BW63: =BW61/BW62 -> 9.8212419 | BX63: =BX61/BX62 -> 10.977138 | BY63: =BY61/BY62 -> 12.214931 | BZ63: =BZ61/BZ62 -> 13.475155 | ... CB63: =CB61/CB62 -> 16.092945
B65: Gross Profit Margin | C65: =C48/C46 -> 0.42602973 | D65: =D48/D46 -> 0.48733797 | E65: =E48/E46 -> 0.48949142 | F65: =F48/F46 -> 0.43344903 | G65: =G48/G46 -> 0.42827272 | H65: =H48/H46 -> 0.46312495 | I65: =I48/I46 -> 0.49141287 | J65: =J48/J46 -> 0.45566903 | ... AY65: =AY48/AY46 -> 0.35841577 | BG65: =BG48/BG46 -> 0.45875074 | BH65: =BH48/BH46 -> 0.45937292 | BI65: =BI48/BI46 -> 0.46086785 | BJ65: =BJ48/BJ46 -> 0.45035094 | BK65: =BK48/BK46 -> 0.44937241 | BL65: =BL48/BL46 -> 0.39573606 | BM65: =BM48/BM46 -> 0.32892886 | BN65: =BN48/BN46 -> 0.33057937 | ... BR65: =BR48/BR46 -> 0.37764363 | BS65: 0.37764363 | BT65: 0.37764363 | BU65: 0.37764363 | BV65: 0.37764363 | BW65: 0.37764363 | BX65: 0.37764363 | BY65: 0.37764363 | BZ65: 0.37764363 | CA65: 0.37764363 | CB65: 0.37764363
B66: SG&A as % of Revenue | C66: =C49/C46 -> 0.16394508 | D66: =D49/D46 -> 0.18164649 | E66: =E49/E46 -> 0.16420664 | F66: =F49/F46 -> 0.19242877 | G66: =G49/G46 -> 0.14450004 | H66: =H49/H46 -> 0.16700104 | I66: =I49/I46 -> 0.16036944 | J66: =J49/J46 -> 0.17806394 | ... AY66: =AY49/AY46 -> 0.15861591 | BG66: =BG49/BG46 -> 0.17546555 | BH66: =BH49/BH46 -> 0.16245116 | BI66: =BI49/BI46 -> 0.15735548 | BJ66: =BJ49/BJ46 -> 0.14828518 | BK66: =BK49/BK46 -> 0.14907292 | BL66: =BL49/BL46 -> 0.16591722 | BM66: =BM49/BM46 -> 0.18916315 | BN66: =BN49/BN46 -> 0.20049542 | ... BR66: =BR49/BR46 -> 0.17475245 | BS66: 0.175 | BT66: 0.16 | BU66: 0.1575 | BV66: 0.155 | BW66: 0.154 | BX66: 0.153 | BY66: 0.152 | BZ66: 0.151 | CA66: 0.15 | CB66: 0.15
B67: Dep. & Am. as % of Revenue | C67: =C50/C46 -> 0.047119994 | D67: =D50/D46 -> 0.053910207 | E67: =E50/E46 -> 0.044681534 | F67: =F50/F46 -> 0.053515215 | G67: =G50/G46 -> 0.044208797 | H67: =H50/H46 -> 0.046866223 | I67: =I50/I46 -> 0.043889779 | J67: =J50/J46 -> 0.048549438 | ... AY67: =AY50/AY46 -> 0.0506524 | BG67: =BG50/BG46 -> 0.049740848 | BH67: =BH50/BH46 -> 0.045878205 | BI67: =BI50/BI46 -> 0.048227639 | BJ67: =BJ50/BJ46 -> 0.052233527 | BK67: =BK50/BK46 -> 0.051216475 | BL67: =BL50/BL46 -> 0.076860086 | BM67: =BM50/BM46 -> 0.16945005 | BN67: =BN50/BN46 -> 0.075810614 | ... BR67: =BR50/BR46 -> 0.056404554 | BS67: 0.056404554 | BT67: 0.058 | BU67: 0.058 | BV67: 0.057 | BW67: 0.057 | BX67: 0.056404554 | BY67: 0.056404554 | BZ67: 0.056404554 | CA67: 0.056404554 | CB67: 0.056404554
B68: Operating Profit Margin | C68: =C51/C46 -> 0.21496466 | D68: =D51/D46 -> 0.25178127 | E68: =E51/E46 -> 0.28060324 | F68: =F51/F46 -> 0.18750504 | G68: =G51/G46 -> 0.23956389 | H68: =H51/H46 -> 0.24925768 | I68: =I51/I46 -> 0.28715365 | J68: =J51/J46 -> 0.22905565 | ... AY68: =AY51/AY46 -> 0.14914745 | BG68: =BG51/BG46 -> 0.23354434 | BH68: =BH51/BH46 -> 0.25104355 | BI68: =BI51/BI46 -> 0.25528473 | BJ68: =BJ51/BJ46 -> 0.24983224 | BK68: =BK51/BK46 -> 0.24908302 | BL68: =BL51/BL46 -> 0.15295875 | BM68: =BM51/BM46 -> -0.029684346 | BN68: =BN51/BN46 -> 0.054273339 | ... CB68: =CB51/CB46 -> 0.17123908
B69: Effective Tax Rate | C69: =C56/C55 -> 0.35238095 | D69: =D56/D55 -> 0.35244094 | E69: =E56/E55 -> 0.34087193 | F69: =F56/F55 -> 0.33969931 | G69: =G56/G55 -> 0.33254015 | H69: =H56/H55 -> 0.32891566 | I69: =I56/I55 -> 0.33392226 | J69: =J56/J55 -> 0.45998759 | ... AY69: =AY56/AY55 -> 0.32737612 | BG69: =BG56/BG55 -> 0.34639882 | BH69: =BH56/BH55 -> 0.36169599 | BI69: =BI56/BI55 -> 0.34153888 | BJ69: =BJ56/BJ55 -> 0.32071366 | BK69: =BK56/BK55 -> 0.11290651 | BL69: =BL56/BL55 -> 0.21733822 | BM69: =BM56/BM55 -> -0.4010327 | BN69: =BN56/BN55 -> 0.0097618118 | ... BR69: =BR56/BR55 -> -0.11897026 | BS69: 0.22 | BT69: 0.23 | BU69: 0.23 | BV69: 0.23 | BW69: 0.23 | BX69: 0.23 | BY69: 0.23 | BZ69: 0.23 | CA69: 0.23 | CB69: 0.23
B70: Net Profit Margin | C70: =C57/C46 -> 0.15468356 | D70: =D57/D46 -> 0.17649584 | E70: =E57/E46 -> 0.19404781 | F70: =F57/F46 -> 0.13116474 | G70: =G57/G46 -> 0.16757524 | H70: =H57/H46 -> 0.17879785 | I70: =I57/I46 -> 0.201435 | J70: =J57/J46 -> 0.12884843 | ... AY70: =AY57/AY46 -> 0.095608329 | BG70: =BG57/BG46 -> 0.16397271 | BH70: =BH57/BH46 -> 0.16872201 | BI70: =BI57/BI46 -> 0.17597785 | BJ70: =BJ57/BJ46 -> 0.16986778 | BK70: =BK57/BK46 -> 0.2198405 | BL70: =BL57/BL46 -> 0.15655035 | BM70: =BM57/BM46 -> -0.037346302 | BN70: =BN57/BN46 -> 0.037616067 | ... CB70: =CB57/CB46 -> 0.21110198
B72: Cash & CEs | AH72: 15959 | AI72: 14444 | AJ72: 13272 | AK72: 12959 | AL72: 11615 | AM72: 8470 | AN72: 10399 | AO72: 11458 | AP72: 14182 | AQ72: 7192 | AR72: 6635 | AS72: 5954 | AT72: 6002 | AU72: 5486 | AV72: 5852 | AW72: 5367 | AX72: 5695 | AY72: 5678 | BO72: =AL72 -> 11615 | BP72: =AP72 -> 14182 | BQ72: =AT72 -> 6002 | BR72: =AX72 -> 5695 | BS72: =BS61+BR72 -> 15615.358 | BT72: =BT61+BS72 -> 27880.477 | BU72: =BU61+BT72 -> 41779.692 | BV72: =BV61+BU72 -> 57548.188 | BW72: =BW61+BV72 -> 75029.999 | BX72: =BX61+BW72 -> 94569.304 | BY72: =BY61+BX72 -> 116311.88 | BZ72: =BZ61+BY72 -> 140297.66 | ... CB72: =CB61+CA72 -> 195265.35 | CD72: Invested Capital | CG72: Avg. (2024-2025) | CI72: Projected ROIC: | CK72: ROIC | CL72: 0.0925
B73: A/R | AH73: 13367 | AI73: 14882 | AJ73: 13746 | AK73: 13685 | AL73: 12652 | AM73: 13993 | AN73: 12770 | AO73: 13112 | AP73: 12330 | AQ73: 14115 | AR73: 12026 | AS73: 12966 | AT73: 12729 | AU73: 13767 | AV73: 12571 | AW73: 13402 | AX73: 13217 | AY73: 15054 | BO73: =AL73 -> 12652 | BP73: =AP73 -> 12330 | BQ73: =AT73 -> 12729 | BR73: =AX73 -> 13217 | CD73: 2024 | CE73: 2025 | CG73: 2024-2025 | CI73: 2025 | CK73: Terminal | CL73: 0.0025
B74: Inventories | AH74: 1331 | AI74: 1345 | AJ74: 1428 | AK74: 1590 | AL74: 1742 | AM74: 1830 | AN74: 1848 | AO74: 1900 | AP74: 1963 | AQ74: 1954 | AR74: 1948 | AS74: 1984 | AT74: 2022 | AU74: 2018 | AV74: 1999 | AW74: 2080 | AX74: 2134 | AY74: 2157 | BO74: =AL74 -> 1742 | BP74: =AP74 -> 1963 | BQ74: =AT74 -> 2022 | BR74: =AX74 -> 2134 | CD74: =SUM(BQ72:BQ75)-BQ87+BQ82+BQ79+BQ83 -> 117013 | CE74: =SUM(BR72:BR75)-BR87+BR82+BR79+BR83 -> 117624 | CG74: =AVERAGE(CD74:CE74) -> 117318.5 | CI74: =AVERAGE(BS55)*(1-BS70) -> 11444.781 | CK74: RFR (10-year yield) | CL74: =CG83 -> 0.0433
B75: Content Advances | AH75: 2183 | AI75: 1125 | AJ75: 1796 | AK75: 1902 | AL75: 1890 | AM75: 1300 | AN75: 1872 | AO75: 2369 | AP75: 3002 | AQ75: 1409 | AR75: 1921 | AS75: 1992 | AT75: 2097 | AU75: 1157 | AV75: 1063 | AW75: 1756 | AX75: 2063 | AY75: 1336 | BO75: =AL75 -> 1890 | BP75: =AP75 -> 3002 | BQ75: =AT75 -> 2097 | BR75: =AX75 -> 2063 | CI75: =CI74/CG74 -> 0.09755308 | CK75: ERP (Avg. market return - (less) RFR) | CL75: =8.75%-CL74 -> 0.0442
B76: Other ST Assets | AH76: 817 | AI76: 1117 | AJ76: 1185 | AK76: 1286 | AL76: 1199 | AM76: 1319 | AN76: 1374 | AO76: 1335 | AP76: 1286 | AQ76: 1301 | AR76: 2106 | AS76: 2597 | AT76: 2391 | AU76: 1239 | AV76: 1250 | AW76: 1215 | AX76: 1158 | AY76: 1241 | BO76: =AL76 -> 1199 | BP76: =AP76 -> 1286 | BQ76: =AT76 -> 2391 | BR76: =AX76 -> 1158 | CD76: Capital Structure | CK76: Equity β (1-year avg.) | CL76: ='Notes | Quant Analysis'!S209 -> 1.0270207
B77: LT Product & Licenses | AH77: 29549 | AI77: 30669 | AJ77: 32349 | AK77: 34077 | AL77: 35777 | AM77: 36266 | AN77: 36949 | AO77: 34607 | AP77: 33591 | AQ77: 32725 | AR77: 32590 | AS77: 32799 | AT77: 32312 | AU77: 32505 | AV77: 31820 | AW77: 31278 | AX77: 31327 | AY77: 31114 | BO77: =AL77 -> 35777 | BP77: =AP77 -> 33591 | BQ77: =AT77 -> 32312 | BR77: =AX77 -> 31327 | CD77: Mkt Cap | CG77: =Main!C5 -> 187781.01 | CK77: Discount (Cost of Equity) | CL77: =+CL74+(CL75*CL76) -> 0.088694316
B78: LT Investments | AH78: 3935 | AI78: 3549 | AJ78: 3356 | AK78: 3236 | AL78: 3218 | AM78: 3169 | AN78: 3387 | AO78: 3062 | AP78: 3080 | AQ78: 3084 | AR78: 3007 | AS78: 4632 | AT78: 4459 | AU78: 8902 | AV78: 8794 | AW78: 8671 | AX78: 8097 | AY78: 8052 | BO78: =AL78 -> 3218 | BP78: =AP78 -> 3080 | BQ78: =AT78 -> 4459 | BR78: =AX78 -> 8097 | CD78: Debt to Ttl Mkt Cap | CG78: =Main!C7/(Main!C7+CG77) -> 0.19895827
B79: Attractions, Buildings and Equipment, Net | AH79: 26972 | AI79: 26752 | AJ79: 26464 | AK79: 26510 | AL79: 27642 | AM79: 27612 | AN79: 28243 | AO79: 27707 | AP79: 27480 | AQ79: 28521 | AR79: 28108 | AS79: 28646 | AT79: 31168 | AU79: 32430 | AV79: 32189 | AW79: 32700 | AX79: 33152 | AY79: 34602 | BO79: =AL79 -> 27642 | BP79: =AP79 -> 27480 | BQ79: =AT79 -> 31168 | BR79: =AX79 -> 33152 | CD79: Mkt Equity to Ttl Mkt Cap | CG79: =CG77/(CG77+Main!C7) -> 0.80104173 | CK79: NPV | CL79: =NPV(CL77,BS57:DZ57) -> 253391.78
B80: Projects in Progress | AH80: 4521 | AI80: 4808 | AJ80: 5327 | AK80: 5956 | AL80: 4814 | AM80: 5430 | AN80: 5175 | AO80: 5689 | AP80: 6285 | AQ80: 5618 | AR80: 6243 | AS80: 6223 | AT80: 4728 | AU80: 4581 | AV80: 5740 | AW80: 6294 | AX80: 6911 | AY80: 7403 | BO80: =AL80 -> 4814 | BP80: =AP80 -> 6285 | BQ80: =AT80 -> 4728 | BR80: =AX80 -> 6911 | CD80: LT Debt / Equity | CG80: =BR90/BR95 -> 0.30812655 | CK80: SC | CL80: =Main!C4 -> 1771.519
B81: Land | AH81: 1131 | AI81: 1121 | AJ81: 1126 | AK81: 1117 | AL81: 1140 | AM81: 1158 | AN81: 1161 | AO81: 1181 | AP81: 1176 | AQ81: 1182 | AR81: 1174 | AS81: 1172 | AT81: 1145 | AU81: 1129 | AV81: 1166 | AW81: 1191 | AX81: 1192 | AY81: 1193 | BO81: =AL81 -> 1140 | BP81: =AP81 -> 1176 | BQ81: =AT81 -> 1145 | BR81: =AX81 -> 1192 | CK81: FV | CL81: =CL79/CL80 -> 143.03645
B82: LT Intangible Assets | AH82: 17115 | AI82: 16574 | AJ82: 15875 | AK82: 15334 | AL82: 14837 | AM82: 14347 | AN82: 13887 | AO82: 13478 | AP82: 13061 | AQ82: 12639 | AR82: 11474 | AS82: 11107 | AT82: 10739 | AU82: 10372 | AV82: 10006 | AW82: 9639 | AX82: 9272 | AY82: 9429 | BO82: =AL82 -> 14837 | BP82: =AP82 -> 13061 | BQ82: =AT82 -> 10739 | BR82: =AX82 -> 9272 | CD82: Cost of Equity | CK82: CP | CL82: =Main!C3 -> 106
B83: Goodwill | AH83: 78071 | AI83: 78052 | AJ83: 78019 | AK83: 77945 | AL83: 77897 | AM83: 77867 | AN83: 77878 | AO83: 77881 | AP83: 77067 | AQ83: 77066 | AR83: 73914 | AS83: 73914 | AT83: 73326 | AU83: 73312 | AV83: 73313 | AW83: 73314 | AX83: 73294 | AY83: 74743 | BO83: =AL83 -> 77897 | BP83: =AP83 -> 77067 | BQ83: =AT83 -> 73326 | BR83: =AX83 -> 73294 | CD83: RFR (10-year yield) | CG83: 0.0433 | CK83: Change Δ | CL83: =CL81/CL82-1 -> 0.34940044 | CM83: =IF(CL83>0,"Upside","Downside") -> Upside
B84: Other LT Assets | AH84: 8658 | AI84: 8873 | AJ84: 8510 | AK84: 8477 | AL84: 9208 | AM84: 9363 | AN84: 9915 | AO84: 10004 | AP84: 11076 | AQ84: 10968 | AR84: 13964 | AS84: 13786 | AT84: 13101 | AU84: 10148 | AV84: 10070 | AW84: 9705 | AX84: 10002 | AY84: 10087 | BO84: =AL84 -> 9208 | BP84: =AP84 -> 11076 | BQ84: =AT84 -> 13101 | BR84: =AX84 -> 10002 | CD84: Equity β (1-year avg.) | CG84: ='Notes | Quant Analysis'!S209 -> 1.0270207 | CK84: {=_xlfn.IFS(CL83>=25%,"Strong Buy",CL83>=10.00001%,"Buy",AND(CL83<=10%,CL83>=-4.9999%),"Hold",AND(CL83<=-5%,CL83>=-14.999999%),"Sell",CL83<=-15%,"Strong Sell")} -> Strong Buy
B85: Ttl Assets | AH85: =SUM(AH72:AH84) -> 203609 | AI85: =SUM(AI72:AI84) -> 203311 | AJ85: =SUM(AJ72:AJ84) -> 202453 | AK85: =SUM(AK72:AK84) -> 204074 | AL85: =SUM(AL72:AL84) -> 203631 | AM85: =SUM(AM72:AM84) -> 202124 | AN85: =SUM(AN72:AN84) -> 204858 | AO85: =SUM(AO72:AO84) -> 203783 | ... AY85: =SUM(AY72:AY84) -> 202089 | BO85: =AL85 -> 203631 | BP85: =AP85 -> 205579 | BQ85: =AT85 -> 196219 | BR85: =AX85 -> 197514 | CD85: Market Return(1-year avg.) | CG85: 0.113
CD86: Cost of Equity | CG86: =(CG83+CG84)*(CG85-CG83) -> 0.074601355
B87: A/R and other Accrued Liabilities | AH87: 20894 | AI87: 18709 | AJ87: 19669 | AK87: 20858 | AL87: 20213 | AM87: 18149 | AN87: 18591 | AO87: 19115 | AP87: 20671 | AQ87: 18676 | AR87: 18798 | AS87: 20216 | AT87: 21070 | AU87: 21635 | AV87: 20729 | AW87: 20500 | AX87: 21203 | AY87: 20541 | BO87: =AL87 -> 20213 | BP87: =AP87 -> 20671 | BQ87: =AT87 -> 21070 | BR87: =AX87 -> 21203
B88: ST Debt | AH88: 5866 | AI88: 6783 | AJ88: 5399 | AK88: 5580 | AL88: 3070 | AM88: 3249 | AN88: 3452 | AO88: 2645 | AP88: 4330 | AQ88: 6087 | AR88: 6789 | AS88: 8060 | AT88: 6845 | AU88: 6620 | AV88: 6446 | AW88: 5732 | AX88: 6711 | AY88: 10819 | BO88: =AL88 -> 3070 | BP88: =AP88 -> 4330 | BQ88: =AT88 -> 6845 | BR88: =AX88 -> 6711 | CD88: Cost of Debt
B89: ST Deferred Revenues | AH89: 4317 | AI89: 4545 | AJ89: 4533 | AK89: 4266 | AL89: 5790 | AM89: 5672 | AN89: 6013 | AO89: 6474 | AP89: 6138 | AQ89: 6270 | AR89: 7287 | AS89: 7336 | AT89: 6684 | AU89: 6591 | AV89: 6854 | AW89: 6740 | AX89: 6248 | AY89: 6686 | BO89: =AL89 -> 5790 | BP89: =AP89 -> 6138 | BQ89: =AT89 -> 6684 | BR89: =AX89 -> 6248 | CD89: Cost of Debt | CG89: 0.059
B90: LT Debt | AH90: 48540 | AI90: 47349 | AJ90: 46624 | AK90: 46022 | AL90: 45299 | AM90: 45128 | AN90: 45066 | AO90: 44544 | AP90: 42101 | AQ90: 41603 | AR90: 39510 | AS90: 39524 | AT90: 38970 | AU90: 38688 | AV90: 36443 | AW90: 36531 | AX90: 35315 | AY90: 35821 | BO90: =AL90 -> 45299 | BP90: =AP90 -> 42101 | BQ90: =AT90 -> 38970 | BR90: =AX90 -> 35315 | BS90: =BR90-(BR90*0.05) -> 33549.25 | BT90: =BS90-(BS90*0.05) -> 31871.787 | BU90: =BT90-(BT90*0.05) -> 30278.198 | BV90: =BU90-(BU90*0.05) -> 28764.288 | BW90: =BV90-(BV90*0.05) -> 27326.074 | BX90: =BW90-(BW90*0.05) -> 25959.77 | BY90: =BX90-(BX90*0.05) -> 24661.782 | BZ90: =BY90-(BY90*0.05) -> 23428.693 | ... CB90: =CA90-(CA90*0.05) -> 21144.395 | CD90: Tax Rate | CG90: 0.146
B91: LT Deffered Income Tax Liabilities | AH91: 7246 | AI91: 8124 | AJ91: 8407 | AK91: 8034 | AL91: 8363 | AM91: 8363 | AN91: 8134 | AO91: 7304 | AP91: 7258 | AQ91: 7041 | AR91: 6860 | AS91: 6628 | AT91: 6277 | AU91: 6336 | AV91: 6298 | AW91: 3097 | AX91: 3524 | AY91: 4126 | BO91: =AL91 -> 8363 | BP91: =AP91 -> 7258 | BQ91: =AT91 -> 6277 | BR91: =AX91 -> 3524 | CD91: After Tax Cost of Debt | CG91: =CG89*(1-CG90) -> 0.050386
B92: Other LT Liabilities | AH92: 14522 | AI92: 14208 | AJ92: 13808 | AK92: 13456 | AL92: 12518 | AM92: 12518 | AN92: 13232 | AO92: 12759 | AP92: 12069 | AQ92: 12596 | AR92: 12103 | AS92: 10705 | AT92: 10851 | AU92: 10437 | AV92: 10297 | AW92: 10256 | AX92: 9901 | AY92: 10088 | BO92: =AL92 -> 12518 | BP92: =AP92 -> 12069 | BQ92: =AT92 -> 10851 | BR92: =AX92 -> 9901 | CD92: WACC | CG92: =(CG79*CG86)+(CG78*CG91*(1-CG90)) -> 0.068319902
B93: LT Commitments and Contingencies | AH93: 9213 | AI93: 9283 | AJ93: 9354 | AK93: 9425 | AL93: 9499 | AM93: 9499 | AN93: 8814 | AO93: 8886 | AP93: 9055 | AQ93: 0 | AR93: 0 | AS93: 0 | AT93: 0 | AU93: 0 | AV93: 0 | AW93: 0 | AX93: 0 | AY93: 0 | BO93: =AL93 -> 9499 | BP93: =AP93 -> 9055 | BQ93: =AT93 -> 0 | BR93: =AX93 -> 0
B94: Ttl Liabilities | AH94: =SUM(AH87:AH93) -> 110598 | AI94: =SUM(AI87:AI93) -> 109001 | AJ94: =SUM(AJ87:AJ93) -> 107794 | AK94: =SUM(AK87:AK93) -> 107641 | AL94: =SUM(AL87:AL93) -> 104752 | AM94: =SUM(AM87:AM93) -> 102578 | AN94: =SUM(AN87:AN93) -> 103302 | AO94: =SUM(AO87:AO93) -> 101727 | ... AY94: =SUM(AY87:AY93) -> 88081 | BO94: =AL94 -> 104752 | BP94: =AP94 -> 101622 | BQ94: =AT94 -> 90697 | BR94: =AX94 -> 82902
B95: Ttl SE | AH95: 93011 | AI95: 94310 | AJ95: 94659 | AK95: 96433 | AL95: 98879 | AM95: 98879 | AN95: 101556 | AO95: 102056 | AP95: 103957 | AQ95: 105501 | AR95: 103763 | AS95: 105303 | AT95: 105522 | AU95: 106739 | AV95: 108766 | AW95: 113756 | AX95: 114612 | AY95: 114008 | BO95: =AL95 -> 98879 | BP95: =AP95 -> 103957 | BQ95: =AT95 -> 105522 | BR95: =AX95 -> 114612
B96: Ttl L + SE | AH96: =AH94+AH95 -> 203609 | AI96: =AI94+AI95 -> 203311 | AJ96: =AJ94+AJ95 -> 202453 | AK96: =AK94+AK95 -> 204074 | AL96: =AL94+AL95 -> 203631 | AM96: =AM94+AM95 -> 201457 | AN96: =AN94+AN95 -> 204858 | AO96: =AO94+AO95 -> 203783 | ... AY96: =AY94+AY95 -> 202089 | BO96: =AL96 -> 203631 | BP96: =AP96 -> 205579 | BQ96: =AT96 -> 196219 | BR96: =AX96 -> 197514
B98: Current Ratio | AH98: =SUM(AH81:AH85)/SUM(AH93:AH97) -> 0.74102072 | AI98: =SUM(AI81:AI85)/SUM(AI93:AI97) -> 0.74038783 | AJ98: =SUM(AJ81:AJ85)/SUM(AJ93:AJ97) -> 0.7386255 | AK98: =SUM(AK81:AK85)/SUM(AK93:AK97) -> 0.73507387 | AL98: =SUM(AL81:AL85)/SUM(AL93:AL97) -> 0.73594458 | AM98: =SUM(AM81:AM85)/SUM(AM93:AM97) -> 0.73920803 | AN98: =SUM(AN81:AN85)/SUM(AN93:AN97) -> 0.73518983 | AO98: =SUM(AO81:AO85)/SUM(AO93:AO97) -> 0.73556376 | ... AY98: =SUM(AY81:AY85)/SUM(AY93:AY97) -> 0.73616327 | BO98: =SUM(BO81:BO85)/SUM(BO93:BO97) -> 0.73594458 | BP98: =SUM(BP81:BP85)/SUM(BP93:BP97) -> 0.73286405 | BQ98: =SUM(BQ81:BQ85)/SUM(BQ93:BQ97) -> 0.75051346 | BR98: =SUM(BR81:BR85)/SUM(BR93:BR97) -> 0.73735026
B99: Quick Ratio | AH99: =(SUM(AH81:AH85)-AH84)/SUM(AH93:AH97) -> 0.72022976 | AI99: =(SUM(AI81:AI85)-AI84)/SUM(AI93:AI97) -> 0.71905363 | AJ99: =(SUM(AJ81:AJ85)-AJ84)/SUM(AJ93:AJ97) -> 0.71808285 | AK99: =(SUM(AK81:AK85)-AK84)/SUM(AK93:AK97) -> 0.71477323 | AL99: =(SUM(AL81:AL85)-AL84)/SUM(AL93:AL97) -> 0.71385038 | AM99: =(SUM(AM81:AM85)-AM84)/SUM(AM93:AM97) -> 0.71650506 | AN99: =(SUM(AN81:AN85)-AN84)/SUM(AN93:AN97) -> 0.71149977 | AO99: =(SUM(AO81:AO85)-AO84)/SUM(AO93:AO97) -> 0.71154179 | ... AY99: =(SUM(AY81:AY85)-AY84)/SUM(AY93:AY97) -> 0.71120645 | BO99: =(SUM(BO81:BO85)-BO84)/SUM(BO93:BO97) -> 0.71385038 | BP99: =(SUM(BP81:BP85)-BP84)/SUM(BP93:BP97) -> 0.70650599 | BQ99: =(SUM(BQ81:BQ85)-BQ84)/SUM(BQ93:BQ97) -> 0.71712984 | BR99: =(SUM(BR81:BR85)-BR84)/SUM(BR93:BR97) -> 0.71203054
B100: Cash Ratio | AH100: =SUM(AH81:AH82)/SUM(AH93:AH97) -> 0.043815182 | AI100: =SUM(AI81:AI82)/SUM(AI93:AI97) -> 0.042545774 | AJ100: =SUM(AJ81:AJ82)/SUM(AJ93:AJ97) -> 0.041039444 | AK100: =SUM(AK81:AK82)/SUM(AK93:AK97) -> 0.039396704 | AL100: =SUM(AL81:AL82)/SUM(AL93:AL97) -> 0.038336121 | AM100: =SUM(AM81:AM82)/SUM(AM93:AM97) -> 0.037595808 | AN100: =SUM(AN81:AN82)/SUM(AN93:AN97) -> 0.035954412 | AO100: =SUM(AO81:AO82)/SUM(AO93:AO97) -> 0.035199735 | ... AY100: =SUM(AY81:AY82)/SUM(AY93:AY97) -> 0.0262805 | BO100: =SUM(BO81:BO82)/SUM(BO93:BO97) -> 0.038336121 | BP100: =SUM(BP81:BP82)/SUM(BP93:BP97) -> 0.033880437 | BQ100: =SUM(BQ81:BQ82)/SUM(BQ93:BQ97) -> 0.03028249 | BR100: =SUM(BR81:BR82)/SUM(BR93:BR97) -> 0.026489262
B101: Fixed Asset Turnover Ratio | AH101: =AH46/SUM(AH79:AH81) -> 0.56810937 | AI101: =AI46/SUM(AI79:AI81) -> 0.66763563 | AJ101: =AJ46/SUM(AJ79:AJ81) -> 0.58477383 | AK101: =AK46/SUM(AK79:AK81) -> 0.64032397 | AL101: =AL46/SUM(AL79:AL81) -> 0.59977378 | AM101: =AM46/SUM(AM79:AM81) -> 0.68748538 | AN101: =AN46/SUM(AN79:AN81) -> 0.63087423 | AO101: =AO46/SUM(AO79:AO81) -> 0.64580501 | ... AY101: =AY46/SUM(AY79:AY81) -> 0.60143988 | BO101: =BO46/SUM(BO79:BO81) -> 2.4622574 | BP101: =BP46/SUM(BP79:BP81) -> 2.5442317 | BQ101: =BQ46/SUM(BQ79:BQ81) -> 2.4664831 | BR101: =BR46/SUM(BR79:BR81) -> 2.2888135
B102: Ttl Asset Turnover Ratio | AH102: =AH46/AH94 -> 0.16757988 | AI102: =AI46/AI94 -> 0.20017248 | AJ102: =AJ46/AJ94 -> 0.17857209 | AK102: =AK46/AK94 -> 0.19977518 | AL102: =AL46/AL94 -> 0.1923591 | AM102: =AM46/AM94 -> 0.22921094 | AN102: =AN46/AN94 -> 0.21117694 | AO102: =AO46/AO94 -> 0.21950908 | ... AY102: =AY46/AY94 -> 0.29496713 | BO102: =BO46/BO94 -> 0.78969375 | BP102: =BP46/BP94 -> 0.87479089 | BQ102: =BQ46/BQ94 -> 1.0073211 | BR102: =BR46/BR94 -> 1.1389954
B103: Inventory Turnover Ratio | AH103: =AH47/AVERAGE(AE84:AH84) -> 1.4253869 | AI103: =AI47/AVERAGE(AF84:AI84) -> 1.6618561 | AJ103: =AJ47/AVERAGE(AG84:AJ84) -> 1.4508659 | AK103: =AK47/AVERAGE(AH84:AK84) -> 1.5854916 | AL103: =AL47/AVERAGE(AI84:AL84) -> 1.5464811 | AM103: =AM47/AVERAGE(AJ84:AM84) -> 1.8432983 | AN103: =AN47/AVERAGE(AK84:AN84) -> 1.5816898 | AO103: =AO47/AVERAGE(AL84:AO84) -> 1.5038711 | ... AY103: =AY47/AVERAGE(AV84:AY84) -> 1.6725868 | BO103: =BO47/AVERAGE(BL84:BO84) -> 5.9080148 | BP103: =BP47/AVERAGE(BM84:BP84) -> 5.8372116 | BQ103: =BQ47/AVERAGE(BN84:BQ84) -> 5.2746443 | BR103: =BR47/AVERAGE(BO84:BR84) -> 5.4178441
B104: Return on Assets | AH104: =AH57/AH96 -> 0.0012573118 | AI104: =AI57/AI96 -> 0.0059022876 | AJ104: =AJ57/AJ96 -> 0.0029488326 | AK104: =AK57/AK96 -> 0.0073600753 | AL104: =AL57/AL96 -> 0.0012473543 | AM104: =AM57/AM96 -> 0.0067557841 | AN104: =AN57/AN96 -> 0.0072635679 | AO104: =AO57/AO96 -> -0.00075079864 | ... AY104: =AY57/AY96 -> 0.012291614 | BO104: =BO57/BO96 -> 0.017448227 | BP104: =BP57/BP96 -> 0.016490011 | BQ104: =BQ57/BQ96 -> 0.029421208 | BR104: =BR57/BR96 -> 0.068000243
B105: Return on Equity | AH105: =AH57/AH95 -> 0.0027523626 | AI105: =AI57/AI95 -> 0.012723995 | AJ105: =AJ57/AJ95 -> 0.0063068488 | AK105: =AK57/AK95 -> 0.015575581 | AL105: =AL57/AL95 -> 0.0025687962 | AM105: =AM57/AM95 -> 0.013764298 | AN105: =AN57/AN95 -> 0.014652015 | AO105: =AO57/AO95 -> -0.0014991769 | ... AY105: =AY57/AY95 -> 0.021787945 | BO105: =BO57/BO95 -> 0.035932807 | BP105: =BP57/BP95 -> 0.032609637 | BQ105: =BQ57/BQ95 -> 0.054708971 | BR105: =BR57/BR95 -> 0.11718668
B107: Net Income | C107: =C57 -> 1904 | D107: =D57 -> 2056 | E107: =E57 -> 2419 | F107: =F57 -> 1625 | G107: =G57 -> 2244 | H107: =H57 -> 2228 | I107: =I57 -> 2639 | J107: =J57 -> 1741 | ... AY107: =AY57 -> 2484 | BG107: =BG57 -> 8004 | BH107: =BH57 -> 8852 | BI107: =BI57 -> 9790 | BJ107: =BJ57 -> 9366 | BK107: =BK57 -> 13066 | BL107: =BL57 -> 10897 | BM107: =BM57 -> -2442 | BN107: =BN57 -> 2536 | ... BR107: =BR57 -> 13431
B108: CFFO | C108: 1212 | D108: 2527 | E108: 2936 | F108: 3105 | G108: 1855 | H108: 2918 | I108: 2808 | J108: 3804 | K108: 2456 | L108: 3529 | M108: 3630 | N108: 3521 | O108: 1445 | P108: 3228 | Q108: 4100 | R108: 3570 | S108: 2237 | T108: 4526 | U108: 3679 | V108: 3853 | W108: 2099 | X108: 3915 | Y108: -1748 | Z108: 1718 | AA108: 1630 | AB108: 3157 | AC108: 1162 | AD108: 1667 | AE108: 75 | AF108: 1393 | AG108: 1466 | AH108: 2632 | AI108: -209 | AJ108: 1765 | AK108: 1922 | AL108: 2524 | AM108: -974 | AN108: 3236 | AO108: 2802 | AP108: 4802 | AQ108: 2185 | AR108: 3666 | AS108: 2602 | AT108: 5518 | AU108: 3205 | AV108: 6753 | AW108: 3669 | AX108: 4474 | AY108: 735 | BG108: =SUM(C108:F108) -> 9780 | BH108: =SUM(G108:J108) -> 11385 | BI108: =SUM(K108:N108) -> 13136 | BJ108: =SUM(O108:R108) -> 12343 | BK108: =SUM(S108:V108) -> 14295 | BL108: =SUM(W108:Z108) -> 5984 | BM108: =SUM(AA108:AD108) -> 7616 | BN108: =SUM(AE108:AH108) -> 5566 | BO108: =SUM(AI108:AL108) -> 6002 | BP108: =SUM(AM108:AP108) -> 9866 | BQ108: =SUM(AQ108:AT108) -> 13971 | BR108: =SUM(AU108:AX108) -> 18101
B109: CapEx, net | C109: -658 | D109: -701 | E109: -889 | F109: -1063 | G109: -998 | H109: -907 | I109: -1156 | J109: -1204 | K109: -1806 | L109: -1150 | M109: -1135 | N109: -1532 | O109: -1040 | P109: -883 | Q109: -805 | R109: -755 | S109: -981 | T109: -1063 | U109: -1220 | V109: -1201 | W109: -1195 | X109: -1195 | Y109: -1177 | Z109: -1309 | AA109: -1338 | AB109: -1247 | AC109: -708 | AD109: -729 | AE109: -760 | AF109: -770 | AG109: -938 | AH109: -1110 | AI109: -981 | AJ109: -1079 | AK109: -1735 | AL109: -1148 | AM109: -1181 | AN109: -1249 | AO109: -1165 | AP109: -1374 | AQ109: -1299 | AR109: -1259 | AS109: -1365 | AT109: -1989 | AU109: -2466 | AV109: -1862 | AW109: -1780 | AX109: -1916 | AY109: -3013 | BG109: =SUM(C109:F109) -> -3311 | BH109: =SUM(G109:J109) -> -4265 | BI109: =SUM(K109:N109) -> -5623 | BJ109: =SUM(O109:R109) -> -3483 | BK109: =SUM(S109:V109) -> -4465 | BL109: =SUM(W109:Z109) -> -4876 | BM109: =SUM(AA109:AD109) -> -4022 | BN109: =SUM(AE109:AH109) -> -3578 | BO109: =SUM(AI109:AL109) -> -4943 | BP109: =SUM(AM109:AP109) -> -4969 | BQ109: =SUM(AQ109:AT109) -> -5912 | BR109: =SUM(AU109:AX109) -> -8024
B110: FCF | C110: =C108+C109 -> 554 | D110: =D108+D109 -> 1826 | E110: =E108+E109 -> 2047 | F110: =F108+F109 -> 2042 | G110: =G108+G109 -> 857 | H110: =H108+H109 -> 2011 | I110: =I108+I109 -> 1652 | J110: =J108+J109 -> 2600 | ... AY110: =AY108+AY109 -> -2278 | BG110: =BG108+BG109 -> 6469 | BH110: =BH108+BH109 -> 7120 | BI110: =BI108+BI109 -> 7513 | BJ110: =BJ108+BJ109 -> 8860 | BK110: =BK108+BK109 -> 9830 | BL110: =BL108+BL109 -> 1108 | BM110: =BM108+BM109 -> 3594 | BN110: =BN108+BN109 -> 1988 | ... BR110: =BR108+BR109 -> 10077
B111: SC | C111: =C62 -> 1700 | D111: =D62 -> 1700 | E111: =E62 -> 1700 | F111: =F62 -> 1700 | G111: =G62 -> 1700 | H111: =H62 -> 1700 | I111: =I62 -> 1600 | J111: =J62 -> 1600 | ... AY111: =AY62 -> 1771 | BG111: =BG62 -> 1700 | BH111: =BH62 -> 1650 | BI111: =BI62 -> 1675 | BJ111: =BJ62 -> 1575 | BK111: =BK62 -> 1500 | BL111: =BL62 -> 1710.75 | BM111: =BM62 -> 1781 | BN111: =BN62 -> 1781 | ... BR111: =BR62 -> 1833.25
B112: FCF per Share | C112: =C110/C111 -> 0.32588235 | D112: =D110/D111 -> 1.0741176 | E112: =E110/E111 -> 1.2041176 | F112: =F110/F111 -> 1.2011765 | G112: =G110/G111 -> 0.50411765 | H112: =H110/H111 -> 1.1829412 | I112: =I110/I111 -> 1.0325 | J112: =J110/J111 -> 1.625 | ... AY112: =AY110/AY111 -> -1.2862789 | BG112: =BG110/BG111 -> 3.8052941 | BH112: =BH110/BH111 -> 4.3151515 | BI112: =BI110/BI111 -> 4.4853731 | BJ112: =BJ110/BJ111 -> 5.6253968 | BK112: =BK110/BK111 -> 6.5533333 | BL112: =BL110/BL111 -> 0.64766915 | BM112: =BM110/BM111 -> 2.0179674 | BN112: =BN110/BN111 -> 1.1162268 | ... BR112: =BR110/BR111 -> 5.4967953

Sheet Notes | Quant Analysis
CI1: 0
P2: Employee Scope: | AL2: General Notes/Observations (Updated Q1'26)
AL35: Financial Stmts. Notes/Observations (Updated Q1'26)
P36: Institutional Ownership Snapshot Q1'26 | AL36: Revenues:
AL37: [Godel Snapshot of projected sales]
Q65: Notes: | R65: [X]
R66: [Y]
R67: [Z]
P69: Revenue Breakdown by Segment | AL69: Earnings Scope:
AL70: [Godel Snapshot of projected earnings/EPS + CFFO]
Q101: Notes: | R101: [X]
R102: [Y]
R103: [Z]
P105: Q/q Total Revenues, Net Income, FCF | AL105: Balance Sheet Scope:
AL106: [Godel Snapshot of projected balances (assets, liabilities, equity)]
Q134: Notes: | R134: [X]
R135: [Y]
R136: [Z]
P138: Y/y Total Revenues, Net Income, FCF | AL138: [Equity Preformance Compared to Peers]
AL139: Use Godel CMS command
Q167: Notes: | R167: [X]
R168: [Y]
R169: [Z]
A184: VOO Historical Returns | I184: DIS Historical Returns
A185: 753 Trading Days (From: 2/20/2023 - 2/20/2026) | I185: 753 Trading Days (From: 2/20/2023 - 2/20/2026)
A186: Close | B186: High | C186: Low | D186: Open | E186: Volume | F186: UTC Date | G186: Change | I186: Close | J186: High | K186: Low | L186: Open | M186: Volume | N186: UTC Date | O186: Change
A187: 635.24 | B187: 636.72 | C187: 626.2 | D187: 626.72 | E187: 12959420 | F187: Fri, 06 Feb 2026 00:00:00 GMT | G187: =A187/D187-1 -> 0.013594588 | I187: 108.7 | J187: 108.9551 | K187: 105.37 | L187: 106.13 | M187: 11923379 | N187: Fri, 06 Feb 2026 00:00:00 GMT | O187: =I187/L187-1 -> 0.024215585
A188: 623.1 | B188: 628.75 | C188: 621.5 | D188: 626.24 | E188: 11506981 | F188: Thu, 05 Feb 2026 00:00:00 GMT | G188: =A188/D188-1 -> -0.0050140521 | I188: 104.97 | J188: 108.33 | K188: 104.81 | L188: 107.05 | M188: 11663806 | N188: Thu, 05 Feb 2026 00:00:00 GMT | O188: =I188/L188-1 -> -0.019430173
A189: 630.91 | B189: 635.92 | C189: 627 | D189: 634.93 | E189: 11228241 | F189: Wed, 04 Feb 2026 00:00:00 GMT | G189: =A189/D189-1 -> -0.0063314066 | I189: 107.05 | J189: 108.6 | K189: 103.63 | L189: 104.2 | M189: 19051573 | N189: Wed, 04 Feb 2026 00:00:00 GMT | O189: =I189/L189-1 -> 0.027351248
A190: 634.15 | B190: 641 | C190: 629.105 | D190: 640.33 | E190: 9644195 | F190: Tue, 03 Feb 2026 00:00:00 GMT | G190: =A190/D190-1 -> -0.0096512736 | I190: 104.22 | J190: 104.99 | K190: 102.34 | L190: 104.78 | M190: 24538397 | N190: Tue, 03 Feb 2026 00:00:00 GMT | O190: =I190/L190-1 -> -0.0053445314
A191: 639.68 | B191: 640.96 | C191: 634.07 | D191: 634.18 | E191: 9124531 | F191: Mon, 02 Feb 2026 00:00:00 GMT | G191: =A191/D191-1 -> 0.0086726166 | I191: 104.45 | J191: 108.61 | K191: 103.75 | L191: 104.01 | M191: 37475239 | N191: Mon, 02 Feb 2026 00:00:00 GMT | O191: =I191/L191-1 -> 0.0042303625
A192: 636.22 | B192: 638.45 | C192: 631.95 | D192: 636.25 | E192: 6519552 | F192: Fri, 30 Jan 2026 00:00:00 GMT | G192: =A192/D192-1 -> -4.7151277e-05 | I192: 112.8 | J192: 112.945 | K192: 110.99 | L192: 111.36 | M192: 17790464 | N192: Fri, 30 Jan 2026 00:00:00 GMT | O192: =I192/L192-1 -> 0.012931034
A193: 638.27 | B193: 641.04 | C193: 629.82 | D193: 640.43 | E193: 8485857 | F193: Thu, 29 Jan 2026 00:00:00 GMT | G193: =A193/D193-1 -> -0.0033727339 | I193: 111.58 | J193: 111.67 | K193: 108.76 | L193: 109.63 | M193: 10775531 | N193: Thu, 29 Jan 2026 00:00:00 GMT | O193: =I193/L193-1 -> 0.017787102
A194: 639.6 | B194: 641.81 | C194: 638.22 | D194: 641.05 | E194: 5488373 | F194: Wed, 28 Jan 2026 00:00:00 GMT | G194: =A194/D194-1 -> -0.002261914 | I194: 109.56 | J194: 111.4299 | K194: 109 | L194: 110.28 | M194: 8980383 | N194: Wed, 28 Jan 2026 00:00:00 GMT | O194: =I194/L194-1 -> -0.0065288357
A195: 639.7 | B195: 640.5959 | C195: 637.87 | D195: 638.42 | E195: 4308306 | F195: Tue, 27 Jan 2026 00:00:00 GMT | G195: =A195/D195-1 -> 0.0020049497 | I195: 110.61 | J195: 111.8 | K195: 110.03 | L195: 111.5 | M195: 8889788 | N195: Tue, 27 Jan 2026 00:00:00 GMT | O195: =I195/L195-1 -> -0.0079820628
A196: 637.09 | B196: 638.39 | C196: 634.52 | D196: 635.03 | E196: 8976388 | F196: Mon, 26 Jan 2026 00:00:00 GMT | G196: =A196/D196-1 -> 0.0032439412 | I196: 111.31 | J196: 112.41 | K196: 111.13 | L196: 111.68 | M196: 8654452 | N196: Mon, 26 Jan 2026 00:00:00 GMT | O196: =I196/L196-1 -> -0.0033130372
A197: 633.83 | B197: 635.4705 | C197: 631.97 | D197: 632.88 | E197: 5827254 | F197: Fri, 23 Jan 2026 00:00:00 GMT | G197: =A197/D197-1 -> 0.0015010745 | I197: 110.98 | J197: 112.9476 | K197: 110.55 | L197: 112.685 | M197: 10634570 | N197: Fri, 23 Jan 2026 00:00:00 GMT | O197: =I197/L197-1 -> -0.015130674
A198: 633.57 | B198: 635.62 | C198: 631.75 | D198: 634.43 | E198: 6057784 | F198: Thu, 22 Jan 2026 00:00:00 GMT | G198: =A198/D198-1 -> -0.0013555475 | I198: 113.21 | J198: 114.29 | K198: 112.17 | L198: 113.165 | M198: 12224987 | N198: Thu, 22 Jan 2026 00:00:00 GMT | O198: =I198/L198-1 -> 0.00039764945
A199: 630.29 | B199: 633.4 | C199: 623.65 | D199: 625.02 | E199: 10354978 | F199: Wed, 21 Jan 2026 00:00:00 GMT | G199: =A199/D199-1 -> 0.0084317302 | I199: 113.19 | J199: 113.25 | K199: 110.5 | L199: 110.57 | M199: 10001042 | N199: Wed, 21 Jan 2026 00:00:00 GMT | O199: =I199/L199-1 -> 0.023695397 | Q199: Notes: | R199: [X]
A200: 623.15 | B200: 629.7599 | C200: 622.22 | D200: 626.76 | E200: 14877629 | F200: Tue, 20 Jan 2026 00:00:00 GMT | G200: =A200/D200-1 -> -0.0057597805 | I200: 110.34 | J200: 111.09 | K200: 108.8 | L200: 109.66 | M200: 9818195 | N200: Tue, 20 Jan 2026 00:00:00 GMT | O200: =I200/L200-1 -> 0.0062009849 | R200: [Y]
A201: 636.09 | B201: 638.5099 | C201: 634.68 | D201: 637.96 | E201: 6694041 | F201: Fri, 16 Jan 2026 00:00:00 GMT | G201: =A201/D201-1 -> -0.0029312183 | I201: 111.2 | J201: 113.85 | K201: 111.12 | L201: 113.2 | M201: 11934883 | N201: Fri, 16 Jan 2026 00:00:00 GMT | O201: =I201/L201-1 -> -0.017667845 | R201: [Z]
A202: 636.62 | B202: 639.58 | C202: 635.7 | D202: 638.77 | E202: 6751601 | F202: Thu, 15 Jan 2026 00:00:00 GMT | G202: =A202/D202-1 -> -0.0033658437 | I202: 113.41 | J202: 114.11 | K202: 112.17 | L202: 113.71 | M202: 7882250 | N202: Thu, 15 Jan 2026 00:00:00 GMT | O202: =I202/L202-1 -> -0.0026382904
A203: 634.94 | B203: 636.119 | C203: 631 | D203: 635.49 | E203: 8576256 | F203: Wed, 14 Jan 2026 00:00:00 GMT | G203: =A203/D203-1 -> -0.00086547389 | I203: 113.53 | J203: 113.59 | K203: 112.26 | L203: 112.81 | M203: 8763228 | N203: Wed, 14 Jan 2026 00:00:00 GMT | O203: =I203/L203-1 -> 0.0063824129 | R203: Min | S203: =MIN(O187:O940) -> -0.065062691
A204: 638.03 | B204: 640.1507 | C204: 635.815 | D204: 639.68 | E204: 8837128 | F204: Tue, 13 Jan 2026 00:00:00 GMT | G204: =A204/D204-1 -> -0.0025794147 | I204: 112.98 | J204: 113.22 | K204: 111.61 | L204: 112.84 | M204: 8843726 | N204: Tue, 13 Jan 2026 00:00:00 GMT | O204: =I204/L204-1 -> 0.0012406948 | R204: Max | S204: =MAX(O187:O940) -> 0.12486161
A205: 639.34 | B205: 640.16 | C205: 635.16 | D205: 635.19 | E205: 7889884 | F205: Mon, 12 Jan 2026 00:00:00 GMT | G205: =A205/D205-1 -> 0.0065334782 | I205: 112.82 | J205: 114.94 | K205: 112.55 | L205: 114.63 | M205: 10579199 | N205: Mon, 12 Jan 2026 00:00:00 GMT | O205: =I205/L205-1 -> -0.015789933 | R205: Mean μ | S205: =AVERAGE(O187:O940) -> 0.00066404875
A206: 638.31 | B206: 639.44 | C206: 633.8 | D206: 635.15 | E206: 7843716 | F206: Fri, 09 Jan 2026 00:00:00 GMT | G206: =A206/D206-1 -> 0.0049752027 | I206: 115.88 | J206: 115.98 | K206: 113.9 | L206: 114.31 | M206: 8913617 | N206: Fri, 09 Jan 2026 00:00:00 GMT | O206: =I206/L206-1 -> 0.013734581 | R206: Median | S206: =MEDIAN(O187:O940) -> 0.00093110426
A207: 634.06 | B207: 635.1001 | C207: 632.2362 | D207: 633.48 | E207: 8962799 | F207: Thu, 08 Jan 2026 00:00:00 GMT | G207: =A207/D207-1 -> 0.00091557745 | I207: 114.17 | J207: 114.99 | K207: 112.545 | L207: 112.545 | M207: 9647104 | N207: Thu, 08 Jan 2026 00:00:00 GMT | O207: =I207/L207-1 -> 0.014438669 | R207: SD σ | S207: =_xlfn.STDEV.P(O187:O940) -> 0.013251485
A208: 634.17 | B208: 638.22 | C208: 633.93 | D208: 636.58 | E208: 8796759 | F208: Wed, 07 Jan 2026 00:00:00 GMT | G208: =A208/D208-1 -> -0.0037858557 | I208: 112.91 | J208: 114.97 | K208: 112.51 | L208: 114.46 | M208: 8289758 | N208: Wed, 07 Jan 2026 00:00:00 GMT | O208: =I208/L208-1 -> -0.013541849 | R208: 3σ 1-Day Δ: ± | S208: =3*S207 -> 0.039754455 | U208: <- Sharpe Ratio (Risk Adjusted Return)
A209: 636.21 | B209: 636.68 | C209: 632.53 | D209: 632.64 | E209: 8630900 | F209: Tue, 06 Jan 2026 00:00:00 GMT | G209: =A209/D209-1 -> 0.0056430197 | I209: 114.57 | J209: 114.7599 | K209: 113.107 | L209: 113.785 | M209: 7374101 | N209: Tue, 06 Jan 2026 00:00:00 GMT | O209: =I209/L209-1 -> 0.0068989761 | R209: β (1-year avg.) | S209: =_xlfn.COVARIANCE.P(O187:O435,G187:G435)/_xlfn.VAR.P(G187:G435) -> 1.0270207 | U209: <- Sortino Ratio (Downside Risk Adjusted Return)
A210: 632.46 | B210: 634.04 | C210: 631.23 | D210: 631.38 | E210: 16140408 | F210: Mon, 05 Jan 2026 00:00:00 GMT | G210: =A210/D210-1 -> 0.0017105388 | I210: 114.07 | J210: 116.03 | K210: 111.38 | L210: 111.42 | M210: 11857701 | N210: Mon, 05 Jan 2026 00:00:00 GMT | O210: =I210/L210-1 -> 0.023783881
A211: 628.3 | B211: 631.66 | C211: 625.21 | D211: 630.635 | E211: 10997544 | F211: Fri, 02 Jan 2026 00:00:00 GMT | G211: =A211/D211-1 -> -0.0037026172 | I211: 111.85 | J211: 113.44 | K211: 111.62 | L211: 113.44 | M211: 8897719 | N211: Fri, 02 Jan 2026 00:00:00 GMT | O211: =I211/L211-1 -> -0.01401622 | Q211: n = | R211: 1014
A212: 627.13 | B212: 632.14 | C212: 626.94 | D212: 631.94 | E212: 5511193 | F212: Wed, 31 Dec 2025 00:00:00 GMT | G212: =A212/D212-1 -> -0.0076114821 | I212: 113.77 | J212: 114.89 | K212: 113.55 | L212: 114.77 | M212: 6538759 | N212: Wed, 31 Dec 2025 00:00:00 GMT | O212: =I212/L212-1 -> -0.0087130783 | Q212: Histogram Data | T212: Distribution Overlay | X212: SD Lines
A213: 631.72 | B213: 633.21 | C213: 631.41 | D213: 632.2 | E213: 4150867 | F213: Tue, 30 Dec 2025 00:00:00 GMT | G213: =A213/D213-1 -> -0.0007592534 | I213: 114.79 | J213: 115.28 | K213: 114.1 | L213: 114.1 | M213: 6592952 | N213: Tue, 30 Dec 2025 00:00:00 GMT | O213: =I213/L213-1 -> 0.0060473269 | Q213: Bin | R213: Frequency | T213: (X) 1-Day Δ | U213: (Y) Pop. Density | X213: X | Y213: Y
A214: 632.6 | B214: 633.79 | C214: 630.95 | D214: 632.3 | E214: 6496953 | F214: Mon, 29 Dec 2025 00:00:00 GMT | G214: =A214/D214-1 -> 0.00047445833 | I214: 114.19 | J214: 114.49 | K214: 113.31 | L214: 113.315 | M214: 7426387 | N214: Mon, 29 Dec 2025 00:00:00 GMT | O214: =I214/L214-1 -> 0.0077218374 | Q214: -0.042 | R214: 4 | T214: =T215-0.001 -> -0.045 | U214: =_xlfn.NORM.DIST(T214,$S$205,$S$207,FALSE) -> 0.07945193 | W214: Mean | X214: =S205 -> 0.00066404875 | Y214: 0
A215: 634.84 | B215: 636.075 | C215: 633.88 | D215: 635.14 | E215: 3829855 | F215: Fri, 26 Dec 2025 00:00:00 GMT | G215: =A215/D215-1 -> -0.00047233681 | I215: 113.56 | J215: 114.74 | K215: 113.27 | L215: 114.15 | M215: 5383118 | N215: Fri, 26 Dec 2025 00:00:00 GMT | O215: =I215/L215-1 -> -0.0051686378 | Q215: -0.041 | R215: 1 | T215: =T216-0.001 -> -0.044 | U215: =_xlfn.NORM.DIST(T215,$S$205,$S$207,FALSE) -> 0.10275504 | X215: =S205 -> 0.00066404875 | Y215: 30
A216: 634.78 | B216: 635.32 | C216: 632.54 | D216: 632.67 | E216: 3273415 | F216: Wed, 24 Dec 2025 00:00:00 GMT | G216: =A216/D216-1 -> 0.003335072 | I216: 114.48 | J216: 114.53 | K216: 112.8 | L216: 112.94 | M216: 4605923 | N216: Wed, 24 Dec 2025 00:00:00 GMT | O216: =I216/L216-1 -> 0.013635559 | Q216: -0.04 | R216: 0 | T216: =T217-0.001 -> -0.043 | U216: =_xlfn.NORM.DIST(T216,$S$205,$S$207,FALSE) -> 0.13213828 | W216: -3σ | X216: =($S$207*-3)+$S$205 -> -0.039090406 | Y216: 0
A217: 632.67 | B217: 632.88 | C217: 628.92 | D217: 628.94 | E217: 13758872 | F217: Tue, 23 Dec 2025 00:00:00 GMT | G217: =A217/D217-1 -> 0.0059306134 | I217: 113.22 | J217: 113.31 | K217: 112.04 | L217: 112.29 | M217: 7578854 | N217: Tue, 23 Dec 2025 00:00:00 GMT | O217: =I217/L217-1 -> 0.0082821266 | Q217: -0.039 | R217: 0 | T217: =T218-0.001 -> -0.042 | U217: =_xlfn.NORM.DIST(T217,$S$205,$S$207,FALSE) -> 0.16895887 | X217: =($S$207*-3)+$S$205 -> -0.039090406 | Y217: 1
A218: 629.73 | B218: 630.27 | C218: 627.8 | D218: 628.965 | E218: 9796066 | F218: Mon, 22 Dec 2025 00:00:00 GMT | G218: =A218/D218-1 -> 0.0012162839 | I218: 112.38 | J218: 112.8 | K218: 111.15 | L218: 111.41 | M218: 8790904 | N218: Mon, 22 Dec 2025 00:00:00 GMT | O218: =I218/L218-1 -> 0.0087065793 | Q218: -0.038 | R218: 0 | T218: =T219-0.001 -> -0.041 | U218: =_xlfn.NORM.DIST(T218,$S$205,$S$207,FALSE) -> 0.2148128 | W218: -2σ | X218: =($S$207*-2)+$S$205 -> -0.025838921 | Y218: 0
A219: 627.56 | B219: 628.13 | C219: 623.86 | D219: 623.98 | E219: 10447326 | F219: Fri, 19 Dec 2025 00:00:00 GMT | G219: =A219/D219-1 -> 0.0057373634 | I219: 111.24 | J219: 113.478 | K219: 110.92 | L219: 112.32 | M219: 20894962 | N219: Fri, 19 Dec 2025 00:00:00 GMT | O219: =I219/L219-1 -> -0.0096153846 | Q219: -0.037 | R219: 0 | T219: =T220-0.001 -> -0.04 | U219: =_xlfn.NORM.DIST(T219,$S$205,$S$207,FALSE) -> 0.27156021 | X219: =($S$207*-2)+$S$205 -> -0.025838921 | Y219: 5
A220: 622.01 | B220: 625.94 | C220: 620.57 | D220: 623.05 | E220: 33420938 | F220: Thu, 18 Dec 2025 00:00:00 GMT | G220: =A220/D220-1 -> -0.0016692079 | I220: 111.87 | J220: 112.8 | K220: 110.42 | L220: 110.53 | M220: 11665213 | N220: Thu, 18 Dec 2025 00:00:00 GMT | O220: =I220/L220-1 -> 0.012123405 | Q220: -0.036 | R220: 0 | T220: =T221-0.001 -> -0.039 | U220: =_xlfn.NORM.DIST(T220,$S$205,$S$207,FALSE) -> 0.34134924 | W220: -1σ | X220: =($S$207*-1)+$S$205 -> -0.012587436 | Y220: 0
A221: 617.35 | B221: 625.64 | C221: 617.159 | D221: 625.19 | E221: 20953077 | F221: Wed, 17 Dec 2025 00:00:00 GMT | G221: =A221/D221-1 -> -0.012540188 | I221: 110.63 | J221: 112.13 | K221: 110.455 | L221: 111.06 | M221: 11533890 | N221: Wed, 17 Dec 2025 00:00:00 GMT | O221: =I221/L221-1 -> -0.003871781 | Q221: -0.035 | R221: 1 | T221: =T222-0.001 -> -0.038 | U221: =_xlfn.NORM.DIST(T221,$S$205,$S$207,FALSE) -> 0.42663706 | X221: =($S$207*-1)+$S$205 -> -0.012587436 | Y221: 19
A222: 624.21 | B222: 626.22 | C222: 620.65 | D222: 624.55 | E222: 13922431 | F222: Tue, 16 Dec 2025 00:00:00 GMT | G222: =A222/D222-1 -> -0.00054439196 | I222: 111.62 | J222: 112.8499 | K222: 110.855 | L222: 111.215 | M222: 14697823 | N222: Tue, 16 Dec 2025 00:00:00 GMT | O222: =I222/L222-1 -> 0.0036415951 | Q222: -0.034 | R222: 0 | T222: =T223-0.001 -> -0.037 | U222: =_xlfn.NORM.DIST(T222,$S$205,$S$207,FALSE) -> 0.53020647 | W222: 1σ | X222: =($S$207*1)+$S$205 -> 0.013915534 | Y222: 0
A223: 625.96 | B223: 630.56 | C223: 624.57 | D223: 630.56 | E223: 11306924 | F223: Mon, 15 Dec 2025 00:00:00 GMT | G223: =A223/D223-1 -> -0.0072951028 | I223: 110.49 | J223: 111.55 | K223: 108.55 | L223: 110.7 | M223: 13777846 | N223: Mon, 15 Dec 2025 00:00:00 GMT | O223: =I223/L223-1 -> -0.001897019 | Q223: -0.033 | R223: 1 | T223: =T224-0.001 -> -0.036 | U223: =_xlfn.NORM.DIST(T223,$S$205,$S$207,FALSE) -> 0.65517648 | X223: =($S$207*1)+$S$205 -> 0.013915534 | Y223: 19
A224: 626.87 | B224: 633.43 | C224: 624.48 | D224: 632.8 | E224: 8504783 | F224: Fri, 12 Dec 2025 00:00:00 GMT | G224: =A224/D224-1 -> -0.0093710493 | I224: 111.6 | J224: 113.34 | K224: 111.15 | L224: 111.73 | M224: 12950047 | N224: Fri, 12 Dec 2025 00:00:00 GMT | O224: =I224/L224-1 -> -0.0011635192 | Q224: -0.032 | R224: 2 | T224: =T225-0.001 -> -0.035 | U224: =_xlfn.NORM.DIST(T224,$S$205,$S$207,FALSE) -> 0.80500466 | W224: 2σ | X224: =($S$207*2)+$S$205 -> 0.027167019 | Y224: 0
A225: 633.71 | B225: 633.87 | C225: 627.27 | D225: 630 | E225: 22128232 | F225: Thu, 11 Dec 2025 00:00:00 GMT | G225: =A225/D225-1 -> 0.0058888889 | I225: 111.46 | J225: 111.56 | K225: 109.11 | L225: 109.2 | M225: 13039648 | N225: Thu, 11 Dec 2025 00:00:00 GMT | O225: =I225/L225-1 -> 0.020695971 | Q225: -0.031 | R225: 0 | T225: =T226-0.001 -> -0.034 | U225: =_xlfn.NORM.DIST(T225,$S$205,$S$207,FALSE) -> 0.98347951 | X225: =($S$207*2)+$S$205 -> 0.027167019 | Y225: 5
A226: 632.16 | B226: 633.505 | C226: 626.47 | D226: 627.63 | E226: 22399235 | F226: Wed, 10 Dec 2025 00:00:00 GMT | G226: =A226/D226-1 -> 0.0072176282 | I226: 108.83 | J226: 109.665 | K226: 106.58 | L226: 107.12 | M226: 10580589 | N226: Wed, 10 Dec 2025 00:00:00 GMT | O226: =I226/L226-1 -> 0.015963406 | Q226: -0.03 | R226: 0 | T226: =T227-0.001 -> -0.033 | U226: =_xlfn.NORM.DIST(T226,$S$205,$S$207,FALSE) -> 1.1947005 | W226: 3σ | X226: =($S$207*3)+$S$205 -> 0.040418503 | Y226: 0
A227: 628.1 | B227: 630.21 | C227: 627.66 | D227: 628.18 | E227: 9617841 | F227: Tue, 09 Dec 2025 00:00:00 GMT | G227: =A227/D227-1 -> -0.00012735203 | I227: 107.02 | J227: 107.745 | K227: 106.55 | L227: 107.59 | M227: 8212769 | N227: Tue, 09 Dec 2025 00:00:00 GMT | O227: =I227/L227-1 -> -0.0052978901 | Q227: -0.029 | R227: 0 | T227: =T228-0.001 -> -0.032 | U227: =_xlfn.NORM.DIST(T227,$S$205,$S$207,FALSE) -> 1.4430442 | X227: =($S$207*3)+$S$205 -> 0.040418503 | Y227: 1
A228: 628.61 | B228: 631.47 | C228: 626.701 | D228: 631.36 | E228: 6833888 | F228: Mon, 08 Dec 2025 00:00:00 GMT | G228: =A228/D228-1 -> -0.0043556766 | I228: 107.63 | J228: 108.045 | K228: 104.83 | L228: 105.3 | M228: 13178635 | N228: Mon, 08 Dec 2025 00:00:00 GMT | O228: =I228/L228-1 -> 0.022127255 | Q228: -0.028 | R228: 3 | T228: =T229-0.001 -> -0.031 | U228: =_xlfn.NORM.DIST(T228,$S$205,$S$207,FALSE) -> 1.7331135
A229: 630.48 | B229: 632.98 | C229: 629.48 | D229: 630.3 | E229: 5007553 | F229: Fri, 05 Dec 2025 00:00:00 GMT | G229: =A229/D229-1 -> 0.0002855783 | I229: 105.3 | J229: 106.17 | K229: 104.56 | L229: 105.18 | M229: 10555238 | N229: Fri, 05 Dec 2025 00:00:00 GMT | O229: =I229/L229-1 -> 0.0011409013 | Q229: -0.027 | R229: 1 | T229: =T230-0.001 -> -0.03 | U229: =_xlfn.NORM.DIST(T229,$S$205,$S$207,FALSE) -> 2.0696706
A230: 629.3 | B230: 630.18 | C230: 626.48 | D230: 630.13 | E230: 5114434 | F230: Thu, 04 Dec 2025 00:00:00 GMT | G230: =A230/D230-1 -> -0.0013171885 | I230: 105.47 | J230: 106.215 | K230: 104.5101 | L230: 105.84 | M230: 11128198 | N230: Thu, 04 Dec 2025 00:00:00 GMT | O230: =I230/L230-1 -> -0.0034958428 | Q230: -0.026 | R230: 7 | T230: =T231-0.001 -> -0.029 | U230: =_xlfn.NORM.DIST(T230,$S$205,$S$207,FALSE) -> 2.4575494
A231: 628.77 | B231: 629.78 | C231: 624.95 | D231: 625.77 | E231: 5149531 | F231: Wed, 03 Dec 2025 00:00:00 GMT | G231: =A231/D231-1 -> 0.0047940937 | I231: 105.74 | J231: 105.85 | K231: 104.47 | L231: 104.9 | M231: 9729053 | N231: Wed, 03 Dec 2025 00:00:00 GMT | O231: =I231/L231-1 -> 0.0080076263 | Q231: -0.025 | R231: 2 | T231: =T232-0.001 -> -0.028 | U231: =_xlfn.NORM.DIST(T231,$S$205,$S$207,FALSE) -> 2.9015504
A232: 626.58 | B232: 628.77 | C232: 624.62 | D232: 627.01 | E232: 5256797 | F232: Tue, 02 Dec 2025 00:00:00 GMT | G232: =A232/D232-1 -> -0.00068579448 | I232: 104.83 | J232: 106.57 | K232: 104.82 | L232: 106.525 | M232: 8460441 | N232: Tue, 02 Dec 2025 00:00:00 GMT | O232: =I232/L232-1 -> -0.015911758 | Q232: -0.024 | R232: 3 | T232: =T233-0.001 -> -0.027 | U232: =_xlfn.NORM.DIST(T232,$S$205,$S$207,FALSE) -> 3.406315
A233: 625.52 | B233: 628.01 | C233: 624.1 | D233: 624.17 | E233: 8381362 | F233: Mon, 01 Dec 2025 00:00:00 GMT | G233: =A233/D233-1 -> 0.0021628723 | I233: 106.77 | J233: 106.83 | K233: 104.47 | L233: 104.92 | M233: 11872100 | N233: Mon, 01 Dec 2025 00:00:00 GMT | O233: =I233/L233-1 -> 0.017632482 | Q233: -0.023 | R233: 3 | T233: =T234-0.001 -> -0.026 | U233: =_xlfn.NORM.DIST(T233,$S$205,$S$207,FALSE) -> 3.9761825
A234: 628.41 | B234: 628.63 | C234: 625.705 | D234: 626.025 | E234: 2949167 | F234: Fri, 28 Nov 2025 00:00:00 GMT | G234: =A234/D234-1 -> 0.003809752 | I234: 104.47 | J234: 104.74 | K234: 103.24 | L234: 103.3 | M234: 6523632 | N234: Fri, 28 Nov 2025 00:00:00 GMT | O234: =I234/L234-1 -> 0.011326234 | Q234: -0.022 | R234: 2 | T234: =T235-0.001 -> -0.025 | U234: =_xlfn.NORM.DIST(T234,$S$205,$S$207,FALSE) -> 4.6150311
A235: 624.95 | B235: 626.81 | C235: 622.26 | D235: 623.06 | E235: 5292533 | F235: Wed, 26 Nov 2025 00:00:00 GMT | G235: =A235/D235-1 -> 0.0030334157 | I235: 103.43 | J235: 104.2509 | K235: 102.88 | L235: 103.315 | M235: 9840581 | N235: Wed, 26 Nov 2025 00:00:00 GMT | O235: =I235/L235-1 -> 0.0011131007 | Q235: -0.021 | R235: 4 | T235: =T236-0.001 -> -0.024 | U235: =_xlfn.NORM.DIST(T235,$S$205,$S$207,FALSE) -> 5.3261057
A236: 620.66 | B236: 621.75 | C236: 610.99 | D236: 614.78 | E236: 7289905 | F236: Tue, 25 Nov 2025 00:00:00 GMT | G236: =A236/D236-1 -> 0.009564397 | I236: 103.31 | J236: 103.915 | K236: 102 | L236: 102.49 | M236: 10509755 | N236: Tue, 25 Nov 2025 00:00:00 GMT | O236: =I236/L236-1 -> 0.0080007806 | Q236: -0.02 | R236: 6 | T236: =T237-0.001 -> -0.023 | U236: =_xlfn.NORM.DIST(T236,$S$205,$S$207,FALSE) -> 6.1118369
A237: 614.94 | B237: 616.09 | C237: 608.305 | D237: 609.28 | E237: 6218559 | F237: Mon, 24 Nov 2025 00:00:00 GMT | G237: =A237/D237-1 -> 0.0092896534 | I237: 101.94 | J237: 104.335 | K237: 101.89 | L237: 104.085 | M237: 14907483 | N237: Mon, 24 Nov 2025 00:00:00 GMT | O237: =I237/L237-1 -> -0.020608157 | Q237: -0.019 | R237: 6 | T237: =T238-0.001 -> -0.022 | U237: =_xlfn.NORM.DIST(T237,$S$205,$S$207,FALSE) -> 6.9736564
A238: 605.93 | B238: 611.01 | C238: 598.38 | D238: 602.25 | E238: 9789866 | F238: Fri, 21 Nov 2025 00:00:00 GMT | G238: =A238/D238-1 -> 0.0061104193 | I238: 104.28 | J238: 104.78 | K238: 102.69 | L238: 103.48 | M238: 10747390 | N238: Fri, 21 Nov 2025 00:00:00 GMT | O238: =I238/L238-1 -> 0.0077309625 | Q238: -0.018 | R238: 3 | T238: =T239-0.001 -> -0.021 | U238: =_xlfn.NORM.DIST(T238,$S$205,$S$207,FALSE) -> 7.9118158
A239: 599.96 | B239: 621.1288 | C239: 599.36 | D239: 618.72 | E239: 13857655 | F239: Thu, 20 Nov 2025 00:00:00 GMT | G239: =A239/D239-1 -> -0.030320662 | I239: 102.7 | J239: 105.8 | K239: 102.5 | L239: 105.37 | M239: 12169947 | N239: Thu, 20 Nov 2025 00:00:00 GMT | O239: =I239/L239-1 -> -0.025339281 | Q239: -0.017 | R239: 9 | T239: =T240-0.001 -> -0.02 | U239: =_xlfn.NORM.DIST(T239,$S$205,$S$207,FALSE) -> 8.9252134
... A258: 622.55 | B258: 623.7899 | C258: 621.207 | D258: 621.92 | E258: 5650844 | F258: Fri, 24 Oct 2025 00:00:00 GMT | G258: =A258/D258-1 -> 0.001012992 | I258: 111.68 | J258: 113.65 | K258: 111.59 | L258: 113.23 | M258: 6225109 | N258: Fri, 24 Oct 2025 00:00:00 GMT | O258: =I258/L258-1 -> -0.013688952 | Q258: 0.002 | R258: 34 | T258: =T259-0.001 -> -0.001 | U258: =_xlfn.NORM.DIST(T258,$S$205,$S$207,FALSE) -> 29.869045
A259: 617.44 | B259: 618.474 | C259: 613.99 | D259: 614.25 | E259: 5825360 | F259: Thu, 23 Oct 2025 00:00:00 GMT | G259: =A259/D259-1 -> 0.0051933252 | I259: 113.03 | J259: 113.83 | K259: 111.9001 | L259: 113.17 | M259: 6930967 | N259: Thu, 23 Oct 2025 00:00:00 GMT | O259: =I259/L259-1 -> -0.001237077 | Q259: 0.003 | R259: 20 | T259: 0 | U259: =_xlfn.NORM.DIST(T259,$S$205,$S$207,FALSE) -> 30.067702
A260: 613.97 | B260: 617.83 | C260: 609.83 | D260: 617.83 | E260: 6119026 | F260: Wed, 22 Oct 2025 00:00:00 GMT | G260: =A260/D260-1 -> -0.0062476733 | I260: 113.08 | J260: 114.28 | K260: 112.98 | L260: 114 | M260: 7017483 | N260: Wed, 22 Oct 2025 00:00:00 GMT | O260: =I260/L260-1 -> -0.0080701754 | Q260: 0.004 | R260: 29 | T260: =T259+0.001 -> 0.001 | U260: =_xlfn.NORM.DIST(T260,$S$205,$S$207,FALSE) -> 30.095804
A261: 617.09 | B261: 618.74 | C261: 615.981 | D261: 617.33 | E261: 4156131 | F261: Tue, 21 Oct 2025 00:00:00 GMT | G261: =A261/D261-1 -> -0.000388771 | I261: 114.3 | J261: 114.5395 | K261: 112.04 | L261: 112.25 | M261: 7873840 | N261: Tue, 21 Oct 2025 00:00:00 GMT | O261: =I261/L261-1 -> 0.018262806 | Q261: 0.005 | R261: 25 | T261: =T260+0.001 -> 0.002 | U261: =_xlfn.NORM.DIST(T261,$S$205,$S$207,FALSE) -> 29.952874
A262: 617.17 | B262: 618.01 | C262: 613.51 | D262: 613.51 | E262: 4049225 | F262: Mon, 20 Oct 2025 00:00:00 GMT | G262: =A262/D262-1 -> 0.0059656729 | I262: 111.96 | J262: 112.25 | K262: 110.6 | L262: 111.03 | M262: 7713377 | N262: Mon, 20 Oct 2025 00:00:00 GMT | O262: =I262/L262-1 -> 0.0083761146 | Q262: 0.006 | R262: 24 | T262: =T261+0.001 -> 0.003 | U262: =_xlfn.NORM.DIST(T262,$S$205,$S$207,FALSE) -> 29.641342
A263: 610.76 | B263: 612.02 | C263: 605.1 | D263: 606.34 | E263: 6884090 | F263: Fri, 17 Oct 2025 00:00:00 GMT | G263: =A263/D263-1 -> 0.0072896395 | I263: 110.67 | J263: 111.46 | K263: 109.44 | L263: 109.74 | M263: 9928744 | N263: Fri, 17 Oct 2025 00:00:00 GMT | O263: =I263/L263-1 -> 0.0084745763 | Q263: 0.007 | R263: 15 | T263: =T262+0.001 -> 0.004 | U263: =_xlfn.NORM.DIST(T263,$S$205,$S$207,FALSE) -> 29.166483
A264: 607.39 | B264: 614.8 | C264: 604.14 | D264: 613.11 | E264: 7533209 | F264: Thu, 16 Oct 2025 00:00:00 GMT | G264: =A264/D264-1 -> -0.0093294841 | I264: 109.88 | J264: 112.085 | K264: 108.51 | L264: 111.79 | M264: 7490291 | N264: Thu, 16 Oct 2025 00:00:00 GMT | O264: =I264/L264-1 -> -0.017085607 | Q264: 0.008 | R264: 27 | T264: =T263+0.001 -> 0.005 | U264: =_xlfn.NORM.DIST(T264,$S$205,$S$207,FALSE) -> 28.536261
A265: 611.43 | B265: 616.205 | C265: 605.82 | D265: 613.07 | E265: 6474986 | F265: Wed, 15 Oct 2025 00:00:00 GMT | G265: =A265/D265-1 -> -0.0026750616 | I265: 111.71 | J265: 112.675 | K265: 111.14 | L265: 111.47 | M265: 6826918 | N265: Wed, 15 Oct 2025 00:00:00 GMT | O265: =I265/L265-1 -> 0.0021530457 | Q265: 0.009 | R265: 19 | T265: =T264+0.001 -> 0.006 | U265: =_xlfn.NORM.DIST(T265,$S$205,$S$207,FALSE) -> 27.761115
A266: 608.75 | B266: 612.14 | C266: 600.51 | D266: 604.2 | E266: 7469018 | F266: Tue, 14 Oct 2025 00:00:00 GMT | G266: =A266/D266-1 -> 0.007530619 | I266: 111.17 | J266: 111.84 | K266: 109.2 | L266: 109.65 | M266: 7846376 | N266: Tue, 14 Oct 2025 00:00:00 GMT | O266: =I266/L266-1 -> 0.013862289 | Q266: 0.01 | R266: 23 | T266: =T265+0.001 -> 0.007 | U266: =_xlfn.NORM.DIST(T266,$S$205,$S$207,FALSE) -> 26.853665
A267: 609.61 | B267: 611.0272 | C267: 606.575 | D267: 607.37 | E267: 6942460 | F267: Mon, 13 Oct 2025 00:00:00 GMT | G267: =A267/D267-1 -> 0.003688032 | I267: 110.27 | J267: 110.96 | K267: 109.38 | L267: 110.39 | M267: 7147641 | N267: Mon, 13 Oct 2025 00:00:00 GMT | O267: =I267/L267-1 -> -0.001087055 | Q267: 0.011 | R267: 16 | T267: =T266+0.001 -> 0.008 | U267: =_xlfn.NORM.DIST(T267,$S$205,$S$207,FALSE) -> 25.828373
A268: 600.51 | B268: 619.6 | C268: 600.23 | D268: 617.99 | E268: 13339202 | F268: Fri, 10 Oct 2025 00:00:00 GMT | G268: =A268/D268-1 -> -0.028285247 | I268: 109.19 | J268: 112.68 | K268: 109.11 | L268: 111.53 | M268: 9454735 | N268: Fri, 10 Oct 2025 00:00:00 GMT | O268: =I268/L268-1 -> -0.020980902 | Q268: 0.012 | R268: 15 | T268: =T267+0.001 -> 0.009 | U268: =_xlfn.NORM.DIST(T268,$S$205,$S$207,FALSE) -> 24.70116
A269: 617.1 | B269: 619.59 | C269: 615.28 | D269: 619.23 | E269: 5879748 | F269: Thu, 09 Oct 2025 00:00:00 GMT | G269: =A269/D269-1 -> -0.0034397558 | I269: 110.99 | J269: 113 | K269: 110.875 | L269: 111.82 | M269: 6366005 | N269: Thu, 09 Oct 2025 00:00:00 GMT | O269: =I269/L269-1 -> -0.0074226435 | Q269: 0.013 | R269: 20 | T269: =T268+0.001 -> 0.01 | U269: =_xlfn.NORM.DIST(T269,$S$205,$S$207,FALSE) -> 23.488997
A270: 618.77 | B270: 618.9 | C270: 615.4642 | D270: 616.215 | E270: 5000436 | F270: Wed, 08 Oct 2025 00:00:00 GMT | G270: =A270/D270-1 -> 0.0041462801 | I270: 111.89 | J270: 113.2 | K270: 111.65 | L270: 112.805 | M270: 7013053 | N270: Wed, 08 Oct 2025 00:00:00 GMT | O270: =I270/L270-1 -> -0.0081113426 | Q270: 0.014 | R270: 12 | T270: =T269+0.001 -> 0.011 | U270: =_xlfn.NORM.DIST(T270,$S$205,$S$207,FALSE) -> 22.209482
A271: 615.2 | B271: 618.7393 | C271: 613.82 | D271: 618.3 | E271: 7439508 | F271: Tue, 07 Oct 2025 00:00:00 GMT | G271: =A271/D271-1 -> -0.0050137474 | I271: 112.53 | J271: 113.4 | K271: 111.8 | L271: 112.63 | M271: 5188949 | N271: Tue, 07 Oct 2025 00:00:00 GMT | O271: =I271/L271-1 -> -0.00088786291 | Q271: 0.015 | R271: 16 | T271: =T270+0.001 -> 0.012 | U271: =_xlfn.NORM.DIST(T271,$S$205,$S$207,FALSE) -> 20.880419
... A298: 596.52 | B298: 597.07 | C298: 593.27 | D298: 595.07 | E298: 5037983 | F298: Thu, 28 Aug 2025 00:00:00 GMT | G298: =A298/D298-1 -> 0.0024366881 | I298: 117.64 | J298: 118.37 | K298: 116.61 | L298: 118.1 | M298: 5666892 | N298: Thu, 28 Aug 2025 00:00:00 GMT | O298: =I298/L298-1 -> -0.0038950042 | Q298: 0.042 | R298: 0 | T298: =T297+0.001 -> 0.039 | U298: =_xlfn.NORM.DIST(T298,$S$205,$S$207,FALSE) -> 0.45845756
A299: 594.42 | B299: 595.14 | C299: 592.44 | D299: 592.52 | E299: 6089564 | F299: Wed, 27 Aug 2025 00:00:00 GMT | G299: =A299/D299-1 -> 0.0032066428 | I299: 118.09 | J299: 118.46 | K299: 117.29 | L299: 117.53 | M299: 4334749 | N299: Wed, 27 Aug 2025 00:00:00 GMT | O299: =I299/L299-1 -> 0.0047647409 | Q299: More | R299: 2 | T299: =T298+0.001 -> 0.04 | U299: =_xlfn.NORM.DIST(T299,$S$205,$S$207,FALSE) -> 0.36749459
A300: 593.06 | B300: 593.43 | C300: 589.795 | D300: 590.38 | E300: 4746851 | F300: Tue, 26 Aug 2025 00:00:00 GMT | G300: =A300/D300-1 -> 0.0045394492 | I300: 117.65 | J300: 118.375 | K300: 117.16 | L300: 117.43 | M300: 5778483 | N300: Tue, 26 Aug 2025 00:00:00 GMT | O300: =I300/L300-1 -> 0.0018734565 | T300: =T299+0.001 -> 0.041 | U300: =_xlfn.NORM.DIST(T300,$S$205,$S$207,FALSE) -> 0.29290689
A301: 590.7 | B301: 593.2299 | C301: 590.55 | D301: 592.05 | E301: 6483035 | F301: Mon, 25 Aug 2025 00:00:00 GMT | G301: =A301/D301-1 -> -0.0022802128 | I301: 117.71 | J301: 119.05 | K301: 117.7 | L301: 118.49 | M301: 5424937 | N301: Mon, 25 Aug 2025 00:00:00 GMT | O301: =I301/L301-1 -> -0.006582834 | T301: =T300+0.001 -> 0.042 | U301: =_xlfn.NORM.DIST(T301,$S$205,$S$207,FALSE) -> 0.23213202
A302: 593.21 | B302: 594.32 | C302: 585.84 | D302: 586.27 | E302: 6368542 | F302: Fri, 22 Aug 2025 00:00:00 GMT | G302: =A302/D302-1 -> 0.011837549 | I302: 118.86 | J302: 119.775 | K302: 117.125 | L302: 117.585 | M302: 7046502 | N302: Fri, 22 Aug 2025 00:00:00 GMT | O302: =I302/L302-1 -> 0.01084322 | T302: =T301+0.001 -> 0.043 | U302: =_xlfn.NORM.DIST(T302,$S$205,$S$207,FALSE) -> 0.18292259
A303: 584.27 | B303: 586.46 | C303: 582.65 | D303: 584.93 | E303: 4807277 | F303: Thu, 21 Aug 2025 00:00:00 GMT | G303: =A303/D303-1 -> -0.0011283401 | I303: 116.21 | J303: 116.66 | K303: 115.53 | L303: 116.57 | M303: 6337059 | N303: Thu, 21 Aug 2025 00:00:00 GMT | O303: =I303/L303-1 -> -0.0030882731 | T303: =T302+0.001 -> 0.044 | U303: =_xlfn.NORM.DIST(T303,$S$205,$S$207,FALSE) -> 0.14332648
A304: 586.58 | B304: 588 | C304: 581.85 | D304: 587.81 | E304: 7054266 | F304: Wed, 20 Aug 2025 00:00:00 GMT | G304: =A304/D304-1 -> -0.0020925129 | I304: 117.04 | J304: 117.89 | K304: 116 | L304: 116.075 | M304: 6789629 | N304: Wed, 20 Aug 2025 00:00:00 GMT | O304: =I304/L304-1 -> 0.0083135904 | T304: =T303+0.001 -> 0.045 | U304: =_xlfn.NORM.DIST(T304,$S$205,$S$207,FALSE) -> 0.11166379
...

Sheet Product Lines

Sheet Management

Sheet Table Formatting
B2: [Bold Title] | G2: [Bold Title]
B3: Line Titles | G3: <-- General
B4: Line Titles | G4: <-- Info
B5: Line Titles | G5: <-- General
B6: Line Titles | G6: <-- Info
B7: Line Titles | G7: <-- General
B8: Line Titles | G8: <-- Info
