Workbook

Sheet Main
A1: Master
B2: DXCM
B3: Price | C3: 78.3 | D3: 9/21/2026
B4: SO | C4: 382.2 | D4: Q2'26
B5: MC | C5: =C3*C4 -> 29926.26
B6: Cash | C6: =1105+842 -> 1947 | D6: Q2'26
B7: Debt | C7: =82.6 -> 82.6 | D7: Q2'26
B8: EV | C8: =C5-C6+C7 -> 28061.86
B10: DexCom, Inc. (DXCM)
B12: Founder(s): Scott Glenn, John Burd, Lauren Otsuki, Ellen Preston, and Bret Megargel | M12: Resources:
B13: Founded: 1999 | M13: SEC filings | P13: https://www.sec.gov/edgar/browse/?CIK=310764&owner=exclude
B14: Headquarters: San Diego, CA | F14: Registered Exchange: NASDAQ | M14: Company Homepage | P14: dexcom.com/en-us
B15: Current CEO: Kevin Sayer | F15: Address: 6340 Sequence Drive San Diego, CA 92121 U.S. | N15: Company IR Page | Q15: https://investors.dexcom.com/overview/default.aspx
B16: Employees: 10,300 | F16: Investor Relations Contact: | M16: Earnings Calls | P16: https://seekingalpha.com/symbol/DXCM/earnings/transcripts
B17: Industry: CGMS - Medical Devices | F17: Investors Relation Department | M17: Equity Analysis | P17: https://stockanalysis.com/stocks/dxcm/company/
B18: Sector: Healthcare | F18: Phone: | G18: (858) 410-1560 | I18: Email: | J18: IR@dexcom.com | M18: MacroTrends | P18: https://www.macrotrends.net/stocks/charts/DXCM/dexcom/cash-flow-statement?freq=Q
B19: IPO: Apr 14, 2005 | M19: ROIC, WACC | P19: https://www.gurufocus.com/term/wacc/DXCM
B20: Fiscal Year: [January - December] | M20: Godel Terminal | P20: https://app.godelterminal.com/
A22: Company Overview:
B23: DexCom, Inc., a medical device company, focuses on the design, development, and commercialization of continuous glucose monitoring (CGM) systems in the United States and internationally
B24: The Company provides its systems for the management of diabetes and metabolic health by patients, caregivers, and clinicians
B25: Its products include:
C26: Dexcom G6 and Dexcom G7, integrated CGM systems for diabetes management
C27: Dexcom Share, a remote monitoring system; Dexcom Real-Time API, which enables authorized third-party software developers to integrate real-time CGM data into their digital health apps and devices
C28: Dexcom ONE, that is designed to replace finger stick blood glucose testing for diabetes treatment decisions
C29: Stelo, a new over-the-counter glucose biosensor designed for adults with prediabetes and Type 2 diabetes
D30: Stelo is a new offering put out by Dexcom and Oura, fitting into the Oura ring software ecosystem
D31: Stelo is an over-the-counter (OTC) continuous glucose monitor (iCGM)—the first in its class FDA-cleared for adults (18+) not on insulin, available without a prescription
D32: Designed for the wellness, prediabetic, and health-optimization population—not intended for diabetics on insulin or those with problematic hypoglycemia … Health nut target
B33: The Company has a collaboration and license agreement with Verily Life Sciences LLC and Verily Ireland Limited to develop blood-based or interstitial glucose monitoring products
C34: Verily Life Sciences LLC is a subsidiary of Alphabet (GOOG) which operates in the wider healthcare market
B35: It markets its products directly to endocrinologists, physicians, and diabetes educators
B36: The Company was incorporated in 1999 and is headquartered in San Diego, California
A38: Business Segments and Geographical Info:

Sheet Model
B1: [Use for Graphing] | AM1: Q1 2020 | AQ1: Q1 2021 | AU1: Q1 2022 | AY1: Q1 2023 | BC1: Q1 2024 | BG1: Q1 2025 | BK1: Q1 2026
B2: Quarterly
B3: Revenues | C3: {="Q"&MOD(_xlfn.SEQUENCE(1,64)-1,4)+1&" "&(2011+INT((_xlfn.SEQUENCE(1,64)-1)/4))} -> Q1 2011 | D3: Q2 2011 | E3: Q3 2011 | F3: Q4 2011 | G3: Q1 2012 | H3: Q2 2012 | I3: Q3 2012 | J3: Q4 2012 | K3: Q1 2013 | L3: Q2 2013 | M3: Q3 2013 | N3: Q4 2013 | O3: Q1 2014 | P3: Q2 2014 | Q3: Q3 2014 | R3: Q4 2014 | S3: Q1 2015 | T3: Q2 2015 | U3: Q3 2015 | V3: Q4 2015 | W3: Q1 2016 | X3: Q2 2016 | Y3: Q3 2016 | Z3: Q4 2016 | AA3: Q1 2017 | AB3: Q2 2017 | AC3: Q3 2017 | AD3: Q4 2017 | AE3: Q1 2018 | AF3: Q2 2018 | AG3: Q3 2018 | AH3: Q4 2018 | AI3: Q1 2019 | AJ3: Q2 2019 | AK3: Q3 2019 | AL3: Q4 2019 | AM3: Q1 2020 | AN3: Q2 2020 | AO3: Q3 2020 | AP3: Q4 2020 | AQ3: Q1 2021 | AR3: Q2 2021 | AS3: Q3 2021 | AT3: Q4 2021 | AU3: Q1 2022 | AV3: Q2 2022 | AW3: Q3 2022 | AX3: Q4 2022 | AY3: Q1 2023 | AZ3: Q2 2023 | BA3: Q3 2023 | BB3: Q4 2023 | BC3: Q1 2024 | BD3: Q2 2024 | BE3: Q3 2024 | BF3: Q4 2024 | BG3: Q1 2025 | BH3: Q2 2025 | BI3: Q3 2025 | BJ3: Q4 2025 | BK3: Q1 2026 | BL3: Q2 2026 | BM3: Q3 2026 | BN3: Q4 2026 | BS3: 2011 | BT3: =BS3+1 -> 2012 | BU3: =BT3+1 -> 2013 | BV3: =BU3+1 -> 2014 | BW3: =BV3+1 -> 2015 | BX3: =BW3+1 -> 2016 | BY3: =BX3+1 -> 2017 | BZ3: =BY3+1 -> 2018 | CA3: =BZ3+1 -> 2019 | ... EO3: =EN3+1 -> 2085
B4: Distributor Revenues | AM4: 286.1 | AN4: 331.7 | AO4: 382.4 | AP4: =1437.6-SUM(AM4:AO4) -> 437.4 | AQ4: 390.7 | AR4: 495.9 | AS4: 552.3 | AT4: =1849.4-SUM(AQ4:AS4) -> 410.5 | AU4: 527.1 | AV4: 585.1 | AW4: 656.2 | AX4: =2470.8-SUM(AU4:AW4) -> 702.4 | AY4: 618.9 | AZ4: 738.8 | BA4: 713.6 | BB4: =3095.6-SUM(AY4:BA4) -> 1024.3 | BC4: 778.8 | BD4: 860.1 | BE4: 843.3 | BF4: =3430.1-SUM(BC4:BE4) -> 947.9 | BG4: 880 | BH4: 977.8 | BI4: 1026 | BJ4: =3959-SUM(BG4:BI4) -> 1075.2 | BK4: 1010.3 | BL4: 1102.4 | CB4: =SUM(AM4:AP4) -> 1437.6 | CC4: =SUM(AQ4:AT4) -> 1849.4 | CD4: =SUM(AU4:AX4) -> 2470.8 | CE4: =SUM(AY4:BB4) -> 3095.6 | CF4: =SUM(BC4:BF4) -> 3430.1 | CG4: =SUM(BG4:BJ4) -> 3959 | CH4: =CG4*(1+CH8) -> 4501.383 | CI4: =CH4*(1+CI8) -> 5145.0808 | CJ4: =CI4*(1+CJ8) -> 5865.3921 | CK4: =CJ4*(1+CK8) -> 6657.22 | CL4: =CK4*(1+CL8) -> 7509.3442 | CM4: =CL4*(1+CM8) -> 8410.4655 | CN4: =CM4*(1+CN8) -> 9377.669 | CO4: =CN4*(1+CO8) -> 10409.213 | ... CQ4: =CP4*(1+CQ8) -> 12652.398
B5: Direct Revenues | AM5: 119 | AN5: 120.1 | AO5: 118.5 | AP5: =489.1-SUM(AM5:AO5) -> 131.5 | AQ5: 114.3 | AR5: 99.2 | AS5: 97.9 | AT5: =599.1-SUM(AQ5:AS5) -> 287.7 | AU5: 101.7 | AV5: 111.1 | AW5: 113.4 | AX5: =439-SUM(AU5:AW5) -> 112.8 | AY5: 122.6 | AZ5: 132.5 | BA5: 261.4 | BB5: =526.7-SUM(AY5:BA5) -> 10.2 | BC5: 142.5 | BD5: 144.2 | BE5: 150.9 | BF5: =602.9-SUM(BC5:BE5) -> 165.3 | BG5: 156 | BH5: 179.3 | BI5: 183.3 | BJ5: =703-SUM(BG5:BI5) -> 184.4 | BK5: 181.6 | BL5: 206 | CB5: =SUM(AM5:AP5) -> 489.1 | CC5: =SUM(AQ5:AT5) -> 599.1 | CD5: =SUM(AU5:AX5) -> 439 | CE5: =SUM(AY5:BB5) -> 526.7 | CF5: =SUM(BC5:BF5) -> 602.9 | CG5: =SUM(BG5:BJ5) -> 703 | CH5: =CG5*(1+CH9) -> 811.965 | CI5: =CH5*(1+CI9) -> 932.13582 | CJ5: =CI5*(1+CJ9) -> 1053.3135 | CK5: =CJ5*(1+CK9) -> 1174.4445 | CL5: =CK5*(1+CL9) -> 1303.6334 | CM5: =CL5*(1+CM9) -> 1440.5149 | CN5: =CM5*(1+CN9) -> 1588.1677 | CO5: =CN5*(1+CO9) -> 1746.9845 | ... CQ5: =CP5*(1+CQ9) -> 2085.1133
B6: Ttl Revenues | AM6: =SUM(AM4:AM5) -> 405.1 | AN6: =SUM(AN4:AN5) -> 451.8 | AO6: =SUM(AO4:AO5) -> 500.9 | AP6: =SUM(AP4:AP5) -> 568.9 | AQ6: =SUM(AQ4:AQ5) -> 505 | AR6: =SUM(AR4:AR5) -> 595.1 | AS6: =SUM(AS4:AS5) -> 650.2 | AT6: =SUM(AT4:AT5) -> 698.2 | ... BL6: =SUM(BL4:BL5) -> 1308.4 | CB6: =SUM(AM6:AP6) -> 1926.7 | CC6: =SUM(AQ6:AT6) -> 2448.5 | CD6: =SUM(AU6:AX6) -> 2909.8 | CE6: =SUM(AY6:BB6) -> 3622.3 | CF6: =SUM(BC6:BF6) -> 4033 | CG6: =SUM(BG6:BJ6) -> 4662 | CH6: =SUM(CH4:CH5) -> 5313.348 | CI6: =SUM(CI4:CI5) -> 6077.2166 | CJ6: =SUM(CJ4:CJ5) -> 6918.7056 | CK6: =SUM(CK4:CK5) -> 7831.6645 | CL6: =SUM(CL4:CL5) -> 8812.9776 | CM6: =SUM(CM4:CM5) -> 9850.9804 | CN6: =SUM(CN4:CN5) -> 10965.837 | CO6: =SUM(CO4:CO5) -> 12156.197 | ... CQ6: =SUM(CQ4:CQ5) -> 14737.511
B8: Distributor Revenue Growth Y/y | AQ8: =AQ4/AM4-1 -> 0.36560643 | AR8: =AR4/AN4-1 -> 0.49502563 | AS8: =AS4/AO4-1 -> 0.44429916 | AT8: =AT4/AP4-1 -> -0.061499771 | AU8: =AU4/AQ4-1 -> 0.34911697 | AV8: =AV4/AR4-1 -> 0.17987497 | AW8: =AW4/AS4-1 -> 0.1881224 | AX8: =AX4/AT4-1 -> 0.71108404 | ... BL8: =BL4/BH4-1 -> 0.12742892 | CC8: =CC4/CB4-1 -> 0.28644964 | CD8: =CD4/CC4-1 -> 0.33600087 | CE8: =CE4/CD4-1 -> 0.25287356 | CF8: =CF4/CE4-1 -> 0.1080566 | CG8: =CG4/CF4-1 -> 0.15419376 | CH8: 0.137 | CI8: 0.143 | CJ8: 0.14 | CK8: 0.135 | CL8: 0.128 | CM8: 0.12 | CN8: 0.115 | CO8: 0.11 | CP8: 0.105 | CQ8: 0.1
B9: Direct Revenue Growth Y/y | AQ9: =AQ5/AM5-1 -> -0.039495798 | AR9: =AR5/AN5-1 -> -0.17402165 | AS9: =AS5/AO5-1 -> -0.17383966 | AT9: =AT5/AP5-1 -> 1.1878327 | AU9: =AU5/AQ5-1 -> -0.11023622 | AV9: =AV5/AR5-1 -> 0.11995968 | AW9: =AW5/AS5-1 -> 0.15832482 | AX9: =AX5/AT5-1 -> -0.60792492 | ... BL9: =BL5/BH5-1 -> 0.14891244 | CC9: =CC5/CB5-1 -> 0.22490288 | CD9: =CD5/CC5-1 -> -0.26723418 | CE9: =CE5/CD5-1 -> 0.19977221 | CF9: =CF5/CE5-1 -> 0.14467439 | CG9: =CG5/CF5-1 -> 0.16603085 | CH9: 0.155 | CI9: 0.148 | CJ9: 0.13 | CK9: 0.115 | CL9: 0.11 | CM9: 0.105 | CN9: 0.1025 | CO9: 0.1 | CP9: 0.095 | CQ9: 0.09
B10: Ttl Revenue Growth Y/y | G10: =G26/C26-1 -> 0.41549296 | H10: =H26/D26-1 -> 0.093457944 | I10: =I26/E26-1 -> 0.26229508 | J10: =J26/F26-1 -> 0.48 | K10: =K26/G26-1 -> 0.47263682 | L10: =L26/H26-1 -> 0.52991453 | M10: =M26/I26-1 -> 0.85714286 | N10: =N26/J26-1 -> 0.55255255 | ... AP10: =AP26/AL26-1 -> 0.2292567 | AQ10: =AQ6/AM6-1 -> 0.24660578 | AR10: =AR6/AN6-1 -> 0.31717574 | AS10: =AS6/AO6-1 -> 0.29806349 | AT10: =AT6/AP6-1 -> 0.22728072 | AU10: =AU6/AQ6-1 -> 0.24514851 | AV10: =AV6/AR6-1 -> 0.16988741 | AW10: =AW6/AS6-1 -> 0.1836358 | AX10: =AX6/AT6-1 -> 0.16757376 | ... BL10: =BL6/BH6-1 -> 0.13075793 | BT10: =BT26/BS26-1 -> 0.30759162 | BU10: =BU26/BT26-1 -> 0.6016016 | BV10: =BV26/BU26-1 -> 0.62 | BW10: =BW26/BV26-1 -> 0.55092593 | BX10: =BX26/BW26-1 -> 0.4261194 | BY10: =BY26/BX26-1 -> 0.25327054 | BZ10: =BZ26/BY26-1 -> 0.43576896 | CA10: =CA26/BZ26-1 -> 0.43078713 | CB10: =CB26/CA26-1 -> 0.3053523 | CC10: =CC6/CB6-1 -> 0.27082576 | CD10: =CD6/CC6-1 -> 0.18840106 | CE10: =CE6/CD6-1 -> 0.24486219 | CF10: =CF6/CE6-1 -> 0.113381 | CG10: =CG6/CF6-1 -> 0.1559633 | CH10: =CH6/CG6-1 -> 0.13971429 | CI10: =CI6/CH6-1 -> 0.14376408 | CJ10: =CJ6/CI6-1 -> 0.13846618 | ... CQ10: =CQ6/CP6-1 -> 0.098574037
B12: Distributor % of Ttl Revenues | AM12: =AM4/AM6 -> 0.70624537 | AN12: =AN4/AN6 -> 0.73417441 | AO12: =AO4/AO6 -> 0.76342583 | AP12: =AP4/AP6 -> 0.76885217 | AQ12: =AQ4/AQ6 -> 0.77366337 | AR12: =AR4/AR6 -> 0.83330533 | AS12: =AS4/AS6 -> 0.84943094 | AT12: =AT4/AT6 -> 0.58794042 | ... BL12: =BL4/BL6 -> 0.84255579 | CB12: =CB4/CB6 -> 0.74614626 | CC12: =CC4/CC6 -> 0.75531958 | CD12: =CD4/CD6 -> 0.84913052 | CE12: =CE4/CE6 -> 0.85459515 | CF12: =CF4/CF6 -> 0.85050831 | CG12: =CG4/CG6 -> 0.84920635 | CH12: =CH4/CH6 -> 0.84718392 | CI12: =CI4/CI6 -> 0.84661797 | ... CQ12: =CQ4/CQ6 -> 0.85851659
B13: Direct % of Ttl Revenues | AM13: =AM5/AM6 -> 0.29375463 | AN13: =AN5/AN6 -> 0.26582559 | AO13: =AO5/AO6 -> 0.23657417 | AP13: =AP5/AP6 -> 0.23114783 | AQ13: =AQ5/AQ6 -> 0.22633663 | AR13: =AR5/AR6 -> 0.16669467 | AS13: =AS5/AS6 -> 0.15056906 | AT13: =AT5/AT6 -> 0.41205958 | ... BL13: =BL5/BL6 -> 0.15744421 | CB13: =CB5/CB6 -> 0.25385374 | CC13: =CC5/CC6 -> 0.24468042 | CD13: =CD5/CD6 -> 0.15086948 | CE13: =CE5/CE6 -> 0.14540485 | CF13: =CF5/CF6 -> 0.14949169 | CG13: =CG5/CG6 -> 0.15079365 | CH13: =CH5/CH6 -> 0.15281608 | CI13: =CI5/CI6 -> 0.15338203 | ... CQ13: =CQ5/CQ6 -> 0.14148341
B15: U.S. Revenues | AM15: 292.3 | AN15: 367.1 | AO15: 398.6 | AP15: =1509.5-SUM(AM15:AO15) -> 451.5 | AQ15: 381.2 | AR15: 461.5 | AS15: 489.6 | AT15: =2024.3-SUM(AQ15:AS15) -> 692 | AU15: 451.2 | AV15: 511 | AW15: 573.4 | AX15: =2142-SUM(AU15:AW15) -> 606.4 | AY15: 526 | AZ15: 616.6 | BA15: 713.6 | BB15: =2625.3-SUM(AY15:BA15) -> 769.1 | BC15: 653.2 | BD15: 731.9 | BE15: 701.9 | BF15: =2889.8-SUM(BC15:BE15) -> 802.8 | BG15: 750.5 | BH15: 841 | BI15: 851.9 | BJ15: =3334.9-SUM(BG15:BI15) -> 891.5 | BK15: 832.3 | BL15: 933.4 | CB15: =SUM(AM15:AP15) -> 1509.5 | CC15: =SUM(AQ15:AT15) -> 2024.3 | CD15: =SUM(AU15:AX15) -> 2142 | CE15: =SUM(AY15:BB15) -> 2625.3 | CF15: =SUM(BC15:BF15) -> 2889.8 | CG15: =SUM(BG15:BJ15) -> 3334.9
B16: Intl. Revenues | AM16: 112.8 | AN16: 84.7 | AO16: 102.3 | AP16: =417.2-SUM(AM16:AO16) -> 117.4 | AQ16: 123.8 | AR16: 133.6 | AS16: 160.6 | AT16: =424.2-SUM(AQ16:AS16) -> 6.2 | AU16: 177.6 | AV16: 185.2 | AW16: 196.2 | AX16: =767.8-SUM(AU16:AW16) -> 208.8 | AY16: 215.5 | AZ16: 254.7 | BA16: 261.4 | BB16: =997-SUM(AY16:BA16) -> 265.4 | BC16: 267.8 | BD16: 272.4 | BE16: 292.3 | BF16: =1143.2-SUM(BC16:BE16) -> 310.7 | BG16: 285.5 | BH16: 316.1 | BI16: 357.4 | BJ16: =1327.1-SUM(BG16:BI16) -> 368.1 | BK16: 359.6 | BL16: 375 | CB16: =SUM(AM16:AP16) -> 417.2 | CC16: =SUM(AQ16:AT16) -> 424.2 | CD16: =SUM(AU16:AX16) -> 767.8 | CE16: =SUM(AY16:BB16) -> 997 | CF16: =SUM(BC16:BF16) -> 1143.2 | CG16: =SUM(BG16:BJ16) -> 1327.1
B17: Ttl Revenues | AM17: =SUM(AM15:AM16) -> 405.1 | AN17: =SUM(AN15:AN16) -> 451.8 | AO17: =SUM(AO15:AO16) -> 500.9 | AP17: =SUM(AP15:AP16) -> 568.9 | AQ17: =SUM(AQ15:AQ16) -> 505 | AR17: =SUM(AR15:AR16) -> 595.1 | AS17: =SUM(AS15:AS16) -> 650.2 | AT17: =SUM(AT15:AT16) -> 698.2 | ... BL17: =SUM(BL15:BL16) -> 1308.4 | CB17: =SUM(AM17:AP17) -> 1926.7 | CC17: =SUM(AQ17:AT17) -> 2448.5 | CD17: =SUM(AU17:AX17) -> 2909.8 | CE17: =SUM(AY17:BB17) -> 3622.3 | CF17: =SUM(BC17:BF17) -> 4033 | CG17: =SUM(BG17:BJ17) -> 4662
B19: U.S. Revenue Growth Y/y | AQ19: =AQ15/AM15-1 -> 0.30413958 | AR19: =AR15/AN15-1 -> 0.25715064 | AS19: =AS15/AO15-1 -> 0.22829905 | AT19: =AT15/AP15-1 -> 0.53266888 | AU19: =AU15/AQ15-1 -> 0.18363064 | AV19: =AV15/AR15-1 -> 0.10725894 | AW19: =AW15/AS15-1 -> 0.17116013 | AX19: =AX15/AT15-1 -> -0.12369942 | ... BL19: =BL15/BH15-1 -> 0.1098692 | CC19: =CC15/CB15-1 -> 0.34104008 | CD19: =CD15/CC15-1 -> 0.058143556 | CE19: =CE15/CD15-1 -> 0.22563025 | CF19: =CF15/CE15-1 -> 0.10075039 | CG19: =CG15/CF15-1 -> 0.1540245
B20: Intl. Revenue Growth Y/y | AQ20: =AQ16/AM16-1 -> 0.09751773 | AR20: =AR16/AN16-1 -> 0.57733176 | AS20: =AS16/AO16-1 -> 0.56989247 | AT20: =AT16/AP16-1 -> -0.9471891 | AU20: =AU16/AQ16-1 -> 0.43457189 | AV20: =AV16/AR16-1 -> 0.38622754 | AW20: =AW16/AS16-1 -> 0.22166874 | AX20: =AX16/AT16-1 -> 32.677419 | ... BL20: =BL16/BH16-1 -> 0.18633344 | CC20: =CC16/CB16-1 -> 0.016778523 | CD20: =CD16/CC16-1 -> 0.80999529 | CE20: =CE16/CD16-1 -> 0.29851524 | CF20: =CF16/CE16-1 -> 0.14663992 | CG20: =CG16/CF16-1 -> 0.16086424
B21: Ttl Revenue Growth Y/y | AQ21: =AQ17/AM17-1 -> 0.24660578 | AR21: =AR17/AN17-1 -> 0.31717574 | AS21: =AS17/AO17-1 -> 0.29806349 | AT21: =AT17/AP17-1 -> 0.22728072 | AU21: =AU17/AQ17-1 -> 0.24514851 | AV21: =AV17/AR17-1 -> 0.16988741 | AW21: =AW17/AS17-1 -> 0.1836358 | AX21: =AX17/AT17-1 -> 0.16757376 | ... BL21: =BL17/BH17-1 -> 0.13075793 | CC21: =CC17/CB17-1 -> 0.27082576 | CD21: =CD17/CC17-1 -> 0.18840106 | CE21: =CE17/CD17-1 -> 0.24486219 | CF21: =CF17/CE17-1 -> 0.113381 | CG21: =CG17/CF17-1 -> 0.1559633
B23: U.S. % of Revenues | AM23: =AM15/AM17 -> 0.72155023 | AN23: =AN15/AN17 -> 0.81252767 | AO23: =AO15/AO17 -> 0.79576762 | AP23: =AP15/AP17 -> 0.79363684 | AQ23: =AQ15/AQ17 -> 0.75485149 | AR23: =AR15/AR17 -> 0.77549992 | AS23: =AS15/AS17 -> 0.75299908 | AT23: =AT15/AT17 -> 0.99112002 | ... BL23: =BL15/BL17 -> 0.7133904 | CB23: =CB15/CB17 -> 0.78346395 | CC23: =CC15/CC17 -> 0.82675107 | CD23: =CD15/CD17 -> 0.73613307 | CE23: =CE15/CE17 -> 0.72476051 | CF23: =CF15/CF17 -> 0.71653856 | CG23: =CG15/CG17 -> 0.71533677
B24: Intl. % of Revenues | AM24: =AM16/AM17 -> 0.27844977 | AN24: =AN16/AN17 -> 0.18747233 | AO24: =AO16/AO17 -> 0.20423238 | AP24: =AP16/AP17 -> 0.20636316 | AQ24: =AQ16/AQ17 -> 0.24514851 | AR24: =AR16/AR17 -> 0.22450008 | AS24: =AS16/AS17 -> 0.24700092 | AT24: =AT16/AT17 -> 0.0088799771 | ... BL24: =BL16/BL17 -> 0.2866096 | CB24: =CB16/CB17 -> 0.21653605 | CC24: =CC16/CC17 -> 0.17324893 | CD24: =CD16/CD17 -> 0.26386693 | CE24: =CE16/CE17 -> 0.27523949 | CF24: =CF16/CF17 -> 0.28346144 | CG24: =CG16/CG17 -> 0.28466323
B26: Revenues | C26: 14.2 | D26: 21.4 | E26: 18.3 | F26: 22.5 | G26: 20.1 | H26: 23.4 | I26: 23.1 | J26: 33.3 | K26: 29.6 | L26: 35.8 | M26: 42.9 | N26: 51.7 | O26: 47.1 | P26: 58.8 | Q26: 69 | R26: 84.3 | S26: 72.8 | T26: 93.2 | U26: 105.2 | V26: 130.8 | W26: 116.2 | X26: 137.3 | Y26: 148.6 | Z26: 171.2 | AA26: 142.3 | AB26: 170.6 | AC26: 184.6 | AD26: 221 | AE26: 184.4 | AF26: 242.5 | AG26: 266.7 | AH26: 338 | AI26: 280.5 | AJ26: 336.4 | AK26: 396.3 | AL26: 462.8 | AM26: =AM6 -> 405.1 | AN26: =AN6 -> 451.8 | AO26: =AO6 -> 500.9 | AP26: =AP6 -> 568.9 | AQ26: =AQ6 -> 505 | AR26: =AR6 -> 595.1 | AS26: =AS6 -> 650.2 | AT26: =AT6 -> 698.2 | ... BL26: =BL6 -> 1308.4 | BS26: =SUM(C26:F26) -> 76.4 | BT26: =SUM(G26:J26) -> 99.9 | BU26: =SUM(K26:N26) -> 160 | BV26: =SUM(O26:R26) -> 259.2 | BW26: =SUM(S26:V26) -> 402 | BX26: =SUM(W26:Z26) -> 573.3 | BY26: =SUM(AA26:AD26) -> 718.5 | BZ26: =SUM(AE26:AH26) -> 1031.6 | CA26: =SUM(AI26:AL26) -> 1476 | CB26: =SUM(AM26:AP26) -> 1926.7 | CC26: =SUM(AQ26:AT26) -> 2448.5 | CD26: =SUM(AU26:AX26) -> 2909.8 | CE26: =SUM(AY26:BB26) -> 3622.3 | CF26: =SUM(BC26:BF26) -> 4033 | CG26: =SUM(BG26:BJ26) -> 4662 | CH26: =CH6 -> 5313.348 | CI26: =CI6 -> 6077.2166 | CJ26: =CJ6 -> 6918.7056 | CK26: =CK6 -> 7831.6645 | CL26: =CL6 -> 8812.9776 | CM26: =CM6 -> 9850.9804 | CN26: =CN6 -> 10965.837 | CO26: =CO6 -> 12156.197 | ... CQ26: =CQ6 -> 14737.511
B27: COGS | C27: 9.1 | D27: 9.5 | E27: 10.1 | F27: 11.7 | G27: 10.7 | H27: 12.2 | I27: 14.7 | J27: 15.7 | K27: 13.1 | L27: 13.9 | M27: 15.3 | N27: 17.6 | O27: 17.3 | P27: 18.9 | Q27: 21.8 | R27: 24.9 | S27: 26.3 | T27: 27.2 | U27: 30.5 | V27: 39.6 | W27: 41.1 | X27: 51.8 | Y27: 47.5 | Z27: 54.5 | AA27: 48.2 | AB27: 53.1 | AC27: 57.6 | AD27: 67.5 | AE27: 65.5 | AF27: 88.9 | AG27: 98.1 | AH27: 115.2 | AI27: 111.7 | AJ27: 129.9 | AK27: 149.4 | AL27: 153.5 | AM27: 148.6 | AN27: 167.7 | AO27: 160.5 | AP27: 169.8 | AQ27: 161.1 | AR27: 178 | AS27: 203.3 | AT27: 225.6 | AU27: 230.7 | AV27: 246.7 | AW27: 275.4 | AX27: 273.9 | AY27: 278.9 | AZ27: 324.9 | BA27: 351.7 | BB27: 377.9 | BC27: 359.1 | BD27: 377.6 | BE27: 400.4 | BF27: 457.7 | BG27: 447 | BH27: 468.3 | BI27: 477.9 | BJ27: =1860.1-SUM(BG27:BI27) -> 466.9 | BK27: 441.6 | BL27: 478.4 | BS27: =SUM(C27:F27) -> 40.4 | BT27: =SUM(G27:J27) -> 53.3 | BU27: =SUM(K27:N27) -> 59.9 | BV27: =SUM(O27:R27) -> 82.9 | BW27: =SUM(S27:V27) -> 123.6 | BX27: =SUM(W27:Z27) -> 194.9 | BY27: =SUM(AA27:AD27) -> 226.4 | BZ27: =SUM(AE27:AH27) -> 367.7 | CA27: =SUM(AI27:AL27) -> 544.5 | CB27: =SUM(AM27:AP27) -> 646.6 | CC27: =SUM(AQ27:AT27) -> 768 | CD27: =SUM(AU27:AX27) -> 1026.7 | CE27: =SUM(AY27:BB27) -> 1333.4 | CF27: =SUM(BC27:BF27) -> 1594.8 | CG27: =SUM(BG27:BJ27) -> 1860.1 | CH27: =CH26*(1-CH39) -> 1992.5055 | CI27: =CI26*(1-CI39) -> 2263.7632 | CJ27: =CJ26*(1-CJ39) -> 2546.0836 | CK27: =CK26*(1-CK39) -> 2858.5576 | CL27: =CL26*(1-CL39) -> 3172.6719 | CM27: =CM26*(1-CM39) -> 3447.8431 | CN27: =CN26*(1-CN39) -> 3783.2137 | CO27: =CO26*(1-CO39) -> 4133.107 | ... CQ27: =CQ26*(1-CQ39) -> 4863.3787
B28: GP | C28: =C26-C27 -> 5.1 | D28: =D26-D27 -> 11.9 | E28: =E26-E27 -> 8.2 | F28: =F26-F27 -> 10.8 | G28: =G26-G27 -> 9.4 | H28: =H26-H27 -> 11.2 | I28: =I26-I27 -> 8.4 | J28: =J26-J27 -> 17.6 | ... BL28: =BL26-BL27 -> 830 | BS28: =SUM(C28:F28) -> 36 | BT28: =SUM(G28:J28) -> 46.6 | BU28: =SUM(K28:N28) -> 100.1 | BV28: =SUM(O28:R28) -> 176.3 | BW28: =SUM(S28:V28) -> 278.4 | BX28: =SUM(W28:Z28) -> 378.4 | BY28: =SUM(AA28:AD28) -> 492.1 | BZ28: =SUM(AE28:AH28) -> 663.9 | CA28: =SUM(AI28:AL28) -> 931.5 | CB28: =SUM(AM28:AP28) -> 1280.1 | CC28: =SUM(AQ28:AT28) -> 1680.5 | CD28: =SUM(AU28:AX28) -> 1883.1 | CE28: =SUM(AY28:BB28) -> 2288.9 | CF28: =SUM(BC28:BF28) -> 2438.2 | CG28: =SUM(BG28:BJ28) -> 2801.9 | CH28: =CH26-CH27 -> 3320.8425 | CI28: =CI26-CI27 -> 3813.4534 | CJ28: =CJ26-CJ27 -> 4372.6219 | CK28: =CK26-CK27 -> 4973.107 | CL28: =CL26-CL27 -> 5640.3057 | CM28: =CM26-CM27 -> 6403.1373 | CN28: =CN26-CN27 -> 7182.623 | CO28: =CO26-CO27 -> 8023.0901 | ... CQ28: =CQ26-CQ27 -> 9874.1325
B29: R&D | C29: 10.7 | D29: 12.2 | E29: 13.2 | F29: 14.9 | G29: 15.4 | H29: 15.9 | I29: 15.4 | J29: 17.3 | K29: 18.1 | L29: 20.7 | M29: 21.6 | N29: 23.8 | O29: 27.6 | P29: 30.9 | Q29: 33.7 | R29: 36.2 | S29: 39.4 | T29: 45.2 | U29: 52.3 | V29: 61.1 | W29: 62.1 | X29: 69.3 | Y29: 75.7 | Z29: 79.1 | AA29: 86.4 | AB29: 85.8 | AC29: 84.2 | AD29: 92.8 | AE29: 104.8 | AF29: 111.3 | AG29: 104.6 | AH29: 112.1 | AI29: 124.2 | AJ29: 138.3 | AK29: 124.2 | AL29: 129 | AM29: 73.1 | AN29: 79.9 | AO29: 87.7 | AP29: 119.2 | AQ29: 109.4 | AR29: 129.1 | AS29: 128.8 | AT29: 236.9 | AU29: 135.9 | AV29: 121.7 | AW29: 110.3 | AX29: 116.3 | AY29: 119 | AZ29: 119.3 | BA29: 131.4 | BB29: 136.1 | BC29: 141.5 | BD29: 136 | BE29: 135.4 | BF29: 139.5 | BG29: 145.2 | BH29: 148.2 | BI29: 157.5 | BJ29: =599.1-SUM(BG29:BI29) -> 148.2 | BK29: 145.3 | BL29: 153 | BS29: =SUM(C29:F29) -> 51 | BT29: =SUM(G29:J29) -> 64 | BU29: =SUM(K29:N29) -> 84.2 | BV29: =SUM(O29:R29) -> 128.4 | BW29: =SUM(S29:V29) -> 198 | BX29: =SUM(W29:Z29) -> 286.2 | BY29: =SUM(AA29:AD29) -> 349.2 | BZ29: =SUM(AE29:AH29) -> 432.8 | CA29: =SUM(AI29:AL29) -> 515.7 | CB29: =SUM(AM29:AP29) -> 359.9 | CC29: =SUM(AQ29:AT29) -> 604.2 | CD29: =SUM(AU29:AX29) -> 484.2 | CE29: =SUM(AY29:BB29) -> 505.8 | CF29: =SUM(BC29:BF29) -> 552.4 | CG29: =SUM(BG29:BJ29) -> 599.1 | CH29: =CH26*CH40 -> 642.91511 | CI29: =CI26*CI40 -> 717.11156 | CJ29: =CJ26*CJ40 -> 802.56984 | CK29: =CK26*CK40 -> 892.80976 | CL29: =CL26*CL40 -> 1022.3054 | CM29: =CM26*CM40 -> 1132.8627 | CN29: =CN26*CN40 -> 1250.1054 | CO29: =CO26*CO40 -> 1373.6503 | ... CQ29: =CQ26*CQ40 -> 1635.8637
B30: SG&A | C30: 6.3 | D30: 7 | E30: 8.2 | F30: 8.1 | G30: 9.4 | H30: 10 | I30: 10.3 | J30: 8.6 | K30: 9.3 | L30: 11.1 | M30: 11.8 | N30: 12.6 | O30: 14.5 | P30: 14.8 | Q30: 18.5 | R30: 21.6 | S30: 19.8 | T30: 24.4 | U30: 64.8 | V30: 28.5 | W30: 32.2 | X30: 36.3 | Y30: 43.9 | Z30: 43.7 | AA30: 48.1 | AB30: 45.3 | AC30: 43.3 | AD30: 48.7 | AE30: 44.8 | AF30: 47.2 | AG30: 50.1 | AH30: 275.3 | AI30: 59 | AJ30: 69 | AK30: 66.7 | AL30: 78.8 | AM30: 149.8 | AN30: 136.4 | AO30: 158.6 | AP30: 173.4 | AQ30: 188.6 | AR30: 186.5 | AS30: 198.5 | AT30: 236.9 | AU30: 218.9 | AV30: 248.9 | AW30: 234.6 | AX30: 305.3 | AY30: 296.4 | AZ30: 299 | BA30: 286.4 | BB30: 303.6 | BC30: 319.3 | BD30: 332.7 | BE30: 306.4 | BF30: 327.4 | BG30: 310.1 | BH30: 328 | BI30: 331.4 | BJ30: =1291-SUM(BG30:BI30) -> 321.5 | BK30: 349.7 | BL30: 358.7 | BS30: =SUM(C30:F30) -> 29.6 | BT30: =SUM(G30:J30) -> 38.3 | BU30: =SUM(K30:N30) -> 44.8 | BV30: =SUM(O30:R30) -> 69.4 | BW30: =SUM(S30:V30) -> 137.5 | BX30: =SUM(W30:Z30) -> 156.1 | BY30: =SUM(AA30:AD30) -> 185.4 | BZ30: =SUM(AE30:AH30) -> 417.4 | CA30: =SUM(AI30:AL30) -> 273.5 | CB30: =SUM(AM30:AP30) -> 618.2 | CC30: =SUM(AQ30:AT30) -> 810.5 | CD30: =SUM(AU30:AX30) -> 1007.7 | CE30: =SUM(AY30:BB30) -> 1185.4 | CF30: =SUM(BC30:BF30) -> 1285.8 | CG30: =SUM(BG30:BJ30) -> 1291 | CH30: =CH26*CH41 -> 1514.3042 | CI30: =CI26*CI41 -> 1671.2346 | CJ30: =CJ26*CJ41 -> 1868.0505 | CK30: =CK26*CK41 -> 2075.3911 | CL30: =CL26*CL41 -> 2322.2196 | CM30: =CM26*CM41 -> 2561.2549 | CN30: =CN26*CN41 -> 2823.703 | CO30: =CO26*CO41 -> 3099.8303 | ... CQ30: =CQ26*CQ41 -> 3610.6903
B31: Operating Income | C31: =C28-SUM(C29:C30) -> -11.9 | D31: =D28-SUM(D29:D30) -> -7.3 | E31: =E28-SUM(E29:E30) -> -13.2 | F31: =F28-SUM(F29:F30) -> -12.2 | G31: =G28-SUM(G29:G30) -> -15.4 | H31: =H28-SUM(H29:H30) -> -14.7 | I31: =I28-SUM(I29:I30) -> -17.3 | J31: =J28-SUM(J29:J30) -> -8.3 | ... BL31: =BL28-SUM(BL29:BL30) -> 318.3 | BS31: =SUM(C31:F31) -> -44.6 | BT31: =SUM(G31:J31) -> -55.7 | BU31: =SUM(K31:N31) -> -28.9 | BV31: =SUM(O31:R31) -> -21.5 | BW31: =SUM(S31:V31) -> -57.1 | BX31: =SUM(W31:Z31) -> -63.9 | BY31: =SUM(AA31:AD31) -> -42.5 | BZ31: =SUM(AE31:AH31) -> -186.3 | CA31: =SUM(AI31:AL31) -> 142.3 | CB31: =SUM(AM31:AP31) -> 302 | CC31: =SUM(AQ31:AT31) -> 265.8 | CD31: =SUM(AU31:AX31) -> 391.2 | CE31: =SUM(AY31:BB31) -> 597.7 | CF31: =SUM(BC31:BF31) -> 600 | CG31: =SUM(BG31:BJ31) -> 911.8 | CH31: =CH28-SUM(CH29:CH30) -> 1163.6232 | CI31: =CI28-SUM(CI29:CI30) -> 1425.1073 | CJ31: =CJ28-SUM(CJ29:CJ30) -> 1702.0016 | CK31: =CK28-SUM(CK29:CK30) -> 2004.9061 | CL31: =CL28-SUM(CL29:CL30) -> 2295.7807 | CM31: =CM28-SUM(CM29:CM30) -> 2709.0196 | CN31: =CN28-SUM(CN29:CN30) -> 3108.8147 | CO31: =CO28-SUM(CO29:CO30) -> 3549.6095 | ... CQ31: =CQ28-SUM(CQ29:CQ30) -> 4627.5785
B32: Other Income | C32: 0 | D32: 0 | E32: 0 | F32: 0 | G32: 0 | H32: 0 | I32: 0 | J32: -0.1 | K32: -0.2 | L32: -0.2 | M32: -0.2 | N32: -0.3 | O32: -0.2 | P32: -0.2 | Q32: -0.2 | R32: -0.2 | S32: -0.2 | T32: -0.1 | U32: -0.1 | V32: 0 | W32: 0 | X32: 0 | Y32: -0.1 | Z32: -0.9 | AA32: 0.1 | AB32: -0.8 | AC32: -2 | AD32: -3.4 | AE32: 6.7 | AF32: 34.5 | AG32: 30.9 | AH32: -12.3 | AI32: -12.2 | AJ32: -8.5 | AK32: -10.2 | AL32: -7.2 | AM32: -11.2 | AN32: -21.6 | AO32: -19 | AP32: 50.2 | AQ32: -4.6 | AR32: -3.9 | AS32: -6.3 | AT32: 5.8 | AU32: -5.2 | AV32: -1.7 | AW32: -1.3 | AX32: 7.8 | AY32: 17.3 | AZ32: 31.2 | BA32: 34.9 | BB32: 29.3 | BC32: 31.4 | BD32: 29.8 | BE32: 25.4 | BF32: 22.4 | BG32: 20.6 | BH32: 28.5 | BI32: 109.8 | BJ32: =176.6-SUM(BG32:BI32) -> 17.7 | BK32: 14.2 | BL32: -0.8 | BS32: =SUM(C32:F32) -> 0 | BT32: =SUM(G32:J32) -> -0.1 | BU32: =SUM(K32:N32) -> -0.9 | BV32: =SUM(O32:R32) -> -0.8 | BW32: =SUM(S32:V32) -> -0.4 | BX32: =SUM(W32:Z32) -> -1 | BY32: =SUM(AA32:AD32) -> -6.1 | BZ32: =SUM(AE32:AH32) -> 59.8 | CA32: =SUM(AI32:AL32) -> -38.1 | CB32: =SUM(AM32:AP32) -> -1.6 | CC32: =SUM(AQ32:AT32) -> -9 | CD32: =SUM(AU32:AX32) -> -0.4 | CE32: =SUM(AY32:BB32) -> 112.7 | CF32: =SUM(BC32:BF32) -> 109 | CG32: =SUM(BG32:BJ32) -> 176.6 | CH32: =CG32*(1+$CQ$49) -> 216.9531 | CI32: =CH32*(1+$CQ$49) -> 266.52688 | CJ32: =CI32*(1+$CQ$49) -> 327.42828 | CK32: =CJ32*(1+$CQ$49) -> 402.24564 | CL32: =CK32*(1+$CQ$49) -> 494.15877 | CM32: =CL32*(1+$CQ$49) -> 607.07404 | CN32: =CM32*(1+$CQ$49) -> 745.79046 | CO32: =CN32*(1+$CQ$49) -> 916.20358 | ... CQ32: =CP32*(1+$CQ$49) -> 1382.7457
B33: Pretax Income | C33: =C31+C32 -> -11.9 | D33: =D31+D32 -> -7.3 | E33: =E31+E32 -> -13.2 | F33: =F31+F32 -> -12.2 | G33: =G31+G32 -> -15.4 | H33: =H31+H32 -> -14.7 | I33: =I31+I32 -> -17.3 | J33: =J31+J32 -> -8.4 | ... BL33: =BL31+BL32 -> 317.5 | BS33: =SUM(C33:F33) -> -44.6 | BT33: =SUM(G33:J33) -> -55.8 | BU33: =SUM(K33:N33) -> -29.8 | BV33: =SUM(O33:R33) -> -22.3 | BW33: =SUM(S33:V33) -> -57.5 | BX33: =SUM(W33:Z33) -> -64.9 | BY33: =SUM(AA33:AD33) -> -48.6 | BZ33: =SUM(AE33:AH33) -> -126.5 | CA33: =SUM(AI33:AL33) -> 104.2 | CB33: =SUM(AM33:AP33) -> 300.4 | CC33: =SUM(AQ33:AT33) -> 256.8 | CD33: =SUM(AU33:AX33) -> 390.8 | CE33: =SUM(AY33:BB33) -> 710.4 | CF33: =SUM(BC33:BF33) -> 709 | CG33: =SUM(BG33:BJ33) -> 1088.4 | CH33: =CH31+CH32 -> 1380.5763 | CI33: =CI31+CI32 -> 1691.6342 | CJ33: =CJ31+CJ32 -> 2029.4298 | CK33: =CK31+CK32 -> 2407.1518 | CL33: =CL31+CL32 -> 2789.9394 | CM33: =CM31+CM32 -> 3316.0937 | CN33: =CN31+CN32 -> 3854.6052 | CO33: =CO31+CO32 -> 4465.8131 | ... CQ33: =CQ31+CQ32 -> 6010.3242
B34: Taxes | C34: 0 | D34: 0 | E34: 0 | F34: 0 | G34: -1.3 | H34: 0 | I34: 0 | J34: 0 | K34: 0 | L34: 0 | M34: 0 | N34: 0 | O34: 0 | P34: 0 | Q34: 0 | R34: 0 | S34: 0 | T34: 0 | U34: 0 | V34: 0 | W34: 0 | X34: 0.1 | Y34: 0.2 | Z34: 0.4 | AA34: 1.4 | AB34: -17.3 | AC34: -0.5 | AD34: 18 | AE34: 0.2 | AF34: -0.6 | AG34: -1.8 | AH34: 2.8 | AI34: 0.3 | AJ34: 1.2 | AK34: 0 | AL34: 1.6 | AM34: 2.5 | AN34: -0.1 | AO34: 2.9 | AP34: -257.1 | AQ34: -15.2 | AR34: 18.7 | AS34: 24.7 | AT34: 11.7 | AU34: -61.2 | AV34: 24.4 | AW34: 45 | AX34: 41.4 | AY34: 15.9 | AZ34: 43.4 | BA34: 119.7 | BB34: -10.1 | BC34: -13.9 | BD34: 44.3 | BE34: 42.8 | BF34: 59.6 | BG34: 48.9 | BH34: 61.3 | BI34: 68.5 | BJ34: =252.1-SUM(BG34:BI34) -> 73.4 | BK34: 70 | BL34: 68.4 | BS34: =SUM(C34:F34) -> 0 | BT34: =SUM(G34:J34) -> -1.3 | BU34: =SUM(K34:N34) -> 0 | BV34: =SUM(O34:R34) -> 0 | BW34: =SUM(S34:V34) -> 0 | BX34: =SUM(W34:Z34) -> 0.7 | BY34: =SUM(AA34:AD34) -> 1.6 | BZ34: =SUM(AE34:AH34) -> 0.6 | CA34: =SUM(AI34:AL34) -> 3.1 | CB34: =SUM(AM34:AP34) -> -251.8 | CC34: =SUM(AQ34:AT34) -> 39.9 | CD34: =SUM(AU34:AX34) -> 49.6 | CE34: =SUM(AY34:BB34) -> 168.9 | CF34: =SUM(BC34:BF34) -> 132.8 | CG34: =SUM(BG34:BJ34) -> 252.1 | CH34: =CH33*CH43 -> 303.72679 | CI34: =CI33*CI43 -> 355.24318 | CJ34: =CJ33*CJ43 -> 405.88597 | CK34: =CK33*CK43 -> 481.43035 | CL34: =CL33*CL43 -> 557.98789 | CM34: =CM33*CM43 -> 696.37967 | CN34: =CN33*CN43 -> 809.46709 | CO34: =CO33*CO43 -> 937.82076 | ... CQ34: =CQ33*CQ43 -> 1262.1681
B35: NI | C35: =C33-C34 -> -11.9 | D35: =D33-D34 -> -7.3 | E35: =E33-E34 -> -13.2 | F35: =F33-F34 -> -12.2 | G35: =G33-G34 -> -14.1 | H35: =H33-H34 -> -14.7 | I35: =I33-I34 -> -17.3 | J35: =J33-J34 -> -8.4 | ... BL35: =BL33-BL34 -> 249.1 | BS35: =SUM(C35:F35) -> -44.6 | BT35: =SUM(G35:J35) -> -54.5 | BU35: =SUM(K35:N35) -> -29.8 | BV35: =SUM(O35:R35) -> -22.3 | BW35: =SUM(S35:V35) -> -57.5 | BX35: =SUM(W35:Z35) -> -65.6 | BY35: =SUM(AA35:AD35) -> -50.2 | BZ35: =SUM(AE35:AH35) -> -127.1 | CA35: =SUM(AI35:AL35) -> 101.1 | CB35: =SUM(AM35:AP35) -> 552.2 | CC35: =SUM(AQ35:AT35) -> 216.9 | CD35: =SUM(AU35:AX35) -> 341.2 | CE35: =SUM(AY35:BB35) -> 541.5 | CF35: =SUM(BC35:BF35) -> 576.2 | CG35: =SUM(BG35:BJ35) -> 836.3 | CH35: =CH33-CH34 -> 1076.8495 | CI35: =CI33-CI34 -> 1336.391 | CJ35: =CJ33-CJ34 -> 1623.5439 | CK35: =CK33-CK34 -> 1925.7214 | CL35: =CL33-CL34 -> 2231.9515 | CM35: =CM33-CM34 -> 2619.714 | CN35: =CN33-CN34 -> 3045.1381 | CO35: =CO33-CO34 -> 3527.9924 | ... CQ35: =CQ33-CQ34 -> 4748.1561 | CR35: =CQ35*(1+$CQ$50) -> 4854.9896 | CS35: =CR35*(1+$CQ$50) -> 4964.2269 | CT35: =CS35*(1+$CQ$50) -> 5075.922 | CU35: =CT35*(1+$CQ$50) -> 5190.1302 | CV35: =CU35*(1+$CQ$50) -> 5306.9082 | CW35: =CV35*(1+$CQ$50) -> 5426.3136 | CX35: =CW35*(1+$CQ$50) -> 5548.4057 | CY35: =CX35*(1+$CQ$50) -> 5673.2448 | ... EO35: =EN35*(1+$CQ$50) -> 14444.111
B36: SC | C36: 249 | D36: 260 | E36: 270 | F36: 262 | G36: 271 | H36: 274 | I36: 276 | J36: 275 | K36: 279 | L36: 284 | M36: 286 | N36: 284 | O36: 293 | P36: 300 | Q36: 303 | R36: 301 | S36: 311 | T36: 311 | U36: 318 | V36: 322 | W36: 319 | X36: 328 | Y36: 334 | Z36: 336 | AA36: 334 | AB36: 341 | AC36: 346 | AD36: 347 | AE36: 345 | AF36: 349 | AG36: 353 | AH36: 354 | AI36: 353 | AJ36: 361 | AK36: 364 | AL36: 365 | AM36: 364 | AN36: 367 | AO36: 375 | AP36: 383 | AQ36: 378 | AR36: 385 | AS36: 387 | AT36: 387 | AU36: 387 | AV36: 389 | AW36: 393 | AX36: 390 | AY36: 689 | AZ36: 687 | BA36: 687 | BB36: 687 | BC36: 386 | BD36: 390 | BE36: 399 | BF36: 394 | BG36: 394 | BH36: 391 | BI36: 391.1 | BJ36: 390.2 | BK36: 385.1 | BL36: 382.2 | BS36: =AVERAGE(C36:F36) -> 260.25 | BT36: =AVERAGE(G36:J36) -> 274 | BU36: =AVERAGE(K36:N36) -> 283.25 | BV36: =AVERAGE(O36:R36) -> 299.25 | BW36: =AVERAGE(S36:V36) -> 315.5 | BX36: =AVERAGE(W36:Z36) -> 329.25 | BY36: =AVERAGE(AA36:AD36) -> 342 | BZ36: =AVERAGE(AE36:AH36) -> 350.25 | CA36: =AVERAGE(AI36:AL36) -> 360.75 | CB36: =AVERAGE(AM36:AP36) -> 372.25 | CC36: =AVERAGE(AQ36:AT36) -> 384.25 | CD36: =AVERAGE(AU36:AX36) -> 389.75 | CE36: =AVERAGE(AY36:BB36) -> 687.5 | CF36: =AVERAGE(BC36:BF36) -> 392.25 | CG36: =AVERAGE(BG36:BJ36) -> 391.575
B37: EPS | C37: =C35/C36 -> -0.047791165 | D37: =D35/D36 -> -0.028076923 | E37: =E35/E36 -> -0.048888889 | F37: =F35/F36 -> -0.046564885 | G37: =G35/G36 -> -0.05202952 | H37: =H35/H36 -> -0.053649635 | I37: =I35/I36 -> -0.062681159 | J37: =J35/J36 -> -0.030545455 | ... BL37: =BL35/BL36 -> 0.65175301 | BS37: =SUM(D37:G37) -> -0.17556022 | BT37: =SUM(H37:K37) -> -0.1866612 | BU37: =SUM(L37:O37) -> -0.10835945 | BV37: =SUM(P37:S37) -> -0.073989653 | BW37: =SUM(T37:W37) -> -0.20076405 | BX37: =SUM(X37:AA37) -> -0.2647469 | BY37: =SUM(AB37:AE37) -> -0.094510213 | BZ37: =SUM(AF37:AI37) -> -0.3652868 | CA37: =SUM(AJ37:AL37) -> 0.35071091 | CB37: =SUM(AM37:AP37) -> 1.4537795 | CC37: =SUM(AQ37:AT37) -> 0.56500028 | CD37: =SUM(AU37:AX37) -> 0.87517754 | CE37: =SUM(AY37:BB37) -> 0.78800426 | CF37: =SUM(BC37:BF37) -> 1.4696078 | CG37: =SUM(BG37:BJ37) -> 2.1380382
B39: Gross Profit Margin | C39: =C28/C26 -> 0.35915493 | D39: =D28/D26 -> 0.55607477 | E39: =E28/E26 -> 0.44808743 | F39: =F28/F26 -> 0.48 | G39: =G28/G26 -> 0.46766169 | H39: =H28/H26 -> 0.47863248 | I39: =I28/I26 -> 0.36363636 | J39: =J28/J26 -> 0.52852853 | ... BL39: =BL28/BL26 -> 0.63436258 | BS39: =BS28/BS26 -> 0.47120419 | BT39: =BT28/BT26 -> 0.46646647 | BU39: =BU28/BU26 -> 0.625625 | BV39: =BV28/BV26 -> 0.68016975 | BW39: =BW28/BW26 -> 0.69253731 | BX39: =BX28/BX26 -> 0.66003837 | BY39: =BY28/BY26 -> 0.6848991 | BZ39: =BZ28/BZ26 -> 0.6435634 | ... CG39: =CG28/CG26 -> 0.60100815 | CH39: 0.625 | CI39: 0.6275 | CJ39: 0.632 | CK39: 0.635 | CL39: 0.64 | CM39: 0.65 | CN39: 0.655 | CO39: 0.66 | CP39: 0.665 | CQ39: 0.67
B40: R&D as % of Revenue | C40: =C29/C26 -> 0.75352113 | D40: =D29/D26 -> 0.57009346 | E40: =E29/E26 -> 0.72131148 | F40: =F29/F26 -> 0.66222222 | G40: =G29/G26 -> 0.76616915 | H40: =H29/H26 -> 0.67948718 | I40: =I29/I26 -> 0.66666667 | J40: =J29/J26 -> 0.51951952 | ... BL40: =BL29/BL26 -> 0.11693672 | BS40: =BS29/BS26 -> 0.66753927 | BT40: =BT29/BT26 -> 0.64064064 | BU40: =BU29/BU26 -> 0.52625 | BV40: =BV29/BV26 -> 0.49537037 | BW40: =BW29/BW26 -> 0.49253731 | BX40: =BX29/BX26 -> 0.49921507 | BY40: =BY29/BY26 -> 0.48601253 | BZ40: =BZ29/BZ26 -> 0.41954246 | ... CG40: =CG29/CG26 -> 0.12850708 | CH40: 0.121 | CI40: 0.118 | CJ40: 0.116 | CK40: 0.114 | CL40: 0.116 | CM40: 0.115 | CN40: 0.114 | CO40: 0.113 | CP40: 0.112 | CQ40: 0.111
B41: SG&A as % of Revenue | C41: =C30/C26 -> 0.44366197 | D41: =D30/D26 -> 0.3271028 | E41: =E30/E26 -> 0.44808743 | F41: =F30/F26 -> 0.36 | G41: =G30/G26 -> 0.46766169 | H41: =H30/H26 -> 0.42735043 | I41: =I30/I26 -> 0.44588745 | J41: =J30/J26 -> 0.25825826 | ... BL41: =BL30/BL26 -> 0.27415164 | BS41: =BS30/BS26 -> 0.38743455 | BT41: =BT30/BT26 -> 0.38338338 | BU41: =BU30/BU26 -> 0.28 | BV41: =BV30/BV26 -> 0.26774691 | BW41: =BW30/BW26 -> 0.3420398 | BX41: =BX30/BX26 -> 0.27228327 | BY41: =BY30/BY26 -> 0.25803758 | BZ41: =BZ30/BZ26 -> 0.40461419 | ... CG41: =CG30/CG26 -> 0.27691978 | CH41: 0.285 | CI41: 0.275 | CJ41: 0.27 | CK41: 0.265 | CL41: 0.2635 | CM41: 0.26 | CN41: 0.2575 | CO41: 0.255 | CP41: 0.25 | CQ41: 0.245
B42: Operating Profit Margin | C42: =C31/C26 -> -0.83802817 | D42: =D31/D26 -> -0.3411215 | E42: =E31/E26 -> -0.72131148 | F42: =F31/F26 -> -0.54222222 | G42: =G31/G26 -> -0.76616915 | H42: =H31/H26 -> -0.62820513 | I42: =I31/I26 -> -0.74891775 | J42: =J31/J26 -> -0.24924925 | ... BL42: =BL31/BL26 -> 0.24327423 | BS42: =BS31/BS26 -> -0.58376963 | BT42: =BT31/BT26 -> -0.55755756 | BU42: =BU31/BU26 -> -0.180625 | BV42: =BV31/BV26 -> -0.082947531 | BW42: =BW31/BW26 -> -0.1420398 | BX42: =BX31/BX26 -> -0.11145997 | BY42: =BY31/BY26 -> -0.059151009 | BZ42: =BZ31/BZ26 -> -0.18059325 | ... CQ42: =CQ31/CQ26 -> 0.314
B43: Effective Tax Rate | C43: =C34/C33 -> 0 | D43: =D34/D33 -> 0 | E43: =E34/E33 -> 0 | F43: =F34/F33 -> 0 | G43: =G34/G33 -> 0.084415584 | H43: =H34/H33 -> 0 | I43: =I34/I33 -> 0 | J43: =J34/J33 -> 0 | ... BL43: =BL34/BL33 -> 0.21543307 | BS43: =BS34/BS33 -> 0 | BT43: =BT34/BT33 -> 0.023297491 | BU43: =BU34/BU33 -> 0 | BV43: =BV34/BV33 -> 0 | BW43: =BW34/BW33 -> 0 | BX43: =BX34/BX33 -> -0.010785824 | BY43: =BY34/BY33 -> -0.032921811 | BZ43: =BZ34/BZ33 -> -0.004743083 | ... CG43: =CG34/CG33 -> 0.2316244 | CH43: 0.22 | CI43: 0.21 | CJ43: 0.2 | CK43: 0.2 | CL43: 0.2 | CM43: 0.21 | CN43: 0.21 | CO43: 0.21 | CP43: 0.21 | CQ43: 0.21
B44: Net Profit Margin | C44: =C35/C26 -> -0.83802817 | D44: =D35/D26 -> -0.3411215 | E44: =E35/E26 -> -0.72131148 | F44: =F35/F26 -> -0.54222222 | G44: =G35/G26 -> -0.70149254 | H44: =H35/H26 -> -0.62820513 | I44: =I35/I26 -> -0.74891775 | J44: =J35/J26 -> -0.25225225 | ... BL44: =BL35/BL26 -> 0.1903852 | BS44: =BS35/BS26 -> -0.58376963 | BT44: =BT35/BT26 -> -0.54554555 | BU44: =BU35/BU26 -> -0.18625 | BV44: =BV35/BV26 -> -0.086033951 | BW44: =BW35/BW26 -> -0.14303483 | BX44: =BX35/BX26 -> -0.11442526 | BY44: =BY35/BY26 -> -0.06986778 | BZ44: =BZ35/BZ26 -> -0.12320667 | ... CG44: =CG35/CG26 -> 0.17938653 | CH44: 0.14287131 | CI44: 0.14287131 | CJ44: 0.14287131 | CK44: 0.14287131 | CL44: 0.14287131 | CM44: 0.14287131 | CN44: 0.14287131 | CO44: 0.14287131 | CP44: 0.14287131 | CQ44: 0.14287131
B46: Cash & CEs | AP46: 817.6 | AQ46: 733.8 | AR46: 1158.8 | AS46: 1444.3 | AT46: 1052.6 | AU46: 716 | AV46: 735.4 | AW46: 698.1 | AX46: 642.3 | AY46: 623.2 | AZ46: 1194.9 | BA46: 643.7 | BB46: 566.3 | BC46: 851.2 | BD46: 939.2 | BE46: 621.2 | BF46: 606.1 | BG46: 904.9 | BH46: 1159 | BI46: 1159 | BJ46: 917.7 | BK46: 1118.2 | BL46: 1105 | CB46: =AP46 -> 817.6 | CC46: =AT46 -> 1052.6 | CD46: =AX46 -> 642.3 | CE46: =BB46 -> 566.3 | CF46: =BF46 -> 606.1 | CG46: =BJ46 -> 917.7 | CH46: =CG46-CF64+CH35 -> 757.54952 | CI46: =CH46-CH64+CI35 -> 2093.9405 | CJ46: =CI46-CI64+CJ35 -> 3717.4844 | CK46: =CJ46-CJ64+CK35 -> 5643.2058 | CL46: =CK46-CK64+CL35 -> 7875.1573 | CM46: =CL46-CL64+CM35 -> 10494.871 | CN46: =CM46-CM64+CN35 -> 13540.009 | CO46: =CN46-CN64+CO35 -> 17068.002 | CP46: =CO46-CO64+CP35 -> 21168.37 | CQ46: =CP46-CP64+CQ35 -> 25916.526
B47: ST Investments | AP47: 1890.1 | AQ47: 1898.8 | AR47: 1426.1 | AS47: 1253.6 | AT47: 1678.6 | AU47: 1972.2 | AV47: 2019.4 | AW47: 1673.8 | AX47: 1813.9 | AY47: 1943.8 | AZ47: 2441.3 | BA47: 2596.6 | BB47: 2157.8 | BC47: 2045.8 | BD47: 2181.5 | BE47: 1871.1 | BF47: 1973.3 | BG47: 1796.5 | BH47: 1770 | BI47: 1770 | BJ47: 1081 | BK47: 1297 | BL47: 842 | CB47: =AP47 -> 1890.1 | CC47: =AT47 -> 1678.6 | CD47: =AX47 -> 1813.9 | CE47: =BB47 -> 2157.8 | CF47: =BF47 -> 1973.3 | CG47: =BJ47 -> 1081
B48: A/R | AP48: 428.5 | AQ48: 443.4 | AR48: 483.5 | AS48: 529.1 | AT48: 514.3 | AU48: 544.5 | AV48: 560.8 | AW48: 564.1 | AX48: 713.3 | AY48: 636.8 | AZ48: 750.6 | BA48: 785.7 | BB48: 973.9 | BC48: 978.6 | BD48: 945.2 | BE48: 1002 | BF48: 1005.7 | BG48: 1155.2 | BH48: 1348.8 | BI48: 1348.8 | BJ48: 1216.1 | BK48: 1088.6 | BL48: 1257.7 | CB48: =AP48 -> 428.5 | CC48: =AT48 -> 514.3 | CD48: =AX48 -> 713.3 | CE48: =BB48 -> 973.9 | CF48: =BF48 -> 1005.7 | CG48: =BJ48 -> 1216.1
B49: Inventories | AP49: 234.7 | AQ49: 289.7 | AR49: 319.3 | AS49: 351.3 | AT49: 357.3 | AU49: 342.2 | AV49: 339.5 | AW49: 311 | AX49: 306.7 | AY49: 366 | AZ49: 421.1 | BA49: 498.6 | BB49: 559.6 | BC49: 589.1 | BD49: 570.3 | BE49: 586.3 | BF49: 542.6 | BG49: 538.2 | BH49: 570.7 | BI49: 570.7 | BJ49: 629.1 | BK49: 693.6 | BL49: 726.4 | CB49: =AP49 -> 234.7 | CC49: =AT49 -> 357.3 | CD49: =AX49 -> 306.7 | CE49: =BB49 -> 559.6 | CF49: =BF49 -> 542.6 | CG49: =BJ49 -> 629.1 | CI49: Invested Capital | CL49: Avg. (2023-2024) | CN49: Projected ROIC: | CP49: ROIC | CQ49: 0.2285
B50: Prepaid Assets | AP50: 53.9 | AQ50: 79.4 | AR50: 86.5 | AS50: 77.9 | AT50: 81.6 | AU50: 171.7 | AV50: 153.6 | AW50: 151.5 | AX50: 192.6 | AY50: 197.6 | AZ50: 195 | BA50: 173.8 | BB50: 168.3 | BC50: 156 | BD50: 212.2 | BE50: 182.2 | BF50: 173.7 | BG50: 159 | BH50: 181.4 | BI50: 181.4 | BJ50: 189.4 | BK50: 134.3 | BL50: 155.5 | CB50: =AP50 -> 53.9 | CC50: =AT50 -> 81.6 | CD50: =AX50 -> 192.6 | CE50: =BB50 -> 168.3 | CF50: =BF50 -> 173.7 | CG50: =BJ50 -> 189.4 | CI50: 2024 | CJ50: 2025 | CL50: 2024-2025 | CN50: 2025 | CP50: Terminal | CQ50: 0.0225
B51: PP&E | AP51: 515.3 | AQ51: 589.9 | AR51: 676 | AS51: 742.2 | AT51: 801.8 | AU51: 856.5 | AV51: 942.9 | AW51: 1002.5 | AX51: 1055.6 | AY51: 1075.5 | AZ51: 1077.6 | BA51: 1078.9 | BB51: 1113.1 | BC51: 1108.6 | BD51: 1183.1 | BE51: 1318.8 | BF51: 1339.9 | BG51: 1364.7 | BH51: 1457.3 | BI51: 1457.3 | BJ51: 1559.9 | BK51: 1559.7 | BL51: 1577.2 | CB51: =AP51 -> 515.3 | CC51: =AT51 -> 801.8 | CD51: =AX51 -> 1055.6 | CE51: =BB51 -> 1113.1 | CF51: =BF51 -> 1339.9 | CG51: =BJ51 -> 1559.9 | CI51: =SUM(CF46:CF50)-CF59+CF54+CF53+CF51 -> 4182.4 | CJ51: =SUM(CG46:CG50)-CG59+CG54+CG53+CG51 -> 3744.2 | CL51: =AVERAGE(CI51:CJ51) -> 3963.3 | CN51: =AVERAGE(CH31)*(1-CH43) -> 907.62611 | CP51: RFR (10-year yield) | CQ51: =CL60 -> 0.0474
B52: LT Operating Lease | AP52: 93.3 | AQ52: 98.8 | AR52: 94.8 | AS52: 91.3 | AT52: 88.1 | AU52: 82.3 | AV52: 77.9 | AW52: 73.1 | AX52: 80 | AY52: 78 | AZ52: 76.3 | BA52: 73.4 | BB52: 71.4 | BC52: 68 | BD52: 71.2 | BE52: 67.5 | BF52: 62.8 | BG52: 59.1 | BH52: 56.4 | BI52: 56.4 | BJ52: 77.4 | BK52: 73.1 | BL52: 88 | CB52: =AP52 -> 93.3 | CC52: =AT52 -> 88.1 | CD52: =AX52 -> 80 | CE52: =BB52 -> 71.4 | CF52: =BF52 -> 62.8 | CG52: =BJ52 -> 77.4 | CN52: =CN51/CL51 -> 0.22900767 | CP52: ERP (Avg. market return - (less) RFR) | CQ52: =8.45%-CQ51 -> 0.0371
B53: Goodwill | AP53: 19.3 | AQ53: 18.9 | AR53: 19.1 | AS53: 23.9 | AT53: 26.5 | AU53: 26.6 | AV53: 25.6 | AW53: 24.7 | AX53: 25.7 | AY53: 25.7 | AZ53: 25.8 | BA53: 25.3 | BB53: 25.2 | BC53: 23.2 | BD53: 23.3 | BE53: 23.8 | BF53: 22.8 | BG53: 23.1 | BH53: 24.1 | BI53: 24.1 | BJ53: 24.2 | BK53: 24.2 | BL53: 24.1 | CB53: =AP53 -> 19.3 | CC53: =AT53 -> 26.5 | CD53: =AX53 -> 25.7 | CE53: =BB53 -> 25.2 | CF53: =BF53 -> 22.8 | CG53: =BJ53 -> 24.2 | CI53: Capital Structure | CP53: Equity β (1-year avg.) | CQ53: ='Notes | Quant Analysis'!K213 -> 1.49
B54: Intangibles | AP54: 0 | AQ54: 0 | AR54: 0 | AS54: 0 | AT54: 31.5 | AU54: 31.4 | AV54: 28 | AW54: 24.4 | AX54: 173.3 | AY54: 163.6 | AZ54: 154.2 | BA54: 144.5 | BB54: 134.5 | BC54: 123.3 | BD54: 114.5 | BE54: 106.2 | BF54: 103.4 | BG54: 95.2 | BH54: 87.2 | BI54: 87.2 | BJ54: 70.8 | BK54: 62.6 | BL54: 101.6 | CB54: =AP54 -> 0 | CC54: =AT54 -> 31.5 | CD54: =AX54 -> 173.3 | CE54: =BB54 -> 134.5 | CF54: =BF54 -> 103.4 | CG54: =BJ54 -> 70.8 | CI54: Mkt Cap | CL54: =Main!C5 -> 29926.26 | CP54: Discount (Cost of Equity) | CQ54: =+CQ51+(CQ52*CQ53) -> 0.102679
B55: LT Deffered Tax Assets | AP55: 216.4 | AQ55: 216.7 | AR55: 216.4 | AS55: 216.3 | AT55: 290.5 | AU55: 290.8 | AV55: 309.5 | AW55: 342.3 | AX55: 341.2 | AY55: 349.1 | AZ55: 417 | BA55: 501.3 | BB55: 419.4 | BC55: 460.7 | BD55: 475.8 | BE55: 486.5 | BF55: 481.2 | BG55: 487.3 | BH55: 496.3 | BI55: 496.3 | BJ55: 295.6 | BK55: 296.1 | BL55: 304.1 | CB55: =AP55 -> 216.4 | CC55: =AT55 -> 290.5 | CD55: =AX55 -> 341.2 | CE55: =BB55 -> 419.4 | CF55: =BF55 -> 481.2 | CG55: =BJ55 -> 295.6 | CI55: Debt to Ttl Mkt Cap | CL55: =Main!C7/(Main!C7+CL54) -> 0.0027525204
B56: Other LT Assets | AP56: 21.4 | AQ56: 20.4 | AR56: 23.3 | AS56: 46 | AT56: 10.5 | AU56: 22.8 | AV56: 24.8 | AW56: 33.7 | AX56: 47.1 | AY56: 56.6 | AZ56: 66.9 | BA56: 74.4 | BB56: 75 | BC56: 77.7 | BD56: 82.9 | BE56: 88.2 | BF56: 173 | BG56: 168.5 | BH56: 175.5 | BI56: 175.5 | BJ56: 278.7 | BK56: 285.9 | BL56: 273.7 | CB56: =AP56 -> 21.4 | CC56: =AT56 -> 10.5 | CD56: =AX56 -> 47.1 | CE56: =BB56 -> 75 | CF56: =BF56 -> 173 | CG56: =BJ56 -> 278.7 | CI56: Mkt Equity to Ttl Mkt Cap | CL56: =CL54/(CL54+Main!C7) -> 0.99724748 | CP56: NPV | CQ56: =NPV(CQ54,CH35:EO35) -> 36315.434
B57: Ttl Assets | AP57: =SUM(AP46:AP56) -> 4290.5 | AQ57: =SUM(AQ46:AQ56) -> 4389.8 | AR57: =SUM(AR46:AR56) -> 4503.8 | AS57: =SUM(AS46:AS56) -> 4775.9 | AT57: =SUM(AT46:AT56) -> 4933.3 | AU57: =SUM(AU46:AU56) -> 5057 | AV57: =SUM(AV46:AV56) -> 5217.4 | AW57: =SUM(AW46:AW56) -> 4899.2 | ... BL57: =SUM(BL46:BL56) -> 6455.3 | CB57: =AP57 -> 4290.5 | CC57: =AT57 -> 4933.3 | CD57: =AX57 -> 5391.7 | CE57: =BB57 -> 6264.5 | CF57: =BF57 -> 6484.5 | CG57: =BJ57 -> 6339.9 | CI57: Debt / Equity | CL57: =CL55/CL56 -> 0.0027601177 | CP57: SC | CQ57: =Main!C4 -> 382.2
CP58: FV | CQ58: =CQ56/CQ57 -> 95.016833
B59: A/P | AP59: 481.1 | AQ59: 502.6 | AR59: 482 | AS59: 598 | AT59: 573 | AU59: 603.1 | AV59: 688.3 | AW59: 764.2 | AX59: 901.8 | AY59: 965.2 | AZ59: 1156.5 | BA59: 1343.1 | BB59: 1345.5 | BC59: 1446.6 | BD59: 1569.8 | BE59: 1592.5 | BF59: 1585.1 | BG59: 1690.6 | BH59: 1943.8 | BI59: 1943.8 | BJ59: 1944 | BK59: 2073.9 | BL59: 2191.5 | CB59: =AP59 -> 481.1 | CC59: =AT59 -> 573 | CD59: =AX59 -> 901.8 | CE59: =BB59 -> 1345.5 | CF59: =BF59 -> 1585.1 | CG59: =BJ59 -> 1944 | CI59: Cost of Equity | CP59: CP | CQ59: =Main!C3 -> 78.3
B60: Accrued Comp. | AP60: 114.3 | AQ60: 81.4 | AR60: 98.1 | AS60: 115.3 | AT60: 125.2 | AU60: 84.7 | AV60: 94.8 | AW60: 112.7 | AX60: 134.3 | AY60: 94.8 | AZ60: 108.6 | BA60: 151.3 | BB60: 171 | BC60: 110.5 | BD60: 116.1 | BE60: 105.8 | BF60: 112 | BG60: 110.8 | BH60: 129.3 | BI60: 129.3 | BJ60: 169.2 | BK60: 121.8 | BL60: 136.3 | CB60: =AP60 -> 114.3 | CC60: =AT60 -> 125.2 | CD60: =AX60 -> 134.3 | CE60: =BB60 -> 171 | CF60: =BF60 -> 112 | CG60: =BJ60 -> 169.2 | CI60: RFR (10-year yield) | CL60: 0.0474 | CP60: Change Δ | CQ60: =CQ58/CQ59-1 -> 0.21349723 | CR60: =IF(CQ60>0,"Upside","Downside") -> Upside
B61: ST Debt | AP61: 0 | AQ61: 0 | AR61: 0 | AS61: 0 | AT61: 0 | AU61: 0 | AV61: 0 | AW61: 0 | AX61: 772.6 | AY61: 773.2 | AZ61: 773.8 | BA61: 124.2 | BB61: 0 | BC61: 0 | BD61: 0 | BE61: 0 | BF61: 1204.4 | BG61: 1205.3 | BH61: 1206.1 | BI61: 1206.1 | BJ61: 0 | BK61: 0 | BL61: 20.7 | CB61: =AP61 -> 0 | CC61: =AT61 -> 0 | CD61: =AX61 -> 772.6 | CE61: =BB61 -> 0 | CF61: =BF61 -> 1204.4 | CG61: =BJ61 -> 0 | CI61: Equity β (1-year avg.) | CL61: 1.21 | CP61: {=_xlfn.IFS(CQ60>=25%,"Strong Buy",CQ60>=10.00001%,"Buy",AND(CQ60<=10%,CQ60>=-4.9999%),"Hold",AND(CQ60<=-5%,CQ60>=-14.999999%),"Sell",CQ60<=-15%,"Strong Sell")} -> Buy
B62: ST Operating Lease Liabilities | AP62: 16.5 | AQ62: 18.2 | AR62: 18.8 | AS62: 19.3 | AT62: 20.5 | AU62: 20.9 | AV62: 21.2 | AW62: 20.9 | AX62: 20.5 | AY62: 22.2 | AZ62: 21.8 | BA62: 21 | BB62: 21.1 | BC62: 20.7 | BD62: 21.6 | BE62: 22.3 | BF62: 22.5 | BG62: 22.6 | BH62: 23.4 | BI62: 23.4 | BJ62: 21.6 | BK62: 20.5 | BL62: 9.2 | CB62: =AP62 -> 16.5 | CC62: =AT62 -> 20.5 | CD62: =AX62 -> 20.5 | CE62: =BB62 -> 21.1 | CF62: =BF62 -> 22.5 | CG62: =BJ62 -> 21.6 | CI62: Market Return(1-year avg.) | CL62: 0.1275
B63: Deffered Revenues | AP63: 2.2 | AQ63: 1.9 | AR63: 1.8 | AS63: 2.3 | AT63: 2.1 | AU63: 2.7 | AV63: 2.7 | AW63: 2.7 | AX63: 10.1 | AY63: 9.6 | AZ63: 9 | BA63: 9 | BB63: 18.4 | BC63: 16.4 | BD63: 14.7 | BE63: 13.9 | BF63: 8 | BG63: 7.8 | BH63: 6.1 | BI63: 6.1 | BJ63: 7.7 | BK63: 7.6 | BL63: 0 | CB63: =AP63 -> 2.2 | CC63: =AT63 -> 2.1 | CD63: =AX63 -> 10.1 | CE63: =BB63 -> 18.4 | CF63: =BF63 -> 8 | CG63: =BJ63 -> 7.7 | CI63: Cost of Equity | CL63: =(CL60+CL61)*(CL62-CL60) -> 0.10071774
B64: LT Debt | AP64: 1667.2 | AQ64: 1688.8 | AR64: 1710.7 | AS64: 1703.5 | AT64: 1981.8 | AU64: 1965.9 | AV64: 1967.3 | AW64: 1968.8 | AX64: 1197.7 | AY64: 1198.5 | AZ64: 2430.6 | BA64: 2432.4 | BB64: 2434.2 | BC64: 2436 | BD64: 2437.8 | BE64: 2439.6 | BF64: 1237 | BG64: 1238 | BH64: 1238.9 | BI64: 1238.9 | BJ64: 1240.9 | BK64: 1241.8 | BL64: 1242.8 | CB64: =AP64 -> 1667.2 | CC64: =AT64 -> 1981.8 | CD64: =AX64 -> 1197.7 | CE64: =BB64 -> 2434.2 | CF64: =BF64 -> 1237 | CG64: =BJ64 -> 1240.9
B65: LT Operating Lease Liabilities | AP65: 101.8 | AQ65: 111.3 | AR65: 107.1 | AS65: 102.9 | AT65: 98.6 | AU65: 93.3 | AV65: 87.7 | AW65: 82.1 | AX65: 94.6 | AY65: 89.7 | AZ65: 86.9 | BA65: 83.4 | BB65: 80.1 | BC65: 75.8 | BD65: 76.8 | BE65: 71.1 | BF65: 65 | BG65: 59.7 | BH65: 23.4 | BI65: 23.4 | BJ65: 73.4 | BK65: 69 | BL65: 82.6 | CB65: =AP65 -> 101.8 | CC65: =AT65 -> 98.6 | CD65: =AX65 -> 94.6 | CE65: =BB65 -> 80.1 | CF65: =BF65 -> 65 | CG65: =BJ65 -> 73.4 | CI65: Cost of Debt
B66: Other LT Liabilities | AP66: 80.9 | AQ66: 82.4 | AR66: 87.7 | AS66: 98.5 | AT66: 90 | AU66: 97.1 | AV66: 99.5 | AW66: 123.3 | AX66: 128.3 | AY66: 129.7 | AZ66: 133.1 | BA66: 133.9 | BB66: 125.6 | BC66: 129.4 | BD66: 128.1 | BE66: 129.6 | BF66: 147.9 | BG66: 150.3 | BH66: 6.1 | BI66: 6.1 | BJ66: 137.1 | BK66: 141.8 | BL66: 150.8 | CB66: =AP66 -> 80.9 | CC66: =AT66 -> 90 | CD66: =AX66 -> 128.3 | CE66: =BB66 -> 125.6 | CF66: =BF66 -> 147.9 | CG66: =BJ66 -> 137.1 | CI66: Cost of Debt | CL66: 0.006
B67: Ttl Liabilities | AP67: =SUM(AP59:AP66) -> 2464 | AQ67: =SUM(AQ59:AQ66) -> 2486.6 | AR67: =SUM(AR59:AR66) -> 2506.2 | AS67: =SUM(AS59:AS66) -> 2639.8 | AT67: =SUM(AT59:AT66) -> 2891.2 | AU67: =SUM(AU59:AU66) -> 2867.7 | AV67: =SUM(AV59:AV66) -> 2961.5 | AW67: =SUM(AW59:AW66) -> 3074.7 | ... BL67: =SUM(BL59:BL66) -> 3833.9 | CB67: =AP67 -> 2464 | CC67: =AT67 -> 2891.2 | CD67: =AX67 -> 3259.9 | CE67: =BB67 -> 4195.9 | CF67: =BF67 -> 4381.9 | CG67: =BJ67 -> 3593.9 | CI67: Tax Rate | CL67: 0.205
B68: Ttl SE | AP68: 1826.5 | AQ68: 1903.2 | AR68: 1997.6 | AS68: 2136.1 | AT68: 2042.1 | AU68: 2189.3 | AV68: 2255.9 | AW68: 1824.5 | AX68: 2131.8 | AY68: 2233 | AZ68: 2100.4 | BA68: 2267.9 | BB68: 2068.6 | BC68: 2246.8 | BD68: 2434.3 | BE68: 1979 | BF68: 2102.6 | BG68: 2266.6 | BH68: 2573.1 | BI68: 2573.1 | BJ68: 2746 | BK68: 2956.9 | BL68: 2621.4 | CB68: =AP68 -> 1826.5 | CC68: =AT68 -> 2042.1 | CD68: =AX68 -> 2131.8 | CE68: =BB68 -> 2068.6 | CF68: =BF68 -> 2102.6 | CG68: =BJ68 -> 2746 | CI68: After Tax Cost of Debt | CL68: =CL66*(1-CL67) -> 0.00477
B69: Ttl L + SE | AP69: =AP67+AP68 -> 4290.5 | AQ69: =AQ67+AQ68 -> 4389.8 | AR69: =AR67+AR68 -> 4503.8 | AS69: =AS67+AS68 -> 4775.9 | AT69: =AT67+AT68 -> 4933.3 | AU69: =AU67+AU68 -> 5057 | AV69: =AV67+AV68 -> 5217.4 | AW69: =AW67+AW68 -> 4899.2 | ... BL69: =BL67+BL68 -> 6455.3 | CB69: =AP69 -> 4290.5 | CC69: =AT69 -> 4933.3 | CD69: =AX69 -> 5391.7 | CE69: =BB69 -> 6264.5 | CF69: =BF69 -> 6484.5 | CG69: =BJ69 -> 6339.9
CI70: WACC | CL70: =(CL56*CL63)+(CL55*CL68*(1-CL67)) -> 0.10045095
B71: Current Ratio | AP71: =SUM(AP46:AP50)/SUM(AP59:AP63) -> 5.5769419 | AQ71: =SUM(AQ46:AQ50)/SUM(AQ59:AQ63) -> 5.7028638 | AR71: =SUM(AR46:AR50)/SUM(AR59:AR63) -> 5.7835858 | AS71: =SUM(AS46:AS50)/SUM(AS59:AS63) -> 4.9750987 | AT71: =SUM(AT46:AT50)/SUM(AT59:AT63) -> 5.1115427 | AU71: =SUM(AU46:AU50)/SUM(AU59:AU63) -> 5.2665167 | AV71: =SUM(AV46:AV50)/SUM(AV59:AV63) -> 4.7195787 | AW71: =SUM(AW46:AW50)/SUM(AW59:AW63) -> 3.7740144 | ... BL71: =SUM(BL46:BL50)/SUM(BL59:BL63) -> 1.7332994 | CB71: =SUM(CB46:CB50)/SUM(CB59:CB63) -> 5.5769419 | CC71: =SUM(CC46:CC50)/SUM(CC59:CC63) -> 5.1115427 | CD71: =SUM(CD46:CD50)/SUM(CD59:CD63) -> 1.9946719 | CE71: =SUM(CE46:CE50)/SUM(CE59:CE63) -> 2.8444087 | CF71: =SUM(CF46:CF50)/SUM(CF59:CF63) -> 1.4670532 | CG71: =SUM(CG46:CG50)/SUM(CG59:CG63) -> 1.8825204
B72: Quick Ratio | AP72: =(SUM(AP46:AP50)-AP49)/SUM(AP59:AP63) -> 5.1947566 | AQ72: =(SUM(AQ46:AQ50)-AQ49)/SUM(AQ59:AQ63) -> 5.2233074 | AR72: =(SUM(AR46:AR50)-AR49)/SUM(AR59:AR63) -> 5.2520393 | AS72: =(SUM(AS46:AS50)-AS49)/SUM(AS59:AS63) -> 4.4970744 | AT72: =(SUM(AT46:AT50)-AT49)/SUM(AT59:AT63) -> 4.6158435 | AU72: =(SUM(AU46:AU50)-AU49)/SUM(AU59:AU63) -> 4.7854934 | AV72: =(SUM(AV46:AV50)-AV49)/SUM(AV59:AV63) -> 4.2988848 | AW72: =(SUM(AW46:AW50)-AW49)/SUM(AW59:AW63) -> 3.4286507 | ... BL72: =(SUM(BL46:BL50)-BL49)/SUM(BL59:BL63) -> 1.4252025 | CB72: =(SUM(CB46:CB50)-CB49)/SUM(CB59:CB63) -> 5.1947566 | CC72: =(SUM(CC46:CC50)-CC49)/SUM(CC59:CC63) -> 4.6158435 | CD72: =(SUM(CD46:CD50)-CD49)/SUM(CD59:CD63) -> 1.8279237 | CE72: =(SUM(CE46:CE50)-CE49)/SUM(CE59:CE63) -> 2.4847686 | CF72: =(SUM(CF46:CF50)-CF49)/SUM(CF59:CF63) -> 1.2819918 | CG72: =(SUM(CG46:CG50)-CG49)/SUM(CG59:CG63) -> 1.5888915
B73: Cash Ratio | AP73: =(AP46+AP47)/SUM(AP59:AP63) -> 4.4092167 | AQ73: =(AQ46+AQ47)/SUM(AQ59:AQ63) -> 4.3578878 | AR73: =(AR46+AR47)/SUM(AR59:AR63) -> 4.3031463 | AS73: =(AS46+AS47)/SUM(AS59:AS63) -> 3.6711117 | AT73: =(AT46+AT47)/SUM(AT59:AT63) -> 3.7891232 | AU73: =(AU46+AU47)/SUM(AU59:AU63) -> 3.7787461 | AV73: =(AV46+AV47)/SUM(AV59:AV63) -> 3.4136307 | AW73: =(AW46+AW47)/SUM(AW59:AW63) -> 2.6339811 | ... BL73: =(BL46+BL47)/SUM(BL59:BL63) -> 0.82580481 | CB73: =(CB46+CB47)/SUM(CB59:CB63) -> 4.4092167 | CC73: =(CC46+CC47)/SUM(CC59:CC63) -> 3.7891232 | CD73: =(CD46+CD47)/SUM(CD59:CD63) -> 1.3353993 | CE73: =(CE46+CE47)/SUM(CE59:CE63) -> 1.7507069 | CF73: =(CF46+CF47)/SUM(CF59:CF63) -> 0.87974079 | CG73: =(CG46+CG47)/SUM(CG59:CG63) -> 0.93288215
B74: Fixed Asset Turnover Ratio | AP74: =AP26/(AP51+AP52) -> 0.93476832 | AQ74: =AQ26/(AQ51+AQ52) -> 0.73326557 | AR74: =AR26/(AR51+AR52) -> 0.77205501 | AS74: =AS26/(AS51+AS52) -> 0.78008398 | AT74: =AT26/(AT51+AT52) -> 0.78458254 | AU74: =AU26/(AU51+AU52) -> 0.66979122 | AV74: =AV26/(AV51+AV52) -> 0.68201411 | AW74: =AW26/(AW51+AW52) -> 0.71550762 | ... BL74: =BL26/(BL51+BL52) -> 0.78573144 | CB74: =CB26/(CB51+CB52) -> 3.1657903 | CC74: =CC26/(CC51+CC52) -> 2.7514327 | CD74: =CD26/(CD51+CD52) -> 2.5623459 | CE74: =CE26/(CE51+CE52) -> 3.0580836 | CF74: =CF26/(CF51+CF52) -> 2.8751693 | CG74: =CG26/(CG51+CG52) -> 2.8473707
B75: Ttl Asset Turnover | AP75: =AP26/AP69 -> 0.13259527 | AQ75: =AQ26/AQ69 -> 0.11503941 | AR75: =AR26/AR69 -> 0.13213287 | AS75: =AS26/AS69 -> 0.13614188 | AT75: =AT26/AT69 -> 0.14152798 | AU75: =AU26/AU69 -> 0.1243425 | AV75: =AV26/AV69 -> 0.13343811 | AW75: =AW26/AW69 -> 0.15708687 | ... BL75: =BL26/BL69 -> 0.20268616 | CB75: =CB26/CB69 -> 0.44906188 | CC75: =CC26/CC69 -> 0.49632092 | CD75: =CD26/CD69 -> 0.53968136 | CE75: =CE26/CE69 -> 0.57822651 | CF75: =CF26/CF69 -> 0.62194464 | CG75: =CG26/CG69 -> 0.73534283
B76: Inventory Turnover Ratio | AP76: =AP27/AVERAGE(AM49:AP49) -> 0.72347678 | AQ76: =AQ27/AVERAGE(AN49:AQ49) -> 0.61441648 | AR76: =AR27/AVERAGE(AO49:AR49) -> 0.6329264 | AS76: =AS27/AVERAGE(AP49:AS49) -> 0.68050209 | AT76: =AT27/AVERAGE(AQ49:AT49) -> 0.6848816 | AU76: =AU27/AVERAGE(AR49:AU49) -> 0.67352748 | AV76: =AV27/AVERAGE(AS49:AV49) -> 0.70977487 | AW76: =AW27/AVERAGE(AT49:AW49) -> 0.816 | ... BL76: =BL27/AVERAGE(BI49:BL49) -> 0.73043744 | CB76: =CB27/AVERAGE(BY49:CB49) -> 2.7550064 | CC76: =CC27/AVERAGE(BZ49:CC49) -> 2.5945946 | CD76: =CD27/AVERAGE(CA49:CD49) -> 3.4272839 | CE76: =CE27/AVERAGE(CB49:CE49) -> 3.6574093 | CF76: =CF27/AVERAGE(CC49:CF49) -> 3.611822 | CG76: =CG27/AVERAGE(CD49:CG49) -> 3.6508342
B77: Return on Assets | AP77: =AP35/AP69 -> 0.096445636 | AQ77: =AQ35/AQ69 -> 0.012870746 | AR77: =AR35/AR69 -> 0.01751854 | AS77: =AS35/AS69 -> 0.018551477 | AT77: =AT35/AT69 -> -0.0014391989 | AU77: =AU35/AU69 -> 0.019636148 | AV77: =AV35/AV69 -> 0.010119983 | AW77: =AW35/AW69 -> 0.021023841 | ... BL77: =BL35/BL69 -> 0.038588447 | CB77: =CB35/CB69 -> 0.12870295 | CC77: =CC35/CC69 -> 0.043966513 | CD77: =CD35/CD69 -> 0.063282453 | CE77: =CE35/CE69 -> 0.08643946 | CF77: =CF35/CF69 -> 0.088858046 | CG77: =CG35/CG69 -> 0.1319106
B78: Return on Equity | AP78: =AP35/AP68 -> 0.22655352 | AQ78: =AQ35/AQ68 -> 0.029686843 | AR78: =AR35/AR68 -> 0.039497397 | AS78: =AS35/AS68 -> 0.041477459 | AT78: =AT35/AT68 -> -0.0034768131 | AU78: =AU35/AU68 -> 0.045356963 | AV78: =AV35/AV68 -> 0.023405293 | AW78: =AW35/AW68 -> 0.056453823 | ... BL78: =BL35/BL68 -> 0.095025559 | CB78: =CB35/CB68 -> 0.30232685 | CC78: =CC35/CC68 -> 0.10621419 | CD78: =CD35/CD68 -> 0.16005254 | CE78: =CE35/CE68 -> 0.26177125 | CF78: =CF35/CF68 -> 0.27404166 | CG78: =CG35/CG68 -> 0.30455208
B80: Net Income | C80: =C35 -> -11.9 | D80: =D35 -> -7.3 | E80: =E35 -> -13.2 | F80: =F35 -> -12.2 | G80: =G35 -> -14.1 | H80: =H35 -> -14.7 | I80: =I35 -> -17.3 | J80: =J35 -> -8.4 | ... BL80: =BL35 -> 249.1 | BS80: =SUM(D80:G80) -> -46.8 | BT80: =SUM(H80:K80) -> -51.5 | BU80: =SUM(L80:O80) -> -31.2 | BV80: =SUM(P80:S80) -> -22.7 | BW80: =SUM(T80:W80) -> -63.8 | BX80: =SUM(X80:AA80) -> -88.1 | BY80: =SUM(AB80:AE80) -> -32.7 | BZ80: =SUM(AF80:AI80) -> -129.8 | CA80: =SUM(AJ80:AL80) -> 128 | CB80: =SUM(AM80:AP80) -> 552.2 | CC80: =SUM(AQ80:AT80) -> 216.9 | CD80: =SUM(AU80:AX80) -> 341.2 | CE80: =SUM(AY80:BB80) -> 541.5 | CF80: =SUM(BC80:BF80) -> 576.2 | CG80: =SUM(BG80:BJ80) -> 836.3
B81: CFFO | C81: -9.3 | D81: -2.5 | E81: -6.7 | F81: -11.5 | G81: -10.2 | H81: -6.3 | I81: -6 | J81: -10.6 | K81: -4.5 | L81: 0.9 | M81: 1.6 | N81: 4.4 | O81: -2.4 | P81: 6.2 | Q81: 11.4 | R81: 8.4 | S81: 3.4 | T81: 16.4 | U81: 17.9 | V81: 11.3 | W81: -0.2 | X81: 20.1 | Y81: 23 | Z81: 13.3 | AA81: 0.3 | AB81: 14.3 | AC81: 36.2 | AD81: 41.2 | AE81: -8.7 | AF81: 41.4 | AG81: 56.8 | AH81: 33.7 | AI81: 11.8 | AJ81: 64.5 | AK81: 94.5 | AL81: 139.5 | AM81: 1.9 | AN81: 154.1 | AO81: 147.6 | AP81: 172 | AQ81: 27.8 | AR81: 61.6 | AS81: 247.4 | AT81: 105.7 | AU81: 71 | AV81: 172.8 | AW81: 293.4 | AX81: 132.3 | AY81: 155.4 | AZ81: 190.3 | BA81: 269.2 | BB81: 133.6 | BC81: 209.2 | BD81: 283 | BE81: 199.5 | BF81: 301.4 | BG81: 183.8 | BH81: 303 | BI81: 659.9 | BJ81: =1440.7-SUM(BG81:BI81) -> 294 | BK81: 525.6 | BL81: 269.2 | BS81: =SUM(C81:F81) -> -30 | BT81: =SUM(G81:J81) -> -33.1 | BU81: =SUM(K81:N81) -> 2.4 | BV81: =SUM(O81:R81) -> 23.6 | BW81: =SUM(S81:V81) -> 49 | BX81: =SUM(W81:Z81) -> 56.2 | BY81: =SUM(AA81:AD81) -> 92 | BZ81: =SUM(AE81:AH81) -> 123.2 | CA81: =SUM(AI81:AL81) -> 310.3 | CB81: =SUM(AM81:AP81) -> 475.6 | CC81: =SUM(AQ81:AT81) -> 442.5 | CD81: =SUM(AU81:AX81) -> 669.5 | CE81: =SUM(AY81:BB81) -> 748.5 | CF81: =SUM(BC81:BF81) -> 993.1 | CG81: =SUM(BG81:BJ81) -> 1440.7
B82: CapEx, net | C82: -1.79 | D82: -1.16 | E82: -1.5 | F82: -3.5 | G82: -2.3 | H82: -2.9 | I82: -2.9 | J82: -1.4 | K82: -1.4 | L82: -2 | M82: -2.2 | N82: -2.3 | O82: -3.9 | P82: -4 | Q82: -3.7 | R82: -4.6 | S82: -8 | T82: -6.3 | U82: -7.4 | V82: -11.6 | W82: -11.5 | X82: -10.5 | Y82: -16.1 | Z82: -17.6 | AA82: -22.9 | AB82: -12 | AC82: -13.5 | AD82: -17.6 | AE82: -15.3 | AF82: -10.3 | AG82: -23.8 | AH82: -17.7 | AI82: -39.3 | AJ82: -46.9 | AK82: -49.7 | AL82: -44.1 | AM82: -33.2 | AN82: -58.2 | AO82: -47.4 | AP82: -60.2 | AQ82: -99.7 | AR82: -101.2 | AS82: -108.1 | AT82: -80.2 | AU82: -101.6 | AV82: -91.5 | AW82: -108.2 | AX82: -63.5 | AY82: -74.7 | AZ82: -59 | BA82: -50.4 | BB82: -52.5 | BC82: -56.9 | BD82: -66.1 | BE82: -111.2 | BF82: -124.6 | BG82: -87 | BH82: -94.1 | BI82: -80.5 | BJ82: -101.9 | BK82: -76.6 | BL82: -84.7 | BS82: =SUM(C82:F82) -> -7.95 | BT82: =SUM(G82:J82) -> -9.5 | BU82: =SUM(K82:N82) -> -7.9 | BV82: =SUM(O82:R82) -> -16.2 | BW82: =SUM(S82:V82) -> -33.3 | BX82: =SUM(W82:Z82) -> -55.7 | BY82: =SUM(AA82:AD82) -> -66 | BZ82: =SUM(AE82:AH82) -> -67.1 | CA82: =SUM(AI82:AL82) -> -180 | CB82: =SUM(AM82:AP82) -> -199 | CC82: =SUM(AQ82:AT82) -> -389.2 | CD82: =SUM(AU82:AX82) -> -364.8 | CE82: =SUM(AY82:BB82) -> -236.6 | CF82: =SUM(BC82:BF82) -> -358.8 | CG82: =SUM(BG82:BJ82) -> -363.5
B83: FCF | C83: =C81+C82 -> -11.09 | D83: =D81+D82 -> -3.66 | E83: =E81+E82 -> -8.2 | F83: =F81+F82 -> -15 | G83: =G81+G82 -> -12.5 | H83: =H81+H82 -> -9.2 | I83: =I81+I82 -> -8.9 | J83: =J81+J82 -> -12 | ... BL83: =BL81+BL82 -> 184.5 | BS83: =SUM(C83:F83) -> -37.95 | BT83: =SUM(G83:J83) -> -42.6 | BU83: =SUM(K83:N83) -> -5.5 | BV83: =SUM(O83:R83) -> 7.4 | BW83: =SUM(S83:V83) -> 15.7 | BX83: =SUM(W83:Z83) -> 0.5 | BY83: =SUM(AA83:AD83) -> 26 | BZ83: =SUM(AE83:AH83) -> 56.1 | CA83: =SUM(AI83:AL83) -> 130.3 | CB83: =SUM(AM83:AP83) -> 276.6 | CC83: =SUM(AQ83:AT83) -> 53.3 | CD83: =SUM(AU83:AX83) -> 304.7 | CE83: =SUM(AY83:BB83) -> 511.9 | CF83: =SUM(BC83:BF83) -> 634.3 | CG83: =SUM(BG83:BJ83) -> 1077.2
B84: SC | C84: =C36 -> 249 | D84: =D36 -> 260 | E84: =E36 -> 270 | F84: =F36 -> 262 | G84: =G36 -> 271 | H84: =H36 -> 274 | I84: =I36 -> 276 | J84: =J36 -> 275 | ... BL84: =BL36 -> 382.2 | BS84: =BS36 -> 260.25 | BT84: =BT36 -> 274 | BU84: =BU36 -> 283.25 | BV84: =BV36 -> 299.25 | BW84: =BW36 -> 315.5 | BX84: =BX36 -> 329.25 | BY84: =BY36 -> 342 | BZ84: =BZ36 -> 350.25 | ... CG84: =CG36 -> 391.575
B85: FCF per Share | C85: =C83/C84 -> -0.044538153 | D85: =D83/D84 -> -0.014076923 | E85: =E83/E84 -> -0.03037037 | F85: =F83/F84 -> -0.057251908 | G85: =G83/G84 -> -0.046125461 | H85: =H83/H84 -> -0.033576642 | I85: =I83/I84 -> -0.032246377 | J85: =J83/J84 -> -0.043636364 | ... BL85: =BL83/BL84 -> 0.48273155 | BS85: =SUM(D85:G85) -> -0.14782466 | BT85: =SUM(H85:K85) -> -0.13060634 | BU85: =SUM(L85:O85) -> -0.020078482 | BV85: =SUM(P85:S85) -> 0.030579463 | BW85: =SUM(T85:W85) -> 0.027885959 | BX85: =SUM(X85:AA85) -> -0.030535314 | BY85: =SUM(AB85:AE85) -> 0.070798114 | BZ85: =SUM(AF85:AI85) -> 0.14989022 | CA85: =SUM(AJ85:AL85) -> 0.43320025 | CB85: =SUM(AM85:AP85) -> 0.7344249 | CC85: =SUM(AQ85:AT85) -> 0.13277101 | CD85: =SUM(AU85:AX85) -> 0.77758474 | CE85: =SUM(AY85:BB85) -> 0.74478275 | CF85: =SUM(BC85:BF85) -> 1.6207477 | CG85: =SUM(BG85:BJ85) -> 2.7537306

Sheet Notes | Quant Analysis
CC1: 0
H2: Employee Scope: | AF2: General Notes/Observations (Updated Q1'25)
I33: Notes: | J33: Kevin Sayer serves as The Company's CEO
J34: [Y]
J35: [Z]
AF36: Financial Stmts. Notes/Observations
H37: Institutional Ownership Snapshot Q2'25 | AF37: Revenues:
I66: Notes: | J66: Alphabet Inc. (GOOG) holds a minority interest in DXCM (~0.27% stake) - just over a million shares … Investigate further … was there an old partnership or spin off?
K67: In August 2015, Dexcom entered a partnership with Google's life sciences team (which later became Verily) to jointly develop next-generation continuous glucose monitoring (CGM) products
K68: The collaboration aimed to combine Google’s miniaturized electronics platform with Dexcom's biometric sensor technologies
L69: This allowed the team to create smaller, less expensive and disposable CGM sensors without finger pricking … This is their patch business which relays data back to the DXCM app
K70: DXCM retained sales and distribution rights but made upfront and milestone payments to Google/Verily as part of the collab and licensing deal
L71: The partnership included Alphabet receiving over a billion shares of Dexcom via stock payments as part of licensing and collaboration agreements
K72: The collaboration involves ongoing joint product development, sharing R&D resources, and expanded options for joint ventures in diabetes technology
J73: [Y]
J74: [Z]
H76: Revenue Breakdown by Segment | AF76: Earnings Scope:
I108: Notes: | J108: [X]
J109: [Y]
J110: [Z]
H112: Q/q Total Revenues, Net Income, FCF | AF112: Balance Sheet Scope:
AF113: [Godel Snapshot of projected balances (assets, liabilities, equity)]
I141: Notes: | J141: [X]
J142: [Y]
J143: [Z]
H145: Y/y Total Revenues, Net Income, FCF | AF145: [Equity Preformance Compared to Peers]
I174: Notes: | J174: [X]
J175: [Y]
J176: [Z]
A192: 1256 Trading Days? (From: 9/13/2020 - 9/13/2025)
A193: Close | B193: High | C193: Low | D193: Open | E193: Volume | F193: UTC Date | G193: Change
A194: 76.22 | B194: 76.69 | C194: 75.39 | D194: 75.77 | E194: 2896173 | F194: Fri, 12 Sep 2025 00:00:00 GMT | G194: =A194/D194-1 -> 0.005939026
A195: 76 | B195: 77.93 | C195: 75.85 | D195: 76.24 | E195: 6307909 | F195: Thu, 11 Sep 2025 00:00:00 GMT | G195: =A195/D195-1 -> -0.0031479538
A196: 76 | B196: 78.28 | C196: 75.555 | D196: 77.97 | E196: 4887541 | F196: Wed, 10 Sep 2025 00:00:00 GMT | G196: =A196/D196-1 -> -0.025266128
A197: 78.4 | B197: 79.2 | C197: 77.61 | D197: 77.61 | E197: 2456957 | F197: Tue, 09 Sep 2025 00:00:00 GMT | G197: =A197/D197-1 -> 0.010179101
A198: 78 | B198: 79.65 | C198: 77.74 | D198: 79.35 | E198: 4033101 | F198: Mon, 08 Sep 2025 00:00:00 GMT | G198: =A198/D198-1 -> -0.017013233
A199: 80.51 | B199: 81.6 | C199: 79.48 | D199: 80.875 | E199: 2672319 | F199: Fri, 05 Sep 2025 00:00:00 GMT | G199: =A199/D199-1 -> -0.0045131376
A200: 80.76 | B200: 81.64 | C200: 78.68 | D200: 79.2 | E200: 4871874 | F200: Thu, 04 Sep 2025 00:00:00 GMT | G200: =A200/D200-1 -> 0.01969697
A201: 78.92 | B201: 79.51 | C201: 74 | D201: 74.32 | E201: 6700804 | F201: Wed, 03 Sep 2025 00:00:00 GMT | G201: =A201/D201-1 -> 0.06189451
A202: 74.3 | B202: 75.1073 | C202: 73.47 | D202: 74.17 | E202: 4415603 | F202: Tue, 02 Sep 2025 00:00:00 GMT | G202: =A202/D202-1 -> 0.0017527302
A203: 75.34 | B203: 75.8 | C203: 74.54 | D203: 75.08 | E203: 2851552 | F203: Fri, 29 Aug 2025 00:00:00 GMT | G203: =A203/D203-1 -> 0.0034629728
A204: 75.08 | B204: 76.36 | C204: 74.21 | D204: 76.26 | E204: 5224813 | F204: Thu, 28 Aug 2025 00:00:00 GMT | G204: =A204/D204-1 -> -0.015473381
A205: 76.38 | B205: 76.97 | C205: 74.74 | D205: 75.8 | E205: 4067723 | F205: Wed, 27 Aug 2025 00:00:00 GMT | G205: =A205/D205-1 -> 0.007651715
A206: 76.12 | B206: 76.89 | C206: 75.72 | D206: 76.25 | E206: 4837354 | F206: Tue, 26 Aug 2025 00:00:00 GMT | G206: =A206/D206-1 -> -0.001704918
A207: 75.96 | B207: 82.2 | C207: 75.89 | D207: 81.705 | E207: 6534615 | F207: Mon, 25 Aug 2025 00:00:00 GMT | G207: =A207/D207-1 -> -0.070313934 | J207: Min | K207: =MIN(G194:G1449) -> -0.0840399
A208: 82.26 | B208: 82.36 | C208: 80.475 | D208: 81.01 | E208: 3645297 | F208: Fri, 22 Aug 2025 00:00:00 GMT | G208: =A208/D208-1 -> 0.015430194 | J208: Max | K208: =MAX(G194:G1449) -> 0.1123315
A209: 80.62 | B209: 81.93 | C209: 79.83 | D209: 81.45 | E209: 3470305 | F209: Thu, 21 Aug 2025 00:00:00 GMT | G209: =A209/D209-1 -> -0.010190301 | J209: Mean μ | K209: =AVERAGE(G194:G1449) -> -4.9793456e-05
A210: 81.67 | B210: 82.05 | C210: 80.43 | D210: 80.77 | E210: 3580863 | F210: Wed, 20 Aug 2025 00:00:00 GMT | G210: =A210/D210-1 -> 0.011142751 | J210: Median | K210: =MEDIAN(G194:G1449) -> 0.00027751259
A211: 80.9 | B211: 81.42 | C211: 80.32 | D211: 80.68 | E211: 2190934 | F211: Tue, 19 Aug 2025 00:00:00 GMT | G211: =A211/D211-1 -> 0.002726822 | J211: SD σ | K211: =_xlfn.STDEV.P(G194:G1449) -> 0.02330129
A212: 80.82 | B212: 81.74 | C212: 80.3227 | D212: 80.93 | E212: 2976858 | F212: Mon, 18 Aug 2025 00:00:00 GMT | G212: =A212/D212-1 -> -0.0013591993 | J212: 3σ 1-Day Δ: ± | K212: =3*K211 -> 0.06990387 | M212: <- Sharpe Ratio (Risk Adjusted Return)
A213: 80.95 | B213: 82.04 | C213: 80.29 | D213: 80.29 | E213: 2174052 | F213: Fri, 15 Aug 2025 00:00:00 GMT | G213: =A213/D213-1 -> 0.0082202018 | J213: β (1-year avg.) | K213: 1.49 | M213: <- Sortino Ratio (Downside Risk Adjusted Return)
A214: 79.96 | B214: 80.205 | C214: 78.86 | D214: 79.74 | E214: 2233731 | F214: Thu, 14 Aug 2025 00:00:00 GMT | G214: =A214/D214-1 -> 0.0027589666
A215: 79.96 | B215: 81.56 | C215: 79.87 | D215: 80.67 | E215: 4278314 | F215: Wed, 13 Aug 2025 00:00:00 GMT | G215: =A215/D215-1 -> -0.0088012892 | I215: n = | J215: 1256
A216: 80.17 | B216: 80.36 | C216: 78.145 | D216: 78.5 | E216: 3479695 | F216: Tue, 12 Aug 2025 00:00:00 GMT | G216: =A216/D216-1 -> 0.021273885 | I216: Histogram Data | L216: Distribution Overlay | P216: SD Lines
A217: 77.85 | B217: 79.22 | C217: 77.599 | D217: 78.74 | E217: 4171168 | F217: Mon, 11 Aug 2025 00:00:00 GMT | G217: =A217/D217-1 -> -0.011303023 | I217: Bin | J217: Frequency | L217: (X) 1-Day Δ | M217: (Y) Pop. Density | P217: X | Q217: Y
A218: 78.86 | B218: 79.05 | C218: 76.27 | D218: 76.27 | E218: 3819972 | F218: Fri, 08 Aug 2025 00:00:00 GMT | G218: =A218/D218-1 -> 0.033958306 | I218: -0.07 | J218: 6 | L218: -0.0725 | M218: =_xlfn.NORM.DIST(L218,$K$209,$K$211,FALSE) -> 0.13621792 | O218: Mean | P218: =K209 -> -4.9793456e-05 | Q218: 0
A219: 76.4 | B219: 77.95 | C219: 75.59 | D219: 77.12 | E219: 3063584 | F219: Thu, 07 Aug 2025 00:00:00 GMT | G219: =A219/D219-1 -> -0.0093360996 | I219: -0.0675 | J219: 1 | L219: -0.07 | M219: =_xlfn.NORM.DIST(L219,$K$209,$K$211,FALSE) -> 0.18906588 | P219: =K209 -> -4.9793456e-05 | Q219: 17
A220: 76.4 | B220: 77.95 | C220: 74.795 | D220: 75.48 | E220: 4824606 | F220: Wed, 06 Aug 2025 00:00:00 GMT | G220: =A220/D220-1 -> 0.012188659 | I220: -0.065 | J220: 0 | L220: -0.0675 | M220: =_xlfn.NORM.DIST(L220,$K$209,$K$211,FALSE) -> 0.25941365 | O220: -3σ | P220: =($K$211*-3)+$K$209 -> -0.069953663 | Q220: 0
A221: 75.46 | B221: 76.53 | C221: 74.88 | D221: 76.3 | E221: 5593546 | F221: Tue, 05 Aug 2025 00:00:00 GMT | G221: =A221/D221-1 -> -0.011009174 | I221: -0.0625 | J221: 2 | L221: -0.065 | M221: =_xlfn.NORM.DIST(L221,$K$209,$K$211,FALSE) -> 0.35186271 | P221: =($K$211*-3)+$K$209 -> -0.069953663 | Q221: 2
A222: 76.25 | B222: 80.215 | C222: 75.94 | D222: 79.9 | E222: 6519030 | F222: Mon, 04 Aug 2025 00:00:00 GMT | G222: =A222/D222-1 -> -0.045682103 | I222: -0.06 | J222: 2 | L222: -0.0625 | M222: =_xlfn.NORM.DIST(L222,$K$209,$K$211,FALSE) -> 0.47179617 | O222: -2σ | P222: =($K$211*-2)+$K$209 -> -0.046652373 | Q222: 0
A223: 79.28 | B223: 80.86 | C223: 78.93 | D223: 80.57 | E223: 5236719 | F223: Fri, 01 Aug 2025 00:00:00 GMT | G223: =A223/D223-1 -> -0.016010922 | I223: -0.0575 | J223: 2 | L223: -0.06 | M223: =_xlfn.NORM.DIST(L223,$K$209,$K$211,FALSE) -> 0.62536898 | P223: =($K$211*-2)+$K$209 -> -0.046652373 | Q223: 3
A224: 80.77 | B224: 87 | C224: 80.46 | D224: 85.7 | E224: 9243641 | F224: Thu, 31 Jul 2025 00:00:00 GMT | G224: =A224/D224-1 -> -0.057526254 | I224: -0.055 | J224: 5 | L224: -0.0575 | M224: =_xlfn.NORM.DIST(L224,$K$209,$K$211,FALSE) -> 0.8194435 | O224: -1σ | P224: =($K$211*-1)+$K$209 -> -0.023351083 | Q224: 0
A225: 89.06 | B225: 89.98 | C225: 88.3 | D225: 89.35 | E225: 4423158 | F225: Wed, 30 Jul 2025 00:00:00 GMT | G225: =A225/D225-1 -> -0.0032456631 | I225: -0.0525 | J225: 9 | L225: -0.055 | M225: =_xlfn.NORM.DIST(L225,$K$209,$K$211,FALSE) -> 1.0614571 | P225: =($K$211*-1)+$K$209 -> -0.023351083 | Q225: 11
A226: 89.35 | B226: 89.96 | C226: 88.97 | D226: 89.64 | E226: 2471071 | F226: Tue, 29 Jul 2025 00:00:00 GMT | G226: =A226/D226-1 -> -0.0032351629 | I226: -0.05 | J226: 4 | L226: -0.0525 | M226: =_xlfn.NORM.DIST(L226,$K$209,$K$211,FALSE) -> 1.3592103 | O226: 1σ | P226: =($K$211*1)+$K$209 -> 0.023251496 | Q226: 0
A227: 89.53 | B227: 89.76 | C227: 88.63 | D227: 88.99 | E227: 2698399 | F227: Mon, 28 Jul 2025 00:00:00 GMT | G227: =A227/D227-1 -> 0.0060680975 | I227: -0.0475 | J227: 6 | L227: -0.05 | M227: =_xlfn.NORM.DIST(L227,$K$209,$K$211,FALSE) -> 1.720567 | P227: =($K$211*1)+$K$209 -> 0.023251496 | Q227: 11
A228: 88.99 | B228: 89.07 | C228: 86.69 | D228: 87.215 | E228: 3054755 | F228: Fri, 25 Jul 2025 00:00:00 GMT | G228: =A228/D228-1 -> 0.020352004 | I228: -0.045 | J228: 6 | L228: -0.0475 | M228: =_xlfn.NORM.DIST(L228,$K$209,$K$211,FALSE) -> 2.1530657 | O228: 2σ | P228: =($K$211*2)+$K$209 -> 0.046552786 | Q228: 0
A229: 86.74 | B229: 87.14 | C229: 86.055 | D229: 86.54 | E229: 1994678 | F229: Thu, 24 Jul 2025 00:00:00 GMT | G229: =A229/D229-1 -> 0.00231107 | I229: -0.0425 | J229: 4 | L229: -0.045 | M229: =_xlfn.NORM.DIST(L229,$K$209,$K$211,FALSE) -> 2.6634451 | P229: =($K$211*2)+$K$209 -> 0.046552786 | Q229: 3
A230: 86.43 | B230: 86.775 | C230: 85.49 | D230: 86.19 | E230: 2188235 | F230: Wed, 23 Jul 2025 00:00:00 GMT | G230: =A230/D230-1 -> 0.0027845458 | I230: -0.04 | J230: 7 | L230: -0.0425 | M230: =_xlfn.NORM.DIST(L230,$K$209,$K$211,FALSE) -> 3.257099 | O230: 3σ | P230: =($K$211*3)+$K$209 -> 0.069854076 | Q230: 0
A231: 85.12 | B231: 85.65 | C231: 84.25 | D231: 84.49 | E231: 1957487 | F231: Tue, 22 Jul 2025 00:00:00 GMT | G231: =A231/D231-1 -> 0.0074565037 | I231: -0.0375 | J231: 8 | L231: -0.04 | M231: =_xlfn.NORM.DIST(L231,$K$209,$K$211,FALSE) -> 3.9374851 | P231: =($K$211*3)+$K$209 -> 0.069854076 | Q231: 2
A232: 84.03 | B232: 84.5 | C232: 83.3 | D232: 83.955 | E232: 2077740 | F232: Mon, 21 Jul 2025 00:00:00 GMT | G232: =A232/D232-1 -> 0.00089333572 | I232: -0.035 | J232: 13 | L232: -0.0375 | M232: =_xlfn.NORM.DIST(L232,$K$209,$K$211,FALSE) -> 4.7055203
A233: 83.89 | B233: 84.775 | C233: 83.23 | D233: 84.7 | E233: 2595277 | F233: Fri, 18 Jul 2025 00:00:00 GMT | G233: =A233/D233-1 -> -0.0095631641 | I233: -0.0325 | J233: 12 | L233: -0.035 | M233: =_xlfn.NORM.DIST(L233,$K$209,$K$211,FALSE) -> 5.5590058
A234: 84.1 | B234: 85.9 | C234: 83.54 | D234: 84.09 | E234: 4776253 | F234: Thu, 17 Jul 2025 00:00:00 GMT | G234: =A234/D234-1 -> 0.0001189202 | I234: -0.03 | J234: 17 | L234: -0.0325 | M234: =_xlfn.NORM.DIST(L234,$K$209,$K$211,FALSE) -> 6.4921323
A235: 84.13 | B235: 85.57 | C235: 83.85 | D235: 85.485 | E235: 2332516 | F235: Wed, 16 Jul 2025 00:00:00 GMT | G235: =A235/D235-1 -> -0.015850734 | I235: -0.0275 | J235: 23 | L235: -0.03 | M235: =_xlfn.NORM.DIST(L235,$K$209,$K$211,FALSE) -> 7.4951158
A236: 84.78 | B236: 86.14 | C236: 84.67 | D236: 86.03 | E236: 2125988 | F236: Tue, 15 Jul 2025 00:00:00 GMT | G236: =A236/D236-1 -> -0.014529815 | I236: -0.025 | J236: 29 | L236: -0.0275 | M236: =_xlfn.NORM.DIST(L236,$K$209,$K$211,FALSE) -> 8.5540167
A237: 85.33 | B237: 85.61 | C237: 82.96 | D237: 83.42 | E237: 2354006 | F237: Mon, 14 Jul 2025 00:00:00 GMT | G237: =A237/D237-1 -> 0.022896188 | I237: -0.0225 | J237: 25 | L237: -0.025 | M237: =_xlfn.NORM.DIST(L237,$K$209,$K$211,FALSE) -> 9.6507839
A238: 83.37 | B238: 85.35 | C238: 83.05 | D238: 85.33 | E238: 2290251 | F238: Fri, 11 Jul 2025 00:00:00 GMT | G238: =A238/D238-1 -> -0.022969647 | I238: -0.02 | J238: 28 | L238: -0.0225 | M238: =_xlfn.NORM.DIST(L238,$K$209,$K$211,FALSE) -> 10.763558
A239: 85.46 | B239: 85.92 | C239: 84.058 | D239: 85.24 | E239: 3669459 | F239: Thu, 10 Jul 2025 00:00:00 GMT | G239: =A239/D239-1 -> 0.0025809479 | I239: -0.0175 | J239: 32 | L239: -0.02 | M239: =_xlfn.NORM.DIST(L239,$K$209,$K$211,FALSE) -> 11.867243
A240: 84.87 | B240: 85.2 | C240: 82.73 | D240: 84.14 | E240: 2692441 | F240: Wed, 09 Jul 2025 00:00:00 GMT | G240: =A240/D240-1 -> 0.0086760162 | I240: -0.015 | J240: 49 | L240: -0.0175 | M240: =_xlfn.NORM.DIST(L240,$K$209,$K$211,FALSE) -> 12.93435
A241: 83.76 | B241: 84.46 | C241: 82.9241 | D241: 83.14 | E241: 3017486 | F241: Tue, 08 Jul 2025 00:00:00 GMT | G241: =A241/D241-1 -> 0.0074573009 | I241: -0.0125 | J241: 49 | L241: -0.015 | M241: =_xlfn.NORM.DIST(L241,$K$209,$K$211,FALSE) -> 13.936064
A242: 82.94 | B242: 83.805 | C242: 82.5 | D242: 82.84 | E242: 2770095 | F242: Mon, 07 Jul 2025 00:00:00 GMT | G242: =A242/D242-1 -> 0.0012071463 | I242: -0.01 | J242: 57 | L242: -0.0125 | M242: =_xlfn.NORM.DIST(L242,$K$209,$K$211,FALSE) -> 14.843503
A243: 82.93 | B243: 84.49 | C243: 82.575 | D243: 83.7 | E243: 1840975 | F243: Thu, 03 Jul 2025 00:00:00 GMT | G243: =A243/D243-1 -> -0.0091995221 | I243: -0.0075 | J243: 64 | L243: -0.01 | M243: =_xlfn.NORM.DIST(L243,$K$209,$K$211,FALSE) -> 15.629081
... A274: 86.96 | B274: 86.99 | C274: 84.34 | D274: 84.67 | E274: 2366501 | F274: Mon, 19 May 2025 00:00:00 GMT | G274: =A274/D274-1 -> 0.027046179 | I274: 0.07 | J274: 1 | L274: 0.0675 | M274: =_xlfn.NORM.DIST(L274,$K$209,$K$211,FALSE) -> 0.25622172
A275: 85.48 | B275: 86 | C275: 84.68 | D275: 85.88 | E275: 3397874 | F275: Fri, 16 May 2025 00:00:00 GMT | G275: =A275/D275-1 -> -0.0046576619 | I275: More | J275: 10 | L275: 0.07 | M275: =_xlfn.NORM.DIST(L275,$K$209,$K$211,FALSE) -> 0.18665393
A276: 85.67 | B276: 86.85 | C276: 84.76 | D276: 86.21 | E276: 2892321 | F276: Thu, 15 May 2025 00:00:00 GMT | G276: =A276/D276-1 -> -0.0062637745 | L276: 0.0725 | M276: =_xlfn.NORM.DIST(L276,$K$209,$K$211,FALSE) -> 0.13441851
A277: 86.52 | B277: 86.565 | C277: 83.64 | D277: 83.64 | E277: 3828441 | F277: Wed, 14 May 2025 00:00:00 GMT | G277: =A277/D277-1 -> 0.034433286
A278: 84.11 | B278: 85.54 | C278: 83.84 | D278: 84.74 | E278: 5514636 | F278: Tue, 13 May 2025 00:00:00 GMT | G278: =A278/D278-1 -> -0.0074345055
A279: 85.05 | B279: 87.02 | C279: 84.31 | D279: 87.02 | E279: 4030142 | F279: Mon, 12 May 2025 00:00:00 GMT | G279: =A279/D279-1 -> -0.022638474
A280: 84.67 | B280: 85.71 | C280: 84.23 | D280: 84.78 | E280: 3349024 | F280: Fri, 09 May 2025 00:00:00 GMT | G280: =A280/D280-1 -> -0.0012974758
A281: 85.34 | B281: 85.74 | C281: 83.48 | D281: 84 | E281: 6159401 | F281: Thu, 08 May 2025 00:00:00 GMT | G281: =A281/D281-1 -> 0.015952381
A282: 83.35 | B282: 83.9 | C282: 80.5 | D282: 81.53 | E282: 3945588 | F282: Wed, 07 May 2025 00:00:00 GMT | G282: =A282/D282-1 -> 0.022323071
A283: 81.53 | B283: 82.48 | C283: 78.5501 | D283: 79.515 | E283: 5205021 | F283: Tue, 06 May 2025 00:00:00 GMT | G283: =A283/D283-1 -> 0.025341131
A284: 80.27 | B284: 81.96 | C284: 80.0018 | D284: 81.65 | E284: 5371566 | F284: Mon, 05 May 2025 00:00:00 GMT | G284: =A284/D284-1 -> -0.016901408
A285: 81.62 | B285: 81.88 | C285: 74.96 | D285: 75.26 | E285: 10696540 | F285: Fri, 02 May 2025 00:00:00 GMT | G285: =A285/D285-1 -> 0.084507042
A286: 70.26 | B286: 71.71 | C286: 69.7 | D286: 71.38 | E286: 6874455 | F286: Thu, 01 May 2025 00:00:00 GMT | G286: =A286/D286-1 -> -0.01569067
A287: 71.38 | B287: 71.57 | C287: 69.75 | D287: 70.665 | E287: 2859756 | F287: Wed, 30 Apr 2025 00:00:00 GMT | G287: =A287/D287-1 -> 0.010118163
A288: 71.3 | B288: 71.46 | C288: 70.29 | D288: 71.275 | E288: 2332053 | F288: Tue, 29 Apr 2025 00:00:00 GMT | G288: =A288/D288-1 -> 0.00035075412
... A1449: 98.4025 | B1449: 99.9325 | C1449: 96.525 | D1449: 96.5525 | E1449: 2465116 | F1449: Mon, 14 Sep 2020 00:00:00 GMT | G1449: =A1449/D1449-1 -> 0.01916056

Sheet Product Lines

Sheet Management

Sheet Table Formatting
B2: [Bold Title] | G2: [Bold Title]
B3: Line Titles | G3: <-- General
B4: Line Titles | G4: <-- Info
B5: Line Titles | G5: <-- General
B6: Line Titles | G6: <-- Info
B7: Line Titles | G7: <-- General
B8: Line Titles | G8: <-- Info
