Workbook

Sheet Main
B2: FIG
B3: Price | C3: 23.95 | D3: 10/22/2026
B4: SO | C4: 455.1136 | D4: Q2'26
B5: MC | C5: =C3*C4 -> 10899.971
B6: Cash | C6: =15.82+1221.293+445.845 -> 1682.958 | D6: Q2'26
B7: Debt | C7: 0 | D7: Q2'26
B8: EV | C8: =C5-C6+C7 -> 9217.0127
B10: Figma, Inc. (FIG)
B12: Founder(s): Dylan Field and Evan Wallace | F12: Registered Exchange: NASDAQ | N12: Resources:
B13: Founded: 2012 | F13: Address: 760 Market Street, San Francisco, CA 94102 U.S. | N13: SEC filings | Q13: https://www.sec.gov/edgar/browse/?CIK=1579878&owner=exclude
B14: Headquarters: San Francisco, CA | F14: Investor Relations Contact: | N14: Company Homepage | Q14: https://www.figma.com/
B15: Current CEO: Dylan Field | F15: Investors Relation Department | O15: Company IR Page | R15: https://investor.figma.com/overview/default.aspx
B16: Employees: 1,886 | F16: Phone: | G16: (415) 890 - 5404 | I16: Email: | N16: Earnings Calls | Q16: https://seekingalpha.com/symbol/FIG/earnings/transcripts
B17: Industry: Software Services | N17: Equity Analysis | Q17: https://stockanalysis.com/stocks/fig/company/
B18: Sector: Technology | N18: MacroTrends | Q18: https://www.macrotrends.net/stocks/charts/FIG/figma/income-statement
B19: IPO: Jul 31, 2025 -- $19.3B valuation | N19: ROIC, WACC | Q19: https://www.gurufocus.com/term/wacc/FIG
B20: Fiscal Year: [January - December] | N20: Godel Terminal | Q20: https://app.godelterminal.com/
A22: Company Overview:
B23: Figma, Inc. develops and sells a collaborative, browser-based platform for designing, prototyping, building digital experiences, and subscriptions for access to its platform
B24: The Company offers Figma Design, a collaborative design tool for teams that explore ideas and gather feedback, build realistic prototypes, and streamline product development with design systems
C25: Dev Mode to inspect designs and translate them into code without changing the design file
C26: FigJam to define ideas, align decisions, and move work forward—all in one place
C27: Figma Slides, a presentation tool built for designers and their teams
B28: It also provides Figma Draw to create expressive designs with illustration tools; Figma Buzz, which publishes brand templates to create social media assets, display ads, one-pagers, and others
C29: Figma Sites to design, prototype, and publish; Payload CMS is an open-source, headless content management system and application framework acquired by Figma; Figma Make, an AI tool to design and prompt way to a functional prototype; Figma Weave for AI-powered media generation and editing
B30: The Company was incorporated in 2012 and is headquartered in San Francisco, California
A32: Business Segments and Geographical Info:

Sheet Model
B1: [Use for Graphing] | C1: Q1 2024 | G1: Q1 2025 | K1: Q1 2026
B2: Quarterly
B3: Revenues | C3: {="Q"&MOD(_xlfn.SEQUENCE(1,12)-1,4)+1&" "&(2024+INT((_xlfn.SEQUENCE(1,12)-1)/4))} -> Q1 2024 | D3: Q2 2024 | E3: Q3 2024 | F3: Q4 2024 | G3: Q1 2025 | H3: Q2 2025 | I3: Q3 2025 | J3: Q4 2025 | K3: Q1 2026 | L3: Q2 2026 | M3: Q3 2026 | N3: Q4 2026 | R3: 2023 | S3: 2024 | T3: =S3+1 -> 2025 | U3: =T3+1 -> 2026 | V3: =U3+1 -> 2027 | W3: =V3+1 -> 2028 | X3: =W3+1 -> 2029 | Y3: =X3+1 -> 2030 | Z3: =Y3+1 -> 2031 | AA3: =Z3+1 -> 2032 | ... CB3: =CA3+1 -> 2085
B4: U.S. Revenues | C4: 73 | D4: 85.198 | E4: 94.668 | F4: =359.406-SUM(C4:E4) -> 106.54 | G4: 107.463 | H4: 116.766 | I4: 126.792 | J4: =491.548-SUM(G4:I4) -> 140.527 | K4: 155.051 | L4: 170.794 | R4: 252.289 | S4: =SUM(C4:F4) -> 359.406 | T4: =SUM(G4:J4) -> 491.548 | U4: =T4*(1+U8) -> 712.7446 | V4: =U4*(1+V8) -> 983.58755 | W4: =V4*(1+W8) -> 1308.1714 | X4: =W4*(1+X8) -> 1661.3777 | Y4: =X4*(1+Y8) -> 2043.4946 | Z4: =Y4*(1+Z8) -> 2452.1935 | AA4: =Z4*(1+AA8) -> 2869.0664 | AB4: =AA4*(1+AB8) -> 3270.7357 | ... AD4: =AC4*(1+AD8) -> 3957.2632
B5: International Revenues | C5: 83.2 | D5: 92 | E5: 103.971 | F5: =389.605-SUM(C5:E5) -> 110.434 | G5: 120.736 | H5: 132.874 | I5: 147.381 | J5: =564.24-SUM(G5:I5) -> 163.249 | K5: 178.388 | L5: 199.289 | R5: 252.585 | S5: =SUM(C5:F5) -> 389.605 | T5: =SUM(G5:J5) -> 564.24 | U5: =T5*(1+U9) -> 835.0752 | V5: =U5*(1+V9) -> 1185.8068 | W5: =V5*(1+W9) -> 1612.6972 | X5: =W5*(1+X9) -> 2112.6334 | Y5: =X5*(1+Y9) -> 2661.918 | Z5: =Y5*(1+Z9) -> 3220.9208 | AA5: =Z5*(1+AA9) -> 3800.6866 | AB5: =AA5*(1+AB9) -> 4408.7964 | ... AD5: =AC5*(1+AD9) -> 5629.1513
B6: Ttl Revenues | C6: =SUM(C4:C5) -> 156.2 | D6: =SUM(D4:D5) -> 177.198 | E6: =SUM(E4:E5) -> 198.639 | F6: =SUM(F4:F5) -> 216.974 | G6: =SUM(G4:G5) -> 228.199 | H6: =SUM(H4:H5) -> 249.64 | I6: =SUM(I4:I5) -> 274.173 | J6: =SUM(J4:J5) -> 303.776 | ... L6: =SUM(L4:L5) -> 370.083 | R6: =SUM(R4:R5) -> 504.874 | S6: =SUM(C6:F6) -> 749.011 | T6: =SUM(G6:J6) -> 1055.788 | U6: =U4+U5 -> 1547.8198 | V6: =V4+V5 -> 2169.3943 | W6: =W4+W5 -> 2920.8687 | X6: =X4+X5 -> 3774.0111 | Y6: =Y4+Y5 -> 4705.4126 | Z6: =Z4+Z5 -> 5673.1144 | AA6: =AA4+AA5 -> 6669.753 | AB6: =AB4+AB5 -> 7679.5322 | ... AD6: =AD4+AD5 -> 9586.4144
B8: U.S. Growth Y/y | G8: =G4/C4-1 -> 0.47209589 | H8: =H4/D4-1 -> 0.37052513 | I8: =I4/E4-1 -> 0.33933325 | J8: =J4/F4-1 -> 0.31900695 | K8: =K4/G4-1 -> 0.44283149 | L8: =L4/H4-1 -> 0.46270318 | S8: =S4/R4-1 -> 0.42458054 | T8: =T4/S4-1 -> 0.36766776 | U8: 0.45 | V8: 0.38 | W8: 0.33 | X8: 0.27 | Y8: 0.23 | Z8: 0.2 | AA8: 0.17 | AB8: 0.14 | AC8: 0.11 | AD8: 0.09
B9: International Growth Y/y | G9: =G5/C5-1 -> 0.45115385 | H9: =H5/D5-1 -> 0.44428261 | I9: =I5/E5-1 -> 0.41752027 | J9: =J5/F5-1 -> 0.47824945 | K9: =K5/G5-1 -> 0.47750464 | L9: =L5/H5-1 -> 0.49983443 | S9: =S5/R5-1 -> 0.54247085 | T9: =T5/S5-1 -> 0.44823603 | U9: 0.48 | V9: 0.42 | W9: 0.36 | X9: 0.31 | Y9: 0.26 | Z9: 0.21 | AA9: 0.18 | AB9: 0.16 | AC9: 0.14 | AD9: 0.12
B10: Ttl Revenue Growth Y/y | G10: =G6/C6-1 -> 0.4609411 | H10: =H6/D6-1 -> 0.40881951 | I10: =I6/E6-1 -> 0.38025765 | J10: =J6/F6-1 -> 0.40005715 | K10: =K6/G6-1 -> 0.46117643 | L10: =L6/H6-1 -> 0.48246675 | S10: =S6/R6-1 -> 0.48356025 | T10: =T6/S6-1 -> 0.40957609 | U10: =U6/T6-1 -> 0.46603276 | V10: =V6/U6-1 -> 0.40158068 | W10: =W6/V6-1 -> 0.34639822 | X10: =X6/W6-1 -> 0.29208517 | Y10: =Y6/X6-1 -> 0.24679354 | Z10: =Z6/Y6-1 -> 0.20565714 | ... AD10: =AD6/AC6-1 -> 0.10741813
B12: U.S. % of Revenues | C12: =C4/C6 -> 0.46734955 | D12: =D4/D6 -> 0.48080678 | E12: =E4/E6 -> 0.47658315 | F12: =F4/F6 -> 0.49102657 | G12: =G4/G6 -> 0.47091793 | H12: =H4/H6 -> 0.46773754 | I12: =I4/I6 -> 0.46245254 | J12: =J4/J6 -> 0.46260073 | ... L12: =L4/L6 -> 0.46150188 | R12: =R4/R6 -> 0.49970686 | S12: =S4/S6 -> 0.47984075 | T12: =T4/T6 -> 0.46557453
B13: International % of Revenues | C13: =C5/C6 -> 0.53265045 | D13: =D5/D6 -> 0.51919322 | E13: =E5/E6 -> 0.52341685 | F13: =F5/F6 -> 0.50897343 | G13: =G5/G6 -> 0.52908207 | H13: =H5/H6 -> 0.53226246 | I13: =I5/I6 -> 0.53754746 | J13: =J5/J6 -> 0.53739927 | ... L13: =L5/L6 -> 0.53849812 | R13: =R5/R6 -> 0.50029314 | S13: =S5/S6 -> 0.52015925 | T13: =T5/T6 -> 0.53442547
B15: Revenues | C15: =C6 -> 156.2 | D15: =D6 -> 177.198 | E15: =E6 -> 198.639 | F15: =F6 -> 216.974 | G15: =G6 -> 228.199 | H15: =H6 -> 249.64 | I15: =I6 -> 274.173 | J15: =J6 -> 303.776 | ... L15: =L6 -> 370.083 | R15: =R6 -> 504.874 | S15: =SUM(C15:F15) -> 749.011 | T15: =SUM(G15:J15) -> 1055.788 | U15: =U6 -> 1547.8198 | V15: =V6 -> 2169.3943 | W15: =W6 -> 2920.8687 | X15: =X6 -> 3774.0111 | Y15: =Y6 -> 4705.4126 | Z15: =Z6 -> 5673.1144 | AA15: =AA6 -> 6669.753 | AB15: =AB6 -> 7679.5322 | ... AD15: =AD6 -> 9586.4144
B16: COGS | C16: 12.79 | D16: 39.558 | E16: 18.703 | F16: =87.514-SUM(C16:E16) -> 16.463 | G16: 19.452 | H16: 27.889 | I16: 83.884 | J16: =185.527-SUM(G16:I16) -> 54.302 | K16: 68.666 | L16: 60.472 | R16: 44.5 | S16: =SUM(C16:F16) -> 87.514 | T16: =SUM(G16:J16) -> 185.527 | U16: =U15*(1-U31) -> 271.98866 | V16: =V15*(1-V31) -> 381.21405 | W16: =W15*(1-W31) -> 513.26592 | X16: =X15*(1-X31) -> 663.18329 | Y16: =Y15*(1-Y31) -> 826.85264 | Z16: =Z15*(1-Z31) -> 996.90079 | AA16: =AA15*(1-AA31) -> 1172.0338 | AB16: =AB15*(1-AB31) -> 1349.476 | ... AD16: =AD15*(1-AD31) -> 1684.5605
B17: GP | C17: =C15-C16 -> 143.41 | D17: =D15-D16 -> 137.64 | E17: =E15-E16 -> 179.936 | F17: =F15-F16 -> 200.511 | G17: =G15-G16 -> 208.747 | H17: =H15-H16 -> 221.751 | I17: =I15-I16 -> 190.289 | J17: =J15-J16 -> 249.474 | ... L17: =L15-L16 -> 309.611 | R17: =R15-R16 -> 460.374 | S17: =SUM(C17:F17) -> 661.497 | T17: =SUM(G17:J17) -> 870.261 | U17: =U15*U31 -> 1275.8311 | V17: =V15*V31 -> 1788.1803 | W17: =W15*W31 -> 2407.6027 | X17: =X15*X31 -> 3110.8278 | Y17: =Y15*Y31 -> 3878.56 | Z17: =Z15*Z31 -> 4676.2136 | AA17: =AA15*AA31 -> 5497.7192 | AB17: =AB15*AB31 -> 6330.0562 | ... AD17: =AD15*AD31 -> 7901.854
B18: R&D | C18: 52.711 | D18: 535.676 | E18: 104.182 | F18: =751.12-SUM(C18:E18) -> 58.551 | G18: 69.925 | H18: 83.052 | I18: 680.885 | J18: =1029.7-SUM(G18:I18) -> 195.838 | K18: 172.974 | L18: 167.329 | R18: 164.774 | S18: =SUM(C18:F18) -> 751.12 | T18: =SUM(G18:J18) -> 1029.7 | U18: =U15*U32 -> 742.9535 | V18: =V15*V32 -> 954.53351 | W18: =W15*W32 -> 1197.5562 | X18: =X15*X32 -> 1434.1242 | Y18: =Y15*Y32 -> 1646.8944 | Z18: =Z15*Z32 -> 1928.8589 | AA18: =AA15*AA32 -> 2201.0185 | AB18: =AB15*AB32 -> 2457.4503 | ... AD18: =AD15*AD32 -> 2875.9243
B19: S&M | C19: 55.334 | D19: 276.246 | E19: 79.29 | F19: =472.076-SUM(C19:E19) -> 61.206 | G19: 68.84 | H19: 97.701 | I19: 274.759 | J19: =575.508-SUM(G19:I19) -> 134.208 | K19: 125.568 | L19: 154.856 | R19: 201.377 | S19: =SUM(C19:F19) -> 472.076 | T19: =SUM(G19:J19) -> 575.508 | U19: =U15*U33 -> 588.17152 | V19: =V15*V33 -> 780.98196 | W19: =W15*W33 -> 993.09535 | X19: =X15*X33 -> 1207.6835 | Y19: =Y15*Y33 -> 1411.6238 | Z19: =Z15*Z33 -> 1645.2032 | AA19: =AA15*AA33 -> 1867.5308 | AB19: =AB15*AB33 -> 2073.4737 | ... AD19: =AD15*AD33 -> 2396.6036
B20: G&A | C20: 22.873 | D20: 220.005 | E20: 43.8 | F20: =315.734-SUM(C20:E20) -> 29.056 | G20: 30.233 | H20: 38.922 | I20: 371.425 | J20: =555.51-SUM(G20:I20) -> 114.93 | K20: 103.629 | L20: 104.715 | R20: 167.679 | S20: =SUM(C20:F20) -> 315.734 | T20: =SUM(G20:J20) -> 555.51 | U20: =U15*U34 -> 433.38954 | V20: =V15*V34 -> 542.34858 | W20: =W15*W34 -> 642.59111 | X20: =X15*X34 -> 717.06211 | Y20: =Y15*Y34 -> 799.92015 | Z20: =Z15*Z34 -> 850.96715 | AA20: =AA15*AA34 -> 867.06789 | AB20: =AB15*AB34 -> 921.54386 | ... AD20: =AD15*AD34 -> 958.64144
B21: OI | C21: =C17-SUM(C18:C20) -> 12.492 | D21: =D17-SUM(D18:D20) -> -894.287 | E21: =E17-SUM(E18:E20) -> -47.336 | F21: =F17-SUM(F18:F20) -> 51.698 | G21: =G17-SUM(G18:G20) -> 39.749 | H21: =H17-SUM(H18:H20) -> 2.076 | I21: =I17-SUM(I18:I20) -> -1136.78 | J21: =J17-SUM(J18:J20) -> -195.502 | ... L21: =L17-SUM(L18:L20) -> -117.289 | R21: =R17-SUM(R18:R20) -> -73.456 | S21: =SUM(C21:F21) -> -877.433 | T21: =SUM(G21:J21) -> -1290.457 | U21: =U17-SUM(U18:U20) -> -488.68343 | V21: =V17-SUM(V18:V20) -> -489.68377 | W21: =W17-SUM(W18:W20) -> -425.63986 | X21: =X17-SUM(X18:X20) -> -248.04207 | Y21: =Y17-SUM(Y18:Y20) -> 20.121639 | Z21: =Z17-SUM(Z18:Z20) -> 251.18437 | AA21: =AA17-SUM(AA18:AA20) -> 562.10194 | AB21: =AB17-SUM(AB18:AB20) -> 877.58833 | ... AD21: =AD17-SUM(AD18:AD20) -> 1670.6846
B22: Other Income | C22: 17.185 | D22: 10.139 | E22: 17.91 | F22: =84.362-SUM(C22:E22) -> 39.128 | G22: 7.274 | H22: 36.978 | I22: 29.305 | J22: =64.815-SUM(G22:I22) -> -8.742 | K22: -4.325 | L22: 7.614 | R22: 1019.375 | S22: =SUM(C22:F22) -> 84.362 | T22: =SUM(G22:J22) -> 64.815 | U22: =SUM(T39:T41)*($AN$39) -> 334.3036 | V22: =SUM(U39:U41)*($AN$39) -> 302.81011 | W22: =SUM(V39:V41)*($AN$39) -> 264.68789 | X22: =SUM(W39:W41)*($AN$39) -> 231.85369 | Y22: =SUM(X39:X41)*($AN$39) -> 228.55126 | Z22: =SUM(Y39:Y41)*($AN$39) -> 279.28053 | AA22: =SUM(Z39:Z41)*($AN$39) -> 387.49537 | AB22: =SUM(AA39:AA41)*($AN$39) -> 581.21322 | ... AD22: =SUM(AC39:AC41)*($AN$39) -> 1312.8683
B23: Pretax Income | C23: =C21+C22 -> 29.677 | D23: =D21+D22 -> -884.148 | E23: =E21+E22 -> -29.426 | F23: =F21+F22 -> 90.826 | G23: =G21+G22 -> 47.023 | H23: =H21+H22 -> 39.054 | I23: =I21+I22 -> -1107.475 | J23: =J21+J22 -> -204.244 | ... L23: =L21+L22 -> -109.675 | R23: =R21+R22 -> 945.919 | S23: =SUM(C23:F23) -> -793.071 | T23: =SUM(G23:J23) -> -1225.642 | U23: =U21+U22 -> -154.37983 | V23: =V21+V22 -> -186.87366 | W23: =W21+W22 -> -160.95197 | X23: =X21+X22 -> -16.188381 | Y23: =Y21+Y22 -> 248.6729 | Z23: =Z21+Z22 -> 530.4649 | AA23: =AA21+AA22 -> 949.59731 | AB23: =AB21+AB22 -> 1458.8015 | ... AD23: =AD21+AD22 -> 2983.5529
B24: Taxes | C24: 16.181 | D24: -56.294 | E24: -13.828 | F24: =-60.951-SUM(C24:E24) -> -7.01 | G24: 2.141 | H24: 10.827 | I24: -10.46 | J24: =24.821-SUM(G24:I24) -> 22.313 | K24: 0.678 | L24: 2.477 | R24: 208.078 | S24: =SUM(C24:F24) -> -60.951 | T24: =SUM(G24:J24) -> 24.821 | U24: =U23*U36 -> 3.0875967 | V24: =V23*V36 -> 3.7374731 | W24: =W23*W36 -> 3.2190395 | X24: =X23*X36 -> 0.32376761 | Y24: =Y23*Y36 -> -4.9734579 | Z24: =Z23*Z36 -> -10.609298 | AA24: =AA23*AA36 -> -18.991946 | AB24: =AB23*AB36 -> -29.176031 | ... AD24: =AD23*AD36 -> -59.671057
B25: Net Income | C25: =C23-C24 -> 13.496 | D25: =D23-D24 -> -827.854 | E25: =E23-E24 -> -15.598 | F25: =F23-F24 -> 97.836 | G25: =G23-G24 -> 44.882 | H25: =H23-H24 -> 28.227 | I25: =I23-I24 -> -1097.015 | J25: =J23-J24 -> -226.557 | ... L25: =L23-L24 -> -112.152 | R25: =R23-R24 -> 737.841 | S25: =SUM(C25:F25) -> -732.12 | T25: =SUM(G25:J25) -> -1250.463 | U25: =U23-U24 -> -157.46743 | V25: =V23-V24 -> -190.61113 | W25: =W23-W24 -> -164.17101 | X25: =X23-X24 -> -16.512148 | Y25: =Y23-Y24 -> 253.64635 | Z25: =Z23-Z24 -> 541.0742 | AA25: =AA23-AA24 -> 968.58925 | AB25: =AB23-AB24 -> 1487.9776 | ... AD25: =AD23-AD24 -> 3043.2239
B26: non-controlling interests | C26: -13.525 | D26: 0 | E26: 0 | F26: =0-SUM(C26:E26) -> 13.525 | G26: -36.271 | H26: -27.381 | I26: 0 | J26: =0-SUM(G26:I26) -> 63.652 | K26: 0 | L26: 0 | R26: -451.982 | S26: =SUM(C26:F26) -> 0 | T26: =SUM(G26:J26) -> 0 | U26: 0 | V26: 0 | W26: 0 | X26: 0 | Y26: 0 | Z26: 0 | AA26: 0 | AB26: 0 | AC26: 0 | AD26: 0
B27: Net Income attr to FIG | C27: =C25+C26 -> -0.029 | D27: =D25+D26 -> -827.854 | E27: =E25+E26 -> -15.598 | F27: =F25+F26 -> 111.361 | G27: =G25+G26 -> 8.611 | H27: =H25+H26 -> 0.846 | I27: =I25+I26 -> -1097.015 | J27: =J25+J26 -> -162.905 | ... L27: =L25+L26 -> -112.152 | R27: =R25+R26 -> 285.859 | S27: =SUM(C27:F27) -> -732.12 | T27: =SUM(G27:J27) -> -1250.463 | U27: =U25+U26 -> -157.46743 | V27: =V25+V26 -> -190.61113 | W27: =W25+W26 -> -164.17101 | X27: =X25+X26 -> -16.512148 | Y27: =Y25+Y26 -> 253.64635 | Z27: =Z25+Z26 -> 541.0742 | AA27: =AA25+AA26 -> 968.58925 | AB27: =AB25+AB26 -> 1487.9776 | ... AD27: =AD25+AD26 -> 3043.2239 | AE27: =AD27*(1+$AN$40) -> 3111.6964 | AF27: =AE27*(1+$AN$40) -> 3181.7096 | AG27: =AF27*(1+$AN$40) -> 3253.2981 | AH27: =AG27*(1+$AN$40) -> 3326.4973 | AI27: =AH27*(1+$AN$40) -> 3401.3435 | AJ27: =AI27*(1+$AN$40) -> 3477.8737 | AK27: =AJ27*(1+$AN$40) -> 3556.1259 | AL27: =AK27*(1+$AN$40) -> 3636.1387 | ... CB27: =CA27*(1+$AN$40) -> 9257.6283
B28: SC | C28: 180.6 | D28: 188.782 | E28: 210.768 | F28: 195.612 | G28: 214.883 | H28: 215.062 | I28: 403.212 | J28: 337.044 | K28: 523.485 | L28: 527.46 | R28: 168.399 | S28: =AVERAGE(C28:F28) -> 193.9405 | T28: =AVERAGE(G28:J28) -> 292.55025
B29: EPS | C29: =C27/C28 -> -0.00016057586 | D29: =D27/D28 -> -4.385238 | E29: =E27/E28 -> -0.074005542 | F29: =F27/F28 -> 0.56929534 | G29: =G27/G28 -> 0.04007297 | H29: =H27/H28 -> 0.0039337493 | I29: =I27/I28 -> -2.7206904 | J29: =J27/J28 -> -0.48333452 | ... L29: =L27/L28 -> -0.21262655 | R29: =R27/R28 -> 1.6975101 | S29: =SUM(C29:F29) -> -3.8901088 | T29: =SUM(G29:J29) -> -3.1600182
B31: Gross Profit Margin | C31: =C17/C15 -> 0.9181178 | D31: =D17/D15 -> 0.7767582 | E31: =E17/E15 -> 0.90584427 | F31: =F17/F15 -> 0.92412455 | G31: =G17/G15 -> 0.91475861 | H31: =H17/H15 -> 0.88828313 | I31: =I17/I15 -> 0.69404719 | J31: =J17/J15 -> 0.82124328 | ... L31: =L17/L15 -> 0.83659882 | R31: =R17/R15 -> 0.9118592 | S31: =S17/S15 -> 0.88316059 | T31: =T17/T15 -> 0.82427628 | U31: 0.82427628 | V31: 0.82427628 | W31: 0.82427628 | X31: 0.82427628 | Y31: 0.82427628 | Z31: 0.82427628 | AA31: 0.82427628 | AB31: 0.82427628 | AC31: 0.82427628 | AD31: 0.82427628
B32: R&D as % of Revenue | C32: =C18/C15 -> 0.33745839 | D32: =D18/D15 -> 3.0230364 | E32: =E18/E15 -> 0.52447908 | F32: =F18/F15 -> 0.26985261 | G32: =G18/G15 -> 0.30642115 | H32: =H18/H15 -> 0.33268707 | I32: =I18/I15 -> 2.4834138 | J32: =J18/J15 -> 0.64467897 | ... L32: =L18/L15 -> 0.45213911 | R32: =R18/R15 -> 0.32636658 | S32: =S18/S15 -> 1.0028157 | T32: =T18/T15 -> 0.97529049 | U32: 0.48 | V32: 0.44 | W32: 0.41 | X32: 0.38 | Y32: 0.35 | Z32: 0.34 | AA32: 0.33 | AB32: 0.32 | AC32: 0.31 | AD32: 0.3
B33: S&M as % of Revenue | C33: =C19/C15 -> 0.35425096 | D33: =D19/D15 -> 1.5589679 | E33: =E19/E15 -> 0.39916633 | F33: =F19/F15 -> 0.2820891 | G33: =G19/G15 -> 0.30166653 | H33: =H19/H15 -> 0.39136757 | I33: =I19/I15 -> 1.0021373 | J33: =J19/J15 -> 0.44179922 | ... L33: =L19/L15 -> 0.41843586 | R33: =R19/R15 -> 0.39886586 | S33: =S19/S15 -> 0.63026578 | T33: =T19/T15 -> 0.54509807 | U33: 0.38 | V33: 0.36 | W33: 0.34 | X33: 0.32 | Y33: 0.3 | Z33: 0.29 | AA33: 0.28 | AB33: 0.27 | AC33: 0.26 | AD33: 0.25
B34: G&A as % of Revenue | C34: =C20/C15 -> 0.14643406 | D34: =D20/D15 -> 1.2415772 | E34: =E20/E15 -> 0.22050051 | F34: =F20/F15 -> 0.13391466 | G34: =G20/G15 -> 0.13248524 | H34: =H20/H15 -> 0.15591251 | I34: =I20/I15 -> 1.3547103 | J34: =J20/J15 -> 0.37833799 | ... L34: =L20/L15 -> 0.28295004 | R34: =R20/R15 -> 0.33212049 | S34: =S20/S15 -> 0.42153453 | T34: =T20/T15 -> 0.52615677 | U34: 0.28 | V34: 0.25 | W34: 0.22 | X34: 0.19 | Y34: 0.17 | Z34: 0.15 | AA34: 0.13 | AB34: 0.12 | AC34: 0.11 | AD34: 0.1
B35: Operating Profit Margin | C35: =C21/C15 -> 0.079974392 | D35: =D21/D15 -> -5.0468233 | E35: =E21/E15 -> -0.23830164 | F35: =F21/F15 -> 0.23826818 | G35: =G21/G15 -> 0.17418569 | H35: =H21/H15 -> 0.008315975 | I35: =I21/I15 -> -4.1462143 | J35: =J21/J15 -> -0.6435729 | ... L35: =L21/L15 -> -0.3169262 | R35: =R21/R15 -> -0.14549373 | S35: =S21/S15 -> -1.1714554 | T35: =T21/T15 -> -1.2222691 | U35: =U21/U15 -> -0.31572372 | V35: =V21/V15 -> -0.22572372 | W35: =W21/W15 -> -0.14572372 | X35: =X21/X15 -> -0.065723725 | Y35: =Y21/Y15 -> 0.0042762752 | ... AD35: =AD21/AD15 -> 0.17427628
B36: Effective Tax Rate | C36: =C24/C23 -> 0.54523705 | D36: =D24/D23 -> 0.063670336 | E36: =E24/E23 -> 0.46992456 | F36: =F24/F23 -> -0.077180543 | G36: =G24/G23 -> 0.04553091 | H36: =H24/H23 -> 0.27723153 | I36: =I24/I23 -> 0.0094449085 | J36: =J24/J23 -> -0.10924678 | ... L36: =L24/L23 -> -0.02258491 | R36: =R24/R23 -> 0.21997444 | S36: =S24/S23 -> 0.076854405 | T36: =T24/T23 -> -0.020251427 | U36: -0.02 | V36: -0.02 | W36: -0.02 | X36: -0.02 | Y36: -0.02 | Z36: -0.02 | AA36: -0.02 | AB36: -0.02 | AC36: -0.02 | AD36: -0.02
B37: Net Profit Margin | C37: =C27/C15 -> -0.00018565941 | D37: =D27/D15 -> -4.671915 | E37: =E27/E15 -> -0.078524358 | F37: =F27/F15 -> 0.51324583 | G37: =G27/G15 -> 0.037734609 | H37: =H27/H15 -> 0.00338888 | I37: =I27/I15 -> -4.0011781 | J37: =J27/J15 -> -0.53626685 | ... L37: =L27/L15 -> -0.30304553 | R37: =R27/R15 -> 0.5661987 | S37: =S27/S15 -> -0.97744893 | T37: =T27/T15 -> -1.1843883 | U37: =U27/U15 -> -0.10173499 | V37: =V27/V15 -> -0.087863753 | W37: =W27/W15 -> -0.056206229 | X37: =X27/X15 -> -0.0043752252 | Y37: =Y27/Y15 -> 0.053905231 | ... AD37: =AD27/AD15 -> 0.31745174
B39: Cash & CEs | F39: 486.954 | G39: 571 | H39: 621.619 | I39: 340.485 | J39: 403.469 | K39: 405.654 | L39: 445.845 | S39: =F39 -> 486.954 | T39: =J39 -> 403.469 | U39: =SUM(T39:T41)+U27 -> 1514.0506 | V39: =U39+V27 -> 1323.4394 | W39: =V39+W27 -> 1159.2684 | X39: =W39+X27 -> 1142.7563 | Y39: =X39+Y27 -> 1396.4026 | Z39: =Y39+Z27 -> 1937.4768 | AA39: =Z39+AA27 -> 2906.0661 | AB39: =AA39+AB27 -> 4394.0437 | AC39: =AB39+AC27 -> 6564.3413 | AD39: =AC39+AD27 -> 9607.5652 | AF39: Invested Capital | AI39: Avg. (2024-2025) | AK39: Projected ROIC: | AM39: ROIC | AN39: 0.2
B40: ST Investments | F40: 0 | G40: 0 | H40: 30.136 | I40: 30.32 | J40: 15.575 | K40: 15.696 | L40: 15.82 | S40: =F40 -> 0 | T40: =J40 -> 15.575 | AF40: 2024 | AG40: 2025 | AI40: 2024-2025 | AK40: 2025 | AM40: Terminal | AN40: 0.0225
B41: Marketable Securities | F41: 970.883 | G41: 970.8 | H41: 971.719 | I41: 1237.048 | J41: 1252.474 | K41: 1232.81 | L41: 1221.293 | S41: =F41 -> 970.883 | T41: =J41 -> 1252.474 | AF41: =SUM(S39:S43)-S53+S46+S48+S47 -> 1676.577 | AG41: =SUM(T39:T43)-T53+T46+T48+T47 -> 2174.121 | AI41: =AVERAGE(AF41:AG41) -> 1925.349 | AK41: =U21*(1-U36) -> -498.4571 | AM41: RFR (10-year yield) | AN41: =AI50 -> 0.0517
B42: A/R | F42: 131.315 | G42: 373 | H42: 124.721 | I42: 156.004 | J42: 247.915 | K42: 188.351 | L42: 190.876 | S42: =F42 -> 131.315 | T42: =J42 -> 247.915 | AK42: =AK41/AI41 -> -0.25889182 | AM42: ERP (Avg. market return - (less) RFR) | AN42: =9.5%-AN41 -> 0.0433
B43: Other ST Assets | F43: 48.873 | H43: 60.059 | I43: 79.904 | J43: 85.267 | K43: 93.882 | L43: 103.206 | S43: =F43 -> 48.873 | T43: =J43 -> 85.267 | AF43: Capital Structure | AM43: Equity β (1-year avg.) | AN43: ='Notes | Quant Analysis'!S206 -> 1.604688
B44: PP&E | F44: 15.017 | H44: 16.593 | I44: 17.946 | J44: 19.996 | K44: 30.982 | L44: 38.321 | S44: =F44 -> 15.017 | T44: =J44 -> 19.996 | AF44: Mkt Cap | AI44: =Main!C5 -> 10899.971 | AM44: Discount (Cost of Equity) | AN44: =+AN41+(AN42*AN43) -> 0.12118299
B45: LT Investments | F45: 0 | H45: 0 | I45: 0 | J45: 19.083 | K45: 12.663 | L45: 13.371 | S45: =F45 -> 0 | T45: =J45 -> 19.083 | AF45: Debt to Ttl Mkt Cap | AI45: =Main!C7/(Main!C7+AI44) -> 0
B46: Intangibles | F46: 2.511 | H46: 13.227 | I46: 16.044 | J46: 15.116 | K46: 11.787 | L46: 10.115 | S46: =F46 -> 2.511 | T46: =J46 -> 15.116 | AF46: Mkt Equity to Ttl Mkt Cap | AI46: =AI44/(AI44+Main!C7) -> 1 | AM46: NPV | AN46: =NPV(AN44,U27:CC27) -> 12717.773
B47: Goodwill | F47: 11.398 | H47: 24.541 | I47: 24.541 | J47: 101.396 | K47: 101.396 | L47: 101.396 | S47: =F47 -> 11.398 | T47: =J47 -> 101.396 | AF47: LT Debt / Equity | AI47: =T52/T61 -> 0 | AM47: SC | AN47: =Main!C4 -> 455.1136
B48: LT Operating Lease Assets | F48: 28.806 | H48: 64.261 | I48: 60.728 | J48: 57.411 | K48: 54.458 | L48: 62.32 | S48: =F48 -> 28.806 | T48: =J48 -> 57.411 | AM48: FV | AN48: =AN46/AN47 -> 27.944172
B49: LT Restricted Cash | F49: 3.631 | H49: 9.799 | I49: 9.799 | J49: 9.799 | K49: 9.8 | L49: 9.8 | S49: =F49 -> 3.631 | T49: =J49 -> 9.799 | AF49: Cost of Equity | AM49: CP | AN49: =Main!C3 -> 23.95
B50: Other LT Assets | F50: 93.76 | H50: 97.988 | I50: 100.406 | J50: 120.706 | K50: 133.309 | L50: 138.911 | S50: =F50 -> 93.76 | T50: =J50 -> 120.706 | AF50: RFR (10-year yield) | AI50: 0.0517 | AM50: Change Δ | AN50: =AN48/AN49-1 -> 0.16677129 | AO50: =IF(AN50>0,"Upside","Downside") -> Upside
B51: Ttl Assets | F51: =SUM(F39:F50) -> 1793.148 | G51: =SUM(G39:G50) -> 1914.8 | H51: =SUM(H39:H50) -> 2034.663 | I51: =SUM(I39:I50) -> 2073.225 | J51: =SUM(J39:J50) -> 2348.207 | K51: =SUM(K39:K50) -> 2290.788 | L51: =SUM(L39:L50) -> 2351.274 | S51: =F51 -> 1793.148 | T51: =J51 -> 2348.207 | AF51: Equity β (1-year avg.) | AI51: ='Notes | Quant Analysis'!S206 -> 1.604688 | AM51: {=_xlfn.IFS(AN50>=25%,"Strong Buy",AN50>=10.00001%,"Buy",AND(AN50<=10%,AN50>=-4.9999%),"Hold",AND(AN50<=-5%,AN50>=-14.999999%),"Sell",AN50<=-15%,"Strong Sell")} -> Buy
AF52: Market Return(1-year avg.) | AI52: 0.16
B53: A/P | F53: 4.163 | G53: 544.391 | H53: 12.029 | I53: 13.364 | J53: 4.502 | K53: 8.928 | L53: 26.149 | S53: =F53 -> 4.163 | T53: =J53 -> 4.502 | AF53: Cost of Equity | AI53: =(AI50+AI51)*(AI52-AI50) -> 0.17938682
B54: ST Accrued & Other Liabilities | F54: 31.119 | H54: 52.761 | I54: 51.84 | J54: 66.535 | K54: 82.157 | L54: 91.557 | S54: =F54 -> 31.119 | T54: =J54 -> 66.535
B55: ST Comp Liabilities | F55: 19.377 | H55: 39.225 | I55: 79.031 | J55: 107.105 | K55: 53.173 | L55: 53.528 | S55: =F55 -> 19.377 | T55: =J55 -> 107.105 | AF55: Cost of Debt
B56: ST Operating Lease Liabilities | F56: 10.937 | H56: 9.4 | I56: 4.677 | J56: 2.63 | K56: 2.54 | L56: 8.661 | S56: =F56 -> 10.937 | T56: =J56 -> 2.63 | AF56: Cost of Debt | AI56: 0
B57: ST Deferred Revenues | F57: 381.363 | H57: 433.147 | I57: 473.567 | J57: 595.334 | K57: 627.664 | L57: 626.783 | S57: =F57 -> 381.363 | T57: =J57 -> 595.334 | AF57: Tax Rate | AI57: 0.146
B58: LT Operating Lease | F58: 17.833 | H58: 55.298 | I58: 56.559 | J58: 55.845 | K58: 53.624 | L58: 59.09 | S58: =F58 -> 17.833 | T58: =J58 -> 55.845 | AF58: After Tax Cost of Debt | AI58: =AI56*(1-AI57) -> 0
B59: Other LT Liabilities | F59: 4.303 | H59: 5.589 | I59: 5.667 | J59: 5.615 | K59: 5.741 | L59: 7.599 | S59: =F59 -> 4.303 | T59: =J59 -> 5.615
B60: Ttl Liabilities | F60: =SUM(F53:F59) -> 469.095 | G60: =SUM(G53:G59) -> 544.391 | H60: =SUM(H53:H59) -> 607.449 | I60: =SUM(I53:I59) -> 684.705 | J60: =SUM(J53:J59) -> 837.566 | K60: =SUM(K53:K59) -> 833.827 | L60: =SUM(L53:L59) -> 873.367 | S60: =F60 -> 469.095 | T60: =J60 -> 837.566 | AF60: WACC | AI60: =(AI46*AI53)+(AI45*AI58*(1-AI57)) -> 0.17938682
B61: Ttl SE | F61: 1324.053 | G61: 1370.36 | H61: 1427.214 | I61: 1388.52 | J61: 1510.641 | K61: 1456.961 | L61: 1477.907 | S61: =F61 -> 1324.053 | T61: =J61 -> 1510.641
B62: Ttl L + SE | F62: =F60+F61 -> 1793.148 | G62: =G60+G61 -> 1914.751 | H62: =H60+H61 -> 2034.663 | I62: =I60+I61 -> 2073.225 | J62: =J60+J61 -> 2348.207 | K62: =K60+K61 -> 2290.788 | L62: =L60+L61 -> 2351.274 | S62: =F62 -> 1793.148 | T62: =J62 -> 2348.207
B64: Current Ratio | F64: =SUM(F39:F44)/SUM(F53:F57) -> 3.6984198 | G64: =SUM(G39:G44)/SUM(G53:G57) -> 3.5173249 | H64: =SUM(H39:H44)/SUM(H53:H57) -> 3.338774 | I64: =SUM(I39:I44)/SUM(I53:I57) -> 2.9907949 | J64: =SUM(J39:J44)/SUM(J53:J57) -> 2.608788 | K64: =SUM(K39:K44)/SUM(K53:K57) -> 2.5403119 | L64: =SUM(L39:L44)/SUM(L53:L57) -> 2.4983463 | S64: =SUM(S39:S44)/SUM(S53:S57) -> 3.6984198 | T64: =SUM(T39:T44)/SUM(T53:T57) -> 2.608788
B65: Cash Ratio | F65: =SUM(F39:F41)/SUM(F53:F57) -> 3.2616795 | G65: =SUM(G39:G41)/SUM(G53:G57) -> 2.8321556 | H65: =SUM(H39:H41)/SUM(H53:H57) -> 2.9703382 | I65: =SUM(I39:I41)/SUM(I53:I57) -> 2.5829835 | J65: =SUM(J39:J41)/SUM(J53:J57) -> 2.1537238 | K65: =SUM(K39:K41)/SUM(K53:K57) -> 2.1358827 | L65: =SUM(L39:L41)/SUM(L53:L57) -> 2.0862823 | S65: =SUM(S39:S41)/SUM(S53:S57) -> 3.2616795 | T65: =SUM(T39:T41)/SUM(T53:T57) -> 2.1537238
B66: Fixed Asset Turnover Ratio | F66: =F48/F15 -> 0.13276245 | G66: =G48/G15 -> 0 | H66: =H48/H15 -> 0.25741468 | I66: =I48/I15 -> 0.22149519 | J66: =J48/J15 -> 0.18899123 | K66: =K48/K15 -> 0.16332223 | L66: =L48/L15 -> 0.16839466 | S66: =S48/S15 -> 0.038458714 | T66: =T48/T15 -> 0.054377394
B67: Ttl Asset Turnover Ratio | F67: =F51/F15 -> 8.264345 | G67: =G51/G15 -> 8.390922 | H67: =H51/H15 -> 8.1503886 | I67: =I51/I15 -> 7.5617402 | J67: =J51/J15 -> 7.730061 | K67: =K51/K15 -> 6.8701862 | L67: =L51/L15 -> 6.3533694 | S67: =S51/S15 -> 2.3940209 | T67: =T51/T15 -> 2.2241274
B68: Return on Assets | F68: =F62/F27 -> 16.102118 | G68: =G62/G27 -> 222.36105 | H68: =H62/H27 -> 2405.039 | I68: =I62/I27 -> -1.8898784 | J68: =J62/J27 -> -14.414579 | K68: =K62/K27 -> -16.086881 | L68: =L62/L27 -> -20.965065 | S68: =S62/S27 -> -2.4492542 | T68: =T62/T27 -> -1.87787
B69: Return on Equity | F69: =F61/F27 -> 11.889737 | G69: =G61/G27 -> 159.14063 | H69: =H61/H27 -> 1687.0142 | I69: =I61/I27 -> -1.2657256 | J69: =J61/J27 -> -9.2731408 | K69: =K61/K27 -> -10.231396 | L69: =L61/L27 -> -13.177714 | S69: =S61/S27 -> -1.8085191 | T69: =T61/T27 -> -1.2080653
B71: Net Income | F71: =F27 -> 111.361 | G71: =G27 -> 8.611 | H71: =H27 -> 0.846 | I71: =I27 -> -1097.015 | J71: =J27 -> -162.905 | K71: =K27 -> -142.401 | L71: =L27 -> -112.152 | S71: =SUM(C71:F71) -> 111.361 | T71: =SUM(G71:J71) -> -1250.463
B72: CFFO | F72: 73.091 | G72: 97.177 | H72: 62.455 | I72: 51.163 | J72: 39.886 | K72: 97.308 | L72: 60.893 | S72: =SUM(C72:F72) -> 73.091 | T72: =SUM(G72:J72) -> 250.681
B73: CapEx, net | F73: -2.266 | G73: -2.595 | H73: -1.852 | I73: -2.116 | J73: -1.434 | K73: -8.7 | L73: -7.683 | S73: =SUM(C73:F73) -> -2.266 | T73: =SUM(G73:J73) -> -7.997
B74: FCF | F74: =F72+F73 -> 70.825 | G74: =G72+G73 -> 94.582 | H74: =H72+H73 -> 60.603 | I74: =I72+I73 -> 49.047 | J74: =J72+J73 -> 38.452 | K74: =K72+K73 -> 88.608 | L74: =L72+L73 -> 53.21 | S74: =SUM(C74:F74) -> 70.825 | T74: =SUM(G74:J74) -> 242.684
B75: SC | F75: =F28 -> 195.612 | G75: =G28 -> 214.883 | H75: =H28 -> 215.062 | I75: =I28 -> 403.212 | J75: =J28 -> 337.044 | K75: =K28 -> 523.485 | L75: =L28 -> 527.46 | S75: =S28 -> 193.9405 | T75: =T28 -> 292.55025
B76: FCF per Share | F76: =F74/F75 -> 0.36206879 | G76: =G74/G75 -> 0.44015581 | H76: =H74/H75 -> 0.28179316 | I76: =I74/I75 -> 0.12164072 | J76: =J74/J75 -> 0.11408599 | K76: =K74/K75 -> 0.1692656 | L76: =L74/L75 -> 0.10087969 | S76: =SUM(C76:F76) -> 0.36206879 | T76: =SUM(G76:J76) -> 0.95767568
B78: CFFO Margin | F78: =F72/F15 -> 0.33686525 | G78: =G72/G15 -> 0.42584323 | H78: =H72/H15 -> 0.25018026 | I78: =I72/I15 -> 0.18660846 | J78: =J72/J15 -> 0.1313007 | K78: =K72/K15 -> 0.29183149 | L78: =L72/L15 -> 0.16453877 | S78: =S72/S15 -> 0.097583347 | T78: =T72/T15 -> 0.23743498
B79: FCF Margin | F79: =F74/F15 -> 0.3264216 | G79: =G74/G15 -> 0.41447158 | H79: =H74/H15 -> 0.24276158 | I79: =I74/I15 -> 0.1788907 | J79: =J74/J15 -> 0.12658011 | K79: =K74/K15 -> 0.26573976 | L79: =L74/L15 -> 0.14377856 | S79: =S74/S15 -> 0.094558024 | T79: =T74/T15 -> 0.22986054
B80: CapEx as % of Revenue | F80: =F73/F15 -> -0.010443648 | G80: =G73/G15 -> -0.011371654 | H80: =H73/H15 -> -0.0074186829 | I80: =I73/I15 -> -0.0077177548 | J80: =J73/J15 -> -0.0047205836 | K80: =K73/K15 -> -0.026091729 | L80: =L73/L15 -> -0.020760208 | S80: =S73/S15 -> -0.0030253227 | T80: =T73/T15 -> -0.0075744373

Sheet Notes | Quant Analysis
CL1: 0
P2: Employee Scope: | AO2: General Notes/Observations
Q32: Notes: | R32: [X]
R33: [Y]
R34: [Z]
AO35: Financial Stmts. Notes/Observations
P36: Institutional Ownership Snapshot | AO36: Revenues:
Q65: Notes: | R65: [X]
R66: [Y]
R67: [Z]
P69: Revenue Breakdown by Segment (Build graph for this section if applicable…. See example below) | AO69: Earnings Scope:
Q101: Notes: | R101: [X]
R102: [Y]
R103: [Z]
P105: Q/q Total Revenues, Net Income, FCF | AO105: Balance Sheet Scope:
Q134: Notes: | R134: [X]
R135: [Y]
R136: [Z]
P138: Y/y Total Revenues, Net Income, FCF | AO138: [Equity Preformance Compared to Peers]
Q167: Notes: | R167: [X]
R168: [Y]
R169: [Z]
A184: VOO Historical Returns | I184: FIG Historical Returns
A185: 252 Trading Days? (From: 10/22/2026 - 10/22/2026) | I185: 252 Trading Days? (From: 10/22/2026 - 10/22/2026)
A186: Close | B186: High | C186: Low | D186: Open | E186: Volume | F186: UTC Date | G186: Change | I186: Close | J186: High | K186: Low | L186: Open | M186: Volume | N186: UTC Date | O186: Change
A187: 702.3 | B187: 705.66 | C187: 699.68 | D187: 704.41 | E187: 6041430.3 | F187: Thu, 22 Oct 2026 00:00:00 GMT | G187: =A187/D187-1 -> -0.0029954146 | I187: 24.1 | J187: 24.38 | K187: 22.95 | L187: 23.18 | M187: 14463544 | N187: Thu, 22 Oct 2026 00:00:00 GMT | O187: =I187/L187-1 -> 0.039689387
A188: 710.72 | B188: 711.83 | C188: 706.33 | D188: 708.84 | E188: 6210315.6 | F188: Wed, 21 Oct 2026 00:00:00 GMT | G188: =A188/D188-1 -> 0.0026522205 | I188: 22.98 | J188: 23.49 | K188: 22.49 | L188: 22.785 | M188: 7603418.2 | N188: Wed, 21 Oct 2026 00:00:00 GMT | O188: =I188/L188-1 -> 0.008558262
A189: 706.8 | B189: 709.81 | C189: 702.49 | D189: 704.01 | E189: 5798006.5 | F189: Tue, 20 Oct 2026 00:00:00 GMT | G189: =A189/D189-1 -> 0.0039630119 | I189: 22.71 | J189: 23.26 | K189: 21.56 | L189: 21.78 | M189: 15122660 | N189: Tue, 20 Oct 2026 00:00:00 GMT | O189: =I189/L189-1 -> 0.042699725
A190: 704.6 | B190: 708.17 | C190: 703.9805 | D190: 705.27 | E190: 5588525.7 | F190: Mon, 19 Oct 2026 00:00:00 GMT | G190: =A190/D190-1 -> -0.00094999078 | I190: 21.54 | J190: 21.845 | K190: 21.14 | L190: 21.3 | M190: 6379348.3 | N190: Mon, 19 Oct 2026 00:00:00 GMT | O190: =I190/L190-1 -> 0.011267606
A191: 701.61 | B191: 710.85 | C191: 699.191 | D191: 710.75 | E191: 6095662.4 | F191: Fri, 16 Oct 2026 00:00:00 GMT | G191: =A191/D191-1 -> -0.012859655 | I191: 21.49 | J191: 23.53 | K191: 21.33 | L191: 23.3 | M191: 9254550.3 | N191: Fri, 16 Oct 2026 00:00:00 GMT | O191: =I191/L191-1 -> -0.077682403
A192: 709.43 | B192: 710.4 | C192: 702.69 | D192: 704.33 | E192: 6035492.3 | F192: Thu, 15 Oct 2026 00:00:00 GMT | G192: =A192/D192-1 -> 0.007240924 | I192: 22.99 | J192: 23.09 | K192: 21.25 | L192: 21.31 | M192: 14702774 | N192: Thu, 15 Oct 2026 00:00:00 GMT | O192: =I192/L192-1 -> 0.078836227
A193: 707.43 | B193: 713.62 | C193: 704.76 | D193: 712.32 | E193: 6228217.1 | F193: Wed, 14 Oct 2026 00:00:00 GMT | G193: =A193/D193-1 -> -0.0068648922 | I193: 21.48 | J193: 21.94 | K193: 21.08 | L193: 21.39 | M193: 12474997 | N193: Wed, 14 Oct 2026 00:00:00 GMT | O193: =I193/L193-1 -> 0.0042075736
A194: 715.2 | B194: 715.835 | C194: 713.27 | D194: 714.54 | E194: 4959098.4 | F194: Tue, 13 Oct 2026 00:00:00 GMT | G194: =A194/D194-1 -> 0.00092367117 | I194: 21.76 | J194: 23.045 | K194: 21.76 | L194: 22.09 | M194: 12282745 | N194: Tue, 13 Oct 2026 00:00:00 GMT | O194: =I194/L194-1 -> -0.014938886
A195: 715.13 | B195: 716.415 | C195: 714.26 | D195: 715.81 | E195: 3635491.2 | F195: Mon, 12 Oct 2026 00:00:00 GMT | G195: =A195/D195-1 -> -0.00094997276 | I195: 21.96 | J195: 22.2863 | K195: 21.385 | L195: 22.23 | M195: 9125955 | N195: Mon, 12 Oct 2026 00:00:00 GMT | O195: =I195/L195-1 -> -0.012145749
A196: 715.59 | B196: 716.435 | C196: 712.54 | D196: 713.54 | E196: 4345835.7 | F196: Fri, 09 Oct 2026 00:00:00 GMT | G196: =A196/D196-1 -> 0.0028729994 | I196: 22.5 | J196: 23.19 | K196: 22.23 | L196: 22.71 | M196: 7799882.4 | N196: Fri, 09 Oct 2026 00:00:00 GMT | O196: =I196/L196-1 -> -0.0092470277
A197: 711.28 | B197: 714.27 | C197: 708.16 | D197: 712.25 | E197: 4763330.7 | F197: Thu, 08 Oct 2026 00:00:00 GMT | G197: =A197/D197-1 -> -0.0013618814 | I197: 22.63 | J197: 22.665 | K197: 21.45 | L197: 21.62 | M197: 10579588 | N197: Thu, 08 Oct 2026 00:00:00 GMT | O197: =I197/L197-1 -> 0.046716004
A198: 714.34 | B198: 715.055 | C198: 711.06 | D198: 713.06 | E198: 4675948.1 | F198: Wed, 07 Oct 2026 00:00:00 GMT | G198: =A198/D198-1 -> 0.0017950804 | I198: 21.62 | J198: 22.293 | K198: 21.24 | L198: 22.02 | M198: 5704414.7 | N198: Wed, 07 Oct 2026 00:00:00 GMT | O198: =I198/L198-1 -> -0.018165304
A199: 716.2 | B199: 718.47 | C199: 715.09 | D199: 715.21 | E199: 4568431.3 | F199: Tue, 06 Oct 2026 00:00:00 GMT | G199: =A199/D199-1 -> 0.0013842088 | I199: 21.93 | J199: 22.315 | K199: 21.8 | L199: 22.21 | M199: 6759920.1 | N199: Tue, 06 Oct 2026 00:00:00 GMT | O199: =I199/L199-1 -> -0.012606934
A200: 712.32 | B200: 713.8583 | C200: 707.42 | D200: 707.44 | E200: 6172916.9 | F200: Mon, 05 Oct 2026 00:00:00 GMT | G200: =A200/D200-1 -> 0.0068981115 | I200: 22.01 | J200: 22.06 | K200: 21.08 | L200: 21.25 | M200: 7726450.3 | N200: Mon, 05 Oct 2026 00:00:00 GMT | O200: =I200/L200-1 -> 0.035764706 | R200: Min | S200: =MIN(O187:O438) -> -0.10444444
A201: 707.54 | B201: 710.2 | C201: 705.12 | D201: 708.31 | E201: 6612533.1 | F201: Fri, 02 Oct 2026 00:00:00 GMT | G201: =A201/D201-1 -> -0.0010870946 | I201: 21.36 | J201: 21.75 | K201: 21.01 | L201: 21.75 | M201: 7927051 | N201: Fri, 02 Oct 2026 00:00:00 GMT | O201: =I201/L201-1 -> -0.017931034 | R201: Max | S201: =MAX(O187:O438) -> 0.11181435
A202: 702.35 | B202: 703.725 | C202: 697.47 | D202: 702.555 | E202: 8433749.3 | F202: Thu, 01 Oct 2026 00:00:00 GMT | G202: =A202/D202-1 -> -0.0002917921 | I202: 21.57 | J202: 22.03 | K202: 20.92 | L202: 21.7 | M202: 10993745 | N202: Thu, 01 Oct 2026 00:00:00 GMT | O202: =I202/L202-1 -> -0.0059907834 | R202: Mean μ | S202: =AVERAGE(O187:O438) -> -0.00026135137
A203: 700.86 | B203: 707.2 | C203: 700.56 | D203: 704.58 | E203: 9876125.1 | F203: Wed, 30 Sep 2026 00:00:00 GMT | G203: =A203/D203-1 -> -0.0052797411 | I203: 21.02 | J203: 21.55 | K203: 20.67 | L203: 20.78 | M203: 10538587 | N203: Wed, 30 Sep 2026 00:00:00 GMT | O203: =I203/L203-1 -> 0.011549567 | R203: Median | S203: =MEDIAN(O187:O438) -> -0.0037219657
A204: 702.46 | B204: 705 | C204: 700.74 | D204: 704.82 | E204: 7643258.6 | F204: Tue, 29 Sep 2026 00:00:00 GMT | G204: =A204/D204-1 -> -0.0033483726 | I204: 20.72 | J204: 20.815 | K204: 19.86 | L204: 20.23 | M204: 11148729 | N204: Tue, 29 Sep 2026 00:00:00 GMT | O204: =I204/L204-1 -> 0.024221453 | R204: SD σ | S204: =_xlfn.STDEV.P(O187:O438) -> 0.041772026
A205: 703.61 | B205: 707.33 | C205: 701.97 | D205: 706.29 | E205: 8539385.2 | F205: Mon, 28 Sep 2026 00:00:00 GMT | G205: =A205/D205-1 -> -0.0037944754 | I205: 20.25 | J205: 20.5376 | K205: 19.58 | L205: 20.3 | M205: 10201879 | N205: Mon, 28 Sep 2026 00:00:00 GMT | O205: =I205/L205-1 -> -0.0024630542 | R205: 3σ 1-Day Δ: ± | S205: =3*S204 -> 0.12531608 | U205: <- Sharpe Ratio (Risk Adjusted Return)
A206: 708.9674 | B206: 709.82021 | C206: 704.36423 | D206: 706.62343 | E206: 5482247.9 | F206: Fri, 25 Sep 2026 00:00:00 GMT | G206: =A206/D206-1 -> 0.0033171475 | I206: 20.85 | J206: 21.65 | K206: 20.8 | L206: 21.25 | M206: 10433071 | N206: Fri, 25 Sep 2026 00:00:00 GMT | O206: =I206/L206-1 -> -0.018823529 | R206: β (1-year avg.) | S206: =_xlfn.COVARIANCE.P(O187:O435,G187:G435)/_xlfn.VAR.P(G187:G435) -> 1.604688 | U206: <- Sortino Ratio (Downside Risk Adjusted Return)
A207: 705.17714 | B207: 706.76805 | C207: 701.54548 | D207: 702.26463 | E207: 9443878 | F207: Thu, 24 Sep 2026 00:00:00 GMT | G207: =A207/D207-1 -> 0.0041473149 | I207: 21.34 | J207: 22 | K207: 21.12 | L207: 21.62 | M207: 10739081 | N207: Thu, 24 Sep 2026 00:00:00 GMT | O207: =I207/L207-1 -> -0.012950971
A208: 705.78558 | B208: 710.55332 | C208: 704.55215 | D208: 710.30895 | E208: 13844442 | F208: Wed, 23 Sep 2026 00:00:00 GMT | G208: =A208/D208-1 -> -0.0063681746 | I208: 21.76 | J208: 22.48 | K208: 21.67 | L208: 21.77 | M208: 8946501.5 | N208: Wed, 23 Sep 2026 00:00:00 GMT | O208: =I208/L208-1 -> -0.00045934773 | Q208: n = | R208: 252
A209: 710.9523 | B209: 712.4684 | C209: 710.15435 | D209: 711.45102 | E209: 20783008 | F209: Tue, 22 Sep 2026 00:00:00 GMT | G209: =A209/D209-1 -> -0.00070098699 | I209: 21.8 | J209: 23.19 | K209: 21.07 | L209: 23.17 | M209: 18423931 | N209: Tue, 22 Sep 2026 00:00:00 GMT | O209: =I209/L209-1 -> -0.059128183 | Q209: Histogram Data | T209: Distribution Overlay | X209: SD Lines
A210: 710.9523 | B210: 712.24398 | C210: 704.14979 | D210: 704.3792 | E210: 8882600.7 | F210: Mon, 21 Sep 2026 00:00:00 GMT | G210: =A210/D210-1 -> 0.0093317662 | I210: 22.33 | J210: 22.99 | K210: 22.235 | L210: 22.85 | M210: 10842731 | N210: Mon, 21 Sep 2026 00:00:00 GMT | O210: =I210/L210-1 -> -0.022757112 | Q210: Bin | R210: Frequency | T210: (X) 1-Day Δ | U210: (Y) Pop. Density | X210: X | Y210: Y
A211: 699.9805 | B211: 700.38945 | C211: 696.70891 | D211: 699.78102 | E211: 9618703.4 | F211: Fri, 18 Sep 2026 00:00:00 GMT | G211: =A211/D211-1 -> 0.00028507084 | I211: 22.69 | J211: 23.59 | K211: 22.5563 | L211: 23.505 | M211: 33913582 | N211: Fri, 18 Sep 2026 00:00:00 GMT | O211: =I211/L211-1 -> -0.034673474 | Q211: -0.13 | R211: 0 | T211: -0.13 | U211: =_xlfn.NORM.DIST(T211,$S$202,$S$204,FALSE) -> 0.076793393 | W211: Mean | X211: =S202 -> -0.00026135137 | Y211: 0
A212: 699.23243 | B212: 700.08025 | C212: 696.81863 | D212: 699.80096 | E212: 9928828.2 | F212: Thu, 17 Sep 2026 00:00:00 GMT | G212: =A212/D212-1 -> -0.00081242873 | I212: 23.29 | J212: 23.6259 | K212: 22.75 | L212: 23.03 | M212: 8378688 | N212: Thu, 17 Sep 2026 00:00:00 GMT | O212: =I212/L212-1 -> 0.011289622 | Q212: -0.1275 | R212: 0 | T212: -0.1275 | U212: =_xlfn.NORM.DIST(T212,$S$202,$S$204,FALSE) -> 0.092315318 | X212: =S202 -> -0.00026135137 | Y212: 9.5
A213: 691.4624 | B213: 698.30481 | C213: 687.27317 | D213: 696.37976 | E213: 14204833 | F213: Wed, 16 Sep 2026 00:00:00 GMT | G213: =A213/D213-1 -> -0.0070613174 | I213: 23.06 | J213: 23.7 | K213: 22.66 | L213: 23.455 | M213: 11326230 | N213: Wed, 16 Sep 2026 00:00:00 GMT | O213: =I213/L213-1 -> -0.016840759 | Q213: -0.125 | R213: 0 | T213: -0.125 | U213: =_xlfn.NORM.DIST(T213,$S$202,$S$204,FALSE) -> 0.11057784 | W213: -3σ | X213: =($S$204*-3)+$S$202 -> -0.12557743 | Y213: 0
A214: 694.41481 | B214: 697.14779 | C214: 693.30766 | D214: 696.97822 | E214: 9682716.1 | F214: Tue, 15 Sep 2026 00:00:00 GMT | G214: =A214/D214-1 -> -0.0036778912 | I214: 23.88 | J214: 24.785 | K214: 23.48 | L214: 23.54 | M214: 8486956.5 | N214: Tue, 15 Sep 2026 00:00:00 GMT | O214: =I214/L214-1 -> 0.0144435 | Q214: -0.1225 | R214: 0 | T214: -0.1225 | U214: =_xlfn.NORM.DIST(T214,$S$202,$S$204,FALSE) -> 0.13197961 | X214: =($S$204*-3)+$S$202 -> -0.12557743 | Y214: 0.1
A215: 697.50686 | B215: 700.05032 | C215: 694.93348 | D215: 695.99076 | E215: 6793476.4 | F215: Mon, 14 Sep 2026 00:00:00 GMT | G215: =A215/D215-1 -> 0.002178337 | I215: 23.91 | J215: 24.28 | K215: 23.15 | L215: 24 | M215: 14279760 | N215: Mon, 14 Sep 2026 00:00:00 GMT | O215: =I215/L215-1 -> -0.00375 | Q215: -0.12 | R215: 0 | T215: -0.12 | U215: =_xlfn.NORM.DIST(T215,$S$202,$S$204,FALSE) -> 0.15696037 | W215: -2σ | X215: =($S$204*-2)+$S$202 -> -0.083805404 | Y215: 0
A216: 700.7585 | B216: 702.68894 | C216: 700.13012 | D216: 701.19738 | E216: 5812878.2 | F216: Fri, 11 Sep 2026 00:00:00 GMT | G216: =A216/D216-1 -> -0.00062588905 | I216: 23.2 | J216: 23.36 | K216: 21.8 | L216: 21.9 | M216: 13544511 | N216: Fri, 11 Sep 2026 00:00:00 GMT | O216: =I216/L216-1 -> 0.059360731 | Q216: -0.1175 | R216: 0 | T216: -0.1175 | U216: =_xlfn.NORM.DIST(T216,$S$202,$S$204,FALSE) -> 0.18600199 | X216: =($S$204*-2)+$S$202 -> -0.083805404 | Y216: 2
A217: 694.86366 | B217: 696.84855 | C217: 693.7586 | D217: 694.99332 | E217: 18360495 | F217: Thu, 10 Sep 2026 00:00:00 GMT | G217: =A217/D217-1 -> -0.00018657252 | I217: 22.14 | J217: 22.575 | K217: 21.62 | L217: 21.96 | M217: 16774137 | N217: Thu, 10 Sep 2026 00:00:00 GMT | O217: =I217/L217-1 -> 0.0081967213 | Q217: -0.115 | R217: 0 | T217: -0.115 | U217: =_xlfn.NORM.DIST(T217,$S$202,$S$204,FALSE) -> 0.21962895 | W217: -1σ | X217: =($S$204*-1)+$S$202 -> -0.042033378 | Y217: 0
A218: 699.07284 | B218: 700.90812 | C218: 697.69139 | D218: 700.54904 | E218: 4311927.8 | F218: Wed, 09 Sep 2026 00:00:00 GMT | G218: =A218/D218-1 -> -0.0021072115 | I218: 22.01 | J218: 23.1434 | K218: 21.83 | L218: 23.05 | M218: 17918806 | N218: Wed, 09 Sep 2026 00:00:00 GMT | O218: =I218/L218-1 -> -0.045119306 | Q218: -0.1125 | R218: 0 | T218: -0.1125 | U218: =_xlfn.NORM.DIST(T218,$S$202,$S$204,FALSE) -> 0.25840803 | X218: =($S$204*-1)+$S$202 -> -0.042033378 | Y218: 6
A219: 702.26463 | B219: 705.69581 | C219: 701.56643 | D219: 705.16717 | E219: 7847677 | F219: Tue, 08 Sep 2026 00:00:00 GMT | G219: =A219/D219-1 -> -0.0041160995 | I219: 22.75 | J219: 24.1 | K219: 22.57 | L219: 24 | M219: 19428485 | N219: Tue, 08 Sep 2026 00:00:00 GMT | O219: =I219/L219-1 -> -0.052083333 | Q219: -0.11 | R219: 0 | T219: -0.11 | U219: =_xlfn.NORM.DIST(T219,$S$202,$S$204,FALSE) -> 0.30294712 | W219: 1σ | X219: =($S$204*1)+$S$202 -> 0.041510675 | Y219: 0
A220: 706.19453 | B220: 708.62827 | C220: 705.08737 | D220: 707.90014 | E220: 6833680.7 | F220: Fri, 04 Sep 2026 00:00:00 GMT | G220: =A220/D220-1 -> -0.0024094009 | I220: 24.12 | J220: 25.02 | K220: 23.895 | L220: 24.69 | M220: 16510724 | N220: Fri, 04 Sep 2026 00:00:00 GMT | O220: =I220/L220-1 -> -0.02308627 | Q220: -0.1075 | R220: 0 | T220: -0.1075 | U220: =_xlfn.NORM.DIST(T220,$S$202,$S$204,FALSE) -> 0.35389309 | X220: =($S$204*1)+$S$202 -> 0.041510675 | Y220: 6
A221: 708.89758 | B221: 709.69054 | C221: 703.70094 | D221: 704.01014 | E221: 8616616.4 | F221: Thu, 03 Sep 2026 00:00:00 GMT | G221: =A221/D221-1 -> 0.0069422799 | I221: 25.22 | J221: 26.75 | K221: 25.13 | L221: 26.36 | M221: 16821596 | N221: Thu, 03 Sep 2026 00:00:00 GMT | O221: =I221/L221-1 -> -0.043247344 | Q221: -0.105 | R221: 0 | T221: -0.105 | U221: =_xlfn.NORM.DIST(T221,$S$202,$S$204,FALSE) -> 0.41192841 | W221: 2σ | X221: =($S$204*2)+$S$202 -> 0.083282701 | Y221: 0
A222: 701.60632 | B222: 702.72345 | C222: 698.38461 | D222: 699.05289 | E222: 7724754.5 | F222: Wed, 02 Sep 2026 00:00:00 GMT | G222: =A222/D222-1 -> 0.0036527074 | I222: 25.73 | J222: 27.24 | K222: 25.68 | L222: 26.78 | M222: 9572905.4 | N222: Wed, 02 Sep 2026 00:00:00 GMT | O222: =I222/L222-1 -> -0.039208364 | Q222: -0.1025 | R222: 1 | T222: -0.1025 | U222: =_xlfn.NORM.DIST(T222,$S$202,$S$204,FALSE) -> 0.47776664 | X222: =($S$204*2)+$S$202 -> 0.083282701 | Y222: 2
A223: 698.48435 | B223: 701.10761 | C223: 696.34964 | D223: 698.65391 | E223: 6503580 | F223: Tue, 01 Sep 2026 00:00:00 GMT | G223: =A223/D223-1 -> -0.00024270112 | I223: 27.2 | J223: 28.39 | K223: 26.57 | L223: 27.06 | M223: 10645291 | N223: Tue, 01 Sep 2026 00:00:00 GMT | O223: =I223/L223-1 -> 0.0051736881 | Q223: -0.1 | R223: 0 | T223: -0.1 | U223: =_xlfn.NORM.DIST(T223,$S$202,$S$204,FALSE) -> 0.5521465 | W223: 3σ | X223: =($S$204*3)+$S$202 -> 0.12505473 | Y223: 0
A224: 703.08253 | B224: 704.12984 | C224: 701.15748 | D224: 703.55132 | E224: 5756351.9 | F224: Mon, 31 Aug 2026 00:00:00 GMT | G224: =A224/D224-1 -> -0.00066632641 | I224: 27.49 | J224: 28 | K224: 27.31 | L224: 27.6 | M224: 19939600 | N224: Mon, 31 Aug 2026 00:00:00 GMT | O224: =I224/L224-1 -> -0.0039855072 | Q224: -0.0975 | R224: 1 | T224: -0.0975 | U224: =_xlfn.NORM.DIST(T224,$S$202,$S$204,FALSE) -> 0.63582447 | X224: =($S$204*3)+$S$202 -> 0.12505473 | Y224: 0.1
A225: 705.4265 | B225: 710.84178 | C225: 704.44902 | D225: 707.57099 | E225: 8105322.5 | F225: Fri, 28 Aug 2026 00:00:00 GMT | G225: =A225/D225-1 -> -0.0030307729 | I225: 28.82 | J225: 30.9199 | K225: 28.765 | L225: 30.18 | M225: 19101093 | N225: Fri, 28 Aug 2026 00:00:00 GMT | O225: =I225/L225-1 -> -0.045062956 | Q225: -0.095 | R225: 0 | T225: -0.095 | U225: =_xlfn.NORM.DIST(T225,$S$202,$S$204,FALSE) -> 0.72956597
A226: 706.93263 | B226: 708.13454 | C226: 703.40211 | D226: 704.57868 | E226: 6773106.6 | F226: Thu, 27 Aug 2026 00:00:00 GMT | G226: =A226/D226-1 -> 0.0033409306 | I226: 30.62 | J226: 31.22 | K226: 27.74 | L226: 28 | M226: 27594583 | N226: Thu, 27 Aug 2026 00:00:00 GMT | O226: =I226/L226-1 -> 0.093571429 | Q226: -0.0925 | R226: 0 | T226: -0.0925 | U226: =_xlfn.NORM.DIST(T226,$S$202,$S$204,FALSE) -> 0.83413495
A227: 702.3943 | B227: 703.51143 | C227: 700.42935 | D227: 701.09763 | E227: 7176219.4 | F227: Wed, 26 Aug 2026 00:00:00 GMT | G227: =A227/D227-1 -> 0.0018494807 | I227: 27.03 | J227: 27.42 | K227: 25.63 | L227: 26.03 | M227: 10282047 | N227: Wed, 26 Aug 2026 00:00:00 GMT | O227: =I227/L227-1 -> 0.038417211 | Q227: -0.09 | R227: 0 | T227: -0.09 | U227: =_xlfn.NORM.DIST(T227,$S$202,$S$204,FALSE) -> 0.95028196
A228: 702.21476 | B228: 703.02797 | C228: 699.65135 | D228: 702.47908 | E228: 4335609.9 | F228: Tue, 25 Aug 2026 00:00:00 GMT | G228: =A228/D228-1 -> -0.00037626813 | I228: 27.27 | J228: 27.97 | K228: 26.86 | L228: 27.2 | M228: 10665032 | N228: Tue, 25 Aug 2026 00:00:00 GMT | O228: =I228/L228-1 -> 0.0025735294 | Q228: -0.0875 | R228: 0 | T228: -0.0875 | U228: =_xlfn.NORM.DIST(T228,$S$202,$S$204,FALSE) -> 1.0787308
A229: 700.03038 | B229: 701.58628 | C229: 698.73371 | D229: 701.16745 | E229: 7757366.3 | F229: Mon, 24 Aug 2026 00:00:00 GMT | G229: =A229/D229-1 -> -0.0016216908 | I229: 27.44 | J229: 27.6 | K229: 26.63 | L229: 26.97 | M229: 8378159.5 | N229: Mon, 24 Aug 2026 00:00:00 GMT | O229: =I229/L229-1 -> 0.01742677 | Q229: -0.085 | R229: 2 | T229: -0.085 | U229: =_xlfn.NORM.DIST(T229,$S$202,$S$204,FALSE) -> 1.2201636
A230: 701.90555 | B230: 703.9902 | C230: 700.63881 | D230: 702.26463 | E230: 10705589 | F230: Fri, 21 Aug 2026 00:00:00 GMT | G230: =A230/D230-1 -> -0.0005113128 | I230: 27.1 | J230: 27.78 | K230: 26.47 | L230: 27.2 | M230: 10663741 | N230: Fri, 21 Aug 2026 00:00:00 GMT | O230: =I230/L230-1 -> -0.0036764706 | Q230: -0.0825 | R230: 0 | T230: -0.0825 | U230: =_xlfn.NORM.DIST(T230,$S$202,$S$204,FALSE) -> 1.3752051
A231: 699.21248 | B231: 704.26948 | C231: 698.67596 | D231: 702.24468 | E231: 8480360 | F231: Thu, 20 Aug 2026 00:00:00 GMT | G231: =A231/D231-1 -> -0.0043178752 | I231: 27.31 | J231: 28.03 | K231: 26.84 | L231: 27.11 | M231: 15444896 | N231: Thu, 20 Aug 2026 00:00:00 GMT | O231: =I231/L231-1 -> 0.0073773515 | Q231: -0.08 | R231: 0 | T231: -0.08 | U231: =_xlfn.NORM.DIST(T231,$S$202,$S$204,FALSE) -> 1.5444054
A232: 705.09735 | B232: 708.27917 | C232: 704.28444 | D232: 706.37407 | E232: 7039831.7 | F232: Wed, 19 Aug 2026 00:00:00 GMT | G232: =A232/D232-1 -> -0.0018074246 | I232: 26.79 | J232: 27.3 | K232: 26.09 | L232: 26.35 | M232: 13560416 | N232: Wed, 19 Aug 2026 00:00:00 GMT | O232: =I232/L232-1 -> 0.016698292 | Q232: -0.0775 | R232: 3 | T232: -0.0775 | U232: =_xlfn.NORM.DIST(T232,$S$202,$S$204,FALSE) -> 1.7282221
A233: 703.59122 | B233: 705.53622 | C233: 703.15235 | D233: 704.79812 | E233: 5292120.7 | F233: Tue, 18 Aug 2026 00:00:00 GMT | G233: =A233/D233-1 -> -0.0017124015 | I233: 26.01 | J233: 26.47 | K233: 25.25 | L233: 25.25 | M233: 13818107 | N233: Tue, 18 Aug 2026 00:00:00 GMT | O233: =I233/L233-1 -> 0.03009901 | Q233: -0.075 | R233: 2 | T233: -0.075 | U233: =_xlfn.NORM.DIST(T233,$S$202,$S$204,FALSE) -> 1.9270023
A234: 708.44873 | B234: 712.21405 | C234: 708.27917 | D234: 711.67045 | E234: 5759776.8 | F234: Mon, 17 Aug 2026 00:00:00 GMT | G234: =A234/D234-1 -> -0.0045269797 | I234: 24.99 | J234: 25.98 | K234: 24.66 | L234: 24.98 | M234: 10337582 | N234: Mon, 17 Aug 2026 00:00:00 GMT | O234: =I234/L234-1 -> 0.00040032026 | Q234: -0.0725 | R234: 0 | T234: -0.0725 | U234: =_xlfn.NORM.DIST(T234,$S$202,$S$204,FALSE) -> 2.1409637
A235: 711.78017 | B235: 714.05432 | C235: 710.97225 | D235: 713.79499 | E235: 4224899.3 | F235: Fri, 14 Aug 2026 00:00:00 GMT | G235: =A235/D235-1 -> -0.0028226877 | I235: 25.42 | J235: 26.5 | K235: 25.225 | L235: 26.29 | M235: 12402741 | N235: Fri, 14 Aug 2026 00:00:00 GMT | O235: =I235/L235-1 -> -0.033092431 | Q235: -0.07 | R235: 1 | T235: -0.07 | U235: =_xlfn.NORM.DIST(T235,$S$202,$S$204,FALSE) -> 2.3701772
A236: 713.11673 | B236: 714.55304 | C236: 709.78031 | D236: 710.47353 | E236: 4562935.4 | F236: Thu, 13 Aug 2026 00:00:00 GMT | G236: =A236/D236-1 -> 0.0037203426 | I236: 26.35 | J236: 26.795 | K236: 23.37 | L236: 23.7 | M236: 23317330 | N236: Thu, 13 Aug 2026 00:00:00 GMT | O236: =I236/L236-1 -> 0.11181435 | Q236: -0.0675 | R236: 1 | T236: -0.0675 | U236: =_xlfn.NORM.DIST(T236,$S$202,$S$204,FALSE) -> 2.6145487
... A315: 643.71559 | B315: 650.2895 | C315: 642.41314 | D315: 649.37452 | E315: 8503460.8 | F315: Tue, 21 Apr 2026 00:00:00 GMT | G315: =A315/D315-1 -> -0.0087144301 | I315: 18.72 | J315: 20.33 | K315: 18.66 | L315: 19 | M315: 21695183 | N315: Tue, 21 Apr 2026 00:00:00 GMT | O315: =I315/L315-1 -> -0.014736842 | Q315: 0.13 | R315: 0 | T315: 0.13 | U315: =_xlfn.NORM.DIST(T315,$S$202,$S$204,FALSE) -> 0.073860326
A316: 647.98217 | B316: 649.03638 | C316: 645.62511 | D316: 648.06173 | E316: 6385417.7 | F316: Mon, 20 Apr 2026 00:00:00 GMT | G316: =A316/D316-1 -> -0.00012277094 | I316: 19.01 | J316: 19.33 | K316: 18.5 | L316: 18.69 | M316: 13423283 | N316: Mon, 20 Apr 2026 00:00:00 GMT | O316: =I316/L316-1 -> 0.017121455 | Q316: More | R316: 0 | T316: More | U316: =_xlfn.NORM.DIST(T316,$S$202,$S$204,FALSE) -> #VALUE!
A317: 649.2154 | B317: 651.30393 | C317: 645.3168 | D317: 645.63505 | E317: 7826716.6 | F317: Fri, 17 Apr 2026 00:00:00 GMT | G317: =A317/D317-1 -> 0.0055454573 | I317: 18.92 | J317: 21.45 | K317: 18.61 | L317: 20.97 | M317: 36413450 | N317: Fri, 17 Apr 2026 00:00:00 GMT | O317: =I317/L317-1 -> -0.097758703
A318: 641.33864 | B318: 642.54204 | C318: 638.64344 | D318: 640.99056 | E318: 5890210.9 | F318: Thu, 16 Apr 2026 00:00:00 GMT | G318: =A318/D318-1 -> 0.00054304821 | I318: 20.32 | J318: 21.3 | K318: 19.3 | L318: 21.235 | M318: 21681625 | N318: Thu, 16 Apr 2026 00:00:00 GMT | O318: =I318/L318-1 -> -0.043089239
A319: 639.93634 | B319: 640.27449 | C319: 634.74485 | D319: 635.69961 | E319: 5078177.9 | F319: Wed, 15 Apr 2026 00:00:00 GMT | G319: =A319/D319-1 -> 0.006664685 | I319: 20.34 | J319: 20.48 | K319: 18.6201 | L319: 18.97 | M319: 18190572 | N319: Wed, 15 Apr 2026 00:00:00 GMT | O319: =I319/L319-1 -> 0.072219294
A320: 634.86419 | B320: 635.03326 | C320: 628.76767 | D320: 628.77264 | E320: 5026396.5 | F320: Tue, 14 Apr 2026 00:00:00 GMT | G320: =A320/D320-1 -> 0.0096880066 | I320: 18.42 | J320: 20.25 | K320: 17.65 | L320: 19.55 | M320: 23170286 | N320: Tue, 14 Apr 2026 00:00:00 GMT | O320: =I320/L320-1 -> -0.057800512
A321: 627.27586 | B321: 627.45488 | C321: 618.58358 | D321: 619.34938 | E321: 5128925.2 | F321: Mon, 13 Apr 2026 00:00:00 GMT | G321: =A321/D321-1 -> 0.012798073 | I321: 19.18 | J321: 19.41 | K321: 17.75 | L321: 18.115 | M321: 14696801 | N321: Mon, 13 Apr 2026 00:00:00 GMT | O321: =I321/L321-1 -> 0.058791057
A322: 621.18928 | B322: 623.56623 | C322: 620.31408 | D322: 622.90486 | E322: 4599410.8 | F322: Fri, 10 Apr 2026 00:00:00 GMT | G322: =A322/D322-1 -> -0.0027541612 | I322: 18.16 | J322: 19.15 | K322: 17.73 | L322: 19.08 | M322: 16471847 | N322: Fri, 10 Apr 2026 00:00:00 GMT | O322: =I322/L322-1 -> -0.048218029
A323: 621.60698 | B323: 622.7507 | C323: 616.01767 | D323: 616.95254 | E323: 5500332.9 | F323: Thu, 09 Apr 2026 00:00:00 GMT | G323: =A323/D323-1 -> 0.0075442499 | I323: 19.08 | J323: 20.215 | K323: 18.78 | L323: 20.01 | M323: 15714551 | N323: Thu, 09 Apr 2026 00:00:00 GMT | O323: =I323/L323-1 -> -0.046476762
A324: 617.94708 | B324: 619.0908 | C324: 613.92914 | D324: 618.39959 | E324: 9819192.8 | F324: Wed, 08 Apr 2026 00:00:00 GMT | G324: =A324/D324-1 -> -0.00073175243 | I324: 20.15 | J324: 23.15 | K324: 20.125 | L324: 22.5 | M324: 15301297 | N324: Wed, 08 Apr 2026 00:00:00 GMT | O324: =I324/L324-1 -> -0.10444444
A325: 602.73063 | B325: 602.99915 | C325: 595.2318 | D325: 600.28406 | E325: 6180055.1 | F325: Tue, 07 Apr 2026 00:00:00 GMT | G325: =A325/D325-1 -> 0.0040756818 | I325: 21.19 | J325: 21.5 | K325: 20.67 | L325: 21.19 | M325: 5943943.7 | N325: Tue, 07 Apr 2026 00:00:00 GMT | O325: =I325/L325-1 -> 0
A326: 602.36265 | B326: 603.12844 | C326: 599.31936 | D326: 599.62766 | E326: 6317133.8 | F326: Mon, 06 Apr 2026 00:00:00 GMT | G326: =A326/D326-1 -> 0.0045611358 | I326: 21.42 | J326: 21.698 | K326: 21.0478 | L326: 21.38 | M326: 5674256.8 | N326: Mon, 06 Apr 2026 00:00:00 GMT | O326: =I326/L326-1 -> 0.0018709074
A327: 599.69728 | B327: 601.48745 | C327: 589.79366 | D327: 590.98512 | E327: 12809464 | F327: Thu, 02 Apr 2026 00:00:00 GMT | G327: =A327/D327-1 -> 0.014741767 | I327: 21.27 | J327: 21.43 | K327: 19.7008 | L327: 20.46 | M327: 8314840 | N327: Thu, 02 Apr 2026 00:00:00 GMT | O327: =I327/L327-1 -> 0.039589443
A328: 599.01105 | B328: 602.04439 | C328: 596.99213 | D328: 597.77782 | E328: 11343588 | F328: Wed, 01 Apr 2026 00:00:00 GMT | G328: =A328/D328-1 -> 0.002063022 | I328: 20.42 | J328: 21.56 | K328: 20.3 | L328: 21.49 | M328: 9286096.1 | N328: Wed, 01 Apr 2026 00:00:00 GMT | O328: =I328/L328-1 -> -0.0497906
... A438: 606.97776 | B438: 610.7938 | C438: 602.8849 | D438: 610.7938 | E438: 6189515.8 | F438: Wed, 22 Oct 2025 00:00:00 GMT | G438: =A438/D438-1 -> -0.0062476733 | I438: 52.81 | J438: 54.85 | K438: 51.1 | L438: 54.72 | M438: 8677575 | N438: Wed, 22 Oct 2025 00:00:00 GMT | O438: =I438/L438-1 -> -0.034904971

Sheet Product Lines

Sheet Economics

Sheet Management

Sheet Table Formatting
B2: [Bold Title] | G2: [Bold Title]
B3: Line Titles | G3: <-- General
B4: Line Titles | G4: <-- Info
B5: Line Titles | G5: <-- General
B6: Line Titles | G6: <-- Info
B7: Line Titles | G7: <-- General
B8: Line Titles | G8: <-- Info
