Workbook

Sheet Main
B2: ILMN
B3: Price | C3: 188.68 | D3: 7/5/2026
B4: SO | C4: 151.3 | D4: Q1'26
B5: MC | C5: =C3*C4 -> 28547.284
B6: Cash | C6: =1089+66 -> 1155 | D6: Q1'26
B7: Debt | C7: =499+1490 -> 1989 | D7: Q1'26
B8: EV | C8: =C5-C6+C7 -> 29381.284
B10: Illumina, Inc. (ILMN)
B12: Founder(s): Larry Bock, John Stuelpnagel, David Walt, Mark Chee, and Anthony Czarnik | F12: Registered Exchange: NASDAQ | M12: Resources:
B13: Founded: April 1998 | F13: Address: 5200 Illumina Way San Diego, CA 92122 U.S. | M13: SEC filings | P13: https://www.sec.gov/edgar/browse/?CIK=1110803&owner=exclude
B14: Headquarters: San Diego, CA | F14: Investor Relations Contact: | M14: Company Homepage | P14: https://www.illumina.com/
B15: Current CEO: Jacob Thaysen | F15: Investors Relation Department | N15: Company IR Page | Q15: https://investor.illumina.com/investors/default.aspx
B16: Employees: 10,080 | F16: Phone: | G16: (858) 202 - 4500 | I16: Email: | M16: Earnings Calls | P16: https://app.godelterminal.com/
B17: Industry: Diagnostics & Research | M17: Equity Analysis | P17: https://stockanalysis.com/stocks/ilmn/company/
B18: Sector: Healthcare | M18: MacroTrends | P18: https://www.macrotrends.net/stocks/charts/ILMN/illumina/revenue
B19: IPO: Jul 28, 2000 -- $500M valuation | M19: ROIC, WACC | P19: https://www.gurufocus.com/term/wacc/ILMN
B20: Fiscal Year: [January - December] | M20: Godel Terminal | P20: https://app.godelterminal.com/
A22: Company Overview:
B23: Illumina, Inc. provides sequencing- and array-based solutions for genetic and genomic analysis in the Americas, Europe, Greater China, the Asia Pacific, the Middle East, and Africa
B24: The Company offers sequencing- and array-based instruments and consumables, which include reagents, flow cells, and library preparation
C25: Whole-genome sequencing kits, which sequence entire genomes of various size and complexity
C26: Targeted resequencing kits, which sequence exomes, specific genes, and RNA or other genomic regions of interest
C27: It also provides whole-genome sequencing, genotyping, noninvasive prenatal testing, and product support services
D28: "Razor and Blade" business model … The Company sells the sequencing hardware (razors) to lock customers in, then relies on continuous sales of high-margin chemical reagents and flow cells (blades)
B29: The Company serves genomic research centers, academic institutions, government laboratories, and hospitals, as well as pharmaceutical, biotechnology, commercial molecular diagnostic laboratories, and consumer genomics companies
C30: The Company markets and distributes its products directly to customers, as well as through life-science distributors
B31: The Company has a collaboration with Labcorp Holdings Inc. for the development of oncology treatments through applications of sequencing solutions across the healthcare ecosystem
C32: Also strategic collaboration with Integrated DNA Technologies to enable a DRAGEN, secondary analysis pipeline for IDT xGena, FFPE and cfDNA next generation sequencing (NGS) library preparation with custom panels, delivering an integrated, end-to-end solution for somatic oncology research
C33: It also has a data partnership with Center for Data-Driven Discovery in Biomedicine to advance research in pediatric cancer and rare disease
B34: Illumina, Inc. was incorporated in 1998 and is headquartered in San Diego, California
A36: Business Segments and Geographical Info:

Sheet Model
B1: [Use for Graphing] | AM1: Q1 2020 | AQ1: Q1 2021 | AU1: Q1 2022 | AY1: Q1 2023 | BC1: Q1 2024 | BG1: Q1 2025 | BK1: Q1 2026
B2: Quarterly
B3: Revenues | C3: {="Q"&MOD(_xlfn.SEQUENCE(1,64)-1,4)+1&" "&(2011+INT((_xlfn.SEQUENCE(1,64)-1)/4))} -> Q1 2011 | D3: Q2 2011 | E3: Q3 2011 | F3: Q4 2011 | G3: Q1 2012 | H3: Q2 2012 | I3: Q3 2012 | J3: Q4 2012 | K3: Q1 2013 | L3: Q2 2013 | M3: Q3 2013 | N3: Q4 2013 | O3: Q1 2014 | P3: Q2 2014 | Q3: Q3 2014 | R3: Q4 2014 | S3: Q1 2015 | T3: Q2 2015 | U3: Q3 2015 | V3: Q4 2015 | W3: Q1 2016 | X3: Q2 2016 | Y3: Q3 2016 | Z3: Q4 2016 | AA3: Q1 2017 | AB3: Q2 2017 | AC3: Q3 2017 | AD3: Q4 2017 | AE3: Q1 2018 | AF3: Q2 2018 | AG3: Q3 2018 | AH3: Q4 2018 | AI3: Q1 2019 | AJ3: Q2 2019 | AK3: Q3 2019 | AL3: Q4 2019 | AM3: Q1 2020 | AN3: Q2 2020 | AO3: Q3 2020 | AP3: Q4 2020 | AQ3: Q1 2021 | AR3: Q2 2021 | AS3: Q3 2021 | AT3: Q4 2021 | AU3: Q1 2022 | AV3: Q2 2022 | AW3: Q3 2022 | AX3: Q4 2022 | AY3: Q1 2023 | AZ3: Q2 2023 | BA3: Q3 2023 | BB3: Q4 2023 | BC3: Q1 2024 | BD3: Q2 2024 | BE3: Q3 2024 | BF3: Q4 2024 | BG3: Q1 2025 | BH3: Q2 2025 | BI3: Q3 2025 | BJ3: Q4 2025 | BK3: Q1 2026 | BL3: Q2 2026 | BM3: Q3 2026 | BN3: Q4 2026 | BS3: 2011 | BT3: =BS3+1 -> 2012 | BU3: =BT3+1 -> 2013 | BV3: =BU3+1 -> 2014 | BW3: =BV3+1 -> 2015 | BX3: =BW3+1 -> 2016 | BY3: =BX3+1 -> 2017 | BZ3: =BY3+1 -> 2018 | CA3: =BZ3+1 -> 2019 | ... EO3: =EN3+1 -> 2085
B4: Consumables | AQ4: 774 | AR4: 778 | AS4: 794 | AT4: =3217-SUM(AQ4:AS4) -> 871 | AU4: 853 | AV4: 813 | AW4: 796 | AX4: =3225-SUM(AU4:AW4) -> 763 | AY4: 764 | AZ4: 804 | BA4: 760 | BB4: =3083-SUM(AY4:BA4) -> 755 | BC4: 762 | BD4: 807 | BE4: 807 | BF4: =3155-SUM(BC4:BE4) -> 779 | BG4: 768 | BH4: 811 | BI4: 816 | BJ4: =3227-SUM(BG4:BI4) -> 832 | BK4: 797 | CC4: =SUM(AQ4:AT4) -> 3217 | CD4: =SUM(AU4:AX4) -> 3225 | CE4: =SUM(AY4:BB4) -> 3083 | CF4: =SUM(BC4:BF4) -> 3155 | CG4: =SUM(BG4:BJ4) -> 3227 | CH4: =CG4*(1+CH10) -> 6454 | CI4: =CH4*(1+CI10) -> 12908 | CJ4: =CI4*(1+CJ10) -> 25816 | CK4: =CJ4*(1+CK10) -> 51632 | CL4: =CK4*(1+CL10) -> 103264 | CM4: =CL4*(1+CM10) -> 206528 | CN4: =CM4*(1+CN10) -> 413056 | CO4: =CN4*(1+CO10) -> 826112 | ... CQ4: =CP4*(1+CQ10) -> 3304448
B5: Instruments | AQ5: 179 | AR5: 194 | AS5: 184 | AT5: =751-SUM(AQ5:AS5) -> 194 | AU5: 217 | AV5: 193 | AW5: 167 | AX5: =728-SUM(AU5:AW5) -> 151 | AY5: 158 | AZ5: 197 | BA5: 181 | BB5: =704-SUM(AY5:BA5) -> 168 | BC5: 114 | BD5: 120 | BE5: 107 | BF5: =501-SUM(BC5:BE5) -> 160 | BG5: 112 | BH5: 101 | BI5: 111 | BJ5: =482-SUM(BG5:BI5) -> 158 | BK5: 120 | CC5: =SUM(AQ5:AT5) -> 751 | CD5: =SUM(AU5:AX5) -> 728 | CE5: =SUM(AY5:BB5) -> 704 | CF5: =SUM(BC5:BF5) -> 501 | CG5: =SUM(BG5:BJ5) -> 482 | CH5: =CG5*(1+CH11) -> 964 | CI5: =CH5*(1+CI11) -> 1928 | CJ5: =CI5*(1+CJ11) -> 3856 | CK5: =CJ5*(1+CK11) -> 7712 | CL5: =CK5*(1+CL11) -> 15424 | CM5: =CL5*(1+CM11) -> 30848 | CN5: =CM5*(1+CN11) -> 61696 | CO5: =CN5*(1+CO11) -> 123392 | ... CQ5: =CP5*(1+CQ11) -> 493568
B6: Ttl Product Revenues | AQ6: =AQ4+AQ5 -> 953 | AR6: =AR4+AR5 -> 972 | AS6: =AS4+AS5 -> 978 | AT6: =AT4+AT5 -> 1065 | AU6: =AU4+AU5 -> 1070 | AV6: =AV4+AV5 -> 1006 | AW6: =AW4+AW5 -> 963 | AX6: =AX4+AX5 -> 914 | ... BK6: =BK4+BK5 -> 917 | CC6: =SUM(AQ6:AT6) -> 3968 | CD6: =SUM(AU6:AX6) -> 3953 | CE6: =SUM(AY6:BB6) -> 3787 | CF6: =SUM(BC6:BF6) -> 3656 | CG6: =SUM(BG6:BJ6) -> 3709 | CH6: =CG6*(1+CH12) -> 7418 | CI6: =CH6*(1+CI12) -> 14836 | CJ6: =CI6*(1+CJ12) -> 29672 | CK6: =CJ6*(1+CK12) -> 59344 | CL6: =CK6*(1+CL12) -> 118688 | CM6: =CL6*(1+CM12) -> 237376 | CN6: =CM6*(1+CN12) -> 474752 | CO6: =CN6*(1+CO12) -> 949504 | ... CQ6: =CP6*(1+CQ12) -> 3798016
B7: Services | AQ7: 140 | AR7: 154 | AS7: 130 | AT7: =558-SUM(AQ7:AS7) -> 134 | AU7: 153 | AV7: 156 | AW7: 152 | AX7: =631-SUM(AU7:AW7) -> 170 | AY7: 165 | AZ7: 175 | BA7: 178 | BB7: =717-SUM(AY7:BA7) -> 199 | BC7: 200 | BD7: 185 | BE7: 166 | BF7: =716-SUM(BC7:BE7) -> 165 | BG7: 161 | BH7: 147 | BI7: 157 | BJ7: =634-SUM(BG7:BI7) -> 169 | BK7: 174 | CC7: =SUM(AQ7:AT7) -> 558 | CD7: =SUM(AU7:AX7) -> 631 | CE7: =SUM(AY7:BB7) -> 717 | CF7: =SUM(BC7:BF7) -> 716 | CG7: =SUM(BG7:BJ7) -> 634 | CH7: =CG7*(1+CH13) -> 1268 | CI7: =CH7*(1+CI13) -> 2536 | CJ7: =CI7*(1+CJ13) -> 5072 | CK7: =CJ7*(1+CK13) -> 10144 | CL7: =CK7*(1+CL13) -> 20288 | CM7: =CL7*(1+CM13) -> 40576 | CN7: =CM7*(1+CN13) -> 81152 | CO7: =CN7*(1+CO13) -> 162304 | ... CQ7: =CP7*(1+CQ13) -> 649216
B8: Ttl Revenues | AQ8: =AQ6+AQ7 -> 1093 | AR8: =AR6+AR7 -> 1126 | AS8: =AS6+AS7 -> 1108 | AT8: =AT6+AT7 -> 1199 | AU8: =AU6+AU7 -> 1223 | AV8: =AV6+AV7 -> 1162 | AW8: =AW6+AW7 -> 1115 | AX8: =AX6+AX7 -> 1084 | ... BK8: =BK6+BK7 -> 1091 | CC8: =SUM(AQ8:AT8) -> 4526 | CD8: =SUM(AU8:AX8) -> 4584 | CE8: =SUM(AY8:BB8) -> 4504 | CF8: =SUM(BC8:BF8) -> 4372 | CG8: =SUM(BG8:BJ8) -> 4343 | CH8: =SUM(CH4:CH7) -> 16104 | CI8: =SUM(CI4:CI7) -> 32208 | CJ8: =SUM(CJ4:CJ7) -> 64416 | CK8: =SUM(CK4:CK7) -> 128832 | CL8: =SUM(CL4:CL7) -> 257664 | CM8: =SUM(CM4:CM7) -> 515328 | CN8: =SUM(CN4:CN7) -> 1030656 | CO8: =SUM(CO4:CO7) -> 2061312 | ... CQ8: =SUM(CQ4:CQ7) -> 8245248
B10: Consumables Growth Y/y | AU10: =AU4/AQ4-1 -> 0.10206718 | AV10: =AV4/AR4-1 -> 0.044987147 | AW10: =AW4/AS4-1 -> 0.0025188917 | AX10: =AX4/AT4-1 -> -0.12399541 | AY10: =AY4/AU4-1 -> -0.10433763 | AZ10: =AZ4/AV4-1 -> -0.011070111 | BA10: =BA4/AW4-1 -> -0.045226131 | BB10: =BB4/AX4-1 -> -0.010484928 | ... BK10: =BK4/BG4-1 -> 0.037760417 | CD10: =CD4/CC4-1 -> 0.0024867889 | CE10: =CE4/CD4-1 -> -0.044031008 | CF10: =CF4/CE4-1 -> 0.023353876 | CG10: =CG4/CF4-1 -> 0.022820919 | CH10: 1 | CI10: 1 | CJ10: 1 | CK10: 1 | CL10: 1 | CM10: 1 | CN10: 1 | CO10: 1 | CP10: 1 | CQ10: 1
B11: Instruments Growth Y/y | AU11: =AU5/AQ5-1 -> 0.2122905 | AV11: =AV5/AR5-1 -> -0.0051546392 | AW11: =AW5/AS5-1 -> -0.092391304 | AX11: =AX5/AT5-1 -> -0.22164948 | AY11: =AY5/AU5-1 -> -0.2718894 | AZ11: =AZ5/AV5-1 -> 0.020725389 | BA11: =BA5/AW5-1 -> 0.083832335 | BB11: =BB5/AX5-1 -> 0.11258278 | ... BK11: =BK5/BG5-1 -> 0.071428571 | CD11: =CD5/CC5-1 -> -0.030625832 | CE11: =CE5/CD5-1 -> -0.032967033 | CF11: =CF5/CE5-1 -> -0.28835227 | CG11: =CG5/CF5-1 -> -0.037924152 | CH11: 1 | CI11: 1 | CJ11: 1 | CK11: 1 | CL11: 1 | CM11: 1 | CN11: 1 | CO11: 1 | CP11: 1 | CQ11: 1
B12: Ttl Product Revenues Growth Y/y | AU12: =AU6/AQ6-1 -> 0.1227702 | AV12: =AV6/AR6-1 -> 0.034979424 | AW12: =AW6/AS6-1 -> -0.015337423 | AX12: =AX6/AT6-1 -> -0.14178404 | AY12: =AY6/AU6-1 -> -0.13831776 | AZ12: =AZ6/AV6-1 -> -0.0049701789 | BA12: =BA6/AW6-1 -> -0.022845275 | BB12: =BB6/AX6-1 -> 0.0098468271 | ... BK12: =BK6/BG6-1 -> 0.042045455 | CD12: =CD6/CC6-1 -> -0.0037802419 | CE12: =CE6/CD6-1 -> -0.041993423 | CF12: =CF6/CE6-1 -> -0.034592025 | CG12: =CG6/CF6-1 -> 0.014496718 | CH12: 1 | CI12: 1 | CJ12: 1 | CK12: 1 | CL12: 1 | CM12: 1 | CN12: 1 | CO12: 1 | CP12: 1 | CQ12: 1
B13: Services Growth Y/y | AU13: =AU7/AQ7-1 -> 0.092857143 | AV13: =AV7/AR7-1 -> 0.012987013 | AW13: =AW7/AS7-1 -> 0.16923077 | AX13: =AX7/AT7-1 -> 0.26865672 | AY13: =AY7/AU7-1 -> 0.078431373 | AZ13: =AZ7/AV7-1 -> 0.12179487 | BA13: =BA7/AW7-1 -> 0.17105263 | BB13: =BB7/AX7-1 -> 0.17058824 | ... BK13: =BK7/BG7-1 -> 0.080745342 | CD13: =CD7/CC7-1 -> 0.13082437 | CE13: =CE7/CD7-1 -> 0.1362916 | CF13: =CF7/CE7-1 -> -0.0013947001 | CG13: =CG7/CF7-1 -> -0.11452514 | CH13: 1 | CI13: 1 | CJ13: 1 | CK13: 1 | CL13: 1 | CM13: 1 | CN13: 1 | CO13: 1 | CP13: 1 | CQ13: 1
B14: Ttl Revenue Growth Y/y | AU14: =AU8/AQ8-1 -> 0.1189387 | AV14: =AV8/AR8-1 -> 0.031971581 | AW14: =AW8/AS8-1 -> 0.0063176895 | AX14: =AX8/AT8-1 -> -0.095913261 | AY14: =AY8/AU8-1 -> -0.11120196 | AZ14: =AZ8/AV8-1 -> 0.012048193 | BA14: =BA8/AW8-1 -> 0.0035874439 | BB14: =BB8/AX8-1 -> 0.035055351 | ... BK14: =BK8/BG8-1 -> 0.04803074 | CD14: =CD8/CC8-1 -> 0.012814848 | CE14: =CE8/CD8-1 -> -0.017452007 | CF14: =CF8/CE8-1 -> -0.029307282 | CG14: =CG8/CF8-1 -> -0.0066331199 | CH14: =CH8/CG8-1 -> 2.7080359 | CI14: =CI8/CH8-1 -> 1 | CJ14: =CJ8/CI8-1 -> 1 | CK14: =CK8/CJ8-1 -> 1 | ... CQ14: =CQ8/CP8-1 -> 1
B16: Consumables % of Ttl Revenues | AQ16: =AQ4/AQ8 -> 0.70814273 | AR16: =AR4/AR8 -> 0.69094139 | AS16: =AS4/AS8 -> 0.7166065 | AT16: =AT4/AT8 -> 0.7264387 | AU16: =AU4/AU8 -> 0.69746525 | AV16: =AV4/AV8 -> 0.69965577 | AW16: =AW4/AW8 -> 0.71390135 | AX16: =AX4/AX8 -> 0.70387454 | ... BK16: =BK4/BK8 -> 0.73052246 | CC16: =CC4/CC8 -> 0.71078215 | CD16: =CD4/CD8 -> 0.70353403 | CE16: =CE4/CE8 -> 0.68450266 | CF16: =CF4/CF8 -> 0.72163769 | CG16: =CG4/CG8 -> 0.74303477
B17: Instruments % of Ttl Revenues | AQ17: =AQ5/AQ8 -> 0.16376944 | AR17: =AR5/AR8 -> 0.1722913 | AS17: =AS5/AS8 -> 0.16606498 | AT17: =AT5/AT8 -> 0.1618015 | AU17: =AU5/AU8 -> 0.17743254 | AV17: =AV5/AV8 -> 0.16609294 | AW17: =AW5/AW8 -> 0.14977578 | AX17: =AX5/AX8 -> 0.13929889 | ... BK17: =BK5/BK8 -> 0.10999083 | CC17: =CC5/CC8 -> 0.16593018 | CD17: =CD5/CD8 -> 0.15881326 | CE17: =CE5/CE8 -> 0.15630551 | CF17: =CF5/CF8 -> 0.11459286 | CG17: =CG5/CG8 -> 0.11098319
B18: Product % of Ttl Revenues | AQ18: =AQ6/AQ8 -> 0.87191217 | AR18: =AR6/AR8 -> 0.86323268 | AS18: =AS6/AS8 -> 0.88267148 | AT18: =AT6/AT8 -> 0.8882402 | AU18: =AU6/AU8 -> 0.87489779 | AV18: =AV6/AV8 -> 0.86574871 | AW18: =AW6/AW8 -> 0.86367713 | AX18: =AX6/AX8 -> 0.84317343 | ... BK18: =BK6/BK8 -> 0.84051329 | CC18: =CC6/CC8 -> 0.87671233 | CD18: =CD6/CD8 -> 0.86234729 | CE18: =CE6/CE8 -> 0.84080817 | CF18: =CF6/CF8 -> 0.83623056 | CG18: =CG6/CG8 -> 0.85401796
B19: Services % of Ttl Revenues | AQ19: =AQ7/AQ8 -> 0.12808783 | AR19: =AR7/AR8 -> 0.13676732 | AS19: =AS7/AS8 -> 0.11732852 | AT19: =AT7/AT8 -> 0.1117598 | AU19: =AU7/AU8 -> 0.12510221 | AV19: =AV7/AV8 -> 0.13425129 | AW19: =AW7/AW8 -> 0.13632287 | AX19: =AX7/AX8 -> 0.15682657 | ... BK19: =BK7/BK8 -> 0.15948671 | CC19: =CC7/CC8 -> 0.12328767 | CD19: =CD7/CD8 -> 0.13765271 | CE19: =CE7/CE8 -> 0.15919183 | CF19: =CF7/CF8 -> 0.16376944 | CG19: =CG7/CG8 -> 0.14598204
B21: Sequencing | AQ21: 1109 | AR21: 1021 | AS21: 1015 | AT21: =4109-SUM(AQ21:AS21) -> 964 | AU21: 1109 | AV21: 1065 | AW21: 1015 | AX21: =4171-SUM(AU21:AW21) -> 982 | AY21: 976 | AZ21: 1083 | BA21: 1029 | BB21: =4112-SUM(AY21:BA21) -> 1024 | BC21: 979 | BD21: 1016 | BE21: 995 | BF21: =3993-SUM(BC21:BE21) -> 1003 | BG21: 947 | BH21: 972 | BI21: 1001 | BJ21: =3985-SUM(BG21:BI21) -> 1065 | BK21: 995 | CC21: =SUM(AQ21:AT21) -> 4109 | CD21: =SUM(AU21:AX21) -> 4171 | CE21: =SUM(AY21:BB21) -> 4112 | CF21: =SUM(BC21:BF21) -> 3993 | CG21: =SUM(BG21:BJ21) -> 3985 | CH21: =CG21*(1+CH25) -> 7970 | CI21: =CH21*(1+CI25) -> 15940 | CJ21: =CI21*(1+CJ25) -> 31880 | CK21: =CJ21*(1+CK25) -> 63760 | CL21: =CK21*(1+CL25) -> 127520 | CM21: =CL21*(1+CM25) -> 255040 | CN21: =CM21*(1+CN25) -> 510080 | CO21: =CN21*(1+CO25) -> 1020160 | ... CQ21: =CP21*(1+CQ25) -> 4080640
B22: Microarray | AQ22: 114 | AR22: 105 | AS22: 93 | AT22: =417-SUM(AQ22:AS22) -> 105 | AU22: 114 | AV22: 97 | AW22: 100 | AX22: =413-SUM(AU22:AW22) -> 102 | AY22: 111 | AZ22: 93 | BA22: 90 | BB22: =392-SUM(AY22:BA22) -> 98 | BC22: 97 | BD22: 96 | BE22: 85 | BF22: =379-SUM(BC22:BE22) -> 101 | BG22: 94 | BH22: 87 | BI22: 83 | BJ22: =358-SUM(BG22:BI22) -> 94 | BK22: 96 | CC22: =SUM(AQ22:AT22) -> 417 | CD22: =SUM(AU22:AX22) -> 413 | CE22: =SUM(AY22:BB22) -> 392 | CF22: =SUM(BC22:BF22) -> 379 | CG22: =SUM(BG22:BJ22) -> 358 | CH22: =CG22*(1+CH26) -> 716 | CI22: =CH22*(1+CI26) -> 1432 | CJ22: =CI22*(1+CJ26) -> 2864 | CK22: =CJ22*(1+CK26) -> 5728 | CL22: =CK22*(1+CL26) -> 11456 | CM22: =CL22*(1+CM26) -> 22912 | CN22: =CM22*(1+CN26) -> 45824 | CO22: =CN22*(1+CO26) -> 91648 | ... CQ22: =CP22*(1+CQ26) -> 366592
B23: Ttl Revenues | AQ23: =AQ21+AQ22 -> 1223 | AR23: =AR21+AR22 -> 1126 | AS23: =AS21+AS22 -> 1108 | AT23: =AT21+AT22 -> 1069 | AU23: =AU21+AU22 -> 1223 | AV23: =AV21+AV22 -> 1162 | AW23: =AW21+AW22 -> 1115 | AX23: =AX21+AX22 -> 1084 | ... BK23: =BK21+BK22 -> 1091 | CC23: =SUM(AQ23:AT23) -> 4526 | CD23: =SUM(AU23:AX23) -> 4584 | CE23: =SUM(AY23:BB23) -> 4504 | CF23: =SUM(BC23:BF23) -> 4372 | CG23: =SUM(BG23:BJ23) -> 4343 | CH23: =CG23*(1+CH27) -> 8686 | CI23: =CH23*(1+CI27) -> 17372 | CJ23: =CI23*(1+CJ27) -> 34744 | CK23: =CJ23*(1+CK27) -> 69488 | CL23: =CK23*(1+CL27) -> 138976 | CM23: =CL23*(1+CM27) -> 277952 | CN23: =CM23*(1+CN27) -> 555904 | CO23: =CN23*(1+CO27) -> 1111808 | ... CQ23: =CP23*(1+CQ27) -> 4447232
B25: Sequencing Growth Y/y | AU25: =AU21/AQ21-1 -> 0 | AV25: =AV21/AR21-1 -> 0.043095005 | AW25: =AW21/AS21-1 -> 0 | AX25: =AX21/AT21-1 -> 0.018672199 | AY25: =AY21/AU21-1 -> -0.11992786 | AZ25: =AZ21/AV21-1 -> 0.016901408 | BA25: =BA21/AW21-1 -> 0.013793103 | BB25: =BB21/AX21-1 -> 0.042769857 | ... BK25: =BK21/BG21-1 -> 0.050686378 | CD25: =CD21/CC21-1 -> 0.015088829 | CE25: =CE21/CD21-1 -> -0.014145289 | CF25: =CF21/CE21-1 -> -0.028939689 | CG25: =CG21/CF21-1 -> -0.0020035061 | CH25: 1 | CI25: 1 | CJ25: 1 | CK25: 1 | CL25: 1 | CM25: 1 | CN25: 1 | CO25: 1 | CP25: 1 | CQ25: 1
B26: Microarray Growth Y/y | AU26: =AU22/AQ22-1 -> 0 | AV26: =AV22/AR22-1 -> -0.076190476 | AW26: =AW22/AS22-1 -> 0.075268817 | AX26: =AX22/AT22-1 -> -0.028571429 | AY26: =AY22/AU22-1 -> -0.026315789 | AZ26: =AZ22/AV22-1 -> -0.041237113 | BA26: =BA22/AW22-1 -> -0.1 | BB26: =BB22/AX22-1 -> -0.039215686 | ... BK26: =BK22/BG22-1 -> 0.021276596 | CD26: =CD22/CC22-1 -> -0.0095923261 | CE26: =CE22/CD22-1 -> -0.050847458 | CF26: =CF22/CE22-1 -> -0.033163265 | CG26: =CG22/CF22-1 -> -0.055408971 | CH26: 1 | CI26: 1 | CJ26: 1 | CK26: 1 | CL26: 1 | CM26: 1 | CN26: 1 | CO26: 1 | CP26: 1 | CQ26: 1
B27: Ttl Revenues Growth Y/y | AU27: =AU23/AQ23-1 -> 0 | AV27: =AV23/AR23-1 -> 0.031971581 | AW27: =AW23/AS23-1 -> 0.0063176895 | AX27: =AX23/AT23-1 -> 0.014031805 | AY27: =AY23/AU23-1 -> -0.11120196 | AZ27: =AZ23/AV23-1 -> 0.012048193 | BA27: =BA23/AW23-1 -> 0.0035874439 | BB27: =BB23/AX23-1 -> 0.035055351 | ... BK27: =BK23/BG23-1 -> 0.04803074 | CD27: =CD23/CC23-1 -> 0.012814848 | CE27: =CE23/CD23-1 -> -0.017452007 | CF27: =CF23/CE23-1 -> -0.029307282 | CG27: =CG23/CF23-1 -> -0.0066331199 | CH27: 1 | CI27: 1 | CJ27: 1 | CK27: 1 | CL27: 1 | CM27: 1 | CN27: 1 | CO27: 1 | CP27: 1 | CQ27: 1
B29: Sequencing % of Ttl Revenues | AQ29: =AQ21/AQ23 -> 0.90678659 | AR29: =AR21/AR23 -> 0.90674956 | AS29: =AS21/AS23 -> 0.91606498 | AT29: =AT21/AT23 -> 0.90177736 | AU29: =AU21/AU23 -> 0.90678659 | AV29: =AV21/AV23 -> 0.91652324 | AW29: =AW21/AW23 -> 0.9103139 | AX29: =AX21/AX23 -> 0.90590406 | ... BK29: =BK21/BK23 -> 0.91200733 | CC29: =CC21/CC23 -> 0.90786567 | CD29: =CD21/CD23 -> 0.90990401 | CE29: =CE21/CE23 -> 0.91296625 | CF29: =CF21/CF23 -> 0.91331199 | CG29: =CG21/CG23 -> 0.9175685
B30: Microarray % of Ttl Revenues | AQ30: =AQ22/AQ23 -> 0.09321341 | AR30: =AR22/AR23 -> 0.093250444 | AS30: =AS22/AS23 -> 0.083935018 | AT30: =AT22/AT23 -> 0.098222638 | AU30: =AU22/AU23 -> 0.09321341 | AV30: =AV22/AV23 -> 0.083476764 | AW30: =AW22/AW23 -> 0.089686099 | AX30: =AX22/AX23 -> 0.094095941 | ... BK30: =BK22/BK23 -> 0.087992667 | CC30: =CC22/CC23 -> 0.092134335 | CD30: =CD22/CD23 -> 0.090095986 | CE30: =CE22/CE23 -> 0.087033748 | CF30: =CF22/CF23 -> 0.086688015 | CG30: =CG22/CG23 -> 0.082431499
B32: U.S. Revenues | AQ32: 562 | AR32: 589 | AS32: 583 | AT32: =2358-SUM(AQ32:AS32) -> 624 | AU32: 648 | AV32: 639 | AW32: 597 | AX32: =2479-SUM(AU32:AW32) -> 595 | AY32: 616 | AZ32: 640 | BA32: 663 | BB32: =2521-SUM(AY32:BA32) -> 602 | BC32: 603 | BD32: 640 | BE32: 609 | BF32: =2441-SUM(BC32:BE32) -> 589 | BG32: 555 | BH32: 586 | BI32: 612 | BJ32: =2406-SUM(BG32:BI32) -> 653 | BK32: 590 | CC32: =SUM(AQ32:AT32) -> 2358 | CD32: =SUM(AU32:AX32) -> 2479 | CE32: =SUM(AY32:BB32) -> 2521 | CF32: =SUM(BC32:BF32) -> 2441 | CG32: =SUM(BG32:BJ32) -> 2406
B33: Euro, Mid-East, Africa, LatAm Revenues | AQ33: 305 | AR33: 320 | AS33: 313 | AT33: =1149-SUM(AQ33:AS33) -> 211 | AU33: 316 | AV33: 274 | AW33: 259 | AX33: =1089-SUM(AU33:AW33) -> 240 | AY33: 261 | AZ33: 303 | BA33: 260 | BB33: =1140-SUM(AY33:BA33) -> 316 | BC33: 279 | BD33: 289 | BE33: 291 | BF33: =1185-SUM(BC33:BE33) -> 326 | BG33: 332 | BH33: 310 | BI33: 309 | BJ33: =1264-SUM(BG33:BI33) -> 313 | BK33: 356 | CC33: =SUM(AQ33:AT33) -> 1149 | CD33: =SUM(AU33:AX33) -> 1089 | CE33: =SUM(AY33:BB33) -> 1140 | CF33: =SUM(BC33:BF33) -> 1185 | CG33: =SUM(BG33:BJ33) -> 1264
B34: Taiwan, China Revenues | AQ34: 127 | AR34: 132 | AS34: 122 | AT34: =502-SUM(AQ34:AS34) -> 121 | AU34: 127 | AV34: 118 | AW34: 133 | AX34: =472-SUM(AU34:AW34) -> 94 | AY34: 91 | AZ34: 115 | BA34: 98 | BB34: =384-SUM(AY34:BA34) -> 80 | BC34: 78 | BD34: 75 | BE34: 75 | BF34: =308-SUM(BC34:BE34) -> 80 | BG34: 72 | BH34: 63 | BI34: 52 | BJ34: =243-SUM(BG34:BI34) -> 56 | BK34: 52 | CC34: =SUM(AQ34:AT34) -> 502 | CD34: =SUM(AU34:AX34) -> 472 | CE34: =SUM(AY34:BB34) -> 384 | CF34: =SUM(BC34:BF34) -> 308 | CG34: =SUM(BG34:BJ34) -> 243
B35: APAC Revenues | AQ35: 99 | AR35: 85 | AS35: 90 | AT35: =517-SUM(AQ35:AS35) -> 243 | AU35: 132 | AV35: 131 | AW35: 126 | AX35: =544-SUM(AU35:AW35) -> 155 | AY35: 119 | AZ35: 118 | BA35: 98 | BB35: =459-SUM(AY35:BA35) -> 124 | BC35: 116 | BD35: 108 | BE35: 105 | BF35: =438-SUM(BC35:BE35) -> 109 | BG35: 82 | BH35: 100 | BI35: 111 | BJ35: =430-SUM(BG35:BI35) -> 137 | BK35: 93 | CC35: =SUM(AQ35:AT35) -> 517 | CD35: =SUM(AU35:AX35) -> 544 | CE35: =SUM(AY35:BB35) -> 459 | CF35: =SUM(BC35:BF35) -> 438 | CG35: =SUM(BG35:BJ35) -> 430
B36: Ttl Revenues | AQ36: =SUM(AQ32:AQ35) -> 1093 | AR36: =SUM(AR32:AR35) -> 1126 | AS36: =SUM(AS32:AS35) -> 1108 | AT36: =SUM(AT32:AT35) -> 1199 | AU36: =SUM(AU32:AU35) -> 1223 | AV36: =SUM(AV32:AV35) -> 1162 | AW36: =SUM(AW32:AW35) -> 1115 | AX36: =SUM(AX32:AX35) -> 1084 | ... BK36: =SUM(BK32:BK35) -> 1091 | CC36: =SUM(AQ36:AT36) -> 4526 | CD36: =SUM(AU36:AX36) -> 4584 | CE36: =SUM(AY36:BB36) -> 4504 | CF36: =SUM(BC36:BF36) -> 4372 | CG36: =SUM(BG36:BJ36) -> 4343
B38: U.S. Revenues Growth Y/y | AU38: =AU32/AQ32-1 -> 0.15302491 | AV38: =AV32/AR32-1 -> 0.084889643 | AW38: =AW32/AS32-1 -> 0.024013722 | AX38: =AX32/AT32-1 -> -0.046474359 | AY38: =AY32/AU32-1 -> -0.049382716 | AZ38: =AZ32/AV32-1 -> 0.0015649452 | BA38: =BA32/AW32-1 -> 0.11055276 | BB38: =BB32/AX32-1 -> 0.011764706 | ... BK38: =BK32/BG32-1 -> 0.063063063 | CD38: =CD32/CC32-1 -> 0.051314673 | CE38: =CE32/CD32-1 -> 0.016942315 | CF38: =CF32/CE32-1 -> -0.031733439 | CG38: =CG32/CF32-1 -> -0.014338386
B39: Euro, Mid-East, Africa, LatAm Revenues Growth Y/y | AU39: =AU33/AQ33-1 -> 0.036065574 | AV39: =AV33/AR33-1 -> -0.14375 | AW39: =AW33/AS33-1 -> -0.17252396 | AX39: =AX33/AT33-1 -> 0.13744076 | AY39: =AY33/AU33-1 -> -0.17405063 | AZ39: =AZ33/AV33-1 -> 0.10583942 | BA39: =BA33/AW33-1 -> 0.0038610039 | BB39: =BB33/AX33-1 -> 0.31666667 | ... BK39: =BK33/BG33-1 -> 0.072289157 | CD39: =CD33/CC33-1 -> -0.052219321 | CE39: =CE33/CD33-1 -> 0.046831956 | CF39: =CF33/CE33-1 -> 0.039473684 | CG39: =CG33/CF33-1 -> 0.066666667
B40: Taiwan, China Revenues Growth Y/y | AU40: =AU34/AQ34-1 -> 0 | AV40: =AV34/AR34-1 -> -0.10606061 | AW40: =AW34/AS34-1 -> 0.090163934 | AX40: =AX34/AT34-1 -> -0.2231405 | AY40: =AY34/AU34-1 -> -0.28346457 | AZ40: =AZ34/AV34-1 -> -0.025423729 | BA40: =BA34/AW34-1 -> -0.26315789 | BB40: =BB34/AX34-1 -> -0.14893617 | ... BK40: =BK34/BG34-1 -> -0.27777778 | CD40: =CD34/CC34-1 -> -0.059760956 | CE40: =CE34/CD34-1 -> -0.18644068 | CF40: =CF34/CE34-1 -> -0.19791667 | CG40: =CG34/CF34-1 -> -0.21103896
B41: APAC Revenues Growth Y/y | AU41: =AU35/AQ35-1 -> 0.33333333 | AV41: =AV35/AR35-1 -> 0.54117647 | AW41: =AW35/AS35-1 -> 0.4 | AX41: =AX35/AT35-1 -> -0.36213992 | AY41: =AY35/AU35-1 -> -0.098484848 | AZ41: =AZ35/AV35-1 -> -0.099236641 | BA41: =BA35/AW35-1 -> -0.22222222 | BB41: =BB35/AX35-1 -> -0.2 | ... BK41: =BK35/BG35-1 -> 0.13414634 | CD41: =CD35/CC35-1 -> 0.052224371 | CE41: =CE35/CD35-1 -> -0.15625 | CF41: =CF35/CE35-1 -> -0.045751634 | CG41: =CG35/CF35-1 -> -0.01826484
B42: Ttl Revenues Growth Y/y | AU42: =AU36/AQ36-1 -> 0.1189387 | AV42: =AV36/AR36-1 -> 0.031971581 | AW42: =AW36/AS36-1 -> 0.0063176895 | AX42: =AX36/AT36-1 -> -0.095913261 | AY42: =AY36/AU36-1 -> -0.11120196 | AZ42: =AZ36/AV36-1 -> 0.012048193 | BA42: =BA36/AW36-1 -> 0.0035874439 | BB42: =BB36/AX36-1 -> 0.035055351 | ... BK42: =BK36/BG36-1 -> 0.04803074 | CD42: =CD36/CC36-1 -> 0.012814848 | CE42: =CE36/CD36-1 -> -0.017452007 | CF42: =CF36/CE36-1 -> -0.029307282 | CG42: =CG36/CF36-1 -> -0.0066331199
B44: U.S. Revenues % of Revenues | AQ44: =AQ32/AQ36 -> 0.51418115 | AR44: =AR32/AR36 -> 0.52309059 | AS44: =AS32/AS36 -> 0.52617329 | AT44: =AT32/AT36 -> 0.52043369 | AU44: =AU32/AU36 -> 0.52984464 | AV44: =AV32/AV36 -> 0.54991394 | AW44: =AW32/AW36 -> 0.53542601 | AX44: =AX32/AX36 -> 0.54889299 | ... BK44: =BK32/BK36 -> 0.54078827 | CC44: =CC32/CC36 -> 0.52098984 | CD44: =CD32/CD36 -> 0.54079407 | CE44: =CE32/CE36 -> 0.55972469 | CF44: =CF32/CF36 -> 0.55832571 | CG44: =CG32/CG36 -> 0.55399493
B45: Euro, Mid-East, Africa, LatAm Revenues % of Revenues | AQ45: =AQ33/AQ36 -> 0.27904849 | AR45: =AR33/AR36 -> 0.28419183 | AS45: =AS33/AS36 -> 0.28249097 | AT45: =AT33/AT36 -> 0.17597998 | AU45: =AU33/AU36 -> 0.25838103 | AV45: =AV33/AV36 -> 0.23580034 | AW45: =AW33/AW36 -> 0.232287 | AX45: =AX33/AX36 -> 0.22140221 | ... BK45: =BK33/BK36 -> 0.32630614 | CC45: =CC33/CC36 -> 0.25386655 | CD45: =CD33/CD36 -> 0.23756545 | CE45: =CE33/CE36 -> 0.25310835 | CF45: =CF33/CF36 -> 0.271043 | CG45: =CG33/CG36 -> 0.29104306
B46: Taiwan, China Revenues % of Revenues | AQ46: =AQ34/AQ36 -> 0.11619396 | AR46: =AR34/AR36 -> 0.11722913 | AS46: =AS34/AS36 -> 0.1101083 | AT46: =AT34/AT36 -> 0.10091743 | AU46: =AU34/AU36 -> 0.10384301 | AV46: =AV34/AV36 -> 0.10154905 | AW46: =AW34/AW36 -> 0.11928251 | AX46: =AX34/AX36 -> 0.086715867 | ... BK46: =BK34/BK36 -> 0.047662695 | CC46: =CC34/CC36 -> 0.11091471 | CD46: =CD34/CD36 -> 0.10296684 | CE46: =CE34/CE36 -> 0.085257549 | CF46: =CF34/CF36 -> 0.070448307 | CG46: =CG34/CG36 -> 0.055952107
B47: APAC Revenues % of Revenues | AQ47: =AQ35/AQ36 -> 0.090576395 | AR47: =AR35/AR36 -> 0.075488455 | AS47: =AS35/AS36 -> 0.081227437 | AT47: =AT35/AT36 -> 0.20266889 | AU47: =AU35/AU36 -> 0.10793132 | AV47: =AV35/AV36 -> 0.11273666 | AW47: =AW35/AW36 -> 0.11300448 | AX47: =AX35/AX36 -> 0.14298893 | ... BK47: =BK35/BK36 -> 0.085242896 | CC47: =CC35/CC36 -> 0.1142289 | CD47: =CD35/CD36 -> 0.11867365 | CE47: =CE35/CE36 -> 0.10190941 | CF47: =CF35/CF36 -> 0.10018298 | CG47: =CG35/CG36 -> 0.099009901
B49: Revenues | C49: 282.515 | D49: 287.45 | E49: 235.499 | F49: 250.071 | G49: 272.77 | H49: 280.607 | I49: 285.874 | J49: 309.265 | K49: 330.958 | L49: 346.094 | M49: 356.8 | N49: 387.326 | O49: 420.781 | P49: 447.568 | Q49: 480.63 | R49: 512.379 | S49: 538.565 | T49: 539.378 | U49: 550.271 | V49: 591.786 | W49: 572 | X49: 600 | Y49: 607 | Z49: 619 | AA49: 598 | AB49: 662 | AC49: 714 | AD49: 778 | AE49: 154 | AF49: 830 | AG49: 853 | AH49: 1496 | AI49: 846 | AJ49: 838 | AK49: 907 | AL49: 952 | AM49: 859 | AN49: 633 | AO49: 794 | AP49: 953 | AQ49: =AQ8 -> 1093 | AR49: =AR8 -> 1126 | AS49: =AS8 -> 1108 | AT49: =AT8 -> 1199 | AU49: =AU8 -> 1223 | AV49: =AV8 -> 1162 | AW49: =AW8 -> 1115 | AX49: =AX8 -> 1084 | ... BK49: =BK8 -> 1091 | BS49: =SUM(C49:F49) -> 1055.535 | BT49: =SUM(G49:J49) -> 1148.516 | BU49: =SUM(K49:N49) -> 1421.178 | BV49: =SUM(O49:R49) -> 1861.358 | BW49: =SUM(S49:V49) -> 2220 | BX49: =SUM(W49:Z49) -> 2398 | BY49: =SUM(AA49:AD49) -> 2752 | BZ49: =SUM(AE49:AH49) -> 3333 | CA49: =SUM(AI49:AL49) -> 3543 | CB49: =SUM(AM49:AP49) -> 3239 | CC49: =SUM(AQ49:AT49) -> 4526 | CD49: =SUM(AU49:AX49) -> 4584 | CE49: =SUM(AY49:BB49) -> 4504 | CF49: =SUM(BC49:BF49) -> 4372 | CG49: =SUM(BG49:BJ49) -> 4343
B50: COGS | C50: 94.474 | D50: 94.094 | E50: 78.384 | F50: 79.485 | G50: 91.759 | H50: 87.61 | I50: 90.001 | J50: 105.618 | K50: 111.666 | L50: 122.685 | M50: 146.86 | N50: 128.08 | O50: 142.489 | P50: 147.028 | Q50: 146.689 | R50: 127.442 | S50: 163.538 | T50: 163.013 | U50: 162.732 | V50: 181.717 | W50: 175 | X50: 176 | Y50: 181 | Z50: 200 | AA50: 230 | AB50: 228 | AC50: 455 | AD50: 13 | AE50: 244 | AF50: 255 | AG50: 256 | AH50: 278 | AI50: 262 | AJ50: 265 | AK50: 259 | AL50: 290 | AM50: 240 | AN50: 205 | AO50: 268 | AP50: 323 | AQ50: 329 | AR50: 324 | AS50: 338 | AT50: 381 | AU50: 408 | AV50: 395 | AW50: 398 | AX50: 411 | AY50: 432 | AZ50: 444 | BA50: 435 | BB50: 449 | BC50: 409 | BD50: 391 | BE50: 335 | BF50: 376 | BG50: 358 | BH50: 364 | BI50: 351 | BJ50: 400 | BK50: 370 | BS50: =SUM(C50:F50) -> 346.437 | BT50: =SUM(G50:J50) -> 374.988 | BU50: =SUM(K50:N50) -> 509.291 | BV50: =SUM(O50:R50) -> 563.648 | BW50: =SUM(S50:V50) -> 671 | BX50: =SUM(W50:Z50) -> 732 | BY50: =SUM(AA50:AD50) -> 926 | BZ50: =SUM(AE50:AH50) -> 1033 | CA50: =SUM(AI50:AL50) -> 1076 | CB50: =SUM(AM50:AP50) -> 1036 | CC50: =SUM(AQ50:AT50) -> 1372 | CD50: =SUM(AU50:AX50) -> 1612 | CE50: =SUM(AY50:BB50) -> 1760 | CF50: =SUM(BC50:BF50) -> 1511 | CG50: =SUM(BG50:BJ50) -> 1473
B51: GP | C51: =C49-C50 -> 188.041 | D51: =D49-D50 -> 193.356 | E51: =E49-E50 -> 157.115 | F51: =F49-F50 -> 170.586 | G51: =G49-G50 -> 181.011 | H51: =H49-H50 -> 192.997 | I51: =I49-I50 -> 195.873 | J51: =J49-J50 -> 203.647 | ... BK51: =BK49-BK50 -> 721 | BS51: =SUM(C51:F51) -> 709.098 | BT51: =SUM(G51:J51) -> 773.528 | BU51: =SUM(K51:N51) -> 911.887 | BV51: =SUM(O51:R51) -> 1297.71 | BW51: =SUM(S51:V51) -> 1549 | BX51: =SUM(W51:Z51) -> 1666 | BY51: =SUM(AA51:AD51) -> 1826 | BZ51: =SUM(AE51:AH51) -> 2300 | CA51: =SUM(AI51:AL51) -> 2467 | CB51: =SUM(AM51:AP51) -> 2203 | CC51: =SUM(AQ51:AT51) -> 3154 | CD51: =SUM(AU51:AX51) -> 2972 | CE51: =SUM(AY51:BB51) -> 2744 | CF51: =SUM(BC51:BF51) -> 2861 | CG51: =SUM(BG51:BJ51) -> 2870
B52: R&D | C52: 50.2 | D52: 50.801 | E52: 50.399 | F52: 45.513 | G52: 48.839 | H52: 71.223 | I52: 54.056 | J52: 56.907 | K52: 61.45 | L52: 67.608 | M52: 70.957 | N52: 76.728 | O52: 77.041 | P52: 82.985 | Q52: 85.082 | R52: 142.947 | S52: 91.772 | T52: 96.182 | U52: 99.226 | V52: 113.82 | W52: 124 | X52: 125 | Y52: 126 | Z52: 129 | AA52: 145 | AB52: 130 | AC52: 134 | AD52: 137 | AE52: 137 | AF52: 151 | AG52: 159 | AH52: 176 | AI52: 169 | AJ52: 166 | AK52: 151 | AL52: 161 | AM52: 156 | AN52: 155 | AO52: 172 | AP52: 199 | AQ52: 197 | AR52: 202 | AS52: 436 | AT52: 350 | AU52: 323 | AV52: 327 | AW52: 325 | AX52: 346 | AY52: 341 | AZ52: 358 | BA52: 315 | BB52: 340 | BC52: 339 | BD52: 325 | BE52: 253 | BF52: 252 | BG52: 252 | BH52: 247 | BI52: 229 | BJ52: 239 | BK52: 240 | BS52: =SUM(C52:F52) -> 196.913 | BT52: =SUM(G52:J52) -> 231.025 | BU52: =SUM(K52:N52) -> 276.743 | BV52: =SUM(O52:R52) -> 388.055 | BW52: =SUM(S52:V52) -> 401 | BX52: =SUM(W52:Z52) -> 504 | BY52: =SUM(AA52:AD52) -> 546 | BZ52: =SUM(AE52:AH52) -> 623 | CA52: =SUM(AI52:AL52) -> 647 | CB52: =SUM(AM52:AP52) -> 682 | CC52: =SUM(AQ52:AT52) -> 1185 | CD52: =SUM(AU52:AX52) -> 1321 | CE52: =SUM(AY52:BB52) -> 1354 | CF52: =SUM(BC52:BF52) -> 1169 | CG52: =SUM(BG52:BJ52) -> 967
B53: SG&A | C53: 65.661 | D53: 69.233 | E53: 66.031 | F53: 60.918 | G53: 67.969 | H53: 68.516 | I53: 69.791 | J53: 79.715 | K53: 85.074 | L53: 88.7 | M53: 95.617 | N53: 111.649 | O53: 109.573 | P53: 114.649 | Q53: 119.888 | R53: 122.173 | S53: 116.317 | T53: 124.441 | U53: 136.648 | V53: 138.594 | W53: 150 | X53: 148 | Y53: 139 | Z53: 147 | AA53: 171 | AB53: 161 | AC53: 167 | AD53: 175 | AE53: 183 | AF53: 197 | AG53: 197 | AH53: 217 | AI53: 211 | AJ53: 202 | AK53: 189 | AL53: 233 | AM53: 274 | AN53: 177 | AO53: 192 | AP53: 298 | AQ53: 374 | AR53: 413 | AS53: 879 | AT53: 426 | AU53: 308 | AV53: 410 | AW53: 146 | AX53: 433 | AY53: 378 | AZ53: 462 | BA53: 303 | BB53: 469 | BC53: 439 | BD53: 147 | BE53: 239 | BF53: 267 | BG53: 267 | BH53: 234 | BI53: 277 | BJ53: 308 | BK53: 272 | BS53: =SUM(C53:F53) -> 261.843 | BT53: =SUM(G53:J53) -> 285.991 | BU53: =SUM(K53:N53) -> 381.04 | BV53: =SUM(O53:R53) -> 466.283 | BW53: =SUM(S53:V53) -> 516 | BX53: =SUM(W53:Z53) -> 584 | BY53: =SUM(AA53:AD53) -> 674 | BZ53: =SUM(AE53:AH53) -> 794 | CA53: =SUM(AI53:AL53) -> 835 | CB53: =SUM(AM53:AP53) -> 941 | CC53: =SUM(AQ53:AT53) -> 2092 | CD53: =SUM(AU53:AX53) -> 1297 | CE53: =SUM(AY53:BB53) -> 1612 | CF53: =SUM(BC53:BF53) -> 1092 | CG53: =SUM(BG53:BJ53) -> 1086
B54: Operating Income | C54: =C51-SUM(C52:C53) -> 72.18 | D54: =D51-SUM(D52:D53) -> 73.322 | E54: =E51-SUM(E52:E53) -> 40.685 | F54: =F51-SUM(F52:F53) -> 64.155 | G54: =G51-SUM(G52:G53) -> 64.203 | H54: =H51-SUM(H52:H53) -> 53.258 | I54: =I51-SUM(I52:I53) -> 72.026 | J54: =J51-SUM(J52:J53) -> 67.025 | ... BK54: =BK51-SUM(BK52:BK53) -> 209 | BS54: =SUM(C54:F54) -> 250.342 | BT54: =SUM(G54:J54) -> 256.512 | BU54: =SUM(K54:N54) -> 254.104 | BV54: =SUM(O54:R54) -> 443.372 | BW54: =SUM(S54:V54) -> 632 | BX54: =SUM(W54:Z54) -> 578 | BY54: =SUM(AA54:AD54) -> 606 | BZ54: =SUM(AE54:AH54) -> 883 | CA54: =SUM(AI54:AL54) -> 985 | CB54: =SUM(AM54:AP54) -> 580 | CC54: =SUM(AQ54:AT54) -> -123 | CD54: =SUM(AU54:AX54) -> 354 | CE54: =SUM(AY54:BB54) -> -222 | CF54: =SUM(BC54:BF54) -> 600 | CG54: =SUM(BG54:BJ54) -> 817
B55: Interest Income | C55: -33.38 | D55: -16.986 | E55: -8.973 | F55: -7.077 | G55: -9.339 | H55: -8.193 | I55: -5.169 | J55: 44.557 | K55: -2.415 | L55: -10.646 | M55: -8.317 | N55: 46.585 | O55: -8.308 | P55: -39.773 | Q55: -7.05 | R55: -10.822 | S55: 1.92 | T55: -10.761 | U55: -11.865 | V55: -9.294 | W55: -5 | X55: -5 | Y55: -7 | Z55: -9 | AA55: 451 | AB55: -2 | AC55: -6 | AD55: -6 | AE55: 3 | AF55: 5 | AG55: -9 | AH55: 12 | AI55: 29 | AJ55: 141 | AK55: -38 | AL55: 1 | AM55: -11 | AN55: 69 | AO55: 53 | AP55: 165 | AQ55: 1 | AR55: 0 | AS55: 0 | AT55: 0 | AU55: 0 | AV55: 1 | AW55: 3 | AX55: 7 | AY55: 17 | AZ55: 17 | BA55: 13 | BB55: 11 | BC55: 12 | BD55: 13 | BE55: 11 | BF55: 12 | BG55: 11 | BH55: 10 | BI55: 9 | BJ55: 20 | BK55: 11 | BS55: =SUM(C55:F55) -> -66.416 | BT55: =SUM(G55:J55) -> 21.856 | BU55: =SUM(K55:N55) -> 25.207 | BV55: =SUM(O55:R55) -> -65.953 | BW55: =SUM(S55:V55) -> -30 | BX55: =SUM(W55:Z55) -> -26 | BY55: =SUM(AA55:AD55) -> 437 | BZ55: =SUM(AE55:AH55) -> 11 | CA55: =SUM(AI55:AL55) -> 133 | CB55: =SUM(AM55:AP55) -> 276 | CC55: =SUM(AQ55:AT55) -> 1 | CD55: =SUM(AU55:AX55) -> 11 | CE55: =SUM(AY55:BB55) -> 58 | CF55: =SUM(BC55:BF55) -> 48 | CG55: =SUM(BG55:BJ55) -> 50
B56: Interest Expenses | AQ56: -19 | AR56: -16 | AS56: -14 | AT56: -12 | AU56: -6 | AV56: -6 | AW56: -6 | AX56: -8 | AY56: 20 | AZ56: -19 | BA56: -19 | BB56: -59 | BC56: -18 | BD56: -20 | BE56: -36 | BF56: 118 | BG56: -25 | BH56: -25 | BI56: -25 | BJ56: -26 | BK56: -24 | BS56: =SUM(C56:F56) -> 0 | BT56: =SUM(G56:J56) -> 0 | BU56: =SUM(K56:N56) -> 0 | BV56: =SUM(O56:R56) -> 0 | BW56: =SUM(S56:V56) -> 0 | BX56: =SUM(W56:Z56) -> 0 | BY56: =SUM(AA56:AD56) -> 0 | BZ56: =SUM(AE56:AH56) -> 0 | CA56: =SUM(AI56:AL56) -> 0 | CB56: =SUM(AM56:AP56) -> 0 | CC56: =SUM(AQ56:AT56) -> -61 | CD56: =SUM(AU56:AX56) -> -26 | CE56: =SUM(AY56:BB56) -> -77 | CF56: =SUM(BC56:BF56) -> 44 | CG56: =SUM(BG56:BJ56) -> -101
B57: Other Income (Expenses) | AQ57: -6 | AR57: 36 | AS57: 979 | AT57: 59 | AU57: -38 | AV57: -53 | AW57: -12 | AX57: -39 | AY57: -11 | AZ57: 1 | BA57: -22 | BB57: 3 | BC57: 8 | BD57: -332 | BE57: 4 | BF57: 28 | BG57: 32 | BH57: 107 | BI57: 9 | BJ57: 172 | BK57: -39 | BS57: =SUM(C57:F57) -> 0 | BT57: =SUM(G57:J57) -> 0 | BU57: =SUM(K57:N57) -> 0 | BV57: =SUM(O57:R57) -> 0 | BW57: =SUM(S57:V57) -> 0 | BX57: =SUM(W57:Z57) -> 0 | BY57: =SUM(AA57:AD57) -> 0 | BZ57: =SUM(AE57:AH57) -> 0 | CA57: =SUM(AI57:AL57) -> 0 | CB57: =SUM(AM57:AP57) -> 0 | CC57: =SUM(AQ57:AT57) -> 1068 | CD57: =SUM(AU57:AX57) -> -142 | CE57: =SUM(AY57:BB57) -> -29 | CF57: =SUM(BC57:BF57) -> -292 | CG57: =SUM(BG57:BJ57) -> 320
B58: Pretax Income | C58: =C54+SUM(C55:C57) -> 38.8 | D58: =D54+SUM(D55:D57) -> 56.336 | E58: =E54+SUM(E55:E57) -> 31.712 | F58: =F54+SUM(F55:F57) -> 57.078 | G58: =G54+SUM(G55:G57) -> 54.864 | H58: =H54+SUM(H55:H57) -> 45.065 | I58: =I54+SUM(I55:I57) -> 66.857 | J58: =J54+SUM(J55:J57) -> 111.582 | ... BK58: =BK54+SUM(BK55:BK57) -> 157 | BS58: =SUM(C58:F58) -> 183.926 | BT58: =SUM(G58:J58) -> 278.368 | BU58: =SUM(K58:N58) -> 279.311 | BV58: =SUM(O58:R58) -> 377.419 | BW58: =SUM(S58:V58) -> 602 | BX58: =SUM(W58:Z58) -> 552 | BY58: =SUM(AA58:AD58) -> 1043 | BZ58: =SUM(AE58:AH58) -> 894 | CA58: =SUM(AI58:AL58) -> 1118 | CB58: =SUM(AM58:AP58) -> 856 | CC58: =SUM(AQ58:AT58) -> 885 | CD58: =SUM(AU58:AX58) -> 197 | CE58: =SUM(AY58:BB58) -> -270 | CF58: =SUM(BC58:BF58) -> 400 | CG58: =SUM(BG58:BJ58) -> 1086
B59: Taxes | C59: 11.871 | D59: 18.404 | E59: 7.64 | F59: 8.502 | G59: 14.071 | H59: 11.386 | I59: 13.897 | J59: 32 | K59: -24.975 | L59: 13.483 | M59: 5.79 | N59: 39.708 | O59: 23.811 | P59: 13.861 | Q59: 18.954 | R59: 38.781 | S59: 41.388 | T59: 38.925 | U59: 13.296 | V59: 31.391 | W59: 28 | X59: 41 | Y59: 37 | Z59: 27 | AA59: 155 | AB59: 21 | AC59: 23 | AD59: 166 | AE59: 24 | AF59: 32 | AG59: 44 | AH59: 12 | AI59: 9 | AJ59: 53 | AK59: 36 | AL59: 30 | AM59: 5 | AN59: 118 | AO59: 36 | AP59: 41 | AQ59: 22 | AR59: 22 | AS59: 103 | AT59: -24 | AU59: 54 | AV59: -102 | AW59: 144 | AX59: -28 | AY59: -81 | AZ59: 145 | BA59: -28 | BB59: 8 | BC59: 17 | BD59: 12 | BE59: 15 | BF59: 0 | BG59: 51 | BH59: 71 | BI59: 70 | BJ59: 44 | BK59: 23 | BS59: =SUM(C59:F59) -> 46.417 | BT59: =SUM(G59:J59) -> 71.354 | BU59: =SUM(K59:N59) -> 34.006 | BV59: =SUM(O59:R59) -> 95.407 | BW59: =SUM(S59:V59) -> 125 | BX59: =SUM(W59:Z59) -> 133 | BY59: =SUM(AA59:AD59) -> 365 | BZ59: =SUM(AE59:AH59) -> 112 | CA59: =SUM(AI59:AL59) -> 128 | CB59: =SUM(AM59:AP59) -> 200 | CC59: =SUM(AQ59:AT59) -> 123 | CD59: =SUM(AU59:AX59) -> 68 | CE59: =SUM(AY59:BB59) -> 44 | CF59: =SUM(BC59:BF59) -> 44 | CG59: =SUM(BG59:BJ59) -> 236
B60: Net Income | C60: =C58-C59 -> 26.929 | D60: =D58-D59 -> 37.932 | E60: =E58-E59 -> 24.072 | F60: =F58-F59 -> 48.576 | G60: =G58-G59 -> 40.793 | H60: =H58-H59 -> 33.679 | I60: =I58-I59 -> 52.96 | J60: =J58-J59 -> 79.582 | ... BK60: =BK58-BK59 -> 134 | BS60: =SUM(C60:F60) -> 137.509 | BT60: =SUM(G60:J60) -> 207.014 | BU60: =SUM(K60:N60) -> 245.305 | BV60: =SUM(O60:R60) -> 282.012 | BW60: =SUM(S60:V60) -> 477 | BX60: =SUM(W60:Z60) -> 419 | BY60: =SUM(AA60:AD60) -> 678 | BZ60: =SUM(AE60:AH60) -> 782 | CA60: =SUM(AI60:AL60) -> 990 | CB60: =SUM(AM60:AP60) -> 656 | CC60: =SUM(AQ60:AT60) -> 762 | CD60: =SUM(AU60:AX60) -> 129 | CE60: =SUM(AY60:BB60) -> -314 | CF60: =SUM(BC60:BF60) -> 356 | CG60: =SUM(BG60:BJ60) -> 850
B61: SC | AQ61: 146 | AR61: 146 | AS61: 152 | AT61: 150 | AU61: 157 | AV61: 157 | AW61: 157 | AX61: 157 | AY61: 158 | AZ61: 158 | BA61: 158 | BB61: 158 | BC61: 159 | BD61: 159 | BE61: 159 | BF61: 159 | BG61: 159 | BH61: 157 | BI61: 153 | BJ61: 155 | BK61: 153 | BS61: =AVERAGE(C61:F61) -> #DIV/0! | BT61: =AVERAGE(G61:J61) -> #DIV/0! | BU61: =AVERAGE(K61:N61) -> #DIV/0! | BV61: =AVERAGE(O61:R61) -> #DIV/0! | BW61: =AVERAGE(S61:V61) -> #DIV/0! | BX61: =AVERAGE(W61:Z61) -> #DIV/0! | BY61: =AVERAGE(AA61:AD61) -> #DIV/0! | BZ61: =AVERAGE(AE61:AH61) -> #DIV/0! | CA61: =AVERAGE(AI61:AL61) -> #DIV/0! | CB61: =AVERAGE(AM61:AP61) -> #DIV/0! | CC61: =AVERAGE(AQ61:AT61) -> 148.5 | CD61: =AVERAGE(AU61:AX61) -> 157 | CE61: =AVERAGE(AY61:BB61) -> 158 | CF61: =AVERAGE(BC61:BF61) -> 159 | CG61: =AVERAGE(BG61:BJ61) -> 156
B62: EPS | C62: =C60/C61 -> #DIV/0! | D62: =D60/D61 -> #DIV/0! | E62: =E60/E61 -> #DIV/0! | F62: =F60/F61 -> #DIV/0! | G62: =G60/G61 -> #DIV/0! | H62: =H60/H61 -> #DIV/0! | I62: =I60/I61 -> #DIV/0! | J62: =J60/J61 -> #DIV/0! | ... BK62: =BK60/BK61 -> 0.87581699 | BS62: =SUM(C62:F62) -> #DIV/0! | BT62: =SUM(G62:J62) -> #DIV/0! | BU62: =SUM(K62:N62) -> #DIV/0! | BV62: =SUM(O62:R62) -> #DIV/0! | BW62: =SUM(S62:V62) -> #DIV/0! | BX62: =SUM(W62:Z62) -> #DIV/0! | BY62: =SUM(AA62:AD62) -> #DIV/0! | BZ62: =SUM(AE62:AH62) -> #DIV/0! | CA62: =SUM(AI62:AL62) -> #DIV/0! | CB62: =SUM(AM62:AP62) -> #DIV/0! | CC62: =SUM(AQ62:AT62) -> 5.1128323 | CD62: =SUM(AU62:AX62) -> 0.82165605 | CE62: =SUM(AY62:BB62) -> -1.9873418 | CF62: =SUM(BC62:BF62) -> 2.2389937 | CG62: =SUM(BG62:BJ62) -> 5.4559455
B64: Gross Profit Margin | C64: =C51/C49 -> 0.66559652 | D64: =D51/D49 -> 0.67265959 | E64: =E51/E49 -> 0.66715782 | F64: =F51/F49 -> 0.68215027 | G64: =G51/G49 -> 0.66360304 | H64: =H51/H49 -> 0.68778398 | I64: =I51/I49 -> 0.68517249 | J64: =J51/J49 -> 0.65848706 | ... BK64: =BK51/BK49 -> 0.66086159 | BS64: =BS51/BS49 -> 0.67179013 | BT64: =BT51/BT49 -> 0.67350215 | BU64: =BU51/BU49 -> 0.64164165 | BV64: =BV51/BV49 -> 0.69718453 | BW64: =BW51/BW49 -> 0.69774775 | BX64: =BX51/BX49 -> 0.69474562 | BY64: =BY51/BY49 -> 0.66351744 | BZ64: =BZ51/BZ49 -> 0.69006901 | ... CG64: =CG51/CG49 -> 0.66083353
B65: R&D as % of Revenue | C65: =C52/C49 -> 0.17768968 | D65: =D52/D49 -> 0.17672987 | E65: =E52/E49 -> 0.2140094 | F65: =F52/F49 -> 0.18200031 | G65: =G52/G49 -> 0.17904828 | H65: =H52/H49 -> 0.25381762 | I65: =I52/I49 -> 0.1890903 | J65: =J52/J49 -> 0.18400724 | ... BK65: =BK52/BK49 -> 0.21998167 | BS65: =BS52/BS49 -> 0.18655279 | BT65: =BT52/BT49 -> 0.20115088 | BU65: =BU52/BU49 -> 0.19472789 | BV65: =BV52/BV49 -> 0.20847951 | BW65: =BW52/BW49 -> 0.18063063 | BX65: =BX52/BX49 -> 0.21017515 | BY65: =BY52/BY49 -> 0.19840116 | BZ65: =BZ52/BZ49 -> 0.18691869 | ... CG65: =CG52/CG49 -> 0.22265715
B66: SG&A as % of Revenue | C66: =C53/C49 -> 0.23241598 | D66: =D53/D49 -> 0.24085232 | E66: =E53/E49 -> 0.2803876 | F66: =F53/F49 -> 0.24360282 | G66: =G53/G49 -> 0.24918063 | H66: =H53/H49 -> 0.24417067 | I66: =I53/I49 -> 0.24413203 | J66: =J53/J49 -> 0.25775629 | ... BK66: =BK53/BK49 -> 0.24931256 | BS66: =BS53/BS49 -> 0.24806662 | BT66: =BT53/BT49 -> 0.24900916 | BU66: =BU53/BU49 -> 0.26811561 | BV66: =BV53/BV49 -> 0.25050689 | BW66: =BW53/BW49 -> 0.23243243 | BX66: =BX53/BX49 -> 0.24353628 | BY66: =BY53/BY49 -> 0.24491279 | BZ66: =BZ53/BZ49 -> 0.23822382 | ... CG66: =CG53/CG49 -> 0.25005756
B67: Operating Profit Margin | C67: =C54/C49 -> 0.25549086 | D67: =D54/D49 -> 0.2550774 | E67: =E54/E49 -> 0.17276082 | F67: =F54/F49 -> 0.25654714 | G67: =G54/G49 -> 0.23537412 | H67: =H54/H49 -> 0.18979569 | I67: =I54/I49 -> 0.25195016 | J67: =J54/J49 -> 0.21672352 | ... BK67: =BK54/BK49 -> 0.19156737 | BS67: =BS54/BS49 -> 0.23717072 | BT67: =BT54/BT49 -> 0.22334212 | BU67: =BU54/BU49 -> 0.17879815 | BV67: =BV54/BV49 -> 0.23819813 | BW67: =BW54/BW49 -> 0.28468468 | BX67: =BX54/BX49 -> 0.2410342 | BY67: =BY54/BY49 -> 0.22020349 | BZ67: =BZ54/BZ49 -> 0.26492649 | ... CG67: =CG54/CG49 -> 0.18811881
B68: Effective Tax Rate | C68: =C59/C58 -> 0.30595361 | D68: =D59/D58 -> 0.32668276 | E68: =E59/E58 -> 0.24091826 | F68: =F59/F58 -> 0.14895406 | G68: =G59/G58 -> 0.25647055 | H68: =H59/H58 -> 0.25265727 | I68: =I59/I58 -> 0.20786156 | J68: =J59/J58 -> 0.28678461 | ... BK68: =BK59/BK58 -> 0.14649682 | BS68: =BS59/BS58 -> 0.2523678 | BT68: =BT59/BT58 -> 0.25632975 | BU68: =BU59/BU58 -> 0.12174959 | BV68: =BV59/BV58 -> 0.25278802 | BW68: =BW59/BW58 -> 0.2076412 | BX68: =BX59/BX58 -> 0.24094203 | BY68: =BY59/BY58 -> 0.34995206 | BZ68: =BZ59/BZ58 -> 0.12527964 | ... CG68: =CG59/CG58 -> 0.21731123
B69: Net Profit Margin | C69: =C60/C49 -> 0.095318833 | D69: =D60/D49 -> 0.13196034 | E69: =E60/E49 -> 0.10221699 | F69: =F60/F49 -> 0.19424883 | G69: =G60/G49 -> 0.1495509 | H69: =H60/H49 -> 0.12002195 | I69: =I60/I49 -> 0.18525644 | J69: =J60/J49 -> 0.25732624 | ... BK69: =BK60/BK49 -> 0.1228231 | BS69: =BS60/BS49 -> 0.13027422 | BT69: =BT60/BT49 -> 0.18024477 | BU69: =BU60/BU49 -> 0.17260681 | BV69: =BV60/BV49 -> 0.15150874 | BW69: =BW60/BW49 -> 0.21486486 | BX69: =BX60/BX49 -> 0.17472894 | BY69: =BY60/BY49 -> 0.24636628 | BZ69: =BZ60/BZ49 -> 0.23462346 | ... CG69: =CG60/CG49 -> 0.19571725
B71: Cash & CEs | BB71: 1048 | BC71: 1108 | BD71: 920 | BE71: 869 | BF71: 1127 | BG71: 1113 | BH71: 934 | BI71: 1050 | BJ71: 1418 | BK71: 1089 | CE71: =BB71 -> 1048 | CF71: =BF71 -> 1127 | CG71: =BG71 -> 1113
B72: ST Investments | BB72: 6 | BC72: 6 | BD72: 74 | BE72: 70 | BF72: 93 | BG72: 124 | BH72: 221 | BI72: 228 | BJ72: 215 | BK72: 66 | CE72: =BB72 -> 6 | CF72: =BF72 -> 93 | CG72: =BG72 -> 124
B73: A/R | BB73: 734 | BC73: 635 | BD73: 641 | BE73: 699 | BF73: 735 | BG73: 699 | BH73: 701 | BI73: 729 | BJ73: 854 | BK73: 738 | CE73: =BB73 -> 734 | CF73: =BF73 -> 735 | CG73: =BG73 -> 699
B74: Inventory | BB74: 587 | BC74: 584 | BD74: 561 | BE74: 574 | BF74: 547 | BG74: 537 | BH74: 575 | BI74: 590 | BJ74: 564 | BK74: 611 | CE74: =BB74 -> 587 | CF74: =BF74 -> 547 | CG74: =BG74 -> 537 | CI74: Invested Capital | CL74: Avg. (2024-2025) | CN74: Projected ROIC: | CP74: ROIC | CQ74: 0.1475
B75: Other ST Assets | BB75: 234 | BC75: 250 | BD75: 263 | BE75: 161 | BF75: 244 | BG75: 200 | BH75: 210 | BI75: 199 | BJ75: 238 | BK75: 234 | CE75: =BB75 -> 234 | CF75: =BF75 -> 244 | CG75: =BG75 -> 200 | CI75: 2024 | CJ75: 2025 | CL75: 2024-2025 | CN75: 2025 | CP75: Terminal | CQ75: 0.015
B76: PP&E | BB76: 1007 | BC76: 964 | BD76: 859 | BE76: 832 | BF76: 815 | BG76: 782 | BH76: 764 | BI76: 748 | BJ76: 759 | BK76: 755 | CE76: =BB76 -> 1007 | CF76: =BF76 -> 815 | CG76: =BG76 -> 782 | CI76: =SUM(CF71:CF74)-CF87+CF77+CF81+CF80 -> 3282 | CJ76: =SUM(CG71:CG74)-CG87+CG77+CG81+CG80 -> 3270 | CL76: =AVERAGE(CI76:CJ76) -> 3276 | CN76: =AVERAGE(CH58)*(1-CH69) -> #DIV/0! | CP76: RFR (10-year yield) | CQ76: =CL87 -> 0.0424
B77: LT Operating Lease Assets | BB77: 544 | BC77: 550 | BD77: 460 | BE77: 453 | BF77: 419 | BG77: 410 | BH77: 397 | BI77: 382 | BJ77: 370 | BK77: 371 | CE77: =BB77 -> 544 | CF77: =BF77 -> 419 | CG77: =BG77 -> 410 | CN77: =CN76/CL76 -> #DIV/0! | CP77: ERP (Avg. market return - (less) RFR) | CQ77: =8.69%-CQ76 -> 0.0445
B78: Goodwill | BB78: 2545 | BC78: 2545 | BD78: 1079 | BE78: 1113 | BF78: 1113 | BG78: 1113 | BH78: 1113 | BI78: 1113 | BJ78: 1113 | BK78: 1284 | CE78: =BB78 -> 2545 | CF78: =BF78 -> 1113 | CG78: =BG78 -> 1113
B79: Intangible Assets | BB79: 2993 | BC79: 2940 | BD79: 278 | BE79: 305 | BF79: 295 | BG79: 278 | BH79: 238 | BI79: 225 | BJ79: 210 | BK79: 430 | CE79: =BB79 -> 2993 | CF79: =BF79 -> 295 | CG79: =BG79 -> 278
B80: LT Deferred Taxes | BB80: 56 | BC80: 62 | BD80: 632 | BE80: 617 | BF80: 567 | BG80: 553 | BH80: 534 | BI80: 490 | BJ80: 454 | BK80: 458 | CE80: =BB80 -> 56 | CF80: =BF80 -> 567 | CG80: =BG80 -> 553 | CI80: Capital Structure | CP80: Equity β (1-year avg.) | CQ80: ='Notes | Quant Analysis'!S206 -> 1.0053004
B81: Other LT Assets | BB81: 357 | BC81: 396 | BD81: 314 | BE81: 321 | BF81: 348 | BG81: 373 | BH81: 400 | BI81: 423 | BJ81: 449 | BK81: 523 | CE81: =BB81 -> 357 | CF81: =BF81 -> 348 | CG81: =BG81 -> 373 | CI81: Mkt Cap | CL81: =Main!C5 -> 28547.284 | CP81: Discount (Cost of Equity) | CQ81: =+CQ76+(CQ77*CQ80) -> 0.087135869
B82: Ttl Assets | BB82: =SUM(BB71:BB81) -> 10111 | BC82: =SUM(BC70:BC81) -> 10040 | BD82: =SUM(BD71:BD81) -> 6081 | BE82: =SUM(BE71:BE81) -> 6014 | BF82: =SUM(BF71:BF81) -> 6303 | BG82: =SUM(BG71:BG81) -> 6182 | BH82: =SUM(BH71:BH81) -> 6087 | BI82: =SUM(BI71:BI81) -> 6177 | BJ82: =SUM(BJ71:BJ81) -> 6644 | BK82: =SUM(BK71:BK81) -> 6559 | CE82: =BB82 -> 10111 | CF82: =BF82 -> 6303 | CG82: =BG82 -> 6182 | CI82: Debt to Ttl Mkt Cap | CL82: =Main!C7/(Main!C7+CL81) -> 0.065135627
CI83: Mkt Equity to Ttl Mkt Cap | CL83: =CL81/(CL81+Main!C7) -> 0.93486437 | CP83: NPV | CQ83: =NPV(CQ81,CH60:EE60) -> 0
B84: A/P | BB84: 245 | BC84: 201 | BD84: 199 | BE84: 191 | BF84: 221 | BG84: 207 | BH84: 200 | BI84: 218 | BJ84: 240 | BK84: 218 | CE84: =BB84 -> 245 | CF84: =BF84 -> 221 | CG84: =BG84 -> 207 | CI84: LT Debt / Equity | CL84: =#REF!/#REF! -> #REF! | CP84: SC | CQ84: =Main!C4 -> 151.3
B85: ST Accrued Liabilities | BB85: 1325 | BC85: 1273 | BD85: 1265 | BE85: 784 | BF85: 827 | BG85: 734 | BH85: 762 | BI85: 746 | BJ85: 846 | BK85: 849 | CE85: =BB85 -> 1325 | CF85: =BF85 -> 827 | CG85: =BG85 -> 734 | CP85: FV | CQ85: =CQ83/CQ84 -> 0
B86: ST Debt | BB86: 0 | BC86: 0 | BD86: 744 | BE86: 0 | BF86: 499 | BG86: 499 | BH86: 499 | BI86: 998 | BJ86: 499 | BK86: 499 | CE86: =BB86 -> 0 | CF86: =BF86 -> 499 | CG86: =BG86 -> 499 | CI86: Cost of Equity | CP86: CP | CQ86: =Main!C3 -> 188.68
B87: LT Operating Lease Liabilities | BB87: 687 | BC87: 700 | BD87: 616 | BE87: 613 | BF87: 554 | BG87: 539 | BH87: 528 | BI87: 506 | BJ87: 486 | BK87: 475 | CE87: =BB87 -> 687 | CF87: =BF87 -> 554 | CG87: =BG87 -> 539 | CI87: RFR (10-year yield) | CL87: 0.0424 | CP87: Change Δ | CQ87: =CQ85/CQ86-1 -> -1 | CR87: =IF(CQ87>0,"Upside","Downside") -> Downside
B88: LT Debt | BB88: 1489 | BC88: 1490 | BD88: 1490 | BE88: 1988 | BF88: 1490 | BG88: 1491 | BH88: 1492 | BI88: 994 | BJ88: 1490 | BK88: 1490 | CE88: =BB88 -> 1489 | CF88: =BF88 -> 1490 | CG88: =BG88 -> 1491 | CI88: Equity β (1-year avg.) | CL88: ='Notes | Quant Analysis'!S206 -> 1.0053004 | CP88: {=_xlfn.IFS(CQ87>=25%,"Strong Buy",CQ87>=10.00001%,"Buy",AND(CQ87<=10%,CQ87>=-4.9999%),"Hold",AND(CQ87<=-5%,CQ87>=-14.999999%),"Sell",CQ87<=-15%,"Strong Sell")} -> Strong Sell
B89: Other LT Liabilities | BB89: 620 | BC89: 642 | BD89: 331 | BE89: 313 | BF89: 339 | BG89: 344 | BH89: 348 | BI89: 334 | BJ89: 360 | BK89: 352 | CE89: =BB89 -> 620 | CF89: =BF89 -> 339 | CG89: =BG89 -> 344 | CI89: Market Return(1-year avg.) | CL89: 0.1433
B90: Ttl Liabilities | BB90: =SUM(BB84:BB89) -> 4366 | BC90: =SUM(BC84:BC89) -> 4306 | BD90: =SUM(BD84:BD89) -> 4645 | BE90: =SUM(BE84:BE89) -> 3889 | BF90: =SUM(BF84:BF89) -> 3930 | BG90: =SUM(BG84:BG89) -> 3814 | BH90: =SUM(BH84:BH89) -> 3829 | BI90: =SUM(BI84:BI89) -> 3796 | ... BK90: =SUM(BK84:BK89) -> 3883 | CE90: =BB90 -> 4366 | CF90: =BF90 -> 3930 | CG90: =BG90 -> 3814 | CI90: Cost of Equity | CL90: =(CL87+CL88)*(CL89-CL87) -> 0.10571297
B91: Ttl SE | BB91: 5745 | BC91: 5734 | BD91: 6081 | BE91: 2125 | BF91: 2373 | BG91: 2368 | BH91: 2258 | BI91: 2381 | BJ91: 2723 | BK91: 2676 | CE91: =BB91 -> 5745 | CF91: =BF91 -> 2373 | CG91: =BG91 -> 2368
B92: Ttl L + SE | BB92: =BB90+BB91 -> 10111 | BC92: =BC90+BC91 -> 10040 | BD92: =BD90+BD91 -> 10726 | BE92: =BE90+BE91 -> 6014 | BF92: =BF90+BF91 -> 6303 | BG92: =BG90+BG91 -> 6182 | BH92: =BH90+BH91 -> 6087 | BI92: =BI90+BI91 -> 6177 | ... BK92: =BK90+BK91 -> 6559 | CE92: =BB92 -> 10111 | CF92: =BF92 -> 6303 | CG92: =BG92 -> 6182 | CI92: Cost of Debt
B94: Current Ratio | BB94: =SUM(BB71:BB75)/SUM(BB84:BB86) -> 1.6617834 | BC94: =SUM(BC71:BC75)/SUM(BC84:BC86) -> 1.7523745 | BD94: =SUM(BD71:BD75)/SUM(BD84:BD86) -> 1.1136775 | BE94: =SUM(BE71:BE75)/SUM(BE84:BE86) -> 2.4338462 | BF94: =SUM(BF71:BF75)/SUM(BF84:BF86) -> 1.7750485 | BG94: =SUM(BG71:BG75)/SUM(BG84:BG86) -> 1.85625 | BH94: =SUM(BH71:BH75)/SUM(BH84:BH86) -> 1.807666 | BI94: =SUM(BI71:BI75)/SUM(BI84:BI86) -> 1.4250765 | ... BK94: =SUM(BK71:BK75)/SUM(BK84:BK86) -> 1.7484036 | CE94: =SUM(CE71:CE75)/SUM(CE84:CE86) -> 1.6617834 | CF94: =SUM(CF71:CF75)/SUM(CF84:CF86) -> 1.7750485 | CG94: =SUM(CG71:CG75)/SUM(CG84:CG86) -> 1.85625
B95: Quick Ratio | BB95: =(SUM(BB71:BB75)-BB74)/SUM(BB84:BB86) -> 1.2878981 | BC95: =(SUM(BC71:BC75)-BC74)/SUM(BC84:BC86) -> 1.3561737 | BD95: =(SUM(BD71:BD75)-BD74)/SUM(BD84:BD86) -> 0.85960145 | BE95: =(SUM(BE71:BE75)-BE74)/SUM(BE84:BE86) -> 1.8451282 | BF95: =(SUM(BF71:BF75)-BF74)/SUM(BF84:BF86) -> 1.4214609 | BG95: =(SUM(BG71:BG75)-BG74)/SUM(BG84:BG86) -> 1.4833333 | BH95: =(SUM(BH71:BH75)-BH74)/SUM(BH84:BH86) -> 1.4140999 | BI95: =(SUM(BI71:BI75)-BI74)/SUM(BI84:BI86) -> 1.1243629 | ... BK95: =(SUM(BK71:BK75)-BK74)/SUM(BK84:BK86) -> 1.3582375 | CE95: =(SUM(CE71:CE75)-CE74)/SUM(CE84:CE86) -> 1.2878981 | CF95: =(SUM(CF71:CF75)-CF74)/SUM(CF84:CF86) -> 1.4214609 | CG95: =(SUM(CG71:CG75)-CG74)/SUM(CG84:CG86) -> 1.4833333
B96: Cash Ratio | BB96: =(BB72+BB71)/SUM(BB84:BB86) -> 0.67133758 | BC96: =(BC72+BC71)/SUM(BC84:BC86) -> 0.75576662 | BD96: =(BD72+BD71)/SUM(BD84:BD86) -> 0.45018116 | BE96: =(BE72+BE71)/SUM(BE84:BE86) -> 0.96307692 | BF96: =(BF72+BF71)/SUM(BF84:BF86) -> 0.78862314 | BG96: =(BG72+BG71)/SUM(BG84:BG86) -> 0.85902778 | BH96: =(BH72+BH71)/SUM(BH84:BH86) -> 0.79055441 | BI96: =(BI72+BI71)/SUM(BI84:BI86) -> 0.65137615 | ... BK96: =(BK72+BK71)/SUM(BK84:BK86) -> 0.73754789 | CE96: =(CE72+CE71)/SUM(CE84:CE86) -> 0.67133758 | CF96: =(CF72+CF71)/SUM(CF84:CF86) -> 0.78862314 | CG96: =(CG72+CG71)/SUM(CG84:CG86) -> 0.85902778
B97: Fixed Asset Turnover Ratio | BB97: =BB49/SUM(BB77:BB78) -> 0.36322434 | BC97: =BC49/SUM(BC77:BC78) -> 0.34765751 | BD97: =BD49/SUM(BD77:BD78) -> 0.72254711 | BE97: =BE49/SUM(BE77:BE78) -> 0.68965517 | BF97: =BF49/SUM(BF77:BF78) -> 0.72062663 | BG97: =BG49/SUM(BG77:BG78) -> 0.68351937 | BH97: =BH49/SUM(BH77:BH78) -> 0.7013245 | BI97: =BI49/SUM(BI77:BI78) -> 0.72508361 | ... BK97: =BK49/SUM(BK77:BK78) -> 0.6592145 | CE97: =CE49/SUM(CE77:CE78) -> 1.458077 | CF97: =CF49/SUM(CF77:CF78) -> 2.8537859 | CG97: =CG49/SUM(CG77:CG78) -> 2.8516087
B98: Ttl Asset Turnover Ratio | BB98: =BB49/BB82 -> 0.11096825 | BC98: =BC49/BC82 -> 0.10717131 | BD98: =BD49/BD82 -> 0.18286466 | BE98: =BE49/BE82 -> 0.17958098 | BF98: =BF49/BF82 -> 0.17515469 | BG98: =BG49/BG82 -> 0.16839211 | BH98: =BH49/BH82 -> 0.17397733 | BI98: =BI49/BI82 -> 0.17548972 | ... BK98: =BK49/BK82 -> 0.16633633 | CE98: =CE49/CE82 -> 0.44545544 | CF98: =CF49/CF82 -> 0.69363795 | CG98: =CG49/CG82 -> 0.70252346
B99: Inventory Turnover Ratio | BB99: {=BB50/AVERAGE(AY74:BB74)} -> 0.7649063 | BC99: {=BC50/AVERAGE(AZ74:BC74)} -> 0.69854825 | BD99: {=BD50/AVERAGE(BA74:BD74)} -> 0.67725173 | BE99: {=BE50/AVERAGE(BB74:BE74)} -> 0.5810928 | BF99: {=BF50/AVERAGE(BC74:BF74)} -> 0.66372462 | BG99: {=BG50/AVERAGE(BD74:BG74)} -> 0.64533574 | BH99: {=BH50/AVERAGE(BE74:BH74)} -> 0.65203762 | BI99: {=BI50/AVERAGE(BF74:BI74)} -> 0.62427746 | ... BK99: {=BK50/AVERAGE(BH74:BK74)} -> 0.63247863 | CE99: {=CE50/AVERAGE(CB74:CE74)} -> 2.9982964 | CF99: {=CF50/AVERAGE(CC74:CF74)} -> 2.664903 | CG99: {=CG50/AVERAGE(CD74:CG74)} -> 2.6445242
B100: Return on Assets | BB100: =BB60/BB82 -> -0.018692513 | BC100: =BC60/BC82 -> -0.012549801 | BD100: =BD60/BD82 -> -0.016773557 | BE100: =BE60/BE82 -> 0.036082474 | BF100: =BF60/BF82 -> 0.058226241 | BG100: =BG60/BG82 -> 0.021190553 | BH100: =BH60/BH82 -> 0.038606867 | BI100: =BI60/BI82 -> 0.024283633 | ... BK100: =BK60/BK82 -> 0.020429944 | CE100: =CE60/CE82 -> -0.031055286 | CF100: =CF60/CF82 -> 0.056481041 | CG100: =CG60/CG82 -> 0.13749596
B101: Return on Equity | BB101: =BB60/BB91 -> -0.032898172 | BC101: =BC60/BC91 -> -0.021974189 | BD101: =BD60/BD91 -> -0.016773557 | BE101: =BE60/BE91 -> 0.10211765 | BF101: =BF60/BF91 -> 0.15465655 | BG101: =BG60/BG91 -> 0.055320946 | BH101: =BH60/BH91 -> 0.1040744 | BI101: =BI60/BI91 -> 0.06299874 | ... BK101: =BK60/BK91 -> 0.050074738 | CE101: =CE60/CE91 -> -0.054656223 | CF101: =CF60/CF91 -> 0.15002107 | CG101: =CG60/CG91 -> 0.3589527
B103: Net Income | C103: =C60 -> 26.929 | D103: =D60 -> 37.932 | E103: =E60 -> 24.072 | F103: =F60 -> 48.576 | G103: =G60 -> 40.793 | H103: =H60 -> 33.679 | I103: =I60 -> 52.96 | J103: =J60 -> 79.582 | ... BK103: =BK60 -> 134 | BS103: =SUM(C103:F103) -> 137.509 | BT103: =SUM(G103:J103) -> 207.014 | BU103: =SUM(K103:N103) -> 245.305 | BV103: =SUM(O103:R103) -> 282.012 | BW103: =SUM(S103:V103) -> 477 | BX103: =SUM(W103:Z103) -> 419 | BY103: =SUM(AA103:AD103) -> 678 | BZ103: =SUM(AE103:AH103) -> 782 | CA103: =SUM(AI103:AL103) -> 990 | CB103: =SUM(AM103:AP103) -> 656 | CC103: =SUM(AQ103:AT103) -> 762 | CD103: =SUM(AU103:AX103) -> 129 | CE103: =SUM(AY103:BB103) -> -314 | CF103: =SUM(BC103:BF103) -> 356 | CG103: =SUM(BG103:BJ103) -> 850
B104: CFFO | C104: 88.578 | D104: 71.22 | E104: 90.042 | F104: 108.3 | G104: 65.44 | H104: 96.329 | I104: 51.228 | J104: 78.876 | K104: 87.84 | L104: 88.606 | M104: 83.136 | N104: 126.839 | O104: 37.087 | P104: 178.03 | Q104: 145.605 | R104: 140.549 | S104: 66.779 | T104: 171.445 | U104: 180.994 | V104: 366.782 | W104: 99 | X104: 242 | Y104: 176 | Z104: 262 | AA104: 168 | AB104: 178 | AC104: 235 | AD104: 294 | AE104: 255 | AF104: 295 | AG104: 292 | AH104: 300 | AI104: 198 | AJ104: 143 | AK104: 267 | AL104: 443 | AM104: 281 | AN104: 240 | AO104: 153 | AP104: 406 | AQ104: 282 | AR104: 253 | AS104: -272 | AT104: 282 | AU104: 172 | AV104: 125 | AW104: -52 | AX104: 147 | AY104: 10 | AZ104: 105 | BA104: 139 | BB104: 224 | BC104: 77 | BD104: 80 | BE104: 316 | BF104: 364 | BG104: 240 | BH104: 234 | BI104: 284 | BJ104: 321 | BK104: 289 | BS104: =SUM(C104:F104) -> 358.14 | BT104: =SUM(G104:J104) -> 291.873 | BU104: =SUM(K104:N104) -> 386.421 | BV104: =SUM(O104:R104) -> 501.271 | BW104: =SUM(S104:V104) -> 786 | BX104: =SUM(W104:Z104) -> 779 | BY104: =SUM(AA104:AD104) -> 875 | BZ104: =SUM(AE104:AH104) -> 1142 | CA104: =SUM(AI104:AL104) -> 1051 | CB104: =SUM(AM104:AP104) -> 1080 | CC104: =SUM(AQ104:AT104) -> 545 | CD104: =SUM(AU104:AX104) -> 392 | CE104: =SUM(AY104:BB104) -> 478 | CF104: =SUM(BC104:BF104) -> 837 | CG104: =SUM(BG104:BJ104) -> 1079
B105: CapEx, net | C105: -12.3 | D105: -16.203 | E105: -22.183 | F105: -27.114 | G105: -13.084 | H105: -20.946 | I105: -17.65 | J105: -17.101 | K105: -21.441 | L105: -11.534 | M105: -18.93 | N105: -27.31 | O105: -19.012 | P105: -23.324 | Q105: -28.828 | R105: -34.832 | S105: -36.551 | T105: -41.351 | U105: -29.459 | V105: -35.639 | W105: -53 | X105: -68 | Y105: -57 | Z105: -82 | AA105: -83 | AB105: -69 | AC105: -82 | AD105: -76 | AE105: -90 | AF105: -77 | AG105: -64 | AH105: -65 | AI105: -56 | AJ105: -47 | AK105: -49 | AL105: -57 | AM105: -40 | AN105: -39 | AO105: -48 | AP105: -62 | AQ105: -42 | AR105: -44 | AS105: -52 | AT105: -70 | AU105: -61 | AV105: -71 | AW105: -66 | AX105: -88 | AY105: -52 | AZ105: -47 | BA105: -45 | BB105: -51 | BC105: -36 | BD105: -31 | BE105: -32 | BF105: -29 | BG105: -32 | BH105: -30 | BI105: -31 | BJ105: -55 | BK105: -38 | BS105: =SUM(C105:F105) -> -77.8 | BT105: =SUM(G105:J105) -> -68.781 | BU105: =SUM(K105:N105) -> -79.215 | BV105: =SUM(O105:R105) -> -105.996 | BW105: =SUM(S105:V105) -> -143 | BX105: =SUM(W105:Z105) -> -260 | BY105: =SUM(AA105:AD105) -> -310 | BZ105: =SUM(AE105:AH105) -> -296 | CA105: =SUM(AI105:AL105) -> -209 | CB105: =SUM(AM105:AP105) -> -189 | CC105: =SUM(AQ105:AT105) -> -208 | CD105: =SUM(AU105:AX105) -> -286 | CE105: =SUM(AY105:BB105) -> -195 | CF105: =SUM(BC105:BF105) -> -128 | CG105: =SUM(BG105:BJ105) -> -148
B106: FCF | C106: =C104+C105 -> 76.278 | D106: =D104+D105 -> 55.017 | E106: =E104+E105 -> 67.859 | F106: =F104+F105 -> 81.186 | G106: =G104+G105 -> 52.356 | H106: =H104+H105 -> 75.383 | I106: =I104+I105 -> 33.578 | J106: =J104+J105 -> 61.775 | ... BK106: =BK104+BK105 -> 251 | BS106: =SUM(C106:F106) -> 280.34 | BT106: =SUM(G106:J106) -> 223.092 | BU106: =SUM(K106:N106) -> 307.206 | BV106: =SUM(O106:R106) -> 395.275 | BW106: =SUM(S106:V106) -> 643 | BX106: =SUM(W106:Z106) -> 519 | BY106: =SUM(AA106:AD106) -> 565 | BZ106: =SUM(AE106:AH106) -> 846 | CA106: =SUM(AI106:AL106) -> 842 | CB106: =SUM(AM106:AP106) -> 891 | CC106: =SUM(AQ106:AT106) -> 337 | CD106: =SUM(AU106:AX106) -> 106 | CE106: =SUM(AY106:BB106) -> 283 | CF106: =SUM(BC106:BF106) -> 709 | CG106: =SUM(BG106:BJ106) -> 931
B107: SC | C107: =C61 -> 0 | D107: =D61 -> 0 | E107: =E61 -> 0 | F107: =F61 -> 0 | G107: =G61 -> 0 | H107: =H61 -> 0 | I107: =I61 -> 0 | J107: =J61 -> 0 | ... BK107: =BK61 -> 153 | BS107: =BS61 -> #DIV/0! | BT107: =BT61 -> #DIV/0! | BU107: =BU61 -> #DIV/0! | BV107: =BV61 -> #DIV/0! | BW107: =BW61 -> #DIV/0! | BX107: =BX61 -> #DIV/0! | BY107: =BY61 -> #DIV/0! | BZ107: =BZ61 -> #DIV/0! | ... CG107: =CG61 -> 156
B108: FCF per Share | C108: =C106/C107 -> #DIV/0! | D108: =D106/D107 -> #DIV/0! | E108: =E106/E107 -> #DIV/0! | F108: =F106/F107 -> #DIV/0! | G108: =G106/G107 -> #DIV/0! | H108: =H106/H107 -> #DIV/0! | I108: =I106/I107 -> #DIV/0! | J108: =J106/J107 -> #DIV/0! | ... BK108: =BK106/BK107 -> 1.6405229 | BS108: =SUM(C108:F108) -> #DIV/0! | BT108: =SUM(G108:J108) -> #DIV/0! | BU108: =SUM(K108:N108) -> #DIV/0! | BV108: =SUM(O108:R108) -> #DIV/0! | BW108: =SUM(S108:V108) -> #DIV/0! | BX108: =SUM(W108:Z108) -> #DIV/0! | BY108: =SUM(AA108:AD108) -> #DIV/0! | BZ108: =SUM(AE108:AH108) -> #DIV/0! | CA108: =SUM(AI108:AL108) -> #DIV/0! | CB108: =SUM(AM108:AP108) -> #DIV/0! | CC108: =SUM(AQ108:AT108) -> 2.3570969 | CD108: =SUM(AU108:AX108) -> 0.67515924 | CE108: =SUM(AY108:BB108) -> 1.7911392 | CF108: =SUM(BC108:BF108) -> 4.4591195 | CG108: =SUM(BG108:BJ108) -> 5.977263
B110: CFFO Margin | C110: =C104/C49 -> 0.31353379 | D110: =D104/D49 -> 0.24776483 | E110: =E104/E49 -> 0.38234557 | F110: =F104/F49 -> 0.43307701 | G110: =G104/G49 -> 0.23990908 | H110: =H104/H49 -> 0.34328794 | I110: =I104/I49 -> 0.17919783 | J110: =J104/J49 -> 0.25504341 | ... BK110: =BK104/BK49 -> 0.26489459 | BS110: =BS104/BS49 -> 0.33929713 | BT110: =BT104/BT49 -> 0.25413055 | BU110: =BU104/BU49 -> 0.2719019 | BV110: =BV104/BV49 -> 0.26930392 | BW110: =BW104/BW49 -> 0.35405405 | BX110: =BX104/BX49 -> 0.32485405 | BY110: =BY104/BY49 -> 0.31795058 | BZ110: =BZ104/BZ49 -> 0.34263426 | ... CG110: =CG104/CG49 -> 0.24844577
B111: FCF Margin | C111: =C106/C49 -> 0.26999628 | D111: =D106/D49 -> 0.19139676 | E111: =E106/E49 -> 0.28814984 | F111: =F106/F49 -> 0.3246518 | G111: =G106/G49 -> 0.19194193 | H111: =H106/H49 -> 0.26864262 | I111: =I106/I49 -> 0.11745734 | J111: =J106/J49 -> 0.19974779 | ... BK111: =BK106/BK49 -> 0.23006416 | BS111: =BS106/BS49 -> 0.26559044 | BT111: =BT106/BT49 -> 0.1942437 | BU111: =BU106/BU49 -> 0.21616293 | BV111: =BV106/BV49 -> 0.2123584 | BW111: =BW106/BW49 -> 0.28963964 | BX111: =BX106/BX49 -> 0.21643036 | BY111: =BY106/BY49 -> 0.20530523 | BZ111: =BZ106/BZ49 -> 0.25382538 | ... CG111: =CG106/CG49 -> 0.21436795
B112: CapEx as % of Revenue | C112: =C105/C49 -> -0.043537511 | D112: =D105/D49 -> -0.056368064 | E112: =E105/E49 -> -0.094195729 | F112: =F105/F49 -> -0.10842521 | G112: =G105/G49 -> -0.047967152 | H112: =H105/H49 -> -0.074645322 | I112: =I105/I49 -> -0.061740487 | J112: =J105/J49 -> -0.05529562 | ... BK112: =BK105/BK49 -> -0.034830431 | BS112: =BS105/BS49 -> -0.073706698 | BT112: =BT105/BT49 -> -0.059886845 | BU112: =BU105/BU49 -> -0.055738971 | BV112: =BV105/BV49 -> -0.05694552 | BW112: =BW105/BW49 -> -0.064414414 | BX112: =BX105/BX49 -> -0.10842369 | BY112: =BY105/BY49 -> -0.11264535 | BZ112: =BZ105/BZ49 -> -0.088808881 | ... CG112: =CG105/CG49 -> -0.034077826

Sheet Notes | Quant Analysis
CI1: 0
P2: Employee Scope: | AL2: General Notes/Observations (Updated Q1'26)
Q32: Notes: | R32: [X]
R33: [Y]
R34: [Z]
AL35: Financial Stmts. Notes/Observations (Updated Q1'26)
P36: Institutional Ownership Snapshot Q4'25 | AL36: Revenues:
AL37: [Godel Snapshot of projected sales]
Q65: Notes: | R65: [X]
R66: [Y]
R67: [Z]
P69: Revenue Breakdown by Segment (Build graph for this section if applicable…. See example below) | AL69: Earnings Scope:
AL70: [Godel Snapshot of projected earnings/EPS + CFFO]
Q101: Notes: | R101: [X]
R102: [Y]
R103: [Z]
P105: Q/q Total Revenues, Net Income, FCF | AL105: Balance Sheet Scope:
AL106: [Godel Snapshot of projected balances (assets, liabilities, equity)]
Q134: Notes: | R134: [X]
R135: [Y]
R136: [Z]
P138: Y/y Total Revenues, Net Income, FCF | AL138: [Equity Preformance Compared to Peers]
AL139: Use Godel CMS command
Q167: Notes: | R167: [X]
R168: [Y]
R169: [Z]
A184: VOO Historical Returns
A185: 1506 Trading Days? (From: 7/4/2020 - 7/4/2026) | I185: 1506 Trading Days? (From: 7/4/2020 - 7/4/2026)
A186: Close | B186: High | C186: Low | D186: Open | E186: Volume | F186: UTC Date | G186: Change | I186: Close | J186: High | K186: Low | L186: Open | M186: Volume | N186: UTC Date | O186: Change
A187: 684.84 | B187: 690.5 | C187: 680.215 | D187: 686.98 | E187: 6980816.8 | F187: Thu, 02 Jul 2026 00:00:00 GMT | G187: =A187/D187-1 -> -0.0031150834 | I187: 188.68 | J187: 189.46 | K187: 184.4 | L187: 186.755 | M187: 2941433.1 | N187: Thu, 02 Jul 2026 00:00:00 GMT | O187: =I187/L187-1 -> 0.010307622
A188: 685.46 | B188: 688.83 | C188: 682.3 | D188: 684.73 | E188: 8627875 | F188: Wed, 01 Jul 2026 00:00:00 GMT | G188: =A188/D188-1 -> 0.0010661137 | I188: 183.89 | J188: 184.9 | K188: 175.6 | L188: 175.83 | M188: 2125399.7 | N188: Wed, 01 Jul 2026 00:00:00 GMT | O188: =I188/L188-1 -> 0.045839732
A189: 686.81 | B189: 687.529 | C189: 680.99 | D189: 681.32 | E189: 9853712.9 | F189: Tue, 30 Jun 2026 00:00:00 GMT | G189: =A189/D189-1 -> 0.0080578876 | I189: 175.83 | J189: 181 | K189: 174.78 | L189: 180.97 | M189: 1753585.7 | N189: Tue, 30 Jun 2026 00:00:00 GMT | O189: =I189/L189-1 -> -0.028402498
A190: 681.01 | B190: 681.565 | C190: 672.93 | D190: 677.01 | E190: 5649228.8 | F190: Mon, 29 Jun 2026 00:00:00 GMT | G190: =A190/D190-1 -> 0.0059083322 | I190: 181.1 | J190: 181.28 | K190: 175.13 | L190: 177.39 | M190: 1506842.1 | N190: Mon, 29 Jun 2026 00:00:00 GMT | O190: =I190/L190-1 -> 0.020914369
A191: 670.26 | B191: 676.955 | C191: 668.1 | D191: 669.96 | E191: 5935648.6 | F191: Fri, 26 Jun 2026 00:00:00 GMT | G191: =A191/D191-1 -> 0.00044778793 | I191: 176.55 | J191: 179.9255 | K191: 173.235 | L191: 176.065 | M191: 2183494.9 | N191: Fri, 26 Jun 2026 00:00:00 GMT | O191: =I191/L191-1 -> 0.0027546645
A192: 673.7478 | B192: 679.56087 | C192: 670.62689 | D192: 679.16203 | E192: 23355606 | F192: Thu, 25 Jun 2026 00:00:00 GMT | G192: =A192/D192-1 -> -0.0079719294 | I192: 177.65 | J192: 182.84 | K192: 176.54 | L192: 178.24 | M192: 2910070.7 | N192: Thu, 25 Jun 2026 00:00:00 GMT | O192: =I192/L192-1 -> -0.0033101436
A193: 673.72786 | B193: 680.08933 | C193: 671.72369 | D193: 675.71208 | E193: 9593615.8 | F193: Wed, 24 Jun 2026 00:00:00 GMT | G193: =A193/D193-1 -> -0.0029364892 | I193: 175.09 | J193: 177.76 | K193: 166.04 | L193: 166.12 | M193: 2643618.1 | N193: Wed, 24 Jun 2026 00:00:00 GMT | O193: =I193/L193-1 -> 0.053997111
A194: 674.37597 | B194: 679.74912 | C194: 673.0598 | D194: 674.39093 | E194: 17263981 | F194: Tue, 23 Jun 2026 00:00:00 GMT | G194: =A194/D194-1 -> -2.2177703e-05 | I194: 164.93 | J194: 166.63 | K194: 159.98 | L194: 160.6 | M194: 2055863 | N194: Tue, 23 Jun 2026 00:00:00 GMT | O194: =I194/L194-1 -> 0.026961395
A195: 684.10763 | B195: 689.49195 | C195: 683.01082 | D195: 687.16871 | E195: 13365185 | F195: Mon, 22 Jun 2026 00:00:00 GMT | G195: =A195/D195-1 -> -0.0044546338 | I195: 161.38 | J195: 163.79 | K195: 158.91 | L195: 161.83 | M195: 1790688 | N195: Mon, 22 Jun 2026 00:00:00 GMT | O195: =I195/L195-1 -> -0.0027806958
A196: 686.11179 | B196: 687.69717 | C196: 683.70879 | D196: 687.29834 | E196: 17768872 | F196: Thu, 18 Jun 2026 00:00:00 GMT | G196: =A196/D196-1 -> -0.0017263891 | I196: 161.93 | J196: 162.78 | K196: 159.51 | L196: 161.31 | M196: 3079550.2 | N196: Thu, 18 Jun 2026 00:00:00 GMT | O196: =I196/L196-1 -> 0.0038435311
A197: 679.43125 | B197: 689.52186 | C197: 677.66639 | D197: 688.7541 | E197: 15004527 | F197: Wed, 17 Jun 2026 00:00:00 GMT | G197: =A197/D197-1 -> -0.013535816 | I197: 159.09 | J197: 165.4 | K197: 157.63 | L197: 163.24 | M197: 1591874.5 | N197: Wed, 17 Jun 2026 00:00:00 GMT | O197: =I197/L197-1 -> -0.025422691
A198: 687.74703 | B198: 692.55303 | C198: 687.43793 | D198: 691.81518 | E198: 13322314 | F198: Tue, 16 Jun 2026 00:00:00 GMT | G198: =A198/D198-1 -> -0.005880403 | I198: 164.28 | J198: 167.42 | K198: 162.7453 | L198: 166.89 | M198: 1260626 | N198: Tue, 16 Jun 2026 00:00:00 GMT | O198: =I198/L198-1 -> -0.015639044
A199: 691.81518 | B199: 693.72961 | C199: 689.25264 | D199: 689.29253 | E199: 14057973 | F199: Mon, 15 Jun 2026 00:00:00 GMT | G199: =A199/D199-1 -> 0.0036597714 | I199: 166.89 | J199: 166.97 | K199: 160.78 | L199: 161.61 | M199: 2094821.1 | N199: Mon, 15 Jun 2026 00:00:00 GMT | O199: =I199/L199-1 -> 0.032671246
A200: 679.96968 | B200: 682.45115 | C200: 673.84751 | D200: 679.09722 | E200: 6314635.8 | F200: Fri, 12 Jun 2026 00:00:00 GMT | G200: =A200/D200-1 -> 0.0012847337 | I200: 160.97 | J200: 167.9978 | K200: 159.34 | L200: 167.845 | M200: 1463812.4 | N200: Fri, 12 Jun 2026 00:00:00 GMT | O200: =I200/L200-1 -> -0.04096041 | R200: Min | S200: =MIN(O187:O1692) -> -0.11996466
A201: 676.26048 | B201: 678.40424 | C201: 664.066 | D201: 668.15409 | E201: 19926769 | F201: Thu, 11 Jun 2026 00:00:00 GMT | G201: =A201/D201-1 -> 0.012132518 | I201: 166.21 | J201: 166.21 | K201: 160.65 | L201: 162.47 | M201: 1475192.1 | N201: Thu, 11 Jun 2026 00:00:00 GMT | O201: =I201/L201-1 -> 0.023019634 | R201: Max | S201: =MAX(O187:O1692) -> 0.1555514
A202: 665.11295 | B202: 676.90361 | C202: 664.94344 | D202: 672.35685 | E202: 16356103 | F202: Wed, 10 Jun 2026 00:00:00 GMT | G202: =A202/D202-1 -> -0.010773896 | I202: 162.47 | J202: 166.97 | K202: 162.09 | L202: 166.16 | M202: 2740734 | N202: Wed, 10 Jun 2026 00:00:00 GMT | O202: =I202/L202-1 -> -0.022207511 | R202: Mean μ | S202: =AVERAGE(O187:O1692) -> 0.0003824088
A203: 675.73202 | B203: 684.76571 | C203: 662.39098 | D203: 681.72457 | E203: 13824282 | F203: Tue, 09 Jun 2026 00:00:00 GMT | G203: =A203/D203-1 -> -0.0087902766 | I203: 160.03 | J203: 161.12 | K203: 155.55 | L203: 158.755 | M203: 1426618.8 | N203: Tue, 09 Jun 2026 00:00:00 GMT | O203: =I203/L203-1 -> 0.0080312431 | R203: Median | S203: =MEDIAN(O187:O1692) -> -0.00059537988
A204: 677.70627 | B204: 683.29998 | C204: 676.72912 | D204: 681.48527 | E204: 8770213.3 | F204: Mon, 08 Jun 2026 00:00:00 GMT | G204: =A204/D204-1 -> -0.0055452324 | I204: 158.04 | J204: 163.05 | K204: 156.58 | L204: 162.39 | M204: 1233565.9 | N204: Mon, 08 Jun 2026 00:00:00 GMT | O204: =I204/L204-1 -> -0.026787364 | R204: SD σ | S204: =_xlfn.STDEV.P(O187:O1692) -> 0.024131211
A205: 676.03115 | B205: 690.16997 | C205: 674.28623 | D205: 689.70134 | E205: 10720357 | F205: Fri, 05 Jun 2026 00:00:00 GMT | G205: =A205/D205-1 -> -0.019820445 | I205: 162.32 | J205: 168.625 | K205: 160.6 | L205: 167.58 | M205: 2041666.6 | N205: Fri, 05 Jun 2026 00:00:00 GMT | O205: =I205/L205-1 -> -0.031387994 | R205: 3σ 1-Day Δ: ± | S205: =3*S204 -> 0.072393634 | U205: <- Sharpe Ratio (Risk Adjusted Return)
A206: 694.03871 | B206: 695.17539 | C206: 688.89369 | D206: 689.48198 | E206: 6594038 | F206: Thu, 04 Jun 2026 00:00:00 GMT | G206: =A206/D206-1 -> 0.006608917 | I206: 168.06 | J206: 177.22 | K206: 166.8 | L206: 171.8 | M206: 2592248.4 | N206: Thu, 04 Jun 2026 00:00:00 GMT | O206: =I206/L206-1 -> -0.021769499 | R206: β (1-year avg.) | S206: =_xlfn.COVARIANCE.P(O132:O380,G132:G380)/_xlfn.VAR.P(G132:G380) -> 1.0053004 | U206: <- Sortino Ratio (Downside Risk Adjusted Return)
A207: 691.34655 | B207: 695.62399 | C207: 690.83803 | D207: 695.05574 | E207: 5899709.5 | F207: Wed, 03 Jun 2026 00:00:00 GMT | G207: =A207/D207-1 -> -0.0053365467 | I207: 170.93 | J207: 172.49 | K207: 160.1 | L207: 162.89 | M207: 3118158.1 | N207: Wed, 03 Jun 2026 00:00:00 GMT | O207: =I207/L207-1 -> 0.049358463
A208: 696.23232 | B208: 697.11973 | C208: 693.75952 | D208: 694.03871 | E208: 4712080 | F208: Tue, 02 Jun 2026 00:00:00 GMT | G208: =A208/D208-1 -> 0.0031606471 | I208: 162.55 | J208: 163.88 | K208: 159.48 | L208: 161.24 | M208: 2113738.6 | N208: Tue, 02 Jun 2026 00:00:00 GMT | O208: =I208/L208-1 -> 0.0081245349 | Q208: n = | R208: 1014
A209: 695.2751 | B209: 697.02999 | C209: 691.92486 | D209: 692.52312 | E209: 9977807.5 | F209: Mon, 01 Jun 2026 00:00:00 GMT | G209: =A209/D209-1 -> 0.0039738532 | I209: 164.4 | J209: 165.97 | K209: 160.84 | L209: 160.85 | M209: 2185319.7 | N209: Mon, 01 Jun 2026 00:00:00 GMT | O209: =I209/L209-1 -> 0.022070252 | Q209: Histogram Data | T209: Distribution Overlay | X209: SD Lines
A210: 693.47036 | B210: 694.97598 | C210: 691.87501 | D210: 692.98178 | E210: 5053895.6 | F210: Fri, 29 May 2026 00:00:00 GMT | G210: =A210/D210-1 -> 0.00070503597 | I210: 162.96 | J210: 165.37 | K210: 158.1 | L210: 159.96 | M210: 2552225.5 | N210: Fri, 29 May 2026 00:00:00 GMT | O210: =I210/L210-1 -> 0.018754689 | Q210: Bin | R210: Frequency | T210: (X) 1-Day Δ | U210: (Y) Pop. Density | X210: X | Y210: Y
A211: 691.89495 | B211: 692.27385 | C211: 686.84964 | D211: 687.757 | E211: 8469446.4 | F211: Thu, 28 May 2026 00:00:00 GMT | G211: =A211/D211-1 -> 0.0060165855 | I211: 158.7 | J211: 158.79 | K211: 150.1 | L211: 150.1 | M211: 2293342 | N211: Thu, 28 May 2026 00:00:00 GMT | O211: =I211/L211-1 -> 0.057295137 | Q211: -0.0775 | R211: 3 | T211: =T212-0.0025 -> -0.08 | U211: =_xlfn.NORM.DIST(T211,$S$202,$S$204,FALSE) -> 0.06439912 | W211: Mean | X211: =S202 -> 0.0003824088 | Y211: 0
A212: 687.95642 | B212: 688.77404 | C212: 685.92234 | D212: 688.35526 | E212: 7356729.2 | F212: Wed, 27 May 2026 00:00:00 GMT | G212: =A212/D212-1 -> -0.00057940785 | I212: 150.17 | J212: 151.75 | K212: 142.945 | L212: 144.74 | M212: 1856492.4 | N212: Wed, 27 May 2026 00:00:00 GMT | O212: =I212/L212-1 -> 0.037515545 | Q212: -0.075 | R212: 0 | T212: =T213-0.0025 -> -0.0775 | U212: =_xlfn.NORM.DIST(T212,$S$202,$S$204,FALSE) -> 0.090453122 | X212: =S202 -> 0.0003824088 | Y212: 30
A213: 688.00627 | B213: 689.50242 | C213: 686.08188 | D213: 687.64732 | E213: 6622042.8 | F213: Tue, 26 May 2026 00:00:00 GMT | G213: =A213/D213-1 -> 0.00052200392 | I213: 145.225 | J213: 146.42 | K213: 142.6149 | L213: 144.61 | M213: 1596829.4 | N213: Tue, 26 May 2026 00:00:00 GMT | O213: =I213/L213-1 -> 0.0042528179 | Q213: -0.0725 | R213: 0 | T213: =T214-0.0025 -> -0.075 | U213: =_xlfn.NORM.DIST(T213,$S$202,$S$204,FALSE) -> 0.1256915 | W213: -3σ | X213: =($S$204*-3)+$S$202 -> -0.072011225 | Y213: 0
A214: 683.55923 | B214: 686.58043 | C214: 682.49223 | D214: 684.10763 | E214: 4276144.9 | F214: Fri, 22 May 2026 00:00:00 GMT | G214: =A214/D214-1 -> -0.00080163242 | I214: 144.41 | J214: 146.49 | K214: 143.17 | L214: 144.69 | M214: 899286.71 | N214: Fri, 22 May 2026 00:00:00 GMT | O214: =I214/L214-1 -> -0.0019351717 | Q214: -0.07 | R214: 3 | T214: =T215-0.0025 -> -0.0725 | U214: =_xlfn.NORM.DIST(T214,$S$202,$S$204,FALSE) -> 0.17279332 | X214: =($S$204*-3)+$S$202 -> -0.072011225 | Y214: 2
A215: 680.8571 | B215: 682.83633 | C215: 675.65225 | D215: 677.10801 | E215: 7310162.6 | F215: Thu, 21 May 2026 00:00:00 GMT | G215: =A215/D215-1 -> 0.0055369029 | I215: 144.83 | J215: 146.61 | K215: 139.535 | L215: 141.02 | M215: 1383175.4 | N215: Thu, 21 May 2026 00:00:00 GMT | O215: =I215/L215-1 -> 0.027017444 | Q215: -0.0675 | R215: 0 | T215: =T216-0.0025 -> -0.07 | U215: =_xlfn.NORM.DIST(T215,$S$202,$S$204,FALSE) -> 0.2350102 | W215: -2σ | X215: =($S$204*-2)+$S$202 -> -0.047880014 | Y215: 0
A216: 679.59078 | B216: 680.01953 | C216: 672.78072 | D216: 674.35603 | E216: 5453356.5 | F216: Wed, 20 May 2026 00:00:00 GMT | G216: =A216/D216-1 -> 0.0077625976 | I216: 141.92 | J216: 142.3225 | K216: 138.64 | L216: 141.76 | M216: 1446194.6 | N216: Wed, 20 May 2026 00:00:00 GMT | O216: =I216/L216-1 -> 0.0011286682 | Q216: -0.065 | R216: 0 | T216: =T217-0.0025 -> -0.0675 | U216: =_xlfn.NORM.DIST(T216,$S$202,$S$204,FALSE) -> 0.31621697 | X216: =($S$204*-2)+$S$202 -> -0.047880014 | Y216: 5
A217: 672.63105 | B217: 676.18071 | C217: 670.59698 | D217: 673.59824 | E217: 5611397.2 | F217: Tue, 19 May 2026 00:00:00 GMT | G217: =A217/D217-1 -> -0.0014358458 | I217: 141.68 | J217: 142.79 | K217: 139.13 | L217: 142.28 | M217: 1522804.7 | N217: Tue, 19 May 2026 00:00:00 GMT | O217: =I217/L217-1 -> -0.0042170368 | Q217: -0.0625 | R217: 2 | T217: =T218-0.0025 -> -0.065 | U217: =_xlfn.NORM.DIST(T217,$S$202,$S$204,FALSE) -> 0.42094209 | W217: -1σ | X217: =($S$204*-1)+$S$202 -> -0.023748803 | Y217: 0
A218: 676.93851 | B218: 679.63067 | C218: 672.29204 | D218: 678.20482 | E218: 7569986.9 | F218: Mon, 18 May 2026 00:00:00 GMT | G218: =A218/D218-1 -> -0.0018671528 | I218: 141.51 | J218: 144.4604 | K218: 140.6901 | L218: 142.22 | M218: 1436033.2 | N218: Mon, 18 May 2026 00:00:00 GMT | O218: =I218/L218-1 -> -0.0049922655 | Q218: -0.06 | R218: 2 | T218: =T219-0.0025 -> -0.0625 | U218: =_xlfn.NORM.DIST(T218,$S$202,$S$204,FALSE) -> 0.55436812 | X218: =($S$204*-1)+$S$202 -> -0.023748803 | Y218: 10
A219: 677.46697 | B219: 681.53512 | C219: 676.47087 | D219: 680.05942 | E219: 6421958.6 | F219: Fri, 15 May 2026 00:00:00 GMT | G219: =A219/D219-1 -> -0.0038120931 | I219: 142.54 | J219: 143.86 | K219: 138.06 | L219: 141.46 | M219: 1752400 | N219: Fri, 15 May 2026 00:00:00 GMT | O219: =I219/L219-1 -> 0.007634667 | Q219: -0.0575 | R219: 1 | T219: =T220-0.0025 -> -0.06 | U219: =_xlfn.NORM.DIST(T219,$S$202,$S$204,FALSE) -> 0.72229207 | W219: 1σ | X219: =($S$204*1)+$S$202 -> 0.02451362 | Y219: 0
A220: 685.7329 | B220: 687.09892 | C220: 681.67471 | D220: 681.75448 | E220: 5353379.5 | F220: Thu, 14 May 2026 00:00:00 GMT | G220: =A220/D220-1 -> 0.0058355515 | I220: 143.24 | J220: 150.2 | K220: 142.97 | L220: 149.45 | M220: 2006093.6 | N220: Thu, 14 May 2026 00:00:00 GMT | O220: =I220/L220-1 -> -0.041552359 | Q220: -0.055 | R220: 5 | T220: =T221-0.0025 -> -0.0575 | U220: =_xlfn.NORM.DIST(T220,$S$202,$S$204,FALSE) -> 0.93103532 | X220: =($S$204*1)+$S$202 -> 0.02451362 | Y220: 10
A221: 680.42834 | B221: 681.92399 | C221: 674.23638 | D221: 676.92854 | E221: 4896730 | F221: Wed, 13 May 2026 00:00:00 GMT | G221: =A221/D221-1 -> 0.0051701281 | I221: 145 | J221: 148.87 | K221: 143.21 | L221: 146.14 | M221: 2062645.4 | N221: Wed, 13 May 2026 00:00:00 GMT | O221: =I221/L221-1 -> -0.007800739 | Q221: -0.0525 | R221: 1 | T221: =T222-0.0025 -> -0.055 | U221: =_xlfn.NORM.DIST(T221,$S$202,$S$204,FALSE) -> 1.1872937 | W221: 2σ | X221: =($S$204*2)+$S$202 -> 0.048644832 | Y221: 0
A222: 676.6992 | B222: 677.28749 | C222: 670.84625 | D222: 675.50269 | E222: 6037564.6 | F222: Tue, 12 May 2026 00:00:00 GMT | G222: =A222/D222-1 -> 0.0017712961 | I222: 145.7 | J222: 146.75 | K222: 142.36 | L222: 143.5 | M222: 2826414.5 | N222: Tue, 12 May 2026 00:00:00 GMT | O222: =I222/L222-1 -> 0.01533101 | Q222: -0.05 | R222: 7 | T222: =T223-0.0025 -> -0.0525 | U222: =_xlfn.NORM.DIST(T222,$S$202,$S$204,FALSE) -> 1.497921 | X222: =($S$204*2)+$S$202 -> 0.048644832 | Y222: 5
A223: 677.54674 | B223: 679.08226 | C223: 675.11382 | D223: 675.11382 | E223: 5676979.9 | F223: Mon, 11 May 2026 00:00:00 GMT | G223: =A223/D223-1 -> 0.00360371 | I223: 142.51 | J223: 145.21 | K223: 139 | L223: 140.67 | M223: 1938157.9 | N223: Mon, 11 May 2026 00:00:00 GMT | O223: =I223/L223-1 -> 0.013080259 | Q223: -0.0475 | R223: 10 | T223: =T224-0.0025 -> -0.05 | U223: =_xlfn.NORM.DIST(T223,$S$202,$S$204,FALSE) -> 1.8696416 | W223: 3σ | X223: =($S$204*3)+$S$202 -> 0.072776043 | Y223: 0
A224: 676.07103 | B224: 676.55961 | C224: 673.40879 | D224: 673.73783 | E224: 4322344.1 | F224: Fri, 08 May 2026 00:00:00 GMT | G224: =A224/D224-1 -> 0.0034630753 | I224: 141.88 | J224: 142.2 | K224: 134.67 | L224: 138 | M224: 1468248.8 | N224: Fri, 08 May 2026 00:00:00 GMT | O224: =I224/L224-1 -> 0.028115942 | Q224: -0.045 | R224: 9 | T224: =T225-0.0025 -> -0.0475 | U224: =_xlfn.NORM.DIST(T224,$S$202,$S$204,FALSE) -> 2.3086947 | X224: =($S$204*3)+$S$202 -> 0.072776043 | Y224: 2
A225: 670.58701 | B225: 674.79485 | C225: 668.97171 | D225: 673.85748 | E225: 6066984.8 | F225: Thu, 07 May 2026 00:00:00 GMT | G225: =A225/D225-1 -> -0.0048533633 | I225: 138.71 | J225: 142.395 | K225: 137.1 | L225: 141.37 | M225: 1234339.5 | N225: Thu, 07 May 2026 00:00:00 GMT | O225: =I225/L225-1 -> -0.018815873 | Q225: -0.0425 | R225: 11 | T225: =T226-0.0025 -> -0.045 | U225: =_xlfn.NORM.DIST(T225,$S$202,$S$204,FALSE) -> 2.8204173
A226: 672.70085 | B226: 673.37887 | C226: 667.20685 | D226: 667.50598 | E226: 6416177.8 | F226: Wed, 06 May 2026 00:00:00 GMT | G226: =A226/D226-1 -> 0.007782508 | I226: 142.58 | J226: 143.01 | K226: 137.96 | L226: 139.04 | M226: 1331689.2 | N226: Wed, 06 May 2026 00:00:00 GMT | O226: =I226/L226-1 -> 0.025460299 | Q226: -0.04 | R226: 10 | T226: =T227-0.0025 -> -0.0425 | U226: =_xlfn.NORM.DIST(T226,$S$202,$S$204,FALSE) -> 3.4087798
A227: 663.36803 | B227: 664.6144 | C227: 661.40375 | D227: 661.65302 | E227: 4962020 | F227: Tue, 05 May 2026 00:00:00 GMT | G227: =A227/D227-1 -> 0.002592001 | I227: 139.07 | J227: 142.41 | K227: 136.36 | L227: 139.58 | M227: 1236281.3 | N227: Tue, 05 May 2026 00:00:00 GMT | O227: =I227/L227-1 -> -0.0036538186 | Q227: -0.0375 | R227: 11 | T227: =T228-0.0025 -> -0.04 | U227: =_xlfn.NORM.DIST(T227,$S$202,$S$204,FALSE) -> 4.0758973
A228: 658.20307 | B228: 661.92224 | C228: 655.481 | D228: 660.06764 | E228: 5944718.8 | F228: Mon, 04 May 2026 00:00:00 GMT | G228: =A228/D228-1 -> -0.0028248161 | I228: 139.37 | J228: 140.84 | K228: 133.97 | L228: 135.45 | M228: 2012840.5 | N228: Mon, 04 May 2026 00:00:00 GMT | O228: =I228/L228-1 -> 0.028940568 | Q228: -0.035 | R228: 18 | T228: =T229-0.0025 -> -0.0375 | U228: =_xlfn.NORM.DIST(T228,$S$202,$S$204,FALSE) -> 4.821545
A229: 660.5961 | B229: 664.47979 | C229: 660.45651 | D229: 661.16445 | E229: 4948602.5 | F229: Fri, 01 May 2026 00:00:00 GMT | G229: =A229/D229-1 -> -0.00085961182 | I229: 135.78 | J229: 136.63 | K229: 128.06 | L229: 133.22 | M229: 2772702.6 | N229: Fri, 01 May 2026 00:00:00 GMT | O229: =I229/L229-1 -> 0.019216334 | Q229: -0.0325 | R229: 17 | T229: =T230-0.0025 -> -0.035 | U229: =_xlfn.NORM.DIST(T229,$S$202,$S$204,FALSE) -> 5.6427126
A230: 658.66174 | B230: 659.84828 | C230: 651.24833 | D230: 655.09213 | E230: 5919880.4 | F230: Thu, 30 Apr 2026 00:00:00 GMT | G230: =A230/D230-1 -> 0.0054490107 | I230: 126.74 | J230: 128.1199 | K230: 121.43 | L230: 121.72 | M230: 2355848.8 | N230: Thu, 30 Apr 2026 00:00:00 GMT | O230: =I230/L230-1 -> 0.041242195 | Q230: -0.03 | R230: 16 | T230: =T231-0.0025 -> -0.0325 | U230: =_xlfn.NORM.DIST(T230,$S$202,$S$204,FALSE) -> 6.533236
A231: 652.34015 | B231: 652.82244 | C231: 649.3688 | D231: 651.72195 | E231: 6221167.1 | F231: Wed, 29 Apr 2026 00:00:00 GMT | G231: =A231/D231-1 -> 0.00094856339 | I231: 120.37 | J231: 127.435 | K231: 119.14 | L231: 125.9 | M231: 1737282.6 | N231: Wed, 29 Apr 2026 00:00:00 GMT | O231: =I231/L231-1 -> -0.043923749 | Q231: -0.0275 | R231: 24 | T231: =T232-0.0025 -> -0.03 | U231: =_xlfn.NORM.DIST(T231,$S$202,$S$204,FALSE) -> 7.4835467
A232: 652.36009 | B232: 653.48681 | C232: 650.11662 | D232: 652.50965 | E232: 5525716 | F232: Tue, 28 Apr 2026 00:00:00 GMT | G232: =A232/D232-1 -> -0.0002292141 | I232: 126.92 | J232: 128.1 | K232: 125.05 | L232: 127.97 | M232: 1249926.5 | N232: Tue, 28 Apr 2026 00:00:00 GMT | O232: =I232/L232-1 -> -0.0082050481 | Q232: -0.025 | R232: 23 | T232: =T233-0.0025 -> -0.0275 | U232: =_xlfn.NORM.DIST(T232,$S$202,$S$204,FALSE) -> 8.4805753
A233: 655.59068 | B233: 655.98952 | C233: 652.9384 | D233: 653.76599 | E233: 5297681.3 | F233: Mon, 27 Apr 2026 00:00:00 GMT | G233: =A233/D233-1 -> 0.0027910382 | I233: 128.52 | J233: 129.28 | K233: 126.93 | L233: 126.93 | M233: 1267495.9 | N233: Mon, 27 Apr 2026 00:00:00 GMT | O233: =I233/L233-1 -> 0.012526589 | Q233: -0.0225 | R233: 38 | T233: =T234-0.0025 -> -0.025 | U233: =_xlfn.NORM.DIST(T233,$S$202,$S$204,FALSE) -> 9.5078399
A234: 654.51382 | B234: 654.91265 | C234: 649.92737 | D234: 651.50259 | E234: 4736752.5 | F234: Fri, 24 Apr 2026 00:00:00 GMT | G234: =A234/D234-1 -> 0.0046219773 | I234: 127.88 | J234: 128.17 | K234: 124.02 | L234: 124.65 | M234: 876476.21 | N234: Fri, 24 Apr 2026 00:00:00 GMT | O234: =I234/L234-1 -> 0.025912555 | Q234: -0.02 | R234: 50 | T234: =T235-0.0025 -> -0.0225 | U234: =_xlfn.NORM.DIST(T234,$S$202,$S$204,FALSE) -> 10.545741
A235: 649.3688 | B235: 652.99823 | C235: 643.78506 | D235: 650.33598 | E235: 6034316.6 | F235: Thu, 23 Apr 2026 00:00:00 GMT | G235: =A235/D235-1 -> -0.0014872054 | I235: 125.44 | J235: 128.67 | K235: 121.265 | L235: 128.46 | M235: 1505055.8 | N235: Thu, 23 Apr 2026 00:00:00 GMT | O235: =I235/L235-1 -> -0.023509264 | Q235: -0.0175 | R235: 43 | T235: =T236-0.0025 -> -0.02 | U235: =_xlfn.NORM.DIST(T235,$S$202,$S$204,FALSE) -> 11.572071
A236: 652.00113 | B236: 652.29029 | C236: 649.19929 | D236: 650.08671 | E236: 4504953.3 | F236: Wed, 22 Apr 2026 00:00:00 GMT | G236: =A236/D236-1 -> 0.0029448756 | I236: 130.5 | J236: 133.645 | K236: 129.16 | L236: 133.22 | M236: 1020589.7 | N236: Wed, 22 Apr 2026 00:00:00 GMT | O236: =I236/L236-1 -> -0.020417355 | Q236: -0.015 | R236: 45 | T236: =T237-0.0025 -> -0.0175 | U236: =_xlfn.NORM.DIST(T236,$S$202,$S$204,FALSE) -> 12.562722
... A242: 636.49629 | B242: 636.6658 | C242: 630.38409 | D242: 630.38908 | E242: 5013507.9 | F242: Tue, 14 Apr 2026 00:00:00 GMT | G242: =A242/D242-1 -> 0.0096880066 | I242: 130.32 | J242: 130.79 | K242: 126.49 | L242: 126.79 | M242: 1195164 | N242: Tue, 14 Apr 2026 00:00:00 GMT | O242: =I242/L242-1 -> 0.027841312 | Q242: 0 | R242: 91 | T242: =T243-0.0025 -> -0.0025 | U242: =_xlfn.NORM.DIST(T242,$S$202,$S$204,FALSE) -> 16.414693
A243: 628.88845 | B243: 629.06792 | C243: 620.17383 | D243: 620.94159 | E243: 5115773.6 | F243: Mon, 13 Apr 2026 00:00:00 GMT | G243: =A243/D243-1 -> 0.012798073 | I243: 126.96 | J243: 127.83 | K243: 120.6049 | L243: 121.39 | M243: 1350248.7 | N243: Mon, 13 Apr 2026 00:00:00 GMT | O243: =I243/L243-1 -> 0.045885164 | Q243: 0.0025 | R243: 64 | T243: 0 | U243: =_xlfn.NORM.DIST(T243,$S$202,$S$204,FALSE) -> 16.530135
A244: 622.78622 | B244: 625.16928 | C244: 621.90877 | D244: 624.50621 | E244: 4587617 | F244: Fri, 10 Apr 2026 00:00:00 GMT | G244: =A244/D244-1 -> -0.0027541612 | I244: 120.93 | J244: 125.932 | K244: 118.3 | L244: 125.07 | M244: 1804892 | N244: Fri, 10 Apr 2026 00:00:00 GMT | O244: =I244/L244-1 -> -0.033101463 | Q244: 0.005 | R244: 72 | T244: =T243+0.0025 -> 0.0025 | U244: =_xlfn.NORM.DIST(T244,$S$202,$S$204,FALSE) -> 16.468679
A245: 623.205 | B245: 624.35166 | C245: 617.60132 | D245: 618.53859 | E245: 5486229 | F245: Thu, 09 Apr 2026 00:00:00 GMT | G245: =A245/D245-1 -> 0.0075442499 | I245: 123.67 | J245: 126.9326 | K245: 122.695 | L245: 126.03 | M245: 2306203.2 | N245: Thu, 09 Apr 2026 00:00:00 GMT | O245: =I245/L245-1 -> -0.0187257 | Q245: 0.0075 | R245: 65 | T245: =T244+0.0025 -> 0.005 | U245: =_xlfn.NORM.DIST(T245,$S$202,$S$204,FALSE) -> 16.232292
A246: 619.53569 | B246: 620.68235 | C246: 615.50742 | D246: 619.98936 | E246: 9794014.5 | F246: Wed, 08 Apr 2026 00:00:00 GMT | G246: =A246/D246-1 -> -0.00073175243 | I246: 128 | J246: 132.79 | K246: 125.71 | L246: 130.99 | M246: 1674487.8 | N246: Wed, 08 Apr 2026 00:00:00 GMT | O246: =I246/L246-1 -> -0.02282617 | Q246: 0.01 | R246: 68 | T246: =T245+0.0025 -> 0.0075 | U246: =_xlfn.NORM.DIST(T246,$S$202,$S$204,FALSE) -> 15.828495
A247: 604.28012 | B247: 604.54933 | C247: 596.76201 | D247: 601.82726 | E247: 6164208.3 | F247: Tue, 07 Apr 2026 00:00:00 GMT | G247: =A247/D247-1 -> 0.0040756818 | I247: 126.44 | J247: 129.06 | K247: 125.24 | L247: 127 | M247: 796483.5 | N247: Tue, 07 Apr 2026 00:00:00 GMT | O247: =I247/L247-1 -> -0.0044094488 | Q247: 0.0125 | R247: 63 | T247: =T246+0.0025 -> 0.01 | U247: =_xlfn.NORM.DIST(T247,$S$202,$S$204,FALSE) -> 15.269968
A248: 603.91119 | B248: 604.67895 | C248: 600.86008 | D248: 601.16918 | E248: 6300935.5 | F248: Mon, 06 Apr 2026 00:00:00 GMT | G248: =A248/D248-1 -> 0.0045611358 | I248: 127.74 | J248: 128.72 | K248: 126.48 | L248: 127.3 | M248: 1033127.6 | N248: Mon, 06 Apr 2026 00:00:00 GMT | O248: =I248/L248-1 -> 0.0034564022 | Q248: 0.015 | R248: 59 | T248: =T247+0.0025 -> 0.0125 | U248: =_xlfn.NORM.DIST(T248,$S$202,$S$204,FALSE) -> 14.573885
A249: 601.23897 | B249: 603.03375 | C249: 591.30989 | D249: 592.50441 | E249: 12776618 | F249: Thu, 02 Apr 2026 00:00:00 GMT | G249: =A249/D249-1 -> 0.014741767 | I249: 127.38 | J249: 130 | K249: 124 | L249: 124.44 | M249: 960447.27 | N249: Thu, 02 Apr 2026 00:00:00 GMT | O249: =I249/L249-1 -> 0.023625844 | Q249: 0.0175 | R249: 55 | T249: =T248+0.0025 -> 0.015 | U249: =_xlfn.NORM.DIST(T249,$S$202,$S$204,FALSE) -> 13.76104
A250: 600.55098 | B250: 603.59212 | C250: 598.52687 | D250: 599.31458 | E250: 11314501 | F250: Wed, 01 Apr 2026 00:00:00 GMT | G250: =A250/D250-1 -> 0.002063022 | I250: 126.63 | J250: 128.5 | K250: 122.61 | L250: 123.62 | M250: 1224022.4 | N250: Wed, 01 Apr 2026 00:00:00 GMT | O250: =I250/L250-1 -> 0.024348811 | Q250: 0.02 | R250: 35 | T250: =T249+0.0025 -> 0.0175 | U250: =_xlfn.NORM.DIST(T250,$S$202,$S$204,FALSE) -> 12.854816
A251: 595.81477 | B251: 597.11099 | C251: 584.79686 | D251: 585.64439 | E251: 12375375 | F251: Tue, 31 Mar 2026 00:00:00 GMT | G251: =A251/D251-1 -> 0.017366136 | I251: 123.26 | J251: 126.105 | K251: 121.95 | L251: 121.98 | M251: 1383139.7 | N251: Tue, 31 Mar 2026 00:00:00 GMT | O251: =I251/L251-1 -> 0.010493524 | Q251: 0.0225 | R251: 33 | T251: =T250+0.0025 -> 0.02 | U251: =_xlfn.NORM.DIST(T251,$S$202,$S$204,FALSE) -> 11.880076
A252: 579.24303 | B252: 586.96056 | C252: 576.78021 | D252: 586.68137 | E252: 11776669 | F252: Mon, 30 Mar 2026 00:00:00 GMT | G252: =A252/D252-1 -> -0.012678666 | I252: 120.81 | J252: 122.445 | K252: 118.82 | L252: 119.58 | M252: 1222848.8 | N252: Mon, 30 Mar 2026 00:00:00 GMT | O252: =I252/L252-1 -> 0.010286001 | Q252: 0.025 | R252: 29 | T252: =T251+0.0025 -> 0.0225 | U252: =_xlfn.NORM.DIST(T252,$S$202,$S$204,FALSE) -> 10.862036
A253: 581.26714 | B253: 589.11428 | C253: 580.33984 | D253: 588.96472 | E253: 11637657 | F253: Fri, 27 Mar 2026 00:00:00 GMT | G253: =A253/D253-1 -> -0.013069682 | I253: 117.67 | J253: 123.32 | K253: 116.735 | L253: 123 | M253: 1217951.2 | N253: Fri, 27 Mar 2026 00:00:00 GMT | O253: =I253/L253-1 -> -0.043333333 | Q253: 0.0275 | R253: 20 | T253: =T252+0.0025 -> 0.025 | U253: =_xlfn.NORM.DIST(T253,$S$202,$S$204,FALSE) -> 9.8252137
A254: 591.32544 | B254: 600.25616 | C254: 591.08689 | D254: 597.66193 | E254: 7632666.6 | F254: Thu, 26 Mar 2026 00:00:00 GMT | G254: =A254/D254-1 -> -0.010602117 | I254: 124.4 | J254: 127.3 | K254: 124.245 | L254: 125.27 | M254: 962238.7 | N254: Thu, 26 Mar 2026 00:00:00 GMT | O254: =I254/L254-1 -> -0.0069449988 | Q254: 0.03 | R254: 25 | T254: =T253+0.0025 -> 0.0275 | U254: =_xlfn.NORM.DIST(T254,$S$202,$S$204,FALSE) -> 8.7924817
A255: 602.00055 | B255: 605.75771 | C255: 599.71445 | D255: 603.73004 | E255: 23373518 | F255: Wed, 25 Mar 2026 00:00:00 GMT | G255: =A255/D255-1 -> -0.0028646691 | I255: 126.2 | J255: 128.74 | K255: 122.04 | L255: 126.21 | M255: 1405970.8 | N255: Wed, 25 Mar 2026 00:00:00 GMT | O255: =I255/L255-1 -> -7.9233024e-05 | Q255: 0.0325 | R255: 18 | T255: =T254+0.0025 -> 0.03 | U255: =_xlfn.NORM.DIST(T255,$S$202,$S$204,FALSE) -> 7.7843015
... A273: 627.2272 | B273: 627.87328 | C273: 623.15198 | D273: 624.44412 | E273: 10491519 | F273: Fri, 27 Feb 2026 00:00:00 GMT | G273: =A273/D273-1 -> 0.0044568955 | I273: 134.46 | J273: 134.76 | K273: 127 | L273: 127.965 | M273: 3998834.1 | N273: Fri, 27 Feb 2026 00:00:00 GMT | O273: =I273/L273-1 -> 0.050756066 | Q273: 0.0775 | R273: 2 | T273: =T272+0.0025 -> 0.075 | U273: =_xlfn.NORM.DIST(T273,$S$202,$S$204,FALSE) -> 0.13870315
A274: 630.11962 | B274: 633.91654 | C274: 625.62693 | D274: 633.79727 | E274: 9465251.1 | F274: Thu, 26 Feb 2026 00:00:00 GMT | G274: =A274/D274-1 -> -0.0058025563 | I274: 127.4 | J274: 127.64 | K274: 118.53 | L274: 122.76 | M274: 3774769.5 | N274: Thu, 26 Feb 2026 00:00:00 GMT | O274: =I274/L274-1 -> 0.037797328 | Q274: More | R274: 10 | T274: =T273+0.0025 -> 0.0775 | U274: =_xlfn.NORM.DIST(T274,$S$202,$S$204,FALSE) -> 0.10014517
A275: 633.67799 | B275: 634.14515 | C275: 630.90485 | D275: 630.93467 | E275: 12065850 | F275: Wed, 25 Feb 2026 00:00:00 GMT | G275: =A275/D275-1 -> 0.0043480316 | I275: 121.87 | J275: 124.025 | K275: 120.88 | L275: 123.825 | M275: 1679791.4 | N275: Wed, 25 Feb 2026 00:00:00 GMT | O275: =I275/L275-1 -> -0.015788411 | T275: =T274+0.0025 -> 0.08 | U275: =_xlfn.NORM.DIST(T275,$S$202,$S$204,FALSE) -> 0.071533981
A276: 628.39013 | B276: 629.26482 | C276: 621.62128 | D276: 623.36071 | E276: 6934297.7 | F276: Tue, 24 Feb 2026 00:00:00 GMT | G276: =A276/D276-1 -> 0.0080682452 | I276: 122.9 | J276: 124.96 | K276: 120.6 | L276: 120.87 | M276: 2321923.1 | N276: Tue, 24 Feb 2026 00:00:00 GMT | O276: =I276/L276-1 -> 0.016794904
A277: 623.83781 | B277: 630.77563 | C277: 621.96917 | D277: 628.78772 | E277: 10883526 | F277: Mon, 23 Feb 2026 00:00:00 GMT | G277: =A277/D277-1 -> -0.0078721487 | I277: 120.54 | J277: 120.6 | K277: 115.88 | L277: 116.55 | M277: 1970009.9 | N277: Mon, 23 Feb 2026 00:00:00 GMT | O277: =I277/L277-1 -> 0.034234234
A278: 630.1892 | B278: 630.74582 | C278: 623.24143 | D278: 623.68871 | E278: 7493334.3 | F278: Fri, 20 Feb 2026 00:00:00 GMT | G278: =A278/D278-1 -> 0.010422643 | I278: 117.67 | J278: 119.685 | K278: 115.8 | L278: 116.18 | M278: 2114085 | N278: Fri, 20 Feb 2026 00:00:00 GMT | O278: =I278/L278-1 -> 0.012824927
A279: 625.72633 | B279: 627.26696 | C279: 623.02276 | D279: 625.14983 | E279: 5201993.9 | F279: Thu, 19 Feb 2026 00:00:00 GMT | G279: =A279/D279-1 -> 0.00092217187 | I279: 120 | J279: 120.41 | K279: 118.68 | L279: 119.28 | M279: 1887781 | N279: Thu, 19 Feb 2026 00:00:00 GMT | O279: =I279/L279-1 -> 0.0060362173
...

Sheet Product Lines

Sheet Management

Sheet Table Formatting
B2: [Bold Title] | G2: [Bold Title]
B3: Line Titles | G3: <-- General
B4: Line Titles | G4: <-- Info
B5: Line Titles | G5: <-- General
B6: Line Titles | G6: <-- Info
B7: Line Titles | G7: <-- General
B8: Line Titles | G8: <-- Info
