Workbook

Sheet Main
A1: Master
A2: Capital Structure Snapshot:
B4: ISRG
B5: Price | C5: 407.34 | D5: 10/21/2026
B6: SO | C6: 349 | D6: Q2'26
B7: MC | C7: =C5*C6 -> 142161.66
B8: Cash | C8: 6800.4 | D8: Q2'26
B9: Debt | C9: 0 | D9: Q2'26
B10: EV | C10: =C7-C8+C9 -> 135361.26
B12: Intuitive Surgical, Inc. (ISRG)
B14: Founder(s): Frederic Moll, John Freund, and Robert Younge | H14: Registered Exchange: NASDAQ | P14: Resources:
B15: Founded: 1995 | H15: Address: 1020 Kifer Road, Sunnyvale, California 94086 | P15: SEC filings | S15: https://www.sec.gov/edgar/browse/?CIK=1035267&owner=exclude
B16: Headquarters: Sunnyvale, CA | H16: Investor Relations Contact: | P16: Intuitive Homepage | S16: https://www.intuitive.com/en-us
B17: Current CEO: David Rosa (Succeeding Gary Guthart who stepped back into Chairman role July 1st, 2025) | H17: Investors Relation Department | Q17: Intuitive IR Page | T17: https://isrg.intuitive.com/
B18: Employees: 15,638 (Q4'24) | H18: Phone: (408) 523-2161 | K18: Email: | L18: investor.relations@intusurg.com | P18: Earnings Calls | S18: https://seekingalpha.com/symbol/ISRG/earnings/transcripts
B19: Industry: Medical Instruments & Supplies | P19: Equity Analysis | S19: https://stockanalysis.com/stocks/isrg/company/
B20: Sector: Healthcare | P20: MacroTrends | S20: https://www.macrotrends.net/stocks/charts/ISRG/intuitive-surgical/cash-flow-statement?freq=Q
B21: IPO: June 13, 2000 -- ~$116M valuation | P21: ROIC, WACC | S21: https://www.gurufocus.com/term/wacc/ISRG
B22: Fiscal Year: [January - December] | P22: Godel Terminal | S22: https://app.godelterminal.com/
A24: Company Overview:
B25: Intuitive Surgical, Inc. develops, manufactures, and markets products that enable physicians and healthcare providers to enhance the quality of and access to minimally invasive care in the United States and internationally
B26: The Company offers the Da Vinci Surgical System that enables surgical procedures using a minimally invasive approach; and Ion endoluminal system, which extends its commercial offerings beyond surgery into diagnostic endoluminal procedures enabling minimally invasive biopsies in the lung
B27: It also provides a suite of stapling, energy, and core instrumentation for its multi-port da Vinci surgical systems; progressive learning pathways to support the use of its technology
C28: Infrastructure of service and support specialists, a complement of services to its customers
C29: Including installation, repair, maintenance, 24/7 technical support, and proactive system health monitoring
C30: Integrated digital capabilities providing connected offerings, streamlining performance for hospitals with program-enhancing insights
B31: The Company sells its products through direct sales organizations, such as capital and clinical sales teams
C32: Intuitive Surgical, Inc. was incorporated in 1995 and is headquartered in Sunnyvale, California
B33: They did surgery on a grape
A35: Business Segments and Geographical Info:

Sheet Model
B1: [Use for Graphing] | AU1: Q1 2020 | AY1: Q1 2021 | BC1: Q1 2022 | BG1: Q1 2023 | BK1: Q1 2024 | BO1: Q1 2025 | BS1: Q1 2026
B2: Quarterly
B3: Revenues | C3: Q1 2009 | D3: Q2 2009 | E3: Q3 2009 | F3: Q4 2009 | G3: Q1 2010 | H3: Q2 2010 | I3: Q3 2010 | J3: Q4 2010 | K3: Q1 2011 | L3: Q2 2011 | M3: Q3 2011 | N3: Q4 2011 | O3: Q1 2012 | P3: Q2 2012 | Q3: Q3 2012 | R3: Q4 2012 | S3: Q1 2013 | T3: Q2 2013 | U3: Q3 2013 | V3: Q4 2013 | W3: Q1 2014 | X3: Q2 2014 | Y3: Q3 2014 | Z3: Q4 2014 | AA3: Q1 2015 | AB3: Q2 2015 | AC3: Q3 2015 | AD3: Q4 2015 | AE3: Q1 2016 | AF3: Q2 2016 | AG3: Q3 2016 | AH3: Q4 2016 | AI3: Q1 2017 | AJ3: Q2 2017 | AK3: Q3 2017 | AL3: Q4 2017 | AM3: Q1 2018 | AN3: Q2 2018 | AO3: Q3 2018 | AP3: Q4 2018 | AQ3: Q1 2019 | AR3: Q2 2019 | AS3: Q3 2019 | AT3: Q4 2019 | AU3: Q1 2020 | AV3: Q2 2020 | AW3: Q3 2020 | AX3: Q4 2020 | AY3: Q1 2021 | AZ3: Q2 2021 | BA3: Q3 2021 | BB3: Q4 2021 | BC3: Q1 2022 | BD3: Q2 2022 | BE3: Q3 2022 | BF3: Q4 2022 | BG3: Q1 2023 | BH3: Q2 2023 | BI3: Q3 2023 | BJ3: Q4 2023 | BK3: Q1 2024 | BL3: Q2 2024 | BM3: Q3 2024 | BN3: Q4 2024 | BO3: Q1 2025 | BP3: Q2 2025 | BQ3: Q3 2025 | BR3: Q4 2025 | BS3: Q1 2026 | BT3: Q2 2026 | BU3: Q3 2026 | BV3: Q4 2026 | CA3: =CB3-1 -> 2009 | CB3: =CC3-1 -> 2010 | CC3: =CD3-1 -> 2011 | CD3: =CE3-1 -> 2012 | CE3: =CF3-1 -> 2013 | CF3: =CG3-1 -> 2014 | CG3: =CH3-1 -> 2015 | CH3: =CI3-1 -> 2016 | ... CK3: =CL3-1 -> 2019 | CL3: 2020 | CM3: =CL3+1 -> 2021 | CN3: =CM3+1 -> 2022 | CO3: =CN3+1 -> 2023 | CP3: =CO3+1 -> 2024 | CQ3: =CP3+1 -> 2025 | CR3: =CQ3+1 -> 2026 | CS3: =CR3+1 -> 2027 | CT3: =CS3+1 -> 2028 | ... EY3: =EX3+1 -> 2085
B4: Instruments & Accessories | AU4: 617.5 | AV4: 460.8 | AW4: 630.5 | AX4: =2455.7-SUM(AU4:AW4) -> 746.9 | AY4: 705.9 | AZ4: 796.4 | BA4: 755.4 | BB4: =3100.5-SUM(AY4:BA4) -> 842.8 | BC4: 810.3 | BD4: 895.3 | BE4: 871.6 | BF4: =3517.9-SUM(BC4:BE4) -> 940.7 | BG4: 985.6 | BH4: 1075.9 | BI4: 1071.4 | BJ4: =4276.6-SUM(BG4:BI4) -> 1143.7 | BK4: 1158.9 | BL4: 1244.4 | BM4: 1264.2 | BN4: =5079-SUM(BK4:BM4) -> 1411.5 | BO4: 1367.7 | BP4: =2841.8-BO4 -> 1474.1 | BQ4: 1518.8 | BR4: 1658.3 | BS4: 1686.4 | BT4: 1734.9 | BU4: 1797.4 | CL4: =SUM(AU4:AX4) -> 2455.7 | CM4: =SUM(AY4:BB4) -> 3100.5 | CN4: =SUM(BC4:BF4) -> 3517.9 | CO4: =SUM(BG4:BJ4) -> 4276.6 | CP4: =SUM(BK4:BN4) -> 5079 | CQ4: =SUM(BO4:BR4) -> 6018.9 | CR4: =CQ4*(1+CR9) -> 7102.302 | CS4: =CR4*(1+CS9) -> 8096.6243 | CT4: =CS4*(1+CT9) -> 9149.1854 | CU4: =CT4*(1+CU9) -> 10247.088 | CV4: =CU4*(1+CV9) -> 11374.267 | CW4: =CV4*(1+CW9) -> 12511.694 | CX4: =CW4*(1+CX9) -> 13637.747 | CY4: =CX4*(1+CY9) -> 14592.389 | ... DA4: =CZ4*(1+DA9) -> 16473.348
B5: Systems | AU5: 283.3 | AV5: 261 | AW5: 267.8 | AX5: =1178.9-SUM(AU5:AW5) -> 366.8 | AY5: 368.7 | AZ5: 439.6 | BA5: 415.2 | BB5: =1693.4-SUM(AY5:BA5) -> 469.9 | BC5: 428.1 | BD5: 375.1 | BE5: 425.9 | BF5: =1680.1-SUM(BC5:BE5) -> 451 | BG5: 427.4 | BH5: 392.7 | BI5: 379.4 | BJ5: =1679.7-SUM(BG5:BI5) -> 480.2 | BK5: 418.2 | BL5: 448.2 | BM5: 445 | BN5: =1966-SUM(BK5:BM5) -> 654.6 | BO5: 522.7 | BP5: =1097.4-BO5 -> 574.7 | BQ5: 590.4 | BR5: 785.9 | BS5: 650.7 | BT5: 685 | BU5: 769.1 | CL5: =SUM(AU5:AX5) -> 1178.9 | CM5: =SUM(AY5:BB5) -> 1693.4 | CN5: =SUM(BC5:BF5) -> 1680.1 | CO5: =SUM(BG5:BJ5) -> 1679.7 | CP5: =SUM(BK5:BN5) -> 1966 | CQ5: =SUM(BO5:BR5) -> 2473.7 | CR5: =CQ5*(1+CR10) -> 2993.177 | CS5: =CR5*(1+CS10) -> 3382.29 | CT5: =CS5*(1+CT10) -> 3788.1648 | CU5: =CT5*(1+CU10) -> 4337.4487 | CV5: =CU5*(1+CV10) -> 4944.6915 | CW5: =CV5*(1+CW10) -> 5612.2249 | CX5: =CW5*(1+CX10) -> 6229.5696 | CY5: =CX5*(1+CY10) -> 6868.1005 | ... DA5: =CZ5*(1+DA10) -> 7899.9038
B6: Services | AU6: 198.7 | AV6: 130.3 | AW6: 179.4 | AX6: =723.8-SUM(AU6:AW6) -> 215.4 | AY6: 217.5 | AZ6: 228 | BA6: 232.7 | BB6: =916.2-SUM(AY6:BA6) -> 238 | BC6: 249.3 | BD6: 251.7 | BE6: 259.9 | BF6: =1024.2-SUM(BC6:BE6) -> 263.3 | BG6: 283.2 | BH6: 287.3 | BI6: 292.9 | BJ6: =1167.8-SUM(BG6:BI6) -> 304.4 | BK6: 313.5 | BL6: 317.3 | BM6: 328.9 | BN6: =1307.1-SUM(BK6:BM6) -> 347.4 | BO6: 363 | BP6: =754.2-BO6 -> 391.2 | BQ6: 395 | BR6: 423 | BS6: 433.7 | BT6: 472.4 | BU6: 482.2 | CL6: =SUM(AU6:AX6) -> 723.8 | CM6: =SUM(AY6:BB6) -> 916.2 | CN6: =SUM(BC6:BF6) -> 1024.2 | CO6: =SUM(BG6:BJ6) -> 1167.8 | CP6: =SUM(BK6:BN6) -> 1307.1 | CQ6: =SUM(BO6:BR6) -> 1572.2 | CR6: =CQ6*(1+CR11) -> 1823.752 | CS6: =CR6*(1+CS11) -> 2097.3148 | CT6: =CS6*(1+CT11) -> 2401.4254 | CU6: =CT6*(1+CU11) -> 2737.625 | CV6: =CU6*(1+CV11) -> 3107.2044 | CW6: =CV6*(1+CW11) -> 3511.141 | CX6: =CW6*(1+CX11) -> 3897.3665 | CY6: =CX6*(1+CY11) -> 4267.6163 | ... DA6: =CZ6*(1+DA11) -> 4885.8872
B7: Ttl Revenues | AU7: =SUM(AU4:AU6) -> 1099.5 | AV7: =SUM(AV4:AV6) -> 852.1 | AW7: =SUM(AW4:AW6) -> 1077.7 | AX7: =SUM(AX4:AX6) -> 1329.1 | AY7: =SUM(AY4:AY6) -> 1292.1 | AZ7: =SUM(AZ4:AZ6) -> 1464 | BA7: =SUM(BA4:BA6) -> 1403.3 | BB7: =SUM(BB4:BB6) -> 1550.7 | ... BU7: =SUM(BU4:BU6) -> 3048.7 | CL7: =SUM(AU7:AX7) -> 4358.4 | CM7: =SUM(AY7:BB7) -> 5710.1 | CN7: =SUM(BC7:BF7) -> 6222.2 | CO7: =SUM(BG7:BJ7) -> 7124.1 | CP7: =SUM(BK7:BN7) -> 8352.1 | CQ7: =SUM(BO7:BR7) -> 10064.8 | CR7: =SUM(CR4:CR6) -> 11919.231 | CS7: =SUM(CS4:CS6) -> 13576.229 | CT7: =SUM(CT4:CT6) -> 15338.776 | CU7: =SUM(CU4:CU6) -> 17322.161 | CV7: =SUM(CV4:CV6) -> 19426.163 | CW7: =SUM(CW4:CW6) -> 21635.06 | CX7: =SUM(CX4:CX6) -> 23764.683 | CY7: =SUM(CY4:CY6) -> 25728.106 | ... DA7: =SUM(DA4:DA6) -> 29259.139
B9: Instruments & Accessories Growth Y/y | AY9: =AY4/AU4-1 -> 0.14315789 | AZ9: =AZ4/AV4-1 -> 0.72829861 | BA9: =BA4/AW4-1 -> 0.19809675 | BB9: =BB4/AX4-1 -> 0.12839738 | BC9: =BC4/AY4-1 -> 0.1478963 | BD9: =BD4/AZ4-1 -> 0.12418383 | BE9: =BE4/BA4-1 -> 0.15382579 | BF9: =BF4/BB4-1 -> 0.11616042 | ... BU9: =BU4/BQ4-1 -> 0.18343429 | CM9: =CM4/CL4-1 -> 0.26257279 | CN9: =CN4/CM4-1 -> 0.13462345 | CO9: =CO4/CN4-1 -> 0.21566844 | CP9: =CP4/CO4-1 -> 0.18762568 | CQ9: =CQ4/CP4-1 -> 0.18505611 | CR9: 0.18 | CS9: 0.14 | CT9: 0.13 | CU9: 0.12 | CV9: 0.11 | CW9: 0.1 | CX9: 0.09 | CY9: 0.07 | CZ9: 0.065 | DA9: 0.06
B10: Systems Growth Y/y | AY10: =AY5/AU5-1 -> 0.30144723 | AZ10: =AZ5/AV5-1 -> 0.68429119 | BA10: =BA5/AW5-1 -> 0.55041075 | BB10: =BB5/AX5-1 -> 0.28107961 | BC10: =BC5/AY5-1 -> 0.16110659 | BD10: =BD5/AZ5-1 -> -0.14672429 | BE10: =BE5/BA5-1 -> 0.025770713 | BF10: =BF5/BB5-1 -> -0.040221324 | ... BU10: =BU5/BQ5-1 -> 0.30267615 | CM10: =CM5/CL5-1 -> 0.43642378 | CN10: =CN5/CM5-1 -> -0.0078540215 | CO10: =CO5/CN5-1 -> -0.00023808107 | CP10: =CP5/CO5-1 -> 0.1704471 | CQ10: =CQ5/CP5-1 -> 0.25824008 | CR10: 0.21 | CS10: 0.13 | CT10: 0.12 | CU10: 0.145 | CV10: 0.14 | CW10: 0.135 | CX10: 0.11 | CY10: 0.1025 | CZ10: 0.0775 | DA10: 0.0675
B11: Services Growth Y/y | AY11: =AY6/AU6-1 -> 0.094614997 | AZ11: =AZ6/AV6-1 -> 0.74980814 | BA11: =BA6/AW6-1 -> 0.29710145 | BB11: =BB6/AX6-1 -> 0.10492108 | BC11: =BC6/AY6-1 -> 0.1462069 | BD11: =BD6/AZ6-1 -> 0.10394737 | BE11: =BE6/BA6-1 -> 0.1168887 | BF11: =BF6/BB6-1 -> 0.10630252 | ... BU11: =BU6/BQ6-1 -> 0.22075949 | CM11: =CM6/CL6-1 -> 0.26581929 | CN11: =CN6/CM6-1 -> 0.11787819 | CO11: =CO6/CN6-1 -> 0.14020699 | CP11: =CP6/CO6-1 -> 0.11928412 | CQ11: =CQ6/CP6-1 -> 0.20281539 | CR11: 0.16 | CS11: 0.15 | CT11: 0.145 | CU11: 0.14 | CV11: 0.135 | CW11: 0.13 | CX11: 0.11 | CY11: 0.095 | CZ11: 0.075 | DA11: 0.065
B12: Ttl Revenue Growth Y/y | AY12: =AY7/AU7-1 -> 0.17517053 | AZ12: =AZ7/AV7-1 -> 0.7181082 | BA12: =BA7/AW7-1 -> 0.3021249 | BB12: =BB7/AX7-1 -> 0.16672937 | BC12: =BC7/AY7-1 -> 0.15138147 | BD12: =BD7/AZ7-1 -> 0.039685792 | BE12: =BE7/BA7-1 -> 0.10981258 | BF12: =BF7/BB7-1 -> 0.067259947 | ... BU12: =BU7/BQ7-1 -> 0.21743471 | CM12: =CM7/CL7-1 -> 0.31013675 | CN12: =CN7/CM7-1 -> 0.089683193 | CO12: =CO7/CN7-1 -> 0.14494873 | CP12: =CP7/CO7-1 -> 0.17237265 | CQ12: =CQ7/CP7-1 -> 0.2050622 | CR12: =CR7/CQ7-1 -> 0.18424917 | CS12: =CS7/CR7-1 -> 0.13901888 | CT12: =CT7/CS7-1 -> 0.12982593 | ... DA12: =DA7/CZ7-1 -> 0.062849409
B14: Instrument & Acc. % of Ttl Revenues | AU14: =AU4/AU7 -> 0.56161892 | AV14: =AV4/AV7 -> 0.5407816 | AW14: =AW4/AW7 -> 0.58504222 | AX14: =AX4/AX7 -> 0.56195922 | AY14: =AY4/AY7 -> 0.54631994 | AZ14: =AZ4/AZ7 -> 0.54398907 | BA14: =BA4/BA7 -> 0.53830257 | BB14: =BB4/BB7 -> 0.54349649 | ... BU14: =BU4/BU7 -> 0.58956276 | CL14: =CL4/CL7 -> 0.56344071 | CM14: =CM4/CM7 -> 0.54298524 | CN14: =CN4/CN7 -> 0.5653788 | CO14: =CO4/CO7 -> 0.60030039 | CP14: =CP4/CP7 -> 0.60811054 | CQ14: =CQ4/CQ7 -> 0.59801486
B15: Systems % of Ttl Revenues | AU15: =AU5/AU7 -> 0.25766257 | AV15: =AV5/AV7 -> 0.30630208 | AW15: =AW5/AW7 -> 0.24849216 | AX15: =AX5/AX7 -> 0.27597622 | AY15: =AY5/AY7 -> 0.28534943 | AZ15: =AZ5/AZ7 -> 0.30027322 | BA15: =BA5/BA7 -> 0.29587401 | BB15: =BB5/BB7 -> 0.30302444 | ... BU15: =BU5/BU7 -> 0.25227146 | CL15: =CL5/CL7 -> 0.27048917 | CM15: =CM5/CM7 -> 0.29656223 | CN15: =CN5/CN7 -> 0.27001704 | CO15: =CO5/CO7 -> 0.23577715 | CP15: =CP5/CP7 -> 0.2353899 | CQ15: =CQ5/CQ7 -> 0.24577736
B16: Services % of Ttl Revenues | AU16: =AU6/AU7 -> 0.18071851 | AV16: =AV6/AV7 -> 0.15291632 | AW16: =AW6/AW7 -> 0.16646562 | AX16: =AX6/AX7 -> 0.16206455 | AY16: =AY6/AY7 -> 0.16833062 | AZ16: =AZ6/AZ7 -> 0.1557377 | BA16: =BA6/BA7 -> 0.16582342 | BB16: =BB6/BB7 -> 0.15347907 | ... BU16: =BU6/BU7 -> 0.15816578 | CL16: =CL6/CL7 -> 0.16607012 | CM16: =CM6/CM7 -> 0.16045253 | CN16: =CN6/CN7 -> 0.16460416 | CO16: =CO6/CO7 -> 0.16392246 | CP16: =CP6/CP7 -> 0.15649956 | CQ16: =CQ6/CQ7 -> 0.15620777
B18: Ttl Revenues | C18: 188.4 | D18: 260.6 | E18: 280.1 | F18: 323.1 | G18: 328.6 | H18: 350.7 | I18: 344.4 | J18: 389.3 | K18: 388.1 | L18: 425.7 | M18: 446.7 | N18: 496.8 | O18: 495.2 | P18: 536.5 | Q18: 537.8 | R18: 609.3 | S18: 611.4 | T18: 578.5 | U18: 499 | V18: 576.2 | W18: 464.7 | X18: 512.2 | Y18: 550.1 | Z18: 604.7 | AA18: 532.1 | AB18: 586.1 | AC18: 589.7 | AD18: 676.5 | AE18: 594.5 | AF18: 670.1 | AG18: 682.9 | AH18: 759 | AI18: 679.6 | AJ18: 758.8 | AK18: 807.8 | AL18: 892 | AM18: 847.5 | AN18: 909.3 | AO18: 920.9 | AP18: 1046.5 | AQ18: 973.7 | AR18: 1098.9 | AS18: 1128.2 | AT18: 1277.7 | AU18: =AU7 -> 1099.5 | AV18: =AV7 -> 852.1 | AW18: =AW7 -> 1077.7 | AX18: =AX7 -> 1329.1 | AY18: =AY7 -> 1292.1 | AZ18: =AZ7 -> 1464 | BA18: =BA7 -> 1403.3 | BB18: =BB7 -> 1550.7 | ... BU18: =BU7 -> 3048.7 | CA18: =SUM(C18:F18) -> 1052.2 | CB18: =SUM(G18:J18) -> 1413 | CC18: =SUM(K18:N18) -> 1757.3 | CD18: =SUM(O18:R18) -> 2178.8 | CE18: =SUM(S18:V18) -> 2265.1 | CF18: =SUM(W18:Z18) -> 2131.7 | CG18: =SUM(AA18:AD18) -> 2384.4 | CH18: =SUM(AE18:AH18) -> 2706.5 | CI18: =SUM(AI18:AL18) -> 3138.2 | CJ18: =SUM(AM18:AP18) -> 3724.2 | CK18: =SUM(AQ18:AT18) -> 4478.5 | CL18: =SUM(AU18:AX18) -> 4358.4 | CM18: =SUM(AY18:BB18) -> 5710.1 | CN18: =SUM(BC18:BF18) -> 6222.2 | CO18: =SUM(BG18:BJ18) -> 7124.1 | CP18: =SUM(BK18:BN18) -> 8352.1 | CQ18: =SUM(BO18:BR18) -> 10064.8 | CR18: =CR7 -> 11919.231 | CS18: =CS7 -> 13576.229 | CT18: =CT7 -> 15338.776 | CU18: =CU7 -> 17322.161 | CV18: =CV7 -> 19426.163 | CW18: =CW7 -> 21635.06 | CX18: =CX7 -> 23764.683 | CY18: =CY7 -> 25728.106 | ... DA18: =DA7 -> 29259.139
B19: COGS | C19: 59.7 | D19: 70.4 | E19: 81.1 | F19: 89.9 | G19: 88.1 | H19: 93.9 | I19: 93.8 | J19: 107.2 | K19: 109.3 | L19: 119.1 | M19: 121.2 | N19: 133.9 | O19: 139.3 | P19: 150.1 | Q19: 147.7 | R19: 171.4 | S19: 177.1 | T19: 173.3 | U19: 142.3 | V19: 178.2 | W19: 149.3 | X19: 167.8 | Y19: 189.5 | Z19: 211.3 | AA19: 195.3 | AB19: 199.6 | AC19: 193.9 | AD19: 217.7 | AE19: 189.5 | AF19: 199.2 | AG19: 195.9 | AH19: 229 | AI19: 209.8 | AJ19: 228.7 | AK19: 239.7 | AL19: 258 | AM19: 253.7 | AN19: 277 | AO19: 278.6 | AP19: 310.8 | AQ19: 304.1 | AR19: 339.9 | AS19: 342.6 | AT19: 381.7 | AU19: 361.3 | AV19: 349.2 | AW19: 353.4 | AX19: =1497.2-SUM(AU19:AW19) -> 433.3 | AY19: 389.5 | AZ19: 440.3 | BA19: 431.9 | BB19: =1751.6-SUM(AY19:BA19) -> 489.9 | BC19: 478 | BD19: 498.8 | BE19: 505.3 | BF19: =2026.2-SUM(BC19:BE19) -> 544.1 | BG19: 583.2 | BH19: 584 | BI19: 576.5 | BJ19: =2394.6-SUM(BG19:BI19) -> 650.9 | BK19: 645.2 | BL19: 637.2 | BM19: 664.2 | BN19: =2717.9-SUM(BK19:BM19) -> 771.3 | BO19: 795.7 | BP19: 822.1 | BQ19: 842.7 | BR19: 961.9 | BS19: 940.3 | BT19: 931.9 | BU19: 964.4 | CA19: =SUM(C19:F19) -> 301.1 | CB19: =SUM(G19:J19) -> 383 | CC19: =SUM(K19:N19) -> 483.5 | CD19: =SUM(O19:R19) -> 608.5 | CE19: =SUM(S19:V19) -> 670.9 | CF19: =SUM(W19:Z19) -> 717.9 | CG19: =SUM(AA19:AD19) -> 806.5 | CH19: =SUM(AE19:AH19) -> 813.6 | CI19: =SUM(AI19:AL19) -> 936.2 | CJ19: =SUM(AM19:AP19) -> 1120.1 | CK19: =SUM(AQ19:AT19) -> 1368.3 | CL19: =SUM(AU19:AX19) -> 1497.2 | CM19: =SUM(AY19:BB19) -> 1751.6 | CN19: =SUM(BC19:BF19) -> 2026.2 | CO19: =SUM(BG19:BJ19) -> 2394.6 | CP19: =SUM(BK19:BN19) -> 2717.9 | CQ19: =SUM(BO19:BR19) -> 3422.4 | CR19: =CR18*(1-CR33) -> 3921.427 | CS19: =CS18*(1-CS33) -> 4507.3081 | CT19: =CT18*(1-CT33) -> 5061.796 | CU19: =CU18*(1-CU33) -> 5698.9911 | CV19: =CV18*(1-CV33) -> 6371.7815 | CW19: =CW18*(1-CW33) -> 7053.0295 | CX19: =CX18*(1-CX33) -> 7723.5218 | CY19: =CY18*(1-CY33) -> 8361.6343 | ... DA19: =DA18*(1-DA33) -> 9509.2201
B20: GP | C20: =C18-C19 -> 128.7 | D20: =D18-D19 -> 190.2 | E20: =E18-E19 -> 199 | F20: =F18-F19 -> 233.2 | G20: =G18-G19 -> 240.5 | H20: =H18-H19 -> 256.8 | I20: =I18-I19 -> 250.6 | J20: =J18-J19 -> 282.1 | ... BU20: =BU18-BU19 -> 2084.3 | CA20: =SUM(C20:F20) -> 751.1 | CB20: =SUM(G20:J20) -> 1030 | CC20: =SUM(K20:N20) -> 1273.8 | CD20: =SUM(O20:R20) -> 1570.3 | CE20: =SUM(S20:V20) -> 1594.2 | CF20: =SUM(W20:Z20) -> 1413.8 | CG20: =SUM(AA20:AD20) -> 1577.9 | CH20: =SUM(AE20:AH20) -> 1892.9 | CI20: =SUM(AI20:AL20) -> 2202 | CJ20: =SUM(AM20:AP20) -> 2604.1 | CK20: =SUM(AQ20:AT20) -> 3110.2 | CL20: =SUM(AU20:AX20) -> 2861.2 | CM20: =SUM(AY20:BB20) -> 3958.5 | CN20: =SUM(BC20:BF20) -> 4196 | CO20: =SUM(BG20:BJ20) -> 4729.5 | CP20: =SUM(BK20:BN20) -> 5634.2 | CQ20: =SUM(BO20:BR20) -> 6642.4 | CR20: =CR18*CR33 -> 7997.804 | CS20: =CS18*CS33 -> 9068.921 | CT20: =CT18*CT33 -> 10276.98 | CU20: =CU18*CU33 -> 11623.17 | CV20: =CV18*CV33 -> 13054.382 | CW20: =CW18*CW33 -> 14582.03 | CX20: =CX18*CX33 -> 16041.161 | CY20: =CY18*CY33 -> 17366.471 | ... DA20: =DA18*DA33 -> 19749.919
B21: SG&A | C21: 62.4 | D21: 67.3 | E21: 69.9 | F21: 79 | G21: 82.8 | H21: 88.6 | I21: 91.6 | J21: 95.8 | K21: 99.1 | L21: 106.5 | M21: 111.2 | N21: 122 | O21: 124.2 | P21: 120.9 | Q21: 129 | R21: 148.1 | S21: 141.5 | T21: 145.5 | U21: 139.3 | V21: 147.7 | W21: 215.8 | X21: 161.2 | Y21: 154 | Z21: 160 | AA21: 162 | AB21: 163.3 | AC21: 154.9 | AD21: 160.3 | AE21: 172.8 | AF21: 170.8 | AG21: 168 | AH21: 192 | AI21: 202.9 | AJ21: 185.6 | AK21: 204.1 | AL21: 217.9 | AM21: 221.6 | AN21: 259.8 | AO21: 221.4 | AP21: 283.8 | AQ21: 273.4 | AR21: 279.2 | AS21: 284 | AT21: 341.8 | AU21: 308.1 | AV21: 279.1 | AW21: 298.9 | AX21: =1216.3-SUM(AU21:AW21) -> 330.2 | AY21: 326 | AZ21: 350.2 | BA21: 363.3 | BB21: =1466.5-SUM(AY21:BA21) -> 427 | BC21: 391.1 | BD21: 418.4 | BE21: 436.1 | BF21: =1739.9-SUM(BC21:BE21) -> 494.3 | BG21: 480.5 | BH21: 464.3 | BI21: 452 | BJ21: =1963.9-SUM(BG21:BI21) -> 567.1 | BK21: 491.5 | BL21: 525.3 | BM21: 510.6 | BN21: =2140-SUM(BK21:BM21) -> 612.6 | BO21: 563.4 | BP21: 561.2 | BQ21: 573.3 | BR21: 687.1 | BS21: 613.3 | BT21: 617.9 | BU21: 1083.4 | CA21: =SUM(C21:F21) -> 278.6 | CB21: =SUM(G21:J21) -> 358.8 | CC21: =SUM(K21:N21) -> 438.8 | CD21: =SUM(O21:R21) -> 522.2 | CE21: =SUM(S21:V21) -> 574 | CF21: =SUM(W21:Z21) -> 691 | CG21: =SUM(AA21:AD21) -> 640.5 | CH21: =SUM(AE21:AH21) -> 703.6 | CI21: =SUM(AI21:AL21) -> 810.5 | CJ21: =SUM(AM21:AP21) -> 986.6 | CK21: =SUM(AQ21:AT21) -> 1178.4 | CL21: =SUM(AU21:AX21) -> 1216.3 | CM21: =SUM(AY21:BB21) -> 1466.5 | CN21: =SUM(BC21:BF21) -> 1739.9 | CO21: =SUM(BG21:BJ21) -> 1963.9 | CP21: =SUM(BK21:BN21) -> 2140 | CQ21: =SUM(BO21:BR21) -> 2385 | CR21: =CR18*CR34 -> 2598.3924 | CS21: =CS18*CS34 -> 2932.4655 | CT21: =CT18*CT34 -> 3297.8368 | CU21: =CU18*CU34 -> 3706.9425 | CV21: =CV18*CV34 -> 4137.7728 | CW21: =CW18*CW34 -> 4586.6327 | CX21: =CX18*CX34 -> 5014.348 | CY21: =CY18*CY34 -> 5402.9022 | ... DA21: =DA18*DA34 -> 6144.4191
B22: R&D | C22: 21.3 | D22: 23.4 | E22: 24.6 | F22: 25.8 | G22: 28 | H22: 28.5 | I22: 26.9 | J22: 32.6 | K22: 31.4 | L22: 32 | M22: 35.4 | N22: 41.4 | O22: 38.4 | P22: 40.2 | Q22: 49.7 | R22: 41.7 | S22: 41.6 | T22: 41.2 | U22: 43.2 | V22: 41.7 | W22: 43 | X22: 40.2 | Y22: 47.5 | Z22: 47.3 | AA22: 44.4 | AB22: 49.4 | AC22: 51 | AD22: 52.6 | AE22: 53.2 | AF22: 54.7 | AG22: 62.6 | AH22: 69.1 | AI22: 73.5 | AJ22: 84.6 | AK22: 83.4 | AL22: 87.1 | AM22: 95.5 | AN22: 95.1 | AO22: 107.6 | AP22: 119.9 | AQ22: 144 | AR22: 120.8 | AS22: 135.9 | AT22: 156.6 | AU22: 147.1 | AV22: 143.2 | AW22: 155 | AX22: =595.1-SUM(AU22:AW22) -> 149.8 | AY22: 159.8 | AZ22: 162.3 | BA22: 165.5 | BB22: =671-SUM(AY22:BA22) -> 183.4 | BC22: 210.5 | BD22: 207.3 | BE22: 217.1 | BF22: =879-SUM(BC22:BE22) -> 244.1 | BG22: 244.9 | BH22: 244.4 | BI22: 249.4 | BJ22: =998.8-SUM(BG22:BI22) -> 260.1 | BK22: 284.5 | BL22: 280.1 | BM22: 286 | BN22: =1145.3-SUM(BK22:BM22) -> 294.7 | BO22: 316.2 | BP22: 313.3 | BQ22: 329.1 | BR22: 352 | BS22: 361.9 | BT22: 370.6 | BU22: 408.3 | CA22: =SUM(C22:F22) -> 95.1 | CB22: =SUM(G22:J22) -> 116 | CC22: =SUM(K22:N22) -> 140.2 | CD22: =SUM(O22:R22) -> 170 | CE22: =SUM(S22:V22) -> 167.7 | CF22: =SUM(W22:Z22) -> 178 | CG22: =SUM(AA22:AD22) -> 197.4 | CH22: =SUM(AE22:AH22) -> 239.6 | CI22: =SUM(AI22:AL22) -> 328.6 | CJ22: =SUM(AM22:AP22) -> 418.1 | CK22: =SUM(AQ22:AT22) -> 557.3 | CL22: =SUM(AU22:AX22) -> 595.1 | CM22: =SUM(AY22:BB22) -> 671 | CN22: =SUM(BC22:BF22) -> 879 | CO22: =SUM(BG22:BJ22) -> 998.8 | CP22: =SUM(BK22:BN22) -> 1145.3 | CQ22: =SUM(BO22:BR22) -> 1310.6 | CR22: =CR18*CR35 -> 1549.5 | CS22: =CS18*CS35 -> 1792.0622 | CT22: =CT18*CT35 -> 1994.0408 | CU22: =CU18*CU35 -> 2234.5588 | CV22: =CV18*CV35 -> 2486.5489 | CW22: =CW18*CW35 -> 2747.6526 | CX22: =CX18*CX35 -> 2994.35 | CY22: =CY18*CY35 -> 3216.0132 | ... DA22: =DA18*DA35 -> 3657.3923
B23: Operating Income | C23: =C20-SUM(C21:C22) -> 45 | D23: =D20-SUM(D21:D22) -> 99.5 | E23: =E20-SUM(E21:E22) -> 104.5 | F23: =F20-SUM(F21:F22) -> 128.4 | G23: =G20-SUM(G21:G22) -> 129.7 | H23: =H20-SUM(H21:H22) -> 139.7 | I23: =I20-SUM(I21:I22) -> 132.1 | J23: =J20-SUM(J21:J22) -> 153.7 | ... BU23: =BU20-SUM(BU21:BU22) -> 592.6 | CA23: =SUM(C23:F23) -> 377.4 | CB23: =SUM(G23:J23) -> 555.2 | CC23: =SUM(K23:N23) -> 694.8 | CD23: =SUM(O23:R23) -> 878.1 | CE23: =SUM(S23:V23) -> 852.5 | CF23: =SUM(W23:Z23) -> 544.8 | CG23: =SUM(AA23:AD23) -> 740 | CH23: =SUM(AE23:AH23) -> 949.7 | CI23: =SUM(AI23:AL23) -> 1062.9 | CJ23: =SUM(AM23:AP23) -> 1199.4 | CK23: =SUM(AQ23:AT23) -> 1374.5 | CL23: =SUM(AU23:AX23) -> 1049.8 | CM23: =SUM(AY23:BB23) -> 1821 | CN23: =SUM(BC23:BF23) -> 1577.1 | CO23: =SUM(BG23:BJ23) -> 1766.8 | CP23: =SUM(BK23:BN23) -> 2348.9 | CQ23: =SUM(BO23:BR23) -> 2946.8 | CR23: =CR20-SUM(CR21:CR22) -> 3849.9116 | CS23: =CS20-SUM(CS21:CS22) -> 4344.3933 | CT23: =CT20-SUM(CT21:CT22) -> 4985.1021 | CU23: =CU20-SUM(CU21:CU22) -> 5681.6689 | CV23: =CV20-SUM(CV21:CV22) -> 6430.06 | CW23: =CW20-SUM(CW21:CW22) -> 7247.7451 | CX23: =CX20-SUM(CX21:CX22) -> 8032.4627 | CY23: =CY20-SUM(CY21:CY22) -> 8747.5559 | ... DA23: =DA20-SUM(DA21:DA22) -> 9948.1072
B24: Interest Income | C24: 5 | D24: 5.2 | E24: 4.3 | F24: 4.2 | G24: 4.1 | H24: 4.5 | I24: 5 | J24: 3.5 | K24: 5.3 | L24: 4.1 | M24: 1.9 | N24: 3.6 | O24: 3.8 | P24: 4 | Q24: 4.3 | R24: 3.7 | S24: 4.3 | T24: 4.3 | U24: 3.9 | V24: 5.9 | W24: 3.9 | X24: -0.4 | Y24: 2 | Z24: -1.3 | AA24: 4.3 | AB24: 4.6 | AC24: 3.7 | AD24: 5.9 | AE24: 5.5 | AF24: 8 | AG24: 10.4 | AH24: 11.7 | AI24: 8.7 | AJ24: 10.1 | AK24: 10.8 | AL24: 12.3 | AM24: 13.2 | AN24: 18.2 | AO24: 21.9 | AP24: 26.8 | AQ24: 27.5 | AR24: 32.8 | AS24: 33.3 | AT24: 34.1 | AU24: 25 | AV24: 26.6 | AW24: 84.8 | AX24: =157.2-SUM(AU24:AW24) -> 20.8 | AY24: 32 | AZ24: 15 | BA24: 18.5 | BB24: =69.3-SUM(AY24:BA24) -> 3.8 | BC24: -5.7 | BD24: 9.3 | BE24: 3.9 | BF24: =29.7-SUM(BC24:BE24) -> 22.2 | BG24: 34.2 | BH24: 36 | BI24: 56.2 | BJ24: =192.1-SUM(BG24:BI24) -> 65.7 | BK24: 69.1 | BL24: 87.2 | BM24: 93.7 | BN24: =324.9-SUM(BK24:BM24) -> 74.9 | BO24: 90.4 | BP24: 88.7 | BQ24: 95.5 | BR24: 91 | BS24: 85.1 | BT24: 82.7 | BU24: 75.8 | CA24: =SUM(C24:F24) -> 18.7 | CB24: =SUM(G24:J24) -> 17.1 | CC24: =SUM(K24:N24) -> 14.9 | CD24: =SUM(O24:R24) -> 15.8 | CE24: =SUM(S24:V24) -> 18.4 | CF24: =SUM(W24:Z24) -> 4.2 | CG24: =SUM(AA24:AD24) -> 18.5 | CH24: =SUM(AE24:AH24) -> 35.6 | CI24: =SUM(AI24:AL24) -> 41.9 | CJ24: =SUM(AM24:AP24) -> 80.1 | CK24: =SUM(AQ24:AT24) -> 127.7 | CL24: =SUM(AU24:AX24) -> 157.2 | CM24: =SUM(AY24:BB24) -> 69.3 | CN24: =SUM(BC24:BF24) -> 29.7 | CO24: =SUM(BG24:BJ24) -> 192.1 | CP24: =SUM(BK24:BN24) -> 324.9 | CQ24: =SUM(BO24:BR24) -> 365.6 | CR24: =CQ40*$DA$43 -> 907.676 | CS24: =CR40*$DA$43 -> 1991.1095 | CT24: =CS40*$DA$43 -> 3425.3407 | CU24: =CT40*$DA$43 -> 5306.6306 | CV24: =CU40*$DA$43 -> 7749.7416 | CW24: =CV40*$DA$43 -> 10883.336 | CX24: =CW40*$DA$43 -> 14890.124 | CY24: =CX40*$DA$43 -> 19955.786 | ... DA24: =CZ40*$DA$43 -> 34179.172
B25: Pretax Income | C25: =C23+C24 -> 50 | D25: =D23+D24 -> 104.7 | E25: =E23+E24 -> 108.8 | F25: =F23+F24 -> 132.6 | G25: =G23+G24 -> 133.8 | H25: =H23+H24 -> 144.2 | I25: =I23+I24 -> 137.1 | J25: =J23+J24 -> 157.2 | ... BU25: =BU23+BU24 -> 668.4 | CA25: =SUM(C25:F25) -> 396.1 | CB25: =SUM(G25:J25) -> 572.3 | CC25: =SUM(K25:N25) -> 709.7 | CD25: =SUM(O25:R25) -> 893.9 | CE25: =SUM(S25:V25) -> 870.9 | CF25: =SUM(W25:Z25) -> 549 | CG25: =SUM(AA25:AD25) -> 758.5 | CH25: =SUM(AE25:AH25) -> 985.3 | CI25: =SUM(AI25:AL25) -> 1104.8 | CJ25: =SUM(AM25:AP25) -> 1279.5 | CK25: =SUM(AQ25:AT25) -> 1502.2 | CL25: =SUM(AU25:AX25) -> 1207 | CM25: =SUM(AY25:BB25) -> 1890.3 | CN25: =SUM(BC25:BF25) -> 1606.8 | CO25: =SUM(BG25:BJ25) -> 1958.9 | CP25: =SUM(BK25:BN25) -> 2673.8 | CQ25: =SUM(BO25:BR25) -> 3312.4 | CR25: =CR23+CR24 -> 4757.5876 | CS25: =CS23+CS24 -> 6335.5028 | CT25: =CT23+CT24 -> 8410.4428 | CU25: =CU23+CU24 -> 10988.299 | CV25: =CV23+CV24 -> 14179.802 | CW25: =CW23+CW24 -> 18131.081 | CX25: =CX23+CX24 -> 22922.586 | CY25: =CY23+CY24 -> 28703.342 | ... DA25: =DA23+DA24 -> 44127.279
B26: Taxes | C26: 21.9 | D26: 42.3 | E26: 44.3 | F26: 55 | G26: 48.5 | H26: 55.5 | I26: 50.5 | J26: 36 | K26: 49.5 | L26: 54.8 | M26: 58.4 | N26: 51.9 | O26: 53.6 | P26: 74.4 | Q26: 32.4 | R26: 76.9 | S26: 66.6 | T26: 63.7 | U26: 21.3 | V26: 48.3 | W26: 16.2 | X26: 38.6 | Y26: 37.4 | Z26: 38 | AA26: 37.7 | AB26: 43.9 | AC26: 26.3 | AD26: 61.8 | AE26: 48.1 | AF26: 68.9 | AG26: 55.8 | AH26: 74.2 | AI26: 21.3 | AJ26: 47 | AK26: -7.2 | AL26: 372.8 | AM26: 2.6 | AN26: 41 | AO26: 43.4 | AP26: 67.5 | AQ26: -24.3 | AR26: 75.4 | AS26: 0.3 | AT26: 69 | AU26: -8 | AV26: 37 | AW26: 38.4 | AX26: =140.2-SUM(AU26:AW26) -> 72.8 | AY26: 13.6 | AZ26: 3.2 | BA26: 73.9 | BB26: =162.2-SUM(AY26:BA26) -> 71.5 | BC26: 33 | BD26: 93.3 | BE26: 78.1 | BF26: =262.4-SUM(BC26:BE26) -> 58 | BG26: 61 | BH26: 73.2 | BI26: 102.2 | BJ26: =141.6-SUM(BG26:BI26) -> -94.8 | BK26: -8.9 | BL26: 123 | BM26: 100.4 | BN26: =336.3-SUM(BK26:BM26) -> 121.8 | BO26: -35.2 | BP26: 167.9 | BQ26: 146 | BR26: 156 | BS26: 114.4 | BT26: 231.4 | BU26: 144 | CA26: =SUM(C26:F26) -> 163.5 | CB26: =SUM(G26:J26) -> 190.5 | CC26: =SUM(K26:N26) -> 214.6 | CD26: =SUM(O26:R26) -> 237.3 | CE26: =SUM(S26:V26) -> 199.9 | CF26: =SUM(W26:Z26) -> 130.2 | CG26: =SUM(AA26:AD26) -> 169.7 | CH26: =SUM(AE26:AH26) -> 247 | CI26: =SUM(AI26:AL26) -> 433.9 | CJ26: =SUM(AM26:AP26) -> 154.5 | CK26: =SUM(AQ26:AT26) -> 120.4 | CL26: =SUM(AU26:AX26) -> 140.2 | CM26: =SUM(AY26:BB26) -> 162.2 | CN26: =SUM(BC26:BF26) -> 262.4 | CO26: =SUM(BG26:BJ26) -> 141.6 | CP26: =SUM(BK26:BN26) -> 336.3 | CQ26: =SUM(BO26:BR26) -> 434.7 | CR26: =CR25*CR37 -> 737.42608 | CS26: =CS25*CS37 -> 1013.6805 | CT26: =CT25*CT37 -> 1429.7753 | CU26: =CU25*CU37 -> 1922.9524 | CV26: =CV25*CV37 -> 2552.3643 | CW26: =CW25*CW37 -> 3263.5946 | CX26: =CX25*CX37 -> 4126.0655 | CY26: =CY25*CY37 -> 5166.6015 | ... DA26: =DA25*DA37 -> 7942.9103
B27: Net Income | C27: =C25-C26 -> 28.1 | D27: =D25-D26 -> 62.4 | E27: =E25-E26 -> 64.5 | F27: =F25-F26 -> 77.6 | G27: =G25-G26 -> 85.3 | H27: =H25-H26 -> 88.7 | I27: =I25-I26 -> 86.6 | J27: =J25-J26 -> 121.2 | ... BU27: =BU25-BU26 -> 524.4 | CA27: =SUM(C27:F27) -> 232.6 | CB27: =SUM(G27:J27) -> 381.8 | CC27: =SUM(K27:N27) -> 495.1 | CD27: =SUM(O27:R27) -> 656.6 | CE27: =SUM(S27:V27) -> 671 | CF27: =SUM(W27:Z27) -> 418.8 | CG27: =SUM(AA27:AD27) -> 588.8 | CH27: =SUM(AE27:AH27) -> 738.3 | CI27: =SUM(AI27:AL27) -> 670.9 | CJ27: =SUM(AM27:AP27) -> 1125 | CK27: =SUM(AQ27:AT27) -> 1381.8 | CL27: =SUM(AU27:AX27) -> 1066.8 | CM27: =SUM(AY27:BB27) -> 1728.1 | CN27: =SUM(BC27:BF27) -> 1344.4 | CO27: =SUM(BG27:BJ27) -> 1817.3 | CP27: =SUM(BK27:BN27) -> 2337.5 | CQ27: =SUM(BO27:BR27) -> 2877.7 | CR27: =CR25-CR26 -> 4020.1615 | CS27: =CS25-CS26 -> 5321.8224 | CT27: =CT25-CT26 -> 6980.6675 | CU27: =CU25-CU26 -> 9065.3471 | CV27: =CV25-CV26 -> 11627.437 | CW27: =CW25-CW26 -> 14867.486 | CX27: =CX25-CX26 -> 18796.521 | CY27: =CY25-CY26 -> 23536.74 | ... DA27: =DA25-DA26 -> 36184.369 | DB27: =DA27*(1+$DA$44) -> 36817.595 | DC27: =DB27*(1+$DA$44) -> 37461.903 | DD27: =DC27*(1+$DA$44) -> 38117.487 | DE27: =DD27*(1+$DA$44) -> 38784.543 | DF27: =DE27*(1+$DA$44) -> 39463.272 | DG27: =DF27*(1+$DA$44) -> 40153.879 | DH27: =DG27*(1+$DA$44) -> 40856.572 | DI27: =DH27*(1+$DA$44) -> 41571.562 | ... EY27: =EX27*(1+$DA$44) -> 86147.345
B28: Less: Joint Venture | AU28: 2.7 | AV28: 2 | AW28: 2.9 | AX28: =6.2-SUM(AU28:AW28) -> -1.4 | AY28: 8.9 | AZ28: 5.8 | BA28: 6.7 | BB28: =23.5-SUM(AY28:BA28) -> 2.1 | BC28: 3.8 | BD28: 5.8 | BE28: 0.7 | BF28: =22.1-SUM(BC28:BE28) -> 11.8 | BG28: 5.5 | BH28: 5.2 | BI28: 4.1 | BJ28: =19.3-SUM(BG28:BI28) -> 4.5 | BK28: 2.5 | BL28: 4.6 | BM28: 5.5 | BN28: =14.9-SUM(BK28:BM28) -> 2.3 | BO28: 5.3 | BP28: 5.8 | BQ28: 4.8 | BR28: 4.7 | BS28: 4.5 | BT28: 5.1 | BU28: 1.6 | CA28: =SUM(C28:F28) -> 0 | CB28: =SUM(G28:J28) -> 0 | CC28: =SUM(K28:N28) -> 0 | CD28: =SUM(O28:R28) -> 0 | CE28: =SUM(S28:V28) -> 0 | CF28: =SUM(W28:Z28) -> 0 | CG28: =SUM(AA28:AD28) -> 0 | CH28: =SUM(AE28:AH28) -> 0 | CI28: =SUM(AI28:AL28) -> 0 | CJ28: =SUM(AM28:AP28) -> 0 | CK28: =SUM(AQ28:AT28) -> 0 | CL28: =SUM(AU28:AX28) -> 6.2 | CM28: =SUM(AY28:BB28) -> 23.5 | CN28: =SUM(BC28:BF28) -> 22.1 | CO28: =SUM(BG28:BJ28) -> 19.3 | CP28: =SUM(BK28:BN28) -> 14.9 | CQ28: =SUM(BO28:BR28) -> 20.6
B29: Attributable Income | C29: =C27-C28 -> 28.1 | D29: =D27-D28 -> 62.4 | E29: =E27-E28 -> 64.5 | F29: =F27-F28 -> 77.6 | G29: =G27-G28 -> 85.3 | H29: =H27-H28 -> 88.7 | I29: =I27-I28 -> 86.6 | J29: =J27-J28 -> 121.2 | ... BU29: =BU27-BU28 -> 522.8 | CA29: =SUM(C29:F29) -> 232.6 | CB29: =SUM(G29:J29) -> 381.8 | CC29: =SUM(K29:N29) -> 495.1 | CD29: =SUM(O29:R29) -> 656.6 | CE29: =SUM(S29:V29) -> 671 | CF29: =SUM(W29:Z29) -> 418.8 | CG29: =SUM(AA29:AD29) -> 588.8 | CH29: =SUM(AE29:AH29) -> 738.3 | CI29: =SUM(AI29:AL29) -> 670.9 | CJ29: =SUM(AM29:AP29) -> 1125 | CK29: =SUM(AQ29:AT29) -> 1381.8 | CL29: =SUM(AU29:AX29) -> 1060.6 | CM29: =SUM(AY29:BB29) -> 1704.6 | CN29: =SUM(BC29:BF29) -> 1322.3 | CO29: =SUM(BG29:BJ29) -> 1798 | CP29: =SUM(BK29:BN29) -> 2322.6 | CQ29: =SUM(BO29:BR29) -> 2857.1
B30: SC | C30: 355 | D30: 355 | E30: 355 | F30: 354 | G30: 354 | H30: 353 | I30: 352 | J30: 352 | K30: 352 | L30: 353 | M30: 352 | N30: 353 | O30: 356 | P30: 359 | Q30: 359 | R30: 358 | S30: 363 | T30: 359 | U30: 347 | V30: 353 | W30: 345 | X30: 332 | Y30: 325 | Z30: 332 | AA30: 330 | AB30: 332 | AC30: 336 | AD30: 334 | AE30: 339 | AF30: 345 | AG30: 348 | AH30: 345 | AI30: 336 | AJ30: 333 | AK30: 335 | AL30: 335 | AM30: 338 | AN30: 341 | AO30: 342 | AP30: 341 | AQ30: 345 | AR30: 346 | AS30: 346 | AT30: 346 | AU30: 349.2 | AV30: 350.4 | AW30: 352 | AX30: 351.1 | AY30: 354.2 | AZ30: 355.7 | BA30: 356.8 | BB30: 356.1 | BC30: 358.4 | BD30: 358.1 | BE30: 355.3 | BF30: 355.7 | BG30: 350.2 | BH30: 350.9 | BI30: 351.7 | BJ30: 351.2 | BK30: 353.5 | BL30: 355 | BM30: 355.8 | BN30: 355.2 | BO30: 357.5 | BP30: 358.5 | BQ30: 356.6 | BR30: 355.13 | BS30: 354.9 | BT30: 354.1 | BU30: 349 | CA30: =AVERAGE(C30:F30) -> 354.75 | CB30: =AVERAGE(G30:J30) -> 352.75 | CC30: =AVERAGE(K30:N30) -> 352.5 | CD30: =AVERAGE(O30:R30) -> 358 | CE30: =AVERAGE(S30:V30) -> 355.5 | CF30: =AVERAGE(W30:Z30) -> 333.5 | CG30: =AVERAGE(AA30:AD30) -> 333 | CH30: =AVERAGE(AE30:AH30) -> 344.25 | CI30: =AVERAGE(AI30:AL30) -> 334.75 | CJ30: =AVERAGE(AM30:AP30) -> 340.5 | CK30: =AVERAGE(AQ30:AT30) -> 345.75 | CL30: =AVERAGE(AU30:AX30) -> 350.675 | CM30: =AVERAGE(AY30:BB30) -> 355.7 | CN30: =AVERAGE(BC30:BF30) -> 356.875 | CO30: =AVERAGE(BG30:BJ30) -> 351 | CP30: =AVERAGE(BK30:BN30) -> 354.875 | CQ30: =AVERAGE(BO30:BR30) -> 356.9325
B31: EPS | C31: =C27/C30 -> 0.07915493 | D31: =D27/D30 -> 0.17577465 | E31: =E27/E30 -> 0.18169014 | F31: =F27/F30 -> 0.21920904 | G31: =G27/G30 -> 0.24096045 | H31: =H27/H30 -> 0.25127479 | I31: =I27/I30 -> 0.24602273 | J31: =J27/J30 -> 0.34431818 | ... BU31: =BU27/BU30 -> 1.5025788 | CA31: =SUM(C31:F31) -> 0.65582876 | CB31: =SUM(G31:J31) -> 1.0825761 | CC31: =SUM(K31:N31) -> 1.4043724 | CD31: =SUM(O31:R31) -> 1.8336987 | CE31: =SUM(S31:V31) -> 1.8862559 | CF31: =SUM(W31:Z31) -> 1.2644429 | CG31: =SUM(AA31:AD31) -> 1.7658388 | CH31: =SUM(AE31:AH31) -> 2.1417252 | CI31: =SUM(AI31:AL31) -> 2.0050783 | CJ31: =SUM(AM31:AP31) -> 3.3040961 | CK31: =SUM(AQ31:AT31) -> 3.9961883 | CL31: =SUM(AU31:AX31) -> 3.04144 | CM31: =SUM(AY31:BB31) -> 4.8589244 | CN31: =SUM(BC31:BF31) -> 3.7668848 | CO31: =SUM(BG31:BJ31) -> 5.1768157 | CP31: =SUM(BK31:BN31) -> 6.5863448 | CQ31: =SUM(BO31:BR31) -> 8.0642869
B33: Gross Profit Margin | C33: =C20/C18 -> 0.68312102 | D33: =D20/D18 -> 0.72985418 | E33: =E20/E18 -> 0.71046055 | F33: =F20/F18 -> 0.72175797 | G33: =G20/G18 -> 0.73189288 | H33: =H20/H18 -> 0.73224979 | I33: =I20/I18 -> 0.72764228 | J33: =J20/J18 -> 0.72463396 | ... BU33: =BU20/BU18 -> 0.68366845 | CL33: =CL20/CL18 -> 0.65647944 | CM33: =CM20/CM18 -> 0.6932453 | CN33: =CN20/CN18 -> 0.67435955 | CO33: =CO20/CO18 -> 0.66387333 | CP33: =CP20/CP18 -> 0.67458483 | CQ33: =CQ20/CQ18 -> 0.65996344 | CR33: 0.671 | CS33: 0.668 | CT33: 0.67 | CU33: 0.671 | CV33: 0.672 | CW33: 0.674 | CX33: 0.675 | CY33: 0.675 | CZ33: 0.675 | DA33: 0.675
B34: SG&A as % of Revenue | C34: =C21/C18 -> 0.33121019 | D34: =D21/D18 -> 0.25825019 | E34: =E21/E18 -> 0.24955373 | F34: =F21/F18 -> 0.24450634 | G34: =G21/G18 -> 0.25197809 | H34: =H21/H18 -> 0.25263758 | I34: =I21/I18 -> 0.2659698 | J34: =J21/J18 -> 0.24608271 | ... BU34: =BU21/BU18 -> 0.35536458 | CL34: =CL21/CL18 -> 0.2790703 | CM34: =CM21/CM18 -> 0.25682562 | CN34: =CN21/CN18 -> 0.27962778 | CO34: =CO21/CO18 -> 0.27566991 | CP34: =CP21/CP18 -> 0.25622299 | CQ34: =CQ21/CQ18 -> 0.23696447 | CR34: 0.218 | CS34: 0.216 | CT34: 0.215 | CU34: 0.214 | CV34: 0.213 | CW34: 0.212 | CX34: 0.211 | CY34: 0.21 | CZ34: 0.21 | DA34: 0.21
B35: R&D as % of Revenue | C35: =C22/C18 -> 0.11305732 | D35: =D22/D18 -> 0.089792786 | E35: =E22/E18 -> 0.087825777 | F35: =F22/F18 -> 0.079851439 | G35: =G22/G18 -> 0.085209982 | H35: =H22/H18 -> 0.081266039 | I35: =I22/I18 -> 0.078106852 | J35: =J22/J18 -> 0.083740046 | ... BU35: =BU22/BU18 -> 0.13392594 | CL35: =CL22/CL18 -> 0.13654093 | CM35: =CM22/CM18 -> 0.11751108 | CN35: =CN22/CN18 -> 0.14126836 | CO35: =CO22/CO18 -> 0.14020017 | CP35: =CP22/CP18 -> 0.13712719 | CQ35: =CQ22/CQ18 -> 0.1302162 | CR35: 0.13 | CS35: 0.132 | CT35: 0.13 | CU35: 0.129 | CV35: 0.128 | CW35: 0.127 | CX35: 0.126 | CY35: 0.125 | CZ35: 0.125 | DA35: 0.125
B36: Operating Profit Margin | C36: =C23/C18 -> 0.2388535 | D36: =D23/D18 -> 0.3818112 | E36: =E23/E18 -> 0.37308104 | F36: =F23/F18 -> 0.39740019 | G36: =G23/G18 -> 0.39470481 | H36: =H23/H18 -> 0.39834616 | I36: =I23/I18 -> 0.38356562 | J36: =J23/J18 -> 0.3948112 | ... BU36: =BU23/BU18 -> 0.19437793 | CL36: =CL23/CL18 -> 0.24086821 | CM36: =CM23/CM18 -> 0.3189086 | CN36: =CN23/CN18 -> 0.25346341 | CO36: =CO23/CO18 -> 0.24800326 | CP36: =CP23/CP18 -> 0.28123466 | CQ36: =CQ23/CQ18 -> 0.29278277 | CR36: =CR23/CR18 -> 0.323 | CS36: =CS23/CS18 -> 0.32 | ... DA36: =DA23/DA18 -> 0.34
B37: Effective Tax Rate | C37: =C26/C25 -> 0.438 | D37: =D26/D25 -> 0.40401146 | E37: =E26/E25 -> 0.40716912 | F37: =F26/F25 -> 0.4147813 | G37: =G26/G25 -> 0.36248132 | H37: =H26/H25 -> 0.38488211 | I37: =I26/I25 -> 0.36834427 | J37: =J26/J25 -> 0.22900763 | ... BU37: =BU26/BU25 -> 0.21543986 | CL37: =CL26/CL25 -> 0.11615576 | CM37: =CM26/CM25 -> 0.085806486 | CN37: =CN26/CN25 -> 0.16330595 | CO37: =CO26/CO25 -> 0.072285466 | CP37: =CP26/CP25 -> 0.12577605 | CQ37: =CQ26/CQ25 -> 0.13123415 | CR37: 0.155 | CS37: 0.16 | CT37: 0.17 | CU37: 0.175 | CV37: 0.18 | CW37: 0.18 | CX37: 0.18 | CY37: 0.18 | CZ37: 0.18 | DA37: 0.18
B38: Net Profit Margin | C38: =C27/C18 -> 0.14915074 | D38: =D27/D18 -> 0.23944743 | E38: =E27/E18 -> 0.2302749 | F38: =F27/F18 -> 0.24017332 | G38: =G27/G18 -> 0.25958612 | H38: =H27/H18 -> 0.25292273 | I38: =I27/I18 -> 0.2514518 | J38: =J27/J18 -> 0.31132802 | ... BU38: =BU27/BU18 -> 0.17200774 | CL38: =CL27/CL18 -> 0.24476872 | CM38: =CM27/CM18 -> 0.30263918 | CN38: =CN27/CN18 -> 0.21606506 | CO38: =CO27/CO18 -> 0.25509187 | CP38: =CP27/CP18 -> 0.27986973 | CQ38: =CQ27/CQ18 -> 0.28591726 | CR38: =CR27/CR18 -> 0.33728363 | CS38: =CS27/CS18 -> 0.39199562 | ... DA38: =DA27/DA18 -> 1.2366861
B40: Cash & CEs | AY40: 1401.8 | AZ40: 1615.5 | BA40: 1346.7 | BB40: 1290.9 | BC40: 1103.1 | BD40: 1536.1 | BE40: 1538 | BF40: 1581.2 | BG40: 2143 | BH40: 3435.4 | BI40: 3602 | BJ40: 2750.1 | BK40: 2839.5 | BL40: 3036.7 | BM40: 2413.3 | BN40: 2027.4 | BO40: 2573.8 | BP40: 3403.1 | BQ40: 2806.6 | BR40: 3368 | BS40: 2006.5 | BT40: 2760.4 | BU40: 2978.1 | CM40: =BB40 -> 1290.9 | CN40: =BF40 -> 1581.2 | CO40: =BJ40 -> 2750.1 | CP40: =BN40 -> 2027.4 | CQ40: =BR40 -> 3368 | CR40: =CQ40+CR27 -> 7388.1615 | CS40: =CR40+CS27 -> 12709.984 | CT40: =CS40+CT27 -> 19690.651 | CU40: =CT40+CU27 -> 28755.999 | CV40: =CU40+CV27 -> 40383.436 | CW40: =CV40+CW27 -> 55250.922 | CX40: =CW40+CX27 -> 74047.443 | CY40: =CX40+CY27 -> 97584.183 | ... DA40: =CZ40+DA27 -> 163008.75
B41: ST Investments | AY41: 3155.7 | AZ41: 2823.7 | BA41: 2741.5 | BB41: 2913 | BC41: 2882.5 | BD41: 2901.3 | BE41: 2775.9 | BF41: 2536.7 | BG41: 2549.2 | BH41: 2363.8 | BI41: 2873.7 | BJ41: 2473.1 | BK41: 1960.6 | BL41: 1720.5 | BM41: 1818.4 | BN41: 1985.9 | BO41: 1937.5 | BP41: 1923.4 | BQ41: 2102.2 | BR41: 2566.9 | BS41: 2510.8 | BT41: 2455.8 | BU41: 1064.4 | CM41: =BB41 -> 2913 | CN41: =BF41 -> 2536.7 | CO41: =BJ41 -> 2473.1 | CP41: =BN41 -> 1985.9 | CQ41: =BR41 -> 2566.9
B42: A/R | AY42: 654.3 | AZ42: 699.9 | BA42: 695 | BB42: 782.7 | BC42: 906.1 | BD42: 838.5 | BE42: 849.6 | BF42: 942.1 | BG42: 925.3 | BH42: 904.2 | BI42: 962.7 | BJ42: 1130 | BK42: 1127.9 | BL42: 1109.1 | BM42: 1153 | BN42: 1225.4 | BO42: 1221.5 | BP42: 1269.2 | BQ42: 1259.7 | BR42: 1527.3 | BS42: 1595.6 | BT42: 1673.2 | BU42: 1721.3 | CM42: =BB42 -> 782.7 | CN42: =BF42 -> 942.1 | CO42: =BJ42 -> 1130 | CP42: =BN42 -> 1225.4 | CQ42: =BR42 -> 1527.3
B43: Inventories | AY43: 576.8 | AZ43: 569.7 | BA43: 584.9 | BB43: 587.1 | BC43: 653 | BD43: 724 | BE43: 837.1 | BF43: 893.2 | BG43: 946.6 | BH43: 1005.2 | BI43: 1147.5 | BJ43: 1220.6 | BK43: 1299.3 | BL43: 1383.9 | BM43: 1481.7 | BN43: 1487.2 | BO43: 1553.6 | BP43: 1667 | BQ43: 1781.9 | BR43: 1840 | BS43: 1945.1 | BT43: 2028.7 | BU43: 2128.2 | CM43: =BB43 -> 587.1 | CN43: =BF43 -> 893.2 | CO43: =BJ43 -> 1220.6 | CP43: =BN43 -> 1487.2 | CQ43: =BR43 -> 1840 | CS43: Invested Capital | CV43: Avg. (2023-2024) | CX43: Projected ROIC: | CZ43: ROIC | DA43: 0.2695
B44: Prepaid Expenses | AY44: 277.8 | AZ44: 307.8 | BA44: 359.9 | BB44: 271 | BC44: 258.5 | BD44: 292.6 | BE44: 292.5 | BF44: 299.8 | BG44: 312.9 | BH44: 323.2 | BI44: 317 | BJ44: 314 | BK44: 405.4 | BL44: 404.1 | BM44: 349.2 | BN44: 385.1 | BO44: 371.4 | BP44: 483.2 | BQ44: 574.9 | BR44: 477.3 | BS44: 751.5 | BT44: 624.6 | BU44: 536.3 | CM44: =BB44 -> 271 | CN44: =BF44 -> 299.8 | CO44: =BJ44 -> 314 | CP44: =BN44 -> 385.1 | CQ44: =BR44 -> 477.3 | CS44: 2023 | CT44: 2024 | CV44: 2023-2024 | CX44: 2025 | CZ44: Terminal | DA44: 0.0175
B45: PP&E | AY45: 1592.9 | AZ45: 1651.2 | BA45: 1737.9 | BB45: 1876.4 | BC45: 1968 | BD45: 2109.3 | BE45: 2243.7 | BF45: 2374.2 | BG45: 2580.2 | BH45: 2830.8 | BI45: 3077 | BJ45: 3537.6 | BK45: 3799.6 | BL45: 4116.8 | BM45: 4433 | BN45: 4646.6 | BO45: 4799 | BP45: 4985.3 | BQ45: 5150.9 | BR45: 5342.4 | BS45: 5447.9 | BT45: 5551.5 | BU45: 5676.2 | CM45: =BB45 -> 1876.4 | CN45: =BF45 -> 2374.2 | CO45: =BJ45 -> 3537.6 | CP45: =BN45 -> 4646.6 | CQ45: =BR45 -> 5342.4 | CS45: =SUM(CO40:CO43)-CO51+CO45+CO48 -> 11908.1 | CT45: =SUM(CP40:CP43)-CP51+CP45+CP48 -> 12300.5 | CV45: =AVERAGE(CS45:CT45) -> 12104.3 | CX45: =AVERAGE(CR23)*(1-CR37) -> 3253.1753 | CZ45: RFR (10-year yield) | DA45: =CV54 -> 0.0517
B46: LT Investments | AY46: 2673 | AZ46: 3295.6 | BA46: 4131.5 | BB46: 4415.5 | BC46: 4416.2 | BD46: 3738 | BE46: 3078.1 | BF46: 2623.6 | BG46: 1886.4 | BH46: 1332.5 | BI46: 1044.9 | BJ46: 2120 | BK46: 2522.6 | BL46: 2925.9 | BM46: 4079.8 | BN46: 4819.1 | BO46: 4589.9 | BP46: 4206 | BQ46: 3523.7 | BR46: 3099.2 | BS46: 3461.9 | BT46: 3409.3 | BU46: 2757.9 | CM46: =BB46 -> 4415.5 | CN46: =BF46 -> 2623.6 | CO46: =BJ46 -> 2120 | CP46: =BN46 -> 4819.1 | CQ46: =BR46 -> 3099.2 | CX46: =CX45/CV45 -> 0.26876195 | CZ46: ERP (Avg. market return - (less) RFR) | DA46: =11.35%-DA45 -> 0.0618
B47: Deferred Tax Assets | AY47: 336.6 | AZ47: 394.4 | BA47: 411.5 | BB47: 441.4 | BC47: 485 | BD47: 515.9 | BE47: 587.4 | BF47: 664.6 | BG47: 644.7 | BH47: 666.5 | BI47: 701.4 | BJ47: 910.5 | BK47: 917.8 | BL47: 946.9 | BM47: 997 | BN47: 1045.1 | BO47: 1038.6 | BP47: 1070.3 | BQ47: 978.9 | BR47: 1018.6 | BS47: 683.8 | BT47: 652.4 | BU47: 719.7 | CM47: =BB47 -> 441.4 | CN47: =BF47 -> 664.6 | CO47: =BJ47 -> 910.5 | CP47: =BN47 -> 1045.1 | CQ47: =BR47 -> 1018.6 | CS47: Capital Structure | CZ47: Equity β (1-year avg.) | DA47: ='Notes | Quant Analysis'!T216 -> 1.3586619
B48: Intangible & Other Assets | AY48: =527+344.5 -> 871.5 | AZ48: =594.9+344.3 -> 939.2 | BA48: =581.4+344.3 -> 925.7 | BB48: =633+343.6 -> 976.6 | BC48: =662+343 -> 1005 | BD48: =700+349 -> 1049 | BE48: =710+348 -> 1058 | BF48: =710.1+348.5 -> 1058.6 | BG48: =716.3+348.6 -> 1064.9 | BH48: =693.1+348.6 -> 1041.7 | BI48: =638.4+348.1 -> 986.5 | BJ48: =636.7+348.7 -> 985.4 | BK48: =607.1+348.2 -> 955.3 | BL48: =658+348 -> 1006 | BM48: =669.7+348.3 -> 1018 | BN48: =773.9+347.5 -> 1121.4 | BO48: =787.6+347.5 -> 1135.1 | BP48: =807+348.7 -> 1155.7 | BQ48: =824.9+348.1 -> 1173 | BR48: =848.7+370.3 -> 1219 | BS48: =1094.7+613.2 -> 1707.9 | BT48: =1140.1+580.6 -> 1720.7 | BU48: =1209.2+557.8 -> 1767 | CM48: =BB48 -> 976.6 | CN48: =BF48 -> 1058.6 | CO48: =BJ48 -> 985.4 | CP48: =BN48 -> 1121.4 | CQ48: =BR48 -> 1219 | CS48: Mkt Cap | CV48: =Main!C7 -> 142161.66 | CZ48: Discount (Cost of Equity) | DA48: =+DA45+(DA46*DA47) -> 0.13566531
B49: Ttl Assets | AY49: =SUM(AY40:AY48) -> 11540.4 | AZ49: =SUM(AZ40:AZ48) -> 12297 | BA49: =SUM(BA40:BA48) -> 12934.6 | BB49: =SUM(BB40:BB48) -> 13554.6 | BC49: =SUM(BC40:BC48) -> 13677.4 | BD49: =SUM(BD40:BD48) -> 13704.7 | BE49: =SUM(BE40:BE48) -> 13260.3 | BF49: =SUM(BF40:BF48) -> 12974 | ... BU49: =SUM(BU40:BU48) -> 19349.1 | CM49: =BB49 -> 13554.6 | CN49: =BF49 -> 12974 | CO49: =BJ49 -> 15441.3 | CP49: =BN49 -> 18743.2 | CQ49: =BR49 -> 20458.7 | CS49: Debt to Ttl Mkt Cap | CV49: =Main!C9/(Main!C9+CV48) -> 0
CS50: Mkt Equity to Ttl Mkt Cap | CV50: =CV48/(CV48+Main!C9) -> 1 | CZ50: NPV | DA50: =NPV(DA48,CR27:EY27) -> 153583.38
B51: A/P | AY51: 103.1 | AZ51: 117.9 | BA51: 120 | BB51: 121.2 | BC51: 128 | BD51: 149.7 | BE51: 164.2 | BF51: 147 | BG51: 164.1 | BH51: 199.7 | BI51: 196.2 | BJ51: 188.7 | BK51: 194.4 | BL51: 194.4 | BM51: 218.7 | BN51: 193.4 | BO51: 276.2 | BP51: 266.8 | BQ51: 291.2 | BR51: 255.1 | BS51: 332.9 | BT51: 277.2 | BU51: 279.5 | CM51: =BB51 -> 121.2 | CN51: =BF51 -> 147 | CO51: =BJ51 -> 188.7 | CP51: =BN51 -> 193.4 | CQ51: =BR51 -> 255.1 | CS51: Debt / Equity | CV51: =CV49/CV50 -> 0 | CZ51: SC | DA51: =Main!C6 -> 349
B52: Accrued Compensation | AY52: 194.8 | AZ52: 254 | BA52: 265 | BB52: 350 | BC52: 219.8 | BD52: 278.6 | BE52: 308 | BF52: 401.6 | BG52: 260.9 | BH52: 346.6 | BI52: 374.8 | BJ52: 436.4 | BK52: 238.4 | BL52: 321.3 | BM52: 377.5 | BN52: 535.6 | BO52: 309.7 | BP52: 420.8 | BQ52: 455.5 | BR52: 648.4 | BS52: 370.7 | BT52: 425.7 | BU52: 505.9 | CM52: =BB52 -> 350 | CN52: =BF52 -> 401.6 | CO52: =BJ52 -> 436.4 | CP52: =BN52 -> 535.6 | CQ52: =BR52 -> 648.4 | CZ52: FV | DA52: =DA50/DA51 -> 440.067
B53: Deffered Revenues | AY53: 358.1 | AZ53: 360 | BA53: 348.5 | BB53: 377.2 | BC53: 386 | BD53: 376.3 | BE53: 358.9 | BF53: 397.3 | BG53: 417.8 | BH53: 405.2 | BI53: 394.8 | BJ53: 446.1 | BK53: 437.5 | BL53: 433.9 | BM53: 426 | BN53: 468.8 | BO53: 496.3 | BP53: 499.9 | BQ53: 491.1 | BR53: 506.7 | BS53: 559.5 | BT53: 549.4 | BU53: 541.2 | CM53: =BB53 -> 377.2 | CN53: =BF53 -> 397.3 | CO53: =BJ53 -> 446.1 | CP53: =BN53 -> 468.8 | CQ53: =BR53 -> 506.7 | CS53: Cost of Equity | CZ53: CP | DA53: =Main!C5 -> 407.34
B54: Other ST Liabilities | AY54: 248.6 | AZ54: 272.7 | BA54: 293.5 | BB54: 301 | BC54: 378.3 | BD54: 370.4 | BE54: 402.1 | BF54: 476.2 | BG54: 464.6 | BH54: 586.9 | BI54: 710.6 | BJ54: 587.5 | BK54: 504.8 | BL54: 537.9 | BM54: 654.6 | BN54: 547.5 | BO54: 455.9 | BP54: 505.1 | BQ54: 565.4 | BR54: 596 | BS54: 647.9 | BT54: 670.6 | BU54: 1206.4 | CM54: =BB54 -> 301 | CN54: =BF54 -> 476.2 | CO54: =BJ54 -> 587.5 | CP54: =BN54 -> 547.5 | CQ54: =BR54 -> 596 | CS54: RFR (10-year yield) | CV54: 0.0517 | CZ54: Change Δ | DA54: =DA52/DA53-1 -> 0.080343191 | DB54: =IF(DA54>0,"Upside","Downside") -> Upside
B55: LT Liabilities | AY55: 445.6 | AZ55: 412.9 | BA55: 447.8 | BB55: 453.7 | BC55: 409.3 | BD55: 447.8 | BE55: 453.4 | BF55: 439.3 | BG55: 451.6 | BH55: 405.2 | BI55: 412.8 | BJ55: 385.5 | BK55: 406.5 | BL55: 365.9 | BM55: 389.1 | BN55: 468.3 | BO55: 474.6 | BP55: 517.5 | BQ55: 506.5 | BR55: 510.8 | BS55: 602.8 | BT55: 656 | BU55: 698.3 | CM55: =BB55 -> 453.7 | CN55: =BF55 -> 439.3 | CO55: =BJ55 -> 385.5 | CP55: =BN55 -> 468.3 | CQ55: =BR55 -> 510.8 | CS55: Equity β (1-year avg.) | CV55: 1.21 | CZ55: {=_xlfn.IFS(DA54>=25%,"Strong Buy",DA54>=10.00001%,"Buy",AND(DA54<=10%,DA54>=-4.9999%),"Hold",AND(DA54<=-5%,DA54>=-14.999999%),"Sell",DA54<=-15%,"Strong Sell")} -> Hold
B56: Ttl Liabilities | AY56: =SUM(AY51:AY55) -> 1350.2 | AZ56: =SUM(AZ51:AZ55) -> 1417.5 | BA56: =SUM(BA51:BA55) -> 1474.8 | BB56: =SUM(BB51:BB55) -> 1603.1 | BC56: =SUM(BC51:BC55) -> 1521.4 | BD56: =SUM(BD51:BD55) -> 1622.8 | BE56: =SUM(BE51:BE55) -> 1686.6 | BF56: =SUM(BF51:BF55) -> 1861.4 | ... BU56: =SUM(BU51:BU55) -> 3231.3 | CM56: =BB56 -> 1603.1 | CN56: =BF56 -> 1861.4 | CO56: =BJ56 -> 2044.2 | CP56: =BN56 -> 2213.6 | CQ56: =BR56 -> 2517 | CS56: Market Return(1-year avg.) | CV56: 0.16
B57: SE | AY57: 10190.2 | AZ57: 10879.5 | BA57: 11460 | BB57: 11951.5 | BC57: 12156 | BD57: 12082.4 | BE57: 11573 | BF57: 11112.6 | BG57: 11294.4 | BH57: 11959.7 | BI57: 12623.5 | BJ57: 13397 | BK57: 14046 | BL57: 14796.5 | BM57: 15677.5 | BN57: 16529.6 | BO57: 17207 | BP57: 17953.1 | BQ57: 17042 | BR57: 17941.7 | BS57: 17597.2 | BT57: 18297.7 | BU57: 16117.8 | CM57: =BB57 -> 11951.5 | CN57: =BF57 -> 11112.6 | CO57: =BJ57 -> 13397 | CP57: =BN57 -> 16529.6 | CQ57: =BR57 -> 17941.7 | CS57: Cost of Equity | CV57: =(CV54+CV55)*(CV56-CV54) -> 0.13664211
B58: Ttl L + SE | AY58: =AY56+AY57 -> 11540.4 | AZ58: =AZ56+AZ57 -> 12297 | BA58: =BA56+BA57 -> 12934.8 | BB58: =BB56+BB57 -> 13554.6 | BC58: =BC56+BC57 -> 13677.4 | BD58: =BD56+BD57 -> 13705.2 | BE58: =BE56+BE57 -> 13259.6 | BF58: =BF56+BF57 -> 12974 | ... BU58: =BU56+BU57 -> 19349.1 | CM58: =BB58 -> 13554.6 | CN58: =BF58 -> 12974 | CO58: =BJ58 -> 15441.2 | CP58: =BN58 -> 18743.2 | CQ58: =BR58 -> 20458.7
CS59: Cost of Debt
B60: Current Ratio | AY60: =SUM(AY40:AY44)/SUM(AY51:AY53) -> 9.247561 | AZ60: =SUM(AZ40:AZ44)/SUM(AZ51:AZ53) -> 8.2205219 | BA60: =SUM(BA40:BA44)/SUM(BA51:BA53) -> 7.8091343 | BB60: =SUM(BB40:BB44)/SUM(BB51:BB53) -> 6.8890853 | BC60: =SUM(BC40:BC44)/SUM(BC51:BC53) -> 7.9084219 | BD60: =SUM(BD40:BD44)/SUM(BD51:BD53) -> 7.8206562 | BE60: =SUM(BE40:BE44)/SUM(BE51:BE53) -> 7.572013 | BF60: =SUM(BF40:BF44)/SUM(BF51:BF53) -> 6.6106354 | ... BU60: =SUM(BU40:BU44)/SUM(BU51:BU53) -> 6.3533092 | CM60: =SUM(CM40:CM44)/SUM(CM51:CM53) -> 6.8890853 | CN60: =SUM(CN40:CN44)/SUM(CN51:CN53) -> 6.6106354 | CO60: =SUM(CO40:CO44)/SUM(CO51:CO53) -> 7.3635176 | CP60: =SUM(CP40:CP44)/SUM(CP51:CP53) -> 5.9367173 | CQ60: =SUM(CQ40:CQ44)/SUM(CQ51:CQ53) -> 6.9348319 | CS60: Cost of Debt | CV60: 0
B61: Quick Ratio | AY61: =(SUM(AY40:AY44)-AY43)/SUM(AY51:AY53) -> 8.3682927 | AZ61: =(SUM(AZ40:AZ44)-AZ43)/SUM(AZ51:AZ53) -> 7.4421369 | BA61: =(SUM(BA40:BA44)-BA43)/SUM(BA51:BA53) -> 7.0117246 | BB61: =(SUM(BB40:BB44)-BB43)/SUM(BB51:BB53) -> 6.1970769 | BC61: =(SUM(BC40:BC44)-BC43)/SUM(BC51:BC53) -> 7.0185337 | BD61: =(SUM(BD40:BD44)-BD43)/SUM(BD51:BD53) -> 6.9208302 | BE61: =(SUM(BE40:BE44)-BE43)/SUM(BE51:BE53) -> 6.5647936 | BF61: =(SUM(BF40:BF44)-BF43)/SUM(BF51:BF53) -> 5.6663495 | ... BU61: =(SUM(BU40:BU44)-BU43)/SUM(BU51:BU53) -> 4.7490577 | CM61: =(SUM(CM40:CM44)-CM43)/SUM(CM51:CM53) -> 6.1970769 | CN61: =(SUM(CN40:CN44)-CN43)/SUM(CN51:CN53) -> 5.6663495 | CO61: =(SUM(CO40:CO44)-CO43)/SUM(CO51:CO53) -> 6.2240478 | CP61: =(SUM(CP40:CP44)-CP43)/SUM(CP51:CP53) -> 4.6951077 | CQ61: =(SUM(CQ40:CQ44)-CQ43)/SUM(CQ51:CQ53) -> 5.6300525 | CS61: Tax Rate | CV61: 0.2
B62: Cash Ratio | AY62: =SUM(AY40)/SUM(AY51:AY53) -> 2.1368902 | AZ62: =SUM(AZ40)/SUM(AZ51:AZ53) -> 2.2072688 | BA62: =SUM(BA40)/SUM(BA51:BA53) -> 1.8359918 | BB62: =SUM(BB40)/SUM(BB51:BB53) -> 1.52157 | BC62: =SUM(BC40)/SUM(BC51:BC53) -> 1.5032706 | BD62: =SUM(BD40)/SUM(BD51:BD53) -> 1.9091474 | BE62: =SUM(BE40)/SUM(BE51:BE53) -> 1.8505595 | BF62: =SUM(BF40)/SUM(BF51:BF53) -> 1.6716355 | ... BU62: =SUM(BU40)/SUM(BU51:BU53) -> 2.2449118 | CM62: =SUM(CM40)/SUM(CM51:CM53) -> 1.52157 | CN62: =SUM(CN40)/SUM(CN51:CN53) -> 1.6716355 | CO62: =SUM(CO40)/SUM(CO51:CO53) -> 2.5673077 | CP62: =SUM(CP40)/SUM(CP51:CP53) -> 1.6926031 | CQ62: =SUM(CQ40)/SUM(CQ51:CQ53) -> 2.3883137 | CS62: After Tax Cost of Debt | CV62: =CV60*(1-CV61) -> 0
B63: Ttl Asset Turnover | AY63: =AY18/AY49 -> 0.11196319 | AZ63: =AZ18/AZ49 -> 0.11905343 | BA63: =BA18/BA49 -> 0.10849195 | BB63: =BB18/BB49 -> 0.11440397 | BC63: =BC18/BC49 -> 0.10877067 | BD63: =BD18/BD49 -> 0.11106409 | BE63: =BE18/BE49 -> 0.11744832 | BF63: =BF18/BF49 -> 0.12756282 | ... BU63: =BU18/BU49 -> 0.15756288 | CM63: =CM18/CM49 -> 0.42126658 | CN63: =CN18/CN49 -> 0.47958995 | CO63: =CO18/CO49 -> 0.46136659 | CP63: =CP18/CP49 -> 0.44560694 | CQ63: =CQ18/CQ49 -> 0.49195697
B64: Inventory Turnover Ratio | AY64: =AY19/AVERAGE(AV43:AY43) -> 0.67527739 | AZ64: =AZ19/AVERAGE(AW43:AZ43) -> 0.76807676 | BA64: =BA19/AVERAGE(AX43:BA43) -> 0.74835393 | BB64: =BB19/AVERAGE(AY43:BB43) -> 0.84520164 | BC64: =BC19/AVERAGE(AZ43:BC43) -> 0.79842987 | BD64: =BD19/AVERAGE(BA43:BD43) -> 0.78273833 | BE64: =BE19/AVERAGE(BB43:BE43) -> 0.72154791 | BF64: =BF19/AVERAGE(BC43:BF43) -> 0.70041515 | ... BU64: =BU19/AVERAGE(BR43:BU43) -> 0.48572148 | CM64: =CM19/AVERAGE(CJ43:CM43) -> 2.9834781 | CN64: =CN19/AVERAGE(CK43:CN43) -> 2.7375532 | CO64: =CO19/AVERAGE(CL43:CO43) -> 2.6597801 | CP64: =CP19/AVERAGE(CM43:CP43) -> 2.595831 | CQ64: =CQ19/AVERAGE(CN43:CQ43) -> 2.5160081 | CS64: WACC | CV64: =(CV50*CV57)+(CV49*CV62*(1-CV61)) -> 0.13664211
B65: Return on Assets | AY65: =AY27/AY49 -> 0.037710998 | AZ65: =AZ27/AZ49 -> 0.042530699 | BA65: =BA27/BA49 -> 0.029935213 | BB65: =BB27/BB49 -> 0.028233957 | BC65: =BC27/BC49 -> 0.027008057 | BD65: =BD27/BD49 -> 0.022882661 | BE65: =BE27/BE49 -> 0.024486625 | BF65: =BF27/BF49 -> 0.025951904 | ... BU65: =BU27/BU49 -> 0.027102036 | CM65: =CM27/CM49 -> 0.12749177 | CN65: =CN27/CN49 -> 0.10362263 | CO65: =CO27/CO49 -> 0.11769087 | CP65: =CP27/CP49 -> 0.1247119 | CQ65: =CQ27/CQ49 -> 0.14065899
B66: Return on Equity | AY66: =AY27/AY57 -> 0.0427077 | AZ66: =AZ27/AZ57 -> 0.048072062 | BA66: =BA27/BA57 -> 0.033787086 | BB66: =BB27/BB57 -> 0.032021085 | BC66: =BC27/BC57 -> 0.030388286 | BD66: =BD27/BD57 -> 0.025955108 | BE66: =BE27/BE57 -> 0.028056684 | BF66: =BF27/BF57 -> 0.03029894 | ... BU66: =BU27/BU57 -> 0.032535458 | CM66: =CM27/CM57 -> 0.14459273 | CN66: =CN27/CN57 -> 0.12097979 | CO66: =CO27/CO57 -> 0.13564977 | CP66: =CP27/CP57 -> 0.14141298 | CQ66: =CQ27/CQ57 -> 0.16039171
B68: Net Income | C68: =C27 -> 28.1 | D68: =D27 -> 62.4 | E68: =E27 -> 64.5 | F68: =F27 -> 77.6 | G68: =G27 -> 85.3 | H68: =H27 -> 88.7 | I68: =I27 -> 86.6 | J68: =J27 -> 121.2 | ... BU68: =BU27 -> 524.4 | CA68: =SUM(C68:F68) -> 232.6 | CB68: =SUM(G68:J68) -> 381.8 | CC68: =SUM(K68:N68) -> 495.1 | CD68: =SUM(O68:R68) -> 656.6 | CE68: =SUM(S68:V68) -> 671 | CF68: =SUM(W68:Z68) -> 418.8 | CG68: =SUM(AA68:AD68) -> 588.8 | CH68: =SUM(AE68:AH68) -> 738.3 | CI68: =SUM(AI68:AL68) -> 670.9 | CJ68: =SUM(AM68:AP68) -> 1125 | CK68: =SUM(AQ68:AT68) -> 1381.8 | CL68: =SUM(AU68:AX68) -> 1066.8 | CM68: =SUM(AY68:BB68) -> 1728.1 | CN68: =SUM(BC68:BF68) -> 1344.4 | CO68: =SUM(BG68:BJ68) -> 1817.3 | CP68: =SUM(BK68:BN68) -> 2337.5 | CQ68: =CQ27 -> 2877.7
B69: CFFO | C69: 90.1 | D69: 83 | E69: 96.3 | F69: 122.8 | G69: 115.6 | H69: 175.5 | I69: 113 | J69: 141.7 | K69: 95.2 | L69: 211.1 | M69: 157.6 | N69: 213.7 | O69: 165 | P69: 210.8 | Q69: 211.6 | R69: 226.8 | S69: 258 | T69: 189.1 | U69: 203.8 | V69: 229.1 | W69: 166.3 | X69: 154 | Y69: 150.6 | Z69: 194.2 | AA69: 123.7 | AB69: 185.1 | AC69: 179.7 | AD69: 317.7 | AE69: 226.8 | AF69: 261.7 | AG69: 268.8 | AH69: 329.7 | AI69: 241.5 | AJ69: 216.5 | AK69: 353.9 | AL69: 332 | AM69: 280.2 | AN69: 231.5 | AO69: 319.8 | AP69: 338.1 | AQ69: 333.2 | AR69: 316 | AS69: 396.3 | AT69: 552.7 | AU69: 352.8 | AV69: 229.9 | AW69: 274.6 | AX69: 627.5 | AY69: 477.6 | AZ69: 542.7 | BA69: 501.4 | BB69: 567.7 | BC69: 223 | BD69: 446.7 | BE69: 383.2 | BF69: 437.9 | BG69: 371.4 | BH69: 665.7 | BI69: 548.4 | BJ69: 228.3 | BK69: 265.4 | BL69: 620.5 | BM69: 706.5 | BN69: 822.6 | BO69: 581.6 | BP69: =1297-BO69 -> 715.4 | BQ69: =2138-SUM(BO69:BP69) -> 841 | BR69: =3030.5-SUM(BO69:BQ69) -> 892.5 | BS69: 911.9 | BT69: 1061 | BU69: =3197-BT69-BS69 -> 1224.1 | CA69: =SUM(C69:F69) -> 392.2 | CB69: =SUM(G69:J69) -> 545.8 | CC69: =SUM(K69:N69) -> 677.6 | CD69: =SUM(O69:R69) -> 814.2 | CE69: =SUM(S69:V69) -> 880 | CF69: =SUM(W69:Z69) -> 665.1 | CG69: =SUM(AA69:AD69) -> 806.2 | CH69: =SUM(AE69:AH69) -> 1087 | CI69: =SUM(AI69:AL69) -> 1143.9 | CJ69: =SUM(AM69:AP69) -> 1169.6 | CK69: =SUM(AQ69:AT69) -> 1598.2 | CL69: =SUM(AU69:AX69) -> 1484.8 | CM69: =SUM(AY69:BB69) -> 2089.4 | CN69: =SUM(BC69:BF69) -> 1490.8 | CO69: =SUM(BG69:BJ69) -> 1813.8 | CP69: =SUM(BK69:BN69) -> 2415 | CQ69: =SUM(BO69:BR69) -> 3030.5
B70: CapEx, net | C70: -13.1 | D70: -14.6 | E70: -13.8 | F70: -26.3 | G70: -14.2 | H70: -13.4 | I70: -16.9 | J70: -14.3 | K70: -14.7 | L70: -38.5 | M70: -14.5 | N70: -15.2 | O70: -48.3 | P70: -8.1 | Q70: 12.9 | R70: -70.7 | S70: -16.7 | T70: -25 | U70: -34 | V70: -28.9 | W70: -8.1 | X70: -18.5 | Y70: -13.8 | Z70: -65.2 | AA70: -19.2 | AB70: -13.6 | AC70: -28.5 | AD70: -19.7 | AE70: -9.6 | AF70: -11.4 | AG70: -15.1 | AH70: -17.8 | AI70: -53 | AJ70: -55.3 | AK70: -51.4 | AL70: -31 | AM70: -40.1 | AN70: -44.8 | AO70: -47 | AP70: -55.5 | AQ70: -114.8 | AR70: -82 | AS70: -87 | AT70: -142 | AU70: -105.2 | AV70: -110 | AW70: -64.4 | AX70: -61.9 | AY70: -58.6 | AZ70: -75.7 | BA70: -68.3 | BB70: -136.9 | BC70: -93.6 | BD70: -130.5 | BE70: -169.1 | BF70: -139.2 | BG70: -194.1 | BH70: -178.3 | BI70: -256.3 | BJ70: -435.5 | BK70: -241.9 | BL70: -309.4 | BM70: -247.9 | BN70: -312 | BO70: -116.6 | BP70: =-271.9-BO70 -> -155.3 | BQ70: =-377.3-SUM(BO70:BP70) -> -105.4 | BR70: =-539.8-SUM(BO70:BQ70) -> -162.5 | BS70: -103.3 | BT70: -113 | BU70: =-329-BT70-BS70 -> -112.7 | CA70: =SUM(C70:F70) -> -67.8 | CB70: =SUM(G70:J70) -> -58.8 | CC70: =SUM(K70:N70) -> -82.9 | CD70: =SUM(O70:R70) -> -114.2 | CE70: =SUM(S70:V70) -> -104.6 | CF70: =SUM(W70:Z70) -> -105.6 | CG70: =SUM(AA70:AD70) -> -81 | CH70: =SUM(AE70:AH70) -> -53.9 | CI70: =SUM(AI70:AL70) -> -190.7 | CJ70: =SUM(AM70:AP70) -> -187.4 | CK70: =SUM(AQ70:AT70) -> -425.8 | CL70: =SUM(AU70:AX70) -> -341.5 | CM70: =SUM(AY70:BB70) -> -339.5 | CN70: =SUM(BC70:BF70) -> -532.4 | CO70: =SUM(BG70:BJ70) -> -1064.2 | CP70: =SUM(BK70:BN70) -> -1111.2 | CQ70: =SUM(BO70:BR70) -> -539.8
B71: FCF | C71: =C69+C70 -> 77 | D71: =D69+D70 -> 68.4 | E71: =E69+E70 -> 82.5 | F71: =F69+F70 -> 96.5 | G71: =G69+G70 -> 101.4 | H71: =H69+H70 -> 162.1 | I71: =I69+I70 -> 96.1 | J71: =J69+J70 -> 127.4 | ... BU71: =BU69+BU70 -> 1111.4 | CA71: =SUM(C71:F71) -> 324.4 | CB71: =SUM(G71:J71) -> 487 | CC71: =SUM(K71:N71) -> 594.7 | CD71: =SUM(O71:R71) -> 700 | CE71: =SUM(S71:V71) -> 775.4 | CF71: =SUM(W71:Z71) -> 559.5 | CG71: =SUM(AA71:AD71) -> 725.2 | CH71: =SUM(AE71:AH71) -> 1033.1 | CI71: =SUM(AI71:AL71) -> 953.2 | CJ71: =SUM(AM71:AP71) -> 982.2 | CK71: =SUM(AQ71:AT71) -> 1172.4 | CL71: =SUM(AU71:AX71) -> 1143.3 | CM71: =SUM(AY71:BB71) -> 1749.9 | CN71: =SUM(BC71:BF71) -> 958.4 | CO71: =SUM(BG71:BJ71) -> 749.6 | CP71: =SUM(BK71:BN71) -> 1303.8 | CQ71: =SUM(BO71:BR71) -> 2490.7
B72: SC | C72: =C30 -> 355 | D72: =D30 -> 355 | E72: =E30 -> 355 | F72: =F30 -> 354 | G72: =G30 -> 354 | H72: =H30 -> 353 | I72: =I30 -> 352 | J72: =J30 -> 352 | ... BU72: =BU30 -> 349 | CA72: =CA30 -> 354.75 | CB72: =CB30 -> 352.75 | CC72: =CC30 -> 352.5 | CD72: =CD30 -> 358 | CE72: =CE30 -> 355.5 | CF72: =CF30 -> 333.5 | CG72: =CG30 -> 333 | CH72: =CH30 -> 344.25 | ... CQ72: =CQ30 -> 356.9325
B73: FCF per Share | C73: =C71/C72 -> 0.21690141 | D73: =D71/D72 -> 0.19267606 | E73: =E71/E72 -> 0.23239437 | F73: =F71/F72 -> 0.27259887 | G73: =G71/G72 -> 0.28644068 | H73: =H71/H72 -> 0.4592068 | I73: =I71/I72 -> 0.27301136 | J73: =J71/J72 -> 0.36193182 | ... BU73: =BU71/BU72 -> 3.1845272 | CA73: =SUM(C73:F73) -> 0.9145707 | CB73: =SUM(G73:J73) -> 1.3805907 | CC73: =SUM(K73:N73) -> 1.6865021 | CD73: =SUM(O73:R73) -> 1.9538147 | CE73: =SUM(S73:V73) -> 2.1783173 | CF73: =SUM(W73:Z73) -> 1.6761605 | CG73: =SUM(AA73:AD73) -> 2.1754485 | CH73: =SUM(AE73:AH73) -> 2.9992962 | CI73: =SUM(AI73:AL73) -> 2.8465885 | CJ73: =SUM(AM73:AP73) -> 2.8842622 | CK73: =SUM(AQ73:AT73) -> 3.3902689 | CL73: =SUM(AU73:AX73) -> 3.2593258 | CM73: =SUM(AY73:BB73) -> 4.9194694 | CN73: =SUM(BC73:BF73) -> 2.6863846 | CO73: =SUM(BG73:BJ73) -> 2.135842 | CP73: =SUM(BK73:BN73) -> 3.6692425 | CQ73: =SUM(BO73:BR73) -> 6.9814432

Sheet Notes | Quant Analysis
Q2: Employee Scope: | AM2: Financial Stmts. Notes/Observations | CJ2: 0
R32: Notes: | S32: In Q2'25 Dr. Gary Guthart stepped down as CEO after 15 years of service… He announced he will now be serving as chairman of the board ... David Rosa is taking on the CEO role
S33: [Y]
S34: [Z]
Q36: Institutional Ownership Snapshot (4/14/2025) | AM36: Revenues:
R67: Notes: | S67: [X]
S68: [Y]
S69: [Z]
Q71: Revenue Breakdown by Segment | AM71: Earnings Scope:
R103: Notes: | S103: [X]
S104: [Y]
S105: [Z]
Q107: Total Revenues, Net Income, FCF | AM107: Balance Sheet Scope:
R136: Notes: | S136: [X]
S137: [Y]
S138: [Z]
Q140: Total Revenues, Net Income, FCF
R169: Notes: | S169: [X]
S170: [Y]
S171: [Z]
Q173: [ISRG] Historical Return Histogram (8/3/2025) | AM173: [Equity Preformance Compared to Peers]
B190: VOO Historical Returns | J190: ISRG Historical Returns
B191: 1004 Trading Days? (From: 4/30/21 - 4/29/25) | J191: 1256 Trading Days (From: 5/11/2020-5/11/2025)
B192: Close | C192: High | D192: Low | E192: Open | F192: Volume | G192: UTC Date | H192: Change | J192: Close | K192: High | L192: Low | M192: Open | N192: Volume | O192: UTC Date | P192: Change
B193: 626.89 | C193: 631.17 | D193: 623.115 | E193: 626.93 | F193: 9248752 | G193: Fri, 13 Feb 2026 00:00:00 GMT | H193: =B193/E193-1 -> -6.3802976e-05 | J193: 485.84 | K193: 495.57 | L193: 479.61 | M193: 480.5 | N193: 1981065 | O193: Fri, 13 Feb 2026 00:00:00 GMT | P193: =J193/M193-1 -> 0.011113424
B194: 626.49 | C194: 639.52 | D194: 625.76 | E194: 638.51 | F194: 8866872 | G194: Thu, 12 Feb 2026 00:00:00 GMT | H194: =B194/E194-1 -> -0.018825077 | J194: 478.6 | K194: 497.84 | L194: 475.83 | M194: 496.12 | N194: 2962887 | O194: Thu, 12 Feb 2026 00:00:00 GMT | P194: =J194/M194-1 -> -0.035314037
B195: 636.35 | C195: 641.15 | D195: 633.84 | E195: 640.49 | F195: 5317092 | G195: Wed, 11 Feb 2026 00:00:00 GMT | H195: =B195/E195-1 -> -0.0064638012 | J195: 496.12 | K195: 500.34 | L195: 490.66 | M195: 492.75 | N195: 1926402 | O195: Wed, 11 Feb 2026 00:00:00 GMT | P195: =J195/M195-1 -> 0.0068391679
B196: 636.44 | C196: 640.62 | D196: 636.08 | E196: 639.14 | F196: 13619951 | G196: Tue, 10 Feb 2026 00:00:00 GMT | H196: =B196/E196-1 -> -0.0042244266 | J196: 495.15 | K196: 500.3756 | L196: 493.5258 | M196: 494.22 | N196: 1805098 | O196: Tue, 10 Feb 2026 00:00:00 GMT | P196: =J196/M196-1 -> 0.0018817531
B197: 638.23 | C197: 639.99 | D197: 633.11 | E197: 634.07 | F197: 8885179 | G197: Mon, 09 Feb 2026 00:00:00 GMT | H197: =B197/E197-1 -> 0.0065607898 | J197: 492.84 | K197: 493.54 | L197: 483.9 | M197: 486.05 | N197: 2180867 | O197: Mon, 09 Feb 2026 00:00:00 GMT | P197: =J197/M197-1 -> 0.013969756
B198: 635.24 | C198: 636.72 | D198: 626.2 | E198: 626.72 | F198: 12959420 | G198: Fri, 06 Feb 2026 00:00:00 GMT | H198: =B198/E198-1 -> 0.013594588 | J198: 488.15 | K198: 491.65 | L198: 480.07 | M198: 482.165 | N198: 2518023 | O198: Fri, 06 Feb 2026 00:00:00 GMT | P198: =J198/M198-1 -> 0.012412763
B199: 623.1 | C199: 628.75 | D199: 621.5 | E199: 626.24 | F199: 11506981 | G199: Thu, 05 Feb 2026 00:00:00 GMT | H199: =B199/E199-1 -> -0.0050140521 | J199: 476.32 | K199: 489.51 | L199: 475.17 | M199: 482.78 | N199: 2694556 | O199: Thu, 05 Feb 2026 00:00:00 GMT | P199: =J199/M199-1 -> -0.013380836
B200: 630.91 | C200: 635.92 | D200: 627 | E200: 634.93 | F200: 11228241 | G200: Wed, 04 Feb 2026 00:00:00 GMT | H200: =B200/E200-1 -> -0.0063314066 | J200: 478.49 | K200: 481.19 | L200: 465.689 | M200: 480.105 | N200: 3402220 | O200: Wed, 04 Feb 2026 00:00:00 GMT | P200: =J200/M200-1 -> -0.0033638475
B201: 634.15 | C201: 641 | D201: 629.105 | E201: 640.33 | F201: 9644195 | G201: Tue, 03 Feb 2026 00:00:00 GMT | H201: =B201/E201-1 -> -0.0096512736 | J201: 478.88 | K201: 499 | L201: 476.79 | M201: 495.21 | N201: 3781824 | O201: Tue, 03 Feb 2026 00:00:00 GMT | P201: =J201/M201-1 -> -0.032975909
B202: 639.68 | C202: 640.96 | D202: 634.07 | E202: 634.18 | F202: 9124531 | G202: Mon, 02 Feb 2026 00:00:00 GMT | H202: =B202/E202-1 -> 0.0086726166 | J202: 496.73 | K202: 504.2 | L202: 496.15 | M202: 502 | N202: 2108426 | O202: Mon, 02 Feb 2026 00:00:00 GMT | P202: =J202/M202-1 -> -0.010498008
B203: 636.22 | C203: 638.45 | D203: 631.95 | E203: 636.25 | F203: 6519552 | G203: Fri, 30 Jan 2026 00:00:00 GMT | H203: =B203/E203-1 -> -4.7151277e-05 | J203: 504.22 | K203: 511.03 | L203: 501.385 | M203: 506.7 | N203: 1696613 | O203: Fri, 30 Jan 2026 00:00:00 GMT | P203: =J203/M203-1 -> -0.0048944148
B204: 638.27 | C204: 641.04 | D204: 629.82 | E204: 640.43 | F204: 8485857 | G204: Thu, 29 Jan 2026 00:00:00 GMT | H204: =B204/E204-1 -> -0.0033727339 | J204: 507.55 | K204: 522 | L204: 502.48 | M204: 521.17 | N204: 2127431 | O204: Thu, 29 Jan 2026 00:00:00 GMT | P204: =J204/M204-1 -> -0.026133507
B205: 639.6 | C205: 641.81 | D205: 638.22 | E205: 641.05 | F205: 5488373 | G205: Wed, 28 Jan 2026 00:00:00 GMT | H205: =B205/E205-1 -> -0.002261914 | J205: 522.04 | K205: 529.36 | L205: 520.24 | M205: 523.91 | N205: 1848874 | O205: Wed, 28 Jan 2026 00:00:00 GMT | P205: =J205/M205-1 -> -0.0035693153
B206: 639.7 | C206: 640.5959 | D206: 637.87 | E206: 638.42 | F206: 4308306 | G206: Tue, 27 Jan 2026 00:00:00 GMT | H206: =B206/E206-1 -> 0.0020049497 | J206: 525.04 | K206: 535 | L206: 523.54 | M206: 532.61 | N206: 1477091 | O206: Tue, 27 Jan 2026 00:00:00 GMT | P206: =J206/M206-1 -> -0.014213026 | R206: Notes: | S206: [X]
B207: 637.09 | C207: 638.39 | D207: 634.52 | E207: 635.03 | F207: 8976388 | G207: Mon, 26 Jan 2026 00:00:00 GMT | H207: =B207/E207-1 -> 0.0032439412 | J207: 528.81 | K207: 533.97 | L207: 518.65 | M207: 523.945 | N207: 2492449 | O207: Mon, 26 Jan 2026 00:00:00 GMT | P207: =J207/M207-1 -> 0.0092853257 | S207: [Y]
B208: 633.83 | C208: 635.4705 | D208: 631.97 | E208: 632.88 | F208: 5827254 | G208: Fri, 23 Jan 2026 00:00:00 GMT | H208: =B208/E208-1 -> 0.0015010745 | J208: 523.99 | K208: 540 | L208: 521.18 | M208: 530 | N208: 2763321 | O208: Fri, 23 Jan 2026 00:00:00 GMT | P208: =J208/M208-1 -> -0.011339623 | S208: [Z]
B209: 633.57 | C209: 635.62 | D209: 631.75 | E209: 634.43 | F209: 6057784 | G209: Thu, 22 Jan 2026 00:00:00 GMT | H209: =B209/E209-1 -> -0.0013555475 | J209: 525.81 | K209: 532 | L209: 522.72 | M209: 525.405 | N209: 2793788 | O209: Thu, 22 Jan 2026 00:00:00 GMT | P209: =J209/M209-1 -> 0.00077083393
B210: 630.29 | C210: 633.4 | D210: 623.65 | E210: 625.02 | F210: 10354978 | G210: Wed, 21 Jan 2026 00:00:00 GMT | H210: =B210/E210-1 -> 0.0084317302 | J210: 523.69 | K210: 530.05 | L210: 518.64 | M210: 527.59 | N210: 2021976 | O210: Wed, 21 Jan 2026 00:00:00 GMT | P210: =J210/M210-1 -> -0.0073921037 | S210: Min | T210: =MIN(P193:P1618) -> -0.0824
B211: 623.15 | C211: 629.7599 | D211: 622.22 | E211: 626.76 | F211: 14877629 | G211: Tue, 20 Jan 2026 00:00:00 GMT | H211: =B211/E211-1 -> -0.0057597805 | J211: 527.44 | K211: 532.605 | L211: 525.23 | M211: 527 | N211: 2149740 | O211: Tue, 20 Jan 2026 00:00:00 GMT | P211: =J211/M211-1 -> 0.00083491461 | S211: Max | T211: =MAX(P193:P1618) -> 0.16211111
B212: 636.09 | C212: 638.5099 | D212: 634.68 | E212: 637.96 | F212: 6694041 | G212: Fri, 16 Jan 2026 00:00:00 GMT | H212: =B212/E212-1 -> -0.0029312183 | J212: 535 | K212: 543 | L212: 532.6301 | M212: 542 | N212: 3007245 | O212: Fri, 16 Jan 2026 00:00:00 GMT | P212: =J212/M212-1 -> -0.012915129 | S212: Mean μ | T212: =AVERAGE(P193:P1618) -> 0.00027790103
B213: 636.62 | C213: 639.58 | D213: 635.7 | E213: 638.77 | F213: 6751601 | G213: Thu, 15 Jan 2026 00:00:00 GMT | H213: =B213/E213-1 -> -0.0033658437 | J213: 541.34 | K213: 553.74 | L213: 535.69 | M213: 553.74 | N213: 1899473 | O213: Thu, 15 Jan 2026 00:00:00 GMT | P213: =J213/M213-1 -> -0.022393181 | S213: Median | T213: =MEDIAN(P193:P1618) -> 0.00075241509
B214: 634.94 | C214: 636.119 | D214: 631 | E214: 635.49 | F214: 8576256 | G214: Wed, 14 Jan 2026 00:00:00 GMT | H214: =B214/E214-1 -> -0.00086547389 | J214: 546.76 | K214: 551 | L214: 528 | M214: 533.96 | N214: 3597689 | O214: Wed, 14 Jan 2026 00:00:00 GMT | P214: =J214/M214-1 -> 0.023971833 | S214: SD σ | T214: =_xlfn.STDEV.P(P193:P1618) -> 0.017000063
B215: 638.03 | C215: 640.1507 | D215: 635.815 | E215: 639.68 | F215: 8837128 | G215: Tue, 13 Jan 2026 00:00:00 GMT | H215: =B215/E215-1 -> -0.0025794147 | J215: 561.82 | K215: 572.59 | L215: 556.04 | M215: 571.45 | N215: 1509670 | O215: Tue, 13 Jan 2026 00:00:00 GMT | P215: =J215/M215-1 -> -0.016851868 | S215: 3σ 1-Day Δ: ± | T215: =3*T214 -> 0.051000188 | V215: <- Sharpe Ratio (Risk Adjusted Return)
B216: 639.34 | C216: 640.16 | D216: 635.16 | E216: 635.19 | F216: 7889884 | G216: Mon, 12 Jan 2026 00:00:00 GMT | H216: =B216/E216-1 -> 0.0065334782 | J216: 572.745 | K216: 582.19 | L216: 566.8 | M216: 581.97 | N216: 1824961 | O216: Mon, 12 Jan 2026 00:00:00 GMT | P216: =J216/M216-1 -> -0.015851333 | S216: β (1-year avg.) | T216: =_xlfn.COVARIANCE.P(P193:P442,H193:H442)/_xlfn.VAR.P(H193:H442) -> 1.3586619 | V216: <- Sortino Ratio (Downside Risk Adjusted Return)
B217: 638.31 | C217: 639.44 | D217: 633.8 | E217: 635.15 | F217: 7843716 | G217: Fri, 09 Jan 2026 00:00:00 GMT | H217: =B217/E217-1 -> 0.0049752027 | J217: 586.24 | K217: 589.58 | L217: 579.62 | M217: 587.32 | N217: 1488926 | O217: Fri, 09 Jan 2026 00:00:00 GMT | P217: =J217/M217-1 -> -0.0018388613
B218: 634.06 | C218: 635.1001 | D218: 632.2362 | E218: 633.48 | F218: 8962799 | G218: Thu, 08 Jan 2026 00:00:00 GMT | H218: =B218/E218-1 -> 0.00091557745 | J218: 585.08 | K218: 589.95 | L218: 582.685 | M218: 582.685 | N218: 1468272 | O218: Thu, 08 Jan 2026 00:00:00 GMT | P218: =J218/M218-1 -> 0.0041102826
B219: 634.17 | C219: 638.22 | D219: 633.93 | E219: 636.58 | F219: 8796759 | G219: Wed, 07 Jan 2026 00:00:00 GMT | H219: =B219/E219-1 -> -0.0037858557 | J219: 592.27 | K219: 603.88 | L219: 590.8 | M219: 592.89 | N219: 1861335 | O219: Wed, 07 Jan 2026 00:00:00 GMT | P219: =J219/M219-1 -> -0.0010457252 | R219: n = | S219: 1256
B220: 636.21 | C220: 636.68 | D220: 632.53 | E220: 632.64 | F220: 8630900 | G220: Tue, 06 Jan 2026 00:00:00 GMT | H220: =B220/E220-1 -> 0.0056430197 | J220: 592.85 | K220: 594.62 | L220: 564.345 | M220: 565 | N220: 2627158 | O220: Tue, 06 Jan 2026 00:00:00 GMT | P220: =J220/M220-1 -> 0.049292035 | R220: Histogram Data | U220: Distribution Overlay | Y220: SD Lines
B221: 632.46 | C221: 634.04 | D221: 631.23 | E221: 631.38 | F221: 16140408 | G221: Mon, 05 Jan 2026 00:00:00 GMT | H221: =B221/E221-1 -> 0.0017105388 | J221: 566.38 | K221: 567.08 | L221: 558 | M221: 561.15 | N221: 1394183 | O221: Mon, 05 Jan 2026 00:00:00 GMT | P221: =J221/M221-1 -> 0.0093201461 | R221: Bin | S221: Frequency | U221: (X) 1-Day Δ | V221: (Y) Pop. Density | Y221: X | Z221: Y
B222: 628.3 | C222: 631.66 | D222: 625.21 | E222: 630.635 | F222: 10997544 | G222: Fri, 02 Jan 2026 00:00:00 GMT | H222: =B222/E222-1 -> -0.0037026172 | J222: 561.98 | K222: 567.39 | L222: 555.4 | M222: 566.78 | N222: 1297073 | O222: Fri, 02 Jan 2026 00:00:00 GMT | P222: =J222/M222-1 -> -0.0084688945 | R222: -0.052 | S222: 4 | U222: -0.053 | V222: =_xlfn.NORM.DIST(U222,$T$212,$T$214,FALSE) -> 0.17285126 | X222: Mean | Y222: =T212 -> 0.00027790103 | Z222: 0
B223: 627.13 | C223: 632.14 | D223: 626.94 | E223: 631.94 | F223: 5511193 | G223: Wed, 31 Dec 2025 00:00:00 GMT | H223: =B223/E223-1 -> -0.0076114821 | J223: 566.36 | K223: 573.28 | L223: 565.77 | M223: 572.5 | N223: 987499 | O223: Wed, 31 Dec 2025 00:00:00 GMT | P223: =J223/M223-1 -> -0.010724891 | R223: -0.051 | S223: 1 | U223: -0.052 | V223: =_xlfn.NORM.DIST(U223,$T$212,$T$214,FALSE) -> 0.20748366 | Y223: =T212 -> 0.00027790103 | Z223: 23.5
B224: 631.72 | C224: 633.21 | D224: 631.41 | E224: 632.2 | F224: 4150867 | G224: Tue, 30 Dec 2025 00:00:00 GMT | H224: =B224/E224-1 -> -0.0007592534 | J224: 572.63 | K224: 574.77 | L224: 570.45 | M224: 572.21 | N224: 720406 | O224: Tue, 30 Dec 2025 00:00:00 GMT | P224: =J224/M224-1 -> 0.00073399626 | R224: -0.05 | S224: 0 | U224: -0.051 | V224: =_xlfn.NORM.DIST(U224,$T$212,$T$214,FALSE) -> 0.24819471 | X224: -3σ | Y224: =($T$214*-3)+$T$212 -> -0.050722287 | Z224: 0
B225: 632.6 | C225: 633.79 | D225: 630.95 | E225: 632.3 | F225: 6496953 | G225: Mon, 29 Dec 2025 00:00:00 GMT | H225: =B225/E225-1 -> 0.00047445833 | J225: 575.4 | K225: 580.5 | L225: 574.215 | M225: 577.81 | N225: 663232 | O225: Mon, 29 Dec 2025 00:00:00 GMT | P225: =J225/M225-1 -> -0.0041709212 | R225: -0.049 | S225: 3 | U225: -0.05 | V225: =_xlfn.NORM.DIST(U225,$T$212,$T$214,FALSE) -> 0.29586828 | Y225: =($T$214*-3)+$T$212 -> -0.050722287 | Z225: 2
B226: 634.84 | C226: 636.075 | D226: 633.88 | E226: 635.14 | F226: 3829855 | G226: Fri, 26 Dec 2025 00:00:00 GMT | H226: =B226/E226-1 -> -0.00047233681 | J226: 577.81 | K226: 579.4 | L226: 575.96 | M226: 578.21 | N226: 489218 | O226: Fri, 26 Dec 2025 00:00:00 GMT | P226: =J226/M226-1 -> -0.00069179018 | R226: -0.048 | S226: 1 | U226: =U225+0.001 -> -0.049 | V226: =_xlfn.NORM.DIST(U226,$T$212,$T$214,FALSE) -> 0.35148075 | X226: -2σ | Y226: =($T$214*-2)+$T$212 -> -0.033722224 | Z226: 0
B227: 634.78 | C227: 635.32 | D227: 632.54 | E227: 632.67 | F227: 3273415 | G227: Wed, 24 Dec 2025 00:00:00 GMT | H227: =B227/E227-1 -> 0.003335072 | J227: 577.15 | K227: 579.85 | L227: 575.03 | M227: 577.34 | N227: 355183 | O227: Wed, 24 Dec 2025 00:00:00 GMT | P227: =J227/M227-1 -> -0.00032909551 | R227: -0.047 | S227: 1 | U227: =U226+0.001 -> -0.048 | V227: =_xlfn.NORM.DIST(U227,$T$212,$T$214,FALSE) -> 0.41610406 | Y227: =($T$214*-2)+$T$212 -> -0.033722224 | Z227: 4
B228: 632.67 | C228: 632.88 | D228: 628.92 | E228: 628.94 | F228: 13758872 | G228: Tue, 23 Dec 2025 00:00:00 GMT | H228: =B228/E228-1 -> 0.0059306134 | J228: 577.34 | K228: 579.2 | L228: 573.6762 | M228: 577.135 | N228: 1272395 | O228: Tue, 23 Dec 2025 00:00:00 GMT | P228: =J228/M228-1 -> 0.00035520286 | R228: -0.046 | S228: 0 | U228: =U227+0.001 -> -0.047 | V228: =_xlfn.NORM.DIST(U228,$T$212,$T$214,FALSE) -> 0.49090744 | X228: -1σ | Y228: =($T$214*-1)+$T$212 -> -0.016722162 | Z228: 0
B229: 629.73 | C229: 630.27 | D229: 627.8 | E229: 628.965 | F229: 9796066 | G229: Mon, 22 Dec 2025 00:00:00 GMT | H229: =B229/E229-1 -> 0.0012162839 | J229: 579.83 | K229: 583.45 | L229: 573.295 | M229: 576 | N229: 1448497 | O229: Mon, 22 Dec 2025 00:00:00 GMT | P229: =J229/M229-1 -> 0.0066493056 | R229: -0.045 | S229: 1 | U229: =U228+0.001 -> -0.046 | V229: =_xlfn.NORM.DIST(U229,$T$212,$T$214,FALSE) -> 0.57715777 | Y229: =($T$214*-1)+$T$212 -> -0.016722162 | Z229: 14
B230: 627.56 | C230: 628.13 | D230: 623.86 | E230: 623.98 | F230: 10447326 | G230: Fri, 19 Dec 2025 00:00:00 GMT | H230: =B230/E230-1 -> 0.0057373634 | J230: 572.47 | K230: 574.57 | L230: 561.31 | M230: 561.63 | N230: 4024629 | O230: Fri, 19 Dec 2025 00:00:00 GMT | P230: =J230/M230-1 -> 0.019300963 | R230: -0.044 | S230: 0 | U230: =U229+0.001 -> -0.045 | V230: =_xlfn.NORM.DIST(U230,$T$212,$T$214,FALSE) -> 0.67621802 | X230: 1σ | Y230: =($T$214*1)+$T$212 -> 0.017277964 | Z230: 0
B231: 622.01 | C231: 625.94 | D231: 620.57 | E231: 623.05 | F231: 33420938 | G231: Thu, 18 Dec 2025 00:00:00 GMT | H231: =B231/E231-1 -> -0.0016692079 | J231: 561.89 | K231: 566.85 | L231: 557.255 | M231: 557.29 | N231: 1518323 | O231: Thu, 18 Dec 2025 00:00:00 GMT | P231: =J231/M231-1 -> 0.0082542303 | R231: -0.043 | S231: 1 | U231: =U230+0.001 -> -0.044 | V231: =_xlfn.NORM.DIST(U231,$T$212,$T$214,FALSE) -> 0.78954373 | Y231: =($T$214*1)+$T$212 -> 0.017277964 | Z231: 14
B232: 617.35 | C232: 625.64 | D232: 617.159 | E232: 625.19 | F232: 20953077 | G232: Wed, 17 Dec 2025 00:00:00 GMT | H232: =B232/E232-1 -> -0.012540188 | J232: 556.86 | K232: 561.455 | L232: 554 | M232: 554.68 | N232: 1655421 | O232: Wed, 17 Dec 2025 00:00:00 GMT | P232: =J232/M232-1 -> 0.003930194 | R232: -0.042 | S232: 1 | U232: =U231+0.001 -> -0.043 | V232: =_xlfn.NORM.DIST(U232,$T$212,$T$214,FALSE) -> 0.91867713 | X232: 2σ | Y232: =($T$214*2)+$T$212 -> 0.034278026 | Z232: 0
B233: 624.21 | C233: 626.22 | D233: 620.65 | E233: 624.55 | F233: 13922431 | G233: Tue, 16 Dec 2025 00:00:00 GMT | H233: =B233/E233-1 -> -0.00054439196 | J233: 554.58 | K233: 559.69 | L233: 546.1301 | M233: 559.05 | N233: 1921893 | O233: Tue, 16 Dec 2025 00:00:00 GMT | P233: =J233/M233-1 -> -0.007995707 | R233: -0.041 | S233: 0 | U233: =U232+0.001 -> -0.042 | V233: =_xlfn.NORM.DIST(U233,$T$212,$T$214,FALSE) -> 1.0652386 | Y233: =($T$214*2)+$T$212 -> 0.034278026 | Z233: 4
B234: 625.96 | C234: 630.56 | D234: 624.57 | E234: 630.56 | F234: 11306924 | G234: Mon, 15 Dec 2025 00:00:00 GMT | H234: =B234/E234-1 -> -0.0072951028 | J234: 559.52 | K234: 561.62 | L234: 546.05 | M234: 546.05 | N234: 2920859 | O234: Mon, 15 Dec 2025 00:00:00 GMT | P234: =J234/M234-1 -> 0.024668071 | R234: -0.04 | S234: 2 | U234: =U233+0.001 -> -0.041 | V234: =_xlfn.NORM.DIST(U234,$T$212,$T$214,FALSE) -> 1.2309152 | X234: 3σ | Y234: =($T$214*3)+$T$212 -> 0.051278089 | Z234: 0
B235: 626.87 | C235: 633.43 | D235: 624.48 | E235: 632.8 | F235: 8504783 | G235: Fri, 12 Dec 2025 00:00:00 GMT | H235: =B235/E235-1 -> -0.0093710493 | J235: 542.32 | K235: 548.99 | L235: 537.69 | M235: 546 | N235: 2080655 | O235: Fri, 12 Dec 2025 00:00:00 GMT | P235: =J235/M235-1 -> -0.0067399267 | R235: -0.039 | S235: 1 | U235: -0.04 | V235: =_xlfn.NORM.DIST(U235,$T$212,$T$214,FALSE) -> 1.4174463 | Y235: =($T$214*3)+$T$212 -> 0.051278089 | Z235: 2
B236: 633.71 | C236: 633.87 | D236: 627.27 | E236: 630 | F236: 22128232 | G236: Thu, 11 Dec 2025 00:00:00 GMT | H236: =B236/E236-1 -> 0.0058888889 | J236: 547.36 | K236: 553.39 | L236: 542.71 | M236: 545.465 | N236: 1513651 | O236: Thu, 11 Dec 2025 00:00:00 GMT | P236: =J236/M236-1 -> 0.0034741001 | R236: -0.038 | S236: 1 | U236: =U235+0.001 -> -0.039 | V236: =_xlfn.NORM.DIST(U236,$T$212,$T$214,FALSE) -> 1.6266061
B237: 632.16 | C237: 633.505 | D237: 626.47 | E237: 627.63 | F237: 22399235 | G237: Wed, 10 Dec 2025 00:00:00 GMT | H237: =B237/E237-1 -> 0.0072176282 | J237: 555.92 | K237: 560.05 | L237: 546.55 | M237: 557.76 | N237: 1538209 | O237: Wed, 10 Dec 2025 00:00:00 GMT | P237: =J237/M237-1 -> -0.0032989099 | R237: -0.037 | S237: 4 | U237: =U236+0.001 -> -0.038 | V237: =_xlfn.NORM.DIST(U237,$T$212,$T$214,FALSE) -> 1.8601819
B238: 628.1 | C238: 630.21 | D238: 627.66 | E238: 628.18 | F238: 9617841 | G238: Tue, 09 Dec 2025 00:00:00 GMT | H238: =B238/E238-1 -> -0.00012735203 | J238: 558.13 | K238: 569 | L238: 557.5 | M238: 566.5 | N238: 1211718 | O238: Tue, 09 Dec 2025 00:00:00 GMT | P238: =J238/M238-1 -> -0.014774934 | R238: -0.036 | S238: 6 | U238: =U237+0.001 -> -0.037 | V238: =_xlfn.NORM.DIST(U238,$T$212,$T$214,FALSE) -> 2.1199504
B239: 628.61 | C239: 631.47 | D239: 626.701 | E239: 631.36 | F239: 6833888 | G239: Mon, 08 Dec 2025 00:00:00 GMT | H239: =B239/E239-1 -> -0.0043556766 | J239: 566.89 | K239: 576.15 | L239: 562.67 | M239: 576.15 | N239: 1294221 | O239: Mon, 08 Dec 2025 00:00:00 GMT | P239: =J239/M239-1 -> -0.016072203 | R239: -0.035 | S239: 0 | U239: =U238+0.001 -> -0.036 | V239: =_xlfn.NORM.DIST(U239,$T$212,$T$214,FALSE) -> 2.4076494
B240: 630.48 | C240: 632.98 | D240: 629.48 | E240: 630.3 | F240: 5007553 | G240: Fri, 05 Dec 2025 00:00:00 GMT | H240: =B240/E240-1 -> 0.0002855783 | J240: 575.34 | K240: 576.88 | L240: 569.43 | M240: 569.5 | N240: 1060838 | O240: Fri, 05 Dec 2025 00:00:00 GMT | P240: =J240/M240-1 -> 0.010254609 | R240: -0.034 | S240: 1 | U240: =U239+0.001 -> -0.035 | V240: =_xlfn.NORM.DIST(U240,$T$212,$T$214,FALSE) -> 2.724947
B241: 629.3 | C241: 630.18 | D241: 626.48 | E241: 630.13 | F241: 5114434 | G241: Thu, 04 Dec 2025 00:00:00 GMT | H241: =B241/E241-1 -> -0.0013171885 | J241: 568.63 | K241: 574.23 | L241: 564.72 | M241: 571.98 | N241: 1147346 | O241: Thu, 04 Dec 2025 00:00:00 GMT | P241: =J241/M241-1 -> -0.0058568481 | R241: -0.033 | S241: 2 | U241: =U240+0.001 -> -0.034 | V241: =_xlfn.NORM.DIST(U241,$T$212,$T$214,FALSE) -> 3.0734074
B242: 628.77 | C242: 629.78 | D242: 624.95 | E242: 625.77 | F242: 5149531 | G242: Wed, 03 Dec 2025 00:00:00 GMT | H242: =B242/E242-1 -> 0.0047940937 | J242: 569.71 | K242: 571.77 | L242: 563.04 | M242: 569.48 | N242: 1088535 | O242: Wed, 03 Dec 2025 00:00:00 GMT | P242: =J242/M242-1 -> 0.00040387722 | R242: -0.032 | S242: 3 | U242: =U241+0.001 -> -0.033 | V242: =_xlfn.NORM.DIST(U242,$T$212,$T$214,FALSE) -> 3.4544544
B243: 626.58 | C243: 628.77 | D243: 624.62 | E243: 627.01 | F243: 5256797 | G243: Tue, 02 Dec 2025 00:00:00 GMT | H243: =B243/E243-1 -> -0.00068579448 | J243: 567.72 | K243: 570.75 | L243: 561.39 | M243: 568.6 | N243: 1745598 | O243: Tue, 02 Dec 2025 00:00:00 GMT | P243: =J243/M243-1 -> -0.0015476609 | R243: -0.031 | S243: 7 | U243: =U242+0.001 -> -0.032 | V243: =_xlfn.NORM.DIST(U243,$T$212,$T$214,FALSE) -> 3.8693326
B244: 625.52 | C244: 628.01 | D244: 624.1 | E244: 624.17 | F244: 8381362 | G244: Mon, 01 Dec 2025 00:00:00 GMT | H244: =B244/E244-1 -> 0.0021628723 | J244: 567.37 | K244: 573.535 | L244: 566.63 | M244: 568.99 | N244: 1083759 | O244: Mon, 01 Dec 2025 00:00:00 GMT | P244: =J244/M244-1 -> -0.0028471502 | R244: -0.03 | S244: 3 | U244: =U243+0.001 -> -0.031 | V244: =_xlfn.NORM.DIST(U244,$T$212,$T$214,FALSE) -> 4.3190668
B245: 628.41 | C245: 628.63 | D245: 625.705 | E245: 626.025 | F245: 2949167 | G245: Fri, 28 Nov 2025 00:00:00 GMT | H245: =B245/E245-1 -> 0.003809752 | J245: 573.48 | K245: 574 | L245: 568.2737 | M245: 571.41 | N245: 1003909 | O245: Fri, 28 Nov 2025 00:00:00 GMT | P245: =J245/M245-1 -> 0.0036226177 | R245: -0.029 | S245: 6 | U245: =U244+0.001 -> -0.03 | V245: =_xlfn.NORM.DIST(U245,$T$212,$T$214,FALSE) -> 4.8044209
B246: 624.95 | C246: 626.81 | D246: 622.26 | E246: 623.06 | F246: 5292533 | G246: Wed, 26 Nov 2025 00:00:00 GMT | H246: =B246/E246-1 -> 0.0030334157 | J246: 574.23 | K246: 582.4147 | L246: 573.75 | M246: 579.85 | N246: 1158423 | O246: Wed, 26 Nov 2025 00:00:00 GMT | P246: =J246/M246-1 -> -0.0096921618 | R246: -0.028 | S246: 9 | U246: =U245+0.001 -> -0.029 | V246: =_xlfn.NORM.DIST(U246,$T$212,$T$214,FALSE) -> 5.3258561
B247: 620.66 | C247: 621.75 | D247: 610.99 | E247: 614.78 | F247: 7289905 | G247: Tue, 25 Nov 2025 00:00:00 GMT | H247: =B247/E247-1 -> 0.009564397 | J247: 578.87 | K247: 580 | L247: 561.29 | M247: 564.44 | N247: 1679921 | O247: Tue, 25 Nov 2025 00:00:00 GMT | P247: =J247/M247-1 -> 0.025565162 | R247: -0.027 | S247: 5 | U247: =U246+0.001 -> -0.028 | V247: =_xlfn.NORM.DIST(U247,$T$212,$T$214,FALSE) -> 5.8834907
... B326: 577.35 | C326: 581.5 | D326: 576.4 | E326: 580.79 | F326: 4647381 | G326: Tue, 05 Aug 2025 00:00:00 GMT | H326: =B326/E326-1 -> -0.005922967 | J326: 477 | K326: 486.51 | L326: 476.75 | M326: 483.22 | N326: 2610355 | O326: Tue, 05 Aug 2025 00:00:00 GMT | P326: =J326/M326-1 -> -0.012871984 | R326: 0.052 | S326: 1 | U326: =U325+0.001 -> 0.051 | V326: =_xlfn.NORM.DIST(U326,$T$212,$T$214,FALSE) -> 0.27377197
B327: 580.14 | C327: 580.21 | D327: 575.08 | E327: 575.17 | F327: 6640089 | G327: Mon, 04 Aug 2025 00:00:00 GMT | H327: =B327/E327-1 -> 0.0086409236 | J327: 483.36 | K327: 490 | L327: 478.82 | M327: 486.75 | N327: 2493666 | O327: Mon, 04 Aug 2025 00:00:00 GMT | P327: =J327/M327-1 -> -0.0069645609 | R327: More | S327: 10 | U327: =U326+0.001 -> 0.052 | V327: =_xlfn.NORM.DIST(U327,$T$212,$T$214,FALSE) -> 0.22930609
B328: 571.45 | C328: 575.74 | D328: 569.29 | E328: 575.73 | F328: 8781254 | G328: Fri, 01 Aug 2025 00:00:00 GMT | H328: =B328/E328-1 -> -0.0074340403 | J328: 483.12 | K328: 486.06 | L328: 473.24 | M328: 475.46 | N328: 2983128 | O328: Fri, 01 Aug 2025 00:00:00 GMT | P328: =J328/M328-1 -> 0.016110714 | U328: =U327+0.001 -> 0.053 | V328: =_xlfn.NORM.DIST(U328,$T$212,$T$214,FALSE) -> 0.19139891
B329: 581.02 | C329: 588.1614 | D329: 579.84 | E329: 587.83 | F329: 7046843 | G329: Thu, 31 Jul 2025 00:00:00 GMT | H329: =B329/E329-1 -> -0.011584982 | J329: 481.09 | K329: 498.965 | L329: 479.6 | M329: 497.24 | N329: 2602193 | O329: Thu, 31 Jul 2025 00:00:00 GMT | P329: =J329/M329-1 -> -0.032479286
B330: 583.21 | C330: 586.15 | D330: 580.55 | E330: 584.66 | F330: 6974729 | G330: Wed, 30 Jul 2025 00:00:00 GMT | H330: =B330/E330-1 -> -0.0024800739 | J330: 500.51 | K330: 503.215 | L330: 496.9475 | M330: 497.71 | N330: 1758836 | O330: Wed, 30 Jul 2025 00:00:00 GMT | P330: =J330/M330-1 -> 0.005625766
B331: 583.92 | C331: 587.08 | D331: 583.12 | E331: 586.82 | F331: 5033308 | G331: Tue, 29 Jul 2025 00:00:00 GMT | H331: =B331/E331-1 -> -0.0049418902 | J331: 496.87 | K331: 502.42 | L331: 496.17 | M331: 497.25 | N331: 1829774 | O331: Tue, 29 Jul 2025 00:00:00 GMT | P331: =J331/M331-1 -> -0.00076420312
B332: 585.44 | C332: 586.5 | D332: 584.24 | E332: 586.04 | F332: 4169858 | G332: Mon, 28 Jul 2025 00:00:00 GMT | H332: =B332/E332-1 -> -0.0010238209 | J332: 493.95 | K332: 502.81 | L332: 493.22 | M332: 498 | N332: 2471527 | O332: Mon, 28 Jul 2025 00:00:00 GMT | P332: =J332/M332-1 -> -0.0081325301
B333: 585.58 | C333: 586.04 | D333: 583.59 | E333: 583.81 | F333: 3189061 | G333: Fri, 25 Jul 2025 00:00:00 GMT | H333: =B333/E333-1 -> 0.0030318083 | J333: 495.86 | K333: 497.5 | L333: 490.76 | M333: 492.48 | N333: 1864184 | O333: Fri, 25 Jul 2025 00:00:00 GMT | P333: =J333/M333-1 -> 0.0068632229
B334: 583.26 | C334: 584.75 | D334: 582.72 | E334: 583.34 | F334: 3840901 | G334: Thu, 24 Jul 2025 00:00:00 GMT | H334: =B334/E334-1 -> -0.00013714129 | J334: 488.61 | K334: 505.74 | L334: 486.54 | M334: 503.52 | N334: 2607994 | O334: Thu, 24 Jul 2025 00:00:00 GMT | P334: =J334/M334-1 -> -0.029611535
B335: 582.86 | C335: 582.96 | D335: 578.87 | E335: 580.57 | F335: 4257345 | G335: Wed, 23 Jul 2025 00:00:00 GMT | H335: =B335/E335-1 -> 0.0039443995 | J335: 501.95 | K335: 530.35 | L335: 491.855 | M335: 522.5 | N335: 4659926 | O335: Wed, 23 Jul 2025 00:00:00 GMT | P335: =J335/M335-1 -> -0.039330144
B336: 577.95 | C336: 578.84 | D336: 575.64 | E336: 578.28 | F336: 4743679 | G336: Tue, 22 Jul 2025 00:00:00 GMT | H336: =B336/E336-1 -> -0.00057065781 | J336: 511 | K336: 519.83 | L336: 508.27 | M336: 516.05 | N336: 2308426 | O336: Tue, 22 Jul 2025 00:00:00 GMT | P336: =J336/M336-1 -> -0.0097858735
B337: 577.95 | C337: 580.53 | D337: 577.59 | E337: 577.98 | F337: 5892207 | G337: Mon, 21 Jul 2025 00:00:00 GMT | H337: =B337/E337-1 -> -5.190491e-05 | J337: 516.12 | K337: 523.09 | L337: 514.955 | M337: 518.185 | N337: 1637240 | O337: Mon, 21 Jul 2025 00:00:00 GMT | P337: =J337/M337-1 -> -0.0039850632
B338: 576.92 | C338: 578.5 | D338: 575.84 | E338: 578.47 | F338: 4244147 | G338: Fri, 18 Jul 2025 00:00:00 GMT | H338: =B338/E338-1 -> -0.0026794821 | J338: 518.62 | K338: 520.963 | L338: 513.27 | M338: 520.21 | N338: 1881716 | O338: Fri, 18 Jul 2025 00:00:00 GMT | P338: =J338/M338-1 -> -0.003056458
B339: 577.18 | C339: 577.65 | D339: 573.8 | E339: 574.02 | F339: 5391575 | G339: Thu, 17 Jul 2025 00:00:00 GMT | H339: =B339/E339-1 -> 0.0055050347 | J339: 516.16 | K339: 517.67 | L339: 509.25 | M339: 510.83 | N339: 2001613 | O339: Thu, 17 Jul 2025 00:00:00 GMT | P339: =J339/M339-1 -> 0.010434
B340: 573.74 | C340: 574.26 | D340: 568.17 | E340: 573.4 | F340: 6119852 | G340: Wed, 16 Jul 2025 00:00:00 GMT | H340: =B340/E340-1 -> 0.00059295431 | J340: 512.64 | K340: 515.14 | L340: 506.2105 | M340: 512.51 | N340: 1848780 | O340: Wed, 16 Jul 2025 00:00:00 GMT | P340: =J340/M340-1 -> 0.00025365359
... B1396: 361.44281 | C1396: 362.56417 | D1396: 360.65127 | E1396: 361.7632 | F1396: 5538720.8 | G1396: Fri, 30 Apr 2021 00:00:00 GMT | H1396: =B1396/E1396-1 -> -0.00088562423 | J1396: 288.33334 | K1396: 288.63666 | L1396: 285.09 | M1396: 285.65668 | N1396: 477669 | O1396: Fri, 30 Apr 2021 00:00:00 GMT | P1396: =J1396/M1396-1 -> 0.0093701992
J1397: 287.74 | K1397: 291.23334 | L1397: 285.94 | M1397: 291.23334 | N1397: 384835 | O1397: Thu, 29 Apr 2021 00:00:00 GMT | P1397: =J1397/M1397-1 -> -0.011994987
J1398: 289.59668 | K1398: 291.94333 | L1398: 286.99335 | M1398: 287.52335 | N1398: 570701 | O1398: Wed, 28 Apr 2021 00:00:00 GMT | P1398: =J1398/M1398-1 -> 0.007210997
J1399: 287.12668 | K1399: 289 | L1399: 286.16666 | M1399: 289 | N1399: 510362 | O1399: Tue, 27 Apr 2021 00:00:00 GMT | P1399: =J1399/M1399-1 -> -0.0064820761
J1400: 288.64667 | K1400: 290.69 | L1400: 286.72467 | M1400: 288.81332 | N1400: 584516 | O1400: Mon, 26 Apr 2021 00:00:00 GMT | P1400: =J1400/M1400-1 -> -0.00057701632
J1401: 291.84332 | K1401: 294.305 | L1401: 280.90668 | M1401: 283.73 | N1401: 833546 | O1401: Fri, 23 Apr 2021 00:00:00 GMT | P1401: =J1401/M1401-1 -> 0.028595214
...

Sheet Product Lines
A2: https://www.intuitive.com/en-gb/-/media/ISI/Intuitive/Pdf/intuitive-company-press-facts-europe-1096203.pdf

Sheet Management

Sheet Table Formatting
B2: [Bold Title] | G2: [Bold Title]
B3: Line Titles | G3: <-- General
B4: Line Titles | G4: <-- Info
B5: Line Titles | G5: <-- General
B6: Line Titles | G6: <-- Info
B7: Line Titles | G7: <-- General
B8: Line Titles | G8: <-- Info
