Workbook

Sheet Main
B2: LHX
B3: Price | C3: 254.23 | D3: 10/22/2026
B4: SO | C4: 186.214 | D4: Q2'26
B5: MC | C5: =C3*C4 -> 47341.185
B6: Cash | C6: =1521 -> 1521 | D6: Q2'26
B7: Debt | C7: =1815+9184 -> 10999 | D7: Q2'26
B8: EV | C8: =C5-C6+C7 -> 56819.185
B10: L3Harris Technologies, Inc. (LHX)
B12: Founder(s): L3 Technologies & Harris Corporation | F12: Registered Exchange: NYSE | N12: Resources:
B13: Founded: 1895 - 2019 merger of equals | F13: Address: 1025 West NASA Boulevard, Melbourne, FL 32919 U.S. | N13: SEC filings | Q13: https://www.sec.gov/edgar/browse/?CIK=202058&owner=exclude
B14: Headquarters: Melbourne, FL | F14: Investor Relations Contact: | N14: Company Homepage | Q14: https://www.l3harris.com/
B15: Current CEO: Samir Mehta | F15: Investors Relation Department | O15: Company IR Page | R15: https://investors.l3harris.com/overview/default.aspx
B16: Employees: 45,000 | F16: Phone: | G16: (321) 727 - 9100 | I16: Email: | N16: Earnings Calls | Q16: https://seekingalpha.com/symbol/LHX/earnings/transcripts
B17: Industry: Aerospace & Defense | N17: Equity Analysis | Q17: https://stockanalysis.com/stocks/lhx/company/
B18: Sector: Industrials | N18: MacroTrends | Q18: https://www.macrotrends.net/stocks/charts/LHX/l3harris-technologies-inc/income-statement
B19: IPO: 2019 | N19: ROIC, WACC | Q19: https://www.gurufocus.com/term/wacc/LHX
B20: Fiscal Year: [February - January] | N20: Godel Terminal | Q20: https://app.godelterminal.com/
A22: Company Overview:
B23: L3Harris Technologies, Inc. provides mission-critical solutions for government and commercial customers worldwide
B24: The Company operates through three segments: Space & Mission Systems (SMS), Communications & Spectrum Dominance (CSD), and Missile Solutions (MSL)
C25: The SMS segment integrates satellite and payload capabilities, including missile warning and defense, with maritime, air special missions, and other global defense and civil government programs
C26: The CSD segment provides tactical radios, software, waveforms, satellite terminals, and end-to-end battlefield systems for the U.S. Department of Defense, international, federal, and state agency customers
C27: Its MSL segment unites propulsion, hypersonic, and other advanced missile technologies
D28: broadband communications; integrated vision solutions, such as helmet-mounted integrated night vision goggles with image intensifier tubes and weapon-mounted sights, aiming lasers, and range finders; and public safety radios and system applications and equipment
B29: The Company was formerly known as Harris Corporation and changed its name to L3Harris Technologies, Inc. in June 2019
B30: L3Harris Technologies, Inc. was founded in 1895 and is headquartered in Melbourne, Florida
A32: Business Segments and Geographical Info:
B33: L3Harris is a trusted US defense prime with end-to-end tech solutions connectiong the psace, air, land and cyber domains for national security interests … Primarily US based but support clients in over 100 countries worldwide
C34: The Company's capabilities have defense and civil government applications, as well as commercial applications
B35: The Company operates through three segments: Space & Mission Systems (SMS), Communications & Spectrum Dominance (CSD), and Missile Solutions (MSL)
C36: Communication Systems (“CS”) | G36: Enables warfighters across all domains with solutions critical to mission success even in the most contested environments
G37: Leading provider of resilient communication solutions for the U.S. Department of War (“DoW”) and international, federal, and state agency customers in the following business sectors:
G38: - | H38: Tactical Communications: Design, manufacture and sustainment of resilient and interoperable secure communication solutions that include tactical radios, software, waveforms, satellite terminals and end-to-end battlefield systems
G39: - | H39: Broadband Communications: Design, manufacture and sustainment of resilient and secure communication solutions that include intelligence, reconnaissance and surveillance (“ISR”) and tactical data links, software and integrated broadband networks
G40: - | H40: Integrated Vision Solutions: Design, manufacture and sustainment of a full suite of helmet-mounted integrated night vision goggles with leading-edge image intensifier tubes, as well as weapon-mounted sights, aiming lasers, and range finders
G41: - | H41: Public Safety and Professional Communications (“PSPC”): State-of-the-art communication equipment, systems and applications for federal agencies, state and local government first responders, utilities and transit agencies
C42: Integrated Mission Systems (“IMS”) | G42: Delivers differentiated mission capabilities and prime systems integration to support multi-mission ISR, passive sensing and targeting, electronic attack, autonomy, power and communications, networks and sensors
G43: IMS specializes in system design, development, integration, production, modernization and sustainment for national security and international customers in the following business sectors
G44: - | H44: ISR: Airborne passive sensing and targeting, mission systems development, integration and life-cycle management for strategic reconnaissance and air superiority platforms, national command and control, tactical surveillance, electronic attack, agile strike, mobility, and classified platforms
G45: - | H45: Maritime: Power, electrical, imaging, communication and sensor systems for naval platforms; integrated autonomous vessels for surface and undersea operations; fleet management; in-service support; missionization prototyping; and naval integration
G46: - | H46: Targeting & Sensor Systems (“TSS”): Multi-domain, multi-spectral electro-optical (“EO”) and infrared (“IR”) sensor systems supporting ISR and target acquisition missions; manufacturing of specialty laser and filter glass materials, laser range finders, target designators and transmitters; and highly scalable autonomous solutions
G47: - | H47: Defense Electronics(“DE”): Space communications and space flight avionics; 360-degree visible/midwave IR passive surveillance; protected GPS communications, navigation and range-testing solutions; and precision electronic components
G48: - | H48: Comm. Avi Solutions (“CAS dispo group”): On March 28, 2025, the CAS disposal group was divested. See Note 13: Acquisitions and Divestitures in the Notes for further information
C49: Space & Airborne Systems (“SAS”) | G49: Supplies full mission solutions as a prime and subsystem integrator in the space, airborne and cyber domains
G50: Provides top-tier capabilities in the design, development, integration, production and sustainment of weapons systems for national security, civil government and international customers in the following business sectors
G51: - | H51: Space Systems: ISR; position, navigation and timing; weather and climate monitoring; missile defense and ground-based space surveillance networks
G52: - | H52: Intel & Cyber: Situational awareness, optical networks and advanced wireless solutions for classified intelligence and defense customers
G53: - | H53: Mission Networks: Communications and networking solutions for air traffic management
G54: - | H54: Airborne Combat Systems: Sensors, processors, hardened electronics, unmanned aircraft systems, precision weapons, infrared search and tracking, distributed aperture systems and precision pointing, weapons release systems; antennas for aircraft platforms; and threat warning and countermeasures for airborne, ground and maritime platforms
C55: Aerojet Rocketdyne (“AR”) | G55: Provides propulsion, power and armament products and systems to U.S. Government, including the DoW, National Aeronautics and Space Administration ("NASA") and major aerospace and defense prime contractors in the following business sectors
G56: - | H56: Missile Solutions: Propulsion technologies and armament systems for strategic defense, missile defense, hypersonic, tactical and fuzing systems
G57: - | H57: Space Propulsion and Power Systems (“SPPS”): Premier propulsion and power systems for national security, space and exploration missions

Sheet Model
B1: [Use for Graphing] | C1: Q1 2020 | G1: Q1 2021 | K1: Q1 2022 | O1: Q1 2023 | S1: Q1 2024 | W1: Q1 2025 | AA1: Q1 2026
B2: Quarterly
B3: Revenues | C3: {="Q"&MOD(_xlfn.SEQUENCE(1,28)-1,4)+1&" "&(2020+INT((_xlfn.SEQUENCE(1,28)-1)/4))} -> Q1 2020 | D3: Q2 2020 | E3: Q3 2020 | F3: Q4 2020 | G3: Q1 2021 | H3: Q2 2021 | I3: Q3 2021 | J3: Q4 2021 | K3: Q1 2022 | L3: Q2 2022 | M3: Q3 2022 | N3: Q4 2022 | O3: Q1 2023 | P3: Q2 2023 | Q3: Q3 2023 | R3: Q4 2023 | S3: Q1 2024 | T3: Q2 2024 | U3: Q3 2024 | V3: Q4 2024 | W3: Q1 2025 | X3: Q2 2025 | Y3: Q3 2025 | Z3: Q4 2025 | AA3: Q1 2026 | AB3: Q2 2026 | AC3: Q3 2026 | AD3: Q4 2026 | AI3: 2020 | AJ3: =AI3+1 -> 2021 | AK3: =AJ3+1 -> 2022 | AL3: =AK3+1 -> 2023 | AM3: =AL3+1 -> 2024 | AN3: =AM3+1 -> 2025 | AO3: =AN3+1 -> 2026 | AP3: =AO3+1 -> 2027 | AQ3: =AP3+1 -> 2028 | ... CV3: =CU3+1 -> 2085
B4: Space & Mission Systems | W4: 2411 | X4: 2770 | Y4: =1462+1700 -> 3162 | Z4: =2995+8357-SUM(W4:Y4) -> 3009 | AA4: 2990 | AB4: 2966 | AN4: =SUM(W4:Z4) -> 11352 | AO4: =AN4*(1+AO10) -> 13054.8 | AP4: =AO4*(1+AP10) -> 14621.376 | AQ4: =AP4*(1+AQ10) -> 16229.727 | AR4: =AQ4*(1+AR10) -> 17852.7 | AS4: =AR4*(1+AS10) -> 19459.443 | AT4: =AS4*(1+AT10) -> 21016.199 | AU4: =AT4*(1+AU10) -> 22487.332 | AV4: =AU4*(1+AV10) -> 23836.572 | ... AX4: =AW4*(1+AX10) -> 26279.821
B5: Communication & Spectrum Dominance | W5: 1809 | X5: 1861 | Y5: 1809 | Z5: =7330-SUM(W5:Y5) -> 1851 | AA5: 1855 | AB5: 1943 | AN5: =SUM(W5:Z5) -> 7330 | AO5: =AN5*(1+AO11) -> 7549.9 | AP5: =AO5*(1+AP11) -> 7700.898 | AQ5: =AP5*(1+AQ11) -> 7931.9249 | AR5: =AQ5*(1+AR11) -> 8249.2019 | AS5: =AR5*(1+AS11) -> 8661.662 | AT5: =AS5*(1+AT11) -> 9008.1285 | AU5: =AT5*(1+AU11) -> 9278.3724 | AV5: =AU5*(1+AV11) -> 9510.3317 | ... AX5: =AW5*(1+AX11) -> 9846.0464
B6: Missile Solutions | W6: 840 | X6: 925 | Y6: 755 | Z6: =3392-SUM(W6:Y6) -> 872 | AA6: 990 | AB6: 1054 | AN6: =SUM(W6:Z6) -> 3392 | AO6: =AN6*(1+AO12) -> 3900.8 | AP6: =AO6*(1+AP12) -> 4388.4 | AQ6: =AP6*(1+AQ12) -> 4827.24 | AR6: =AQ6*(1+AR12) -> 5261.6916 | AS6: =AR6*(1+AS12) -> 5682.6269 | AT6: =AS6*(1+AT12) -> 6080.4108 | AU6: =AT6*(1+AU12) -> 6445.2355 | AV6: =AU6*(1+AV12) -> 6799.7234 | ... AX6: =AW6*(1+AX12) -> 7425.298
B7: Intersegment | W7: -60 | X7: -72 | Y7: -67 | Z7: =-209-SUM(W7:Y7) -> -10 | AA7: -91 | AB7: -82 | AN7: =SUM(W7:Z7) -> -209 | AO7: =AN7*(1+AO13) -> -275.88 | AP7: =AO7*(1+AP13) -> -344.85 | AQ7: =AP7*(1+AQ13) -> -420.717 | AR7: =AQ7*(1+AR13) -> -488.03172 | AS7: =AR7*(1+AS13) -> -546.59553 | AT7: =AS7*(1+AT13) -> -601.25508 | AU7: =AT7*(1+AU13) -> -661.38059 | AV7: =AU7*(1+AV13) -> -727.51865 | ... AX7: =AW7*(1+AX13) -> -880.29756
B8: Ttl Revenues | W8: =SUM(W4:W6)+W7 -> 5000 | X8: =SUM(X4:X6)+X7 -> 5484 | Y8: =SUM(Y4:Y6)+Y7 -> 5659 | Z8: =SUM(Z4:Z6)+Z7 -> 5722 | AA8: =SUM(AA4:AA6)+AA7 -> 5744 | AB8: =SUM(AB4:AB6)+AB7 -> 5881 | AN8: =SUM(W8:Z8) -> 21865 | AO8: =SUM(AO4:AO6)+AO7 -> 24229.62 | AP8: =SUM(AP4:AP6)+AP7 -> 26365.824 | AQ8: =SUM(AQ4:AQ6)+AQ7 -> 28568.175 | AR8: =SUM(AR4:AR6)+AR7 -> 30875.562 | AS8: =SUM(AS4:AS6)+AS7 -> 33257.137 | AT8: =SUM(AT4:AT6)+AT7 -> 35503.483 | AU8: =SUM(AU4:AU6)+AU7 -> 37549.56 | AV8: =SUM(AV4:AV6)+AV7 -> 39419.109 | ... AX8: =SUM(AX4:AX6)+AX7 -> 42670.868
B10: SMS Growth Y/y | AA10: =AA4/W4-1 -> 0.24014932 | AB10: =AB4/X4-1 -> 0.070758123 | AN10: =AN4/AM4-1 -> #DIV/0! | AO10: 0.15 | AP10: 0.12 | AQ10: 0.11 | AR10: 0.1 | AS10: 0.09 | AT10: 0.08 | AU10: 0.07 | AV10: 0.06 | AW10: 0.05 | AX10: 0.05
B11: CSD Growth Y/y | AA11: =AA5/W5-1 -> 0.025428413 | AB11: =AB5/X5-1 -> 0.044062332 | AN11: =AN5/AM5-1 -> #DIV/0! | AO11: 0.03 | AP11: 0.02 | AQ11: 0.03 | AR11: 0.04 | AS11: 0.05 | AT11: 0.04 | AU11: 0.03 | AV11: 0.025 | AW11: 0.02 | AX11: 0.015
B12: MSL Growth Y/y | AA12: =AA6/W6-1 -> 0.17857143 | AB12: =AB6/X6-1 -> 0.13945946 | AN12: =AN6/AM6-1 -> #DIV/0! | AO12: 0.15 | AP12: 0.125 | AQ12: 0.1 | AR12: 0.09 | AS12: 0.08 | AT12: 0.07 | AU12: 0.06 | AV12: 0.055 | AW12: 0.05 | AX12: 0.04
B13: Intersegment | AA13: =AA7/W7-1 -> 0.51666667 | AB13: =AB7/X7-1 -> 0.13888889 | AN13: =AN7/AM7-1 -> #DIV/0! | AO13: 0.32 | AP13: 0.25 | AQ13: 0.22 | AR13: 0.16 | AS13: 0.12 | AT13: 0.1 | AU13: 0.1 | AV13: 0.1 | AW13: 0.1 | AX13: 0.1
B14: Ttl Revenue Growth Y/y | AA14: =AA8/W8-1 -> 0.1488 | AB14: =AB8/X8-1 -> 0.072392414 | AN14: =AN8/AM8-1 -> #DIV/0! | AO14: =AO8/AN8-1 -> 0.10814635 | AP14: =AP8/AO8-1 -> 0.088164982 | AQ14: =AQ8/AP8-1 -> 0.083530532 | AR14: =AR8/AQ8-1 -> 0.080767728 | AS14: =AS8/AR8-1 -> 0.077134616 | AT14: =AT8/AS8-1 -> 0.067544789 | AU14: =AU8/AT8-1 -> 0.057630315 | ... AX14: =AX8/AW8-1 -> 0.039020032
B16: SMS % of Revenues | W16: =W4/W8 -> 0.4822 | X16: =X4/X8 -> 0.50510576 | Y16: =Y4/Y8 -> 0.55875596 | Z16: =Z4/Z8 -> 0.52586508 | AA16: =AA4/AA8 -> 0.52054318 | AB16: =AB4/AB8 -> 0.504336 | AN16: =AN4/AN8 -> 0.51918591
B17: CSD % of Revenues | W17: =W5/W8 -> 0.3618 | X17: =X5/X8 -> 0.33935084 | Y17: =Y5/Y8 -> 0.31966779 | Z17: =Z5/Z8 -> 0.32348829 | AA17: =AA5/AA8 -> 0.32294568 | AB17: =AB5/AB8 -> 0.33038599 | AN17: =AN5/AN8 -> 0.33523897
B18: MSL % of Revenues | W18: =W6/W8 -> 0.168 | X18: =X6/X8 -> 0.1686725 | Y18: =Y6/Y8 -> 0.1334158 | Z18: =Z6/Z8 -> 0.15239427 | AA18: =AA6/AA8 -> 0.17235376 | AB18: =AB6/AB8 -> 0.17922122 | AN18: =AN6/AN8 -> 0.15513378
B20: U.S. Revenues | X20: 2380 | Z20: =1000-SUM(W20:Y20) -> -1380 | AA20: 2540 | AB20: =2505+1076+922 -> 4503 | AM20: =SUM(S20:V20) -> 0 | AN20: =SUM(W20:Z20) -> 1000
B21: International Revenues | X21: 362 | Z21: =1000-SUM(W21:Y21) -> 638 | AA21: 427 | AB21: =439+819+120 -> 1378 | AM21: =SUM(S21:V21) -> 0 | AN21: =SUM(W21:Z21) -> 1000
B22: Intersegment Revenues | X22: 28 | Z22: =1000-SUM(W22:Y22) -> 972 | AA22: 23 | AB22: =22+48+12 -> 82 | AM22: =SUM(S22:V22) -> 0 | AN22: =SUM(W22:Z22) -> 1000
B23: Ttl Revenues | W23: =SUM(W20:W22) -> 0 | X23: =SUM(X20:X22) -> 2770 | Y23: =SUM(Y20:Y22) -> 0 | Z23: =SUM(Z20:Z22) -> 230 | AA23: =SUM(AA20:AA22) -> 2990 | AB23: =SUM(AB20:AB22) -> 5963 | AM23: =SUM(S23:V23) -> 0 | AN23: =SUM(W23:Z23) -> 3000
B25: U.S. Growth Y/y | W25: =W19/S19-1 -> #DIV/0! | X25: =X19/T19-1 -> #DIV/0! | Y25: =Y19/U19-1 -> #DIV/0! | Z25: =Z19/V19-1 -> #DIV/0! | AA25: =AA19/W19-1 -> #DIV/0! | AB25: =AB19/X19-1 -> #DIV/0! | AM25: =AM20/AL20-1 -> #DIV/0! | AN25: =AN20/AM20-1 -> #DIV/0!
B26: International Growth Y/y | W26: =W20/S20-1 -> #DIV/0! | X26: =X20/T20-1 -> #DIV/0! | Y26: =Y20/U20-1 -> #DIV/0! | Z26: =Z20/V20-1 -> #DIV/0! | AA26: =AA20/W20-1 -> #DIV/0! | AB26: =AB20/X20-1 -> 0.89201681 | AM26: =AM21/AL21-1 -> #DIV/0! | AN26: =AN21/AM21-1 -> #DIV/0!
B27: Intersegment Growth Y/y | W27: =W21/S21-1 -> #DIV/0! | X27: =X21/T21-1 -> #DIV/0! | Y27: =Y21/U21-1 -> #DIV/0! | Z27: =Z21/V21-1 -> #DIV/0! | AA27: =AA21/W21-1 -> #DIV/0! | AB27: =AB21/X21-1 -> 2.8066298 | AM27: =AM22/AL22-1 -> #DIV/0! | AN27: =AN22/AM22-1 -> #DIV/0!
B28: Ttl Revenue Growth Y/y | W28: =W23/S23-1 -> #DIV/0! | X28: =X23/T23-1 -> #DIV/0! | Y28: =Y23/U23-1 -> #DIV/0! | Z28: =Z23/V23-1 -> #DIV/0! | AA28: =AA23/W23-1 -> #DIV/0! | AB28: =AB23/X23-1 -> 1.1527076 | AM28: =AM23/AL23-1 -> #DIV/0! | AN28: =AN23/AM23-1 -> #DIV/0!
B30: U.S. % of Revenues | W30: =W19/W23 -> #DIV/0! | X30: =X19/X23 -> 0 | Y30: =Y19/Y23 -> #DIV/0! | Z30: =Z19/Z23 -> 0 | AA30: =AA19/AA23 -> 0 | AB30: =AB19/AB23 -> 0 | AM30: =AM20/AM23 -> #DIV/0! | AN30: =AN20/AN23 -> 0.33333333
B31: International % of Revenues | W31: =W20/W23 -> #DIV/0! | X31: =X20/X23 -> 0.85920578 | Y31: =Y20/Y23 -> #DIV/0! | Z31: =Z20/Z23 -> -6 | AA31: =AA20/AA23 -> 0.84949833 | AB31: =AB20/AB23 -> 0.7551568 | AM31: =AM21/AM23 -> #DIV/0! | AN31: =AN21/AN23 -> 0.33333333
B32: Intersegment % of Revenues | W32: =W21/W23 -> #DIV/0! | X32: =X21/X23 -> 0.13068592 | Y32: =Y21/Y23 -> #DIV/0! | Z32: =Z21/Z23 -> 2.773913 | AA32: =AA21/AA23 -> 0.14280936 | AB32: =AB21/AB23 -> 0.23109173 | AM32: =AM22/AM23 -> #DIV/0! | AN32: =AN22/AN23 -> 0.33333333
B34: Revenues | C34: 4626 | D34: 4445 | E34: 4463 | F34: 4660 | G34: 4567 | H34: 4668 | I34: 4229 | J34: 4350 | K34: 4103 | L34: 4135 | M34: 4246 | N34: 4578 | O34: 4471 | P34: 4693 | Q34: 4915 | R34: 5340 | S34: 5211 | T34: 5299 | U34: 5292 | V34: 5523 | W34: 5132 | X34: 5426 | Y34: 5659 | Z34: 5648 | AA34: 5744 | AB34: 5881 | AI34: =SUM(C34:F34) -> 18194 | AJ34: =SUM(G34:J34) -> 17814 | AK34: =SUM(K34:N34) -> 17062 | AL34: =SUM(O34:R34) -> 19419 | AM34: =SUM(S34:V34) -> 21325 | AN34: =SUM(W34:Z34) -> 21865 | AO34: =AO8 -> 24229.62 | AP34: =AP8 -> 26365.824 | AQ34: =AQ8 -> 28568.175 | AR34: =AR8 -> 30875.562 | AS34: =AS8 -> 33257.137 | AT34: =AT8 -> 35503.483 | AU34: =AU8 -> 37549.56 | AV34: =AV8 -> 39419.109 | ... AX34: =AX8 -> 42670.868
B35: COGS | C35: 3298 | D35: 3175 | E35: 3152 | F35: 3261 | G35: 3213 | H35: 3251 | I35: 2921 | J35: 3053 | K35: 2860 | L35: 2907 | M35: 3052 | N35: 3316 | O35: 3305 | P35: 3506 | Q35: 3608 | R35: 3887 | S35: 3863 | T35: 3939 | U35: 3873 | V35: 4126 | W35: 3782 | X35: 4091 | Y35: 4165 | Z35: 4202 | AA35: 4342 | AB35: 4379 | AI35: =SUM(C35:F35) -> 12886 | AJ35: =SUM(G35:J35) -> 12438 | AK35: =SUM(K35:N35) -> 12135 | AL35: =SUM(O35:R35) -> 14306 | AM35: =SUM(S35:V35) -> 15801 | AN35: =SUM(W35:Z35) -> 16240 | AO35: =AO34*(1-AO49) -> 17996.297 | AP35: =AP34*(1-AP49) -> 19582.94 | AQ35: =AQ34*(1-AQ49) -> 21218.713 | AR35: =AR34*(1-AR49) -> 22932.501 | AS35: =AS34*(1-AS49) -> 24701.39 | AT35: =AT34*(1-AT49) -> 26369.84 | AU35: =AU34*(1-AU49) -> 27889.543 | AV35: =AV34*(1-AV49) -> 29278.131 | ... AX35: =AX34*(1-AX49) -> 31693.341
B36: GP | C36: =C34-C35 -> 1328 | D36: =D34-D35 -> 1270 | E36: =E34-E35 -> 1311 | F36: =F34-F35 -> 1399 | G36: =G34-G35 -> 1354 | H36: =H34-H35 -> 1417 | I36: =I34-I35 -> 1308 | J36: =J34-J35 -> 1297 | ... AB36: =AB34-AB35 -> 1502 | AI36: =SUM(C36:F36) -> 5308 | AJ36: =SUM(G36:J36) -> 5376 | AK36: =SUM(K36:N36) -> 4927 | AL36: =SUM(O36:R36) -> 5113 | AM36: =SUM(S36:V36) -> 5524 | AN36: =SUM(W36:Z36) -> 5625 | AO36: =AO34*AO49 -> 6233.3232 | AP36: =AP34*AP49 -> 6782.8841 | AQ36: =AQ34*AQ49 -> 7349.462 | AR36: =AR34*AR49 -> 7943.0613 | AS36: =AS34*AS49 -> 8555.7463 | AT36: =AT34*AT49 -> 9133.6424 | AU36: =AU34*AU49 -> 9660.0171 | AV36: =AV34*AV49 -> 10140.978 | ... AX36: =AX34*AX49 -> 10977.527
B37: G&A | C37: 812 | D37: 855 | E37: 817 | F37: 831 | G37: 863 | H37: 1036 | I37: 793 | J37: 575 | K37: 745 | L37: 744 | M37: 1544 | N37: 767 | O37: 773 | P37: 787 | Q37: 828 | R37: 1299 | S37: 970 | T37: 884 | U37: 924 | V37: 790 | W37: 825 | X37: 764 | Y37: 873 | Z37: 1053 | AA37: 750 | AB37: 848 | AI37: =SUM(C37:F37) -> 3315 | AJ37: =SUM(G37:J37) -> 3267 | AK37: =SUM(K37:N37) -> 3800 | AL37: =SUM(O37:R37) -> 3687 | AM37: =SUM(S37:V37) -> 3568 | AN37: =SUM(W37:Z37) -> 3515 | AO37: =AO34*AO50 -> 3634.443 | AP37: =AP34*AP50 -> 3954.8736 | AQ37: =AQ34*AQ50 -> 4285.2263 | AR37: =AR34*AR50 -> 4631.3343 | AS37: =AS34*AS50 -> 4988.5705 | AT37: =AT34*AT50 -> 5325.5224 | AU37: =AU34*AU50 -> 5632.434 | AV37: =AV34*AV50 -> 5912.8663 | ... AX37: =AX34*AX50 -> 6400.6302
B38: OI | C38: =C36-C37 -> 516 | D38: =D36-D37 -> 415 | E38: =E36-E37 -> 494 | F38: =F36-F37 -> 568 | G38: =G36-G37 -> 491 | H38: =H36-H37 -> 381 | I38: =I36-I37 -> 515 | J38: =J36-J37 -> 722 | ... AB38: =AB36-AB37 -> 654 | AI38: =SUM(C38:F38) -> 1993 | AJ38: =SUM(G38:J38) -> 2109 | AK38: =SUM(K38:N38) -> 1127 | AL38: =SUM(O38:R38) -> 1426 | AM38: =SUM(S38:V38) -> 1956 | AN38: =SUM(W38:Z38) -> 2110 | AO38: =AO36-AO37 -> 2598.8802 | AP38: =AP36-AP37 -> 2828.0105 | AQ38: =AQ36-AQ37 -> 3064.2357 | AR38: =AR36-AR37 -> 3311.727 | AS38: =AS36-AS37 -> 3567.1758 | AT38: =AT36-AT37 -> 3808.12 | AU38: =AU36-AU37 -> 4027.5831 | AV38: =AV36-AV37 -> 4228.1118 | ... AX38: =AX36-AX37 -> 4576.897
B39: Non-service Pension & Other Income | C39: 0 | D39: 0 | E39: 0 | F39: 0 | G39: 0 | H39: 0 | I39: 0 | J39: 0 | K39: 0 | L39: 0 | M39: 0 | N39: 0 | O39: 0 | P39: 0 | Q39: 0 | R39: 0 | S39: 0 | T39: 0 | U39: 0 | V39: 0 | W39: 0 | X39: 0 | Y39: 0 | Z39: 0 | AA39: 0 | AB39: 0 | AI39: =SUM(C39:F39) -> 0 | AJ39: =SUM(G39:J39) -> 0 | AK39: =SUM(K39:N39) -> 0 | AL39: =SUM(O39:R39) -> 0 | AM39: =SUM(S39:V39) -> 0 | AN39: =SUM(W39:Z39) -> 0 | AO39: =AN55*$BH$55 -> 46.5015 | AP39: =AO55*$BH$55 -> 119.21604 | AQ39: =AP55*$BH$55 -> 204.7227 | AR39: =AQ55*$BH$55 -> 303.65075 | AS39: =AR55*$BH$55 -> 416.81386 | AT39: =AS55*$BH$55 -> 544.93991 | AU39: =AT55*$BH$55 -> 687.95915 | AV39: =AU55*$BH$55 -> 845.54697 | ... AX39: =AW55*$BH$55 -> 1203.3021
B40: Interest Income (Expense) | C40: -295 | D40: -79 | E40: 24 | F40: -321 | G40: -26 | H40: 201 | I40: 71 | J40: -134 | K40: 38 | L40: 41 | M40: 29 | N40: 38 | O40: -20 | P40: -28 | Q40: -79 | R40: -78 | S40: -88 | T40: -86 | U40: -65 | V40: -120 | W40: -66 | X40: -47 | Y40: -54 | Z40: -11 | AA40: -63 | AB40: 56 | AI40: =SUM(C40:F40) -> -671 | AJ40: =SUM(G40:J40) -> 112 | AK40: =SUM(K40:N40) -> 146 | AL40: =SUM(O40:R40) -> -205 | AM40: =SUM(S40:V40) -> -359 | AN40: =SUM(W40:Z40) -> -178 | AO40: =AN74*(-$BC$72) -> -678.795 | AP40: =AO74*(-$BC$72) -> -634.67332 | AQ40: =AP74*(-$BC$72) -> -593.41956 | AR40: =AQ74*(-$BC$72) -> -554.84729 | AS40: =AR74*(-$BC$72) -> -518.78221 | AT40: =AS74*(-$BC$72) -> -485.06137 | AU40: =AT74*(-$BC$72) -> -453.53238 | AV40: =AU74*(-$BC$72) -> -424.05278 | ... AX40: =AW74*(-$BC$72) -> -370.71754
B41: Pretax Income | C41: =C38+SUM(C39:C40) -> 221 | D41: =D38+SUM(D39:D40) -> 336 | E41: =E38+SUM(E39:E40) -> 518 | F41: =F38+SUM(F39:F40) -> 247 | G41: =G38+SUM(G39:G40) -> 465 | H41: =H38+SUM(H39:H40) -> 582 | I41: =I38+SUM(I39:I40) -> 586 | J41: =J38+SUM(J39:J40) -> 588 | ... AB41: =AB38+SUM(AB39:AB40) -> 710 | AI41: =SUM(C41:F41) -> 1322 | AJ41: =SUM(G41:J41) -> 2221 | AK41: =SUM(K41:N41) -> 1273 | AL41: =SUM(O41:R41) -> 1221 | AM41: =SUM(S41:V41) -> 1597 | AN41: =SUM(W41:Z41) -> 1932 | AO41: =AO38+SUM(AO39:AO40) -> 1966.5867 | AP41: =AP38+SUM(AP39:AP40) -> 2312.5532 | AQ41: =AQ38+SUM(AQ39:AQ40) -> 2675.5388 | AR41: =AR38+SUM(AR39:AR40) -> 3060.5305 | AS41: =AS38+SUM(AS39:AS40) -> 3465.2075 | AT41: =AT38+SUM(AT39:AT40) -> 3867.9985 | AU41: =AU38+SUM(AU39:AU40) -> 4262.0099 | AV41: =AV38+SUM(AV39:AV40) -> 4649.606 | ... AX41: =AX38+SUM(AX39:AX40) -> 5409.4816
B42: Taxes | C42: 26 | D42: 58 | E42: 87 | F42: 63 | G42: 60 | H42: 169 | I42: 107 | J42: 104 | K42: 61 | L42: 55 | M42: -20 | N42: 116 | O42: 34 | P42: 21 | Q42: 18 | R42: -50 | S42: 5 | T42: 23 | U42: 26 | V42: 31 | W42: 73 | X42: 66 | Y42: 105 | Z42: 82 | AA42: 77 | AB42: 110 | AI42: =SUM(C42:F42) -> 234 | AJ42: =SUM(G42:J42) -> 440 | AK42: =SUM(K42:N42) -> 212 | AL42: =SUM(O42:R42) -> 23 | AM42: =SUM(S42:V42) -> 85 | AN42: =SUM(W42:Z42) -> 326 | AO42: =AO41*AO52 -> 294.98801 | AP42: =AP41*AP52 -> 346.88298 | AQ42: =AQ41*AQ52 -> 401.33082 | AR42: =AR41*AR52 -> 459.07957 | AS42: =AS41*AS52 -> 519.78112 | AT42: =AT41*AT52 -> 580.19978 | AU42: =AU41*AU52 -> 639.30148 | AV42: =AV41*AV52 -> 697.4409 | ... AX42: =AX41*AX52 -> 811.42224
B43: Net Income | C43: =C41-C42 -> 195 | D43: =D41-D42 -> 278 | E43: =E41-E42 -> 431 | F43: =F41-F42 -> 184 | G43: =G41-G42 -> 405 | H43: =H41-H42 -> 413 | I43: =I41-I42 -> 479 | J43: =J41-J42 -> 484 | ... AB43: =AB41-AB42 -> 600 | AI43: =SUM(C43:F43) -> 1088 | AJ43: =SUM(G43:J43) -> 1781 | AK43: =SUM(K43:N43) -> 1061 | AL43: =SUM(O43:R43) -> 1198 | AM43: =SUM(S43:V43) -> 1512 | AN43: =SUM(W43:Z43) -> 1606 | AO43: =AO41-AO42 -> 1671.5987 | AP43: =AP41-AP42 -> 1965.6702 | AQ43: =AQ41-AQ42 -> 2274.208 | AR43: =AR41-AR42 -> 2601.4509 | AS43: =AS41-AS42 -> 2945.4264 | AT43: =AT41-AT42 -> 3287.7987 | AU43: =AU41-AU42 -> 3622.7084 | AV43: =AV41-AV42 -> 3952.1651 | ... AX43: =AX41-AX42 -> 4598.0594
B44: non-controlling interest | C44: 0 | D44: 0 | E44: 0 | F44: 0 | G44: 0 | H44: 0 | I44: 0 | J44: 0 | K44: 0 | L44: 0 | M44: 0 | N44: 0 | O44: 0 | P44: 0 | Q44: 0 | R44: 0 | S44: 0 | T44: 0 | U44: 4 | V44: 0 | W44: 0 | X44: 0 | Y44: 0 | Z44: 0 | AA44: 0 | AB44: 14 | AI44: =SUM(C44:F44) -> 0 | AJ44: =SUM(G44:J44) -> 0 | AK44: =SUM(K44:N44) -> 0 | AL44: =SUM(O44:R44) -> 0 | AM44: =SUM(S44:V44) -> 4 | AN44: =SUM(W44:Z44) -> 0 | AO44: 0 | AP44: 0 | AQ44: 0 | AR44: 0 | AS44: 0 | AT44: 0 | AU44: 0 | AV44: 0 | AW44: 0 | AX44: 0
B45: Net Income attr to LHX | C45: =C43-C44 -> 195 | D45: =D43-D44 -> 278 | E45: =E43-E44 -> 431 | F45: =F43-F44 -> 184 | G45: =G43-G44 -> 405 | H45: =H43-H44 -> 413 | I45: =I43-I44 -> 479 | J45: =J43-J44 -> 484 | ... AB45: =AB43-AB44 -> 586 | AI45: =SUM(C45:F45) -> 1088 | AJ45: =SUM(G45:J45) -> 1781 | AK45: =SUM(K45:N45) -> 1061 | AL45: =SUM(O45:R45) -> 1198 | AM45: =SUM(S45:V45) -> 1508 | AN45: =SUM(W45:Z45) -> 1606 | AO45: =AO43-AO44 -> 1671.5987 | AP45: =AP43-AP44 -> 1965.6702 | AQ45: =AQ43-AQ44 -> 2274.208 | AR45: =AR43-AR44 -> 2601.4509 | AS45: =AS43-AS44 -> 2945.4264 | AT45: =AT43-AT44 -> 3287.7987 | AU45: =AU43-AU44 -> 3622.7084 | AV45: =AV43-AV44 -> 3952.1651 | ... AX45: =AX43-AX44 -> 4598.0594 | AY45: =AX45*(1+$BH$56) -> 4655.5351 | AZ45: =AY45*(1+$BH$56) -> 4713.7293 | BA45: =AZ45*(1+$BH$56) -> 4772.6509 | BB45: =BA45*(1+$BH$56) -> 4832.309 | BC45: =BB45*(1+$BH$56) -> 4892.7129 | BD45: =BC45*(1+$BH$56) -> 4953.8718 | BE45: =BD45*(1+$BH$56) -> 5015.7952 | BF45: =BE45*(1+$BH$56) -> 5078.4926 | ... CV45: =CU45*(1+$BH$56) -> 8557.0913
B46: SC | C46: 217 | D46: 216 | E46: 213 | F46: 214 | G46: 207 | H46: 204 | I46: 200 | J46: 201 | K46: 193 | L46: 192 | M46: 191 | N46: 192 | O46: 190 | P46: 189 | Q46: 189 | R46: 190 | S46: 190 | T46: 190 | U46: 190 | V46: 190 | W46: 188 | X46: 187.1 | Y46: 187 | Z46: 187 | AA46: 187 | AB46: 186.214 | AI46: =AVERAGE(C46:F46) -> 215 | AJ46: =AVERAGE(G46:J46) -> 203 | AK46: =AVERAGE(K46:N46) -> 192 | AL46: =AVERAGE(O46:R46) -> 189.5 | AM46: =AVERAGE(S46:V46) -> 190 | AN46: =AVERAGE(W46:Z46) -> 187.275
B47: EPS | C47: =C45/C46 -> 0.89861751 | D47: =D45/D46 -> 1.287037 | E47: =E45/E46 -> 2.0234742 | F47: =F45/F46 -> 0.85981308 | G47: =G45/G46 -> 1.9565217 | H47: =H45/H46 -> 2.0245098 | I47: =I45/I46 -> 2.395 | J47: =J45/J46 -> 2.4079602 | ... AB47: =AB45/AB46 -> 3.146917 | AI47: =SUM(C47:F47) -> 5.0689418 | AJ47: =SUM(G47:J47) -> 8.7839917 | AK47: =SUM(K47:N47) -> 5.5050153 | AL47: =SUM(O47:R47) -> 6.3256753 | AM47: =SUM(S47:V47) -> 7.9368421 | AN47: =SUM(W47:Z47) -> 8.5759466
B49: Gross Profit Margin | C49: =C36/C34 -> 0.28707307 | D49: =D36/D34 -> 0.28571429 | E49: =E36/E34 -> 0.2937486 | F49: =F36/F34 -> 0.30021459 | G49: =G36/G34 -> 0.29647471 | H49: =H36/H34 -> 0.30355613 | I49: =I36/I34 -> 0.30929298 | J49: =J36/J34 -> 0.29816092 | ... AB49: =AB36/AB34 -> 0.25539874 | AI49: =AI36/AI34 -> 0.29174453 | AJ49: =AJ36/AJ34 -> 0.30178511 | AK49: =AK36/AK34 -> 0.28877037 | AL49: =AL36/AL34 -> 0.26329883 | AM49: =AM36/AM34 -> 0.25903869 | AN49: =AN36/AN34 -> 0.25726046 | AO49: 0.25726046 | AP49: 0.25726046 | AQ49: 0.25726046 | AR49: 0.25726046 | AS49: 0.25726046 | AT49: 0.25726046 | AU49: 0.25726046 | AV49: 0.25726046 | AW49: 0.25726046 | AX49: 0.25726046
B50: G&A as % of Revenue | C50: =C37/C34 -> 0.17552962 | D50: =D37/D34 -> 0.19235096 | E50: =E37/E34 -> 0.18306072 | F50: =F37/F34 -> 0.17832618 | G50: =G37/G34 -> 0.18896431 | H50: =H37/H34 -> 0.22193659 | I50: =I37/I34 -> 0.18751478 | J50: =J37/J34 -> 0.13218391 | ... AB50: =AB37/AB34 -> 0.14419316 | AI50: =AI37/AI34 -> 0.18220292 | AJ50: =AJ37/AJ34 -> 0.18339508 | AK50: =AK37/AK34 -> 0.22271715 | AL50: =AL37/AL34 -> 0.1898656 | AM50: =AM37/AM34 -> 0.16731536 | AN50: =AN37/AN34 -> 0.1607592 | AO50: 0.15 | AP50: 0.15 | AQ50: 0.15 | AR50: 0.15 | AS50: 0.15 | AT50: 0.15 | AU50: 0.15 | AV50: 0.15 | AW50: 0.15 | AX50: 0.15
B51: Operating Profit Margin | C51: =C38/C34 -> 0.11154345 | D51: =D38/D34 -> 0.09336333 | E51: =E38/E34 -> 0.11068788 | F51: =F38/F34 -> 0.12188841 | G51: =G38/G34 -> 0.1075104 | H51: =H38/H34 -> 0.081619537 | I51: =I38/I34 -> 0.1217782 | J51: =J38/J34 -> 0.16597701 | ... AB51: =AB38/AB34 -> 0.11120558 | AI51: =AI38/AI34 -> 0.10954161 | AJ51: =AJ38/AJ34 -> 0.11839003 | AK51: =AK38/AK34 -> 0.066053218 | AL51: =AL38/AL34 -> 0.073433235 | AM51: =AM38/AM34 -> 0.091723329 | AN51: =AN38/AN34 -> 0.096501258 | AO51: =AO38/AO34 -> 0.10726046 | AP51: =AP38/AP34 -> 0.10726046 | ... AX51: =AX38/AX34 -> 0.10726046
B52: Effective Tax Rate | C52: =C42/C41 -> 0.11764706 | D52: =D42/D41 -> 0.17261905 | E52: =E42/E41 -> 0.16795367 | F52: =F42/F41 -> 0.25506073 | G52: =G42/G41 -> 0.12903226 | H52: =H42/H41 -> 0.29037801 | I52: =I42/I41 -> 0.18259386 | J52: =J42/J41 -> 0.17687075 | ... AB52: =AB42/AB41 -> 0.15492958 | AI52: =AI42/AI41 -> 0.17700454 | AJ52: =AJ42/AJ41 -> 0.19810896 | AK52: =AK42/AK41 -> 0.16653574 | AL52: =AL42/AL41 -> 0.018837019 | AM52: =AM42/AM41 -> 0.053224796 | AN52: =AN42/AN41 -> 0.16873706 | AO52: 0.15 | AP52: 0.15 | AQ52: 0.15 | AR52: 0.15 | AS52: 0.15 | AT52: 0.15 | AU52: 0.15 | AV52: 0.15 | AW52: 0.15 | AX52: 0.15
B53: Net Profit Margin | C53: =C45/C34 -> 0.042153048 | D53: =D45/D34 -> 0.062542182 | E53: =E45/E34 -> 0.096571813 | F53: =F45/F34 -> 0.039484979 | G53: =G45/G34 -> 0.088679658 | H53: =H45/H34 -> 0.088474722 | I53: =I45/I34 -> 0.11326555 | J53: =J45/J34 -> 0.11126437 | ... AB53: =AB45/AB34 -> 0.099642918 | AI53: =AI45/AI34 -> 0.059799934 | AJ53: =AJ45/AJ34 -> 0.099977546 | AK53: =AK45/AK34 -> 0.062184972 | AL53: =AL45/AL34 -> 0.061692157 | AM53: =AM45/AM34 -> 0.070715123 | AN53: =AN45/AN34 -> 0.07345072 | AO53: =AO45/AO34 -> 0.068989886 | AP53: =AP45/AP34 -> 0.074553718 | ... AX53: =AX45/AX34 -> 0.10775641
B55: Cash & C.E.s | R55: 560 | S55: 477 | T55: 547 | U55: 539 | V55: 615 | W55: 517 | X55: 482 | Y55: 339 | Z55: 1069 | AA55: 590 | AB55: 1521 | AL55: =R55 -> 560 | AM55: =V55 -> 615 | AN55: =Z55 -> 1069 | AO55: =AN55+AO45 -> 2740.5987 | AP55: =AO55+AP45 -> 4706.2689 | AQ55: =AP55+AQ45 -> 6980.4769 | AR55: =AQ55+AR45 -> 9581.9278 | AS55: =AR55+AS45 -> 12527.354 | AT55: =AS55+AT45 -> 15815.153 | AU55: =AT55+AU45 -> 19437.861 | AV55: =AU55+AV45 -> 23390.026 | ... AX55: =AW55+AX45 -> 32260.177 | AZ55: Invested Capital | BC55: Avg. (2024-2025) | BE55: Projected ROIC: | BG55: ROIC | BH55: 0.0435
B56: A/R | R56: 1230 | S56: 1209 | T56: 1230 | U56: 1042 | V56: 1072 | W56: 1501 | X56: 1437 | Y56: 1528 | Z56: 1371 | AA56: 1912 | AB56: 1950 | AL56: =R56 -> 1230 | AM56: =V56 -> 1072 | AN56: =Z56 -> 1371 | AZ56: 2024 | BA56: 2025 | BC56: 2024-2025 | BE56: 2025 | BG56: Terminal | BH56: 0.0125
B57: ST Contract Assets | R57: 3196 | S57: 3502 | T57: 3209 | U57: 3401 | V57: 3230 | W57: 3643 | X57: 3857 | Y57: 3677 | Z57: 3566 | AA57: 3530 | AB57: 3674 | AL57: =R57 -> 3196 | AM57: =V57 -> 3230 | AN57: =Z57 -> 3566 | AZ57: =SUM(AM55:AM58)-AM71+AM62+AM65+AM63 -> 36685 | BA57: =SUM(AN55:AN58)-AN71+AN62+AN65+AN63 -> 36604 | BC57: =AVERAGE(AZ57:BA57) -> 36644.5 | BE57: =AVERAGE(AO43)*(1-AO53) -> 1556.2753 | BG57: RFR (10-year yield) | BH57: =BC66 -> 0.0499
B58: Inventories | R58: 1472 | S58: 1476 | T58: 1432 | U58: 1399 | V58: 1330 | W58: 1252 | X58: 1258 | Y58: 1291 | Z58: 1219 | AA58: 1234 | AB58: 1272 | AL58: =R58 -> 1472 | AM58: =V58 -> 1330 | AN58: =Z58 -> 1219 | BE58: =BE57/BC57 -> 0.042469547 | BG58: ERP (Avg. market return - (less) RFR) | BH58: =8.95%-BH57 -> 0.0396
B59: Other ST Assets | R59: =61+430 -> 491 | S59: 466 | T59: 502 | U59: =329+462 -> 791 | V59: =379+461 -> 840 | W59: =205+478 -> 683 | X59: =93+481 -> 574 | Y59: =281+477 -> 758 | Z59: 484 | AA59: 702 | AB59: 656 | AL59: =R59 -> 491 | AM59: =V59 -> 840 | AN59: =Z59 -> 484 | AZ59: Capital Structure | BG59: Equity β (1-year avg.) | BH59: ='Notes | Quant Analysis'!$S$206 -> 0.53448517
B60: ST Assets of Business held for Sale | R60: 1106 | S60: 1136 | T60: 1127 | U60: 1130 | V60: 1131 | W60: 0 | X60: 0 | Y60: 0 | Z60: 884 | AA60: 926 | AB60: 1010 | AL60: =R60 -> 1106 | AM60: =V60 -> 1131 | AN60: =Z60 -> 884 | AZ60: Mkt Cap | BC60: =Main!C5 -> 47341.185 | BG60: Discount (Cost of Equity) | BH60: =+BH57+(BH58*BH59) -> 0.071065613
B61: PP&E | R61: 2862 | S61: 2836 | T61: 2800 | U61: 2795 | V61: 2806 | W61: 2755 | X61: 2742 | Y61: 2761 | Z61: 2665 | AA61: 2658 | AB61: 2686 | AL61: =R61 -> 2862 | AM61: =V61 -> 2806 | AN61: =Z61 -> 2665 | AZ61: Debt to Ttl Mkt Cap | BC61: =Main!C7/(Main!C7+BC60) -> 0.18853214
B62: Goodwill | R62: 19979 | S62: 20070 | T62: 20367 | U62: 20433 | V62: 20325 | W62: 20337 | X62: 20372 | Y62: 20370 | Z62: 20010 | AA62: 19999 | AB62: 19996 | AL62: =R62 -> 19979 | AM62: =V62 -> 20325 | AN62: =Z62 -> 20010 | AZ62: Mkt Equity to Ttl Mkt Cap | BC62: =BC60/(BC60+Main!C7) -> 0.81146786 | BG62: NPV | BH62: =NPV(BH60,AO45:CL45) -> 56298.455
B63: Intangibles | R63: 8540 | S63: 8340 | T63: 8080 | U63: 7874 | V63: 7639 | W63: 7448 | X63: 7261 | Y63: 7072 | Z63: 6509 | AA63: 6331 | AB63: 6540 | AL63: =R63 -> 8540 | AM63: =V63 -> 7639 | AN63: =Z63 -> 6509 | AZ63: LT Debt / Equity | BC63: =AN74/AN80 -> 0.53185638 | BG63: SC | BH63: =Main!C4 -> 186.214
B64: LT Tax Assets | R64: 91 | S64: 113 | T64: 134 | U64: 119 | V64: 120 | W64: 128 | X64: 89 | Y64: 87 | Z64: 76 | AA64: 71 | AB64: 65 | AL64: =R64 -> 91 | AM64: =V64 -> 120 | AN64: =Z64 -> 76 | BG64: FV | BH64: =BH62/BH63 -> 302.33202
B65: Other LT Assets | R65: 2160 | S65: 2191 | T65: 2229 | U65: 2366 | V65: 2893 | W65: 2984 | X65: 3168 | Y65: 3131 | Z65: 3342 | AA65: 3427 | AB65: 3568 | AL65: =R65 -> 2160 | AM65: =V65 -> 2893 | AN65: =Z65 -> 3342 | AZ65: Cost of Equity | BG65: CP | BH65: =Main!C3 -> 254.23
B66: Ttl Assets | R66: =SUM(R55:R65) -> 41687 | S66: =SUM(S55:S65) -> 41816 | T66: =SUM(T55:T65) -> 41657 | U66: =SUM(U55:U65) -> 41889 | V66: =SUM(V55:V65) -> 42001 | W66: =SUM(W55:W65) -> 41248 | X66: =SUM(X55:X65) -> 41240 | Y66: =SUM(Y55:Y65) -> 41014 | ... AB66: =SUM(AB55:AB65) -> 42938 | AL66: =SUM(AL55:AL65) -> 41687 | AM66: =SUM(AM55:AM65) -> 42001 | AN66: =SUM(AN55:AN65) -> 41195 | AZ66: RFR (10-year yield) | BC66: 0.0499 | BG66: Change Δ | BH66: =BH64/BH65-1 -> 0.1892067 | BI66: =IF(BH66>0,"Upside","Downside") -> Upside
AZ67: Equity β (1-year avg.) | BC67: ='Notes | Quant Analysis'!$S$206 -> 0.53448517 | BG67: {=_xlfn.IFS(BH66>=25%,"Strong Buy",BH66>=10.00001%,"Buy",AND(BH66<=10%,BH66>=-4.9999%),"Hold",AND(BH66<=-5%,BH66>=-14.999999%),"Sell",BH66<=-15%,"Strong Sell")} -> Buy
B68: ST Debt | R68: =1602+363 -> 1965 | S68: =2203+365 -> 2568 | T68: =2102+617 -> 2719 | U68: =1177+640 -> 1817 | V68: 515 | W68: =535+740 -> 1275 | X68: =985+141 -> 1126 | Y68: 725 | Z68: 673 | AA68: =350+1816 -> 2166 | AB68: 1815 | AL68: =R68 -> 1965 | AM68: =V68 -> 515 | AN68: =Z68 -> 673 | AZ68: Market Return(1-year avg.) | BC68: 0.17
B69: A/P | R69: 2106 | S69: 2112 | T69: 1896 | U69: 2049 | V69: 2005 | W69: 2047 | X69: 2033 | Y69: 1902 | Z69: 2461 | AA69: 1930 | AB69: 2085 | AL69: =R69 -> 2106 | AM69: =V69 -> 2005 | AN69: =Z69 -> 2461 | AZ69: Cost of Equity | BC69: =(BC66+BC67)*(BC68-BC66) -> 0.070184659
B70: ST Contract Liabilities | R70: 1900 | S70: 1777 | T70: 1889 | U70: 1878 | V70: 2142 | W70: 2124 | X70: 2317 | Y70: 2231 | Z70: 2262 | AA70: 2736 | AB70: 2936 | AL70: =R70 -> 1900 | AM70: =V70 -> 2142 | AN70: =Z70 -> 2262
B71: ST Comp Liabilities | R71: 544 | S71: 379 | T71: 445 | U71: 402 | V71: 419 | W71: 314 | X71: 444 | Y71: 486 | Z71: 482 | AA71: 391 | AB71: 376 | AL71: =R71 -> 544 | AM71: =V71 -> 419 | AN71: =Z71 -> 482 | AZ71: Cost of Debt
B72: Other ST Liabilities | R72: =88+1129 -> 1217 | S72: =1174+182 -> 1356 | T72: =1515+274 -> 1789 | U72: =35+1549 -> 1584 | V72: 2317 | W72: 1689 | X72: 1402 | Y72: 1294 | Z72: 1235 | AA72: 1267 | AB72: 1192 | AL72: =R72 -> 1217 | AM72: =V72 -> 2317 | AN72: =Z72 -> 1235 | AZ72: Cost of Debt | BC72: 0.065
B73: ST Liabilities of Business held for Sale | R73: 272 | S73: 285 | T73: 243 | U73: 243 | V73: 235 | W73: 0 | X73: 0 | Y73: 0 | Z73: 113 | AA73: 111 | AB73: 113 | AL73: =R73 -> 272 | AM73: =V73 -> 235 | AN73: =Z73 -> 113 | AZ73: Tax Rate | BC73: 0.17
B74: LT Debt | R74: 11160 | S74: 11140 | T74: 10533 | U74: 11093 | V74: 11081 | W74: 10977 | X74: 10976 | Y74: 10997 | Z74: 10443 | AA74: 9191 | AB74: 9184 | AL74: =R74 -> 11160 | AM74: =V74 -> 11081 | AN74: =Z74 -> 10443 | AO74: =AN74+AO40 -> 9764.205 | AP74: =AO74+AP40 -> 9129.5317 | AQ74: =AP74+AQ40 -> 8536.1121 | AR74: =AQ74+AR40 -> 7981.2648 | AS74: =AR74+AS40 -> 7462.4826 | AT74: =AS74+AT40 -> 6977.4212 | AU74: =AT74+AU40 -> 6523.8889 | AV74: =AU74+AV40 -> 6099.8361 | ... AX74: =AW74+AX40 -> 5332.6292 | AZ74: After Tax Cost of Debt | BC74: =BC72*(1-BC73) -> 0.05395
B75: LT Tax Liabilities | R75: 815 | S75: 683 | T75: 443 | U75: 885 | V75: 942 | W75: 842 | X75: 800 | Y75: 1039 | Z75: 1114 | AA75: 1225 | AB75: 1369 | AL75: =R75 -> 815 | AM75: =V75 -> 942 | AN75: =Z75 -> 1114
B76: LT Subsidiary PS Conversion Liability | R76: 0 | S76: 0 | T76: 0 | U76: 0 | V76: 0 | W76: 0 | X76: 0 | Y76: 0 | Z76: 0 | AA76: 0 | AB76: 130 | AL76: =R76 -> 0 | AM76: =V76 -> 0 | AN76: =Z76 -> 0 | AZ76: WACC | BC76: =(BC62*BC69)+(BC61*BC74*(1-BC73)) -> 0.065394782
B77: LT Subsidiary Warrant Liabilities | R77: 0 | S77: 0 | T77: 0 | U77: 0 | V77: 0 | W77: 0 | X77: 0 | Y77: 0 | Z77: 0 | AA77: 0 | AB77: 186 | AL77: =R77 -> 0 | AM77: =V77 -> 0 | AN77: =Z77 -> 0
B78: Other LT Liabilities | R78: 2879 | S78: 2826 | T78: 2796 | U78: 2876 | V78: 2766 | W78: 2850 | X78: 2864 | Y78: 2808 | Z78: 2777 | AA78: 2683 | AB78: 2702 | AL78: =R78 -> 2879 | AM78: =V78 -> 2766 | AN78: =Z78 -> 2777
B79: Ttl Liabilities | R79: =SUM(R68:R78) -> 22858 | S79: =SUM(S68:S78) -> 23126 | T79: =SUM(T68:T78) -> 22753 | U79: =SUM(U68:U78) -> 22827 | V79: =SUM(V68:V78) -> 22422 | W79: =SUM(W68:W78) -> 22118 | X79: =SUM(X68:X78) -> 21962 | Y79: =SUM(Y68:Y78) -> 21482 | ... AB79: =SUM(AB68:AB78) -> 22088 | AL79: =SUM(AL68:AL78) -> 22858 | AM79: =SUM(AM68:AM78) -> 22422 | AN79: =SUM(AN68:AN78) -> 21560
B80: Ttl SE | R80: 18829 | S80: 18730 | T80: 18904 | U80: 19062 | V80: 19579 | W80: 19130 | X80: 19278 | Y80: 19532 | Z80: 19635 | AA80: 19680 | AB80: 19882 | AL80: =R80 -> 18829 | AM80: =V80 -> 19579 | AN80: =Z80 -> 19635
B81: Ttl L + SE | R81: =R79+R80 -> 41687 | S81: =S79+S80 -> 41856 | T81: =T79+T80 -> 41657 | U81: =U79+U80 -> 41889 | V81: =V79+V80 -> 42001 | W81: =W79+W80 -> 41248 | X81: =X79+X80 -> 41240 | Y81: =Y79+Y80 -> 41014 | ... AB81: =AB79+AB80 -> 41970 | AL81: =AL79+AL80 -> 41687 | AM81: =AM79+AM80 -> 42001 | AN81: =AN79+AN80 -> 41195
B83: Current Ratio | R83: =SUM(R55:R60)/SUM(R68:R73) -> 1.0063718 | S83: =SUM(S55:S60)/SUM(S68:S73) -> 0.97510912 | T83: =SUM(T55:T60)/SUM(T68:T73) -> 0.89600267 | U83: =SUM(U55:U60)/SUM(U68:U73) -> 1.0412643 | V83: =SUM(V55:V60)/SUM(V68:V73) -> 1.0766409 | W83: =SUM(W55:W60)/SUM(W68:W73) -> 1.0197342 | X83: =SUM(X55:X60)/SUM(X68:X73) -> 1.0390604 | Y83: =SUM(Y55:Y60)/SUM(Y68:Y73) -> 1.1438686 | ... AB83: =SUM(AB55:AB60)/SUM(AB68:AB73) -> 1.1838676 | AL83: =SUM(AL55:AL60)/SUM(AL68:AL73) -> 1.0063718 | AM83: =SUM(AM55:AM60)/SUM(AM68:AM73) -> 1.0766409 | AN83: =SUM(AN55:AN60)/SUM(AN68:AN73) -> 1.189178
B84: Quick Ratio | R84: =(SUM(R55:R60)-R58)/SUM(R68:R73) -> 0.82246377 | S84: =(SUM(S55:S60)-S58)/SUM(S68:S73) -> 0.80099092 | T84: =(SUM(T55:T60)-T58)/SUM(T68:T73) -> 0.73655495 | U84: =(SUM(U55:U60)-U58)/SUM(U68:U73) -> 0.86579707 | V84: =(SUM(V55:V60)-V58)/SUM(V68:V73) -> 0.90239748 | W84: =(SUM(W55:W60)-W58)/SUM(W68:W73) -> 0.85165794 | X84: =(SUM(X55:X60)-X58)/SUM(X68:X73) -> 0.86724939 | Y84: =(SUM(Y55:Y60)-Y58)/SUM(Y68:Y73) -> 0.94938234 | ... AB84: =(SUM(AB55:AB60)-AB58)/SUM(AB68:AB73) -> 1.0345192 | AL84: =(SUM(AL55:AL60)-AL58)/SUM(AL68:AL73) -> 0.82246377 | AM84: =(SUM(AM55:AM60)-AM58)/SUM(AM68:AM73) -> 0.90239748 | AN84: =(SUM(AN55:AN60)-AN58)/SUM(AN68:AN73) -> 1.0204816
B85: Cash Ratio | R85: =SUM(R58:R59)/SUM(R68:R73) -> 0.24525237 | S85: =SUM(S58:S59)/SUM(S68:S73) -> 0.22909048 | T85: =SUM(T58:T59)/SUM(T68:T73) -> 0.2153435 | U85: =SUM(U58:U59)/SUM(U68:U73) -> 0.27467703 | V85: =SUM(V58:V59)/SUM(V68:V73) -> 0.28429189 | W85: =SUM(W58:W59)/SUM(W68:W73) -> 0.25976641 | X85: =SUM(X58:X59)/SUM(X68:X73) -> 0.25020486 | Y85: =SUM(Y58:Y59)/SUM(Y68:Y73) -> 0.30867731 | ... AB85: =SUM(AB58:AB59)/SUM(AB68:AB73) -> 0.22637079 | AL85: =SUM(AL58:AL59)/SUM(AL68:AL73) -> 0.24525237 | AM85: =SUM(AM58:AM59)/SUM(AM68:AM73) -> 0.28429189 | AN85: =SUM(AN58:AN59)/SUM(AN68:AN73) -> 0.23567672
B86: Fixed Asset Turnover Ratio | R86: =R34/SUM(R61) -> 1.8658281 | S86: =S34/SUM(S61) -> 1.8374471 | T86: =T34/SUM(T61) -> 1.8925 | U86: =U34/SUM(U61) -> 1.893381 | V86: =V34/SUM(V61) -> 1.9682823 | W86: =W34/SUM(W61) -> 1.8627949 | X86: =X34/SUM(X61) -> 1.9788476 | Y86: =Y34/SUM(Y61) -> 2.0496197 | ... AB86: =AB34/SUM(AB61) -> 2.1895011 | AL86: =AL34/SUM(AL61) -> 6.7851153 | AM86: =AM34/SUM(AM61) -> 7.5997862 | AN86: =AN34/SUM(AN61) -> 8.2045028
B87: Ttl Asset Turnover Ratio | R87: =R34/R66 -> 0.12809749 | S87: =S34/S66 -> 0.12461737 | T87: =T34/T66 -> 0.12720551 | U87: =U34/U66 -> 0.12633388 | V87: =V34/V66 -> 0.13149687 | W87: =W34/W66 -> 0.12441815 | X87: =X34/X66 -> 0.13157129 | Y87: =Y34/Y66 -> 0.13797728 | ... AB87: =AB34/AB66 -> 0.13696493 | AL87: =AL34/AL66 -> 0.46582868 | AM87: =AM34/AM66 -> 0.50772601 | AN87: =AN34/AN66 -> 0.5307683
B88: Inventory Turnover Ratio | R88: =R35/AVERAGE(O58:R58) -> 2.640625 | S88: =S35/AVERAGE(P58:S58) -> 2.6207598 | T88: =T35/AVERAGE(Q58:T58) -> 2.6979452 | U88: =U35/AVERAGE(R58:U58) -> 2.6807406 | V88: =V35/AVERAGE(S58:V58) -> 2.9277985 | W88: =W35/AVERAGE(T58:W58) -> 2.7947534 | X88: =X35/AVERAGE(U58:X58) -> 3.1234969 | Y88: =Y35/AVERAGE(V58:Y58) -> 3.2469304 | ... AB88: =AB35/AVERAGE(Y58:AB58) -> 3.4920255 | AL88: =AL35/AVERAGE(AI58:AL58) -> 9.71875 | AM88: =AM35/AVERAGE(AJ58:AM58) -> 11.278373 | AN88: =AN35/AVERAGE(AK58:AN58) -> 12.116389
B89: Return on Assets | R89: =R45/R66 -> 0.003022525 | S89: =S45/S66 -> 0.006815573 | T89: =T45/T66 -> 0.0088100439 | U89: =U45/U66 -> 0.0095490463 | V89: =V45/V66 -> 0.010856884 | W89: =W45/W66 -> 0.0093580295 | X89: =X45/X66 -> 0.011105723 | Y89: =Y45/Y66 -> 0.011264446 | ... AB89: =AB45/AB66 -> 0.013647585 | AL89: =AL45/AL66 -> 0.028737976 | AM89: =AM45/AM66 -> 0.035903907 | AN89: =AN45/AN66 -> 0.038985314
B90: Return on Equity | R90: =R45/R80 -> 0.0066918052 | S90: =S45/S80 -> 0.015216231 | T90: =T45/T80 -> 0.019413881 | U90: =U45/U80 -> 0.020984157 | V90: =V45/V80 -> 0.02329026 | W90: =W45/W80 -> 0.020177731 | X90: =X45/X80 -> 0.023757651 | Y90: =Y45/Y80 -> 0.023653492 | ... AB90: =AB45/AB80 -> 0.029473896 | AL90: =AL45/AL80 -> 0.063625259 | AM90: =AM45/AM80 -> 0.077021298 | AN90: =AN45/AN80 -> 0.081792717
B92: Net Income | C92: =C45 -> 195 | D92: =D45 -> 278 | E92: =E45 -> 431 | F92: =F45 -> 184 | G92: =G45 -> 405 | H92: =H45 -> 413 | I92: =I45 -> 479 | J92: =J45 -> 484 | ... AB92: =AB45 -> 586 | AI92: =SUM(C92:F92) -> 1088 | AJ92: =SUM(G92:J92) -> 1781 | AK92: =SUM(K92:N92) -> 1061 | AL92: =SUM(O92:R92) -> 1198 | AM92: =SUM(S92:V92) -> 1508 | AN92: =SUM(W92:Z92) -> 1606
B93: CFFO | C93: 533 | D93: 802 | E93: 757 | F93: 698 | G93: 661 | H93: 720 | I93: 484 | J93: 822 | K93: 39 | L93: 749 | M93: 588 | N93: 782 | O93: 350 | P93: 414 | Q93: 543 | R93: 789 | S93: -104 | T93: 754 | U93: 780 | V93: 1129 | W93: -42 | X93: 640 | Y93: 546 | Z93: 1962 | AA93: -95 | AB93: 879 | AI93: =SUM(C93:F93) -> 2790 | AJ93: =SUM(G93:J93) -> 2687 | AK93: =SUM(K93:N93) -> 2158 | AL93: =SUM(O93:R93) -> 2096 | AM93: =SUM(S93:V93) -> 2559 | AN93: =SUM(W93:Z93) -> 3106
B94: CapEx, net | C94: -48 | D94: -60 | E94: -86 | F94: -174 | G94: -67 | H94: -61 | I94: -79 | J94: -135 | K94: -55 | L94: -62 | M94: -64 | N94: -71 | O94: -71 | P94: -93 | Q94: -148 | R94: -137 | S94: -115 | T94: -97 | U94: -78 | V94: -118 | W94: -59 | X94: -88 | Y94: -119 | Z94: -158 | AA94: -99 | AB94: -108 | AI94: =SUM(C94:F94) -> -368 | AJ94: =SUM(G94:J94) -> -342 | AK94: =SUM(K94:N94) -> -252 | AL94: =SUM(O94:R94) -> -449 | AM94: =SUM(S94:V94) -> -408 | AN94: =SUM(W94:Z94) -> -424
B95: FCF | C95: =C93+C94 -> 485 | D95: =D93+D94 -> 742 | E95: =E93+E94 -> 671 | F95: =F93+F94 -> 524 | G95: =G93+G94 -> 594 | H95: =H93+H94 -> 659 | I95: =I93+I94 -> 405 | J95: =J93+J94 -> 687 | ... AB95: =AB93+AB94 -> 771 | AI95: =SUM(C95:F95) -> 2422 | AJ95: =SUM(G95:J95) -> 2345 | AK95: =SUM(K95:N95) -> 1906 | AL95: =SUM(O95:R95) -> 1647 | AM95: =SUM(S95:V95) -> 2151 | AN95: =SUM(W95:Z95) -> 2682
B96: SC | C96: =C46 -> 217 | D96: =D46 -> 216 | E96: =E46 -> 213 | F96: =F46 -> 214 | G96: =G46 -> 207 | H96: =H46 -> 204 | I96: =I46 -> 200 | J96: =J46 -> 201 | ... AB96: =AB46 -> 186.214 | AI96: =AI46 -> 215 | AJ96: =AJ46 -> 203 | AK96: =AK46 -> 192 | AL96: =AL46 -> 189.5 | AM96: =AM46 -> 190 | AN96: =AN46 -> 187.275
B97: FCF per Share | C97: =C95/C96 -> 2.235023 | D97: =D95/D96 -> 3.4351852 | E97: =E95/E96 -> 3.1502347 | F97: =F95/F96 -> 2.4485981 | G97: =G95/G96 -> 2.8695652 | H97: =H95/H96 -> 3.2303922 | I97: =I95/I96 -> 2.025 | J97: =J95/J96 -> 3.4179104 | ... AB97: =AB95/AB96 -> 4.1403976 | AI97: =SUM(C97:F97) -> 11.269041 | AJ97: =SUM(G97:J97) -> 11.542868 | AK97: =SUM(K97:N97) -> 9.9418039 | AL97: =SUM(O97:R97) -> 8.6883598 | AM97: =SUM(S97:V97) -> 11.321053 | AN97: =SUM(W97:Z97) -> 14.343541
B99: CFFO Margin | C99: =C93/C34 -> 0.11521833 | D99: =D93/D34 -> 0.18042745 | E99: =E93/E34 -> 0.16961685 | F99: =F93/F34 -> 0.14978541 | G99: =G93/G34 -> 0.14473396 | H99: =H93/H34 -> 0.15424165 | I99: =I93/I34 -> 0.11444786 | J99: =J93/J34 -> 0.18896552 | ... AB99: =AB93/AB34 -> 0.14946438 | AI99: =AI93/AI34 -> 0.15334726 | AJ99: =AJ93/AJ34 -> 0.15083642 | AK99: =AK93/AK34 -> 0.1264799 | AL99: =AL93/AL34 -> 0.10793553 | AM99: =AM93/AM34 -> 0.12 | AN99: =AN93/AN34 -> 0.14205351
B100: FCF Margin | C100: =C95/C34 -> 0.1048422 | D100: =D95/D34 -> 0.16692913 | E100: =E95/E34 -> 0.1503473 | F100: =F95/F34 -> 0.11244635 | G100: =G95/G34 -> 0.1300635 | H100: =H95/H34 -> 0.14117395 | I100: =I95/I34 -> 0.095767321 | J100: =J95/J34 -> 0.15793103 | ... AB100: =AB95/AB34 -> 0.13110015 | AI100: =AI95/AI34 -> 0.13312081 | AJ100: =AJ95/AJ34 -> 0.13163804 | AK100: =AK95/AK34 -> 0.11171023 | AL100: =AL95/AL34 -> 0.084813842 | AM100: =AM95/AM34 -> 0.10086753 | AN100: =AN95/AN34 -> 0.12266179
B101: CapEx as % of Revenue | C101: =C94/C34 -> -0.010376135 | D101: =D94/D34 -> -0.013498313 | E101: =E94/E34 -> -0.01926955 | F101: =F94/F34 -> -0.037339056 | G101: =G94/G34 -> -0.014670462 | H101: =H94/H34 -> -0.013067695 | I101: =I94/I34 -> -0.018680539 | J101: =J94/J34 -> -0.031034483 | ... AB101: =AB94/AB34 -> -0.018364224 | AI101: =AI94/AI34 -> -0.020226448 | AJ101: =AJ94/AJ34 -> -0.019198383 | AK101: =AK94/AK34 -> -0.014769664 | AL101: =AL94/AL34 -> -0.023121685 | AM101: =AM94/AM34 -> -0.019132474 | AN101: =AN94/AN34 -> -0.019391722

Sheet Notes | Quant Analysis
CK1: 0
P2: Employee Scope: | AN2: General Notes/Observations
Q32: Notes: | R32: [X]
R33: [Y]
R34: [Z]
AN35: Financial Stmts. Notes/Observations
P36: Institutional Ownership Snapshot | AN36: Revenues:
Q65: Notes: | R65: [X]
R66: [Y]
R67: [Z]
P69: Revenue Breakdown by Segment (Build graph for this section if applicable…. See example below) | AN69: Earnings Scope:
Q101: Notes: | R101: [X]
R102: [Y]
R103: [Z]
P105: Q/q Total Revenues, Net Income, FCF | AN105: Balance Sheet Scope:
Q134: Notes: | R134: [X]
R135: [Y]
R136: [Z]
P138: Y/y Total Revenues, Net Income, FCF | AN138: [Equity Preformance Compared to Peers]
Q167: Notes: | R167: [X]
R168: [Y]
R169: [Z]
A184: VOO Historical Returns | I184: LHX Historical Returns
A185: 753 Trading Days? (From: 10/22/2023 - 10/22/2026) | I185: 753 Trading Days? (From: 10/22/2023 - 10/22/2026)
A186: Close | B186: High | C186: Low | D186: Open | E186: Volume | F186: UTC Date | G186: Change | I186: Close | J186: High | K186: Low | L186: Open | M186: Volume | N186: UTC Date | O186: Change
A187: 702.3 | B187: 705.66 | C187: 699.68 | D187: 704.41 | E187: 6041430.3 | F187: Thu, 22 Oct 2026 00:00:00 GMT | G187: =A187/D187-1 -> -0.0029954146 | I187: 254.23 | J187: 254.785 | K187: 249.16 | L187: 249.16 | M187: 1889117.4 | N187: Thu, 22 Oct 2026 00:00:00 GMT | O187: =I187/L187-1 -> 0.020348371
A188: 710.72 | B188: 711.83 | C188: 706.33 | D188: 708.84 | E188: 6210315.6 | F188: Wed, 21 Oct 2026 00:00:00 GMT | G188: =A188/D188-1 -> 0.0026522205 | I188: 247.55 | J188: 251.54 | K188: 246.72 | L188: 249.5 | M188: 1050418.4 | N188: Wed, 21 Oct 2026 00:00:00 GMT | O188: =I188/L188-1 -> -0.0078156313
A189: 706.8 | B189: 709.81 | C189: 702.49 | D189: 704.01 | E189: 5798006.5 | F189: Tue, 20 Oct 2026 00:00:00 GMT | G189: =A189/D189-1 -> 0.0039630119 | I189: 248.77 | J189: 250.19 | K189: 243.6 | L189: 244.97 | M189: 1900703.3 | N189: Tue, 20 Oct 2026 00:00:00 GMT | O189: =I189/L189-1 -> 0.015512104
A190: 704.6 | B190: 708.17 | C190: 703.9805 | D190: 705.27 | E190: 5588525.7 | F190: Mon, 19 Oct 2026 00:00:00 GMT | G190: =A190/D190-1 -> -0.00094999078 | I190: 243.84 | J190: 246.89 | K190: 242.95 | L190: 245.16 | M190: 1235212.8 | N190: Mon, 19 Oct 2026 00:00:00 GMT | O190: =I190/L190-1 -> -0.0053842389
A191: 701.61 | B191: 710.85 | C191: 699.191 | D191: 710.75 | E191: 6095662.4 | F191: Fri, 16 Oct 2026 00:00:00 GMT | G191: =A191/D191-1 -> -0.012859655 | I191: 248.51 | J191: 248.63 | K191: 242.01 | L191: 243.54 | M191: 3372290.9 | N191: Fri, 16 Oct 2026 00:00:00 GMT | O191: =I191/L191-1 -> 0.020407325
A192: 709.43 | B192: 710.4 | C192: 702.69 | D192: 704.33 | E192: 6035492.3 | F192: Thu, 15 Oct 2026 00:00:00 GMT | G192: =A192/D192-1 -> 0.007240924 | I192: 240.5 | J192: 242.2 | K192: 238.88 | L192: 241.48 | M192: 3008243.3 | N192: Thu, 15 Oct 2026 00:00:00 GMT | O192: =I192/L192-1 -> -0.0040583071
A193: 707.43 | B193: 713.62 | C193: 704.76 | D193: 712.32 | E193: 6228217.1 | F193: Wed, 14 Oct 2026 00:00:00 GMT | G193: =A193/D193-1 -> -0.0068648922 | I193: 237.5 | J193: 239.44 | K193: 236.09 | L193: 237.88 | M193: 2427008.1 | N193: Wed, 14 Oct 2026 00:00:00 GMT | O193: =I193/L193-1 -> -0.0015974441
A194: 715.2 | B194: 715.835 | C194: 713.27 | D194: 714.54 | E194: 4959098.4 | F194: Tue, 13 Oct 2026 00:00:00 GMT | G194: =A194/D194-1 -> 0.00092367117 | I194: 234.72 | J194: 238.89 | K194: 233.61 | L194: 238.75 | M194: 1558201.5 | N194: Tue, 13 Oct 2026 00:00:00 GMT | O194: =I194/L194-1 -> -0.016879581
A195: 715.13 | B195: 716.415 | C195: 714.26 | D195: 715.81 | E195: 3635491.2 | F195: Mon, 12 Oct 2026 00:00:00 GMT | G195: =A195/D195-1 -> -0.00094997276 | I195: 238.25 | J195: 238.39 | K195: 236.01 | L195: 237.08 | M195: 1077026.2 | N195: Mon, 12 Oct 2026 00:00:00 GMT | O195: =I195/L195-1 -> 0.004935043
A196: 715.59 | B196: 716.435 | C196: 712.54 | D196: 713.54 | E196: 4345835.7 | F196: Fri, 09 Oct 2026 00:00:00 GMT | G196: =A196/D196-1 -> 0.0028729994 | I196: 236.97 | J196: 238.08 | K196: 235.0748 | L196: 237 | M196: 973952.31 | N196: Fri, 09 Oct 2026 00:00:00 GMT | O196: =I196/L196-1 -> -0.00012658228
A197: 711.28 | B197: 714.27 | C197: 708.16 | D197: 712.25 | E197: 4763330.7 | F197: Thu, 08 Oct 2026 00:00:00 GMT | G197: =A197/D197-1 -> -0.0013618814 | I197: 236.92 | J197: 237.15 | K197: 232.3427 | L197: 233.5 | M197: 1203427.4 | N197: Thu, 08 Oct 2026 00:00:00 GMT | O197: =I197/L197-1 -> 0.014646681
A198: 714.34 | B198: 715.055 | C198: 711.06 | D198: 713.06 | E198: 4675948.1 | F198: Wed, 07 Oct 2026 00:00:00 GMT | G198: =A198/D198-1 -> 0.0017950804 | I198: 233.63 | J198: 238.669 | K198: 233.01 | L198: 237.17 | M198: 978954.72 | N198: Wed, 07 Oct 2026 00:00:00 GMT | O198: =I198/L198-1 -> -0.014926002
A199: 716.2 | B199: 718.47 | C199: 715.09 | D199: 715.21 | E199: 4568431.3 | F199: Tue, 06 Oct 2026 00:00:00 GMT | G199: =A199/D199-1 -> 0.0013842088 | I199: 237.9 | J199: 239.4599 | K199: 235.3 | L199: 236.3 | M199: 1139704 | N199: Tue, 06 Oct 2026 00:00:00 GMT | O199: =I199/L199-1 -> 0.0067710537
A200: 712.32 | B200: 713.8583 | C200: 707.42 | D200: 707.44 | E200: 6172916.9 | F200: Mon, 05 Oct 2026 00:00:00 GMT | G200: =A200/D200-1 -> 0.0068981115 | I200: 236.88 | J200: 239.22 | K200: 235.545 | L200: 237.04 | M200: 1273649.3 | N200: Mon, 05 Oct 2026 00:00:00 GMT | O200: =I200/L200-1 -> -0.00067499156 | R200: Min | S200: =MIN(O187:O939) -> -0.064419904
A201: 707.54 | B201: 710.2 | C201: 705.12 | D201: 708.31 | E201: 6612533.1 | F201: Fri, 02 Oct 2026 00:00:00 GMT | G201: =A201/D201-1 -> -0.0010870946 | I201: 236.6 | J201: 238.62 | K201: 234.66 | L201: 238.22 | M201: 1528992.9 | N201: Fri, 02 Oct 2026 00:00:00 GMT | O201: =I201/L201-1 -> -0.0068004366 | R201: Max | S201: =MAX(O187:O939) -> 0.084383063
A202: 702.35 | B202: 703.725 | C202: 697.47 | D202: 702.555 | E202: 8433749.3 | F202: Thu, 01 Oct 2026 00:00:00 GMT | G202: =A202/D202-1 -> -0.0002917921 | I202: 238.4 | J202: 239.24 | K202: 236.07 | L202: 236.72 | M202: 1310076.2 | N202: Thu, 01 Oct 2026 00:00:00 GMT | O202: =I202/L202-1 -> 0.0070969922 | R202: Mean μ | S202: =AVERAGE(O187:O939) -> -0.00060403241
A203: 700.86 | B203: 707.2 | C203: 700.56 | D203: 704.58 | E203: 9876125.1 | F203: Wed, 30 Sep 2026 00:00:00 GMT | G203: =A203/D203-1 -> -0.0052797411 | I203: 236.78 | J203: 238.69 | K203: 234.01 | L203: 236.72 | M203: 1467397.4 | N203: Wed, 30 Sep 2026 00:00:00 GMT | O203: =I203/L203-1 -> 0.00025346401 | R203: Median | S203: =MEDIAN(O187:O939) -> -0.0002820079
A204: 702.46 | B204: 705 | C204: 700.74 | D204: 704.82 | E204: 7643258.6 | F204: Tue, 29 Sep 2026 00:00:00 GMT | G204: =A204/D204-1 -> -0.0033483726 | I204: 236.47 | J204: 239.36 | K204: 235.02 | L204: 236.36 | M204: 1833950.3 | N204: Tue, 29 Sep 2026 00:00:00 GMT | O204: =I204/L204-1 -> 0.00046539178 | R204: SD σ | S204: =_xlfn.STDEV.P(O187:O939) -> 0.013387238
A205: 703.61 | B205: 707.33 | C205: 701.97 | D205: 706.29 | E205: 8539385.2 | F205: Mon, 28 Sep 2026 00:00:00 GMT | G205: =A205/D205-1 -> -0.0037944754 | I205: 237.7 | J205: 240.095 | K205: 234.59 | L205: 237 | M205: 1997238.5 | N205: Mon, 28 Sep 2026 00:00:00 GMT | O205: =I205/L205-1 -> 0.0029535865 | R205: 3σ 1-Day Δ: ± | S205: =3*S204 -> 0.040161715 | U205: <- Sharpe Ratio (Risk Adjusted Return)
A206: 708.9674 | B206: 709.82021 | C206: 704.36423 | D206: 706.62343 | E206: 5482247.9 | F206: Fri, 25 Sep 2026 00:00:00 GMT | G206: =A206/D206-1 -> 0.0033171475 | I206: 237.69 | J206: 240.98 | K206: 236.79 | L206: 238.11 | M206: 1646774.7 | N206: Fri, 25 Sep 2026 00:00:00 GMT | O206: =I206/L206-1 -> -0.0017638906 | R206: β (1-year avg.) | S206: =_xlfn.COVARIANCE.P(O187:O435,G187:G435)/_xlfn.VAR.P(G187:G435) -> 0.53448517 | U206: <- Sortino Ratio (Downside Risk Adjusted Return)
A207: 705.17714 | B207: 706.76805 | C207: 701.54548 | D207: 702.26463 | E207: 9443878 | F207: Thu, 24 Sep 2026 00:00:00 GMT | G207: =A207/D207-1 -> 0.0041473149 | I207: 238.04 | J207: 242.12 | K207: 237.85 | L207: 239.15 | M207: 1450873.8 | N207: Thu, 24 Sep 2026 00:00:00 GMT | O207: =I207/L207-1 -> -0.0046414384
A208: 705.78558 | B208: 710.55332 | C208: 704.55215 | D208: 710.30895 | E208: 13844442 | F208: Wed, 23 Sep 2026 00:00:00 GMT | G208: =A208/D208-1 -> -0.0063681746 | I208: 239.21 | J208: 243.5 | K208: 239 | L208: 239.99 | M208: 1330444.9 | N208: Wed, 23 Sep 2026 00:00:00 GMT | O208: =I208/L208-1 -> -0.0032501354 | Q208: n = | R208: 1014
A209: 710.9523 | B209: 712.4684 | C209: 710.15435 | D209: 711.45102 | E209: 20783008 | F209: Tue, 22 Sep 2026 00:00:00 GMT | G209: =A209/D209-1 -> -0.00070098699 | I209: 239.89 | J209: 248.62 | K209: 239.51 | L209: 248.51 | M209: 1715492.8 | N209: Tue, 22 Sep 2026 00:00:00 GMT | O209: =I209/L209-1 -> -0.034686733 | Q209: Histogram Data | T209: Distribution Overlay | X209: SD Lines
A210: 710.9523 | B210: 712.24398 | C210: 704.14979 | D210: 704.3792 | E210: 8882600.7 | F210: Mon, 21 Sep 2026 00:00:00 GMT | G210: =A210/D210-1 -> 0.0093317662 | I210: 246.93 | J210: 248.18 | K210: 244.91 | L210: 246.61 | M210: 1461888 | N210: Mon, 21 Sep 2026 00:00:00 GMT | O210: =I210/L210-1 -> 0.0012975954 | Q210: Bin | R210: Frequency | T210: (X) 1-Day Δ | U210: (Y) Pop. Density | X210: X | Y210: Y
A211: 699.9805 | B211: 700.38945 | C211: 696.70891 | D211: 699.78102 | E211: 9618703.4 | F211: Fri, 18 Sep 2026 00:00:00 GMT | G211: =A211/D211-1 -> 0.00028507084 | I211: 247.29 | J211: 251.5 | K211: 246.11 | L211: 250.03 | M211: 2845995.2 | N211: Fri, 18 Sep 2026 00:00:00 GMT | O211: =I211/L211-1 -> -0.010958685 | Q211: -0.042 | R211: 4 | T211: =T212-0.001 -> -0.045 | U211: =_xlfn.NORM.DIST(T211,$S$202,$S$204,FALSE) -> 0.12192178 | W211: Mean | X211: =S202 -> -0.00060403241 | Y211: 0
A212: 699.23243 | B212: 700.08025 | C212: 696.81863 | D212: 699.80096 | E212: 9928828.2 | F212: Thu, 17 Sep 2026 00:00:00 GMT | G212: =A212/D212-1 -> -0.00081242873 | I212: 250.46 | J212: 252.085 | K212: 246.63 | L212: 251 | M212: 1904502.5 | N212: Thu, 17 Sep 2026 00:00:00 GMT | O212: =I212/L212-1 -> -0.0021513944 | Q212: -0.041 | R212: 1 | T212: =T213-0.001 -> -0.044 | U212: =_xlfn.NORM.DIST(T212,$S$202,$S$204,FALSE) -> 0.15575902 | X212: =S202 -> -0.00060403241 | Y212: 29.75
A213: 691.4624 | B213: 698.30481 | C213: 687.27317 | D213: 696.37976 | E213: 14204833 | F213: Wed, 16 Sep 2026 00:00:00 GMT | G213: =A213/D213-1 -> -0.0070613174 | I213: 250.74 | J213: 251.915 | K213: 248.135 | L213: 250.07 | M213: 1285323 | N213: Wed, 16 Sep 2026 00:00:00 GMT | O213: =I213/L213-1 -> 0.0026792498 | Q213: -0.04 | R213: 0 | T213: =T214-0.001 -> -0.043 | U213: =_xlfn.NORM.DIST(T213,$S$202,$S$204,FALSE) -> 0.19787997 | W213: -3σ | X213: =($S$204*-3)+$S$202 -> -0.040765747 | Y213: 0
A214: 694.41481 | B214: 697.14779 | C214: 693.30766 | D214: 696.97822 | E214: 9682716.1 | F214: Tue, 15 Sep 2026 00:00:00 GMT | G214: =A214/D214-1 -> -0.0036778912 | I214: 249.66 | J214: 253.12 | K214: 247.865 | L214: 251.9 | M214: 1445385.2 | N214: Tue, 15 Sep 2026 00:00:00 GMT | O214: =I214/L214-1 -> -0.0088924176 | Q214: -0.039 | R214: 0 | T214: =T215-0.001 -> -0.042 | U214: =_xlfn.NORM.DIST(T214,$S$202,$S$204,FALSE) -> 0.24999263 | X214: =($S$204*-3)+$S$202 -> -0.040765747 | Y214: 2
A215: 697.50686 | B215: 700.05032 | C215: 694.93348 | D215: 695.99076 | E215: 6793476.4 | F215: Mon, 14 Sep 2026 00:00:00 GMT | G215: =A215/D215-1 -> 0.002178337 | I215: 248.93 | J215: 250.2696 | K215: 245.77 | L215: 247.81 | M215: 2313915.3 | N215: Mon, 14 Sep 2026 00:00:00 GMT | O215: =I215/L215-1 -> 0.0045195916 | Q215: -0.038 | R215: 1 | T215: =T216-0.001 -> -0.041 | U215: =_xlfn.NORM.DIST(T215,$S$202,$S$204,FALSE) -> 0.31407205 | W215: -2σ | X215: =($S$204*-2)+$S$202 -> -0.027378509 | Y215: 0
A216: 700.7585 | B216: 702.68894 | C216: 700.13012 | D216: 701.19738 | E216: 5812878.2 | F216: Fri, 11 Sep 2026 00:00:00 GMT | G216: =A216/D216-1 -> -0.00062588905 | I216: 245.54 | J216: 251.8511 | K216: 244.76 | L216: 250.57 | M216: 1924090.5 | N216: Fri, 11 Sep 2026 00:00:00 GMT | O216: =I216/L216-1 -> -0.020074231 | Q216: -0.037 | R216: 3 | T216: =T217-0.001 -> -0.04 | U216: =_xlfn.NORM.DIST(T216,$S$202,$S$204,FALSE) -> 0.39238113 | X216: =($S$204*-2)+$S$202 -> -0.027378509 | Y216: 4
A217: 694.86366 | B217: 696.84855 | C217: 693.7586 | D217: 694.99332 | E217: 18360495 | F217: Thu, 10 Sep 2026 00:00:00 GMT | G217: =A217/D217-1 -> -0.00018657252 | I217: 248.37 | J217: 252.21 | K217: 246.51 | L217: 250.81 | M217: 1675802.2 | N217: Thu, 10 Sep 2026 00:00:00 GMT | O217: =I217/L217-1 -> -0.0097284797 | Q217: -0.036 | R217: 0 | T217: =T218-0.001 -> -0.039 | U217: =_xlfn.NORM.DIST(T217,$S$202,$S$204,FALSE) -> 0.48748769 | W217: -1σ | X217: =($S$204*-1)+$S$202 -> -0.013991271 | Y217: 0
A218: 699.07284 | B218: 700.90812 | C218: 697.69139 | D218: 700.54904 | E218: 4311927.8 | F218: Wed, 09 Sep 2026 00:00:00 GMT | G218: =A218/D218-1 -> -0.0021072115 | I218: 250.41 | J218: 258.04 | K218: 250.28 | L218: 256.32 | M218: 1251789.5 | N218: Wed, 09 Sep 2026 00:00:00 GMT | O218: =I218/L218-1 -> -0.023057116 | Q218: -0.035 | R218: 0 | T218: =T219-0.001 -> -0.038 | U218: =_xlfn.NORM.DIST(T218,$S$202,$S$204,FALSE) -> 0.60227651 | X218: =($S$204*-1)+$S$202 -> -0.013991271 | Y218: 18
A219: 702.26463 | B219: 705.69581 | C219: 701.56643 | D219: 705.16717 | E219: 7847677 | F219: Tue, 08 Sep 2026 00:00:00 GMT | G219: =A219/D219-1 -> -0.0041160995 | I219: 255.74 | J219: 257.06 | K219: 253.3 | L219: 253.6 | M219: 1479861.1 | N219: Tue, 08 Sep 2026 00:00:00 GMT | O219: =I219/L219-1 -> 0.0084384858 | Q219: -0.034 | R219: 3 | T219: =T220-0.001 -> -0.037 | U219: =_xlfn.NORM.DIST(T219,$S$202,$S$204,FALSE) -> 0.73995434 | W219: 1σ | X219: =($S$204*1)+$S$202 -> 0.012783206 | Y219: 0
A220: 706.19453 | B220: 708.62827 | C220: 705.08737 | D220: 707.90014 | E220: 6833680.7 | F220: Fri, 04 Sep 2026 00:00:00 GMT | G220: =A220/D220-1 -> -0.0024094009 | I220: 256.45 | J220: 259.78 | K220: 256.05 | L220: 259.52 | M220: 1213222.7 | N220: Fri, 04 Sep 2026 00:00:00 GMT | O220: =I220/L220-1 -> -0.011829531 | Q220: -0.033 | R220: 1 | T220: =T221-0.001 -> -0.036 | U220: =_xlfn.NORM.DIST(T220,$S$202,$S$204,FALSE) -> 0.90404624 | X220: =($S$204*1)+$S$202 -> 0.012783206 | Y220: 18
A221: 708.89758 | B221: 709.69054 | C221: 703.70094 | D221: 704.01014 | E221: 8616616.4 | F221: Thu, 03 Sep 2026 00:00:00 GMT | G221: =A221/D221-1 -> 0.0069422799 | I221: 260.89 | J221: 263.73636 | K221: 257.90431 | L221: 262.97999 | M221: 1420917.2 | N221: Thu, 03 Sep 2026 00:00:00 GMT | O221: =I221/L221-1 -> -0.0079473206 | Q221: -0.032 | R221: 1 | T221: =T222-0.001 -> -0.035 | U221: =_xlfn.NORM.DIST(T221,$S$202,$S$204,FALSE) -> 1.0983812 | W221: 2σ | X221: =($S$204*2)+$S$202 -> 0.026170444 | Y221: 0
A222: 701.60632 | B222: 702.72345 | C222: 698.38461 | D222: 699.05289 | E222: 7724754.5 | F222: Wed, 02 Sep 2026 00:00:00 GMT | G222: =A222/D222-1 -> 0.0036527074 | I222: 260.06396 | J222: 265.22921 | K222: 258.87963 | L222: 263.23875 | M222: 1320485.1 | N222: Wed, 02 Sep 2026 00:00:00 GMT | O222: =I222/L222-1 -> -0.012060491 | Q222: -0.031 | R222: 1 | T222: =T223-0.001 -> -0.034 | U222: =_xlfn.NORM.DIST(T222,$S$202,$S$204,FALSE) -> 1.3270652 | X222: =($S$204*2)+$S$202 -> 0.026170444 | Y222: 4
A223: 698.48435 | B223: 701.10761 | C223: 696.34964 | D223: 698.65391 | E223: 6503580 | F223: Tue, 01 Sep 2026 00:00:00 GMT | G223: =A223/D223-1 -> -0.00024270112 | I223: 262.30323 | J223: 268.2148 | K223: 260.92981 | L223: 265.22921 | M223: 1347020.6 | N223: Tue, 01 Sep 2026 00:00:00 GMT | O223: =I223/L223-1 -> -0.011031895 | Q223: -0.03 | R223: 0 | T223: =T224-0.001 -> -0.033 | U223: =_xlfn.NORM.DIST(T223,$S$202,$S$204,FALSE) -> 1.59444 | W223: 3σ | X223: =($S$204*3)+$S$202 -> 0.039557683 | Y223: 0
A224: 703.08253 | B224: 704.12984 | C224: 701.15748 | D224: 703.55132 | E224: 5756351.9 | F224: Mon, 31 Aug 2026 00:00:00 GMT | G224: =A224/D224-1 -> -0.00066632641 | I224: 264.9804 | J224: 266.5678 | K224: 260.10377 | L224: 261.79566 | M224: 2599977.7 | N224: Mon, 31 Aug 2026 00:00:00 GMT | O224: =I224/L224-1 -> 0.012164988 | Q224: -0.029 | R224: 3 | T224: =T225-0.001 -> -0.032 | U224: =_xlfn.NORM.DIST(T224,$S$202,$S$204,FALSE) -> 1.9050256 | X224: =($S$204*3)+$S$202 -> 0.039557683 | Y224: 2
A225: 705.4265 | B225: 710.84178 | C225: 704.44902 | D225: 707.57099 | E225: 8105322.5 | F225: Fri, 28 Aug 2026 00:00:00 GMT | G225: =A225/D225-1 -> -0.0030307729 | I225: 261.56676 | J225: 263.87569 | K225: 260.20329 | L225: 263.06956 | M225: 1622885.4 | N225: Fri, 28 Aug 2026 00:00:00 GMT | O225: =I225/L225-1 -> -0.0057125563 | Q225: -0.028 | R225: 2 | T225: =T226-0.001 -> -0.031 | U225: =_xlfn.NORM.DIST(T225,$S$202,$S$204,FALSE) -> 2.2634462
A226: 706.93263 | B226: 708.13454 | C226: 703.40211 | D226: 704.57868 | E226: 6773106.6 | F226: Thu, 27 Aug 2026 00:00:00 GMT | G226: =A226/D226-1 -> 0.0033409306 | I226: 260.73076 | J226: 262.20371 | K226: 258.36151 | L226: 260.89995 | M226: 1693285 | N226: Thu, 27 Aug 2026 00:00:00 GMT | O226: =I226/L226-1 -> -0.00064848369 | Q226: -0.027 | R226: 4 | T226: =T227-0.001 -> -0.03 | U226: =_xlfn.NORM.DIST(T226,$S$202,$S$204,FALSE) -> 2.6743378
A227: 702.3943 | B227: 703.51143 | C227: 700.42935 | D227: 701.09763 | E227: 7176219.4 | F227: Wed, 26 Aug 2026 00:00:00 GMT | G227: =A227/D227-1 -> 0.0018494807 | I227: 261.70609 | J227: 263.58708 | K227: 257.30358 | L227: 258.7403 | M227: 1402369.5 | N227: Wed, 26 Aug 2026 00:00:00 GMT | O227: =I227/L227-1 -> 0.01146242 | Q227: -0.026 | R227: 2 | T227: =T228-0.001 -> -0.029 | U227: =_xlfn.NORM.DIST(T227,$S$202,$S$204,FALSE) -> 3.142238
A228: 702.21476 | B228: 703.02797 | C228: 699.65135 | D228: 702.47908 | E228: 4335609.9 | F228: Tue, 25 Aug 2026 00:00:00 GMT | G228: =A228/D228-1 -> -0.00037626813 | I228: 260.91986 | J228: 262.55701 | K228: 259.70567 | L228: 261.98475 | M228: 1757363.2 | N228: Tue, 25 Aug 2026 00:00:00 GMT | O228: =I228/L228-1 -> -0.0040647318 | Q228: -0.025 | R228: 3 | T228: =T229-0.001 -> -0.028 | U228: =_xlfn.NORM.DIST(T228,$S$202,$S$204,FALSE) -> 3.6714585
A229: 700.03038 | B229: 701.58628 | C229: 698.73371 | D229: 701.16745 | E229: 7757366.3 | F229: Mon, 24 Aug 2026 00:00:00 GMT | G229: =A229/D229-1 -> -0.0016216908 | I229: 261.57671 | J229: 264.50767 | K229: 260.30281 | L229: 264.42307 | M229: 1583962.6 | N229: Mon, 24 Aug 2026 00:00:00 GMT | O229: =I229/L229-1 -> -0.010764425 | Q229: -0.024 | R229: 1 | T229: =T230-0.001 -> -0.027 | U229: =_xlfn.NORM.DIST(T229,$S$202,$S$204,FALSE) -> 4.2659414
A230: 701.90555 | B230: 703.9902 | C230: 700.63881 | D230: 702.26463 | E230: 10705589 | F230: Fri, 21 Aug 2026 00:00:00 GMT | G230: =A230/D230-1 -> -0.0005113128 | I230: 265.45811 | J230: 270.45418 | K230: 265.15954 | L230: 269.87694 | M230: 1948245.4 | N230: Fri, 21 Aug 2026 00:00:00 GMT | O230: =I230/L230-1 -> -0.016373493 | Q230: -0.023 | R230: 3 | T230: =T231-0.001 -> -0.026 | U230: =_xlfn.NORM.DIST(T230,$S$202,$S$204,FALSE) -> 4.9291029
A231: 699.21248 | B231: 704.26948 | C231: 698.67596 | D231: 702.24468 | E231: 8480360 | F231: Thu, 20 Aug 2026 00:00:00 GMT | G231: =A231/D231-1 -> -0.0043178752 | I231: 269.15042 | J231: 275.30095 | K231: 268.30448 | L231: 274.37539 | M231: 1737582.9 | N231: Thu, 20 Aug 2026 00:00:00 GMT | O231: =I231/L231-1 -> -0.019043128 | Q231: -0.022 | R231: 2 | T231: =T232-0.001 -> -0.025 | U231: =_xlfn.NORM.DIST(T231,$S$202,$S$204,FALSE) -> 5.6636657
A232: 705.09735 | B232: 708.27917 | C232: 704.28444 | D232: 706.37407 | E232: 7039831.7 | F232: Wed, 19 Aug 2026 00:00:00 GMT | G232: =A232/D232-1 -> -0.0018074246 | I232: 275.78862 | J232: 279.66007 | K232: 275.03224 | L232: 279.66007 | M232: 1082339.8 | N232: Wed, 19 Aug 2026 00:00:00 GMT | O232: =I232/L232-1 -> -0.013843416 | Q232: -0.021 | R232: 6 | T232: =T233-0.001 -> -0.024 | U232: =_xlfn.NORM.DIST(T232,$S$202,$S$204,FALSE) -> 6.4714866
A233: 703.59122 | B233: 705.53622 | C233: 703.15235 | D233: 704.79812 | E233: 5292120.7 | F233: Tue, 18 Aug 2026 00:00:00 GMT | G233: =A233/D233-1 -> -0.0017124015 | I233: 278.20703 | J233: 282.64576 | K233: 278.00798 | L233: 278.66484 | M233: 1820631.5 | N233: Tue, 18 Aug 2026 00:00:00 GMT | O233: =I233/L233-1 -> -0.0016428571 | Q233: -0.02 | R233: 8 | T233: =T234-0.001 -> -0.023 | U233: =_xlfn.NORM.DIST(T233,$S$202,$S$204,FALSE) -> 7.3533838
A234: 708.44873 | B234: 712.21405 | C234: 708.27917 | D234: 711.67045 | E234: 5759776.8 | F234: Mon, 17 Aug 2026 00:00:00 GMT | G234: =A234/D234-1 -> -0.0045269797 | I234: 277.05256 | J234: 284.58577 | K234: 276.44547 | L234: 281.65053 | M234: 2995637.4 | N234: Mon, 17 Aug 2026 00:00:00 GMT | O234: =I234/L234-1 -> -0.016325088 | Q234: -0.019 | R234: 3 | T234: =T235-0.001 -> -0.022 | U234: =_xlfn.NORM.DIST(T234,$S$202,$S$204,FALSE) -> 8.308969
A235: 711.78017 | B235: 714.05432 | C235: 710.97225 | D235: 713.79499 | E235: 4224899.3 | F235: Fri, 14 Aug 2026 00:00:00 GMT | G235: =A235/D235-1 -> -0.0028226877 | I235: 290.42847 | J235: 291.60285 | K235: 287.41292 | L235: 290.16971 | M235: 1016650.6 | N235: Fri, 14 Aug 2026 00:00:00 GMT | O235: =I235/L235-1 -> 0.0008917547 | Q235: -0.018 | R235: 4 | T235: =T236-0.001 -> -0.021 | U235: =_xlfn.NORM.DIST(T235,$S$202,$S$204,FALSE) -> 9.3364929
A236: 713.11673 | B236: 714.55304 | C236: 709.78031 | D236: 710.47353 | E236: 4562935.4 | F236: Thu, 13 Aug 2026 00:00:00 GMT | G236: =A236/D236-1 -> 0.0037203426 | I236: 287.08449 | J236: 290.40359 | K236: 284.92484 | L236: 289.68205 | M236: 1106806.5 | N236: Thu, 13 Aug 2026 00:00:00 GMT | O236: =I236/L236-1 -> -0.0089669152 | Q236: -0.017 | R236: 6 | T236: =T237-0.001 -> -0.02 | U236: =_xlfn.NORM.DIST(T236,$S$202,$S$204,FALSE) -> 10.43271
... A255: 681.41822 | B255: 685.10405 | C255: 679.17399 | D255: 680.37092 | E255: 5642108.9 | F255: Fri, 17 Jul 2026 00:00:00 GMT | G255: =A255/D255-1 -> 0.0015393186 | I255: 280.66525 | J255: 288.8162 | K255: 280.16764 | L255: 285.73098 | M255: 1143780.3 | N255: Fri, 17 Jul 2026 00:00:00 GMT | O255: =I255/L255-1 -> -0.017729014 | Q255: 0.002 | R255: 25 | T255: =T256-0.001 -> -0.001 | U255: =_xlfn.NORM.DIST(T255,$S$202,$S$204,FALSE) -> 29.78716
A256: 688.37035 | B256: 691.77161 | C256: 685.6673 | D256: 690.20563 | E256: 4734752 | F256: Thu, 16 Jul 2026 00:00:00 GMT | G256: =A256/D256-1 -> -0.0026590364 | I256: 283.07371 | J256: 286.62669 | K256: 281.11311 | L256: 285.57174 | M256: 1039769.8 | N256: Thu, 16 Jul 2026 00:00:00 GMT | O256: =I256/L256-1 -> -0.0087474733 | Q256: 0.003 | R256: 29 | T256: 0 | U256: =_xlfn.NORM.DIST(T256,$S$202,$S$204,FALSE) -> 29.769874
A257: 692.02097 | B257: 692.71917 | C257: 687.81179 | D257: 691.49232 | E257: 4120626 | F257: Wed, 15 Jul 2026 00:00:00 GMT | G257: =A257/D257-1 -> 0.00076449291 | I257: 285.45231 | J257: 291.57797 | K257: 284.66111 | L257: 290.28914 | M257: 987271.6 | N257: Wed, 15 Jul 2026 00:00:00 GMT | O257: =I257/L257-1 -> -0.016662095 | Q257: 0.004 | R257: 25 | T257: =T256+0.001 -> 0.001 | U257: =_xlfn.NORM.DIST(T257,$S$202,$S$204,FALSE) -> 29.587047
A258: 689.32789 | B258: 690.62456 | C258: 686.43533 | D258: 688.44017 | E258: 4581789 | F258: Tue, 14 Jul 2026 00:00:00 GMT | G258: =A258/D258-1 -> 0.0012894626 | I258: 288.6271 | J258: 293.3246 | K258: 287.62202 | L258: 288.51763 | M258: 1034543 | N258: Tue, 14 Jul 2026 00:00:00 GMT | O258: =I258/L258-1 -> 0.00037944119 | Q258: 0.005 | R258: 21 | T258: =T257+0.001 -> 0.002 | U258: =_xlfn.NORM.DIST(T258,$S$202,$S$204,FALSE) -> 29.241725
A259: 686.73456 | B259: 691.18312 | C259: 685.77702 | D259: 689.82661 | E259: 6604827.4 | F259: Mon, 13 Jul 2026 00:00:00 GMT | G259: =A259/D259-1 -> -0.0044823597 | I259: 287.3134 | J259: 292.04572 | K259: 286.95511 | L259: 290.68723 | M259: 718933.73 | N259: Mon, 13 Jul 2026 00:00:00 GMT | O259: =I259/L259-1 -> -0.011606409 | Q259: 0.006 | R259: 24 | T259: =T258+0.001 -> 0.003 | U259: =_xlfn.NORM.DIST(T259,$S$202,$S$204,FALSE) -> 28.739623
A260: 692.08081 | B260: 692.54961 | C260: 685.86679 | D260: 689.4775 | E260: 4678890.4 | F260: Fri, 10 Jul 2026 00:00:00 GMT | G260: =A260/D260-1 -> 0.0037757685 | I260: 289.38348 | J260: 289.98062 | K260: 286.74114 | L260: 289.26405 | M260: 627201.56 | N260: Fri, 10 Jul 2026 00:00:00 GMT | O260: =I260/L260-1 -> 0.00041286771 | Q260: 0.007 | R260: 16 | T260: =T259+0.001 -> 0.004 | U260: =_xlfn.NORM.DIST(T260,$S$202,$S$204,FALSE) -> 28.088974
A261: 688.91894 | B261: 689.41387 | C261: 683.53279 | D261: 685.18853 | E261: 6412322.8 | F261: Thu, 09 Jul 2026 00:00:00 GMT | G261: =A261/D261-1 -> 0.0054443555 | I261: 288.48777 | J261: 293.52265 | K261: 286.80583 | L261: 290.87633 | M261: 914552.92 | N261: Thu, 09 Jul 2026 00:00:00 GMT | O261: =I261/L261-1 -> -0.0082115852 | Q261: 0.008 | R261: 20 | T261: =T260+0.001 -> 0.005 | U261: =_xlfn.NORM.DIST(T261,$S$202,$S$204,FALSE) -> 27.3003
A262: 683.50286 | B262: 684.08138 | C262: 677.98704 | D262: 681.3484 | E262: 4817716.3 | F262: Wed, 08 Jul 2026 00:00:00 GMT | G262: =A262/D262-1 -> 0.0031620553 | I262: 292.04075 | J262: 293.12555 | K262: 289.33372 | L262: 291.97108 | M262: 1250413.3 | N262: Wed, 08 Jul 2026 00:00:00 GMT | O262: =I262/L262-1 -> 0.00023860654 | Q262: 0.009 | R262: 21 | T262: =T261+0.001 -> 0.006 | U262: =_xlfn.NORM.DIST(T262,$S$202,$S$204,FALSE) -> 26.386129
A263: 685.3182 | B263: 688.47009 | C263: 683.23256 | D263: 687.81179 | E263: 4828423.5 | F263: Tue, 07 Jul 2026 00:00:00 GMT | G263: =A263/D263-1 -> -0.0036253952 | I263: 293.9914 | J263: 303.04801 | K263: 292.97627 | L263: 302.1523 | M263: 1230201.4 | N263: Tue, 07 Jul 2026 00:00:00 GMT | O263: =I263/L263-1 -> -0.027009223 | Q263: 0.01 | R263: 18 | T263: =T262+0.001 -> 0.007 | U263: =_xlfn.NORM.DIST(T263,$S$202,$S$204,FALSE) -> 25.360667
A264: 688.84912 | B264: 689.80167 | C264: 685.2384 | D264: 686.34556 | E264: 5589993 | F264: Mon, 06 Jul 2026 00:00:00 GMT | G264: =A264/D264-1 -> 0.0036476726 | I264: 299.83341 | J264: 301.37602 | K264: 296.3501 | L264: 300.37084 | M264: 892329.76 | N264: Mon, 06 Jul 2026 00:00:00 GMT | O264: =I264/L264-1 -> -0.0017892051 | Q264: 0.011 | R264: 13 | T264: =T263+0.001 -> 0.008 | U264: =_xlfn.NORM.DIST(T264,$S$202,$S$204,FALSE) -> 24.239429
A265: 683.08394 | B265: 688.72943 | C265: 678.4708 | D265: 685.21845 | E265: 6998763 | F265: Thu, 02 Jul 2026 00:00:00 GMT | G265: =A265/D265-1 -> -0.0031150834 | I265: 300.6296 | J265: 301.65468 | K265: 295.0135 | L265: 295.81268 | M265: 1422255.6 | N265: Thu, 02 Jul 2026 00:00:00 GMT | O265: =I265/L265-1 -> 0.016283686 | Q265: 0.012 | R265: 13 | T265: =T264+0.001 -> 0.009 | U265: =_xlfn.NORM.DIST(T265,$S$202,$S$204,FALSE) -> 23.038852
A266: 683.70235 | B266: 687.06371 | C266: 680.55045 | D266: 682.97422 | E266: 8650055.4 | F266: Wed, 01 Jul 2026 00:00:00 GMT | G266: =A266/D266-1 -> 0.0010661137 | I266: 290.83652 | J266: 294.93687 | K266: 290.53795 | L266: 292.58813 | M266: 1903846.9 | N266: Wed, 01 Jul 2026 00:00:00 GMT | O266: =I266/L266-1 -> -0.0059865982 | Q266: 0.013 | R266: 11 | T266: =T265+0.001 -> 0.01 | U266: =_xlfn.NORM.DIST(T266,$S$202,$S$204,FALSE) -> 21.775894
A267: 685.04889 | B267: 685.76605 | C267: 679.24381 | D267: 679.57297 | E267: 9879044.6 | F267: Tue, 30 Jun 2026 00:00:00 GMT | G267: =A267/D267-1 -> 0.0080578876 | I267: 289.20434 | J267: 290.36876 | K267: 286.62669 | L267: 289.20434 | M267: 2207562.6 | N267: Tue, 30 Jun 2026 00:00:00 GMT | O267: =I267/L267-1 -> 0 | Q267: 0.014 | R267: 8 | T267: =T266+0.001 -> 0.011 | U267: =_xlfn.NORM.DIST(T267,$S$202,$S$204,FALSE) -> 20.467646
A268: 679.26376 | B268: 679.81734 | C268: 671.20448 | D268: 675.27402 | E268: 5663751.7 | F268: Mon, 29 Jun 2026 00:00:00 GMT | G268: =A268/D268-1 -> 0.0059083322 | I268: 288.00011 | J268: 291.72725 | K268: 285.87031 | L268: 289.483 | M268: 1295899.1 | N268: Mon, 29 Jun 2026 00:00:00 GMT | O268: =I268/L268-1 -> -0.0051225633 | Q268: 0.015 | R268: 10 | T268: =T267+0.001 -> 0.012 | U268: =_xlfn.NORM.DIST(T268,$S$202,$S$204,FALSE) -> 19.13095
... A295: 670.9063 | B295: 674.44686 | C295: 668.87744 | D295: 671.871 | E295: 5625822.9 | F295: Tue, 19 May 2026 00:00:00 GMT | G295: =A295/D295-1 -> -0.0014358458 | I295: 305.44311 | J295: 309.14034 | K295: 302.27122 | L295: 309.05114 | M295: 1208887.4 | N295: Tue, 19 May 2026 00:00:00 GMT | O295: =I295/L295-1 -> -0.011674525 | Q295: 0.042 | R295: 1 | T295: =T294+0.001 -> 0.039 | U295: =_xlfn.NORM.DIST(T295,$S$202,$S$204,FALSE) -> 0.37479371
A296: 675.20271 | B296: 677.88797 | C296: 670.56816 | D296: 676.46577 | E296: 7589447.6 | F296: Mon, 18 May 2026 00:00:00 GMT | G296: =A296/D296-1 -> -0.0018671528 | I296: 308.42667 | J296: 308.57535 | K296: 300.45234 | L296: 301.31965 | M296: 1126679.2 | N296: Mon, 18 May 2026 00:00:00 GMT | O296: =I296/L296-1 -> 0.023586302 | Q296: More | R296: 1 | T296: =T295+0.001 -> 0.04 | U296: =_xlfn.NORM.DIST(T296,$S$202,$S$204,FALSE) -> 0.29964655
A297: 675.72981 | B297: 679.78754 | C297: 674.73627 | D297: 678.31562 | E297: 6438468.1 | F297: Fri, 15 May 2026 00:00:00 GMT | G297: =A297/D297-1 -> -0.0038120931 | I297: 300.72492 | J297: 307.13809 | K297: 300.51677 | L297: 304.2933 | M297: 1284063.1 | N297: Fri, 15 May 2026 00:00:00 GMT | O297: =I297/L297-1 -> -0.011726766 | T297: =T296+0.001 -> 0.041 | U297: =_xlfn.NORM.DIST(T297,$S$202,$S$204,FALSE) -> 0.23823359
A298: 683.97455 | B298: 685.33707 | C298: 679.92677 | D298: 680.00633 | E298: 5367141.9 | F298: Thu, 14 May 2026 00:00:00 GMT | G298: =A298/D298-1 -> 0.0058355515 | I298: 304.91777 | J298: 307.78238 | K298: 301.71118 | L298: 303.09393 | M298: 977805.53 | N298: Thu, 14 May 2026 00:00:00 GMT | O298: =I298/L298-1 -> 0.0060173981 | T298: =T297+0.001 -> 0.042 | U298: =_xlfn.NORM.DIST(T298,$S$202,$S$204,FALSE) -> 0.18835339
A299: 678.6836 | B299: 680.17541 | C299: 672.50751 | D299: 675.19276 | E299: 4909318.4 | F299: Wed, 13 May 2026 00:00:00 GMT | G299: =A299/D299-1 -> 0.0051701281 | I299: 302.2514 | J299: 304.88307 | K299: 295.42192 | L299: 303.87699 | M299: 805913.12 | N299: Wed, 13 May 2026 00:00:00 GMT | O299: =I299/L299-1 -> -0.0053495123 | T299: =T298+0.001 -> 0.043 | U299: =_xlfn.NORM.DIST(T299,$S$202,$S$204,FALSE) -> 0.14808825
A300: 674.96402 | B300: 675.5508 | C300: 669.12607 | D300: 673.77057 | E300: 6053085.9 | F300: Tue, 12 May 2026 00:00:00 GMT | G300: =A300/D300-1 -> 0.0017712961 | I300: 306.75152 | J300: 307.53656 | K300: 299.36696 | L300: 299.69406 | M300: 1350165.7 | N300: Tue, 12 May 2026 00:00:00 GMT | O300: =I300/L300-1 -> 0.023548867 | T300: =T299+0.001 -> 0.044 | U300: =_xlfn.NORM.DIST(T300,$S$202,$S$204,FALSE) -> 0.11578292
A301: 675.80938 | B301: 677.34097 | C301: 673.3827 | D301: 673.3827 | E301: 5691574.2 | F301: Mon, 11 May 2026 00:00:00 GMT | G301: =A301/D301-1 -> 0.00360371 | I301: 299.69406 | J301: 301.24036 | K301: 294.06485 | L301: 295.38227 | M301: 1297111.6 | N301: Mon, 11 May 2026 00:00:00 GMT | O301: =I301/L301-1 -> 0.014597315 | T301: =T300+0.001 -> 0.045 | U301: =_xlfn.NORM.DIST(T301,$S$202,$S$204,FALSE) -> 0.090021266
A302: 674.33746 | B302: 674.82478 | C302: 671.68204 | D302: 672.01024 | E302: 4333455.9 | F302: Fri, 08 May 2026 00:00:00 GMT | G302: =A302/D302-1 -> 0.0034630753 | I302: 297.00786 | J302: 300.30376 | K302: 295.04526 | L302: 298.19732 | M302: 1130167.2 | N302: Fri, 08 May 2026 00:00:00 GMT | O302: =I302/L302-1 -> -0.0039888313
A303: 668.86749 | B303: 673.06455 | C303: 667.25634 | D303: 672.12958 | E303: 6082581.7 | F303: Thu, 07 May 2026 00:00:00 GMT | G303: =A303/D303-1 -> -0.0048533633 | I303: 298.53434 | J303: 302.31087 | K303: 296.47261 | L303: 300.38791 | M303: 1331540 | N303: Thu, 07 May 2026 00:00:00 GMT | O303: =I303/L303-1 -> -0.0061705989
A304: 670.97592 | B304: 671.6522 | C304: 665.49601 | D304: 665.79437 | E304: 6432672.4 | F304: Wed, 06 May 2026 00:00:00 GMT | G304: =A304/D304-1 -> 0.007782508 | I304: 299.54538 | J304: 301.70623 | K304: 296.38836 | L304: 299.04977 | M304: 2300862.4 | N304: Wed, 06 May 2026 00:00:00 GMT | O304: =I304/L304-1 -> 0.0016572754
A305: 661.66703 | B305: 662.9102 | C305: 659.70779 | D305: 659.95642 | E305: 4974776.3 | F305: Tue, 05 May 2026 00:00:00 GMT | G305: =A305/D305-1 -> 0.002592001 | I305: 299.99142 | J305: 308.50101 | K305: 297.43409 | L305: 307.72291 | M305: 2096799.6 | N305: Tue, 05 May 2026 00:00:00 GMT | O305: =I305/L305-1 -> -0.025124819
...

Sheet Product Lines

Sheet Management

Sheet Table Formatting
B2: [Bold Title] | G2: [Bold Title]
B3: Line Titles | G3: <-- General
B4: Line Titles | G4: <-- Info
B5: Line Titles | G5: <-- General
B6: Line Titles | G6: <-- Info
B7: Line Titles | G7: <-- General
B8: Line Titles | G8: <-- Info
