Workbook

Sheet Main
B2: LULU
B3: Price | C3: 147.03 | D3: 2/18/2025
B4: SO | C4: 118.981 | D4: Q3'25
B5: MC | C5: =C3*C4 -> 17493.776
B6: Cash | C6: 1807.2 | D6: Q3'25
B7: Debt | C7: 0 | D7: Q3'25
B8: EV | C8: =C5-C6+C7 -> 15686.576
B10: Lululemon Athletica Inc. (LULU)
B12: Founder(s): Dennis "Chip" Wilson | G12: Registered Exchange: NASDAQ | O12: Resources:
B13: Founded: 1998 | G13: Address: 1818 Cornwall Avenue, Vancouver, BC V6J 1C7 CA | O13: SEC filings | R13: https://www.sec.gov/edgar/browse/?CIK=1397187&owner=exclude
B14: Headquarters: Vancouver, BC, Canada | G14: Investor Relations Contact: | O14: Company Homepage | R14: https://shop.lululemon.com/
B15: Current CEO: Calvin McDonald | G15: Investors Relation Department | P15: Company IR Page | S15: https://corporate.lululemon.com/investors
B16: Employees: 39,000 | G16: Phone: | H16: (604) 732 - 6124 | J16: Email: | K16: investors@lululemon.com | O16: Earnings Calls | R16: https://seekingalpha.com/symbol/LULU/earnings/transcripts
B17: Industry: Clothing Apparel - Retail | O17: Equity Analysis | R17: https://stockanalysis.com/stocks/lulu/company/
B18: Sector: Consumer Discretionary | O18: MacroTrends | R18: https://www.macrotrends.net/stocks/charts/LULU/lululemon-athletica-inc/income-statement?freq=A
B19: IPO: July 27, 2007 | O19: ROIC, WACC | R19: https://www.gurufocus.com/term/wacc/LULU
B20: Fiscal Year: [March - February] | O20: Godel Terminal | R20: https://app.godelterminal.com/
A22: Company Overview:
B23: Lululemon is a leading global retailer specializing in athletic apparel, footwear, and accessories
C24: The Company has a strong North American and growing international presence
C25: Management recent implementation of cost-saving programs and inventory discipline in response to tariff and U.S. market headwinds
B26: Founded in 1998 and headquartered in Vancouver, Canada, Lululemon has built a strong brand in premium athleisure and activewear, recognized for its innovation, retail experience, and community engagement
C27: The Company offers pants, shorts, tops, and jackets for athletic activities, such as yoga, running, training, and other activities … The Company also offers fitness-inspired accessories
C28: Strong brand loyalty and premium positioning in athleisure/activewear
B29: Business Segments
B30: Product Segments:
C31: Women’s apparel (core yoga, training, running, lifestyle), men’s athletic wear (rapidly expanding), footwear, and accessories (bags, yoga mats, and more)
C32: Retail Channels:
D33: Physical company-operated stores (784 globally as of Q2 2025), direct-to-consumer (DTC, including digital sales), and wholesale/partnered retail
C34: Digital Channels:
D35: Digital (e-commerce) has grown rapidly since pandemic … strong omni-channel strategy
C36: Integrated omni-channel presence, blending engaging physical retail with high-penetration digital
A38: Business Segments and Geographical Info:

Sheet Model
AM1: Q1 2020 | AQ1: Q1 2021 | AU1: Q1 2022 | AY1: Q1 2023 | BC1: Q1 2024 | BG1: Q1 2025
B2: Quarterly | C2: June | D2: Sept. | E2: Dec. | F2: Mar. | G2: June | H2: Sept. | I2: Dec. | J2: Mar. | K2: June | L2: Sept. | M2: Dec. | N2: Mar. | O2: June | P2: Sept. | Q2: Dec. | R2: Mar. | S2: June | T2: Sept. | U2: Dec. | V2: Mar. | W2: June | X2: Sept. | Y2: Dec. | Z2: Mar. | AA2: June | AB2: Sept. | AC2: Dec. | AD2: Mar. | AE2: June | AF2: Sept. | AG2: Dec. | AH2: Mar. | AI2: June | AJ2: Sept. | AK2: Dec. | AL2: Mar. | AM2: June | AN2: Sept. | AO2: Dec. | AP2: Mar. | AQ2: June | AR2: Sept. | AS2: Dec. | AT2: Mar. | AU2: June | AV2: Sept. | AW2: Dec. | AX2: Mar. | AY2: June | AZ2: Sept. | BA2: Dec. | BB2: Mar. | BC2: June | BD2: Sept. | BE2: Dec. | BF2: Mar. | BG2: June | BH2: Sept. | BI2: Dec. | BJ2: Mar. | BK2: June | BL2: Sept. | BM2: Dec. | BN2: Mar.
B3: Revenues | C3: Q1 2011 | D3: Q2 2011 | E3: Q3 2011 | F3: Q4 2011 | G3: Q1 2012 | H3: Q2 2012 | I3: Q3 2012 | J3: Q4 2012 | K3: Q1 2013 | L3: Q2 2013 | M3: Q3 2013 | N3: Q4 2013 | O3: Q1 2014 | P3: Q2 2014 | Q3: Q3 2014 | R3: Q4 2014 | S3: Q1 2015 | T3: Q2 2015 | U3: Q3 2015 | V3: Q4 2015 | W3: Q1 2016 | X3: Q2 2016 | Y3: Q3 2016 | Z3: Q4 2016 | AA3: Q1 2017 | AB3: Q2 2017 | AC3: Q3 2017 | AD3: Q4 2017 | AE3: Q1 2018 | AF3: Q2 2018 | AG3: Q3 2018 | AH3: Q4 2018 | AI3: Q1 2019 | AJ3: Q2 2019 | AK3: Q3 2019 | AL3: Q4 2019 | AM3: Q1 2020 | AN3: Q2 2020 | AO3: Q3 2020 | AP3: Q4 2020 | AQ3: Q1 2021 | AR3: Q2 2021 | AS3: Q3 2021 | AT3: Q4 2021 | AU3: Q1 2022 | AV3: Q2 2022 | AW3: Q3 2022 | AX3: Q4 2022 | AY3: Q1 2023 | AZ3: Q2 2023 | BA3: Q3 2023 | BB3: Q4 2023 | BC3: Q1 2024 | BD3: Q2 2024 | BE3: Q3 2024 | BF3: Q4 2024 | BG3: Q1 2025 | BH3: Q2 2025 | BI3: Q3 2025 | BJ3: Q4 2025 | BK3: Q1 2026 | BL3: Q2 2026 | BM3: Q3 2026 | BN3: Q4 2026 | BS3: 2011 | BT3: =BS3+1 -> 2012 | BU3: =BT3+1 -> 2013 | BV3: =BU3+1 -> 2014 | BW3: =BV3+1 -> 2015 | BX3: =BW3+1 -> 2016 | BY3: =BX3+1 -> 2017 | BZ3: =BY3+1 -> 2018 | CA3: =BZ3+1 -> 2019 | ... EO3: =EN3+1 -> 2085
B4: Women's Apparel | AM4: 477.627 | AN4: 647.198 | AO4: 787.402 | AP4: =3049.906-SUM(AM4:AO4) -> 1137.679 | AQ4: 849.645 | AR4: 968.951 | AS4: 984.952 | AT4: =4171.762-SUM(AQ4:AS4) -> 1368.214 | AU4: 1073.92 | AV4: 1205.636 | AW4: 1204.835 | AX4: =5259.803-SUM(AU4:AW4) -> 1775.412 | AY4: 1308.828 | AZ4: 1396.32 | BA4: 1433.92 | BB4: =6147.37-SUM(AY4:BA4) -> 2008.302 | BC4: 1435.24 | BD4: 1476.121 | BE4: 1555.68 | BF4: =6692.63-SUM(BC4:BE4) -> 2225.589 | BG4: 1535.172 | BH4: 1547.32 | BI4: 1644.95 | BJ4: =6995.36-SUM(BG4:BI4) -> 2267.918 | CB4: =SUM(AM4:AP4) -> 3049.906 | CC4: =SUM(AQ4:AT4) -> 4171.762 | CD4: =SUM(AU4:AX4) -> 5259.803 | CE4: =SUM(AY4:BB4) -> 6147.37 | CF4: =SUM(BC4:BF4) -> 6692.63 | CG4: =SUM(BG4:BJ4) -> 6995.36 | CH4: =CG4*(1+CH9) -> 7240.1976 | CI4: =CH4*(1+CI9) -> 7529.8055 | CJ4: =CI4*(1+CJ9) -> 7868.6468 | CK4: =CJ4*(1+CK9) -> 8262.0791 | CL4: =CK4*(1+CL9) -> 8633.8726 | CM4: =CL4*(1+CM9) -> 9000.8122 | CN4: =CM4*(1+CN9) -> 9360.8447 | CO4: =CN4*(1+CO9) -> 9711.8764 | ... CQ4: =CP4*(1+CQ9) -> 10393.553
B5: Men's Apparel | AM5: 128.391 | AN5: 190.381 | AO5: 238.05 | AP5: =953.183-SUM(AM5:AO5) -> 396.361 | AQ5: 274.307 | AR5: 363.06 | AS5: 343.26 | AT5: =1535.85-SUM(AQ5:AS5) -> 555.223 | AU5: 374.998 | AV5: 461.31 | AW5: 440.56 | AX5: =1956.602-SUM(AU5:AW5) -> 679.734 | AY5: 438.165 | AZ5: 530.72 | BA5: 504.828 | BB5: =2252.75-SUM(AY5:BA5) -> 779.037 | BC5: 505.698 | BD5: 587.525 | BE5: 551.43 | BF5: =2558.38-SUM(BC5:BE5) -> 913.727 | BG5: 544.788 | BH5: 624.59 | BI5: 596.24 | BJ5: =2663.98-SUM(BG5:BI5) -> 898.362 | CB5: =SUM(AM5:AP5) -> 953.183 | CC5: =SUM(AQ5:AT5) -> 1535.85 | CD5: =SUM(AU5:AX5) -> 1956.602 | CE5: =SUM(AY5:BB5) -> 2252.75 | CF5: =SUM(BC5:BF5) -> 2558.38 | CG5: =SUM(BF5:BI5) -> 2679.345 | CH5: =CG5*(1+CH10) -> 2834.747 | CI5: =CH5*(1+CI10) -> 3019.0056 | CJ5: =CI5*(1+CJ10) -> 3207.6934 | CK5: =CJ5*(1+CK10) -> 3416.1935 | CL5: =CK5*(1+CL10) -> 3612.6246 | CM5: =CL5*(1+CM10) -> 3829.3821 | CN5: =CM5*(1+CN10) -> 4039.9981 | CO5: =CN5*(1+CO10) -> 4241.998 | ... CQ5: =CP5*(1+CQ10) -> 4610.2034
B6: Acccessories & Other | AM6: 45.94 | AN6: 65.363 | AO6: 91.97 | AP6: =398.79-SUM(AM6:AO6) -> 195.517 | AQ6: 102.513 | AR6: 118.604 | AS6: 122.206 | AT6: =549.005-SUM(AQ6:AS6) -> 205.682 | AU6: 164.54 | AV6: 201.382 | AW6: 211.49 | AX6: =894.113-SUM(AU6:AW6) -> 316.701 | AY6: 253.799 | AZ6: 282.11 | BA6: 265.46 | BB6: =1219.15-SUM(AY6:BA6) -> 417.781 | BC6: 267.95 | BD6: 307.43 | BE6: 289.54 | BF6: =1337.116-SUM(BC6:BE6) -> 472.196 | BG6: 290.7 | BH6: 353.3 | BI6: 324.727 | BJ6: =1443.24-SUM(BG6:BI6) -> 474.513 | CB6: =SUM(AM6:AP6) -> 398.79 | CC6: =SUM(AQ6:AT6) -> 549.005 | CD6: =SUM(AU6:AX6) -> 894.113 | CE6: =SUM(AY6:BB6) -> 1219.15 | CF6: =SUM(BC6:BF6) -> 1337.116 | CG6: =SUM(BF6:BI6) -> 1440.923 | CH6: =CG6*(1+CH11) -> 1534.583 | CI6: =CH6*(1+CI11) -> 1642.0038 | CJ6: =CI6*(1+CJ11) -> 1765.1541 | CK6: =CJ6*(1+CK11) -> 1879.8891 | CL6: =CK6*(1+CL11) -> 1997.3822 | CM6: =CL6*(1+CM11) -> 2117.2251 | CN6: =CM6*(1+CN11) -> 2233.6725 | CO6: =CN6*(1+CO11) -> 2345.3561 | ... CQ6: =CP6*(1+CQ11) -> 2524.424
B7: Ttl Revenues | AM7: =SUM(AM4:AM6) -> 651.958 | AN7: =SUM(AN4:AN6) -> 902.942 | AO7: =SUM(AO4:AO6) -> 1117.422 | AP7: =SUM(AP4:AP6) -> 1729.557 | AQ7: =SUM(AQ4:AQ6) -> 1226.465 | AR7: =SUM(AR4:AR6) -> 1450.615 | AS7: =SUM(AS4:AS6) -> 1450.418 | AT7: =SUM(AT4:AT6) -> 2129.119 | ... BJ7: =SUM(BJ4:BJ6) -> 3640.793 | CB7: =SUM(AM7:AP7) -> 4401.879 | CC7: =SUM(AQ7:AT7) -> 6256.617 | CD7: =SUM(AU7:AX7) -> 8110.518 | CE7: =SUM(AY7:BB7) -> 9619.27 | CF7: =SUM(BC7:BF7) -> 10588.126 | CG7: =SUM(BF7:BI7) -> 11073.299 | CH7: =SUM(CH4:CH6) -> 11609.528 | CI7: =SUM(CI4:CI6) -> 12190.815 | CJ7: =SUM(CJ4:CJ6) -> 12841.494 | CK7: =SUM(CK4:CK6) -> 13558.162 | CL7: =SUM(CL4:CL6) -> 14243.879 | CM7: =SUM(CM4:CM6) -> 14947.419 | CN7: =SUM(CN4:CN6) -> 15634.515 | CO7: =SUM(CO4:CO6) -> 16299.231 | ... CQ7: =SUM(CQ4:CQ6) -> 17528.18
B9: Women's Apparel Growth Y/y | AQ9: =AQ4/AM4-1 -> 0.77888813 | AR9: =AR4/AN4-1 -> 0.4971477 | AS9: =AS4/AO4-1 -> 0.25088836 | AT9: =AT4/AP4-1 -> 0.20263624 | AU9: =AU4/AQ4-1 -> 0.26396318 | AV9: =AV4/AR4-1 -> 0.24426932 | AW9: =AW4/AS4-1 -> 0.22324235 | AX9: =AX4/AT4-1 -> 0.2976128 | ... BJ9: =BJ4/BF4-1 -> 0.019019235 | CC9: =CC4/CB4-1 -> 0.36783298 | CD9: =CD4/CC4-1 -> 0.2608109 | CE9: =CE4/CD4-1 -> 0.16874529 | CF9: =CF4/CE4-1 -> 0.088698094 | CG9: =CG4/CF4-1 -> 0.045233339 | CH9: 0.035 | CI9: 0.04 | CJ9: 0.045 | CK9: 0.05 | CL9: 0.045 | CM9: 0.0425 | CN9: 0.04 | CO9: 0.0375 | CP9: 0.035 | CQ9: 0.034
B10: Men's Apparel Growth Y/y | AQ10: =AQ5/AM5-1 -> 1.1364971 | AR10: =AR5/AN5-1 -> 0.90701803 | AS10: =AS5/AO5-1 -> 0.44196597 | AT10: =AT5/AP5-1 -> 0.40080129 | AU10: =AU5/AQ5-1 -> 0.36707412 | AV10: =AV5/AR5-1 -> 0.27061643 | AW10: =AW5/AS5-1 -> 0.2834586 | AX10: =AX5/AT5-1 -> 0.22425404 | ... BJ10: =BJ5/BF5-1 -> -0.016815745 | CC10: =CC5/CB5-1 -> 0.61128556 | CD10: =CD5/CC5-1 -> 0.27395384 | CE10: =CE5/CD5-1 -> 0.15135832 | CF10: =CF5/CE5-1 -> 0.13566974 | CG10: =CG5/CF5-1 -> 0.047281874 | CH10: 0.058 | CI10: 0.065 | CJ10: 0.0625 | CK10: 0.065 | CL10: 0.0575 | CM10: 0.06 | CN10: 0.055 | CO10: 0.05 | CP10: 0.045 | CQ10: 0.04
B11: Acccessories & Other Growth Y/y | AQ11: =AQ6/AM6-1 -> 1.2314541 | AR11: =AR6/AN6-1 -> 0.8145434 | AS11: =AS6/AO6-1 -> 0.32875938 | AT11: =AT6/AP6-1 -> 0.051990364 | AU11: =AU6/AQ6-1 -> 0.60506472 | AV11: =AV6/AR6-1 -> 0.69793599 | AW11: =AW6/AS6-1 -> 0.73060243 | AX11: =AX6/AT6-1 -> 0.53976041 | ... BJ11: =BJ6/BF6-1 -> 0.0049068607 | CC11: =CC6/CB6-1 -> 0.37667695 | CD11: =CD6/CC6-1 -> 0.6286063 | CE11: =CE6/CD6-1 -> 0.36353011 | CF11: =CF6/CE6-1 -> 0.096760858 | CG11: =CG6/CF6-1 -> 0.077635 | CH11: 0.065 | CI11: 0.07 | CJ11: 0.075 | CK11: 0.065 | CL11: 0.0625 | CM11: 0.06 | CN11: 0.055 | CO11: 0.05 | CP11: 0.045 | CQ11: 0.03
B12: Ttl Revenue Growth Y/y | G12: =G38/C38-1 -> 0.52944325 | H12: =H38/D38-1 -> 0.33301887 | I12: =I38/E38-1 -> 0.3748914 | J12: =J38/F38-1 -> 0.30679371 | K12: =K38/G38-1 -> 0.21036052 | L12: =L38/H38-1 -> 0.21903751 | M12: =M38/I38-1 -> 0.20031596 | N12: =N38/J38-1 -> 0.073120494 | ... AP12: =AP38/AL38-1 -> 0.23760787 | AQ12: =AQ7/AM7-1 -> 0.88120247 | AR12: =AR7/AN7-1 -> 0.60654283 | AS12: =AS7/AO7-1 -> 0.2980038 | AT12: =AT7/AP7-1 -> 0.23101985 | AU12: =AU7/AQ7-1 -> 0.3155353 | AV12: =AV7/AR7-1 -> 0.2879558 | AW12: =AW7/AS7-1 -> 0.28024128 | AX12: =AX7/AT7-1 -> 0.30187509 | ... BJ12: =BJ7/BF7-1 -> 0.0081076845 | BT12: =BT38/BS38-1 -> 0.36958781 | BU12: =BU38/BT38-1 -> 0.16120558 | BV12: =BV38/BU38-1 -> 0.12946204 | BW12: =BW38/BV38-1 -> 0.14650568 | BX12: =BX38/BW38-1 -> 0.13773356 | BY12: =BY38/BX38-1 -> 0.13006015 | BZ12: =BZ38/BY38-1 -> 0.24128039 | CA12: =CA38/BZ38-1 -> 0.21010218 | CB12: =CB38/CA38-1 -> 0.10619431 | CC12: =CC7/CB7-1 -> 0.42135143 | CD12: =CD7/CC7-1 -> 0.29631045 | CE12: =CE7/CD7-1 -> 0.18602412 | CF12: =CF7/CE7-1 -> 0.10072032 | CG12: =CG7/CF7-1 -> 0.045822367 | CH12: =CH7/CG7-1 -> 0.04842537 | CI12: =CI7/CH7-1 -> 0.050069847 | CJ12: =CJ7/CI7-1 -> 0.05337456 | ... CQ12: =CQ7/CP7-1 -> 0.034991625
B14: Women's Apparel % of Ttl Revenues | AM14: =AM4/AM7 -> 0.73260394 | AN14: =AN4/AN7 -> 0.71676586 | AO14: =AO4/AO7 -> 0.70465948 | AP14: =AP4/AP7 -> 0.65778636 | AQ14: =AQ4/AQ7 -> 0.69275927 | AR14: =AR4/AR7 -> 0.66795876 | AS14: =AS4/AS7 -> 0.67908148 | AT14: =AT4/AT7 -> 0.64261979 | ... BJ14: =BJ4/BJ7 -> 0.62291869 | CB14: =CB4/CB7 -> 0.69286457 | CC14: =CC4/CC7 -> 0.66677599 | CD14: =CD4/CD7 -> 0.64851628 | CE14: =CE4/CE7 -> 0.63906825 | CF14: =CF4/CF7 -> 0.63208825 | CG14: =CG4/CG7 -> 0.63173224
B15: Men's Apparel % of Ttl Revenues | AM15: =AM5/AM7 -> 0.1969314 | AN15: =AN5/AN7 -> 0.21084521 | AO15: =AO5/AO7 -> 0.213035 | AP15: =AP5/AP7 -> 0.22916909 | AQ15: =AQ5/AQ7 -> 0.22365661 | AR15: =AR5/AR7 -> 0.25028005 | AS15: =AS5/AS7 -> 0.23666281 | AT15: =AT5/AT7 -> 0.26077594 | ... BJ15: =BJ5/BJ7 -> 0.24674899 | CB15: =CB5/CB7 -> 0.21654003 | CC15: =CC5/CC7 -> 0.24547611 | CD15: =CD5/CD7 -> 0.24124254 | CE15: =CE5/CE7 -> 0.23419137 | CF15: =CF5/CF7 -> 0.24162727 | CG15: =CG5/CG7 -> 0.24196448
B16: Acccessories & Other % of Ttl Revenues | AM16: =AM6/AM7 -> 0.070464662 | AN16: =AN6/AN7 -> 0.072388924 | AO16: =AO6/AO7 -> 0.082305521 | AP16: =AP6/AP7 -> 0.11304455 | AQ16: =AQ6/AQ7 -> 0.083584122 | AR16: =AR6/AR7 -> 0.081761184 | AS16: =AS6/AS7 -> 0.084255711 | AT16: =AT6/AT7 -> 0.096604276 | ... BJ16: =BJ6/BJ7 -> 0.13033232 | CB16: =CB6/CB7 -> 0.090595403 | CC16: =CC6/CC7 -> 0.0877479 | CD16: =CD6/CD7 -> 0.11024117 | CE16: =CE6/CE7 -> 0.12674039 | CF16: =CF6/CF7 -> 0.12628448 | CG16: =CG6/CG7 -> 0.1301259
B18: U.S. Revenues | AU18: 1098.32 | AV18: 1278.361 | AW18: 1268.51 | AX18: =5654.34-SUM(AU18:AW18) -> 2009.149 | AY18: 1314.39 | AZ18: 1424.926 | BA18: 1423.57 | BB18: =6346-SUM(AY18:BA18) -> 2183.114 | BC18: 1340.4 | BD18: 1421.98 | BE18: 1424.23 | BF18: =6483.18-SUM(BC18:BE18) -> 2296.57 | BG18: 1362.52 | BH18: 1415.002 | BI18: 1380.97 | BJ18: =6328.38-SUM(BG18:BI18) -> 2169.888 | CD18: =SUM(AU18:AX18) -> 5654.34 | CE18: =SUM(AY18:BB18) -> 6346 | CF18: =SUM(BC18:BF18) -> 6483.18 | CG18: =SUM(BG18:BJ18) -> 6328.38
B19: Canada Revenues | AU19: 244.944 | AV19: 268.62 | AW19: 271.82 | AX19: =1163.11-SUM(AU19:AW19) -> 377.726 | AY19: 253.34 | AZ19: 294.847 | BA19: 308.82 | BB19: =1285.25-SUM(AY19:BA19) -> 428.243 | BC19: 281.86 | BD19: 319.453 | BE19: 335.48 | BF19: =1411.67-SUM(BC19:BE19) -> 474.877 | BG19: 292.82 | BH19: 321.29 | BI19: 331.596 | BJ19: =1423.17-SUM(BG19:BI19) -> 477.464 | CD19: =SUM(AU19:AX19) -> 1163.11 | CE19: =SUM(AY19:BB19) -> 1285.25 | CF19: =SUM(BC19:BF19) -> 1411.67 | CG19: =SUM(BG19:BJ19) -> 1423.17
B20: Mexico Revenues | AU20: 0 | AV20: 0 | AW20: 0 | AX20: =0-SUM(AU20:AW20) -> 0 | AY20: 0 | AZ20: 0 | BA20: 0 | BB20: =0-SUM(AY20:BA20) -> 0 | BC20: 0 | BD20: 0 | BE20: 10.66 | BF20: =33.3-SUM(BC20:BE20) -> 22.64 | BG20: 19.214 | BH20: 21.92 | BI20: 20.81 | BJ20: =95.48-SUM(BG20:BI20) -> 33.536 | CD20: =SUM(AU20:AX20) -> 0 | CE20: =SUM(AY20:BB20) -> 0 | CF20: =SUM(BC20:BF20) -> 33.3 | CG20: =SUM(BG20:BJ20) -> 95.48
B21: China Revenues | AU21: 139.427 | AV21: 172.02 | AW21: 174.15 | AX21: =681.63-SUM(AU21:AW21) -> 196.033 | AY21: 249.68 | AZ21: 277.5 | BA21: 266.891 | BB21: =1134.29-SUM(AY21:BA21) -> 340.219 | BC21: 346.05 | BD21: 356.224 | BE21: 359.388 | BF21: =1541.42-SUM(BC21:BE21) -> 479.758 | BG21: 412.205 | BH21: 440.532 | BI21: 511.82 | BJ21: =1754.79+199.07-SUM(BG21:BI21) -> 589.303 | CD21: =SUM(AU21:AX21) -> 681.63 | CE21: =SUM(AY21:BB21) -> 1134.29 | CF21: =SUM(BC21:BF21) -> 1541.42 | CG21: =SUM(BG21:BJ21) -> 1953.86
B22: Other Revenues | AU22: 130.763 | AV22: 149.325 | AW22: 142.4 | AX22: =611.43-SUM(AU22:AW22) -> 188.942 | AY22: 183.36 | AZ22: 211.892 | BA22: 204.929 | BB22: =853.338-SUM(AY22:BA22) -> 253.157 | BC22: 240.57 | BD22: 273.42 | BE22: 266.89 | BF22: =1118.54-SUM(BC22:BE22) -> 337.66 | BG22: 283.897 | BH22: 326.47 | BI22: 320.71 | BJ22: =1301.67-SUM(BG22:BI22) -> 370.593 | CD22: =SUM(AU22:AX22) -> 611.43 | CE22: =SUM(AY22:BB22) -> 853.338 | CF22: =SUM(BC22:BF22) -> 1118.54 | CG22: =SUM(BG22:BJ22) -> 1301.67
B23: Ttl Revenues | AU23: =SUM(AU18:AU22) -> 1613.454 | AV23: =SUM(AV18:AV22) -> 1868.326 | AW23: =SUM(AW18:AW22) -> 1856.88 | AX23: =SUM(AX18:AX22) -> 2771.85 | AY23: =SUM(AY18:AY22) -> 2000.77 | AZ23: =SUM(AZ18:AZ22) -> 2209.165 | BA23: =SUM(BA18:BA22) -> 2204.21 | BB23: =SUM(BB18:BB22) -> 3204.733 | ... BJ23: =SUM(BJ18:BJ22) -> 3640.784 | CD23: =SUM(CD18:CD22) -> 8110.51 | CE23: =SUM(CE18:CE22) -> 9618.878 | CF23: =SUM(CF18:CF22) -> 10588.11 | CG23: =SUM(BG23:BJ23) -> 11102.56
B25: U.S. Revenue Growth Y/y | AY25: =AY18/AU18-1 -> 0.19672773 | AZ25: =AZ18/AV18-1 -> 0.11465071 | BA25: =BA18/AW18-1 -> 0.1222379 | BB25: =BB18/AX18-1 -> 0.08658641 | BC25: =BC18/AY18-1 -> 0.019788647 | BD25: =BD18/AZ18-1 -> -0.0020674758 | BE25: =BE18/BA18-1 -> 0.00046362314 | BF25: =BF18/BB18-1 -> 0.051969801 | ... BJ25: =BJ18/BF18-1 -> -0.055161393 | CE25: =CE18/CD18-1 -> 0.12232374 | CF25: =CF18/CE18-1 -> 0.021616766 | CG25: =CG18/CF18-1 -> -0.023877171
B26: Canada Revenue Growth Y/y | AY26: =AY19/AU19-1 -> 0.034277223 | AZ26: =AZ19/AV19-1 -> 0.097636066 | BA26: =BA19/AW19-1 -> 0.13611949 | BB26: =BB19/AX19-1 -> 0.1337398 | BC26: =BC19/AY19-1 -> 0.11257598 | BD26: =BD19/AZ19-1 -> 0.083453452 | BE26: =BE19/BA19-1 -> 0.086328606 | BF26: =BF19/BB19-1 -> 0.10889612 | ... BJ26: =BJ19/BF19-1 -> 0.0054477265 | CE26: =CE19/CD19-1 -> 0.10501156 | CF26: =CF19/CE19-1 -> 0.098362186 | CG26: =CG19/CF19-1 -> 0.0081463798
B27: Mexico Revenue Growth Y/y | AY27: 0 | AZ27: 0 | BA27: 0 | BB27: 0 | BC27: 0 | BD27: 0 | BE27: 0 | BF27: 0 | BG27: 0 | BH27: 0 | BI27: 0 | BJ27: 0 | CE27: 0 | CF27: 0 | CG27: 0
B28: China Revenue Growth Y/y | AY28: =AY21/AU21-1 -> 0.79075789 | AZ28: =AZ21/AV21-1 -> 0.61318451 | BA28: =BA21/AW21-1 -> 0.53253517 | BB28: =BB21/AX21-1 -> 0.73551902 | BC28: =BC21/AY21-1 -> 0.38597405 | BD28: =BD21/AZ21-1 -> 0.28369009 | BE28: =BE21/BA21-1 -> 0.3465722 | BF28: =BF21/BB21-1 -> 0.41014464 | ... BJ28: =BJ21/BF21-1 -> 0.22833387 | CE28: =CE21/CD21-1 -> 0.66408462 | CF28: =CF21/CE21-1 -> 0.35892937 | CG28: =CG21/CF21-1 -> 0.26757146
B29: Other Revenue Growth Y/y | AY29: =AY22/AU22-1 -> 0.40223152 | AZ29: =AZ22/AV22-1 -> 0.41899883 | BA29: =BA22/AW22-1 -> 0.43910815 | BB29: =BB22/AX22-1 -> 0.3398662 | BC29: =BC22/AY22-1 -> 0.31200916 | BD29: =BD22/AZ22-1 -> 0.29037434 | BE29: =BE22/BA22-1 -> 0.3023535 | BF29: =BF22/BB22-1 -> 0.33379681 | ... BJ29: =BJ22/BF22-1 -> 0.097533021 | CE29: =CE22/CD22-1 -> 0.395643 | CF29: =CF22/CE22-1 -> 0.31078189 | CG29: =CG22/CF22-1 -> 0.16372235
B30: Ttl Revenue Growth Y/y | AY30: =AY23/AU23-1 -> 0.24005395 | AZ30: =AZ23/AV23-1 -> 0.18243015 | BA30: =BA23/AW23-1 -> 0.18705032 | BB30: =BB23/AX23-1 -> 0.15617115 | BC30: =BC23/AY23-1 -> 0.10401495 | BD30: =BD23/AZ23-1 -> 0.07329104 | BE30: =BE23/BA23-1 -> 0.087304749 | BF30: =BF23/BB23-1 -> 0.12692851 | ... BJ30: =BJ23/BF23-1 -> 0.0081071465 | CE30: =CE23/CD23-1 -> 0.18597696 | CF30: =CF23/CE23-1 -> 0.10076352 | CG30: =CG23/CF23-1 -> 0.048587519
B32: U.S. % of Revenues | AU32: =AU18/$BH$23 -> 0.43494136 | AV32: =AV18/$BH$23 -> 0.50623868 | AW32: =AW18/$BH$23 -> 0.50233762 | AX32: =AX18/$BH$23 -> 0.79563514 | AY32: =AY18/$BH$23 -> 0.52050638 | AZ32: =AZ18/$BH$23 -> 0.5642793 | BA32: =BA18/$BH$23 -> 0.56374232 | BB32: =BB18/$BH$23 -> 0.86452633 | ... BJ32: =BJ18/$BH$23 -> 0.85928876 | CD32: =CD18/$BH$23 -> 2.2391528 | CE32: =CE18/$BH$23 -> 2.5130543 | CF32: =CF18/$BH$23 -> 2.5673784 | CG32: =CG18/$BH$23 -> 2.5060767
B33: Canada % of Revenues | AU33: =AU19/$BH$23 -> 0.096999304 | AV33: =AV19/$BH$23 -> 0.10637514 | AW33: =AW19/$BH$23 -> 0.10764236 | AX33: =AX19/$BH$23 -> 0.14958178 | AY33: =AY19/$BH$23 -> 0.10032417 | AZ33: =AZ19/$BH$23 -> 0.11676119 | BA33: =BA19/$BH$23 -> 0.12229459 | BB33: =BB19/$BH$23 -> 0.16958682 | ... BJ33: =BJ19/$BH$23 -> 0.18907863 | CD33: =CD19/$BH$23 -> 0.46059859 | CE33: =CE19/$BH$23 -> 0.50896676 | CF33: =CF19/$BH$23 -> 0.55902985 | CG33: =CG19/$BH$23 -> 0.56358392
B34: Mexico % of Revenues | AU34: =AU20/$BH$23 -> 0 | AV34: =AV20/$BH$23 -> 0 | AW34: =AW20/$BH$23 -> 0 | AX34: =AX20/$BH$23 -> 0 | AY34: =AY20/$BH$23 -> 0 | AZ34: =AZ20/$BH$23 -> 0 | BA34: =BA20/$BH$23 -> 0 | BB34: =BB20/$BH$23 -> 0 | ... BJ34: =BJ20/$BH$23 -> 0.013280459 | CD34: =CD20/$BH$23 -> 0 | CE34: =CE20/$BH$23 -> 0 | CF34: =CF20/$BH$23 -> 0.013187001 | CG34: =CG20/$BH$23 -> 0.037810657
B35: China % of Revenues | AU35: =AU21/$BH$23 -> 0.055213934 | AV35: =AV21/$BH$23 -> 0.068120959 | AW35: =AW21/$BH$23 -> 0.068964452 | AX35: =AX21/$BH$23 -> 0.077630252 | AY35: =AY21/$BH$23 -> 0.098874788 | AZ35: =AZ21/$BH$23 -> 0.10989168 | BA35: =BA21/$BH$23 -> 0.10569045 | BB35: =BB21/$BH$23 -> 0.13472878 | ... BJ35: =BJ21/$BH$23 -> 0.23336755 | CD35: =CD21/$BH$23 -> 0.2699296 | CE35: =CE21/$BH$23 -> 0.44918569 | CF35: =CF21/$BH$23 -> 0.61041163 | CG35: =CG21/$BH$23 -> 0.77374036
B36: Other % of Revenues | AU36: =AU22/$BH$23 -> 0.051782938 | AV36: =AV22/$BH$23 -> 0.059133602 | AW36: =AW22/$BH$23 -> 0.05639126 | AX36: =AX22/$BH$23 -> 0.074822173 | AY36: =AY22/$BH$23 -> 0.072611668 | AZ36: =AZ22/$BH$23 -> 0.083910512 | BA36: =BA22/$BH$23 -> 0.081153122 | BB36: =BB22/$BH$23 -> 0.1002517 | ... BJ36: =BJ22/$BH$23 -> 0.14675707 | CD36: =CD22/$BH$23 -> 0.24212997 | CE36: =CE22/$BH$23 -> 0.337927 | CF36: =CF22/$BH$23 -> 0.4429486 | CG36: =CG22/$BH$23 -> 0.51546918
B38: Revenues | C38: 186.8 | D38: 212 | E38: 230.2 | F38: 371.52 | G38: 285.7 | H38: 282.6 | I38: 316.5 | J38: 485.5 | K38: 345.8 | L38: 344.5 | M38: 379.9 | N38: 521 | O38: 384.6 | P38: 390.7 | Q38: 419.4 | R38: 602.5 | S38: 423.5 | T38: 453 | U38: 479.7 | V38: 704.3 | W38: 495.5 | X38: 514.5 | Y38: 544.4 | Z38: 789.9 | AA38: 520.3 | AB38: 581.1 | AC38: 619 | AD38: 928.8 | AE38: 649.7 | AF38: 723.5 | AG38: 747.7 | AH38: 1167.5 | AI38: 782.3 | AJ38: 883.4 | AK38: 916.1 | AL38: 1397.5 | AM38: =AM7 -> 651.958 | AN38: =AN7 -> 902.942 | AO38: =AO7 -> 1117.422 | AP38: =AP7 -> 1729.557 | AQ38: =AQ7 -> 1226.465 | AR38: =AR7 -> 1450.615 | AS38: =AS7 -> 1450.418 | AT38: =AT7 -> 2129.119 | ... BJ38: =BJ7 -> 3640.793 | BS38: =SUM(C38:F38) -> 1000.52 | BT38: =SUM(G38:J38) -> 1370.3 | BU38: =SUM(K38:N38) -> 1591.2 | BV38: =SUM(O38:R38) -> 1797.2 | BW38: =SUM(S38:V38) -> 2060.5 | BX38: =SUM(W38:Z38) -> 2344.3 | BY38: =SUM(AA38:AD38) -> 2649.2 | BZ38: =SUM(AE38:AH38) -> 3288.4 | CA38: =SUM(AI38:AL38) -> 3979.3 | CB38: =SUM(AM38:AP38) -> 4401.879 | CC38: =SUM(AQ38:AT38) -> 6256.617 | CD38: =SUM(AU38:AX38) -> 8110.518 | CE38: =SUM(AY38:BB38) -> 9619.27 | CF38: =SUM(BC38:BF38) -> 10588.126 | CG38: =SUM(BG38:BJ38) -> 11102.58 | CH38: =CH7 -> 11609.528 | CI38: =CI7 -> 12190.815 | CJ38: =CJ7 -> 12841.494 | CK38: =CK7 -> 13558.162 | CL38: =CL7 -> 14243.879 | CM38: =CM7 -> 14947.419 | CN38: =CN7 -> 15634.515 | CO38: =CO7 -> 16299.231 | ... CQ38: =CQ7 -> 17528.18
B39: COGS | C39: 77.1 | D39: 90.3 | E39: 101.7 | F39: 162.47 | G39: 128.4 | H39: 126.9 | I39: 141.2 | J39: 211 | K39: 175.1 | L39: 158.6 | M39: 175.3 | N39: 242.2 | O39: 188.9 | P39: 193.4 | Q39: 208.3 | R39: 292.4 | S39: 217.7 | T39: 241 | U39: 254.9 | V39: 349.8 | W39: 256.4 | X39: 260.4 | Y39: 266 | Z39: 362 | AA39: 263.4 | AB39: 283.6 | AC39: 297.1 | AD39: 406.3 | AE39: 305 | AF39: 327.3 | AG39: 340.9 | AH39: 498.9 | AI39: 360.6 | AJ39: 397.6 | AK39: 411.1 | AL39: 586.7 | AM39: 317.6 | AN39: 413.4 | AO39: 490.1 | AP39: 716.8 | AQ39: 526.2 | AR39: 607.9 | AS39: 621 | AT39: 892.9 | AU39: 743.1 | AV39: 812.9 | AW39: 818 | AX39: 1244.2 | AY39: 850 | AZ39: 910.7 | BA39: 947.6 | BB39: 1301.7 | BC39: 933.8 | BD39: 958.9 | BE39: 995.1 | BF39: 1429.5 | BG39: 987.5 | BH39: 1048 | BI39: 1140 | BJ39: 1642.9 | BS39: =SUM(C39:F39) -> 431.57 | BT39: =SUM(G39:J39) -> 607.5 | BU39: =SUM(K39:N39) -> 751.2 | BV39: =SUM(O39:R39) -> 883 | BW39: =SUM(S39:V39) -> 1063.4 | BX39: =SUM(W39:Z39) -> 1144.8 | BY39: =SUM(AA39:AD39) -> 1250.4 | BZ39: =SUM(AE39:AH39) -> 1472.1 | CA39: =SUM(AI39:AL39) -> 1756 | CB39: =SUM(AM39:AP39) -> 1937.9 | CC39: =SUM(AQ39:AT39) -> 2648 | CD39: =SUM(AU39:AX39) -> 3618.2 | CE39: =SUM(AY39:BB39) -> 4010 | CF39: =SUM(BC39:BF39) -> 4317.3 | CG39: =SUM(BG39:BJ39) -> 4818.4 | CH39: =CH38*(1-CH51) -> 5061.754 | CI39: =CI38*(1-CI51) -> 5266.432 | CJ39: =CJ38*(1-CJ51) -> 5534.684 | CK39: =CK38*(1-CK51) -> 5830.0095 | CL39: =CL38*(1-CL51) -> 6053.6488 | CM39: =CM38*(1-CM51) -> 6277.9162 | CN39: =CN38*(1-CN51) -> 6488.3239 | CO39: =CO38*(1-CO51) -> 6682.6845 | ... CQ39: =CQ38*(1-CQ51) -> 7055.0926
B40: GP | C40: =C38-C39 -> 109.7 | D40: =D38-D39 -> 121.7 | E40: =E38-E39 -> 128.5 | F40: =F38-F39 -> 209.05 | G40: =G38-G39 -> 157.3 | H40: =H38-H39 -> 155.7 | I40: =I38-I39 -> 175.3 | J40: =J38-J39 -> 274.5 | ... BJ40: =BJ38-BJ39 -> 1997.893 | BS40: =SUM(C40:F40) -> 568.95 | BT40: =SUM(G40:J40) -> 762.8 | BU40: =SUM(K40:N40) -> 840 | BV40: =SUM(O40:R40) -> 914.2 | BW40: =SUM(S40:V40) -> 997.1 | BX40: =SUM(W40:Z40) -> 1199.5 | BY40: =SUM(AA40:AD40) -> 1398.8 | BZ40: =SUM(AE40:AH40) -> 1816.3 | CA40: =SUM(AI40:AL40) -> 2223.3 | CB40: =SUM(AM40:AP40) -> 2463.979 | CC40: =SUM(AQ40:AT40) -> 3608.617 | CD40: =SUM(AU40:AX40) -> 4492.318 | CE40: =SUM(AY40:BB40) -> 5609.27 | CF40: =SUM(BC40:BF40) -> 6270.826 | CG40: =SUM(BG40:BJ40) -> 6284.18 | CH40: =CH38-CH39 -> 6547.7736 | CI40: =CI38-CI39 -> 6924.3828 | CJ40: =CJ38-CJ39 -> 7306.8102 | CK40: =CK38-CK39 -> 7728.1522 | CL40: =CL38-CL39 -> 8190.2307 | CM40: =CM38-CM39 -> 8669.5033 | CN40: =CN38-CN39 -> 9146.1915 | CO40: =CO38-CO39 -> 9616.546 | ... CQ40: =CQ38-CQ39 -> 10473.088
B41: SG&A | C41: 58 | D41: 63 | E41: 68.8 | F41: 92.97 | G41: 84.2 | H41: 85.6 | I41: 94.7 | J41: 121.9 | K41: 104.8 | L41: 107 | M41: 112.3 | N41: 124.6 | O41: 125.9 | P41: 129.4 | Q41: 129.9 | R41: 152.9 | S41: 137.8 | T41: 145.4 | U41: 156.6 | V41: 188.2 | W41: 181.5 | X41: 180.2 | Y41: 185.5 | Z41: 231.3 | AA41: 199.1 | AB41: 225.5 | AC41: 215.4 | AD41: 264.2 | AE41: 240.4 | AF41: 262 | AG41: 270.9 | AH41: 337.1 | AI41: 292.9 | AJ41: 317.8 | AK41: 329.2 | AL41: 394.3 | AM41: 299.6 | AN41: 352.9 | AO41: 411.7 | AP41: 544.8 | AQ41: 496.6 | AR41: 541.3 | AS41: 545.1 | AT41: 642 | AU41: 607.9 | AV41: 662.3 | AW41: 684.2 | AX41: 803.1 | AY41: 747.5 | AZ41: 817.4 | BA41: 842.8 | BB41: 989.5 | BC41: 842.4 | BD41: 872 | BE41: 909.8 | BF41: 1138.2 | BG41: 942.9 | BH41: 951.7 | BI41: 988.25 | BJ41: 1183.8 | BS41: =SUM(C41:F41) -> 282.77 | BT41: =SUM(G41:J41) -> 386.4 | BU41: =SUM(K41:N41) -> 448.7 | BV41: =SUM(O41:R41) -> 538.1 | BW41: =SUM(S41:V41) -> 628 | BX41: =SUM(W41:Z41) -> 778.5 | BY41: =SUM(AA41:AD41) -> 904.2 | BZ41: =SUM(AE41:AH41) -> 1110.4 | CA41: =SUM(AI41:AL41) -> 1334.2 | CB41: =SUM(AM41:AP41) -> 1609 | CC41: =SUM(AQ41:AT41) -> 2225 | CD41: =SUM(AU41:AX41) -> 2757.5 | CE41: =SUM(AY41:BB41) -> 3397.2 | CF41: =SUM(BC41:BF41) -> 3762.4 | CG41: =SUM(BG41:BJ41) -> 4066.65 | CH41: =CH38*CH52 -> 4208.4538 | CI41: =CI38*CI52 -> 4388.6934 | CJ41: =CJ38*CJ52 -> 4494.523 | CK41: =CK38*CK52 -> 4474.1934 | CL41: =CL38*CL52 -> 4664.8705 | CM41: =CM38*CM52 -> 4857.9113 | CN41: =CN38*CN52 -> 5042.1312 | CO41: =CO38*CO52 -> 5215.7538 | ... CQ41: =CQ38*CQ52 -> 5609.0178
B42: Amortization of Intangibles | D42: 0 | E42: 0 | F42: 1 | G42: 0 | H42: 0 | I42: 0 | J42: 0 | K42: 0 | L42: 0 | M42: 0 | N42: 0 | O42: 0 | P42: 1 | Q42: 1 | R42: 0 | S42: 0 | T42: 0 | U42: 0 | V42: 0 | W42: 0 | X42: 0 | Y42: 0 | Z42: 0 | AA42: 13 | AB42: 4 | AC42: 22 | AD42: 3 | AE42: 0 | AF42: 0 | AG42: 0 | AH42: 1 | AI42: 0 | AJ42: 0 | AK42: 0 | AL42: 0 | AM42: 3 | AN42: 13 | AO42: 11 | AP42: 10 | AQ42: 11 | AR42: 10 | AS42: 27 | AT42: 3 | AU42: 2 | AV42: -8 | AW42: 1 | AX42: 411 | AY42: 2 | AZ42: 2 | BA42: 76 | BB42: 0 | BC42: 0 | BD42: 0 | BE42: 1 | BF42: 2 | BG42: 2 | BH42: 2 | BI42: 1.776 | BJ42: 2 | BS42: =SUM(C42:F42) -> 1 | BT42: =SUM(G42:J42) -> 0 | BU42: =SUM(K42:N42) -> 0 | BV42: =SUM(O42:R42) -> 2 | BW42: =SUM(S42:V42) -> 0 | BX42: =SUM(W42:Z42) -> 0 | BY42: =SUM(AA42:AD42) -> 42 | BZ42: =SUM(AE42:AH42) -> 1 | CA42: =SUM(AI42:AL42) -> 0 | CB42: =SUM(AM42:AP42) -> 37 | CC42: =SUM(AQ42:AT42) -> 51 | CD42: =SUM(AU42:AX42) -> 406 | CE42: =SUM(AY42:BB42) -> 80 | CF42: =SUM(BC42:BF42) -> 3 | CG42: =SUM(BG42:BJ42) -> 7.776 | CH42: 0 | CI42: 0 | CJ42: 0 | CK42: 0 | CL42: 0 | CM42: 0 | CN42: 0 | CO42: 0 | CP42: 0 | CQ42: 0
B43: OI | C43: =C40-SUM(C41:C42) -> 51.7 | D43: =D40-SUM(D41:D42) -> 58.7 | E43: =E40-SUM(E41:E42) -> 59.7 | F43: =F40-SUM(F41:F42) -> 115.08 | G43: =G40-SUM(G41:G42) -> 73.1 | H43: =H40-SUM(H41:H42) -> 70.1 | I43: =I40-SUM(I41:I42) -> 80.6 | J43: =J40-SUM(J41:J42) -> 152.6 | ... BJ43: =BJ40-SUM(BJ41:BJ42) -> 812.093 | BS43: =SUM(C43:F43) -> 285.18 | BT43: =SUM(G43:J43) -> 376.4 | BU43: =SUM(K43:N43) -> 391.3 | BV43: =SUM(O43:R43) -> 374.1 | BW43: =SUM(S43:V43) -> 369.1 | BX43: =SUM(W43:Z43) -> 421 | BY43: =SUM(AA43:AD43) -> 452.6 | BZ43: =SUM(AE43:AH43) -> 704.9 | CA43: =SUM(AI43:AL43) -> 889.1 | CB43: =SUM(AM43:AP43) -> 817.979 | CC43: =SUM(AQ43:AT43) -> 1332.617 | CD43: =SUM(AU43:AX43) -> 1328.818 | CE43: =SUM(AY43:BB43) -> 2132.07 | CF43: =SUM(BC43:BF43) -> 2505.426 | CG43: =SUM(BG43:BJ43) -> 2209.754 | CH43: =CH40-SUM(CH41:CH42) -> 2339.3198 | CI43: =CI40-SUM(CI41:CI42) -> 2535.6895 | CJ43: =CJ40-SUM(CJ41:CJ42) -> 2812.2872 | CK43: =CK40-SUM(CK41:CK42) -> 3253.9588 | CL43: =CL40-SUM(CL41:CL42) -> 3525.3602 | CM43: =CM40-SUM(CM41:CM42) -> 3811.592 | CN43: =CN40-SUM(CN41:CN42) -> 4104.0603 | CO43: =CO40-SUM(CO41:CO42) -> 4400.7922 | ... CQ43: =CQ40-SUM(CQ41:CQ42) -> 4864.0701
B44: Other Income | C44: 0.9 | D44: 1 | E44: 0.6 | F44: 1.6 | G44: 0.9 | H44: 1.2 | I44: 1.4 | J44: 1.5 | K44: 1.5 | L44: 1.3 | M44: 1.5 | N44: 1.5 | O44: 1.6 | P44: 1.9 | Q44: 1.8 | R44: 1.8 | S44: 0.5 | T44: 0.8 | U44: -2.9 | V44: 0.9 | W44: -0.5 | X44: 0.6 | Y44: 0.6 | Z44: 0.9 | AA44: 0.9 | AB44: 0.8 | AC44: 1.1 | AD44: 1.2 | AE44: 2.9 | AF44: 1.6 | AG44: 2 | AH44: 2.9 | AI44: 2.4 | AJ44: 1.8 | AK44: 1.9 | AL44: 2.1 | AM44: 1.2 | AN44: -0.3 | AO44: -0.6 | AP44: -0.9 | AQ44: 0.2 | AR44: 0.1 | AS44: 0 | AT44: 0.2 | AU44: 0 | AV44: 0.1 | AW44: 0.3 | AX44: 3.7 | AY44: 8 | AZ44: 7.4 | BA44: 9.8 | BB44: 17.8 | BC44: 23.3 | BD44: 18 | BE44: 13.7 | BF44: 15.4 | BG44: 11.8 | BH44: 10 | BI44: 5.854 | BJ44: 1 | BS44: =SUM(C44:F44) -> 4.1 | BT44: =SUM(G44:J44) -> 5 | BU44: =SUM(K44:N44) -> 5.8 | BV44: =SUM(O44:R44) -> 7.1 | BW44: =SUM(S44:V44) -> -0.7 | BX44: =SUM(W44:Z44) -> 1.6 | BY44: =SUM(AA44:AD44) -> 4 | BZ44: =SUM(AE44:AH44) -> 9.4 | CA44: =SUM(AI44:AL44) -> 8.2 | CB44: =SUM(AM44:AP44) -> -0.6 | CC44: =SUM(AQ44:AT44) -> 0.5 | CD44: =SUM(AU44:AX44) -> 4.1 | CE44: =SUM(AY44:BB44) -> 43 | CF44: =SUM(BC44:BF44) -> 70.4 | CG44: =SUM(BG44:BJ44) -> 28.654 | CH44: =CG44*(1+$CQ$60) -> 36.82039 | CI44: =CH44*(1+$CQ$60) -> 47.314201 | CJ44: =CI44*(1+$CQ$60) -> 60.798748 | CK44: =CJ44*(1+$CQ$60) -> 78.126392 | CL44: =CK44*(1+$CQ$60) -> 100.39241 | CM44: =CL44*(1+$CQ$60) -> 129.00425 | CN44: =CM44*(1+$CQ$60) -> 165.77046 | CO44: =CN44*(1+$CQ$60) -> 213.01504 | ... CQ44: =CP44*(1+$CQ$60) -> 351.73577
B45: Pretax Income | C45: =C43+C44 -> 52.6 | D45: =D43+D44 -> 59.7 | E45: =E43+E44 -> 60.3 | F45: =F43+F44 -> 116.68 | G45: =G43+G44 -> 74 | H45: =H43+H44 -> 71.3 | I45: =I43+I44 -> 82 | J45: =J43+J44 -> 154.1 | ... BJ45: =BJ43+BJ44 -> 813.093 | BS45: =SUM(C45:F45) -> 289.28 | BT45: =SUM(G45:J45) -> 381.4 | BU45: =SUM(K45:N45) -> 397.1 | BV45: =SUM(O45:R45) -> 381.2 | BW45: =SUM(S45:V45) -> 368.4 | BX45: =SUM(W45:Z45) -> 422.6 | BY45: =SUM(AA45:AD45) -> 456.6 | BZ45: =SUM(AE45:AH45) -> 714.3 | CA45: =SUM(AI45:AL45) -> 897.3 | CB45: =SUM(AM45:AP45) -> 817.379 | CC45: =SUM(AQ45:AT45) -> 1333.117 | CD45: =SUM(AU45:AX45) -> 1332.918 | CE45: =SUM(AY45:BB45) -> 2175.07 | CF45: =SUM(BC45:BF45) -> 2575.826 | CG45: =SUM(BG45:BJ45) -> 2238.408 | CH45: =CH43+CH44 -> 2376.1402 | CI45: =CI43+CI44 -> 2583.0037 | CJ45: =CJ43+CJ44 -> 2873.086 | CK45: =CK43+CK44 -> 3332.0852 | CL45: =CL43+CL44 -> 3625.7526 | CM45: =CM43+CM44 -> 3940.5962 | CN45: =CN43+CN44 -> 4269.8307 | CO45: =CO43+CO44 -> 4613.8073 | ... CQ45: =CQ43+CQ44 -> 5215.8059
B46: Taxes | C46: 19.1 | D46: 21.46 | E46: 21.4 | F46: 42.55 | G46: 27 | H46: 13.7 | I46: 24.7 | J46: 44.7 | K46: 20.1 | L46: 23.8 | M46: 27.7 | N46: 46 | O46: 52.5 | P46: 21 | Q46: 22.5 | R46: 48.1 | S46: 20.8 | T46: 19.8 | U46: 12.1 | V46: 49.8 | W46: 11.8 | X46: 20.9 | Y46: 25.3 | Z46: 61.4 | AA46: 15.1 | AB46: 20.8 | AC46: 27.7 | AD46: 137.7 | AE46: 32.1 | AF46: 40 | AG46: 43.5 | AH46: 115.8 | AI46: 34.6 | AJ46: 44.8 | AK46: 51.8 | AL46: 120.6 | AM46: 5.3 | AN46: 37.3 | AO46: 60.7 | AP46: 127.2 | AQ46: 49.1 | AR46: 83.1 | AS46: 70.2 | AT46: 156.2 | AU46: 70.3 | AV46: 111.8 | AW46: 97.3 | AX46: 198.3 | AY46: 119 | AZ46: 145 | BA46: 99.2 | BB46: 262.3 | BC46: 134.5 | BD46: 165.3 | BE46: 152.5 | BF46: 309.1 | BG46: 135.8 | BH46: 161 | BI46: 134.905 | BJ46: 226.4 | BS46: =SUM(C46:F46) -> 104.51 | BT46: =SUM(G46:J46) -> 110.1 | BU46: =SUM(K46:N46) -> 117.6 | BV46: =SUM(O46:R46) -> 144.1 | BW46: =SUM(S46:V46) -> 102.5 | BX46: =SUM(W46:Z46) -> 119.4 | BY46: =SUM(AA46:AD46) -> 201.3 | BZ46: =SUM(AE46:AH46) -> 231.4 | CA46: =SUM(AI46:AL46) -> 251.8 | CB46: =SUM(AM46:AP46) -> 230.5 | CC46: =SUM(AQ46:AT46) -> 358.6 | CD46: =SUM(AU46:AX46) -> 477.7 | CE46: =SUM(AY46:BB46) -> 625.5 | CF46: =SUM(BC46:BF46) -> 761.4 | CG46: =SUM(BG46:BJ46) -> 658.105 | CH46: =CH45*CH54 -> 712.84206 | CI46: =CI45*CI54 -> 774.90111 | CJ46: =CJ45*CJ54 -> 861.9258 | CK46: =CK45*CK54 -> 999.62556 | CL46: =CL45*CL54 -> 1087.7258 | CM46: =CM45*CM54 -> 1182.1789 | CN46: =CN45*CN54 -> 1280.9492 | CO46: =CO45*CO54 -> 1384.1422 | ... CQ46: =CQ45*CQ54 -> 1564.7418
B47: NI | C47: =C45-C46 -> 33.5 | D47: =D45-D46 -> 38.24 | E47: =E45-E46 -> 38.9 | F47: =F45-F46 -> 74.13 | G47: =G45-G46 -> 47 | H47: =H45-H46 -> 57.6 | I47: =I45-I46 -> 57.3 | J47: =J45-J46 -> 109.4 | ... BJ47: =BJ45-BJ46 -> 586.693 | BS47: =SUM(C47:F47) -> 184.77 | BT47: =SUM(G47:J47) -> 271.3 | BU47: =SUM(K47:N47) -> 279.5 | BV47: =SUM(O47:R47) -> 237.1 | BW47: =SUM(S47:V47) -> 265.9 | BX47: =SUM(W47:Z47) -> 303.2 | BY47: =SUM(AA47:AD47) -> 255.3 | BZ47: =SUM(AE47:AH47) -> 482.9 | CA47: =SUM(AI47:AL47) -> 645.5 | CB47: =SUM(AM47:AP47) -> 586.879 | CC47: =SUM(AQ47:AT47) -> 974.517 | CD47: =SUM(AU47:AX47) -> 855.218 | CE47: =SUM(AY47:BB47) -> 1549.57 | CF47: =SUM(BC47:BF47) -> 1814.426 | CG47: =SUM(BG47:BJ47) -> 1580.303 | CH47: =CH45-CH46 -> 1663.2981 | CI47: =CI45-CI46 -> 1808.1026 | CJ47: =CJ45-CJ46 -> 2011.1602 | CK47: =CK45-CK46 -> 2332.4596 | CL47: =CL45-CL46 -> 2538.0268 | CM47: =CM45-CM46 -> 2758.4173 | CN47: =CN45-CN46 -> 2988.8815 | CO47: =CO45-CO46 -> 3229.6651 | ... CQ47: =CQ45-CQ46 -> 3651.0641 | CR47: =CQ47*(1+$CQ$61) -> 3605.4258 | CS47: =CR47*(1+$CQ$61) -> 3560.358 | CT47: =CS47*(1+$CQ$61) -> 3515.8535 | CU47: =CT47*(1+$CQ$61) -> 3471.9053 | CV47: =CU47*(1+$CQ$61) -> 3428.5065 | CW47: =CV47*(1+$CQ$61) -> 3385.6502 | CX47: =CW47*(1+$CQ$61) -> 3343.3296 | CY47: =CX47*(1+$CQ$61) -> 3301.5379 | ... EO47: =EN47*(1+$CQ$61) -> 1946.5908
B48: SC | C48: 143 | D48: 143 | E48: 143 | F48: 143 | G48: 144 | H48: 144 | I48: 144 | J48: 144 | K48: 144 | L48: 145 | M48: 145 | N48: 145 | O48: 145 | P48: 145 | Q48: 143 | R48: 144 | S48: 142 | T48: 141 | U48: 140 | V48: 140 | W48: 137 | X48: 137 | Y48: 137 | Z48: 137 | AA48: 137 | AB48: 136 | AC48: 135 | AD48: 136 | AE48: 136 | AF48: 134 | AG48: 132 | AH48: 133 | AI48: 131 | AJ48: 130 | AK48: 130 | AL48: 130 | AM48: 130 | AN48: 130 | AO48: 130 | AP48: 130 | AQ48: 130 | AR48: 130 | AS48: 130 | AT48: 130 | AU48: 128 | AV48: 128 | AW48: 128 | AX48: 128 | AY48: 127 | AZ48: 127 | BA48: 126 | BB48: 127 | BC48: 126 | BD48: 125 | BE48: 123 | BF48: 124 | BG48: 121 | BH48: 120 | BI48: 118.535 | BJ48: 118.98 | BS48: =AVERAGE(C48:F48) -> 143 | BT48: =AVERAGE(G48:J48) -> 144 | BU48: =AVERAGE(K48:N48) -> 144.75 | BV48: =AVERAGE(O48:R48) -> 144.25 | BW48: =AVERAGE(S48:V48) -> 140.75 | BX48: =AVERAGE(W48:Z48) -> 137 | BY48: =AVERAGE(AA48:AD48) -> 136 | BZ48: =AVERAGE(AE48:AH48) -> 133.75 | CA48: =AVERAGE(AI48:AL48) -> 130.25 | CB48: =AVERAGE(AM48:AP48) -> 130 | CC48: =AVERAGE(AQ48:AT48) -> 130 | CD48: =AVERAGE(AU48:AX48) -> 128 | CE48: =AVERAGE(AY48:BB48) -> 126.75 | CF48: =AVERAGE(BC48:BF48) -> 124.5 | CG48: =AVERAGE(BG48:BJ48) -> 119.62875
B49: EPS | C49: =C47/C48 -> 0.23426573 | D49: =D47/D48 -> 0.26741259 | E49: =E47/E48 -> 0.27202797 | F49: =F47/F48 -> 0.51839161 | G49: =G47/G48 -> 0.32638889 | H49: =H47/H48 -> 0.4 | I49: =I47/I48 -> 0.39791667 | J49: =J47/J48 -> 0.75972222 | ... BJ49: =BJ47/BJ48 -> 4.931022 | BS49: =SUM(C49:F49) -> 1.2920979 | BT49: =SUM(G49:J49) -> 1.8840278 | BU49: =SUM(K49:N49) -> 1.9298515 | BV49: =SUM(O49:R49) -> 1.6462228 | BW49: =SUM(S49:V49) -> 1.8920756 | BX49: =SUM(W49:Z49) -> 2.2131387 | BY49: =SUM(AA49:AD49) -> 1.8787171 | BZ49: =SUM(AE49:AH49) -> 3.618373 | CA49: =SUM(AI49:AL49) -> 4.9597123 | CB49: =SUM(AM49:AP49) -> 4.5144538 | CC49: =SUM(AQ49:AT49) -> 7.4962846 | CD49: =SUM(AU49:AX49) -> 6.6813906 | CE49: =SUM(AY49:BB49) -> 12.216862 | CF49: =SUM(BC49:BF49) -> 14.589043 | CG49: =SUM(BG49:BJ49) -> 13.221065
B51: Gross Profit Margin | C51: =C40/C38 -> 0.5872591 | D51: =D40/D38 -> 0.5740566 | E51: =E40/E38 -> 0.55821025 | F51: =F40/F38 -> 0.56268842 | G51: =G40/G38 -> 0.55057753 | H51: =H40/H38 -> 0.55095541 | I51: =I40/I38 -> 0.55387046 | J51: =J40/J38 -> 0.5653965 | ... BJ51: =BJ40/BJ38 -> 0.54875215 | BS51: =BS40/BS38 -> 0.5686543 | BT51: =BT40/BT38 -> 0.55666642 | BU51: =BU40/BU38 -> 0.52790347 | BV51: =BV40/BV38 -> 0.50868017 | BW51: =BW40/BW38 -> 0.48391167 | BX51: =BX40/BX38 -> 0.5116666 | BY51: =BY40/BY38 -> 0.52800846 | BZ51: =BZ40/BZ38 -> 0.55233548 | ... CG51: =CG40/CG38 -> 0.56601078 | CH51: 0.564 | CI51: 0.568 | CJ51: 0.569 | CK51: 0.57 | CL51: 0.575 | CM51: 0.58 | CN51: 0.585 | CO51: 0.59 | CP51: 0.595 | CQ51: 0.5975
B52: SG&A as % of Revenue | C52: =C41/C38 -> 0.31049251 | D52: =D41/D38 -> 0.29716981 | E52: =E41/E38 -> 0.29887055 | F52: =F41/F38 -> 0.25024225 | G52: =G41/G38 -> 0.29471474 | H52: =H41/H38 -> 0.30290163 | I52: =I41/I38 -> 0.29921011 | J52: =J41/J38 -> 0.25108136 | ... BJ52: =BJ41/BJ38 -> 0.32514894 | BS52: =BS41/BS38 -> 0.28262304 | BT52: =BT41/BT38 -> 0.28198205 | BU52: =BU41/BU38 -> 0.28198844 | BV52: =BV41/BV38 -> 0.29941019 | BW52: =BW41/BW38 -> 0.30478039 | BX52: =BX41/BX38 -> 0.33208207 | BY52: =BY41/BY38 -> 0.34131058 | BZ52: =BZ41/BZ38 -> 0.33767182 | ... CG52: =CG41/CG38 -> 0.36627973 | CH52: 0.3625 | CI52: 0.36 | CJ52: 0.35 | CK52: 0.33 | CL52: 0.3275 | CM52: 0.325 | CN52: 0.3225 | CO52: 0.32 | CP52: 0.32 | CQ52: 0.32
B53: Operating Profit Margin | C53: =C43/C38 -> 0.2767666 | D53: =D43/D38 -> 0.27688679 | E53: =E43/E38 -> 0.2593397 | F53: =F43/F38 -> 0.30975452 | G53: =G43/G38 -> 0.25586279 | H53: =H43/H38 -> 0.24805379 | I53: =I43/I38 -> 0.25466035 | J53: =J43/J38 -> 0.31431514 | ... BJ53: =BJ43/BJ38 -> 0.22305388 | BS53: =BS43/BS38 -> 0.28503178 | BT53: =BT43/BT38 -> 0.27468438 | BU53: =BU43/BU38 -> 0.24591503 | BV53: =BV43/BV38 -> 0.20815713 | BW53: =BW43/BW38 -> 0.17913128 | BX53: =BX43/BX38 -> 0.17958452 | BY53: =BY43/BY38 -> 0.17084403 | BZ53: =BZ43/BZ38 -> 0.21435957 | ... CQ53: =CQ43/CQ38 -> 0.2775
B54: Effective Tax Rate | C54: =C46/C45 -> 0.36311787 | D54: =D46/D45 -> 0.35946399 | E54: =E46/E45 -> 0.35489221 | F54: =F46/F45 -> 0.36467261 | G54: =G46/G45 -> 0.36486486 | H54: =H46/H45 -> 0.19214586 | I54: =I46/I45 -> 0.30121951 | J54: =J46/J45 -> 0.29007138 | ... BJ54: =BJ46/BJ45 -> 0.27844293 | BS54: =BS46/BS45 -> 0.36127627 | BT54: =BT46/BT45 -> 0.28867331 | BU54: =BU46/BU45 -> 0.29614707 | BV54: =BV46/BV45 -> 0.37801679 | BW54: =BW46/BW45 -> 0.27823018 | BX54: =BX46/BX45 -> 0.28253668 | BY54: =BY46/BY45 -> 0.44086728 | BZ54: =BZ46/BZ45 -> 0.32395352 | ... CG54: =CG46/CG45 -> 0.29400583 | CH54: 0.3 | CI54: 0.3 | CJ54: 0.3 | CK54: 0.3 | CL54: 0.3 | CM54: 0.3 | CN54: 0.3 | CO54: 0.3 | CP54: 0.3 | CQ54: 0.3
B55: Net Profit Margin | C55: =C47/C38 -> 0.17933619 | D55: =D47/D38 -> 0.18037736 | E55: =E47/E38 -> 0.16898349 | F55: =F47/F38 -> 0.19953165 | G55: =G47/G38 -> 0.16450823 | H55: =H47/H38 -> 0.20382166 | I55: =I47/I38 -> 0.18104265 | J55: =J47/J38 -> 0.22533471 | ... BJ55: =BJ47/BJ38 -> 0.16114429 | BS55: =BS47/BS38 -> 0.18467397 | BT55: =BT47/BT38 -> 0.19798584 | BU55: =BU47/BU38 -> 0.17565359 | BV55: =BV47/BV38 -> 0.13192744 | BW55: =BW47/BW38 -> 0.12904635 | BX55: =BX47/BX38 -> 0.12933498 | BY55: =BY47/BY38 -> 0.096368715 | BZ55: =BZ47/BZ38 -> 0.14684953 | ... CQ55: =CQ47/CQ38 -> 0.20829681
B57: Cash & CEs | AX57: 1154.86 | AY57: 950.607 | AZ57: 1107.53 | BA57: 1091.13 | BB57: 2243.97 | BC57: 1900.672 | BD57: 1610.11 | BE57: 1188.41 | BF57: 1984.33 | BG57: 1325.27 | BH57: 1155.79 | BI57: 1035.86 | BJ57: 1807.2 | CD57: =AX57 -> 1154.86 | CE57: =BB57 -> 2243.97 | CF57: =BF57 -> 1984.33 | CG57: =BJ57 -> 1807.2 | CH57: =CF57+CH47 -> 3647.6281 | CI57: =CH57+CI47 -> 5455.7307 | CJ57: =CI57+CJ47 -> 7466.8909 | CK57: =CJ57+CK47 -> 9799.3506 | CL57: =CK57+CL47 -> 12337.377 | CM57: =CL57+CM47 -> 15095.795 | CN57: =CM57+CN47 -> 18084.676 | CO57: =CN57+CO47 -> 21314.341 | CP57: =CO57+CP47 -> 24766.047 | CQ57: =CP57+CQ47 -> 28417.111
B58: A/R | AX58: 132.906 | AY58: 107.468 | AZ58: 106.22 | BA58: 107 | BB58: 124.769 | BC58: 126.349 | BD58: 126.121 | BE58: 143.4 | BF58: 120.17 | BG58: 141.24 | BH58: 139 | BI58: 250.3 | BJ58: 190.657 | CD58: =AX58 -> 132.906 | CE58: =BB58 -> 124.769 | CF58: =BF58 -> 120.17 | CG58: =BJ58 -> 190.657
B59: Inventories | AX59: 1447.367 | AY59: 1580.313 | AZ59: 1660.7 | BA59: 1663.6 | BB59: 1323.6 | BC59: 1345.26 | BD59: 1429 | BE59: 1800.89 | BF59: 1442.08 | BG59: 1652.09 | BH59: 1722.57 | BI59: 1997.84 | BJ59: 1700.75 | CD59: =AX59 -> 1447.367 | CE59: =BB59 -> 1323.6 | CF59: =BF59 -> 1442.08 | CG59: =BJ59 -> 1700.75
B60: Prepaid ST Taxes | AX60: 185.64 | AY60: 182.393 | AZ60: 224.916 | BA60: 300.25 | BB60: 183.7 | BC60: 192.95 | BD60: 210.969 | BE60: 257.38 | BF60: 182.253 | BG60: 230.28 | BH60: 323.22 | BI60: 430.3 | BJ60: 352.469 | CD60: =AX60 -> 185.64 | CE60: =BB60 -> 183.7 | CF60: =BF60 -> 182.253 | CG60: =BJ60 -> 352.469 | CI60: Invested Capital | CL60: Avg. (2024-2025) | CN60: Projected ROIC: | CP60: ROIC | CQ60: 0.285
B61: Preaid ST Expenses | AX61: 238.672 | AY61: 232.521 | AZ61: 224.5 | BA61: 202.88 | BB61: 184.5 | BC61: 202.84 | BD61: 195.499 | BE61: 215.17 | BF61: 251.45 | BG61: 233.633 | BH61: 187.87 | BI61: 209.34 | BJ61: 211.62 | CD61: =AX61 -> 238.672 | CE61: =BB61 -> 184.5 | CF61: =BF61 -> 251.45 | CG61: =BJ61 -> 211.62 | CI61: 2023 | CJ61: 2024 | CL61: 2023-2024 | CN61: 2024 | CP61: Terminal | CQ61: -0.0125
B62: PP&E | AX62: 1269.61 | AY62: 1312.79 | AZ62: 1367.17 | BA62: 1413.91 | BB62: 1545.811 | BC62: 1561.18 | BD62: 1614.89 | BE62: 1697.75 | BF62: 1780.617 | BG62: 1846.609 | BH62: 1917.36 | BI62: 1952 | BJ62: 2033.72 | CD62: =AX62 -> 1269.61 | CE62: =BB62 -> 1545.811 | CF62: =BF62 -> 1780.617 | CG62: =BJ62 -> 2033.72 | CI62: =SUM(CE57:CE61)-CE70+CE62+CE65+CE64 -> 5281.99 | CJ62: =SUM(CF57:CF61)-CF70+CF62+CF65+CF64 -> 5660.691 | CL62: =AVERAGE(CI62:CJ62) -> 5471.3405 | CN62: =AVERAGE(CH43)*(1-CH54) -> 1637.5239 | CP62: RFR (10-year yield) | CQ62: 0.0409
B63: LT Prepaid Leases | AX63: 969.4 | AY63: 993.47 | AZ63: 1079.19 | BA63: 1048.6 | BB63: 1265.6 | BC63: 1263.74 | BD63: 1302.94 | BE63: 1360.58 | BF63: 1416.25 | BG63: 1549.4 | BH63: 1605 | BI63: 1600.38 | BJ63: 1630.181 | CD63: =AX63 -> 969.4 | CE63: =BB63 -> 1265.6 | CF63: =BF63 -> 1416.25 | CG63: =BJ63 -> 1630.181 | CN63: =CN62/CL62 -> 0.29929116 | CP63: ERP (Avg. market return - (less) RFR) | CQ63: =11.75%-CQ62 -> 0.0766
B64: Goodwill | AX64: 24.14 | AY64: 24.04 | AZ64: 24.17 | BA64: 23.91 | BB64: 24.08 | BC64: 23.992 | BD64: 23.92 | BE64: 164.46 | BF64: 159.518 | BG64: 167.35 | BH64: 172.907 | BI64: 175.3 | BJ64: 184.91 | CD64: =AX64 -> 24.14 | CE64: =BB64 -> 24.08 | CF64: =BF64 -> 159.518 | CG64: =BJ64 -> 184.91 | CI64: Capital Structure | CP64: Equity β (1-year avg.) | CQ64: ='Notes | Quant Analysis'!L206 -> 1.13
B65: LT Intangibles | AX65: 21.96 | AY65: 20.082 | AZ65: 18.2 | BA65: 0 | BB65: 0 | BC65: 0 | BD65: 0 | BE65: 13.72 | BF65: 11.673 | BG65: 10.652 | BH65: 9.3 | BI65: 7.68 | BJ65: 6.28 | CD65: =AX65 -> 21.96 | CE65: =BB65 -> 0 | CF65: =BF65 -> 11.673 | CG65: =BJ65 -> 6.28 | CI65: Mkt Cap | CL65: =Main!C5 -> 17493.776 | CP65: Discount (Cost of Equity) | CQ65: =+CQ62+(CQ63*CQ64) -> 0.127458
B66: Prepaid LT Taxes | AX66: 6.4 | AY66: 6.13 | AZ66: 6.188 | BA66: 5.8 | BB66: 9.17 | BC66: 9.099 | BD66: 9.09 | BE66: 9.25 | BF66: 17.085 | BG66: 17.598 | BH66: 21.41 | BI66: 21.58 | BJ66: 24.03 | CD66: =AX66 -> 6.4 | CE66: =BB66 -> 9.17 | CF66: =BF66 -> 17.085 | CG66: =BJ66 -> 24.03 | CI66: Debt to Ttl Mkt Cap | CL66: =Main!C7/(Main!C7+CL65) -> 0
B67: Other LT Assets | AX67: 156 | AY67: 161.725 | AZ67: 173.587 | BA67: 165 | BB67: 186.6 | BC67: 202.383 | BD67: 221.52 | BE67: 232.59 | BF67: 237.84 | BG67: 256.417 | BH67: 268.709 | BI67: 274.56 | BJ67: 314.91 | CD67: =AX67 -> 156 | CE67: =BB67 -> 186.6 | CF67: =BF67 -> 237.84 | CG67: =BJ67 -> 314.91 | CI67: Mkt Equity to Ttl Mkt Cap | CL67: =CL65/(CL65+Main!C7) -> 1 | CP67: NPV | CQ67: =NPV(CQ65,CH47:EO47) -> 21032.117
B68: Ttl Assets | AX68: =SUM(AX57:AX67) -> 5606.955 | AY68: =SUM(AY57:AY67) -> 5571.539 | AZ68: =SUM(AZ57:AZ67) -> 5992.371 | BA68: =SUM(BA57:BA67) -> 6022.08 | BB68: =SUM(BB57:BB67) -> 7091.8 | BC68: =SUM(BC57:BC67) -> 6828.465 | BD68: =SUM(BD57:BD67) -> 6744.059 | BE68: =SUM(BE57:BE67) -> 7083.6 | ... BJ68: =SUM(BJ57:BJ67) -> 8456.727 | CD68: =AX68 -> 5606.955 | CE68: =BB68 -> 7091.8 | CF68: =BF68 -> 7603.266 | CG68: =BJ68 -> 8456.727 | CI68: LT Debt / Equity | CL68: =CF69/CF81 -> 0 | CP68: SC | CQ68: =Main!C4 -> 118.981
CP69: FV | CQ69: =CQ67/CQ68 -> 176.7687
B70: A/P | AX70: 172.7 | AY70: 287.464 | AZ70: 298.91 | BA70: 309.32 | BB70: 348.44 | BC70: 261.6 | BD70: 317.34 | BE70: 385.96 | BF70: 271.4 | BG70: 303.97 | BH70: 373.33 | BI70: 352.16 | BJ70: 331.421 | CD70: =AX70 -> 172.7 | CE70: =BB70 -> 348.44 | CF70: =BF70 -> 271.4 | CG70: =BJ70 -> 331.421 | CI70: Cost of Equity | CP70: CP | CQ70: =Main!C3 -> 147.03
B71: Accrued ST Liabilities | AX71: 399.2 | AY71: 342.75 | AZ71: 399.17 | BA71: 392.949 | BB71: 348.55 | BC71: 374.44 | BD71: 396.42 | BE71: 561.615 | BF71: 559.46 | BG71: 506.99 | BH71: 423.933 | BI71: 621.155 | BJ71: 662.982 | CD71: =AX71 -> 399.2 | CE71: =BB71 -> 348.55 | CF71: =BF71 -> 559.46 | CG71: =BJ71 -> 662.982 | CI71: RFR (10-year yield) | CL71: 0.0409 | CP71: Change Δ | CQ71: =CQ69/CQ70-1 -> 0.20226283 | CR71: =IF(CQ71>0,"Upside","Downside") -> Upside
B72: Accrued ST Comp. | AX72: 248.167 | AY72: 125.05 | AZ72: 192.28 | BA72: 250.479 | BB72: 326.11 | BC72: 132.911 | BD72: 174.7 | BE72: 190.16 | BF72: 204.54 | BG72: 144.22 | BH72: 148.89 | BI72: 186.37 | BJ72: 187.887 | CD72: =AX72 -> 248.167 | CE72: =BB72 -> 326.11 | CF72: =BF72 -> 204.54 | CG72: =BJ72 -> 187.887 | CI72: Equity β (1-year avg.) | CL72: ='Notes | Quant Analysis'!L206 -> 1.13 | CP72: {=_xlfn.IFS(CQ71>=25%,"Strong Buy",CQ71>=10.00001%,"Buy",AND(CQ71<=10%,CQ71>=-4.9999%),"Hold",AND(CQ71<=-5%,CQ71>=-14.999999%),"Sell",CQ71<=-15%,"Strong Sell")} -> Buy
B73: ST Lease Liabilities | AX73: 207.97 | AY73: 210.5 | AZ73: 216.83 | BA73: 217.138 | BB73: 249.27 | BC73: 254.4 | BD73: 278.06 | BE73: 290.36 | BF73: 275.15 | BG73: 281.83 | BH73: 297.919 | BI73: 317.482 | BJ73: 298.724 | CD73: =AX73 -> 207.97 | CE73: =BB73 -> 249.27 | CF73: =BF73 -> 275.15 | CG73: =BJ73 -> 298.724 | CI73: Market Return(1-year avg.) | CL73: 0.1497
B74: ST Taxes Payable | AX74: 174.22 | AY74: 30.2 | AZ74: 20.576 | BA74: 27.231 | BB74: 12.098 | BC74: 53.08 | BD74: 19.23 | BE74: 96.8 | BF74: 183.12 | BG74: 31.276 | BH74: 26.745 | BI74: 62.71 | BJ74: 43.94 | CD74: =AX74 -> 174.22 | CE74: =BB74 -> 12.098 | CF74: =BF74 -> 183.12 | CG74: =BJ74 -> 43.94 | CI74: Cost of Equity | CL74: =(CL71+CL72)*(CL73-CL71) -> 0.12739392
B75: ST Gift Card Liabilities | AX75: 251.47 | AY75: 223.97 | AZ75: 216.11 | BA75: 213.256 | BB75: 306.479 | BC75: 268.296 | BD75: 250.75 | BE75: 238.327 | BF75: 308.35 | BG75: 271.07 | BH75: 252.334 | BI75: 253.798 | BJ75: 316.632 | CD75: =AX75 -> 251.47 | CE75: =BB75 -> 306.479 | CF75: =BF75 -> 308.35 | CG75: =BJ75 -> 316.632
B76: Other ST Liabilities | AX76: 38.405 | AY76: 36.81 | AZ76: 42.46 | BA76: 37.737 | BB76: 40.308 | BC76: 38.78 | BD76: 32.12 | BE76: 40.28 | BF76: 37.58 | BG76: 33 | BH76: 34.186 | BI76: 48.49 | BJ76: 45.95 | CD76: =AX76 -> 38.405 | CE76: =BB76 -> 40.308 | CF76: =BF76 -> 37.58 | CG76: =BJ76 -> 45.95 | CI76: Cost of Debt
B77: LT Lease Liabilities | AX77: 862.36 | AY77: 888.5 | AZ77: 976.73 | BA77: 950.954 | BB77: 1154.012 | BC77: 1147.6 | BD77: 1180.8 | BE77: 1223.73 | BF77: 1300.63 | BG77: 1424.94 | BH77: 1464.799 | BI77: 1445.312 | BJ77: 1499.71 | CD77: =AX77 -> 862.36 | CE77: =BB77 -> 1154.012 | CF77: =BF77 -> 1300.63 | CG77: =BJ77 -> 1499.71 | CI77: Cost of Debt | CL77: 0
B78: LT Income Taxes | AX78: =28.55+55.08 -> 83.63 | AY78: =28.55+54.5 -> 83.05 | AZ78: =15.864+55.25 -> 71.114 | BA78: =15.86+53.833 -> 69.693 | BB78: =15.86+29.52 -> 45.38 | BC78: =15.86+29.15 -> 45.01 | BD78: 28.87 | BE78: 33.231 | BF78: 98.188 | BG78: 98.189 | BH78: 62.4 | BI78: 111.59 | BJ78: 52.27 | CD78: =AX78 -> 83.63 | CE78: =BB78 -> 45.38 | CF78: =BF78 -> 98.188 | CG78: =BJ78 -> 52.27 | CI78: Tax Rate | CL78: 0.3
B79: Other LT Liabilities | AX79: 20.04 | AY79: 23.027 | AZ79: 24.748 | BA79: 27.65 | BB79: 29.52 | BC79: 32.47 | BD79: 34.14 | BE79: 37.44 | BF79: 40.79 | BG79: 45.45 | BH79: 51.615 | BI79: 54.088 | BJ79: 55.36 | CD79: =AX79 -> 20.04 | CE79: =BB79 -> 29.52 | CF79: =BF79 -> 40.79 | CG79: =BJ79 -> 55.36 | CI79: After Tax Cost of Debt | CL79: =CL77*(1-CL78) -> 0
B80: Ttl Liabilities | AX80: =SUM(AX70:AX79) -> 2458.162 | AY80: =SUM(AY70:AY79) -> 2251.321 | AZ80: =SUM(AZ70:AZ79) -> 2458.928 | BA80: =SUM(BA70:BA79) -> 2496.407 | BB80: =SUM(BB70:BB79) -> 2860.167 | BC80: =SUM(BC70:BC79) -> 2608.587 | BD80: =SUM(BD70:BD79) -> 2712.43 | BE80: =SUM(BE70:BE79) -> 3097.903 | ... BJ80: =SUM(BJ70:BJ79) -> 3494.876 | CD80: =AX80 -> 2458.162 | CE80: =BB80 -> 2860.167 | CF80: =BF80 -> 3279.208 | CG80: =BJ80 -> 3494.876
B81: SE | AX81: 3148.79 | AY81: 3321.07 | AZ81: 3533.48 | BA81: 3525.849 | BB81: 4232 | BC81: 4219.8 | BD81: 4031.64 | BE81: 3985.73 | BF81: 4324.04 | BG81: 4289.57 | BH81: 4387.279 | BI81: 4502 | BJ81: 4961.84 | CD81: =AX81 -> 3148.79 | CE81: =BB81 -> 4232 | CF81: =BF81 -> 4324.04 | CG81: =BJ81 -> 4961.84 | CI81: WACC | CL81: =(CL67*CL74)+(CL66*CL79*(1-CL78)) -> 0.12739392
B82: Ttl L + SE | AX82: =AX80+AX81 -> 5606.952 | AY82: =AY80+AY81 -> 5572.391 | AZ82: =AZ80+AZ81 -> 5992.408 | BA82: =BA80+BA81 -> 6022.256 | BB82: =BB80+BB81 -> 7092.167 | BC82: =BC80+BC81 -> 6828.387 | BD82: =BD80+BD81 -> 6744.07 | BE82: =BE80+BE81 -> 7083.633 | ... BJ82: =BJ80+BJ81 -> 8456.716 | CD82: =AX82 -> 5606.952 | CE82: =BB82 -> 7092.167 | CF82: =BF82 -> 7603.248 | CG82: =BJ82 -> 8456.716
B84: Current Ratio | AX84: =SUM(AX57:AX61)/SUM(AX70:AX76) -> 2.1174032 | AY84: =SUM(AY57:AY61)/SUM(AY70:AY76) -> 2.4295338 | AZ84: =SUM(AZ57:AZ61)/SUM(AZ70:AZ76) -> 2.3975905 | BA84: =SUM(BA57:BA61)/SUM(BA70:BA76) -> 2.3236218 | BB84: =SUM(BB57:BB61)/SUM(BB70:BB76) -> 2.4892117 | BC84: =SUM(BC57:BC61)/SUM(BC70:BC76) -> 2.7235648 | BD84: =SUM(BD57:BD61)/SUM(BD70:BD76) -> 2.4320103 | BE84: =SUM(BE57:BE61)/SUM(BE70:BE76) -> 1.9990274 | ... BJ84: =SUM(BJ57:BJ61)/SUM(BJ70:BJ76) -> 2.2583389 | CD84: =SUM(CD57:CD61)/SUM(CD70:CD76) -> 2.1174032 | CE84: =SUM(CE57:CE61)/SUM(CE70:CE76) -> 2.4892117 | CF84: =SUM(CF57:CF61)/SUM(CF70:CF76) -> 2.1636676 | CG84: =SUM(CG57:CG61)/SUM(CG70:CG76) -> 2.2583389
B85: Quick Ratio | AX85: =(SUM(AX57:AX61)-AX59)/SUM(AX70:AX75) -> 1.1777163 | AY85: =(SUM(AY57:AY61)-AY59)/SUM(AY70:AY75) -> 1.2074334 | AZ85: =(SUM(AZ57:AZ61)-AZ59)/SUM(AZ70:AZ75) -> 1.2375889 | BA85: =(SUM(BA57:BA61)-BA59)/SUM(BA70:BA75) -> 1.2062483 | BB85: =(SUM(BB57:BB61)-BB59)/SUM(BB70:BB75) -> 1.7203207 | BC85: =(SUM(BC57:BC61)-BC59)/SUM(BC70:BC75) -> 1.8017122 | BD85: =(SUM(BD57:BD61)-BD59)/SUM(BD70:BD75) -> 1.4916109 | BE85: =(SUM(BE57:BE61)-BE59)/SUM(BE70:BE75) -> 1.0233312 | ... BJ85: =(SUM(BJ57:BJ61)-BJ59)/SUM(BJ70:BJ75) -> 1.3911628 | CD85: =(SUM(CD57:CD61)-CD59)/SUM(CD70:CD75) -> 1.1777163 | CE85: =(SUM(CE57:CE61)-CE59)/SUM(CE70:CE75) -> 1.7203207 | CF85: =(SUM(CF57:CF61)-CF59)/SUM(CF70:CF75) -> 1.4085321 | CG85: =(SUM(CG57:CG61)-CG59)/SUM(CG70:CG75) -> 1.3911628
B86: Cash Ratio | AX86: =AX57/SUM(AX70:AX76) -> 0.77396638 | AY86: =AY57/SUM(AY70:AY76) -> 0.75640465 | AZ86: =AZ57/SUM(AZ70:AZ76) -> 0.79889002 | BA86: =BA57/SUM(BA70:BA76) -> 0.75348558 | BB86: =BB57/SUM(BB70:BB76) -> 1.3756096 | BC86: =BC57/SUM(BC70:BC76) -> 1.3738073 | BD86: =BD57/SUM(BD70:BD76) -> 1.0963421 | BE86: =BE57/SUM(BE70:BE76) -> 0.65894576 | ... BJ86: =BJ57/SUM(BJ70:BJ76) -> 0.95743869 | CD86: =CD57/SUM(CD70:CD76) -> 0.77396638 | CE86: =CE57/SUM(CE70:CE76) -> 1.3756096 | CF86: =CF57/SUM(CF70:CF76) -> 1.0786747 | CG86: =CG57/SUM(CG70:CG76) -> 0.95743869
B87: Ttl Asset Turnover | AX87: =AX82/AX38 -> 2.0228216 | AY87: =AY82/AY38 -> 2.7850926 | AZ87: =AZ82/AZ38 -> 2.7125401 | BA87: =BA82/BA38 -> 2.7321632 | BB87: =BB82/BB38 -> 2.2127618 | BC87: =BC82/BC38 -> 3.0913233 | BD87: =BD82/BD38 -> 2.8443078 | BE87: =BE82/BE38 -> 2.9556393 | ... BJ87: =BJ82/BJ38 -> 2.3227676 | CD87: =CD82/CD38 -> 0.69131861 | CE87: =CE82/CE38 -> 0.73728744 | CF87: =CF82/CF38 -> 0.71809195 | CG87: =CG82/CG38 -> 0.76168927
B88: Inventory Turnover Ratio | AX88: =AX39/AVERAGE(AU59:AX59) -> 0.85962993 | AY88: =AY39/AVERAGE(AV59:AY59) -> 0.56148602 | AZ88: =AZ39/AVERAGE(AW59:AZ59) -> 0.5827386 | BA88: =BA39/AVERAGE(AX59:BA59) -> 0.59672732 | BB88: =BB39/AVERAGE(AY59:BB59) -> 0.83600224 | BC88: =BC39/AVERAGE(AZ59:BC59) -> 0.62324383 | BD88: =BD39/AVERAGE(BA59:BD59) -> 0.66573403 | BE88: =BE39/AVERAGE(BB59:BE59) -> 0.67478703 | ... BJ88: =BJ39/AVERAGE(BG59:BJ59) -> 0.92907786 | CD88: =CD39/AVERAGE(CA59:CD59) -> 2.4998497 | CE88: =CE39/AVERAGE(CB59:CE59) -> 2.8942965 | CF88: =CF39/AVERAGE(CC59:CF59) -> 3.0742358 | CG88: =CG39/AVERAGE(CD59:CG59) -> 3.2590906
B89: Return on Assets | AX89: =AX47/AX82 -> 0.0212142 | AY89: =AY47/AY82 -> 0.052094693 | AZ89: =AZ47/AZ82 -> 0.056980433 | BA89: =BA47/BA82 -> 0.04124833 | BB89: =BB47/BB82 -> 0.09438864 | BC89: =BC47/BC82 -> 0.047081104 | BD89: =BD47/BD82 -> 0.05825503 | BE89: =BE47/BE82 -> 0.049684957 | ... BJ89: =BJ47/BJ82 -> 0.069375985 | CD89: =CD47/CD82 -> 0.15252815 | CE89: =CE47/CE82 -> 0.21849034 | CF89: =CF47/CF82 -> 0.23863828 | CG89: =CG47/CG82 -> 0.18686958
B90: Return on Equity | AX90: =AX47/AX81 -> 0.037775463 | AY90: =AY47/AY81 -> 0.087409178 | AZ90: =AZ47/AZ81 -> 0.096632781 | BA90: =BA47/BA81 -> 0.070453386 | BB90: =BB47/BB81 -> 0.15818053 | BC90: =BC47/BC81 -> 0.076185601 | BD90: =BD47/BD81 -> 0.097448185 | BE90: =BE47/BE81 -> 0.088302519 | ... BJ90: =BJ47/BJ81 -> 0.11824102 | CD90: =CD47/CD81 -> 0.27160211 | CE90: =CE47/CE81 -> 0.36615548 | CF90: =CF47/CF81 -> 0.4196136 | CG90: =CG47/CG81 -> 0.31849133
B92: NI | C92: =C47 -> 33.5 | D92: =D47 -> 38.24 | E92: =E47 -> 38.9 | F92: =F47 -> 74.13 | G92: =G47 -> 47 | H92: =H47 -> 57.6 | I92: =I47 -> 57.3 | J92: =J47 -> 109.4 | ... BJ92: =BJ47 -> 586.693 | BS92: =BS47 -> 184.77 | BT92: =BT47 -> 271.3 | BU92: =BU47 -> 279.5 | BV92: =BV47 -> 237.1 | BW92: =BW47 -> 265.9 | BX92: =BX47 -> 303.2 | BY92: =BY47 -> 255.3 | BZ92: =BZ47 -> 482.9 | ... CF92: =CF47 -> 1814.426 | CG92: =SUM(BG92:BJ92) -> 1580.303
B93: CFFO | C93: 5.7 | D93: 13.9 | E93: 34 | F93: 150.1 | G93: 16 | H93: 47.6 | I93: 49.7 | J93: 166.9 | K93: 25.1 | L93: 45.8 | M93: 23.9 | N93: 183.5 | O93: 71 | P93: 53 | Q93: 42.9 | R93: 147.6 | S93: 20.9 | T93: 11.2 | U93: -6.2 | V93: 271.6 | W93: 40 | X93: 61.2 | Y93: -2.5 | Z93: 287.7 | AA93: 19.4 | AB93: 82.6 | AC93: 29.3 | AD93: 358 | AE93: 35.8 | AF93: 174.2 | AG93: 106.8 | AH93: 425.9 | AI93: -62.8 | AJ93: 112.8 | AK93: 45.1 | AL93: 574.2 | AM93: -121.2 | AN93: 181.3 | AO93: 25.3 | AP93: 717.9 | AQ93: 214.1 | AR93: 285.7 | AS93: 158.4 | AT93: 731 | AU93: -243.3 | AV93: 97.6 | AW93: 65.8 | AX93: 1046.3 | AY93: 45.5 | AZ93: 476.7 | BA93: 389.9 | BB93: 1384.1 | BC93: 127.5 | BD93: 443.1 | BE93: 300.7 | BF93: 1401.4 | BG93: -119 | BH93: 328.7 | BI93: 249.9 | BJ93: 1142.9 | BS93: =SUM(C93:F93) -> 203.7 | BT93: =SUM(G93:J93) -> 280.2 | BU93: =SUM(K93:N93) -> 278.3 | BV93: =SUM(O93:R93) -> 314.5 | BW93: =SUM(S93:V93) -> 297.5 | BX93: =SUM(W93:Z93) -> 386.4 | BY93: =SUM(AA93:AD93) -> 489.3 | BZ93: =SUM(AE93:AH93) -> 742.7 | CA93: =SUM(AI93:AL93) -> 669.3 | CB93: =SUM(AM93:AP93) -> 803.3 | CC93: =SUM(AQ93:AT93) -> 1389.2 | CD93: =SUM(AU93:AX93) -> 966.4 | CE93: =SUM(AY93:BB93) -> 2296.2 | CF93: =SUM(BC93:BF93) -> 2272.7 | CG93: =SUM(BG93:BJ93) -> 1602.5
B94: CapEx, net | C94: -74.8 | D94: -12.49 | E94: -13.36 | F94: -15.967 | G94: -12.696 | H94: -26.35 | I94: -32.99 | J94: -21.18 | K94: -20.97 | L94: -23.03 | M94: -27.93 | N94: -34.46 | O94: -25.4 | P94: -26.7 | Q94: -37.3 | R94: -30.4 | S94: -27.9 | T94: -37.2 | U94: -42.9 | V94: -35.4 | W94: -26.6 | X94: -44.6 | Y94: -34.9 | Z94: -43.3 | AA94: -19.9 | AB94: -30 | AC94: -57.2 | AD94: -50.7 | AE94: -34.3 | AF94: -49.7 | AG94: -72.7 | AH94: -69.1 | AI94: -68.4 | AJ94: -67.3 | AK94: -78.5 | AL94: -68.8 | AM94: -52.1 | AN94: -52.6 | AO94: -66.1 | AP94: -58.4 | AQ94: -64.2 | AR94: -80.3 | AS94: -122.5 | AT94: -127.5 | AU94: -111.4 | AV94: -144.7 | AW94: -175.6 | AX94: -207 | AY94: -136.9 | AZ94: -145.5 | BA94: -162.9 | BB94: -206.5 | BC94: -130.7 | BD94: -145.1 | BE94: -178.5 | BF94: -235 | BG94: -152.3 | BH94: -177.9 | BI94: -167.4 | BJ94: -183.2 | BS94: =SUM(C94:F94) -> -116.617 | BT94: =SUM(G94:J94) -> -93.216 | BU94: =SUM(K94:N94) -> -106.39 | BV94: =SUM(O94:R94) -> -119.8 | BW94: =SUM(S94:V94) -> -143.4 | BX94: =SUM(W94:Z94) -> -149.4 | BY94: =SUM(AA94:AD94) -> -157.8 | BZ94: =SUM(AE94:AH94) -> -225.8 | CA94: =SUM(AI94:AL94) -> -283 | CB94: =SUM(AM94:AP94) -> -229.2 | CC94: =SUM(AQ94:AT94) -> -394.5 | CD94: =SUM(AU94:AX94) -> -638.7 | CE94: =SUM(AY94:BB94) -> -651.8 | CF94: =SUM(BC94:BF94) -> -689.3 | CG94: =SUM(BG94:BJ94) -> -680.8
B95: FCF | C95: =C94+C93 -> -69.1 | D95: =D94+D93 -> 1.41 | E95: =E94+E93 -> 20.64 | F95: =F94+F93 -> 134.133 | G95: =G94+G93 -> 3.304 | H95: =H94+H93 -> 21.25 | I95: =I94+I93 -> 16.71 | J95: =J94+J93 -> 145.72 | ... BJ95: =BJ94+BJ93 -> 959.7 | BS95: =SUM(C95:F95) -> 87.083 | BT95: =SUM(G95:J95) -> 186.984 | BU95: =SUM(K95:N95) -> 171.91 | BV95: =SUM(O95:R95) -> 194.7 | BW95: =SUM(S95:V95) -> 154.1 | BX95: =SUM(W95:Z95) -> 237 | BY95: =SUM(AA95:AD95) -> 331.5 | BZ95: =SUM(AE95:AH95) -> 516.9 | CA95: =SUM(AI95:AL95) -> 386.3 | CB95: =SUM(AM95:AP95) -> 574.1 | CC95: =SUM(AQ95:AT95) -> 994.7 | CD95: =SUM(AU95:AX95) -> 327.7 | CE95: =SUM(AY95:BB95) -> 1644.4 | CF95: =SUM(BC95:BF95) -> 1583.4 | CG95: =SUM(BG95:BJ95) -> 921.7
B96: SC | C96: =C48 -> 143 | D96: =D48 -> 143 | E96: =E48 -> 143 | F96: =F48 -> 143 | G96: =G48 -> 144 | H96: =H48 -> 144 | I96: =I48 -> 144 | J96: =J48 -> 144 | ... BJ96: =BJ48 -> 118.98 | BS96: =BS48 -> 143 | BT96: =BT48 -> 144 | BU96: =BU48 -> 144.75 | BV96: =BV48 -> 144.25 | BW96: =BW48 -> 140.75 | BX96: =BX48 -> 137 | BY96: =BY48 -> 136 | BZ96: =BZ48 -> 133.75 | ... CF96: =CF48 -> 124.5 | CG96: =AVERAGE(BG96:BJ96) -> 119.62875
B97: FCF per Share | C97: =C95/C96 -> -0.48321678 | D97: =D95/D96 -> 0.0098601399 | E97: =E95/E96 -> 0.14433566 | F97: =F95/F96 -> 0.93799301 | G97: =G95/G96 -> 0.022944444 | H97: =H95/H96 -> 0.14756944 | I97: =I95/I96 -> 0.11604167 | J97: =J95/J96 -> 1.0119444 | ... BJ97: =BJ95/BJ96 -> 8.0660615 | BS97: =SUM(C97:F97) -> 0.60897203 | BT97: =SUM(G97:J97) -> 1.2985 | BU97: =SUM(K97:N97) -> 1.185784 | BV97: =SUM(O97:R97) -> 1.3489118 | BW97: =SUM(S97:V97) -> 1.1027356 | BX97: =SUM(W97:Z97) -> 1.729927 | BY97: =SUM(AA97:AD97) -> 2.4360072 | BZ97: =SUM(AE97:AH97) -> 3.881174 | CA97: =SUM(AI97:AL97) -> 2.9792425 | CB97: =SUM(AM97:AP97) -> 4.4161538 | CC97: =SUM(AQ97:AT97) -> 7.6515385 | CD97: =SUM(AU97:AX97) -> 2.5601562 | CE97: =SUM(AY97:BB97) -> 12.962217 | CF97: =SUM(BC97:BF97) -> 12.758551 | CG97: =SUM(BG97:BJ97) -> 7.7765764

Sheet Notes | Quant Analysis
CD1: 0
I2: Employee Scope: | AG2: General Notes/Observations
J33: Notes: | K33: [X]
K34: [Y]
K35: [Z] | AG35: Financial Stmts. Notes/Observations
AG36: Revenues:
I37: Institutional Ownership Snapshot Q2'25
J65: Notes: | K65: [X]
K66: [Y]
K67: [Z]
I69: Revenue Breakdown by Segment | AG69: Earnings Scope:
J101: Notes: | K101: [X]
K102: [Y]
K103: [Z]
I105: Q/q Total Revenues, Net Income, FCF | AG105: Balance Sheet Scope:
J134: Notes: | K134: [X]
K135: [Y]
K136: [Z]
I138: Y/y Total Revenues, Net Income, FCF | AG138: [Equity Preformance Compared to Peers]
J167: Notes: | K167: [X] | AG167: Notes: | AH167: Clothing / Consumer Discretionary has really been hammered the last year … LEVI is an outpreformer, but even their management team has ste tampered expectations for future earnings in the coming quarters
K168: [Y] | AH168: [Y]
K169: [Z] | AH169: [Z]
B185: 1256 Trading Days? (From: 9/22/2020 - 9/22/2025)
B186: Close | C186: High | D186: Low | E186: Open | F186: Volume | G186: UTC Date | H186: Change
B187: 169.62 | C187: 170.8998 | D187: 167.5342 | E187: 169.7 | F187: 7885914 | G187: Fri, 19 Sep 2025 00:00:00 GMT | H187: =B187/E187-1 -> -0.00047142015
B188: 169.76 | C188: 170.72 | D188: 166.52 | E188: 169.02 | F188: 7061041 | G188: Thu, 18 Sep 2025 00:00:00 GMT | H188: =B188/E188-1 -> 0.0043781801
B189: 163.48 | C189: 165.69 | D189: 162.22 | E189: 162.34 | F189: 4339919 | G189: Wed, 17 Sep 2025 00:00:00 GMT | H189: =B189/E189-1 -> 0.0070222989
B190: 162.34 | C190: 163.64 | D190: 159.75 | E190: 160 | F190: 5069165 | G190: Tue, 16 Sep 2025 00:00:00 GMT | H190: =B190/E190-1 -> 0.014625
B191: 159.98 | C191: 162.165 | D191: 159.2515 | E191: 160.73 | F191: 5535418 | G191: Mon, 15 Sep 2025 00:00:00 GMT | H191: =B191/E191-1 -> -0.0046662104
B192: 159.865 | C192: 165.93 | D192: 159.75 | E192: 165.26 | F192: 7922053 | G192: Fri, 12 Sep 2025 00:00:00 GMT | H192: =B192/E192-1 -> -0.032645528
B193: 165.78 | C193: 168.59 | D193: 163.34 | E193: 163.955 | F193: 6620102 | G193: Thu, 11 Sep 2025 00:00:00 GMT | H193: =B193/E193-1 -> 0.011131103
B194: 163.9 | C194: 167.3522 | D194: 163.2 | E194: 164.7 | F194: 5737178 | G194: Wed, 10 Sep 2025 00:00:00 GMT | H194: =B194/E194-1 -> -0.0048573163
B195: 165.69 | C195: 169.15 | D195: 164.38 | E195: 167.83 | F195: 8578585 | G195: Tue, 09 Sep 2025 00:00:00 GMT | H195: =B195/E195-1 -> -0.012750998
B196: 168.1 | C196: 169.61 | D196: 162.8 | E196: 167.76 | F196: 13808121 | G196: Mon, 08 Sep 2025 00:00:00 GMT | H196: =B196/E196-1 -> 0.0020267048
B197: 167.8 | C197: 176.1785 | D197: 163.98 | E197: 165.14 | F197: 36663712 | G197: Fri, 05 Sep 2025 00:00:00 GMT | H197: =B197/E197-1 -> 0.016107545
B198: 206.09 | C198: 206.6399 | D198: 197.67 | E198: 200.9 | F198: 11429740 | G198: Thu, 04 Sep 2025 00:00:00 GMT | H198: =B198/E198-1 -> 0.025833748
B199: 198.53 | C199: 203.0099 | D199: 197.6101 | E199: 201.3 | F199: 4023399 | G199: Wed, 03 Sep 2025 00:00:00 GMT | H199: =B199/E199-1 -> -0.013760556
B200: 200.21 | C200: 201.27 | D200: 195.58 | E200: 199.81 | F200: 4359898 | G200: Tue, 02 Sep 2025 00:00:00 GMT | H200: =B200/E200-1 -> 0.0020019018 | K200: Min | L200: =MIN(H187:H1442) -> -0.080917561
B201: 202.2 | C201: 205.8 | D201: 200.71 | E201: 204.62 | F201: 3121633 | G201: Fri, 29 Aug 2025 00:00:00 GMT | H201: =B201/E201-1 -> -0.011826801 | K201: Max | L201: =MAX(H187:H1442) -> 0.12227208
B202: 205.08 | C202: 206.605 | D202: 202.38 | E202: 206.05 | F202: 2778977 | G202: Thu, 28 Aug 2025 00:00:00 GMT | H202: =B202/E202-1 -> -0.0047075952 | K202: Mean μ | L202: =AVERAGE(H187:H1442) -> -0.00046874586
B203: 205.57 | C203: 207.67 | D203: 203.5 | E203: 203.8 | F203: 3351780 | G203: Wed, 27 Aug 2025 00:00:00 GMT | H203: =B203/E203-1 -> 0.0086849853 | K203: Median | L203: =MEDIAN(H187:H1442) -> -0.00024107491
B204: 202.53 | C204: 204.3854 | D204: 200.5 | E204: 204.36 | F204: 2472253 | G204: Tue, 26 Aug 2025 00:00:00 GMT | H204: =B204/E204-1 -> -0.0089547857 | K204: SD σ | L204: =_xlfn.STDEV.P(H187:H1442) -> 0.01974337
B205: 202.44 | C205: 208 | D205: 202.37 | E205: 206.7 | F205: 2933069 | G205: Mon, 25 Aug 2025 00:00:00 GMT | H205: =B205/E205-1 -> -0.020609579 | K205: 3σ 1-Day Δ: ± | L205: =3*L204 -> 0.059230111 | N205: <- Sharpe Ratio (Risk Adjusted Return)
B206: 207.59 | C206: 208.13 | D206: 198.5 | E206: 198.5 | F206: 3726997 | G206: Fri, 22 Aug 2025 00:00:00 GMT | H206: =B206/E206-1 -> 0.045793451 | K206: β (1-year avg.) | L206: 1.13 | N206: <- Sortino Ratio (Downside Risk Adjusted Return)
B207: 198.18 | C207: 198.48 | D207: 195.2 | E207: 196.905 | F207: 2222686 | G207: Thu, 21 Aug 2025 00:00:00 GMT | H207: =B207/E207-1 -> 0.0064752038
B208: 198.12 | C208: 200.3 | D208: 195.31 | E208: 197.675 | F208: 2797638 | G208: Wed, 20 Aug 2025 00:00:00 GMT | H208: =B208/E208-1 -> 0.0022511698 | J208: n = | K208: 1256
B209: 197.66 | C209: 205.8942 | D209: 196.52 | E209: 204.7 | F209: 4286456 | G209: Tue, 19 Aug 2025 00:00:00 GMT | H209: =B209/E209-1 -> -0.034391793 | J209: Histogram Data | M209: Distribution Overlay | Q209: SD Lines
B210: 203.62 | C210: 206.74 | D210: 200.31 | E210: 200.34 | F210: 4864443 | G210: Mon, 18 Aug 2025 00:00:00 GMT | H210: =B210/E210-1 -> 0.016372167 | J210: Bin | K210: Frequency | M210: (X) 1-Day Δ | N210: (Y) Pop. Density | Q210: X | R210: Y
B211: 198.46 | C211: 201.14 | D211: 196.4 | E211: 200.78 | F211: 4757473 | G211: Fri, 15 Aug 2025 00:00:00 GMT | H211: =B211/E211-1 -> -0.011554936 | J211: -0.062 | K211: 5 | M211: =M212-0.001 -> -0.063 | N211: =_xlfn.NORM.DIST(M211,$L$202,$L$204,FALSE) -> 0.134044 | P211: Mean | Q211: =L202 -> -0.00046874586 | R211: 0
B212: 195.19 | C212: 197.023 | D212: 192.35 | E212: 196.9 | F212: 4102420 | G212: Thu, 14 Aug 2025 00:00:00 GMT | H212: =B212/E212-1 -> -0.0086846115 | J212: -0.061 | K212: 0 | M212: =M213-0.001 -> -0.062 | N212: =_xlfn.NORM.DIST(M212,$L$202,$L$204,FALSE) -> 0.15716622 | Q212: =L202 -> -0.00046874586 | R212: 20
B213: 200.49 | C213: 200.829 | D213: 192.85 | E213: 195.61 | F213: 4239265 | G213: Wed, 13 Aug 2025 00:00:00 GMT | H213: =B213/E213-1 -> 0.0249476 | J213: -0.06 | K213: 2 | M213: =M214-0.001 -> -0.061 | N213: =_xlfn.NORM.DIST(M213,$L$202,$L$204,FALSE) -> 0.18380481 | P213: -3σ | Q213: =($L$204*-3)+$L$202 -> -0.059698857 | R213: 0
B214: 192.93 | C214: 193.15 | D214: 186.7626 | E214: 188.16 | F214: 3397154 | G214: Tue, 12 Aug 2025 00:00:00 GMT | H214: =B214/E214-1 -> 0.025350765 | J214: -0.059 | K214: 0 | M214: =M215-0.001 -> -0.06 | N214: =_xlfn.NORM.DIST(M214,$L$202,$L$204,FALSE) -> 0.21440771 | Q214: =($L$204*-3)+$L$202 -> -0.059698857 | R214: 2
B215: 186.44 | C215: 191.9999 | D215: 185.95 | E215: 189.13 | F215: 2581798 | G215: Mon, 11 Aug 2025 00:00:00 GMT | H215: =B215/E215-1 -> -0.014223021 | J215: -0.058 | K215: 0 | M215: =M216-0.001 -> -0.059 | N215: =_xlfn.NORM.DIST(M215,$L$202,$L$204,FALSE) -> 0.24946508 | P215: -2σ | Q215: =($L$204*-2)+$L$202 -> -0.039955487 | R215: 0
B216: 189.43 | C216: 191.25 | D216: 186.52 | E216: 191.08 | F216: 3191223 | G216: Fri, 08 Aug 2025 00:00:00 GMT | H216: =B216/E216-1 -> -0.0086351266 | J216: -0.057 | K216: 1 | M216: =M217-0.001 -> -0.058 | N216: =_xlfn.NORM.DIST(M216,$L$202,$L$204,FALSE) -> 0.28951095 | Q216: =($L$204*-2)+$L$202 -> -0.039955487 | R216: 5
B217: 191.14 | C217: 198.1 | D217: 189.77 | E217: 197.7 | F217: 3160135 | G217: Thu, 07 Aug 2025 00:00:00 GMT | H217: =B217/E217-1 -> -0.033181588 | J217: -0.056 | K217: 1 | M217: =M218-0.001 -> -0.057 | N217: =_xlfn.NORM.DIST(M217,$L$202,$L$204,FALSE) -> 0.33512443 | P217: -1σ | Q217: =($L$204*-1)+$L$202 -> -0.020212116 | R217: 0
B218: 196.51 | C218: 198.15 | D218: 194.85 | E218: 195.65 | F218: 2143781 | G218: Wed, 06 Aug 2025 00:00:00 GMT | H218: =B218/E218-1 -> 0.0043956044 | J218: -0.055 | K218: 0 | M218: =M219-0.001 -> -0.056 | N218: =_xlfn.NORM.DIST(M218,$L$202,$L$204,FALSE) -> 0.38693056 | Q218: =($L$204*-1)+$L$202 -> -0.020212116 | R218: 12
B219: 195.07 | C219: 197.82 | D219: 194.64 | E219: 195.475 | F219: 2871555 | G219: Tue, 05 Aug 2025 00:00:00 GMT | H219: =B219/E219-1 -> -0.0020718762 | J219: -0.054 | K219: 0 | M219: =M220-0.001 -> -0.055 | N219: =_xlfn.NORM.DIST(M219,$L$202,$L$204,FALSE) -> 0.44560066 | P219: 1σ | Q219: =($L$204*1)+$L$202 -> 0.019274625 | R219: 0
B220: 196.45 | C220: 197.49 | D220: 192.81 | E220: 195.08 | F220: 3524454 | G220: Mon, 04 Aug 2025 00:00:00 GMT | H220: =B220/E220-1 -> 0.0070227599 | J220: -0.053 | K220: 0 | M220: =M221-0.001 -> -0.054 | N220: =_xlfn.NORM.DIST(M220,$L$202,$L$204,FALSE) -> 0.51185209 | Q220: =($L$204*1)+$L$202 -> 0.019274625 | R220: 12
B221: 193.33 | C221: 200 | D221: 191.44 | E221: 199.94 | F221: 4697884 | G221: Fri, 01 Aug 2025 00:00:00 GMT | H221: =B221/E221-1 -> -0.033059918 | J221: -0.052 | K221: 2 | M221: =M222-0.001 -> -0.053 | N221: =_xlfn.NORM.DIST(M221,$L$202,$L$204,FALSE) -> 0.5864473 | P221: 2σ | Q221: =($L$204*2)+$L$202 -> 0.039017995 | R221: 0
B222: 200.53 | C222: 206.635 | D222: 200.24 | E222: 203.965 | F222: 4173883 | G222: Thu, 31 Jul 2025 00:00:00 GMT | H222: =B222/E222-1 -> -0.016841125 | J222: -0.051 | K222: 1 | M222: =M223-0.001 -> -0.052 | N222: =_xlfn.NORM.DIST(M222,$L$202,$L$204,FALSE) -> 0.67019217 | Q222: =($L$204*2)+$L$202 -> 0.039017995 | R222: 5
B223: 206.47 | C223: 214.1499 | D223: 205.89 | E223: 214 | F223: 3850934 | G223: Wed, 30 Jul 2025 00:00:00 GMT | H223: =B223/E223-1 -> -0.035186916 | J223: -0.05 | K223: 1 | M223: =M224-0.001 -> -0.051 | N223: =_xlfn.NORM.DIST(M223,$L$202,$L$204,FALSE) -> 0.76393352 | P223: 3σ | Q223: =($L$204*3)+$L$202 -> 0.058761365 | R223: 0
B224: 214.04 | C224: 219.12 | D224: 213.88 | E224: 216 | F224: 2570261 | G224: Tue, 29 Jul 2025 00:00:00 GMT | H224: =B224/E224-1 -> -0.0090740741 | J224: -0.049 | K224: 4 | M224: =M225-0.001 -> -0.05 | N224: =_xlfn.NORM.DIST(M224,$L$202,$L$204,FALSE) -> 0.86855563 | Q224: =($L$204*3)+$L$202 -> 0.058761365 | R224: 2
B225: 216.59 | C225: 220.7 | D225: 216.33 | E225: 220.32 | F225: 2333769 | G225: Mon, 28 Jul 2025 00:00:00 GMT | H225: =B225/E225-1 -> -0.01692992 | J225: -0.048 | K225: 0 | M225: =M226-0.001 -> -0.049 | N225: =_xlfn.NORM.DIST(M225,$L$202,$L$204,FALSE) -> 0.98497582
B226: 219.43 | C226: 220.51 | D226: 216.49 | E226: 220.25 | F226: 2624560 | G226: Fri, 25 Jul 2025 00:00:00 GMT | H226: =B226/E226-1 -> -0.003723042 | J226: -0.047 | K226: 2 | M226: =M227-0.001 -> -0.048 | N226: =_xlfn.NORM.DIST(M226,$L$202,$L$204,FALSE) -> 1.1141389
B227: 218.69 | C227: 225.31 | D227: 218.45 | E227: 223.41 | F227: 3480348 | G227: Thu, 24 Jul 2025 00:00:00 GMT | H227: =B227/E227-1 -> -0.021127076 | J227: -0.046 | K227: 0 | M227: =M228-0.001 -> -0.047 | N227: =_xlfn.NORM.DIST(M227,$L$202,$L$204,FALSE) -> 1.2570107
B228: 224.03 | C228: 226.235 | D228: 222.87 | E228: 225 | F228: 2212147 | G228: Wed, 23 Jul 2025 00:00:00 GMT | H228: =B228/E228-1 -> -0.0043111111 | J228: -0.045 | K228: 2 | M228: =M229-0.001 -> -0.046 | N228: =_xlfn.NORM.DIST(M228,$L$202,$L$204,FALSE) -> 1.4145701
B229: 223.93 | C229: 225.45 | D229: 221.09 | E229: 221.77 | F229: 3301417 | G229: Tue, 22 Jul 2025 00:00:00 GMT | H229: =B229/E229-1 -> 0.0097398205 | J229: -0.044 | K229: 0 | M229: =M230-0.001 -> -0.045 | N229: =_xlfn.NORM.DIST(M229,$L$202,$L$204,FALSE) -> 1.5878001
B230: 223.21 | C230: 230.5 | D230: 222.65 | E230: 229.97 | F230: 2966897 | G230: Mon, 21 Jul 2025 00:00:00 GMT | H230: =B230/E230-1 -> -0.029395138 | J230: -0.043 | K230: 0 | M230: =M231-0.001 -> -0.044 | N230: =_xlfn.NORM.DIST(M230,$L$202,$L$204,FALSE) -> 1.7776777
B231: 229.77 | C231: 233 | D231: 228.065 | E231: 232.785 | F231: 2541421 | G231: Fri, 18 Jul 2025 00:00:00 GMT | H231: =B231/E231-1 -> -0.012951865 | J231: -0.042 | K231: 1 | M231: =M232-0.001 -> -0.043 | N231: =_xlfn.NORM.DIST(M231,$L$202,$L$204,FALSE) -> 1.9851626
B232: 233.31 | C232: 233.75 | D232: 226.93 | E232: 227 | F232: 2914069 | G232: Thu, 17 Jul 2025 00:00:00 GMT | H232: =B232/E232-1 -> 0.027797357 | J232: -0.041 | K232: 3 | M232: =M233-0.001 -> -0.042 | N232: =_xlfn.NORM.DIST(M232,$L$202,$L$204,FALSE) -> 2.2111846
B233: 226.11 | C233: 227.66 | D233: 222.46 | E233: 224.15 | F233: 3219665 | G233: Wed, 16 Jul 2025 00:00:00 GMT | H233: =B233/E233-1 -> 0.0087441445 | J233: -0.04 | K233: 0 | M233: =M234-0.001 -> -0.041 | N233: =_xlfn.NORM.DIST(M233,$L$202,$L$204,FALSE) -> 2.4566301
B234: 222.19 | C234: 230.5399 | D234: 222.06 | E234: 229.19 | F234: 4698556 | G234: Tue, 15 Jul 2025 00:00:00 GMT | H234: =B234/E234-1 -> -0.030542345 | J234: -0.039 | K234: 3 | M234: =M235-0.001 -> -0.04 | N234: =_xlfn.NORM.DIST(M234,$L$202,$L$204,FALSE) -> 2.7223276
B235: 228.89 | C235: 236.19 | D235: 228.75 | E235: 235.61 | F235: 3370147 | G235: Mon, 14 Jul 2025 00:00:00 GMT | H235: =B235/E235-1 -> -0.02852171 | J235: -0.038 | K235: 7 | M235: =M236-0.001 -> -0.039 | N235: =_xlfn.NORM.DIST(M235,$L$202,$L$204,FALSE) -> 3.0090324
B236: 236.51 | C236: 238.45 | D236: 235.532 | E236: 237.04 | F236: 1653261 | G236: Fri, 11 Jul 2025 00:00:00 GMT | H236: =B236/E236-1 -> -0.0022359096 | J236: -0.037 | K236: 4 | M236: =M237-0.001 -> -0.038 | N236: =_xlfn.NORM.DIST(M236,$L$202,$L$204,FALSE) -> 3.3174104
... B273: 321.44 | C273: 325.44 | D273: 317.33 | E273: 320 | F273: 1277499 | G273: Fri, 16 May 2025 00:00:00 GMT | H273: =B273/E273-1 -> 0.0045 | J273: 0 | K273: 31 | M273: =M274-0.001 -> -0.001 | N273: =_xlfn.NORM.DIST(M273,$L$202,$L$204,FALSE) -> 20.199078
B274: 318.96 | C274: 319.41 | D274: 312.35 | E274: 313.86 | F274: 1176278 | G274: Thu, 15 May 2025 00:00:00 GMT | H274: =B274/E274-1 -> 0.016249283 | J274: 0.001 | K274: 25 | M274: 0 | N274: =_xlfn.NORM.DIST(M274,$L$202,$L$204,FALSE) -> 20.200698
B275: 315.84 | C275: 319.0738 | D275: 309.81 | E275: 310.78 | F275: 1574299 | G275: Wed, 14 May 2025 00:00:00 GMT | H275: =B275/E275-1 -> 0.016281614 | J275: 0.002 | K275: 28 | M275: =M274+0.001 -> 0.001 | N275: =_xlfn.NORM.DIST(M275,$L$202,$L$204,FALSE) -> 20.150557
B276: 310.61 | C276: 311.84 | D276: 304.87 | E276: 308.72 | F276: 1643690 | G276: Tue, 13 May 2025 00:00:00 GMT | H276: =B276/E276-1 -> 0.0061220523 | J276: 0.003 | K276: 35 | M276: =M275+0.001 -> 0.002 | N276: =_xlfn.NORM.DIST(M276,$L$202,$L$204,FALSE) -> 20.04904
B277: 304.2 | C277: 309.82 | D277: 297.975 | E277: 297.975 | F277: 2531655 | G277: Mon, 12 May 2025 00:00:00 GMT | H277: =B277/E277-1 -> 0.020891014 | J277: 0.004 | K277: 29 | M277: =M276+0.001 -> 0.003 | N277: =_xlfn.NORM.DIST(M277,$L$202,$L$204,FALSE) -> 19.896925
B278: 279.77 | C278: 284 | D278: 279.58 | E278: 283.26 | F278: 1680324 | G278: Fri, 09 May 2025 00:00:00 GMT | H278: =B278/E278-1 -> -0.012320836 | J278: 0.005 | K278: 31 | M278: =M277+0.001 -> 0.004 | N278: =_xlfn.NORM.DIST(M278,$L$202,$L$204,FALSE) -> 19.695373
B279: 282.43 | C279: 286.26 | D279: 277.38 | E279: 279.8 | F279: 1483869 | G279: Thu, 08 May 2025 00:00:00 GMT | H279: =B279/E279-1 -> 0.0093995711 | J279: 0.006 | K279: 26 | M279: =M278+0.001 -> 0.005 | N279: =_xlfn.NORM.DIST(M279,$L$202,$L$204,FALSE) -> 19.445911
B280: 275.69 | C280: 277.13 | D280: 271.92 | E280: 273.52 | F280: 1120818 | G280: Wed, 07 May 2025 00:00:00 GMT | H280: =B280/E280-1 -> 0.0079336063 | J280: 0.007 | K280: 31 | M280: =M279+0.001 -> 0.006 | N280: =_xlfn.NORM.DIST(M280,$L$202,$L$204,FALSE) -> 19.150418
B281: 270.8 | C281: 275.05 | D281: 269.57 | E281: 274.2 | F281: 1141672 | G281: Tue, 06 May 2025 00:00:00 GMT | H281: =B281/E281-1 -> -0.012399708 | J281: 0.008 | K281: 26 | M281: =M280+0.001 -> 0.007 | N281: =_xlfn.NORM.DIST(M281,$L$202,$L$204,FALSE) -> 18.811094
B282: 278.55 | C282: 281.44 | D282: 276.15 | E282: 276.42 | F282: 1330101 | G282: Mon, 05 May 2025 00:00:00 GMT | H282: =B282/E282-1 -> 0.0077056653 | J282: 0.009 | K282: 33 | M282: =M281+0.001 -> 0.008 | N282: =_xlfn.NORM.DIST(M282,$L$202,$L$204,FALSE) -> 18.430441
B283: 277.36 | C283: 279.435 | D283: 272.81 | E283: 273.93 | F283: 1811383 | G283: Fri, 02 May 2025 00:00:00 GMT | H283: =B283/E283-1 -> 0.012521447 | J283: 0.01 | K283: 24 | M283: =M282+0.001 -> 0.009 | N283: =_xlfn.NORM.DIST(M283,$L$202,$L$204,FALSE) -> 18.011224
B284: 268.6 | C284: 274.335 | D284: 268.36 | E284: 271.34 | F284: 1227779 | G284: Thu, 01 May 2025 00:00:00 GMT | H284: =B284/E284-1 -> -0.010098032 | J284: 0.011 | K284: 18 | M284: =M283+0.001 -> 0.01 | N284: =_xlfn.NORM.DIST(M284,$L$202,$L$204,FALSE) -> 17.556446
B285: 270.77 | C285: 271.265 | D285: 259.33 | E285: 265.705 | F285: 2015598 | G285: Wed, 30 Apr 2025 00:00:00 GMT | H285: =B285/E285-1 -> 0.019062494 | J285: 0.012 | K285: 30 | M285: =M284+0.001 -> 0.011 | N285: =_xlfn.NORM.DIST(M285,$L$202,$L$204,FALSE) -> 17.069305
B286: 271.27 | C286: 272 | D286: 266.06 | E286: 267.96 | F286: 1533760 | G286: Tue, 29 Apr 2025 00:00:00 GMT | H286: =B286/E286-1 -> 0.01235259 | J286: 0.013 | K286: 21 | M286: =M285+0.001 -> 0.012 | N286: =_xlfn.NORM.DIST(M286,$L$202,$L$204,FALSE) -> 16.55316
... B335: 372.44 | C335: 372.94 | D335: 354.05 | E335: 365.68 | F335: 2250957 | G335: Tue, 18 Feb 2025 00:00:00 GMT | H335: =B335/E335-1 -> 0.018486108 | J335: 0.062 | K335: 0 | M335: =M334+0.001 -> 0.061 | N335: =_xlfn.NORM.DIST(M335,$L$202,$L$204,FALSE) -> 0.15872388
B336: 366.68 | C336: 393.54 | D336: 365.62 | E336: 393.52 | F336: 3310326 | G336: Fri, 14 Feb 2025 00:00:00 GMT | H336: =B336/E336-1 -> -0.06820492 | J336: More | K336: 7 | M336: =M335+0.001 -> 0.062 | N336: =_xlfn.NORM.DIST(M336,$L$202,$L$204,FALSE) -> 0.13539421
B337: 390.85 | C337: 400.01 | D337: 390.025 | E337: 400.01 | F337: 1529602 | G337: Thu, 13 Feb 2025 00:00:00 GMT | H337: =B337/E337-1 -> -0.022899428 | M337: =M336+0.001 -> 0.063 | N337: =_xlfn.NORM.DIST(M337,$L$202,$L$204,FALSE) -> 0.11519769
B338: 395.16 | C338: 399.78 | D338: 390.3 | E338: 392.945 | F338: 1169522 | G338: Wed, 12 Feb 2025 00:00:00 GMT | H338: =B338/E338-1 -> 0.0056369212
B339: 397.63 | C339: 403.21 | D339: 397.1339 | E339: 398.17 | F339: 866275 | G339: Tue, 11 Feb 2025 00:00:00 GMT | H339: =B339/E339-1 -> -0.0013562046
B340: 399.71 | C340: 401.07 | D340: 387.28 | E340: 398.1 | F340: 1341692 | G340: Mon, 10 Feb 2025 00:00:00 GMT | H340: =B340/E340-1 -> 0.00404421
B341: 398.1 | C341: 414.14 | D341: 396.735 | E341: 414.14 | F341: 1487987 | G341: Fri, 07 Feb 2025 00:00:00 GMT | H341: =B341/E341-1 -> -0.038730864
B342: 411.83 | C342: 417.115 | D342: 407.74 | E342: 416.25 | F342: 1236545 | G342: Thu, 06 Feb 2025 00:00:00 GMT | H342: =B342/E342-1 -> -0.010618619
B343: 412.8 | C343: 417 | D343: 411.0674 | E343: 415.98 | F343: 1186709 | G343: Wed, 05 Feb 2025 00:00:00 GMT | H343: =B343/E343-1 -> -0.0076445983
B344: 415.9 | C344: 417.91 | D344: 408.43 | E344: 409.24 | F344: 1088367 | G344: Tue, 04 Feb 2025 00:00:00 GMT | H344: =B344/E344-1 -> 0.016274069
B345: 410.29 | C345: 413.1399 | D345: 399.4804 | E345: 404.5 | F345: 1752573 | G345: Mon, 03 Feb 2025 00:00:00 GMT | H345: =B345/E345-1 -> 0.014313968
B346: 414.2 | C346: 422.87 | D346: 412 | E346: 419.11 | F346: 1297961 | G346: Fri, 31 Jan 2025 00:00:00 GMT | H346: =B346/E346-1 -> -0.011715301
...

Sheet Product Lines

Sheet Management

Sheet Table Formatting
B2: [Bold Title] | G2: [Bold Title]
B3: Line Titles | G3: <-- General
B4: Line Titles | G4: <-- Info
B5: Line Titles | G5: <-- General
B6: Line Titles | G6: <-- Info
B7: Line Titles | G7: <-- General
B8: Line Titles | G8: <-- Info
