Workbook

Sheet Main
B2: NFLX
B3: Price | C3: 91.29 | D3: 2/18/2026
B4: SO | C4: 4222 | D4: Q4'25
B5: MC | C5: =C3*C4 -> 385426.38
B6: Cash | C6: =9033.68+28.67 -> 9062.35 | D6: Q4'25
B7: Debt | C7: =998.86+13463.97 -> 14462.83 | D7: Q4'25
B8: EV | C8: =C5-C6+C7 -> 390826.86
B10: Netflix, Inc. (NFLX)
B12: Founder(s): Reed Hastings & Marc Randolph | G12: Registered Exchange: NASDAQ | N12: Resources:
B13: Founded: 1997 | G13: Address: 121 Albright Way Los Gatos, CA 95032 U.S. | N13: SEC filings | Q13: https://www.sec.gov/edgar/browse/?CIK=1065280&owner=exclude
B14: Headquarters: Los Gatos, CA | G14: Investor Relations Contact: | N14: Company Homepage | Q14: https://www.netflix.com/
B15: Current CEOs: Gregory Peters & Theodore Sarandos | G15: Investors Relation Department | O15: Company IR Page | R15: https://ir.netflix.net/ir-overview/profile/default.aspx
B16: Employees: 16,000 | G16: Phone: | H16: (408) 540-3700 | J16: Email: | K16: ir@netflix.com | N16: Earnings Calls | Q16: https://seekingalpha.com/symbol/NFLX/earnings/transcripts
B17: Industry: Entertainment - Digital Media | N17: Equity Analysis | Q17: https://stockanalysis.com/stocks/nflx/company/
B18: Sector: Communication Services | N18: MacroTrends | Q18: https://www.macrotrends.net/stocks/charts/NFLX/netflix/income-statement
B19: IPO: May 23, 2002 -- $82.5M valuation | N19: ROIC, WACC | Q19: https://www.gurufocus.com/term/wacc/NFLX
B20: Fiscal Year: [January - December] | N20: Godel Terminal | Q20: https://app.godelterminal.com/
A22: Company Overview:
B23: Netflix, Inc. provides entertainment services worldwide
C24: The Company offers television (TV) series, documentaries, feature films, games, and live programming across various genres and languages
C25: The Company also provides members the ability to receive streaming content through a host of internet-connected devices, including TVs, digital video players, TV set-top boxes, and mobile devices
B26: Netflix, Inc. was incorporated in 1997 and is headquartered in Los Gatos, California
A33: Business Segments and Geographical Info:
B34: [Begin researching fundamentals / core business … begin with SEC filings, but expand and use all public resources available]

Sheet Model
B1: [Use for Graphing] | AU1: Q1 2020 | AY1: Q1 2021 | BC1: Q1 2022 | BG1: Q1 2023 | BK1: Q1 2024 | BO1: Q1 2025
B2: Quarterly
B3: Revenues | C3: {="Q"&MOD(_xlfn.SEQUENCE(1,72)-1,4)+1&" "&(2009+INT((_xlfn.SEQUENCE(1,72)-1)/4))} -> Q1 2009 | D3: Q2 2009 | E3: Q3 2009 | F3: Q4 2009 | G3: Q1 2010 | H3: Q2 2010 | I3: Q3 2010 | J3: Q4 2010 | K3: Q1 2011 | L3: Q2 2011 | M3: Q3 2011 | N3: Q4 2011 | O3: Q1 2012 | P3: Q2 2012 | Q3: Q3 2012 | R3: Q4 2012 | S3: Q1 2013 | T3: Q2 2013 | U3: Q3 2013 | V3: Q4 2013 | W3: Q1 2014 | X3: Q2 2014 | Y3: Q3 2014 | Z3: Q4 2014 | AA3: Q1 2015 | AB3: Q2 2015 | AC3: Q3 2015 | AD3: Q4 2015 | AE3: Q1 2016 | AF3: Q2 2016 | AG3: Q3 2016 | AH3: Q4 2016 | AI3: Q1 2017 | AJ3: Q2 2017 | AK3: Q3 2017 | AL3: Q4 2017 | AM3: Q1 2018 | AN3: Q2 2018 | AO3: Q3 2018 | AP3: Q4 2018 | AQ3: Q1 2019 | AR3: Q2 2019 | AS3: Q3 2019 | AT3: Q4 2019 | AU3: Q1 2020 | AV3: Q2 2020 | AW3: Q3 2020 | AX3: Q4 2020 | AY3: Q1 2021 | AZ3: Q2 2021 | BA3: Q3 2021 | BB3: Q4 2021 | BC3: Q1 2022 | BD3: Q2 2022 | BE3: Q3 2022 | BF3: Q4 2022 | BG3: Q1 2023 | BH3: Q2 2023 | BI3: Q3 2023 | BJ3: Q4 2023 | BK3: Q1 2024 | BL3: Q2 2024 | BM3: Q3 2024 | BN3: Q4 2024 | BO3: Q1 2025 | BP3: Q2 2025 | BQ3: Q3 2025 | BR3: Q4 2025 | BS3: Q1 2026 | BT3: Q2 2026 | BU3: Q3 2026 | BV3: Q4 2026 | CA3: 2009 | CB3: =CA3+1 -> 2010 | CC3: =CB3+1 -> 2011 | CD3: =CC3+1 -> 2012 | CE3: =CD3+1 -> 2013 | CF3: =CE3+1 -> 2014 | CG3: =CF3+1 -> 2015 | CH3: =CG3+1 -> 2016 | CI3: =CH3+1 -> 2017 | ... EY3: =EX3+1 -> 2085
B4: U.S. / Canada Revenues | BJ4: =14873.78-SUM(BG4:BI4) -> 14873.78 | BK4: 4224.31 | BL4: 4295.56 | BM4: 4322.47 | BN4: =17359.36-SUM(BK4:BM4) -> 4517.02 | BO4: 4617.09 | BP4: 4929.003 | BQ4: 5071.78 | BR4: =19957.15-SUM(BO4:BQ4) -> 5339.277 | CO4: =SUM(BG4:BJ4) -> 14873.78 | CP4: =SUM(BK4:BN4) -> 17359.36 | CQ4: =SUM(BL4:BO4) -> 17752.14 | CR4: =CQ4*(1+CR10) -> 20237.44 | CS4: =CR4*(1+CS10) -> 22463.558 | CT4: =CS4*(1+CT10) -> 24485.278 | CU4: =CT4*(1+CU10) -> 26444.1 | CV4: =CU4*(1+CV10) -> 28295.187 | CW4: =CV4*(1+CW10) -> 29992.899 | CX4: =CW4*(1+CX10) -> 31492.544 | CY4: =CX4*(1+CY10) -> 32909.708 | ... DA4: =CZ4*(1+DA10) -> 35424.01
B5: Euro, Mid-East, Africa Revenues | BJ5: =10556.48-SUM(BG5:BI5) -> 10556.48 | BK5: 2958.19 | BL5: 3007 | BM5: 3133.46 | BN5: =12387.03-SUM(BK5:BM5) -> 3288.38 | BO5: 3404.67 | BP5: 3538.17 | BQ5: 3699.05 | BR5: =14514.646-SUM(BO5:BQ5) -> 3872.756 | CO5: =SUM(BG5:BJ5) -> 10556.48 | CP5: =SUM(BK5:BN5) -> 12387.03 | CQ5: =SUM(BL5:BO5) -> 12833.51 | CR5: =CQ5*(1+CR11) -> 14245.196 | CS5: =CR5*(1+CS11) -> 15527.264 | CT5: =CS5*(1+CT11) -> 16614.172 | CU5: =CT5*(1+CU11) -> 17611.023 | CV5: =CU5*(1+CV11) -> 18491.574 | CW5: =CV5*(1+CW11) -> 19231.237 | CX5: =CW5*(1+CX11) -> 19904.33 | CY5: =CX5*(1+CY11) -> 20551.221 | ... DA5: =CZ5*(1+DA11) -> 21591.112
B6: LatAm Revenues | BJ6: =4446.46-SUM(BG6:BI6) -> 4446.46 | BK6: 1165 | BL6: 1204.14 | BM6: 1240.89 | BN6: =4839.81-SUM(BK6:BM6) -> 1229.78 | BO6: 1261.93 | BP6: 1306.73 | BQ6: 1370.91 | BR6: =5357.52-SUM(BO6:BQ6) -> 1417.95 | CO6: =SUM(BG6:BJ6) -> 4446.46 | CP6: =SUM(BK6:BN6) -> 4839.81 | CQ6: =SUM(BL6:BO6) -> 4936.74 | CR6: =CQ6*(1+CR12) -> 5726.6184 | CS6: =CR6*(1+CS12) -> 6356.5464 | CT6: =CS6*(1+CT12) -> 6928.6356 | CU6: =CT6*(1+CU12) -> 7482.9265 | CV6: =CU6*(1+CV12) -> 8006.7313 | CW6: =CV6*(1+CW12) -> 8487.1352 | CX6: =CW6*(1+CX12) -> 8911.4919 | CY6: =CX6*(1+CY12) -> 9312.5091 | ... DA6: =CZ6*(1+DA12) -> 10023.985
B7: APac Revenues | BJ7: =3763.72-SUM(BG7:BI7) -> 3763.72 | BK7: 1022.92 | BL7: 1051.833 | BM7: 1127.86 | BN7: =4414.74-SUM(BK7:BM7) -> 1212.127 | BO7: 1259.09 | BP7: 1305.25 | BQ7: 1368.56 | BR7: =5353.717-SUM(BO7:BQ7) -> 1420.817 | CO7: =SUM(BG7:BJ7) -> 3763.72 | CP7: =SUM(BK7:BN7) -> 4414.74 | CQ7: =SUM(BL7:BO7) -> 4650.91 | CR7: =CQ7*(1+CR13) -> 5627.6011 | CS7: =CR7*(1+CS13) -> 6640.5693 | CT7: =CS7*(1+CT13) -> 7636.6547 | CU7: =CT7*(1+CU13) -> 8629.4198 | CV7: =CU7*(1+CV13) -> 9578.656 | CW7: =CV7*(1+CW13) -> 10440.735 | CX7: =CW7*(1+CX13) -> 11171.586 | CY7: =CX7*(1+CY13) -> 11841.882 | ... DA7: =CZ7*(1+DA13) -> 12931.335
B8: Ttl Revenues | BJ8: =SUM(BJ4:BJ7) -> 33640.44 | BK8: =SUM(BK4:BK7) -> 9370.42 | BL8: =SUM(BL4:BL7) -> 9558.533 | BM8: =SUM(BM4:BM7) -> 9824.68 | BN8: =SUM(BN4:BN7) -> 10247.307 | BO8: =SUM(BO4:BO7) -> 10542.78 | BP8: =SUM(BP4:BP7) -> 11079.153 | BQ8: =SUM(BQ4:BQ7) -> 11510.3 | BR8: =SUM(BR4:BR7) -> 12050.8 | CO8: =SUM(BG8:BJ8) -> 33640.44 | CP8: =SUM(BK8:BN8) -> 39000.94 | CQ8: =SUM(BL8:BO8) -> 40173.3 | CR8: =SUM(CR4:CR7) -> 45836.855 | CS8: =SUM(CS4:CS7) -> 50987.937 | CT8: =SUM(CT4:CT7) -> 55664.741 | CU8: =SUM(CU4:CU7) -> 60167.469 | CV8: =SUM(CV4:CV7) -> 64372.148 | CW8: =SUM(CW4:CW7) -> 68152.006 | CX8: =SUM(CX4:CX7) -> 71479.952 | CY8: =SUM(CY4:CY7) -> 74615.319 | ... DA8: =SUM(DA4:DA7) -> 79970.442
B10: U.S. / Canada Revenues Revenue Growth Y/y | BN10: =BN4/BJ4-1 -> -0.69630988 | BO10: =BO4/BK4-1 -> 0.092980866 | BP10: =BP4/BL4-1 -> 0.14746459 | BQ10: =BQ4/BM4-1 -> 0.17335227 | BR10: =BR4/BN4-1 -> 0.18203528 | CP10: =CP4/CO4-1 -> 0.16711152 | CQ10: =CQ4/CP4-1 -> 0.02262641 | CR10: 0.14 | CS10: 0.11 | CT10: 0.09 | CU10: 0.08 | CV10: 0.07 | CW10: 0.06 | CX10: 0.05 | CY10: 0.045 | CZ10: 0.04 | DA10: 0.035
B11: Euro, Mid-East, Africa Revenue Growth Y/y | BN11: =BN5/BJ5-1 -> -0.68849654 | BO11: =BO5/BK5-1 -> 0.15093013 | BP11: =BP5/BL5-1 -> 0.1766445 | BQ11: =BQ5/BM5-1 -> 0.18050015 | BR11: =BR5/BN5-1 -> 0.17770939 | CP11: =CP5/CO5-1 -> 0.17340534 | CQ11: =CQ5/CP5-1 -> 0.036044153 | CR11: 0.11 | CS11: 0.09 | CT11: 0.07 | CU11: 0.06 | CV11: 0.05 | CW11: 0.04 | CX11: 0.035 | CY11: 0.0325 | CZ11: 0.03 | DA11: 0.02
B12: LatAm Revenue Growth Y/y | BN12: =BN6/BJ6-1 -> -0.72342493 | BO12: =BO6/BK6-1 -> 0.083201717 | BP12: =BP6/BL6-1 -> 0.085197734 | BQ12: =BQ6/BM6-1 -> 0.10477963 | BR12: =BR6/BN6-1 -> 0.15301111 | CP12: =CP6/CO6-1 -> 0.088463632 | CQ12: =CQ6/CP6-1 -> 0.020027646 | CR12: 0.16 | CS12: 0.11 | CT12: 0.09 | CU12: 0.08 | CV12: 0.07 | CW12: 0.06 | CX12: 0.05 | CY12: 0.045 | CZ12: 0.04 | DA12: 0.035
B13: APac Revenue Growth Y/y | BN13: =BN7/BJ7-1 -> -0.67794443 | BO13: =BO7/BK7-1 -> 0.23087827 | BP13: =BP7/BL7-1 -> 0.24092893 | BQ13: =BQ7/BM7-1 -> 0.21341301 | BR13: =BR7/BN7-1 -> 0.17216843 | CP13: =CP7/CO7-1 -> 0.17297248 | CQ13: =CQ7/CP7-1 -> 0.053495789 | CR13: 0.21 | CS13: 0.18 | CT13: 0.15 | CU13: 0.13 | CV13: 0.11 | CW13: 0.09 | CX13: 0.07 | CY13: 0.06 | CZ13: 0.05 | DA13: 0.04
B14: Ttl Revenue Growth Y/y | BN14: =BN8/BJ8-1 -> -0.69538725 | BO14: =BO8/BK8-1 -> 0.12511286 | BP14: =BP8/BL8-1 -> 0.15908508 | BQ14: =BQ8/BM8-1 -> 0.17156996 | BR14: =BR8/BN8-1 -> 0.17599678 | CP14: =CP8/CO8-1 -> 0.15934691 | CQ14: =CQ8/CP8-1 -> 0.030059788 | CR14: =CR8/CQ8-1 -> 0.14097809 | CS14: =CS8/CR8-1 -> 0.11237861 | CT14: =CT8/CS8-1 -> 0.091723719 | CU14: =CU8/CT8-1 -> 0.080890138 | CV14: =CV8/CU8-1 -> 0.069882932 | CW14: =CW8/CV8-1 -> 0.058718828 | ... DA14: =DA8/CZ8-1 -> 0.031705752
B16: U.S. / Canada % of Ttl Revenues | BJ16: =BJ4/BJ8 -> 0.44213988 | BK16: =BK4/BK8 -> 0.4508133 | BL16: =BL4/BL8 -> 0.44939532 | BM16: =BM4/BM8 -> 0.43996039 | BN16: =BN4/BN8 -> 0.44080069 | BO16: =BO4/BO8 -> 0.43793857 | BP16: =BP4/BP8 -> 0.44488988 | BQ16: =BQ4/BQ8 -> 0.4406297 | BR16: =BR4/BR8 -> 0.44306411 | CO16: =CO4/CO8 -> 0.44213988 | CP16: =CP4/CP8 -> 0.44510107 | CQ16: =CQ4/CQ8 -> 0.44188902
B17: Euro, Mid-East, Africa % of Ttl Revenues | BJ17: =BJ5/BJ8 -> 0.31380327 | BK17: =BK5/BK8 -> 0.31569449 | BL17: =BL5/BL8 -> 0.31458802 | BM17: =BM5/BM8 -> 0.31893761 | BN17: =BN5/BN8 -> 0.32090187 | BO17: =BO5/BO8 -> 0.32293854 | BP17: =BP5/BP8 -> 0.31935384 | BQ17: =BQ5/BQ8 -> 0.32136869 | BR17: =BR5/BR8 -> 0.3213692 | CO17: =CO5/CO8 -> 0.31380327 | CP17: =CP5/CP8 -> 0.3176085 | CQ17: =CQ5/CQ8 -> 0.31945372
B18: LatAm % of Ttl Revenues | BJ18: =BJ6/BJ8 -> 0.13217604 | BK18: =BK6/BK8 -> 0.1243274 | BL18: =BL6/BL8 -> 0.1259754 | BM18: =BM6/BM8 -> 0.12630335 | BN18: =BN6/BN8 -> 0.12001007 | BO18: =BO6/BO8 -> 0.11969613 | BP18: =BP6/BP8 -> 0.11794494 | BQ18: =BQ6/BQ8 -> 0.11910289 | BR18: =BR6/BR8 -> 0.11766439 | CO18: =CO6/CO8 -> 0.13217604 | CP18: =CP6/CP8 -> 0.1240947 | CQ18: =CQ6/CQ8 -> 0.1228861
B19: APac % of Ttl Revenues | BJ19: =BJ7/BJ8 -> 0.11188082 | BK19: =BK7/BK8 -> 0.1091648 | BL19: =BL7/BL8 -> 0.11004126 | BM19: =BM7/BM8 -> 0.11479865 | BN19: =BN7/BN8 -> 0.11828737 | BO19: =BO7/BO8 -> 0.11942675 | BP19: =BP7/BP8 -> 0.11781135 | BQ19: =BQ7/BQ8 -> 0.11889873 | BR19: =BR7/BR8 -> 0.1179023 | CO19: =CO7/CO8 -> 0.11188082 | CP19: =CP7/CP8 -> 0.11319573 | CQ19: =CQ7/CQ8 -> 0.11577117
B21: Revenues | C21: 394.1 | D21: 408.5 | E21: 423.1 | F21: 936.9 | G21: 493.7 | H21: 519.8 | I21: 553.2 | J21: 1637.9 | K21: 718.6 | L21: 788.6 | M21: 821.8 | N21: 875.6 | O21: 869.8 | P21: 889.2 | Q21: 905.1 | R21: 945.2 | S21: 1024 | T21: 1069.4 | U21: 1106 | V21: 1175.2 | W21: 1270.1 | X21: 1340.4 | Y21: 1409.4 | Z21: 1484.7 | AA21: 1573.1 | AB21: 1644.7 | AC21: 1738.4 | AD21: 1823.3 | AE21: 1957.7 | AF21: 2105.2 | AG21: 2290.2 | AH21: 2477.5 | AI21: 2636.6 | AJ21: 2785.5 | AK21: 2984.9 | AL21: 3285.8 | AM21: 3700.9 | AN21: 3907.3 | AO21: 3999.4 | AP21: 4186.8 | AQ21: 4521 | AR21: 4923.1 | AS21: 5244.9 | AT21: 5467.4 | AU21: 5767.7 | AV21: 6148.3 | AW21: 6435.6 | AX21: 6644.4 | AY21: 7163.3 | AZ21: 7341.8 | BA21: 7483.5 | BB21: 7709.3 | BC21: 7867.8 | BD21: 7970.1 | BE21: 7925.6 | BF21: 7852.1 | BG21: 8161.5 | BH21: 8187.3 | BI21: 8541.7 | BJ21: 8832.8 | BK21: 9370.4 | BL21: 9559.3 | BM21: 9824.7 | BN21: 10246.5 | BO21: 10542.8 | BP21: 11079.2 | BQ21: 11510.3 | BR21: 12050.8 | CA21: =SUM(C21:F21) -> 2162.6 | CB21: =SUM(G21:J21) -> 3204.6 | CC21: =SUM(K21:N21) -> 3204.6 | CD21: =SUM(O21:R21) -> 3609.3 | CE21: =SUM(S21:V21) -> 4374.6 | CF21: =SUM(W21:Z21) -> 5504.6 | CG21: =SUM(AA21:AD21) -> 6779.5 | CH21: =SUM(AE21:AH21) -> 8830.6 | CI21: =SUM(AI21:AL21) -> 11692.8 | CJ21: =SUM(AM21:AP21) -> 15794.4 | CK21: =SUM(AQ21:AT21) -> 20156.4 | CL21: =SUM(AU21:AX21) -> 24996 | CM21: =SUM(AY21:BB21) -> 29697.9 | CN21: =SUM(BC21:BF21) -> 31615.6 | CO21: =SUM(BG21:BJ21) -> 33723.3 | CP21: =SUM(BK21:BN21) -> 39000.9 | CQ21: =SUM(BO21:BR21) -> 45183.1 | CR21: =CR8 -> 45836.855 | CS21: =CS8 -> 50987.937 | CT21: =CT8 -> 55664.741 | CU21: =CU8 -> 60167.469 | CV21: =CV8 -> 64372.148 | CW21: =CW8 -> 68152.006 | CX21: =CX8 -> 71479.952 | CY21: =CY8 -> 74615.319 | ... DA21: =DA8 -> 79970.442
B22: COGS | C22: 259.3 | D22: 269.2 | E22: 275.3 | F22: 553.6 | G22: 307.2 | H22: 314.9 | I22: 344.5 | J22: 1073.3 | K22: 438.2 | L22: 490 | M22: 536.6 | N22: 575.2 | O22: 623.9 | P22: 643.4 | Q22: 662.6 | R22: 722.1 | S22: 737 | T22: 760.7 | U22: 798.9 | V22: 820.7 | W22: 869.2 | X22: 914.8 | Y22: 954.4 | Z22: 1014.3 | AA22: 1046.4 | AB22: 1121.8 | AC22: 1174 | AD22: 1249.4 | AE22: 1369.5 | AF22: 1473.1 | AG22: 1532.8 | AH22: 1882 | AI22: 1657 | AJ22: 1902.3 | AK22: 1993 | AL22: 2480.7 | AM22: 2300.6 | AN22: 2402.4 | AO22: 2531.1 | AP22: 2733.4 | AQ22: 2870.6 | AR22: 3005.7 | AS22: 3097.9 | AT22: 3466 | AU22: 3599.7 | AV22: 3643.7 | AW22: 3867.8 | AX22: 4165.2 | AY22: 3868.5 | AZ22: 4018 | BA22: 4206.6 | BB22: 5239.6 | BC22: 4284.7 | BD22: 4690.8 | BE22: 4788.7 | BF22: 5404.2 | BG22: 4803.6 | BH22: 4673.5 | BI22: 4930.8 | BJ22: 5307.5 | BK22: 4977.1 | BL22: 5174.1 | BM22: 5119.9 | BN22: 5767.4 | BO22: 5263.1 | BP22: 5325.3 | BQ22: 6164.2 | BR22: 6522.6 | CA22: =SUM(C22:F22) -> 1357.4 | CB22: =SUM(G22:J22) -> 2039.9 | CC22: =SUM(K22:N22) -> 2040 | CD22: =SUM(O22:R22) -> 2652 | CE22: =SUM(S22:V22) -> 3117.3 | CF22: =SUM(W22:Z22) -> 3752.7 | CG22: =SUM(AA22:AD22) -> 4591.6 | CH22: =SUM(AE22:AH22) -> 6257.4 | CI22: =SUM(AI22:AL22) -> 8033 | CJ22: =SUM(AM22:AP22) -> 9967.5 | CK22: =SUM(AQ22:AT22) -> 12440.2 | CL22: =SUM(AU22:AX22) -> 15276.4 | CM22: =SUM(AY22:BB22) -> 17332.7 | CN22: =SUM(BC22:BF22) -> 19168.4 | CO22: =SUM(BG22:BJ22) -> 19715.4 | CP22: =SUM(BK22:BN22) -> 21038.5 | CQ22: =SUM(BO22:BR22) -> 23275.2 | CR22: =CR21*(1-CR37) -> 24330.787 | CS22: =CS21*(1-CS37) -> 27065.047 | CT22: =CT21*(1-CT37) -> 29547.554 | CU22: =CU21*(1-CU37) -> 31937.66 | CV22: =CV21*(1-CV37) -> 34169.557 | CW22: =CW21*(1-CW37) -> 36175.954 | CX22: =CX21*(1-CX37) -> 37942.47 | CY22: =CY21*(1-CY37) -> 39606.763 | ... DA22: =DA21*(1-DA37) -> 42449.33
B23: GP | C23: =C21-C22 -> 134.8 | D23: =D21-D22 -> 139.3 | E23: =E21-E22 -> 147.8 | F23: =F21-F22 -> 383.3 | G23: =G21-G22 -> 186.5 | H23: =H21-H22 -> 204.9 | I23: =I21-I22 -> 208.7 | J23: =J21-J22 -> 564.6 | ... BR23: =BR21-BR22 -> 5528.2 | CA23: =SUM(C23:F23) -> 805.2 | CB23: =SUM(G23:J23) -> 1164.7 | CC23: =SUM(K23:N23) -> 1164.6 | CD23: =SUM(O23:R23) -> 957.3 | CE23: =SUM(S23:V23) -> 1257.3 | CF23: =SUM(W23:Z23) -> 1751.9 | CG23: =SUM(AA23:AD23) -> 2187.9 | CH23: =SUM(AE23:AH23) -> 2573.2 | CI23: =SUM(AI23:AL23) -> 3659.8 | CJ23: =SUM(AM23:AP23) -> 5826.9 | CK23: =SUM(AQ23:AT23) -> 7716.2 | CL23: =SUM(AU23:AX23) -> 9719.6 | CM23: =SUM(AY23:BB23) -> 12365.2 | CN23: =SUM(BC23:BF23) -> 12447.2 | CO23: =SUM(BG23:BJ23) -> 14007.9 | CP23: =SUM(BK23:BN23) -> 17962.4 | CQ23: =SUM(BO23:BR23) -> 21907.9 | CR23: =CR21*CR37 -> 21506.068 | CS23: =CS21*CS37 -> 23922.89 | CT23: =CT21*CT37 -> 26117.186 | CU23: =CU21*CU37 -> 28229.809 | CV23: =CV21*CV37 -> 30202.591 | CW23: =CW21*CW37 -> 31976.052 | CX23: =CX21*CX37 -> 33537.482 | CY23: =CY21*CY37 -> 35008.556 | ... DA23: =DA21*DA37 -> 37521.111
B24: Sales & Marketing | C24: 61.2 | D24: 46.1 | E24: 57 | F24: 129.6 | G24: 75.3 | H24: 74.5 | I24: 81.2 | J24: 171.7 | K24: 104.3 | L24: 94.9 | M24: 89.1 | N24: 92.9 | O24: 129.9 | P24: 114 | Q24: 108.5 | R24: 82.1 | S24: 119.1 | T24: 114.7 | U24: 108.3 | V24: 128.1 | W24: 137.1 | X24: 120.8 | Y24: 145.6 | Z24: 203.7 | AA24: 194.7 | AB24: 197.1 | AC24: 208.1 | AD24: 224.2 | AE24: 208 | AF24: 216 | AG24: 282 | AH24: 391.4 | AI24: 271.3 | AJ24: 274.3 | AK24: 312.6 | AL24: 578.2 | AM24: 536.8 | AN24: 592 | AO24: 510.4 | AP24: 730.4 | AQ24: 616.5 | AR24: 603.1 | AS24: 553.7 | AT24: 878.9 | AU24: 503.8 | AV24: 434.5 | AW24: 527.6 | AX24: 762.6 | AY24: 512.5 | AZ24: 604 | BA24: 635.9 | BB24: 792.7 | BC24: 556 | BD24: 575 | BE24: 568 | BF24: 831.6 | BG24: 555.4 | BH24: 627.1 | BI24: 558.7 | BJ24: 916.6 | BK24: 654.3 | BL24: 644 | BM24: 642.8 | BN24: 976.2 | BO24: 688.4 | BP24: 713.3 | BQ24: 786.3 | BR24: 1113.4 | CA24: =SUM(C24:F24) -> 293.9 | CB24: =SUM(G24:J24) -> 402.7 | CC24: =SUM(K24:N24) -> 381.2 | CD24: =SUM(O24:R24) -> 434.5 | CE24: =SUM(S24:V24) -> 470.2 | CF24: =SUM(W24:Z24) -> 607.2 | CG24: =SUM(AA24:AD24) -> 824.1 | CH24: =SUM(AE24:AH24) -> 1097.4 | CI24: =SUM(AI24:AL24) -> 1436.4 | CJ24: =SUM(AM24:AP24) -> 2369.6 | CK24: =SUM(AQ24:AT24) -> 2652.2 | CL24: =SUM(AU24:AX24) -> 2228.5 | CM24: =SUM(AY24:BB24) -> 2545.1 | CN24: =SUM(BC24:BF24) -> 2530.6 | CO24: =SUM(BG24:BJ24) -> 2657.8 | CP24: =SUM(BK24:BN24) -> 2917.3 | CQ24: =SUM(BO24:BR24) -> 3301.4 | CR24: =CR21*CR38 -> 3437.7641 | CS24: =CS21*CS38 -> 3798.6013 | CT24: =CT21*CT38 -> 4119.1908 | CU24: =CU21*CU38 -> 2617.2849 | CV24: =CV21*CV38 -> 4699.1668 | CW24: =CW21*CW38 -> 4941.0204 | CX24: =CX21*CX38 -> 5146.5565 | CY24: =CY21*CY38 -> 5334.9953 | ... DA24: =DA21*DA38 -> 5597.9309
B25: General & Admin | C25: 13 | D25: 13.3 | E25: 11.5 | F25: 26.7 | G25: 15.5 | H25: 15.1 | I25: 15.9 | J25: 80.3 | K25: 23 | L25: 30.7 | M25: 29.8 | N25: 64.8 | O25: 35.1 | P25: 34.1 | Q25: 35.3 | R25: 39.3 | S25: 44.1 | T25: 43.8 | U25: 46.2 | V25: 46.1 | W25: 55.9 | X25: 60 | Y25: 78 | Z25: 75.8 | AA25: 91.5 | AB25: 95.9 | AC25: 110.9 | AD25: 109 | AE25: 127.2 | AF25: 138.4 | AG25: 153.2 | AH25: -103.1 | AI25: 194.3 | AJ25: 213.9 | AK25: 215.5 | AL25: -192.7 | AM25: 134.6 | AN25: 151.5 | AO25: 168.6 | AP25: 175.5 | AQ25: 202 | AR25: 224.7 | AS25: 233.2 | AT25: 254.6 | AU25: 252.1 | AV25: 277.2 | AW25: 271.6 | AX25: 275.5 | AY25: 297.2 | AZ25: 334.8 | BA25: 321.8 | BB25: 397.8 | BC25: 397.9 | BD25: 409.3 | BE25: 373.2 | BF25: 392.5 | BG25: 400.9 | BH25: 401.5 | BI25: 478.6 | BJ25: 439.3 | BK25: 404 | BL25: 427 | BM25: 417.4 | BN25: 453.7 | BO25: 421.5 | BP25: 441.2 | BQ25: 457.9 | BR25: 567.8 | CA25: =SUM(C25:F25) -> 64.5 | CB25: =SUM(G25:J25) -> 126.8 | CC25: =SUM(K25:N25) -> 148.3 | CD25: =SUM(O25:R25) -> 143.8 | CE25: =SUM(S25:V25) -> 180.2 | CF25: =SUM(W25:Z25) -> 269.7 | CG25: =SUM(AA25:AD25) -> 407.3 | CH25: =SUM(AE25:AH25) -> 315.7 | CI25: =SUM(AI25:AL25) -> 431 | CJ25: =SUM(AM25:AP25) -> 630.2 | CK25: =SUM(AQ25:AT25) -> 914.5 | CL25: =SUM(AU25:AX25) -> 1076.4 | CM25: =SUM(AY25:BB25) -> 1351.6 | CN25: =SUM(BC25:BF25) -> 1572.9 | CO25: =SUM(BG25:BJ25) -> 1720.3 | CP25: =SUM(BK25:BN25) -> 1702.1 | CQ25: =SUM(BO25:BR25) -> 1888.4 | CR25: =CR22*CR39 -> 1041.4684 | CS25: =CS22*CS39 -> 1150.2645 | CT25: =CT22*CT39 -> 1248.3842 | CU25: =CU22*CU39 -> 1341.3817 | CV25: =CV22*CV39 -> 1418.0366 | CW25: =CW22*CW39 -> 1483.2141 | CX25: =CX22*CX39 -> 1536.67 | CY25: =CY22*CY39 -> 1594.1722 | ... DA25: =DA22*DA39 -> 1697.9732
B26: R&D | C26: 24.2 | D26: 27.1 | E26: 30 | F26: 82 | G26: 37.4 | H26: 37.9 | I26: 42.1 | J26: 141.7 | K26: 50.9 | L26: 57.9 | M26: 69.5 | N26: 80.8 | O26: 82.8 | P26: 81.5 | Q26: 82.5 | R26: 82.1 | S26: 92 | T26: 93.1 | U26: 95.5 | V26: 98.1 | W26: 110.3 | X26: 115.2 | Y26: 121 | Z26: 125.9 | AA26: 143.1 | AB26: 155.1 | AC26: 171.8 | AD26: 180.9 | AE26: 203.5 | AF26: 207.3 | AG26: 216.1 | AH26: 153.3 | AI26: 257.1 | AJ26: 267.1 | AK26: 255.2 | AL26: 174.3 | AM26: 282.3 | AN26: 299.1 | AO26: 308.6 | AP26: 331.8 | AQ26: 372.8 | AR26: 383.2 | AS26: 379.8 | AT26: 409.4 | AU26: 453.8 | AV26: 435 | AW26: 453.8 | AX26: 486.9 | AY26: 525.2 | AZ26: 537.3 | BA26: 563.9 | BB26: 647.5 | BC26: 657.5 | BD26: 716.8 | BE26: 662.7 | BF26: 673.9 | BG26: 687.3 | BH26: 658 | BI26: 657.2 | BJ26: 673.3 | BK26: 702.5 | BL26: 711.3 | BM26: 735.1 | BN26: 776.5 | BO26: 822.8 | BP26: 824.7 | BQ26: 853.6 | BR26: 890.3 | CA26: =SUM(C26:F26) -> 163.3 | CB26: =SUM(G26:J26) -> 259.1 | CC26: =SUM(K26:N26) -> 259.1 | CD26: =SUM(O26:R26) -> 328.9 | CE26: =SUM(S26:V26) -> 378.7 | CF26: =SUM(W26:Z26) -> 472.4 | CG26: =SUM(AA26:AD26) -> 650.9 | CH26: =SUM(AE26:AH26) -> 780.2 | CI26: =SUM(AI26:AL26) -> 953.7 | CJ26: =SUM(AM26:AP26) -> 1221.8 | CK26: =SUM(AQ26:AT26) -> 1545.2 | CL26: =SUM(AU26:AX26) -> 1829.5 | CM26: =SUM(AY26:BB26) -> 2273.9 | CN26: =SUM(BC26:BF26) -> 2710.9 | CO26: =SUM(BG26:BJ26) -> 2675.8 | CP26: =SUM(BK26:BN26) -> 2925.4 | CQ26: =SUM(BO26:BR26) -> 3391.4 | CR26: =CR23*CR40 -> 1591.449 | CS26: =CS23*CS40 -> 1746.371 | CT26: =CT23*CT40 -> 1880.4374 | CU26: =CU23*CU40 -> 2004.3165 | CV26: =CV23*CV40 -> 2114.1814 | CW26: =CW23*CW40 -> 2238.3236 | CX26: =CX23*CX40 -> 2347.6237 | CY26: =CY23*CY40 -> 2450.5989 | ... DA26: =DA23*DA40 -> 2626.4778
B27: Ttl Operating Expenses | C27: =SUM(C24:C26) -> 98.4 | D27: =SUM(D24:D26) -> 86.5 | E27: =SUM(E24:E26) -> 98.5 | F27: =SUM(F24:F26) -> 238.3 | G27: =SUM(G24:G26) -> 128.2 | H27: =SUM(H24:H26) -> 127.5 | I27: =SUM(I24:I26) -> 139.2 | J27: =SUM(J24:J26) -> 393.7 | ... BR27: =SUM(BR24:BR26) -> 2571.5 | CA27: =SUM(C27:F27) -> 521.7 | CB27: =SUM(G27:J27) -> 788.6 | CC27: =SUM(K27:N27) -> 788.6 | CD27: =SUM(O27:R27) -> 907.2 | CE27: =SUM(S27:V27) -> 1029.1 | CF27: =SUM(W27:Z27) -> 1349.3 | CG27: =SUM(AA27:AD27) -> 1882.3 | CH27: =SUM(AE27:AH27) -> 2193.3 | CI27: =SUM(AI27:AL27) -> 2821.1 | CJ27: =SUM(AM27:AP27) -> 4221.6 | CK27: =SUM(AQ27:AT27) -> 5111.9 | CL27: =SUM(AU27:AX27) -> 5134.4 | CM27: =SUM(AY27:BB27) -> 6170.6 | CN27: =SUM(BC27:BF27) -> 6814.4 | CO27: =SUM(BG27:BJ27) -> 7053.9 | CP27: =SUM(BK27:BN27) -> 7544.8 | CQ27: =SUM(BO27:BR27) -> 8581.2 | CR27: =SUM(CR24:CR26) -> 6070.6815 | CS27: =SUM(CS24:CS26) -> 6695.2368 | CT27: =SUM(CT24:CT26) -> 7248.0124 | CU27: =SUM(CU24:CU26) -> 5962.9831 | CV27: =SUM(CV24:CV26) -> 8231.3848 | CW27: =SUM(CW24:CW26) -> 8662.5581 | CX27: =SUM(CX24:CX26) -> 9030.8503 | CY27: =SUM(CY24:CY26) -> 9379.7665 | ... DA27: =SUM(DA24:DA26) -> 9922.3819
B28: Operating Income | C28: =C23-C27 -> 36.4 | D28: =D23-D27 -> 52.8 | E28: =E23-E27 -> 49.3 | F28: =F23-F27 -> 145 | G28: =G23-G27 -> 58.3 | H28: =H23-H27 -> 77.4 | I28: =I23-I27 -> 69.5 | J28: =J23-J27 -> 170.9 | ... BR28: =BR23-BR27 -> 2956.7 | CA28: =SUM(C28:F28) -> 283.5 | CB28: =SUM(G28:J28) -> 376.1 | CC28: =SUM(K28:N28) -> 376 | CD28: =SUM(O28:R28) -> 50.1 | CE28: =SUM(S28:V28) -> 228.2 | CF28: =SUM(W28:Z28) -> 402.6 | CG28: =SUM(AA28:AD28) -> 305.6 | CH28: =SUM(AE28:AH28) -> 379.9 | CI28: =SUM(AI28:AL28) -> 838.7 | CJ28: =SUM(AM28:AP28) -> 1605.3 | CK28: =SUM(AQ28:AT28) -> 2604.3 | CL28: =SUM(AU28:AX28) -> 4585.2 | CM28: =SUM(AY28:BB28) -> 6194.6 | CN28: =SUM(BC28:BF28) -> 5632.8 | CO28: =SUM(BG28:BJ28) -> 6954 | CP28: =SUM(BK28:BN28) -> 10417.6 | CQ28: =SUM(BO28:BR28) -> 13326.7 | CR28: =CR23-CR27 -> 15435.386 | CS28: =CS23-CS27 -> 17227.653 | CT28: =CT23-CT27 -> 18869.174 | CU28: =CU23-CU27 -> 22266.826 | CV28: =CV23-CV27 -> 21971.206 | CW28: =CW23-CW27 -> 23313.494 | CX28: =CX23-CX27 -> 24506.632 | CY28: =CY23-CY27 -> 25628.79 | ... DA28: =DA23-DA27 -> 27598.729
B29: Interest Expenses | C29: 0.9 | D29: 0.2 | E29: 1.1 | F29: -18.2 | G29: -4 | H29: -4 | I29: -4.1 | J29: -4.5 | K29: -4 | L29: -4.3 | M29: -3.2 | N29: -5 | O29: -5.1 | P29: -5.5 | Q29: -4.2 | R29: -4.7 | S29: -30.9 | T29: -10.5 | U29: -7.6 | V29: -8.3 | W29: -8.7 | X29: -12.2 | Y29: -12.9 | Z29: -19.5 | AA29: -59 | AB29: -34.3 | AC29: -31.4 | AD29: -39.2 | AE29: -9.6 | AF29: -19.1 | AG29: -26.9 | AH29: -63.7 | AI29: -33.2 | AJ29: -113.8 | AK29: -92.4 | AL29: -114 | AM29: -147 | AN29: -33.6 | AO29: -101.9 | AP29: -96.4 | AQ29: -59.4 | AR29: -205.5 | AS29: 32.1 | AT29: -309.2 | AU29: -162.4 | AV29: -322.3 | AW29: -453.4 | AX29: -447.8 | AY29: 74.6 | AZ29: -253.8 | BA29: -94.3 | BB29: -80.9 | BC29: 8.1 | BD29: 44.8 | BE29: 88.8 | BF29: -510.6 | BG29: -245.4 | BH29: -147.9 | BI29: -7.3 | BJ29: -348 | BK29: -18 | BL29: -89 | BM29: -206.5 | BN29: -138.5 | BO29: -133.3 | BP29: -143 | BQ29: -138.8 | BR29: -188.9 | CA29: =SUM(C29:F29) -> -16 | CB29: =SUM(G29:J29) -> -16.6 | CC29: =SUM(K29:N29) -> -16.5 | CD29: =SUM(O29:R29) -> -19.5 | CE29: =SUM(S29:V29) -> -57.3 | CF29: =SUM(W29:Z29) -> -53.3 | CG29: =SUM(AA29:AD29) -> -163.9 | CH29: =SUM(AE29:AH29) -> -119.3 | CI29: =SUM(AI29:AL29) -> -353.4 | CJ29: =SUM(AM29:AP29) -> -378.9 | CK29: =SUM(AQ29:AT29) -> -542 | CL29: =SUM(AU29:AX29) -> -1385.9 | CM29: =SUM(AY29:BB29) -> -354.4 | CN29: =SUM(BC29:BF29) -> -368.9 | CO29: =SUM(BG29:BJ29) -> -748.6 | CP29: =SUM(BK29:BN29) -> -452 | CQ29: =SUM(BO29:BR29) -> -604 | CR29: =-(CQ57+CQ59)*($DF$52) -> -802.68706 | CS29: =-(CR57+CR59)*($DF$52) -> -758.13793 | CT29: =-(CS57+CS59)*($DF$52) -> -716.06128 | CU29: =-(CT57+CT59)*($DF$52) -> -676.31988 | CV29: =-(CU57+CU59)*($DF$52) -> -638.78412 | CW29: =-(CV57+CV59)*($DF$52) -> -603.3316 | CX29: =-(CW57+CW59)*($DF$52) -> -569.8467 | CY29: =-(CX57+CX59)*($DF$52) -> -538.22021 | ... DA29: =-(CZ57+CZ59)*($DF$52) -> -480.13562
B30: Other Income | C30: 0 | D30: 0 | E30: 0 | F30: 0 | G30: 0 | H30: 0 | I30: 0 | J30: 0 | K30: 0 | L30: 0 | M30: 0 | N30: 0 | O30: 0 | P30: 0 | Q30: 0 | R30: 0 | S30: 0 | T30: 0 | U30: 0 | V30: 0 | W30: 0 | X30: 0 | Y30: 0 | Z30: 0 | AA30: 0 | AB30: 0 | AC30: 0 | AD30: 0 | AE30: 0 | AF30: 0 | AG30: 0 | AH30: 0 | AI30: 0 | AJ30: 0 | AK30: 0 | AL30: 0 | AM30: 0 | AN30: 0 | AO30: 0 | AP30: 0 | AQ30: 0 | AR30: 0 | AS30: 0 | AT30: 0 | AU30: 0 | AV30: 0 | AW30: 0 | AX30: 0 | AY30: 0 | AZ30: 0 | BA30: 0 | BB30: 0 | BC30: 0 | BD30: 0 | BE30: 0 | BF30: 0 | BG30: 0 | BH30: 0 | BI30: 0 | BJ30: 0 | BK30: 0 | BL30: 0 | BM30: 0 | BN30: 0 | BO30: 0 | BP30: 0 | BQ30: 0 | BR30: 0 | CA30: =SUM(C30:F30) -> 0 | CB30: =SUM(G30:J30) -> 0 | CC30: =SUM(K30:N30) -> 0 | CD30: =SUM(O30:R30) -> 0 | CE30: =SUM(S30:V30) -> 0 | CF30: =SUM(W30:Z30) -> 0 | CG30: =SUM(AA30:AD30) -> 0 | CH30: =SUM(AE30:AH30) -> 0 | CI30: =SUM(AI30:AL30) -> 0 | CJ30: =SUM(AM30:AP30) -> 0 | CK30: =SUM(AQ30:AT30) -> 0 | CL30: =SUM(AU30:AX30) -> 0 | CM30: =SUM(AY30:BB30) -> 0 | CN30: =SUM(BC30:BF30) -> 0 | CO30: =SUM(BG30:BJ30) -> 0 | CP30: =SUM(BK30:BN30) -> 0 | CQ30: =SUM(BO30:BR30) -> 0 | CR30: =6000*$DK$38 -> 1845 | CS30: =CR30*(1+$DK$38) -> 2412.3375 | CT30: =CS30*(1+$DK$38) -> 3154.1313 | CU30: =CT30*(1+$DK$38) -> 4124.0267 | CV30: =CU30*(1+$DK$38) -> 5392.1648 | CW30: =CV30*(1+$DK$38) -> 7050.2555 | CX30: =CW30*(1+$DK$38) -> 9218.2091 | CY30: =CX30*(1+$DK$38) -> 12052.808 | CZ30: =CY30*(1+$DK$38) -> 15759.047 | DA30: =CZ30*(1+$DK$38) -> 20604.954
B31: Pretax Income | C31: =C28+SUM(C29:C29) -> 37.3 | D31: =D28+SUM(D29:D29) -> 53 | E31: =E28+SUM(E29:E29) -> 50.4 | F31: =F28+SUM(F29:F29) -> 126.8 | G31: =G28+SUM(G29:G29) -> 54.3 | H31: =H28+SUM(H29:H29) -> 73.4 | I31: =I28+SUM(I29:I29) -> 65.4 | J31: =J28+SUM(J29:J29) -> 166.4 | ... BR31: =BR28+SUM(BR29:BR29) -> 2767.8 | CA31: =SUM(C31:F31) -> 267.5 | CB31: =SUM(G31:J31) -> 359.5 | CC31: =SUM(K31:N31) -> 359.5 | CD31: =SUM(O31:R31) -> 30.6 | CE31: =SUM(S31:V31) -> 170.9 | CF31: =SUM(W31:Z31) -> 349.3 | CG31: =SUM(AA31:AD31) -> 141.7 | CH31: =SUM(AE31:AH31) -> 260.6 | CI31: =SUM(AI31:AL31) -> 485.3 | CJ31: =SUM(AM31:AP31) -> 1226.4 | CK31: =SUM(AQ31:AT31) -> 2062.3 | CL31: =SUM(AU31:AX31) -> 3199.3 | CM31: =SUM(AY31:BB31) -> 5840.2 | CN31: =SUM(BC31:BF31) -> 5263.9 | CO31: =SUM(BG31:BJ31) -> 6205.4 | CP31: =SUM(BK31:BN31) -> 9965.6 | CQ31: =SUM(BO31:BR31) -> 12722.7 | CR31: =CR28+SUM(CR29:CR30) -> 16477.699 | CS31: =CS28+SUM(CS29:CS30) -> 18881.853 | CT31: =CT28+SUM(CT29:CT30) -> 21307.244 | CU31: =CU28+SUM(CU29:CU30) -> 25714.533 | CV31: =CV28+SUM(CV29:CV30) -> 26724.587 | CW31: =CW28+SUM(CW29:CW30) -> 29760.418 | CX31: =CX28+SUM(CX29:CX30) -> 33154.994 | CY31: =CY28+SUM(CY29:CY30) -> 37143.378 | ... DA31: =DA28+SUM(DA29:DA30) -> 47723.548
B32: Taxes | C32: 15 | D32: 20.5 | E32: 20.3 | F32: 50.9 | G32: 22.1 | H32: 29.9 | I32: 27.4 | J32: 54 | K32: 38 | L32: 42.6 | M32: 31.2 | N32: 21.6 | O32: -2.4 | P32: 4.5 | Q32: 4.3 | R32: 7 | S32: -1.8 | T32: 17.2 | U32: 17.7 | V32: 25.6 | W32: 35.8 | X32: 46.4 | Y32: 38.2 | Z32: -37.9 | AA32: 14.7 | AB32: 14.2 | AC32: 12.8 | AD32: -22.4 | AE32: 12.2 | AF32: 10.5 | AG32: 27.6 | AH32: 23.5 | AI32: 45.6 | AJ32: -51.6 | AK32: -13.4 | AL32: -54.2 | AM32: 9.5 | AN32: 44.3 | AO32: -24 | AP32: -14.5 | AQ32: 55.6 | AR32: 230.3 | AS32: 347.1 | AT32: -437.6 | AU32: 86.8 | AV32: 315.4 | AW32: 71.5 | AX32: -35.7 | AY32: 327.8 | AZ32: 240.8 | BA32: 211.9 | BB32: -56.6 | BC32: 382.2 | BD32: 182.1 | BE32: 223.6 | BF32: -15.9 | BG32: 163.8 | BH32: 191.7 | BI32: 231.6 | BJ32: 210.3 | BK32: 282.4 | BL32: 366.6 | BM32: 339.4 | BN32: 265.7 | BO32: 323.4 | BP32: 506.3 | BQ32: 562.5 | BR32: 349.2 | CA32: =SUM(C32:F32) -> 106.7 | CB32: =SUM(G32:J32) -> 133.4 | CC32: =SUM(K32:N32) -> 133.4 | CD32: =SUM(O32:R32) -> 13.4 | CE32: =SUM(S32:V32) -> 58.7 | CF32: =SUM(W32:Z32) -> 82.5 | CG32: =SUM(AA32:AD32) -> 19.3 | CH32: =SUM(AE32:AH32) -> 73.8 | CI32: =SUM(AI32:AL32) -> -73.6 | CJ32: =SUM(AM32:AP32) -> 15.3 | CK32: =SUM(AQ32:AT32) -> 195.4 | CL32: =SUM(AU32:AX32) -> 438 | CM32: =SUM(AY32:BB32) -> 723.9 | CN32: =SUM(BC32:BF32) -> 772 | CO32: =SUM(BG32:BJ32) -> 797.4 | CP32: =SUM(BK32:BN32) -> 1254.1 | CQ32: =SUM(BO32:BR32) -> 1741.4 | CR32: =CR31*CR42 -> 2471.6549 | CS32: =CS31*CS42 -> 3021.0964 | CT32: =CT31*CT42 -> 3409.159 | CU32: =CU31*CU42 -> 4114.3253 | CV32: =CV31*CV42 -> 4275.9339 | CW32: =CW31*CW42 -> 4761.6668 | CX32: =CX31*CX42 -> 5304.799 | CY32: =CY31*CY42 -> 5942.9405 | ... DA32: =DA31*DA42 -> 7635.7676
B33: NI | C33: =C31-C32 -> 22.3 | D33: =D31-D32 -> 32.5 | E33: =E31-E32 -> 30.1 | F33: =F31-F32 -> 75.9 | G33: =G31-G32 -> 32.2 | H33: =H31-H32 -> 43.5 | I33: =I31-I32 -> 38 | J33: =J31-J32 -> 112.4 | ... BR33: =BR31-BR32 -> 2418.6 | CA33: =SUM(C33:F33) -> 160.8 | CB33: =SUM(G33:J33) -> 226.1 | CC33: =SUM(K33:N33) -> 226.1 | CD33: =SUM(O33:R33) -> 17.2 | CE33: =SUM(S33:V33) -> 112.2 | CF33: =SUM(W33:Z33) -> 266.8 | CG33: =SUM(AA33:AD33) -> 122.4 | CH33: =SUM(AE33:AH33) -> 186.8 | CI33: =SUM(AI33:AL33) -> 558.9 | CJ33: =SUM(AM33:AP33) -> 1211.1 | CK33: =SUM(AQ33:AT33) -> 1866.9 | CL33: =SUM(AU33:AX33) -> 2761.3 | CM33: =SUM(AY33:BB33) -> 5116.3 | CN33: =SUM(BC33:BF33) -> 4491.9 | CO33: =SUM(BG33:BJ33) -> 5408 | CP33: =SUM(BK33:BN33) -> 8711.5 | CQ33: =SUM(BO33:BR33) -> 10981.3 | CR33: =CR31-CR32 -> 14006.044 | CS33: =CS31-CS32 -> 15860.756 | CT33: =CT31-CT32 -> 17898.085 | CU33: =CU31-CU32 -> 21600.208 | CV33: =CV31-CV32 -> 22448.653 | CW33: =CW31-CW32 -> 24998.751 | CX33: =CX31-CX32 -> 27850.195 | CY33: =CY31-CY32 -> 31200.437 | ... DA33: =DA31-DA32 -> 40087.78 | DB33: =DA33*(1+$DK$39) -> 41069.931 | DC33: =DB33*(1+$DK$39) -> 42076.144 | DD33: =DC33*(1+$DK$39) -> 43107.01 | DE33: =DD33*(1+$DK$39) -> 44163.131 | DF33: =DE33*(1+$DK$39) -> 45245.128 | DG33: =DF33*(1+$DK$39) -> 46353.634 | DH33: =DG33*(1+$DK$39) -> 47489.298 | DI33: =DH33*(1+$DK$39) -> 48652.785 | ... EY33: =EX33*(1+$DK$39) -> 134465.27
B34: SC | C34: 3735 | D34: 3730 | E34: 3725 | F34: 3720 | G34: 3710 | H34: 3710 | I34: 3700 | J34: 3699 | K34: 3693 | L34: 3673 | M34: 3680 | N34: 3699 | O34: 3882 | P34: 3887 | Q34: 3888 | R34: 3886 | S34: 3918 | T34: 4073 | U34: 4138 | V34: 4074 | W34: 4187 | X34: 4200 | Y34: 4212 | Z34: 4205 | AA34: 4236 | AB34: 4253 | AC34: 4269 | AD34: 4259 | AE34: 4281 | AF34: 4285 | AG34: 4289 | AH34: 4288 | AI34: 4306 | AJ34: 4314 | AK34: 4324 | AL34: 4319 | AM34: 4342 | AN34: 4351 | AO34: 4358 | AP34: 4354 | AQ34: 4369 | AR34: 4376 | AS34: 4381 | AT34: 4378 | AU34: 4394 | AV34: 4406 | AW34: 4415 | AX34: 4409 | AY34: 4432 | AZ34: 4432 | BA34: 4428 | BB34: 4432 | BC34: 4441 | BD34: 4446 | BE34: 4449 | BF34: 4447 | BG34: 4452 | BH34: 4439 | BI34: 4415 | BJ34: 4416 | BK34: 4321 | BL34: 4301 | BM34: 4282 | BN34: 4295 | BO34: 4273 | BP34: 4252 | BQ34: 4245 | BR34: 4250 | CA34: =AVERAGE(C34:F34) -> 3727.5 | CB34: =AVERAGE(G34:J34) -> 3704.75 | CC34: =AVERAGE(K34:N34) -> 3686.25 | CD34: =AVERAGE(O34:R34) -> 3885.75 | CE34: =AVERAGE(S34:V34) -> 4050.75 | CF34: =AVERAGE(W34:Z34) -> 4201 | CG34: =AVERAGE(AA34:AD34) -> 4254.25 | CH34: =AVERAGE(AE34:AH34) -> 4285.75 | CI34: =AVERAGE(AI34:AL34) -> 4315.75 | CJ34: =AVERAGE(AM34:AP34) -> 4351.25 | CK34: =AVERAGE(AQ34:AT34) -> 4376 | CL34: =AVERAGE(AU34:AX34) -> 4406 | CM34: =AVERAGE(AY34:BB34) -> 4431 | CN34: =AVERAGE(BC34:BF34) -> 4445.75 | CO34: =AVERAGE(BG34:BJ34) -> 4430.5 | CP34: =AVERAGE(BK34:BN34) -> 4299.75 | CQ34: =AVERAGE(BO34:BR34) -> 4255
B35: EPS | C35: =C33/C34 -> 0.0059705489 | D35: =D33/D34 -> 0.0087131367 | E35: =E33/E34 -> 0.0080805369 | F35: =F33/F34 -> 0.020403226 | G35: =G33/G34 -> 0.0086792453 | H35: =H33/H34 -> 0.011725067 | I35: =I33/I34 -> 0.01027027 | J35: =J33/J34 -> 0.030386591 | ... BR35: =BR33/BR34 -> 0.56908235 | CA35: =SUM(C35:F35) -> 0.043167448 | CB35: =SUM(G35:J35) -> 0.061061174 | CC35: =SUM(K35:N35) -> 0.06136868 | CD35: =SUM(O35:R35) -> 0.0044234957 | CE35: =SUM(S35:V35) -> 0.027447936 | CF35: =SUM(W35:Z35) -> 0.063499227 | CG35: =SUM(AA35:AD35) -> 0.028761897 | CH35: =SUM(AE35:AH35) -> 0.043577851 | CI35: =SUM(AI35:AL35) -> 0.12951238 | CJ35: =SUM(AM35:AP35) -> 0.27831812 | CK35: =SUM(AQ35:AT35) -> 0.42651369 | CL35: =SUM(AU35:AX35) -> 0.62670392 | CM35: =SUM(AY35:BB35) -> 1.1546952 | CN35: =SUM(BC35:BF35) -> 1.0105136 | CO35: =SUM(BG35:BJ35) -> 1.2205885 | CP35: =SUM(BK35:BN35) -> 2.0259948 | CQ35: =SUM(BO35:BR35) -> 2.5805347 | DC35: Invested Capital | DF35: Avg. (2024-2025) | DH35: Projected ROIC:
DC36: 2024 | DD36: 2025 | DF36: 2024-2025 | DH36: 2025
B37: Gross Profit Margin | C37: =C23/C21 -> 0.34204517 | D37: =D23/D21 -> 0.34100367 | E37: =E23/E21 -> 0.3493264 | F37: =F23/F21 -> 0.40911517 | G37: =G23/G21 -> 0.37775977 | H37: =H23/H21 -> 0.39419007 | I37: =I23/I21 -> 0.37725958 | J37: =J23/J21 -> 0.34470969 | ... BR37: =BR23/BR21 -> 0.45874133 | CA37: =CA23/CA21 -> 0.3723296 | CB37: =CB23/CB21 -> 0.3634463 | CC37: =CC23/CC21 -> 0.36341509 | CD37: =CD23/CD21 -> 0.26523149 | CE37: =CE23/CE21 -> 0.28740913 | CF37: =CF23/CF21 -> 0.31826109 | CG37: =CG23/CG21 -> 0.32272291 | CH37: =CH23/CH21 -> 0.29139583 | ... CQ37: =CQ23/CQ21 -> 0.48486934 | CR37: 0.46918725 | CS37: 0.46918725 | CT37: 0.46918725 | CU37: 0.46918725 | CV37: 0.46918725 | CW37: 0.46918725 | CX37: 0.46918725 | CY37: 0.46918725 | CZ37: 0.46918725 | DA37: 0.46918725 | DC37: =SUM(CP45:CP47)-CP54-CP53+CP48+CP49 -> 41853.003 | DD37: =SUM(CQ45:CQ47)-CQ54-CQ53+CQ48+CQ49 -> 42817.46 | DF37: =AVERAGE(DC37:DD37) -> 42335.231 | DH37: =AVERAGE(CR28)*(1-CR42) -> 13120.078
B38: S&M as % of Revenue | C38: =C24/C21 -> 0.15529054 | D38: =D24/D21 -> 0.1128519 | E38: =E24/E21 -> 0.13471992 | F38: =F24/F21 -> 0.13832853 | G38: =G24/G21 -> 0.15252177 | H38: =H24/H21 -> 0.14332436 | I38: =I24/I21 -> 0.14678236 | J38: =J24/J21 -> 0.10482935 | ... BR38: =BR24/BR21 -> 0.092392206 | CA38: =CA24/CA21 -> 0.13590123 | CB38: =CB24/CB21 -> 0.12566311 | CC38: =CC24/CC21 -> 0.118954 | CD38: =CD24/CD21 -> 0.12038345 | CE38: =CE24/CE21 -> 0.10748411 | CF38: =CF24/CF21 -> 0.11030774 | CG38: =CG24/CG21 -> 0.12155764 | CH38: =CH24/CH21 -> 0.12427242 | ... CQ38: =CQ24/CQ21 -> 0.073067142 | CR38: 0.075 | CS38: 0.0745 | CT38: 0.074 | CU38: 0.0435 | CV38: 0.073 | CW38: 0.0725 | CX38: 0.072 | CY38: 0.0715 | CZ38: 0.071 | DA38: 0.07 | DH38: =DH37/DF37 -> 0.30990922 | DJ38: ROIC | DK38: 0.3075
B39: G&A as % of Revenue | C39: =C25/C21 -> 0.032986552 | D39: =D25/D21 -> 0.03255814 | E39: =E25/E21 -> 0.027180336 | F39: =F25/F21 -> 0.028498239 | G39: =G25/G21 -> 0.031395584 | H39: =H25/H21 -> 0.029049634 | I39: =I25/I21 -> 0.028741866 | J39: =J25/J21 -> 0.049026192 | ... BR39: =BR25/BR21 -> 0.047117204 | CA39: =CA25/CA21 -> 0.02982521 | CB39: =CB25/CB21 -> 0.039568121 | CC39: =CC25/CC21 -> 0.046277226 | CD39: =CD25/CD21 -> 0.039841521 | CE39: =CE25/CE21 -> 0.041192338 | CF39: =CF25/CF21 -> 0.048995386 | CG39: =CG25/CG21 -> 0.060078177 | CH39: =CH25/CH21 -> 0.035750685 | ... CQ39: =CQ25/CQ21 -> 0.041794388 | CR39: 0.042804549 | CS39: 0.0425 | CT39: 0.04225 | CU39: 0.042 | CV39: 0.0415 | CW39: 0.041 | CX39: 0.0405 | CY39: 0.04025 | CZ39: 0.04 | DA39: 0.04 | DC39: Capital Structure | DJ39: Terminal | DK39: 0.0245
B40: R&D as % of Revenue | C40: =C26/C21 -> 0.061405735 | D40: =D26/D21 -> 0.066340269 | E40: =E26/E21 -> 0.070905223 | F40: =F26/F21 -> 0.087522681 | G40: =G26/G21 -> 0.075754507 | H40: =H26/H21 -> 0.072912659 | I40: =I26/I21 -> 0.076102675 | J40: =J26/J21 -> 0.086513218 | ... BR40: =BR26/BR21 -> 0.073878913 | CA40: =CA26/CA21 -> 0.075510959 | CB40: =CB26/CB21 -> 0.080852524 | CC40: =CC26/CC21 -> 0.080852524 | CD40: =CD26/CD21 -> 0.091125703 | CE40: =CE26/CE21 -> 0.086567915 | CF40: =CF26/CF21 -> 0.085819133 | CG40: =CG26/CG21 -> 0.09601003 | CH40: =CH26/CH21 -> 0.088351867 | ... CQ40: =CQ26/CQ21 -> 0.075059038 | CR40: 0.074 | CS40: 0.073 | CT40: 0.072 | CU40: 0.071 | CV40: 0.07 | CW40: 0.07 | CX40: 0.07 | CY40: 0.07 | CZ40: 0.07 | DA40: 0.07 | DC40: Mkt Cap | DF40: =Main!C5 -> 385426.38 | DJ40: RFR (10-year yield) | DK40: =DF46 -> 0.0409
B41: Operating Profit Margin | C41: =C28/C21 -> 0.092362345 | D41: =D28/D21 -> 0.12925337 | E41: =E28/E21 -> 0.11652092 | F41: =F28/F21 -> 0.15476572 | G41: =G28/G21 -> 0.11808791 | H41: =H28/H21 -> 0.14890342 | I41: =I28/I21 -> 0.12563268 | J41: =J28/J21 -> 0.10434092 | ... BR41: =BR28/BR21 -> 0.24535301 | CA41: =CA28/CA21 -> 0.1310922 | CB41: =CB28/CB21 -> 0.11736254 | CC41: =CC28/CC21 -> 0.11733134 | CD41: =CD28/CD21 -> 0.013880808 | CE41: =CE28/CE21 -> 0.052164769 | CF41: =CF28/CF21 -> 0.073138829 | CG41: =CG28/CG21 -> 0.045077071 | CH41: =CH28/CH21 -> 0.043020859 | ... DA41: =DA28/DA21 -> 0.34511163 | DC41: Debt to Ttl Mkt Cap | DF41: =Main!C7/(Main!C7+DF40) -> 0.036167092 | DJ41: ERP (Avg. market return - (less) RFR) | DK41: =8.69%-DK40 -> 0.046
B42: Effective Tax Rate | C42: =C32/C31 -> 0.40214477 | D42: =D32/D31 -> 0.38679245 | E42: =E32/E31 -> 0.40277778 | F42: =F32/F31 -> 0.40141956 | G42: =G32/G31 -> 0.40699816 | H42: =H32/H31 -> 0.40735695 | I42: =I32/I31 -> 0.41896024 | J42: =J32/J31 -> 0.32451923 | ... BR42: =BR32/BR31 -> 0.12616519 | CA42: =CA32/CA31 -> 0.3988785 | CB42: =CB32/CB31 -> 0.37107093 | CC42: =CC32/CC31 -> 0.37107093 | CD42: =CD32/CD31 -> 0.4379085 | CE42: =CE32/CE31 -> 0.34347572 | CF42: =CF32/CF31 -> 0.23618666 | CG42: =CG32/CG31 -> 0.13620325 | CH42: =CH32/CH31 -> 0.28319263 | ... CQ42: =CQ32/CQ31 -> 0.13687346 | CR42: 0.15 | CS42: 0.16 | CT42: 0.16 | CU42: 0.16 | CV42: 0.16 | CW42: 0.16 | CX42: 0.16 | CY42: 0.16 | CZ42: 0.16 | DA42: 0.16 | DC42: Mkt Equity to Ttl Mkt Cap | DF42: =DF40/(DF40+Main!C7) -> 0.96383291 | DJ42: Equity β (1-year avg.) | DK42: ='Notes | Quant Analysis'!S209 -> 1.0345819
B43: Net Profit Margin | C43: =C33/C21 -> 0.056584623 | D43: =D33/D21 -> 0.079559364 | E43: =E33/E21 -> 0.071141574 | F43: =F33/F21 -> 0.081011848 | G43: =G33/G21 -> 0.065221795 | H43: =H33/H21 -> 0.083686033 | I43: =I33/I21 -> 0.068691251 | J43: =J33/J21 -> 0.068624458 | ... BR43: =BR33/BR21 -> 0.20070037 | CA43: =CA33/CA21 -> 0.074354943 | CB43: =CB33/CB21 -> 0.070554827 | CC43: =CC33/CC21 -> 0.070554827 | CD43: =CD33/CD21 -> 0.004765467 | CE43: =CE33/CE21 -> 0.025648059 | CF43: =CF33/CF21 -> 0.048468554 | CG43: =CG33/CG21 -> 0.018054429 | CH43: =CH33/CH21 -> 0.021153715 | ... DA43: =DA33/DA21 -> 0.50128246 | DC43: LT Debt / Equity | DF43: =(CQ59+CQ57)/CQ62 -> 0.54339902 | DJ43: Discount (Cost of Equity) | DK43: =+DK40+(DK41*DK42) -> 0.088490767
B45: Cash & CEs | BF45: 5147.17 | BG45: 6714.59 | BH45: 7662.78 | BI45: 7353.24 | BJ45: 7116.91 | BK45: 7024.76 | BL45: 6624.939 | BM45: 7457.02 | BN45: 7804.733 | BO45: 7199.84 | BP45: 8177.4 | BQ45: 9287.28 | BR45: 9033.68 | CN45: =BF45 -> 5147.17 | CO45: =BJ45 -> 7116.91 | CP45: =BN45 -> 7804.733 | CQ45: =BR45 -> 9033.68 | CR45: =CQ45+CR33 -> 23039.724 | CS45: =CR45+CS33 -> 38900.481 | CT45: =CS45+CT33 -> 56798.566 | CU45: =CT45+CU33 -> 78398.773 | CV45: =CU45+CV33 -> 100847.43 | CW45: =CV45+CW33 -> 125846.18 | CX45: =CW45+CX33 -> 153696.37 | CY45: =CX45+CY33 -> 184896.81 | ... DA45: =CZ45+DA33 -> 260200.55 | DC45: Cost of Equity | DJ45: NPV | DK45: =NPV(DK43,CR33:EY33) -> 411645.78
B46: ST Investments | BF46: 911.27 | BG46: 1112.91 | BH46: 914.2 | BI46: 514.2 | BJ46: 20.97 | BK46: 20.97 | BL46: 30.973 | BM46: 1766.9 | BN46: 1779 | BO46: 1171.14 | BP46: 213.11 | BQ46: 38 | BR46: 28.67 | CN46: =BF46 -> 911.27 | CO46: =BJ46 -> 20.97 | CP46: =BN46 -> 1779 | CQ46: =BR46 -> 28.67 | DC46: RFR (10-year yield) | DF46: 0.0409 | DJ46: SC | DK46: =Main!C4 -> 4222
B47: Other ST Assets | BF47: 3208.02 | BG47: 2655.11 | BH47: 2929.34 | BI47: 2912.02 | BJ47: 2780.24 | BK47: 2875.57 | BL47: 2959.64 | BM47: 2905.17 | BN47: 3516.64 | BO47: 3326.64 | BP47: 3602.58 | BQ47: 3638.54 | BR47: 3957.83 | CN47: =BF47 -> 3208.02 | CO47: =BJ47 -> 2780.24 | CP47: =BN47 -> 3516.64 | CQ47: =BR47 -> 3957.83 | DC47: Equity β (1-year avg.) | DF47: ='Notes | Quant Analysis'!S209 -> 1.0345819 | DJ47: FV | DK47: =DK45/DK46 -> 97.500185
B48: LT Content Assets | BF48: 32736.7 | BG48: 32349.18 | BH48: 32520.77 | BI48: 31749.86 | BJ48: 31658.05 | BK48: 31662.1 | BL48: 31927.355 | BM48: 32175.38 | BN48: 32452.46 | BO48: 32040.83 | BP48: 32089.39 | BQ48: 32639 | BR48: 32778.39 | CN48: =BF48 -> 32736.7 | CO48: =BJ48 -> 31658.05 | CP48: =BN48 -> 32452.46 | CQ48: =BR48 -> 32778.39 | DC48: Market Return(1-year avg.) | DF48: 0.1197 | DJ48: CP | DK48: =Main!C3 -> 91.29
B49: PP&E | BF49: 1398.25 | BG49: 1413.09 | BH49: 1471.96 | BI49: 1498.39 | BJ49: 1491.44 | BK49: 1501.16 | BL49: 1510.958 | BM49: 1568.21 | BN49: 1593.75 | BO49: 1644.34 | BP49: 1743.56 | BQ49: 1837.88 | BR49: 2004.35 | CN49: =BF49 -> 1398.25 | CO49: =BJ49 -> 1491.44 | CP49: =BN49 -> 1593.75 | CQ49: =BR49 -> 2004.35 | DC49: Cost of Equity | DF49: =(DF46+DF47)*(DF48-DF46) -> 0.084747972 | DJ49: Change Δ | DK49: =DK47/DK48-1 -> 0.068026997 | DL49: =IF(DK49>0,"Upside","Downside") -> Upside
B50: Other LT Assets | BF50: 5193.32 | BG50: 5245.444 | BH50: 5318.39 | BI50: 5474.06 | BJ50: 5664.35 | BK50: 5743.14 | BL50: 6045.02 | BM50: 6409.15 | BN50: 6483.77 | BO50: 6704.82 | BP50: 7273.59 | BQ50: 7494.13 | BR50: 7794.06 | CN50: =BF50 -> 5193.32 | CO50: =BJ50 -> 5664.35 | CP50: =BN50 -> 6483.77 | CQ50: =BR50 -> 7794.06 | DJ50: {=_xlfn.IFS(DK49>=25%,"Strong Buy",DK49>=10.00001%,"Buy",AND(DK49<=10%,DK49>=-4.9999%),"Hold",AND(DK49<=-5%,DK49>=-14.999999%),"Sell",DK49<=-15%,"Strong Sell")} -> Hold
B51: Ttl Assets | BF51: =SUM(BF45:BF50) -> 48594.73 | BG51: =SUM(BG45:BG50) -> 49490.324 | BH51: =SUM(BH45:BH50) -> 50817.44 | BI51: =SUM(BI45:BI50) -> 49501.77 | BJ51: =SUM(BJ45:BJ50) -> 48731.96 | BK51: =SUM(BK45:BK50) -> 48827.7 | BL51: =SUM(BL45:BL50) -> 49098.885 | BM51: =SUM(BM45:BM50) -> 52281.83 | ... BR51: =SUM(BR45:BR50) -> 55596.98 | CN51: =BF51 -> 48594.73 | CO51: =BJ51 -> 48731.96 | CP51: =BN51 -> 53630.353 | CQ51: =BR51 -> 55596.98 | DC51: Cost of Debt
DC52: Cost of Debt | DF52: 0.0555
B53: ST Content Liabilities | BF53: 4480.15 | BG53: 4344.58 | BH53: 4440.4 | BI53: 4259.58 | BJ53: 4466.47 | BK53: 4436.02 | BL53: 4391.43 | BM53: 4489.97 | BN53: 4393.68 | BO53: 4128.905 | BP53: 4091.77 | BQ53: 4102.64 | BR53: 4084.85 | CN53: =BF53 -> 4480.15 | CO53: =BJ53 -> 4466.47 | CP53: =BN53 -> 4393.68 | CQ53: =BR53 -> 4084.85 | DC53: Tax Rate | DF53: 0.14
B54: A/P | BF54: 671.513 | BG54: 591.98 | BH54: 615.37 | BI54: 534.42 | BJ54: 747.41 | BK54: 607.348 | BL54: 598.55 | BM54: 641.95 | BN54: 899.9 | BO54: 614.489 | BP54: 632.71 | BQ54: 793.23 | BR54: 900.61 | CN54: =BF54 -> 671.513 | CO54: =BJ54 -> 747.41 | CP54: =BN54 -> 899.9 | CQ54: =BR54 -> 900.61 | DC54: After Tax Cost of Debt | DF54: =DF52*(1-DF53) -> 0.04773
B55: Accrued ST Expenses | BF55: 1514.65 | BG55: 1718.06 | BH55: 1908.71 | BI55: 1838.9 | BJ55: 1803.96 | BK55: 1977.42 | BL55: 1876.24 | BM55: 2241.75 | BN55: 2156.54 | BO55: 2359.518 | BP55: 2489.486 | BQ55: 3111.31 | BR55: 3220.86 | CN55: =BF55 -> 1514.65 | CO55: =BJ55 -> 1803.96 | CP55: =BN55 -> 2156.54 | CQ55: =BR55 -> 3220.86
B56: Deferred ST Revenues | BF56: 1264.66 | BG56: 1262.27 | BH56: 1311.91 | BI56: 1306.18 | BJ56: 1442.969 | BK56: 1469.484 | BL56: 1473.72 | BM56: 1513.04 | BN56: 1520.81 | BO56: 1609.726 | BP56: 1728.36 | BQ56: 1724.67 | BR56: 1775.83 | CN56: =BF56 -> 1264.66 | CO56: =BJ56 -> 1442.969 | CP56: =BN56 -> 1520.81 | CQ56: =BR56 -> 1775.83 | DC56: WACC | DF56: =(DF42*DF49)+(DF41*DF54*(1-DF53)) -> 0.083167464
B57: ST Debt | BF57: 0 | BG57: 399.16 | BH57: 399.38 | BI57: 399.61 | BJ57: 399.8 | BK57: 798.93 | BL57: 1800.04 | BM57: 1820.39 | BN57: 1784.45 | BO57: 1005.88 | BP57: 0 | BQ57: 0 | BR57: 998.86 | CN57: =BF57 -> 0 | CO57: =BJ57 -> 399.8 | CP57: =BN57 -> 1784.45 | CQ57: =BR57 -> 998.86 | CR57: =(CQ57+CQ59)+CR29 -> 13660.143 | CS57: =CR57+CS29 -> 12902.005 | CT57: =CS57+CT29 -> 12185.944 | CU57: =CT57+CU29 -> 11509.624 | CV57: =CU57+CV29 -> 10870.84 | CW57: =CV57+CW29 -> 10267.508 | CX57: =CW57+CX29 -> 9697.6614 | CY57: =CX57+CY29 -> 9159.4412 | CZ57: =CY57+CZ29 -> 8651.0922 | DA57: =CZ57+DA29 -> 8170.9566
B58: LT Content Liabilities | BF58: 3081.27 | BG58: 2908.02 | BH58: 2849.38 | BI58: 2668.472 | BJ58: 2578.17 | BK58: 2370.69 | BL58: 2028.78 | BM58: 1918.08 | BN58: 1780.8 | BO58: 1696.66 | BP58: 1606.404 | BQ58: 1591.97 | BR58: 1579.47 | CN58: =BF58 -> 3081.27 | CO58: =BJ58 -> 2578.17 | CP58: =BN58 -> 1780.8 | CQ58: =BR58 -> 1579.47
B59: LT Debt | BF59: 14353.07 | BG59: 14037.96 | BH59: 14070.15 | BI59: 13900.75 | BJ59: 14143.41 | BK59: 13217.03 | BL59: 12180.02 | BM59: 14160.93 | BN59: 13798.35 | BO59: 14011.03 | BP59: 14453.206 | BQ59: 14463.02 | BR59: 13463.97 | CN59: =BF59 -> 14353.07 | CO59: =BJ59 -> 14143.41 | CP59: =BN59 -> 13798.35 | CQ59: =BR59 -> 13463.97
B60: Other LT Liabilities | BF60: 2452.04 | BG60: 2400.08 | BH60: 2389.9 | BI60: 2486.2 | BJ60: 2561.434 | BK60: 2585.36 | BL60: 2637.39 | BM60: 2774.96 | BN60: 2552.25 | BO60: 2633.35 | BP60: 3145.82 | BQ60: 3193.94 | BR60: 2957.128 | CN60: =BF60 -> 2452.04 | CO60: =BJ60 -> 2561.434 | CP60: =BN60 -> 2552.25 | CQ60: =BR60 -> 2957.128
B61: Ttl Liabilities | BF61: =SUM(BF53:BF60) -> 27817.353 | BG61: =SUM(BG53:BG60) -> 27662.11 | BH61: =SUM(BH53:BH60) -> 27985.2 | BI61: =SUM(BI53:BI60) -> 27394.112 | BJ61: =SUM(BJ53:BJ60) -> 28143.623 | BK61: =SUM(BK53:BK60) -> 27462.282 | BL61: =SUM(BL53:BL60) -> 26986.17 | BM61: =SUM(BM53:BM60) -> 29561.07 | ... BR61: =SUM(BR53:BR60) -> 28981.578 | CN61: =BF61 -> 27817.353 | CO61: =BJ61 -> 28143.623 | CP61: =BN61 -> 28886.78 | CQ61: =BR61 -> 28981.578
B62: Ttl SE | BF62: 20777.4 | BG62: 21828.19 | BH62: 22832.215 | BI62: 22107.62 | BJ62: 20588.3 | BK62: 21365 | BL62: 22112.69 | BM62: 22720.73 | BN62: 24743.567 | BO62: 24028.07 | BP62: 24951.899 | BQ62: 25954.03 | BR62: 26615.488 | CN62: =BF62 -> 20777.4 | CO62: =BJ62 -> 20588.3 | CP62: =BN62 -> 24743.567 | CQ62: =BR62 -> 26615.488
B63: Ttl L + SE | BF63: =BF61+BF62 -> 48594.753 | BG63: =BG61+BG62 -> 49490.3 | BH63: =BH61+BH62 -> 50817.415 | BI63: =BI61+BI62 -> 49501.732 | BJ63: =BJ61+BJ62 -> 48731.923 | BK63: =BK61+BK62 -> 48827.282 | BL63: =BL61+BL62 -> 49098.86 | BM63: =BM61+BM62 -> 52281.8 | ... BR63: =BR61+BR62 -> 55597.066 | CN63: =BF63 -> 48594.753 | CO63: =BJ63 -> 48731.923 | CP63: =BN63 -> 53630.347 | CQ63: =BR63 -> 55597.066
B65: Current Ratio | BF65: =SUM(BF45:BF47)/SUM(BF53:BF57) -> 1.1683888 | BG65: =SUM(BG45:BG47)/SUM(BG53:BG57) -> 1.2605275 | BH65: =SUM(BH45:BH47)/SUM(BH53:BH57) -> 1.3262592 | BI65: =SUM(BI45:BI47)/SUM(BI53:BI57) -> 1.2927042 | BJ65: =SUM(BJ45:BJ47)/SUM(BJ53:BJ57) -> 1.1193497 | BK65: =SUM(BK45:BK47)/SUM(BK53:BK57) -> 1.0680465 | BL65: =SUM(BL45:BL47)/SUM(BL53:BL57) -> 0.94828116 | BM65: =SUM(BM45:BM47)/SUM(BM53:BM57) -> 1.1328081 | ... BR65: =SUM(BR45:BR47)/SUM(BR53:BR57) -> 1.1856997 | CN65: =SUM(CN45:CN47)/SUM(CN53:CN57) -> 1.1683888 | CO65: =SUM(CO45:CO47)/SUM(CO53:CO57) -> 1.1193497 | CP65: =SUM(CP45:CP47)/SUM(CP53:CP57) -> 1.2180298 | CQ65: =SUM(CQ45:CQ47)/SUM(CQ53:CQ57) -> 1.1856997
B66: Cash Ratio | BF66: =SUM(BF45:BF46)/SUM(BF53:BF57) -> 0.76389618 | BG66: =SUM(BG45:BG46)/SUM(BG53:BG57) -> 0.94125216 | BH66: =SUM(BH45:BH46)/SUM(BH53:BH57) -> 0.98861311 | BI66: =SUM(BI45:BI46)/SUM(BI53:BI57) -> 0.94348633 | BJ66: =SUM(BJ45:BJ46)/SUM(BJ53:BJ57) -> 0.80557442 | BK66: =SUM(BK45:BK46)/SUM(BK53:BK57) -> 0.75848604 | BL66: =SUM(BL45:BL46)/SUM(BL53:BL57) -> 0.65640287 | BM66: =SUM(BM45:BM46)/SUM(BM53:BM57) -> 0.86147696 | ... BR66: =SUM(BR45:BR46)/SUM(BR53:BR57) -> 0.82527472 | CN66: =SUM(CN45:CN46)/SUM(CN53:CN57) -> 0.76389618 | CO66: =SUM(CO45:CO46)/SUM(CO53:CO57) -> 0.80557442 | CP66: =SUM(CP45:CP46)/SUM(CP53:CP57) -> 0.8910641 | CQ66: =SUM(CQ45:CQ46)/SUM(CQ53:CQ57) -> 0.82527472
B67: Ttl Asset Turnover Ratio | BF67: =BF21/BF51 -> 0.16158337 | BG67: =BG21/BG51 -> 0.16491102 | BH67: =BH21/BH51 -> 0.16111201 | BI67: =BI21/BI51 -> 0.17255343 | BJ67: =BJ21/BJ51 -> 0.18125271 | BK67: =BK21/BK51 -> 0.19190746 | BL67: =BL21/BL51 -> 0.19469485 | BM67: =BM21/BM51 -> 0.18791806 | ... BR67: =BR21/BR51 -> 0.21675278 | CN67: =CN21/CN51 -> 0.6505973 | CO67: =CO21/CO51 -> 0.69201608 | CP67: =CP21/CP51 -> 0.72721692 | CQ67: =CQ21/CQ51 -> 0.81268983
B68: Return on Assets | BF68: =BF33/BF51 -> 0.0011359256 | BG68: =BG33/BG51 -> 0.026370811 | BH68: =BH33/BH51 -> 0.029273415 | BI68: =BI33/BI51 -> 0.033887677 | BJ68: =BJ33/BJ51 -> 0.019244044 | BK68: =BK33/BK51 -> 0.047761824 | BL68: =BL33/BL51 -> 0.043734191 | BM68: =BM33/BM51 -> 0.045208823 | ... BR68: =BR33/BR51 -> 0.043502363 | CN68: =CN33/CN51 -> 0.092435949 | CO68: =CO33/CO51 -> 0.1109744 | CP68: =CP33/CP51 -> 0.162436 | CQ68: =CQ33/CQ51 -> 0.19751612
B69: Return on Equity | BF69: =BF33/BF62 -> 0.0026567328 | BG69: =BG33/BG62 -> 0.059789657 | BH69: =BH33/BH62 -> 0.065153556 | BI69: =BI33/BI62 -> 0.075878815 | BJ69: =BJ33/BJ62 -> 0.045550143 | BK69: =BK33/BK62 -> 0.10915516 | BL69: =BL33/BL62 -> 0.097107136 | BM69: =BM33/BM62 -> 0.10402835 | ... BR69: =BR33/BR62 -> 0.090871901 | CN69: =CN33/CN62 -> 0.21619163 | CO69: =CO33/CO62 -> 0.26267346 | CP69: =CP33/CP62 -> 0.35207131 | CQ69: =CQ33/CQ62 -> 0.41259059
B71: Net Income | C71: =C33 -> 22.3 | D71: =D33 -> 32.5 | E71: =E33 -> 30.1 | F71: =F33 -> 75.9 | G71: =G33 -> 32.2 | H71: =H33 -> 43.5 | I71: =I33 -> 38 | J71: =J33 -> 112.4 | ... BR71: =BR33 -> 2418.6 | CA71: =CA33 -> 160.8 | CB71: =CB33 -> 226.1 | CC71: =CC33 -> 226.1 | CD71: =CD33 -> 17.2 | CE71: =CE33 -> 112.2 | CF71: =CF33 -> 266.8 | CG71: =CG33 -> 122.4 | CH71: =CH33 -> 186.8 | ... CQ71: =CQ33 -> 10981.3
B72: CFFO | C72: 65.6 | D72: 75.3 | E72: 78.3 | F72: 57.2 | G72: 76.7 | H72: 61.8 | I72: 41.2 | J72: 138 | K72: 116.3 | L72: 86.4 | M72: 49.5 | N72: 65.5 | O72: 19.1 | P72: 19.4 | Q72: -2.9 | R72: -17.4 | S72: -12.2 | T72: 33.9 | U72: 34.7 | V72: 41.4 | W72: 36.4 | X72: 56 | Y72: -37.4 | Z72: -38.5 | AA72: -127.4 | AB72: -181.3 | AC72: -196 | AD72: -244.7 | AE72: -228.6 | AF72: -226.3 | AG72: -461.9 | AH72: -557.2 | AI72: -343.9 | AJ72: -534.5 | AK72: -419.6 | AL72: -488 | AM72: -236.8 | AN72: -518.2 | AO72: -690.4 | AP72: -1235.1 | AQ72: -379.8 | AR72: -543.8 | AS72: -501.8 | AT72: -1462 | AU72: 259.9 | AV72: 1041.1 | AW72: 1263.8 | AX72: -137.7 | AY72: 777.3 | AZ72: -63.8 | BA72: 82.4 | BB72: -403.3 | BC72: 922.8 | BD72: 102.8 | BE72: 556.8 | BF72: 443.9 | BG72: 2178.7 | BH72: 1440.2 | BI72: 1992.3 | BJ72: 1663 | BK72: 2212.5 | BL72: 1290.8 | BM72: 2321.1 | BN72: 1536.9 | BO72: 2789.2 | BP72: 2423.3 | BQ72: 2825.2 | BR72: 2111.6 | CA72: =SUM(C72:F72) -> 276.4 | CB72: =SUM(G72:J72) -> 317.7 | CC72: =SUM(K72:N72) -> 317.7 | CD72: =SUM(O72:R72) -> 18.2 | CE72: =SUM(S72:V72) -> 97.8 | CF72: =SUM(W72:Z72) -> 16.5 | CG72: =SUM(AA72:AD72) -> -749.4 | CH72: =SUM(AE72:AH72) -> -1474 | CI72: =SUM(AI72:AL72) -> -1786 | CJ72: =SUM(AM72:AP72) -> -2680.5 | CK72: =SUM(AQ72:AT72) -> -2887.4 | CL72: =SUM(AU72:AX72) -> 2427.1 | CM72: =SUM(AY72:BB72) -> 392.6 | CN72: =SUM(BC72:BF72) -> 2026.3 | CO72: =SUM(BG72:BJ72) -> 7274.2 | CP72: =SUM(BK72:BN72) -> 7361.3 | CQ72: =SUM(BL72:BO72) -> 7938
B73: CapEx, net | C73: -11 | D73: -12 | E73: -8.3 | F73: -14.5 | G73: -8.1 | H73: -11.5 | I73: -13.6 | J73: -8.6 | K73: -16.3 | L73: -8.6 | M73: -14.08 | N73: -10.6 | O73: -4.7 | P73: -3.3 | Q73: -10.8 | R73: -21.3 | S73: -12.1 | T73: -8 | U73: -10.8 | V73: -23 | W73: -13.3 | X73: -19.9 | Y73: -21 | Z73: -15.5 | AA73: -13 | AB73: -27.5 | AC73: -37.8 | AD73: -12.9 | AE73: -8.4 | AF73: -10.8 | AG73: -27.4 | AH73: -61 | AI73: -52.5 | AJ73: -65.2 | AK73: -34 | AL73: -21.6 | AM73: -37.2 | AN73: -27.3 | AO73: -39.3 | AP73: -70.1 | AQ73: -60.4 | AR73: -39.6 | AS73: -45.3 | AT73: -107.7 | AU73: -98 | AV73: -141.7 | AW73: -109.8 | AX73: -148.4 | AY73: -81 | AZ73: -110.3 | BA73: -167.3 | BB73: -166 | BC73: -121.2 | BD73: -90 | BE73: -85 | BF73: -111.6 | BG73: -62 | BH73: -101 | BI73: -103.9 | BJ73: -81.6 | BK73: -75.7 | BL73: -78.3 | BM73: -126.9 | BN73: -158.7 | BO73: -128.3 | BP73: -155.9 | BQ73: -164.7 | BR73: -239.3 | CA73: =SUM(C73:F73) -> -45.8 | CB73: =SUM(G73:J73) -> -41.8 | CC73: =SUM(K73:N73) -> -49.58 | CD73: =SUM(O73:R73) -> -40.1 | CE73: =SUM(S73:V73) -> -53.9 | CF73: =SUM(W73:Z73) -> -69.7 | CG73: =SUM(AA73:AD73) -> -91.2 | CH73: =SUM(AE73:AH73) -> -107.6 | CI73: =SUM(AI73:AL73) -> -173.3 | CJ73: =SUM(AM73:AP73) -> -173.9 | CK73: =SUM(AQ73:AT73) -> -253 | CL73: =SUM(AU73:AX73) -> -497.9 | CM73: =SUM(AY73:BB73) -> -524.6 | CN73: =SUM(BC73:BF73) -> -407.8 | CO73: =SUM(BG73:BJ73) -> -348.5 | CP73: =SUM(BK73:BN73) -> -439.6 | CQ73: =SUM(BL73:BO73) -> -492.2
B74: FCF | C74: =C72+C73 -> 54.6 | D74: =D72+D73 -> 63.3 | E74: =E72+E73 -> 70 | F74: =F72+F73 -> 42.7 | G74: =G72+G73 -> 68.6 | H74: =H72+H73 -> 50.3 | I74: =I72+I73 -> 27.6 | J74: =J72+J73 -> 129.4 | ... BR74: =BR72+BR73 -> 1872.3 | CA74: =CA72+CA73 -> 230.6 | CB74: =CB72+CB73 -> 275.9 | CC74: =CC72+CC73 -> 268.12 | CD74: =CD72+CD73 -> -21.9 | CE74: =CE72+CE73 -> 43.9 | CF74: =CF72+CF73 -> -53.2 | CG74: =CG72+CG73 -> -840.6 | CH74: =CH72+CH73 -> -1581.6 | ... CQ74: =CQ72+CQ73 -> 7445.8
B75: SC | C75: =C34 -> 3735 | D75: =D34 -> 3730 | E75: =E34 -> 3725 | F75: =F34 -> 3720 | G75: =G34 -> 3710 | H75: =H34 -> 3710 | I75: =I34 -> 3700 | J75: =J34 -> 3699 | ... BR75: =BR34 -> 4250 | CA75: =CA34 -> 3727.5 | CB75: =CB34 -> 3704.75 | CC75: =CC34 -> 3686.25 | CD75: =CD34 -> 3885.75 | CE75: =CE34 -> 4050.75 | CF75: =CF34 -> 4201 | CG75: =CG34 -> 4254.25 | CH75: =CH34 -> 4285.75 | ... CQ75: =CQ34 -> 4255
B76: FCF per Share | C76: =C74/C75 -> 0.014618474 | D76: =D74/D75 -> 0.016970509 | E76: =E74/E75 -> 0.018791946 | F76: =F74/F75 -> 0.011478495 | G76: =G74/G75 -> 0.018490566 | H76: =H74/H75 -> 0.013557951 | I76: =I74/I75 -> 0.0074594595 | J76: =J74/J75 -> 0.034982428 | ... BR76: =BR74/BR75 -> 0.44054118 | CA76: =CA74/CA75 -> 0.06186452 | CB76: =CB74/CB75 -> 0.074471962 | CC76: =CC74/CC75 -> 0.072735164 | CD76: =CD74/CD75 -> -0.0056359776 | CE76: =CE74/CE75 -> 0.010837499 | CF76: =CF74/CF75 -> -0.012663652 | CG76: =CG74/CG75 -> -0.19759064 | CH76: =CH74/CH75 -> -0.36903692 | ... CQ76: =CQ74/CQ75 -> 1.7498942

Sheet Notes | Quant Analysis
CI1: 0
P2: Employee Scope: | AL2: General Notes/Observations (Updated Q1'26)
P36: Institutional Ownership Snapshot Q4'25
AL37: Financial Stmts. Notes/Observations (Updated Q1'26)
AL38: Revenues:
Q65: Notes: | R65: [X]
R66: [Y]
R67: [Z]
P69: Revenue Breakdown by Segment (Build graph for this section if applicable…. See example below) | AL69: Earnings Scope:
Q101: Notes: | R101: [X]
R102: [Y]
R103: [Z]
P105: Q/q Total Revenues, Net Income, FCF | AL105: Balance Sheet Scope:
Q134: Notes: | R134: [X]
R135: [Y]
R136: [Z]
P138: Y/y Total Revenues, Net Income, FCF | AL138: [Equity Preformance Compared to Peers]
Q167: Notes: | R167: [X]
R168: [Y]
R169: [Z]
A184: VOO Historical Returns | I184: NFLX Historical Returns
A185: 753 Trading Days (From: 2/19/2022 - 2/19/2026) | I185: 753 Trading Days (From: 2/19/2022 - 2/19/2026)
A186: Close | B186: High | C186: Low | D186: Open | E186: Volume | F186: UTC Date | G186: Change | I186: Close | J186: High | K186: Low | L186: Open | M186: Volume | N186: UTC Date | O186: Change
A187: 630.48 | B187: 632.98 | C187: 629.48 | D187: 630.3 | E187: 5007553 | F187: Fri, 05 Dec 2025 00:00:00 GMT | G187: =A187/D187-1 -> 0.0002855783 | I187: 100.24 | J187: 104.79 | K187: 97.74 | L187: 98.775 | M187: 132389043 | N187: Fri, 05 Dec 2025 00:00:00 GMT | O187: =I187/L187-1 -> 0.014831688
A188: 629.3 | B188: 630.18 | C188: 626.48 | D188: 630.13 | E188: 5114434 | F188: Thu, 04 Dec 2025 00:00:00 GMT | G188: =A188/D188-1 -> -0.0013171885 | I188: 103.22 | J188: 103.8 | K188: 101.77 | L188: 103.57 | M188: 51328769 | N188: Thu, 04 Dec 2025 00:00:00 GMT | O188: =I188/L188-1 -> -0.003379357
A189: 628.77 | B189: 629.78 | C189: 624.95 | D189: 625.77 | E189: 5149531 | F189: Wed, 03 Dec 2025 00:00:00 GMT | G189: =A189/D189-1 -> 0.0047940937 | I189: 103.96 | J189: 106.87 | K189: 102.03 | L189: 106.59 | M189: 52928334 | N189: Wed, 03 Dec 2025 00:00:00 GMT | O189: =I189/L189-1 -> -0.024673984
A190: 626.58 | B190: 628.77 | C190: 624.62 | D190: 627.01 | E190: 5256797 | F190: Tue, 02 Dec 2025 00:00:00 GMT | G190: =A190/D190-1 -> -0.00068579448 | I190: 109.35 | J190: 109.73 | K190: 107.52 | L190: 109.205 | M190: 24894150 | N190: Tue, 02 Dec 2025 00:00:00 GMT | O190: =I190/L190-1 -> 0.001327778
A191: 625.52 | B191: 628.01 | C191: 624.1 | D191: 624.17 | E191: 8381362 | F191: Mon, 01 Dec 2025 00:00:00 GMT | G191: =A191/D191-1 -> 0.0021628723 | I191: 109.13 | J191: 109.335 | K191: 106.31 | L191: 106.51 | M191: 24049038 | N191: Mon, 01 Dec 2025 00:00:00 GMT | O191: =I191/L191-1 -> 0.024598629
A192: 628.41 | B192: 628.63 | C192: 625.705 | D192: 626.025 | E192: 2949167 | F192: Fri, 28 Nov 2025 00:00:00 GMT | G192: =A192/D192-1 -> 0.003809752 | I192: 107.58 | J192: 107.94 | K192: 106.24 | L192: 106.435 | M192: 15011024 | N192: Fri, 28 Nov 2025 00:00:00 GMT | O192: =I192/L192-1 -> 0.010757739
A193: 624.95 | B193: 626.81 | C193: 622.26 | D193: 623.06 | E193: 5292533 | F193: Wed, 26 Nov 2025 00:00:00 GMT | G193: =A193/D193-1 -> 0.0030334157 | I193: 106.14 | J193: 106.95 | K193: 105.22 | L193: 105.74 | M193: 27859165 | N193: Wed, 26 Nov 2025 00:00:00 GMT | O193: =I193/L193-1 -> 0.0037828636
A194: 620.66 | B194: 621.75 | C194: 610.99 | D194: 614.78 | E194: 7289905 | F194: Tue, 25 Nov 2025 00:00:00 GMT | G194: =A194/D194-1 -> 0.009564397 | I194: 104.4 | J194: 106.3 | K194: 103.82 | L194: 106.12 | M194: 34376260 | N194: Tue, 25 Nov 2025 00:00:00 GMT | O194: =I194/L194-1 -> -0.016208066
A195: 614.94 | B195: 616.09 | C195: 608.305 | D195: 609.28 | E195: 6218559 | F195: Mon, 24 Nov 2025 00:00:00 GMT | G195: =A195/D195-1 -> 0.0092896534 | I195: 106.97 | J195: 108.04 | K195: 103.32 | L195: 104.25 | M195: 62152616 | N195: Mon, 24 Nov 2025 00:00:00 GMT | O195: =I195/L195-1 -> 0.026091127
A196: 605.93 | B196: 611.01 | C196: 598.38 | D196: 602.25 | E196: 9789866 | F196: Fri, 21 Nov 2025 00:00:00 GMT | G196: =A196/D196-1 -> 0.0061104193 | I196: 104.31 | J196: 106.53 | K196: 103.81 | L196: 105.13 | M196: 40853314 | N196: Fri, 21 Nov 2025 00:00:00 GMT | O196: =I196/L196-1 -> -0.0077998668
A197: 599.96 | B197: 621.1288 | C197: 599.36 | D197: 618.72 | E197: 13857655 | F197: Thu, 20 Nov 2025 00:00:00 GMT | G197: =A197/D197-1 -> -0.030320662 | I197: 105.67 | J197: 111.1 | K197: 105.39 | L197: 111 | M197: 36618387 | N197: Thu, 20 Nov 2025 00:00:00 GMT | O197: =I197/L197-1 -> -0.048018018
A198: 609.2 | B198: 613.5699 | C198: 605.67 | D198: 607.52 | E198: 7297298 | F198: Wed, 19 Nov 2025 00:00:00 GMT | G198: =A198/D198-1 -> 0.0027653411 | I198: 110 | J198: 113.34 | K198: 108.61 | L198: 113 | M198: 30905213 | N198: Wed, 19 Nov 2025 00:00:00 GMT | O198: =I198/L198-1 -> -0.026548673
A199: 607 | B199: 611.51 | C199: 603 | D199: 608.72 | E199: 8485565 | F199: Tue, 18 Nov 2025 00:00:00 GMT | G199: =A199/D199-1 -> -0.0028256013 | I199: 114.09 | J199: 115.25 | K199: 109.2 | L199: 110.29 | M199: 43257053 | N199: Tue, 18 Nov 2025 00:00:00 GMT | O199: =I199/L199-1 -> 0.03445462 | Q199: Notes: | R199: [X]
A200: 612.04 | B200: 619.4485 | C200: 608.81 | D200: 615.74 | E200: 8858869 | F200: Mon, 17 Nov 2025 00:00:00 GMT | G200: =A200/D200-1 -> -0.0060090298 | I200: 110.29 | J200: 111.85 | K200: 109.55 | L200: 110.75 | M200: 25704297 | N200: Mon, 17 Nov 2025 00:00:00 GMT | O200: =I200/L200-1 -> -0.0041534989 | R200: [Y]
A201: 617.83 | B201: 621.2199 | C201: 609.83 | D201: 611.75 | E201: 9651895 | F201: Fri, 14 Nov 2025 00:00:00 GMT | G201: =A201/D201-1 -> 0.0099387004 | I201: 111.217 | J201: 114.273 | K201: 110.721 | L201: 114.273 | M201: 47202170 | N201: Fri, 14 Nov 2025 00:00:00 GMT | O201: =I201/L201-1 -> -0.026742975 | R201: [Z]
A202: 617.99 | B202: 626.02 | C202: 616.51 | D202: 625.67 | E202: 10526401 | F202: Thu, 13 Nov 2025 00:00:00 GMT | G202: =A202/D202-1 -> -0.012274841 | I202: 115.423 | J202: 116.733 | K202: 114.569 | L202: 115.85 | M202: 39706350 | N202: Thu, 13 Nov 2025 00:00:00 GMT | O202: =I202/L202-1 -> -0.0036858006
A203: 628.22 | B203: 629.77 | C203: 626.1 | D203: 629.65 | E203: 6065826 | F203: Wed, 12 Nov 2025 00:00:00 GMT | G203: =A203/D203-1 -> -0.002271103 | I203: 115.75 | J203: 116.43399 | K203: 112.826 | L203: 113.817 | M203: 39042490 | N203: Wed, 12 Nov 2025 00:00:00 GMT | O203: =I203/L203-1 -> 0.016983403 | R203: Min | S203: =MIN(O181:O1143) -> -0.068479635
A204: 627.91 | B204: 628.49 | C204: 624.07 | D204: 625.16 | E204: 5610874 | F204: Tue, 11 Nov 2025 00:00:00 GMT | G204: =A204/D204-1 -> 0.0043988739 | I204: 113.644 | J204: 113.92199 | K204: 111.28 | L204: 111.76 | M204: 27841570 | N204: Tue, 11 Nov 2025 00:00:00 GMT | O204: =I204/L204-1 -> 0.016857552 | R204: Max | S204: =MAX(O181:O1143) -> 0.10461136
A205: 626.47 | B205: 627.21 | C205: 620.66 | D205: 622.69 | E205: 8383792 | F205: Mon, 10 Nov 2025 00:00:00 GMT | G205: =A205/D205-1 -> 0.0060704363 | I205: 112.007 | J205: 112.82 | K205: 110.405 | L205: 110.6715 | M205: 36807600 | N205: Mon, 10 Nov 2025 00:00:00 GMT | O205: =I205/L205-1 -> 0.012067244 | R205: Mean μ | S205: =AVERAGE(O181:O1143) -> 0.00073773025
A206: 616.89 | B206: 617.02 | C206: 607.92 | D206: 614.09 | E206: 7527198 | F206: Fri, 07 Nov 2025 00:00:00 GMT | G206: =A206/D206-1 -> 0.0045595922 | I206: 110.366 | J206: 110.822 | K206: 108.75 | L206: 109.4175 | M206: 43369520 | N206: Fri, 07 Nov 2025 00:00:00 GMT | O206: =I206/L206-1 -> 0.0086686316 | R206: Median | S206: =MEDIAN(O181:O1143) -> 0.00082876744
A207: 616.24 | B207: 622.79 | C207: 614.82 | D207: 621.96 | E207: 7032116 | F207: Thu, 06 Nov 2025 00:00:00 GMT | G207: =A207/D207-1 -> -0.0091967329 | I207: 109.702 | J207: 110.37 | K207: 108.513 | L207: 109.458 | M207: 36049290 | N207: Thu, 06 Nov 2025 00:00:00 GMT | O207: =I207/L207-1 -> 0.0022291655 | R207: SD σ | S207: =_xlfn.STDEV.P(O181:O1143) -> 0.016965596
A208: 622.86 | B208: 626 | C208: 619.83 | D208: 620.59 | E208: 10264461 | F208: Wed, 05 Nov 2025 00:00:00 GMT | G208: =A208/D208-1 -> 0.0036578095 | I208: 109.846 | J208: 110.085 | K208: 107.33701 | L208: 108.5 | M208: 35381670 | N208: Wed, 05 Nov 2025 00:00:00 GMT | O208: =I208/L208-1 -> 0.01240553 | R208: 3σ 1-Day Δ: ± | S208: =3*S207 -> 0.050896787 | U208: <- Sharpe Ratio (Risk Adjusted Return)
A209: 620.99 | B209: 625.17 | C209: 620.2 | D209: 621.65 | E209: 8203353 | F209: Tue, 04 Nov 2025 00:00:00 GMT | G209: =A209/D209-1 -> -0.0010616907 | I209: 109.296 | J209: 110.45999 | K209: 108.668 | L209: 109.999 | M209: 36968890 | N209: Tue, 04 Nov 2025 00:00:00 GMT | O209: =I209/L209-1 -> -0.0063909672 | R209: β (1-year avg.) | S209: =_xlfn.COVARIANCE.P(O187:O435,G187:G435)/_xlfn.VAR.P(G187:G435) -> 1.0345819 | U209: <- Sortino Ratio (Downside Risk Adjusted Return)
A210: 628.27 | B210: 630.54 | C210: 625.16 | D210: 630.42 | E210: 5510227 | F210: Mon, 03 Nov 2025 00:00:00 GMT | G210: =A210/D210-1 -> -0.0034104248 | I210: 110.009 | J210: 113.35 | K210: 107.515 | L210: 113.324 | M210: 57309570 | N210: Mon, 03 Nov 2025 00:00:00 GMT | O210: =I210/L210-1 -> -0.029252409
A211: 627.04 | B211: 629.94 | C211: 624.5 | D211: 629.84 | E211: 7019277 | F211: Fri, 31 Oct 2025 00:00:00 GMT | G211: =A211/D211-1 -> -0.0044455735 | I211: 111.886 | J211: 113.488 | K211: 110.198 | L211: 110.539 | M211: 66060390 | N211: Fri, 31 Oct 2025 00:00:00 GMT | O211: =I211/L211-1 -> 0.012185744
A212: 625.24 | B212: 630.63 | C212: 625.1 | D212: 628.81 | E212: 6171678 | F212: Thu, 30 Oct 2025 00:00:00 GMT | G212: =A212/D212-1 -> -0.0056773906 | I212: 108.9 | J212: 110.616 | K212: 108.811 | L212: 109.44 | M212: 37919390 | N212: Thu, 30 Oct 2025 00:00:00 GMT | O212: =I212/L212-1 -> -0.0049342105 | Q212: n = | R212: 1014
A213: 631.95 | B213: 634.13 | C213: 627.87 | D213: 633.21 | E213: 6037388 | F213: Wed, 29 Oct 2025 00:00:00 GMT | G213: =A213/D213-1 -> -0.0019898612 | I213: 110.041 | J213: 110.855 | K213: 109.6 | L213: 109.984 | M213: 33242870 | N213: Wed, 29 Oct 2025 00:00:00 GMT | O213: =I213/L213-1 -> 0.0005182572 | Q213: Histogram Data | T213: Distribution Overlay | X213: SD Lines
A214: 631.69 | B214: 633.39 | C214: 629.64 | D214: 631.71 | E214: 5575277 | F214: Tue, 28 Oct 2025 00:00:00 GMT | G214: =A214/D214-1 -> -3.1660097e-05 | I214: 110.25 | J214: 111.69799 | K214: 109.30083 | L214: 109.4 | M214: 40045830 | N214: Tue, 28 Oct 2025 00:00:00 GMT | O214: =I214/L214-1 -> 0.0077696527 | Q214: Bin | R214: Frequency | T214: (X) 1-Day Δ | U214: (Y) Pop. Density | X214: X | Y214: Y
A215: 630 | B215: 630.29 | C215: 627.16 | D215: 627.74 | E215: 7804316 | F215: Mon, 27 Oct 2025 00:00:00 GMT | G215: =A215/D215-1 -> 0.0036002167 | I215: 109.456 | J215: 110.228 | K215: 108.73 | L215: 110.067 | M215: 46911140 | N215: Mon, 27 Oct 2025 00:00:00 GMT | O215: =I215/L215-1 -> -0.0055511643 | Q215: -0.0575 | R215: 1 | T215: =T216-0.0025 -> -0.06 | U215: =_xlfn.NORM.DIST(T215,$S$205,$S$207,FALSE) -> 0.03874474 | W215: Mean | X215: =S205 -> 0.00073773025 | Y215: 0
A216: 622.55 | B216: 623.7899 | C216: 621.207 | D216: 621.92 | E216: 5650844 | F216: Fri, 24 Oct 2025 00:00:00 GMT | G216: =A216/D216-1 -> 0.001012992 | I216: 109.469 | J216: 111.451 | K216: 109.441 | L216: 111.1 | M216: 59818390 | N216: Fri, 24 Oct 2025 00:00:00 GMT | O216: =I216/L216-1 -> -0.014680468 | Q216: -0.055 | R216: 0 | T216: =T217-0.0025 -> -0.0575 | U216: =_xlfn.NORM.DIST(T216,$S$205,$S$207,FALSE) -> 0.064954302 | X216: =S205 -> 0.00073773025 | Y216: 24
A217: 617.44 | B217: 618.474 | C217: 613.99 | D217: 614.25 | E217: 5825360 | F217: Thu, 23 Oct 2025 00:00:00 GMT | G217: =A217/D217-1 -> 0.0051933252 | I217: 111.359 | J217: 112.78285 | K217: 109.973 | L217: 112.69 | M217: 68101860 | N217: Thu, 23 Oct 2025 00:00:00 GMT | O217: =I217/L217-1 -> -0.011811163 | Q217: -0.0525 | R217: 1 | T217: =T218-0.0025 -> -0.055 | U217: =_xlfn.NORM.DIST(T217,$S$205,$S$207,FALSE) -> 0.10655474 | W217: -3σ | X217: =($S$207*-3)+$S$205 -> -0.050159056 | Y217: 0
A218: 613.97 | B218: 617.83 | C218: 609.83 | D218: 617.83 | E218: 6119026 | F218: Wed, 22 Oct 2025 00:00:00 GMT | G218: =A218/D218-1 -> -0.0062476733 | I218: 111.637 | J218: 115.76 | K218: 111.251 | L218: 114.29 | M218: 1.4534328e+08 | N218: Wed, 22 Oct 2025 00:00:00 GMT | O218: =I218/L218-1 -> -0.02321288 | Q218: -0.05 | R218: 0 | T218: =T219-0.0025 -> -0.0525 | U218: =_xlfn.NORM.DIST(T218,$S$205,$S$207,FALSE) -> 0.17104379 | X218: =($S$207*-3)+$S$205 -> -0.050159056 | Y218: 1
A219: 617.09 | B219: 618.74 | C219: 615.981 | D219: 617.33 | E219: 4156131 | F219: Tue, 21 Oct 2025 00:00:00 GMT | G219: =A219/D219-1 -> -0.000388771 | I219: 124.135 | J219: 124.85999 | K219: 123.176 | L219: 124.283 | M219: 55372370 | N219: Tue, 21 Oct 2025 00:00:00 GMT | O219: =I219/L219-1 -> -0.0011908306 | Q219: -0.0475 | R219: 1 | T219: =T220-0.0025 -> -0.05 | U219: =_xlfn.NORM.DIST(T219,$S$205,$S$207,FALSE) -> 0.26866528 | W219: -2σ | X219: =($S$207*-2)+$S$205 -> -0.033193461 | Y219: 0
A220: 617.17 | B220: 618.01 | C220: 613.51 | D220: 613.51 | E220: 4049225 | F220: Mon, 20 Oct 2025 00:00:00 GMT | G220: =A220/D220-1 -> 0.0059656729 | I220: 123.856 | J220: 124.776 | K220: 120.69 | L220: 120.7875 | M220: 38736880 | N220: Mon, 20 Oct 2025 00:00:00 GMT | O220: =I220/L220-1 -> 0.025404119 | Q220: -0.045 | R220: 3 | T220: =T221-0.0025 -> -0.0475 | U220: =_xlfn.NORM.DIST(T220,$S$205,$S$207,FALSE) -> 0.41293858 | X220: =($S$207*-2)+$S$205 -> -0.033193461 | Y220: 4
A221: 610.76 | B221: 612.02 | C221: 605.1 | D221: 606.34 | E221: 6884090 | F221: Fri, 17 Oct 2025 00:00:00 GMT | G221: =A221/D221-1 -> 0.0072896395 | I221: 119.936 | J221: 120.312 | K221: 117.895 | L221: 118.36 | M221: 29145780 | N221: Fri, 17 Oct 2025 00:00:00 GMT | O221: =I221/L221-1 -> 0.013315309 | Q221: -0.0425 | R221: 2 | T221: =T222-0.0025 -> -0.045 | U221: =_xlfn.NORM.DIST(T221,$S$205,$S$207,FALSE) -> 0.62105356 | W221: -1σ | X221: =($S$207*-1)+$S$205 -> -0.016227865 | Y221: 0
A222: 607.39 | B222: 614.8 | C222: 604.14 | D222: 613.11 | E222: 7533209 | F222: Thu, 16 Oct 2025 00:00:00 GMT | G222: =A222/D222-1 -> -0.0093294841 | I222: 118.359 | J222: 121.671 | K222: 117.6 | L222: 121.215 | M222: 28207840 | N222: Thu, 16 Oct 2025 00:00:00 GMT | O222: =I222/L222-1 -> -0.02356144 | Q222: -0.04 | R222: 3 | T222: =T223-0.0025 -> -0.0425 | U222: =_xlfn.NORM.DIST(T222,$S$205,$S$207,FALSE) -> 0.9139919 | X222: =($S$207*-1)+$S$205 -> -0.016227865 | Y222: 15
A223: 611.43 | B223: 616.205 | C223: 605.82 | D223: 613.07 | E223: 6474986 | F223: Wed, 15 Oct 2025 00:00:00 GMT | G223: =A223/D223-1 -> -0.0026750616 | I223: 120.329 | J223: 121.962 | K223: 120.161 | L223: 121.301 | M223: 19650450 | N223: Wed, 15 Oct 2025 00:00:00 GMT | O223: =I223/L223-1 -> -0.0080131244 | Q223: -0.0375 | R223: 3 | T223: =T224-0.0025 -> -0.04 | U223: =_xlfn.NORM.DIST(T223,$S$205,$S$207,FALSE) -> 1.3162104 | W223: 1σ | X223: =($S$207*1)+$S$205 -> 0.017703326 | Y223: 0
A224: 608.75 | B224: 612.14 | C224: 600.51 | D224: 604.2 | E224: 7469018 | F224: Tue, 14 Oct 2025 00:00:00 GMT | G224: =A224/D224-1 -> 0.007530619 | I224: 121.535 | J224: 122.42899 | K224: 120.31 | L224: 121.475 | M224: 23472830 | N224: Tue, 14 Oct 2025 00:00:00 GMT | O224: =I224/L224-1 -> 0.00049392879 | Q224: -0.035 | R224: 2 | T224: =T225-0.0025 -> -0.0375 | U224: =_xlfn.NORM.DIST(T224,$S$205,$S$207,FALSE) -> 1.8547184 | X224: =($S$207*1)+$S$205 -> 0.017703326 | Y224: 15
A225: 609.61 | B225: 611.0272 | C225: 606.575 | D225: 607.37 | E225: 6942460 | F225: Mon, 13 Oct 2025 00:00:00 GMT | G225: =A225/D225-1 -> 0.003688032 | I225: 121.903 | J225: 123.112 | K225: 120.681 | L225: 122.135 | M225: 22905110 | N225: Mon, 13 Oct 2025 00:00:00 GMT | O225: =I225/L225-1 -> -0.0018995374 | Q225: -0.0325 | R225: 5 | T225: =T226-0.0025 -> -0.035 | U225: =_xlfn.NORM.DIST(T225,$S$205,$S$207,FALSE) -> 2.5574099 | W225: 2σ | X225: =($S$207*2)+$S$205 -> 0.034668921 | Y225: 0
A226: 600.51 | B226: 619.6 | C226: 600.23 | D226: 617.99 | E226: 13339202 | F226: Fri, 10 Oct 2025 00:00:00 GMT | G226: =A226/D226-1 -> -0.028285247 | I226: 122.008 | J226: 124.7 | K226: 121.91 | L226: 122.9 | M226: 41158570 | N226: Fri, 10 Oct 2025 00:00:00 GMT | O226: =I226/L226-1 -> -0.0072579333 | Q226: -0.03 | R226: 7 | T226: =T227-0.0025 -> -0.0325 | U226: =_xlfn.NORM.DIST(T226,$S$205,$S$207,FALSE) -> 3.4505822 | X226: =($S$207*2)+$S$205 -> 0.034668921 | Y226: 4
A227: 617.1 | B227: 619.59 | C227: 615.28 | D227: 619.23 | E227: 5879748 | F227: Thu, 09 Oct 2025 00:00:00 GMT | G227: =A227/D227-1 -> -0.0034397558 | I227: 123.107 | J227: 123.75 | K227: 121.182 | L227: 121.425 | M227: 28154240 | N227: Thu, 09 Oct 2025 00:00:00 GMT | O227: =I227/L227-1 -> 0.013852172 | Q227: -0.0275 | R227: 5 | T227: =T228-0.0025 -> -0.03 | U227: =_xlfn.NORM.DIST(T227,$S$205,$S$207,FALSE) -> 4.5556893 | W227: 3σ | X227: =($S$207*3)+$S$205 -> 0.051634517 | Y227: 0
A228: 618.77 | B228: 618.9 | C228: 615.4642 | D228: 616.215 | E228: 5000436 | F228: Wed, 08 Oct 2025 00:00:00 GMT | G228: =A228/D228-1 -> 0.0041462801 | I228: 121.425 | J228: 121.739 | K228: 119.2 | L228: 119.711 | M228: 28425140 | N228: Wed, 08 Oct 2025 00:00:00 GMT | O228: =I228/L228-1 -> 0.014317815 | Q228: -0.025 | R228: 12 | T228: =T229-0.0025 -> -0.0275 | U228: =_xlfn.NORM.DIST(T228,$S$205,$S$207,FALSE) -> 5.885529 | X228: =($S$207*3)+$S$205 -> 0.051634517 | Y228: 1
A229: 615.2 | B229: 618.7393 | C229: 613.82 | D229: 618.3 | E229: 7439508 | F229: Tue, 07 Oct 2025 00:00:00 GMT | G229: =A229/D229-1 -> -0.0050137474 | I229: 119.106 | J229: 120.1365 | K229: 117.746 | L229: 117.779 | M229: 32840040 | N229: Tue, 07 Oct 2025 00:00:00 GMT | O229: =I229/L229-1 -> 0.011266864 | Q229: -0.0225 | R229: 19 | T229: =T230-0.0025 -> -0.025 | U229: =_xlfn.NORM.DIST(T229,$S$205,$S$207,FALSE) -> 7.4402342
A230: 617.4 | B230: 618.28 | C230: 615.48 | D230: 617.46 | E230: 5958193 | F230: Mon, 06 Oct 2025 00:00:00 GMT | G230: =A230/D230-1 -> -9.7172286e-05 | I230: 116.331 | J230: 116.358 | K230: 114.545 | L230: 116.037 | M230: 29190720 | N230: Mon, 06 Oct 2025 00:00:00 GMT | O230: =I230/L230-1 -> 0.0025336746 | Q230: -0.02 | R230: 12 | T230: =T231-0.0025 -> -0.0225 | U230: =_xlfn.NORM.DIST(T230,$S$205,$S$207,FALSE) -> 9.2035926
A231: 615.3 | B231: 618.42 | C231: 614.288 | D231: 615.95 | E231: 7187163 | F231: Fri, 03 Oct 2025 00:00:00 GMT | G231: =A231/D231-1 -> -0.0010552805 | I231: 115.332 | J231: 116.8 | K231: 114.322 | L231: 116.5 | M231: 30555430 | N231: Fri, 03 Oct 2025 00:00:00 GMT | O231: =I231/L231-1 -> -0.010025751 | Q231: -0.0175 | R231: 18 | T231: =T232-0.0025 -> -0.02 | U231: =_xlfn.NORM.DIST(T231,$S$205,$S$207,FALSE) -> 11.140325
A232: 615.25 | B232: 616.48 | C232: 613.02 | D232: 616.41 | E232: 7036646 | F232: Thu, 02 Oct 2025 00:00:00 GMT | G232: =A232/D232-1 -> -0.0018818643 | I232: 116.253 | J232: 116.333 | K232: 113.4 | L232: 116.15 | M232: 46725370 | N232: Thu, 02 Oct 2025 00:00:00 GMT | O232: =I232/L232-1 -> 0.00088678433 | Q232: -0.015 | R232: 22 | T232: =T233-0.0025 -> -0.0175 | U232: =_xlfn.NORM.DIST(T232,$S$205,$S$207,FALSE) -> 13.194958
A233: 614.57 | B233: 615.39 | C233: 609.57 | D233: 609.7 | E233: 9753029 | F233: Wed, 01 Oct 2025 00:00:00 GMT | G233: =A233/D233-1 -> 0.0079875349 | I233: 117.09 | J233: 117.914 | K233: 116.321 | L233: 117.549 | M233: 40935500 | N233: Wed, 01 Oct 2025 00:00:00 GMT | O233: =I233/L233-1 -> -0.0039047546 | Q233: -0.0125 | R233: 29 | T233: =T234-0.0025 -> -0.015 | U233: =_xlfn.NORM.DIST(T233,$S$205,$S$207,FALSE) -> 15.29283
A234: 612.38 | B234: 612.86 | C234: 608.27 | D234: 609.43 | E234: 6481423 | F234: Tue, 30 Sep 2025 00:00:00 GMT | G234: =A234/D234-1 -> 0.0048405887 | I234: 119.892 | J234: 120.85 | K234: 117.8 | L234: 120.641 | M234: 37987060 | N234: Tue, 30 Sep 2025 00:00:00 GMT | O234: =I234/L234-1 -> -0.0062085029 | Q234: -0.01 | R234: 37 | T234: =T235-0.0025 -> -0.0125 | U234: =_xlfn.NORM.DIST(T234,$S$205,$S$207,FALSE) -> 17.343526
A235: 610.13 | B235: 611.68 | C235: 608.48 | D235: 610.79 | E235: 5658835 | F235: Mon, 29 Sep 2025 00:00:00 GMT | G235: =A235/D235-1 -> -0.0010805678 | I235: 120.641 | J235: 122.449 | K235: 118.754 | L235: 120.5 | M235: 30331740 | N235: Mon, 29 Sep 2025 00:00:00 GMT | O235: =I235/L235-1 -> 0.0011701245 | Q235: -0.0075 | R235: 30 | T235: =T236-0.0025 -> -0.01 | U235: =_xlfn.NORM.DIST(T235,$S$205,$S$207,FALSE) -> 19.246715
A236: 610.16 | B236: 610.7 | C236: 606.565 | D236: 608.03 | E236: 6438634 | F236: Fri, 26 Sep 2025 00:00:00 GMT | G236: =A236/D236-1 -> 0.0035031166 | I236: 121.061 | J236: 121.4 | K236: 120 | L236: 120.542 | M236: 19449570 | N236: Fri, 26 Sep 2025 00:00:00 GMT | O236: =I236/L236-1 -> 0.0043055533 | Q236: -0.005 | R236: 41 | T236: =T237-0.0025 -> -0.0075 | U236: =_xlfn.NORM.DIST(T236,$S$205,$S$207,FALSE) -> 20.899963
A237: 606.59 | B237: 607.93 | C237: 603.35 | D237: 606.62 | E237: 6927746 | F237: Thu, 25 Sep 2025 00:00:00 GMT | G237: =A237/D237-1 -> -4.9454354e-05 | I237: 120.824 | J237: 121.684 | K237: 119.151 | L237: 120.309 | M237: 19898220 | N237: Thu, 25 Sep 2025 00:00:00 GMT | O237: =I237/L237-1 -> 0.004280644 | Q237: -0.0025 | R237: 57 | T237: =T238-0.0025 -> -0.005 | U237: =_xlfn.NORM.DIST(T237,$S$205,$S$207,FALSE) -> 22.207727
A238: 609.5 | B238: 612.74 | C238: 608.19 | D238: 612.63 | E238: 23764079 | F238: Wed, 24 Sep 2025 00:00:00 GMT | G238: =A238/D238-1 -> -0.0051091197 | I238: 120.395 | J238: 122.15 | K238: 119.42 | L238: 121.861 | M238: 27366350 | N238: Wed, 24 Sep 2025 00:00:00 GMT | O238: =I238/L238-1 -> -0.0120301 | Q238: 0 | R238: 48 | T238: =T239-0.0025 -> -0.0025 | U238: =_xlfn.NORM.DIST(T238,$S$205,$S$207,FALSE) -> 23.09045
A239: 611.54 | B239: 615.26 | C239: 610.341 | D239: 614.705 | E239: 10728553 | F239: Tue, 23 Sep 2025 00:00:00 GMT | G239: =A239/D239-1 -> -0.0051488112 | I239: 121.847 | J239: 122.779 | K239: 120.847 | L239: 122.733 | M239: 23693530 | N239: Tue, 23 Sep 2025 00:00:00 GMT | O239: =I239/L239-1 -> -0.0072189224 | Q239: 0.0025 | R239: 48 | T239: 0 | U239: =_xlfn.NORM.DIST(T239,$S$205,$S$207,FALSE) -> 23.492561
A240: 614.76 | B240: 615.22 | C240: 610.51 | D240: 610.52 | E240: 11551587 | F240: Mon, 22 Sep 2025 00:00:00 GMT | G240: =A240/D240-1 -> 0.0069448994 | I240: 122.737 | J240: 122.976 | K240: 121.42432 | L240: 122.19 | M240: 25332970 | N240: Mon, 22 Sep 2025 00:00:00 GMT | O240: =I240/L240-1 -> 0.0044766347 | Q240: 0.005 | R240: 53 | T240: =T239+0.0025 -> 0.0025 | U240: =_xlfn.NORM.DIST(T240,$S$205,$S$207,FALSE) -> 23.388266
A241: 611.78 | B241: 612.67 | C241: 608.85 | D241: 610.62 | E241: 6065655 | F241: Fri, 19 Sep 2025 00:00:00 GMT | G241: =A241/D241-1 -> 0.0018997085 | I241: 122.697 | J241: 122.99499 | K241: 120.81 | L241: 121.862 | M241: 49475900 | N241: Fri, 19 Sep 2025 00:00:00 GMT | O241: =I241/L241-1 -> 0.0068520129 | Q241: 0.0075 | R241: 45 | T241: =T240+0.0025 -> 0.005 | U241: =_xlfn.NORM.DIST(T241,$S$205,$S$207,FALSE) -> 22.784283
A242: 608.94 | B242: 611.31 | C242: 607.07 | D242: 608.55 | E242: 11029230 | F242: Thu, 18 Sep 2025 00:00:00 GMT | G242: =A242/D242-1 -> 0.00064086764 | I242: 120.778 | J242: 123.3 | K242: 120.55 | L242: 122.082 | M242: 31232610 | N242: Thu, 18 Sep 2025 00:00:00 GMT | O242: =I242/L242-1 -> -0.010681345 | Q242: 0.01 | R242: 40 | T242: =T241+0.0025 -> 0.0075 | U242: =_xlfn.NORM.DIST(T242,$S$205,$S$207,FALSE) -> 21.719128
A243: 606.09 | B243: 608.33 | C243: 601.55 | D243: 606.84 | E243: 11613628 | F243: Wed, 17 Sep 2025 00:00:00 GMT | G243: =A243/D243-1 -> -0.0012359106 | I243: 122.85 | J243: 123.393 | K243: 120.6605 | L243: 122.102 | M243: 34597960 | N243: Wed, 17 Sep 2025 00:00:00 GMT | O243: =I243/L243-1 -> 0.0061260258 | Q243: 0.0125 | R243: 35 | T243: =T242+0.0025 -> 0.01 | U243: =_xlfn.NORM.DIST(T243,$S$205,$S$207,FALSE) -> 20.259051
A244: 606.79 | B244: 608.42 | C244: 606.0609 | D244: 608.16 | E244: 6367152 | F244: Tue, 16 Sep 2025 00:00:00 GMT | G244: =A244/D244-1 -> -0.0022526967 | I244: 120.051 | J244: 120.89999 | K244: 119.728 | L244: 120.564 | M244: 21513840 | N244: Tue, 16 Sep 2025 00:00:00 GMT | O244: =I244/L244-1 -> -0.0042550015 | Q244: 0.015 | R244: 48 | T244: =T243+0.0025 -> 0.0125 | U244: =_xlfn.NORM.DIST(T244,$S$205,$S$207,FALSE) -> 18.491217
A245: 607.59 | B245: 607.77 | C245: 606.2 | D245: 606.47 | E245: 7447134 | F245: Mon, 15 Sep 2025 00:00:00 GMT | G245: =A245/D245-1 -> 0.0018467525 | I245: 120.226 | J245: 120.724 | K245: 117.32076 | L245: 118.84 | M245: 28638400 | N245: Mon, 15 Sep 2025 00:00:00 GMT | O245: =I245/L245-1 -> 0.01166274 | Q245: 0.0175 | R245: 26 | T245: =T244+0.0025 -> 0.015 | U245: =_xlfn.NORM.DIST(T245,$S$205,$S$207,FALSE) -> 16.515115
A246: 604.44 | B246: 605.98 | C246: 603.95 | D246: 604.59 | E246: 8108692 | F246: Fri, 12 Sep 2025 00:00:00 GMT | G246: =A246/D246-1 -> -0.00024810202 | I246: 118.844 | J246: 121.178 | K246: 118.24 | L246: 120.3055 | M246: 37707550 | N246: Fri, 12 Sep 2025 00:00:00 GMT | O246: =I246/L246-1 -> -0.012148239 | Q246: 0.02 | R246: 24 | T246: =T245+0.0025 -> 0.0175 | U246: =_xlfn.NORM.DIST(T246,$S$205,$S$207,FALSE) -> 14.433358
A247: 604.57 | B247: 605.23 | C247: 600.89 | D247: 601.43 | E247: 9086806 | F247: Thu, 11 Sep 2025 00:00:00 GMT | G247: =A247/D247-1 -> 0.0052208902 | I247: 120.35 | J247: 125.3445 | K247: 119.2 | L247: 125.1 | M247: 56401680 | N247: Thu, 11 Sep 2025 00:00:00 GMT | O247: =I247/L247-1 -> -0.037969624 | Q247: 0.0225 | R247: 20 | T247: =T246+0.0025 -> 0.02 | U247: =_xlfn.NORM.DIST(T247,$S$205,$S$207,FALSE) -> 12.34306
A248: 599.68 | B248: 601.75 | C248: 598.16 | D248: 600.92 | E248: 21542357 | F248: Wed, 10 Sep 2025 00:00:00 GMT | G248: =A248/D248-1 -> -0.0020635026 | I248: 124.771 | J248: 126.7 | K248: 124.6355 | L248: 126.3975 | M248: 25312790 | N248: Wed, 10 Sep 2025 00:00:00 GMT | O248: =I248/L248-1 -> -0.012868134 | Q248: 0.025 | R248: 13 | T248: =T247+0.0025 -> 0.0225 | U248: =_xlfn.NORM.DIST(T248,$S$205,$S$207,FALSE) -> 10.328755
A249: 597.95 | B249: 598.37 | C249: 595.01 | D249: 596.61 | E249: 7780114 | F249: Tue, 09 Sep 2025 00:00:00 GMT | G249: =A249/D249-1 -> 0.0022460234 | I249: 126.325 | J249: 126.5721 | K249: 124.667 | L249: 124.667 | M249: 21707390 | N249: Tue, 09 Sep 2025 00:00:00 GMT | O249: =I249/L249-1 -> 0.01329943 | Q249: 0.0275 | R249: 11 | T249: =T248+0.0025 -> 0.025 | U249: =_xlfn.NORM.DIST(T249,$S$205,$S$207,FALSE) -> 8.4575159
A250: 596.5 | B250: 597.41 | C250: 595.03 | D250: 596.31 | E250: 9448293 | F250: Mon, 08 Sep 2025 00:00:00 GMT | G250: =A250/D250-1 -> 0.00031862622 | I250: 124.476 | J250: 125.20405 | K250: 123.2 | L250: 124.854 | M250: 19060760 | N250: Mon, 08 Sep 2025 00:00:00 GMT | O250: =I250/L250-1 -> -0.0030275362 | Q250: 0.03 | R250: 8 | T250: =T249+0.0025 -> 0.0275 | U250: =_xlfn.NORM.DIST(T250,$S$205,$S$207,FALSE) -> 6.7765297
A251: 594.96 | B251: 599.6 | C251: 591.45 | D251: 598.91 | E251: 6622130 | F251: Fri, 05 Sep 2025 00:00:00 GMT | G251: =A251/D251-1 -> -0.0065953148 | I251: 124.382 | J251: 126.71 | K251: 123.90201 | L251: 126 | M251: 23670580 | N251: Fri, 05 Sep 2025 00:00:00 GMT | O251: =I251/L251-1 -> -0.01284127 | Q251: 0.0325 | R251: 1 | T251: =T250+0.0025 -> 0.03 | U251: =_xlfn.NORM.DIST(T251,$S$205,$S$207,FALSE) -> 5.3130213
... A261: 584.27 | B261: 586.46 | C261: 582.65 | D261: 584.93 | E261: 4807277 | F261: Thu, 21 Aug 2025 00:00:00 GMT | G261: =A261/D261-1 -> -0.0011283401 | I261: 120.621 | J261: 122.13999 | K261: 119.7635 | L261: 121.143 | M261: 20471780 | N261: Thu, 21 Aug 2025 00:00:00 GMT | O261: =I261/L261-1 -> -0.0043089572 | Q261: 0.0575 | R261: 0 | T261: =T260+0.0025 -> 0.055 | U261: =_xlfn.NORM.DIST(T261,$S$205,$S$207,FALSE) -> 0.14125911
A262: 586.58 | B262: 588 | C262: 581.85 | D262: 587.81 | E262: 7054266 | F262: Wed, 20 Aug 2025 00:00:00 GMT | G262: =A262/D262-1 -> -0.0020925129 | I262: 121.386 | J262: 122.29999 | K262: 119.33101 | L262: 121.8 | M262: 23705390 | N262: Wed, 20 Aug 2025 00:00:00 GMT | O262: =I262/L262-1 -> -0.0033990148 | Q262: More | R262: 2 | T262: =T261+0.0025 -> 0.0575 | U262: =_xlfn.NORM.DIST(T262,$S$205,$S$207,FALSE) -> 0.087220228
A263: 588.13 | B263: 592.12 | C263: 586.94 | D263: 591.25 | E263: 6689596 | F263: Tue, 19 Aug 2025 00:00:00 GMT | G263: =A263/D263-1 -> -0.0052769556 | I263: 121.415 | J263: 124.09999 | K263: 119.279 | L263: 124.02 | M263: 36886930 | N263: Tue, 19 Aug 2025 00:00:00 GMT | O263: =I263/L263-1 -> -0.021004677 | T263: =T262+0.0025 -> 0.06 | U263: =_xlfn.NORM.DIST(T263,$S$205,$S$207,FALSE) -> 0.052697216
A264: 591.36 | B264: 592.02 | C264: 590.35 | D264: 590.98 | E264: 5311743 | F264: Mon, 18 Aug 2025 00:00:00 GMT | G264: =A264/D264-1 -> 0.00064299976 | I264: 124.509 | J264: 125.11599 | K264: 123.545 | L264: 123.563 | M264: 21110870 | N264: Mon, 18 Aug 2025 00:00:00 GMT | O264: =I264/L264-1 -> 0.0076560135
A265: 591.57 | B265: 593.95 | C265: 590.66 | D265: 593.86 | E265: 7196315 | F265: Fri, 15 Aug 2025 00:00:00 GMT | G265: =A265/D265-1 -> -0.0038561277 | I265: 123.895 | J265: 124.6941 | K265: 122.788 | L265: 123.404 | M265: 27678040 | N265: Fri, 15 Aug 2025 00:00:00 GMT | O265: =I265/L265-1 -> 0.0039788013
A266: 592.85 | B266: 593.51 | C266: 590.5 | D266: 590.92 | E266: 6236666 | F266: Thu, 14 Aug 2025 00:00:00 GMT | G266: =A266/D266-1 -> 0.0032660935 | I266: 123.056 | J266: 124.409 | K266: 120.703 | L266: 120.989 | M266: 39046680 | N266: Thu, 14 Aug 2025 00:00:00 GMT | O266: =I266/L266-1 -> 0.017084198
A267: 592.84 | B267: 594.03 | C267: 590.81 | D267: 592.86 | E267: 5392973 | F267: Wed, 13 Aug 2025 00:00:00 GMT | G267: =A267/D267-1 -> -3.3734777e-05 | I267: 120.444 | J267: 123.712 | K267: 120.3 | L267: 123.4 | M267: 27623550 | N267: Wed, 13 Aug 2025 00:00:00 GMT | O267: =I267/L267-1 -> -0.023954619
A268: 590.78 | B268: 590.96 | C268: 585.435 | D268: 586.75 | E268: 5874245 | F268: Tue, 12 Aug 2025 00:00:00 GMT | G268: =A268/D268-1 -> 0.0068683426 | I268: 122.528 | J268: 123.199 | K268: 120.6505 | L268: 122.5 | M268: 22826270 | N268: Tue, 12 Aug 2025 00:00:00 GMT | O268: =I268/L268-1 -> 0.00022857143
A269: 584.54 | B269: 587.36 | C269: 583.44 | D269: 586.03 | E269: 5373949 | F269: Mon, 11 Aug 2025 00:00:00 GMT | G269: =A269/D269-1 -> -0.002542532 | I269: 121.831 | J269: 122.307 | K269: 120.193 | L269: 121.401 | M269: 24556480 | N269: Mon, 11 Aug 2025 00:00:00 GMT | O269: =I269/L269-1 -> 0.0035419807
A270: 585.74 | B270: 586.17 | C270: 582.6 | D270: 582.93 | E270: 4342341 | F270: Fri, 08 Aug 2025 00:00:00 GMT | G270: =A270/D270-1 -> 0.0048204759 | I270: 121.164 | J270: 121.411 | K270: 118.03701 | L270: 118.319 | M270: 38166890 | N270: Fri, 08 Aug 2025 00:00:00 GMT | O270: =I270/L270-1 -> 0.024045166
A271: 581.29 | B271: 585.52 | C271: 578.3127 | D271: 584.87 | E271: 4594260 | F271: Thu, 07 Aug 2025 00:00:00 GMT | G271: =A271/D271-1 -> -0.0061210183 | I271: 118.037 | J271: 119.122 | K271: 116.82 | L271: 118.176 | M271: 26283210 | N271: Thu, 07 Aug 2025 00:00:00 GMT | O271: =I271/L271-1 -> -0.0011762118
A272: 581.64 | B272: 582.27 | C272: 577.41 | D272: 578.25 | E272: 4545015 | F272: Wed, 06 Aug 2025 00:00:00 GMT | G272: =A272/D272-1 -> 0.0058625162 | I272: 117.848 | J272: 118.1375 | K272: 115.18701 | L272: 115.352 | M272: 33621610 | N272: Wed, 06 Aug 2025 00:00:00 GMT | O272: =I272/L272-1 -> 0.021638116
...

Sheet Product Lines

Sheet Management

Sheet Table Formatting
B2: [Bold Title] | G2: [Bold Title]
B3: Line Titles | G3: <-- General
B4: Line Titles | G4: <-- Info
B5: Line Titles | G5: <-- General
B6: Line Titles | G6: <-- Info
B7: Line Titles | G7: <-- General
B8: Line Titles | G8: <-- Info
