Workbook

Sheet Main
B2: NOC
B3: Price | C3: 530.4 | D3: 10/21/2026
B4: SO | C4: 142.1 | D4: Q3'26
B5: MC | C5: =C3*C4 -> 75369.84
B6: Cash | C6: 3744 | D6: Q3'26
B7: Debt | C7: 14433 | D7: Q3'26
B8: EV | C8: =C5-C6+C7 -> 86058.84
B10: Northrop Grumman Corporation (NOC)
B12: Founder(s): Merger between Northrop Corp. & Grumman Aircraft Engineering Corp. | F12: Registered Exchange: | N12: Resources:
B13: Founded: Merged April 1994 | F13: Address: | N13: SEC filings | Q13: https://www.sec.gov/edgar/browse/?CIK=1133421&owner=exclude
B14: Headquarters: Falls Church, VA | F14: Investor Relations Contact: | N14: Company Homepage | Q14: https://www.northropgrumman.com/
B15: Current CEO: Kathy Warden | F15: Investors Relation Department | O15: Company IR Page | R15: https://investor.northropgrumman.com/
B16: Employees: 95,000 | F16: Phone: | G16: (703) 280 - 2900 | I16: Email: | N16: Earnings Calls | Q16: https://seekingalpha.com/symbol/NOC/earnings/transcripts
B17: Industry: Industrials | N17: Equity Analysis | Q17: https://stockanalysis.com/stocks/noc/company/
B18: Sector: Aerospace & Defense | N18: MacroTrends | Q18: https://www.macrotrends.net/stocks/charts/NOC/northrop-grumman/financial-statements
B19: IPO: Merged April 1994 | N19: ROIC, WACC | Q19: https://www.gurufocus.com/term/wacc/NOC
B20: Fiscal Year: [January - December] | N20: Godel Terminal | Q20: https://app.godelterminal.com/
A22: Company Overview:
B23: Northrop Grumman Corporation operates as an aerospace and defense technology company in the United States, Asia/Pacific, Europe, and internationally
B24: It operates through four segments: Aeronautics Systems, Defense Systems, Mission Systems and Space Systems …
C25: The Aeronautics Systems segment designs, develops, produces, integrates, sustains, and modernizes aircraft systems.
D26: This segment also offers unmanned autonomous aircraft systems, including high-altitude long-endurance strategic, surveillance and reconnaissance systems; and strategic long-range strike aircraft, tactical fighter and air dominance aircraft, and airborne battle management and command and control systems
E27: B-21 Raider long-range strategic stealth bomber that define sixth-generation technologies
E28: B-2 Spirit strategic stealth bomber
E29: E-130J Phoenix II nuclear command, control and communications (NC3) aircraft
E30: F-35 Lighting II Joint Strike Fighter
E31: F/A-18 Super Hornet
E32: E-2D Advanced Hawkeye AWACS
E33: MQ-4C Triton & RQ-4 Global Hawk (Navy and AF variants) strategic long-range ISR drones
E34: A-10 Warthog
E35: RQ-170 & RQ-180 Stealth ISR UAVs
C36: The Defense Systems segment designs, develops, integrates, and produces strategic deterrent systems, tactical weapons, and missile defense solutions; and provides sustainment, modernization, and training services for manned and unmanned aircraft and electronics systems
D37: This segment also offers strategic missiles; integrated all-domain command and control systems; precision strike weapons; tactical solid rocket motors, and high-speed air-breathing and hypersonic systems; high-performance gun systems, ammunition, precision munitions, and advanced fuzes; and sustainment, operation, and modernization
C38: The Mission Systems segment provides command, control, communication and computer, intelligence, surveillance, and reconnaissance systems; radar, electro-optical/infrared, and acoustic sensors; electronic warfare systems; advanced communications and network systems; microelectronics; navigation and positioning sensors; maritime power, propulsion, and payload launch systems; cyber solutions; and intelligence processing systems
C39: Its Space Systems segment offers satellites, spacecraft systems, subsystems, sensors, and payloads; ground systems; missile defense systems and interceptors; and launch vehicles and related propulsion systems
B40: The Company was founded in 1939 and is based in Falls Church, Virginia
A42: Business Segments and Geographical Info:
B43: [Begin researching fundamentals / core business … begin with SEC filings, but expand and use all public resources available]

Sheet Model
B1: [Use for Graphing] | AE1: Q1 2020 | AI1: Q1 2021 | AM1: Q1 2022 | AQ1: Q1 2023 | AU1: Q1 2024 | AY1: Q1 2025 | BC1: Q1 2026
B2: Quarterly
B3: Revenues | C3: {="Q"&MOD(_xlfn.SEQUENCE(1,56)-1,4)+1&" "&(2013+INT((_xlfn.SEQUENCE(1,56)-1)/4))} -> Q1 2013 | D3: Q2 2013 | E3: Q3 2013 | F3: Q4 2013 | G3: Q1 2014 | H3: Q2 2014 | I3: Q3 2014 | J3: Q4 2014 | K3: Q1 2015 | L3: Q2 2015 | M3: Q3 2015 | N3: Q4 2015 | O3: Q1 2016 | P3: Q2 2016 | Q3: Q3 2016 | R3: Q4 2016 | S3: Q1 2017 | T3: Q2 2017 | U3: Q3 2017 | V3: Q4 2017 | W3: Q1 2018 | X3: Q2 2018 | Y3: Q3 2018 | Z3: Q4 2018 | AA3: Q1 2019 | AB3: Q2 2019 | AC3: Q3 2019 | AD3: Q4 2019 | AE3: Q1 2020 | AF3: Q2 2020 | AG3: Q3 2020 | AH3: Q4 2020 | AI3: Q1 2021 | AJ3: Q2 2021 | AK3: Q3 2021 | AL3: Q4 2021 | AM3: Q1 2022 | AN3: Q2 2022 | AO3: Q3 2022 | AP3: Q4 2022 | AQ3: Q1 2023 | AR3: Q2 2023 | AS3: Q3 2023 | AT3: Q4 2023 | AU3: Q1 2024 | AV3: Q2 2024 | AW3: Q3 2024 | AX3: Q4 2024 | AY3: Q1 2025 | AZ3: Q2 2025 | BA3: Q3 2025 | BB3: Q4 2025 | BC3: Q1 2026 | BD3: Q2 2026 | BE3: Q3 2026 | BF3: Q4 2026 | BM3: 2013 | BN3: =BM3+1 -> 2014 | BO3: =BN3+1 -> 2015 | BP3: =BO3+1 -> 2016 | BQ3: =BP3+1 -> 2017 | BR3: =BQ3+1 -> 2018 | BS3: =BR3+1 -> 2019 | BT3: =BS3+1 -> 2020 | BU3: =BT3+1 -> 2021 | ... EG3: =EF3+1 -> 2085
B4: Aeronautics | AI4: 2990 | AJ4: 2913 | AK4: 2725 | AL4: =11259-SUM(AI4:AK4) -> 2631 | AM4: 2703 | AN4: 2534 | AO4: 2537 | AP4: =10531-SUM(AM4:AO4) -> 2757 | AQ4: 2515 | AR4: 2595 | AS4: 2766 | AT4: =11164-SUM(AQ4:AS4) -> 3288 | AU4: 3044 | AV4: 3060 | AW4: 2961 | AX4: =12396-SUM(AU4:AW4) -> 3331 | AY4: 2814 | AZ4: 3114 | BA4: 3142 | BB4: =12992-SUM(AY4:BA4) -> 3922 | BC4: 3283 | BD4: 3519 | BE4: 3575 | BU4: =SUM(AI4:AL4) -> 11259 | BV4: =SUM(AM4:AP4) -> 10531 | BW4: =SUM(AQ4:AT4) -> 11164 | BX4: =SUM(AU4:AX4) -> 12396 | BY4: =SUM(AY4:BB4) -> 12992 | BZ4: =BY4*(1+BZ11) -> 14810.88 | CA4: =BZ4*(1+CA11) -> 16440.077 | CB4: =CA4*(1+CB11) -> 17426.481 | CC4: =CB4*(1+CC11) -> 17949.276 | CD4: =CC4*(1+CD11) -> 18398.008 | CE4: =CD4*(1+CE11) -> 18811.963 | CF4: =CE4*(1+CF11) -> 19188.202 | CG4: =CF4*(1+CG11) -> 19523.996 | ... CI4: =CH4*(1+CI11) -> 20183.526
B5: Defense | AI5: 1562 | AJ5: 1427 | AK5: 1409 | AL5: =5776-SUM(AI5:AK5) -> 1378 | AM5: 1283 | AN5: 1294 | AO5: 1345 | AP5: =5579-SUM(AM5:AO5) -> 1657 | AQ5: 1376 | AR5: 1420 | AS5: 2050 | AT5: =7185-SUM(AQ5:AS5) -> 2339 | AU5: 1737 | AV5: 1859 | AW5: 1800 | AX5: =7399-SUM(AU5:AW5) -> 2003 | AY5: 1805 | AZ5: 1991 | BA5: 2059 | BB5: =8002-SUM(AY5:BA5) -> 2147 | BC5: 1899 | BD5: 2093 | BE5: 2307 | BU5: =SUM(AI5:AL5) -> 5776 | BV5: =SUM(AM5:AP5) -> 5579 | BW5: =SUM(AQ5:AT5) -> 7185 | BX5: =SUM(AU5:AX5) -> 7399 | BY5: =SUM(AY5:BB5) -> 8002 | BZ5: =BY5*(1+BZ12) -> 8602.15 | CA5: =BZ5*(1+CA12) -> 9032.2575 | CB5: =CA5*(1+CB12) -> 9393.5478 | CC5: =CB5*(1+CC12) -> 9722.322 | CD5: =CC5*(1+CD12) -> 10013.992 | CE5: =CD5*(1+CE12) -> 10289.376 | CF5: =CE5*(1+CF12) -> 10546.611 | CG5: =CF5*(1+CG12) -> 10783.91 | ... CI5: =CH5*(1+CI12) -> 11219.58
B6: Mission Systems | AI6: 2589 | AJ6: 2588 | AK6: 2436 | AL6: =10134-SUM(AI6:AK6) -> 2521 | AM6: 2497 | AN6: 2516 | AO6: 2456 | AP6: =10396-SUM(AM6:AO6) -> 2927 | AQ6: 2563 | AR6: 2641 | AS6: 2628 | AT6: =10895-SUM(AQ6:AS6) -> 3063 | AU6: 2659 | AV6: 2773 | AW6: 2823 | AX6: =11399-SUM(AU6:AW6) -> 3144 | AY6: 2807 | AZ6: 3157 | BA6: 3093 | BB6: =12506-SUM(AY6:BA6) -> 3449 | BC6: 2861 | BD6: 3250 | BE6: 3155 | BU6: =SUM(AI6:AL6) -> 10134 | BV6: =SUM(AM6:AP6) -> 10396 | BW6: =SUM(AQ6:AT6) -> 10895 | BX6: =SUM(AU6:AX6) -> 11399 | BY6: =SUM(AY6:BB6) -> 12506 | BZ6: =BY6*(1+BZ13) -> 12881.18 | CA6: =BZ6*(1+CA13) -> 13254.734 | CB6: =CA6*(1+CB13) -> 13625.867 | CC6: =CB6*(1+CC13) -> 13993.765 | CD6: =CC6*(1+CD13) -> 14357.603 | CE6: =CD6*(1+CE13) -> 14716.543 | CF6: =CE6*(1+CF13) -> 15069.74 | CG6: =CF6*(1+CG13) -> 15416.344 | ... CI6: =CH6*(1+CI13) -> 16086.369
B7: Space Systems | AI7: 2521 | AJ7: 2748 | AK7: 2681 | AL7: =10608-SUM(AI7:AK7) -> 2658 | AM7: 2855 | AN7: 2979 | AO7: 3163 | AP7: =12275-SUM(AM7:AO7) -> 3278 | AQ7: 3350 | AR7: 3488 | AS7: 2953 | AT7: =11873-SUM(AQ7:AS7) -> 2082 | AU7: 3149 | AV7: 3002 | AW7: 2870 | AX7: =11731-SUM(AU7:AW7) -> 2710 | AY7: 2568 | AZ7: 2646 | BA7: 2698 | BB7: =10771-SUM(AY7:BA7) -> 2859 | BC7: 2480 | BD7: 2753 | BE7: 2749 | BU7: =SUM(AI7:AL7) -> 10608 | BV7: =SUM(AM7:AP7) -> 12275 | BW7: =SUM(AQ7:AT7) -> 11873 | BX7: =SUM(AU7:AX7) -> 11731 | BY7: =SUM(AY7:BB7) -> 10771 | BZ7: =BY7*(1+BZ14) -> 10878.71 | CA7: =BZ7*(1+CA14) -> 11205.071 | CB7: =CA7*(1+CB14) -> 11765.325 | CC7: =CB7*(1+CC14) -> 12294.764 | CD7: =CC7*(1+CD14) -> 12786.555 | CE7: =CD7*(1+CE14) -> 13234.084 | CF7: =CE7*(1+CF14) -> 13631.107 | CG7: =CF7*(1+CG14) -> 13971.885 | ... CI7: =CH7*(1+CI14) -> 14465.092
B8: Intersegment Eliminations | AI8: =-44-185-237-39 -> -505 | AJ8: =-45-195-254-31 -> -525 | AK8: =-48-206-244-33 -> -531 | AL8: =-189-789-993-139-SUM(AI8:AK8) -> -549 | AM8: =-65-199-246-31 -> -541 | AN8: =-58-174-259-31 -> -522 | AO8: =-58-194-250-28 -> -530 | AP8: =-239-806-1015-119-SUM(AM8:AO8) -> -586 | AQ8: =-65-169-237-32 -> -503 | AR8: =-64-195-283-26 -> -568 | AS8: =-54-197-263-108 -> -622 | AT8: =-139-151-1054-483-SUM(AQ8:AS8) -> -134 | AU8: =-32-42-277-105 -> -456 | AV8: =-34-45-297-100 -> -476 | AW8: =-33-43-275-107 -> -458 | AX8: =-132-171-1177-412-SUM(AU8:AW8) -> -502 | AY8: =-41-45-335-105 -> -526 | AZ8: =-38-53-341-125 -> -557 | BA8: =-42-51-339-137 -> -569 | BB8: =-167-210-1434-506-SUM(AY8:BA8) -> -665 | BC8: =-34-52-385-171 -> -642 | BD8: =-41-55-464-179 -> -739 | BE8: -664 | BU8: =SUM(AI8:AL8) -> -2110 | BV8: =SUM(AM8:AP8) -> -2179 | BW8: =SUM(AQ8:AT8) -> -1827 | BX8: =SUM(AU8:AX8) -> -1892 | BY8: =SUM(AY8:BB8) -> -2317 | BZ8: =BY8*(1+BZ15) -> -2896.25 | CA8: =BZ8*(1+CA15) -> -2954.175 | CB8: =CA8*(1+CB15) -> -3013.2585 | CC8: =CB8*(1+CC15) -> -3073.5237 | CD8: =CC8*(1+CD15) -> -3134.9941 | CE8: =CD8*(1+CE15) -> -3197.694 | CF8: =CE8*(1+CF15) -> -3261.6479 | CG8: =CF8*(1+CG15) -> -3326.8809 | ... CI8: =CH8*(1+CI15) -> -3461.2869
B9: Ttl Revenues | AI9: =SUM(AI4:AI7)+AI8 -> 9157 | AJ9: =SUM(AJ4:AJ7)+AJ8 -> 9151 | AK9: =SUM(AK4:AK7)+AK8 -> 8720 | AL9: =SUM(AL4:AL7)+AL8 -> 8639 | AM9: =SUM(AM4:AM7)+AM8 -> 8797 | AN9: =SUM(AN4:AN7)+AN8 -> 8801 | AO9: =SUM(AO4:AO7)+AO8 -> 8971 | AP9: =SUM(AP4:AP7)+AP8 -> 10033 | ... BE9: =SUM(BE4:BE7)+BE8 -> 11122 | BU9: =SUM(AI9:AL9) -> 35667 | BV9: =SUM(AM9:AP9) -> 36602 | BW9: =SUM(AQ9:AT9) -> 39290 | BX9: =SUM(AU9:AX9) -> 41033 | BY9: =SUM(AY9:BB9) -> 41954 | BZ9: =SUM(BZ4:BZ8) -> 44276.67 | CA9: =SUM(CA4:CA8) -> 46977.965 | CB9: =SUM(CB4:CB8) -> 49197.962 | CC9: =SUM(CC4:CC8) -> 50886.604 | CD9: =SUM(CD4:CD8) -> 52421.163 | CE9: =SUM(CE4:CE8) -> 53854.273 | CF9: =SUM(CF4:CF8) -> 55174.012 | CG9: =SUM(CG4:CG8) -> 56369.253 | ... CI9: =SUM(CI4:CI8) -> 58493.28
B11: Aeronautics Growth Y/y | AM11: =AM4/AI4-1 -> -0.095986622 | AN11: =AN4/AJ4-1 -> -0.13010642 | AO11: =AO4/AK4-1 -> -0.068990826 | AP11: =AP4/AL4-1 -> 0.047890536 | AQ11: =AQ4/AM4-1 -> -0.069552349 | AR11: =AR4/AN4-1 -> 0.024072612 | AS11: =AS4/AO4-1 -> 0.090264091 | AT11: =AT4/AP4-1 -> 0.19260065 | ... BE11: =BE4/BA4-1 -> 0.13781031 | BV11: =BV4/BU4-1 -> -0.064659384 | BW11: =BW4/BV4-1 -> 0.060108252 | BX11: =BX4/BW4-1 -> 0.11035471 | BY11: =BY4/BX4-1 -> 0.048080026 | BZ11: 0.14 | CA11: 0.11 | CB11: 0.06 | CC11: 0.03 | CD11: 0.025 | CE11: 0.0225 | CF11: 0.02 | CG11: 0.0175 | CH11: 0.017 | CI11: 0.0165
B12: Defense Growth Y/y | AM12: =AM5/AI5-1 -> -0.17861716 | AN12: =AN5/AJ5-1 -> -0.093202523 | AO12: =AO5/AK5-1 -> -0.045422285 | AP12: =AP5/AL5-1 -> 0.20246734 | AQ12: =AQ5/AM5-1 -> 0.07248636 | AR12: =AR5/AN5-1 -> 0.097372488 | AS12: =AS5/AO5-1 -> 0.52416357 | AT12: =AT5/AP5-1 -> 0.41158721 | ... BE12: =BE5/BA5-1 -> 0.12044682 | BV12: =BV5/BU5-1 -> -0.034106648 | BW12: =BW5/BV5-1 -> 0.28786521 | BX12: =BX5/BW5-1 -> 0.029784273 | BY12: =BY5/BX5-1 -> 0.0814975 | BZ12: 0.075 | CA12: 0.05 | CB12: 0.04 | CC12: 0.035 | CD12: 0.03 | CE12: 0.0275 | CF12: 0.025 | CG12: 0.0225 | CH12: 0.02 | CI12: 0.02
B13: Mission Systems Growth Y/y | AM13: =AM6/AI6-1 -> -0.035534956 | AN13: =AN6/AJ6-1 -> -0.027820711 | AO13: =AO6/AK6-1 -> 0.0082101806 | AP13: =AP6/AL6-1 -> 0.1610472 | AQ13: =AQ6/AM6-1 -> 0.026431718 | AR13: =AR6/AN6-1 -> 0.049682035 | AS13: =AS6/AO6-1 -> 0.070032573 | AT13: =AT6/AP6-1 -> 0.046463956 | ... BE13: =BE6/BA6-1 -> 0.020045263 | BV13: =BV6/BU6-1 -> 0.025853562 | BW13: =BW6/BV6-1 -> 0.04799923 | BX13: =BX6/BW6-1 -> 0.046259752 | BY13: =BY6/BX6-1 -> 0.097113782 | BZ13: 0.03 | CA13: 0.029 | CB13: 0.028 | CC13: 0.027 | CD13: 0.026 | CE13: 0.025 | CF13: 0.024 | CG13: 0.023 | CH13: 0.022 | CI13: 0.021
B14: Space Systems Growth Y/y | AM14: =AM7/AI7-1 -> 0.13248711 | AN14: =AN7/AJ7-1 -> 0.084061135 | AO14: =AO7/AK7-1 -> 0.17978366 | AP14: =AP7/AL7-1 -> 0.23325809 | AQ14: =AQ7/AM7-1 -> 0.17338004 | AR14: =AR7/AN7-1 -> 0.17086271 | AS14: =AS7/AO7-1 -> -0.066392665 | AT14: =AT7/AP7-1 -> -0.36485662 | ... BE14: =BE7/BA7-1 -> 0.018902891 | BV14: =BV7/BU7-1 -> 0.15714555 | BW14: =BW7/BV7-1 -> -0.032749491 | BX14: =BX7/BW7-1 -> -0.011959909 | BY14: =BY7/BX7-1 -> -0.081834456 | BZ14: 0.01 | CA14: 0.03 | CB14: 0.05 | CC14: 0.045 | CD14: 0.04 | CE14: 0.035 | CF14: 0.03 | CG14: 0.025 | CH14: 0.02 | CI14: 0.015
B15: Intersegment Eliminations Growth Y/y | AM15: =AM8/AI8-1 -> 0.071287129 | AN15: =AN8/AJ8-1 -> -0.0057142857 | AO15: =AO8/AK8-1 -> -0.0018832392 | AP15: =AP8/AL8-1 -> 0.067395264 | AQ15: =AQ8/AM8-1 -> -0.070240296 | AR15: =AR8/AN8-1 -> 0.088122605 | AS15: =AS8/AO8-1 -> 0.17358491 | AT15: =AT8/AP8-1 -> -0.77133106 | ... BE15: =BE8/BA8-1 -> 0.16695958 | BV15: =BV8/BU8-1 -> 0.032701422 | BW15: =BW8/BV8-1 -> -0.16154199 | BX15: =BX8/BW8-1 -> 0.035577449 | BY15: =BY8/BX8-1 -> 0.22463002 | BZ15: 0.25 | CA15: 0.02 | CB15: 0.02 | CC15: 0.02 | CD15: 0.02 | CE15: 0.02 | CF15: 0.02 | CG15: 0.02 | CH15: 0.02 | CI15: 0.02
B16: Ttl Revenue Growth Y/y | AM16: =AM9/AI9-1 -> -0.039314186 | AN16: =AN9/AJ9-1 -> -0.038247186 | AO16: =AO9/AK9-1 -> 0.028784404 | AP16: =AP9/AL9-1 -> 0.16136127 | AQ16: =AQ9/AM9-1 -> 0.057292259 | AR16: =AR9/AN9-1 -> 0.088058175 | AS16: =AS9/AO9-1 -> 0.089622116 | AT16: =AT9/AP9-1 -> 0.060301007 | ... BE16: =BE9/BA9-1 -> 0.067063226 | BV16: =BV9/BU9-1 -> 0.026214708 | BW16: =BW9/BV9-1 -> 0.07343861 | BX16: =BX9/BW9-1 -> 0.044362433 | BY16: =BY9/BX9-1 -> 0.022445349 | BZ16: =BZ9/BY9-1 -> 0.055362302 | CA16: =CA9/BZ9-1 -> 0.06100944 | CB16: =CB9/CA9-1 -> 0.047256145 | CC16: =CC9/CB9-1 -> 0.034323403 | ... CI16: =CI9/CH9-1 -> 0.017824967
B18: Aeronautics % of Ttl Revenues | AI18: =AI4/AI9 -> 0.32652615 | AJ18: =AJ4/AJ9 -> 0.31832587 | AK18: =AK4/AK9 -> 0.3125 | AL18: =AL4/AL9 -> 0.30454914 | AM18: =AM4/AM9 -> 0.30726384 | AN18: =AN4/AN9 -> 0.28792183 | AO18: =AO4/AO9 -> 0.28280013 | AP18: =AP4/AP9 -> 0.27479318 | ... BE18: =BE4/BE9 -> 0.32143499 | BU18: =BU4/BU9 -> 0.31566995 | BV18: =BV4/BV9 -> 0.28771652 | BW18: =BW4/BW9 -> 0.28414355 | BX18: =BX4/BX9 -> 0.30209831 | BY18: =BY4/BY9 -> 0.3096725
B19: Defense % of Ttl Revenues | AI19: =AI5/AI9 -> 0.17057988 | AJ19: =AJ5/AJ9 -> 0.15593924 | AK19: =AK5/AK9 -> 0.16158257 | AL19: =AL5/AL9 -> 0.1595092 | AM19: =AM5/AM9 -> 0.14584517 | AN19: =AN5/AN9 -> 0.14702875 | AO19: =AO5/AO9 -> 0.14992754 | AP19: =AP5/AP9 -> 0.16515499 | ... BE19: =BE5/BE9 -> 0.20742672 | BU19: =BU5/BU9 -> 0.16194241 | BV19: =BV5/BV9 -> 0.15242336 | BW19: =BW5/BW9 -> 0.18287096 | BX19: =BX5/BX9 -> 0.18031828 | BY19: =BY5/BY9 -> 0.19073271
B20: Mission Systems % of Ttl Revenues | AI20: =AI6/AI9 -> 0.28273452 | AJ20: =AJ6/AJ9 -> 0.28281062 | AK20: =AK6/AK9 -> 0.2793578 | AL20: =AL6/AL9 -> 0.29181618 | AM20: =AM6/AM9 -> 0.28384677 | AN20: =AN6/AN9 -> 0.2858766 | AO20: =AO6/AO9 -> 0.27377104 | AP20: =AP6/AP9 -> 0.29173727 | ... BE20: =BE6/BE9 -> 0.283672 | BU20: =BU6/BU9 -> 0.28412819 | BV20: =BV6/BV9 -> 0.2840282 | BW20: =BW6/BW9 -> 0.27729702 | BX20: =BX6/BX9 -> 0.27780079 | BY20: =BY6/BY9 -> 0.29808838
B21: Space Systems % of Ttl Revenues | AI21: =AI7/AI9 -> 0.27530851 | AJ21: =AJ7/AJ9 -> 0.30029505 | AK21: =AK7/AK9 -> 0.30745413 | AL21: =AL7/AL9 -> 0.3076745 | AM21: =AM7/AM9 -> 0.32454246 | AN21: =AN7/AN9 -> 0.33848426 | AO21: =AO7/AO9 -> 0.35258054 | AP21: =AP7/AP9 -> 0.32672182 | ... BE21: =BE7/BE9 -> 0.24716778 | BU21: =BU7/BU9 -> 0.29741778 | BV21: =BV7/BV9 -> 0.33536419 | BW21: =BW7/BW9 -> 0.30218885 | BX21: =BX7/BX9 -> 0.28589184 | BY21: =BY7/BY9 -> 0.25673357
B22: Intersegment Eliminations % of Revenue | AI22: =AI8/AI9 -> -0.055149066 | AJ22: =AJ8/AJ9 -> -0.057370779 | AK22: =AK8/AK9 -> -0.060894495 | AL22: =AL8/AL9 -> -0.063549022 | AM22: =AM8/AM9 -> -0.061498238 | AN22: =AN8/AN9 -> -0.059311442 | AO22: =AO8/AO9 -> -0.059079255 | AP22: =AP8/AP9 -> -0.058407256 | ... BE22: =BE8/BE9 -> -0.059701493 | BU22: =BU8/BU9 -> -0.059158326 | BV22: =BV8/BV9 -> -0.059532266 | BW22: =BW8/BW9 -> -0.046500382 | BX22: =BX8/BX9 -> -0.046109229 | BY22: =BY8/BY9 -> -0.055227154
B24: U.S. | AI24: 7799 | AJ24: 7943 | AK24: 7535 | AL24: =30685-SUM(AI24:AK24) -> 7408 | AM24: 7656 | AN24: 7646 | AO24: 7761 | AP24: =31754-SUM(AM24:AO24) -> 8691 | AQ24: 8135 | AR24: 8374 | AS24: 8536 | AT24: =34385-SUM(AQ24:AS24) -> 9340 | AU24: 8971 | AV24: 9033 | AW24: 8778 | AX24: =36033-SUM(AU24:AW24) -> 9251 | AY24: 8182 | AZ24: 8950 | BA24: 8820 | BB24: =35964-SUM(AY24:BA24) -> 10012 | BC24: 8600 | BD24: 9333 | BE24: 9639 | BU24: =SUM(AI24:AL24) -> 30685 | BV24: =SUM(AM24:AP24) -> 31754 | BW24: =SUM(AQ24:AT24) -> 34385 | BX24: =SUM(AU24:AX24) -> 36033 | BY24: =SUM(AY24:BB24) -> 35964
B25: APAC | AI25: 558 | AJ25: 441 | AK25: 470 | AL25: =1939-SUM(AI25:AK25) -> 470 | AM25: 463 | AN25: 489 | AO25: 469 | AP25: =1802-SUM(AM25:AO25) -> 381 | AQ25: 376 | AR25: 397 | AS25: 376 | AT25: =1568-SUM(AQ25:AS25) -> 419 | AU25: 359 | AV25: 377 | AW25: 378 | AX25: =1552-SUM(AU25:AW25) -> 438 | AY25: 417 | AZ25: 452 | BA25: 504 | BB25: =1919-SUM(AY25:BA25) -> 546 | BC25: 442 | BD25: 536 | BE25: 483 | BU25: =SUM(AI25:AL25) -> 1939 | BV25: =SUM(AM25:AP25) -> 1802 | BW25: =SUM(AQ25:AT25) -> 1568 | BX25: =SUM(AU25:AX25) -> 1552 | BY25: =SUM(AY25:BB25) -> 1919
B26: Euro | AI26: 533 | AJ26: 537 | AK26: 498 | AL26: =2107-SUM(AI26:AK26) -> 539 | AM26: 503 | AN26: 483 | AO26: 543 | AP26: =2252-SUM(AM26:AO26) -> 723 | AQ26: 547 | AR26: 601 | AS26: 640 | AT26: =2455-SUM(AQ26:AS26) -> 667 | AU26: 676 | AV26: 667 | AW26: 685 | AX26: =2837-SUM(AU26:AW26) -> 809 | AY26: 704 | AZ26: 752 | BA26: 918 | BB26: =3286-SUM(AY26:BA26) -> 912 | BC26: 686 | BD26: 828 | BE26: 810 | BU26: =SUM(AI26:AL26) -> 2107 | BV26: =SUM(AM26:AP26) -> 2252 | BW26: =SUM(AQ26:AT26) -> 2455 | BX26: =SUM(AU26:AX26) -> 2837 | BY26: =SUM(AY26:BB26) -> 3286
B27: Other regions | AI27: 267 | AJ27: 230 | AK27: 217 | AL27: =936-SUM(AI27:AK27) -> 222 | AM27: 175 | AN27: 183 | AO27: 198 | AP27: =794-SUM(AM27:AO27) -> 238 | AQ27: 243 | AR27: 204 | AS27: 223 | AT27: =882-SUM(AQ27:AS27) -> 212 | AU27: 127 | AV27: 141 | AW27: 155 | AX27: =611-SUM(AU27:AW27) -> 188 | AY27: 165 | AZ27: 197 | BA27: 181 | BB27: =785-SUM(AY27:BA27) -> 242 | BC27: 153 | BD27: 179 | BE27: 190 | BU27: =SUM(AI27:AL27) -> 936 | BV27: =SUM(AM27:AP27) -> 794 | BW27: =SUM(AQ27:AT27) -> 882 | BX27: =SUM(AU27:AX27) -> 611 | BY27: =SUM(AY27:BB27) -> 785
B28: Ttl Revenues | AI28: =SUM(AI24:AI27) -> 9157 | AJ28: =SUM(AJ24:AJ27) -> 9151 | AK28: =SUM(AK24:AK27) -> 8720 | AL28: =SUM(AL24:AL27) -> 8639 | AM28: =SUM(AM24:AM27) -> 8797 | AN28: =SUM(AN24:AN27) -> 8801 | AO28: =SUM(AO24:AO27) -> 8971 | AP28: =SUM(AP24:AP27) -> 10033 | ... BE28: =SUM(BE24:BE27) -> 11122 | BU28: =SUM(AI28:AL28) -> 35667 | BV28: =SUM(AM28:AP28) -> 36602 | BW28: =SUM(AQ28:AT28) -> 39290 | BX28: =SUM(AU28:AX28) -> 41033 | BY28: =SUM(AY28:BB28) -> 41954
B30: U.S. Growth Y/y | AM30: =AM24/AI24-1 -> -0.018335684 | AN30: =AN24/AJ24-1 -> -0.037391414 | AO30: =AO24/AK24-1 -> 0.029993364 | AP30: =AP24/AL24-1 -> 0.17319114 | AQ30: =AQ24/AM24-1 -> 0.062565308 | AR30: =AR24/AN24-1 -> 0.095213183 | AS30: =AS24/AO24-1 -> 0.099858266 | AT30: =AT24/AP24-1 -> 0.074674951 | ... BE30: =BE24/BA24-1 -> 0.092857143 | BV30: =BV24/BU24-1 -> 0.034837869 | BW30: =BW24/BV24-1 -> 0.082855703 | BX30: =BX24/BW24-1 -> 0.047927876 | BY30: =BY24/BX24-1 -> -0.0019149113
B31: APAC Growth Y/y | AM31: =AM25/AI25-1 -> -0.1702509 | AN31: =AN25/AJ25-1 -> 0.10884354 | AO31: =AO25/AK25-1 -> -0.0021276596 | AP31: =AP25/AL25-1 -> -0.1893617 | AQ31: =AQ25/AM25-1 -> -0.18790497 | AR31: =AR25/AN25-1 -> -0.18813906 | AS31: =AS25/AO25-1 -> -0.19829424 | AT31: =AT25/AP25-1 -> 0.099737533 | ... BE31: =BE25/BA25-1 -> -0.041666667 | BV31: =BV25/BU25-1 -> -0.070654977 | BW31: =BW25/BV25-1 -> -0.12985572 | BX31: =BX25/BW25-1 -> -0.010204082 | BY31: =BY25/BX25-1 -> 0.23646907
B32: Euro Growth Y/y | AM32: =AM26/AI26-1 -> -0.056285178 | AN32: =AN26/AJ26-1 -> -0.10055866 | AO32: =AO26/AK26-1 -> 0.090361446 | AP32: =AP26/AL26-1 -> 0.34137291 | AQ32: =AQ26/AM26-1 -> 0.087475149 | AR32: =AR26/AN26-1 -> 0.24430642 | AS32: =AS26/AO26-1 -> 0.1786372 | AT32: =AT26/AP26-1 -> -0.077455048 | ... BE32: =BE26/BA26-1 -> -0.11764706 | BV32: =BV26/BU26-1 -> 0.068818225 | BW32: =BW26/BV26-1 -> 0.090142096 | BX32: =BX26/BW26-1 -> 0.15560081 | BY32: =BY26/BX26-1 -> 0.15826577
B33: Other Revenue Growth Y/y | AM33: =AM27/AI27-1 -> -0.34456929 | AN33: =AN27/AJ27-1 -> -0.20434783 | AO33: =AO27/AK27-1 -> -0.087557604 | AP33: =AP27/AL27-1 -> 0.072072072 | AQ33: =AQ27/AM27-1 -> 0.38857143 | AR33: =AR27/AN27-1 -> 0.1147541 | AS33: =AS27/AO27-1 -> 0.12626263 | AT33: =AT27/AP27-1 -> -0.1092437 | ... BE33: =BE27/BA27-1 -> 0.049723757 | BV33: =BV27/BU27-1 -> -0.1517094 | BW33: =BW27/BV27-1 -> 0.11083123 | BX33: =BX27/BW27-1 -> -0.30725624 | BY33: =BY27/BX27-1 -> 0.28477905
B34: Ttl Revenue Growth Y/y | AM34: =AM28/AI28-1 -> -0.039314186 | AN34: =AN28/AJ28-1 -> -0.038247186 | AO34: =AO28/AK28-1 -> 0.028784404 | AP34: =AP28/AL28-1 -> 0.16136127 | AQ34: =AQ28/AM28-1 -> 0.057292259 | AR34: =AR28/AN28-1 -> 0.088058175 | AS34: =AS28/AO28-1 -> 0.089622116 | AT34: =AT28/AP28-1 -> 0.060301007 | ... BE34: =BE28/BA28-1 -> 0.067063226 | BV34: =BV28/BU28-1 -> 0.026214708 | BW34: =BW28/BV28-1 -> 0.07343861 | BX34: =BX28/BW28-1 -> 0.044362433 | BY34: =BY28/BX28-1 -> 0.022445349
B36: U.S. % of Revenues | AI36: =AI24/AI28 -> 0.85169815 | AJ36: =AJ24/AJ28 -> 0.86799257 | AK36: =AK24/AK28 -> 0.8641055 | AL36: =AL24/AL28 -> 0.85750666 | AM36: =AM24/AM28 -> 0.87029669 | AN36: =AN24/AN28 -> 0.86876491 | AO36: =AO24/AO28 -> 0.86512095 | AP36: =AP24/AP28 -> 0.8662414 | ... BE36: =BE24/BE28 -> 0.86666067 | BU36: =BU24/BU28 -> 0.86031906 | BV36: =BV24/BV28 -> 0.86754822 | BW36: =BW24/BW28 -> 0.87515907 | BX36: =BX24/BX28 -> 0.87814686 | BY36: =BY24/BY28 -> 0.85722458
B37: APAC % of Revenues | AI37: =AI25/AI28 -> 0.060936988 | AJ37: =AJ25/AJ28 -> 0.048191454 | AK37: =AK25/AK28 -> 0.053899083 | AL37: =AL25/AL28 -> 0.054404445 | AM37: =AM25/AM28 -> 0.052631579 | AN37: =AN25/AN28 -> 0.055561868 | AO37: =AO25/AO28 -> 0.052279567 | AP37: =AP25/AP28 -> 0.037974684 | ... BE37: =BE25/BE28 -> 0.043427441 | BU37: =BU25/BU28 -> 0.054363978 | BV37: =BV25/BV28 -> 0.049232282 | BW37: =BW25/BW28 -> 0.039908374 | BX37: =BX25/BX28 -> 0.037823215 | BY37: =BY25/BY28 -> 0.045740573
B38: Euro % of Revenues | AI38: =AI26/AI28 -> 0.058206836 | AJ38: =AJ26/AJ28 -> 0.058682111 | AK38: =AK26/AK28 -> 0.057110092 | AL38: =AL26/AL28 -> 0.06239148 | AM38: =AM26/AM28 -> 0.057178584 | AN38: =AN26/AN28 -> 0.054880127 | AO38: =AO26/AO28 -> 0.060528369 | AP38: =AP26/AP28 -> 0.072062195 | ... BE38: =BE26/BE28 -> 0.072828628 | BU38: =BU26/BU28 -> 0.059074214 | BV38: =BV26/BV28 -> 0.061526693 | BW38: =BW26/BW28 -> 0.062484093 | BX38: =BX26/BX28 -> 0.069139473 | BY38: =BY26/BY28 -> 0.078323879
B39: Other regions % of Revenues | AI39: =AI27/AI28 -> 0.029158021 | AJ39: =AJ27/AJ28 -> 0.025133865 | AK39: =AK27/AK28 -> 0.024885321 | AL39: =AL27/AL28 -> 0.025697419 | AM39: =AM27/AM28 -> 0.019893145 | AN39: =AN27/AN28 -> 0.020793092 | AO39: =AO27/AO28 -> 0.022071118 | AP39: =AP27/AP28 -> 0.023721718 | ... BE39: =BE27/BE28 -> 0.017083258 | BU39: =BU27/BU28 -> 0.026242745 | BV39: =BV27/BV28 -> 0.021692804 | BW39: =BW27/BW28 -> 0.02244846 | BX39: =BX27/BX28 -> 0.014890454 | BY39: =BY27/BY28 -> 0.018710969
B41: Revenues | C41: 6104 | D41: 6294 | E41: 6106 | F41: 6157 | G41: 5848 | H41: 6039 | I41: 5984 | J41: 6108 | K41: 5957 | L41: 5896 | M41: 5979 | N41: 5694 | O41: 5956 | P41: 6000 | Q41: 6155 | R41: 6595 | S41: 6410 | T41: 6473 | U41: 6569 | V41: 6552 | W41: 6735 | X41: 7119 | Y41: 8085 | Z41: 8156 | AA41: 8189 | AB41: 8456 | AC41: 8475 | AD41: 8721 | AE41: 8620 | AF41: 8884 | AG41: 9083 | AH41: 10212 | AI41: 9157 | AJ41: 9151 | AK41: 8720 | AL41: 8639 | AM41: 8797 | AN41: 8801 | AO41: 8971 | AP41: 10033 | AQ41: =AQ9 -> 9301 | AR41: =AR9 -> 9576 | AS41: =AS9 -> 9775 | AT41: =AT9 -> 10638 | AU41: =AU9 -> 10133 | AV41: =AV9 -> 10218 | AW41: =AW9 -> 9996 | AX41: =AX9 -> 10686 | ... BE41: =BE9 -> 11122 | BM41: =SUM(C41:F41) -> 24661 | BN41: =SUM(G41:J41) -> 23979 | BO41: =SUM(K41:N41) -> 23526 | BP41: =SUM(O41:R41) -> 24706 | BQ41: =SUM(S41:V41) -> 26004 | BR41: =SUM(W41:Z41) -> 30095 | BS41: =SUM(AA41:AD41) -> 33841 | BT41: =SUM(AE41:AH41) -> 36799 | BU41: =SUM(AI41:AL41) -> 35667 | BV41: =SUM(AM41:AP41) -> 36602 | BW41: =SUM(AQ41:AT41) -> 39290 | BX41: =SUM(AU41:AX41) -> 41033 | BY41: =SUM(AY41:BB41) -> 41954 | BZ41: =BZ9 -> 44276.67 | CA41: =CA9 -> 46977.965 | CB41: =CB9 -> 49197.962 | CC41: =CC9 -> 50886.604 | CD41: =CD9 -> 52421.163 | CE41: =CE9 -> 53854.273 | CF41: =CF9 -> 55174.012 | CG41: =CG9 -> 56369.253 | ... CI41: =CI9 -> 58493.28
B42: COGS | C42: 4787 | D42: 4906 | E42: 4761 | F42: 4828 | G42: 4461 | H42: 4629 | I42: 4635 | J42: 4653 | K42: 4542 | L42: 4442 | M42: 4522 | N42: 4378 | O42: 4561 | P42: 4583 | Q42: 4667 | R42: 4986 | S42: 4850 | T42: 4914 | U42: 5053 | V42: 5257 | W42: 5176 | X42: 5563 | Y42: 6096 | Z42: 6469 | AA42: 6493 | AB42: 6726 | AC42: 6748 | AD42: 6615 | AE42: 6898 | AF42: 7058 | AG42: 7243 | AH42: 8122 | AI42: 7417 | AJ42: 7108 | AK42: 6786 | AL42: 7088 | AM42: 6924 | AN42: 6842 | AO42: 7153 | AP42: 8209 | AQ42: =5727+1589 -> 7316 | AR42: =5876+1660 -> 7536 | AS42: =6135+1599 -> 7734 | AT42: =26226+6513-SUM(AQ42:AS42) -> 10153 | AU42: =6411+1589 -> 8000 | AV42: =6388+1639 -> 8027 | AW42: =6280+1610 -> 7890 | AX42: =26188+6483-SUM(AU42:AW42) -> 8754 | AY42: =6366+1522 -> 7888 | AZ42: =6526+1615 -> 8141 | BA42: =6631+1565 -> 8196 | BB42: =27280+6361-SUM(AY42:BA42) -> 9416 | BC42: =6433+1488 -> 7921 | BD42: =7155+1600 -> 8755 | BE42: =7198+1572 -> 8770 | BM42: =SUM(C42:F42) -> 19282 | BN42: =SUM(G42:J42) -> 18378 | BO42: =SUM(K42:N42) -> 17884 | BP42: =SUM(O42:R42) -> 18797 | BQ42: =SUM(S42:V42) -> 20074 | BR42: =SUM(W42:Z42) -> 23304 | BS42: =SUM(AA42:AD42) -> 26582 | BT42: =SUM(AE42:AH42) -> 29321 | BU42: =SUM(AI42:AL42) -> 28399 | BV42: =SUM(AM42:AP42) -> 29128 | BW42: =SUM(AQ42:AT42) -> 32739 | BX42: =SUM(AU42:AX42) -> 32671 | BY42: =SUM(AY42:BB42) -> 33641 | BZ42: =BZ41*(1-BZ55) -> 35503.443 | CA42: =CA41*(1-CA55) -> 37347.482 | CB42: =CB41*(1-CB55) -> 38866.39 | CC42: =CC41*(1-CC55) -> 39945.984 | CD42: =CD41*(1-CD55) -> 40888.507 | CE42: =CE41*(1-CE55) -> 41952.479 | CF42: =CF41*(1-CF55) -> 42925.382 | CG42: =CG41*(1-CG55) -> 43798.91 | ... CI42: =CI41*(1-CI55) -> 45332.292
B43: GP | C43: =C41-C42 -> 1317 | D43: =D41-D42 -> 1388 | E43: =E41-E42 -> 1345 | F43: =F41-F42 -> 1329 | G43: =G41-G42 -> 1387 | H43: =H41-H42 -> 1410 | I43: =I41-I42 -> 1349 | J43: =J41-J42 -> 1455 | ... BE43: =BE41-BE42 -> 2352 | BM43: =SUM(C43:F43) -> 5379 | BN43: =SUM(G43:J43) -> 5601 | BO43: =SUM(K43:N43) -> 5642 | BP43: =SUM(O43:R43) -> 5909 | BQ43: =SUM(S43:V43) -> 5930 | BR43: =SUM(W43:Z43) -> 6791 | BS43: =SUM(AA43:AD43) -> 7259 | BT43: =SUM(AE43:AH43) -> 7478 | BU43: =SUM(AI43:AL43) -> 7268 | BV43: =SUM(AM43:AP43) -> 7474 | BW43: =SUM(AQ43:AT43) -> 6551 | BX43: =SUM(AU43:AX43) -> 8362 | BY43: =SUM(AY43:BB43) -> 8313 | BZ43: =BZ41-BZ42 -> 8773.2268 | CA43: =CA41-CA42 -> 9630.4828 | CB43: =CB41-CB42 -> 10331.572 | CC43: =CC41-CC42 -> 10940.62 | CD43: =CD41-CD42 -> 11532.656 | CE43: =CE41-CE42 -> 11901.794 | CF43: =CF41-CF42 -> 12248.631 | CG43: =CG41-CG42 -> 12570.343 | ... CI43: =CI41-CI42 -> 13160.988
B44: G&A | C44: 558 | D44: 582 | E44: 555 | F44: 561 | G44: 542 | H44: 590 | I44: 580 | J44: 693 | K44: 635 | L44: 641 | M44: 663 | N44: 627 | O44: 656 | P44: 620 | Q44: 662 | R44: 694 | S44: 698 | T44: 686 | U44: 679 | V44: 649 | W44: 711 | X44: 739 | Y44: 817 | Z44: 744 | AA44: 760 | AB44: 784 | AC44: 776 | AD44: 970 | AE44: 788 | AF44: 832 | AG44: 855 | AH44: 938 | AI44: 898 | AJ44: 999 | AK44: 891 | AL44: 809 | AM44: 976 | AN44: 1005 | AO44: 974 | AP44: 918 | AQ44: 1038 | AR44: 1073 | AS44: 1025 | AT44: =4014-SUM(AQ44:AS44) -> 878 | AU44: 1062 | AV44: 1101 | AW44: 986 | AX44: =3992-SUM(AU44:AW44) -> 843 | AY44: 1007 | AZ44: 1016 | BA44: 985 | BB44: =4033-SUM(AY44:BA44) -> 1025 | BC44: 971 | BD44: 1025 | BE44: 1083 | BM44: =SUM(C44:F44) -> 2256 | BN44: =SUM(G44:J44) -> 2405 | BO44: =SUM(K44:N44) -> 2566 | BP44: =SUM(O44:R44) -> 2632 | BQ44: =SUM(S44:V44) -> 2712 | BR44: =SUM(W44:Z44) -> 3011 | BS44: =SUM(AA44:AD44) -> 3290 | BT44: =SUM(AE44:AH44) -> 3413 | BU44: =SUM(AI44:AL44) -> 3597 | BV44: =SUM(AM44:AP44) -> 3873 | BW44: =SUM(AQ44:AT44) -> 4014 | BX44: =SUM(AU44:AX44) -> 3992 | BY44: =SUM(AY44:BB44) -> 4033 | BZ44: =BZ41*BZ56 -> 4256.2762 | CA44: =CA41*CA56 -> 4515.9492 | CB44: =CB41*CB56 -> 4729.3555 | CC44: =CC41*CC56 -> 4891.6831 | CD44: =CD41*CD56 -> 5039.1989 | CE44: =CE41*CE56 -> 5176.9625 | CF44: =CF41*CF56 -> 5303.8278 | CG44: =CG41*CG56 -> 5418.7252 | ... CI44: =CI41*CI56 -> 5622.906
B45: OI | C45: =C43-C44 -> 759 | D45: =D43-D44 -> 806 | E45: =E43-E44 -> 790 | F45: =F43-F44 -> 768 | G45: =G43-G44 -> 845 | H45: =H43-H44 -> 820 | I45: =I43-I44 -> 769 | J45: =J43-J44 -> 762 | ... AY45: =AY43-AY44 -> 573 | AZ45: =AZ43-AZ44+231 -> 1425 | BA45: =BA43-BA44 -> 1242 | BB45: =BB43-BB44 -> 1271 | BC45: =BC43-BC44 -> 989 | BD45: =BD43-BD44 -> 1096 | BE45: =BE43-BE44 -> 1269 | BM45: =SUM(C45:F45) -> 3123 | BN45: =SUM(G45:J45) -> 3196 | BO45: =SUM(K45:N45) -> 3076 | BP45: =SUM(O45:R45) -> 3277 | BQ45: =SUM(S45:V45) -> 3218 | BR45: =SUM(W45:Z45) -> 3780 | BS45: =SUM(AA45:AD45) -> 3969 | BT45: =SUM(AE45:AH45) -> 4065 | BU45: =SUM(AI45:AL45) -> 3671 | BV45: =SUM(AM45:AP45) -> 3601 | BW45: =SUM(AQ45:AT45) -> 2537 | BX45: =SUM(AU45:AX45) -> 4370 | BY45: =SUM(AY45:BB45) -> 4511 | BZ45: =BZ43-BZ44 -> 4516.9507 | CA45: =CA43-CA44 -> 5114.5336 | CB45: =CB43-CB44 -> 5602.2166 | CC45: =CC43-CC44 -> 6048.9367 | CD45: =CD43-CD44 -> 6493.457 | CE45: =CE43-CE44 -> 6724.8319 | CF45: =CF43-CF44 -> 6944.8029 | CG45: =CG43-CG44 -> 7151.6183 | ... CI45: =CI43-CI44 -> 7538.082
B46: Interest Expenses | C46: 0 | D46: 0 | E46: 0 | F46: 0 | G46: 0 | H46: 0 | I46: 0 | J46: 0 | K46: 0 | L46: 0 | M46: 0 | N46: 0 | O46: 0 | P46: 0 | Q46: 0 | R46: 0 | S46: 0 | T46: 0 | U46: 0 | V46: 0 | W46: 0 | X46: 0 | Y46: 0 | Z46: 0 | AA46: 0 | AB46: 0 | AC46: 0 | AD46: 0 | AE46: 0 | AF46: 0 | AG46: 0 | AH46: 0 | AI46: 0 | AJ46: 0 | AK46: 0 | AL46: 0 | AM46: 0 | AN46: 0 | AO46: 0 | AP46: 0 | AQ46: -129 | AR46: -147 | AS46: -141 | AT46: =-545-SUM(AQ46:AS46) -> -128 | AU46: -146 | AV46: -154 | AW46: -161 | AX46: =-621-SUM(AU46:AW46) -> -160 | AY46: -156 | AZ46: -173 | BA46: -161 | BB46: =-665-SUM(AY46:BA46) -> -175 | BC46: -162 | BD46: -161 | BE46: -158 | BM46: =SUM(C46:F46) -> 0 | BN46: =SUM(G46:J46) -> 0 | BO46: =SUM(K46:N46) -> 0 | BP46: =SUM(O46:R46) -> 0 | BQ46: =SUM(S46:V46) -> 0 | BR46: =SUM(W46:Z46) -> 0 | BS46: =SUM(AA46:AD46) -> 0 | BT46: =SUM(AE46:AH46) -> 0 | BU46: =SUM(AI46:AL46) -> 0 | BV46: =SUM(AM46:AP46) -> 0 | BW46: =SUM(AQ46:AT46) -> -545 | BX46: =SUM(AU46:AX46) -> -621 | BY46: =SUM(AY46:BB46) -> -665 | BZ46: =(-BY78)*$CN$78 -> -637.515 | CA46: =(-BZ78)*$CN$78 -> -608.82682 | CB46: =(-CA78)*$CN$78 -> -581.42962 | CC46: =(-CB78)*$CN$78 -> -555.26529 | CD46: =(-CC78)*$CN$78 -> -530.27835 | CE46: =(-CD78)*$CN$78 -> -506.41582 | CF46: =(-CE78)*$CN$78 -> -483.62711 | CG46: =(-CF78)*$CN$78 -> -461.86389 | ... CI46: =(-CH78)*$CN$78 -> -421.23141
B47: FAS Pension Benefit | C47: 0 | D47: 0 | E47: 0 | F47: 0 | G47: 0 | H47: 0 | I47: 0 | J47: 0 | K47: 0 | L47: 0 | M47: 0 | N47: 0 | O47: 0 | P47: 0 | Q47: 0 | R47: 0 | S47: 0 | T47: 0 | U47: 0 | V47: 0 | W47: 0 | X47: 0 | Y47: 0 | Z47: 0 | AA47: 0 | AB47: 0 | AC47: 0 | AD47: 0 | AE47: 0 | AF47: 0 | AG47: 0 | AH47: 0 | AI47: 0 | AJ47: 0 | AK47: 0 | AL47: 0 | AM47: 0 | AN47: 0 | AO47: 0 | AP47: 0 | AQ47: 132 | AR47: 133 | AS47: 132 | AT47: =530-SUM(AQ47:AS47) -> 133 | AU47: 168 | AV47: 167 | AW47: 168 | AX47: =656-SUM(AU47:AW47) -> 153 | AY47: 130 | AZ47: 137 | BA47: 136 | BB47: =541-SUM(AY47:BA47) -> 138 | BC47: 166 | BD47: 166 | BE47: 167 | BM47: =SUM(C47:F47) -> 0 | BN47: =SUM(G47:J47) -> 0 | BO47: =SUM(K47:N47) -> 0 | BP47: =SUM(O47:R47) -> 0 | BQ47: =SUM(S47:V47) -> 0 | BR47: =SUM(W47:Z47) -> 0 | BS47: =SUM(AA47:AD47) -> 0 | BT47: =SUM(AE47:AH47) -> 0 | BU47: =SUM(AI47:AL47) -> 0 | BV47: =SUM(AM47:AP47) -> 0 | BW47: =SUM(AQ47:AT47) -> 530 | BX47: =SUM(AU47:AX47) -> 656 | BY47: =SUM(AY47:BB47) -> 541 | BZ47: 0 | CA47: 0 | CB47: 0 | CC47: 0 | CD47: 0 | CE47: 0 | CF47: 0 | CG47: 0 | CH47: 0 | CI47: 0
B48: Other Income | C48: -47 | D48: -82 | E48: -70 | F48: -61 | G48: -59 | H48: -64 | I48: -75 | J48: -61 | K48: -76 | L48: -77 | M48: -65 | N48: -68 | O48: -63 | P48: -67 | Q48: -57 | R48: -409 | S48: -74 | T48: -61 | U48: -55 | V48: 1201 | W48: 151 | X48: 159 | Y48: 192 | Z48: -540 | AA48: 98 | AB48: 82 | AC48: 104 | AD48: -1705 | AE48: 119 | AF48: 209 | AG48: 182 | AH48: -847 | AI48: 212 | AJ48: 258 | AK48: 232 | AL48: 2566 | AM48: 247 | AN48: 196 | AO48: 246 | AP48: 1546 | AQ48: 48 | AR48: 34 | AS48: 111 | AT48: =-422+246-SUM(AQ48:AS48) -> -369 | AU48: 38 | AV48: 43 | AW48: 61 | AX48: =443+168-SUM(AU48:AW48) -> 469 | AY48: 31 | AZ48: 38 | BA48: 106 | BB48: =527+154-SUM(AY48:BA48) -> 506 | BC48: 37 | BD48: 67 | BE48: 20 | BM48: =SUM(C48:F48) -> -260 | BN48: =SUM(G48:J48) -> -259 | BO48: =SUM(K48:N48) -> -286 | BP48: =SUM(O48:R48) -> -596 | BQ48: =SUM(S48:V48) -> 1011 | BR48: =SUM(W48:Z48) -> -38 | BS48: =SUM(AA48:AD48) -> -1421 | BT48: =SUM(AE48:AH48) -> -337 | BU48: =SUM(AI48:AL48) -> 3268 | BV48: =SUM(AM48:AP48) -> 2235 | BW48: =SUM(AQ48:AT48) -> -176 | BX48: =SUM(AU48:AX48) -> 611 | BY48: =SUM(AY48:BB48) -> 681 | BZ48: =BY61*$CS$61 -> 35.385 | CA48: =BZ61*$CS$61 -> 106.90877 | CB48: =CA61*$CS$61 -> 188.27531 | CC48: =CB61*$CS$61 -> 277.97536 | CD48: =CC61*$CS$61 -> 376.15108 | CE48: =CD61*$CS$61 -> 482.65182 | CF48: =CE61*$CS$61 -> 593.82253 | CG48: =CF61*$CS$61 -> 709.3834 | ... CI48: =CH61*$CS$61 -> 957.33138
B49: Pretax Income | C49: =C45+SUM(C46:C48) -> 712 | D49: =D45+SUM(D46:D48) -> 724 | E49: =E45+SUM(E46:E48) -> 720 | F49: =F45+SUM(F46:F48) -> 707 | G49: =G45+SUM(G46:G48) -> 786 | H49: =H45+SUM(H46:H48) -> 756 | I49: =I45+SUM(I46:I48) -> 694 | J49: =J45+SUM(J46:J48) -> 701 | ... BE49: =BE45+SUM(BE46:BE48) -> 1298 | BM49: =SUM(C49:F49) -> 2863 | BN49: =SUM(G49:J49) -> 2937 | BO49: =SUM(K49:N49) -> 2790 | BP49: =SUM(O49:R49) -> 2681 | BQ49: =SUM(S49:V49) -> 4229 | BR49: =SUM(W49:Z49) -> 3742 | BS49: =SUM(AA49:AD49) -> 2548 | BT49: =SUM(AE49:AH49) -> 3728 | BU49: =SUM(AI49:AL49) -> 6939 | BV49: =SUM(AM49:AP49) -> 5836 | BW49: =SUM(AQ49:AT49) -> 2346 | BX49: =SUM(AU49:AX49) -> 5016 | BY49: =SUM(AY49:BB49) -> 5068 | BZ49: =BZ45+SUM(BZ46:BZ48) -> 3914.8207 | CA49: =CA45+SUM(CA46:CA48) -> 4612.6156 | CB49: =CB45+SUM(CB46:CB48) -> 5209.0623 | CC49: =CC45+SUM(CC46:CC48) -> 5771.6468 | CD49: =CD45+SUM(CD46:CD48) -> 6339.3297 | CE49: =CE45+SUM(CE46:CE48) -> 6701.0679 | CF49: =CF45+SUM(CF46:CF48) -> 7054.9983 | CG49: =CG45+SUM(CG46:CG48) -> 7399.1378 | ... CI49: =CI45+SUM(CI46:CI48) -> 8074.182
B50: Taxes | C50: 223 | D50: 236 | E50: 223 | F50: 229 | G50: 207 | H50: 245 | I50: 221 | J50: 195 | K50: 220 | L50: 205 | M50: 213 | N50: 162 | O50: 120 | P50: 213 | Q50: 167 | R50: 138 | S50: 138 | T50: 257 | U50: 139 | V50: 826 | W50: 159 | X50: 187 | Y50: 120 | Z50: 47 | AA50: 171 | AB50: 167 | AC50: 122 | AD50: -160 | AE50: 185 | AF50: 198 | AG50: 181 | AH50: -25 | AI50: 821 | AJ50: 265 | AK50: 212 | AL50: 635 | AM50: 189 | AN50: 204 | AO50: 175 | AP50: 372 | AQ50: 156 | AR50: 175 | AS50: 181 | AT50: =290-SUM(AQ50:AS50) -> -222 | AU50: 187 | AV50: 206 | AW50: 162 | AX50: =842-SUM(AU50:AW50) -> 287 | AY50: 97 | AZ50: 97 | BA50: 223 | BB50: =886-SUM(AY50:BA50) -> 469 | BC50: 155 | BD50: 74 | BE50: 174 | BM50: =SUM(C50:F50) -> 911 | BN50: =SUM(G50:J50) -> 868 | BO50: =SUM(K50:N50) -> 800 | BP50: =SUM(O50:R50) -> 638 | BQ50: =SUM(S50:V50) -> 1360 | BR50: =SUM(W50:Z50) -> 513 | BS50: =SUM(AA50:AD50) -> 300 | BT50: =SUM(AE50:AH50) -> 539 | BU50: =SUM(AI50:AL50) -> 1933 | BV50: =SUM(AM50:AP50) -> 940 | BW50: =SUM(AQ50:AT50) -> 290 | BX50: =SUM(AU50:AX50) -> 842 | BY50: =SUM(AY50:BB50) -> 886 | BZ50: =BZ49*BZ58 -> 508.92668 | CA50: =CA49*CA58 -> 738.01849 | CB50: =CB49*CB58 -> 937.63121 | CC50: =CC49*CC58 -> 1096.6129 | CD50: =CD49*CD58 -> 1267.8659 | CE50: =CE49*CE58 -> 1407.2243 | CF50: =CF49*CF58 -> 1552.0996 | CG50: =CG49*CG58 -> 1627.8103 | ... CI50: =CI49*CI58 -> 1776.32
B51: Net Income | C51: =C49-C50 -> 489 | D51: =D49-D50 -> 488 | E51: =E49-E50 -> 497 | F51: =F49-F50 -> 478 | G51: =G49-G50 -> 579 | H51: =H49-H50 -> 511 | I51: =I49-I50 -> 473 | J51: =J49-J50 -> 506 | ... BE51: =BE49-BE50 -> 1124 | BM51: =SUM(C51:F51) -> 1952 | BN51: =SUM(G51:J51) -> 2069 | BO51: =SUM(K51:N51) -> 1990 | BP51: =SUM(O51:R51) -> 2043 | BQ51: =SUM(S51:V51) -> 2869 | BR51: =SUM(W51:Z51) -> 3229 | BS51: =SUM(AA51:AD51) -> 2248 | BT51: =SUM(AE51:AH51) -> 3189 | BU51: =SUM(AI51:AL51) -> 5006 | BV51: =SUM(AM51:AP51) -> 4896 | BW51: =SUM(AQ51:AT51) -> 2056 | BX51: =SUM(AU51:AX51) -> 4174 | BY51: =SUM(AY51:BB51) -> 4182 | BZ51: =BZ49-BZ50 -> 3405.894 | CA51: =CA49-CA50 -> 3874.5971 | CB51: =CB49-CB50 -> 4271.431 | CC51: =CC49-CC50 -> 4675.0339 | CD51: =CD49-CD50 -> 5071.4638 | CE51: =CE49-CE50 -> 5293.8436 | CF51: =CF49-CF50 -> 5502.8987 | CG51: =CG49-CG50 -> 5771.3275 | ... CI51: =CI49-CI50 -> 6297.862 | CJ51: =CI51*(1+$CS$62) -> 6329.3513 | CK51: =CJ51*(1+$CS$62) -> 6360.998 | CL51: =CK51*(1+$CS$62) -> 6392.803 | CM51: =CL51*(1+$CS$62) -> 6424.767 | CN51: =CM51*(1+$CS$62) -> 6456.8909 | CO51: =CN51*(1+$CS$62) -> 6489.1753 | CP51: =CO51*(1+$CS$62) -> 6521.6212 | CQ51: =CP51*(1+$CS$62) -> 6554.2293 | ... EG51: =EF51*(1+$CS$62) -> 8081.5791
B52: SC | C52: 232.4 | D52: 226.1 | E52: 219.9 | F52: 216.2 | G52: 213.3 | H52: 207.8 | I52: 206.5 | J52: 204.1 | K52: 195.6 | L52: 192.3 | M52: 187.2 | N52: 182.7 | O52: 178.4 | P52: 177.3 | Q52: 176.1 | R52: 175.6 | S52: 174.43 | T52: 174.41 | U52: 174.39 | V52: 174.36 | W52: 174.34 | X52: 174.3 | Y52: 174.2 | Z52: 173.9 | AA52: 173.4 | AB52: 173.1 | AC52: 172.6 | AD52: 171.3 | AE52: 169.2 | AF52: 167.5 | AG52: 166.4 | AH52: 165.9 | AI52: 164.1 | AJ52: 162.2 | AK52: 160.7 | AL52: 159.1 | AM52: 158.6 | AN52: 155.9 | AO52: 155.6 | AP52: 154.8 | AQ52: 154.3 | AR52: 153.6 | AS52: 152.1 | AT52: 150.6 | AU52: 149.8 | AV52: 148.3 | AW52: 145.69 | AX52: 144.75 | AY52: 144.1 | AZ52: 143.7 | BA52: 142.8 | BB52: 142.6 | BC52: 142.2 | BD52: 142.2 | BE52: 142.1 | BM52: =AVERAGE(C52:F52) -> 223.65 | BN52: =AVERAGE(G52:J52) -> 207.925 | BO52: =AVERAGE(K52:N52) -> 189.45 | BP52: =AVERAGE(O52:R52) -> 176.85 | BQ52: =AVERAGE(S52:V52) -> 174.3975 | BR52: =AVERAGE(W52:Z52) -> 174.185 | BS52: =AVERAGE(AA52:AD52) -> 172.6 | BT52: =AVERAGE(AE52:AH52) -> 167.25 | BU52: =AVERAGE(AI52:AL52) -> 161.525 | BV52: =AVERAGE(AM52:AP52) -> 156.225 | BW52: =AVERAGE(AQ52:AT52) -> 152.65 | BX52: =AVERAGE(AU52:AX52) -> 147.135 | BY52: =AVERAGE(AY52:BB52) -> 143.3
B53: EPS | C53: =C51/C52 -> 2.1041308 | D53: =D51/D52 -> 2.158337 | E53: =E51/E52 -> 2.2601182 | F53: =F51/F52 -> 2.2109158 | G53: =G51/G52 -> 2.7144866 | H53: =H51/H52 -> 2.4590953 | I53: =I51/I52 -> 2.2905569 | J53: =J51/J52 -> 2.4791769 | ... BE53: =BE51/BE52 -> 7.9099226 | BM53: =SUM(C53:F53) -> 8.7335019 | BN53: =SUM(G53:J53) -> 9.9433157 | BO53: =SUM(K53:N53) -> 10.504474 | BP53: =SUM(O53:R53) -> 11.546738 | BQ53: =SUM(S53:V53) -> 16.451419 | BR53: =SUM(W53:Z53) -> 18.53322 | BS53: =SUM(AA53:AD53) -> 12.968873 | BT53: =SUM(AE53:AH53) -> 19.044655 | BU53: =SUM(AI53:AL53) -> 31.228772 | BV53: =SUM(AM53:AP53) -> 31.406585 | BW53: =SUM(AQ53:AT53) -> 13.351324 | BX53: =SUM(AU53:AX53) -> 28.414886 | BY53: =SUM(AY53:BB53) -> 29.209478
B55: Gross Profit Margin | C55: =C43/C41 -> 0.21576016 | D55: =D43/D41 -> 0.22052749 | E55: =E43/E41 -> 0.22027514 | F55: =F43/F41 -> 0.21585188 | G55: =G43/G41 -> 0.2371751 | H55: =H43/H41 -> 0.23348236 | I55: =I43/I41 -> 0.22543449 | J55: =J43/J41 -> 0.23821218 | ... BE55: =BE43/BE41 -> 0.21147276 | BM55: =BM43/BM41 -> 0.21811768 | BN55: =BN43/BN41 -> 0.23357938 | BO55: =BO43/BO41 -> 0.23981977 | BP55: =BP43/BP41 -> 0.23917267 | BQ55: =BQ43/BQ41 -> 0.22804184 | BR55: =BR43/BR41 -> 0.2256521 | BS55: =BS43/BS41 -> 0.21450312 | BT55: =BT43/BT41 -> 0.20321204 | ... BX55: =BX43/BX41 -> 0.2037872 | BY55: 0.19814559 | BZ55: 0.19814559 | CA55: 0.205 | CB55: 0.21 | CC55: 0.215 | CD55: 0.22 | CE55: 0.221 | CF55: 0.222 | CG55: 0.223 | CH55: 0.224 | CI55: 0.225
B56: SG&A as % of Revenue | C56: =C44/C41 -> 0.091415465 | D56: =D44/D41 -> 0.092469018 | E56: =E44/E41 -> 0.090894202 | F56: =F44/F41 -> 0.091115803 | G56: =G44/G41 -> 0.092681259 | H56: =H44/H41 -> 0.097698294 | I56: =I44/I41 -> 0.096925134 | J56: =J44/J41 -> 0.11345776 | ... BE56: =BE44/BE41 -> 0.097374573 | BM56: =BM44/BM41 -> 0.091480475 | BN56: =BN44/BN41 -> 0.10029609 | BO56: =BO44/BO41 -> 0.10907082 | BP56: =BP44/BP41 -> 0.10653283 | BQ56: =BQ44/BQ41 -> 0.10429165 | BR56: =BR44/BR41 -> 0.10004984 | BS56: =BS44/BS41 -> 0.097219349 | BT56: =BT44/BT41 -> 0.092747086 | ... BX56: =BX44/BX41 -> 0.097287549 | BY56: 0.096129094 | BZ56: 0.096129094 | CA56: 0.096129094 | CB56: 0.096129094 | CC56: 0.096129094 | CD56: 0.096129094 | CE56: 0.096129094 | CF56: 0.096129094 | CG56: 0.096129094 | CH56: 0.096129094 | CI56: 0.096129094
B57: Operating Profit Margin | C57: =C45/C41 -> 0.12434469 | D57: =D45/D41 -> 0.12805847 | E57: =E45/E41 -> 0.12938094 | F57: =F45/F41 -> 0.12473607 | G57: =G45/G41 -> 0.14449384 | H57: =H45/H41 -> 0.13578407 | I57: =I45/I41 -> 0.12850936 | J57: =J45/J41 -> 0.12475442 | ... BE57: =BE45/BE41 -> 0.11409818 | BM57: =BM45/BM41 -> 0.1266372 | BN57: =BN45/BN41 -> 0.13328329 | BO57: =BO45/BO41 -> 0.13074896 | BP57: =BP45/BP41 -> 0.13263984 | BQ57: =BQ45/BQ41 -> 0.12375019 | BR57: =BR45/BR41 -> 0.12560226 | BS57: =BS45/BS41 -> 0.11728377 | BT57: =BT45/BT41 -> 0.11046496 | ... BX57: =BX45/BX41 -> 0.10649965 | BY57: 0.10752252 | BZ57: 0.10752252 | CA57: 0.10752252 | CB57: 0.10752252 | CC57: 0.10752252 | CD57: 0.10752252 | CE57: 0.10752252 | CF57: 0.10752252 | CG57: 0.10752252 | CH57: 0.10752252 | CI57: 0.10752252
B58: Effective Tax Rate | C58: =C50/C49 -> 0.31320225 | D58: =D50/D49 -> 0.32596685 | E58: =E50/E49 -> 0.30972222 | F58: =F50/F49 -> 0.32390382 | G58: =G50/G49 -> 0.26335878 | H58: =H50/H49 -> 0.32407407 | I58: =I50/I49 -> 0.3184438 | J58: =J50/J49 -> 0.27817404 | ... BE58: =BE50/BE49 -> 0.13405239 | BM58: =BM50/BM49 -> 0.31819769 | BN58: =BN50/BN49 -> 0.29553967 | BO58: =BO50/BO49 -> 0.28673835 | BP58: =BP50/BP49 -> 0.23797091 | BQ58: =BQ50/BQ49 -> 0.32158903 | BR58: =BR50/BR49 -> 0.13709246 | BS58: =BS50/BS49 -> 0.1177394 | BT58: =BT50/BT49 -> 0.14458155 | ... BX58: =BX50/BX49 -> 0.16786284 | BY58: 0.17482242 | BZ58: 0.13 | CA58: 0.16 | CB58: 0.18 | CC58: 0.19 | CD58: 0.2 | CE58: 0.21 | CF58: 0.22 | CG58: 0.22 | CH58: 0.22 | CI58: 0.22
B59: Net Profit Margin | C59: =C51/C41 -> 0.080111402 | D59: =D51/D41 -> 0.07753416 | E59: =E51/E41 -> 0.081395349 | F59: =F51/F41 -> 0.077635212 | G59: =G51/G41 -> 0.099008208 | H59: =H51/H41 -> 0.084616658 | I59: =I51/I41 -> 0.079044118 | J59: =J51/J41 -> 0.082842174 | ... BE59: =BE51/BE41 -> 0.10106096 | BM59: =BM51/BM41 -> 0.079153319 | BN59: =BN51/BN41 -> 0.086283832 | BO59: =BO51/BO41 -> 0.084587265 | BP59: =BP51/BP41 -> 0.082692463 | BQ59: =BQ51/BQ41 -> 0.11032918 | BR59: =BR51/BR41 -> 0.10729357 | BS59: =BS51/BS41 -> 0.066428297 | BT59: =BT51/BT41 -> 0.086659964 | ... BX59: =BX51/BX41 -> 0.101723 | BY59: 0.099680603 | BZ59: 0.099680603 | CA59: 0.099680603 | CB59: 0.099680603 | CC59: 0.099680603 | CD59: 0.099680603 | CE59: 0.099680603 | CF59: 0.099680603 | CG59: 0.099680603 | CH59: 0.099680603 | CI59: 0.099680603
B61: Cash & CEs | AT61: 3109 | AU61: 3061 | AV61: 3272 | AW61: 3326 | AX61: 4353 | AY61: 1685 | AZ61: 1899 | BA61: 1957 | BB61: 4403 | BC61: 2090 | BD61: 2307 | BE61: 3744 | BW61: =AT61 -> 3109 | BX61: =AX61 -> 4353 | BY61: =AY61 -> 1685 | BZ61: =BY61+BZ51 -> 5090.894 | CA61: =BZ61+CA51 -> 8965.491 | CB61: =CA61+CB51 -> 13236.922 | CC61: =CB61+CC51 -> 17911.956 | CD61: =CC61+CD51 -> 22983.42 | CE61: =CD61+CE51 -> 28277.263 | CF61: =CE61+CF51 -> 33780.162 | CG61: =CF61+CG51 -> 39551.49 | ... CI61: =CH61+CI51 -> 51885.071 | CK61: Invested Capital | CN61: Avg. (2024-2025) | CP61: Projected ROIC: | CR61: ROIC | CS61: 0.021
B62: A/R | AT62: 1454 | AU62: 1832 | AV62: 1694 | AW62: 1609 | AX62: 1272 | AY62: 1805 | AZ62: 2196 | BA62: 1983 | BB62: 1375 | BC62: 1806 | BD62: 2311 | BE62: 2080 | BW62: =AT62 -> 1454 | BX62: =AX62 -> 1272 | BY62: =AY62 -> 1805 | CK62: 2024 | CL62: 2025 | CN62: 2024-2025 | CP62: 2025 | CR62: Terminal | CS62: 0.005
B63: Unbilled Receivables | AT63: 5693 | AU63: 6450 | AV63: 6434 | AW63: 6518 | AX63: 5908 | AY63: 6857 | AZ63: 7133 | BA63: 7030 | BB63: 6544 | BC63: 7556 | BD63: 7953 | BE63: 7899 | BW63: =AT63 -> 5693 | BX63: =AX63 -> 5908 | BY63: =AY63 -> 6857 | CK63: =SUM(BX61:BX64)-BX77+BX68+BX71+BX70 -> 28980 | CL63: =SUM(BY61:BY64)-BY77+BY68+BY71+BY70 -> 26968 | CN63: =AVERAGE(CK63:CL63) -> 27974 | CP63: =AVERAGE(BZ50)*(1-BZ59) -> 458.19657 | CR63: RFR (10-year yield) | CS63: =CN72 -> 0.0517
B64: Inventories | AT64: 1109 | AU64: 1370 | AV64: 1504 | AW64: 1646 | AX64: 1455 | AY64: 1578 | AZ64: 1553 | BA64: 1615 | BB64: 1309 | BC64: 1450 | BD64: 1415 | BE64: 1361 | BW64: =AT64 -> 1109 | BX64: =AX64 -> 1455 | BY64: =AY64 -> 1578 | CP64: =CP63/CN63 -> 0.016379372 | CR64: ERP (Avg. market return - (less) RFR) | CS64: =8.15%-CS63 -> 0.0298
B65: ST Liabilities | AT65: 2341 | AU65: 2083 | AV65: 1363 | AW65: 1233 | AX65: 1286 | AY65: 1342 | AZ65: 1245 | BA65: 1520 | BB65: 1656 | BC65: 1868 | BD65: 1604 | BE65: 1893 | BW65: =AT65 -> 2341 | BX65: =AX65 -> 1286 | BY65: =AY65 -> 1342 | CK65: Capital Structure | CR65: Equity β (1-year avg.) | CS65: ='Notes | Quant Analysis'!S242 -> 0.32949713
B66: PP&E | AT66: 9653 | AU66: 9690 | AV66: 9771 | AW66: 10078 | AX66: 10536 | AY66: 10552 | AZ66: 10537 | BA66: 10542 | BB66: 10972 | BC66: 10243 | BD66: 10297 | BE66: 10461 | BW66: =AT66 -> 9653 | BX66: =AX66 -> 10536 | BY66: =AY66 -> 10552 | CK66: Mkt Cap | CN66: =Main!C5 -> 75369.84 | CR66: Discount (Cost of Equity) | CS66: =+CS63+(CS64*CS65) -> 0.061519014
B67: LT Operating Lease | AT67: 1818 | AU67: 1763 | AV67: 1823 | AW67: 1779 | AX67: 1770 | AY67: 1826 | AZ67: 1783 | BA67: 1783 | BB67: 1859 | BC67: 1925 | BD67: 1901 | BE67: 2182 | BW67: =AT67 -> 1818 | BX67: =AX67 -> 1770 | BY67: =AY67 -> 1826 | CK67: Debt to Ttl Mkt Cap | CN67: =Main!C7/(Main!C7+CN66) -> 0.16071875
B68: Goodwill | AT68: 17517 | AU68: 17515 | AV68: 17516 | AW68: 17517 | AX68: 17512 | AY68: 17434 | AZ68: 17435 | BA68: 17436 | BB68: 17437 | BC68: 17439 | BD68: 17439 | BE68: 17440 | BW68: =AT68 -> 17517 | BX68: =AX68 -> 17512 | BY68: =AY68 -> 17434 | CK68: Mkt Equity to Ttl Mkt Cap | CN68: =CN66/(CN66+Main!C7) -> 0.83928125 | CR68: NPV | CS68: =NPV(CS66,BZ51:DW51) -> 90293.483
B69: LT Deferred Tax Assets | AT69: 1020 | AU69: 1123 | AV69: 1250 | AW69: 1407 | AX69: 1599 | AY69: 1633 | AZ69: 1713 | BA69: 1255 | BB69: 1051 | BC69: 743 | BD69: 598 | BE69: 488 | BW69: =AT69 -> 1020 | BX69: =AX69 -> 1599 | BY69: =AY69 -> 1633 | CK69: LT Debt / Equity | CN69: =BY82/BY83 -> 2.2346503 | CR69: SC | CS69: =Main!C4 -> 142.1
B70: Pension & Other Benefit Assets | AT70: 0 | AU70: 0 | AV70: 0 | AW70: 0 | AX70: 2184 | AY70: 2285 | AZ70: 2393 | BA70: 2501 | BB70: 3167 | BC70: 3307 | BD70: 3447 | BE70: 3447 | BW70: =AT70 -> 0 | BX70: =AX70 -> 2184 | BY70: =AY70 -> 2285 | CR70: FV | CS70: =CS68/CS69 -> 635.42212
B71: Other LT Assets | AT71: =2525+305 -> 2830 | AU71: =290+2641 -> 2931 | AV71: =282+2761 -> 3043 | AW71: =268+2908 -> 3176 | AX71: =254+1230 -> 1484 | AY71: =1230+254 -> 1484 | AZ71: =231+1333 -> 1564 | BA71: =220+1458 -> 1678 | BB71: 1604 | BC71: 1580 | BD71: 1491 | BE71: 1502 | BW71: =AT71 -> 2830 | BX71: =AX71 -> 1484 | BY71: =AY71 -> 1484 | CK71: Cost of Equity | CR71: CP | CS71: =Main!C3 -> 530.4
B72: Ttl Assets | AT72: =SUM(AT61:AT71) -> 46544 | AU72: =SUM(AU61:AU71) -> 47818 | AV72: =SUM(AV61:AV71) -> 47670 | AW72: =SUM(AW61:AW71) -> 48289 | AX72: =SUM(AX61:AX71) -> 49359 | AY72: =SUM(AY61:AY71) -> 48481 | AZ72: =SUM(AZ61:AZ71) -> 49451 | BA72: =SUM(BA61:BA71) -> 49300 | ... BE72: =SUM(BE61:BE71) -> 52497 | BW72: =AT72 -> 46544 | BX72: =AX72 -> 49359 | BY72: =AY72 -> 48481 | CK72: RFR (10-year yield) | CN72: 0.0517 | CR72: Change Δ | CS72: =CS70/CS71-1 -> 0.1980055 | CT72: =IF(CS72>0,"Upside","Downside") -> Upside
CK73: Equity β (1-year avg.) | CN73: ='Notes | Quant Analysis'!S242 -> 0.32949713 | CR73: {=_xlfn.IFS(CS72>=25%,"Strong Buy",CS72>=10.00001%,"Buy",AND(CS72<=10%,CS72>=-4.9999%),"Hold",AND(CS72<=-5%,CS72>=-14.999999%),"Sell",CS72<=-15%,"Strong Sell")} -> Buy
B74: A/P | AT74: 2110 | AU74: 2580 | AV74: 2352 | AW74: 2518 | AX74: 2599 | AY74: 2501 | AZ74: 2592 | BA74: 2797 | BB74: 3240 | BC74: 2681 | BD74: 2895 | BE74: 3281 | BW74: =AT74 -> 2110 | BX74: =AX74 -> 2599 | BY74: =AY74 -> 2501 | CK74: Market Return(1-year avg.) | CN74: 0.18
B75: ST Employee Comp | AT75: 2251 | AU75: 1701 | AV75: 1903 | AW75: 1924 | AX75: 2271 | AY75: 1598 | AZ75: 1856 | BA75: 1946 | BB75: 2309 | BC75: 1732 | BD75: 1991 | BE75: 2039 | BW75: =AT75 -> 2251 | BX75: =AX75 -> 2271 | BY75: =AY75 -> 1598 | CK75: Cost of Equity | CN75: =(CN72+CN73)*(CN74-CN72) -> 0.048907591
B76: ST Unbilled Contract Liabilities | AT76: 4193 | AU76: 3530 | AV76: 3292 | AW76: 3157 | AX76: 4070 | AY76: 3710 | AZ76: 3997 | BA76: 3562 | BB76: 4086 | BC76: 3697 | BD76: 3823 | BE76: 3838 | BW76: =AT76 -> 4193 | BX76: =AX76 -> 4070 | BY76: =AY76 -> 3710
B77: Other ST Liabilities | AT77: 3388 | AU77: 5321 | AV77: 5361 | AW77: 5502 | AX77: 5188 | AY77: 6160 | AZ77: 5014 | BA77: 4413 | BB77: 4247 | BC77: 4711 | BD77: 4636 | BE77: 4595 | BW77: =AT77 -> 3388 | BX77: =AX77 -> 5188 | BY77: =AY77 -> 6160 | CK77: Cost of Debt
B78: LT Debt | AT78: 13786 | AU78: 14742 | AV78: 14706 | AW78: 14689 | AX78: 14692 | AY78: 14167 | AZ78: 15160 | BA78: 15162 | BB78: 15162 | BC78: 14411 | BD78: 14428 | BE78: 14433 | BW78: =AT78 -> 13786 | BX78: =AX78 -> 14692 | BY78: =AY78 -> 14167 | BZ78: =BY78+BZ46 -> 13529.485 | CA78: =BZ78+CA46 -> 12920.658 | CB78: =CA78+CB46 -> 12339.229 | CC78: =CB78+CC46 -> 11783.963 | CD78: =CC78+CD46 -> 11253.685 | CE78: =CD78+CE46 -> 10747.269 | CF78: =CE78+CF46 -> 10263.642 | CG78: =CF78+CG46 -> 9801.7781 | ... CI78: =CH78+CI46 -> 8939.4667 | CK78: Cost of Debt | CN78: 0.045
B79: LT Pension & Other Benefit Liabilities | AT79: 1290 | AU79: 1250 | AV79: 1211 | AW79: 1186 | AX79: 1120 | AY79: 1115 | AZ79: 1108 | BA79: 1100 | BB79: 1110 | BC79: 1095 | BD79: 1086 | BE79: 1076 | BW79: =AT79 -> 1290 | BX79: =AX79 -> 1120 | BY79: =AY79 -> 1115 | CK79: Tax Rate | CN79: 0.146
B80: LT Operating Lease Liabilities | AT80: 1892 | AU80: 1830 | AV80: 1870 | AW80: 1821 | AX80: 1798 | AY80: 1854 | AZ80: 1805 | BA80: 1796 | BB80: 1857 | BC80: 1905 | BD80: 1861 | BE80: 2202 | BW80: =AT80 -> 1892 | BX80: =AX80 -> 1798 | BY80: =AY80 -> 1854 | CK80: After Tax Cost of Debt | CN80: =CN78*(1-CN79) -> 0.03843
B81: Other LT Liabilities | AT81: 2839 | AU81: 2641 | AV81: 2674 | AW81: 2744 | AX81: 2331 | AY81: 2379 | AZ81: 2448 | BA81: 2536 | BB81: 2692 | BC81: 2660 | BD81: 2159 | BE81: 2350 | BW81: =AT81 -> 2839 | BX81: =AX81 -> 2331 | BY81: =AY81 -> 2379
B82: Ttl Liabilities | AT82: =SUM(AT74:AT81) -> 31749 | AU82: =SUM(AU74:AU81) -> 33595 | AV82: =SUM(AV74:AV81) -> 33369 | AW82: =SUM(AW74:AW81) -> 33541 | AX82: =SUM(AX74:AX81) -> 34069 | AY82: =SUM(AY74:AY81) -> 33484 | AZ82: =SUM(AZ74:AZ81) -> 33980 | BA82: =SUM(BA74:BA81) -> 33312 | ... BE82: =SUM(BE74:BE81) -> 33814 | BW82: =AT82 -> 31749 | BX82: =AX82 -> 34069 | BY82: =AY82 -> 33484 | CK82: WACC | CN82: =(CN68*CN75)+(CN67*CN80*(1-CN79)) -> 0.046321888
B83: Ttl SE | AT83: 14795 | AU83: 14223 | AV83: 14301 | AW83: 14748 | AX83: 15290 | AY83: 14984 | AZ83: 15471 | BA83: 15988 | BB83: 16674 | BC83: 17115 | BD83: 17884 | BE83: 18683 | BW83: =AT83 -> 14795 | BX83: =AX83 -> 15290 | BY83: =AY83 -> 14984
B84: Ttl L + SE | AT84: =AT82+AT83 -> 46544 | AU84: =AU82+AU83 -> 47818 | AV84: =AV82+AV83 -> 47670 | AW84: =AW82+AW83 -> 48289 | AX84: =AX82+AX83 -> 49359 | AY84: =AY82+AY83 -> 48468 | AZ84: =AZ82+AZ83 -> 49451 | BA84: =BA82+BA83 -> 49300 | ... BE84: =BE82+BE83 -> 52497 | BW84: =AT84 -> 46544 | BX84: =AX84 -> 49359 | BY84: =AY84 -> 48468
B86: Current Ratio | AT86: =SUM(AT61:AT65)/SUM(AT74:AT77) -> 1.147714 | AU86: =SUM(AU61:AU65)/SUM(AU74:AU77) -> 1.1267134 | AV86: =SUM(AV61:AV65)/SUM(AV74:AV77) -> 1.1052835 | AW86: =SUM(AW61:AW65)/SUM(AW74:AW77) -> 1.0939623 | AX86: =SUM(AX61:AX65)/SUM(AX74:AX77) -> 1.0103341 | AY86: =SUM(AY61:AY65)/SUM(AY74:AY77) -> 0.94974587 | AZ86: =SUM(AZ61:AZ65)/SUM(AZ74:AZ77) -> 1.0421279 | BA86: =SUM(BA61:BA65)/SUM(BA74:BA77) -> 1.109058 | ... BE86: =SUM(BE61:BE65)/SUM(BE74:BE77) -> 1.2344216 | BW86: =SUM(BW61:BW65)/SUM(BW74:BW77) -> 1.147714 | BX86: =SUM(BX61:BX65)/SUM(BX74:BX77) -> 1.0103341 | BY86: =SUM(BY61:BY65)/SUM(BY74:BY77) -> 0.94974587
B87: Quick Ratio | AT87: =(SUM(AT61:AT65)-AT64)/SUM(AT74:AT77) -> 1.0548484 | AU87: =(SUM(AU61:AU65)-AU64)/SUM(AU74:AU77) -> 1.0223881 | AV87: =(SUM(AV61:AV65)-AV64)/SUM(AV74:AV77) -> 0.98876666 | AW87: =(SUM(AW61:AW65)-AW64)/SUM(AW74:AW77) -> 0.96832303 | AX87: =(SUM(AX61:AX65)-AX64)/SUM(AX74:AX77) -> 0.90734711 | AY87: =(SUM(AY61:AY65)-AY64)/SUM(AY74:AY77) -> 0.83678144 | AZ87: =(SUM(AZ61:AZ65)-AZ64)/SUM(AZ74:AZ77) -> 0.92674047 | BA87: =(SUM(BA61:BA65)-BA64)/SUM(BA74:BA77) -> 0.98207265 | ... BE87: =(SUM(BE61:BE65)-BE64)/SUM(BE74:BE77) -> 1.1354614 | BW87: =(SUM(BW61:BW65)-BW64)/SUM(BW74:BW77) -> 1.0548484 | BX87: =(SUM(BX61:BX65)-BX64)/SUM(BX74:BX77) -> 0.90734711 | BY87: =(SUM(BY61:BY65)-BY64)/SUM(BY74:BY77) -> 0.83678144
B88: Cash Ratio | AT88: =SUM(AT61)/SUM(AT74:AT77) -> 0.26034165 | AU88: =SUM(AU61)/SUM(AU74:AU77) -> 0.23309473 | AV88: =SUM(AV61)/SUM(AV74:AV77) -> 0.25348621 | AW88: =SUM(AW61)/SUM(AW74:AW77) -> 0.25387375 | AX88: =SUM(AX61)/SUM(AX74:AX77) -> 0.30811155 | AY88: =SUM(AY61)/SUM(AY74:AY77) -> 0.12062424 | AZ88: =SUM(AZ61)/SUM(AZ74:AZ77) -> 0.14109518 | BA88: =SUM(BA61)/SUM(BA74:BA77) -> 0.1538764 | ... BE88: =SUM(BE61)/SUM(BE74:BE77) -> 0.27223151 | BW88: =SUM(BW61)/SUM(BW74:BW77) -> 0.26034165 | BX88: =SUM(BX61)/SUM(BX74:BX77) -> 0.30811155 | BY88: =SUM(BY61)/SUM(BY74:BY77) -> 0.12062424
B89: Fixed Asset Turnover Ratio | AT89: =AT41/SUM(AT66:AT67) -> 0.92738209 | AU89: =AU41/SUM(AU66:AU67) -> 0.88474635 | AV89: =AV41/SUM(AV66:AV67) -> 0.88131792 | AW89: =AW41/SUM(AW66:AW67) -> 0.8430463 | AX89: =AX41/SUM(AX66:AX67) -> 0.8683569 | AY89: =AY41/SUM(AY66:AY67) -> 0.76490548 | AZ89: =AZ41/SUM(AZ66:AZ67) -> 0.84017857 | BA89: =BA41/SUM(BA66:BA67) -> 0.84567951 | ... BE89: =BE41/SUM(BE66:BE67) -> 0.87969627 | BW89: =BW41/SUM(BW66:BW67) -> 3.4251591 | BX89: =BX41/SUM(BX66:BX67) -> 3.3343897 | BY89: =BY41/SUM(BY66:BY67) -> 3.3894005
B90: Ttl Asset Turnover Ratio | AT90: =AT41/AT72 -> 0.22855792 | AU90: =AU41/AU72 -> 0.21190765 | AV90: =AV41/AV72 -> 0.21434865 | AW90: =AW41/AW72 -> 0.20700367 | AX90: =AX41/AX72 -> 0.21649547 | AY90: =AY41/AY72 -> 0.195293 | AZ90: =AZ41/AZ72 -> 0.20931832 | BA90: =BA41/BA72 -> 0.21141988 | ... BE90: =BE41/BE72 -> 0.21185973 | BW90: =BW41/BW72 -> 0.84414747 | BX90: =BX41/BX72 -> 0.83131749 | BY90: =BY41/BY72 -> 0.86536994
B91: Inventory Turnover Ratio | AT91: =AT42/AVERAGE(AQ64:AT64) -> 9.1550947 | AU91: =AU42/AVERAGE(AR64:AU64) -> 6.4542154 | AV91: =AV42/AVERAGE(AS64:AV64) -> 6.0459453 | AW91: =AW42/AVERAGE(AT64:AW64) -> 5.6066797 | AX91: =AX42/AVERAGE(AU64:AX64) -> 5.8604184 | AY91: =AY42/AVERAGE(AV64:AY64) -> 5.1030244 | AZ91: =AZ42/AVERAGE(AW64:AZ64) -> 5.2252888 | BA91: =BA42/AVERAGE(AX64:BA64) -> 5.2868892 | ... BE91: =BE42/AVERAGE(BB64:BE64) -> 6.33785 | BW91: =BW42/AVERAGE(BT64:BW64) -> 29.52119 | BX91: =BX42/AVERAGE(BU64:BX64) -> 25.484399 | BY91: =BY42/AVERAGE(BV64:BY64) -> 24.365765
B92: Return on Assets | AT92: =AT51/AT72 -> -0.0114945 | AU92: =AU51/AU72 -> 0.01974152 | AV92: =AV51/AV72 -> 0.019718901 | AW92: =AW51/AW72 -> 0.021247075 | AX92: =AX51/AX72 -> 0.025608298 | AY92: =AY51/AY72 -> 0.0099214125 | AZ92: =AZ51/AZ72 -> 0.026895311 | BA92: =BA51/BA72 -> 0.022312373 | ... BE92: =BE51/BE72 -> 0.021410747 | BW92: =BW51/BW72 -> 0.044173255 | BX92: =BX51/BX72 -> 0.084564112 | BY92: =BY51/BY72 -> 0.086260597
B93: Return on Equity | AT93: =AT51/AT83 -> -0.036160865 | AU93: =AU51/AU83 -> 0.06637137 | AV93: =AV51/AV83 -> 0.065729669 | AW93: =AW51/AW83 -> 0.069568755 | AX93: =AX51/AX83 -> 0.082668411 | AY93: =AY51/AY83 -> 0.032100908 | AZ93: =AZ51/AZ83 -> 0.085967294 | BA93: =BA51/BA83 -> 0.068801601 | ... BE93: =BE51/BE83 -> 0.060161644 | BW93: =BW51/BW83 -> 0.13896587 | BX93: =BX51/BX83 -> 0.27298888 | BY93: =BY51/BY83 -> 0.2790977
B95: Net Income | C95: =C51 -> 489 | D95: =D51 -> 488 | E95: =E51 -> 497 | F95: =F51 -> 478 | G95: =G51 -> 579 | H95: =H51 -> 511 | I95: =I51 -> 473 | J95: =J51 -> 506 | ... BE95: =BE51 -> 1124 | BM95: =SUM(C95:F95) -> 1952 | BN95: =SUM(G95:J95) -> 2069 | BO95: =SUM(K95:N95) -> 1990 | BP95: =SUM(O95:R95) -> 2043 | BQ95: =SUM(S95:V95) -> 2869 | BR95: =SUM(W95:Z95) -> 3229 | BS95: =SUM(AA95:AD95) -> 2248 | BT95: =SUM(AE95:AH95) -> 3189 | BU95: =SUM(AI95:AL95) -> 5006 | BV95: =SUM(AM95:AP95) -> 4896 | BW95: =SUM(AQ95:AT95) -> 2056 | BX95: =SUM(AU95:AX95) -> 4174 | BY95: =SUM(AY95:BB95) -> 4182
B96: CFFO | C96: 1 | D96: 328 | E96: 950 | F96: 1204 | G96: -402 | H96: 572 | I96: 933 | J96: 1490 | K96: -654 | L96: 626 | M96: 557 | N96: 1633 | O96: -60 | P96: 604 | Q96: 738 | R96: 1531 | S96: -439 | T96: 507 | U96: 938 | V96: 1607 | W96: -237 | X96: 875 | Y96: 812 | Z96: 2377 | AA96: -913 | AB96: 1607 | AC96: 1139 | AD96: 2990 | AE96: -993 | AF96: 2475 | AG96: 1421 | AH96: 1402 | AI96: 10 | AJ96: 1100 | AK96: 1015 | AL96: 1442 | AM96: -488 | AN96: -197 | AO96: 1335 | AP96: 2251 | AQ96: -702 | AR96: 919 | AS96: 1228 | AT96: 2430 | AU96: -706 | AV96: 1425 | AW96: 1091 | AX96: 2578 | AY96: -1565 | AZ96: 868 | BA96: 1557 | BB96: 3897 | BC96: -1656 | BD96: 1280 | BE96: 1369 | BM96: =SUM(C96:F96) -> 2483 | BN96: =SUM(G96:J96) -> 2593 | BO96: =SUM(K96:N96) -> 2162 | BP96: =SUM(O96:R96) -> 2813 | BQ96: =SUM(S96:V96) -> 2613 | BR96: =SUM(W96:Z96) -> 3827 | BS96: =SUM(AA96:AD96) -> 4823 | BT96: =SUM(AE96:AH96) -> 4305 | BU96: =SUM(AI96:AL96) -> 3567 | BV96: =SUM(AM96:AP96) -> 2901 | BW96: =SUM(AQ96:AT96) -> 3875 | BX96: =SUM(AU96:AX96) -> 4388 | BY96: =SUM(AY96:BB96) -> 4757
B97: CapEx, net | C97: -40 | D97: -48 | E97: -90 | F97: -186 | G97: -60 | H97: -116 | I97: -109 | J97: -276 | K97: -117 | L97: -115 | M97: -102 | N97: -137 | O97: -298 | P97: -173 | Q97: -137 | R97: -312 | S97: -216 | T97: -217 | U97: -217 | V97: -278 | W97: -305 | X97: -199 | Y97: -282 | Z97: -463 | AA97: -284 | AB97: -252 | AC97: -257 | AD97: -471 | AE97: -272 | AF97: -269 | AG97: -287 | AH97: -592 | AI97: -205 | AJ97: -230 | AK97: -247 | AL97: -733 | AM97: -244 | AN97: -263 | AO97: -296 | AP97: -632 | AQ97: -309 | AR97: -304 | AS97: -359 | AT97: -803 | AU97: -270 | AV97: -320 | AW97: -361 | AX97: -816 | AY97: -256 | AZ97: -231 | BA97: -301 | BB97: -662 | BC97: -167 | BD97: -302 | BE97: -775 | BM97: =SUM(C97:F97) -> -364 | BN97: =SUM(G97:J97) -> -561 | BO97: =SUM(K97:N97) -> -471 | BP97: =SUM(O97:R97) -> -920 | BQ97: =SUM(S97:V97) -> -928 | BR97: =SUM(W97:Z97) -> -1249 | BS97: =SUM(AA97:AD97) -> -1264 | BT97: =SUM(AE97:AH97) -> -1420 | BU97: =SUM(AI97:AL97) -> -1415 | BV97: =SUM(AM97:AP97) -> -1435 | BW97: =SUM(AQ97:AT97) -> -1775 | BX97: =SUM(AU97:AX97) -> -1767 | BY97: =SUM(AY97:BB97) -> -1450
B98: FCF | C98: =C96+C97 -> -39 | D98: =D96+D97 -> 280 | E98: =E96+E97 -> 860 | F98: =F96+F97 -> 1018 | G98: =G96+G97 -> -462 | H98: =H96+H97 -> 456 | I98: =I96+I97 -> 824 | J98: =J96+J97 -> 1214 | ... BE98: =BE96+BE97 -> 594 | BM98: =SUM(C98:F98) -> 2119 | BN98: =SUM(G98:J98) -> 2032 | BO98: =SUM(K98:N98) -> 1691 | BP98: =SUM(O98:R98) -> 1893 | BQ98: =SUM(S98:V98) -> 1685 | BR98: =SUM(W98:Z98) -> 2578 | BS98: =SUM(AA98:AD98) -> 3559 | BT98: =SUM(AE98:AH98) -> 2885 | BU98: =SUM(AI98:AL98) -> 2152 | BV98: =SUM(AM98:AP98) -> 1466 | BW98: =SUM(AQ98:AT98) -> 2100 | BX98: =SUM(AU98:AX98) -> 2621 | BY98: =SUM(AY98:BB98) -> 3307
B99: SC | C99: =C52 -> 232.4 | D99: =D52 -> 226.1 | E99: =E52 -> 219.9 | F99: =F52 -> 216.2 | G99: =G52 -> 213.3 | H99: =H52 -> 207.8 | I99: =I52 -> 206.5 | J99: =J52 -> 204.1 | ... BE99: =BE52 -> 142.1 | BM99: =BM52 -> 223.65 | BN99: =BN52 -> 207.925 | BO99: =BO52 -> 189.45 | BP99: =BP52 -> 176.85 | BQ99: =BQ52 -> 174.3975 | BR99: =BR52 -> 174.185 | BS99: =BS52 -> 172.6 | BT99: =BT52 -> 167.25 | ... BY99: =BY52 -> 143.3
B100: FCF per Share | C100: =C98/C99 -> -0.16781411 | D100: =D98/D99 -> 1.2383901 | E100: =E98/E99 -> 3.9108686 | F100: =F98/F99 -> 4.7086031 | G100: =G98/G99 -> -2.1659634 | H100: =H98/H99 -> 2.1944177 | I100: =I98/I99 -> 3.9903148 | J100: =J98/J99 -> 5.9480647 | ... BE100: =BE98/BE99 -> 4.1801548 | BM100: =SUM(C100:F100) -> 9.6900477 | BN100: =SUM(G100:J100) -> 9.9668337 | BO100: =SUM(K100:N100) -> 9.3344309 | BP100: =SUM(O100:R100) -> 10.778929 | BQ100: =SUM(S100:V100) -> 9.6642331 | BR100: =SUM(W100:Z100) -> 14.818308 | BS100: =SUM(AA100:AD100) -> 20.740008 | BT100: =SUM(AE100:AH100) -> 17.391153 | BU100: =SUM(AI100:AL100) -> 13.410857 | BV100: =SUM(AM100:AP100) -> 9.5700402 | BW100: =SUM(AQ100:AT100) -> 13.968534 | BX100: =SUM(AU100:AX100) -> 18.119109 | BY100: =SUM(AY100:BB100) -> 23.277141
B102: CFFO Margin | C102: =C96/C41 -> 0.000163827 | D102: =D96/D41 -> 0.052113124 | E102: =E96/E41 -> 0.15558467 | F102: =F96/F41 -> 0.19554978 | G102: =G96/G41 -> -0.06874145 | H102: =H96/H41 -> 0.094717668 | I102: =I96/I41 -> 0.15591578 | J102: =J96/J41 -> 0.24394237 | ... BE102: =BE96/BE41 -> 0.12308937 | BM102: =BM96/BM41 -> 0.10068529 | BN102: =BN96/BN41 -> 0.10813629 | BO102: =BO96/BO41 -> 0.091898325 | BP102: =BP96/BP41 -> 0.11385898 | BQ102: =BQ96/BQ41 -> 0.10048454 | BR102: =BR96/BR41 -> 0.12716398 | BS102: =BS96/BS41 -> 0.14251943 | BT102: =BT96/BT41 -> 0.11698687 | ... BY102: =BY96/BY41 -> 0.11338609
B103: FCF Margin | C103: =C98/C41 -> -0.0063892529 | D103: =D98/D41 -> 0.044486813 | E103: =E98/E41 -> 0.14084507 | F103: =F98/F41 -> 0.16534026 | G103: =G98/G41 -> -0.079001368 | H103: =H98/H41 -> 0.07550919 | I103: =I98/I41 -> 0.13770053 | J103: =J98/J41 -> 0.19875573 | ... BE103: =BE98/BE41 -> 0.05340766 | BM103: =BM98/BM41 -> 0.085925145 | BN103: =BN98/BN41 -> 0.084740815 | BO103: =BO98/BO41 -> 0.071877922 | BP103: =BP98/BP41 -> 0.076621064 | BQ103: =BQ98/BQ41 -> 0.064797723 | BR103: =BR98/BR41 -> 0.08566207 | BS103: =BS98/BS41 -> 0.10516829 | BT103: =BT98/BT41 -> 0.07839887 | ... BY103: =BY98/BY41 -> 0.078824427
B104: CapEx as % of Revenue | C104: =C97/C41 -> -0.0065530799 | D104: =D97/D41 -> -0.0076263108 | E104: =E97/E41 -> -0.0147396 | F104: =F97/F41 -> -0.030209518 | G104: =G97/G41 -> -0.010259918 | H104: =H97/H41 -> -0.019208478 | I104: =I97/I41 -> -0.018215241 | J104: =J97/J41 -> -0.04518664 | ... BE104: =BE97/BE41 -> -0.069681712 | BM104: =BM97/BM41 -> -0.014760148 | BN104: =BN97/BN41 -> -0.023395471 | BO104: =BO97/BO41 -> -0.020020403 | BP104: =BP97/BP41 -> -0.037237918 | BQ104: =BQ97/BQ41 -> -0.035686817 | BR104: =BR97/BR41 -> -0.041501911 | BS104: =BS97/BS41 -> -0.037351142 | BT104: =BT97/BT41 -> -0.038588005 | ... BY104: =BY97/BY41 -> -0.034561663

Sheet Notes | Quant Analysis
CI1: 0
P2: Employee Scope: | AL2: General Notes/Observations
AL35: Financial Stmts. Notes/Observations
P36: Institutional Ownership Snapshot | AL36: Revenues:
P69: Revenue Breakdown by Segment | AL69: Earnings Scope:
Q101: Notes: | R101: [X]
R102: [Y]
R103: [Z]
P105: Revenue Breakdown by Segment | AL105: Balance Sheet Scope:
Q137: Notes: | R137: [X]
R138: [Y] | AL138: [Equity Preformance Compared to Peers]
R139: [Z]
P141: Q/q Total Revenues, Net Income, FCF
Q170: Notes: | R170: [X]
R171: [Y]
R172: [Z]
P174: Y/y Total Revenues, Net Income, FCF
Q203: Notes: | R203: [X]
R204: [Y]
R205: [Z]
A220: VOO Historical Returns | I220: NOC Historical Returns
A221: 1256 Trading Days? (From: 9/30/2020 - 9/30/2026) | I221: 1256 Trading Days? (From: 9/30/2020 - 9/30/2026)
A222: Close | B222: High | C222: Low | D222: Open | E222: Volume | F222: UTC Date | G222: Change | I222: Close | J222: High | K222: Low | L222: Open | M222: Volume | N222: UTC Date | O222: Change
A223: 605.40586 | B223: 605.8804 | C223: 601.34267 | D223: 602.48946 | E223: 6556087.5 | F223: Tue, 30 Sep 2025 00:00:00 GMT | G223: =A223/D223-1 -> 0.0048405887 | I223: 599.54549 | J223: 600.33266 | K223: 583.58569 | L223: 583.58569 | M223: 815710.35 | N223: Tue, 30 Sep 2025 00:00:00 GMT | O223: =I223/L223-1 -> 0.027347833
A224: 603.18149 | B224: 604.71384 | C224: 601.55028 | D224: 603.83397 | E224: 5724023.5 | F224: Mon, 29 Sep 2025 00:00:00 GMT | G224: =A224/D224-1 -> -0.0010805678 | I224: 584.46141 | J224: 594.43383 | K224: 582.0212 | L224: 588.71211 | M224: 789810.88 | N224: Mon, 29 Sep 2025 00:00:00 GMT | O224: =I224/L224-1 -> -0.0072203373
A225: 601.49096 | B225: 602.02329 | C225: 597.94704 | D225: 599.39123 | E225: 6531431.3 | F225: Fri, 26 Sep 2025 00:00:00 GMT | G225: =A225/D225-1 -> 0.0035031166 | I225: 584.98291 | J225: 585.41585 | K225: 577.43595 | L225: 580.0336 | M225: 519347.19 | N225: Fri, 26 Sep 2025 00:00:00 GMT | O225: =I225/L225-1 -> 0.0085327995
A226: 597.97168 | B226: 599.29265 | C226: 594.77772 | D226: 598.00126 | E226: 7027592.7 | F226: Thu, 25 Sep 2025 00:00:00 GMT | G226: =A226/D226-1 -> -4.9454354e-05 | I226: 576.37327 | J226: 584.22526 | K226: 573.14097 | L226: 580.53542 | M226: 1062869.2 | N226: Thu, 25 Sep 2025 00:00:00 GMT | O226: =I226/L226-1 -> -0.0071694915
A227: 600.84034 | B227: 604.03431 | C227: 599.54895 | D227: 603.92587 | E227: 24106581 | F227: Wed, 24 Sep 2025 00:00:00 GMT | G227: =A227/D227-1 -> -0.0051091197 | I227: 576.86525 | J227: 580.14184 | K227: 567.74396 | L227: 571.32557 | M227: 796791.87 | N227: Wed, 24 Sep 2025 00:00:00 GMT | O227: =I227/L227-1 -> 0.0096961973
A228: 602.85136 | B228: 606.5185 | C228: 601.66939 | D228: 605.97139 | E228: 10883179 | F228: Tue, 23 Sep 2025 00:00:00 GMT | G228: =A228/D228-1 -> -0.0051488112 | I228: 567.82268 | J228: 571.35017 | K228: 561.91893 | L228: 566.76 | M228: 666890.03 | N228: Tue, 23 Sep 2025 00:00:00 GMT | O228: =I228/L228-1 -> 0.001875
A229: 606.02561 | B229: 606.47907 | C229: 601.83599 | D229: 601.84585 | E229: 11718075 | F229: Mon, 22 Sep 2025 00:00:00 GMT | G229: =A229/D229-1 -> 0.0069448994 | I229: 566.9076 | J229: 568.38107 | K229: 561.11208 | L229: 564.48706 | M229: 547755.92 | N229: Mon, 22 Sep 2025 00:00:00 GMT | O229: =I229/L229-1 -> 0.0042880301
A230: 603.08795 | B230: 603.9653 | C230: 600.19957 | D230: 601.94443 | E230: 6153076.7 | F230: Fri, 19 Sep 2025 00:00:00 GMT | G230: =A230/D230-1 -> 0.0018997085 | I230: 563.83765 | J230: 566.9076 | K230: 556.42844 | L230: 562.73561 | M230: 1502482.3 | N230: Fri, 19 Sep 2025 00:00:00 GMT | O230: =I230/L230-1 -> 0.0019583501
A231: 600.2883 | B231: 602.62462 | C231: 598.44486 | D231: 599.90384 | E231: 11188190 | F231: Thu, 18 Sep 2025 00:00:00 GMT | G231: =A231/D231-1 -> 0.00064086764 | I231: 564.5461 | J231: 567.72428 | K231: 559.2032 | L231: 562.82417 | M231: 795871.1 | N231: Thu, 18 Sep 2025 00:00:00 GMT | O231: =I231/L231-1 -> 0.0030594406
A232: 597.47879 | B232: 599.68696 | C232: 593.00329 | D232: 598.21813 | E232: 11781010 | F232: Wed, 17 Sep 2025 00:00:00 GMT | G232: =A232/D232-1 -> -0.0012359106 | I232: 567.82268 | J232: 575.61563 | K232: 567.14384 | L232: 569.81027 | M232: 803154.94 | N232: Wed, 17 Sep 2025 00:00:00 GMT | O232: =I232/L232-1 -> -0.0034881713
A233: 598.16884 | B233: 599.77568 | C233: 597.4501 | D233: 599.51938 | E233: 6458919.1 | F233: Tue, 16 Sep 2025 00:00:00 GMT | G233: =A233/D233-1 -> -0.0022526967 | I233: 570.0661 | J233: 577.81969 | K233: 566.7108 | L233: 568.72792 | M233: 1122505.9 | N233: Tue, 16 Sep 2025 00:00:00 GMT | O233: =I233/L233-1 -> 0.0023529412
A234: 598.95748 | B234: 599.13492 | C234: 597.58723 | D234: 597.85339 | E234: 7554466.4 | F234: Mon, 15 Sep 2025 00:00:00 GMT | G234: =A234/D234-1 -> 0.0018467525 | I234: 565.32342 | J234: 567.22246 | K234: 561.95337 | L234: 564.79209 | M234: 808521.02 | N234: Mon, 15 Sep 2025 00:00:00 GMT | O234: =I234/L234-1 -> 0.00094076655
A235: 595.85223 | B235: 597.37035 | C235: 595.36919 | D235: 596.0001 | E235: 8225559.2 | F235: Fri, 12 Sep 2025 00:00:00 GMT | G235: =A235/D235-1 -> -0.00024810202 | I235: 566.72064 | J235: 573.77562 | K235: 565.95316 | L235: 572.9983 | M235: 627500.15 | N235: Fri, 12 Sep 2025 00:00:00 GMT | O235: =I235/L235-1 -> -0.010955799
A236: 595.98038 | B236: 596.63101 | C236: 592.35267 | D236: 592.885 | E236: 9217770.3 | F236: Thu, 11 Sep 2025 00:00:00 GMT | G236: =A236/D236-1 -> 0.0052208902 | I236: 573.59851 | J236: 576.36344 | K236: 568.72792 | L236: 570.0169 | M236: 912824.22 | N236: Thu, 11 Sep 2025 00:00:00 GMT | O236: =I236/L236-1 -> 0.0062833371 | R236: Min | S236: =MIN(O223:O1478) -> -0.063566673
A237: 591.15986 | B237: 593.20045 | C237: 589.66146 | D237: 592.38224 | E237: 21852838 | F237: Wed, 10 Sep 2025 00:00:00 GMT | G237: =A237/D237-1 -> -0.0020635026 | I237: 570.56792 | J237: 571.52236 | K237: 560.85625 | L237: 562.07636 | M237: 515502.52 | N237: Wed, 10 Sep 2025 00:00:00 GMT | O237: =I237/L237-1 -> 0.015107485 | R237: Max | S237: =MAX(O223:O1478) -> 0.067171924
A238: 589.45444 | B238: 589.86847 | C238: 586.55621 | D238: 588.13348 | E238: 7892245.5 | F238: Tue, 09 Sep 2025 00:00:00 GMT | G238: =A238/D238-1 -> 0.0022460234 | I238: 562.4601 | J238: 571.17797 | K238: 562.27315 | L238: 571.14846 | M238: 480849.63 | N238: Tue, 09 Sep 2025 00:00:00 GMT | O238: =I238/L238-1 -> -0.015212073 | R238: Mean μ | S238: =AVERAGE(O223:O1478) -> 0.00031000386
A239: 588.02504 | B239: 588.92211 | C239: 586.57593 | D239: 587.83774 | E239: 9584467.3 | F239: Mon, 08 Sep 2025 00:00:00 GMT | G239: =A239/D239-1 -> 0.00031862622 | I239: 572.56536 | J239: 572.79167 | K239: 562.19935 | L239: 565.7662 | M239: 799143.59 | N239: Mon, 08 Sep 2025 00:00:00 GMT | O239: =I239/L239-1 -> 0.0120176 | R239: Median | S239: =MEDIAN(O223:O1478) -> 0.00054112784
A240: 586.50692 | B240: 591.081 | C240: 583.04679 | D240: 590.4008 | E240: 6717572 | F240: Fri, 05 Sep 2025 00:00:00 GMT | G240: =A240/D240-1 -> -0.0065953148 | I240: 571.483 | J240: 571.84215 | K240: 565.59893 | L240: 570.04642 | M240: 640391.95 | N240: Fri, 05 Sep 2025 00:00:00 GMT | O240: =I240/L240-1 -> 0.0025201091 | R240: SD σ | S240: =_xlfn.STDEV.P(O223:O1478) -> 0.013197297
A241: 588.11376 | B241: 588.2912 | C241: 583.19466 | D241: 584.0523 | E241: 8127957.5 | F241: Thu, 04 Sep 2025 00:00:00 GMT | G241: =A241/D241-1 -> 0.0069539386 | I241: 570.45969 | J241: 572.60471 | K241: 566.76 | L241: 572.3784 | M241: 489813.42 | N241: Thu, 04 Sep 2025 00:00:00 GMT | O241: =I241/L241-1 -> -0.0033521858 | R241: 3σ 1-Day Δ: ± | S241: =3*S240 -> 0.039591891 | U241: <- Sharpe Ratio (Risk Adjusted Return)
A242: 583.31295 | B242: 583.81571 | C242: 580.41473 | D242: 582.41588 | E242: 6766005.1 | F242: Wed, 03 Sep 2025 00:00:00 GMT | G242: =A242/D242-1 -> 0.0015402583 | I242: 571.68963 | J242: 578.5675 | K242: 568.42289 | L242: 577.12108 | M242: 466187.42 | N242: Wed, 03 Sep 2025 00:00:00 GMT | O242: =I242/L242-1 -> -0.0094112833 | R242: β (1-year avg.) | S242: =_xlfn.COVARIANCE.P(O223:O471,G223:G471)/_xlfn.VAR.P(G223:G471) -> 0.32949713 | U242: <- Sortino Ratio (Downside Risk Adjusted Return)
A243: 580.34572 | B243: 580.43444 | C243: 575.37733 | D243: 577.73337 | E243: 11223118 | F243: Tue, 02 Sep 2025 00:00:00 GMT | G243: =A243/D243-1 -> 0.0045217213 | I243: 579.86633 | J243: 586.60123 | K243: 575.87146 | L243: 582.38526 | M243: 644192.93 | N243: Tue, 02 Sep 2025 00:00:00 GMT | O243: =I243/L243-1 -> -0.0043252011
A244: 584.65363 | B244: 587.08854 | C244: 582.8447 | D244: 586.78294 | E244: 7588562.9 | F244: Fri, 29 Aug 2025 00:00:00 GMT | G244: =A244/D244-1 -> -0.0036287884 | I244: 578.30183 | J244: 579.80316 | K244: 575.40072 | L244: 576.20441 | M244: 538308.02 | N244: Fri, 29 Aug 2025 00:00:00 GMT | O244: =I244/L244-1 -> 0.0036400748 | Q244: n = | R244: 1014
A245: 588.04476 | B245: 588.58694 | C245: 584.84093 | D245: 586.61536 | E245: 5110593.3 | F245: Thu, 28 Aug 2025 00:00:00 GMT | G245: =A245/D245-1 -> 0.0024366881 | I245: 576.20441 | J245: 576.24361 | K245: 569.34366 | L245: 574.94007 | M245: 488397.1 | N245: Thu, 28 Aug 2025 00:00:00 GMT | O245: =I245/L245-1 -> 0.002199076 | Q245: Histogram Data | T245: Distribution Overlay | X245: SD Lines
A246: 585.97459 | B246: 586.68436 | C246: 584.02272 | D246: 584.10159 | E246: 6177330.3 | F246: Wed, 27 Aug 2025 00:00:00 GMT | G246: =A246/D246-1 -> 0.0032066428 | I246: 574.94007 | J246: 582.72211 | K246: 573.39895 | L246: 582.72211 | M246: 689158.01 | N246: Wed, 27 Aug 2025 00:00:00 GMT | O246: =I246/L246-1 -> -0.013354638 | Q246: Bin | R246: Frequency | T246: (X) 1-Day Δ | U246: (Y) Pop. Density | X246: X | Y246: Y
A247: 584.63392 | B247: 584.99866 | C247: 581.4153 | D247: 581.99199 | E247: 4815265.4 | F247: Tue, 26 Aug 2025 00:00:00 GMT | G247: =A247/D247-1 -> 0.0045394492 | I247: 581.22255 | J247: 583.99625 | K247: 576.41513 | L247: 576.68466 | M247: 1021643.4 | N247: Tue, 26 Aug 2025 00:00:00 GMT | O247: =I247/L247-1 -> 0.0078689305 | Q247: -0.04 | R247: 10 | T247: =T248-0.001 -> -0.042 | U247: =_xlfn.NORM.DIST(T247,$S$238,$S$240,FALSE) -> 0.17723399 | W247: Mean | X247: =S238 -> 0.00031000386 | Y247: 0
A248: 582.30745 | B248: 584.8014 | C248: 582.15958 | D248: 583.63827 | E248: 6576472.3 | F248: Mon, 25 Aug 2025 00:00:00 GMT | G248: =A248/D248-1 -> -0.0022802128 | I248: 575.06748 | J248: 583.5552 | K248: 574.39121 | L248: 580.22284 | M248: 487903.27 | N248: Mon, 25 Aug 2025 00:00:00 GMT | O248: =I248/L248-1 -> -0.0088851351 | Q248: -0.039 | R248: 1 | T248: =T249-0.001 -> -0.041 | U248: =_xlfn.NORM.DIST(T248,$S$238,$S$240,FALSE) -> 0.22532089 | X248: =S238 -> 0.00031000386 | Y248: 30
A249: 584.78178 | B249: 585.87601 | C249: 577.5165 | D249: 577.94039 | E249: 6460329.1 | F249: Fri, 22 Aug 2025 00:00:00 GMT | G249: =A249/D249-1 -> 0.011837549 | I249: 580.65409 | J249: 589.034 | K249: 579.60283 | L249: 587.85787 | M249: 628359.49 | N249: Fri, 22 Aug 2025 00:00:00 GMT | O249: =I249/L249-1 -> -0.012254289 | Q249: -0.038 | R249: 0 | T249: =T250-0.001 -> -0.04 | U249: =_xlfn.NORM.DIST(T249,$S$238,$S$240,FALSE) -> 0.28481467 | W249: -3σ | X249: =($S$240*-3)+$S$238 -> -0.039281887 | Y249: 0
A250: 575.9688 | B250: 578.12769 | C250: 574.37182 | D250: 576.61943 | E250: 4876562.3 | F250: Thu, 21 Aug 2025 00:00:00 GMT | G250: =A250/D250-1 -> -0.0011283401 | I250: 585.32919 | J250: 586.91697 | K250: 579.54951 | L250: 581.20295 | M250: 622675.41 | N250: Thu, 21 Aug 2025 00:00:00 GMT | O250: =I250/L250-1 -> 0.0070994941 | Q250: -0.037 | R250: 0 | T250: =T251-0.001 -> -0.039 | U250: =_xlfn.NORM.DIST(T250,$S$238,$S$240,FALSE) -> 0.35795607 | X250: =($S$240*-3)+$S$238 -> -0.039281887 | Y250: 2
A251: 578.24598 | B251: 579.64581 | C251: 573.58319 | D251: 579.45851 | E251: 7155936.2 | F251: Wed, 20 Aug 2025 00:00:00 GMT | G251: =A251/D251-1 -> -0.0020925129 | I251: 580.7521 | J251: 583.47679 | K251: 576.07699 | L251: 578.10581 | M251: 620631.75 | N251: Wed, 20 Aug 2025 00:00:00 GMT | O251: =I251/L251-1 -> 0.0045775125 | Q251: -0.036 | R251: 1 | T251: =T252-0.001 -> -0.038 | U251: =_xlfn.NORM.DIST(T251,$S$238,$S$240,FALSE) -> 0.44730482 | W251: -2σ | X251: =($S$240*-2)+$S$238 -> -0.02608459 | Y251: 0
A252: 579.77396 | B252: 583.70727 | C252: 578.60087 | D252: 582.84963 | E252: 6786010.3 | F252: Tue, 19 Aug 2025 00:00:00 GMT | G252: =A252/D252-1 -> -0.0052769556 | I252: 574.56763 | J252: 577.75297 | K252: 570.63985 | L252: 572.38199 | M252: 477032 | N252: Tue, 19 Aug 2025 00:00:00 GMT | O252: =I252/L252-1 -> 0.0038184932 | Q252: -0.035 | R252: 1 | T252: =T253-0.001 -> -0.037 | U252: =_xlfn.NORM.DIST(T252,$S$238,$S$240,FALSE) -> 0.55575567 | X252: =($S$240*-2)+$S$238 -> -0.02608459 | Y252: 7
A253: 582.95807 | B253: 583.60869 | C253: 581.96242 | D253: 582.58347 | E253: 5388298.9 | F253: Mon, 18 Aug 2025 00:00:00 GMT | G253: =A253/D253-1 -> 0.00064299976 | I253: 573.18568 | J253: 580.44337 | K253: 571.93144 | L253: 575.78296 | M253: 941123.57 | N253: Mon, 18 Aug 2025 00:00:00 GMT | O253: =I253/L253-1 -> -0.0045108686 | Q253: -0.034 | R253: 0 | T253: =T254-0.001 -> -0.036 | U253: =_xlfn.NORM.DIST(T253,$S$238,$S$240,FALSE) -> 0.68654767 | W253: -1σ | X253: =($S$240*-1)+$S$238 -> -0.012887293 | Y253: 0
A254: 583.16509 | B254: 585.51127 | C254: 582.26801 | D254: 585.42255 | E254: 7300032.5 | F254: Fri, 15 Aug 2025 00:00:00 GMT | G254: =A254/D254-1 -> -0.0038561277 | I254: 572.34279 | J254: 575.07728 | K254: 569.36189 | L254: 571.80373 | M254: 681129.28 | N254: Fri, 15 Aug 2025 00:00:00 GMT | O254: =I254/L254-1 -> 0.00094273324 | Q254: -0.033 | R254: 1 | T254: =T255-0.001 -> -0.035 | U254: =_xlfn.NORM.DIST(T254,$S$238,$S$240,FALSE) -> 0.84326477 | X254: =($S$240*-1)+$S$238 -> -0.012887293 | Y254: 18
A255: 584.4269 | B255: 585.07752 | C255: 582.11029 | D255: 582.52432 | E255: 6326552.5 | F255: Thu, 14 Aug 2025 00:00:00 GMT | G255: =A255/D255-1 -> 0.0032660935 | I255: 572.10756 | J255: 573.64143 | K255: 569.37797 | L255: 572.27418 | M255: 554362.4 | N255: Thu, 14 Aug 2025 00:00:00 GMT | O255: =I255/L255-1 -> -0.00029115073 | Q255: -0.032 | R255: 2 | T255: =T256-0.001 -> -0.034 | U255: =_xlfn.NORM.DIST(T255,$S$238,$S$240,FALSE) -> 1.0298256 | W255: 1σ | X255: =($S$240*1)+$S$238 -> 0.013507301 | Y255: 0
A256: 584.41704 | B256: 585.59013 | C256: 582.41588 | D256: 584.43676 | E256: 5470699.7 | F256: Wed, 13 Aug 2025 00:00:00 GMT | G256: =A256/D256-1 -> -3.3734777e-05 | I256: 570.50999 | J256: 575.21117 | K256: 564.75677 | L256: 570.90203 | M256: 760811.47 | N256: Wed, 13 Aug 2025 00:00:00 GMT | O256: =I256/L256-1 -> -0.00068670707 | Q256: -0.031 | R256: 3 | T256: =T257-0.001 -> -0.033 | U256: =_xlfn.NORM.DIST(T256,$S$238,$S$240,FALSE) -> 1.2504603 | X256: =($S$240*1)+$S$238 -> 0.013507301 | Y256: 18
A257: 582.38631 | B257: 582.56375 | C257: 577.11725 | D257: 578.41357 | E257: 5958908 | F257: Tue, 12 Aug 2025 00:00:00 GMT | G257: =A257/D257-1 -> 0.0068683426 | I257: 569.24565 | J257: 570.05424 | K257: 566.12891 | L257: 567.68728 | M257: 656962.51 | N257: Tue, 12 Aug 2025 00:00:00 GMT | O257: =I257/L257-1 -> 0.0027451184 | Q257: -0.03 | R257: 3 | T257: =T258-0.001 -> -0.032 | U257: =_xlfn.NORM.DIST(T257,$S$238,$S$240,FALSE) -> 1.5096719 | W257: 2σ | X257: =($S$240*2)+$S$238 -> 0.026704598 | Y257: 0
A258: 576.23497 | B258: 579.0149 | C258: 575.1506 | D258: 577.7038 | E258: 5451401.5 | F258: Mon, 11 Aug 2025 00:00:00 GMT | G258: =A258/D258-1 -> -0.002542532 | I258: 568.69679 | J258: 572.16147 | K258: 564.00208 | L258: 568.27535 | M258: 759912.59 | N258: Mon, 11 Aug 2025 00:00:00 GMT | O258: =I258/L258-1 -> 0.00074162226 | Q258: -0.029 | R258: 2 | T258: =T259-0.001 -> -0.031 | U258: =_xlfn.NORM.DIST(T258,$S$238,$S$240,FALSE) -> 1.8121816 | X258: =($S$240*2)+$S$238 -> 0.026704598 | Y258: 7
A259: 577.41792 | B259: 577.84181 | C259: 574.32253 | D259: 574.64784 | E259: 4404925.3 | F259: Fri, 08 Aug 2025 00:00:00 GMT | G259: =A259/D259-1 -> 0.0048204759 | I259: 569.54949 | J259: 579.31134 | K259: 567.62848 | L259: 576.01819 | M259: 764692.68 | N259: Fri, 08 Aug 2025 00:00:00 GMT | O259: =I259/L259-1 -> -0.011230028 | Q259: -0.028 | R259: 4 | T259: =T260-0.001 -> -0.03 | U259: =_xlfn.NORM.DIST(T259,$S$238,$S$240,FALSE) -> 2.1628547 | W259: 3σ | X259: =($S$240*3)+$S$238 -> 0.039901895 | Y259: 0
A260: 573.03114 | B260: 577.20104 | C260: 570.09614 | D260: 576.56028 | E260: 4660475.1 | F260: Thu, 07 Aug 2025 00:00:00 GMT | G260: =A260/D260-1 -> -0.0061210183 | I260: 575.69475 | J260: 576.52784 | K260: 568.46157 | L260: 571.60771 | M260: 639360.34 | N260: Thu, 07 Aug 2025 00:00:00 GMT | O260: =I260/L260-1 -> 0.0071500832 | Q260: -0.027 | R260: 2 | T260: =T261-0.001 -> -0.029 | U260: =_xlfn.NORM.DIST(T260,$S$238,$S$240,FALSE) -> 2.5666074 | X260: =($S$240*3)+$S$238 -> 0.039901895 | Y260: 2
A261: 573.37617 | B261: 573.99722 | C261: 569.20627 | D261: 570.03433 | E261: 4610520.4 | F261: Wed, 06 Aug 2025 00:00:00 GMT | G261: =A261/D261-1 -> 0.0058625162 | I261: 577.56675 | J261: 581.6734 | K261: 575.02828 | L261: 578.26263 | M261: 1012701.5 | N261: Wed, 06 Aug 2025 00:00:00 GMT | O261: =I261/L261-1 -> -0.0012033898 | Q261: -0.026 | R261: 6 | T261: =T262-0.001 -> -0.028 | U261: =_xlfn.NORM.DIST(T261,$S$238,$S$240,FALSE) -> 3.0282938
A262: 569.14712 | B262: 573.23816 | C262: 568.21062 | D262: 572.53825 | E262: 4714361.8 | F262: Tue, 05 Aug 2025 00:00:00 GMT | G262: =A262/D262-1 -> -0.005922967 | I262: 578.21362 | J262: 582.84953 | K262: 574.35201 | L262: 578.47825 | M262: 924208.06 | N262: Tue, 05 Aug 2025 00:00:00 GMT | O262: =I262/L262-1 -> -0.00045745654 | Q262: -0.025 | R262: 3 | T262: =T263-0.001 -> -0.027 | U262: =_xlfn.NORM.DIST(T262,$S$238,$S$240,FALSE) -> 3.5525733
A263: 571.89748 | B263: 571.96649 | C263: 566.90937 | D263: 566.99809 | E263: 6735789.8 | F263: Mon, 04 Aug 2025 00:00:00 GMT | G263: =A263/D263-1 -> 0.0086409236 | I263: 578.0176 | J263: 580.37966 | K263: 572.50451 | L263: 574.03837 | M263: 990042.76 | N263: Mon, 04 Aug 2025 00:00:00 GMT | O263: =I263/L263-1 -> 0.0069319947 | Q263: -0.024 | R263: 2 | T263: =T264-0.001 -> -0.026 | U263: =_xlfn.NORM.DIST(T263,$S$238,$S$240,FALSE) -> 4.1437596
A264: 563.33095 | B264: 567.56 | C264: 561.20164 | D264: 567.55014 | E264: 8907814.5 | F264: Fri, 01 Aug 2025 00:00:00 GMT | G264: =A264/D264-1 -> -0.0074340403 | I264: 574.77345 | J264: 576.1848 | K264: 561.55182 | L264: 565.65356 | M264: 1026931.6 | N264: Fri, 01 Aug 2025 00:00:00 GMT | O264: =I264/L264-1 -> 0.016122744 | Q264: -0.023 | R264: 1 | T264: =T265-0.001 -> -0.025 | U264: =_xlfn.NORM.DIST(T264,$S$238,$S$240,FALSE) -> 4.8056543
A265: 572.76498 | B265: 579.80491 | C265: 571.60174 | D265: 579.47822 | E265: 7148406.2 | F265: Thu, 31 Jul 2025 00:00:00 GMT | G265: =A265/D265-1 -> -0.011584982 | I265: 565.13901 | J265: 565.89369 | K265: 557.57269 | L265: 560.62072 | M265: 867932.52 | N265: Thu, 31 Jul 2025 00:00:00 GMT | O265: =I265/L265-1 -> 0.0080594406 | Q265: -0.022 | R265: 7 | T265: =T266-0.001 -> -0.024 | U265: =_xlfn.NORM.DIST(T265,$S$238,$S$240,FALSE) -> 5.5413678
A266: 574.92386 | B266: 577.82209 | C266: 572.30166 | D266: 576.35326 | E266: 7075252.9 | F266: Wed, 30 Jul 2025 00:00:00 GMT | G266: =A266/D266-1 -> -0.0024800739 | I266: 561.4146 | J266: 562.39461 | K266: 557.39715 | L266: 561.54202 | M266: 675201.35 | N266: Wed, 30 Jul 2025 00:00:00 GMT | O266: =I266/L266-1 -> -0.00022689985 | Q266: -0.021 | R266: 6 | T266: =T267-0.001 -> -0.023 | U266: =_xlfn.NORM.DIST(T266,$S$238,$S$240,FALSE) -> 6.3531323
A267: 575.62378 | B267: 578.73888 | C267: 574.83514 | D267: 578.48257 | E267: 5105851 | F267: Tue, 29 Jul 2025 00:00:00 GMT | G267: =A267/D267-1 -> -0.0049418902 | I267: 561.81645 | J267: 561.89486 | K267: 556.88651 | L267: 560.03265 | M267: 695897.07 | N267: Tue, 29 Jul 2025 00:00:00 GMT | O267: =I267/L267-1 -> 0.0031851593 | Q267: -0.02 | R267: 4 | T267: =T268-0.001 -> -0.022 | U267: =_xlfn.NORM.DIST(T267,$S$238,$S$240,FALSE) -> 7.242113
A268: 577.12218 | B268: 578.16712 | C268: 575.93923 | D268: 577.71365 | E268: 4229956.4 | F268: Mon, 28 Jul 2025 00:00:00 GMT | G268: =A268/D268-1 -> -0.0010238209 | I268: 557.30796 | J268: 558.66051 | K268: 552.42703 | L268: 557.91563 | M268: 692309.71 | N268: Mon, 28 Jul 2025 00:00:00 GMT | O268: =I268/L268-1 -> -0.0010891715 | Q268: -0.019 | R268: 6 | T268: =T269-0.001 -> -0.021 | U268: =_xlfn.NORM.DIST(T268,$S$238,$S$240,FALSE) -> 8.2082233
A269: 577.26019 | B269: 577.71365 | C269: 575.29846 | D269: 575.51534 | E269: 3235023.6 | F269: Fri, 25 Jul 2025 00:00:00 GMT | G269: =A269/D269-1 -> 0.0030318083 | I269: 558.40568 | J269: 558.81242 | K269: 552.0987 | L269: 556.70029 | M269: 645492.33 | N269: Fri, 25 Jul 2025 00:00:00 GMT | O269: =I269/L269-1 -> 0.0030633803 | Q269: -0.018 | R269: 12 | T269: =T270-0.001 -> -0.02 | U269: =_xlfn.NORM.DIST(T269,$S$238,$S$240,FALSE) -> 9.2499524
A270: 574.97315 | B270: 576.44198 | C270: 574.44082 | D270: 575.05202 | E270: 3896258.3 | F270: Thu, 24 Jul 2025 00:00:00 GMT | G270: =A270/D270-1 -> -0.00013714129 | I270: 557.17074 | J270: 565.38403 | K270: 555.30864 | L270: 556.94532 | M270: 994743.27 | N270: Thu, 24 Jul 2025 00:00:00 GMT | O270: =I270/L270-1 -> 0.00040475143 | Q270: -0.017 | R270: 10 | T270: =T271-0.001 -> -0.019 | U270: =_xlfn.NORM.DIST(T270,$S$238,$S$240,FALSE) -> 10.364212
A271: 574.57884 | B271: 574.67741 | C271: 570.64552 | D271: 572.32137 | E271: 4318704.3 | F271: Wed, 23 Jul 2025 00:00:00 GMT | G271: =A271/D271-1 -> 0.0039443995 | I271: 557.19035 | J271: 557.35696 | K271: 540.82747 | L271: 551.16269 | M271: 1276471.9 | N271: Wed, 23 Jul 2025 00:00:00 GMT | O271: =I271/L271-1 -> 0.01093625 | Q271: -0.016 | R271: 17 | T271: =T272-0.001 -> -0.018 | U271: =_xlfn.NORM.DIST(T271,$S$238,$S$240,FALSE) -> 11.546214
A272: 569.7386 | B272: 570.61595 | C272: 567.46142 | D272: 570.06391 | E272: 4812047.7 | F272: Tue, 22 Jul 2025 00:00:00 GMT | G272: =A272/D272-1 -> -0.00057065781 | I272: 552.57405 | J272: 555.84113 | K272: 524.86645 | L272: 525.3467 | M272: 2441934.5 | N272: Tue, 22 Jul 2025 00:00:00 GMT | O272: =I272/L272-1 -> 0.051827391 | Q272: -0.015 | R272: 14 | T272: =T273-0.001 -> -0.017 | U272: =_xlfn.NORM.DIST(T272,$S$238,$S$240,FALSE) -> 12.789375
... A288: 557.17497 | B288: 558.53118 | C288: 553.49945 | D288: 555.36669 | E288: 6162779.1 | F288: Fri, 27 Jun 2025 00:00:00 GMT | G288: =A288/D288-1 -> 0.0032560033 | I288: 484.17244 | J288: 484.83891 | K288: 479.52674 | L288: 481.18311 | M288: 892109.49 | N288: Fri, 27 Jun 2025 00:00:00 GMT | O288: =I288/L288-1 -> 0.0062124453 | Q288: 0.001 | R288: 47 | T288: =T289-0.001 -> -0.001 | U288: =_xlfn.NORM.DIST(T288,$S$238,$S$240,FALSE) -> 30.08053
A289: 554.42325 | B289: 554.81635 | C289: 551.28825 | D289: 551.83859 | E289: 6188136.3 | F289: Thu, 26 Jun 2025 00:00:00 GMT | G289: =A289/D289-1 -> 0.0046837156 | I289: 483.8392 | J289: 487.15196 | K289: 477.97817 | L289: 479.45813 | M289: 894242.93 | N289: Thu, 26 Jun 2025 00:00:00 GMT | O289: =I289/L289-1 -> 0.0091375539 | Q289: 0.002 | R289: 52 | T289: 0 | U289: =_xlfn.NORM.DIST(T289,$S$238,$S$240,FALSE) -> 30.220751
A290: 550.06963 | B290: 551.34721 | C290: 548.71342 | D290: 550.85583 | E290: 16761294 | F290: Wed, 25 Jun 2025 00:00:00 GMT | G290: =A290/D290-1 -> -0.0014272461 | I290: 477.23329 | J290: 478.74265 | K290: 474.21456 | L290: 478.2918 | M290: 739541.32 | N290: Wed, 25 Jun 2025 00:00:00 GMT | O290: =I290/L290-1 -> -0.0022131148 | Q290: 0.003 | R290: 44 | T290: =T289+0.001 -> 0.001 | U290: =_xlfn.NORM.DIST(T290,$S$238,$S$240,FALSE) -> 30.187802
A291: 549.79445 | B291: 550.76738 | C291: 546.77738 | D291: 547.57342 | E291: 6888808.9 | F291: Tue, 24 Jun 2025 00:00:00 GMT | G291: =A291/D291-1 -> 0.0040561398 | I291: 474.37138 | J291: 485.27016 | K291: 471.70549 | L291: 484.95652 | M291: 949507.36 | N291: Tue, 24 Jun 2025 00:00:00 GMT | O291: =I291/L291-1 -> -0.021827001 | Q291: 0.004 | R291: 55 | T291: =T290+0.001 -> 0.002 | U291: =_xlfn.NORM.DIST(T291,$S$238,$S$240,FALSE) -> 29.982249
A292: 543.81928 | B292: 544.15342 | C292: 536.34049 | D292: 539.20032 | E292: 9861171.7 | F292: Mon, 23 Jun 2025 00:00:00 GMT | G292: =A292/D292-1 -> 0.0085663252 | I292: 489.72964 | J292: 498.20756 | K292: 486.56507 | L292: 490.84696 | M292: 981316.16 | N292: Mon, 23 Jun 2025 00:00:00 GMT | O292: =I292/L292-1 -> -0.0022763124 | Q292: 0.005 | R292: 44 | T292: =T291+0.001 -> 0.003 | U292: =_xlfn.NORM.DIST(T292,$S$238,$S$240,FALSE) -> 29.607613
A293: 538.27652 | B293: 543.19032 | C293: 537.19549 | D293: 542.20756 | E293: 10117295 | F293: Fri, 20 Jun 2025 00:00:00 GMT | G293: =A293/D293-1 -> -0.0072500544 | I293: 487.79883 | J293: 489.91586 | K293: 478.2918 | L293: 486.74032 | M293: 931395.03 | N293: Fri, 20 Jun 2025 00:00:00 GMT | O293: =I293/L293-1 -> 0.002174701 | Q293: 0.006 | R293: 37 | T293: =T292+0.001 -> 0.004 | U293: =_xlfn.NORM.DIST(T293,$S$238,$S$240,FALSE) -> 29.070269
A294: 539.77032 | B294: 543.18049 | C294: 538.93497 | D294: 540.67445 | E294: 4683071.9 | F294: Wed, 18 Jun 2025 00:00:00 GMT | G294: =A294/D294-1 -> -0.0016722408 | I294: 484.80951 | J294: 496.52168 | K294: 483.76079 | L294: 494.38514 | M294: 808769.54 | N294: Wed, 18 Jun 2025 00:00:00 GMT | O294: =I294/L294-1 -> -0.01936878 | Q294: 0.007 | R294: 34 | T294: =T293+0.001 -> 0.005 | U294: =_xlfn.NORM.DIST(T294,$S$238,$S$240,FALSE) -> 28.379267
A295: 539.87842 | B295: 543.62273 | C295: 539.17575 | D295: 542.27635 | E295: 4836736.3 | F295: Tue, 17 Jun 2025 00:00:00 GMT | G295: =A295/D295-1 -> -0.0044219721 | I295: 493.9441 | J295: 495.7867 | K295: 488.15069 | L295: 492.01329 | M295: 779812.47 | N295: Tue, 17 Jun 2025 00:00:00 GMT | O295: =I295/L295-1 -> 0.0039243028 | Q295: 0.008 | R295: 49 | T295: =T294+0.001 -> 0.006 | U295: =_xlfn.NORM.DIST(T295,$S$238,$S$240,FALSE) -> 27.546078
A296: 544.51704 | B296: 546.10911 | C296: 542.35497 | D296: 542.42376 | E296: 7551526.1 | F296: Mon, 16 Jun 2025 00:00:00 GMT | G296: =A296/D296-1 -> 0.0038591151 | I296: 487.62241 | J296: 504.75467 | K296: 485.72101 | L296: 500.64802 | M296: 1192383.1 | N296: Mon, 16 Jun 2025 00:00:00 GMT | O296: =I296/L296-1 -> -0.026017502 | Q296: 0.009 | R296: 25 | T296: =T295+0.001 -> 0.007 | U296: =_xlfn.NORM.DIST(T296,$S$238,$S$240,FALSE) -> 26.584276
A297: 539.30842 | B297: 543.70626 | C297: 537.97187 | D297: 540.75307 | E297: 7186216.7 | F297: Fri, 13 Jun 2025 00:00:00 GMT | G297: =A297/D297-1 -> -0.0026715615 | I297: 506.44045 | J297: 509.09654 | K297: 493.18941 | L297: 493.9735 | M297: 1872611.5 | N297: Fri, 13 Jun 2025 00:00:00 GMT | O297: =I297/L297-1 -> 0.025238095 | Q297: 0.01 | R297: 34 | T297: =T296+0.001 -> 0.008 | U297: =_xlfn.NORM.DIST(T297,$S$238,$S$240,FALSE) -> 25.509173
A298: 545.38187 | B298: 545.43101 | C298: 541.62989 | D298: 542.08963 | E298: 8570714.4 | F298: Thu, 12 Jun 2025 00:00:00 GMT | G298: =A298/D298-1 -> 0.0060732415 | I298: 487.24017 | J298: 487.42639 | K298: 478.2379 | L298: 479.09549 | M298: 648069.6 | N298: Thu, 12 Jun 2025 00:00:00 GMT | O298: =I298/L298-1 -> 0.017000123 | Q298: 0.011 | R298: 27 | T298: =T297+0.001 -> 0.009 | U298: =_xlfn.NORM.DIST(T298,$S$238,$S$240,FALSE) -> 24.337412
A299: 543.3279 | B299: 546.63488 | C299: 541.41152 | D299: 545.83394 | E299: 21165480 | F299: Wed, 11 Jun 2025 00:00:00 GMT | G299: =A299/D299-1 -> -0.0045912029 | I299: 478.74265 | J299: 478.98768 | K299: 462.62971 | L299: 473.94993 | M299: 913420.45 | N299: Wed, 11 Jun 2025 00:00:00 GMT | O299: =I299/L299-1 -> 0.01011229 | Q299: 0.012 | R299: 30 | T299: =T298+0.001 -> 0.01 | U299: =_xlfn.NORM.DIST(T299,$S$238,$S$240,FALSE) -> 23.086541
A300: 544.83152 | B300: 545.17549 | C300: 541.24445 | D300: 542.26652 | E300: 6055698.9 | F300: Tue, 10 Jun 2025 00:00:00 GMT | G300: =A300/D300-1 -> 0.0047301461 | I300: 479.07589 | J300: 481.75158 | K300: 476.95396 | L300: 481.75158 | M300: 542840.18 | N300: Tue, 10 Jun 2025 00:00:00 GMT | O300: =I300/L300-1 -> -0.0055540862 | Q300: 0.013 | R300: 25 | T300: =T299+0.001 -> 0.011 | U300: =_xlfn.NORM.DIST(T300,$S$238,$S$240,FALSE) -> 21.774582
A301: 541.74566 | B301: 543.17066 | C301: 540.71376 | D301: 541.7948 | E301: 4561016.5 | F301: Mon, 09 Jun 2025 00:00:00 GMT | G301: =A301/D301-1 -> -9.0694722e-05 | I301: 481.58496 | J301: 482.32004 | K301: 474.13615 | L301: 480.25201 | M301: 629988.9 | N301: Mon, 09 Jun 2025 00:00:00 GMT | O301: =I301/L301-1 -> 0.0027755102 | Q301: 0.014 | R301: 11 | T301: =T300+0.001 -> 0.012 | U301: =_xlfn.NORM.DIST(T301,$S$238,$S$240,FALSE) -> 20.419601
... A327: 504.49911 | B327: 509.50135 | C327: 503.92911 | D327: 506.24842 | E327: 5885965.5 | F327: Thu, 01 May 2025 00:00:00 GMT | G327: =A327/D327-1 -> -0.0034554384 | I327: 474.71534 | J327: 476.1785 | K327: 470.24589 | L327: 473.25219 | M327: 1224095.9 | N327: Thu, 01 May 2025 00:00:00 GMT | O327: =I327/L327-1 -> 0.0030916998 | Q327: 0.04 | R327: 0 | T327: =T326+0.001 -> 0.038 | U327: =_xlfn.NORM.DIST(T327,$S$238,$S$240,FALSE) -> 0.51209654
A328: 500.95135 | B328: 502.68101 | C328: 489.1779 | D328: 494.58308 | E328: 8011821.3 | F328: Wed, 30 Apr 2025 00:00:00 GMT | G328: =A328/D328-1 -> 0.012876048 | I328: 474.54952 | J328: 475.83709 | K328: 463.85874 | L328: 472.19872 | M328: 1345702.1 | N328: Wed, 30 Apr 2025 00:00:00 GMT | O328: =I328/L328-1 -> 0.0049784131 | Q328: More | R328: 11 | T328: =T327+0.001 -> 0.039 | U328: =_xlfn.NORM.DIST(T328,$S$238,$S$240,FALSE) -> 0.41126713
A329: 500.70566 | B329: 501.74709 | C329: 495.56584 | D329: 495.84101 | E329: 6639939.1 | F329: Tue, 29 Apr 2025 00:00:00 GMT | G329: =A329/D329-1 -> 0.0098109169 | I329: 470.2576 | J329: 475.14941 | K329: 468.20918 | L329: 471.90609 | M329: 1001967.5 | N329: Tue, 29 Apr 2025 00:00:00 GMT | O329: =I329/L329-1 -> -0.0034932512 | T329: =T328+0.001 -> 0.04 | U329: =_xlfn.NORM.DIST(T329,$S$238,$S$240,FALSE) -> 0.32839961
A330: 497.68859 | B330: 499.96859 | C330: 492.32273 | D330: 498.07187 | E330: 4283876.2 | F330: Mon, 28 Apr 2025 00:00:00 GMT | G330: =A330/D330-1 -> -0.00076951915 | I330: 471.43788 | J330: 475.03724 | K330: 463.8685 | L330: 463.8685 | M330: 1863094.4 | N330: Mon, 28 Apr 2025 00:00:00 GMT | O330: =I330/L330-1 -> 0.016317948 | T330: =T329+0.001 -> 0.041 | U330: =_xlfn.NORM.DIST(T330,$S$238,$S$240,FALSE) -> 0.26072804
A331: 497.38394 | B331: 497.78687 | C331: 491.13359 | D331: 493.77722 | E331: 7055062.4 | F331: Fri, 25 Apr 2025 00:00:00 GMT | G331: =A331/D331-1 -> 0.0073043547 | I331: 461.57622 | J331: 461.8591 | K331: 447.091 | L331: 453.87028 | M331: 1362964.1 | N331: Fri, 25 Apr 2025 00:00:00 GMT | O331: =I331/L331-1 -> 0.016978294 | T331: =T330+0.001 -> 0.042 | U331: =_xlfn.NORM.DIST(T331,$S$238,$S$240,FALSE) -> 0.20581608
A332: 493.74773 | B332: 494.32756 | C332: 483.73647 | D332: 484.75549 | E332: 6292830.4 | F332: Thu, 24 Apr 2025 00:00:00 GMT | G332: =A332/D332-1 -> 0.018550055 | I332: 451.69506 | J332: 459.66924 | K332: 451.11955 | L332: 458.02563 | M332: 1850759.4 | N332: Thu, 24 Apr 2025 00:00:00 GMT | O332: =I332/L332-1 -> -0.01382145
A333: 483.58601 | B333: 492.53894 | C333: 482.23963 | D333: 488.12635 | E333: 8188787.4 | F333: Wed, 23 Apr 2025 00:00:00 GMT | G333: =A333/D333-1 -> -0.0093015764 | I333: 461.03973 | J333: 467.05807 | K333: 449.05163 | L333: 455.20663 | M333: 1977752.9 | N333: Wed, 23 Apr 2025 00:00:00 GMT | O333: =I333/L333-1 -> 0.012814194
A334: 475.94015 | B334: 478.09239 | C334: 468.96256 | D334: 469.82739 | E334: 6345728.4 | F334: Tue, 22 Apr 2025 00:00:00 GMT | G334: =A334/D334-1 -> 0.013010647 | I334: 452.68025 | J334: 482.06037 | K334: 439.07292 | L334: 472.8425 | M334: 4909019.1 | N334: Tue, 22 Apr 2025 00:00:00 GMT | O334: =I334/L334-1 -> -0.042640536
A335: 464.22566 | B335: 471.22291 | C335: 459.27256 | D335: 470.76101 | E335: 7898685.6 | F335: Mon, 21 Apr 2025 00:00:00 GMT | G335: =A335/D335-1 -> -0.01388251 | I335: 518.2783 | J335: 526.73533 | K335: 513.5133 | L335: 526.73533 | M335: 1376767.2 | N335: Mon, 21 Apr 2025 00:00:00 GMT | O335: =I335/L335-1 -> -0.016055556
A336: 475.55687 | B336: 479.74342 | C336: 473.19825 | D336: 476.43153 | E336: 5737868.1 | F336: Thu, 17 Apr 2025 00:00:00 GMT | G336: =A336/D336-1 -> -0.0018358464 | I336: 527.11575 | J336: 531.37841 | K336: 517.05901 | L336: 517.05901 | M336: 1130189.2 | N336: Thu, 17 Apr 2025 00:00:00 GMT | O336: =I336/L336-1 -> 0.019449894
A337: 474.89842 | B337: 483.28627 | C337: 469.98463 | D337: 480.22497 | E337: 6486709.2 | F337: Wed, 16 Apr 2025 00:00:00 GMT | G337: =A337/D337-1 -> -0.011091783 | I337: 524.3065 | J337: 530.63708 | K337: 521.00952 | L337: 523.91632 | M337: 1416349.5 | N337: Wed, 16 Apr 2025 00:00:00 GMT | O337: =I337/L337-1 -> 0.00074472641
A338: 485.57118 | B338: 490.66187 | C338: 484.91273 | D338: 487.47773 | E338: 8344453.3 | F338: Tue, 15 Apr 2025 00:00:00 GMT | G338: =A338/D338-1 -> -0.0039110538 | I338: 516.3567 | J338: 523.36764 | K338: 515.0301 | L338: 521.47773 | M338: 950415.19 | N338: Tue, 15 Apr 2025 00:00:00 GMT | O338: =I338/L338-1 -> -0.0098202428
A339: 486.93722 | B339: 491.6348 | C339: 482.2298 | D339: 491.42842 | E339: 7836602.2 | F339: Mon, 14 Apr 2025 00:00:00 GMT | G339: =A339/D339-1 -> -0.0091390861 | I339: 522.65801 | J339: 525.45263 | K339: 512.79636 | L339: 516.8249 | M339: 732361.88 | N339: Mon, 14 Apr 2025 00:00:00 GMT | O339: =I339/L339-1 -> 0.011286426
...

Sheet Product Lines

Sheet Economics

Sheet Management

Sheet Table Formatting
B2: [Bold Title] | G2: [Bold Title]
B3: Line Titles | G3: <-- General
B4: Line Titles | G4: <-- Info
B5: Line Titles | G5: <-- General
B6: Line Titles | G6: <-- Info
B7: Line Titles | G7: <-- General
B8: Line Titles | G8: <-- Info
