Workbook

Sheet Main
B2: ORCL
B3: Price | C3: 141.4 | D3: 10/9/2026
B4: SO | C4: 2966 | D4: Q2'26
B5: MC | C5: =C3*C4 -> 419392.4
B6: Cash | C6: =36369+708 -> 37077 | D6: Q2'26
B7: Debt | C7: =7625+117712 -> 125337 | D7: Q2'26
B8: EV | C8: =C5-C6+C7 -> 507652.4
B10: Oracle Corporation (ORCL)
B12: Founder(s): Larry Ellison, Bob Miner, and Ed Oates | G12: Registered Exchange: NYSE | N12: Resources:
B13: Founded: 1977 | G13: Address: 2300 Oracle Way, Austin TX 78741 U.S. | N13: SEC filings | Q13: https://www.sec.gov/edgar/browse/?CIK=1341439&owner=exclude
B14: Headquarters: Austin, TX | G14: Investor Relations Contact: | N14: Company Homepage | Q14: https://www.oracle.com/
B15: Current CEO: Safra Catz | G15: Investors Relation Department | O15: Company IR Page | R15: https://investor.oracle.com/home/default.aspx
B16: Employees: 162,000 (Q4'24) | G16: Phone: | H16: (650) 506-4073 | J16: Email: | K16: investor_us@oracle.com | N16: Earnings Calls | Q16: https://seekingalpha.com/symbol/ORCL#source=content_type%3Aall%7Csection%3Asearch_enter%7Csection_asset%3Asearch-basic%7Csearch_item%3Aorcl%7Crow_num%3A0%7CURL_first_level%3Asymbol%7Ctopic%3Akeyword
B17: Industry: Software - Infrastructure | N17: Equity Analysis | Q17: https://stockanalysis.com/stocks/orcl/company/
B18: Sector: Technology | N18: MacroTrends | Q18: https://www.macrotrends.net/stocks/charts/ORCL/oracle/income-statement?freq=Q
B19: IPO: March 12, 1986 | N19: ROIC, WACC | Q19: https://www.gurufocus.com/term/wacc/ORCL
B20: Fiscal Year: [June - May] | N20: Godel Terminal | Q20: https://app.godelterminal.com/
A22: Company Overview:
B23: Oracle operates through three primary business segments, each aligned to a single operating segment:
C24: Cloud and License:
D25: The largest segment, encompassing Oracle’s Fusion Cloud Applications (ERP, HCM, SCM, EPM, and industry solutions), Oracle Cloud Infrastructure (OCI), as well as on‑premise license and support. OCI includes autonomous database, compute, storage, networking, and AI/ML tools.
D26: Strong base of license support contracts and hardware support provides a substantial recurring revenue stream
C27: Hardware:
D28: Sales of Oracle Engineered Systems, servers, storage solutions, and industry‑specific hardware. Most hardware buyers also purchase recurring hardware support contracts
C29: Services:
D30: Professional consulting, advanced customer support, and implementation assistance to maximize customer ROI from Oracle deployments
B31: Oracle Corporation has a strategic alliance with Metron, Inc.
B32: Oracle’s growth strategy centers on Oracle Cloud Services:
C33: Cloud growth is central to long‑term valuation, with multi‑year R&D and acquisition investments directed toward expanding market share
C34: Oracle Cloud Applications (OCA) – Integrated enterprise software suite across ERP, HCM, SCM, EPM, and CRM (Sales, Service, Marketing)
C35: Oracle Cloud Infrastructure (OCI) – Infrastructure‑as‑a‑Service competing with AWS, Microsoft Azure, and Google Cloud
D36: OCI is highly differentiated by its Exadata Cloud@Customer deployments, enabling cloud infrastructure within a customer’s datacenter
C37: Oracle emphasizes flexibility via three deployment models: cloud‑based, on‑premise, or hybrid, giving customers choice in migrating workloads
D38: This interoperability is positioned as a competitive advantage relative to peers with more restrictive models
B39: Oracle serves a diversified global base of customers including Enterprises of all sizes, Government Agencies (that is their roots after all), Academic Institutions, and Resellers & Partners
C40: Use cases span AI companies training generative models on OCI, multinational financial firms migrating banking applications to Oracle Exadata Cloud@Customer, and consumer product companies adopting Fusion ERP for global operations
B41: Oracle competes across enterprise applications (against SAP, Workday, Salesforce, Microsoft Dynamics) and cloud infrastructure (against AWS, Azure, Google Cloud)
A43: Business Segments and Geographical Info:

Sheet Model
B1: Fiscal Year: [June - May] | AM1: Q1 2021 | AQ1: Q1 2022 | AU1: Q1 2023 | AY1: Q1 2024 | BC1: Q1 2025 | BG1: Q1 2026 | BK1: Q1 2027
B2: Quarterly | C2: Sept. | D2: Dec. | E2: Mar. | F2: June | G2: Sept. | H2: Dec. | I2: Mar. | J2: June | K2: Sept. | L2: Dec. | M2: Mar. | N2: June | O2: Sept. | P2: Dec. | Q2: Mar. | R2: June | S2: Sept. | T2: Dec. | U2: Mar. | V2: June | W2: Sept. | X2: Dec. | Y2: Mar. | Z2: June | AA2: Sept. | AB2: Dec. | AC2: Mar. | AD2: June | AE2: Sept. | AF2: Dec. | AG2: Mar. | AH2: June | AI2: Sept. | AJ2: Dec. | AK2: Mar. | AL2: June | AM2: Sept. | AN2: Dec. | AO2: Mar. | AP2: June | AQ2: Sept. | AR2: Dec. | AS2: Mar. | AT2: June | AU2: Sept. | AV2: Dec. | AW2: Mar. | AX2: June | AY2: Sept. | AZ2: Dec. | BA2: Mar. | BB2: June | BC2: Sept. | BD2: Dec. | BE2: Mar. | BF2: June | BG2: Sept. | BH2: Dec. | BI2: Mar. | BJ2: June | BK2: Sept. | BL2: Dec. | BM2: Mar. | BN2: June
B3: Revenues | C3: Q1 2012 | D3: Q2 2012 | E3: Q3 2012 | F3: Q4 2012 | G3: Q1 2013 | H3: Q2 2013 | I3: Q3 2013 | J3: Q4 2013 | K3: Q1 2014 | L3: Q2 2014 | M3: Q3 2014 | N3: Q4 2014 | O3: Q1 2015 | P3: Q2 2015 | Q3: Q3 2015 | R3: Q4 2015 | S3: Q1 2016 | T3: Q2 2016 | U3: Q3 2016 | V3: Q4 2016 | W3: Q1 2017 | X3: Q2 2017 | Y3: Q3 2017 | Z3: Q4 2017 | AA3: Q1 2018 | AB3: Q2 2018 | AC3: Q3 2018 | AD3: Q4 2018 | AE3: Q1 2019 | AF3: Q2 2019 | AG3: Q3 2019 | AH3: Q4 2019 | AI3: Q1 2020 | AJ3: Q2 2020 | AK3: Q3 2020 | AL3: Q4 2020 | AM3: Q1 2021 | AN3: Q2 2021 | AO3: Q3 2021 | AP3: Q4 2021 | AQ3: Q1 2022 | AR3: Q2 2022 | AS3: Q3 2022 | AT3: Q4 2022 | AU3: Q1 2023 | AV3: Q2 2023 | AW3: Q3 2023 | AX3: Q4 2023 | AY3: Q1 2024 | AZ3: Q2 2024 | BA3: Q3 2024 | BB3: Q4 2024 | BC3: Q1 2025 | BD3: Q2 2025 | BE3: Q3 2025 | BF3: Q4 2025 | BG3: Q1 2026 | BH3: Q2 2026 | BI3: Q3 2026 | BJ3: Q4 2026 | BK3: Q1 2027 | BL3: Q2 2027 | BM3: Q3 2027 | BN3: Q4 2027 | BS3: 2012 | BT3: =BS3+1 -> 2013 | BU3: =BT3+1 -> 2014 | BV3: =BU3+1 -> 2015 | BW3: =BV3+1 -> 2016 | BX3: =BW3+1 -> 2017 | BY3: =BX3+1 -> 2018 | BZ3: =BY3+1 -> 2019 | CA3: =BZ3+1 -> 2020 | ... EO3: =EN3+1 -> 2086
B4: Cloud | BC4: 5623 | BD4: 5937 | BE4: 6210 | BF4: =24506-SUM(BC4:BE4) -> 6736 | BG4: 7186 | BH4: 7977 | BI4: 8914 | BJ4: =33989-SUM(BG4:BI4) -> 9912 | BK4: 11607 | CE4: =19774-SUM(AY4:BA4) -> 19774 | CF4: =SUM(BC4:BF4) -> 24506 | CG4: =SUM(BG4:BJ4) -> 33989 | CH4: =CG4*(1+CH10) -> 53872.565 | CI4: =CH4*(1+CI10) -> 93468.9 | CJ4: =CI4*(1+CJ10) -> 126183.02 | CK4: =CJ4*(1+CK10) -> 161514.26 | CL4: =CK4*(1+CL10) -> 197047.4 | CM4: =CL4*(1+CM10) -> 228574.98 | CN4: =CM4*(1+CN10) -> 256003.98 | CO4: =CN4*(1+CO10) -> 276484.3 | ... CQ4: =CP4*(1+CQ10) -> 304796.29
B5: Software | BC5: 5766 | BD5: 6064 | BE5: 5926 | BF5: =24724-SUM(BC5:BE5) -> 6968 | BG5: 5721 | BH5: 5877 | BI5: 6119 | BJ5: =24541-SUM(BG5:BI5) -> 6824 | BK5: 5550 | CE5: =24690-SUM(AY5:BA5) -> 24690 | CF5: =SUM(BC5:BF5) -> 24724 | CG5: =SUM(BG5:BJ5) -> 24541 | CH5: =CG5*(1+CH11) -> 25768.05 | CI5: =CH5*(1+CI11) -> 26283.411 | CJ5: =CI5*(1+CJ11) -> 27597.582 | CK5: =CJ5*(1+CK11) -> 28977.461 | CL5: =CK5*(1+CL11) -> 30426.334 | CM5: =CL5*(1+CM11) -> 31947.65 | CN5: =CM5*(1+CN11) -> 33545.033 | CO5: =CN5*(1+CO11) -> 35222.285 | ... CQ5: =CP5*(1+CQ11) -> 38832.569
B6: Hardware | BC6: 655 | BD6: 728 | BE6: 703 | BF6: =2936-SUM(BC6:BE6) -> 850 | BG6: 670 | BH6: 776 | BI6: 714 | BJ6: =3084-SUM(BG6:BI6) -> 924 | BK6: 774 | CE6: =3066-SUM(AY6:BA6) -> 3066 | CF6: =SUM(BC6:BF6) -> 2936 | CG6: =SUM(BG6:BJ6) -> 3084 | CH6: =CG6*(1+CH12) -> 3284.46 | CI6: =CH6*(1+CI12) -> 3520.9411 | CJ6: =CI6*(1+CJ12) -> 3742.7604 | CK6: =CJ6*(1+CK12) -> 3948.6122 | CL6: =CK6*(1+CL12) -> 4161.8373 | CM6: =CL6*(1+CM12) -> 4378.2528 | CN6: =CM6*(1+CN12) -> 4597.1655 | CO6: =CN6*(1+CO12) -> 4808.6351 | ... CQ6: =CP6*(1+CQ12) -> 5211.0217
B7: Services | BC7: 1263 | BD7: 1330 | BE7: 1291 | BF7: =5233-SUM(BC7:BE7) -> 1349 | BG7: 1349 | BH7: 1428 | BI7: 1443 | BJ7: =5743-SUM(BG7:BI7) -> 1523 | BK7: 1414 | CE7: =5431-SUM(AY7:BA7) -> 5431 | CF7: =SUM(BC7:BF7) -> 5233 | CG7: =SUM(BG7:BJ7) -> 5743 | CH7: =CG7*(1+CH13) -> 6374.73 | CI7: =CH7*(1+CI13) -> 7203.4449 | CJ7: =CI7*(1+CJ13) -> 8283.9616 | CK7: =CJ7*(1+CK13) -> 9443.7163 | CL7: =CK7*(1+CL13) -> 10671.399 | CM7: =CL7*(1+CM13) -> 11845.253 | CN7: =CM7*(1+CN13) -> 12911.326 | CO7: =CN7*(1+CO13) -> 13815.119 | ... CQ7: =CP7*(1+CQ13) -> 14941.051
B8: Ttl Revenues | BC8: =SUM(BC4:BC7) -> 13307 | BD8: =SUM(BD4:BD7) -> 14059 | BE8: =SUM(BE4:BE7) -> 14130 | BF8: =SUM(BF4:BF7) -> 15903 | BG8: =SUM(BG4:BG7) -> 14926 | BH8: =SUM(BH4:BH7) -> 16058 | BI8: =SUM(BI4:BI7) -> 17190 | BJ8: =SUM(BJ4:BJ7) -> 19183 | BK8: =SUM(BK4:BK7) -> 19345 | CE8: =SUM(CE4:CE7) -> 52961 | CF8: =SUM(BC8:BF8) -> 57399 | CG8: =SUM(BG8:BJ8) -> 67357 | CH8: =SUM(CH4:CH7) -> 89299.805 | CI8: =SUM(CI4:CI7) -> 130476.7 | CJ8: =SUM(CJ4:CJ7) -> 165807.32 | CK8: =SUM(CK4:CK7) -> 203884.05 | CL8: =SUM(CL4:CL7) -> 242306.97 | CM8: =SUM(CM4:CM7) -> 276746.14 | CN8: =SUM(CN4:CN7) -> 307057.5 | CO8: =SUM(CO4:CO7) -> 330330.33 | ... CQ8: =SUM(CQ4:CQ7) -> 363780.93
B10: Cloud Growth Y/y | BG10: =BG4/BC4-1 -> 0.2779655 | BH10: =BH4/BD4-1 -> 0.34360788 | BI10: =BI4/BE4-1 -> 0.43542673 | BJ10: =BJ4/BF4-1 -> 0.47149644 | BK10: =BK4/BG4-1 -> 0.61522405 | CF10: =CF4/CE4-1 -> 0.23930414 | CG10: =CG4/CF4-1 -> 0.38696646 | CH10: 0.585 | CI10: 0.735 | CJ10: 0.35 | CK10: 0.28 | CL10: 0.22 | CM10: 0.16 | CN10: 0.12 | CO10: 0.08 | CP10: 0.06 | CQ10: 0.04
B11: Software Growth Y/y | BG11: =BG5/BC5-1 -> -0.0078043704 | BH11: =BH5/BD5-1 -> -0.030837731 | BI11: =BI5/BE5-1 -> 0.032568343 | BJ11: =BJ5/BF5-1 -> -0.020665901 | BK11: =BK5/BG5-1 -> -0.029889879 | CF11: =CF5/CE5-1 -> 0.0013770757 | CG11: =CG5/CF5-1 -> -0.0074017149 | CH11: 0.05 | CI11: 0.02 | CJ11: 0.05 | CK11: 0.05 | CL11: 0.05 | CM11: 0.05 | CN11: 0.05 | CO11: 0.05 | CP11: 0.05 | CQ11: 0.05
B12: Hardware Growth Y/y | BG12: =BG6/BC6-1 -> 0.022900763 | BH12: =BH6/BD6-1 -> 0.065934066 | BI12: =BI6/BE6-1 -> 0.015647226 | BJ12: =BJ6/BF6-1 -> 0.087058824 | BK12: =BK6/BG6-1 -> 0.15522388 | CF12: =CF6/CE6-1 -> -0.042400522 | CG12: =CG6/CF6-1 -> 0.050408719 | CH12: 0.065 | CI12: 0.072 | CJ12: 0.063 | CK12: 0.055 | CL12: 0.054 | CM12: 0.052 | CN12: 0.05 | CO12: 0.046 | CP12: 0.042 | CQ12: 0.04
B13: Services Growth Y/y | BG13: =BG7/BC7-1 -> 0.068091845 | BH13: =BH7/BD7-1 -> 0.073684211 | BI13: =BI7/BE7-1 -> 0.11773819 | BJ13: =BJ7/BF7-1 -> 0.12898443 | BK13: =BK7/BG7-1 -> 0.04818384 | CF13: =CF7/CE7-1 -> -0.036457374 | CG13: =CG7/CF7-1 -> 0.097458437 | CH13: 0.11 | CI13: 0.13 | CJ13: 0.15 | CK13: 0.14 | CL13: 0.13 | CM13: 0.11 | CN13: 0.09 | CO13: 0.07 | CP13: 0.05 | CQ13: 0.03
B14: Ttl Revenue Growth Y/y | BG14: =BG8/BC8-1 -> 0.12166529 | BH14: =BH8/BD8-1 -> 0.1421865 | BI14: =BI8/BE8-1 -> 0.21656051 | BJ14: =BJ8/BF8-1 -> 0.20625039 | BK14: =BK8/BG8-1 -> 0.29606057 | CF14: =CF8/CE8-1 -> 0.083797511 | CG14: =CG8/CF8-1 -> 0.17348734 | CH14: =CH8/CG8-1 -> 0.32576874 | CI14: =CI8/CH8-1 -> 0.46110842 | CJ14: =CJ8/CI8-1 -> 0.27078109 | CK14: =CK8/CJ8-1 -> 0.22964445 | CL14: =CL8/CK8-1 -> 0.18845475 | CM14: =CM8/CL8-1 -> 0.14213033 | ... CQ14: =CQ8/CP8-1 -> 0.040642999
B16: Cloud % of Ttl Revenues | BC16: =BC4/BC8 -> 0.42255956 | BD16: =BD4/BD8 -> 0.42229177 | BE16: =BE4/BE8 -> 0.43949045 | BF16: =BF4/BF8 -> 0.42356788 | BG16: =BG4/BG8 -> 0.48144178 | BH16: =BH4/BH8 -> 0.49676174 | BI16: =BI4/BI8 -> 0.5185573 | BJ16: =BJ4/BJ8 -> 0.5167075 | BK16: =BK4/BK8 -> 0.6 | CE16: =CE4/CE8 -> 0.37336908 | CF16: =CF4/CF8 -> 0.42694124 | CG16: =CG4/CG8 -> 0.50460977
B17: Software % of Ttl Revenues | BC17: =BC5/BC8 -> 0.43330578 | BD17: =BD5/BD8 -> 0.43132513 | BE17: =BE5/BE8 -> 0.41939137 | BF17: =BF5/BF8 -> 0.43815632 | BG17: =BG5/BG8 -> 0.3832909 | BH17: =BH5/BH8 -> 0.3659858 | BI17: =BI5/BI8 -> 0.35596277 | BJ17: =BJ5/BJ8 -> 0.35573164 | BK17: =BK5/BK8 -> 0.28689584 | CE17: =CE5/CE8 -> 0.4661921 | CF17: =CF5/CF8 -> 0.43073921 | CG17: =CG5/CG8 -> 0.36434224
B18: Hardware % of Ttl Revenues | BC18: =BC6/BC8 -> 0.049222214 | BD18: =BD6/BD8 -> 0.051781777 | BE18: =BE6/BE8 -> 0.0497523 | BF18: =BF6/BF8 -> 0.053449035 | BG18: =BG6/BG8 -> 0.044888115 | BH18: =BH6/BH8 -> 0.048324823 | BI18: =BI6/BI8 -> 0.041535777 | BJ18: =BJ6/BJ8 -> 0.048167648 | BK18: =BK6/BK8 -> 0.040010339 | CE18: =CE6/CE8 -> 0.057891656 | CF18: =CF6/CF8 -> 0.051150717 | CG18: =CG6/CG8 -> 0.045785887
B19: Services % of Ttl Revenues | BC19: =BC7/BC8 -> 0.094912452 | BD19: =BD7/BD8 -> 0.094601323 | BE19: =BE7/BE8 -> 0.091365888 | BF19: =BF7/BF8 -> 0.084826762 | BG19: =BG7/BG8 -> 0.090379204 | BH19: =BH7/BH8 -> 0.088927637 | BI19: =BI7/BI8 -> 0.083944154 | BJ19: =BJ7/BJ8 -> 0.079393213 | BK19: =BK7/BK8 -> 0.073093823 | CE19: =CE7/CE8 -> 0.10254716 | CF19: =CF7/CF8 -> 0.091168836 | CG19: =CG7/CG8 -> 0.085262111
B21: Revenues | C21: 8374 | D21: 8792 | E21: 9039 | F21: 10916 | G21: 8181 | H21: 9094 | I21: 8958 | J21: 10947 | K21: 8372 | L21: 9275 | M21: 9307 | N21: 11321 | O21: 8596 | P21: 9598 | Q21: 9327 | R21: 10705 | S21: 8448 | T21: 8993 | U21: 9012 | V21: 10594 | W21: 8595 | X21: 9035 | Y21: 9205 | Z21: 10957 | AA21: 9104 | AB21: 9589 | AC21: 9676 | AD21: 11014 | AE21: 9193 | AF21: 9562 | AG21: 9614 | AH21: 11137 | AI21: 9218 | AJ21: 9614 | AK21: 9796 | AL21: 10441 | AM21: 9367 | AN21: 9800 | AO21: 10086 | AP21: 11227 | AQ21: 9728 | AR21: 10360 | AS21: 10513 | AT21: 11840 | AU21: 11445 | AV21: 12275 | AW21: 12398 | AX21: 13837 | AY21: 12453 | AZ21: 12941 | BA21: 13280 | BB21: 14287 | BC21: 13307 | BD21: 14059 | BE21: 14130 | BF21: 15903 | BG21: 14926 | BH21: 16058 | BI21: 17190 | BJ21: 19183 | BK21: =BK8 -> 19345 | BS21: =SUM(C21:F21) -> 37121 | BT21: =SUM(G21:J21) -> 37180 | BU21: =SUM(K21:N21) -> 38275 | BV21: =SUM(O21:R21) -> 38226 | BW21: =SUM(S21:V21) -> 37047 | BX21: =SUM(W21:Z21) -> 37792 | BY21: =SUM(AA21:AD21) -> 39383 | BZ21: =SUM(AE21:AH21) -> 39506 | CA21: =SUM(AI21:AL21) -> 39069 | CB21: =SUM(AM21:AP21) -> 40480 | CC21: =SUM(AQ21:AT21) -> 42441 | CD21: =SUM(AU21:AX21) -> 49955 | CE21: =SUM(AY21:BB21) -> 52961 | CF21: =SUM(BC21:BF21) -> 57399 | CG21: =SUM(BG21:BJ21) -> 67357 | CH21: =CH8 -> 89299.805 | CI21: =CI8 -> 130476.7 | CJ21: =CJ8 -> 165807.32 | CK21: =CK8 -> 203884.05 | CL21: =CL8 -> 242306.97 | CM21: =CM8 -> 276746.14 | CN21: =CN8 -> 307057.5 | CO21: =CO8 -> 330330.33 | ... CQ21: =CQ8 -> 363780.93
B22: Cloud & Software Op. Ex. | C22: 0 | D22: 0 | E22: 0 | F22: 0 | G22: 0 | H22: 0 | I22: 0 | J22: 0 | K22: 0 | L22: 0 | M22: 0 | N22: 0 | O22: 0 | P22: 0 | Q22: 0 | R22: 0 | S22: 0 | T22: 0 | U22: 0 | V22: 0 | W22: 0 | X22: 0 | Y22: 0 | Z22: 0 | AA22: 0 | AB22: 0 | AC22: 0 | AD22: 0 | AE22: 0 | AF22: 0 | AG22: 0 | AH22: 0 | AI22: 0 | AJ22: 0 | AK22: 0 | AL22: 0 | AM22: 1011 | AN22: 1064 | AO22: 1064 | AP22: =4353-SUM(AM22:AO22) -> 1214 | AQ22: 1214 | AR22: 1259 | AS22: 1305 | AT22: =5213-SUM(AQ22:AS22) -> 1435 | AU22: 1735 | AV22: 1891 | AW22: 1980 | AX22: =7763-SUM(AU22:AW22) -> 2157 | AY22: 2179 | AZ22: 2274 | BA22: 2452 | BB22: =9427-SUM(AY22:BA22) -> 2522 | BC22: 2597 | BD22: 2746 | BE22: 2882 | BF22: =11569-SUM(BC22:BE22) -> 3344 | BG22: 3607 | BH22: 3990 | BI22: 4776 | BJ22: =17597-SUM(BG22:BI22) -> 5224 | BK22: 6400 | BS22: =SUM(C22:F22) -> 0 | BT22: =SUM(G22:J22) -> 0 | BU22: =SUM(K22:N22) -> 0 | BV22: =SUM(O22:R22) -> 0 | BW22: =SUM(S22:V22) -> 0 | BX22: =SUM(W22:Z22) -> 0 | BY22: =SUM(AA22:AD22) -> 0 | BZ22: =SUM(AE22:AH22) -> 0 | CA22: =SUM(AI22:AL22) -> 0 | CB22: =SUM(AM22:AP22) -> 4353 | CC22: =SUM(AQ22:AT22) -> 5213 | CD22: =SUM(AU22:AX22) -> 7763 | CE22: =SUM(AY22:BB22) -> 9427 | CF22: =SUM(BC22:BF22) -> 11569 | CG22: =SUM(BG22:BJ22) -> 17597 | CH22: =CH21*CH42 -> 25003.945 | CI22: =CI21*CI42 -> 37838.242 | CJ22: =CJ21*CJ42 -> 49742.196 | CK22: =CK21*CK42 -> 57087.534 | CL22: =CL21*CL42 -> 65422.881 | CM22: =CM21*CM42 -> 73337.726 | CN22: =CN21*CN42 -> 79834.951 | CO22: =CO21*CO42 -> 84234.235 | ... CQ22: =CQ21*CQ42 -> 89126.328
B23: Hardware Op. Ex. | C23: 0 | D23: 0 | E23: 0 | F23: 0 | G23: 0 | H23: 0 | I23: 0 | J23: 0 | K23: 0 | L23: 0 | M23: 0 | N23: 0 | O23: 0 | P23: 0 | Q23: 0 | R23: 0 | S23: 0 | T23: 0 | U23: 0 | V23: 0 | W23: 0 | X23: 0 | Y23: 0 | Z23: 0 | AA23: 0 | AB23: 0 | AC23: 0 | AD23: 0 | AE23: 0 | AF23: 0 | AG23: 0 | AH23: 0 | AI23: 0 | AJ23: 0 | AK23: 0 | AL23: 0 | AM23: 246 | AN23: 244 | AO23: 230 | AP23: =972-SUM(AM23:AO23) -> 252 | AQ23: 245 | AR23: 229 | AS23: 244 | AT23: =972-SUM(AQ23:AS23) -> 254 | AU23: 249 | AV23: 286 | AW23: 244 | AX23: =1040-SUM(AU23:AW23) -> 261 | AY23: 219 | AZ23: 213 | BA23: 217 | BB23: =891-SUM(AY23:BA23) -> 242 | BC23: 162 | BD23: 172 | BE23: 197 | BF23: =782-SUM(BC23:BE23) -> 251 | BG23: 178 | BH23: 215 | BI23: 183 | BJ23: =868-SUM(BG23:BI23) -> 292 | BK23: 281 | BS23: =SUM(C23:F23) -> 0 | BT23: =SUM(G23:J23) -> 0 | BU23: =SUM(K23:N23) -> 0 | BV23: =SUM(O23:R23) -> 0 | BW23: =SUM(S23:V23) -> 0 | BX23: =SUM(W23:Z23) -> 0 | BY23: =SUM(AA23:AD23) -> 0 | BZ23: =SUM(AE23:AH23) -> 0 | CA23: =SUM(AI23:AL23) -> 0 | CB23: =SUM(AM23:AP23) -> 972 | CC23: =SUM(AQ23:AT23) -> 972 | CD23: =SUM(AU23:AX23) -> 1040 | CE23: =SUM(AY23:BB23) -> 891 | CF23: =SUM(BC23:BF23) -> 782 | CG23: =SUM(BG23:BJ23) -> 868 | CH23: =CH21*CH43 -> 1250.1973 | CI23: =CI21*CI43 -> 1696.1971 | CJ23: =CJ21*CJ43 -> 2155.4951 | CK23: =CK21*CK43 -> 2446.6086 | CL23: =CL21*CL43 -> 2907.6836 | CM23: =CM21*CM43 -> 3044.2075 | CN23: =CN21*CN43 -> 3377.6325 | CO23: =CO21*CO43 -> 3303.3033 | ... CQ23: =CQ21*CQ43 -> 3637.8093
B24: Services Op. Ex. | C24: 0 | D24: 0 | E24: 0 | F24: 0 | G24: 0 | H24: 0 | I24: 0 | J24: 0 | K24: 0 | L24: 0 | M24: 0 | N24: 0 | O24: 0 | P24: 0 | Q24: 0 | R24: 0 | S24: 0 | T24: 0 | U24: 0 | V24: 0 | W24: 0 | X24: 0 | Y24: 0 | Z24: 0 | AA24: 0 | AB24: 0 | AC24: 0 | AD24: 0 | AE24: 0 | AF24: 0 | AG24: 0 | AH24: 0 | AI24: 0 | AJ24: 0 | AK24: 0 | AL24: 0 | AM24: 623 | AN24: 631 | AO24: 621 | AP24: =2530-SUM(AM24:AO24) -> 655 | AQ24: 644 | AR24: 671 | AS24: 669 | AT24: =2692-SUM(AQ24:AS24) -> 708 | AU24: 1053 | AV24: 1181 | AW24: 1215 | AX24: =4761-SUM(AU24:AW24) -> 1312 | AY24: 1212 | AZ24: 1253 | BA24: 1200 | BB24: =4825-SUM(AY24:BA24) -> 1160 | BC24: 1147 | BD24: 1167 | BE24: 1116 | BF24: =4576-SUM(BC24:BE24) -> 1146 | BG24: 1099 | BH24: 1169 | BI24: 1133 | BJ24: =4556-SUM(BG24:BI24) -> 1155 | BK24: 1052 | BS24: =SUM(C24:F24) -> 0 | BT24: =SUM(G24:J24) -> 0 | BU24: =SUM(K24:N24) -> 0 | BV24: =SUM(O24:R24) -> 0 | BW24: =SUM(S24:V24) -> 0 | BX24: =SUM(W24:Z24) -> 0 | BY24: =SUM(AA24:AD24) -> 0 | BZ24: =SUM(AE24:AH24) -> 0 | CA24: =SUM(AI24:AL24) -> 0 | CB24: =SUM(AM24:AP24) -> 2530 | CC24: =SUM(AQ24:AT24) -> 2692 | CD24: =SUM(AU24:AX24) -> 4761 | CE24: =SUM(AY24:BB24) -> 4825 | CF24: =SUM(BC24:BF24) -> 4576 | CG24: =SUM(BG24:BJ24) -> 4556 | CH24: =CH21*CH44 -> 5715.1875 | CI24: =CI21*CI44 -> 8480.9853 | CJ24: =CJ21*CJ44 -> 10445.861 | CK24: =CK21*CK44 -> 12640.811 | CL24: =CL21*CL44 -> 14780.725 | CM24: =CM21*CM44 -> 16604.768 | CN24: =CN21*CN44 -> 18116.393 | CO24: =CO21*CO44 -> 19159.159 | ... CQ24: =CQ21*CQ44 -> 20371.732
B25: S&M | C25: 0 | D25: 0 | E25: 0 | F25: 0 | G25: 0 | H25: 0 | I25: 0 | J25: 0 | K25: 0 | L25: 0 | M25: 0 | N25: 0 | O25: 0 | P25: 0 | Q25: 0 | R25: 0 | S25: 0 | T25: 0 | U25: 0 | V25: 0 | W25: 0 | X25: 0 | Y25: 0 | Z25: 0 | AA25: 0 | AB25: 0 | AC25: 0 | AD25: 0 | AE25: 0 | AF25: 0 | AG25: 0 | AH25: 0 | AI25: 0 | AJ25: 0 | AK25: 0 | AL25: 0 | AM25: 1854 | AN25: 1836 | AO25: 1915 | AP25: =7682-SUM(AM25:AO25) -> 2077 | AQ25: 1854 | AR25: 1954 | AS25: 2004 | AT25: =8047-SUM(AQ25:AS25) -> 2235 | AU25: 2177 | AV25: 2216 | AW25: 2150 | AX25: =8833-SUM(AU25:AW25) -> 2290 | AY25: 2026 | AZ25: 2093 | BA25: 2042 | BB25: =8274-SUM(AY25:BA25) -> 2113 | BC25: 2036 | BD25: 2190 | BE25: 2119 | BF25: =8651-SUM(BC25:BE25) -> 2306 | BG25: 2063 | BH25: 2149 | BI25: 2052 | BJ25: =8331-SUM(BG25:BI25) -> 2067 | BK25: 1811 | BS25: =SUM(C25:F25) -> 0 | BT25: =SUM(G25:J25) -> 0 | BU25: =SUM(K25:N25) -> 0 | BV25: =SUM(O25:R25) -> 0 | BW25: =SUM(S25:V25) -> 0 | BX25: =SUM(W25:Z25) -> 0 | BY25: =SUM(AA25:AD25) -> 0 | BZ25: =SUM(AE25:AH25) -> 0 | CA25: =SUM(AI25:AL25) -> 0 | CB25: =SUM(AM25:AP25) -> 7682 | CC25: =SUM(AQ25:AT25) -> 8047 | CD25: =SUM(AU25:AX25) -> 8833 | CE25: =SUM(AY25:BB25) -> 8274 | CF25: =SUM(BC25:BF25) -> 8651 | CG25: =SUM(BG25:BJ25) -> 8331 | CH25: =CH21*CH45 -> 10626.677 | CI25: =CI21*CI45 -> 15265.774 | CJ25: =CJ21*CJ45 -> 19067.842 | CK25: =CK21*CK45 -> 23242.782 | CL25: =CL21*CL45 -> 27380.687 | CM25: =CM21*CM45 -> 30995.567 | CN25: =CN21*CN45 -> 34083.383 | CO25: =CO21*CO45 -> 36336.337 | ... CQ25: =CQ21*CQ45 -> 40015.902
B26: R&D | C26: 0 | D26: 0 | E26: 0 | F26: 0 | G26: 0 | H26: 0 | I26: 0 | J26: 0 | K26: 0 | L26: 0 | M26: 0 | N26: 0 | O26: 0 | P26: 0 | Q26: 0 | R26: 0 | S26: 0 | T26: 0 | U26: 0 | V26: 0 | W26: 0 | X26: 0 | Y26: 0 | Z26: 0 | AA26: 0 | AB26: 0 | AC26: 0 | AD26: 0 | AE26: 0 | AF26: 0 | AG26: 0 | AH26: 0 | AI26: 0 | AJ26: 0 | AK26: 0 | AL26: 0 | AM26: 1589 | AN26: 1601 | AO26: 1621 | AP26: =6527-SUM(AM26:AO26) -> 1716 | AQ26: 1684 | AR26: 1754 | AS26: 1816 | AT26: =7219-SUM(AQ26:AS26) -> 1965 | AU26: 2093 | AV26: 2158 | AW26: 2146 | AX26: =8623-SUM(AU26:AW26) -> 2226 | AY26: 2216 | AZ26: 2226 | BA26: 2248 | BB26: =8915-SUM(AY26:BA26) -> 2225 | BC26: 2306 | BD26: 2471 | BE26: 2429 | BF26: =9860-SUM(BC26:BE26) -> 2654 | BG26: 2491 | BH26: 2561 | BI26: 2607 | BJ26: =10272-SUM(BG26:BI26) -> 2613 | BK26: 2401 | BS26: =SUM(C26:F26) -> 0 | BT26: =SUM(G26:J26) -> 0 | BU26: =SUM(K26:N26) -> 0 | BV26: =SUM(O26:R26) -> 0 | BW26: =SUM(S26:V26) -> 0 | BX26: =SUM(W26:Z26) -> 0 | BY26: =SUM(AA26:AD26) -> 0 | BZ26: =SUM(AE26:AH26) -> 0 | CA26: =SUM(AI26:AL26) -> 0 | CB26: =SUM(AM26:AP26) -> 6527 | CC26: =SUM(AQ26:AT26) -> 7219 | CD26: =SUM(AU26:AX26) -> 8623 | CE26: =SUM(AY26:BB26) -> 8915 | CF26: =SUM(BC26:BF26) -> 9860 | CG26: =SUM(BG26:BJ26) -> 10272 | CH26: =CH21*CH46 -> 13841.47 | CI26: =CI21*CI46 -> 19897.808 | CJ26: =CJ21*CJ46 -> 25202.712 | CK26: =CK21*CK46 -> 30786.491 | CL26: =CL21*CL46 -> 36346.045 | CM26: =CM21*CM46 -> 41235.174 | CN26: =CN21*CN46 -> 45444.51 | CO26: =CO21*CO46 -> 48558.559 | ... CQ26: =CQ21*CQ46 -> 52748.235
B27: G&A | C27: 0 | D27: 0 | E27: 0 | F27: 0 | G27: 0 | H27: 0 | I27: 0 | J27: 0 | K27: 0 | L27: 0 | M27: 0 | N27: 0 | O27: 0 | P27: 0 | Q27: 0 | R27: 0 | S27: 0 | T27: 0 | U27: 0 | V27: 0 | W27: 0 | X27: 0 | Y27: 0 | Z27: 0 | AA27: 0 | AB27: 0 | AC27: 0 | AD27: 0 | AE27: 0 | AF27: 0 | AG27: 0 | AH27: 0 | AI27: 0 | AJ27: 0 | AK27: 0 | AL27: 0 | AM27: 295 | AN27: 324 | AO27: 330 | AP27: =1254-SUM(AM27:AO27) -> 305 | AQ27: 298 | AR27: 319 | AS27: 335 | AT27: =1317-SUM(AQ27:AS27) -> 365 | AU27: 411 | AV27: 366 | AW27: 402 | AX27: =1579-SUM(AU27:AW27) -> 400 | AY27: 393 | AZ27: 375 | BA27: 377 | BB27: =1548-SUM(AY27:BA27) -> 403 | BC27: 358 | BD27: 387 | BE27: 390 | BF27: =1602-SUM(BC27:BE27) -> 467 | BG27: 376 | BH27: 409 | BI27: 389 | BJ27: =1618-SUM(BG27:BI27) -> 444 | BK27: 376 | BS27: =SUM(C27:F27) -> 0 | BT27: =SUM(G27:J27) -> 0 | BU27: =SUM(K27:N27) -> 0 | BV27: =SUM(O27:R27) -> 0 | BW27: =SUM(S27:V27) -> 0 | BX27: =SUM(W27:Z27) -> 0 | BY27: =SUM(AA27:AD27) -> 0 | BZ27: =SUM(AE27:AH27) -> 0 | CA27: =SUM(AI27:AL27) -> 0 | CB27: =SUM(AM27:AP27) -> 1254 | CC27: =SUM(AQ27:AT27) -> 1317 | CD27: =SUM(AU27:AX27) -> 1579 | CE27: =SUM(AY27:BB27) -> 1548 | CF27: =SUM(BC27:BF27) -> 1602 | CG27: =SUM(BG27:BJ27) -> 1618 | CH27: =CH21*CH47 -> 2145.0938 | CI27: =CI21*CI47 -> 3134.2147 | CJ27: =CJ21*CJ47 -> 3982.9007 | CK27: =CK21*CK47 -> 4689.3331 | CL27: =CL21*CL47 -> 5573.0602 | CM27: =CM21*CM47 -> 6365.1611 | CN27: =CN21*CN47 -> 6755.2651 | CO27: =CO21*CO47 -> 7267.2674 | ... CQ27: =CQ21*CQ47 -> 8003.1805
B28: Ammortization | C28: 0 | D28: 0 | E28: 0 | F28: 0 | G28: 0 | H28: 0 | I28: 0 | J28: 0 | K28: 0 | L28: 0 | M28: 0 | N28: 0 | O28: 0 | P28: 0 | Q28: 0 | R28: 0 | S28: 0 | T28: 0 | U28: 0 | V28: 0 | W28: 0 | X28: 0 | Y28: 0 | Z28: 0 | AA28: 0 | AB28: 0 | AC28: 0 | AD28: 0 | AE28: 0 | AF28: 0 | AG28: 0 | AH28: 0 | AI28: 0 | AJ28: 0 | AK28: 0 | AL28: 0 | AM28: 345 | AN28: 345 | AO28: 347 | AP28: =1379-SUM(AM28:AO28) -> 342 | AQ28: 303 | AR28: 299 | AS28: 279 | AT28: =1150-SUM(AQ28:AS28) -> 269 | AU28: 919 | AV28: 907 | AW28: 886 | AX28: =3582-SUM(AU28:AW28) -> 870 | AY28: 763 | AZ28: 755 | BA28: 749 | BB28: =3010-SUM(AY28:BA28) -> 743 | BC28: 624 | BD28: 591 | BE28: 548 | BF28: =2307-SUM(BC28:BE28) -> 544 | BG28: 420 | BH28: 407 | BI28: 413 | BJ28: =1671-SUM(BG28:BI28) -> 431 | BK28: 202 | BS28: =SUM(C28:F28) -> 0 | BT28: =SUM(G28:J28) -> 0 | BU28: =SUM(K28:N28) -> 0 | BV28: =SUM(O28:R28) -> 0 | BW28: =SUM(S28:V28) -> 0 | BX28: =SUM(W28:Z28) -> 0 | BY28: =SUM(AA28:AD28) -> 0 | BZ28: =SUM(AE28:AH28) -> 0 | CA28: =SUM(AI28:AL28) -> 0 | CB28: =SUM(AM28:AP28) -> 1379 | CC28: =SUM(AQ28:AT28) -> 1150 | CD28: =SUM(AU28:AX28) -> 3582 | CE28: =SUM(AY28:BB28) -> 3010 | CF28: =SUM(BC28:BF28) -> 2307 | CG28: =SUM(BG28:BJ28) -> 1671 | CH28: =CH21*CH48 -> 2215.3596 | CI28: =CI21*CI48 -> 3236.8805 | CJ28: =CJ21*CJ48 -> 4113.3665 | CK28: =CK21*CK48 -> 4893.2172 | CL28: =CL21*CL48 -> 5815.3672 | CM28: =CM21*CM48 -> 6641.9073 | CN28: =CN21*CN48 -> 7062.3226 | CO28: =CO21*CO48 -> 7597.5977 | ... CQ28: =CQ21*CQ48 -> 8366.9614
B29: Restructuring & Other Op. Ex. | C29: 0 | D29: 0 | E29: 0 | F29: 0 | G29: 0 | H29: 0 | I29: 0 | J29: 0 | K29: 0 | L29: 0 | M29: 0 | N29: 0 | O29: 0 | P29: 0 | Q29: 0 | R29: 0 | S29: 0 | T29: 0 | U29: 0 | V29: 0 | W29: 0 | X29: 0 | Y29: 0 | Z29: 0 | AA29: 0 | AB29: 0 | AC29: 0 | AD29: 0 | AE29: 0 | AF29: 0 | AG29: 0 | AH29: 0 | AI29: 0 | AJ29: 0 | AK29: 0 | AL29: 0 | AM29: =19+174 -> 193 | AN29: =76+96 -> 172 | AO29: =13+66 -> 79 | AP29: =138+431-SUM(AM29:AO29) -> 125 | AQ29: =21+38 -> 59 | AR29: =4667+32 -> 4699 | AS29: =20+19 -> 39 | AT29: =4713+191-SUM(AQ29:AS29) -> 107 | AU29: =41+144 -> 185 | AV29: =62+137 -> 199 | AW29: =37+78 -> 115 | AX29: =190+490-SUM(AU29:AW29) -> 181 | AY29: =11+138 -> 149 | AZ29: =47+83 -> 130 | BA29: =155+90 -> 245 | BB29: =718-SUM(AY29:BA29) -> 194 | BC29: =13+73 -> 86 | BD29: =31+84 -> 115 | BE29: =28+63 -> 91 | BF29: =374-SUM(BC29:BE29) -> 82 | BG29: =13+402 -> 415 | BH29: =21+406 -> 427 | BI29: =20+153 -> 173 | BJ29: =1838-SUM(BG29:BI29) -> 823 | BK29: 94 | BS29: =SUM(C29:F29) -> 0 | BT29: =SUM(G29:J29) -> 0 | BU29: =SUM(K29:N29) -> 0 | BV29: =SUM(O29:R29) -> 0 | BW29: =SUM(S29:V29) -> 0 | BX29: =SUM(W29:Z29) -> 0 | BY29: =SUM(AA29:AD29) -> 0 | BZ29: =SUM(AE29:AH29) -> 0 | CA29: =SUM(AI29:AL29) -> 0 | CB29: =SUM(AM29:AP29) -> 569 | CC29: =SUM(AQ29:AT29) -> 4904 | CD29: =SUM(AU29:AX29) -> 680 | CE29: =SUM(AY29:BB29) -> 718 | CF29: =SUM(BC29:BF29) -> 374 | CG29: =SUM(BG29:BJ29) -> 1838 | CH29: =CH21*CH49 -> 4018.4912 | CI29: =CI21*CI49 -> 7176.2184 | CJ29: =CJ21*CJ49 -> 11606.512 | CK29: =CK21*CK49 -> 12233.043 | CL29: =CL21*CL49 -> 12115.348 | CM29: =CM21*CM49 -> 11069.845 | CN29: =CN21*CN49 -> 10747.013 | CO29: =CO21*CO49 -> 10735.736 | ... CQ29: =CQ21*CQ49 -> 10003.976
B30: Ttl Op. Ex. | C30: 5691 | D30: 5681 | E30: 5722 | F30: 6321 | G30: 5302 | H30: 5623 | I30: 5624 | J30: 5947 | K30: 5499 | L30: 5865 | M30: 5740 | N30: 6412 | O30: 5633 | P30: 6056 | Q30: 5944 | R30: 6722 | S30: 5794 | T30: 6038 | U30: 5985 | V30: 6626 | W30: 5954 | X30: 5998 | Y30: 6246 | Z30: 6681 | AA30: 6355 | AB30: 6550 | AC30: 6361 | AD30: 6853 | AE30: 6415 | AF30: 6461 | AG30: 6215 | AH30: 6880 | AI30: 6341 | AJ30: 6431 | AK30: 6268 | AL30: 6132 | AM30: =SUM(AM22:AM29) -> 6156 | AN30: =SUM(AN22:AN29) -> 6217 | AO30: =SUM(AO22:AO29) -> 6207 | AP30: =SUM(AP22:AP29) -> 6686 | AQ30: =SUM(AQ22:AQ29) -> 6301 | AR30: =SUM(AR22:AR29) -> 11184 | AS30: =SUM(AS22:AS29) -> 6691 | AT30: =SUM(AT22:AT29) -> 7338 | ... BK30: =SUM(BK22:BK29) -> 12617 | BS30: =SUM(C30:F30) -> 23415 | BT30: =SUM(G30:J30) -> 22496 | BU30: =SUM(K30:N30) -> 23516 | BV30: =SUM(O30:R30) -> 24355 | BW30: =SUM(S30:V30) -> 24443 | BX30: =SUM(W30:Z30) -> 24879 | BY30: =SUM(AA30:AD30) -> 26119 | BZ30: =SUM(AE30:AH30) -> 25971 | CA30: =SUM(AI30:AL30) -> 25172 | CB30: =SUM(AM30:AP30) -> 25266 | CC30: =SUM(AQ30:AT30) -> 31514 | CD30: =SUM(AU30:AX30) -> 36861 | CE30: =SUM(AY30:BB30) -> 37608 | CF30: =SUM(BC30:BF30) -> 39721 | CG30: =SUM(BG30:BJ30) -> 46751 | CH30: =SUM(CH22:CH29) -> 64816.421 | CI30: =SUM(CI22:CI29) -> 96726.319 | CJ30: =SUM(CJ22:CJ29) -> 126316.89 | CK30: =SUM(CK22:CK29) -> 148019.82 | CL30: =SUM(CL22:CL29) -> 170341.8 | CM30: =SUM(CM22:CM29) -> 189294.36 | CN30: =SUM(CN22:CN29) -> 205421.47 | CO30: =SUM(CO22:CO29) -> 217192.2 | ... CQ30: =SUM(CQ22:CQ29) -> 232274.12
B31: OI | C31: =C21-C30 -> 2683 | D31: =D21-D30 -> 3111 | E31: =E21-E30 -> 3317 | F31: =F21-F30 -> 4595 | G31: =G21-G30 -> 2879 | H31: =H21-H30 -> 3471 | I31: =I21-I30 -> 3334 | J31: =J21-J30 -> 5000 | ... BK31: =BK21-BK30 -> 6728 | BS31: =SUM(C31:F31) -> 13706 | BT31: =SUM(G31:J31) -> 14684 | BU31: =SUM(K31:N31) -> 14759 | BV31: =SUM(O31:R31) -> 13871 | BW31: =SUM(S31:V31) -> 12604 | BX31: =SUM(W31:Z31) -> 12913 | BY31: =SUM(AA31:AD31) -> 13264 | BZ31: =SUM(AE31:AH31) -> 13535 | CA31: =SUM(AI31:AL31) -> 13897 | CB31: =SUM(AM31:AP31) -> 15214 | CC31: =SUM(AQ31:AT31) -> 10927 | CD31: =SUM(AU31:AX31) -> 13094 | CE31: =SUM(AY31:BB31) -> 15353 | CF31: =SUM(BC31:BF31) -> 17678 | CG31: =SUM(BG31:BJ31) -> 20606 | CH31: =CH21-CH30 -> 24483.384 | CI31: =CI21-CI30 -> 33750.378 | CJ31: =CJ21-CJ30 -> 39490.433 | CK31: =CK21-CK30 -> 55864.229 | CL31: =CL21-CL30 -> 71965.169 | CM31: =CM21-CM30 -> 87451.779 | CN31: =CN21-CN30 -> 101636.03 | CO31: =CO21-CO30 -> 113138.14 | ... CQ31: =CQ21-CQ30 -> 131506.81
B32: Interest Expenses | C32: 0 | D32: 0 | E32: 0 | F32: 0 | G32: 0 | H32: 0 | I32: 0 | J32: 0 | K32: 0 | L32: 0 | M32: 0 | N32: 0 | O32: 0 | P32: 0 | Q32: 0 | R32: 0 | S32: 0 | T32: 0 | U32: 0 | V32: 0 | W32: 0 | X32: 0 | Y32: 0 | Z32: 0 | AA32: 0 | AB32: 0 | AC32: 0 | AD32: 0 | AE32: 0 | AF32: 0 | AG32: 0 | AH32: 0 | AI32: 0 | AJ32: 0 | AK32: 0 | AL32: 0 | AM32: -614 | AN32: -600 | AO32: -585 | AP32: =-2496-SUM(AM32:AO32) -> -697 | AQ32: -705 | AR32: -679 | AS32: -667 | AT32: =-2755-SUM(AQ32:AS32) -> -704 | AU32: -787 | AV32: -856 | AW32: -908 | AX32: =-3505-SUM(AU32:AW32) -> -954 | AY32: -872 | AZ32: -888 | BA32: -876 | BB32: =-3514-SUM(AY32:BA32) -> -878 | BC32: -842 | BD32: -866 | BE32: -892 | BF32: =-3578-SUM(BC32:BE32) -> -978 | BG32: -923 | BH32: -1057 | BI32: -1180 | BJ32: =-4599-SUM(BG32:BI32) -> -1439 | BK32: -1428 | BS32: =SUM(C32:F32) -> 0 | BT32: =SUM(G32:J32) -> 0 | BU32: =SUM(K32:N32) -> 0 | BV32: =SUM(O32:R32) -> 0 | BW32: =SUM(S32:V32) -> 0 | BX32: =SUM(W32:Z32) -> 0 | BY32: =SUM(AA32:AD32) -> 0 | BZ32: =SUM(AE32:AH32) -> 0 | CA32: =SUM(AI32:AL32) -> 0 | CB32: =SUM(AM32:AP32) -> -2496 | CC32: =SUM(AQ32:AT32) -> -2755 | CD32: =SUM(AU32:AX32) -> -3505 | CE32: =SUM(AY32:BB32) -> -3514 | CF32: =SUM(BC32:BF32) -> -3578 | CG32: =SUM(BG32:BJ32) -> -4599 | CH32: =CG70*-$CV$71 -> -8869.795 | CI32: =CH70*-$CV$71 -> -8226.7349 | CJ32: =CI70*-$CV$71 -> -7630.2966 | CK32: =CJ70*-$CV$71 -> -7077.1001 | CL32: =CK70*-$CV$71 -> -6564.0103 | CM32: =CL70*-$CV$71 -> -6088.1196 | CN32: =CM70*-$CV$71 -> -5646.7309 | CO32: =CN70*-$CV$71 -> -5237.3429 | ... CQ32: =CP70*-$CV$71 -> -4505.457
B33: Other Income | C33: -212 | D33: -151 | E33: -169 | F33: -212 | G33: -177 | H33: -191 | I33: -244 | J33: -174 | K33: -210 | L33: -207 | M33: -318 | N33: -320 | O33: -245 | P33: -273 | Q33: -233 | R33: -286 | S33: -344 | T33: -287 | U33: -295 | V33: -236 | W33: -268 | X33: -352 | Y33: -261 | Z33: -352 | AA33: -249 | AB33: -213 | AC33: -124 | AD33: -254 | AE33: -238 | AF33: -327 | AG33: -311 | AH33: -391 | AI33: -395 | AJ33: -373 | AK33: -452 | AL33: -613 | AM33: -2 | AN33: -11 | AO33: -17 | AP33: =282-SUM(AM33:AO33) -> 312 | AQ33: -41 | AR33: 7 | AS33: -315 | AT33: =-522-SUM(AQ33:AS33) -> -173 | AU33: -180 | AV33: -71 | AW33: -134 | AX33: =-462-SUM(AU33:AW33) -> -77 | AY33: -49 | AZ33: -14 | BA33: -9 | BB33: =-98-SUM(AY33:BA33) -> -26 | BC33: 20 | BD33: 36 | BE33: -18 | BF33: =60-SUM(BC33:BE33) -> 22 | BG33: 73 | BH33: 2668 | BI33: 132 | BJ33: =3547-SUM(BG33:BI33) -> 674 | BK33: 307 | BS33: =SUM(C33:F33) -> -744 | BT33: =SUM(G33:J33) -> -786 | BU33: =SUM(K33:N33) -> -1055 | BV33: =SUM(O33:R33) -> -1037 | BW33: =SUM(S33:V33) -> -1162 | BX33: =SUM(W33:Z33) -> -1233 | BY33: =SUM(AA33:AD33) -> -840 | BZ33: =SUM(AE33:AH33) -> -1267 | CA33: =SUM(AI33:AL33) -> -1833 | CB33: =SUM(AM33:AP33) -> 282 | CC33: =SUM(AQ33:AT33) -> -522 | CD33: =SUM(AU33:AX33) -> -462 | CE33: =SUM(AY33:BB33) -> -98 | CF33: =SUM(BC33:BF33) -> 60 | CG33: =SUM(BG33:BJ33) -> 3547 | CH33: =CG54*$DA$54 -> 938.67 | CI33: =CH54*$DA$54 -> 1372.5891 | CJ33: =CI54*$DA$54 -> 2077.6764 | CK33: =CJ54*$DA$54 -> 2967.3594 | CL33: =CK54*$DA$54 -> 4324.1084 | CM33: =CL54*$DA$54 -> 6151.963 | CN33: =CM54*$DA$54 -> 8446.1935 | CO33: =CN54*$DA$54 -> 11183.98 | ... CQ33: =CP54*$DA$54 -> 17779.245
B34: Pretax Income | C34: =C31+SUM(C32:C33) -> 2471 | D34: =D31+SUM(D32:D33) -> 2960 | E34: =E31+SUM(E32:E33) -> 3148 | F34: =F31+SUM(F32:F33) -> 4383 | G34: =G31+SUM(G32:G33) -> 2702 | H34: =H31+SUM(H32:H33) -> 3280 | I34: =I31+SUM(I32:I33) -> 3090 | J34: =J31+SUM(J32:J33) -> 4826 | ... BK34: =BK31+SUM(BK32:BK33) -> 5607 | BS34: =SUM(C34:F34) -> 12962 | BT34: =SUM(G34:J34) -> 13898 | BU34: =SUM(K34:N34) -> 13704 | BV34: =SUM(O34:R34) -> 12834 | BW34: =SUM(S34:V34) -> 11442 | BX34: =SUM(W34:Z34) -> 11680 | BY34: =SUM(AA34:AD34) -> 12424 | BZ34: =SUM(AE34:AH34) -> 12268 | CA34: =SUM(AI34:AL34) -> 12064 | CB34: =SUM(AM34:AP34) -> 13000 | CC34: =SUM(AQ34:AT34) -> 7650 | CD34: =SUM(AU34:AX34) -> 9127 | CE34: =SUM(AY34:BB34) -> 11741 | CF34: =SUM(BC34:BF34) -> 14160 | CG34: =SUM(BG34:BJ34) -> 19554 | CH34: =CH31+SUM(CH32:CH33) -> 16552.259 | CI34: =CI31+SUM(CI32:CI33) -> 26896.232 | CJ34: =CJ31+SUM(CJ32:CJ33) -> 33937.813 | CK34: =CK31+SUM(CK32:CK33) -> 51754.489 | CL34: =CL31+SUM(CL32:CL33) -> 69725.267 | CM34: =CM31+SUM(CM32:CM33) -> 87515.623 | CN34: =CN31+SUM(CN32:CN33) -> 104435.5 | CO34: =CO31+SUM(CO32:CO33) -> 119084.78 | ... CQ34: =CQ31+SUM(CQ32:CQ33) -> 144780.59
B35: Taxes | C35: 631 | D35: 768 | E35: 650 | F35: 932 | G35: 668 | H35: 699 | I35: 586 | J35: 1020 | K35: 472 | L35: 650 | M35: 684 | N35: 943 | O35: 534 | P35: 767 | Q35: 655 | R35: 940 | S35: 563 | T35: 471 | U35: 590 | V35: 917 | W35: 541 | X35: 653 | Y35: 459 | Z35: 575 | AA35: 356 | AB35: 612 | AC35: 7238 | AD35: 631 | AE35: 275 | AF35: 441 | AG35: 343 | AH35: 126 | AI35: 345 | AJ35: 499 | AK35: 505 | AL35: 579 | AM35: 344 | AN35: 530 | AO35: 1745 | AP35: =747-SUM(AM35:AO35) -> -1872 | AQ35: 224 | AR35: -249 | AS35: -521 | AT35: =932-SUM(AQ35:AS35) -> 1478 | AU35: 108 | AV35: 403 | AW35: 322 | AX35: =623-SUM(AU35:AW35) -> -210 | AY35: 45 | AZ35: 217 | BA35: 464 | BB35: =1274-SUM(AY35:BA35) -> 548 | BC35: 240 | BD35: 239 | BE35: 512 | BF35: =1717-SUM(BC35:BE35) -> 726 | BG35: 500 | BH35: 207 | BI35: 695 | BJ35: =2467-SUM(BG35:BI35) -> 1065 | BK35: 847 | BS35: =SUM(C35:F35) -> 2981 | BT35: =SUM(G35:J35) -> 2973 | BU35: =SUM(K35:N35) -> 2749 | BV35: =SUM(O35:R35) -> 2896 | BW35: =SUM(S35:V35) -> 2541 | BX35: =SUM(W35:Z35) -> 2228 | BY35: =SUM(AA35:AD35) -> 8837 | BZ35: =SUM(AE35:AH35) -> 1185 | CA35: =SUM(AI35:AL35) -> 1928 | CB35: =SUM(AM35:AP35) -> 747 | CC35: =SUM(AQ35:AT35) -> 932 | CD35: =SUM(AU35:AX35) -> 623 | CE35: =SUM(AY35:BB35) -> 1274 | CF35: =SUM(BC35:BF35) -> 1717 | CG35: =SUM(BG35:BJ35) -> 2467 | CH35: =CH34*CH51 -> 2088.29 | CI35: =CI34*CI51 -> 3393.3213 | CJ35: =CJ34*CJ51 -> 4281.7114 | CK35: =CK34*CK51 -> 6529.5246 | CL35: =CL34*CL51 -> 8796.7799 | CM35: =CM34*CM51 -> 11041.272 | CN35: =CN34*CN51 -> 13175.942 | CO35: =CO34*CO51 -> 15024.146 | ... CQ35: =CQ34*CQ51 -> 18266.019
B36: Net Income | C36: =C34-C35 -> 1840 | D36: =D34-D35 -> 2192 | E36: =E34-E35 -> 2498 | F36: =F34-F35 -> 3451 | G36: =G34-G35 -> 2034 | H36: =H34-H35 -> 2581 | I36: =I34-I35 -> 2504 | J36: =J34-J35 -> 3806 | ... BK36: =BK34-BK35 -> 4760 | BS36: =SUM(C36:F36) -> 9981 | BT36: =SUM(G36:J36) -> 10925 | BU36: =SUM(K36:N36) -> 10955 | BV36: =SUM(O36:R36) -> 9938 | BW36: =SUM(S36:V36) -> 8901 | BX36: =SUM(W36:Z36) -> 9452 | BY36: =SUM(AA36:AD36) -> 3587 | BZ36: =SUM(AE36:AH36) -> 11083 | CA36: =SUM(AI36:AL36) -> 10136 | CB36: =SUM(AM36:AP36) -> 12253 | CC36: =SUM(AQ36:AT36) -> 6718 | CD36: =SUM(AU36:AX36) -> 8504 | CE36: =SUM(AY36:BB36) -> 10467 | CF36: =SUM(BC36:BF36) -> 12443 | CG36: =SUM(BG36:BJ36) -> 17087 | CH36: =CH34-CH35 -> 14463.969 | CI36: =CI34-CI35 -> 23502.911 | CJ36: =CJ34-CJ35 -> 29656.102 | CK36: =CK34-CK35 -> 45224.964 | CL36: =CL34-CL35 -> 60928.487 | CM36: =CM34-CM35 -> 76474.35 | CN36: =CN34-CN35 -> 91259.554 | CO36: =CO34-CO35 -> 104060.63 | ... CQ36: =CQ34-CQ35 -> 126514.58
B37: Preferred Stock Dividends | C37: 0 | D37: 0 | E37: 0 | F37: 0 | G37: 0 | H37: 0 | I37: 0 | J37: 0 | K37: 0 | L37: 0 | M37: 0 | N37: 0 | O37: 0 | P37: 0 | Q37: 0 | R37: 0 | S37: 0 | T37: 0 | U37: 0 | V37: 0 | W37: 0 | X37: 0 | Y37: 0 | Z37: 0 | AA37: 0 | AB37: 0 | AC37: 0 | AD37: 0 | AE37: 0 | AF37: 0 | AG37: 0 | AH37: 0 | AI37: 0 | AJ37: 0 | AK37: 0 | AL37: 0 | AM37: 0 | AN37: 0 | AO37: 0 | AP37: =0-SUM(AM37:AO37) -> 0 | AQ37: 0 | AR37: 0 | AS37: 0 | AT37: =0-SUM(AQ37:AS37) -> 0 | AU37: 0 | AV37: 0 | AW37: 0 | AX37: 0 | AY37: 0 | AZ37: 0 | BA37: 0 | BB37: =0-SUM(AY37:BA37) -> 0 | BC37: 0 | BD37: 0 | BE37: 0 | BF37: =0-SUM(BC37:BE37) -> 0 | BG37: 0 | BH37: 0 | BI37: 22 | BJ37: =103-SUM(BG37:BI37) -> 81 | BK37: 81 | BS37: =SUM(C37:F37) -> 0 | BT37: =SUM(G37:J37) -> 0 | BU37: =SUM(K37:N37) -> 0 | BV37: =SUM(O37:R37) -> 0 | BW37: =SUM(S37:V37) -> 0 | BX37: =SUM(W37:Z37) -> 0 | BY37: =SUM(AA37:AD37) -> 0 | BZ37: =SUM(AE37:AH37) -> 0 | CA37: =SUM(AI37:AL37) -> 0 | CB37: =SUM(AM37:AP37) -> 0 | CC37: =SUM(AQ37:AT37) -> 0 | CD37: =SUM(AU37:AX37) -> 0 | CE37: =SUM(AY37:BB37) -> 0 | CF37: =SUM(BC37:BF37) -> 0 | CG37: =SUM(BG37:BJ37) -> 103
B38: Net Income to CS | C38: =C36-C37 -> 1840 | D38: =D36-D37 -> 2192 | E38: =E36-E37 -> 2498 | F38: =F36-F37 -> 3451 | G38: =G36-G37 -> 2034 | H38: =H36-H37 -> 2581 | I38: =I36-I37 -> 2504 | J38: =J36-J37 -> 3806 | ... BK38: =BK36-BK37 -> 4679 | BS38: =SUM(C38:F38) -> 9981 | BT38: =SUM(G38:J38) -> 10925 | BU38: =SUM(K38:N38) -> 10955 | BV38: =SUM(O38:R38) -> 9938 | BW38: =SUM(S38:V38) -> 8901 | BX38: =SUM(W38:Z38) -> 9452 | BY38: =SUM(AA38:AD38) -> 3587 | BZ38: =SUM(AE38:AH38) -> 11083 | CA38: =SUM(AI38:AL38) -> 10136 | CB38: =SUM(AM38:AP38) -> 12253 | CC38: =SUM(AQ38:AT38) -> 6718 | CD38: =SUM(AU38:AX38) -> 8504 | CE38: =SUM(AY38:BB38) -> 10467 | CF38: =SUM(BC38:BF38) -> 12443 | CG38: =SUM(BG38:BJ38) -> 16984 | CH38: =CH36-CH37 -> 14463.969 | CI38: =CI36-CI37 -> 23502.911 | CJ38: =CJ36-CJ37 -> 29656.102 | CK38: =CK36-CK37 -> 45224.964 | CL38: =CL36-CL37 -> 60928.487 | CM38: =CM36-CM37 -> 76474.35 | CN38: =CN36-CN37 -> 91259.554 | CO38: =CO36-CO37 -> 104060.63 | ... CQ38: =CQ36-CQ37 -> 126514.58 | CR38: =CQ38*(1+$DA$55) -> 128412.29 | CS38: =CR38*(1+$DA$55) -> 130338.48 | CT38: =CS38*(1+$DA$55) -> 132293.56 | CU38: =CT38*(1+$DA$55) -> 134277.96 | CV38: =CU38*(1+$DA$55) -> 136292.13 | CW38: =CV38*(1+$DA$55) -> 138336.51 | CX38: =CW38*(1+$DA$55) -> 140411.56 | CY38: =CX38*(1+$DA$55) -> 142517.73 | ... EO38: =EN38*(1+$DA$55) -> 266343.85
B39: SC | C39: 5020 | D39: 5030 | E39: 5040 | F39: 5060 | G39: 5060 | H39: 5040 | I39: 5010 | J39: 487 | K39: 4790 | L39: 4740 | M39: 4610 | N39: 4540 | O39: 4500 | P39: 4450 | Q39: 4420 | R39: 4390 | S39: 4360 | T39: 4320 | U39: 4240 | V39: 4180 | W39: 4150 | X39: 4120 | Y39: 4100 | Z39: 4110 | AA39: 4130 | AB39: 4155 | AC39: 4160 | AD39: 4120 | AE39: 4050 | AF39: 3900 | AG39: 3720 | AH39: 3530 | AI39: 3390 | AJ39: 3320 | AK39: 3250 | AL39: 3190 | AM39: 3040 | AN39: 2977 | AO39: 2913 | AP39: 2850 | AQ39: 2770 | AR39: 2690 | AS39: 2670 | AT39: 2670 | AU39: 2685 | AV39: 2700 | AW39: 2700 | AX39: 2710 | AY39: 2730 | AZ39: 2750 | BA39: 2750 | BB39: 2750 | BC39: 2760 | BD39: 2791 | BE39: 2806 | BF39: 2830 | BG39: 2860 | BH39: 2874 | BI39: 2876 | BJ39: 2880 | BK39: 2966 | BS39: =SUM(C39:F39) -> 20150 | BT39: =SUM(G39:J39) -> 15597 | BU39: =SUM(K39:N39) -> 18680 | BV39: =SUM(O39:R39) -> 17760 | BW39: =SUM(S39:V39) -> 17100 | BX39: =SUM(W39:Z39) -> 16480 | BY39: =SUM(AA39:AD39) -> 16565 | BZ39: =SUM(AE39:AH39) -> 15200 | CA39: =SUM(AI39:AL39) -> 13150 | CB39: =SUM(AM39:AP39) -> 11780 | CC39: =SUM(AQ39:AT39) -> 10800 | CD39: =SUM(AU39:AX39) -> 10795 | CE39: =SUM(AY39:BB39) -> 10980 | CF39: =SUM(BC39:BF39) -> 11187 | CG39: =SUM(BG39:BJ39) -> 11490
B40: EPS | C40: =C38/C39 -> 0.36653386 | D40: =D38/D39 -> 0.43578529 | E40: =E38/E39 -> 0.49563492 | F40: =F38/F39 -> 0.68201581 | G40: =G38/G39 -> 0.40197628 | H40: =H38/H39 -> 0.51210317 | I40: =I38/I39 -> 0.4998004 | J40: =J38/J39 -> 7.8151951 | ... BK40: =BK38/BK39 -> 1.5775455 | BS40: =SUM(C40:F40) -> 1.9799699 | BT40: =SUM(G40:J40) -> 9.2290749 | BU40: =SUM(K40:N40) -> 2.3555017 | BV40: =SUM(O40:R40) -> 2.2400784 | BW40: =SUM(S40:V40) -> 2.0878865 | BX40: =SUM(W40:Z40) -> 2.2955891 | BY40: =SUM(AA40:AD40) -> 0.87428941 | BZ40: =SUM(AE40:AH40) -> 2.9548577 | CA40: =SUM(AI40:AL40) -> 3.0946607 | CB40: =SUM(AM40:AP40) -> 4.2017554 | CC40: =SUM(AQ40:AT40) -> 2.4863562 | CD40: =SUM(AU40:AX40) -> 3.1482966 | CE40: =SUM(AY40:BB40) -> 3.8123889 | CF40: =SUM(BC40:BF40) -> 4.4475013 | CG40: =SUM(BG40:BJ40) -> 5.9105629
B42: Cloud & Software Op. Ex. | AM42: =AM22/AM21 -> 0.1079321 | AN42: =AN22/AN21 -> 0.10857143 | AO42: =AO22/AO21 -> 0.10549276 | AP42: =AP22/AP21 -> 0.10813218 | AQ42: =AQ22/AQ21 -> 0.12479441 | AR42: =AR22/AR21 -> 0.1215251 | AS42: =AS22/AS21 -> 0.12413203 | AT42: =AT22/AT21 -> 0.12119932 | ... BK42: =BK22/BK21 -> 0.33083484 | CD42: =CD22/CD21 -> 0.15539986 | CE42: =CE22/CE21 -> 0.1779989 | CF42: =CF22/CF21 -> 0.20155403 | CG42: =CG22/CG21 -> 0.26124976 | CH42: 0.28 | CI42: 0.29 | CJ42: 0.3 | CK42: 0.28 | CL42: 0.27 | CM42: 0.265 | CN42: 0.26 | CO42: 0.255 | CP42: 0.25 | CQ42: 0.245
B43: Hardware Op. Ex. | AM43: =AM23/AM21 -> 0.026262411 | AN43: =AN23/AN21 -> 0.024897959 | AO43: =AO23/AO21 -> 0.022803887 | AP43: =AP23/AP21 -> 0.022445889 | AQ43: =AQ23/AQ21 -> 0.025185033 | AR43: =AR23/AR21 -> 0.022104247 | AS43: =AS23/AS21 -> 0.02320936 | AT43: =AT23/AT21 -> 0.021452703 | ... BK43: =BK23/BK21 -> 0.014525717 | CD43: =CD23/CD21 -> 0.020818737 | CE43: =CE23/CE21 -> 0.0168237 | CF43: =CF23/CF21 -> 0.013623931 | CG43: =CG23/CG21 -> 0.01288656 | CH43: 0.014 | CI43: 0.013 | CJ43: 0.013 | CK43: 0.012 | CL43: 0.012 | CM43: 0.011 | CN43: 0.011 | CO43: 0.01 | CP43: 0.01 | CQ43: 0.01
B44: Services Op. Ex. | AM44: =AM24/AM21 -> 0.066510089 | AN44: =AN24/AN21 -> 0.064387755 | AO44: =AO24/AO21 -> 0.061570494 | AP44: =AP24/AP21 -> 0.058341498 | AQ44: =AQ24/AQ21 -> 0.066200658 | AR44: =AR24/AR21 -> 0.06476834 | AS44: =AS24/AS21 -> 0.063635499 | AT44: =AT24/AT21 -> 0.059797297 | ... BK44: =BK24/BK21 -> 0.054380977 | CD44: =CD24/CD21 -> 0.095305775 | CE44: =CE24/CE21 -> 0.091104775 | CF44: =CF24/CF21 -> 0.079722643 | CG44: =CG24/CG21 -> 0.067639592 | CH44: 0.064 | CI44: 0.065 | CJ44: 0.063 | CK44: 0.062 | CL44: 0.061 | CM44: 0.06 | CN44: 0.059 | CO44: 0.058 | CP44: 0.057 | CQ44: 0.056
B45: S&M % of Revenue | AM45: =AM25/AM21 -> 0.1979289 | AN45: =AN25/AN21 -> 0.18734694 | AO45: =AO25/AO21 -> 0.18986714 | AP45: =AP25/AP21 -> 0.18500045 | AQ45: =AQ25/AQ21 -> 0.19058388 | AR45: =AR25/AR21 -> 0.18861004 | AS45: =AS25/AS21 -> 0.19062114 | AT45: =AT25/AT21 -> 0.18876689 | ... BK45: =BK25/BK21 -> 0.093615921 | CD45: =CD25/CD21 -> 0.17681914 | CE45: =CE25/CE21 -> 0.15622817 | CF45: =CF25/CF21 -> 0.15071691 | CG45: =CG25/CG21 -> 0.12368425 | CH45: 0.119 | CI45: 0.117 | CJ45: 0.115 | CK45: 0.114 | CL45: 0.113 | CM45: 0.112 | CN45: 0.111 | CO45: 0.11 | CP45: 0.11 | CQ45: 0.11
B46: R&D as % of Revenue | AM46: =AM26/AM21 -> 0.16963809 | AN46: =AN26/AN21 -> 0.16336735 | AO46: =AO26/AO21 -> 0.16071783 | AP46: =AP26/AP21 -> 0.15284582 | AQ46: =AQ26/AQ21 -> 0.17310855 | AR46: =AR26/AR21 -> 0.16930502 | AS46: =AS26/AS21 -> 0.17273851 | AT46: =AT26/AT21 -> 0.16596284 | ... BK46: =BK26/BK21 -> 0.12411476 | CD46: =CD26/CD21 -> 0.17261535 | CE46: =CE26/CE21 -> 0.16833141 | CF46: =CF26/CF21 -> 0.17178 | CG46: =CG26/CG21 -> 0.15250085 | CH46: 0.155 | CI46: 0.15250085 | CJ46: 0.152 | CK46: 0.151 | CL46: 0.15 | CM46: 0.149 | CN46: 0.148 | CO46: 0.147 | CP46: 0.146 | CQ46: 0.145
B47: G&A as % of Revenue | AM47: =AM27/AM21 -> 0.031493541 | AN47: =AN27/AN21 -> 0.033061224 | AO47: =AO27/AO21 -> 0.03271862 | AP47: =AP27/AP21 -> 0.027166652 | AQ47: =AQ27/AQ21 -> 0.030633224 | AR47: =AR27/AR21 -> 0.030791506 | AS47: =AS27/AS21 -> 0.03186531 | AT47: =AT27/AT21 -> 0.030827703 | ... BK47: =BK27/BK21 -> 0.019436547 | CD47: =CD27/CD21 -> 0.031608448 | CE47: =CE27/CE21 -> 0.029229055 | CF47: =CF27/CF21 -> 0.027909894 | CG47: =CG27/CG21 -> 0.02402126 | CH47: 0.02402126 | CI47: 0.02402126 | CJ47: 0.02402126 | CK47: 0.023 | CL47: 0.023 | CM47: 0.023 | CN47: 0.022 | CO47: 0.022 | CP47: 0.022 | CQ47: 0.022
B48: Amm. % of Revenue | AM48: =AM28/AM21 -> 0.036831429 | AN48: =AN28/AN21 -> 0.035204082 | AO48: =AO28/AO21 -> 0.034404125 | AP48: =AP28/AP21 -> 0.030462278 | AQ48: =AQ28/AQ21 -> 0.031147204 | AR48: =AR28/AR21 -> 0.028861004 | AS48: =AS28/AS21 -> 0.026538571 | AT48: =AT28/AT21 -> 0.022719595 | ... BK48: =BK28/BK21 -> 0.010441975 | CD48: =CD28/CD21 -> 0.071704534 | CE48: =CE28/CE21 -> 0.056834274 | CF48: =CF28/CF21 -> 0.040192338 | CG48: =CG28/CG21 -> 0.024808112 | CH48: 0.024808112 | CI48: 0.024808112 | CJ48: 0.024808112 | CK48: 0.024 | CL48: 0.024 | CM48: 0.024 | CN48: 0.023 | CO48: 0.023 | CP48: 0.023 | CQ48: 0.023
B49: Other Op. Ex. % of Revenue | C49: =C30/C21 -> 0.67960353 | D49: =D30/D21 -> 0.6461556 | E49: =E30/E21 -> 0.63303463 | F49: =F30/F21 -> 0.57905826 | G49: =G30/G21 -> 0.64808703 | H49: =H30/H21 -> 0.61831977 | I49: =I30/I21 -> 0.62781871 | J49: =J30/J21 -> 0.54325386 | ... AL49: =AL30/AL21 -> 0.58730007 | AM49: =AM29/AM21 -> 0.020604249 | AN49: =AN29/AN21 -> 0.01755102 | AO49: =AO29/AO21 -> 0.0078326393 | AP49: =AP29/AP21 -> 0.011133874 | AQ49: =AQ29/AQ21 -> 0.0060649671 | AR49: =AR29/AR21 -> 0.45357143 | AS49: =AS29/AS21 -> 0.0037096928 | AT49: =AT29/AT21 -> 0.0090371622 | ... BK49: =BK29/BK21 -> 0.0048591367 | CD49: =CD29/CD21 -> 0.013612251 | CE49: =CE29/CE21 -> 0.013557146 | CF49: =CF29/CF21 -> 0.006515793 | CG49: =CG29/CG21 -> 0.027287439 | CH49: 0.045 | CI49: 0.055 | CJ49: 0.07 | CK49: 0.06 | CL49: 0.05 | CM49: 0.04 | CN49: 0.035 | CO49: 0.0325 | CP49: 0.03 | CQ49: 0.0275
B50: Operating Profit Margin | C50: =C31/C21 -> 0.32039647 | D50: =D31/D21 -> 0.3538444 | E50: =E31/E21 -> 0.36696537 | F50: =F31/F21 -> 0.42094174 | G50: =G31/G21 -> 0.35191297 | H50: =H31/H21 -> 0.38168023 | I50: =I31/I21 -> 0.37218129 | J50: =J31/J21 -> 0.45674614 | ... BK50: =BK31/BK21 -> 0.34779013 | CD50: =CD31/CD21 -> 0.2621159 | CE50: =CE31/CE21 -> 0.28989256 | CF50: =CF31/CF21 -> 0.30798446 | CG50: =CG31/CG21 -> 0.30592218 | CH50: =CH31/CH21 -> 0.27417063 | CI50: =CI31/CI21 -> 0.25866977 | CJ50: =CJ31/CJ21 -> 0.23817063 | CK50: =CK31/CK21 -> 0.274 | ... CQ50: =CQ31/CQ21 -> 0.3615
B51: Effective Tax Rate | C51: =C35/C34 -> 0.2553622 | D51: =D35/D34 -> 0.25945946 | E51: =E35/E34 -> 0.2064803 | F51: =F35/F34 -> 0.21263974 | G51: =G35/G34 -> 0.24722428 | H51: =H35/H34 -> 0.21310976 | I51: =I35/I34 -> 0.18964401 | J51: =J35/J34 -> 0.21135516 | ... BK51: =BK35/BK34 -> 0.15106117 | CD51: =CD35/CD34 -> 0.068259012 | CE51: =CE35/CE34 -> 0.10850864 | CF51: =CF35/CF34 -> 0.12125706 | CG51: =CG35/CG34 -> 0.12616344 | CH51: 0.12616344 | CI51: 0.12616344 | CJ51: 0.12616344 | CK51: 0.12616344 | CL51: 0.12616344 | CM51: 0.12616344 | CN51: 0.12616344 | CO51: 0.12616344 | CP51: 0.12616344 | CQ51: 0.12616344
B52: Net Profit Margin | C52: =C38/C21 -> 0.21972773 | D52: =D38/D21 -> 0.24931756 | E52: =E38/E21 -> 0.276358 | F52: =F38/F21 -> 0.31614144 | G52: =G38/G21 -> 0.24862486 | H52: =H38/H21 -> 0.2838135 | I52: =I38/I21 -> 0.27952668 | J52: =J38/J21 -> 0.34767516 | ... BK52: =BK38/BK21 -> 0.24187128 | CD52: =CD38/CD21 -> 0.17023321 | CE52: =CE38/CE21 -> 0.197636 | CF52: =CF38/CF21 -> 0.21678078 | CG52: =CG38/CG21 -> 0.252149 | CH52: 0.252149 | CI52: 0.252149 | CJ52: 0.252149 | CK52: 0.252149 | CL52: 0.252149 | CM52: 0.252149 | CN52: 0.252149 | CO52: 0.252149 | CP52: 0.252149 | CQ52: 0.252149
B54: Cash & CEs | AX54: 9765 | AY54: 11613 | AZ54: 8244 | BA54: 9481 | BB54: 10454 | BC54: 10616 | BD54: 10941 | BE54: 17406 | BF54: 10786 | BG54: 10445 | BH54: 19241 | BI54: 38455 | BJ54: 31289 | BK54: 36369 | CD54: =AX54 -> 9765 | CE54: =BB54 -> 10454 | CF54: =BF54 -> 10786 | CG54: =BJ54 -> 31289 | CH54: =CG54+CH38 -> 45752.969 | CI54: =CH54+CI38 -> 69255.879 | CJ54: =CI54+CJ38 -> 98911.981 | CK54: =CJ54+CK38 -> 144136.95 | CL54: =CK54+CL38 -> 205065.43 | CM54: =CL54+CM38 -> 281539.78 | CN54: =CM54+CN38 -> 372799.34 | CO54: =CN54+CO38 -> 476859.97 | ... CQ54: =CP54+CQ38 -> 719156.09 | CS54: Invested Capital | CV54: Avg. (2025-2026) | CX54: Projected ROIC: | CZ54: ROIC | DA54: 0.03
B55: Marketable Securities | AX55: 422 | AY55: 470 | AZ55: 446 | BA55: 423 | BB55: 207 | BC55: 295 | BD55: 370 | BE55: 417 | BF55: 417 | BG55: 560 | BH55: 525 | BI55: 677 | BJ55: 605 | BK55: 708 | CD55: =AX55 -> 422 | CE55: =BB55 -> 207 | CF55: =BF55 -> 417 | CG55: =BJ55 -> 605 | CS55: 2025 | CT55: 2026 | CV55: 2025-2026 | CX55: 2025 | CZ55: Terminal | DA55: 0.015
B56: A/R | AX56: 6915 | AY56: 6519 | AZ56: 6804 | BA56: 7297 | BB56: 7874 | BC56: 8021 | BD56: 8177 | BE56: 8051 | BF56: 8558 | BG56: 8843 | BH56: 9440 | BI56: 10719 | BJ56: 10385 | BK56: 11394 | CD56: =AX56 -> 6915 | CE56: =BB56 -> 7874 | CF56: =BF56 -> 8558 | CG56: =BJ56 -> 10385 | CS56: =SUM(CF54:CF57)-CF65-CF66+CF58+CF60 -> 117924 | CT56: =SUM(CG54:CG57)-CG65-CG66+CG58+CG60 -> 190609 | CV56: =AVERAGE(CS56:CS56) -> 117924 | CX56: =AVERAGE(CG35)*(1-CG51) -> 2155.7548 | CZ56: RFR (10-year yield) | DA56: =CV65 -> 0.0474
B57: Other ST Assets | AX57: 3902 | AY57: 3564 | AZ57: 3795 | BA57: 3862 | BB57: 4019 | BC57: 4140 | BD57: 4015 | BE57: 4242 | BF57: 4818 | BG57: 4786 | BH57: 5160 | BI57: 5023 | BJ57: 4288 | BK57: 7159 | CD57: =AX57 -> 3902 | CE57: =BB57 -> 4019 | CF57: =BF57 -> 4818 | CG57: =BJ57 -> 4288 | CX57: =CX56/CV56 -> 0.018280882 | CZ57: ERP (Avg. market return - (less) RFR) | DA57: =9.75%-DA56 -> 0.0501
B58: PP&E | AX58: 17069 | AY58: 17644 | AZ58: 18009 | BA58: 19117 | BB58: 21536 | BC58: 23094 | BD58: 26432 | BE58: 31970 | BF58: 43522 | BG58: 53194 | BH58: 67875 | BI58: 83617 | BJ58: 99957 | BK58: 127845 | CD58: =AX58 -> 17069 | CE58: =BB58 -> 21536 | CF58: =BF58 -> 43522 | CG58: =BJ58 -> 99957 | CS58: Capital Structure | CZ58: Equity β (1-year avg.) | DA58: ='Notes | Quant Analysis'!S206 -> 1.916003
B59: LT Operating Lease Assets | AX59: 9837 | AY59: 9074 | AZ59: 8378 | BA59: 7629 | BB59: 6890 | BC59: 6270 | BD59: 5679 | BE59: 5131 | BF59: 13145 | BG59: 4167 | BH59: 3760 | BI59: 3641 | BJ59: 29690 | BK59: 33967 | CD59: =AX59 -> 9837 | CE59: =BB59 -> 6890 | CF59: =BF59 -> 13145 | CG59: =BJ59 -> 29690 | CS59: Mkt Cap | CV59: =Main!C5 -> 419392.4 | CZ59: Discount (Cost of Equity) | DA59: =+DA56+(DA57*DA58) -> 0.14339175
B60: Goodwill | AX60: 62261 | AY60: 62206 | AZ60: 62231 | BA60: 62222 | BB60: 62230 | BC60: 62249 | BD60: 62204 | BE60: 62171 | BF60: 62207 | BG60: 62211 | BH60: 62207 | BI60: 62274 | BJ60: 62261 | BK60: 62267 | CD60: =AX60 -> 62261 | CE60: =BB60 -> 62230 | CF60: =BF60 -> 62207 | CG60: =BJ60 -> 62261 | CS60: Debt to Ttl Mkt Cap | CV60: =Main!C7/(Main!C7+CV59) -> 0.23009039
B61: LT Deferred Tax Assets | AX61: 12226 | AY61: 12243 | AZ61: 12758 | BA61: 12688 | BB61: 12273 | BC61: 12219 | BD61: 11984 | BE61: 11799 | BF61: 11877 | BG61: 11734 | BH61: 11531 | BI61: 11360 | BJ61: 11541 | BK61: 11625 | CD61: =AX61 -> 12226 | CE61: =BB61 -> 12273 | CF61: =BF61 -> 11877 | CG61: =BJ61 -> 11541 | CS61: Mkt Equity to Ttl Mkt Cap | CV61: =CV59/(CV59+Main!C7) -> 0.76990961 | CZ61: NPV | DA61: =NPV(DA59,CH38:EO38) -> 542676.59
B62: Other LT Assets | AX62: 11987 | AY62: 13329 | AZ62: 13659 | BA62: 14363 | BB62: 15493 | BC62: 17310 | BD62: 18681 | BE62: 20191 | BF62: 13031 | BG62: 24509 | BH62: 25245 | BI62: 29474 | BJ62: 11743 | BK62: 11925 | CD62: =AX62 -> 11987 | CE62: =BB62 -> 15493 | CF62: =BF62 -> 13031 | CG62: =BJ62 -> 11743 | CS62: LT Debt / Equity | CV62: =CG70/CG75 -> 2.8414623 | CZ62: SC | DA62: =Main!C4 -> 2966
B63: Ttl Assets | AX63: =SUM(AX54:AX62) -> 134384 | AY63: =SUM(AY54:AY62) -> 136662 | AZ63: =SUM(AZ54:AZ62) -> 134324 | BA63: =SUM(BA54:BA62) -> 137082 | BB63: =SUM(BB54:BB62) -> 140976 | BC63: =SUM(BC54:BC62) -> 144214 | BD63: =SUM(BD54:BD62) -> 148483 | BE63: =SUM(BE54:BE62) -> 161378 | ... BK63: =SUM(BK54:BK62) -> 303259 | CD63: =AX63 -> 134384 | CE63: =BB63 -> 140976 | CF63: =BF63 -> 168361 | CG63: =BJ63 -> 261759 | CZ63: FV | DA63: =DA61/DA62 -> 182.96581
CS64: Cost of Equity | CZ64: CP | DA64: =Main!C3 -> 141.4
B65: ST Debt | AX65: 4061 | AY65: 4499 | AZ65: 6321 | BA65: 5510 | BB65: 10605 | BC65: 9201 | BD65: 8162 | BE65: 8167 | BF65: 7271 | BG65: 9079 | BH65: 8091 | BI65: 9887 | BJ65: 7199 | BK65: 7625 | CD65: =AX65 -> 4061 | CE65: =BB65 -> 10605 | CF65: =BF65 -> 7271 | CG65: =BJ65 -> 7199 | CS65: RFR (10-year yield) | CV65: 0.0474 | CZ65: Change Δ | DA65: =DA63/DA64-1 -> 0.29395904 | DB65: =IF(DA65>0,"Upside","Downside") -> Upside
B66: A/P | AX66: 1204 | AY66: 1034 | AZ66: 1107 | BA66: 1658 | BB66: 2357 | BC66: 2207 | BD66: 2679 | BE66: 2423 | BF66: 5113 | BG66: 8203 | BH66: 10140 | BI66: 9474 | BJ66: 10977 | BK66: 11063 | CD66: =AX66 -> 1204 | CE66: =BB66 -> 2357 | CF66: =BF66 -> 5113 | CG66: =BJ66 -> 10977 | CS66: Equity β (1-year avg.) | CV66: ='Notes | Quant Analysis'!S206 -> 1.916003 | CZ66: {=_xlfn.IFS(DA65>=25%,"Strong Buy",DA65>=10.00001%,"Buy",AND(DA65<=10%,DA65>=-4.9999%),"Hold",AND(DA65<=-5%,DA65>=-14.999999%),"Sell",DA65<=-15%,"Strong Sell")} -> Strong Buy
B67: ST Comp & Benefits Liabilities | AX67: 2053 | AY67: 1818 | AZ67: 1706 | BA67: 1796 | BB67: 1916 | BC67: 1772 | BD67: 1653 | BE67: 1839 | BF67: 2243 | BG67: 1794 | BH67: 1947 | BI67: 1940 | BJ67: 2225 | BK67: 1760 | CD67: =AX67 -> 2053 | CE67: =BB67 -> 1916 | CF67: =BF67 -> 2243 | CG67: =BJ67 -> 2225 | CS67: Market Return(1-year avg.) | CV67: 0.1015
B68: ST Deferred Revenues Liabilities | AX68: 8970 | AY68: 11120 | AZ68: 8878 | BA68: 8931 | BB68: 9313 | BC68: 11455 | BD68: 9430 | BE68: 9019 | BF68: 9387 | BG68: 12098 | BH68: 9940 | BI68: 9881 | BJ68: 9916 | BK68: 14686 | CD68: =AX68 -> 8970 | CE68: =BB68 -> 9313 | CF68: =BF68 -> 9387 | CG68: =BJ68 -> 9916 | CS68: Cost of Equity | CV68: =(CV65+CV66)*(CV67-CV65) -> 0.1062201
B69: Other ST Liabilities | AX69: 6802 | AY69: 6886 | AZ69: 6395 | BA69: 6990 | BB69: 7353 | BC69: 7410 | BD69: 7128 | BE69: 8175 | BF69: 8629 | BG69: 8700 | BH69: 7677 | BI69: 9555 | BJ69: 11447 | BK69: 12380 | CD69: =AX69 -> 6802 | CE69: =BB69 -> 7353 | CF69: =BF69 -> 8629 | CG69: =BJ69 -> 11447
B70: LT Debt | AX70: 86420 | AY70: 84442 | AZ70: 82468 | BA70: 82470 | BB70: 76264 | BC70: 75314 | BD70: 80462 | BE70: 88109 | BF70: 85297 | BG70: 82236 | BH70: 99984 | BI70: 124718 | BJ70: 122342 | BK70: 117712 | CD70: =AX70 -> 86420 | CE70: =BB70 -> 76264 | CF70: =BF70 -> 85297 | CG70: =BJ70 -> 122342 | CH70: =CG70+CH32 -> 113472.21 | CI70: =CH70+CI32 -> 105245.47 | CJ70: =CI70+CJ32 -> 97615.174 | CK70: =CJ70+CK32 -> 90538.073 | CL70: =CK70+CL32 -> 83974.063 | CM70: =CL70+CM32 -> 77885.944 | CN70: =CM70+CN32 -> 72239.213 | CO70: =CN70+CO32 -> 67001.87 | ... CQ70: =CP70+CQ32 -> 57638.777 | CS70: Cost of Debt
B71: LT Taxes Payable | AX71: 11077 | AY71: 11201 | AZ71: 10046 | BA71: 10451 | BB71: 10817 | BC71: 11038 | BD71: 9553 | BE71: 9813 | BF71: 10269 | BG71: 10583 | BH71: 10885 | BI71: 11402 | BJ71: 11771 | BK71: 12060 | CD71: =AX71 -> 11077 | CE71: =BB71 -> 10817 | CF71: =BF71 -> 10269 | CG71: =BJ71 -> 11771 | CS71: Cost of Debt | CV71: 0.0725
B72: LT Operating Lease Liabilities | AX72: 5772 | AY72: 5281 | AZ72: 5244 | BA72: 4483 | BB72: 3692 | BC72: 3442 | BD72: 2864 | BE72: 2208 | BF72: 11536 | BG72: 14094 | BH72: 16311 | BI72: 18512 | BJ72: 26648 | BK72: 30594 | CD72: =AX72 -> 5772 | CE72: =BB72 -> 3692 | CF72: =BF72 -> 11536 | CG72: =BJ72 -> 26648 | CS72: Tax Rate | CV72: =CG51 -> 0.12616344
B73: Other LT Liabilities | AX73: 6469 | AY73: 7540 | AZ73: 7781 | BA73: 8611 | BB73: 9420 | BC73: 11106 | BD73: 12316 | BE73: 14364 | BF73: 7647 | BG73: 8996 | BH73: 9552 | BI73: 10820 | BJ73: 16178 | BK73: 28183 | CD73: =AX73 -> 6469 | CE73: =BB73 -> 9420 | CF73: =BF73 -> 7647 | CG73: =BJ73 -> 16178 | CS73: After Tax Cost of Debt | CV73: =CV71*(1-CV72) -> 0.06335315
B74: Ttl Liabilities | AX74: =SUM(AX65:AX73) -> 132828 | AY74: =SUM(AY65:AY73) -> 133821 | AZ74: =SUM(AZ65:AZ73) -> 129946 | BA74: =SUM(BA65:BA73) -> 130900 | BB74: =SUM(BB65:BB73) -> 131737 | BC74: =SUM(BC65:BC73) -> 132945 | BD74: =SUM(BD65:BD73) -> 134247 | BE74: =SUM(BE65:BE73) -> 144117 | ... BK74: =SUM(BK65:BK73) -> 236063 | CD74: =AX74 -> 132828 | CE74: =BB74 -> 131737 | CF74: =BF74 -> 147392 | CG74: =BJ74 -> 218703
B75: Ttl SE | AX75: 1556 | AY75: 2841 | AZ75: 4378 | BA75: 6182 | BB75: 9239 | BC75: 11269 | BD75: 14236 | BE75: 17261 | BF75: 20969 | BG75: 24666 | BH75: 30457 | BI75: 39051 | BJ75: 43056 | BK75: 67196 | CD75: =AX75 -> 1556 | CE75: =BB75 -> 9239 | CF75: =BF75 -> 20969 | CG75: =BJ75 -> 43056 | CS75: WACC | CV75: =(CV61*CV68)+(CV60*CV73*(1-CV72)) -> 0.094517752
B76: Ttl L + SE | AX76: =AX74+AX75 -> 134384 | AY76: =AY74+AY75 -> 136662 | AZ76: =AZ74+AZ75 -> 134324 | BA76: =BA74+BA75 -> 137082 | BB76: =BB74+BB75 -> 140976 | BC76: =BC74+BC75 -> 144214 | BD76: =BD74+BD75 -> 148483 | BE76: =BE74+BE75 -> 161378 | ... BK76: =BK74+BK75 -> 303259 | CD76: =AX76 -> 134384 | CE76: =BB76 -> 140976 | CF76: =BF76 -> 168361 | CG76: =BJ76 -> 261759
B78: Current Ratio | AX78: =SUM(AX54:AX57)/SUM(AX65:AX69) -> 0.90965786 | AY78: =SUM(AY54:AY57)/SUM(AY65:AY69) -> 0.87415704 | AZ78: =SUM(AZ54:AZ57)/SUM(AZ65:AZ69) -> 0.79030606 | BA78: =SUM(BA54:BA57)/SUM(BA65:BA69) -> 0.8464135 | BB78: =SUM(BB54:BB57)/SUM(BB65:BB69) -> 0.71500127 | BC78: =SUM(BC54:BC57)/SUM(BC65:BC69) -> 0.71998752 | BD78: =SUM(BD54:BD57)/SUM(BD65:BD69) -> 0.80899766 | BE78: =SUM(BE54:BE57)/SUM(BE65:BE69) -> 1.0166425 | ... BK78: =SUM(BK54:BK57)/SUM(BK65:BK69) -> 1.1708128 | CD78: =SUM(CD54:CD57)/SUM(CD65:CD69) -> 0.90965786 | CE78: =SUM(CE54:CE57)/SUM(CE65:CE69) -> 0.71500127 | CF78: =SUM(CF54:CF57)/SUM(CF65:CF69) -> 0.75296388 | CG78: =SUM(CG54:CG57)/SUM(CG65:CG69) -> 1.1150034
B79: Cash Ratio | AX79: =SUM(AX54:AX55)/SUM(AX65:AX69) -> 0.44118666 | AY79: =SUM(AY54:AY55)/SUM(AY65:AY69) -> 0.47651536 | AZ79: =SUM(AZ54:AZ55)/SUM(AZ65:AZ69) -> 0.3560454 | BA79: =SUM(BA54:BA55)/SUM(BA65:BA69) -> 0.39799076 | BB79: =SUM(BB54:BB55)/SUM(BB65:BB69) -> 0.33797236 | BC79: =SUM(BC54:BC55)/SUM(BC65:BC69) -> 0.34048994 | BD79: =SUM(BD54:BD55)/SUM(BD65:BD69) -> 0.38933636 | BE79: =SUM(BE54:BE55)/SUM(BE65:BE69) -> 0.60166087 | ... BK79: =SUM(BK54:BK55)/SUM(BK65:BK69) -> 0.78033843 | CD79: =SUM(CD54:CD55)/SUM(CD65:CD69) -> 0.44118666 | CE79: =SUM(CE54:CE55)/SUM(CE65:CE69) -> 0.33797236 | CF79: =SUM(CF54:CF55)/SUM(CF65:CF69) -> 0.34319762 | CG79: =SUM(CG54:CG55)/SUM(CG65:CG69) -> 0.76367206
B80: Fixed Asset Turnover Ratio | AX80: =AX21/(AVERAGE((AU58:AX58))) -> 0.81065089 | AY80: =AY21/(AVERAGE((AV58:AY58))) -> 0.71748336 | AZ80: =AZ21/(AVERAGE((AW58:AZ58))) -> 0.73637191 | BA80: =BA21/(AVERAGE((AX58:BA58))) -> 0.73943123 | BB80: =BB21/(AVERAGE((AY58:BB58))) -> 0.74893193 | BC80: =BC21/(AVERAGE((AZ58:BC58))) -> 0.65105925 | BD80: =BD21/(AVERAGE((BA58:BD58))) -> 0.62360417 | BE80: =BE21/(AVERAGE((BB58:BE58))) -> 0.54856744 | ... BK80: =BK21/(AVERAGE((BH58:BK58))) -> 0.20401061 | CD80: =CD21/(AVERAGE((CA58:CD58))) -> 2.9266507 | CE80: =CE21/(AVERAGE((CB58:CE58))) -> 2.7437379 | CF80: =CF21/(AVERAGE((CC58:CF58))) -> 2.0967161 | CG80: =CG21/(AVERAGE((CD58:CG58))) -> 1.4796907
B81: Ttl Asset Turnover Ratio | AX81: =AX21/AX76 -> 0.10296613 | AY81: =AY21/AY76 -> 0.091122624 | AZ81: =AZ21/AZ76 -> 0.096341681 | BA81: =BA21/BA76 -> 0.096876322 | BB81: =BB21/BB76 -> 0.10134349 | BC81: =BC21/BC76 -> 0.092272595 | BD81: =BD21/BD76 -> 0.09468424 | BE81: =BE21/BE76 -> 0.087558403 | ... BK81: =BK21/BK76 -> 0.063790357 | CD81: =CD21/CD76 -> 0.37173324 | CE81: =CE21/CE76 -> 0.37567387 | CF81: =CF21/CF76 -> 0.34092812 | CG81: =CG21/CG76 -> 0.25732449
B82: Return on Assets | AX82: =AX38/AX76 -> 0.024697881 | AY82: =AY38/AY76 -> 0.017049363 | AZ82: =AZ38/AZ76 -> 0.018634049 | BA82: =BA38/BA76 -> 0.017515064 | BB82: =BB38/BB76 -> 0.022932982 | BC82: =BC38/BC76 -> 0.020310095 | BD82: =BD38/BD76 -> 0.021221285 | BE82: =BE38/BE76 -> 0.01819331 | ... BK82: =BK38/BK76 -> 0.015429056 | CD82: =CD38/CD76 -> 0.063281343 | CE82: =CE38/CE76 -> 0.07424668 | CF82: =CF38/CF76 -> 0.073906665 | CG82: =CG38/CG76 -> 0.064884111
B83: Return on Equity | AX83: =AX38/AX75 -> 2.1330334 | AY83: =AY38/AY75 -> 0.82013376 | AZ83: =AZ38/AZ75 -> 0.57172225 | BA83: =BA38/BA75 -> 0.38838564 | BB83: =BB38/BB75 -> 0.34992965 | BC83: =BC38/BC75 -> 0.25991659 | BD83: =BD38/BD75 -> 0.22134026 | BE83: =BE38/BE75 -> 0.17009443 | ... BK83: =BK38/BK75 -> 0.069632121 | CD83: =CD38/CD75 -> 5.4652956 | CE83: =CE38/CE75 -> 1.1329148 | CF83: =CF38/CF75 -> 0.59339978 | CG83: =CG38/CG75 -> 0.39446302
B85: Net Income | C85: =C38 -> 1840 | D85: =D38 -> 2192 | E85: =E38 -> 2498 | F85: =F38 -> 3451 | G85: =G38 -> 2034 | H85: =H38 -> 2581 | I85: =I38 -> 2504 | J85: =J38 -> 3806 | ... BK85: =BK38 -> 4679 | BS85: =SUM(C85:F85) -> 9981 | BT85: =SUM(G85:J85) -> 10925 | BU85: =SUM(K85:N85) -> 10955 | BV85: =SUM(O85:R85) -> 9938 | BW85: =SUM(S85:V85) -> 8901 | BX85: =SUM(W85:Z85) -> 9452 | BY85: =SUM(AA85:AD85) -> 3587 | BZ85: =SUM(AE85:AH85) -> 11083 | CA85: =SUM(AI85:AL85) -> 10136 | CB85: =SUM(AM85:AP85) -> 12253 | CC85: =SUM(AQ85:AT85) -> 6718 | CD85: =SUM(AU85:AX85) -> 8504 | CE85: =SUM(AY85:BB85) -> 10467 | CF85: =SUM(BC85:BF85) -> 12443 | CG85: =SUM(BG85:BJ85) -> 16984
B86: CFFO | C86: 5421 | D86: 1255 | E86: 3010 | F86: 4057 | G86: 5671 | H86: 795 | I86: 3194 | J86: 4564 | K86: 6292 | L86: 1146 | M86: 3027 | N86: 4456 | O86: 6728 | P86: 1062 | Q86: 2263 | R86: 4527 | S86: 5881 | T86: 516 | U86: 3495 | V86: 3793 | W86: 5875 | X86: 1086 | Y86: 2699 | Z86: 4466 | AA86: 6566 | AB86: 850 | AC86: 3310 | AD86: 4660 | AE86: 6722 | AF86: 546 | AG86: 2861 | AH86: 4422 | AI86: 6000 | AJ86: 513 | AK86: 3012 | AL86: 3614 | AM86: 5953 | AN86: 1388 | AO86: 3704 | AP86: 4842 | AQ86: 5391 | AR86: -3682 | AS86: 3845 | AT86: 3985 | AU86: 6394 | AV86: 849 | AW86: 4275 | AX86: 5647 | AY86: 6974 | AZ86: 143 | BA86: 5475 | BB86: 6081 | BC86: 7427 | BD86: 1304 | BE86: 5933 | BF86: 6157 | BG86: 8140 | BH86: 2066 | BI86: 7151 | BJ86: 14620 | BK86: 23103 | BS86: =SUM(C86:F86) -> 13743 | BT86: =SUM(G86:J86) -> 14224 | BU86: =SUM(K86:N86) -> 14921 | BV86: =SUM(O86:R86) -> 14580 | BW86: =SUM(S86:V86) -> 13685 | BX86: =SUM(W86:Z86) -> 14126 | BY86: =SUM(AA86:AD86) -> 15386 | BZ86: =SUM(AE86:AH86) -> 14551 | CA86: =SUM(AI86:AL86) -> 13139 | CB86: =SUM(AM86:AP86) -> 15887 | CC86: =SUM(AQ86:AT86) -> 9539 | CD86: =SUM(AU86:AX86) -> 17165 | CE86: =SUM(AY86:BB86) -> 18673 | CF86: =SUM(BC86:BF86) -> 20821 | CG86: =SUM(BG86:BJ86) -> 31977
B87: CapEx, net | C87: -160 | D87: -129 | E87: -142 | F87: -217 | G87: -139 | H87: -212 | I87: -116 | J87: -183 | K87: -153 | L87: -126 | M87: -147 | N87: -154 | O87: -201 | P87: -225 | Q87: -368 | R87: -597 | S87: -446 | T87: -195 | U87: -368 | V87: -180 | W87: -299 | X87: -757 | Y87: -440 | Z87: -525 | AA87: -473 | AB87: -599 | AC87: -286 | AD87: -378 | AE87: -383 | AF87: -421 | AG87: -443 | AH87: -413 | AI87: -386 | AJ87: -349 | AK87: -396 | AL87: -433 | AM87: -436 | AN87: -568 | AO87: -414 | AP87: -717 | AQ87: -1062 | AR87: -925 | AS87: -1101 | AT87: -1423 | AU87: -1719 | AV87: -2435 | AW87: -2628 | AX87: -1913 | AY87: -1314 | AZ87: -1080 | BA87: -1674 | BB87: -2798 | BC87: -2303 | BD87: -3970 | BE87: -5862 | BF87: -9080 | BG87: -8502 | BH87: -12033 | BI87: -18635 | BJ87: -16493 | BK87: -28499 | BS87: =SUM(C87:F87) -> -648 | BT87: =SUM(G87:J87) -> -650 | BU87: =SUM(K87:N87) -> -580 | BV87: =SUM(O87:R87) -> -1391 | BW87: =SUM(S87:V87) -> -1189 | BX87: =SUM(W87:Z87) -> -2021 | BY87: =SUM(AA87:AD87) -> -1736 | BZ87: =SUM(AE87:AH87) -> -1660 | CA87: =SUM(AI87:AL87) -> -1564 | CB87: =SUM(AM87:AP87) -> -2135 | CC87: =SUM(AQ87:AT87) -> -4511 | CD87: =SUM(AU87:AX87) -> -8695 | CE87: =SUM(AY87:BB87) -> -6866 | CF87: =SUM(BC87:BF87) -> -21215 | CG87: =SUM(BG87:BJ87) -> -55663
B88: FCF | C88: =C86+C87 -> 5261 | D88: =D86+D87 -> 1126 | E88: =E86+E87 -> 2868 | F88: =F86+F87 -> 3840 | G88: =G86+G87 -> 5532 | H88: =H86+H87 -> 583 | I88: =I86+I87 -> 3078 | J88: =J86+J87 -> 4381 | ... BK88: =BK86+BK87 -> -5396 | BS88: =SUM(C88:F88) -> 13095 | BT88: =SUM(G88:J88) -> 13574 | BU88: =SUM(K88:N88) -> 14341 | BV88: =SUM(O88:R88) -> 13189 | BW88: =SUM(S88:V88) -> 12496 | BX88: =SUM(W88:Z88) -> 12105 | BY88: =SUM(AA88:AD88) -> 13650 | BZ88: =SUM(AE88:AH88) -> 12891 | CA88: =SUM(AI88:AL88) -> 11575 | CB88: =SUM(AM88:AP88) -> 13752 | CC88: =SUM(AQ88:AT88) -> 5028 | CD88: =SUM(AU88:AX88) -> 8470 | CE88: =SUM(AY88:BB88) -> 11807 | CF88: =SUM(BC88:BF88) -> -394 | CG88: =SUM(BG88:BJ88) -> -23686
B89: SC | C89: =C39 -> 5020 | D89: =D39 -> 5030 | E89: =E39 -> 5040 | F89: =F39 -> 5060 | G89: =G39 -> 5060 | H89: =H39 -> 5040 | I89: =I39 -> 5010 | J89: =J39 -> 487 | ... BK89: =BK39 -> 2966 | BS89: =SUM(C89:F89) -> 20150 | BT89: =SUM(G89:J89) -> 15597 | BU89: =SUM(K89:N89) -> 18680 | BV89: =SUM(O89:R89) -> 17760 | BW89: =SUM(S89:V89) -> 17100 | BX89: =SUM(W89:Z89) -> 16480 | BY89: =SUM(AA89:AD89) -> 16565 | BZ89: =SUM(AE89:AH89) -> 15200 | CA89: =SUM(AI89:AL89) -> 13150 | CB89: =SUM(AM89:AP89) -> 11780 | CC89: =SUM(AQ89:AT89) -> 10800 | CD89: =SUM(AU89:AX89) -> 10795 | CE89: =SUM(AY89:BB89) -> 10980 | CF89: =SUM(BC89:BF89) -> 11187 | CG89: =SUM(BG89:BJ89) -> 11490
B90: FCF per Share | C90: =C88/C89 -> 1.048008 | D90: =D88/D89 -> 0.22385686 | E90: =E88/E89 -> 0.56904762 | F90: =F88/F89 -> 0.75889328 | G90: =G88/G89 -> 1.0932806 | H90: =H88/H89 -> 0.1156746 | I90: =I88/I89 -> 0.61437126 | J90: =J88/J89 -> 8.9958932 | ... BK90: =BK88/BK89 -> -1.8192852 | BS90: =SUM(C90:F90) -> 2.5998057 | BT90: =SUM(G90:J90) -> 10.81922 | BU90: =SUM(K90:N90) -> 3.0691242 | BV90: =SUM(O90:R90) -> 2.9624838 | BW90: =SUM(S90:V90) -> 2.9227193 | BX90: =SUM(W90:Z90) -> 2.9333252 | BY90: =SUM(AA90:AD90) -> 3.3019553 | BZ90: =SUM(AE90:AH90) -> 3.3829305 | CA90: =SUM(AI90:AL90) -> 3.5075465 | CB90: =SUM(AM90:AP90) -> 4.667036 | CC90: =SUM(AQ90:AT90) -> 1.8374424 | CD90: =SUM(AU90:AX90) -> 3.1416069 | CE90: =SUM(AY90:BB90) -> 4.3085328 | CF90: =SUM(BC90:BF90) -> -0.10625071 | CG90: =SUM(BG90:BJ90) -> -8.2379554
B92: CFFO Margin | C92: =C86/C21 -> 0.64736088 | D92: =D86/D21 -> 0.1427434 | E92: =E86/E21 -> 0.33300144 | F92: =F86/F21 -> 0.37165628 | G92: =G86/G21 -> 0.69319154 | H92: =H86/H21 -> 0.087420277 | I92: =I86/I21 -> 0.3565528 | J92: =J86/J21 -> 0.41691788 | ... BK92: =BK86/BK21 -> 1.1942621 | BS92: =BS86/BS21 -> 0.37022171 | BT92: =BT86/BT21 -> 0.38257127 | BU92: =BU86/BU21 -> 0.38983671 | BV92: =BV86/BV21 -> 0.38141579 | BW92: =BW86/BW21 -> 0.36939563 | BX92: =BX86/BX21 -> 0.37378281 | BY92: =BY86/BY21 -> 0.39067618 | BZ92: =BZ86/BZ21 -> 0.3683238 | ... CG92: =CG86/CG21 -> 0.47473908
B93: FCF Margin | C93: =C88/C21 -> 0.62825412 | D93: =D88/D21 -> 0.12807097 | E93: =E88/E21 -> 0.31729174 | F93: =F88/F21 -> 0.35177721 | G93: =G88/G21 -> 0.67620095 | H93: =H88/H21 -> 0.064108203 | I93: =I88/I21 -> 0.34360348 | J93: =J88/J21 -> 0.40020097 | ... BK93: =BK88/BK21 -> -0.27893513 | BS93: =BS88/BS21 -> 0.35276528 | BT93: =BT88/BT21 -> 0.36508876 | BU93: =BU88/BU21 -> 0.37468321 | BV93: =BV88/BV21 -> 0.34502695 | BW93: =BW88/BW21 -> 0.33730127 | BX93: =BX88/BX21 -> 0.32030588 | BY93: =BY88/BY21 -> 0.34659625 | BZ93: =BZ88/BZ21 -> 0.32630487 | ... CG93: =CG88/CG21 -> -0.35164868
B94: CapEx as % of Revenue | C94: =C87/C21 -> -0.019106759 | D94: =D87/D21 -> -0.014672429 | E94: =E87/E21 -> -0.015709702 | F94: =F87/F21 -> -0.019879077 | G94: =G87/G21 -> -0.016990588 | H94: =H87/H21 -> -0.023312074 | I94: =I87/I21 -> -0.012949319 | J94: =J87/J21 -> -0.016716909 | ... BK94: =BK87/BK21 -> -1.4731972 | BS94: =BS87/BS21 -> -0.017456426 | BT94: =BT87/BT21 -> -0.017482517 | BU94: =BU87/BU21 -> -0.015153494 | BV94: =BV87/BV21 -> -0.036388845 | BW94: =BW87/BW21 -> -0.032094367 | BX94: =BX87/BX21 -> -0.053476926 | BY94: =BY87/BY21 -> -0.044079933 | BZ94: =BZ87/BZ21 -> -0.042018934 | ... CG94: =CG87/CG21 -> -0.82638775

Sheet Notes | Quant Analysis
CI1: 0
P2: Employee Scope: | AL2: General Notes/Observations (Updated Q2'26)
AL35: Financial Stmts. Notes/Observations (Updated Q2'26)
P36: Institutional Ownership Snapshot Q4'25 | AL36: Revenues:
P69: Revenue Breakdown by Segment | AL69: Earnings Scope:
Q101: Notes: | R101: [X]
R102: [Y]
R103: [Z]
P105: Q/q Total Revenues, Net Income, FCF | AL105: Balance Sheet Scope:
Q134: Notes: | R134: [X]
R135: [Y]
R136: [Z]
P138: Y/y Total Revenues, Net Income, FCF | AL138: [Equity Preformance Compared to Peers]
Q167: Notes: | R167: [X]
R168: [Y]
R169: [Z]
A184: VOO Historical Returns | I184: ORCL Historical Returns
A185: 752 Trading Days? (From: 8/12/2023 -8/12/2026) | I185: 752 Trading Days? (From: 8/12/2023 -8/12/2026)
A186: Close | B186: High | C186: Low | D186: Open | E186: Volume | F186: UTC Date | G186: Change | I186: Close | J186: High | K186: Low | L186: Open | M186: Volume | N186: UTC Date | O186: Change
A187: 710.17 | B187: 712.26 | C187: 708.93 | D187: 712.12 | E187: 4871287.5 | F187: Wed, 12 Aug 2026 00:00:00 GMT | G187: =A187/D187-1 -> -0.0027383025 | I187: 153.28 | J187: 154.89 | K187: 147.89 | L187: 152.81 | M187: 43260277 | N187: Wed, 12 Aug 2026 00:00:00 GMT | O187: =I187/L187-1 -> 0.0030757149
A188: 708.42 | B188: 712 | C188: 707 | D188: 711.96 | E188: 5010440 | F188: Tue, 11 Aug 2026 00:00:00 GMT | G188: =A188/D188-1 -> -0.0049721894 | I188: 145.48 | J188: 151.99 | K188: 144.24 | L188: 151.2 | M188: 28220614 | N188: Tue, 11 Aug 2026 00:00:00 GMT | O188: =I188/L188-1 -> -0.037830688
A189: 710.65 | B189: 712.4378 | C189: 709.5 | D189: 710.31 | E189: 6657921.2 | F189: Mon, 10 Aug 2026 00:00:00 GMT | G189: =A189/D189-1 -> 0.00047866425 | I189: 151.05 | J189: 151.99 | K189: 146.62 | L189: 148.26 | M189: 23971967 | N189: Mon, 10 Aug 2026 00:00:00 GMT | O189: =I189/L189-1 -> 0.018818292
A190: 710.71 | B190: 711.37 | C190: 707.44 | D190: 708.73 | E190: 4631469 | F190: Fri, 07 Aug 2026 00:00:00 GMT | G190: =A190/D190-1 -> 0.0027937296 | I190: 147.02 | J190: 147.16 | K190: 142.34 | L190: 145.32 | M190: 21938050 | N190: Fri, 07 Aug 2026 00:00:00 GMT | O190: =I190/L190-1 -> 0.011698321
A191: 706.4 | B191: 709.4619 | C191: 705.43 | D191: 707.93 | E191: 4523037.3 | F191: Thu, 06 Aug 2026 00:00:00 GMT | G191: =A191/D191-1 -> -0.0021612306 | I191: 143.47 | J191: 146.58 | K191: 138.72 | L191: 139.25 | M191: 21885222 | N191: Thu, 06 Aug 2026 00:00:00 GMT | O191: =I191/L191-1 -> 0.030305206
A192: 707.6 | B192: 714.16 | C192: 707.32 | D192: 713.14 | E192: 5187471.1 | F192: Wed, 05 Aug 2026 00:00:00 GMT | G192: =A192/D192-1 -> -0.0077684606 | I192: 144.39 | J192: 146.3899 | K192: 142.5 | L192: 145 | M192: 21661600 | N192: Wed, 05 Aug 2026 00:00:00 GMT | O192: =I192/L192-1 -> -0.0042068966
A193: 708.98 | B193: 710.9083 | C193: 699.07 | D193: 699.16 | E193: 6510852.7 | F193: Tue, 04 Aug 2026 00:00:00 GMT | G193: =A193/D193-1 -> 0.014045426 | I193: 145.74 | J193: 148.7 | K193: 141.01 | L193: 141.01 | M193: 43051564 | N193: Tue, 04 Aug 2026 00:00:00 GMT | O193: =I193/L193-1 -> 0.03354372
A194: 696.4 | B194: 697.31 | C194: 688.61 | D194: 688.83 | E194: 7244316 | F194: Mon, 03 Aug 2026 00:00:00 GMT | G194: =A194/D194-1 -> 0.010989649 | I194: 141.85 | J194: 143.07 | K194: 130.21 | L194: 131.92 | M194: 49139578 | N194: Mon, 03 Aug 2026 00:00:00 GMT | O194: =I194/L194-1 -> 0.075272893
A195: 686.65 | B195: 688.35 | C195: 678.06 | D195: 684.5 | E195: 7661568.2 | F195: Fri, 31 Jul 2026 00:00:00 GMT | G195: =A195/D195-1 -> 0.0031409788 | I195: 129.87 | J195: 132.4 | K195: 125.7 | L195: 130.07 | M195: 34214876 | N195: Fri, 31 Jul 2026 00:00:00 GMT | O195: =I195/L195-1 -> -0.0015376336
A196: 681.79 | B196: 682.4363 | C196: 675.21 | D196: 676.54 | E196: 6009104.5 | F196: Thu, 30 Jul 2026 00:00:00 GMT | G196: =A196/D196-1 -> 0.0077600733 | I196: 127.56 | J196: 128.34 | K196: 121.58 | L196: 122.87 | M196: 36950065 | N196: Thu, 30 Jul 2026 00:00:00 GMT | O196: =I196/L196-1 -> 0.038170424
A197: 670.63 | B197: 682.63 | C197: 670.155 | D197: 680.12 | E197: 7845443.5 | F197: Wed, 29 Jul 2026 00:00:00 GMT | G197: =A197/D197-1 -> -0.01395342 | I197: 117.74 | J197: 121.92 | K197: 116.2 | L197: 119.42 | M197: 27177467 | N197: Wed, 29 Jul 2026 00:00:00 GMT | O197: =I197/L197-1 -> -0.014067995
A198: 680.96 | B198: 682.755 | C198: 676.4801 | D198: 679.45 | E198: 5021080 | F198: Tue, 28 Jul 2026 00:00:00 GMT | G198: =A198/D198-1 -> 0.0022223858 | I198: 119.96 | J198: 122.33 | K198: 114.5 | L198: 118.18 | M198: 28081150 | N198: Tue, 28 Jul 2026 00:00:00 GMT | O198: =I198/L198-1 -> 0.01506177
A199: 679.31 | B199: 685.2391 | C199: 676.395 | D199: 684.69 | E199: 5207757.8 | F199: Mon, 27 Jul 2026 00:00:00 GMT | G199: =A199/D199-1 -> -0.0078575706 | I199: 119.9 | J199: 121.99 | K199: 116.8 | L199: 118 | M199: 36633880 | N199: Mon, 27 Jul 2026 00:00:00 GMT | O199: =I199/L199-1 -> 0.016101695
A200: 679.14 | B200: 683.55 | C200: 677.7 | D200: 678.8 | E200: 6286807 | F200: Fri, 24 Jul 2026 00:00:00 GMT | G200: =A200/D200-1 -> 0.00050088391 | I200: 114.99 | J200: 123.08 | K200: 114.75 | L200: 122.47 | M200: 44922930 | N200: Fri, 24 Jul 2026 00:00:00 GMT | O200: =I200/L200-1 -> -0.061076182 | R200: Min | S200: =MIN(O187:O1149) -> -0.088553383
A201: 678.61 | B201: 682.5495 | C201: 675.755 | D201: 679.55 | E201: 4942804.8 | F201: Thu, 23 Jul 2026 00:00:00 GMT | G201: =A201/D201-1 -> -0.0013832683 | I201: 120.04 | J201: 124.7 | K201: 119.44 | L201: 123.96 | M201: 29200007 | N201: Thu, 23 Jul 2026 00:00:00 GMT | O201: =I201/L201-1 -> -0.031623104 | R201: Max | S201: =MAX(O187:O1149) -> 0.13200972
A202: 687.03 | B202: 689.4 | C202: 686.02 | D202: 686.29 | E202: 3349102.7 | F202: Wed, 22 Jul 2026 00:00:00 GMT | G202: =A202/D202-1 -> 0.0010782614 | I202: 125.84 | J202: 128.84 | K202: 124.7 | L202: 126.18 | M202: 20775642 | N202: Wed, 22 Jul 2026 00:00:00 GMT | O202: =I202/L202-1 -> -0.0026945633 | R202: Mean μ | S202: =AVERAGE(O187:O1149) -> -0.00089280539
A203: 687.87 | B203: 688.485 | C203: 684.03 | D203: 685.95 | E203: 4054717.9 | F203: Tue, 21 Jul 2026 00:00:00 GMT | G203: =A203/D203-1 -> 0.0027990378 | I203: 127.05 | J203: 127.42 | K203: 122.21 | L203: 122.81 | M203: 27409567 | N203: Tue, 21 Jul 2026 00:00:00 GMT | O203: =I203/L203-1 -> 0.034524876 | R203: Median | S203: =MEDIAN(O187:O1149) -> -0.00046218195
A204: 682.21 | B204: 688.2 | C204: 681.57 | D204: 686.67 | E204: 5321985.3 | F204: Mon, 20 Jul 2026 00:00:00 GMT | G204: =A204/D204-1 -> -0.0064951141 | I204: 121.38 | J204: 125.4897 | K204: 120.03 | L204: 124.27 | M204: 36295668 | N204: Mon, 20 Jul 2026 00:00:00 GMT | O204: =I204/L204-1 -> -0.023255814 | R204: SD σ | S204: =_xlfn.STDEV.P(O187:O1149) -> 0.021848969
A205: 683.17 | B205: 686.8653 | C205: 680.92 | D205: 682.12 | E205: 5627641.4 | F205: Fri, 17 Jul 2026 00:00:00 GMT | G205: =A205/D205-1 -> 0.0015393186 | I205: 126.41 | J205: 128.435 | K205: 121.5 | L205: 121.7 | M205: 39690283 | N205: Fri, 17 Jul 2026 00:00:00 GMT | O205: =I205/L205-1 -> 0.038701726 | R205: 3σ 1-Day Δ: ± | S205: =3*S204 -> 0.065546906 | U205: <- Sharpe Ratio (Risk Adjusted Return)
A206: 690.14 | B206: 693.55 | C206: 687.43 | D206: 691.98 | E206: 4722611.2 | F206: Thu, 16 Jul 2026 00:00:00 GMT | G206: =A206/D206-1 -> -0.0026590364 | I206: 124.21 | J206: 131.78 | K206: 123.66 | L206: 131.475 | M206: 54220667 | N206: Thu, 16 Jul 2026 00:00:00 GMT | O206: =I206/L206-1 -> -0.055257654 | R206: β (1-year avg.) | S206: =_xlfn.COVARIANCE.P(O187:O435,G187:G435)/_xlfn.VAR.P(G187:G435) -> 1.916003 | U206: <- Sortino Ratio (Downside Risk Adjusted Return)
A207: 693.8 | B207: 694.5 | C207: 689.58 | D207: 693.27 | E207: 4110059.9 | F207: Wed, 15 Jul 2026 00:00:00 GMT | G207: =A207/D207-1 -> 0.00076449291 | I207: 132.49 | J207: 133.9 | K207: 128.84 | L207: 130.56 | M207: 48228999 | N207: Wed, 15 Jul 2026 00:00:00 GMT | O207: =I207/L207-1 -> 0.014782475
A208: 691.1 | B208: 692.4 | C208: 688.2 | D208: 690.21 | E208: 4570040.4 | F208: Tue, 14 Jul 2026 00:00:00 GMT | G208: =A208/D208-1 -> 0.0012894626 | I208: 127.94 | J208: 132.76 | K208: 127.6 | L208: 132 | M208: 50934764 | N208: Tue, 14 Jul 2026 00:00:00 GMT | O208: =I208/L208-1 -> -0.030757576 | Q208: n = | R208: 752
A209: 688.5 | B209: 692.96 | C209: 687.54 | D209: 691.6 | E209: 6587891.4 | F209: Mon, 13 Jul 2026 00:00:00 GMT | G209: =A209/D209-1 -> -0.0044823597 | I209: 131.54 | J209: 139.65 | K209: 131.35 | L209: 139.03 | M209: 55982009 | N209: Mon, 13 Jul 2026 00:00:00 GMT | O209: =I209/L209-1 -> -0.053873265 | Q209: Histogram Data | T209: Distribution Overlay | X209: SD Lines
A210: 693.86 | B210: 694.33 | C210: 687.63 | D210: 691.25 | E210: 4666892.9 | F210: Fri, 10 Jul 2026 00:00:00 GMT | G210: =A210/D210-1 -> 0.0037757685 | I210: 140.64 | J210: 145.68 | K210: 139.26 | L210: 145.65 | M210: 26526959 | N210: Fri, 10 Jul 2026 00:00:00 GMT | O210: =I210/L210-1 -> -0.034397528 | Q210: Bin | R210: Frequency | T210: (X) 1-Day Δ | U210: (Y) Pop. Density | X210: X | Y210: Y
A211: 690.69 | B211: 691.1862 | C211: 685.29 | D211: 686.95 | E211: 6395880.4 | F211: Thu, 09 Jul 2026 00:00:00 GMT | G211: =A211/D211-1 -> 0.0054443555 | I211: 143.72 | J211: 148.55319 | K211: 140.45137 | L211: 140.92971 | M211: 34910558 | N211: Thu, 09 Jul 2026 00:00:00 GMT | O211: =I211/L211-1 -> 0.01979918 | Q211: -0.065 | R211: 4 | T211: =T212-0.001 -> -0.07 | U211: =_xlfn.NORM.DIST(T211,$S$202,$S$204,FALSE) -> 0.12276747 | W211: Mean | X211: =S202 -> -0.00089280539 | Y211: 0
A212: 685.26 | B212: 685.84 | C212: 679.73 | D212: 683.1 | E212: 4805362.7 | F212: Wed, 08 Jul 2026 00:00:00 GMT | G212: =A212/D212-1 -> 0.0031620553 | I212: 140.00293 | J212: 141.34825 | K212: 137.06814 | L212: 138.57291 | M212: 34247610 | N212: Wed, 08 Jul 2026 00:00:00 GMT | O212: =I212/L212-1 -> 0.010319658 | Q212: -0.064 | R212: 0 | T212: =T213-0.001 -> -0.069 | U212: =_xlfn.NORM.DIST(T212,$S$202,$S$204,FALSE) -> 0.14174206 | X212: =S202 -> -0.00089280539 | Y212: 18
A213: 687.08 | B213: 690.24 | C213: 684.989 | D213: 689.58 | E213: 4816042.5 | F213: Tue, 07 Jul 2026 00:00:00 GMT | G213: =A213/D213-1 -> -0.0036253952 | I213: 141.10908 | J213: 145.05535 | K213: 137.07312 | L213: 143.22173 | M213: 42873887 | N213: Tue, 07 Jul 2026 00:00:00 GMT | O213: =I213/L213-1 -> -0.014750905 | Q213: -0.063 | R213: 1 | T213: =T214-0.001 -> -0.068 | U213: =_xlfn.NORM.DIST(T213,$S$202,$S$204,FALSE) -> 0.16330686 | W213: -3σ | X213: =($S$204*-3)+$S$202 -> -0.066439711 | Y213: 0
A214: 690.62 | B214: 691.575 | C214: 687 | D214: 688.11 | E214: 5575659.2 | F214: Mon, 06 Jul 2026 00:00:00 GMT | G214: =A214/D214-1 -> 0.0036476726 | I214: 143.26159 | J214: 145.11734 | K214: 140.67061 | L214: 143.79972 | M214: 34244239 | N214: Mon, 06 Jul 2026 00:00:00 GMT | O214: =I214/L214-1 -> -0.0037422037 | Q214: -0.062 | R214: 2 | T214: =T215-0.001 -> -0.067 | U214: =_xlfn.NORM.DIST(T214,$S$202,$S$204,FALSE) -> 0.18775884 | X214: =($S$204*-3)+$S$202 -> -0.066439711 | Y214: 1
A215: 684.84 | B215: 690.5 | C215: 680.215 | D215: 686.98 | E215: 6980816.8 | F215: Thu, 02 Jul 2026 00:00:00 GMT | G215: =A215/D215-1 -> -0.0031150834 | I215: 139.78369 | J215: 146.55015 | K215: 138.3459 | L215: 142.80319 | M215: 43036166 | N215: Thu, 02 Jul 2026 00:00:00 GMT | O215: =I215/L215-1 -> -0.021144452 | Q215: -0.061 | R215: 1 | T215: =T216-0.001 -> -0.066 | U215: =_xlfn.NORM.DIST(T215,$S$202,$S$204,FALSE) -> 0.21542028 | W215: -2σ | X215: =($S$204*-2)+$S$202 -> -0.044590743 | Y215: 0
A216: 685.46 | B216: 688.83 | C216: 682.3 | D216: 684.73 | E216: 8627875 | F216: Wed, 01 Jul 2026 00:00:00 GMT | G216: =A216/D216-1 -> 0.0010661137 | I216: 142.00596 | J216: 147.03846 | K216: 142.00596 | L216: 143.98906 | M216: 45543502 | N216: Wed, 01 Jul 2026 00:00:00 GMT | O216: =I216/L216-1 -> -0.013772579 | Q216: -0.06 | R216: 1 | T216: =T217-0.001 -> -0.065 | U216: =_xlfn.NORM.DIST(T216,$S$202,$S$204,FALSE) -> 0.24663972 | X216: =($S$204*-2)+$S$202 -> -0.044590743 | Y216: 3
A217: 686.81 | B217: 687.529 | C217: 680.99 | D217: 681.32 | E217: 9853712.9 | F217: Tue, 30 Jun 2026 00:00:00 GMT | G217: =A217/D217-1 -> 0.0080578876 | I217: 146.04192 | J217: 149.4102 | K217: 143.9791 | L217: 146.7395 | M217: 34918287 | N217: Tue, 30 Jun 2026 00:00:00 GMT | O217: =I217/L217-1 -> -0.00475382 | Q217: -0.059 | R217: 0 | T217: =T218-0.001 -> -0.064 | U217: =_xlfn.NORM.DIST(T217,$S$202,$S$204,FALSE) -> 0.28179269 | W217: -1σ | X217: =($S$204*-1)+$S$202 -> -0.022741774 | Y217: 0
A218: 681.01 | B218: 681.565 | C218: 672.93 | D218: 677.01 | E218: 5649228.8 | F218: Mon, 29 Jun 2026 00:00:00 GMT | G218: =A218/D218-1 -> 0.0059083322 | I218: 147.24773 | J218: 153.96436 | K218: 144.6966 | L218: 153.4063 | M218: 34146890 | N218: Mon, 29 Jun 2026 00:00:00 GMT | O218: =I218/L218-1 -> -0.040145511 | Q218: -0.058 | R218: 1 | T218: =T219-0.001 -> -0.063 | U218: =_xlfn.NORM.DIST(T218,$S$202,$S$204,FALSE) -> 0.3212822 | X218: =($S$204*-1)+$S$202 -> -0.022741774 | Y218: 11
A219: 670.26 | B219: 676.955 | C219: 668.1 | D219: 669.96 | E219: 5935648.6 | F219: Fri, 26 Jun 2026 00:00:00 GMT | G219: =A219/D219-1 -> 0.00044778793 | I219: 148.01506 | J219: 153.00769 | K219: 147.4869 | L219: 149.73906 | M219: 36068922 | N219: Fri, 26 Jun 2026 00:00:00 GMT | O219: =I219/L219-1 -> -0.011513377 | Q219: -0.057 | R219: 0 | T219: =T220-0.001 -> -0.062 | U219: =_xlfn.NORM.DIST(T219,$S$202,$S$204,FALSE) -> 0.36553911 | W219: 1σ | X219: =($S$204*1)+$S$202 -> 0.020956163 | Y219: 0
A220: 673.7478 | B220: 679.56087 | C220: 670.62689 | D220: 679.16203 | E220: 23355606 | F220: Thu, 25 Jun 2026 00:00:00 GMT | G220: =A220/D220-1 -> -0.0079719294 | I220: 151.93143 | J220: 157.07354 | K220: 149.83871 | L220: 156.80448 | M220: 36182966 | N220: Thu, 25 Jun 2026 00:00:00 GMT | O220: =I220/L220-1 -> -0.031077216 | Q220: -0.056 | R220: 1 | T220: =T221-0.001 -> -0.061 | U220: =_xlfn.NORM.DIST(T220,$S$202,$S$204,FALSE) -> 0.41502217 | X220: =($S$204*1)+$S$202 -> 0.020956163 | Y220: 11
A221: 673.72786 | B221: 680.08933 | C221: 671.72369 | D221: 675.71208 | E221: 9593615.8 | F221: Wed, 24 Jun 2026 00:00:00 GMT | G221: =A221/D221-1 -> -0.0029364892 | I221: 156.98386 | J221: 165.17536 | K221: 154.81141 | L221: 161.91171 | M221: 37936303 | N221: Wed, 24 Jun 2026 00:00:00 GMT | O221: =I221/L221-1 -> -0.030435452 | Q221: -0.055 | R221: 1 | T221: =T222-0.001 -> -0.06 | U221: =_xlfn.NORM.DIST(T221,$S$202,$S$204,FALSE) -> 0.47021772 | W221: 2σ | X221: =($S$204*2)+$S$202 -> 0.042805132 | Y221: 0
A222: 674.37597 | B222: 679.74912 | C222: 673.0598 | D222: 674.39093 | E222: 17263981 | F222: Tue, 23 Jun 2026 00:00:00 GMT | G222: =A222/D222-1 -> -2.2177703e-05 | I222: 164.5874 | J222: 173.72561 | K222: 164.03931 | L222: 169.63983 | M222: 32064930 | N222: Tue, 23 Jun 2026 00:00:00 GMT | O222: =I222/L222-1 -> -0.029783234 | Q222: -0.054 | R222: 0 | T222: =T223-0.001 -> -0.059 | U222: =_xlfn.NORM.DIST(T222,$S$202,$S$204,FALSE) -> 0.53163912 | X222: =($S$204*2)+$S$202 -> 0.042805132 | Y222: 3
A223: 684.10763 | B223: 689.49195 | C223: 683.01082 | D223: 687.16871 | E223: 13365185 | F223: Mon, 22 Jun 2026 00:00:00 GMT | G223: =A223/D223-1 -> -0.0044546338 | I223: 174.46305 | J223: 183.94007 | K223: 173.79537 | L223: 181.67794 | M223: 22894314 | N223: Mon, 22 Jun 2026 00:00:00 GMT | O223: =I223/L223-1 -> -0.039712577 | Q223: -0.053 | R223: 1 | T223: =T224-0.001 -> -0.058 | U223: =_xlfn.NORM.DIST(T223,$S$202,$S$204,FALSE) -> 0.59982577 | W223: 3σ | X223: =($S$204*3)+$S$202 -> 0.0646541 | Y223: 0
A224: 686.11179 | B224: 687.69717 | C224: 683.70879 | D224: 687.29834 | E224: 17768872 | F224: Thu, 18 Jun 2026 00:00:00 GMT | G224: =A224/D224-1 -> -0.0017263891 | I224: 183.65108 | J224: 187.33825 | K224: 177.08393 | L224: 182.37552 | M224: 30858197 | N224: Thu, 18 Jun 2026 00:00:00 GMT | O224: =I224/L224-1 -> 0.0069941533 | Q224: -0.052 | R224: 0 | T224: =T225-0.001 -> -0.057 | U224: =_xlfn.NORM.DIST(T224,$S$202,$S$204,FALSE) -> 0.67534168 | X224: =($S$204*3)+$S$202 -> 0.0646541 | Y224: 1
A225: 679.43125 | B225: 689.52186 | C225: 677.66639 | D225: 688.7541 | E225: 15004527 | F225: Wed, 17 Jun 2026 00:00:00 GMT | G225: =A225/D225-1 -> -0.013535816 | I225: 182.89372 | J225: 189.53063 | K225: 181.94701 | L225: 185.50961 | M225: 16478391 | N225: Wed, 17 Jun 2026 00:00:00 GMT | O225: =I225/L225-1 -> -0.014101152 | Q225: -0.051 | R225: 0 | T225: =T226-0.001 -> -0.056 | U225: =_xlfn.NORM.DIST(T225,$S$202,$S$204,FALSE) -> 0.75877366
A226: 687.74703 | B226: 692.55303 | C226: 687.43793 | D226: 691.81518 | E226: 13322314 | F226: Tue, 16 Jun 2026 00:00:00 GMT | G226: =A226/D226-1 -> -0.005880403 | I226: 187.67707 | J226: 194.64284 | K226: 187.0094 | L226: 189.35125 | M226: 16799241 | N226: Tue, 16 Jun 2026 00:00:00 GMT | O226: =I226/L226-1 -> -0.0088416399 | Q226: -0.05 | R226: 1 | T226: =T227-0.001 -> -0.055 | U226: =_xlfn.NORM.DIST(T226,$S$202,$S$204,FALSE) -> 0.85072889
A227: 691.81518 | B227: 693.72961 | C227: 689.25264 | D227: 689.29253 | E227: 14057973 | F227: Mon, 15 Jun 2026 00:00:00 GMT | G227: =A227/D227-1 -> 0.0036597714 | I227: 191.97213 | J227: 194.64284 | K227: 185.56781 | L227: 186.74033 | M227: 19912616 | N227: Mon, 15 Jun 2026 00:00:00 GMT | O227: =I227/L227-1 -> 0.028016436 | Q227: -0.049 | R227: 0 | T227: =T228-0.001 -> -0.054 | U227: =_xlfn.NORM.DIST(T227,$S$202,$S$204,FALSE) -> 0.95183215
A228: 679.96968 | B228: 682.45115 | C228: 673.84751 | D228: 679.09722 | E228: 6314635.8 | F228: Fri, 12 Jun 2026 00:00:00 GMT | G228: =A228/D228-1 -> 0.0012847337 | I228: 183.49164 | J228: 184.93661 | K228: 178.37942 | L228: 184.36858 | M228: 28544241 | N228: Fri, 12 Jun 2026 00:00:00 GMT | O228: =I228/L228-1 -> -0.0047564996 | Q228: -0.048 | R228: 2 | T228: =T229-0.001 -> -0.053 | U228: =_xlfn.NORM.DIST(T228,$S$202,$S$204,FALSE) -> 1.0627223
A229: 676.26048 | B229: 678.40424 | C229: 664.066 | D229: 668.15409 | E229: 19926769 | F229: Thu, 11 Jun 2026 00:00:00 GMT | G229: =A229/D229-1 -> 0.012132518 | I229: 183.46174 | J229: 184.12942 | K229: 174.67232 | L229: 179.0471 | M229: 63343032 | N229: Thu, 11 Jun 2026 00:00:00 GMT | O229: =I229/L229-1 -> 0.024656314 | Q229: -0.047 | R229: 2 | T229: =T230-0.001 -> -0.052 | U229: =_xlfn.NORM.DIST(T229,$S$202,$S$204,FALSE) -> 1.1840485
A230: 665.11295 | B230: 676.90361 | C230: 664.94344 | D230: 672.35685 | E230: 16356103 | F230: Wed, 10 Jun 2026 00:00:00 GMT | G230: =A230/D230-1 -> -0.010773896 | I230: 200.56225 | J230: 211.74325 | K230: 197.49292 | L230: 197.81182 | M230: 37540726 | N230: Wed, 10 Jun 2026 00:00:00 GMT | O230: =I230/L230-1 -> 0.013904282 | Q230: -0.046 | R230: 1 | T230: =T231-0.001 -> -0.051 | U230: =_xlfn.NORM.DIST(T230,$S$202,$S$204,FALSE) -> 1.3164653
A231: 675.73202 | B231: 684.76571 | C231: 662.39098 | D231: 681.72457 | E231: 13824282 | F231: Tue, 09 Jun 2026 00:00:00 GMT | G231: =A231/D231-1 -> -0.0087902766 | I231: 205.09647 | J231: 219.73554 | K231: 197.10438 | L231: 213.16341 | M231: 25625532 | N231: Tue, 09 Jun 2026 00:00:00 GMT | O231: =I231/L231-1 -> -0.037843903 | Q231: -0.045 | R231: 0 | T231: =T232-0.001 -> -0.05 | U231: =_xlfn.NORM.DIST(T231,$S$202,$S$204,FALSE) -> 1.4606279
A232: 677.70627 | B232: 683.29998 | C232: 676.72912 | D232: 681.48527 | E232: 8770213.3 | F232: Mon, 08 Jun 2026 00:00:00 GMT | G232: =A232/D232-1 -> -0.0055452324 | I232: 211.08564 | J232: 218.30054 | K232: 208.60527 | L232: 216.99508 | M232: 17168458 | N232: Mon, 08 Jun 2026 00:00:00 GMT | O232: =I232/L232-1 -> -0.027233065 | Q232: -0.044 | R232: 3 | T232: =T233-0.001 -> -0.049 | U232: =_xlfn.NORM.DIST(T232,$S$202,$S$204,FALSE) -> 1.6171862
A233: 676.03115 | B233: 690.16997 | C233: 674.28623 | D233: 689.70134 | E233: 10720357 | F233: Fri, 05 Jun 2026 00:00:00 GMT | G233: =A233/D233-1 -> -0.019820445 | I233: 212.93919 | J233: 230.63761 | K233: 208.72395 | L233: 228.69438 | M233: 28762078 | N233: Fri, 05 Jun 2026 00:00:00 GMT | O233: =I233/L233-1 -> -0.068891891 | Q233: -0.043 | R233: 1 | T233: =T234-0.001 -> -0.048 | U233: =_xlfn.NORM.DIST(T233,$S$202,$S$204,FALSE) -> 1.7867785
A234: 694.03871 | B234: 695.17539 | C234: 688.89369 | D234: 689.48198 | E234: 6594038 | F234: Thu, 04 Jun 2026 00:00:00 GMT | G234: =A234/D234-1 -> 0.006608917 | I234: 235.52063 | J234: 238.12158 | K234: 223.22341 | L234: 226.21301 | M234: 19317614 | N234: Thu, 04 Jun 2026 00:00:00 GMT | O234: =I234/L234-1 -> 0.041145374 | Q234: -0.042 | R234: 1 | T234: =T235-0.001 -> -0.047 | U234: =_xlfn.NORM.DIST(T234,$S$202,$S$204,FALSE) -> 1.9700246
A235: 691.34655 | B235: 695.62399 | C235: 690.83803 | D235: 695.05574 | E235: 5899709.5 | F235: Wed, 03 Jun 2026 00:00:00 GMT | G235: =A235/D235-1 -> -0.0053365467 | I235: 229.53146 | J235: 239.67617 | K235: 226.81591 | L235: 239.64627 | M235: 22876252 | N235: Wed, 03 Jun 2026 00:00:00 GMT | O235: =I235/L235-1 -> -0.042207252 | Q235: -0.041 | R235: 1 | T235: =T236-0.001 -> -0.046 | U235: =_xlfn.NORM.DIST(T235,$S$202,$S$204,FALSE) -> 2.1675186
A236: 696.23232 | B236: 697.11973 | C236: 693.75952 | D236: 694.03871 | E236: 4712080 | F236: Tue, 02 Jun 2026 00:00:00 GMT | G236: =A236/D236-1 -> 0.0031606471 | I236: 243.73206 | J236: 248.13674 | K236: 238.01196 | L236: 241.95823 | M236: 29906753 | N236: Tue, 02 Jun 2026 00:00:00 GMT | O236: =I236/L236-1 -> 0.0073311367 | Q236: -0.04 | R236: 6 | T236: =T237-0.001 -> -0.045 | U236: =_xlfn.NORM.DIST(T236,$S$202,$S$204,FALSE) -> 2.3798208
... A280: 579.24303 | B280: 586.96056 | C280: 576.78021 | D280: 586.68137 | E280: 11776669 | F280: Mon, 30 Mar 2026 00:00:00 GMT | G280: =A280/D280-1 -> -0.012678666 | I280: 137.83738 | J280: 140.22074 | K280: 136.00021 | L280: 139.06878 | M280: 18185633 | N280: Mon, 30 Mar 2026 00:00:00 GMT | O280: =I280/L280-1 -> -0.008854613 | Q280: 0.004 | R280: 21 | T280: =T281-0.001 -> -0.001 | U280: =_xlfn.NORM.DIST(T280,$S$202,$S$204,FALSE) -> 18.25887
A281: 581.26714 | B281: 589.11428 | C281: 580.33984 | D281: 588.96472 | E281: 11637657 | F281: Fri, 27 Mar 2026 00:00:00 GMT | G281: =A281/D281-1 -> -0.013069682 | I281: 138.69142 | J281: 140.70734 | K281: 137.34184 | L281: 139.95261 | M281: 17949888 | N281: Fri, 27 Mar 2026 00:00:00 GMT | O281: =I281/L281-1 -> -0.009011566 | Q281: 0.005 | R281: 18 | T281: 0 | U281: =_xlfn.NORM.DIST(T281,$S$202,$S$204,FALSE) -> 18.243852
A282: 591.32544 | B282: 600.25616 | C282: 591.08689 | D282: 597.66193 | E282: 7632666.6 | F282: Thu, 26 Mar 2026 00:00:00 GMT | G282: =A282/D282-1 -> -0.010602117 | I282: 141.81957 | J282: 145.45419 | K282: 141.55144 | L282: 142.89208 | M282: 16954175 | N282: Thu, 26 Mar 2026 00:00:00 GMT | O282: =I282/L282-1 -> -0.0075057335 | Q282: 0.006 | R282: 19 | T282: =T281+0.001 -> 0.001 | U282: =_xlfn.NORM.DIST(T282,$S$202,$S$204,FALSE) -> 18.190701
A283: 602.00055 | B283: 605.75771 | C283: 599.71445 | D283: 603.73004 | E283: 23373518 | F283: Wed, 25 Mar 2026 00:00:00 GMT | G283: =A283/D283-1 -> -0.0028646691 | I283: 145.00731 | J283: 148.80081 | K283: 143.59795 | L283: 148.19008 | M283: 20672316 | N283: Wed, 25 Mar 2026 00:00:00 GMT | O283: =I283/L283-1 -> -0.021477634 | Q283: 0.007 | R283: 21 | T283: =T282+0.001 -> 0.002 | U283: =_xlfn.NORM.DIST(T283,$S$202,$S$204,FALSE) -> 18.09975
A284: 598.74037 | B284: 602.24904 | C284: 595.69886 | D284: 597.00094 | E284: 18309375 | F284: Tue, 24 Mar 2026 00:00:00 GMT | G284: =A284/D284-1 -> 0.0029136074 | I284: 146.06989 | J284: 152.83266 | K284: 145.83155 | L284: 151.9389 | M284: 25980967 | N284: Tue, 24 Mar 2026 00:00:00 GMT | O284: =I284/L284-1 -> -0.038627451 | Q284: 0.008 | R284: 18 | T284: =T283+0.001 -> 0.003 | U284: =_xlfn.NORM.DIST(T284,$S$202,$S$204,FALSE) -> 17.971568
A285: 600.77798 | B285: 607.33314 | C285: 599.41626 | D285: 603.1933 | E285: 24112840 | F285: Mon, 23 Mar 2026 00:00:00 GMT | G285: =A285/D285-1 -> -0.0040042184 | I285: 153.26961 | J285: 154.69962 | K285: 149.66478 | L285: 150.36986 | M285: 19818547 | N285: Mon, 23 Mar 2026 00:00:00 GMT | O285: =I285/L285-1 -> 0.01928411 | Q285: 0.009 | R285: 13 | T285: =T284+0.001 -> 0.004 | U285: =_xlfn.NORM.DIST(T285,$S$202,$S$204,FALSE) -> 17.806953
A286: 594.3272 | B286: 601.94091 | C286: 590.97756 | D286: 601.77194 | E286: 17638954 | F286: Fri, 20 Mar 2026 00:00:00 GMT | G286: =A286/D286-1 -> -0.012371372 | I286: 148.64192 | J286: 152.18717 | K286: 146.92392 | L286: 151.98855 | M286: 37313601 | N286: Fri, 20 Mar 2026 00:00:00 GMT | O286: =I286/L286-1 -> -0.022018948 | Q286: 0.01 | R286: 9 | T286: =T285+0.001 -> 0.005 | U286: =_xlfn.NORM.DIST(T286,$S$202,$S$204,FALSE) -> 17.606925
A287: 603.08397 | B287: 606.0062 | C287: 598.8994 | D287: 600.48974 | E287: 10249751 | F287: Thu, 19 Mar 2026 00:00:00 GMT | G287: =A287/D287-1 -> 0.0043201907 | I287: 154.44142 | J287: 155.83171 | K287: 147.8574 | L287: 149.41651 | M287: 22069731 | N287: Thu, 19 Mar 2026 00:00:00 GMT | O287: =I287/L287-1 -> 0.033630201 | Q287: 0.011 | R287: 16 | T287: =T286+0.001 -> 0.006 | U287: =_xlfn.NORM.DIST(T287,$S$202,$S$204,FALSE) -> 17.372713
A288: 604.70412 | B288: 612.16874 | C288: 604.45563 | D288: 610.97599 | E288: 12362167 | F288: Wed, 18 Mar 2026 00:00:00 GMT | G288: =A288/D288-1 -> -0.010265337 | I288: 151.83959 | J288: 153.89047 | K288: 150.98556 | L288: 152.33613 | M288: 17998826 | N288: Wed, 18 Mar 2026 00:00:00 GMT | O288: =I288/L288-1 -> -0.0032594524 | Q288: 0.012 | R288: 12 | T288: =T287+0.001 -> 0.007 | U288: =_xlfn.NORM.DIST(T288,$S$202,$S$204,FALSE) -> 17.105747
A289: 613.1627 | B289: 616.52228 | C289: 612.54645 | D289: 614.63376 | E289: 8800087.7 | F289: Tue, 17 Mar 2026 00:00:00 GMT | G289: =A289/D289-1 -> -0.0023933891 | I289: 153.61718 | J289: 157.81784 | K289: 152.43553 | L289: 154.36198 | M289: 24006606 | N289: Tue, 17 Mar 2026 00:00:00 GMT | O289: =I289/L289-1 -> -0.0048250129 | Q289: 0.013 | R289: 19 | T289: =T288+0.001 -> 0.008 | U289: =_xlfn.NORM.DIST(T289,$S$202,$S$204,FALSE) -> 16.807638
A290: 611.47297 | B290: 614.34551 | C290: 609.83294 | D290: 611.00581 | E290: 8274060.1 | F290: Mon, 16 Mar 2026 00:00:00 GMT | G290: =A290/D290-1 -> 0.00076457574 | I290: 154.8883 | J290: 157.63909 | K290: 153.43882 | L290: 154.97768 | M290: 21661056 | N290: Mon, 16 Mar 2026 00:00:00 GMT | O290: =I290/L290-1 -> -0.00057670127 | Q290: 0.014 | R290: 7 | T290: =T289+0.001 -> 0.009 | U290: =_xlfn.NORM.DIST(T290,$S$202,$S$204,FALSE) -> 16.480165
A291: 605.40983 | B291: 614.59797 | C291: 604.5749 | D291: 611.82086 | E291: 23660320 | F291: Fri, 13 Mar 2026 00:00:00 GMT | G291: =A291/D291-1 -> -0.010478604 | I291: 154.03427 | J291: 159.65501 | K291: 153.08092 | L291: 157.94694 | M291: 26349582 | N291: Fri, 13 Mar 2026 00:00:00 GMT | O291: =I291/L291-1 -> -0.024772084 | Q291: 0.015 | R291: 10 | T291: =T290+0.001 -> 0.01 | U291: =_xlfn.NORM.DIST(T291,$S$202,$S$204,FALSE) -> 16.125259
A292: 608.79922 | B292: 613.97774 | C292: 608.71971 | D292: 613.49071 | E292: 12076076 | F292: Thu, 12 Mar 2026 00:00:00 GMT | G292: =A292/D292-1 -> -0.0076471922 | I292: 158.05618 | J292: 166.66605 | K292: 157.50999 | L292: 163.51803 | M292: 37102732 | N292: Thu, 12 Mar 2026 00:00:00 GMT | O292: =I292/L292-1 -> -0.033402162 | Q292: 0.016 | R292: 13 | T292: =T291+0.001 -> 0.011 | U292: =_xlfn.NORM.DIST(T292,$S$202,$S$204,FALSE) -> 15.744979
A293: 618.27164 | B293: 621.6511 | C293: 615.55814 | D293: 619.43457 | E293: 6365253 | F293: Wed, 11 Mar 2026 00:00:00 GMT | G293: =A293/D293-1 -> -0.0018774069 | I293: 161.98871 | J293: 170.56879 | K293: 159.46633 | L293: 165.2261 | M293: 83158930 | N293: Wed, 11 Mar 2026 00:00:00 GMT | O293: =I293/L293-1 -> -0.019593701 | Q293: 0.017 | R293: 9 | T293: =T292+0.001 -> 0.012 | U293: =_xlfn.NORM.DIST(T293,$S$202,$S$204,FALSE) -> 15.341496
... A341: 627.9031 | B341: 629.38409 | C341: 627.59497 | D341: 628.3802 | E341: 4176099.3 | F341: Tue, 30 Dec 2025 00:00:00 GMT | G341: =A341/D341-1 -> -0.0007592534 | I341: 195.32596 | J341: 196.48479 | K341: 193.84029 | L341: 194.18695 | M341: 14256356 | N341: Tue, 30 Dec 2025 00:00:00 GMT | O341: =I341/L341-1 -> 0.0058655514 | Q341: 0.065 | R341: 0 | T341: =T340+0.001 -> 0.06 | U341: =_xlfn.NORM.DIST(T341,$S$202,$S$204,FALSE) -> 0.37569148
A342: 628.77778 | B342: 629.96059 | C342: 627.13775 | D342: 628.47959 | E342: 6536446.8 | F342: Mon, 29 Dec 2025 00:00:00 GMT | G342: =A342/D342-1 -> 0.00047445833 | I342: 193.51345 | J342: 196.61354 | K342: 190.79962 | L342: 192.3051 | M342: 14484719 | N342: Mon, 29 Dec 2025 00:00:00 GMT | O342: =I342/L342-1 -> 0.0062834775 | Q342: More | R342: 7 | T342: =T341+0.001 -> 0.061 | U342: =_xlfn.NORM.DIST(T342,$S$202,$S$204,FALSE) -> 0.33035371
A343: 631.00424 | B343: 632.23178 | C343: 630.05004 | D343: 631.30243 | E343: 3853136 | F343: Fri, 26 Dec 2025 00:00:00 GMT | G343: =A343/D343-1 -> -0.00047233681 | I343: 196.09851 | J343: 198.45568 | K343: 194.23647 | L343: 196.16784 | M343: 11260412 | N343: Fri, 26 Dec 2025 00:00:00 GMT | O343: =I343/L343-1 -> -0.00035342825 | T343: =T342+0.001 -> 0.062 | U343: =_xlfn.NORM.DIST(T343,$S$202,$S$204,FALSE) -> 0.28987936
A344: 630.94461 | B344: 631.48134 | C344: 628.71814 | D344: 628.84736 | E344: 3293313.5 | F344: Wed, 24 Dec 2025 00:00:00 GMT | G344: =A344/D344-1 -> 0.003335072 | I344: 195.60329 | J344: 196.38574 | K344: 192.56262 | L344: 193.13708 | M344: 9368552 | N344: Wed, 24 Dec 2025 00:00:00 GMT | O344: =I344/L344-1 -> 0.012769231 | T344: =T343+0.001 -> 0.063 | U344: =_xlfn.NORM.DIST(T344,$S$202,$S$204,FALSE) -> 0.25383157
A345: 628.84736 | B345: 629.05609 | C345: 625.12001 | D345: 625.13989 | E345: 13842510 | F345: Tue, 23 Dec 2025 00:00:00 GMT | G345: =A345/D345-1 -> 0.0059306134 | I345: 193.47383 | J345: 195.31606 | K345: 190.35392 | L345: 194.55342 | M345: 18368228 | N345: Tue, 23 Dec 2025 00:00:00 GMT | O345: =I345/L345-1 -> -0.0055490506 | T345: =T344+0.001 -> 0.064 | U345: =_xlfn.NORM.DIST(T345,$S$202,$S$204,FALSE) -> 0.22180137
A346: 625.92512 | B346: 626.46186 | C346: 624.00678 | D346: 625.16474 | E346: 9855614.4 | F346: Mon, 22 Dec 2025 00:00:00 GMT | G346: =A346/D346-1 -> 0.0012162839 | I346: 196.48479 | J346: 196.90077 | K346: 190.98781 | L346: 194.93969 | M346: 27160698 | N346: Mon, 22 Dec 2025 00:00:00 GMT | O346: =I346/L346-1 -> 0.0079260238 | T346: =T345+0.001 -> 0.065 | U346: =_xlfn.NORM.DIST(T346,$S$202,$S$204,FALSE) -> 0.1934074
A347: 622.00793 | B347: 622.57289 | C347: 618.34067 | D347: 618.4596 | E347: 10540579 | F347: Fri, 19 Dec 2025 00:00:00 GMT | G347: =A347/D347-1 -> 0.0057373634 | I347: 190.13602 | J347: 193.25593 | K347: 186.3228 | L347: 186.58527 | M347: 76822390 | N347: Fri, 19 Dec 2025 00:00:00 GMT | O347: =I347/L347-1 -> 0.019030178 | T347: =T346+0.001 -> 0.066 | U347: =_xlfn.NORM.DIST(T347,$S$202,$S$204,FALSE) -> 0.16829537
A348: 616.50703 | B348: 620.40226 | C348: 615.07977 | D348: 617.53783 | E348: 33719255 | F348: Thu, 18 Dec 2025 00:00:00 GMT | G348: =A348/D348-1 -> -0.0016692079 | I348: 178.31009 | J348: 182.9949 | K348: 176.87394 | L348: 180.97439 | M348: 33019183 | N348: Thu, 18 Dec 2025 00:00:00 GMT | O348: =I348/L348-1 -> -0.014721979 | T348: =T347+0.001 -> 0.067 | U348: =_xlfn.NORM.DIST(T348,$S$202,$S$204,FALSE) -> 0.14613745
A349: 611.88826 | B349: 620.10492 | C349: 611.69895 | D349: 619.6589 | E349: 21140105 | F349: Wed, 17 Dec 2025 00:00:00 GMT | G349: =A349/D349-1 -> -0.012540188 | I349: 176.75509 | J349: 184.71828 | K349: 175.37837 | L349: 181.55876 | M349: 49705769 | N349: Wed, 17 Dec 2025 00:00:00 GMT | O349: =I349/L349-1 -> -0.026457913 | T349: =T348+0.001 -> 0.068 | U349: =_xlfn.NORM.DIST(T349,$S$202,$S$204,FALSE) -> 0.12663131
A350: 618.68757 | B350: 620.67979 | C350: 615.15906 | D350: 619.02456 | E350: 14046703 | F350: Tue, 16 Dec 2025 00:00:00 GMT | G350: =A350/D350-1 -> -0.00054439196 | I350: 186.84774 | J350: 187.98676 | K350: 182.72748 | L350: 182.93548 | M350: 32420955 | N350: Tue, 16 Dec 2025 00:00:00 GMT | O350: =I350/L350-1 -> 0.021386031 | T350: =T349+0.001 -> 0.069 | U350: =_xlfn.NORM.DIST(T350,$S$202,$S$204,FALSE) -> 0.1094992
A351: 620.42209 | B351: 624.98139 | C351: 619.04438 | D351: 624.98139 | E351: 11407850 | F351: Mon, 15 Dec 2025 00:00:00 GMT | G351: =A351/D351-1 -> -0.0072951028 | I351: 183.15338 | J351: 187.16439 | K351: 179.667 | L351: 186.49118 | M351: 43976623 | N351: Mon, 15 Dec 2025 00:00:00 GMT | O351: =I351/L351-1 -> -0.017897923 | T351: =T350+0.001 -> 0.07 | U351: =_xlfn.NORM.DIST(T351,$S$202,$S$204,FALSE) -> 0.094486778
A352: 621.32404 | B352: 627.826 | C352: 618.95518 | D352: 627.20157 | E352: 8580697.1 | F352: Fri, 12 Dec 2025 00:00:00 GMT | G352: =A352/D352-1 -> -0.0093710493 | I352: 188.15513 | J352: 195.95985 | K352: 184.20325 | L352: 194.49399 | M352: 55281226 | N352: Fri, 12 Dec 2025 00:00:00 GMT | O352: =I352/L352-1 -> -0.032591536
A353: 628.10352 | B353: 628.26211 | C353: 621.7205 | D353: 624.42634 | E353: 22325750 | F353: Thu, 11 Dec 2025 00:00:00 GMT | G353: =A353/D353-1 -> 0.0058888889 | I353: 196.9503 | J353: 200.0603 | K353: 184.45086 | L353: 188.79892 | M353: 1.0067784e+08 | N353: Thu, 11 Dec 2025 00:00:00 GMT | O353: =I353/L353-1 -> 0.043174903
A354: 626.56723 | B354: 627.90034 | C354: 620.92757 | D354: 622.07731 | E354: 22599172 | F354: Wed, 10 Dec 2025 00:00:00 GMT | G354: =A354/D354-1 -> 0.0072176282 | I354: 220.87949 | J354: 223.16742 | K354: 215.50136 | L354: 219.68104 | M354: 37923293 | N354: Wed, 10 Dec 2025 00:00:00 GMT | O354: =I354/L354-1 -> 0.0054553652
A355: 622.54315 | B355: 624.63449 | C355: 622.10705 | D355: 622.62245 | E355: 9703690.3 | F355: Tue, 09 Dec 2025 00:00:00 GMT | G355: =A355/D355-1 -> -0.00012735203 | I355: 219.41362 | J355: 220.49321 | K355: 216.19467 | L355: 217.92795 | M355: 17399578 | N355: Tue, 09 Dec 2025 00:00:00 GMT | O355: =I355/L355-1 -> 0.0068172522
A356: 623.04864 | B356: 625.88334 | C356: 621.15653 | D356: 625.77431 | E356: 6894887.6 | F356: Mon, 08 Dec 2025 00:00:00 GMT | G356: =A356/D356-1 -> -0.0043556766 | I356: 218.43308 | J356: 222.60286 | K356: 214.83776 | L356: 219.23039 | M356: 24666888 | N356: Mon, 08 Dec 2025 00:00:00 GMT | O356: =I356/L356-1 -> -0.0036368565
A357: 624.9021 | B357: 627.37998 | C357: 623.91094 | D357: 624.72369 | E357: 5052250.6 | F357: Fri, 05 Dec 2025 00:00:00 GMT | G357: =A357/D357-1 -> 0.0002855783 | I357: 215.50136 | J357: 217.40302 | K357: 211.57919 | L357: 216.90779 | M357: 24193778 | N357: Fri, 05 Dec 2025 00:00:00 GMT | O357: =I357/L357-1 -> -0.0064840183
...

Sheet Product Lines

Sheet Management

Sheet Table Formatting
B2: [Bold Title] | G2: [Bold Title]
B3: Line Titles | G3: <-- General
B4: Line Titles | G4: <-- Info
B5: Line Titles | G5: <-- General
B6: Line Titles | G6: <-- Info
B7: Line Titles | G7: <-- General
B8: Line Titles | G8: <-- Info
