Workbook

Sheet Main | Overview
A1: Master | CU1: -
B2: PEN | AN2: Thrombus/I : A clot that forms and remains in place inside a blood vessel
B3: Price | C3: 319.11 | D3: 10/72026 | P3: Resources:
B4: SO | C4: 39.389 | D4: Q2'26 | P4: SEC Filings | S4: https://www.sec.gov/edgar/browse/?CIK=1321732&owner=exclude | AN4: Thrombosis: Thrombosis is the formation of a blood clot (thrombus) inside a blood vessel, obstructing blood flow
B5: MC | C5: =C3*C4 -> 12569.424 | P5: Penumbra Homepage | S5: https://www.penumbrainc.com/ | AP5: Can occur in arteries (arterial thrombosis) or veins (venous thrombosis) <-- Penumbra's product are FDA-approved for arterial cases, but have been used off-label for DVT/PE in some cases
B6: Cash | C6: =205.271+453.52 -> 658.791 | D6: Q2'26 | Q6: Penumbra IR Page | T6: https://www.penumbrainc.com/about-us/leadership/
B7: Debt | C7: 0 | D7: Q2'26 | P7: Comp. + Board structure | S7: https://www.sec.gov/Archives/edgar/data/1321732/000114036125014193/ef20047412_ars.pdf | AN7: Thrombectomy: | AP7: Restores blood flow by clearing a blockage
B8: EV | C8: =C5-C6+C7 -> 11910.633 | P8: U.S. Patent Office Search | S8: https://ppubs.uspto.gov/pubThe Companybapp/static/pages/ppubsbasic.html
Q9: Penumbra IP Catalog | T9: https://www.penumbrainc.com/patents/ | AN9: Embolus/i : a thrombus, or other substance that breaks free and circulates through blood vessels
B10: Penumbra Inc. (PEN) | P10: PubMed/NIH reporting's | S10: https://pubmed.ncbi.nlm.nih.gov/
P11: Clinical Trail.Gov | S11: https://clinicaltrials.gov/ | AN11: Embolism: An embolism occurs when a blood clot (thrombus), air bubble, fat globule, or other foreign material travels through the bloodstream and lodges in a blood vessel, blocking blood flow.
B12: Founders: Arani Bose, Adam Elsesser | G12: Registered Exchange: NYSE | Q12: FDAAA Trail Tracker | T12: https://fdaaa.trialstracker.net/
B13: Founded: 2004 | G13: Address: One Penumbra Place, Alameda, CA 94502 | P13: FDA Med Device reporting's | S13: https://www.fda.gov/medical-devices | AN13: Embolization: | AP13: Stops blood flow to prevent or control bleeding or to cut off supply to abnormal tissue
B14: Headquarted: Alameda, CA | G14: Investor Relations / Corporate Strategy Contacts | P14: EV Today Trade News | S14: https://evtoday.com/
B15: Current CEO: Adam Elsesser (Co-Founder) | H15: Investor Relations | J15: (Cecilia Furlong) | P15: MedTech News | S15: https://www.medtechdive.com/news/stryker-inari-medical-acquisition/736615/
B16: Employees: 4,600 (Q2'25) | H16: Phone: | I16: (510) 995-2461 | K16: Email: | L16: investors@penumbrainc.com | P16: American Heart Association | S16: https://www.heart.org/en/
B17: Sector: Medical Devices | I17: (510) 748-3200 | P17: MacroTrends | S17: https://www.macrotrends.net/stocks/charts/PEN/penumbra/income-statement?freq=Q
B18: Industry: Thrombectomy/Embolization | P18: ROIC, WACC | S18: https://www.gurufocus.com/term/wacc/PEN
B19: IPO: September 18, 2015 -- $895M valuation … Secondary offering May 27, 2020, 1 week after NARIs IPO? | P19: Earnings Calls | S19: https://seekingalpha.com/symbol/PEN/earnings/transcripts
B20: Fiscal Year: [January - December] | P20: Godel Terminal | S20: https://app.godelterminal.com/
A22: Company Overview:
B23: Penumbra, the world’s leading thrombectomy company, is focused on developing the most innovative technologies for challenging medical conditions in the thrombectomy and embolization space
B24: The Company designs, develops, manufactures, and markets medical devices in the United States and internationally
C25: The Company's broad portfolio, which includes computer assisted vacuum thrombectomy (CAVT), centers on removing blood clots from head-to-toe with speed, safety and simplicity
D26: Strong track record of organic product development and commercial expansion that has established a strong foundation for The Company's global operations
E27: Focused and lean portfolio of assets … many individual offerings feed into a system
D28: Company managers state their belief that the cost-effectiveness of The Company's products are attractive to customers
E29: Offerings are cheaper for MT products when compared to almost all other competitors … Economic impact is even greater due to leading edge speed safety and ease of use
B30: The Company has successfully developed, obtained regulatory clearance or approval for, and introduced products into a range of markets which make up a portfolio including:
C31: the Thrombectomy market (entered 2007)
C32: the Access market (entered 2008)
C33: the Embolization market (entered 2011)
C34: the Neurosurgical market (entered 2014)
C35: the Immersive Healthcare market (entered 2020, divested September 2024) <-- Decision to wind down and exit the Immersive Healthcare business, and as a result, incurred a $115.3 million impairment charge at year-end
D36: During year ended December 31, 2024, The Company permanently ceased sales of Immersive Healthcare products and related commercial operations
D37: (important to track/sum the total impairment cost in model) … (see additional comments in Notes tab)
B38: The Company sells its products through direct sales organizations and distributors
C39: The Company sells products to healthcare providers primarily through The Company's direct sales organization in the United States, most of Europe, Canada and Australia, and as a partner with distributors in select international markets (China, APac, LatAm)
D40: Salesforce serves as a consultative ramp of sorts … top notch sales people are necessary to effectively describe the superiority of The Company's offering (CAVT, Ruby, etc.) as well as the clinical and economic impact demonstated from PEN products
C41: A significant portion of the company's inventory is outstanding and in consignment, ready to be used by healthcare providers
B42: The Company expects to continue developing and building a portfolio of products, including thrombectomy, embolization and access technologies, while iterating on currently available products
C43: The Company's research and development activities are centered around development of new products and clinical activities designed to support regulatory submissions and demonstrate product efficacy to regulating bodies and medical professionals
C44: Generally, when introducing a next generation product or a new product designed to replace a current product, sales of the earlier generation product or the product replaced decline
D45: Similar to BioPharma, economic returns decline once a treatment option "goes generic," or a newer, more effective form of treatment is developed/commercialized
B46: The Company attributes it's success to their culture built on cooperation, it's highly efficient product innovation process, it's disciplined approach to product and commercial development, it's deep understanding of it's target end markets and it's relationships with specialist physicians and other healthcare providers. We believe these factors have enabled us to rapidly innovate in a highly efficient manner
B47: The Company sells it's products to healthcare providers primarily through it's direct sales organization in the United States, most of Europe, Canada and Australia, as well as through distributors in select international markets
A49: Markets:
B50: The Company concentrates on improving treatment outcomes for patients with certain forms of vascular disease
C51: Vascular disease refers to any condition that affects the circulatory system and typically manifests as a blockage or rupture of an artery or a vein
B52: The Company classifies end markets according to the anatomic location of the disorder and divides them into two categories:
C53: Neuro, which included neurovascular and neurosurgical (Stroke, Aneurysm)
C54: Vascular, which included peripheral vascular and cardiovascular.
B55: The Company began to classify end markets based on the type of procedure being performed (beginning with the three months ended December 31, 2023), and therefore divide markets into two segment categories:
C56: Thrombectomy, which includes products that treat conditions such as pulmonary embolism, deep vein thrombosis, acute limb ischemia, ischemic stroke and coronary disease
C57: Embolization and Access, which include products to treat aneurysms and to occlude vessels as well as products to access the vasculature
A59: Thrombectomy Market:
B60: The thrombectomy market is comprised of vascular diseases and disorders occurring in vessels throughout the body, including ischemic stroke, VT such as pulmonary embolism, acute limb ischemia, DVT, coronary disease and other conditions
C61: Disruption of blood flow to the vasculature can have serious adverse consequences, including death and morbidity, and The Company's solutions address the intervention of these diseases
C62: There are approximately 2.15 million incidences of clot in the vasculature each year in the United States, the vast majority of which do not currently receive mechanical thrombectomy intervention
C63: Studies have shown that patients treated with mechanical thrombectomy had improved functional outcomes compared with treatments such as tissue-type plasminogen activator (tPA) alone
D64: [Commit to tracking hospital adoption … terrific products will win, but continued education to demonstrate efficacy that trumps both status quo pharmaceuticals (which a cheap and available everywhere … but with lower patient outcome quality, or other mechanical offerings (which are inferior)]
B65: Common conditions The Company is focused on include:
E67: Estimated Elligible Patient Population | G67: Pulmonary Embolism ("PE"):
B68: U.S. # of PEs per year: | E68: ~150k | H68: PE is a condition that occurs when blood clots, which typically travel from the veins in the legs, get caught in the lungs
B69: Intl. # of PEs per year: | E69: ~350k | I69: Approximately 1.2 million PEs occur annually worldwide. In the U.S., there are approximately 350,000 PEs per year causing approximately 50,000 annual deaths according to the Centers for Disease Control and Prevention
B70: Total est. PEs per year: | E70: ~500k | I70: High- and intermediate-risk PEs, which are generally eligible for treatment with mechanical or computer assisted vacuum thrombectomy, represent approximately 44% of such PEs, or approximately 150,000 U.S. patients
B71: Cases per year (globally) | E71: 1.2m | I71: Approximately 800,000 annual PEs outside the U.S. and approximately 350,000 of them are massive or sub-massive, making them eligible for thrombectomy
E73: Estimated Elligible Patient Population | G73: Deep Vein Thrombosis ("DVT"):
B74: U.S. # of DVTs per year: | E74: ~350k | H74: DVT occurs when a clot forms in a deep vein, usually in the leg and sometimes in the arm
B75: Intl. # of DVTs per year: | E75: ~2m | I75: Approximately 4 million DVTs occur annually worldwide
B76: Total est. DVTs per year: | E76: ~2.4m | I76: Approximately 350,000 DVTs are eligible for treatment with mechanical or computer assisted vacuum thrombectomy in the U.S. … In the U.S., there are approximately 30,000 annual deaths caused by DVT according to the Centers for Disease Control and Prevention
B77: Cases per year (globally) | E77: 4m | I77: Approximately 2 million annual DVTs outside the U.S. that are eligible for thrombectomy procedures
E79: Estimated Elligible Patient Population | G79: Acute Limb Ischemia ("ALI"):
B80: U.S. # of ALIs per year: | E80: ~250k | H80: ALI occurs when the leg experiences an occlusion in an artery, caused either by a blood clot in the artery or by emboli from the heart or another place within the body that travel to the leg and cause an occlusion
B81: Intl. # of ALIs per year: | E81: ~2.25m | I81: Approximately 2.5 million ALIs occur annually and that there are approximately 16 million ALI survivors worldwide.
B82: Total est. ALIs per year: | E82: ~2.5m | I82: Approximately 250,000 ALIs per year in the U.S., which are generally eligible for treatment with mechanical or computer assisted vacuum thrombectomy
B83: Cases per year (globally) | E83: 2.5m | I83: Approximately 2.25 million annual ALIs outside the U.S. that are eligible for thrombectomy
E85: Estimated Elligible Patient Population | G85: Ischemic Stroke:
B86: U.S. # of strokes per year: | E86: ~200k | H86: A stroke occurs when a blood vessel that carries oxygen and nutrients to the brain is either blocked by a clot or bursts (ruptures) … Ischemic strokes represent approximately 87% of strokes, or approximately 800,000 patients annually, in the United States
B87: Intl. # of strokes per year: | E87: ~1.9m | I87: Nearly 800,000 strokes occur annually, and lead to approximately 150,000 deaths per year.
B88: Total est. strokes per year: | E88: ~2.1m | J88: Of these cases, The Company estimate that approximately 200,000 are treatable with mechanical thrombectomy, which involves removal of the clot causing the blockage by mechanical means and restoring blood flow to the blocked vessels
B89: Cases per year (globally) | E89: 9.7m | I89: Outside of the United States, The Company estimate, based on published sources, that there are approximately 9.7 million ischemic strokes annually and that 1.9 million of these patients are treatable with mechanical thrombectomy
E91: Estimated Elligible Patient Population | G91: Acute Coronary Syndrome ("ACS"):
B92: U.S. # of ACS per year: | E92: ~300k | H92: ACS includes various conditions associated with sudden, reduced blood flow to the heart
B93: Intl. # of ACS per year: | E93: ~8m | I93: One such condition is a heart attack (acute myocardial infarction or “AMI”), when cell death results in damaged or destroyed heart tissue. Heart attacks can often be associated with high thrombus burden in the coronary arteries
B94: Total est. ACS per year: | E94: ~8.3m | H94: Approximately 8.5 million AMIs occur annually and there are approximately 23.5 million AMI survivors worldwide
B95: Cases per year (globally) | E95: 8.5m | H95: In the U.S., there are approximately 500,000 AMIs per year causing approximately 350,000 annual deaths according to the American Heart Association.
I96: AMIs involving high thrombus burden, which are generally eligible for treatment with mechanical thrombectomy, represent approximately 60% of U.S. AMIs, or approximately 300,000 U.S. patients
H97: The Company estimate there are approximately 8 million annual AMIs outside the U.S. that are eligible for mechanical thrombectomy.
G99: Clot from Arteriovenous Graft or Fistula:
H100: Arteriovenous grafts or fistulas are created for access to dialyze the blood of patients with end-stage renal disease.
I101: It is common for clots to form within these access vessels when patients undergo dialysis long-term
A103: Embolization and Access Market:
B104: The Embolization and Access markets are comprised of various diseases and conditions throughout the body, such as aneurysm, hemorrhagic stroke, vessel malformations, bleeding, endoleaks, ovarian veins, varicoceles, and hematomas, as well as products that provide access to the diseased area.
E105: Aneurysm: | G105: An aneurysm is a weak area in a blood vessel that usually enlarges and is often described as a “ballooning” of the blood vessel.
G106: Approximately 2% of the general population has or will develop an aneurysm and approximately 9 million people in the United States may currently have an aneurysm
H107: If a patient has had an aneurysm, there is a 20% likelihood that the patient will have one or more additional aneurysms
G108: The primary endovascular procedure for treating unruptured aneurysms uses a repair technique called embolization, in which the aneurysm is packed with coils in a minimally invasive procedure
E109: Hemorrhagic Stroke: | G109: Hemorrhagic strokes, caused by the sudden rupture of a brain artery that leads to bleeding into or around the brain, represent approximately 13% of strokes in the United States
H110: Brain aneurysms and arteriovenous malformations (“AVM”) can both cause hemorrhagic stroke
...

Sheet Bull Case (30%)
S1: Q1 2019 | W1: Q1 2020 | AA1: Q1 2021 | AE1: Q1 2022 | AI1: Q1 2023 | AM1: Q1 2024 | AQ1: Q1 2025 | AU1: Q1 2026
B2: Quarterly | C2: Apr | D2: July | E2: Oct | F2: Jan | G2: Apr | H2: July | I2: Oct | J2: Jan | K2: Apr | L2: July | M2: Oct | N2: Jan | O2: Apr | P2: July | Q2: Oct | R2: Jan | S2: Apr | T2: July | U2: Oct | V2: Jan | W2: Apr | X2: July | Y2: Oct | Z2: Jan | AA2: Apr | AB2: July | AC2: Oct | AD2: Jan | AE2: Apr | AF2: July | AG2: Oct | AH2: Jan | AI2: Apr | AJ2: July | AK2: Oct | AL2: Jan | AM2: Apr | AN2: July | AO2: Oct | AP2: Jan | AQ2: Apr | AR2: July | AS2: Oct | AT2: Jan | AU2: Apr | AV2: July | AW2: Oct | AX2: Jan | AY2: Apr | AZ2: July | BA2: Oct | BB2: Jan
B3: Revenues | C3: Q1 2015 | D3: Q2 2015 | E3: Q3 2015 | F3: Q4 2015 | G3: Q1 2016 | H3: Q2 2016 | I3: Q3 2016 | J3: Q4 2016 | K3: Q1 2017 | L3: Q2 2017 | M3: Q3 2017 | N3: Q4 2017 | O3: Q1 2018 | P3: Q2 2018 | Q3: Q3 2018 | R3: Q4 2018 | S3: Q1 2019 | T3: Q2 2019 | U3: Q3 2019 | V3: Q4 2019 | W3: Q1 2020 | X3: Q2 2020 | Y3: Q3 2020 | Z3: Q4 2020 | AA3: Q1 2021 | AB3: Q2 2021 | AC3: Q3 2021 | AD3: Q4 2021 | AE3: Q1 2022 | AF3: Q2 2022 | AG3: Q3 2022 | AH3: Q4 2022 | AI3: Q1 2023 | AJ3: Q2 2023 | AK3: Q3 2023 | AL3: Q4 2023 | AM3: Q1 2024 | AN3: Q2 2024 | AO3: Q3 2024 | AP3: Q4 2024 | AQ3: Q1 2025 | AR3: Q2 2025 | AS3: Q3 2025 | AT3: Q4 2025 | AU3: Q1 2026 | AV3: Q2 2026 | AW3: Q3 2026 | AX3: Q4 2026 | AY3: Q1 2027 | AZ3: Q2 2027 | BA3: Q3 2027 | BB3: Q4 2027 | BG3: 2015 | BH3: 2016 | BI3: 2017 | BJ3: 2018 | BK3: 2019 | BL3: 2020 | BM3: 2021 | BN3: 2022 | BO3: =BN3+1 -> 2023 | BP3: =BO3+1 -> 2024 | BQ3: =BP3+1 -> 2025 | BR3: =BQ3+1 -> 2026 | BS3: =BR3+1 -> 2027 | BT3: =BS3+1 -> 2028 | BU3: =BT3+1 -> 2029 | BV3: =BU3+1 -> 2030 | ... DO3: =DN3+1 -> 2075
B4: Thrombectomy (Neuro + Peripheral) | AI4: 145 | AJ4: 162 | AK4: 179 | AL4: =677-SUM(AI4:AK4) -> 191 | AM4: 188 | AN4: 203 | AO4: 204 | AP4: =815-SUM(AM4:AO4) -> 220 | AQ4: 226.544 | AR4: 230.256 | AS4: 236.4 | AT4: =947.918-SUM(AQ4:AS4) -> 254.718 | AU4: 253.917 | AV4: 258.981 | AW4: =AS4*(1+AW8) -> 293.136 | AX4: =AT4*(1+AX8) -> 315.85032 | BO4: =SUM(AI4:AL4) -> 677 | BP4: =SUM(AM4:AP4) -> 815 | BQ4: =SUM(AQ4:AT4) -> 947.918 | BR4: =BQ4*(1+BR8) -> 1123.2828 | BS4: =BR4*(1+BS8) -> 1370.4051 | BT4: =BS4*(1+BT8) -> 1658.1901 | BU4: =BT4*(1+BU8) -> 1964.9553 | BV4: =BU4*(1+BV8) -> 2298.9977 | BW4: =BV4*(1+BW8) -> 2666.8373 | BX4: =BW4*(1+BX8) -> 3066.8629 | BY4: =BX4*(1+BY8) -> 3496.2237 | ... CA4: =BZ4*(1+CA8) -> 4484.0817
B5: Embolization & Access (Peripheral Embolization + Neuro Embolization + Access + Neurosurgical Tools) | AI5: 96 | AJ5: 99 | AK5: 92 | AL5: =381-SUM(AI5:AK5) -> 94 | AM5: 91 | AN5: 96 | AO5: 96.89 | AP5: =379-SUM(AM5:AO5) -> 95.11 | AQ5: 97.596 | AR5: 109.199 | AS5: 118.3 | AT5: =455.747-SUM(AQ5:AS5) -> 130.652 | AU5: 120.841 | AV5: 131.065 | AW5: =AS5*(1+AW9) -> 129.83425 | AX5: =AT5*(1+AX9) -> 143.06394 | BO5: =SUM(AI5:AL5) -> 381 | BP5: =SUM(AM5:AP5) -> 379 | BQ5: =SUM(AQ5:AT5) -> 455.747 | BR5: =BQ5*(1+BR9) -> 524.10905 | BS5: =BR5*(1+BS9) -> 607.9665 | BT5: =BS5*(1+BT9) -> 693.08181 | BU5: =BT5*(1+BU9) -> 776.25162 | BV5: =BU5*(1+BV9) -> 853.87679 | BW5: =BV5*(1+BW9) -> 922.18693 | BX5: =BW5*(1+BX9) -> 986.74002 | BY5: =BX5*(1+BY9) -> 1045.9444 | ... CA5: =BZ5*(1+CA9) -> 1142.1713
B6: Ttl Revenues | AI6: =SUM(AI4:AI5) -> 241 | AJ6: =SUM(AJ4:AJ5) -> 261 | AK6: =SUM(AK4:AK5) -> 271 | AL6: =SUM(AL4:AL5) -> 285 | AM6: =SUM(AM4:AM5) -> 279 | AN6: =SUM(AN4:AN5) -> 299 | AO6: =SUM(AO4:AO5) -> 300.89 | AP6: =SUM(AP4:AP5) -> 315.11 | ... AT6: =SUM(AT4:AT5) -> 385.37 | AU6: =AU4+AU5 -> 374.758 | AV6: =AV4+AV5 -> 390.046 | AW6: =AW4+AW5 -> 422.97025 | AX6: =AX4+AX5 -> 458.91426 | BO6: =BO4+BO5 -> 1058 | BP6: =BP4+BP5 -> 1194 | BQ6: =SUM(AQ6:AT6) -> 1403.665 | BR6: =BR4+BR5 -> 1647.3919 | BS6: =BS4+BS5 -> 1978.3716 | BT6: =BT4+BT5 -> 2351.2719 | BU6: =BU4+BU5 -> 2741.2069 | BV6: =BV4+BV5 -> 3152.8745 | BW6: =BW4+BW5 -> 3589.0242 | BX6: =BX4+BX5 -> 4053.6029 | BY6: =BY4+BY5 -> 4542.1681 | ... CA6: =CA4+CA5 -> 5626.253
B8: Thrombectomy Revenue Growth Y/y | AM8: =AM4/AI4-1 -> 0.29655172 | AN8: =AN4/AJ4-1 -> 0.25308642 | AO8: =AO4/AK4-1 -> 0.1396648 | AP8: =AP4/AL4-1 -> 0.15183246 | AQ8: =AQ4/AM4-1 -> 0.20502128 | AR8: =AR4/AN4-1 -> 0.13426601 | AS8: =AS4/AO4-1 -> 0.15882353 | AT8: =AT4/AP4-1 -> 0.15780909 | AU8: 0.17 | AV8: 0.22 | AW8: 0.24 | AX8: 0.24 | BP8: =BP4/BO4-1 -> 0.20384047 | BQ8: =BQ4/BP4-1 -> 0.16308957 | BR8: 0.185 | BS8: 0.22 | BT8: 0.21 | BU8: 0.185 | BV8: 0.17 | BW8: 0.16 | BX8: 0.15 | BY8: 0.14 | BZ8: 0.135 | CA8: 0.13
B9: E & A Revenue Growth Y/y | AM9: =AM5/AI5-1 -> -0.052083333 | AN9: =AN5/AJ5-1 -> -0.03030303 | AO9: =AO5/AK5-1 -> 0.053152174 | AP9: =AP5/AL5-1 -> 0.011808511 | AQ9: =AQ5/AM5-1 -> 0.072483516 | AR9: =AR5/AN5-1 -> 0.13748958 | AS9: =AS5/AO5-1 -> 0.22097224 | AT9: =AT5/AP5-1 -> 0.37369362 | AU9: 0.16 | AV9: 0.105 | AW9: 0.0975 | AX9: 0.095 | BP9: =BP5/BO5-1 -> -0.0052493438 | BQ9: =BQ5/BP5-1 -> 0.20249868 | BR9: 0.15 | BS9: 0.16 | BT9: 0.14 | BU9: 0.12 | BV9: 0.1 | BW9: 0.08 | BX9: 0.07 | BY9: 0.06 | BZ9: 0.05 | CA9: 0.04
B10: Total Revenue Growth Y/y | AM10: =AM6/AI6-1 -> 0.15767635 | AN10: =AN6/AJ6-1 -> 0.14559387 | AO10: =AO6/AK6-1 -> 0.1102952 | AP10: =AP6/AL6-1 -> 0.10564912 | AQ10: =AQ6/AM6-1 -> 0.16179211 | AR10: =AR6/AN6-1 -> 0.135301 | AS10: =AS6/AO6-1 -> 0.17883612 | AT10: =AT6/AP6-1 -> 0.22296976 | ... AX10: =AX6/AT6-1 -> 0.19084065 | BP10: =BP6/BO6-1 -> 0.12854442 | BQ10: =BQ6/BP6-1 -> 0.17559883 | BR10: =BR6/BQ6-1 -> 0.17363607 | BS10: =BS6/BR6-1 -> 0.20091132 | BT10: =BT6/BS6-1 -> 0.18848854 | BU10: =BU6/BT6-1 -> 0.16584002 | BV10: =BV6/BU6-1 -> 0.15017749 | BW10: =BW6/BV6-1 -> 0.13833401 | ... CA10: =CA6/BZ6-1 -> 0.11049095
B12: Thrombectomy % of Ttl Revenues | AI12: =AI4/AI6 -> 0.60165975 | AJ12: =AJ4/AJ6 -> 0.62068966 | AK12: =AK4/AK6 -> 0.66051661 | AL12: =AL4/AL6 -> 0.67017544 | AM12: =AM4/AM6 -> 0.67383513 | AN12: =AN4/AN6 -> 0.67892977 | AO12: =AO4/AO6 -> 0.67798863 | AP12: =AP4/AP6 -> 0.69816889 | ... AX12: =AX4/AX6 -> 0.68825562 | BO12: =AVERAGE(AI12:AL12) -> 0.63826036 | BP12: =AVERAGE(AM12:AP12) -> 0.6822306 | BQ12: =AVERAGE(AN12:AQ12) -> 0.68849879 | BR12: =BR4/BR6 -> 0.68185527 | BS12: =BS4/BS6 -> 0.69269347 | BT12: =BT4/BT6 -> 0.70523111 | BU12: =BU4/BU6 -> 0.71682122 | BV12: =BV4/BV6 -> 0.72917514 | BW12: =BW4/BW6 -> 0.74305358 | BX12: =BX4/BX6 -> 0.75657704 | BY12: =BY4/BY6 -> 0.76972574 | ... CA12: =CA4/CA6 -> 0.79699255
B13: E & A % of Ttl Revenues | AI13: =AI5/AI6 -> 0.39834025 | AJ13: =AJ5/AJ6 -> 0.37931034 | AK13: =AK5/AK6 -> 0.33948339 | AL13: =AL5/AL6 -> 0.32982456 | AM13: =AM5/AM6 -> 0.32616487 | AN13: =AN5/AN6 -> 0.32107023 | AO13: =AO5/AO6 -> 0.32201137 | AP13: =AP5/AP6 -> 0.30183111 | ... AX13: =AX5/AX6 -> 0.31174438 | BO13: =AVERAGE(AI13:AL13) -> 0.36173964 | BP13: =AVERAGE(AM13:AP13) -> 0.3177694 | BQ13: =AVERAGE(AN13:AQ13) -> 0.31150121 | BR13: =BR5/BR6 -> 0.31814473 | BS13: =BS5/BS6 -> 0.30730653 | BT13: =BT5/BT6 -> 0.29476889 | BU13: =BU5/BU6 -> 0.28317878 | BV13: =BV5/BV6 -> 0.27082486 | BW13: =BW5/BW6 -> 0.25694642 | BX13: =BX5/BX6 -> 0.24342296 | BY13: =BY5/BY6 -> 0.23027426 | ... CA13: =CA5/CA6 -> 0.20300745
B15: U.S. Revenues | S15: 82.511 | T15: 86.374 | U15: 90.272 | V15: =355.22-SUM(S15:U15) -> 96.063 | W15: 96 | X15: 78 | Y15: 110 | Z15: =400-SUM(W15:Y15) -> 116 | AA15: 120 | AB15: 128 | AC15: 135 | AD15: =528-SUM(AA15:AC15) -> 145 | AE15: 144 | AF15: 141 | AG15: 149 | AH15: =592-SUM(AE15:AG15) -> 158 | AI15: 172 | AJ15: 186 | AK15: 195 | AL15: =757-SUM(AI15:AK15) -> 204 | AM15: 210 | AN15: 218 | AO15: 226 | AP15: =902-SUM(AM15:AO15) -> 248 | AQ15: 256.86 | AR15: 260.818 | AS15: 275.029 | AT15: =1091.761-SUM(AQ15:AS15) -> 299.054 | AU15: 296.387 | AV15: 305.445 | BK15: =SUM(S15:V15) -> 355.22 | BL15: =SUM(W15:Z15) -> 400 | BM15: =SUM(AA15:AC15) -> 383 | BN15: =SUM(AE15:AG15) -> 434 | BO15: =SUM(AI15:AL15) -> 757 | BP15: =SUM(AM15:AP15) -> 902 | BQ15: =SUM(AQ15:AT15) -> 1091.761
B16: International Revenues | S16: =9.522+36.406 -> 45.928 | T16: =12.231+35.596 -> 47.827 | U16: =11.214+38.016 -> 49.23 | V16: =42.52+149.663-SUM(S16:U16) -> 49.198 | W16: 41 | X16: 27 | Y16: 41 | Z16: =160-SUM(W16:Y16) -> 51 | AA16: 49 | AB16: 56 | AC16: 55 | AD16: =220-SUM(AA16:AC16) -> 60 | AE16: 60 | AF16: 67 | AG16: 65 | AH16: =255-SUM(AE16:AG16) -> 63 | AI16: 69 | AJ16: 75 | AK16: 76 | AL16: =301-SUM(AI16:AK16) -> 81 | AM16: 69 | AN16: 81 | AO16: 77 | AP16: =292-SUM(AM16:AO16) -> 65 | AQ16: 67.28 | AR16: 78.637 | AS16: 79.656 | AT16: =311.904-SUM(AQ16:AS16) -> 86.331 | AU16: 78.371 | AV16: 84.601 | BK16: =SUM(S16:V16) -> 192.183 | BL16: =SUM(W16:Z16) -> 160 | BM16: =SUM(AA16:AC16) -> 160 | BN16: =SUM(AE16:AG16) -> 192 | BO16: =SUM(AI16:AL16) -> 301 | BP16: =SUM(AM16:AP16) -> 292 | BQ16: =SUM(AQ16:AT16) -> 311.904
B17: Ttl Revenues | S17: =SUM(S15:S16) -> 128.439 | T17: =SUM(T15:T16) -> 134.201 | U17: =SUM(U15:U16) -> 139.502 | V17: =SUM(V15:V16) -> 145.261 | W17: =SUM(W15:W16) -> 137 | X17: =SUM(X15:X16) -> 105 | Y17: =SUM(Y15:Y16) -> 151 | Z17: =SUM(Z15:Z16) -> 167 | ... AV17: =SUM(AV15:AV16) -> 390.046 | BK17: =SUM(S17:V17) -> 547.403 | BL17: =SUM(W17:Z17) -> 560 | BM17: =SUM(AA17:AD17) -> 748 | BN17: =SUM(AE17:AH17) -> 847 | BO17: =SUM(AI17:AL17) -> 1058 | BP17: =SUM(AM17:AP17) -> 1194 | BQ17: =SUM(AQ17:AT17) -> 1403.665
B19: U.S. Revenue Growth Y/y | W19: =W15/S15-1 -> 0.16348123 | X19: =X15/T15-1 -> -0.096950471 | Y19: =Y15/U15-1 -> 0.21853952 | Z19: =Z15/V15-1 -> 0.20754088 | AA19: =AA15/W15-1 -> 0.25 | AB19: =AB15/X15-1 -> 0.64102564 | AC19: =AC15/Y15-1 -> 0.22727273 | AD19: =AD15/Z15-1 -> 0.25 | ... AV19: =AV15/AR15-1 -> 0.17110399 | BL19: =BL15/BK15-1 -> 0.12606272 | BM19: =BM15/BL15-1 -> -0.0425 | BN19: =BN15/BM15-1 -> 0.13315927 | BO19: =BO15/BN15-1 -> 0.74423963 | BP19: =BP15/BO15-1 -> 0.19154557 | BQ19: =BQ15/BP15-1 -> 0.21037805
B20: International Revenue Growth Y/y | W20: =W16/S16-1 -> -0.10729838 | X20: =X16/T16-1 -> -0.43546532 | Y20: =Y16/U16-1 -> -0.16717449 | Z20: =Z16/V16-1 -> 0.036627505 | AA20: =AA16/W16-1 -> 0.19512195 | AB20: =AB16/X16-1 -> 1.0740741 | AC20: =AC16/Y16-1 -> 0.34146341 | AD20: =AD16/Z16-1 -> 0.17647059 | ... AV20: =AV16/AR16-1 -> 0.075842161 | BL20: =BL16/BK16-1 -> -0.16746018 | BM20: =BM16/BL16-1 -> 0 | BN20: =BN16/BM16-1 -> 0.2 | BO20: =BO16/BN16-1 -> 0.56770833 | BP20: =BP16/BO16-1 -> -0.029900332 | BQ20: =BQ16/BP16-1 -> 0.068164384
B21: Total Revenue Growth Y/y | W21: =W17/S17-1 -> 0.066654209 | X21: =X17/T17-1 -> -0.21759152 | Y21: =Y17/U17-1 -> 0.082421757 | Z21: =Z17/V17-1 -> 0.14965476 | AA21: =AA17/W17-1 -> 0.23357664 | AB21: =AB17/X17-1 -> 0.75238095 | AC21: =AC17/Y17-1 -> 0.25827815 | AD21: =AD17/Z17-1 -> 0.22754491 | ... AV21: =AV17/AR17-1 -> 0.14903595 | BL21: =BL17/BK17-1 -> 0.023012296 | BM21: =BM17/BL17-1 -> 0.33571429 | BN21: =BN17/BM17-1 -> 0.13235294 | BO21: =BO17/BN17-1 -> 0.24911452 | BP21: =BP17/BO17-1 -> 0.12854442 | BQ21: =BQ17/BP17-1 -> 0.17559883
B23: U.S. % of Ttl Revenues | S23: =S15/S17 -> 0.64241391 | T23: =T15/T17 -> 0.64361666 | U23: =U15/U17 -> 0.64710183 | V23: =V15/V17 -> 0.66131308 | W23: =W15/W17 -> 0.70072993 | X23: =X15/X17 -> 0.74285714 | Y23: =Y15/Y17 -> 0.72847682 | Z23: =Z15/Z17 -> 0.69461078 | ... AV23: =AV15/AV17 -> 0.78309994 | BK23: =BK15/BK17 -> 0.64891862 | BL23: =BL15/BL17 -> 0.71428571 | BM23: =BM15/BM17 -> 0.51203209 | BN23: =BN15/BN17 -> 0.51239669 | BO23: =BO15/BO17 -> 0.71550095 | BP23: =BP15/BP17 -> 0.75544389 | BQ23: =BQ15/BQ17 -> 0.77779313
B24: International % of Ttl Revenues | S24: =S16/S17 -> 0.35758609 | T24: =T16/T17 -> 0.35638334 | U24: =U16/U17 -> 0.35289817 | V24: =V16/V17 -> 0.33868692 | W24: =W16/W17 -> 0.29927007 | X24: =X16/X17 -> 0.25714286 | Y24: =Y16/Y17 -> 0.27152318 | Z24: =Z16/Z17 -> 0.30538922 | ... AV24: =AV16/AV17 -> 0.21690006 | BK24: =BK16/BK17 -> 0.35108138 | BL24: =BL16/BL17 -> 0.28571429 | BM24: =BM16/BM17 -> 0.21390374 | BN24: =BN16/BN17 -> 0.22668241 | BO24: =BO16/BO17 -> 0.28449905 | BP24: =BP16/BP17 -> 0.24455611 | BQ24: =BQ16/BQ17 -> 0.22220687
B26: Revenues | C26: 39 | D26: 42.3 | E26: 50.4 | F26: 54.4 | G26: 57.9 | H26: 65.1 | I26: 67.2 | J26: 73.1 | K26: 73.2 | L26: 80.6 | M26: 83.9 | N26: 96.1 | O26: 102.7 | P26: 109.6 | Q26: 111.8 | R26: 120.8 | S26: =S17 -> 128.439 | T26: =T17 -> 134.201 | U26: =U17 -> 139.502 | V26: =V17 -> 145.261 | W26: 137.3 | X26: 105.1 | Y26: 151.1 | Z26: =560.412-SUM(W26:Y26) -> 166.912 | AA26: 169.2 | AB26: 184.3 | AC26: 190.1 | AD26: =747.59-SUM(AA26:AC26) -> 203.99 | AE26: 203.9 | AF26: 208.3 | AG26: 213.7 | AH26: =847.133-SUM(AE26:AG26) -> 221.233 | AI26: 241.4 | AJ26: 261.5 | AK26: 270.9 | AL26: =1058.52-SUM(AI26:AK26) -> 284.72 | AM26: 278.7 | AN26: 299.4 | AO26: 301 | AP26: =1194.6-SUM(AM26:AO26) -> 315.5 | AQ26: =AQ17 -> 324.14 | AR26: =AR17 -> 339.455 | AS26: =AS17 -> 354.685 | AT26: =1403.665-SUM(AQ26:AS26) -> 385.385 | AU26: =AU17 -> 374.758 | AV26: =AV17 -> 390.046 | AW26: =AW6 -> 422.97025 | AX26: =AX6 -> 458.91426 | BG26: =SUM(C26:F26) -> 186.1 | BH26: =SUM(G26:J26) -> 263.3 | BI26: =SUM(K26:N26) -> 333.8 | BJ26: =SUM(O26:R26) -> 444.9 | BK26: =SUM(S26:V26) -> 547.403 | BL26: =SUM(W26:Z26) -> 560.412 | BM26: =SUM(AA26:AD26) -> 747.59 | BN26: =SUM(AE26:AH26) -> 847.133 | BO26: =SUM(AI26:AL26) -> 1058.52 | BP26: =SUM(AM26:AP26) -> 1194.6 | BQ26: =SUM(AQ26:AT26) -> 1403.665 | BR26: =BR6 -> 1647.3919 | BS26: =BS6 -> 1978.3716 | BT26: =BT6 -> 2351.2719 | BU26: =BU6 -> 2741.2069 | BV26: =BV6 -> 3152.8745 | BW26: =BW6 -> 3589.0242 | BX26: =BX6 -> 4053.6029 | BY26: =BY6 -> 4542.1681 | ... CA26: =CA6 -> 5626.253
B27: COGS | C27: 12.2 | D27: 14.9 | E27: 16.9 | F27: 18 | G27: 18 | H27: 23.6 | I27: 24.3 | J27: 26.5 | K27: 25.5 | L27: 29.7 | M27: 29.1 | N27: 32.3 | O27: 36.1 | P27: 37.4 | Q27: 36.8 | R27: 42.1 | S27: 44.529 | T27: 40.273 | U27: 43.504 | V27: =175.441-SUM(S27:U27) -> 47.135 | W27: 49.3 | X27: 40.2 | Y27: 60.153 | Z27: =222.237-SUM(W27:Y27) -> 72.584 | AA27: 57.867 | AB27: 65.6 | AC27: 70.2 | AD27: =272.208-SUM(AA27:AC27) -> 78.541 | AE27: 76.5 | AF27: 74.3 | AG27: 78.4 | AH27: =311.926-SUM(AE27:AG27) -> 82.726 | AI27: 90.3 | AJ27: 94.6 | AK27: 93.2 | AL27: =375.9-SUM(AI27:AK27) -> 97.8 | AM27: 97.5 | AN27: 136.6 | AO27: 100.7 | AP27: =439.6-SUM(AM27:AO27) -> 104.8 | AQ27: 108.257 | AR27: 115.445 | AS27: 114.269 | AT27: =461.228-SUM(AQ27:AS27) -> 123.257 | AU27: 121.347 | AV27: 125.102 | AW27: =AW26*(1-AW43) -> 130.27484 | AX27: =AX26*(1-AX43) -> 137.67428 | BG27: =SUM(C27:F27) -> 62 | BH27: =SUM(G27:J27) -> 92.4 | BI27: =SUM(K27:N27) -> 116.6 | BJ27: =SUM(O27:R27) -> 152.4 | BK27: =SUM(S27:V27) -> 175.441 | BL27: =SUM(W27:Z27) -> 222.237 | BM27: =SUM(AA27:AD27) -> 272.208 | BN27: =SUM(AE27:AH27) -> 311.926 | BO27: =SUM(AI27:AL27) -> 375.9 | BP27: =SUM(AM27:AP27) -> 439.6 | BQ27: =SUM(AQ27:AT27) -> 461.228 | BR27: =BR26*(1-BR43) -> 535.40236 | BS27: =BS26*(1-BS43) -> 609.33844 | BT27: =BT26*(1-BT43) -> 698.32776 | BU27: =BU26*(1-BU43) -> 794.95 | BV27: =BV26*(1-BV43) -> 898.56922 | BW27: =BW26*(1-BW43) -> 1004.9268 | BX27: =BX26*(1-BX43) -> 1114.7408 | BY27: =BY26*(1-BY43) -> 1226.3854 | ... CA27: =CA26*(1-CA43) -> 1462.8258
B28: GP | C28: =C26-C27 -> 26.8 | D28: =D26-D27 -> 27.4 | E28: =E26-E27 -> 33.5 | F28: =F26-F27 -> 36.4 | G28: =G26-G27 -> 39.9 | H28: =H26-H27 -> 41.5 | I28: =I26-I27 -> 42.9 | J28: =J26-J27 -> 46.6 | ... AX28: =AX26-AX27 -> 321.23998 | BG28: =SUM(C28:F28) -> 124.1 | BH28: =SUM(G28:J28) -> 170.9 | BI28: =SUM(K28:N28) -> 217.2 | BJ28: =SUM(O28:R28) -> 292.5 | BK28: =BK26-BK27 -> 371.962 | BL28: =BL26-BL27 -> 338.175 | BM28: =BM26-BM27 -> 475.382 | BN28: =BN26-BN27 -> 535.207 | BO28: =BO26-BO27 -> 682.62 | BP28: =BP26-BP27 -> 755 | BQ28: =SUM(AQ28:AT28) -> 942.437 | BR28: =BR26-BR27 -> 1111.9895 | BS28: =BS26-BS27 -> 1369.0331 | BT28: =BT26-BT27 -> 1652.9442 | BU28: =BU26-BU27 -> 1946.2569 | BV28: =BV26-BV27 -> 2254.3052 | BW28: =BW26-BW27 -> 2584.0975 | BX28: =BX26-BX27 -> 2938.8621 | BY28: =BY26-BY27 -> 3315.7827 | ... CA28: =CA26-CA27 -> 4163.4272
B29: R&D | C29: 3.2 | D29: 4.8 | E29: 4.6 | F29: 5.5 | G29: 5 | H29: 6.3 | I29: 6.5 | J29: 6.1 | K29: 7 | L29: 8.1 | M29: 8.1 | N29: 8.4 | O29: 8 | P29: 8.2 | Q29: 39.9 | R29: 10.9 | S29: 11.667 | T29: 13.462 | U29: 13.733 | V29: =51.723-SUM(S29:U29) -> 12.861 | W29: 12.946 | X29: 22.725 | Y29: 34.923 | Z29: =90.049-SUM(W29:Y29) -> 19.455 | AA29: 18.076 | AB29: 17.738 | AC29: 16.73 | AD29: =104.552-SUM(AA29:AC29) -> 52.008 | AE29: 20.56 | AF29: 19.559 | AG29: 21.32 | AH29: =79.407-SUM(AE29:AG29) -> 17.968 | AI29: 19.98 | AJ29: 21.5 | AK29: 21 | AL29: =84.4-SUM(AI29:AK29) -> 21.92 | AM29: 24.6 | AN29: 24.9 | AO29: 25.2 | AP29: =94.8-SUM(AM29:AO29) -> 20.1 | AQ29: 22.077 | AR29: 23.218 | AS29: 22.677 | AT29: =89.766-SUM(AQ29:AS29) -> 21.794 | AU29: 22.382 | AV29: 25.396 | AW29: =AW26*AW44 -> 31.722769 | AX29: =AX26*AX44 -> 34.418569 | BG29: =SUM(C29:F29) -> 18.1 | BH29: =SUM(G29:J29) -> 23.9 | BI29: =SUM(K29:N29) -> 31.6 | BJ29: =SUM(O29:R29) -> 67 | BK29: =SUM(S29:V29) -> 51.723 | BL29: =SUM(W29:Z29) -> 90.049 | BM29: =SUM(AA29:AD29) -> 104.552 | BN29: =SUM(AE29:AH29) -> 79.407 | BO29: =SUM(AI29:AL29) -> 84.4 | BP29: =SUM(AM29:AP29) -> 94.8 | BQ29: =SUM(AQ29:AT29) -> 89.766 | BR29: =BR26*BR44 -> 120.25961 | BS29: =BS26*BS44 -> 148.37787 | BT29: =BT26*BT44 -> 188.10175 | BU29: =BU26*BU44 -> 233.00259 | BV29: =BV26*BV44 -> 283.7587 | BW29: =BW26*BW44 -> 340.9573 | BX29: =BX26*BX44 -> 374.95827 | BY29: =BY26*BY44 -> 408.79513 | ... CA29: =CA26*CA44 -> 506.36277
B30: SG&A | C30: 19.5 | D30: 26.4 | E30: 26.8 | F30: 29.2 | G30: 33.1 | H30: 35.9 | I30: 37.7 | J30: 41.6 | K30: 42.7 | L30: 44.2 | M30: 46 | N30: 51.5 | O30: 54.5 | P30: 54.8 | Q30: 55.9 | R30: 61.2 | S30: 61.091 | T30: 67.665 | U30: 69.289 | V30: =272.733-SUM(S30:U30) -> 74.688 | W30: 74.453 | X30: 59.8 | Y30: 76.2 | Z30: =287.068-SUM(W30:Y30) -> 76.615 | AA30: 79.798 | AB30: 90.63 | AC30: 94.397 | AD30: =378.331-SUM(AA30:AC30) -> 113.506 | AE30: 110.9 | AF30: 114.615 | AG30: 108.57 | AH30: =449.718-SUM(AE30:AG30) -> 115.633 | AI30: 123.07 | AJ30: 127.4 | AK30: 125.9 | AL30: =506.4-SUM(AI30:AK30) -> 130.03 | AM30: 144.4 | AN30: 141.9 | AO30: 139.7 | AP30: =574-SUM(AM30:AO30) -> 148 | AQ30: 153.456 | AR30: 159.964 | AS30: 168.901 | AT30: =663.422-SUM(AQ30:AS30) -> 181.101 | AU30: 192.795 | AV30: 198.509 | AW30: =AW26*AW45 -> 195.41226 | AX30: =AX26*AX45 -> 211.10056 | BG30: =SUM(C30:F30) -> 101.9 | BH30: =SUM(G30:J30) -> 148.3 | BI30: =SUM(K30:N30) -> 184.4 | BJ30: =SUM(O30:R30) -> 226.4 | BK30: =SUM(S30:V30) -> 272.733 | BL30: =SUM(W30:Z30) -> 287.068 | BM30: =SUM(AA30:AD30) -> 378.331 | BN30: =SUM(AE30:AH30) -> 449.718 | BO30: =SUM(AI30:AL30) -> 506.4 | BP30: =SUM(AM30:AP30) -> 574 | BQ30: =SUM(AQ30:AT30) -> 663.422 | BR30: =BR26*BR45 -> 766.03722 | BS30: =BS26*BS45 -> 895.21313 | BT30: =BT26*BT45 -> 1048.6673 | BU30: =BU26*BU45 -> 1203.3898 | BV30: =BV26*BV45 -> 1371.5004 | BW30: =BW26*BW45 -> 1552.253 | BX30: =BX26*BX45 -> 1734.9421 | BY30: =BY26*BY45 -> 1930.4215 | ... CA30: =CA26*CA45 -> 2306.7637
B31: Acquired In-Process R&D | C31: 0 | D31: 0 | E31: 0 | F31: 0 | G31: 0 | H31: 0 | I31: 0 | J31: 0 | K31: 0 | L31: 0 | M31: 0 | N31: 0 | O31: 0 | P31: 0 | Q31: 0 | R31: 0 | S31: 0 | T31: 0 | U31: 0 | V31: =0-SUM(S31:U31) -> 0 | W31: 0 | X31: 0 | Y31: 0 | Z31: =0-SUM(W31:Y31) -> 0 | AA31: 0 | AB31: 0 | AC31: 0 | AD31: =0-SUM(AA31:AC31) -> 0 | AE31: 0 | AF31: 0 | AG31: 0 | AH31: =0-SUM(AE31:AG31) -> 0 | AI31: 0 | AJ31: 0 | AK31: 18.2 | AL31: =18.2-SUM(AI31:AK31) -> 0 | AM31: 0 | AN31: 0 | AO31: 0 | AP31: =0-SUM(AM31:AO31) -> 0 | AQ31: 0 | AR31: 0 | AS31: 0 | AT31: =0-SUM(AQ31:AS31) -> 0 | AU31: 0 | AV31: 0 | AW31: 0 | AX31: 0 | BG31: =SUM(C31:F31) -> 0 | BH31: =SUM(G31:J31) -> 0 | BI31: =SUM(K31:N31) -> 0 | BJ31: =SUM(O31:R31) -> 0 | BK31: =SUM(S31:V31) -> 0 | BL31: =SUM(W31:Z31) -> 0 | BM31: =SUM(AA31:AD31) -> 0 | BN31: =SUM(AE31:AH31) -> 0 | BO31: =SUM(AI31:AL31) -> 18.2 | BP31: =SUM(AM31:AP31) -> 0 | BQ31: =SUM(AQ31:AT31) -> 0 | BR31: 0 | BS31: 0 | BT31: 0 | BU31: 0 | BV31: 0 | BW31: 0 | BX31: 0 | BY31: 0 | BZ31: 0 | CA31: 0
B32: Impairment Charges | C32: 0.1 | D32: =31.2-SUM(D29:D31) -> 0 | E32: =31.3-SUM(E29:E31) -> -0.1 | F32: =34.6-SUM(F29:F31) -> -0.1 | G32: =38.1-SUM(G29:G31) -> 0 | H32: 0 | I32: 0.1 | J32: 0.1 | K32: 0 | L32: -0.1 | M32: 0 | N32: 0 | O32: 0.1 | P32: -0.1 | Q32: 0 | R32: -0.1 | S32: 0 | T32: 0 | U32: 0 | V32: =0-SUM(S32:U32) -> 0 | W32: 0 | X32: 0 | Y32: 0 | Z32: =0-SUM(W32:Y32) -> 0 | AA32: 0 | AB32: 0 | AC32: 0 | AD32: =0-SUM(AA32:AC32) -> 0 | AE32: 0 | AF32: 0 | AG32: 0 | AH32: =0-SUM(AE32:AG32) -> 0 | AI32: 0 | AJ32: 0 | AK32: 0 | AL32: =0-SUM(AI32:AK32) -> 0 | AM32: 0 | AN32: 76.9 | AO32: 0 | AP32: =76.94-SUM(AM32:AO32) -> 0.04 | AQ32: 0 | AR32: 0 | AS32: 0 | AT32: =0-SUM(AQ32:AS32) -> 0 | AU32: 0 | AV32: 0 | AW32: 0 | AX32: 0 | BG32: =SUM(C32:F32) -> -0.1 | BH32: =SUM(G32:J32) -> 0.2 | BI32: =SUM(K32:N32) -> -0.1 | BJ32: =SUM(O32:R32) -> -0.1 | BK32: =SUM(S32:V32) -> 0 | BL32: =SUM(W32:Z32) -> 0 | BM32: =SUM(AA32:AD32) -> 0 | BN32: =SUM(AE32:AH32) -> 0 | BO32: =SUM(AI32:AL32) -> 0 | BP32: =SUM(AM32:AP32) -> 76.94 | BQ32: =SUM(AQ32:AT32) -> 0 | BR32: 0 | BS32: 0 | BT32: 0 | BU32: 0 | BV32: 0 | BW32: 0 | BX32: 0 | BY32: 0 | BZ32: 0 | CA32: 0
B33: Operating Income | C33: =C28-SUM(C29:C32) -> 4 | D33: =D28-SUM(D29:D32) -> -3.8 | E33: =E28-SUM(E29:E32) -> 2.2 | F33: =F28-SUM(F29:F32) -> 1.8 | G33: =G28-SUM(G29:G32) -> 1.8 | H33: =H28-SUM(H29:H32) -> -0.7 | I33: =I28-SUM(I29:I32) -> -1.4 | J33: =J28-SUM(J29:J32) -> -1.2 | ... T33: =T28-SUM(T29:T32) -> 12.801 | U33: 12.976 | V33: =V28-SUM(V29:V32) -> 10.577 | W33: =W28-SUM(W29:W32) -> 0.601 | X33: =X28-SUM(X29:X32) -> -17.625 | Y33: =Y28-SUM(Y29:Y32) -> -20.176 | Z33: =Z28-SUM(Z29:Z32) -> -1.742 | AA33: =AA28-SUM(AA29:AA32) -> 13.459 | AB33: =AB28-SUM(AB29:AB32) -> 10.332 | AC33: =AC28-SUM(AC29:AC32) -> 8.773 | ... AX33: =AX28-SUM(AX29:AX32) -> 75.720853 | BG33: =SUM(C33:F33) -> 4.2 | BH33: =SUM(G33:J33) -> -1.5 | BI33: =SUM(K33:N33) -> 1.3 | BJ33: =SUM(O33:R33) -> -0.8 | BK33: =BK28-SUM(BK29:BK32) -> 47.506 | BL33: =BL28-SUM(BL29:BL32) -> -38.942 | BM33: =BM28-SUM(BM29:BM32) -> -7.501 | BN33: =BN28-SUM(BN29:BN32) -> 6.082 | BO33: =BO28-SUM(BO29:BO32) -> 73.62 | BP33: =BP28-SUM(BP29:BP32) -> 9.26 | BQ33: =SUM(AQ33:AT33) -> 189.249 | BR33: =BR28-SUM(BR29:BR32) -> 225.69269 | BS33: =BS28-SUM(BS29:BS32) -> 325.44212 | BT33: =BT28-SUM(BT29:BT32) -> 416.17513 | BU33: =BU28-SUM(BU29:BU32) -> 509.86449 | BV33: =BV28-SUM(BV29:BV32) -> 599.04615 | BW33: =BW28-SUM(BW29:BW32) -> 690.88717 | BX33: =BX28-SUM(BX29:BX32) -> 828.9618 | BY33: =BY28-SUM(BY29:BY32) -> 976.56615 | ... CA33: =CA28-SUM(CA29:CA32) -> 1350.3007
B34: Interest and Other Income, net | C34: 0.3 | D34: -0.4 | E34: -0.1 | F34: 0.1 | G34: 0.3 | H34: 0.3 | I34: 0.3 | J34: -0.4 | K34: 0.3 | L34: 0.4 | M34: 0.6 | N34: 0 | O34: 0.5 | P34: 0.4 | Q34: 0.9 | R34: 0.7 | S34: =0.733+0.024 -> 0.757 | T34: =0.784-0.071 -> 0.713 | U34: =0.759-0.772 -> -0.013 | V34: =2.854-0.227-SUM(S34:U34) -> 1.17 | W34: =0.299-1.555 -> -1.256 | X34: =0.108+0.508 -> 0.616 | Y34: =0.413+0.014 -> 0.427 | Z34: =1.267-0.243-SUM(W34:Y34) -> 1.237 | AA34: =0.48-1.476 -> -0.996 | AB34: =0.299-0.408 -> -0.109 | AC34: =0.138-1.137 -> -0.999 | AD34: =0.938-3.939-SUM(AA34:AC34) -> -0.897 | AE34: =-0.041-1.01 -> -1.051 | AF34: =-0.07-0.9 -> -0.97 | AG34: =-0.04-2.35 -> -2.39 | AH34: =0.137-2.327-SUM(AE34:AG34) -> 2.221 | AI34: 0.644 | AJ34: 1.6 | AK34: 0.7 | AL34: =6.09-SUM(AI34:AK34) -> 3.146 | AM34: 2.5 | AN34: 3.1 | AO34: 4.4 | AP34: =11.59-SUM(AM34:AO34) -> 1.59 | AQ34: 3.508 | AR34: 4.482 | AS34: 3.487 | AT34: =15.876-SUM(AQ34:AS34) -> 4.399 | AU34: 3.454 | AV34: 5.148 | AW34: =AV50*0.045 -> 9.237195 | AX34: =AW50*0.045 -> 11.409795 | BG34: =SUM(C34:F34) -> -0.1 | BH34: =SUM(G34:J34) -> 0.5 | BI34: =SUM(K34:N34) -> 1.3 | BJ34: =SUM(O34:R34) -> 2.5 | BK34: =SUM(S34:V34) -> 2.627 | BL34: =SUM(W34:Z34) -> 1.024 | BM34: =SUM(AA34:AD34) -> -3.001 | BN34: =SUM(AE34:AH34) -> -2.19 | BO34: =SUM(AI34:AL34) -> 6.09 | BP34: =SUM(AM34:AP34) -> 11.59 | BQ34: =SUM(AQ34:AT34) -> 15.876 | BR34: =BQ50*$CA$53 -> 30.743405 | BS34: =BR50*$CA$53 -> 64.490395 | BT34: =BS50*$CA$53 -> 114.52264 | BU34: =BT50*$CA$53 -> 181.74347 | BV34: =BU50*$CA$53 -> 269.34599 | BW34: =BV50*$CA$53 -> 379.34088 | BX34: =BW50*$CA$53 -> 514.90132 | BY34: =BX50*$CA$53 -> 685.12174 | ... CA34: =BZ50*$CA$53 -> 1153.4326
B35: Pretax Income | C35: =C33+C34 -> 4.3 | D35: =D33+D34 -> -4.2 | E35: =E33+E34 -> 2.1 | F35: =F33+F34 -> 1.9 | G35: =G33+G34 -> 2.1 | H35: =H33+H34 -> -0.4 | I35: =I33+I34 -> -1.1 | J35: =J33+J34 -> -1.6 | ... AX35: =AX33+AX34 -> 87.130648 | BG35: =SUM(C35:F35) -> 4.1 | BH35: =SUM(G35:J35) -> -1 | BI35: =SUM(K35:N35) -> 2.6 | BJ35: =SUM(O35:R35) -> 1.7 | BK35: =BK33+BK34 -> 50.133 | BL35: =BL33+BL34 -> -37.918 | BM35: =BM33+BM34 -> -10.502 | BN35: =BN33+BN34 -> 3.892 | BO35: =BO33+BO34 -> 79.71 | BP35: =BP33+BP34 -> 20.85 | BQ35: =SUM(AQ35:AT35) -> 205.125 | BR35: =BR33+BR34 -> 256.43609 | BS35: =BS33+BS34 -> 389.93251 | BT35: =BT33+BT34 -> 530.69777 | BU35: =BU33+BU34 -> 691.60795 | BV35: =BV33+BV34 -> 868.39214 | BW35: =BW33+BW34 -> 1070.228 | BX35: =BX33+BX34 -> 1343.8631 | BY35: =BY33+BY34 -> 1661.6879 | ... CA35: =CA33+CA34 -> 2503.7333
B36: Tax Expense (Benefit) | C36: 1.7 | D36: -1.5 | E36: 1.2 | F36: 0.2 | G36: -0.2 | H36: -3.4 | I36: -13 | J36: 0.9 | K36: 1.4 | L36: 0.5 | M36: 0.5 | N36: -5.9 | O36: -1.9 | P36: -4.9 | Q36: 1.6 | R36: 0.9 | S36: 1.455 | T36: -2.735 | U36: 1.963 | V36: =3.131-SUM(S36:U36) -> 2.448 | W36: -1.634 | X36: -4.129 | Y36: -9.855 | Z36: =-18.761-SUM(W36:Y36) -> -3.143 | AA36: 1.541 | AB36: 1.9 | AC36: -0.249 | AD36: =-13.125-SUM(AA36:AC36) -> -16.317 | AE36: -5.183 | AF36: 2.52 | AG36: 5.3 | AH36: =5.894-SUM(AE36:AG36) -> 3.257 | AI36: 0.09 | AJ36: 0.5 | AK36: 4.09 | AL36: =-11.3-SUM(AI36:AK36) -> -15.98 | AM36: 3.6 | AN36: -17.6 | AO36: 10.3 | AP36: =6.86-SUM(AM36:AO36) -> 10.56 | AQ36: 4.635 | AR36: 0.04 | AS36: 6.474 | AT36: =27.438-SUM(AQ36:AS36) -> 16.289 | AU36: 9.104 | AV36: 11.376 | AW36: =AW35*AW47 -> 17.203444 | AX36: =AX35*AX47 -> 20.040049 | BG36: =SUM(C36:F36) -> 1.6 | BH36: =SUM(G36:J36) -> -15.7 | BI36: =SUM(K36:N36) -> -3.5 | BJ36: =SUM(O36:R36) -> -4.3 | BK36: =SUM(S36:V36) -> 3.131 | BL36: =SUM(W36:Z36) -> -18.761 | BM36: =SUM(AA36:AD36) -> -13.125 | BN36: =SUM(AE36:AH36) -> 5.894 | BO36: =SUM(AI36:AL36) -> -11.3 | BP36: =SUM(AM36:AP36) -> 6.86 | BQ36: =SUM(AQ36:AT36) -> 27.438 | BR36: =BR35*BR47 -> 51.287219 | BS36: =BS35*BS47 -> 85.785153 | BT36: =BT35*BT47 -> 122.06049 | BU36: =BU35*BU47 -> 159.06983 | BV36: =BV35*BV47 -> 199.73019 | BW36: =BW35*BW47 -> 246.15245 | BX36: =BX35*BX47 -> 309.08852 | BY36: =BY35*BY47 -> 382.18821 | ... CA36: =CA35*CA47 -> 575.85867
B37: Consolidated Net Income | C37: 2.5 | D37: -2.7 | E37: 0.9 | F37: 1.6 | G37: 2.3 | H37: 3 | I37: 11.9 | J37: -2.4 | K37: -3.1 | L37: -1.6 | M37: 0.2 | N37: 9.1 | O37: 5.5 | P37: 13.4 | Q37: -22.4 | R37: 6.5 | S37: =S35-S36 -> 10.454 | T37: =T35-T36 -> 16.249 | U37: =U35-U36 -> 11 | V37: =V35-V36 -> 9.299 | W37: =W35-W36 -> 0.979 | X37: =X35-X36 -> -12.88 | Y37: =Y35-Y36 -> -9.894 | Z37: =Z35-Z36 -> 2.638 | ... AX37: =AX35-AX36 -> 67.090599 | BG37: =SUM(C37:F37) -> 2.3 | BH37: =SUM(G37:J37) -> 14.8 | BI37: =SUM(K37:N37) -> 4.6 | BJ37: =SUM(O37:R37) -> 3 | BK37: =BK35-BK36 -> 47.002 | BL37: =BL35-BL36 -> -19.157 | BM37: =BM35-BM36 -> 2.623 | BN37: =BN35-BN36 -> -2.002 | BO37: =BO35-BO36 -> 91.01 | BP37: =BP35-BP36 -> 13.99 | BQ37: =SUM(AQ37:AT37) -> 177.687 | BR37: =BR35-BR36 -> 205.14887 | BS37: =BS35-BS36 -> 304.14736 | BT37: =BT35-BT36 -> 408.63728 | BU37: =BU35-BU36 -> 532.53812 | BV37: =BV35-BV36 -> 668.66195 | BW37: =BW35-BW36 -> 824.0756 | BX37: =BX35-BX36 -> 1034.7746 | BY37: =BY35-BY36 -> 1279.4997 | ... CA37: =CA35-CA36 -> 1927.8747
B38: Net Income attr to Non-Cont. | C38: 2 | D38: -2.15 | E38: 0.58 | F38: 0.85 | G38: -0.2 | H38: 0 | I38: -0.3 | J38: 0 | K38: 0 | L38: 0 | M38: 0 | N38: 0 | O38: 0 | P38: 0 | Q38: -3.5 | R38: -0.02 | S38: -0.244 | T38: -0.537 | U38: -0.483 | V38: =-1.454-SUM(S38:U38) -> -0.19 | W38: -0.537 | X38: -0.94 | Y38: -1.061 | Z38: =-3.555-SUM(W38:Y38) -> -1.017 | AA38: -0.91 | AB38: -0.932 | AC38: -0.819 | AD38: =-2.641-SUM(AA38:AC38) -> 0.02 | AE38: 0 | AF38: 0 | AG38: 0 | AH38: 0 | AI38: 0 | AJ38: 0 | AK38: 0 | AL38: 0 | AM38: 0 | AN38: 0 | AO38: 0 | AP38: 0 | AQ38: 0 | AR38: 0 | AS38: 0 | AT38: 0 | AU38: 0 | AV38: 0 | AW38: 0 | AX38: 0 | BG38: =SUM(C38:F38) -> 1.28 | BH38: =SUM(G38:J38) -> -0.5 | BI38: =SUM(K38:N38) -> 0 | BJ38: =SUM(O38:R38) -> -3.52 | BK38: =SUM(S38:V38) -> -1.454 | BL38: -3.555 | BM38: -2.661 | BN38: 0 | BO38: 0 | BP38: 0 | BQ38: =SUM(AQ38:AT38) -> 0 | BR38: 0 | BS38: 0 | BT38: 0 | BU38: 0 | BV38: 0 | BW38: 0 | BX38: 0 | BY38: 0 | BZ38: 0 | CA38: 0
B39: Net Income attr to PEN | C39: =C37-C38 -> 0.5 | D39: =D37-D38 -> -0.55 | E39: =E37-E38 -> 0.32 | F39: =F37-F38 -> 0.75 | G39: =G37-G38 -> 2.5 | H39: =H37-H38 -> 3 | I39: =I37-I38 -> 12.2 | J39: =J37-J38 -> -2.4 | ... AV39: =AV37-AV38 -> 34.811 | AW39: 48.28 | AX39: 56.5 | BG39: =SUM(C39:F39) -> 1.02 | BH39: =SUM(G39:J39) -> 15.3 | BI39: =SUM(K39:N39) -> 4.6 | BJ39: =SUM(O39:R39) -> 6.52 | BK39: =BK37-BK38 -> 48.456 | BL39: =BL37-BL38 -> -15.602 | BM39: =BM37-BM38 -> 5.284 | BN39: =BN37-BN38 -> -2.002 | BO39: =BO37-BO38 -> 91.01 | BP39: =BP37-BP38 -> 13.99 | BQ39: =SUM(AQ39:AT39) -> 177.687 | BR39: =BR37-BR38 -> 205.14887 | BS39: =BS37-BS38 -> 304.14736 | BT39: =BT37-BT38 -> 408.63728 | BU39: =BU37-BU38 -> 532.53812 | BV39: =BV37-BV38 -> 668.66195 | BW39: =BW37-BW38 -> 824.0756 | BX39: =BX37-BX38 -> 1034.7746 | BY39: =BY37-BY38 -> 1279.4997 | ... CA39: =CA37-CA38 -> 1927.8747 | CB39: =CA39*(1+$CA$54) -> 1977.0355 | CC39: =CB39*(1+$CA$54) -> 2027.4499 | CD39: =CC39*(1+$CA$54) -> 2079.1499 | CE39: =CD39*(1+$CA$54) -> 2132.1682 | CF39: =CE39*(1+$CA$54) -> 2186.5385 | CG39: =CF39*(1+$CA$54) -> 2242.2952 | CH39: =CG39*(1+$CA$54) -> 2299.4737 | CI39: =CH39*(1+$CA$54) -> 2358.1103 | ... DO39: =DN39*(1+$CA$54) -> 5278.4375
B40: SC | C40: 5 | D40: 5 | E40: 8 | F40: 12 | G40: 30 | H40: 30 | I40: 31 | J40: 30 | K40: 32 | L40: 33 | M40: 33 | N40: 33 | O40: 34 | P40: 34 | Q40: 34 | R40: 34 | S40: 34.507 | T40: 34.694 | U40: 34.84 | V40: 35 | W40: 35 | X40: 35.4 | Y40: 36.207 | Z40: 37.651 | AA40: 36.455 | AB40: 36.523 | AC40: 36.617 | AD40: 36.7 | AE40: 37.646 | AF40: 37.767 | AG40: 37.918 | AH40: 37.841 | AI40: 39.07 | AJ40: 38.15 | AK40: 38.956 | AL40: 38.4 | AM40: 39.3 | AN40: 38.8 | AO40: 38.6 | AP40: 38.63 | AQ40: 38.562 | AR40: 38.834 | AS40: 39.078 | AT40: 38.63 | AU40: 39.275 | AV40: 39.353 | BG40: 12 | BH40: 31 | BI40: 33 | BJ40: 34 | BK40: 34.8 | BL40: 35.5 | BM40: =AD40 -> 36.7 | BN40: =AH40 -> 37.841 | BO40: =AL40 -> 38.4 | BP40: =AP40 -> 38.63 | BQ40: =AVERAGE(AQ40:AT40) -> 38.776 | BR40: =BQ40*1.05 -> 40.7148 | BS40: =BR40*1.05 -> 42.75054 | BT40: =BS40*1.05 -> 44.888067 | BU40: =BT40*1.05 -> 47.13247 | BV40: =BU40*1.05 -> 49.489094 | BW40: =BV40*1.05 -> 51.963549 | BX40: =BW40*1.05 -> 54.561726 | BY40: =BX40*1.05 -> 57.289812 | ... CA40: =BZ40*1.05 -> 63.162018
B41: EPS | C41: =C39/C40 -> 0.1 | D41: =D39/D40 -> -0.11 | E41: =E39/E40 -> 0.04 | F41: =F39/F40 -> 0.0625 | G41: =G39/G40 -> 0.083333333 | H41: =H39/H40 -> 0.1 | I41: =I39/I40 -> 0.39354839 | J41: =J39/J40 -> -0.08 | ... AV41: =AV39/AV40 -> 0.88458313 | BG41: =BG39/BG40 -> 0.085 | BH41: =BH39/BH40 -> 0.49354839 | BI41: =BI39/BI40 -> 0.13939394 | BJ41: =BJ39/BJ40 -> 0.19176471 | BK41: =BK39/BK40 -> 1.3924138 | BL41: =BL39/BL40 -> -0.43949296 | BM41: =BM39/BM40 -> 0.1439782 | BN41: =BN39/BN40 -> -0.052905579 | ... BP41: =BP39/BP40 -> 0.36215377 | BQ41: =SUM(AQ41:AT41) -> 4.5817424 | BR41: =BR39/BR40 -> 5.0386806 | BS41: =BS39/BS40 -> 7.1144683 | BT41: =BT39/BT40 -> 9.1034724 | BU41: =BU39/BU40 -> 11.298753 | BV41: =BV39/BV40 -> 13.511299 | BW41: =BW39/BW40 -> 15.858724 | BX41: =BX39/BX40 -> 18.96521 | BY41: =BY39/BY40 -> 22.333808 | ... CA41: =CA39/CA40 -> 30.52269
B43: Gross Profit Margin | C43: =C28/C26 -> 0.68717949 | D43: =D28/D26 -> 0.64775414 | E43: =E28/E26 -> 0.66468254 | F43: =F28/F26 -> 0.66911765 | G43: =G28/G26 -> 0.68911917 | H43: =H28/H26 -> 0.6374808 | I43: =I28/I26 -> 0.63839286 | J43: =J28/J26 -> 0.6374829 | ... AR43: =AR28/AR26 -> 0.65991074 | AS43: 0.67 | AT43: =AT28/AT26 -> 0.68017178 | AU43: 0.678 | AV43: 0.685 | AW43: 0.692 | AX43: 0.7 | BG43: =BG28/BG26 -> 0.66684578 | BH43: =BH28/BH26 -> 0.6490695 | BI43: =BI28/BI26 -> 0.65068904 | BJ43: =BJ28/BJ26 -> 0.65745111 | BK43: =BK28/BK26 -> 0.67950304 | BL43: =BL28/BL26 -> 0.60343997 | BM43: =BM28/BM26 -> 0.63588598 | BN43: =BN28/BN26 -> 0.63178627 | ... BQ43: =BQ28/BQ26 -> 0.67141163 | BR43: 0.675 | BS43: 0.692 | BT43: 0.703 | BU43: 0.71 | BV43: 0.715 | BW43: 0.72 | BX43: 0.725 | BY43: 0.73 | BZ43: 0.735 | CA43: 0.74
B44: R&D as % of Revenues | C44: =C29/C26 -> 0.082051282 | D44: =D29/D26 -> 0.11347518 | E44: =E29/E26 -> 0.091269841 | F44: =F29/F26 -> 0.10110294 | G44: =G29/G26 -> 0.086355786 | H44: =H29/H26 -> 0.096774194 | I44: =I29/I26 -> 0.09672619 | J44: =J29/J26 -> 0.083447332 | ... AR44: =AR29/AR26 -> 0.068397873 | AS44: 0.068 | AT44: =AT29/AT26 -> 0.056551241 | AU44: 0.073 | AV44: 0.075 | AW44: 0.075 | AX44: 0.075 | BG44: =BG29/BG26 -> 0.097259538 | BH44: =BH29/BH26 -> 0.090770984 | BI44: =BI29/BI26 -> 0.094667466 | BJ44: =BJ29/BJ26 -> 0.15059564 | BK44: =BK29/BK26 -> 0.094487973 | BL44: =BL29/BL26 -> 0.16068357 | BM44: =BM29/BM26 -> 0.13985206 | BN44: =BN29/BN26 -> 0.093736167 | ... BQ44: =BQ29/BQ26 -> 0.063951156 | BR44: 0.073 | BS44: 0.075 | BT44: 0.08 | BU44: 0.085 | BV44: 0.09 | BW44: 0.095 | BX44: 0.0925 | BY44: 0.09 | BZ44: 0.09 | CA44: 0.09
B45: SG&A as % of Revenues | C45: =C30/C26 -> 0.5 | D45: =D30/D26 -> 0.62411348 | E45: =E30/E26 -> 0.53174603 | F45: =F30/F26 -> 0.53676471 | G45: =G30/G26 -> 0.5716753 | H45: =H30/H26 -> 0.55145929 | I45: =I30/I26 -> 0.5610119 | J45: =J30/J26 -> 0.56908345 | ... AR45: =AR30/AR26 -> 0.47123772 | AS45: 0.47 | AT45: =AT30/AT26 -> 0.46992229 | AU45: 0.466 | AV45: 0.464 | AW45: 0.462 | AX45: 0.46 | BG45: =BG30/BG26 -> 0.54755508 | BH45: =BH30/BH26 -> 0.56323585 | BI45: =BI30/BI26 -> 0.5524266 | BJ45: =BJ30/BJ26 -> 0.5088784 | BK45: =BK30/BK26 -> 0.49823074 | BL45: =BL30/BL26 -> 0.51224456 | BM45: =BM30/BM26 -> 0.5060675 | BN45: =BN30/BN26 -> 0.5308706 | ... BQ45: =BQ30/BQ26 -> 0.47263556 | BR45: 0.465 | BS45: 0.4525 | BT45: 0.446 | BU45: 0.439 | BV45: 0.435 | BW45: 0.4325 | BX45: 0.428 | BY45: 0.425 | BZ45: 0.42 | CA45: 0.41
B46: Operating Profit Margin | C46: =C33/C26 -> 0.1025641 | D46: =D33/D26 -> -0.089834515 | E46: =E33/E26 -> 0.043650794 | F46: =F33/F26 -> 0.033088235 | G46: =G33/G26 -> 0.031088083 | H46: =H33/H26 -> -0.010752688 | I46: =I33/I26 -> -0.020833333 | J46: =J33/J26 -> -0.016415869 | ... AX46: =AX33/AX26 -> 0.165 | BG46: =BG33/BG26 -> 0.022568512 | BH46: =BH33/BH26 -> -0.0056969237 | BI46: =BI33/BI26 -> 0.0038945476 | BJ46: =BJ33/BJ26 -> -0.0017981569 | BK46: =BK33/BK26 -> 0.086784325 | BL46: =BL33/BL26 -> -0.069488162 | BM46: =BM33/BM26 -> -0.010033575 | BN46: =BN33/BN26 -> 0.0071795102 | ... CA46: =CA33/CA26 -> 0.24
B47: Effective Tax Rate | C47: =C36/C35 -> 0.39534884 | D47: =D36/D35 -> 0.35714286 | E47: =E36/E35 -> 0.57142857 | F47: =F36/F35 -> 0.10526316 | G47: =G36/G35 -> -0.095238095 | H47: =H36/H35 -> 8.5 | I47: =I36/I35 -> 11.818182 | J47: =J36/J35 -> -0.5625 | ... AR47: =AR36/AR35 -> 0.00088280733 | AS47: 0.2 | AT47: =AT36/AT35 -> 0.25598755 | AU47: 0.23 | AV47: 0.23 | AW47: 0.23 | AX47: 0.23 | BG47: =BG36/BG35 -> 0.3902439 | BH47: =BH36/BH35 -> 15.7 | BI47: =BI36/BI35 -> -1.3461538 | BJ47: =BJ36/BJ35 -> -2.5294118 | BK47: =BK36/BK35 -> 0.062453873 | BL47: =BL36/BL35 -> 0.49477821 | BM47: =BM36/BM35 -> 1.249762 | BN47: =BN36/BN35 -> 1.5143885 | ... BQ47: =BQ36/BQ35 -> 0.13376234 | BR47: 0.2 | BS47: 0.22 | BT47: 0.23 | BU47: 0.23 | BV47: 0.23 | BW47: 0.23 | BX47: 0.23 | BY47: 0.23 | BZ47: 0.23 | CA47: 0.23
B48: Net Profit Margin | C48: =C37/C26 -> 0.064102564 | D48: =D37/D26 -> -0.063829787 | E48: =E37/E26 -> 0.017857143 | F48: =F37/F26 -> 0.029411765 | G48: =G37/G26 -> 0.039723661 | H48: =H37/H26 -> 0.046082949 | I48: =I37/I26 -> 0.17708333 | J48: =J37/J26 -> -0.032831737 | ... AR48: =AR37/AR26 -> 0.13336083 | AS48: =AS39/AS26 -> 0.12927245 | AT48: =AT37/AT26 -> 0.12284599 | AU48: =AU39/AU26 -> 0.086946776 | AV48: =AV39/AV26 -> 0.089248448 | AW48: =AW39/AW26 -> 0.11414514 | AX48: =AX39/AX26 -> 0.12311668 | BG48: =BG39/BG26 -> 0.0054809242 | BH48: =BH39/BH26 -> 0.058108621 | BI48: =BI39/BI26 -> 0.013780707 | BJ48: =BJ39/BJ26 -> 0.014654979 | BK48: =BK39/BK26 -> 0.088519793 | BL48: =BL39/BL26 -> -0.027840232 | BM48: =BM39/BM26 -> 0.0070680453 | BN48: =BN39/BN26 -> -0.0023632653 | ... CA48: =CA39/CA26 -> 0.34265695
B50: Cash & C.E.s | S50: 95.606 | T50: 77.261 | U50: 111.581 | V50: 72.779 | W50: 72.456 | X50: 134.381 | Y50: 80.115 | Z50: 69.67 | AA50: 55.632 | AB50: 82.277 | AC50: 66.29 | AD50: 59.379 | AE50: 68.163 | AF50: 58.234 | AG50: 54.844 | AH50: 69.858 | AI50: 94.688 | AJ50: 114.167 | AK50: 100.757 | AL50: 167.486 | AM50: 223.114 | AN50: 288.332 | AO50: 280.476 | AP50: 324.4 | AQ50: 376.054 | AR50: 421.768 | AS50: 321.029 | AT50: 186.89 | AU50: 241.289 | AV50: 205.271 | AW50: =AV50+AW39 -> 253.551 | AX50: =AW50+AX39 -> 310.051 | BK50: =V50 -> 72.779 | BL50: =Z50 -> 69.67 | BM50: =AD50 -> 59.379 | BN50: =AH50 -> 69.858 | BO50: =AL50 -> 167.486 | BP50: =AP50 -> 324.4 | BQ50: 186.89 | BR50: =BQ50+BR39 -> 392.03887 | BS50: =BR50+BS39 -> 696.18624 | BT50: =BS50+BT39 -> 1104.8235 | BU50: =BT50+BU39 -> 1637.3616 | BV50: =BU50+BV39 -> 2306.0236 | BW50: =BV50+BW39 -> 3130.0992 | BX50: =BW50+BX39 -> 4164.8738 | BY50: =BX50+BY39 -> 5444.3735 | ... CA50: =BZ50+CA39 -> 8939.6231
B51: Marketable Investments | S51: 99.241 | T51: 109.996 | U51: 82.864 | V51: 116.61 | W51: 95.766 | X51: 143.914 | Y51: 188.611 | Z51: 195.162 | AA51: 186.977 | AB51: 156.722 | AC51: 200.637 | AD51: 195.496 | AE51: 172.178 | AF51: 146.135 | AG51: 129.583 | AH51: 118.172 | AI51: 104.409 | AJ51: 106.896 | AK51: 148.098 | AL51: 121.701 | AM51: 90.36 | AN51: 51.363 | AO51: 10.548 | AP51: 15.727 | AQ51: 2.794 | AR51: 2.795 | AS51: 149.267 | AT51: 357.919 | AU51: 374.371 | AV51: 453.524 | BK51: =V51 -> 116.61 | BL51: =Z51 -> 195.162 | BM51: =AD51 -> 195.496 | BN51: =AH51 -> 118.172 | BO51: =AL51 -> 121.701 | BP51: =AP51 -> 15.727 | BQ51: 357.919
B52: A/R | S52: 94.679 | T52: 99.011 | U52: 101.828 | V52: 105.901 | W52: 103.963 | X52: 97.613 | Y52: 112.817 | Z52: 114.608 | AA52: 126.415 | AB52: 136.61 | AC52: 120.074 | AD52: 133.94 | AE52: 143.417 | AF52: 187.389 | AG52: 189.006 | AH52: 203.384 | AI52: 207.364 | AJ52: 208.965 | AK52: 206.615 | AL52: 201.768 | AM52: 191.989 | AN52: 200.831 | AO52: 176.051 | AP52: 167.667 | AQ52: 167.981 | AR52: 175.536 | AS52: 183.43 | AT52: 190.02 | AU52: 183.295 | AV52: 190.407 | BK52: =V52 -> 105.901 | BL52: =Z52 -> 114.608 | BM52: =AD52 -> 133.94 | BN52: =AH52 -> 203.384 | BO52: =AL52 -> 201.768 | BP52: =AP52 -> 167.667 | BQ52: 190.02
B53: Inventories | S53: 121.691 | T53: 132.735 | U53: 140.359 | V53: 152.992 | W53: 166.152 | X53: 183.442 | Y53: 191.547 | Z53: 219.527 | AA53: 245.321 | AB53: 254.977 | AC53: 258.316 | AD53: 263.504 | AE53: 274.349 | AF53: 295.883 | AG53: 320.304 | AH53: 334.006 | AI53: 344.042 | AJ53: 358.77 | AK53: 374.245 | AL53: 388.023 | AM53: 398.366 | AN53: 373.799 | AO53: 393.413 | AP53: 406.737 | AQ53: 415.863 | AR53: 427.628 | AS53: 432.365 | AT53: 431.549 | AU53: 438.539 | AV53: 442.65 | BK53: =V53 -> 152.992 | BL53: =Z53 -> 219.527 | BM53: =AD53 -> 263.504 | BN53: =AH53 -> 334.006 | BO53: =AL53 -> 388.023 | BP53: =AP53 -> 406.737 | BQ53: 431.549 | BS53: Invested Capital | BV53: Avg. (2023-2024) | BX53: Projected ROIC: | BZ53: ROIC | CA53: 0.1645 | CD53: Preface:
B54: Prepaid Expenses | S54: 11.869 | T54: 15.601 | U54: 14.702 | V54: 14.852 | W54: 15.403 | X54: 16.545 | Y54: 17.109 | Z54: 18.735 | AA54: 20.782 | AB54: 22.526 | AC54: 22.67 | AD54: 29.155 | AE54: 32.219 | AF54: 30.32 | AG54: 29.888 | AH54: 30.279 | AI54: 35.987 | AJ54: 39.078 | AK54: 38.761 | AL54: 36.424 | AM54: 31.194 | AN54: 29.47 | AO54: 31.265 | AP54: 36.589 | AQ54: 37.017 | AR54: 37.757 | AS54: 55.429 | AT54: 50.298 | AU54: 37.912 | AV54: 52.27 | BK54: =V54 -> 14.852 | BL54: =Z54 -> 18.735 | BM54: =AD54 -> 29.155 | BN54: =AH54 -> 30.279 | BO54: =AL54 -> 36.424 | BP54: =AP54 -> 36.589 | BQ54: 50.298 | BS54: 2024 | BT54: 2025 | BV54: 2024-2025 | BX54: 2025 | BZ54: Terminal | CA54: 0.0255 | CE54: I am treating this as an exercise to improve my excel modeling skills, to become more comfortable with researching public companies using a variety of professional resources, and to begin developing a deeper understanding of The Business's products/markets, operations and current financial standing
B55: PP&E | S55: 35.38 | T55: 37.94 | U55: 45.625 | V55: 51.812 | W55: 58.698 | X55: 62.188 | Y55: 64.906 | Z55: 48.169 | AA55: 50.314 | AB55: 50.854 | AC55: 56.632 | AD55: 58.856 | AE55: 60.327 | AF55: 63.458 | AG55: 64.082 | AH55: 65.015 | AI55: 65.224 | AJ55: 65.958 | AK55: 65.632 | AL55: 72.691 | AM55: 75.744 | AN55: 57.709 | AO55: 59.919 | AP55: 62.641 | AQ55: 72.465 | AR55: 84.825 | AS55: 97.73 | AT55: 117.436 | AU55: 134.059 | AV55: 146.718 | BK55: =V55 -> 51.812 | BL55: =Z55 -> 48.169 | BM55: =AD55 -> 58.856 | BN55: =AH55 -> 65.015 | BO55: =AL55 -> 72.691 | BP55: =AP55 -> 62.641 | BQ55: 117.436 | BS55: =SUM(BP50:BP53)-BP64+BP56+BP58+BP57 -> 1095.523 | BT55: =SUM(BQ50:BQ53)-BQ64+BQ56+BQ58+BQ57 -> 1337.387 | BV55: =AVERAGE(BS55:BS55) -> 1095.523 | BX55: =AVERAGE(BR33)*(1-BR47) -> 180.55415 | BZ55: RFR (10-year yield) | CA55: =BV64 -> 0.0511 | CE55: I understand that to accurately value a firm's common stock, the analyst must derive an NPV from a series of discounted cash flows, not net income (which adheres to GAAP and includes non-cash expenses such as D&A, and does not consider the firm's future cash outflows such as CapEx investment demand or ΔNWC)
B56: Operating Leases | S56: 42.376 | T56: 42.476 | U56: 41.817 | V56: 43.717 | W56: 43.168 | X56: 42.669 | Y56: 41.778 | Z56: 41.192 | AA56: 40.691 | AB56: 92.791 | AC56: 133.552 | AD56: 131.955 | AE56: 176.892 | AF56: 177.423 | AG56: 174.684 | AH56: 192.636 | AI56: 189.839 | AJ56: 187.494 | AK56: 184.52 | AL56: 188.756 | AM56: 185.845 | AN56: 183.316 | AO56: 180.923 | AP56: 177.787 | AQ56: 175.331 | AR56: 174.059 | AS56: 170.715 | AT56: 173.587 | AU56: 170.273 | AV56: 167.194 | BK56: =V56 -> 43.717 | BL56: =Z56 -> 41.192 | BM56: =AD56 -> 131.955 | BN56: =AH56 -> 192.636 | BO56: =AL56 -> 188.756 | BP56: =AP56 -> 177.787 | BQ56: 173.587 | BX56: =BX55/BV55 -> 0.16481092 | BZ56: ERP (Avg. market return - (less) RFR) | CA56: =10.1%-CA55 -> 0.0499 | CE56: I am discounting net income under the somewhat-flawed assumption that in the long run, net income and FCF converge (as CapEx "switches" from investment to maintenance and D&A roughly balances with the period's CapEx spend)
B57: Financing Leases | T57: 0 | U57: 0 | V57: 39.924 | W57: 39.287 | X57: 37.927 | Y57: 38.798 | Z57: 38.065 | AA57: 37.697 | AB57: 37.031 | AC57: 36.845 | AD57: 36.276 | AE57: 35.55 | AF57: 34.743 | AG57: 34.114 | AH57: 33.323 | AI57: 32.569 | AJ57: 31.751 | AK57: 31.364 | AL57: 31.092 | AM57: 30.234 | AN57: 29.366 | AO57: 28.888 | AP57: 28.018 | AQ57: 27.126 | AR57: 27.606 | AS57: 26.79 | AT57: 25.972 | AU57: 25.209 | AV57: 24.357 | BK57: =V57 -> 39.924 | BL57: =Z57 -> 38.065 | BM57: =AD57 -> 36.276 | BN57: =AH57 -> 33.323 | BO57: =AL57 -> 31.092 | BP57: =AP57 -> 28.018 | BQ57: 25.972 | BS57: Capital Structure | BZ57: Equity β (1-year avg.) | CA57: ='Notes | Analysis'!T240 -> 0.76850681 | CD57: Assumptions:
B58: Intangible Assets, net | S58: 26.813 | T58: 26.031 | U58: 25.494 | V58: 25.407 | W58: 25.024 | X58: 10.645 | Y58: 10.64 | Z58: 10.639 | AA58: 10.097 | AB58: 9.895 | AC58: 9.49 | AD58: 90.618 | AE58: 88.472 | AF58: 86.162 | AG58: 83.36 | AH58: 81.161 | AI58: 78.669 | AJ58: 76.116 | AK58: 73.452 | AL58: 71.056 | AM58: 68.421 | AN58: 6.955 | AO58: 6.92 | AP58: 6.513 | AQ58: 6.469 | AR58: 6.552 | AS58: 6.368 | AT58: 6.186 | AU58: 5.946 | AV58: 5.742 | BK58: =V58 -> 25.407 | BL58: =Z58 -> 10.639 | BM58: =AD58 -> 90.618 | BN58: =AH58 -> 81.161 | BO58: =AL58 -> 71.056 | BP58: =AP58 -> 6.513 | BQ58: 6.186 | BS58: Mkt Cap | BV58: ='Main | Overview'!C5 -> 12569.424 | BZ58: Discount (Cost of Equity) | CA58: =+CA55+(CA56*CA57) -> 0.08944849 | CE58: Revenue growth continues, with sequential Thrombectomy revenues remaining strong into the terminal period
B59: Goodwill | S59: 7.659 | T59: 7.765 | U59: 7.452 | V59: 7.656 | W59: 7.509 | X59: 7.665 | Y59: 8.004 | Z59: 8.372 | AA59: 8.006 | AB59: 8.109 | AC59: 7.911 | AD59: 166.388 | AE59: 166.232 | AF59: 165.779 | AG59: 165.426 | AH59: 166.046 | AI59: 166.161 | AJ59: 166.166 | AK59: 165.954 | AL59: 166.27 | AM59: 166.103 | AN59: 166.05 | AO59: 166.355 | AP59: 165.826 | AQ59: 166.123 | AR59: 166.752 | AS59: 166.748 | AT59: 166.75 | AU59: 166.589 | AV59: 166.523 | BK59: =V59 -> 7.656 | BL59: =Z59 -> 8.372 | BM59: =AD59 -> 166.388 | BN59: =AH59 -> 166.046 | BO59: =AL59 -> 166.27 | BP59: =AP59 -> 165.826 | BQ59: 166.75 | BS59: Debt to Ttl Mkt Cap | BV59: ='Main | Overview'!C7/('Main | Overview'!C7+BV58) -> 0 | CE59: Margins continue to expand (with no noise on a Y/y basis) as revenues mature … company is able to continue innovating and developing a competitive product mix
B60: Deferred Tax Assets | S60: 31.862 | T60: 34.661 | U60: 32.818 | V60: 31.305 | W60: 32.945 | X60: 36.474 | Y60: 47.91 | Z60: 50.139 | AA60: 48.978 | AB60: 47.67 | AC60: 49.454 | AD60: 65.698 | AE60: 70.08 | AF60: 68.404 | AG60: 62.827 | AH60: 64.213 | AI60: 65.173 | AJ60: 66.671 | AK60: 64.236 | AL60: 85.158 | AM60: 84.661 | AN60: 108.852 | AO60: 105.851 | AP60: 100.332 | AQ60: 102.355 | AR60: 109.141 | AS60: 94.478 | AT60: 79.188 | AU60: 79.972 | AV60: 79.376 | BK60: =V60 -> 31.305 | BL60: =Z60 -> 50.139 | BM60: =AD60 -> 65.698 | BN60: =AH60 -> 64.213 | BO60: =AL60 -> 85.158 | BP60: =AP60 -> 100.332 | BQ60: 79.188 | BS60: Mkt Equity to Ttl Mkt Cap | BV60: =BV58/(BV58+'Main | Overview'!C7) -> 1 | BZ60: NPV | CA60: =NPV(CA58,BR39:DO39) -> 16781.401 | CF60: R&D as a percentage of revenues remains at a constant 10% as the company innovates into the 2030's (look into patent expiry for product mix, as well as R&D + FDA pipeline)
B61: Other LT Assets | S61: 1.613 | T61: 1.632 | U61: 9.63 | V61: 2.946 | W61: 3.869 | X61: 6.737 | Y61: 8.069 | Z61: 8.705 | AA61: 9.914 | AB61: 10.756 | AC61: 11.37 | AD61: 12.985 | AE61: 13.694 | AF61: 13.97 | AG61: 13.483 | AH61: 12.793 | AI61: 11.173 | AJ61: 10.5 | AK61: 14.743 | AL61: 25.88 | AM61: 33.814 | AN61: 38.518 | AO61: 38.514 | AP61: 40.939 | AQ61: 43.729 | AR61: 40.39 | AS61: 40.02 | AT61: 40.716 | AU61: 40.984 | AV61: 40.691 | BK61: =V61 -> 2.946 | BL61: =Z61 -> 8.705 | BM61: =AD61 -> 12.985 | BN61: =AH61 -> 12.793 | BO61: =AL61 -> 25.88 | BP61: =AP61 -> 40.939 | BQ61: 40.716 | BS61: Debt / Equity | BV61: =BV59/BV60 -> 0 | BZ61: SC | CA61: ='Main | Overview'!C4 -> 39.389 | CF61: SG&A expenses begin to tail off as a % of revenues (applying simple theory that as revenue growth takes off, fixed costs remain relatively the same/grow at a lower rate than revenues)
B62: Ttl Assets | S62: =SUM(S50:S61) -> 568.789 | T62: =SUM(T50:T61) -> 585.109 | U62: =SUM(U50:U61) -> 614.17 | V62: =SUM(V50:V61) -> 665.901 | W62: =SUM(W50:W61) -> 664.24 | X62: =SUM(X50:X61) -> 780.2 | Y62: =SUM(Y50:Y61) -> 810.304 | Z62: =SUM(Z50:Z61) -> 822.983 | ... AV62: =SUM(AV50:AV61) -> 1974.723 | BK62: =SUM(BK50:BK61) -> 665.901 | BL62: =SUM(BL50:BL61) -> 822.983 | BM62: =SUM(BM50:BM61) -> 1244.25 | BN62: =SUM(BN50:BN61) -> 1370.886 | BO62: =SUM(BO50:BO61) -> 1556.305 | BP62: =SUM(BP50:BP61) -> 1533.176 | BQ62: =SUM(BQ50:BQ61) -> 1826.511 | BZ62: FV | CA62: =CA60/CA61 -> 426.04283 | CG62: No SBC adjustments -- SBC is a very real expense in the form of dilution, but is still non-cash; excluding SBC adjustments leads to an overstatement in the firms calculated equity value (for fully integrated 3 statement model)
BS63: Cost of Equity | BZ63: CP | CA63: ='Main | Overview'!C3 -> 319.11 | CE63: Stable corporate tax rate -- TCJA is not allowed to sunset this year and The Company must remain relatively unaffected by tariff regime policies
B64: A/P | S64: 7.692 | T64: 8.743 | U64: 11.962 | V64: 15.111 | W64: 15.843 | X64: 14.432 | Y64: 14.544 | Z64: 14.109 | AA64: 15.389 | AB64: 13.712 | AC64: 13.679 | AD64: 13.421 | AE64: 14.137 | AF64: 23.096 | AG64: 25.365 | AH64: 26.679 | AI64: 28.199 | AJ64: 25.819 | AK64: 27.996 | AL64: 27.155 | AM64: 32.4545 | AN64: 32.822 | AO64: 33.151 | AP64: 31.326 | AQ64: 31.153 | AR64: 28.121 | AS64: 29.821 | AT64: 34.736 | AU64: 43.658 | AV64: 44.728 | BK64: =V64 -> 15.111 | BL64: =Z64 -> 14.109 | BM64: =AD64 -> 13.421 | BN64: =AH64 -> 26.679 | BO64: =AL64 -> 27.155 | BP64: =AP64 -> 31.326 | BQ64: 34.736 | BS64: RFR (10-year yield) | BV64: 0.0511 | BZ64: Change Δ | CA64: =CA62/CA63-1 -> 0.33509709 | CB64: =IF(CA64>0,"Upside","Downside") -> Upside | CF64: The Company is only taxed at the federal corporate rate of 21% + California's 8.84% (does not consider any exotic tax circumstances)
B65: Accrued Liabilities | S65: 58.032 | T65: 57.276 | U65: 70.163 | V65: 67.63 | W65: 65.335 | X65: 57.718 | Y65: 87.691 | Z65: 85.795 | AA65: 90.214 | AB65: 86.503 | AC65: 93.22 | AD65: 99.796 | AE65: 105.533 | AF65: 111.405 | AG65: 101.672 | AH65: 106.3 | AI65: 105.869 | AJ65: 105.606 | AK65: 104.184 | AL65: 110.555 | AM65: 106.549 | AN65: 104.071 | AO65: 105.55 | AP65: 112.429 | AQ65: 112.675 | AR65: 114.389 | AS65: 124.273 | AT65: 132.163 | AU65: 151.543 | AV65: 172.27 | BK65: =V65 -> 67.63 | BL65: =Z65 -> 85.795 | BM65: =AD65 -> 99.796 | BN65: =AH65 -> 106.3 | BO65: =AL65 -> 110.555 | BP65: =AP65 -> 112.429 | BQ65: 132.163 | BS65: Equity β (1-year avg.) | BV65: ='Notes | Analysis'!T240 -> 0.76850681 | BZ65: {=_xlfn.IFS(CA64>=25%,"Strong Buy",CA64>=10.00001%,"Buy",AND(CA64<=10%,CA64>=-4.9999%),"Hold",AND(CA64<=-5%,CA64>=-14.999999%),"Sell",CA64<=-15%,"Strong Sell")} -> Strong Buy | CE65: Higher than average terminal rate value (~1.4x GDP)
B66: Current Operating Lease Liabilities | S66: 3.688 | T66: 3.742 | U66: 4.042 | V66: 4.142 | W66: 4.435 | X66: 4.446 | Y66: 4.484 | Z66: 4.697 | AA66: 4.822 | AB66: 6.347 | AC66: 7.531 | AD66: 8.267 | AE66: 8.66 | AF66: 9.297 | AG66: 9.417 | AH66: 10.033 | AI66: 10.303 | AJ66: 10.715 | AK66: 10.827 | AL66: 11.203 | AM66: 11.52 | AN66: 11.776 | AO66: 12.068 | AP66: 12.221 | AQ66: 12.51 | AR66: 12.855 | AS66: 13.086 | AT66: 13.841 | AU66: 14.144 | AV66: 14.398 | BK66: =V66 -> 4.142 | BL66: =Z66 -> 4.697 | BM66: =AD66 -> 8.267 | BN66: =AH66 -> 10.033 | BO66: =AL66 -> 11.203 | BP66: =AP66 -> 12.221 | BQ66: 13.841 | BS66: Market Return(1-year avg.) | BV66: 0.18 | CE66: Long-term NI ≈ FCF (sub assumptions: CapEx purely maintenance ... D&A netting out CapEx balance, No delta in WC)
B67: Current Finance Lease Liabilities | S67: 0 | T67: 0 | U67: 0 | V67: 4.165 | W67: 2.461 | X67: 1.016 | Y67: 1.336 | Z67: 1.331 | AA67: 1.437 | AB67: 1.484 | AC67: 1.627 | AD67: 1.713 | AE67: 1.769 | AF67: 1.806 | AG67: 1.878 | AH67: 1.92 | AI67: 1.957 | AJ67: 1.984 | AK67: 2.071 | AL67: 2.231 | AM67: 2.28 | AN67: 2.325 | AO67: 2.416 | AP67: 2.369 | AQ67: 2.292 | AR67: 2.396 | AS67: 2.423 | AT67: 2.393 | AU67: 2.386 | AV67: 2.38 | BK67: =V67 -> 4.165 | BL67: =Z67 -> 1.331 | BM67: =AD67 -> 1.713 | BN67: =AH67 -> 1.92 | BO67: =AL67 -> 2.231 | BP67: =AP67 -> 2.369 | BQ67: 2.393 | BS67: Cost of Equity | BV67: =(BV64+BV65)*(BV66-BV64) -> 0.10564732 | CF67: CapEx = Dep. & Am.
B68: Non-current Operating Lease Liabilities | S68: 46.07 | T68: 46.146 | U68: 45.4 | V68: 47.242 | W68: 46.416 | X68: 45.925 | Y68: 44.998 | Z68: 44.183 | AA68: 43.525 | AB68: 94.444 | AC68: 138.169 | AD68: 137.045 | AE68: 182.438 | AF68: 183.155 | AG68: 180.897 | AH68: 198.955 | AI68: 196.837 | AJ68: 194.655 | AK68: 192.117 | AL68: 197.229 | AM68: 194.537 | AN68: 192.216 | AO68: 189.96 | AP68: 187.068 | AQ68: 184.652 | AR68: 183.493 | AS68: 180.3 | AT68: 182.751 | AU68: 179.424 | AV68: 176.304 | BK68: =V68 -> 47.242 | BL68: =Z68 -> 44.183 | BM68: =AD68 -> 137.045 | BN68: =AH68 -> 198.955 | BO68: =AL68 -> 197.229 | BP68: =AP68 -> 187.068 | BQ68: 182.751 | CF68: ΔNWC = 0
B69: Non-current Finance Lease Liabilities | S69: 0 | T69: 0 | U69: 0 | V69: 26.748 | W69: 26.483 | X69: 26.202 | Y69: 27.391 | Z69: 27.066 | AA69: 27 | AB69: 26.691 | AC69: 26.775 | AD69: 26.523 | AE69: 26.122 | AF69: 25.654 | AG69: 25.325 | AH69: 24.865 | AI69: 24.423 | AJ69: 23.922 | AK69: 23.779 | AL69: 23.68 | AM69: 23.098 | AN69: 22.501 | AO69: 22.245 | AP69: 21.731 | AQ69: 21.201 | AR69: 21.785 | AS69: 21.223 | AT69: 20.714 | AU69: 20.221 | AV69: 19.628 | BK69: =V69 -> 26.748 | BL69: =Z69 -> 27.066 | BM69: =AD69 -> 26.523 | BN69: =AH69 -> 24.865 | BO69: =AL69 -> 23.68 | BP69: =AP69 -> 21.731 | BQ69: 20.714 | BS69: Cost of Debt | CE69: No future debt issuance - I only calculated for Cost of Equity... Net income is more sensitive to changes in capital structure, and will distort NPV calculation further between NI and FCF approaches
B70: Other Liabilities | S70: 16.644 | T70: 15.019 | U70: 15.662 | V70: 15.25 | W70: 15.15 | X70: 7.3 | Y70: 10.147 | Z70: 8.014 | AA70: 7.966 | AB70: 7.661 | AC70: 7.635 | AD70: 3.558 | AE70: 3.612 | AF70: 3.472 | AG70: 3.295 | AH70: 3.276 | AI70: 3.241 | AJ70: 3.288 | AK70: 3.265 | AL70: 5.308 | AM70: 5.876 | AN70: 7.619 | AO70: 9.453 | AP70: 15.103 | AQ70: 15.942 | AR70: 17.819 | AS70: 14.53 | AT70: 12.318 | AU70: 13.25 | AV70: 14.249 | BK70: =V70 -> 15.25 | BL70: =Z70 -> 8.014 | BM70: =AD70 -> 3.558 | BN70: =AH70 -> 3.276 | BO70: =AL70 -> 5.308 | BP70: =AP70 -> 15.103 | BQ70: 12.318 | BS70: Cost of Debt | BV70: 0 | CD70: Strategies to improve model's efficacy:
B71: Ttl Liabilities | S71: =SUM(S64:S70) -> 132.126 | T71: =SUM(T64:T70) -> 130.926 | U71: =SUM(U64:U70) -> 147.229 | V71: =SUM(V64:V70) -> 180.288 | W71: =SUM(W64:W70) -> 176.123 | X71: =SUM(X64:X70) -> 157.039 | Y71: =SUM(Y64:Y70) -> 190.591 | Z71: =SUM(Z64:Z70) -> 185.195 | ... AV71: =SUM(AV64:AV70) -> 443.957 | BK71: =SUM(BK64:BK70) -> 180.288 | BL71: =SUM(BL64:BL70) -> 185.195 | BM71: =SUM(BM64:BM70) -> 290.323 | BN71: =SUM(BN64:BN70) -> 372.028 | BO71: =SUM(BO64:BO70) -> 377.361 | BP71: =SUM(BP64:BP70) -> 382.247 | BQ71: =SUM(BQ64:BQ70) -> 398.916 | BS71: Tax Rate | BV71: 0.2 | CE71: Focus on bringing the amount of assumptions down (many of which can addressed by simply completing a projected Stmt. of Cash Flow)
B72: SE | S72: 436.663 | T72: 454.183 | U72: 466.941 | V72: 485.613 | W72: 488.117 | X72: 623.161 | Y72: 619.712 | Z72: 637.788 | AA72: 650.471 | AB72: 673.376 | AC72: 684.603 | AD72: 953.927 | AE72: 959.302 | AF72: 970.015 | AG72: 973.752 | AH72: 998.858 | AI72: 1024.469 | AJ72: 1066.543 | AK72: 1104.138 | AL72: 1178.94 | AM72: 1203.531 | AN72: 1161.231 | AO72: 1104.28 | AP72: 1150.931 | AQ72: 1212.882 | AR72: 1293.95 | AS72: 1358.696 | AT72: 1427.603 | AU72: 1473.812 | AV72: 1530.766 | BK72: =V72 -> 485.613 | BL72: =Z72 -> 637.788 | BM72: =AD72 -> 953.927 | BN72: =AH72 -> 998.858 | BO72: =AL72 -> 1178.94 | BP72: =AP72 -> 1150.931 | BQ72: 1427.603 | BS72: After Tax Cost of Debt | BV72: =BV70*(1-BV71) -> 0 | CE72: An easy one - Complete Stmt of Cash Flows and build a true DCF model that calculates NPV from cash flows, not net income… begin building assumptions for projecting the following:
B73: Ttl L + SE | S73: =SUM(S71:S72) -> 568.789 | T73: =SUM(T71:T72) -> 585.109 | U73: =SUM(U71:U72) -> 614.17 | V73: =SUM(V71:V72) -> 665.901 | W73: =SUM(W71:W72) -> 664.24 | X73: =SUM(X71:X72) -> 780.2 | Y73: =SUM(Y71:Y72) -> 810.303 | Z73: =SUM(Z71:Z72) -> 822.983 | ... AV73: =SUM(AV71:AV72) -> 1974.723 | BK73: =SUM(BK71:BK72) -> 665.901 | BL73: =SUM(BL71:BL72) -> 822.983 | BM73: =SUM(BM71:BM72) -> 1244.25 | BN73: =SUM(BN71:BN72) -> 1370.886 | BO73: =SUM(BO71:BO72) -> 1556.301 | BP73: =SUM(BP71:BP72) -> 1533.178 | BQ73: =SUM(BQ71:BQ72) -> 1826.519 | CG73: Non-cash expenses
BS74: WACC | BV74: =(BV60*BV67)+(BV59*BV72*(1-BV71)) -> 0.10564732 | CG74: Future CapEx investment + differentiating maintenance v. investment CapEx
B75: Current Ratio | S75: =SUM(S50:S54)/SUM(S64:S67) -> 6.0952861 | T75: =SUM(T50:T54)/SUM(T64:T67) -> 6.2298992 | U75: =SUM(U50:U54)/SUM(U64:U67) -> 5.2378985 | V75: =SUM(V50:V54)/SUM(V64:V67) -> 5.0867015 | W75: =SUM(W50:W54)/SUM(W64:W67) -> 5.1518042 | X75: =SUM(X50:X54)/SUM(X64:X67) -> 7.4201799 | Y75: =SUM(Y50:Y54)/SUM(Y64:Y67) -> 5.462024 | Z75: =SUM(Z50:Z54)/SUM(Z64:Z67) -> 5.8311181 | ... AV75: =SUM(AV50:AV54)/SUM(AV64:AV67) -> 5.749615 | BK75: =SUM(BK50:BK54)/SUM(BK64:BK67) -> 5.0867015 | BL75: =SUM(BL50:BL54)/SUM(BL64:BL67) -> 5.8311181 | BM75: =SUM(BM50:BM54)/SUM(BM64:BM67) -> 5.5315795 | BN75: =SUM(BN50:BN54)/SUM(BN64:BN67) -> 5.2141625 | BO75: =SUM(BO50:BO54)/SUM(BO64:BO67) -> 6.0564892 | BP75: =SUM(BP50:BP54)/SUM(BP64:BP67) -> 6.0066311 | BQ75: =SUM(BQ50:BQ54)/SUM(BQ64:BQ67) -> 6.6436743 | CG75: Sensitivity to potential swings in working capital -- stress-test model in dedicated page
B76: Quick Ratio | S76: =(SUM(S50:S54)-S53)/SUM(S64:S67) -> 4.3421166 | T76: =(SUM(T50:T54)-T53)/SUM(T64:T67) -> 4.3271885 | U76: =(SUM(U50:U54)-U53)/SUM(U64:U67) -> 3.6089802 | V76: =(SUM(V50:V54)-V53)/SUM(V64:V67) -> 3.4063571 | W76: =(SUM(W50:W54)-W53)/SUM(W64:W67) -> 3.2652996 | X76: =(SUM(X50:X54)-X53)/SUM(X64:X67) -> 5.0566021 | Y76: =(SUM(Y50:Y54)-Y53)/SUM(Y64:Y67) -> 3.6893434 | Z76: =(SUM(Z50:Z54)-Z53)/SUM(Z64:Z67) -> 3.7587792 | ... AV76: =(SUM(AV50:AV54)-AV53)/SUM(AV64:AV67) -> 3.8561358 | BK76: =(SUM(BK50:BK54)-BK53)/SUM(BK64:BK67) -> 3.4063571 | BL76: =(SUM(BL50:BL54)-BL53)/SUM(BL64:BL67) -> 3.7587792 | BM76: =(SUM(BM50:BM54)-BM53)/SUM(BM64:BM67) -> 3.3926963 | BN76: =(SUM(BN50:BN54)-BN53)/SUM(BN64:BN67) -> 2.9095921 | BO76: =(SUM(BO50:BO54)-BO53)/SUM(BO64:BO67) -> 3.4892487 | BP76: =(SUM(BP50:BP54)-BP53)/SUM(BP64:BP67) -> 3.4379551 | BQ76: =(SUM(BQ50:BQ54)-BQ53)/SUM(BQ64:BQ67) -> 4.2871956 | CF76: This is the tricky part, and demands learning more about Penumbra's product mix, their product's operating lifecycles, and The Company's need to create/innovate to generate future returns (the patents ultimately expire in 20 years- follows similar behavior to pharma-economics)
B77: Cash Ratio | S77: =S50/SUM(S64:S67) -> 1.3773699 | T77: =T50/SUM(T64:T67) -> 1.1075099 | U77: =U50/SUM(U64:U67) -> 1.2949389 | V77: =V50/SUM(V64:V67) -> 0.7993476 | W77: =W50/SUM(W64:W67) -> 0.82267184 | X77: =X50/SUM(X64:X67) -> 1.7314462 | Y77: =Y50/SUM(Y64:Y67) -> 0.74142798 | Z77: =Z50/SUM(Z64:Z67) -> 0.65768606 | ... AV77: =AV50/SUM(AV64:AV67) -> 0.87806704 | BK77: =SUM(BK50:BK51)/SUM(BK64:BK67) -> 2.0801006 | BL77: =SUM(BL50:BL51)/SUM(BL64:BL67) -> 2.5000189 | BM77: =SUM(BM50:BM51)/SUM(BM64:BM67) -> 2.068841 | BN77: =SUM(BN50:BN51)/SUM(BN64:BN67) -> 1.297367 | BO77: =SUM(BO50:BO51)/SUM(BO64:BO67) -> 1.9133211 | BP77: =SUM(BP50:BP51)/SUM(BP64:BP67) -> 2.1480123 | BQ77: =SUM(BQ50:BQ51)/SUM(BQ64:BQ67) -> 2.9749362 | CE77: Each one of my inputs (terminal, cost of debt/equity, ROIC and others) for the end NPV calculation should have separate tables to record all assumptions/formulaic inputs
B78: Fixed Asset Turnover Ratio | S78: =S26/SUM(S55:S57) -> 1.6518211 | T78: =T26/SUM(T55:T57) -> 1.6688346 | U78: =U26/SUM(U55:U57) -> 1.5953661 | V78: =V26/SUM(V55:V57) -> 1.0724089 | W78: =W26/SUM(W55:W57) -> 0.97270338 | X78: =X26/SUM(X55:X57) -> 0.73607687 | Y78: =Y26/SUM(Y55:Y57) -> 1.0386165 | Z78: =Z26/SUM(Z55:Z57) -> 1.309874 | ... AV78: =AV26/SUM(AV55:AV57) -> 1.1530646 | BK78: =BK26/SUM(BK55:BK57) -> 4.0412763 | BL78: =BL26/SUM(BL55:BL57) -> 4.3979408 | BM78: =BM26/SUM(BM55:BM57) -> 3.2920863 | BN78: =BN26/SUM(BN55:BN57) -> 2.9113701 | BO78: =BO26/SUM(BO55:BO57) -> 3.6183893 | BP78: =BP26/SUM(BP55:BP57) -> 4.450057 | BQ78: =BQ26/SUM(BQ55:BQ57) -> 4.4280351 | CE78: Determine whether to employ a terminal rate or exit multiple method for the full DCF model
B79: Ttl Asset Turnover | S79: =S26/S62 -> 0.22581133 | T79: =T26/T62 -> 0.22936068 | U79: =U26/U62 -> 0.22713907 | V79: =V26/V62 -> 0.21814204 | W79: =W26/W62 -> 0.2067024 | X79: =X26/X62 -> 0.13470905 | Y79: =Y26/Y62 -> 0.18647322 | Z79: =Z26/Z62 -> 0.20281342 | ... AV79: =AV26/AV62 -> 0.19751935 | BK79: =BK26/BK62 -> 0.82204862 | BL79: =BL26/BL62 -> 0.6809521 | BM79: =BM26/BM62 -> 0.60083584 | BN79: =BN26/BN62 -> 0.61794562 | BO79: =BO26/BO62 -> 0.68014946 | BP79: =BP26/BP62 -> 0.77916691 | BQ79: =BQ26/BQ62 -> 0.76849523 | CE79: Build out models for long term outcome potentiality ("High IP value + cont. innovation" v. "generic competitor" outcomes for Penumbra in the long run?)
B80: Inventory Turnover Ratio | T80: =T27/AVERAGE(A53:T53) -> 0.31657928 | U80: =U27/AVERAGE(B53:U53) -> 0.33059007 | V80: =V27/AVERAGE(S53:V53) -> 0.34419116 | W80: =W27/AVERAGE(T53:W53) -> 0.33297424 | X80: =X27/AVERAGE(U53:X53) -> 0.25009915 | Y80: =Y27/AVERAGE(V53:Y53) -> 0.34663674 | Z80: =Z27/AVERAGE(W53:Z53) -> 0.38168557 | AA80: =AA27/AVERAGE(X53:AA53) -> 0.27561062 | AB80: =AB27/AVERAGE(Y53:AB53) -> 0.28791756 | AC80: =AC27/AVERAGE(Z53:AC53) -> 0.28707518 | ... AV80: =AV27/AVERAGE(AS53:AV53) -> 0.28674984 | BK80: =BK27/AVERAGE(BH53:BK53) -> 1.1467332 | BL80: =BL27/AVERAGE(BI53:BL53) -> 1.1931579 | BM80: =BM27/AVERAGE(BJ53:BM53) -> 1.2839536 | BN80: =BN27/AVERAGE(BK53:BN53) -> 1.2862543 | BO80: =BO27/AVERAGE(BL53:BO53) -> 1.2477387 | BP80: =BP27/AVERAGE(BM53:BP53) -> 1.2629734 | BQ80: =BQ27/AVERAGE(BN53:BQ53) -> 1.1823971 | CF80: !! It is absolutely necessary to begin tracking individual products Penumbra owns/markets and creating useful life tables !! Understanding the finances and the product is what is expected of analysts
B81: Return on Assets | S81: =S39/S62 -> 0.018808381 | T81: =T39/T62 -> 0.028688672 | U81: =U39/U62 -> 0.018696778 | V81: =V39/V62 -> 0.014249866 | W81: =W39/W62 -> 0.0022823076 | X81: =X39/X62 -> -0.015303768 | Y81: =Y39/Y62 -> -0.010900847 | Z81: =Z39/Z62 -> 0.004441161 | ... AV81: =AV39/AV62 -> 0.017628295 | BK81: =BK39/BK62 -> 0.072767574 | BL81: =BL39/BL62 -> -0.018957864 | BM81: =BM39/BM62 -> 0.004246735 | BN81: =BN39/BN62 -> -0.0014603694 | BO81: =BO39/BO62 -> 0.058478255 | BP81: =BP39/BP62 -> 0.0091248493 | BQ81: =BQ39/BQ62 -> 0.097282195 | CE81: Build out models for firms with competitive overlap + other operators in the MedTech/Life Science industries; mosaic theory some comparables
B82: Return on Equity | S82: =S39/S72 -> 0.024499442 | T82: =T39/T72 -> 0.036958671 | U82: =U39/U72 -> 0.024591972 | V82: =V39/V72 -> 0.019540251 | W82: =W39/W72 -> 0.0031058127 | X82: =X39/X72 -> -0.019160377 | Y82: =Y39/Y72 -> -0.014253395 | Z82: =Z39/Z72 -> 0.0057307444 | ... AV82: =AV39/AV72 -> 0.022740902 | BK82: =BK39/BK72 -> 0.099783161 | BL82: =BL39/BL72 -> -0.024462674 | BM82: =BM39/BM72 -> 0.0055392079 | BN82: =BN39/BN72 -> -0.0020042889 | BO82: =BO39/BO72 -> 0.077196465 | BP82: =BP39/BP72 -> 0.012155377 | BQ82: =BQ39/BQ72 -> 0.12446528 | CG82: Gives a chance to study other operators, their financial standing, + the technological "asset value" firms possess (which is where the real α is found from an equity interest)
CG83: Stryker managers are intelligent and didn't pay a 60% premium above the market's current trading price on Inari for no reason…
B84: NI | C84: =C39 -> 0.5 | D84: =D39 -> -0.55 | E84: =E39 -> 0.32 | F84: =F39 -> 0.75 | G84: =G39 -> 2.5 | H84: =H39 -> 3 | I84: =I39 -> 12.2 | J84: =J39 -> -2.4 | ... AV84: =AV39 -> 34.811 | BG84: =SUM(C84:F84) -> 1.02 | BH84: =SUM(G84:J84) -> 15.3 | BI84: =SUM(K84:N84) -> 4.6 | BJ84: =SUM(O84:R84) -> 6.52 | BK84: =BK39 -> 48.456 | BL84: =BL39 -> -15.602 | BM84: =BM39 -> 5.284 | BN84: =BN39 -> -2.002 | BO84: =BO39 -> 91.01 | BP84: =BP39 -> 13.99 | BQ84: =SUM(AQ84:AT84) -> 177.687 | CG84: If NARI was a traditional enterprise, say a bottling plant, and SYK managers acquired it for a 60% premium above its current valuation, other participants would laugh and call them dumb... This means that NARI (and potentially MedTech companies in general) are valued by the market for more than just the net present value of cash flows... or makes positive assumptions about those future returns
B85: CFFO | C85: -2.7 | D85: -5.6 | E85: -4.3 | F85: -8 | G85: -2.1 | H85: -6.1 | I85: 5.7 | J85: -10.4 | K85: 2.2 | L85: 0.6 | M85: 10.8 | N85: -0.9 | O85: 10.7 | P85: 0.1 | Q85: 10.4 | R85: 7.5 | S85: -2.1 | T85: 1.9 | U85: 22 | V85: 4.8 | W85: -5.92 | X85: =-27.609-W85 -> -21.689 | Y85: =-31.159-SUM(W85:X85) -> -3.55 | Z85: =-33.242-SUM(W85:Y85) -> -2.083 | AA85: -14.368 | AB85: =-17.678-AA85 -> -3.31 | AC85: =18.772-SUM(AA85:AB85) -> 36.45 | AD85: =9.502-SUM(AA85:AC85) -> -9.27 | AE85: -4.514 | AF85: =-44.089-AE85 -> -39.575 | AG85: =-56.998-SUM(AE85:AF85) -> -12.909 | AH85: =-55.661-SUM(AE85:AG85) -> 1.337 | AI85: 13.129 | AJ85: =30.228-AI85 -> 17.099 | AK85: =61.072-SUM(AI85:AJ85) -> 30.844 | AL85: =97.333-SUM(AI85:AK85) -> 36.261 | AM85: 38.295 | AN85: =60.906-AM85 -> 22.611 | AO85: =117.373-SUM(AM85:AN85) -> 56.467 | AP85: =168.481-SUM(AM85:AO85) -> 51.108 | AQ85: =48.97 -> 48.97 | AR85: =93.916-AQ85 -> 44.946 | AS85: 58.263 | AT85: =238.663-SUM(AQ85:AS85) -> 86.484 | AU85: 86.97 | AV85: 46.084 | BG85: =SUM(C85:F85) -> -20.6 | BH85: =SUM(G85:J85) -> -12.9 | BI85: =SUM(K85:N85) -> 12.7 | BJ85: =SUM(O85:R85) -> 28.7 | BK85: 26.652 | BL85: =SUM(W85:Z85) -> -33.242 | BM85: =SUM(AA85:AD85) -> 9.502 | BN85: =SUM(AE85:AH85) -> -55.661 | BO85: =SUM(AI85:AL85) -> 97.333 | BP85: =SUM(AM85:AP85) -> 168.481 | BQ85: =SUM(AQ85:AT85) -> 238.663 | CH85: How do you value IP??? Commercialization ramp track
B86: CapEx | C86: -1.3 | D86: -1.8 | E86: -1.4 | F86: -1 | G86: -1.1 | H86: -2.6 | I86: -3.4 | J86: -6.6 | K86: -3.2 | L86: -2.2 | M86: -1.4 | N86: -5.7 | O86: -2.8 | P86: -2.3 | Q86: -1.5 | R86: -3 | S86: -2.5 | T86: -3.7 | U86: -7.9 | V86: -8 | W86: -10.131 | X86: =-16.85-W86 -> -6.719 | Y86: =-21.003-SUM(W86:X86) -> -4.153 | Z86: =-24.756-SUM(W86:Y86) -> -3.753 | AA86: -3.991 | AB86: =-7.286-AA86 -> -3.295 | AC86: =-13.088-SUM(AA86:AB86) -> -5.802 | AD86: =-21.18-SUM(AA86:AC86) -> -8.092 | AE86: -4.957 | AF86: =-9.388-AE86 -> -4.431 | AG86: =-15.736-SUM(AE86:AF86) -> -6.348 | AH86: =-19.298-SUM(AE86:AG86) -> -3.562 | AI86: -3.894 | AJ86: =-8.236-AI86 -> -4.342 | AK86: =-12.568-SUM(AI86:AJ86) -> -4.332 | AL86: =-16.213-SUM(AI86:AK86) -> -3.645 | AM86: -5.824 | AN86: =-10.36-AM86 -> -4.536 | AO86: =-15.811-SUM(AM86:AN86) -> -5.451 | AP86: =-21.182-SUM(AM86:AO86) -> -5.371 | AQ86: =-13.467 -> -13.467 | AR86: =-29.046-AQ86 -> -15.579 | AS86: -16.249 | AT86: =-63.729-SUM(AQ86:AS86) -> -18.434 | AU86: -13.671 | AV86: -13.542 | BG86: =SUM(C86:F86) -> -5.5 | BH86: =SUM(G86:J86) -> -13.7 | BI86: =SUM(K86:N86) -> -12.5 | BJ86: =SUM(O86:R86) -> -9.6 | BK86: -22.109 | BL86: =SUM(W86:Z86) -> -24.756 | BM86: =SUM(AA86:AD86) -> -21.18 | BN86: =SUM(AE86:AH86) -> -19.298 | BO86: =SUM(AI86:AL86) -> -16.213 | BP86: =SUM(AM86:AP86) -> -21.182 | BQ86: =SUM(AQ86:AT86) -> -63.729 | CE86: R&D spend is treated as an expense (by accountants at least), but in MedTech it almost acts as a capital-like investment into the firm's future product mix … How do we as investors account for this?
B87: FCF | C87: =C85+C86 -> -4 | D87: =D85+D86 -> -7.4 | E87: =E85+E86 -> -5.7 | F87: =F85+F86 -> -9 | G87: =G85+G86 -> -3.2 | H87: =H85+H86 -> -8.7 | I87: =I85+I86 -> 2.3 | J87: =J85+J86 -> -17 | ... AV87: =AV85+AV86 -> 32.542 | BG87: =BG85+BG86 -> -26.1 | BH87: =BH85+BH86 -> -26.6 | BI87: =BI85+BI86 -> 0.2 | BJ87: =BJ85+BJ86 -> 19.1 | BK87: =BK85+BK86 -> 4.543 | BL87: =BL85+BL86 -> -57.998 | BM87: =BM85+BM86 -> -11.678 | BN87: =BN85+BN86 -> -74.959 | ... BP87: =BP85+BP86 -> 147.299 | BQ87: =SUM(AQ87:AT87) -> 174.934 | CF87: Learn more about R&D initiatives and gauge whether to capitalize R&D on the balance sheet over a useful life
B88: SC | C88: =C40 -> 5 | D88: =D40 -> 5 | E88: =E40 -> 8 | F88: =F40 -> 12 | G88: =G40 -> 30 | H88: =H40 -> 30 | I88: =I40 -> 31 | J88: =J40 -> 30 | ... AV88: =AV40 -> 39.353 | BG88: =BG40 -> 12 | BH88: =BH40 -> 31 | BI88: =BI40 -> 33 | BJ88: =BJ40 -> 34 | BK88: =BK40 -> 34.8 | BL88: =BL40 -> 35.5 | BM88: =AD88 -> 36.7 | BN88: =AH88 -> 37.841 | BO88: =AL88 -> 38.4 | BP88: =AP88 -> 38.63 | BQ88: =AVERAGE(AQ88:AT88) -> 38.776 | CE88: Identify key sectoral KPI's, which drive material changes in common stock price (Pricing v. Volume Mix; Complete product pipeline schedules; Clinical/Medical representative support)
B89: FCF per Share | C89: =C87/C88 -> -0.8 | D89: =D87/D88 -> -1.48 | E89: =E87/E88 -> -0.7125 | F89: =F87/F88 -> -0.75 | G89: =G87/G88 -> -0.10666667 | H89: =H87/H88 -> -0.29 | I89: =I87/I88 -> 0.074193548 | J89: =J87/J88 -> -0.56666667 | ... AV89: =AV87/AV88 -> 0.82692552 | BG89: =BG87/BG88 -> -2.175 | BH89: =BH87/BH88 -> -0.85806452 | BI89: =BI87/BI88 -> 0.0060606061 | BJ89: =BJ87/BJ88 -> 0.56176471 | BK89: =BK87/BK88 -> 0.13054598 | BL89: =BL87/BL88 -> -1.6337465 | BM89: =BM87/BM88 -> -0.31820163 | BN89: =BN87/BN88 -> -1.9808937 | ... BP89: =BP87/BP88 -> 3.8130727 | BQ89: =SUM(AQ89:AT89) -> 4.513608 | CD89: Closing remarks:
CE90: There are a variety of assumptions listed above that immediately invalidate the calculated valuation and any potential upside/downside. I hope to continue iterating on this model in order to better capture the firm's true potential value on the open market
CE91: While my current net income based model provides a rough estimate, transitioning to an expanded DCF model with Stmt. Of Cashflow considerations are necessary for the model to be of any use/investment value. I hope to address these pitfalls and improve accuracy
CF92: Additionally, working to capture qualitative factors in the valuation (IP/innovation runway, product's standing as flagship in the space( taking dominant market share), management strategy, etc.) will increase accuracy.
CG93: Working to uncover/understand qualitative factors may also unlock a view into the markets reasoning behind justifying a large equity premium from a glance ... ("I don’t pay an analyst big bucks to tell me if a 6x P/E Fwd. sotck is cheap… I pay them to tell me if a 156x Fwd. P/E stock is cheap!")
CG94: Understanding the market factors baked into a valuation are of upmost importance (think TSLA's valuation, with AVs already being priced in)
CE95: This net income to NPV shortcut approach assumes absolutely perfect FCF conversion, which is far from realistic for a still-growing firm like Penumbra
CE96: My terminal value makes an assumption of strong, stable future revenues and margins, but Med-Tech is prone to patent expiry cliffs (similar to pharma) and FDA/health regulation risks

Sheet Base Case (55%)
S1: Q1 2019 | W1: Q1 2020 | AA1: Q1 2021 | AE1: Q1 2022 | AI1: Q1 2023 | AM1: Q1 2024 | AQ1: Q1 2025 | AU1: Q1 2026
B2: Quarterly | C2: Apr | D2: July | E2: Oct | F2: Jan | G2: Apr | H2: July | I2: Oct | J2: Jan | K2: Apr | L2: July | M2: Oct | N2: Jan | O2: Apr | P2: July | Q2: Oct | R2: Jan | S2: Apr | T2: July | U2: Oct | V2: Jan | W2: Apr | X2: July | Y2: Oct | Z2: Jan | AA2: Apr | AB2: July | AC2: Oct | AD2: Jan | AE2: Apr | AF2: July | AG2: Oct | AH2: Jan | AI2: Apr | AJ2: July | AK2: Oct | AL2: Jan | AM2: Apr | AN2: July | AO2: Oct | AP2: Jan | AQ2: Apr | AR2: July | AS2: Oct | AT2: Jan | AU2: Apr | AV2: July | AW2: Oct | AX2: Jan | AY2: Apr | AZ2: July | BA2: Oct | BB2: Jan
B3: Revenues | C3: Q1 2015 | D3: Q2 2015 | E3: Q3 2015 | F3: Q4 2015 | G3: Q1 2016 | H3: Q2 2016 | I3: Q3 2016 | J3: Q4 2016 | K3: Q1 2017 | L3: Q2 2017 | M3: Q3 2017 | N3: Q4 2017 | O3: Q1 2018 | P3: Q2 2018 | Q3: Q3 2018 | R3: Q4 2018 | S3: Q1 2019 | T3: Q2 2019 | U3: Q3 2019 | V3: Q4 2019 | W3: Q1 2020 | X3: Q2 2020 | Y3: Q3 2020 | Z3: Q4 2020 | AA3: Q1 2021 | AB3: Q2 2021 | AC3: Q3 2021 | AD3: Q4 2021 | AE3: Q1 2022 | AF3: Q2 2022 | AG3: Q3 2022 | AH3: Q4 2022 | AI3: Q1 2023 | AJ3: Q2 2023 | AK3: Q3 2023 | AL3: Q4 2023 | AM3: Q1 2024 | AN3: Q2 2024 | AO3: Q3 2024 | AP3: Q4 2024 | AQ3: Q1 2025 | AR3: Q2 2025 | AS3: Q3 2025 | AT3: Q4 2025 | AU3: Q1 2026 | AV3: Q2 2026 | AW3: Q3 2026 | AX3: Q4 2026 | AY3: Q1 2027 | AZ3: Q2 2027 | BA3: Q3 2027 | BB3: Q4 2027 | BG3: 2015 | BH3: 2016 | BI3: 2017 | BJ3: 2018 | BK3: 2019 | BL3: 2020 | BM3: 2021 | BN3: 2022 | BO3: =BN3+1 -> 2023 | BP3: =BO3+1 -> 2024 | BQ3: =BP3+1 -> 2025 | BR3: =BQ3+1 -> 2026 | BS3: =BR3+1 -> 2027 | BT3: =BS3+1 -> 2028 | BU3: =BT3+1 -> 2029 | BV3: =BU3+1 -> 2030 | ... DO3: =DN3+1 -> 2075
B4: Thrombectomy (Neuro + Peripheral) | AI4: 145 | AJ4: 162 | AK4: 179 | AL4: =677-SUM(AI4:AK4) -> 191 | AM4: 188 | AN4: 203 | AO4: 204 | AP4: =815-SUM(AM4:AO4) -> 220 | AQ4: 226.544 | AR4: 230.256 | AS4: 236.4 | AT4: =947.918-SUM(AQ4:AS4) -> 254.718 | AU4: 253.917 | AV4: 258.981 | AW4: =AS4*(1+AW8) -> 293.136 | AX4: =AT4*(1+AX8) -> 315.85032 | BO4: =SUM(AI4:AL4) -> 677 | BP4: =SUM(AM4:AP4) -> 815 | BQ4: =SUM(AQ4:AT4) -> 947.918 | BR4: =BQ4*(1+BR8) -> 1118.5432 | BS4: =BR4*(1+BS8) -> 1314.2883 | BT4: =BS4*(1+BT8) -> 1537.7173 | BU4: =BT4*(1+BU8) -> 1791.4407 | BV4: =BU4*(1+BV8) -> 2078.0712 | BW4: =BV4*(1+BW8) -> 2389.7819 | BX4: =BW4*(1+BX8) -> 2736.3002 | BY4: =BX4*(1+BY8) -> 3119.3823 | ... CA4: =BZ4*(1+CA8) -> 4000.7637
B5: Embolization & Access (Peripheral Embolization + Neuro Embolization + Access + Neurosurgical Tools) | AI5: 96 | AJ5: 99 | AK5: 92 | AL5: =381-SUM(AI5:AK5) -> 94 | AM5: 91 | AN5: 96 | AO5: 96.89 | AP5: =379-SUM(AM5:AO5) -> 95.11 | AQ5: 97.596 | AR5: 109.199 | AS5: 118.3 | AT5: =455.747-SUM(AQ5:AS5) -> 130.652 | AU5: 120.841 | AV5: 131.065 | AW5: =AS5*(1+AW9) -> 129.83425 | AX5: =AT5*(1+AX9) -> 143.06394 | BO5: =SUM(AI5:AL5) -> 381 | BP5: =SUM(AM5:AP5) -> 379 | BQ5: =SUM(AQ5:AT5) -> 455.747 | BR5: =BQ5*(1+BR9) -> 524.10905 | BS5: =BR5*(1+BS9) -> 597.48432 | BT5: =BS5*(1+BT9) -> 669.18244 | BU5: =BT5*(1+BU9) -> 736.10068 | BV5: =BU5*(1+BV9) -> 794.98873 | BW5: =BV5*(1+BW9) -> 842.68806 | BX5: =BW5*(1+BX9) -> 884.82246 | BY5: =BX5*(1+BY9) -> 920.21536 | ... CA5: =BZ5*(1+CA9) -> 980.99558
B6: Ttl Revenues | AI6: =SUM(AI4:AI5) -> 241 | AJ6: =SUM(AJ4:AJ5) -> 261 | AK6: =SUM(AK4:AK5) -> 271 | AL6: =SUM(AL4:AL5) -> 285 | AM6: =SUM(AM4:AM5) -> 279 | AN6: =SUM(AN4:AN5) -> 299 | AO6: =SUM(AO4:AO5) -> 300.89 | AP6: =SUM(AP4:AP5) -> 315.11 | ... AT6: =SUM(AT4:AT5) -> 385.37 | AU6: =AU4+AU5 -> 374.758 | AV6: =AV4+AV5 -> 390.046 | AW6: =AW4+AW5 -> 422.97025 | AX6: =AX4+AX5 -> 458.91426 | BO6: =BO4+BO5 -> 1058 | BP6: =BP4+BP5 -> 1194 | BQ6: =SUM(AQ6:AT6) -> 1403.665 | BR6: =BR4+BR5 -> 1642.6523 | BS6: =BS4+BS5 -> 1911.7726 | BT6: =BT4+BT5 -> 2206.8998 | BU6: =BU4+BU5 -> 2527.5414 | BV6: =BV4+BV5 -> 2873.0599 | BW6: =BW4+BW5 -> 3232.4699 | BX6: =BX4+BX5 -> 3621.1227 | BY6: =BY4+BY5 -> 4039.5976 | ... CA6: =CA4+CA5 -> 4981.7593
B8: Thrombectomy Revenue Growth Y/y | AM8: =AM4/AI4-1 -> 0.29655172 | AN8: =AN4/AJ4-1 -> 0.25308642 | AO8: =AO4/AK4-1 -> 0.1396648 | AP8: =AP4/AL4-1 -> 0.15183246 | AQ8: =AQ4/AM4-1 -> 0.20502128 | AR8: =AR4/AN4-1 -> 0.13426601 | AS8: =AS4/AO4-1 -> 0.15882353 | AT8: =AT4/AP4-1 -> 0.15780909 | AU8: 0.17 | AV8: 0.22 | AW8: 0.24 | AX8: 0.24 | BP8: =BP4/BO4-1 -> 0.20384047 | BQ8: =BQ4/BP4-1 -> 0.16308957 | BR8: 0.18 | BS8: 0.175 | BT8: 0.17 | BU8: 0.165 | BV8: 0.16 | BW8: 0.15 | BX8: 0.145 | BY8: 0.14 | BZ8: 0.135 | CA8: 0.13
B9: E & A Revenue Growth Y/y | AM9: =AM5/AI5-1 -> -0.052083333 | AN9: =AN5/AJ5-1 -> -0.03030303 | AO9: =AO5/AK5-1 -> 0.053152174 | AP9: =AP5/AL5-1 -> 0.011808511 | AQ9: =AQ5/AM5-1 -> 0.072483516 | AR9: =AR5/AN5-1 -> 0.13748958 | AS9: =AS5/AO5-1 -> 0.22097224 | AT9: =AT5/AP5-1 -> 0.37369362 | AU9: 0.16 | AV9: 0.105 | AW9: 0.0975 | AX9: 0.095 | BP9: =BP5/BO5-1 -> -0.0052493438 | BQ9: =BQ5/BP5-1 -> 0.20249868 | BR9: 0.15 | BS9: 0.14 | BT9: 0.12 | BU9: 0.1 | BV9: 0.08 | BW9: 0.06 | BX9: 0.05 | BY9: 0.04 | BZ9: 0.035 | CA9: 0.03
B10: Total Revenue Growth Y/y | AM10: =AM6/AI6-1 -> 0.15767635 | AN10: =AN6/AJ6-1 -> 0.14559387 | AO10: =AO6/AK6-1 -> 0.1102952 | AP10: =AP6/AL6-1 -> 0.10564912 | AQ10: =AQ6/AM6-1 -> 0.16179211 | AR10: =AR6/AN6-1 -> 0.135301 | AS10: =AS6/AO6-1 -> 0.17883612 | AT10: =AT6/AP6-1 -> 0.22296976 | ... AX10: =AX6/AT6-1 -> 0.19084065 | BP10: =BP6/BO6-1 -> 0.12854442 | BQ10: =BQ6/BP6-1 -> 0.17559883 | BR10: =BR6/BQ6-1 -> 0.17025949 | BS10: =BS6/BR6-1 -> 0.16383281 | BT10: =BT6/BS6-1 -> 0.15437355 | BU10: =BU6/BT6-1 -> 0.14529051 | BV10: =BV6/BU6-1 -> 0.13670145 | BW10: =BW6/BV6-1 -> 0.12509659 | ... CA10: =CA6/BZ6-1 -> 0.1088017
B12: Thrombectomy % of Ttl Revenues | AI12: =AI4/AI6 -> 0.60165975 | AJ12: =AJ4/AJ6 -> 0.62068966 | AK12: =AK4/AK6 -> 0.66051661 | AL12: =AL4/AL6 -> 0.67017544 | AM12: =AM4/AM6 -> 0.67383513 | AN12: =AN4/AN6 -> 0.67892977 | AO12: =AO4/AO6 -> 0.67798863 | AP12: =AP4/AP6 -> 0.69816889 | ... AX12: =AX4/AX6 -> 0.68825562 | BO12: =AVERAGE(AI12:AL12) -> 0.63826036 | BP12: =AVERAGE(AM12:AP12) -> 0.6822306 | BQ12: =AVERAGE(AN12:AQ12) -> 0.68849879 | BR12: =BR4/BR6 -> 0.68093732 | BS12: =BS4/BS6 -> 0.68747104 | BT12: =BT4/BT6 -> 0.69677715 | BU12: =BU4/BU6 -> 0.7087681 | BV12: =BV4/BV6 -> 0.72329546 | BW12: =BW4/BW6 -> 0.73930521 | BX12: =BX4/BX6 -> 0.75564969 | BY12: =BY4/BY6 -> 0.77220123 | ... CA12: =CA4/CA6 -> 0.8030825
B13: E & A % of Ttl Revenues | AI13: =AI5/AI6 -> 0.39834025 | AJ13: =AJ5/AJ6 -> 0.37931034 | AK13: =AK5/AK6 -> 0.33948339 | AL13: =AL5/AL6 -> 0.32982456 | AM13: =AM5/AM6 -> 0.32616487 | AN13: =AN5/AN6 -> 0.32107023 | AO13: =AO5/AO6 -> 0.32201137 | AP13: =AP5/AP6 -> 0.30183111 | ... AX13: =AX5/AX6 -> 0.31174438 | BO13: =AVERAGE(AI13:AL13) -> 0.36173964 | BP13: =AVERAGE(AM13:AP13) -> 0.3177694 | BQ13: =AVERAGE(AN13:AQ13) -> 0.31150121 | BR13: =BR5/BR6 -> 0.31906268 | BS13: =BS5/BS6 -> 0.31252896 | BT13: =BT5/BT6 -> 0.30322285 | BU13: =BU5/BU6 -> 0.2912319 | BV13: =BV5/BV6 -> 0.27670454 | BW13: =BW5/BW6 -> 0.26069479 | BX13: =BX5/BX6 -> 0.24435031 | BY13: =BY5/BY6 -> 0.22779877 | ... CA13: =CA5/CA6 -> 0.1969175
B15: U.S. Revenues | S15: 82.511 | T15: 86.374 | U15: 90.272 | V15: =355.22-SUM(S15:U15) -> 96.063 | W15: 96 | X15: 78 | Y15: 110 | Z15: =400-SUM(W15:Y15) -> 116 | AA15: 120 | AB15: 128 | AC15: 135 | AD15: =528-SUM(AA15:AC15) -> 145 | AE15: 144 | AF15: 141 | AG15: 149 | AH15: =592-SUM(AE15:AG15) -> 158 | AI15: 172 | AJ15: 186 | AK15: 195 | AL15: =757-SUM(AI15:AK15) -> 204 | AM15: 210 | AN15: 218 | AO15: 226 | AP15: =902-SUM(AM15:AO15) -> 248 | AQ15: 256.86 | AR15: 260.818 | AS15: 275.029 | AT15: =1091.761-SUM(AQ15:AS15) -> 299.054 | AU15: 296.387 | AV15: 305.445 | BK15: =SUM(S15:V15) -> 355.22 | BL15: =SUM(W15:Z15) -> 400 | BM15: =SUM(AA15:AC15) -> 383 | BN15: =SUM(AE15:AG15) -> 434 | BO15: =SUM(AI15:AL15) -> 757 | BP15: =SUM(AM15:AP15) -> 902 | BQ15: =SUM(AQ15:AT15) -> 1091.761
B16: International Revenues | S16: =9.522+36.406 -> 45.928 | T16: =12.231+35.596 -> 47.827 | U16: =11.214+38.016 -> 49.23 | V16: =42.52+149.663-SUM(S16:U16) -> 49.198 | W16: 41 | X16: 27 | Y16: 41 | Z16: =160-SUM(W16:Y16) -> 51 | AA16: 49 | AB16: 56 | AC16: 55 | AD16: =220-SUM(AA16:AC16) -> 60 | AE16: 60 | AF16: 67 | AG16: 65 | AH16: =255-SUM(AE16:AG16) -> 63 | AI16: 69 | AJ16: 75 | AK16: 76 | AL16: =301-SUM(AI16:AK16) -> 81 | AM16: 69 | AN16: 81 | AO16: 77 | AP16: =292-SUM(AM16:AO16) -> 65 | AQ16: 67.28 | AR16: 78.637 | AS16: 79.656 | AT16: =311.904-SUM(AQ16:AS16) -> 86.331 | AU16: 78.371 | AV16: 84.601 | BK16: =SUM(S16:V16) -> 192.183 | BL16: =SUM(W16:Z16) -> 160 | BM16: =SUM(AA16:AC16) -> 160 | BN16: =SUM(AE16:AG16) -> 192 | BO16: =SUM(AI16:AL16) -> 301 | BP16: =SUM(AM16:AP16) -> 292 | BQ16: =SUM(AQ16:AT16) -> 311.904
B17: Ttl Revenues | S17: =SUM(S15:S16) -> 128.439 | T17: =SUM(T15:T16) -> 134.201 | U17: =SUM(U15:U16) -> 139.502 | V17: =SUM(V15:V16) -> 145.261 | W17: =SUM(W15:W16) -> 137 | X17: =SUM(X15:X16) -> 105 | Y17: =SUM(Y15:Y16) -> 151 | Z17: =SUM(Z15:Z16) -> 167 | ... AV17: =SUM(AV15:AV16) -> 390.046 | BK17: =SUM(S17:V17) -> 547.403 | BL17: =SUM(W17:Z17) -> 560 | BM17: =SUM(AA17:AD17) -> 748 | BN17: =SUM(AE17:AH17) -> 847 | BO17: =SUM(AI17:AL17) -> 1058 | BP17: =SUM(AM17:AP17) -> 1194 | BQ17: =SUM(AQ17:AT17) -> 1403.665
B19: U.S. Revenue Growth Y/y | W19: =W15/S15-1 -> 0.16348123 | X19: =X15/T15-1 -> -0.096950471 | Y19: =Y15/U15-1 -> 0.21853952 | Z19: =Z15/V15-1 -> 0.20754088 | AA19: =AA15/W15-1 -> 0.25 | AB19: =AB15/X15-1 -> 0.64102564 | AC19: =AC15/Y15-1 -> 0.22727273 | AD19: =AD15/Z15-1 -> 0.25 | ... AV19: =AV15/AR15-1 -> 0.17110399 | BL19: =BL15/BK15-1 -> 0.12606272 | BM19: =BM15/BL15-1 -> -0.0425 | BN19: =BN15/BM15-1 -> 0.13315927 | BO19: =BO15/BN15-1 -> 0.74423963 | BP19: =BP15/BO15-1 -> 0.19154557 | BQ19: =BQ15/BP15-1 -> 0.21037805
B20: International Revenue Growth Y/y | W20: =W16/S16-1 -> -0.10729838 | X20: =X16/T16-1 -> -0.43546532 | Y20: =Y16/U16-1 -> -0.16717449 | Z20: =Z16/V16-1 -> 0.036627505 | AA20: =AA16/W16-1 -> 0.19512195 | AB20: =AB16/X16-1 -> 1.0740741 | AC20: =AC16/Y16-1 -> 0.34146341 | AD20: =AD16/Z16-1 -> 0.17647059 | ... AV20: =AV16/AR16-1 -> 0.075842161 | BL20: =BL16/BK16-1 -> -0.16746018 | BM20: =BM16/BL16-1 -> 0 | BN20: =BN16/BM16-1 -> 0.2 | BO20: =BO16/BN16-1 -> 0.56770833 | BP20: =BP16/BO16-1 -> -0.029900332 | BQ20: =BQ16/BP16-1 -> 0.068164384
B21: Total Revenue Growth Y/y | W21: =W17/S17-1 -> 0.066654209 | X21: =X17/T17-1 -> -0.21759152 | Y21: =Y17/U17-1 -> 0.082421757 | Z21: =Z17/V17-1 -> 0.14965476 | AA21: =AA17/W17-1 -> 0.23357664 | AB21: =AB17/X17-1 -> 0.75238095 | AC21: =AC17/Y17-1 -> 0.25827815 | AD21: =AD17/Z17-1 -> 0.22754491 | ... AV21: =AV17/AR17-1 -> 0.14903595 | BL21: =BL17/BK17-1 -> 0.023012296 | BM21: =BM17/BL17-1 -> 0.33571429 | BN21: =BN17/BM17-1 -> 0.13235294 | BO21: =BO17/BN17-1 -> 0.24911452 | BP21: =BP17/BO17-1 -> 0.12854442 | BQ21: =BQ17/BP17-1 -> 0.17559883
B23: U.S. % of Ttl Revenues | S23: =S15/S17 -> 0.64241391 | T23: =T15/T17 -> 0.64361666 | U23: =U15/U17 -> 0.64710183 | V23: =V15/V17 -> 0.66131308 | W23: =W15/W17 -> 0.70072993 | X23: =X15/X17 -> 0.74285714 | Y23: =Y15/Y17 -> 0.72847682 | Z23: =Z15/Z17 -> 0.69461078 | ... AV23: =AV15/AV17 -> 0.78309994 | BK23: =BK15/BK17 -> 0.64891862 | BL23: =BL15/BL17 -> 0.71428571 | BM23: =BM15/BM17 -> 0.51203209 | BN23: =BN15/BN17 -> 0.51239669 | BO23: =BO15/BO17 -> 0.71550095 | BP23: =BP15/BP17 -> 0.75544389 | BQ23: =BQ15/BQ17 -> 0.77779313
B24: International % of Ttl Revenues | S24: =S16/S17 -> 0.35758609 | T24: =T16/T17 -> 0.35638334 | U24: =U16/U17 -> 0.35289817 | V24: =V16/V17 -> 0.33868692 | W24: =W16/W17 -> 0.29927007 | X24: =X16/X17 -> 0.25714286 | Y24: =Y16/Y17 -> 0.27152318 | Z24: =Z16/Z17 -> 0.30538922 | ... AV24: =AV16/AV17 -> 0.21690006 | BK24: =BK16/BK17 -> 0.35108138 | BL24: =BL16/BL17 -> 0.28571429 | BM24: =BM16/BM17 -> 0.21390374 | BN24: =BN16/BN17 -> 0.22668241 | BO24: =BO16/BO17 -> 0.28449905 | BP24: =BP16/BP17 -> 0.24455611 | BQ24: =BQ16/BQ17 -> 0.22220687
B26: Revenues | C26: 39 | D26: 42.3 | E26: 50.4 | F26: 54.4 | G26: 57.9 | H26: 65.1 | I26: 67.2 | J26: 73.1 | K26: 73.2 | L26: 80.6 | M26: 83.9 | N26: 96.1 | O26: 102.7 | P26: 109.6 | Q26: 111.8 | R26: 120.8 | S26: =S17 -> 128.439 | T26: =T17 -> 134.201 | U26: =U17 -> 139.502 | V26: =V17 -> 145.261 | W26: 137.3 | X26: 105.1 | Y26: 151.1 | Z26: =560.412-SUM(W26:Y26) -> 166.912 | AA26: 169.2 | AB26: 184.3 | AC26: 190.1 | AD26: =747.59-SUM(AA26:AC26) -> 203.99 | AE26: 203.9 | AF26: 208.3 | AG26: 213.7 | AH26: =847.133-SUM(AE26:AG26) -> 221.233 | AI26: 241.4 | AJ26: 261.5 | AK26: 270.9 | AL26: =1058.52-SUM(AI26:AK26) -> 284.72 | AM26: 278.7 | AN26: 299.4 | AO26: 301 | AP26: =1194.6-SUM(AM26:AO26) -> 315.5 | AQ26: =AQ17 -> 324.14 | AR26: =AR17 -> 339.455 | AS26: =AS17 -> 354.685 | AT26: =1403.665-SUM(AQ26:AS26) -> 385.385 | AU26: =AU17 -> 374.758 | AV26: =AV17 -> 390.046 | AW26: =AW6 -> 422.97025 | AX26: =AX6 -> 458.91426 | BG26: =SUM(C26:F26) -> 186.1 | BH26: =SUM(G26:J26) -> 263.3 | BI26: =SUM(K26:N26) -> 333.8 | BJ26: =SUM(O26:R26) -> 444.9 | BK26: =SUM(S26:V26) -> 547.403 | BL26: =SUM(W26:Z26) -> 560.412 | BM26: =SUM(AA26:AD26) -> 747.59 | BN26: =SUM(AE26:AH26) -> 847.133 | BO26: =SUM(AI26:AL26) -> 1058.52 | BP26: =SUM(AM26:AP26) -> 1194.6 | BQ26: =SUM(AQ26:AT26) -> 1403.665 | BR26: =BR6 -> 1642.6523 | BS26: =BS6 -> 1911.7726 | BT26: =BT6 -> 2206.8998 | BU26: =BU6 -> 2527.5414 | BV26: =BV6 -> 2873.0599 | BW26: =BW6 -> 3232.4699 | BX26: =BX6 -> 3621.1227 | BY26: =BY6 -> 4039.5976 | ... CA26: =CA6 -> 4981.7593
B27: COGS | C27: 12.2 | D27: 14.9 | E27: 16.9 | F27: 18 | G27: 18 | H27: 23.6 | I27: 24.3 | J27: 26.5 | K27: 25.5 | L27: 29.7 | M27: 29.1 | N27: 32.3 | O27: 36.1 | P27: 37.4 | Q27: 36.8 | R27: 42.1 | S27: 44.529 | T27: 40.273 | U27: 43.504 | V27: =175.441-SUM(S27:U27) -> 47.135 | W27: 49.3 | X27: 40.2 | Y27: 60.153 | Z27: =222.237-SUM(W27:Y27) -> 72.584 | AA27: 57.867 | AB27: 65.6 | AC27: 70.2 | AD27: =272.208-SUM(AA27:AC27) -> 78.541 | AE27: 76.5 | AF27: 74.3 | AG27: 78.4 | AH27: =311.926-SUM(AE27:AG27) -> 82.726 | AI27: 90.3 | AJ27: 94.6 | AK27: 93.2 | AL27: =375.9-SUM(AI27:AK27) -> 97.8 | AM27: 97.5 | AN27: 136.6 | AO27: 100.7 | AP27: =439.6-SUM(AM27:AO27) -> 104.8 | AQ27: 108.257 | AR27: 115.445 | AS27: 114.269 | AT27: =461.228-SUM(AQ27:AS27) -> 123.257 | AU27: 121.347 | AV27: 125.102 | AW27: =AW26*(1-AW43) -> 130.27484 | AX27: =AX26*(1-AX43) -> 139.96885 | BG27: =SUM(C27:F27) -> 62 | BH27: =SUM(G27:J27) -> 92.4 | BI27: =SUM(K27:N27) -> 116.6 | BJ27: =SUM(O27:R27) -> 152.4 | BK27: =SUM(S27:V27) -> 175.441 | BL27: =SUM(W27:Z27) -> 222.237 | BM27: =SUM(AA27:AD27) -> 272.208 | BN27: =SUM(AE27:AH27) -> 311.926 | BO27: =SUM(AI27:AL27) -> 375.9 | BP27: =SUM(AM27:AP27) -> 439.6 | BQ27: =SUM(AQ27:AT27) -> 461.228 | BR27: =BR26*(1-BR43) -> 542.07526 | BS27: =BS26*(1-BS43) -> 588.82597 | BT27: =BT26*(1-BT43) -> 655.44923 | BU27: =BU26*(1-BU43) -> 732.98699 | BV27: =BV26*(1-BV43) -> 818.82208 | BW27: =BW26*(1-BW43) -> 905.09158 | BX27: =BX26*(1-BX43) -> 995.80874 | BY27: =BY26*(1-BY43) -> 1090.6914 | ... CA27: =CA26*(1-CA43) -> 1295.2574
B28: GP | C28: =C26-C27 -> 26.8 | D28: =D26-D27 -> 27.4 | E28: =E26-E27 -> 33.5 | F28: =F26-F27 -> 36.4 | G28: =G26-G27 -> 39.9 | H28: =H26-H27 -> 41.5 | I28: =I26-I27 -> 42.9 | J28: =J26-J27 -> 46.6 | ... AX28: =AX26-AX27 -> 318.94541 | BG28: =SUM(C28:F28) -> 124.1 | BH28: =SUM(G28:J28) -> 170.9 | BI28: =SUM(K28:N28) -> 217.2 | BJ28: =SUM(O28:R28) -> 292.5 | BK28: =BK26-BK27 -> 371.962 | BL28: =BL26-BL27 -> 338.175 | BM28: =BM26-BM27 -> 475.382 | BN28: =BN26-BN27 -> 535.207 | BO28: =BO26-BO27 -> 682.62 | BP28: =BP26-BP27 -> 755 | BQ28: =SUM(AQ28:AT28) -> 942.437 | BR28: =BR26-BR27 -> 1100.577 | BS28: =BS26-BS27 -> 1322.9467 | BT28: =BT26-BT27 -> 1551.4505 | BU28: =BU26-BU27 -> 1794.5544 | BV28: =BV26-BV27 -> 2054.2378 | BW28: =BW26-BW27 -> 2327.3783 | BX28: =BX26-BX27 -> 2625.314 | BY28: =BY26-BY27 -> 2948.9063 | ... CA28: =CA26-CA27 -> 3686.5019
B29: R&D | C29: 3.2 | D29: 4.8 | E29: 4.6 | F29: 5.5 | G29: 5 | H29: 6.3 | I29: 6.5 | J29: 6.1 | K29: 7 | L29: 8.1 | M29: 8.1 | N29: 8.4 | O29: 8 | P29: 8.2 | Q29: 39.9 | R29: 10.9 | S29: 11.667 | T29: 13.462 | U29: 13.733 | V29: =51.723-SUM(S29:U29) -> 12.861 | W29: 12.946 | X29: 22.725 | Y29: 34.923 | Z29: =90.049-SUM(W29:Y29) -> 19.455 | AA29: 18.076 | AB29: 17.738 | AC29: 16.73 | AD29: =104.552-SUM(AA29:AC29) -> 52.008 | AE29: 20.56 | AF29: 19.559 | AG29: 21.32 | AH29: =79.407-SUM(AE29:AG29) -> 17.968 | AI29: 19.98 | AJ29: 21.5 | AK29: 21 | AL29: =84.4-SUM(AI29:AK29) -> 21.92 | AM29: 24.6 | AN29: 24.9 | AO29: 25.2 | AP29: =94.8-SUM(AM29:AO29) -> 20.1 | AQ29: 22.077 | AR29: 23.218 | AS29: 22.677 | AT29: =89.766-SUM(AQ29:AS29) -> 21.794 | AU29: 22.382 | AV29: 25.396 | AW29: =AW26*AW44 -> 31.722769 | AX29: =AX26*AX44 -> 34.418569 | BG29: =SUM(C29:F29) -> 18.1 | BH29: =SUM(G29:J29) -> 23.9 | BI29: =SUM(K29:N29) -> 31.6 | BJ29: =SUM(O29:R29) -> 67 | BK29: =SUM(S29:V29) -> 51.723 | BL29: =SUM(W29:Z29) -> 90.049 | BM29: =SUM(AA29:AD29) -> 104.552 | BN29: =SUM(AE29:AH29) -> 79.407 | BO29: =SUM(AI29:AL29) -> 84.4 | BP29: =SUM(AM29:AP29) -> 94.8 | BQ29: =SUM(AQ29:AT29) -> 89.766 | BR29: =BR26*BR44 -> 123.19892 | BS29: =BS26*BS44 -> 145.29472 | BT29: =BT26*BT44 -> 178.75888 | BU29: =BU26*BU44 -> 214.84102 | BV29: =BV26*BV44 -> 244.21009 | BW29: =BW26*BW44 -> 282.84112 | BX29: =BX26*BX44 -> 325.90104 | BY29: =BY26*BY44 -> 383.76177 | ... CA29: =CA26*CA44 -> 473.26713
B30: SG&A | C30: 19.5 | D30: 26.4 | E30: 26.8 | F30: 29.2 | G30: 33.1 | H30: 35.9 | I30: 37.7 | J30: 41.6 | K30: 42.7 | L30: 44.2 | M30: 46 | N30: 51.5 | O30: 54.5 | P30: 54.8 | Q30: 55.9 | R30: 61.2 | S30: 61.091 | T30: 67.665 | U30: 69.289 | V30: =272.733-SUM(S30:U30) -> 74.688 | W30: 74.453 | X30: 59.8 | Y30: 76.2 | Z30: =287.068-SUM(W30:Y30) -> 76.615 | AA30: 79.798 | AB30: 90.63 | AC30: 94.397 | AD30: =378.331-SUM(AA30:AC30) -> 113.506 | AE30: 110.9 | AF30: 114.615 | AG30: 108.57 | AH30: =449.718-SUM(AE30:AG30) -> 115.633 | AI30: 123.07 | AJ30: 127.4 | AK30: 125.9 | AL30: =506.4-SUM(AI30:AK30) -> 130.03 | AM30: 144.4 | AN30: 141.9 | AO30: 139.7 | AP30: =574-SUM(AM30:AO30) -> 148 | AQ30: 153.456 | AR30: 159.964 | AS30: 168.901 | AT30: =663.422-SUM(AQ30:AS30) -> 181.101 | AU30: 192.795 | AV30: 198.509 | AW30: =AW26*AW45 -> 195.83523 | AX30: =AX26*AX45 -> 212.01839 | BG30: =SUM(C30:F30) -> 101.9 | BH30: =SUM(G30:J30) -> 148.3 | BI30: =SUM(K30:N30) -> 184.4 | BJ30: =SUM(O30:R30) -> 226.4 | BK30: =SUM(S30:V30) -> 272.733 | BL30: =SUM(W30:Z30) -> 287.068 | BM30: =SUM(AA30:AD30) -> 378.331 | BN30: =SUM(AE30:AH30) -> 449.718 | BO30: =SUM(AI30:AL30) -> 506.4 | BP30: =SUM(AM30:AP30) -> 574 | BQ30: =SUM(AQ30:AT30) -> 663.422 | BR30: =BR26*BR45 -> 770.40392 | BS30: =BS26*BS45 -> 865.07711 | BT30: =BT26*BT45 -> 984.27729 | BU30: =BU26*BU45 -> 1109.5907 | BV30: =BV26*BV45 -> 1249.7811 | BW30: =BW26*BW45 -> 1398.0432 | BX30: =BX26*BX45 -> 1549.8405 | BY30: =BY26*BY45 -> 1716.829 | ... CA30: =CA26*CA45 -> 2042.5213
B31: Acquired In-Process R&D | C31: 0 | D31: 0 | E31: 0 | F31: 0 | G31: 0 | H31: 0 | I31: 0 | J31: 0 | K31: 0 | L31: 0 | M31: 0 | N31: 0 | O31: 0 | P31: 0 | Q31: 0 | R31: 0 | S31: 0 | T31: 0 | U31: 0 | V31: =0-SUM(S31:U31) -> 0 | W31: 0 | X31: 0 | Y31: 0 | Z31: =0-SUM(W31:Y31) -> 0 | AA31: 0 | AB31: 0 | AC31: 0 | AD31: =0-SUM(AA31:AC31) -> 0 | AE31: 0 | AF31: 0 | AG31: 0 | AH31: =0-SUM(AE31:AG31) -> 0 | AI31: 0 | AJ31: 0 | AK31: 18.2 | AL31: =18.2-SUM(AI31:AK31) -> 0 | AM31: 0 | AN31: 0 | AO31: 0 | AP31: =0-SUM(AM31:AO31) -> 0 | AQ31: 0 | AR31: 0 | AS31: 0 | AT31: =0-SUM(AQ31:AS31) -> 0 | AU31: 0 | AV31: 0 | AW31: 0 | AX31: 0 | BG31: =SUM(C31:F31) -> 0 | BH31: =SUM(G31:J31) -> 0 | BI31: =SUM(K31:N31) -> 0 | BJ31: =SUM(O31:R31) -> 0 | BK31: =SUM(S31:V31) -> 0 | BL31: =SUM(W31:Z31) -> 0 | BM31: =SUM(AA31:AD31) -> 0 | BN31: =SUM(AE31:AH31) -> 0 | BO31: =SUM(AI31:AL31) -> 18.2 | BP31: =SUM(AM31:AP31) -> 0 | BQ31: =SUM(AQ31:AT31) -> 0 | BR31: 0 | BS31: 0 | BT31: 0 | BU31: 0 | BV31: 0 | BW31: 0 | BX31: 0 | BY31: 0 | BZ31: 0 | CA31: 0
B32: Impairment Charges | C32: 0.1 | D32: =31.2-SUM(D29:D31) -> 0 | E32: =31.3-SUM(E29:E31) -> -0.1 | F32: =34.6-SUM(F29:F31) -> -0.1 | G32: =38.1-SUM(G29:G31) -> 0 | H32: 0 | I32: 0.1 | J32: 0.1 | K32: 0 | L32: -0.1 | M32: 0 | N32: 0 | O32: 0.1 | P32: -0.1 | Q32: 0 | R32: -0.1 | S32: 0 | T32: 0 | U32: 0 | V32: =0-SUM(S32:U32) -> 0 | W32: 0 | X32: 0 | Y32: 0 | Z32: =0-SUM(W32:Y32) -> 0 | AA32: 0 | AB32: 0 | AC32: 0 | AD32: =0-SUM(AA32:AC32) -> 0 | AE32: 0 | AF32: 0 | AG32: 0 | AH32: =0-SUM(AE32:AG32) -> 0 | AI32: 0 | AJ32: 0 | AK32: 0 | AL32: =0-SUM(AI32:AK32) -> 0 | AM32: 0 | AN32: 76.9 | AO32: 0 | AP32: =76.94-SUM(AM32:AO32) -> 0.04 | AQ32: 0 | AR32: 0 | AS32: 0 | AT32: =0-SUM(AQ32:AS32) -> 0 | AU32: 0 | AV32: 0 | AW32: 0 | AX32: 0 | BG32: =SUM(C32:F32) -> -0.1 | BH32: =SUM(G32:J32) -> 0.2 | BI32: =SUM(K32:N32) -> -0.1 | BJ32: =SUM(O32:R32) -> -0.1 | BK32: =SUM(S32:V32) -> 0 | BL32: =SUM(W32:Z32) -> 0 | BM32: =SUM(AA32:AD32) -> 0 | BN32: =SUM(AE32:AH32) -> 0 | BO32: =SUM(AI32:AL32) -> 0 | BP32: =SUM(AM32:AP32) -> 76.94 | BQ32: =SUM(AQ32:AT32) -> 0 | BR32: 115.3 | BS32: 0 | BT32: 0 | BU32: 0 | BV32: 0 | BW32: 0 | BX32: 0 | BY32: 0 | BZ32: 0 | CA32: 0
B33: Operating Income | C33: =C28-SUM(C29:C32) -> 4 | D33: =D28-SUM(D29:D32) -> -3.8 | E33: =E28-SUM(E29:E32) -> 2.2 | F33: =F28-SUM(F29:F32) -> 1.8 | G33: =G28-SUM(G29:G32) -> 1.8 | H33: =H28-SUM(H29:H32) -> -0.7 | I33: =I28-SUM(I29:I32) -> -1.4 | J33: =J28-SUM(J29:J32) -> -1.2 | ... T33: =T28-SUM(T29:T32) -> 12.801 | U33: 12.976 | V33: =V28-SUM(V29:V32) -> 10.577 | W33: =W28-SUM(W29:W32) -> 0.601 | X33: =X28-SUM(X29:X32) -> -17.625 | Y33: =Y28-SUM(Y29:Y32) -> -20.176 | Z33: =Z28-SUM(Z29:Z32) -> -1.742 | AA33: =AA28-SUM(AA29:AA32) -> 13.459 | AB33: =AB28-SUM(AB29:AB32) -> 10.332 | AC33: =AC28-SUM(AC29:AC32) -> 8.773 | ... AX33: =AX28-SUM(AX29:AX32) -> 72.508453 | BG33: =SUM(C33:F33) -> 4.2 | BH33: =SUM(G33:J33) -> -1.5 | BI33: =SUM(K33:N33) -> 1.3 | BJ33: =SUM(O33:R33) -> -0.8 | BK33: =BK28-SUM(BK29:BK32) -> 47.506 | BL33: =BL28-SUM(BL29:BL32) -> -38.942 | BM33: =BM28-SUM(BM29:BM32) -> -7.501 | BN33: =BN28-SUM(BN29:BN32) -> 6.082 | BO33: =BO28-SUM(BO29:BO32) -> 73.62 | BP33: =BP28-SUM(BP29:BP32) -> 9.26 | BQ33: =SUM(AQ33:AT33) -> 189.249 | BR33: =BR28-SUM(BR29:BR32)+BR32 -> 206.97419 | BS33: =BS28-SUM(BS29:BS32) -> 312.57482 | BT33: =BT28-SUM(BT29:BT32) -> 388.41436 | BU33: =BU28-SUM(BU29:BU32) -> 470.12269 | BV33: =BV28-SUM(BV29:BV32) -> 560.24668 | BW33: =BW28-SUM(BW29:BW32) -> 646.49398 | BX33: =BX28-SUM(BX29:BX32) -> 749.5724 | BY33: =BY28-SUM(BY29:BY32) -> 848.3155 | BZ33: =BZ28-SUM(BZ29:BZ32) -> 988.44279 | CA33: =CA28-SUM(CA29:CA32) -> 1170.7134
B34: Interest and Other Income, net | C34: 0.3 | D34: -0.4 | E34: -0.1 | F34: 0.1 | G34: 0.3 | H34: 0.3 | I34: 0.3 | J34: -0.4 | K34: 0.3 | L34: 0.4 | M34: 0.6 | N34: 0 | O34: 0.5 | P34: 0.4 | Q34: 0.9 | R34: 0.7 | S34: =0.733+0.024 -> 0.757 | T34: =0.784-0.071 -> 0.713 | U34: =0.759-0.772 -> -0.013 | V34: =2.854-0.227-SUM(S34:U34) -> 1.17 | W34: =0.299-1.555 -> -1.256 | X34: =0.108+0.508 -> 0.616 | Y34: =0.413+0.014 -> 0.427 | Z34: =1.267-0.243-SUM(W34:Y34) -> 1.237 | AA34: =0.48-1.476 -> -0.996 | AB34: =0.299-0.408 -> -0.109 | AC34: =0.138-1.137 -> -0.999 | AD34: =0.938-3.939-SUM(AA34:AC34) -> -0.897 | AE34: =-0.041-1.01 -> -1.051 | AF34: =-0.07-0.9 -> -0.97 | AG34: =-0.04-2.35 -> -2.39 | AH34: =0.137-2.327-SUM(AE34:AG34) -> 2.221 | AI34: 0.644 | AJ34: 1.6 | AK34: 0.7 | AL34: =6.09-SUM(AI34:AK34) -> 3.146 | AM34: 2.5 | AN34: 3.1 | AO34: 4.4 | AP34: =11.59-SUM(AM34:AO34) -> 1.59 | AQ34: 3.508 | AR34: 4.482 | AS34: 3.487 | AT34: =15.876-SUM(AQ34:AS34) -> 4.399 | AU34: 3.454 | AV34: 5.148 | AW34: =AV50*0.045 -> 9.237195 | AX34: =AW50*0.045 -> 11.409795 | BG34: =SUM(C34:F34) -> -0.1 | BH34: =SUM(G34:J34) -> 0.5 | BI34: =SUM(K34:N34) -> 1.3 | BJ34: =SUM(O34:R34) -> 2.5 | BK34: =SUM(S34:V34) -> 2.627 | BL34: =SUM(W34:Z34) -> 1.024 | BM34: =SUM(AA34:AD34) -> -3.001 | BN34: =SUM(AE34:AH34) -> -2.19 | BO34: =SUM(AI34:AL34) -> 6.09 | BP34: =SUM(AM34:AP34) -> 11.59 | BQ34: =SUM(AQ34:AT34) -> 15.876 | BR34: =BQ50*$CA$53 -> 29.9024 | BS34: =BR50*$CA$53 -> 63.254624 | BT34: =BS50*$CA$53 -> 110.15814 | BU34: =BT50*$CA$53 -> 172.37999 | BV34: =BU50*$CA$53 -> 251.53632 | BW34: =BV50*$CA$53 -> 351.54798 | BX34: =BW50*$CA$53 -> 474.50675 | BY34: =BX50*$CA$53 -> 625.3133 | ... CA34: =BZ50*$CA$53 -> 1028.0462
B35: Pretax Income | C35: =C33+C34 -> 4.3 | D35: =D33+D34 -> -4.2 | E35: =E33+E34 -> 2.1 | F35: =F33+F34 -> 1.9 | G35: =G33+G34 -> 2.1 | H35: =H33+H34 -> -0.4 | I35: =I33+I34 -> -1.1 | J35: =J33+J34 -> -1.6 | ... AX35: =AX33+AX34 -> 83.918248 | BG35: =SUM(C35:F35) -> 4.1 | BH35: =SUM(G35:J35) -> -1 | BI35: =SUM(K35:N35) -> 2.6 | BJ35: =SUM(O35:R35) -> 1.7 | BK35: =BK33+BK34 -> 50.133 | BL35: =BL33+BL34 -> -37.918 | BM35: =BM33+BM34 -> -10.502 | BN35: =BN33+BN34 -> 3.892 | BO35: =BO33+BO34 -> 79.71 | BP35: =BP33+BP34 -> 20.85 | BQ35: =SUM(AQ35:AT35) -> 205.125 | BR35: =BR33+BR34 -> 236.87659 | BS35: =BS33+BS34 -> 375.82945 | BT35: =BT33+BT34 -> 498.5725 | BU35: =BU33+BU34 -> 642.50268 | BV35: =BV33+BV34 -> 811.783 | BW35: =BW33+BW34 -> 998.04197 | BX35: =BX33+BX34 -> 1224.0791 | BY35: =BY33+BY34 -> 1473.6288 | ... CA35: =CA33+CA34 -> 2198.7597
B36: Tax Expense (Benefit) | C36: 1.7 | D36: -1.5 | E36: 1.2 | F36: 0.2 | G36: -0.2 | H36: -3.4 | I36: -13 | J36: 0.9 | K36: 1.4 | L36: 0.5 | M36: 0.5 | N36: -5.9 | O36: -1.9 | P36: -4.9 | Q36: 1.6 | R36: 0.9 | S36: 1.455 | T36: -2.735 | U36: 1.963 | V36: =3.131-SUM(S36:U36) -> 2.448 | W36: -1.634 | X36: -4.129 | Y36: -9.855 | Z36: =-18.761-SUM(W36:Y36) -> -3.143 | AA36: 1.541 | AB36: 1.9 | AC36: -0.249 | AD36: =-13.125-SUM(AA36:AC36) -> -16.317 | AE36: -5.183 | AF36: 2.52 | AG36: 5.3 | AH36: =5.894-SUM(AE36:AG36) -> 3.257 | AI36: 0.09 | AJ36: 0.5 | AK36: 4.09 | AL36: =-11.3-SUM(AI36:AK36) -> -15.98 | AM36: 3.6 | AN36: -17.6 | AO36: 10.3 | AP36: =6.86-SUM(AM36:AO36) -> 10.56 | AQ36: 4.635 | AR36: 0.04 | AS36: 6.474 | AT36: =27.438-SUM(AQ36:AS36) -> 16.289 | AU36: 9.104 | AV36: 11.376 | AW36: =AW35*AW47 -> 17.106161 | AX36: =AX35*AX47 -> 19.301197 | BG36: =SUM(C36:F36) -> 1.6 | BH36: =SUM(G36:J36) -> -15.7 | BI36: =SUM(K36:N36) -> -3.5 | BJ36: =SUM(O36:R36) -> -4.3 | BK36: =SUM(S36:V36) -> 3.131 | BL36: =SUM(W36:Z36) -> -18.761 | BM36: =SUM(AA36:AD36) -> -13.125 | BN36: =SUM(AE36:AH36) -> 5.894 | BO36: =SUM(AI36:AL36) -> -11.3 | BP36: =SUM(AM36:AP36) -> 6.86 | BQ36: =SUM(AQ36:AT36) -> 27.438 | BR36: =BR35*BR47 -> 28.425191 | BS36: =BS35*BS47 -> 82.682478 | BT36: =BT35*BT47 -> 109.68595 | BU36: =BU35*BU47 -> 147.77562 | BV36: =BV35*BV47 -> 186.71009 | BW36: =BW35*BW47 -> 229.54965 | BX36: =BX35*BX47 -> 281.5382 | BY36: =BY35*BY47 -> 338.93462 | ... CA36: =CA35*CA47 -> 505.71472
B37: Consolidated Net Income | C37: 2.5 | D37: -2.7 | E37: 0.9 | F37: 1.6 | G37: 2.3 | H37: 3 | I37: 11.9 | J37: -2.4 | K37: -3.1 | L37: -1.6 | M37: 0.2 | N37: 9.1 | O37: 5.5 | P37: 13.4 | Q37: -22.4 | R37: 6.5 | S37: =S35-S36 -> 10.454 | T37: =T35-T36 -> 16.249 | U37: =U35-U36 -> 11 | V37: =V35-V36 -> 9.299 | W37: =W35-W36 -> 0.979 | X37: =X35-X36 -> -12.88 | Y37: =Y35-Y36 -> -9.894 | Z37: =Z35-Z36 -> 2.638 | ... AX37: =AX35-AX36 -> 64.617051 | BG37: =SUM(C37:F37) -> 2.3 | BH37: =SUM(G37:J37) -> 14.8 | BI37: =SUM(K37:N37) -> 4.6 | BJ37: =SUM(O37:R37) -> 3 | BK37: =BK35-BK36 -> 47.002 | BL37: =BL35-BL36 -> -19.157 | BM37: =BM35-BM36 -> 2.623 | BN37: =BN35-BN36 -> -2.002 | BO37: =BO35-BO36 -> 91.01 | BP37: =BP35-BP36 -> 13.99 | BQ37: =SUM(AQ37:AT37) -> 177.687 | BR37: =BR35-BR36 -> 208.4514 | BS37: =BS35-BS36 -> 293.14697 | BT37: =BT35-BT36 -> 388.88655 | BU37: =BU35-BU36 -> 494.72706 | BV37: =BV35-BV36 -> 625.07291 | BW37: =BW35-BW36 -> 768.49231 | BX37: =BX35-BX36 -> 942.54094 | BY37: =BY35-BY36 -> 1134.6942 | ... CA37: =CA35-CA36 -> 1693.0449
B38: Net Income attr to Non-Cont. | C38: 2 | D38: -2.15 | E38: 0.58 | F38: 0.85 | G38: -0.2 | H38: 0 | I38: -0.3 | J38: 0 | K38: 0 | L38: 0 | M38: 0 | N38: 0 | O38: 0 | P38: 0 | Q38: -3.5 | R38: -0.02 | S38: -0.244 | T38: -0.537 | U38: -0.483 | V38: =-1.454-SUM(S38:U38) -> -0.19 | W38: -0.537 | X38: -0.94 | Y38: -1.061 | Z38: =-3.555-SUM(W38:Y38) -> -1.017 | AA38: -0.91 | AB38: -0.932 | AC38: -0.819 | AD38: =-2.641-SUM(AA38:AC38) -> 0.02 | AE38: 0 | AF38: 0 | AG38: 0 | AH38: 0 | AI38: 0 | AJ38: 0 | AK38: 0 | AL38: 0 | AM38: 0 | AN38: 0 | AO38: 0 | AP38: 0 | AQ38: 0 | AR38: 0 | AS38: 0 | AT38: 0 | AU38: 0 | AV38: 0 | AW38: 0 | AX38: 0 | BG38: =SUM(C38:F38) -> 1.28 | BH38: =SUM(G38:J38) -> -0.5 | BI38: =SUM(K38:N38) -> 0 | BJ38: =SUM(O38:R38) -> -3.52 | BK38: =SUM(S38:V38) -> -1.454 | BL38: -3.555 | BM38: -2.661 | BN38: 0 | BO38: 0 | BP38: 0 | BQ38: =SUM(AQ38:AT38) -> 0 | BR38: 0 | BS38: 0 | BT38: 0 | BU38: 0 | BV38: 0 | BW38: 0 | BX38: 0 | BY38: 0 | BZ38: 0 | CA38: 0
B39: Net Income attr to PEN | C39: =C37-C38 -> 0.5 | D39: =D37-D38 -> -0.55 | E39: =E37-E38 -> 0.32 | F39: =F37-F38 -> 0.75 | G39: =G37-G38 -> 2.5 | H39: =H37-H38 -> 3 | I39: =I37-I38 -> 12.2 | J39: =J37-J38 -> -2.4 | ... AV39: =AV37-AV38 -> 34.811 | AW39: 48.28 | AX39: 56.5 | BG39: =SUM(C39:F39) -> 1.02 | BH39: =SUM(G39:J39) -> 15.3 | BI39: =SUM(K39:N39) -> 4.6 | BJ39: =SUM(O39:R39) -> 6.52 | BK39: =BK37-BK38 -> 48.456 | BL39: =BL37-BL38 -> -15.602 | BM39: =BM37-BM38 -> 5.284 | BN39: =BN37-BN38 -> -2.002 | BO39: =BO37-BO38 -> 91.01 | BP39: =BP37-BP38 -> 13.99 | BQ39: =SUM(AQ39:AT39) -> 177.687 | BR39: =BR37-BR38 -> 208.4514 | BS39: =BS37-BS38 -> 293.14697 | BT39: =BT37-BT38 -> 388.88655 | BU39: =BU37-BU38 -> 494.72706 | BV39: =BV37-BV38 -> 625.07291 | BW39: =BW37-BW38 -> 768.49231 | BX39: =BX37-BX38 -> 942.54094 | BY39: =BY37-BY38 -> 1134.6942 | ... CA39: =CA37-CA38 -> 1693.0449 | CB39: =CA39*(1+$CA$54) -> 1734.5245 | CC39: =CB39*(1+$CA$54) -> 1777.0204 | CD39: =CC39*(1+$CA$54) -> 1820.5574 | CE39: =CD39*(1+$CA$54) -> 1865.161 | CF39: =CE39*(1+$CA$54) -> 1910.8575 | CG39: =CF39*(1+$CA$54) -> 1957.6735 | CH39: =CG39*(1+$CA$54) -> 2005.6365 | CI39: =CH39*(1+$CA$54) -> 2054.7746 | ... DO39: =DN39*(1+$CA$54) -> 4458.0711
B40: SC | C40: 5 | D40: 5 | E40: 8 | F40: 12 | G40: 30 | H40: 30 | I40: 31 | J40: 30 | K40: 32 | L40: 33 | M40: 33 | N40: 33 | O40: 34 | P40: 34 | Q40: 34 | R40: 34 | S40: 34.507 | T40: 34.694 | U40: 34.84 | V40: 35 | W40: 35 | X40: 35.4 | Y40: 36.207 | Z40: 37.651 | AA40: 36.455 | AB40: 36.523 | AC40: 36.617 | AD40: 36.7 | AE40: 37.646 | AF40: 37.767 | AG40: 37.918 | AH40: 37.841 | AI40: 39.07 | AJ40: 38.15 | AK40: 38.956 | AL40: 38.4 | AM40: 39.3 | AN40: 38.8 | AO40: 38.6 | AP40: 38.63 | AQ40: 38.562 | AR40: 38.834 | AS40: 39.078 | AT40: 38.63 | AU40: 39.275 | AV40: 39.353 | BG40: 12 | BH40: 31 | BI40: 33 | BJ40: 34 | BK40: 34.8 | BL40: 35.5 | BM40: =AD40 -> 36.7 | BN40: =AH40 -> 37.841 | BO40: =AL40 -> 38.4 | BP40: =AP40 -> 38.63 | BQ40: =AVERAGE(AQ40:AT40) -> 38.776 | BR40: =BP40*1.05 -> 40.5615 | BS40: =BR40*1.05 -> 42.589575 | BT40: =BS40*1.05 -> 44.719054 | BU40: =BT40*1.05 -> 46.955006 | BV40: =BU40*1.05 -> 49.302757 | BW40: =BV40*1.05 -> 51.767895 | BX40: =BW40*1.05 -> 54.356289 | BY40: =BX40*1.05 -> 57.074104 | BZ40: =BY40*1.05 -> 59.927809 | CA40: =BZ40*1.05 -> 62.924199
B41: EPS | C41: =C39/C40 -> 0.1 | D41: =D39/D40 -> -0.11 | E41: =E39/E40 -> 0.04 | F41: =F39/F40 -> 0.0625 | G41: =G39/G40 -> 0.083333333 | H41: =H39/H40 -> 0.1 | I41: =I39/I40 -> 0.39354839 | J41: =J39/J40 -> -0.08 | ... AV41: =AV39/AV40 -> 0.88458313 | BG41: =BG39/BG40 -> 0.085 | BH41: =BH39/BH40 -> 0.49354839 | BI41: =BI39/BI40 -> 0.13939394 | BJ41: =BJ39/BJ40 -> 0.19176471 | BK41: =BK39/BK40 -> 1.3924138 | BL41: =BL39/BL40 -> -0.43949296 | BM41: =BM39/BM40 -> 0.1439782 | BN41: =BN39/BN40 -> -0.052905579 | ... BP41: =BP39/BP40 -> 0.36215377 | BQ41: =SUM(AQ41:AT41) -> 4.5817424 | BR41: =BR39/BR40 -> 5.1391442 | BS41: =BS39/BS40 -> 6.8830687 | BT41: =BT39/BT40 -> 8.6962159 | BU41: =BU39/BU40 -> 10.536194 | BV41: =BV39/BV40 -> 12.678255 | BW41: =BW39/BW40 -> 14.84496 | BX41: =BX39/BX40 -> 17.340053 | BY41: =BY39/BY40 -> 19.881069 | ... CA41: =CA39/CA40 -> 26.906102
B43: Gross Profit Margin | C43: =C28/C26 -> 0.68717949 | D43: =D28/D26 -> 0.64775414 | E43: =E28/E26 -> 0.66468254 | F43: =F28/F26 -> 0.66911765 | G43: =G28/G26 -> 0.68911917 | H43: =H28/H26 -> 0.6374808 | I43: =I28/I26 -> 0.63839286 | J43: =J28/J26 -> 0.6374829 | ... AR43: =AR28/AR26 -> 0.65991074 | AS43: 0.67 | AT43: =AT28/AT26 -> 0.68017178 | AU43: 0.678 | AV43: 0.685 | AW43: 0.692 | AX43: 0.695 | BG43: =BG28/BG26 -> 0.66684578 | BH43: =BH28/BH26 -> 0.6490695 | BI43: =BI28/BI26 -> 0.65068904 | BJ43: =BJ28/BJ26 -> 0.65745111 | BK43: =BK28/BK26 -> 0.67950304 | BL43: =BL28/BL26 -> 0.60343997 | BM43: =BM28/BM26 -> 0.63588598 | BN43: =BN28/BN26 -> 0.63178627 | ... BQ43: =BQ28/BQ26 -> 0.67141163 | BR43: 0.67 | BS43: 0.692 | BT43: 0.703 | BU43: 0.71 | BV43: 0.715 | BW43: 0.72 | BX43: 0.725 | BY43: 0.73 | BZ43: 0.735 | CA43: 0.74
B44: R&D as % of Revenues | C44: =C29/C26 -> 0.082051282 | D44: =D29/D26 -> 0.11347518 | E44: =E29/E26 -> 0.091269841 | F44: =F29/F26 -> 0.10110294 | G44: =G29/G26 -> 0.086355786 | H44: =H29/H26 -> 0.096774194 | I44: =I29/I26 -> 0.09672619 | J44: =J29/J26 -> 0.083447332 | ... AR44: =AR29/AR26 -> 0.068397873 | AS44: 0.068 | AT44: =AT29/AT26 -> 0.056551241 | AU44: 0.073 | AV44: 0.075 | AW44: 0.075 | AX44: 0.075 | BG44: =BG29/BG26 -> 0.097259538 | BH44: =BH29/BH26 -> 0.090770984 | BI44: =BI29/BI26 -> 0.094667466 | BJ44: =BJ29/BJ26 -> 0.15059564 | BK44: =BK29/BK26 -> 0.094487973 | BL44: =BL29/BL26 -> 0.16068357 | BM44: =BM29/BM26 -> 0.13985206 | BN44: =BN29/BN26 -> 0.093736167 | ... BQ44: =BQ29/BQ26 -> 0.063951156 | BR44: 0.075 | BS44: 0.076 | BT44: 0.081 | BU44: 0.085 | BV44: 0.085 | BW44: 0.0875 | BX44: 0.09 | BY44: 0.095 | BZ44: 0.095 | CA44: 0.095
B45: SG&A as % of Revenues | C45: =C30/C26 -> 0.5 | D45: =D30/D26 -> 0.62411348 | E45: =E30/E26 -> 0.53174603 | F45: =F30/F26 -> 0.53676471 | G45: =G30/G26 -> 0.5716753 | H45: =H30/H26 -> 0.55145929 | I45: =I30/I26 -> 0.5610119 | J45: =J30/J26 -> 0.56908345 | ... AR45: =AR30/AR26 -> 0.47123772 | AS45: 0.47 | AT45: =AT30/AT26 -> 0.46992229 | AU45: 0.466 | AV45: 0.464 | AW45: 0.463 | AX45: 0.462 | BG45: =BG30/BG26 -> 0.54755508 | BH45: =BH30/BH26 -> 0.56323585 | BI45: =BI30/BI26 -> 0.5524266 | BJ45: =BJ30/BJ26 -> 0.5088784 | BK45: =BK30/BK26 -> 0.49823074 | BL45: =BL30/BL26 -> 0.51224456 | BM45: =BM30/BM26 -> 0.5060675 | BN45: =BN30/BN26 -> 0.5308706 | ... BQ45: =BQ30/BQ26 -> 0.47263556 | BR45: 0.469 | BS45: 0.4525 | BT45: 0.446 | BU45: 0.439 | BV45: 0.435 | BW45: 0.4325 | BX45: 0.428 | BY45: 0.425 | BZ45: 0.42 | CA45: 0.41
B46: Operating Profit Margin | C46: =C33/C26 -> 0.1025641 | D46: =D33/D26 -> -0.089834515 | E46: =E33/E26 -> 0.043650794 | F46: =F33/F26 -> 0.033088235 | G46: =G33/G26 -> 0.031088083 | H46: =H33/H26 -> -0.010752688 | I46: =I33/I26 -> -0.020833333 | J46: =J33/J26 -> -0.016415869 | ... AX46: =AX33/AX26 -> 0.158 | BG46: =BG33/BG26 -> 0.022568512 | BH46: =BH33/BH26 -> -0.0056969237 | BI46: =BI33/BI26 -> 0.0038945476 | BJ46: =BJ33/BJ26 -> -0.0017981569 | BK46: =BK33/BK26 -> 0.086784325 | BL46: =BL33/BL26 -> -0.069488162 | BM46: =BM33/BM26 -> -0.010033575 | BN46: =BN33/BN26 -> 0.0071795102 | ... CA46: =CA33/CA26 -> 0.235
B47: Effective Tax Rate | C47: =C36/C35 -> 0.39534884 | D47: =D36/D35 -> 0.35714286 | E47: =E36/E35 -> 0.57142857 | F47: =F36/F35 -> 0.10526316 | G47: =G36/G35 -> -0.095238095 | H47: =H36/H35 -> 8.5 | I47: =I36/I35 -> 11.818182 | J47: =J36/J35 -> -0.5625 | ... AR47: =AR36/AR35 -> 0.00088280733 | AS47: 0.2 | AT47: =AT36/AT35 -> 0.25598755 | AU47: 0.23 | AV47: 0.23 | AW47: 0.23 | AX47: 0.23 | BG47: =BG36/BG35 -> 0.3902439 | BH47: =BH36/BH35 -> 15.7 | BI47: =BI36/BI35 -> -1.3461538 | BJ47: =BJ36/BJ35 -> -2.5294118 | BK47: =BK36/BK35 -> 0.062453873 | BL47: =BL36/BL35 -> 0.49477821 | BM47: =BM36/BM35 -> 1.249762 | BN47: =BN36/BN35 -> 1.5143885 | ... BQ47: =BQ36/BQ35 -> 0.13376234 | BR47: 0.12 | BS47: 0.22 | BT47: 0.22 | BU47: 0.23 | BV47: 0.23 | BW47: 0.23 | BX47: 0.23 | BY47: 0.23 | BZ47: 0.23 | CA47: 0.23
B48: Net Profit Margin | C48: =C37/C26 -> 0.064102564 | D48: =D37/D26 -> -0.063829787 | E48: =E37/E26 -> 0.017857143 | F48: =F37/F26 -> 0.029411765 | G48: =G37/G26 -> 0.039723661 | H48: =H37/H26 -> 0.046082949 | I48: =I37/I26 -> 0.17708333 | J48: =J37/J26 -> -0.032831737 | ... AR48: =AR37/AR26 -> 0.13336083 | AS48: =AS39/AS26 -> 0.12927245 | AT48: =AT37/AT26 -> 0.12284599 | AU48: =AU39/AU26 -> 0.086946776 | AV48: =AV39/AV26 -> 0.089248448 | AW48: =AW39/AW26 -> 0.11414514 | AX48: =AX39/AX26 -> 0.12311668 | BG48: =BG39/BG26 -> 0.0054809242 | BH48: =BH39/BH26 -> 0.058108621 | BI48: =BI39/BI26 -> 0.013780707 | BJ48: =BJ39/BJ26 -> 0.014654979 | BK48: =BK39/BK26 -> 0.088519793 | BL48: =BL39/BL26 -> -0.027840232 | BM48: =BM39/BM26 -> 0.0070680453 | BN48: =BN39/BN26 -> -0.0023632653 | ... CA48: =CA39/CA26 -> 0.3398488
B50: Cash & C.E.s | S50: 95.606 | T50: 77.261 | U50: 111.581 | V50: 72.779 | W50: 72.456 | X50: 134.381 | Y50: 80.115 | Z50: 69.67 | AA50: 55.632 | AB50: 82.277 | AC50: 66.29 | AD50: 59.379 | AE50: 68.163 | AF50: 58.234 | AG50: 54.844 | AH50: 69.858 | AI50: 94.688 | AJ50: 114.167 | AK50: 100.757 | AL50: 167.486 | AM50: 223.114 | AN50: 288.332 | AO50: 280.476 | AP50: 324.4 | AQ50: 376.054 | AR50: 421.768 | AS50: 321.029 | AT50: 186.89 | AU50: 241.289 | AV50: 205.271 | AW50: =AV50+AW39 -> 253.551 | AX50: =AW50+AX39 -> 310.051 | BK50: =V50 -> 72.779 | BL50: =Z50 -> 69.67 | BM50: =AD50 -> 59.379 | BN50: =AH50 -> 69.858 | BO50: =AL50 -> 167.486 | BP50: =AP50 -> 324.4 | BQ50: 186.89 | BR50: =BQ50+BR39 -> 395.3414 | BS50: =BR50+BS39 -> 688.48837 | BT50: =BS50+BT39 -> 1077.3749 | BU50: =BT50+BU39 -> 1572.102 | BV50: =BU50+BV39 -> 2197.1749 | BW50: =BV50+BW39 -> 2965.6672 | BX50: =BW50+BX39 -> 3908.2081 | BY50: =BX50+BY39 -> 5042.9023 | ... CA50: =BZ50+CA39 -> 8118.3338
B51: Marketable Investments | S51: 99.241 | T51: 109.996 | U51: 82.864 | V51: 116.61 | W51: 95.766 | X51: 143.914 | Y51: 188.611 | Z51: 195.162 | AA51: 186.977 | AB51: 156.722 | AC51: 200.637 | AD51: 195.496 | AE51: 172.178 | AF51: 146.135 | AG51: 129.583 | AH51: 118.172 | AI51: 104.409 | AJ51: 106.896 | AK51: 148.098 | AL51: 121.701 | AM51: 90.36 | AN51: 51.363 | AO51: 10.548 | AP51: 15.727 | AQ51: 2.794 | AR51: 2.795 | AS51: 149.267 | AT51: 357.919 | AU51: 374.371 | AV51: 453.524 | BK51: =V51 -> 116.61 | BL51: =Z51 -> 195.162 | BM51: =AD51 -> 195.496 | BN51: =AH51 -> 118.172 | BO51: =AL51 -> 121.701 | BP51: =AP51 -> 15.727 | BQ51: 357.919
B52: A/R | S52: 94.679 | T52: 99.011 | U52: 101.828 | V52: 105.901 | W52: 103.963 | X52: 97.613 | Y52: 112.817 | Z52: 114.608 | AA52: 126.415 | AB52: 136.61 | AC52: 120.074 | AD52: 133.94 | AE52: 143.417 | AF52: 187.389 | AG52: 189.006 | AH52: 203.384 | AI52: 207.364 | AJ52: 208.965 | AK52: 206.615 | AL52: 201.768 | AM52: 191.989 | AN52: 200.831 | AO52: 176.051 | AP52: 167.667 | AQ52: 167.981 | AR52: 175.536 | AS52: 183.43 | AT52: 190.02 | AU52: 183.295 | AV52: 190.407 | BK52: =V52 -> 105.901 | BL52: =Z52 -> 114.608 | BM52: =AD52 -> 133.94 | BN52: =AH52 -> 203.384 | BO52: =AL52 -> 201.768 | BP52: =AP52 -> 167.667 | BQ52: 190.02
B53: Inventories | S53: 121.691 | T53: 132.735 | U53: 140.359 | V53: 152.992 | W53: 166.152 | X53: 183.442 | Y53: 191.547 | Z53: 219.527 | AA53: 245.321 | AB53: 254.977 | AC53: 258.316 | AD53: 263.504 | AE53: 274.349 | AF53: 295.883 | AG53: 320.304 | AH53: 334.006 | AI53: 344.042 | AJ53: 358.77 | AK53: 374.245 | AL53: 388.023 | AM53: 398.366 | AN53: 373.799 | AO53: 393.413 | AP53: 406.737 | AQ53: 415.863 | AR53: 427.628 | AS53: 432.365 | AT53: 431.549 | AU53: 438.539 | AV53: 442.65 | BK53: =V53 -> 152.992 | BL53: =Z53 -> 219.527 | BM53: =AD53 -> 263.504 | BN53: =AH53 -> 334.006 | BO53: =AL53 -> 388.023 | BP53: =AP53 -> 406.737 | BQ53: 431.549 | BS53: Invested Capital | BV53: Avg. (2024-2025) | BX53: Projected ROIC: | BZ53: ROIC | CA53: 0.16 | CD53: Preface:
B54: Prepaid Expenses | S54: 11.869 | T54: 15.601 | U54: 14.702 | V54: 14.852 | W54: 15.403 | X54: 16.545 | Y54: 17.109 | Z54: 18.735 | AA54: 20.782 | AB54: 22.526 | AC54: 22.67 | AD54: 29.155 | AE54: 32.219 | AF54: 30.32 | AG54: 29.888 | AH54: 30.279 | AI54: 35.987 | AJ54: 39.078 | AK54: 38.761 | AL54: 36.424 | AM54: 31.194 | AN54: 29.47 | AO54: 31.265 | AP54: 36.589 | AQ54: 37.017 | AR54: 37.757 | AS54: 55.429 | AT54: 50.298 | AU54: 37.912 | AV54: 52.27 | BK54: =V54 -> 14.852 | BL54: =Z54 -> 18.735 | BM54: =AD54 -> 29.155 | BN54: =AH54 -> 30.279 | BO54: =AL54 -> 36.424 | BP54: =AP54 -> 36.589 | BQ54: 50.298 | BS54: 2024 | BT54: 2025 | BV54: 2024-2025 | BX54: 2025 | BZ54: Terminal | CA54: 0.0245 | CE54: I am treating this as an exercise to improve my excel modeling skills, to become more comfortable with researching public companies using a variety of professional resources, and to begin developing a deeper understanding of The Business's products/markets, operations and current financial standing
B55: PP&E | S55: 35.38 | T55: 37.94 | U55: 45.625 | V55: 51.812 | W55: 58.698 | X55: 62.188 | Y55: 64.906 | Z55: 48.169 | AA55: 50.314 | AB55: 50.854 | AC55: 56.632 | AD55: 58.856 | AE55: 60.327 | AF55: 63.458 | AG55: 64.082 | AH55: 65.015 | AI55: 65.224 | AJ55: 65.958 | AK55: 65.632 | AL55: 72.691 | AM55: 75.744 | AN55: 57.709 | AO55: 59.919 | AP55: 62.641 | AQ55: 72.465 | AR55: 84.825 | AS55: 97.73 | AT55: 117.436 | AU55: 134.059 | AV55: 146.718 | BK55: =V55 -> 51.812 | BL55: =Z55 -> 48.169 | BM55: =AD55 -> 58.856 | BN55: =AH55 -> 65.015 | BO55: =AL55 -> 72.691 | BP55: =AP55 -> 62.641 | BQ55: 117.436 | BS55: =SUM(BP50:BP53)-BP64+BP56+BP58+BP57 -> 1095.523 | BT55: =SUM(BQ50:BQ53)-BQ64+BQ56+BQ58+BQ57 -> 1337.387 | BV55: =AVERAGE(BS55:BS55) -> 1095.523 | BX55: =AVERAGE(BR33)*(1-BR47) -> 182.13729 | BZ55: RFR (10-year yield) | CA55: ='Bull Case (30%)'!BV64 -> 0.0511 | CE55: I understand that to accurately value a firm's common stock, the analyst must derive an NPV from a series of discounted cash flows, not net income (which adheres to GAAP and includes non-cash expenses such as D&A, and does not consider the firm's future cash outflows such as CapEx investment demand or ΔNWC)
B56: Operating Leases | S56: 42.376 | T56: 42.476 | U56: 41.817 | V56: 43.717 | W56: 43.168 | X56: 42.669 | Y56: 41.778 | Z56: 41.192 | AA56: 40.691 | AB56: 92.791 | AC56: 133.552 | AD56: 131.955 | AE56: 176.892 | AF56: 177.423 | AG56: 174.684 | AH56: 192.636 | AI56: 189.839 | AJ56: 187.494 | AK56: 184.52 | AL56: 188.756 | AM56: 185.845 | AN56: 183.316 | AO56: 180.923 | AP56: 177.787 | AQ56: 175.331 | AR56: 174.059 | AS56: 170.715 | AT56: 173.587 | AU56: 170.273 | AV56: 167.194 | BK56: =V56 -> 43.717 | BL56: =Z56 -> 41.192 | BM56: =AD56 -> 131.955 | BN56: =AH56 -> 192.636 | BO56: =AL56 -> 188.756 | BP56: =AP56 -> 177.787 | BQ56: 173.587 | BX56: =BX55/BV55 -> 0.16625601 | BZ56: ERP (Avg. market return - (less) RFR) | CA56: =10.1%-CA55 -> 0.0499 | CE56: I am discounting net income under the somewhat-flawed assumption that in the long run, net income and FCF converge (as CapEx "switches" from investment to maintenance and D&A roughly balances with the period's CapEx spend)
B57: Financing Leases | T57: 0 | U57: 0 | V57: 39.924 | W57: 39.287 | X57: 37.927 | Y57: 38.798 | Z57: 38.065 | AA57: 37.697 | AB57: 37.031 | AC57: 36.845 | AD57: 36.276 | AE57: 35.55 | AF57: 34.743 | AG57: 34.114 | AH57: 33.323 | AI57: 32.569 | AJ57: 31.751 | AK57: 31.364 | AL57: 31.092 | AM57: 30.234 | AN57: 29.366 | AO57: 28.888 | AP57: 28.018 | AQ57: 27.126 | AR57: 27.606 | AS57: 26.79 | AT57: 25.972 | AU57: 25.209 | AV57: 24.357 | BK57: =V57 -> 39.924 | BL57: =Z57 -> 38.065 | BM57: =AD57 -> 36.276 | BN57: =AH57 -> 33.323 | BO57: =AL57 -> 31.092 | BP57: =AP57 -> 28.018 | BQ57: 25.972 | BS57: Capital Structure | BZ57: Equity β (1-year avg.) | CA57: ='Notes | Analysis'!T240 -> 0.76850681 | CD57: Assumptions:
B58: Intangible Assets, net | S58: 26.813 | T58: 26.031 | U58: 25.494 | V58: 25.407 | W58: 25.024 | X58: 10.645 | Y58: 10.64 | Z58: 10.639 | AA58: 10.097 | AB58: 9.895 | AC58: 9.49 | AD58: 90.618 | AE58: 88.472 | AF58: 86.162 | AG58: 83.36 | AH58: 81.161 | AI58: 78.669 | AJ58: 76.116 | AK58: 73.452 | AL58: 71.056 | AM58: 68.421 | AN58: 6.955 | AO58: 6.92 | AP58: 6.513 | AQ58: 6.469 | AR58: 6.552 | AS58: 6.368 | AT58: 6.186 | AU58: 5.946 | AV58: 5.742 | BK58: =V58 -> 25.407 | BL58: =Z58 -> 10.639 | BM58: =AD58 -> 90.618 | BN58: =AH58 -> 81.161 | BO58: =AL58 -> 71.056 | BP58: =AP58 -> 6.513 | BQ58: 6.186 | BS58: Mkt Cap | BV58: ='Main | Overview'!C5 -> 12569.424 | BZ58: Discount (Cost of Equity) | CA58: =+CA55+(CA56*CA57) -> 0.08944849 | CE58: Revenue growth continues, with sequential Thrombectomy revenues remaining strong into the terminal period
B59: Goodwill | S59: 7.659 | T59: 7.765 | U59: 7.452 | V59: 7.656 | W59: 7.509 | X59: 7.665 | Y59: 8.004 | Z59: 8.372 | AA59: 8.006 | AB59: 8.109 | AC59: 7.911 | AD59: 166.388 | AE59: 166.232 | AF59: 165.779 | AG59: 165.426 | AH59: 166.046 | AI59: 166.161 | AJ59: 166.166 | AK59: 165.954 | AL59: 166.27 | AM59: 166.103 | AN59: 166.05 | AO59: 166.355 | AP59: 165.826 | AQ59: 166.123 | AR59: 166.752 | AS59: 166.748 | AT59: 166.75 | AU59: 166.589 | AV59: 166.523 | BK59: =V59 -> 7.656 | BL59: =Z59 -> 8.372 | BM59: =AD59 -> 166.388 | BN59: =AH59 -> 166.046 | BO59: =AL59 -> 166.27 | BP59: =AP59 -> 165.826 | BQ59: 166.75 | BS59: Debt to Ttl Mkt Cap | BV59: ='Main | Overview'!C7/('Main | Overview'!C7+BV58) -> 0 | CE59: Margins continue to expand (with no noise on a Y/y basis) as revenues mature … company is able to continue innovating and developing a competitive product mix
B60: Deferred Tax Assets | S60: 31.862 | T60: 34.661 | U60: 32.818 | V60: 31.305 | W60: 32.945 | X60: 36.474 | Y60: 47.91 | Z60: 50.139 | AA60: 48.978 | AB60: 47.67 | AC60: 49.454 | AD60: 65.698 | AE60: 70.08 | AF60: 68.404 | AG60: 62.827 | AH60: 64.213 | AI60: 65.173 | AJ60: 66.671 | AK60: 64.236 | AL60: 85.158 | AM60: 84.661 | AN60: 108.852 | AO60: 105.851 | AP60: 100.332 | AQ60: 102.355 | AR60: 109.141 | AS60: 94.478 | AT60: 79.188 | AU60: 79.972 | AV60: 79.376 | BK60: =V60 -> 31.305 | BL60: =Z60 -> 50.139 | BM60: =AD60 -> 65.698 | BN60: =AH60 -> 64.213 | BO60: =AL60 -> 85.158 | BP60: =AP60 -> 100.332 | BQ60: 79.188 | BS60: Mkt Equity to Ttl Mkt Cap | BV60: =BV58/(BV58+'Main | Overview'!C7) -> 1 | BZ60: NPV | CA60: =NPV(CA58,BR39:DO39) -> 14772.798 | CF60: R&D as a percentage of revenues remains at a constant 10% as the company innovates into the 2030's (look into patent expiry for product mix, as well as R&D + FDA pipeline)
B61: Other LT Assets | S61: 1.613 | T61: 1.632 | U61: 9.63 | V61: 2.946 | W61: 3.869 | X61: 6.737 | Y61: 8.069 | Z61: 8.705 | AA61: 9.914 | AB61: 10.756 | AC61: 11.37 | AD61: 12.985 | AE61: 13.694 | AF61: 13.97 | AG61: 13.483 | AH61: 12.793 | AI61: 11.173 | AJ61: 10.5 | AK61: 14.743 | AL61: 25.88 | AM61: 33.814 | AN61: 38.518 | AO61: 38.514 | AP61: 40.939 | AQ61: 43.729 | AR61: 40.39 | AS61: 40.02 | AT61: 40.716 | AU61: 40.984 | AV61: 40.691 | BK61: =V61 -> 2.946 | BL61: =Z61 -> 8.705 | BM61: =AD61 -> 12.985 | BN61: =AH61 -> 12.793 | BO61: =AL61 -> 25.88 | BP61: =AP61 -> 40.939 | BQ61: 40.716 | BS61: Debt / Equity | BV61: =BV59/BV60 -> 0 | BZ61: SC | CA61: ='Main | Overview'!C4 -> 39.389 | CF61: SG&A expenses begin to tail off as a % of revenues (applying simple theory that as revenue growth takes off, fixed costs remain relatively the same/grow at a lower rate than revenues)
B62: Ttl Assets | S62: =SUM(S50:S61) -> 568.789 | T62: =SUM(T50:T61) -> 585.109 | U62: =SUM(U50:U61) -> 614.17 | V62: =SUM(V50:V61) -> 665.901 | W62: =SUM(W50:W61) -> 664.24 | X62: =SUM(X50:X61) -> 780.2 | Y62: =SUM(Y50:Y61) -> 810.304 | Z62: =SUM(Z50:Z61) -> 822.983 | ... AV62: =SUM(AV50:AV61) -> 1974.723 | BK62: =SUM(BK50:BK61) -> 665.901 | BL62: =SUM(BL50:BL61) -> 822.983 | BM62: =SUM(BM50:BM61) -> 1244.25 | BN62: =SUM(BN50:BN61) -> 1370.886 | BO62: =SUM(BO50:BO61) -> 1556.305 | BP62: =SUM(BP50:BP61) -> 1533.176 | BQ62: =SUM(BQ50:BQ61) -> 1826.511 | BZ62: FV | CA62: =CA60/CA61 -> 375.04882 | CG62: No SBC adjustments -- SBC is a very real expense in the form of dilution, but is still non-cash; excluding SBC adjustments leads to an overstatement in the firms calculated equity value (for fully integrated 3 statement model)
BS63: Cost of Equity | BZ63: CP | CA63: ='Main | Overview'!C3 -> 319.11 | CE63: Stable corporate tax rate -- TCJA is not allowed to sunset this year and The Company must remain relatively unaffected by tariff regime policies
B64: A/P | S64: 7.692 | T64: 8.743 | U64: 11.962 | V64: 15.111 | W64: 15.843 | X64: 14.432 | Y64: 14.544 | Z64: 14.109 | AA64: 15.389 | AB64: 13.712 | AC64: 13.679 | AD64: 13.421 | AE64: 14.137 | AF64: 23.096 | AG64: 25.365 | AH64: 26.679 | AI64: 28.199 | AJ64: 25.819 | AK64: 27.996 | AL64: 27.155 | AM64: 32.4545 | AN64: 32.822 | AO64: 33.151 | AP64: 31.326 | AQ64: 31.153 | AR64: 28.121 | AS64: 29.821 | AT64: 34.736 | AU64: 43.658 | AV64: 44.728 | BK64: =V64 -> 15.111 | BL64: =Z64 -> 14.109 | BM64: =AD64 -> 13.421 | BN64: =AH64 -> 26.679 | BO64: =AL64 -> 27.155 | BP64: =AP64 -> 31.326 | BQ64: 34.736 | BS64: RFR (10-year yield) | BV64: ='Bull Case (30%)'!BV64 -> 0.0511 | BZ64: Change Δ | CA64: =CA62/CA63-1 -> 0.17529634 | CB64: =IF(CA64>0,"Upside","Downside") -> Upside | CF64: The Company is only taxed at the federal corporate rate of 21% + California's 8.84% (does not consider any exotic tax circumstances)
B65: Accrued Liabilities | S65: 58.032 | T65: 57.276 | U65: 70.163 | V65: 67.63 | W65: 65.335 | X65: 57.718 | Y65: 87.691 | Z65: 85.795 | AA65: 90.214 | AB65: 86.503 | AC65: 93.22 | AD65: 99.796 | AE65: 105.533 | AF65: 111.405 | AG65: 101.672 | AH65: 106.3 | AI65: 105.869 | AJ65: 105.606 | AK65: 104.184 | AL65: 110.555 | AM65: 106.549 | AN65: 104.071 | AO65: 105.55 | AP65: 112.429 | AQ65: 112.675 | AR65: 114.389 | AS65: 124.273 | AT65: 132.163 | AU65: 151.543 | AV65: 172.27 | BK65: =V65 -> 67.63 | BL65: =Z65 -> 85.795 | BM65: =AD65 -> 99.796 | BN65: =AH65 -> 106.3 | BO65: =AL65 -> 110.555 | BP65: =AP65 -> 112.429 | BQ65: 132.163 | BS65: Equity β (1-year avg.) | BV65: ='Notes | Analysis'!T240 -> 0.76850681 | BZ65: {=_xlfn.IFS(CA64>=25%,"Strong Buy",CA64>=10.00001%,"Buy",AND(CA64<=10%,CA64>=-4.9999%),"Hold",AND(CA64<=-5%,CA64>=-14.999999%),"Sell",CA64<=-15%,"Strong Sell")} -> Buy | CE65: Higher than average terminal rate value (~1.4x GDP)
B66: Current Operating Lease Liabilities | S66: 3.688 | T66: 3.742 | U66: 4.042 | V66: 4.142 | W66: 4.435 | X66: 4.446 | Y66: 4.484 | Z66: 4.697 | AA66: 4.822 | AB66: 6.347 | AC66: 7.531 | AD66: 8.267 | AE66: 8.66 | AF66: 9.297 | AG66: 9.417 | AH66: 10.033 | AI66: 10.303 | AJ66: 10.715 | AK66: 10.827 | AL66: 11.203 | AM66: 11.52 | AN66: 11.776 | AO66: 12.068 | AP66: 12.221 | AQ66: 12.51 | AR66: 12.855 | AS66: 13.086 | AT66: 13.841 | AU66: 14.144 | AV66: 14.398 | BK66: =V66 -> 4.142 | BL66: =Z66 -> 4.697 | BM66: =AD66 -> 8.267 | BN66: =AH66 -> 10.033 | BO66: =AL66 -> 11.203 | BP66: =AP66 -> 12.221 | BQ66: 13.841 | BS66: Market Return(1-year avg.) | BV66: ='Bull Case (30%)'!BV66 -> 0.18 | CE66: Long-term NI ≈ FCF (sub assumptions: CapEx purely maintenance ... D&A netting out CapEx balance, No delta in WC)
B67: Current Finance Lease Liabilities | S67: 0 | T67: 0 | U67: 0 | V67: 4.165 | W67: 2.461 | X67: 1.016 | Y67: 1.336 | Z67: 1.331 | AA67: 1.437 | AB67: 1.484 | AC67: 1.627 | AD67: 1.713 | AE67: 1.769 | AF67: 1.806 | AG67: 1.878 | AH67: 1.92 | AI67: 1.957 | AJ67: 1.984 | AK67: 2.071 | AL67: 2.231 | AM67: 2.28 | AN67: 2.325 | AO67: 2.416 | AP67: 2.369 | AQ67: 2.292 | AR67: 2.396 | AS67: 2.423 | AT67: 2.393 | AU67: 2.386 | AV67: 2.38 | BK67: =V67 -> 4.165 | BL67: =Z67 -> 1.331 | BM67: =AD67 -> 1.713 | BN67: =AH67 -> 1.92 | BO67: =AL67 -> 2.231 | BP67: =AP67 -> 2.369 | BQ67: 2.393 | BS67: Cost of Equity | BV67: =(BV64+BV65)*(BV66-BV64) -> 0.10564732 | CF67: CapEx = Dep. & Am.
B68: Non-current Operating Lease Liabilities | S68: 46.07 | T68: 46.146 | U68: 45.4 | V68: 47.242 | W68: 46.416 | X68: 45.925 | Y68: 44.998 | Z68: 44.183 | AA68: 43.525 | AB68: 94.444 | AC68: 138.169 | AD68: 137.045 | AE68: 182.438 | AF68: 183.155 | AG68: 180.897 | AH68: 198.955 | AI68: 196.837 | AJ68: 194.655 | AK68: 192.117 | AL68: 197.229 | AM68: 194.537 | AN68: 192.216 | AO68: 189.96 | AP68: 187.068 | AQ68: 184.652 | AR68: 183.493 | AS68: 180.3 | AT68: 182.751 | AU68: 179.424 | AV68: 176.304 | BK68: =V68 -> 47.242 | BL68: =Z68 -> 44.183 | BM68: =AD68 -> 137.045 | BN68: =AH68 -> 198.955 | BO68: =AL68 -> 197.229 | BP68: =AP68 -> 187.068 | BQ68: 182.751 | CF68: ΔNWC = 0
B69: Non-current Finance Lease Liabilities | S69: 0 | T69: 0 | U69: 0 | V69: 26.748 | W69: 26.483 | X69: 26.202 | Y69: 27.391 | Z69: 27.066 | AA69: 27 | AB69: 26.691 | AC69: 26.775 | AD69: 26.523 | AE69: 26.122 | AF69: 25.654 | AG69: 25.325 | AH69: 24.865 | AI69: 24.423 | AJ69: 23.922 | AK69: 23.779 | AL69: 23.68 | AM69: 23.098 | AN69: 22.501 | AO69: 22.245 | AP69: 21.731 | AQ69: 21.201 | AR69: 21.785 | AS69: 21.223 | AT69: 20.714 | AU69: 20.221 | AV69: 19.628 | BK69: =V69 -> 26.748 | BL69: =Z69 -> 27.066 | BM69: =AD69 -> 26.523 | BN69: =AH69 -> 24.865 | BO69: =AL69 -> 23.68 | BP69: =AP69 -> 21.731 | BQ69: 20.714 | BS69: Cost of Debt | CE69: No future debt issuance - I only calculated for Cost of Equity... Net income is more sensitive to changes in capital structure, and will distort NPV calculation further between NI and FCF approaches
B70: Other Liabilities | S70: 16.644 | T70: 15.019 | U70: 15.662 | V70: 15.25 | W70: 15.15 | X70: 7.3 | Y70: 10.147 | Z70: 8.014 | AA70: 7.966 | AB70: 7.661 | AC70: 7.635 | AD70: 3.558 | AE70: 3.612 | AF70: 3.472 | AG70: 3.295 | AH70: 3.276 | AI70: 3.241 | AJ70: 3.288 | AK70: 3.265 | AL70: 5.308 | AM70: 5.876 | AN70: 7.619 | AO70: 9.453 | AP70: 15.103 | AQ70: 15.942 | AR70: 17.819 | AS70: 14.53 | AT70: 12.318 | AU70: 13.25 | AV70: 14.249 | BK70: =V70 -> 15.25 | BL70: =Z70 -> 8.014 | BM70: =AD70 -> 3.558 | BN70: =AH70 -> 3.276 | BO70: =AL70 -> 5.308 | BP70: =AP70 -> 15.103 | BQ70: 12.318 | BS70: Cost of Debt | BV70: 0 | CD70: Strategies to improve model's efficacy:
B71: Ttl Liabilities | S71: =SUM(S64:S70) -> 132.126 | T71: =SUM(T64:T70) -> 130.926 | U71: =SUM(U64:U70) -> 147.229 | V71: =SUM(V64:V70) -> 180.288 | W71: =SUM(W64:W70) -> 176.123 | X71: =SUM(X64:X70) -> 157.039 | Y71: =SUM(Y64:Y70) -> 190.591 | Z71: =SUM(Z64:Z70) -> 185.195 | ... AV71: =SUM(AV64:AV70) -> 443.957 | BK71: =SUM(BK64:BK70) -> 180.288 | BL71: =SUM(BL64:BL70) -> 185.195 | BM71: =SUM(BM64:BM70) -> 290.323 | BN71: =SUM(BN64:BN70) -> 372.028 | BO71: =SUM(BO64:BO70) -> 377.361 | BP71: =SUM(BP64:BP70) -> 382.247 | BQ71: =SUM(BQ64:BQ70) -> 398.916 | BS71: Tax Rate | BV71: 0.2 | CE71: Focus on bringing the amount of assumptions down (many of which can addressed by simply completing a projected Stmt. of Cash Flow)
B72: SE | S72: 436.663 | T72: 454.183 | U72: 466.941 | V72: 485.613 | W72: 488.117 | X72: 623.161 | Y72: 619.712 | Z72: 637.788 | AA72: 650.471 | AB72: 673.376 | AC72: 684.603 | AD72: 953.927 | AE72: 959.302 | AF72: 970.015 | AG72: 973.752 | AH72: 998.858 | AI72: 1024.469 | AJ72: 1066.543 | AK72: 1104.138 | AL72: 1178.94 | AM72: 1203.531 | AN72: 1161.231 | AO72: 1104.28 | AP72: 1150.931 | AQ72: 1212.882 | AR72: 1293.95 | AS72: 1358.696 | AT72: 1427.603 | AU72: 1473.812 | AV72: 1530.766 | BK72: =V72 -> 485.613 | BL72: =Z72 -> 637.788 | BM72: =AD72 -> 953.927 | BN72: =AH72 -> 998.858 | BO72: =AL72 -> 1178.94 | BP72: =AP72 -> 1150.931 | BQ72: 1427.603 | BS72: After Tax Cost of Debt | BV72: =BV70*(1-BV71) -> 0 | CE72: An easy one - Complete Stmt of Cash Flows and build a true DCF model that calculates NPV from cash flows, not net income… begin building assumptions for projecting the following:
B73: Ttl L + SE | S73: =SUM(S71:S72) -> 568.789 | T73: =SUM(T71:T72) -> 585.109 | U73: =SUM(U71:U72) -> 614.17 | V73: =SUM(V71:V72) -> 665.901 | W73: =SUM(W71:W72) -> 664.24 | X73: =SUM(X71:X72) -> 780.2 | Y73: =SUM(Y71:Y72) -> 810.303 | Z73: =SUM(Z71:Z72) -> 822.983 | ... AV73: =SUM(AV71:AV72) -> 1974.723 | BK73: =SUM(BK71:BK72) -> 665.901 | BL73: =SUM(BL71:BL72) -> 822.983 | BM73: =SUM(BM71:BM72) -> 1244.25 | BN73: =SUM(BN71:BN72) -> 1370.886 | BO73: =SUM(BO71:BO72) -> 1556.301 | BP73: =SUM(BP71:BP72) -> 1533.178 | BQ73: =SUM(BQ71:BQ72) -> 1826.519 | CG73: Non-cash expenses
BS74: WACC | BV74: =(BV60*BV67)+(BV59*BV72*(1-BV71)) -> 0.10564732 | CG74: Future CapEx investment + differentiating maintenance v. investment CapEx
B75: Current Ratio | S75: =SUM(S50:S54)/SUM(S64:S67) -> 6.0952861 | T75: =SUM(T50:T54)/SUM(T64:T67) -> 6.2298992 | U75: =SUM(U50:U54)/SUM(U64:U67) -> 5.2378985 | V75: =SUM(V50:V54)/SUM(V64:V67) -> 5.0867015 | W75: =SUM(W50:W54)/SUM(W64:W67) -> 5.1518042 | X75: =SUM(X50:X54)/SUM(X64:X67) -> 7.4201799 | Y75: =SUM(Y50:Y54)/SUM(Y64:Y67) -> 5.462024 | Z75: =SUM(Z50:Z54)/SUM(Z64:Z67) -> 5.8311181 | ... AV75: =SUM(AV50:AV54)/SUM(AV64:AV67) -> 5.749615 | BK75: =SUM(BK50:BK54)/SUM(BK64:BK67) -> 5.0867015 | BL75: =SUM(BL50:BL54)/SUM(BL64:BL67) -> 5.8311181 | BM75: =SUM(BM50:BM54)/SUM(BM64:BM67) -> 5.5315795 | BN75: =SUM(BN50:BN54)/SUM(BN64:BN67) -> 5.2141625 | BO75: =SUM(BO50:BO54)/SUM(BO64:BO67) -> 6.0564892 | BP75: =SUM(BP50:BP54)/SUM(BP64:BP67) -> 6.0066311 | BQ75: =SUM(BQ50:BQ54)/SUM(BQ64:BQ67) -> 6.6436743 | CG75: Sensitivity to potential swings in working capital -- stress-test model in dedicated page
B76: Quick Ratio | S76: =(SUM(S50:S54)-S53)/SUM(S64:S67) -> 4.3421166 | T76: =(SUM(T50:T54)-T53)/SUM(T64:T67) -> 4.3271885 | U76: =(SUM(U50:U54)-U53)/SUM(U64:U67) -> 3.6089802 | V76: =(SUM(V50:V54)-V53)/SUM(V64:V67) -> 3.4063571 | W76: =(SUM(W50:W54)-W53)/SUM(W64:W67) -> 3.2652996 | X76: =(SUM(X50:X54)-X53)/SUM(X64:X67) -> 5.0566021 | Y76: =(SUM(Y50:Y54)-Y53)/SUM(Y64:Y67) -> 3.6893434 | Z76: =(SUM(Z50:Z54)-Z53)/SUM(Z64:Z67) -> 3.7587792 | ... AV76: =(SUM(AV50:AV54)-AV53)/SUM(AV64:AV67) -> 3.8561358 | BK76: =(SUM(BK50:BK54)-BK53)/SUM(BK64:BK67) -> 3.4063571 | BL76: =(SUM(BL50:BL54)-BL53)/SUM(BL64:BL67) -> 3.7587792 | BM76: =(SUM(BM50:BM54)-BM53)/SUM(BM64:BM67) -> 3.3926963 | BN76: =(SUM(BN50:BN54)-BN53)/SUM(BN64:BN67) -> 2.9095921 | BO76: =(SUM(BO50:BO54)-BO53)/SUM(BO64:BO67) -> 3.4892487 | BP76: =(SUM(BP50:BP54)-BP53)/SUM(BP64:BP67) -> 3.4379551 | BQ76: =(SUM(BQ50:BQ54)-BQ53)/SUM(BQ64:BQ67) -> 4.2871956 | CF76: This is the tricky part, and demands learning more about Penumbra's product mix, their product's operating lifecycles, and The Company's need to create/innovate to generate future returns (the patents ultimately expire in 20 years- follows similar behavior to pharma-economics)
B77: Cash Ratio | S77: =S50/SUM(S64:S67) -> 1.3773699 | T77: =T50/SUM(T64:T67) -> 1.1075099 | U77: =U50/SUM(U64:U67) -> 1.2949389 | V77: =V50/SUM(V64:V67) -> 0.7993476 | W77: =W50/SUM(W64:W67) -> 0.82267184 | X77: =X50/SUM(X64:X67) -> 1.7314462 | Y77: =Y50/SUM(Y64:Y67) -> 0.74142798 | Z77: =Z50/SUM(Z64:Z67) -> 0.65768606 | ... AV77: =AV50/SUM(AV64:AV67) -> 0.87806704 | BK77: =SUM(BK50:BK51)/SUM(BK64:BK67) -> 2.0801006 | BL77: =SUM(BL50:BL51)/SUM(BL64:BL67) -> 2.5000189 | BM77: =SUM(BM50:BM51)/SUM(BM64:BM67) -> 2.068841 | BN77: =SUM(BN50:BN51)/SUM(BN64:BN67) -> 1.297367 | BO77: =SUM(BO50:BO51)/SUM(BO64:BO67) -> 1.9133211 | BP77: =SUM(BP50:BP51)/SUM(BP64:BP67) -> 2.1480123 | BQ77: =SUM(BQ50:BQ51)/SUM(BQ64:BQ67) -> 2.9749362 | CE77: Each one of my inputs (terminal, cost of debt/equity, ROIC and others) for the end NPV calculation should have separate tables to record all assumptions/formulaic inputs
B78: Fixed Asset Turnover Ratio | S78: =S26/SUM(S55:S57) -> 1.6518211 | T78: =T26/SUM(T55:T57) -> 1.6688346 | U78: =U26/SUM(U55:U57) -> 1.5953661 | V78: =V26/SUM(V55:V57) -> 1.0724089 | W78: =W26/SUM(W55:W57) -> 0.97270338 | X78: =X26/SUM(X55:X57) -> 0.73607687 | Y78: =Y26/SUM(Y55:Y57) -> 1.0386165 | Z78: =Z26/SUM(Z55:Z57) -> 1.309874 | ... AV78: =AV26/SUM(AV55:AV57) -> 1.1530646 | BK78: =BK26/SUM(BK55:BK57) -> 4.0412763 | BL78: =BL26/SUM(BL55:BL57) -> 4.3979408 | BM78: =BM26/SUM(BM55:BM57) -> 3.2920863 | BN78: =BN26/SUM(BN55:BN57) -> 2.9113701 | BO78: =BO26/SUM(BO55:BO57) -> 3.6183893 | BP78: =BP26/SUM(BP55:BP57) -> 4.450057 | BQ78: =BQ26/SUM(BQ55:BQ57) -> 4.4280351 | CE78: Determine whether to employ a terminal rate or exit multiple method for the full DCF model
B79: Ttl Asset Turnover | S79: =S26/S62 -> 0.22581133 | T79: =T26/T62 -> 0.22936068 | U79: =U26/U62 -> 0.22713907 | V79: =V26/V62 -> 0.21814204 | W79: =W26/W62 -> 0.2067024 | X79: =X26/X62 -> 0.13470905 | Y79: =Y26/Y62 -> 0.18647322 | Z79: =Z26/Z62 -> 0.20281342 | ... AV79: =AV26/AV62 -> 0.19751935 | BK79: =BK26/BK62 -> 0.82204862 | BL79: =BL26/BL62 -> 0.6809521 | BM79: =BM26/BM62 -> 0.60083584 | BN79: =BN26/BN62 -> 0.61794562 | BO79: =BO26/BO62 -> 0.68014946 | BP79: =BP26/BP62 -> 0.77916691 | BQ79: =BQ26/BQ62 -> 0.76849523 | CE79: Build out models for long term outcome potentiality ("High IP value + cont. innovation" v. "generic competitor" outcomes for Penumbra in the long run?)
B80: Inventory Turnover Ratio | T80: =T27/AVERAGE(A53:T53) -> 0.31657928 | U80: =U27/AVERAGE(B53:U53) -> 0.33059007 | V80: =V27/AVERAGE(S53:V53) -> 0.34419116 | W80: =W27/AVERAGE(T53:W53) -> 0.33297424 | X80: =X27/AVERAGE(U53:X53) -> 0.25009915 | Y80: =Y27/AVERAGE(V53:Y53) -> 0.34663674 | Z80: =Z27/AVERAGE(W53:Z53) -> 0.38168557 | AA80: =AA27/AVERAGE(X53:AA53) -> 0.27561062 | AB80: =AB27/AVERAGE(Y53:AB53) -> 0.28791756 | AC80: =AC27/AVERAGE(Z53:AC53) -> 0.28707518 | ... AV80: =AV27/AVERAGE(AS53:AV53) -> 0.28674984 | BK80: =BK27/AVERAGE(BH53:BK53) -> 1.1467332 | BL80: =BL27/AVERAGE(BI53:BL53) -> 1.1931579 | BM80: =BM27/AVERAGE(BJ53:BM53) -> 1.2839536 | BN80: =BN27/AVERAGE(BK53:BN53) -> 1.2862543 | BO80: =BO27/AVERAGE(BL53:BO53) -> 1.2477387 | BP80: =BP27/AVERAGE(BM53:BP53) -> 1.2629734 | BQ80: =BQ27/AVERAGE(BN53:BQ53) -> 1.1823971 | CF80: !! It is absolutely necessary to begin tracking individual products Penumbra owns/markets and creating useful life tables !! Understanding the finances and the product is what is expected of analysts
B81: Return on Assets | S81: =S39/S62 -> 0.018808381 | T81: =T39/T62 -> 0.028688672 | U81: =U39/U62 -> 0.018696778 | V81: =V39/V62 -> 0.014249866 | W81: =W39/W62 -> 0.0022823076 | X81: =X39/X62 -> -0.015303768 | Y81: =Y39/Y62 -> -0.010900847 | Z81: =Z39/Z62 -> 0.004441161 | ... AV81: =AV39/AV62 -> 0.017628295 | BK81: =BK39/BK62 -> 0.072767574 | BL81: =BL39/BL62 -> -0.018957864 | BM81: =BM39/BM62 -> 0.004246735 | BN81: =BN39/BN62 -> -0.0014603694 | BO81: =BO39/BO62 -> 0.058478255 | BP81: =BP39/BP62 -> 0.0091248493 | BQ81: =BQ39/BQ62 -> 0.097282195 | CE81: Build out models for firms with competitive overlap + other operators in the MedTech/Life Science industries; mosaic theory some comparables
B82: Return on Equity | S82: =S39/S72 -> 0.024499442 | T82: =T39/T72 -> 0.036958671 | U82: =U39/U72 -> 0.024591972 | V82: =V39/V72 -> 0.019540251 | W82: =W39/W72 -> 0.0031058127 | X82: =X39/X72 -> -0.019160377 | Y82: =Y39/Y72 -> -0.014253395 | Z82: =Z39/Z72 -> 0.0057307444 | ... AV82: =AV39/AV72 -> 0.022740902 | BK82: =BK39/BK72 -> 0.099783161 | BL82: =BL39/BL72 -> -0.024462674 | BM82: =BM39/BM72 -> 0.0055392079 | BN82: =BN39/BN72 -> -0.0020042889 | BO82: =BO39/BO72 -> 0.077196465 | BP82: =BP39/BP72 -> 0.012155377 | BQ82: =BQ39/BQ72 -> 0.12446528 | CG82: Gives a chance to study other operators, their financial standing, + the technological "asset value" firms possess (which is where the real α is found from an equity interest)
CG83: Stryker managers are intelligent and didn't pay a 60% premium above the market's current trading price on Inari for no reason…
B84: NI | C84: =C39 -> 0.5 | D84: =D39 -> -0.55 | E84: =E39 -> 0.32 | F84: =F39 -> 0.75 | G84: =G39 -> 2.5 | H84: =H39 -> 3 | I84: =I39 -> 12.2 | J84: =J39 -> -2.4 | ... AV84: =AV39 -> 34.811 | BG84: =SUM(C84:F84) -> 1.02 | BH84: =SUM(G84:J84) -> 15.3 | BI84: =SUM(K84:N84) -> 4.6 | BJ84: =SUM(O84:R84) -> 6.52 | BK84: =BK39 -> 48.456 | BL84: =BL39 -> -15.602 | BM84: =BM39 -> 5.284 | BN84: =BN39 -> -2.002 | BO84: =BO39 -> 91.01 | BP84: =BP39 -> 13.99 | BQ84: =SUM(AQ84:AT84) -> 177.687 | CG84: If NARI was a traditional enterprise, say a bottling plant, and SYK managers acquired it for a 60% premium above its current valuation, other participants would laugh and call them dumb... This means that NARI (and potentially MedTech companies in general) are valued by the market for more than just the net present value of cash flows... or makes positive assumptions about those future returns
B85: CFFO | C85: -2.7 | D85: -5.6 | E85: -4.3 | F85: -8 | G85: -2.1 | H85: -6.1 | I85: 5.7 | J85: -10.4 | K85: 2.2 | L85: 0.6 | M85: 10.8 | N85: -0.9 | O85: 10.7 | P85: 0.1 | Q85: 10.4 | R85: 7.5 | S85: -2.1 | T85: 1.9 | U85: 22 | V85: 4.8 | W85: -5.92 | X85: =-27.609-W85 -> -21.689 | Y85: =-31.159-SUM(W85:X85) -> -3.55 | Z85: =-33.242-SUM(W85:Y85) -> -2.083 | AA85: -14.368 | AB85: =-17.678-AA85 -> -3.31 | AC85: =18.772-SUM(AA85:AB85) -> 36.45 | AD85: =9.502-SUM(AA85:AC85) -> -9.27 | AE85: -4.514 | AF85: =-44.089-AE85 -> -39.575 | AG85: =-56.998-SUM(AE85:AF85) -> -12.909 | AH85: =-55.661-SUM(AE85:AG85) -> 1.337 | AI85: 13.129 | AJ85: =30.228-AI85 -> 17.099 | AK85: =61.072-SUM(AI85:AJ85) -> 30.844 | AL85: =97.333-SUM(AI85:AK85) -> 36.261 | AM85: 38.295 | AN85: =60.906-AM85 -> 22.611 | AO85: =117.373-SUM(AM85:AN85) -> 56.467 | AP85: =168.481-SUM(AM85:AO85) -> 51.108 | AQ85: =48.97 -> 48.97 | AR85: =93.916-AQ85 -> 44.946 | AS85: 58.263 | AT85: =238.663-SUM(AQ85:AS85) -> 86.484 | AU85: 86.97 | AV85: 46.084 | BG85: =SUM(C85:F85) -> -20.6 | BH85: =SUM(G85:J85) -> -12.9 | BI85: =SUM(K85:N85) -> 12.7 | BJ85: =SUM(O85:R85) -> 28.7 | BK85: 26.652 | BL85: =SUM(W85:Z85) -> -33.242 | BM85: =SUM(AA85:AD85) -> 9.502 | BN85: =SUM(AE85:AH85) -> -55.661 | BO85: =SUM(AI85:AL85) -> 97.333 | BP85: =SUM(AM85:AP85) -> 168.481 | BQ85: =SUM(AQ85:AT85) -> 238.663 | CH85: How do you value IP??? Commercialization ramp track
B86: CapEx | C86: -1.3 | D86: -1.8 | E86: -1.4 | F86: -1 | G86: -1.1 | H86: -2.6 | I86: -3.4 | J86: -6.6 | K86: -3.2 | L86: -2.2 | M86: -1.4 | N86: -5.7 | O86: -2.8 | P86: -2.3 | Q86: -1.5 | R86: -3 | S86: -2.5 | T86: -3.7 | U86: -7.9 | V86: -8 | W86: -10.131 | X86: =-16.85-W86 -> -6.719 | Y86: =-21.003-SUM(W86:X86) -> -4.153 | Z86: =-24.756-SUM(W86:Y86) -> -3.753 | AA86: -3.991 | AB86: =-7.286-AA86 -> -3.295 | AC86: =-13.088-SUM(AA86:AB86) -> -5.802 | AD86: =-21.18-SUM(AA86:AC86) -> -8.092 | AE86: -4.957 | AF86: =-9.388-AE86 -> -4.431 | AG86: =-15.736-SUM(AE86:AF86) -> -6.348 | AH86: =-19.298-SUM(AE86:AG86) -> -3.562 | AI86: -3.894 | AJ86: =-8.236-AI86 -> -4.342 | AK86: =-12.568-SUM(AI86:AJ86) -> -4.332 | AL86: =-16.213-SUM(AI86:AK86) -> -3.645 | AM86: -5.824 | AN86: =-10.36-AM86 -> -4.536 | AO86: =-15.811-SUM(AM86:AN86) -> -5.451 | AP86: =-21.182-SUM(AM86:AO86) -> -5.371 | AQ86: =-13.467 -> -13.467 | AR86: =-29.046-AQ86 -> -15.579 | AS86: -16.249 | AT86: =-63.729-SUM(AQ86:AS86) -> -18.434 | AU86: -13.671 | AV86: -13.542 | BG86: =SUM(C86:F86) -> -5.5 | BH86: =SUM(G86:J86) -> -13.7 | BI86: =SUM(K86:N86) -> -12.5 | BJ86: =SUM(O86:R86) -> -9.6 | BK86: -22.109 | BL86: =SUM(W86:Z86) -> -24.756 | BM86: =SUM(AA86:AD86) -> -21.18 | BN86: =SUM(AE86:AH86) -> -19.298 | BO86: =SUM(AI86:AL86) -> -16.213 | BP86: =SUM(AM86:AP86) -> -21.182 | BQ86: =SUM(AQ86:AT86) -> -63.729 | CE86: R&D spend is treated as an expense (by accountants at least), but in MedTech it almost acts as a capital-like investment into the firm's future product mix … How do we as investors account for this?
B87: FCF | C87: =C85+C86 -> -4 | D87: =D85+D86 -> -7.4 | E87: =E85+E86 -> -5.7 | F87: =F85+F86 -> -9 | G87: =G85+G86 -> -3.2 | H87: =H85+H86 -> -8.7 | I87: =I85+I86 -> 2.3 | J87: =J85+J86 -> -17 | ... AV87: =AV85+AV86 -> 32.542 | BG87: =BG85+BG86 -> -26.1 | BH87: =BH85+BH86 -> -26.6 | BI87: =BI85+BI86 -> 0.2 | BJ87: =BJ85+BJ86 -> 19.1 | BK87: =BK85+BK86 -> 4.543 | BL87: =BL85+BL86 -> -57.998 | BM87: =BM85+BM86 -> -11.678 | BN87: =BN85+BN86 -> -74.959 | ... BP87: =BP85+BP86 -> 147.299 | BQ87: =SUM(AQ87:AT87) -> 174.934 | CF87: Learn more about R&D initiatives and gauge whether to capitalize R&D on the balance sheet over a useful life
B88: SC | C88: =C40 -> 5 | D88: =D40 -> 5 | E88: =E40 -> 8 | F88: =F40 -> 12 | G88: =G40 -> 30 | H88: =H40 -> 30 | I88: =I40 -> 31 | J88: =J40 -> 30 | ... AV88: =AV40 -> 39.353 | BG88: =BG40 -> 12 | BH88: =BH40 -> 31 | BI88: =BI40 -> 33 | BJ88: =BJ40 -> 34 | BK88: =BK40 -> 34.8 | BL88: =BL40 -> 35.5 | BM88: =AD88 -> 36.7 | BN88: =AH88 -> 37.841 | BO88: =AL88 -> 38.4 | BP88: =AP88 -> 38.63 | BQ88: =AVERAGE(AQ88:AT88) -> 38.776 | CE88: Identify key sectoral KPI's, which drive material changes in common stock price (Pricing v. Volume Mix; Complete product pipeline schedules; Clinical/Medical representative support)
B89: FCF per Share | C89: =C87/C88 -> -0.8 | D89: =D87/D88 -> -1.48 | E89: =E87/E88 -> -0.7125 | F89: =F87/F88 -> -0.75 | G89: =G87/G88 -> -0.10666667 | H89: =H87/H88 -> -0.29 | I89: =I87/I88 -> 0.074193548 | J89: =J87/J88 -> -0.56666667 | ... AV89: =AV87/AV88 -> 0.82692552 | BG89: =BG87/BG88 -> -2.175 | BH89: =BH87/BH88 -> -0.85806452 | BI89: =BI87/BI88 -> 0.0060606061 | BJ89: =BJ87/BJ88 -> 0.56176471 | BK89: =BK87/BK88 -> 0.13054598 | BL89: =BL87/BL88 -> -1.6337465 | BM89: =BM87/BM88 -> -0.31820163 | BN89: =BN87/BN88 -> -1.9808937 | ... BP89: =BP87/BP88 -> 3.8130727 | BQ89: =SUM(AQ89:AT89) -> 4.513608 | CD89: Closing remarks:
CE90: There are a variety of assumptions listed above that immediately invalidate the calculated valuation and any potential upside/downside. I hope to continue iterating on this model in order to better capture the firm's true potential value on the open market
CE91: While my current net income based model provides a rough estimate, transitioning to an expanded DCF model with Stmt. Of Cashflow considerations are necessary for the model to be of any use/investment value. I hope to address these pitfalls and improve accuracy
CF92: Additionally, working to capture qualitative factors in the valuation (IP/innovation runway, product's standing as flagship in the space( taking dominant market share), management strategy, etc.) will increase accuracy.
CG93: Working to uncover/understand qualitative factors may also unlock a view into the markets reasoning behind justifying a large equity premium from a glance ... ("I don’t pay an analyst big bucks to tell me if a 6x P/E Fwd. sotck is cheap… I pay them to tell me if a 156x Fwd. P/E stock is cheap!")
CG94: Understanding the market factors baked into a valuation are of upmost importance (think TSLA's valuation, with AVs already being priced in)
CE95: This net income to NPV shortcut approach assumes absolutely perfect FCF conversion, which is far from realistic for a still-growing firm like Penumbra
CE96: My terminal value makes an assumption of strong, stable future revenues and margins, but Med-Tech is prone to patent expiry cliffs (similar to pharma) and FDA/health regulation risks

Sheet Bear Case (15%)
T1: Q1 2019 | X1: Q1 2020 | AB1: Q1 2021 | AF1: Q1 2022 | AJ1: Q1 2023 | AN1: Q1 2024 | AR1: Q1 2025 | AV1: Q1 2026
C2: Quarterly | D2: Apr | E2: July | F2: Oct | G2: Jan | H2: Apr | I2: July | J2: Oct | K2: Jan | L2: Apr | M2: July | N2: Oct | O2: Jan | P2: Apr | Q2: July | R2: Oct | S2: Jan | T2: Apr | U2: July | V2: Oct | W2: Jan | X2: Apr | Y2: July | Z2: Oct | AA2: Jan | AB2: Apr | AC2: July | AD2: Oct | AE2: Jan | AF2: Apr | AG2: July | AH2: Oct | AI2: Jan | AJ2: Apr | AK2: July | AL2: Oct | AM2: Jan | AN2: Apr | AO2: July | AP2: Oct | AQ2: Jan | AR2: Apr | AS2: July | AT2: Oct | AU2: Jan | AV2: Apr | AW2: July | AX2: Oct | AY2: Jan | AZ2: Apr | BA2: July | BB2: Oct | BC2: Jan
C3: Revenues | D3: Q1 2015 | E3: Q2 2015 | F3: Q3 2015 | G3: Q4 2015 | H3: Q1 2016 | I3: Q2 2016 | J3: Q3 2016 | K3: Q4 2016 | L3: Q1 2017 | M3: Q2 2017 | N3: Q3 2017 | O3: Q4 2017 | P3: Q1 2018 | Q3: Q2 2018 | R3: Q3 2018 | S3: Q4 2018 | T3: Q1 2019 | U3: Q2 2019 | V3: Q3 2019 | W3: Q4 2019 | X3: Q1 2020 | Y3: Q2 2020 | Z3: Q3 2020 | AA3: Q4 2020 | AB3: Q1 2021 | AC3: Q2 2021 | AD3: Q3 2021 | AE3: Q4 2021 | AF3: Q1 2022 | AG3: Q2 2022 | AH3: Q3 2022 | AI3: Q4 2022 | AJ3: Q1 2023 | AK3: Q2 2023 | AL3: Q3 2023 | AM3: Q4 2023 | AN3: Q1 2024 | AO3: Q2 2024 | AP3: Q3 2024 | AQ3: Q4 2024 | AR3: Q1 2025 | AS3: Q2 2025 | AT3: Q3 2025 | AU3: Q4 2025 | AV3: Q1 2026 | AW3: Q2 2026 | AX3: Q3 2026 | AY3: Q4 2026 | AZ3: Q1 2027 | BA3: Q2 2027 | BB3: Q3 2027 | BC3: Q4 2027 | BH3: 2015 | BI3: 2016 | BJ3: 2017 | BK3: 2018 | BL3: 2019 | BM3: 2020 | BN3: 2021 | BO3: 2022 | BP3: =BO3+1 -> 2023 | BQ3: =BP3+1 -> 2024 | BR3: =BQ3+1 -> 2025 | BS3: =BQ3+1 -> 2025 | BT3: =BS3+1 -> 2026 | BU3: =BT3+1 -> 2027 | BV3: =BU3+1 -> 2028 | BW3: =BV3+1 -> 2029 | BX3: =BW3+1 -> 2030 | BY3: =BX3+1 -> 2031 | BZ3: =BY3+1 -> 2032 | CA3: =BZ3+1 -> 2033 | ... DP3: =DO3+1 -> 2074
C4: Thrombectomy (Neuro + Peripheral) | AJ4: 145 | AK4: 162 | AL4: 179 | AM4: =677-SUM(AJ4:AL4) -> 191 | AN4: 188 | AO4: 203 | AP4: 204 | AQ4: =815-SUM(AN4:AP4) -> 220 | AR4: 226.544 | AS4: 230.256 | AT4: 236.4 | AU4: =947.918-SUM(AR4:AT4) -> 254.718 | AV4: 253.917 | AW4: 258.981 | BP4: =SUM(AJ4:AM4) -> 677 | BQ4: =SUM(AN4:AQ4) -> 815 | BR4: =SUM(AR4:AU4) -> 947.918 | BS4: =BR4*(1+BS8) -> 1109.0641 | BT4: =BS4*(1+BT8) -> 1286.5143 | BU4: =BT4*(1+BU8) -> 1479.4915 | BV4: =BU4*(1+BV8) -> 1671.8253 | BW4: =BV4*(1+BW8) -> 1872.4444 | BX4: =BW4*(1+BX8) -> 2078.4133 | BY4: =BX4*(1+BY8) -> 2275.8625 | BZ4: =BY4*(1+BZ8) -> 2457.9315 | ... CB4: =CA4*(1+CB8) -> 2827.2357
C5: Embolization & Access (Peripheral Embolization + Neuro Embolization + Access + Neurosurgical Tools) | AJ5: 96 | AK5: 99 | AL5: 92 | AM5: =381-SUM(AJ5:AL5) -> 94 | AN5: 91 | AO5: 96 | AP5: 96.89 | AQ5: =379-SUM(AN5:AP5) -> 95.11 | AR5: 97.596 | AS5: 109.199 | AT5: 118.3 | AU5: =455.747-SUM(AR5:AT5) -> 130.652 | AV5: 120.841 | AW5: 131.065 | BP5: =SUM(AJ5:AM5) -> 381 | BQ5: =SUM(AN5:AQ5) -> 379 | BR5: =SUM(AR5:AU5) -> 455.747 | BS5: =BR5*(1+BS9) -> 514.99411 | BT5: =BS5*(1+BT9) -> 561.34358 | BU5: =BT5*(1+BU9) -> 603.44435 | BV5: =BU5*(1+BV9) -> 639.65101 | BW5: =BV5*(1+BW9) -> 668.4353 | BX5: =BW5*(1+BX9) -> 691.83054 | BY5: =BX5*(1+BY9) -> 712.58546 | BZ5: =BY5*(1+BZ9) -> 730.40009 | ... CB5: =CA5*(1+CB9) -> 756.18322
C6: Ttl Revenues | AJ6: =SUM(AJ4:AJ5) -> 241 | AK6: =SUM(AK4:AK5) -> 261 | AL6: =SUM(AL4:AL5) -> 271 | AM6: =SUM(AM4:AM5) -> 285 | AN6: =SUM(AN4:AN5) -> 279 | AO6: =SUM(AO4:AO5) -> 299 | AP6: =SUM(AP4:AP5) -> 300.89 | AQ6: =SUM(AQ4:AQ5) -> 315.11 | ... AU6: =SUM(AU4:AU5) -> 385.37 | AV6: =AV4+AV5 -> 374.758 | AW6: =AW4+AW5 -> 390.046 | BP6: =BP4+BP5 -> 1058 | BQ6: =BQ4+BQ5 -> 1194 | BR6: =SUM(AR6:AU6) -> 1403.665 | BS6: =BS4+BS5 -> 1624.0582 | BT6: =BT4+BT5 -> 1847.8579 | BU6: =BU4+BU5 -> 2082.9358 | BV6: =BV4+BV5 -> 2311.4764 | BW6: =BW4+BW5 -> 2540.8797 | BX6: =BX4+BX5 -> 2770.2438 | BY6: =BY4+BY5 -> 2988.448 | BZ6: =BZ4+BZ5 -> 3188.3316 | ... CB6: =CB4+CB5 -> 3583.419
C8: Thrombectomy Revenue Growth Y/y | AN8: =AN4/AJ4-1 -> 0.29655172 | AO8: =AO4/AK4-1 -> 0.25308642 | AP8: =AP4/AL4-1 -> 0.1396648 | AQ8: =AQ4/AM4-1 -> 0.15183246 | AR8: =AR4/AN4-1 -> 0.20502128 | AS8: =AS4/AO4-1 -> 0.13426601 | AT8: =AT4/AP4-1 -> 0.15882353 | AU8: =AU4/AQ4-1 -> 0.15780909 | AV8: 0.17 | AW8: 0.22 | BQ8: =BQ4/BP4-1 -> 0.20384047 | BR8: =BR4/BQ4-1 -> 0.16308957 | BS8: 0.17 | BT8: 0.16 | BU8: 0.15 | BV8: 0.13 | BW8: 0.12 | BX8: 0.11 | BY8: 0.095 | BZ8: 0.08 | CA8: 0.075 | CB8: 0.07
C9: E & A Revenue Growth Y/y | AN9: =AN5/AJ5-1 -> -0.052083333 | AO9: =AO5/AK5-1 -> -0.03030303 | AP9: =AP5/AL5-1 -> 0.053152174 | AQ9: =AQ5/AM5-1 -> 0.011808511 | AR9: =AR5/AN5-1 -> 0.072483516 | AS9: =AS5/AO5-1 -> 0.13748958 | AT9: =AT5/AP5-1 -> 0.22097224 | AU9: =AU5/AQ5-1 -> 0.37369362 | AV9: 0.16 | AW9: 0.105 | BQ9: =BQ5/BP5-1 -> -0.0052493438 | BR9: =BR5/BQ5-1 -> 0.20249868 | BS9: 0.13 | BT9: 0.09 | BU9: 0.075 | BV9: 0.06 | BW9: 0.045 | BX9: 0.035 | BY9: 0.03 | BZ9: 0.025 | CA9: 0.02 | CB9: 0.015
C10: Total Revenue Growth Y/y | AN10: =AN6/AJ6-1 -> 0.15767635 | AO10: =AO6/AK6-1 -> 0.14559387 | AP10: =AP6/AL6-1 -> 0.1102952 | AQ10: =AQ6/AM6-1 -> 0.10564912 | AR10: =AR6/AN6-1 -> 0.16179211 | AS10: =AS6/AO6-1 -> 0.135301 | AT10: =AT6/AP6-1 -> 0.17883612 | AU10: =AU6/AQ6-1 -> 0.22296976 | ... AW10: =AW6/AS6-1 -> 0.14903595 | BQ10: =BQ6/BP6-1 -> 0.12854442 | BR10: =BR6/BQ6-1 -> 0.17559883 | BS10: =BS6/BR6-1 -> 0.15701266 | BT10: =BT6/BS6-1 -> 0.13780277 | BU10: =BU6/BT6-1 -> 0.12721645 | BV10: =BV6/BU6-1 -> 0.1097204 | BW10: =BW6/BV6-1 -> 0.099245375 | BX10: =BX6/BW6-1 -> 0.09026957 | ... CB10: =CB6/CA6-1 -> 0.057903158
C12: Thrombectomy % of Ttl Revenues | AJ12: =AJ4/AJ6 -> 0.60165975 | AK12: =AK4/AK6 -> 0.62068966 | AL12: =AL4/AL6 -> 0.66051661 | AM12: =AM4/AM6 -> 0.67017544 | AN12: =AN4/AN6 -> 0.67383513 | AO12: =AO4/AO6 -> 0.67892977 | AP12: =AP4/AP6 -> 0.67798863 | AQ12: =AQ4/AQ6 -> 0.69816889 | ... AW12: =AW4/AW6 -> 0.66397553 | BP12: =AVERAGE(AJ12:AM12) -> 0.63826036 | BQ12: =AVERAGE(AN12:AQ12) -> 0.6822306 | BR12: =AVERAGE(AO12:AR12) -> 0.68849879 | BS12: =BS4/BS6 -> 0.68289676 | BT12: =BT4/BT6 -> 0.69621929 | BU12: =BU4/BU6 -> 0.71029143 | BV12: =BV4/BV6 -> 0.72327166 | BW12: =BW4/BW6 -> 0.73692761 | BX12: =BX4/BX6 -> 0.75026366 | BY12: =BY4/BY6 -> 0.76155333 | BZ12: =BZ4/BZ6 -> 0.77091464 | ... CB12: =CB4/CB6 -> 0.78897717
C13: E & A % of Ttl Revenues | AJ13: =AJ5/AJ6 -> 0.39834025 | AK13: =AK5/AK6 -> 0.37931034 | AL13: =AL5/AL6 -> 0.33948339 | AM13: =AM5/AM6 -> 0.32982456 | AN13: =AN5/AN6 -> 0.32616487 | AO13: =AO5/AO6 -> 0.32107023 | AP13: =AP5/AP6 -> 0.32201137 | AQ13: =AQ5/AQ6 -> 0.30183111 | ... AW13: =AW5/AW6 -> 0.33602447 | BP13: =AVERAGE(AJ13:AM13) -> 0.36173964 | BQ13: =AVERAGE(AN13:AQ13) -> 0.3177694 | BR13: =AVERAGE(AO13:AR13) -> 0.31150121 | BS13: =BS5/BS6 -> 0.31710324 | BT13: =BT5/BT6 -> 0.30378071 | BU13: =BU5/BU6 -> 0.28970857 | BV13: =BV5/BV6 -> 0.27672834 | BW13: =BW5/BW6 -> 0.26307239 | BX13: =BX5/BX6 -> 0.24973634 | BY13: =BY5/BY6 -> 0.23844667 | BZ13: =BZ5/BZ6 -> 0.22908536 | ... CB13: =CB5/CB6 -> 0.21102283
C15: U.S. Revenues | T15: 82.511 | U15: 86.374 | V15: 90.272 | W15: =355.22-SUM(T15:V15) -> 96.063 | X15: 96 | Y15: 78 | Z15: 110 | AA15: =400-SUM(X15:Z15) -> 116 | AB15: 120 | AC15: 128 | AD15: 135 | AE15: =528-SUM(AB15:AD15) -> 145 | AF15: 144 | AG15: 141 | AH15: 149 | AI15: =592-SUM(AF15:AH15) -> 158 | AJ15: 172 | AK15: 186 | AL15: 195 | AM15: =757-SUM(AJ15:AL15) -> 204 | AN15: 210 | AO15: 218 | AP15: 226 | AQ15: =902-SUM(AN15:AP15) -> 248 | AR15: 256.86 | AS15: 260.818 | AT15: 275.029 | AU15: =1091.761-SUM(AR15:AT15) -> 299.054 | AV15: 296.387 | AW15: 305.445 | BL15: =SUM(T15:W15) -> 355.22 | BM15: =SUM(X15:AA15) -> 400 | BN15: =SUM(AB15:AD15) -> 383 | BO15: =SUM(AF15:AH15) -> 434 | BP15: =SUM(AJ15:AM15) -> 757 | BQ15: =SUM(AN15:AQ15) -> 902 | BR15: =SUM(AR15:AU15) -> 1091.761
C16: International Revenues | T16: =9.522+36.406 -> 45.928 | U16: =12.231+35.596 -> 47.827 | V16: =11.214+38.016 -> 49.23 | W16: =42.52+149.663-SUM(T16:V16) -> 49.198 | X16: 41 | Y16: 27 | Z16: 41 | AA16: =160-SUM(X16:Z16) -> 51 | AB16: 49 | AC16: 56 | AD16: 55 | AE16: =220-SUM(AB16:AD16) -> 60 | AF16: 60 | AG16: 67 | AH16: 65 | AI16: =255-SUM(AF16:AH16) -> 63 | AJ16: 69 | AK16: 75 | AL16: 76 | AM16: =301-SUM(AJ16:AL16) -> 81 | AN16: 69 | AO16: 81 | AP16: 77 | AQ16: =292-SUM(AN16:AP16) -> 65 | AR16: 67.28 | AS16: 78.637 | AT16: 79.656 | AU16: =311.904-SUM(AR16:AT16) -> 86.331 | AV16: 78.371 | AW16: 84.601 | BL16: =SUM(T16:W16) -> 192.183 | BM16: =SUM(X16:AA16) -> 160 | BN16: =SUM(AB16:AD16) -> 160 | BO16: =SUM(AF16:AH16) -> 192 | BP16: =SUM(AJ16:AM16) -> 301 | BQ16: =SUM(AN16:AQ16) -> 292 | BR16: =SUM(AR16:AU16) -> 311.904
C17: Ttl Revenues | T17: =SUM(T15:T16) -> 128.439 | U17: =SUM(U15:U16) -> 134.201 | V17: =SUM(V15:V16) -> 139.502 | W17: =SUM(W15:W16) -> 145.261 | X17: =SUM(X15:X16) -> 137 | Y17: =SUM(Y15:Y16) -> 105 | Z17: =SUM(Z15:Z16) -> 151 | AA17: =SUM(AA15:AA16) -> 167 | ... AW17: =SUM(AW15:AW16) -> 390.046 | BL17: =SUM(T17:W17) -> 547.403 | BM17: =SUM(X17:AA17) -> 560 | BN17: =SUM(AB17:AE17) -> 748 | BO17: =SUM(AF17:AI17) -> 847 | BP17: =SUM(AJ17:AM17) -> 1058 | BQ17: =SUM(AN17:AQ17) -> 1194 | BR17: =SUM(AR17:AU17) -> 1403.665
C19: U.S. Revenue Growth Y/y | X19: =X15/T15-1 -> 0.16348123 | Y19: =Y15/U15-1 -> -0.096950471 | Z19: =Z15/V15-1 -> 0.21853952 | AA19: =AA15/W15-1 -> 0.20754088 | AB19: =AB15/X15-1 -> 0.25 | AC19: =AC15/Y15-1 -> 0.64102564 | AD19: =AD15/Z15-1 -> 0.22727273 | AE19: =AE15/AA15-1 -> 0.25 | ... AW19: =AW15/AS15-1 -> 0.17110399 | BM19: =BM15/BL15-1 -> 0.12606272 | BN19: =BN15/BM15-1 -> -0.0425 | BO19: =BO15/BN15-1 -> 0.13315927 | BP19: =BP15/BO15-1 -> 0.74423963 | BQ19: =BQ15/BP15-1 -> 0.19154557 | BR19: =BR15/BQ15-1 -> 0.21037805
C20: International Revenue Growth Y/y | X20: =X16/T16-1 -> -0.10729838 | Y20: =Y16/U16-1 -> -0.43546532 | Z20: =Z16/V16-1 -> -0.16717449 | AA20: =AA16/W16-1 -> 0.036627505 | AB20: =AB16/X16-1 -> 0.19512195 | AC20: =AC16/Y16-1 -> 1.0740741 | AD20: =AD16/Z16-1 -> 0.34146341 | AE20: =AE16/AA16-1 -> 0.17647059 | ... AW20: =AW16/AS16-1 -> 0.075842161 | BM20: =BM16/BL16-1 -> -0.16746018 | BN20: =BN16/BM16-1 -> 0 | BO20: =BO16/BN16-1 -> 0.2 | BP20: =BP16/BO16-1 -> 0.56770833 | BQ20: =BQ16/BP16-1 -> -0.029900332 | BR20: =BR16/BQ16-1 -> 0.068164384
C21: Total Revenue Growth Y/y | X21: =X17/T17-1 -> 0.066654209 | Y21: =Y17/U17-1 -> -0.21759152 | Z21: =Z17/V17-1 -> 0.082421757 | AA21: =AA17/W17-1 -> 0.14965476 | AB21: =AB17/X17-1 -> 0.23357664 | AC21: =AC17/Y17-1 -> 0.75238095 | AD21: =AD17/Z17-1 -> 0.25827815 | AE21: =AE17/AA17-1 -> 0.22754491 | ... AW21: =AW17/AS17-1 -> 0.14903595 | BM21: =BM17/BL17-1 -> 0.023012296 | BN21: =BN17/BM17-1 -> 0.33571429 | BO21: =BO17/BN17-1 -> 0.13235294 | BP21: =BP17/BO17-1 -> 0.24911452 | BQ21: =BQ17/BP17-1 -> 0.12854442 | BR21: =BR17/BQ17-1 -> 0.17559883
C23: U.S. % of Ttl Revenues | T23: =T15/T17 -> 0.64241391 | U23: =U15/U17 -> 0.64361666 | V23: =V15/V17 -> 0.64710183 | W23: =W15/W17 -> 0.66131308 | X23: =X15/X17 -> 0.70072993 | Y23: =Y15/Y17 -> 0.74285714 | Z23: =Z15/Z17 -> 0.72847682 | AA23: =AA15/AA17 -> 0.69461078 | ... AW23: =AW15/AW17 -> 0.78309994 | BL23: =BL15/BL17 -> 0.64891862 | BM23: =BM15/BM17 -> 0.71428571 | BN23: =BN15/BN17 -> 0.51203209 | BO23: =BO15/BO17 -> 0.51239669 | BP23: =BP15/BP17 -> 0.71550095 | BQ23: =BQ15/BQ17 -> 0.75544389 | BR23: =BR15/BR17 -> 0.77779313
C24: International % of Ttl Revenues | T24: =T16/T17 -> 0.35758609 | U24: =U16/U17 -> 0.35638334 | V24: =V16/V17 -> 0.35289817 | W24: =W16/W17 -> 0.33868692 | X24: =X16/X17 -> 0.29927007 | Y24: =Y16/Y17 -> 0.25714286 | Z24: =Z16/Z17 -> 0.27152318 | AA24: =AA16/AA17 -> 0.30538922 | ... AW24: =AW16/AW17 -> 0.21690006 | BL24: =BL16/BL17 -> 0.35108138 | BM24: =BM16/BM17 -> 0.28571429 | BN24: =BN16/BN17 -> 0.21390374 | BO24: =BO16/BO17 -> 0.22668241 | BP24: =BP16/BP17 -> 0.28449905 | BQ24: =BQ16/BQ17 -> 0.24455611 | BR24: =BR16/BR17 -> 0.22220687
C26: Revenues | D26: 39 | E26: 42.3 | F26: 50.4 | G26: 54.4 | H26: 57.9 | I26: 65.1 | J26: 67.2 | K26: 73.1 | L26: 73.2 | M26: 80.6 | N26: 83.9 | O26: 96.1 | P26: 102.7 | Q26: 109.6 | R26: 111.8 | S26: 120.8 | T26: =T17 -> 128.439 | U26: =U17 -> 134.201 | V26: =V17 -> 139.502 | W26: =W17 -> 145.261 | X26: 137.3 | Y26: 105.1 | Z26: 151.1 | AA26: =560.412-SUM(X26:Z26) -> 166.912 | AB26: 169.2 | AC26: 184.3 | AD26: 190.1 | AE26: =747.59-SUM(AB26:AD26) -> 203.99 | AF26: 203.9 | AG26: 208.3 | AH26: 213.7 | AI26: =847.133-SUM(AF26:AH26) -> 221.233 | AJ26: 241.4 | AK26: 261.5 | AL26: 270.9 | AM26: =1058.52-SUM(AJ26:AL26) -> 284.72 | AN26: 278.7 | AO26: 299.4 | AP26: 301 | AQ26: =1194.6-SUM(AN26:AP26) -> 315.5 | AR26: =AR17 -> 324.14 | AS26: =AS17 -> 339.455 | AT26: =AT17 -> 354.685 | AU26: =1403.665-SUM(AR26:AT26) -> 385.385 | AV26: =AV17 -> 374.758 | AW26: =AW17 -> 390.046 | AX26: 396 | AY26: 403 | AZ26: 412 | BH26: =SUM(D26:G26) -> 186.1 | BI26: =SUM(H26:K26) -> 263.3 | BJ26: =SUM(L26:O26) -> 333.8 | BK26: =SUM(P26:S26) -> 444.9 | BL26: =SUM(T26:W26) -> 547.403 | BM26: =SUM(X26:AA26) -> 560.412 | BN26: =SUM(AB26:AE26) -> 747.59 | BO26: =SUM(AF26:AI26) -> 847.133 | BP26: =SUM(AJ26:AM26) -> 1058.52 | BQ26: =SUM(AN26:AQ26) -> 1194.6 | BR26: =SUM(AR26:AU26) -> 1403.665 | BS26: =BS6 -> 1624.0582 | BT26: =BT6 -> 1847.8579 | BU26: =BU6 -> 2082.9358 | BV26: =BV6 -> 2311.4764 | BW26: =BW6 -> 2540.8797 | BX26: =BX6 -> 2770.2438 | BY26: =BY6 -> 2988.448 | BZ26: =BZ6 -> 3188.3316 | ... CB26: =CB6 -> 3583.419
C27: COGS | D27: 12.2 | E27: 14.9 | F27: 16.9 | G27: 18 | H27: 18 | I27: 23.6 | J27: 24.3 | K27: 26.5 | L27: 25.5 | M27: 29.7 | N27: 29.1 | O27: 32.3 | P27: 36.1 | Q27: 37.4 | R27: 36.8 | S27: 42.1 | T27: 44.529 | U27: 40.273 | V27: 43.504 | W27: =175.441-SUM(T27:V27) -> 47.135 | X27: 49.3 | Y27: 40.2 | Z27: 60.153 | AA27: =222.237-SUM(X27:Z27) -> 72.584 | AB27: 57.867 | AC27: 65.6 | AD27: 70.2 | AE27: =272.208-SUM(AB27:AD27) -> 78.541 | AF27: 76.5 | AG27: 74.3 | AH27: 78.4 | AI27: =311.926-SUM(AF27:AH27) -> 82.726 | AJ27: 90.3 | AK27: 94.6 | AL27: 93.2 | AM27: =375.9-SUM(AJ27:AL27) -> 97.8 | AN27: 97.5 | AO27: 136.6 | AP27: 100.7 | AQ27: =439.6-SUM(AN27:AP27) -> 104.8 | AR27: 108.257 | AS27: 115.445 | AT27: 114.269 | AU27: =461.228-SUM(AR27:AT27) -> 123.257 | AV27: 121.347 | AW27: 125.102 | BH27: =SUM(D27:G27) -> 62 | BI27: =SUM(H27:K27) -> 92.4 | BJ27: =SUM(L27:O27) -> 116.6 | BK27: =SUM(P27:S27) -> 152.4 | BL27: =SUM(T27:W27) -> 175.441 | BM27: =SUM(X27:AA27) -> 222.237 | BN27: =SUM(AB27:AE27) -> 272.208 | BO27: =SUM(AF27:AI27) -> 311.926 | BP27: =SUM(AJ27:AM27) -> 375.9 | BQ27: =SUM(AN27:AQ27) -> 439.6 | BR27: =SUM(AR27:AU27) -> 461.228 | BS27: =BS26*(1-BS43) -> 535.9392 | BT27: =BT26*(1-BT43) -> 582.07524 | BU27: =BU26*(1-BU43) -> 645.7101 | BV27: =BV26*(1-BV43) -> 699.2216 | BW27: =BW26*(1-BW43) -> 762.26391 | BX27: =BX26*(1-BX43) -> 828.3029 | BY27: =BY26*(1-BY43) -> 890.5575 | BZ27: =BZ26*(1-BZ43) -> 946.93449 | ... CB27: =CB26*(1-CB43) -> 1057.1086
C28: GP | D28: =D26-D27 -> 26.8 | E28: =E26-E27 -> 27.4 | F28: =F26-F27 -> 33.5 | G28: =G26-G27 -> 36.4 | H28: =H26-H27 -> 39.9 | I28: =I26-I27 -> 41.5 | J28: =J26-J27 -> 42.9 | K28: =K26-K27 -> 46.6 | ... AW28: =AW26-AW27 -> 264.944 | BH28: =SUM(D28:G28) -> 124.1 | BI28: =SUM(H28:K28) -> 170.9 | BJ28: =SUM(L28:O28) -> 217.2 | BK28: =SUM(P28:S28) -> 292.5 | BL28: =BL26-BL27 -> 371.962 | BM28: =BM26-BM27 -> 338.175 | BN28: =BN26-BN27 -> 475.382 | BO28: =BO26-BO27 -> 535.207 | BP28: =BP26-BP27 -> 682.62 | BQ28: =BQ26-BQ27 -> 755 | BR28: =SUM(AR28:AU28) -> 942.437 | BS28: =BS26-BS27 -> 1088.119 | BT28: =BT26-BT27 -> 1265.7827 | BU28: =BU26-BU27 -> 1437.2257 | BV28: =BV26-BV27 -> 1612.2548 | BW28: =BW26-BW27 -> 1778.6158 | BX28: =BX26-BX27 -> 1941.9409 | BY28: =BY26-BY27 -> 2097.8905 | BZ28: =BZ26-BZ27 -> 2241.3971 | ... CB28: =CB26-CB27 -> 2526.3104
C29: R&D | D29: 3.2 | E29: 4.8 | F29: 4.6 | G29: 5.5 | H29: 5 | I29: 6.3 | J29: 6.5 | K29: 6.1 | L29: 7 | M29: 8.1 | N29: 8.1 | O29: 8.4 | P29: 8 | Q29: 8.2 | R29: 39.9 | S29: 10.9 | T29: 11.667 | U29: 13.462 | V29: 13.733 | W29: =51.723-SUM(T29:V29) -> 12.861 | X29: 12.946 | Y29: 22.725 | Z29: 34.923 | AA29: =90.049-SUM(X29:Z29) -> 19.455 | AB29: 18.076 | AC29: 17.738 | AD29: 16.73 | AE29: =104.552-SUM(AB29:AD29) -> 52.008 | AF29: 20.56 | AG29: 19.559 | AH29: 21.32 | AI29: =79.407-SUM(AF29:AH29) -> 17.968 | AJ29: 19.98 | AK29: 21.5 | AL29: 21 | AM29: =84.4-SUM(AJ29:AL29) -> 21.92 | AN29: 24.6 | AO29: 24.9 | AP29: 25.2 | AQ29: =94.8-SUM(AN29:AP29) -> 20.1 | AR29: 22.077 | AS29: 23.218 | AT29: 22.677 | AU29: =89.766-SUM(AR29:AT29) -> 21.794 | AV29: 22.382 | AW29: 25.396 | BH29: =SUM(D29:G29) -> 18.1 | BI29: =SUM(H29:K29) -> 23.9 | BJ29: =SUM(L29:O29) -> 31.6 | BK29: =SUM(P29:S29) -> 67 | BL29: =SUM(T29:W29) -> 51.723 | BM29: =SUM(X29:AA29) -> 90.049 | BN29: =SUM(AB29:AE29) -> 104.552 | BO29: =SUM(AF29:AI29) -> 79.407 | BP29: =SUM(AJ29:AM29) -> 84.4 | BQ29: =SUM(AN29:AQ29) -> 94.8 | BR29: =SUM(AR29:AU29) -> 89.766 | BS29: =BS26*BS44 -> 126.67654 | BT29: =BT26*BT44 -> 145.98077 | BU29: =BU26*BU44 -> 166.63486 | BV29: =BV26*BV44 -> 196.47549 | BW29: =BW26*BW44 -> 215.97477 | BX29: =BX26*BX44 -> 249.32194 | BY29: =BY26*BY44 -> 298.8448 | BZ29: =BZ26*BZ44 -> 318.83316 | ... CB29: =CB26*CB44 -> 358.3419
C30: SG&A | D30: 19.5 | E30: 26.4 | F30: 26.8 | G30: 29.2 | H30: 33.1 | I30: 35.9 | J30: 37.7 | K30: 41.6 | L30: 42.7 | M30: 44.2 | N30: 46 | O30: 51.5 | P30: 54.5 | Q30: 54.8 | R30: 55.9 | S30: 61.2 | T30: 61.091 | U30: 67.665 | V30: 69.289 | W30: =272.733-SUM(T30:V30) -> 74.688 | X30: 74.453 | Y30: 59.8 | Z30: 76.2 | AA30: =287.068-SUM(X30:Z30) -> 76.615 | AB30: 79.798 | AC30: 90.63 | AD30: 94.397 | AE30: =378.331-SUM(AB30:AD30) -> 113.506 | AF30: 110.9 | AG30: 114.615 | AH30: 108.57 | AI30: =449.718-SUM(AF30:AH30) -> 115.633 | AJ30: 123.07 | AK30: 127.4 | AL30: 125.9 | AM30: =506.4-SUM(AJ30:AL30) -> 130.03 | AN30: 144.4 | AO30: 141.9 | AP30: 139.7 | AQ30: =574-SUM(AN30:AP30) -> 148 | AR30: 153.456 | AS30: 159.964 | AT30: 168.901 | AU30: =663.422-SUM(AR30:AT30) -> 181.101 | AV30: 192.795 | AW30: 198.509 | BH30: =SUM(D30:G30) -> 101.9 | BI30: =SUM(H30:K30) -> 148.3 | BJ30: =SUM(L30:O30) -> 184.4 | BK30: =SUM(P30:S30) -> 226.4 | BL30: =SUM(T30:W30) -> 272.733 | BM30: =SUM(X30:AA30) -> 287.068 | BN30: =SUM(AB30:AE30) -> 378.331 | BO30: =SUM(AF30:AI30) -> 449.718 | BP30: =SUM(AJ30:AM30) -> 506.4 | BQ30: =SUM(AN30:AQ30) -> 574 | BR30: =SUM(AR30:AU30) -> 663.422 | BS30: =BS26*BS45 -> 771.42763 | BT30: =BT26*BT45 -> 850.01463 | BU30: =BU26*BU45 -> 943.56992 | BV30: =BV26*BV45 -> 1033.2299 | BW30: =BW26*BW45 -> 1125.6097 | BX30: =BX26*BX45 -> 1218.9073 | BY30: =BY26*BY45 -> 1296.9864 | BZ30: =BZ26*BZ45 -> 1370.9826 | ... CB30: =CB26*CB45 -> 1505.036
C31: Acquired In-Process R&D | D31: 0 | E31: 0 | F31: 0 | G31: 0 | H31: 0 | I31: 0 | J31: 0 | K31: 0 | L31: 0 | M31: 0 | N31: 0 | O31: 0 | P31: 0 | Q31: 0 | R31: 0 | S31: 0 | T31: 0 | U31: 0 | V31: 0 | W31: =0-SUM(T31:V31) -> 0 | X31: 0 | Y31: 0 | Z31: 0 | AA31: =0-SUM(X31:Z31) -> 0 | AB31: 0 | AC31: 0 | AD31: 0 | AE31: =0-SUM(AB31:AD31) -> 0 | AF31: 0 | AG31: 0 | AH31: 0 | AI31: =0-SUM(AF31:AH31) -> 0 | AJ31: 0 | AK31: 0 | AL31: 18.2 | AM31: =18.2-SUM(AJ31:AL31) -> 0 | AN31: 0 | AO31: 0 | AP31: 0 | AQ31: =0-SUM(AN31:AP31) -> 0 | AR31: 0 | AS31: 0 | AT31: 0 | AU31: =0-SUM(AR31:AT31) -> 0 | AV31: 0 | AW31: 0 | BH31: =SUM(D31:G31) -> 0 | BI31: =SUM(H31:K31) -> 0 | BJ31: =SUM(L31:O31) -> 0 | BK31: =SUM(P31:S31) -> 0 | BL31: =SUM(T31:W31) -> 0 | BM31: =SUM(X31:AA31) -> 0 | BN31: =SUM(AB31:AE31) -> 0 | BO31: =SUM(AF31:AI31) -> 0 | BP31: =SUM(AJ31:AM31) -> 18.2 | BQ31: =SUM(AN31:AQ31) -> 0 | BR31: =SUM(AR31:AU31) -> 0 | BS31: 0 | BT31: 0 | BU31: 0 | BV31: 0 | BW31: 0 | BX31: 0 | BY31: 0 | BZ31: 0 | CA31: 0 | CB31: 0
C32: Impairment Charges | D32: 0.1 | E32: =31.2-SUM(E29:E31) -> 0 | F32: =31.3-SUM(F29:F31) -> -0.1 | G32: =34.6-SUM(G29:G31) -> -0.1 | H32: =38.1-SUM(H29:H31) -> 0 | I32: 0 | J32: 0.1 | K32: 0.1 | L32: 0 | M32: -0.1 | N32: 0 | O32: 0 | P32: 0.1 | Q32: -0.1 | R32: 0 | S32: -0.1 | T32: 0 | U32: 0 | V32: 0 | W32: =0-SUM(T32:V32) -> 0 | X32: 0 | Y32: 0 | Z32: 0 | AA32: =0-SUM(X32:Z32) -> 0 | AB32: 0 | AC32: 0 | AD32: 0 | AE32: =0-SUM(AB32:AD32) -> 0 | AF32: 0 | AG32: 0 | AH32: 0 | AI32: =0-SUM(AF32:AH32) -> 0 | AJ32: 0 | AK32: 0 | AL32: 0 | AM32: =0-SUM(AJ32:AL32) -> 0 | AN32: 0 | AO32: 76.9 | AP32: 0 | AQ32: =76.94-SUM(AN32:AP32) -> 0.04 | AR32: 0 | AS32: 0 | AT32: 0 | AU32: =0-SUM(AR32:AT32) -> 0 | AV32: 0 | AW32: 0 | BH32: =SUM(D32:G32) -> -0.1 | BI32: =SUM(H32:K32) -> 0.2 | BJ32: =SUM(L32:O32) -> -0.1 | BK32: =SUM(P32:S32) -> -0.1 | BL32: =SUM(T32:W32) -> 0 | BM32: =SUM(X32:AA32) -> 0 | BN32: =SUM(AB32:AE32) -> 0 | BO32: =SUM(AF32:AI32) -> 0 | BP32: =SUM(AJ32:AM32) -> 0 | BQ32: =SUM(AN32:AQ32) -> 76.94 | BR32: =SUM(AR32:AU32) -> 0 | BS32: 115.3 | BT32: 0 | BU32: 0 | BV32: 0 | BW32: 0 | BX32: 0 | BY32: 0 | BZ32: 0 | CA32: 0 | CB32: 0
C33: Operating Income | D33: =D28-SUM(D29:D32) -> 4 | E33: =E28-SUM(E29:E32) -> -3.8 | F33: =F28-SUM(F29:F32) -> 2.2 | G33: =G28-SUM(G29:G32) -> 1.8 | H33: =H28-SUM(H29:H32) -> 1.8 | I33: =I28-SUM(I29:I32) -> -0.7 | J33: =J28-SUM(J29:J32) -> -1.4 | K33: =K28-SUM(K29:K32) -> -1.2 | ... U33: =U28-SUM(U29:U32) -> 12.801 | V33: 12.976 | W33: =W28-SUM(W29:W32) -> 10.577 | X33: =X28-SUM(X29:X32) -> 0.601 | Y33: =Y28-SUM(Y29:Y32) -> -17.625 | Z33: =Z28-SUM(Z29:Z32) -> -20.176 | AA33: =AA28-SUM(AA29:AA32) -> -1.742 | AB33: =AB28-SUM(AB29:AB32) -> 13.459 | AC33: =AC28-SUM(AC29:AC32) -> 10.332 | AD33: =AD28-SUM(AD29:AD32) -> 8.773 | ... AW33: =AW28-SUM(AW29:AW32) -> 41.039 | BH33: =SUM(D33:G33) -> 4.2 | BI33: =SUM(H33:K33) -> -1.5 | BJ33: =SUM(L33:O33) -> 1.3 | BK33: =SUM(P33:S33) -> -0.8 | BL33: =BL28-SUM(BL29:BL32) -> 47.506 | BM33: =BM28-SUM(BM29:BM32) -> -38.942 | BN33: =BN28-SUM(BN29:BN32) -> -7.501 | BO33: =BO28-SUM(BO29:BO32) -> 6.082 | BP33: =BP28-SUM(BP29:BP32) -> 73.62 | BQ33: =BQ28-SUM(BQ29:BQ32) -> 9.26 | BR33: =SUM(AR33:AU33) -> 189.249 | BS33: =BS28-SUM(BS29:BS32)+BS32 -> 190.01481 | BT33: =BT28-SUM(BT29:BT32) -> 269.78725 | BU33: =BU28-SUM(BU29:BU32) -> 327.02092 | BV33: =BV28-SUM(BV29:BV32) -> 382.54934 | BW33: =BW28-SUM(BW29:BW32) -> 437.03131 | BX33: =BX28-SUM(BX29:BX32) -> 473.71169 | BY33: =BY28-SUM(BY29:BY32) -> 502.05926 | BZ33: =BZ28-SUM(BZ29:BZ32) -> 551.58137 | CA33: =CA28-SUM(CA29:CA32) -> 606.32392 | CB33: =CB28-SUM(CB29:CB32) -> 662.93251
C34: Interest and Other Income, net | D34: 0.3 | E34: -0.4 | F34: -0.1 | G34: 0.1 | H34: 0.3 | I34: 0.3 | J34: 0.3 | K34: -0.4 | L34: 0.3 | M34: 0.4 | N34: 0.6 | O34: 0 | P34: 0.5 | Q34: 0.4 | R34: 0.9 | S34: 0.7 | T34: =0.733+0.024 -> 0.757 | U34: =0.784-0.071 -> 0.713 | V34: =0.759-0.772 -> -0.013 | W34: =2.854-0.227-SUM(T34:V34) -> 1.17 | X34: =0.299-1.555 -> -1.256 | Y34: =0.108+0.508 -> 0.616 | Z34: =0.413+0.014 -> 0.427 | AA34: =1.267-0.243-SUM(X34:Z34) -> 1.237 | AB34: =0.48-1.476 -> -0.996 | AC34: =0.299-0.408 -> -0.109 | AD34: =0.138-1.137 -> -0.999 | AE34: =0.938-3.939-SUM(AB34:AD34) -> -0.897 | AF34: =-0.041-1.01 -> -1.051 | AG34: =-0.07-0.9 -> -0.97 | AH34: =-0.04-2.35 -> -2.39 | AI34: =0.137-2.327-SUM(AF34:AH34) -> 2.221 | AJ34: 0.644 | AK34: 1.6 | AL34: 0.7 | AM34: =6.09-SUM(AJ34:AL34) -> 3.146 | AN34: 2.5 | AO34: 3.1 | AP34: 4.4 | AQ34: =11.59-SUM(AN34:AP34) -> 1.59 | AR34: 3.508 | AS34: 4.482 | AT34: 3.487 | AU34: =15.876-SUM(AR34:AT34) -> 4.399 | AV34: 3.454 | AW34: 5.148 | BH34: =SUM(D34:G34) -> -0.1 | BI34: =SUM(H34:K34) -> 0.5 | BJ34: =SUM(L34:O34) -> 1.3 | BK34: =SUM(P34:S34) -> 2.5 | BL34: =SUM(T34:W34) -> 2.627 | BM34: =SUM(X34:AA34) -> 1.024 | BN34: =SUM(AB34:AE34) -> -3.001 | BO34: =SUM(AF34:AI34) -> -2.19 | BP34: =SUM(AJ34:AM34) -> 6.09 | BQ34: =SUM(AN34:AQ34) -> 11.59 | BR34: =SUM(AR34:AU34) -> 15.876 | BS34: =BR50*$CB$53 -> 28.96795 | BT34: =BS50*$CB$53 -> 58.837198 | BU34: =BT50*$CB$53 -> 99.58663 | BV34: =BU50*$CB$53 -> 152.48597 | BW34: =BV50*$CB$53 -> 218.83034 | BX34: =BW50*$CB$53 -> 300.15719 | BY34: =BX50*$CB$53 -> 396.11693 | BZ34: =BY50*$CB$53 -> 507.49078 | ... CB34: =CA50*$CB$53 -> 793.21304
C35: Pretax Income | D35: =D33+D34 -> 4.3 | E35: =E33+E34 -> -4.2 | F35: =F33+F34 -> 2.1 | G35: =G33+G34 -> 1.9 | H35: =H33+H34 -> 2.1 | I35: =I33+I34 -> -0.4 | J35: =J33+J34 -> -1.1 | K35: =K33+K34 -> -1.6 | ... AW35: =AW33+AW34 -> 46.187 | BH35: =SUM(D35:G35) -> 4.1 | BI35: =SUM(H35:K35) -> -1 | BJ35: =SUM(L35:O35) -> 2.6 | BK35: =SUM(P35:S35) -> 1.7 | BL35: =BL33+BL34 -> 50.133 | BM35: =BM33+BM34 -> -37.918 | BN35: =BN33+BN34 -> -10.502 | BO35: =BO33+BO34 -> 3.892 | BP35: =BP33+BP34 -> 79.71 | BQ35: =BQ33+BQ34 -> 20.85 | BR35: =SUM(AR35:AU35) -> 205.125 | BS35: =BS33+BS34 -> 218.98276 | BT35: =BT33+BT34 -> 328.62445 | BU35: =BU33+BU34 -> 426.60755 | BV35: =BV33+BV34 -> 535.0353 | BW35: =BW33+BW34 -> 655.86165 | BX35: =BX33+BX34 -> 773.86888 | BY35: =BY33+BY34 -> 898.17619 | BZ35: =BZ33+BZ34 -> 1059.0721 | ... CB35: =CB33+CB34 -> 1456.1455
C36: Tax Expense (Benefit) | D36: 1.7 | E36: -1.5 | F36: 1.2 | G36: 0.2 | H36: -0.2 | I36: -3.4 | J36: -13 | K36: 0.9 | L36: 1.4 | M36: 0.5 | N36: 0.5 | O36: -5.9 | P36: -1.9 | Q36: -4.9 | R36: 1.6 | S36: 0.9 | T36: 1.455 | U36: -2.735 | V36: 1.963 | W36: =3.131-SUM(T36:V36) -> 2.448 | X36: -1.634 | Y36: -4.129 | Z36: -9.855 | AA36: =-18.761-SUM(X36:Z36) -> -3.143 | AB36: 1.541 | AC36: 1.9 | AD36: -0.249 | AE36: =-13.125-SUM(AB36:AD36) -> -16.317 | AF36: -5.183 | AG36: 2.52 | AH36: 5.3 | AI36: =5.894-SUM(AF36:AH36) -> 3.257 | AJ36: 0.09 | AK36: 0.5 | AL36: 4.09 | AM36: =-11.3-SUM(AJ36:AL36) -> -15.98 | AN36: 3.6 | AO36: -17.6 | AP36: 10.3 | AQ36: =6.86-SUM(AN36:AP36) -> 10.56 | AR36: 4.635 | AS36: 0.04 | AT36: 6.474 | AU36: =27.438-SUM(AR36:AT36) -> 16.289 | AV36: 9.104 | AW36: 11.376 | BH36: =SUM(D36:G36) -> 1.6 | BI36: =SUM(H36:K36) -> -15.7 | BJ36: =SUM(L36:O36) -> -3.5 | BK36: =SUM(P36:S36) -> -4.3 | BL36: =SUM(T36:W36) -> 3.131 | BM36: =SUM(X36:AA36) -> -18.761 | BN36: =SUM(AB36:AE36) -> -13.125 | BO36: =SUM(AF36:AI36) -> 5.894 | BP36: =SUM(AJ36:AM36) -> -11.3 | BQ36: =SUM(AN36:AQ36) -> 6.86 | BR36: =SUM(AR36:AU36) -> 27.438 | BS36: =BS35*BS47 -> 26.277931 | BT36: =BT35*BT47 -> 65.72489 | BU36: =BU35*BU47 -> 85.32151 | BV36: =BV35*BV47 -> 107.00706 | BW36: =BW35*BW47 -> 131.17233 | BX36: =BX35*BX47 -> 154.77378 | BY36: =BY35*BY47 -> 179.63524 | BZ36: =BZ35*BZ47 -> 211.81443 | ... CB36: =CB35*CB47 -> 291.22911
C37: Consolidated Net Income | D37: 2.5 | E37: -2.7 | F37: 0.9 | G37: 1.6 | H37: 2.3 | I37: 3 | J37: 11.9 | K37: -2.4 | L37: -3.1 | M37: -1.6 | N37: 0.2 | O37: 9.1 | P37: 5.5 | Q37: 13.4 | R37: -22.4 | S37: 6.5 | T37: =T35-T36 -> 10.454 | U37: =U35-U36 -> 16.249 | V37: =V35-V36 -> 11 | W37: =W35-W36 -> 9.299 | X37: =X35-X36 -> 0.979 | Y37: =Y35-Y36 -> -12.88 | Z37: =Z35-Z36 -> -9.894 | AA37: =AA35-AA36 -> 2.638 | ... AW37: =AW35-AW36 -> 34.811 | BH37: =SUM(D37:G37) -> 2.3 | BI37: =SUM(H37:K37) -> 14.8 | BJ37: =SUM(L37:O37) -> 4.6 | BK37: =SUM(P37:S37) -> 3 | BL37: =BL35-BL36 -> 47.002 | BM37: =BM35-BM36 -> -19.157 | BN37: =BN35-BN36 -> 2.623 | BO37: =BO35-BO36 -> -2.002 | BP37: =BP35-BP36 -> 91.01 | BQ37: =BQ35-BQ36 -> 13.99 | BR37: =SUM(AR37:AU37) -> 177.687 | BS37: =BS35-BS36 -> 192.70483 | BT37: =BT35-BT36 -> 262.89956 | BU37: =BU35-BU36 -> 341.28604 | BV37: =BV35-BV36 -> 428.02824 | BW37: =BW35-BW36 -> 524.68932 | BX37: =BX35-BX36 -> 619.0951 | BY37: =BY35-BY36 -> 718.54095 | BZ37: =BZ35-BZ36 -> 847.25772 | ... CB37: =CB35-CB36 -> 1164.9164
C38: Net Income attr to Non-Cont. | D38: 2 | E38: -2.15 | F38: 0.58 | G38: 0.85 | H38: -0.2 | I38: 0 | J38: -0.3 | K38: 0 | L38: 0 | M38: 0 | N38: 0 | O38: 0 | P38: 0 | Q38: 0 | R38: -3.5 | S38: -0.02 | T38: -0.244 | U38: -0.537 | V38: -0.483 | W38: =-1.454-SUM(T38:V38) -> -0.19 | X38: -0.537 | Y38: -0.94 | Z38: -1.061 | AA38: =-3.555-SUM(X38:Z38) -> -1.017 | AB38: -0.91 | AC38: -0.932 | AD38: -0.819 | AE38: =-2.641-SUM(AB38:AD38) -> 0.02 | AF38: 0 | AG38: 0 | AH38: 0 | AI38: 0 | AJ38: 0 | AK38: 0 | AL38: 0 | AM38: 0 | AN38: 0 | AO38: 0 | AP38: 0 | AQ38: 0 | AR38: 0 | AS38: 0 | AT38: 0 | AU38: 0 | AV38: 0 | AW38: 0 | BH38: =SUM(D38:G38) -> 1.28 | BI38: =SUM(H38:K38) -> -0.5 | BJ38: =SUM(L38:O38) -> 0 | BK38: =SUM(P38:S38) -> -3.52 | BL38: =SUM(T38:W38) -> -1.454 | BM38: -3.555 | BN38: -2.661 | BO38: 0 | BP38: 0 | BQ38: 0 | BR38: =SUM(AR38:AU38) -> 0 | BS38: 0 | BT38: 0 | BU38: 0 | BV38: 0 | BW38: 0 | BX38: 0 | BY38: 0 | BZ38: 0 | CA38: 0 | CB38: 0
C39: Net Income attr to PEN | D39: =D37-D38 -> 0.5 | E39: =E37-E38 -> -0.55 | F39: =F37-F38 -> 0.32 | G39: =G37-G38 -> 0.75 | H39: =H37-H38 -> 2.5 | I39: =I37-I38 -> 3 | J39: =J37-J38 -> 12.2 | K39: =K37-K38 -> -2.4 | ... AW39: =AW37-AW38 -> 34.811 | BH39: =SUM(D39:G39) -> 1.02 | BI39: =SUM(H39:K39) -> 15.3 | BJ39: =SUM(L39:O39) -> 4.6 | BK39: =SUM(P39:S39) -> 6.52 | BL39: =BL37-BL38 -> 48.456 | BM39: =BM37-BM38 -> -15.602 | BN39: =BN37-BN38 -> 5.284 | BO39: =BO37-BO38 -> -2.002 | BP39: =BP37-BP38 -> 91.01 | BQ39: =BQ37-BQ38 -> 13.99 | BR39: =SUM(AR39:AU39) -> 177.687 | BS39: =BS37-BS38 -> 192.70483 | BT39: =BT37-BT38 -> 262.89956 | BU39: =BU37-BU38 -> 341.28604 | BV39: =BV37-BV38 -> 428.02824 | BW39: =BW37-BW38 -> 524.68932 | BX39: =BX37-BX38 -> 619.0951 | BY39: =BY37-BY38 -> 718.54095 | BZ39: =BZ37-BZ38 -> 847.25772 | ... CB39: =CB37-CB38 -> 1164.9164 | CC39: =CB39*(1+$CB$54) -> 1192.292 | CD39: =CC39*(1+$CB$54) -> 1220.3108 | CE39: =CD39*(1+$CB$54) -> 1248.9881 | CF39: =CE39*(1+$CB$54) -> 1278.3394 | CG39: =CF39*(1+$CB$54) -> 1308.3803 | CH39: =CG39*(1+$CB$54) -> 1339.1273 | CI39: =CH39*(1+$CB$54) -> 1370.5968 | CJ39: =CI39*(1+$CB$54) -> 1402.8058 | ... DP39: =DO39*(1+$CB$54) -> 2949.9092
C40: SC | D40: 5 | E40: 5 | F40: 8 | G40: 12 | H40: 30 | I40: 30 | J40: 31 | K40: 30 | L40: 32 | M40: 33 | N40: 33 | O40: 33 | P40: 34 | Q40: 34 | R40: 34 | S40: 34 | T40: 34.507 | U40: 34.694 | V40: 34.84 | W40: 35 | X40: 35 | Y40: 35.4 | Z40: 36.207 | AA40: 37.651 | AB40: 36.455 | AC40: 36.523 | AD40: 36.617 | AE40: 36.7 | AF40: 37.646 | AG40: 37.767 | AH40: 37.918 | AI40: 37.841 | AJ40: 39.07 | AK40: 38.15 | AL40: 38.956 | AM40: 38.4 | AN40: 39.3 | AO40: 38.8 | AP40: 38.6 | AQ40: 38.63 | AR40: 38.562 | AS40: 38.834 | AT40: 39.078 | AU40: 38.63 | AV40: 39.275 | AW40: 39.353 | BH40: 12 | BI40: 31 | BJ40: 33 | BK40: 34 | BL40: 34.8 | BM40: 35.5 | BN40: =AE40 -> 36.7 | BO40: =AI40 -> 37.841 | BP40: =AM40 -> 38.4 | BQ40: =AQ40 -> 38.63 | BR40: =AVERAGE(AR40:AU40) -> 38.776 | BS40: =BQ40*1.05 -> 40.5615 | BT40: =BS40*1.05 -> 42.589575 | BU40: =BT40*1.05 -> 44.719054 | BV40: =BU40*1.05 -> 46.955006 | BW40: =BV40*1.05 -> 49.302757 | BX40: =BW40*1.05 -> 51.767895 | BY40: =BX40*1.05 -> 54.356289 | BZ40: =BY40*1.05 -> 57.074104 | CA40: =BZ40*1.05 -> 59.927809 | CB40: =CA40*1.05 -> 62.924199
C41: EPS | D41: =D39/D40 -> 0.1 | E41: =E39/E40 -> -0.11 | F41: =F39/F40 -> 0.04 | G41: =G39/G40 -> 0.0625 | H41: =H39/H40 -> 0.083333333 | I41: =I39/I40 -> 0.1 | J41: =J39/J40 -> 0.39354839 | K41: =K39/K40 -> -0.08 | ... AW41: =AW39/AW40 -> 0.88458313 | AX41: 1.29 | AY41: 1.47 | AZ41: 1.24 | BH41: =BH39/BH40 -> 0.085 | BI41: =BI39/BI40 -> 0.49354839 | BJ41: =BJ39/BJ40 -> 0.13939394 | BK41: =BK39/BK40 -> 0.19176471 | BL41: =BL39/BL40 -> 1.3924138 | BM41: =BM39/BM40 -> -0.43949296 | BN41: =BN39/BN40 -> 0.1439782 | BO41: =BO39/BO40 -> -0.052905579 | ... BQ41: =BQ39/BQ40 -> 0.36215377 | BR41: =SUM(AR41:AU41) -> 4.5817424 | BS41: =BS39/BS40 -> 4.7509295 | BT41: =BT39/BT40 -> 6.1728618 | BU41: =BU39/BU40 -> 7.6317814 | BV41: =BV39/BV40 -> 9.1157104 | BW41: =BW39/BW40 -> 10.64219 | BX41: =BX39/BX40 -> 11.959055 | BY41: =BY39/BY40 -> 13.219095 | BZ41: =BZ39/BZ40 -> 14.844871 | ... CB41: =CB39/CB40 -> 18.513012
C43: Gross Profit Margin | D43: =D28/D26 -> 0.68717949 | E43: =E28/E26 -> 0.64775414 | F43: =F28/F26 -> 0.66468254 | G43: =G28/G26 -> 0.66911765 | H43: =H28/H26 -> 0.68911917 | I43: =I28/I26 -> 0.6374808 | J43: =J28/J26 -> 0.63839286 | K43: =K28/K26 -> 0.6374829 | ... AS43: =AS28/AS26 -> 0.65991074 | AT43: 0.67 | AU43: =AU28/AU26 -> 0.68017178 | AV43: 0.678 | AW43: 0.685 | BH43: =BH28/BH26 -> 0.66684578 | BI43: =BI28/BI26 -> 0.6490695 | BJ43: =BJ28/BJ26 -> 0.65068904 | BK43: =BK28/BK26 -> 0.65745111 | BL43: =BL28/BL26 -> 0.67950304 | BM43: =BM28/BM26 -> 0.60343997 | BN43: =BN28/BN26 -> 0.63588598 | BO43: =BO28/BO26 -> 0.63178627 | ... BR43: =BR28/BR26 -> 0.67141163 | BS43: 0.67 | BT43: 0.685 | BU43: 0.69 | BV43: 0.6975 | BW43: 0.7 | BX43: 0.701 | BY43: 0.702 | BZ43: 0.703 | CA43: 0.704 | CB43: 0.705
C44: R&D as % of Revenues | D44: =D29/D26 -> 0.082051282 | E44: =E29/E26 -> 0.11347518 | F44: =F29/F26 -> 0.091269841 | G44: =G29/G26 -> 0.10110294 | H44: =H29/H26 -> 0.086355786 | I44: =I29/I26 -> 0.096774194 | J44: =J29/J26 -> 0.09672619 | K44: =K29/K26 -> 0.083447332 | ... AS44: =AS29/AS26 -> 0.068397873 | AT44: 0.068 | AU44: =AU29/AU26 -> 0.056551241 | AV44: 0.073 | AW44: 0.075 | BH44: =BH29/BH26 -> 0.097259538 | BI44: =BI29/BI26 -> 0.090770984 | BJ44: =BJ29/BJ26 -> 0.094667466 | BK44: =BK29/BK26 -> 0.15059564 | BL44: =BL29/BL26 -> 0.094487973 | BM44: =BM29/BM26 -> 0.16068357 | BN44: =BN29/BN26 -> 0.13985206 | BO44: =BO29/BO26 -> 0.093736167 | ... BR44: =BR29/BR26 -> 0.063951156 | BS44: 0.078 | BT44: 0.079 | BU44: 0.08 | BV44: 0.085 | BW44: 0.085 | BX44: 0.09 | BY44: 0.1 | BZ44: 0.1 | CA44: 0.1 | CB44: 0.1
C45: SG&A as % of Revenues | D45: =D30/D26 -> 0.5 | E45: =E30/E26 -> 0.62411348 | F45: =F30/F26 -> 0.53174603 | G45: =G30/G26 -> 0.53676471 | H45: =H30/H26 -> 0.5716753 | I45: =I30/I26 -> 0.55145929 | J45: =J30/J26 -> 0.5610119 | K45: =K30/K26 -> 0.56908345 | ... AS45: =AS30/AS26 -> 0.47123772 | AT45: 0.47 | AU45: =AU30/AU26 -> 0.46992229 | AV45: 0.466 | AW45: 0.464 | BH45: =BH30/BH26 -> 0.54755508 | BI45: =BI30/BI26 -> 0.56323585 | BJ45: =BJ30/BJ26 -> 0.5524266 | BK45: =BK30/BK26 -> 0.5088784 | BL45: =BL30/BL26 -> 0.49823074 | BM45: =BM30/BM26 -> 0.51224456 | BN45: =BN30/BN26 -> 0.5060675 | BO45: =BO30/BO26 -> 0.5308706 | ... BR45: =BR30/BR26 -> 0.47263556 | BS45: 0.475 | BT45: 0.46 | BU45: 0.453 | BV45: 0.447 | BW45: 0.443 | BX45: 0.44 | BY45: 0.434 | BZ45: 0.43 | CA45: 0.425 | CB45: 0.42
C46: Operating Profit Margin | D46: =D33/D26 -> 0.1025641 | E46: =E33/E26 -> -0.089834515 | F46: =F33/F26 -> 0.043650794 | G46: =G33/G26 -> 0.033088235 | H46: =H33/H26 -> 0.031088083 | I46: =I33/I26 -> -0.010752688 | J46: =J33/J26 -> -0.020833333 | K46: =K33/K26 -> -0.016415869 | ... AW46: =AW33/AW26 -> 0.1052158 | BH46: =BH33/BH26 -> 0.022568512 | BI46: =BI33/BI26 -> -0.0056969237 | BJ46: =BJ33/BJ26 -> 0.0038945476 | BK46: =BK33/BK26 -> -0.0017981569 | BL46: =BL33/BL26 -> 0.086784325 | BM46: =BM33/BM26 -> -0.069488162 | BN46: =BN33/BN26 -> -0.010033575 | BO46: =BO33/BO26 -> 0.0071795102 | ... CB46: =CB33/CB26 -> 0.185
C47: Effective Tax Rate | D47: =D36/D35 -> 0.39534884 | E47: =E36/E35 -> 0.35714286 | F47: =F36/F35 -> 0.57142857 | G47: =G36/G35 -> 0.10526316 | H47: =H36/H35 -> -0.095238095 | I47: =I36/I35 -> 8.5 | J47: =J36/J35 -> 11.818182 | K47: =K36/K35 -> -0.5625 | ... AS47: =AS36/AS35 -> 0.00088280733 | AT47: 0.2 | AU47: =AU36/AU35 -> 0.25598755 | AV47: 0.23 | AW47: 0.23 | BH47: =BH36/BH35 -> 0.3902439 | BI47: =BI36/BI35 -> 15.7 | BJ47: =BJ36/BJ35 -> -1.3461538 | BK47: =BK36/BK35 -> -2.5294118 | BL47: =BL36/BL35 -> 0.062453873 | BM47: =BM36/BM35 -> 0.49477821 | BN47: =BN36/BN35 -> 1.249762 | BO47: =BO36/BO35 -> 1.5143885 | ... BR47: =BR36/BR35 -> 0.13376234 | BS47: 0.12 | BT47: 0.2 | BU47: 0.2 | BV47: 0.2 | BW47: 0.2 | BX47: 0.2 | BY47: 0.2 | BZ47: 0.2 | CA47: 0.2 | CB47: 0.2
C48: Net Profit Margin | D48: =D37/D26 -> 0.064102564 | E48: =E37/E26 -> -0.063829787 | F48: =F37/F26 -> 0.017857143 | G48: =G37/G26 -> 0.029411765 | H48: =H37/H26 -> 0.039723661 | I48: =I37/I26 -> 0.046082949 | J48: =J37/J26 -> 0.17708333 | K48: =K37/K26 -> -0.032831737 | ... AS48: =AS37/AS26 -> 0.13336083 | AT48: =AT39/AT26 -> 0.12927245 | AU48: =AU37/AU26 -> 0.12284599 | AV48: =AV39/AV26 -> 0.086946776 | AW48: =AW39/AW26 -> 0.089248448 | BH48: =BH39/BH26 -> 0.0054809242 | BI48: =BI39/BI26 -> 0.058108621 | BJ48: =BJ39/BJ26 -> 0.013780707 | BK48: =BK39/BK26 -> 0.014654979 | BL48: =BL39/BL26 -> 0.088519793 | BM48: =BM39/BM26 -> -0.027840232 | BN48: =BN39/BN26 -> 0.0070680453 | BO48: =BO39/BO26 -> -0.0023632653 | ... CB48: =CB39/CB26 -> 0.32508519
C50: Cash & C.E.s | T50: 95.606 | U50: 77.261 | V50: 111.581 | W50: 72.779 | X50: 72.456 | Y50: 134.381 | Z50: 80.115 | AA50: 69.67 | AB50: 55.632 | AC50: 82.277 | AD50: 66.29 | AE50: 59.379 | AF50: 68.163 | AG50: 58.234 | AH50: 54.844 | AI50: 69.858 | AJ50: 94.688 | AK50: 114.167 | AL50: 100.757 | AM50: 167.486 | AN50: 223.114 | AO50: 288.332 | AP50: 280.476 | AQ50: 324.4 | AR50: 376.054 | AS50: 421.768 | AT50: 321.029 | AU50: 186.89 | AV50: 241.289 | AW50: 205.271 | BL50: =W50 -> 72.779 | BM50: =AA50 -> 69.67 | BN50: =AE50 -> 59.379 | BO50: =AI50 -> 69.858 | BP50: =AM50 -> 167.486 | BQ50: =AQ50 -> 324.4 | BR50: 186.89 | BS50: =BR50+BS39 -> 379.59483 | BT50: =BS50+BT39 -> 642.49438 | BU50: =BT50+BU39 -> 983.78043 | BV50: =BU50+BV39 -> 1411.8087 | BW50: =BV50+BW39 -> 1936.498 | BX50: =BW50+BX39 -> 2555.5931 | BY50: =BX50+BY39 -> 3274.134 | BZ50: =BY50+BZ39 -> 4121.3918 | ... CB50: =CA50+CB39 -> 6282.4199
C51: Marketable Investments | T51: 99.241 | U51: 109.996 | V51: 82.864 | W51: 116.61 | X51: 95.766 | Y51: 143.914 | Z51: 188.611 | AA51: 195.162 | AB51: 186.977 | AC51: 156.722 | AD51: 200.637 | AE51: 195.496 | AF51: 172.178 | AG51: 146.135 | AH51: 129.583 | AI51: 118.172 | AJ51: 104.409 | AK51: 106.896 | AL51: 148.098 | AM51: 121.701 | AN51: 90.36 | AO51: 51.363 | AP51: 10.548 | AQ51: 15.727 | AR51: 2.794 | AS51: 2.795 | AT51: 149.267 | AU51: 357.919 | AV51: 374.371 | AW51: 453.524 | BL51: =W51 -> 116.61 | BM51: =AA51 -> 195.162 | BN51: =AE51 -> 195.496 | BO51: =AI51 -> 118.172 | BP51: =AM51 -> 121.701 | BQ51: =AQ51 -> 15.727 | BR51: 357.919
C52: A/R | T52: 94.679 | U52: 99.011 | V52: 101.828 | W52: 105.901 | X52: 103.963 | Y52: 97.613 | Z52: 112.817 | AA52: 114.608 | AB52: 126.415 | AC52: 136.61 | AD52: 120.074 | AE52: 133.94 | AF52: 143.417 | AG52: 187.389 | AH52: 189.006 | AI52: 203.384 | AJ52: 207.364 | AK52: 208.965 | AL52: 206.615 | AM52: 201.768 | AN52: 191.989 | AO52: 200.831 | AP52: 176.051 | AQ52: 167.667 | AR52: 167.981 | AS52: 175.536 | AT52: 183.43 | AU52: 190.02 | AV52: 183.295 | AW52: 190.407 | BL52: =W52 -> 105.901 | BM52: =AA52 -> 114.608 | BN52: =AE52 -> 133.94 | BO52: =AI52 -> 203.384 | BP52: =AM52 -> 201.768 | BQ52: =AQ52 -> 167.667 | BR52: 190.02
C53: Inventories | T53: 121.691 | U53: 132.735 | V53: 140.359 | W53: 152.992 | X53: 166.152 | Y53: 183.442 | Z53: 191.547 | AA53: 219.527 | AB53: 245.321 | AC53: 254.977 | AD53: 258.316 | AE53: 263.504 | AF53: 274.349 | AG53: 295.883 | AH53: 320.304 | AI53: 334.006 | AJ53: 344.042 | AK53: 358.77 | AL53: 374.245 | AM53: 388.023 | AN53: 398.366 | AO53: 373.799 | AP53: 393.413 | AQ53: 406.737 | AR53: 415.863 | AS53: 427.628 | AT53: 432.365 | AU53: 431.549 | AV53: 438.539 | AW53: 442.65 | BL53: =W53 -> 152.992 | BM53: =AA53 -> 219.527 | BN53: =AE53 -> 263.504 | BO53: =AI53 -> 334.006 | BP53: =AM53 -> 388.023 | BQ53: =AQ53 -> 406.737 | BR53: 431.549 | BT53: Invested Capital | BW53: Avg. (2023-2024) | BY53: Projected ROIC: | CA53: ROIC | CB53: 0.155
C54: Prepaid Expenses | T54: 11.869 | U54: 15.601 | V54: 14.702 | W54: 14.852 | X54: 15.403 | Y54: 16.545 | Z54: 17.109 | AA54: 18.735 | AB54: 20.782 | AC54: 22.526 | AD54: 22.67 | AE54: 29.155 | AF54: 32.219 | AG54: 30.32 | AH54: 29.888 | AI54: 30.279 | AJ54: 35.987 | AK54: 39.078 | AL54: 38.761 | AM54: 36.424 | AN54: 31.194 | AO54: 29.47 | AP54: 31.265 | AQ54: 36.589 | AR54: 37.017 | AS54: 37.757 | AT54: 55.429 | AU54: 50.298 | AV54: 37.912 | AW54: 52.27 | BL54: =W54 -> 14.852 | BM54: =AA54 -> 18.735 | BN54: =AE54 -> 29.155 | BO54: =AI54 -> 30.279 | BP54: =AM54 -> 36.424 | BQ54: =AQ54 -> 36.589 | BR54: 50.298 | BT54: 2024 | BU54: 2025 | BW54: 2024-2025 | BY54: 2025 | CA54: Terminal | CB54: 0.0235
C55: PP&E | T55: 35.38 | U55: 37.94 | V55: 45.625 | W55: 51.812 | X55: 58.698 | Y55: 62.188 | Z55: 64.906 | AA55: 48.169 | AB55: 50.314 | AC55: 50.854 | AD55: 56.632 | AE55: 58.856 | AF55: 60.327 | AG55: 63.458 | AH55: 64.082 | AI55: 65.015 | AJ55: 65.224 | AK55: 65.958 | AL55: 65.632 | AM55: 72.691 | AN55: 75.744 | AO55: 57.709 | AP55: 59.919 | AQ55: 62.641 | AR55: 72.465 | AS55: 84.825 | AT55: 97.73 | AU55: 117.436 | AV55: 134.059 | AW55: 146.718 | BL55: =W55 -> 51.812 | BM55: =AA55 -> 48.169 | BN55: =AE55 -> 58.856 | BO55: =AI55 -> 65.015 | BP55: =AM55 -> 72.691 | BQ55: =AQ55 -> 62.641 | BR55: 117.436 | BT55: =SUM(BQ50:BQ53)-BQ64+BQ56+BQ58+BQ57 -> 1095.523 | BU55: =SUM(BR50:BR53)-BR64+BR56+BR58+BR57 -> 1337.387 | BW55: =AVERAGE(BT55:BT55) -> 1095.523 | BY55: =AVERAGE(BS33)*(1-BS47) -> 167.21303 | CA55: RFR (10-year yield) | CB55: ='Bull Case (30%)'!BV64 -> 0.0511
C56: Operating Leases | T56: 42.376 | U56: 42.476 | V56: 41.817 | W56: 43.717 | X56: 43.168 | Y56: 42.669 | Z56: 41.778 | AA56: 41.192 | AB56: 40.691 | AC56: 92.791 | AD56: 133.552 | AE56: 131.955 | AF56: 176.892 | AG56: 177.423 | AH56: 174.684 | AI56: 192.636 | AJ56: 189.839 | AK56: 187.494 | AL56: 184.52 | AM56: 188.756 | AN56: 185.845 | AO56: 183.316 | AP56: 180.923 | AQ56: 177.787 | AR56: 175.331 | AS56: 174.059 | AT56: 170.715 | AU56: 173.587 | AV56: 170.273 | AW56: 167.194 | BL56: =W56 -> 43.717 | BM56: =AA56 -> 41.192 | BN56: =AE56 -> 131.955 | BO56: =AI56 -> 192.636 | BP56: =AM56 -> 188.756 | BQ56: =AQ56 -> 177.787 | BR56: 173.587 | BY56: =BY55/BW55 -> 0.15263306 | CA56: ERP (Avg. market return - (less) RFR) | CB56: =10.25%-CB55 -> 0.0514
C57: Financing Leases | U57: 0 | V57: 0 | W57: 39.924 | X57: 39.287 | Y57: 37.927 | Z57: 38.798 | AA57: 38.065 | AB57: 37.697 | AC57: 37.031 | AD57: 36.845 | AE57: 36.276 | AF57: 35.55 | AG57: 34.743 | AH57: 34.114 | AI57: 33.323 | AJ57: 32.569 | AK57: 31.751 | AL57: 31.364 | AM57: 31.092 | AN57: 30.234 | AO57: 29.366 | AP57: 28.888 | AQ57: 28.018 | AR57: 27.126 | AS57: 27.606 | AT57: 26.79 | AU57: 25.972 | AV57: 25.209 | AW57: 24.357 | BL57: =W57 -> 39.924 | BM57: =AA57 -> 38.065 | BN57: =AE57 -> 36.276 | BO57: =AI57 -> 33.323 | BP57: =AM57 -> 31.092 | BQ57: =AQ57 -> 28.018 | BR57: 25.972 | BT57: Capital Structure | CA57: Equity β (1-year avg.) | CB57: ='Notes | Analysis'!T240 -> 0.76850681
