Workbook

Sheet Main
B2: PL
B3: Price | C3: 17.43 | D3: 7/5/2026
B4: SO | C4: 359.594 | D4: Q1'26
B5: MC | C5: =C3*C4 -> 6267.7234
B6: Cash | C6: =415.13+1.891+450.288 -> 867.309 | D6: Q1'26
B7: Debt | C7: 448.255 | D7: Q1'26
B8: EV | C8: =C5-C6+C7 -> 5848.6694
M9: Resources:
B10: Planet Labs PBC (PL) | M10: SEC filings | P10: https://www.sec.gov/edgar/browse/?CIK=1836833&owner=exclude
M11: Company Homepage | P11: https://www.planet.com/
B12: Founder(s): Will Marshall, Robbie Schingler, and Chris Boshuizen (three former NASA scientists) | F12: Registered Exchange: NYSE | N12: Company IR Page | Q12: https://investors.planet.com/overview/default.aspx
B13: Founded: 2010 | F13: Address: 645 Harrison Street, San Francisco, CA 94107 U.S. | N13: Planet Labs Constellations | Q13: https://www.planet.com/constellations/
B14: Headquarters: San Francisco, CA | F14: Investor Relations Contact: | N14: Comprehensive Dove 1 Space Missions | Q14: https://space.skyrocket.de/doc_sdat/dove-1.htm
B15: Current CEO: William Marshall | F15: Investors Relation Department | M15: Earnings Calls | P15: https://seekingalpha.com/symbol/PL/earnings/transcripts
B16: Employees: 1,000 | F16: Phone: | G16: (415) 829 - 3313 | I16: Email: | M16: Equity Analysis | P16: https://stockanalysis.com/stocks/pl/company/
B17: Industry: Aerospace & Defense | M17: MacroTrends | P17: https://www.macrotrends.net/stocks/charts/PL/planet-labs-pbc/revenue
B18: Sector: Industrials | M18: ROIC, WACC | P18: https://www.gurufocus.com/term/wacc/PL
B19: IPO: December 8th, 2021 (Through SPAC) -- $2.8B valuation | M19: Godel Terminal | P19: https://app.godelterminal.com/
B20: Fiscal Year: [February - January] | M20: SpaceNews | P20: https://spacenews.com/
A22: Company Overview:
B23: Planet is a vertically integrated Earth Observation (EO) enterprise and operates a large fleet of LEO imaging satellites. The Company sells satellite images, analytics, and related services through a cloud platform and APIs ... Their main value is giving customers frequent, updated views of Earth for monitoring change over time
C24: The Company is best viewed as a geospatial data platform, not just a satellite company … Market offerings are strongest where customers need frequent monitoring of large areas rather than one-off high-resolution snapshots … sells daily satellite imagery and analytics through a recurring subscription model
B25: The Company's core asset is the Dove/SuperDove constellation for daily, broad-earth coverage, with SkySat and Pelican for higher-resolution tasking and Tanager for hyperspectral monitoring
C26: The Earth Observation platform enables customers to access, analyze, and act on proprietary data catalogs by discovering image tasking capacity, relevant data layers, extracting useful information, and delivering insights through custom-built solutions or GIS workflows via APIs and browser-based applications
C27: In addition, the company’s satellite services arrangements include designing and manufacturing customer-owned satellites, mission systems engineering, launch procurement, ground station infrastructure, satellite operations, and maintenance, as well as dedicated image tasking capacity on company-owned or customer-owned satellites
B28: Main Satellite Assets:
C29: Dove / SuperDove: daily, medium-resolution global coverage
C30: SkySat: higher-resolution imagery for specific locations
C31: Pelican: next-gen very-high-resolution tasking satellites
C32: Tanager: hyperspectral satellites for more detailed environmental monitoring
B33: The Company reports revenue through a consolidated revenue reporting framework (no segmentation) but frequently destinguishes end customers between Government / National Defense and Enterprise Solutions … Main Customers include: Government, defense, agriculture, forestry, mapping, energy, finance, and insurance customers
C34: Google has maintained a close relationship with Planet Labs, acting as a major partner … similar in nature to PLTR / BKSY partnership … very interesting
B35: Planet Labs was founded in 2010 as a Public Benefit Corporation and is headquartered in San Francisco, California
A37: Business Segments and Geographical Info:
B38: [Begin researching fundamentals / core business … begin with SEC filings, but expand and use all public resources available]

Sheet Bull Case
B1: [Use for Graphing] | C1: Q1 2021 | G1: Q1 2022 | K1: Q1 2023 | O1: Q1 2024 | S1: Q1 2025 | W1: Q1 2026
B2: Quarterly
B3: Revenues | C3: Q1 2021 | D3: Q2 2021 | E3: Q3 2021 | F3: Q4 2021 | G3: Q1 2022 | H3: Q2 2022 | I3: Q3 2022 | J3: Q4 2022 | K3: Q1 2023 | L3: Q2 2023 | M3: Q3 2023 | N3: Q4 2023 | O3: Q1 2024 | P3: Q2 2024 | Q3: Q3 2024 | R3: Q4 2024 | S3: Q1 2025 | T3: Q2 2025 | U3: Q3 2025 | V3: Q4 2025 | W3: Q1 2026 | X3: Q2 2026 | Y3: Q3 2026 | Z3: Q4 2026 | AF3: 2020 | AG3: =AF3+1 -> 2021 | AH3: =AG3+1 -> 2022 | AI3: =AH3+1 -> 2023 | AJ3: =AI3+1 -> 2024 | AK3: =AJ3+1 -> 2025 | AL3: 2026 | AM3: =AL3+1 -> 2027 | AN3: =AM3+1 -> 2028 | AO3: =AN3+1 -> 2029 | AP3: =AO3+1 -> 2030 | AQ3: =AP3+1 -> 2031 | AR3: =AQ3+1 -> 2032 | AS3: =AR3+1 -> 2033 | AT3: =AS3+1 -> 2034 | ... CS3: =CR3+1 -> 2085
B4: Civil Government | O4: 18.049 | P4: 17.179 | Q4: 18.552 | R4: =71.887-SUM(O4:Q4) -> 18.107 | S4: 16.28 | T4: 16.426 | U4: 18.828 | V4: =71.91-SUM(S4:U4) -> 20.376 | W4: 16.169 | X4: 17.498 | AI4: =SUM(O4:R4) -> 71.887 | AJ4: =SUM(P4:S4) -> 70.118 | AK4: =SUM(S4:V4) -> 71.91 | AL4: =AK4*(1+AL9) -> 76.2246 | AM4: =AL4*(1+AM9) -> 81.560322 | AN4: =AM4*(1+AN9) -> 88.085148 | AO4: =AN4*(1+AO9) -> 94.251108 | AP4: =AO4*(1+AP9) -> 99.906175 | AQ4: =AP4*(1+AQ9) -> 104.90148 | AR4: =AQ4*(1+AR9) -> 109.09754 | AS4: =AR4*(1+AS9) -> 112.91596 | ... AU4: =AT4*(1+AU9) -> 119.21102
B5: Commercial | O5: 12.777 | P5: 14.232 | Q5: 14.173 | R5: =56.184-SUM(O5:Q5) -> 15.002 | S5: 13.338 | T5: 15.051 | U5: 13.061 | V5: =55.585-SUM(S5:U5) -> 14.135 | W5: 16.595 | X5: 17.559 | AI5: =SUM(O5:R5) -> 56.184 | AJ5: =SUM(P5:S5) -> 56.745 | AK5: =SUM(S5:V5) -> 55.585 | AL5: =AK5*(1+AL10) -> 68.9254 | AM5: =AL5*(1+AM10) -> 83.399734 | AN5: =AM5*(1+AN10) -> 98.411686 | AO5: =AN5*(1+AO10) -> 114.15756 | AP5: =AO5*(1+AP10) -> 130.13961 | AQ5: =AP5*(1+AQ10) -> 145.75637 | AR5: =AQ5*(1+AR10) -> 160.332 | AS5: =AR5*(1+AS10) -> 173.15856 | ... AU5: =AT5*(1+AU10) -> 190.89
B6: Defense & Intelligence | O6: 29.614 | P6: 29.681 | Q6: 28.541 | R6: =116.281-SUM(O6:Q6) -> 28.445 | S6: 36.647 | T6: 41.909 | U6: 49.365 | V6: =180.232-SUM(S6:U6) -> 52.311 | W6: 61.386 | X6: 80.995 | AI6: =SUM(O6:R6) -> 116.281 | AJ6: =SUM(P6:S6) -> 123.314 | AK6: =SUM(S6:V6) -> 180.232 | AL6: =AK6*(1+AL11) -> 306.3944 | AM6: =AL6*(1+AM11) -> 459.5916 | AN6: =AM6*(1+AN11) -> 652.62007 | AO6: =AN6*(1+AO11) -> 822.30129 | AP6: =AO6*(1+AP11) -> 1060.7687 | AQ6: =AP6*(1+AQ11) -> 1336.5685 | AR6: =AQ6*(1+AR11) -> 1643.9793 | AS6: =AR6*(1+AS11) -> 1972.7751 | ... AU6: =AT6*(1+AU11) -> 2654.3689
B7: Ttl Revenues | O7: =SUM(O4:O6) -> 60.44 | P7: =SUM(P4:P6) -> 61.092 | Q7: =SUM(Q4:Q6) -> 61.266 | R7: =SUM(R4:R6) -> 61.554 | S7: =SUM(S4:S6) -> 66.265 | T7: =SUM(T4:T6) -> 73.386 | U7: =SUM(U4:U6) -> 81.254 | V7: =SUM(V4:V6) -> 86.822 | ... X7: =SUM(X4:X6) -> 116.052 | AI7: =SUM(O7:R7) -> 244.352 | AJ7: =SUM(P7:S7) -> 250.177 | AK7: =SUM(S7:V7) -> 307.727 | AL7: =SUM(AL4:AL6) -> 451.5444 | AM7: =SUM(AM4:AM6) -> 624.55166 | AN7: =SUM(AN4:AN6) -> 839.11691 | AO7: =SUM(AO4:AO6) -> 1030.71 | AP7: =SUM(AP4:AP6) -> 1290.8145 | AQ7: =SUM(AQ4:AQ6) -> 1587.2264 | AR7: =SUM(AR4:AR6) -> 1913.4088 | AS7: =SUM(AS4:AS6) -> 2258.8497 | ... AU7: =SUM(AU4:AU6) -> 2964.47
B9: Civil Government Growth Y/y | S9: =S4/O4-1 -> -0.09801097 | T9: =T4/P4-1 -> -0.043832586 | U9: =U4/Q4-1 -> 0.014877102 | V9: =V4/R4-1 -> 0.12531065 | W9: =W4/S4-1 -> -0.0068181818 | X9: =X4/T4-1 -> 0.065262389 | AJ9: =AJ4/AI4-1 -> -0.024608065 | AK9: =AK4/AJ4-1 -> 0.025556918 | AL9: 0.06 | AM9: 0.07 | AN9: 0.08 | AO9: 0.07 | AP9: 0.06 | AQ9: 0.05 | AR9: 0.04 | AS9: 0.035 | AT9: 0.03 | AU9: 0.025
B10: Commercial Growth Y/y | S10: =S5/O5-1 -> 0.04390702 | T10: =T5/P5-1 -> 0.057546374 | U10: =U5/Q5-1 -> -0.078459042 | V10: =V5/R5-1 -> -0.057792294 | W10: =W5/S5-1 -> 0.24418953 | X10: =X5/T5-1 -> 0.16663345 | AJ10: =AJ5/AI5-1 -> 0.0099850491 | AK10: =AK5/AJ5-1 -> -0.02044233 | AL10: 0.24 | AM10: 0.21 | AN10: 0.18 | AO10: 0.16 | AP10: 0.14 | AQ10: 0.12 | AR10: 0.1 | AS10: 0.08 | AT10: 0.06 | AU10: 0.04
B11: Defense & Intelligence Growth Y/y | S11: =S6/O6-1 -> 0.23748903 | T11: =T6/P6-1 -> 0.41198073 | U11: =U6/Q6-1 -> 0.72961704 | V11: =V6/R6-1 -> 0.83902268 | W11: =W6/S6-1 -> 0.67506208 | X11: =X6/T6-1 -> 0.93263977 | AJ11: =AJ6/AI6-1 -> 0.060482796 | AK11: =AK6/AJ6-1 -> 0.46156965 | AL11: 0.7 | AM11: 0.5 | AN11: 0.42 | AO11: 0.26 | AP11: 0.29 | AQ11: 0.26 | AR11: 0.23 | AS11: 0.2 | AT11: 0.17 | AU11: 0.15
B12: Ttl Revenue Growth Y/y | S12: =S7/O7-1 -> 0.096376572 | T12: =T7/P7-1 -> 0.20123748 | U12: =U7/Q7-1 -> 0.32624947 | V12: =V7/R7-1 -> 0.41050135 | W12: =W7/S7-1 -> 0.42081038 | X12: =X7/T7-1 -> 0.58139155 | AJ12: =AJ7/AI7-1 -> 0.023838561 | AK12: =AK7/AJ7-1 -> 0.23003713 | AL12: =AL7/AK7-1 -> 0.46735386 | AM12: =AM7/AL7-1 -> 0.38314561 | AN12: =AN7/AM7-1 -> 0.34355085 | AO12: =AO7/AN7-1 -> 0.228327 | AP12: =AP7/AO7-1 -> 0.2523547 | AQ12: =AQ7/AP7-1 -> 0.2296317 | ... AU12: =AU7/AT7-1 -> 0.13668396
B14: Civil Government % of Ttl Revenues | O14: =O4/O7 -> 0.29862674 | P14: =P4/P7 -> 0.28119885 | Q14: =Q4/Q7 -> 0.30281069 | R14: =R4/R7 -> 0.29416447 | S14: =S4/S7 -> 0.24568022 | T14: =T4/T7 -> 0.22383016 | U14: =U4/U7 -> 0.23171782 | V14: =V4/V7 -> 0.23468706 | ... X14: =X4/X7 -> 0.15077724 | AI14: =AI4/AI7 -> 0.29419444 | AJ14: =AJ4/AJ7 -> 0.28027357 | AK14: =AK4/AK7 -> 0.23368115
B15: Commercial % of Ttl Revenues | O15: =O5/O7 -> 0.21139974 | P15: =P5/P7 -> 0.23296013 | Q15: =Q5/Q7 -> 0.23133549 | R15: =R5/R7 -> 0.24372096 | S15: =S5/S7 -> 0.20128273 | T15: =T5/T7 -> 0.20509361 | U15: =U5/U7 -> 0.16074286 | V15: =V5/V7 -> 0.16280436 | ... X15: =X5/X7 -> 0.15130286 | AI15: =AI5/AI7 -> 0.22993059 | AJ15: =AJ5/AJ7 -> 0.22681941 | AK15: =AK5/AK7 -> 0.18063088
B16: Defense & Intelligence % of Ttl Revenues | O16: =O6/O7 -> 0.48997353 | P16: =P6/P7 -> 0.48584103 | Q16: =Q6/Q7 -> 0.46585382 | R16: =R6/R7 -> 0.46211457 | S16: =S6/S7 -> 0.55303705 | T16: =T6/T7 -> 0.57107623 | U16: =U6/U7 -> 0.60753932 | V16: =V6/V7 -> 0.60250858 | ... X16: =X6/X7 -> 0.6979199 | AI16: =AI6/AI7 -> 0.47587497 | AJ16: =AJ6/AJ7 -> 0.49290702 | AK16: =AK6/AK7 -> 0.58568796
B18: North America | O18: 32.713 | P18: 30.797 | Q18: 27.038 | R18: =119.35-SUM(O18:Q18) -> 28.802 | S18: 29.533 | T18: 31.093 | U18: 35.148 | V18: =132.01-SUM(S18:U18) -> 36.236 | W18: 37.037 | X18: 39.015 | AI18: =SUM(O18:R18) -> 119.35 | AJ18: =SUM(P18:S18) -> 116.17 | AK18: =SUM(S18:V18) -> 132.01
B19: APAC | O19: 11.142 | P19: 10.298 | Q19: 10.334 | R19: =42.401-SUM(O19:Q19) -> 10.627 | S19: 15.307 | T19: 16.15 | U19: 14.324 | V19: =59.813-SUM(S19:U19) -> 14.032 | W19: 19.307 | X19: 19.094 | AI19: =SUM(O19:R19) -> 42.401 | AJ19: =SUM(P19:S19) -> 46.566 | AK19: =SUM(S19:V19) -> 59.813
B20: Euro, Mid-East & Africa | O20: 13.694 | P20: 17.226 | Q20: 20.011 | R20: =70.085-SUM(O20:Q20) -> 19.154 | S20: 18.849 | T20: 23.467 | U20: 27.613 | V20: =103.674-SUM(S20:U20) -> 33.745 | W20: 35.053 | X20: 55.2 | AI20: =SUM(O20:R20) -> 70.085 | AJ20: =SUM(P20:S20) -> 75.24 | AK20: =SUM(S20:V20) -> 103.674
B21: LATAM | O21: 2.891 | P21: 2.771 | Q21: 3.883 | R21: =12.516-SUM(O21:Q21) -> 2.971 | S21: 2.576 | T21: 2.676 | U21: 4.169 | V21: =12.23-SUM(S21:U21) -> 2.809 | W21: 2.753 | X21: 2.743 | AI21: =SUM(O21:R21) -> 12.516 | AJ21: =SUM(P21:S21) -> 12.201 | AK21: =SUM(S21:V21) -> 12.23
B22: Ttl Revenues | O22: =SUM(O18:O21) -> 60.44 | P22: =SUM(P18:P21) -> 61.092 | Q22: =SUM(Q18:Q21) -> 61.266 | R22: =SUM(R18:R21) -> 61.554 | S22: =SUM(S18:S21) -> 66.265 | T22: =SUM(T18:T21) -> 73.386 | U22: =SUM(U18:U21) -> 81.254 | V22: =SUM(V18:V21) -> 86.822 | ... X22: =SUM(X18:X21) -> 116.052 | AI22: =SUM(O22:R22) -> 244.352 | AJ22: =SUM(P22:S22) -> 250.177 | AK22: =SUM(S22:V22) -> 307.727
B24: North America Growth Y/y | S24: =S18/O18-1 -> -0.097209061 | T24: =T18/P18-1 -> 0.0096113258 | U24: =U18/Q18-1 -> 0.29994822 | V24: =V18/R18-1 -> 0.25810708 | W24: =W18/S18-1 -> 0.25408865 | X24: =X18/T18-1 -> 0.25478403 | AJ24: =AJ18/AI18-1 -> -0.026644323 | AK24: =AK18/AJ18-1 -> 0.1363519
B25: APAC Growth Y/y | S25: =S19/O19-1 -> 0.37381081 | T25: =T19/P19-1 -> 0.56826568 | U25: =U19/Q19-1 -> 0.38610412 | V25: =V19/R19-1 -> 0.32041028 | W25: =W19/S19-1 -> 0.26131835 | X25: =X19/T19-1 -> 0.18229102 | AJ25: =AJ19/AI19-1 -> 0.098228815 | AK25: =AK19/AJ19-1 -> 0.28447795
B26: Euro, Mid-East & Africa Growth Y/y | S26: =S20/O20-1 -> 0.37644224 | T26: =T20/P20-1 -> 0.36230117 | U26: =U20/Q20-1 -> 0.37989106 | V26: =V20/R20-1 -> 0.761773 | W26: =W20/S20-1 -> 0.85967425 | X26: =X20/T20-1 -> 1.3522393 | AJ26: =AJ20/AI20-1 -> 0.073553542 | AK26: =AK20/AJ20-1 -> 0.37791069
B27: LATAM Growth Y/y | S27: =S21/O21-1 -> -0.10895884 | T27: =T21/P21-1 -> -0.034283652 | U27: =U21/Q21-1 -> 0.073654391 | V27: =V21/R21-1 -> -0.054527095 | W27: =W21/S21-1 -> 0.06871118 | X27: =X21/T21-1 -> 0.025037369 | AJ27: =AJ21/AI21-1 -> -0.025167785 | AK27: =AK21/AJ21-1 -> 0.0023768544
B28: Ttl Revenue Growth Y/y | S28: =S22/O22-1 -> 0.096376572 | T28: =T22/P22-1 -> 0.20123748 | U28: =U22/Q22-1 -> 0.32624947 | V28: =V22/R22-1 -> 0.41050135 | W28: =W22/S22-1 -> 0.42081038 | X28: =X22/T22-1 -> 0.58139155 | AJ28: =AJ22/AI22-1 -> 0.023838561 | AK28: =AK22/AJ22-1 -> 0.23003713
B30: North America % of Ttl Revenues | O30: =O18/O22 -> 0.54124752 | P30: =P18/P22 -> 0.50410856 | Q30: =Q18/Q22 -> 0.44132145 | R30: =R18/R22 -> 0.46791435 | S30: =S18/S22 -> 0.44568022 | T30: =T18/T22 -> 0.42369117 | U30: =U18/U22 -> 0.43256947 | V30: =V18/V22 -> 0.41735966 | ... X30: =X18/X22 -> 0.3361855 | AI30: =AI18/AI22 -> 0.48843472 | AJ30: =AJ18/AJ22 -> 0.46435124 | AK30: =AK18/AK22 -> 0.42898413
B31: APAC % of Ttl Revenues | O31: =O19/O22 -> 0.18434811 | P31: =P19/P22 -> 0.16856544 | Q31: =Q19/Q22 -> 0.16867431 | R31: =R19/R22 -> 0.17264516 | S31: =S19/S22 -> 0.23099676 | T31: =T19/T22 -> 0.22006922 | U31: =U19/U22 -> 0.17628671 | V31: =V19/V22 -> 0.16161802 | ... X31: =X19/X22 -> 0.16452969 | AI31: =AI19/AI22 -> 0.17352426 | AJ31: =AJ19/AJ22 -> 0.18613222 | AK31: =AK19/AK22 -> 0.19437033
B32: Euro, Mid-East & Africa % of Ttl Revenues | O32: =O20/O22 -> 0.22657181 | P32: =P20/P22 -> 0.28196818 | Q32: =Q20/Q22 -> 0.32662488 | R32: =R20/R22 -> 0.31117393 | S32: =S20/S22 -> 0.2844488 | T32: =T20/T22 -> 0.31977489 | U32: =U20/U22 -> 0.33983558 | V32: =V20/V22 -> 0.38866877 | ... X32: =X20/X22 -> 0.47564885 | AI32: =AI20/AI22 -> 0.28681983 | AJ32: =AJ20/AJ22 -> 0.30074707 | AK32: =AK20/AK22 -> 0.33690251
B33: LATAM % of Ttl Revenues | O33: =O21/O22 -> 0.047832561 | P33: =P21/P22 -> 0.045357821 | Q33: =Q21/Q22 -> 0.063379362 | R33: =R21/R22 -> 0.048266563 | S33: =S21/S22 -> 0.038874217 | T33: =T21/T22 -> 0.036464721 | U33: =U21/U22 -> 0.051308243 | V33: =V21/V22 -> 0.032353551 | ... X33: =X21/X22 -> 0.023635956 | AI33: =AI21/AI22 -> 0.051221189 | AJ33: =AJ21/AJ22 -> 0.048769471 | AK33: =AK21/AK22 -> 0.039743019
B35: Sales Backlog | O35: 242.392 | P35: 213.5 | Q35: 232.14 | R35: 503.749 | S35: 527.047 | T35: 736.077 | U35: 734.471 | V35: 900.427 | W35: 906.055 | X35: 814.863 | AI35: =AVERAGE(O35:R35) -> 297.94525 | AJ35: =AVERAGE(P35:S35) -> 369.109 | AK35: =AVERAGE(S35:V35) -> 724.5055
B37: Revenues | C37: 32 | D37: 30.4 | E37: 31.7 | F37: 37.1 | G37: 40.1 | H37: 48.4 | I37: 49.7 | J37: 53 | K37: 52.7 | L37: 53.8 | M37: 55.4 | N37: 58.9 | O37: 60.4 | P37: 61.1 | Q37: 61.3 | R37: 61.6 | S37: 66.3 | T37: 73.4 | U37: 81.3 | V37: 86.8 | W37: 94.2 | X37: 116.052 | AF37: =SUM(C37:F37) -> 131.2 | AG37: =SUM(G37:J37) -> 191.2 | AH37: =SUM(K37:N37) -> 220.8 | AI37: =SUM(O37:R37) -> 244.4 | AJ37: =SUM(P37:S37) -> 250.3 | AK37: =SUM(S37:V37) -> 307.8 | AL37: =AL7 -> 451.5444 | AM37: =AM7 -> 624.55166 | AN37: =AN7 -> 839.11691 | AO37: =AO7 -> 1030.71 | AP37: =AP7 -> 1290.8145 | AQ37: =AQ7 -> 1587.2264 | AR37: =AR7 -> 1913.4088 | AS37: =AS7 -> 2258.8497 | ... AU37: =AU7 -> 2964.47
B38: COGS | C38: 19.126 | D38: 19.82 | E38: 20.811 | F38: =82.987-SUM(C38:E38) -> 23.23 | G38: 23.628 | H38: 24.977 | I38: 24.728 | J38: =97.248-SUM(G38:I38) -> 23.915 | K38: 24.556 | L38: 27.469 | M38: 29.35 | N38: =107.746-SUM(K38:M38) -> 26.371 | O38: 28.757 | P38: 28.782 | Q38: 23.749 | R38: =104.627-SUM(O38:Q38) -> 23.339 | S38: 29.662 | T38: 31.118 | U38: 34.67 | V38: =135.242-SUM(S38:U38) -> 39.792 | W38: 43.749 | X38: 50.42 | AF38: =SUM(C38:F38) -> 82.987 | AG38: =SUM(G38:J38) -> 97.248 | AH38: =SUM(K38:N38) -> 107.746 | AI38: =SUM(O38:R38) -> 104.627 | AJ38: =SUM(P38:S38) -> 105.532 | AK38: =SUM(S38:V38) -> 135.242 | AL38: =AL37*(1-AL54) -> 203.19498 | AM38: =AM37*(1-AM54) -> 271.67997 | AN38: =AN37*(1-AN54) -> 356.62468 | AO38: =AO37*(1-AO54) -> 422.59108 | AP38: =AP37*(1-AP54) -> 516.32578 | AQ38: =AQ37*(1-AQ54) -> 619.01828 | AR38: =AR37*(1-AR54) -> 727.09535 | AS38: =AS37*(1-AS54) -> 835.77437 | ... AU38: =AU37*(1-AU54) -> 1037.5645
B39: GP | C39: =C37-C38 -> 12.874 | D39: =D37-D38 -> 10.58 | E39: =E37-E38 -> 10.889 | F39: =F37-F38 -> 13.87 | G39: =G37-G38 -> 16.472 | H39: =H37-H38 -> 23.423 | I39: =I37-I38 -> 24.972 | J39: =J37-J38 -> 29.085 | ... X39: =X37-X38 -> 65.632 | AF39: =SUM(C39:F39) -> 48.213 | AG39: =SUM(G39:J39) -> 93.952 | AH39: =SUM(K39:N39) -> 113.054 | AI39: =SUM(O39:R39) -> 139.773 | AJ39: =SUM(P39:S39) -> 144.768 | AK39: =SUM(S39:V39) -> 172.558 | AL39: =AL37*AL54 -> 248.34942 | AM39: =AM37*AM54 -> 352.87169 | AN39: =AN37*AN54 -> 482.49222 | AO39: =AO37*AO54 -> 608.11887 | AP39: =AP37*AP54 -> 774.48867 | AQ39: =AQ37*AQ54 -> 968.20808 | AR39: =AR37*AR54 -> 1186.3135 | AS39: =AS37*AS54 -> 1423.0753 | ... AU39: =AU37*AU54 -> 1926.9055
B40: R&D | C40: 12.13 | D40: 12.432 | E40: 14.959 | F40: =66.684-SUM(C40:E40) -> 27.163 | G40: 24.75 | H40: 26.737 | I40: 27.598 | J40: =110.916-SUM(G40:I40) -> 31.831 | K40: 28.186 | L40: 26.741 | M40: 33.002 | N40: =116.339-SUM(K40:M40) -> 28.41 | O40: 25.589 | P40: 27.25 | Q40: 25.216 | R40: =101.006-SUM(O40:Q40) -> 22.951 | S40: 23.074 | T40: 24.155 | U40: 27.327 | V40: =106.749-SUM(S40:U40) -> 32.193 | W40: 33.42 | X40: 35.156 | AF40: =SUM(C40:F40) -> 66.684 | AG40: =SUM(G40:J40) -> 110.916 | AH40: =SUM(K40:N40) -> 116.339 | AI40: =SUM(O40:R40) -> 101.006 | AJ40: =SUM(P40:S40) -> 98.491 | AK40: =SUM(S40:V40) -> 106.749 | AL40: =AL37*AL55 -> 158.04054 | AM40: =AM37*AM55 -> 199.85653 | AN40: =AN37*AN55 -> 243.3439 | AO40: =AO37*AO55 -> 263.86175 | AP40: =AP37*AP55 -> 304.89037 | AQ40: =AQ37*AQ55 -> 353.95148 | AR40: =AR37*AR55 -> 401.81585 | AS40: =AS37*AS55 -> 451.76993 | ... AU40: =AU37*AU55 -> 533.60459
B41: Sales and Marketing | C41: 10.653 | D41: 10.597 | E41: 12.441 | F41: =52.917-SUM(C41:E41) -> 19.226 | G41: 18.855 | H41: 19.483 | I41: 19.383 | J41: =78.02-SUM(G41:I41) -> 20.299 | K41: 23.125 | L41: 22.31 | M41: 20.774 | N41: =86.304-SUM(K41:M41) -> 20.095 | O41: 21.485 | P41: 23.733 | Q41: 16.795 | R41: =77.694-SUM(O41:Q41) -> 15.681 | S41: 16.314 | T41: 17.574 | U41: 18.783 | V41: =72.676-SUM(S41:U41) -> 20.005 | W41: 22.782 | X41: 21.498 | AF41: =SUM(C41:F41) -> 52.917 | AG41: =SUM(G41:J41) -> 78.02 | AH41: =SUM(K41:N41) -> 86.304 | AI41: =SUM(O41:R41) -> 77.694 | AJ41: =SUM(P41:S41) -> 72.523 | AK41: =SUM(S41:V41) -> 72.676 | AL41: =AL37*AL56 -> 108.37066 | AM41: =AM37*AM56 -> 143.64688 | AN41: =AN37*AN56 -> 184.60572 | AO41: =AO37*AO56 -> 216.44909 | AP41: =AP37*AP56 -> 264.61696 | AQ41: =AQ37*AQ56 -> 317.44527 | AR41: =AR37*AR56 -> 373.11472 | AS41: =AS37*AS56 -> 429.18143 | ... AU41: =AU37*AU56 -> 533.60459
B42: General and Admin | C42: 8.315 | D42: 11.824 | E42: 11.8 | F42: =56.672-SUM(C42:E42) -> 24.733 | G42: 20.608 | H42: 19.893 | I42: 20.627 | J42: =80.747-SUM(G42:I42) -> 19.619 | K42: 21.528 | L42: 20.521 | M42: 20.112 | N42: =80.055-SUM(K42:M42) -> 17.894 | O42: 19.18 | P42: 20.904 | Q42: 18.114 | R42: =77.147-SUM(O42:Q42) -> 18.949 | S42: 19.986 | T42: 18.499 | U42: 18.814 | V42: =88.133-SUM(S42:U42) -> 30.834 | W42: 29.087 | X42: 22.487 | AF42: =SUM(C42:F42) -> 56.672 | AG42: =SUM(G42:J42) -> 80.747 | AH42: =SUM(K42:N42) -> 80.055 | AI42: =SUM(O42:R42) -> 77.147 | AJ42: =SUM(P42:S42) -> 77.953 | AK42: =SUM(S42:V42) -> 88.133 | AL42: =AL37*AL57 -> 137.72104 | AM42: =AM37*AM57 -> 177.99722 | AN42: =AN37*AN57 -> 230.75715 | AO42: =AO37*AO57 -> 273.13814 | AP42: =AP37*AP57 -> 329.15769 | AQ42: =AQ37*AQ57 -> 388.87046 | AR42: =AR37*AR57 -> 449.65107 | AS42: =AS37*AS57 -> 646.78102 | ... AU42: =AU37*AU57 -> 848.82271
B43: Operating Income | C43: =C39-SUM(C40:C42) -> -18.224 | D43: =D39-SUM(D40:D42) -> -24.273 | E43: =E39-SUM(E40:E42) -> -28.311 | F43: =F39-SUM(F40:F42) -> -57.252 | G43: =G39-SUM(G40:G42) -> -47.741 | H43: =H39-SUM(H40:H42) -> -42.69 | I43: =I39-SUM(I40:I42) -> -42.636 | J43: =J39-SUM(J40:J42) -> -42.664 | ... X43: =X39-SUM(X40:X42) -> -13.509 | AF43: =SUM(C43:F43) -> -128.06 | AG43: =SUM(G43:J43) -> -175.731 | AH43: =SUM(K43:N43) -> -169.644 | AI43: =SUM(O43:R43) -> -116.074 | AJ43: =SUM(P43:S43) -> -104.199 | AK43: =SUM(S43:V43) -> -95 | AL43: =AL39-SUM(AL40:AL42) -> -155.78282 | AM43: =AM39-SUM(AM40:AM42) -> -168.62895 | AN43: =AN39-SUM(AN40:AN42) -> -176.21455 | AO43: =AO39-SUM(AO40:AO42) -> -145.3301 | AP43: =AP39-SUM(AP40:AP42) -> -124.17635 | AQ43: =AQ39-SUM(AQ40:AQ42) -> -92.059129 | AR43: =AR39-SUM(AR40:AR42) -> -38.268176 | AS43: =AS39-SUM(AS40:AS42) -> -104.6571 | ... AU43: =AU39-SUM(AU40:AU42) -> 10.873576
B44: Interest Income | C44: 0 | D44: 0 | E44: 0.008 | F44: =0.021-SUM(C44:E44) -> 0.013 | G44: 0.112 | H44: 1.311 | I44: 2.853 | J44: =7.67-SUM(G44:I44) -> 3.394 | K44: 4.506 | L44: 3.802 | M44: 3.445 | N44: =15.414-SUM(K44:M44) -> 3.661 | O44: 3.107 | P44: 2.771 | Q44: 2.414 | R44: =10.257-SUM(O44:Q44) -> 1.965 | S44: 1.884 | T44: 2.172 | U44: 4.414 | V44: =14.329-SUM(S44:U44) -> 5.859 | W44: 5.153 | X44: 6.433 | AF44: =SUM(C44:F44) -> 0.021 | AG44: =SUM(G44:J44) -> 7.67 | AH44: =SUM(K44:N44) -> 15.414 | AI44: =SUM(O44:R44) -> 10.257 | AJ44: =SUM(P44:S44) -> 9.034 | AK44: =SUM(S44:V44) -> 14.329 | AL44: =SUM(AK62:AK64)*($BE$62) -> 200.22875 | AM44: =SUM(AL62:AL64)*($BE$62) -> 213.67345 | AN44: =SUM(AM62:AM63)*($BE$62) -> 226.92127 | AO44: =SUM(AN62:AN63)*($BE$62) -> 241.77274 | AP44: =SUM(AO62:AO63)*($BE$62) -> 270.33971 | AQ44: =SUM(AP62:AP63)*($BE$62) -> 313.98162 | AR44: =SUM(AQ62:AQ63)*($BE$62) -> 380.59133 | AS44: =SUM(AR62:AR63)*($BE$62) -> 483.7008 | AT44: =SUM(AS62:AS63)*($BE$62) -> 597.94446 | AU44: =SUM(AT62:AT63)*($BE$62) -> 761.68166
B45: Interest Expense | C45: -2.527 | D45: -2.611 | E45: -2.612 | F45: =-8.772-SUM(C45:E45) -> -1.022 | G45: 0 | H45: 0 | I45: 0 | J45: =0-SUM(G45:I45) -> 0 | K45: 0 | L45: 0 | M45: 0 | N45: =0-SUM(K45:M45) -> 0 | O45: 0 | P45: 0 | Q45: -0.277 | R45: =-0.832-SUM(O45:Q45) -> -0.555 | S45: -0.499 | T45: 0 | U45: -1.02 | V45: =-3.436-SUM(S45:U45) -> -1.917 | W45: -1.446 | X45: -1.439 | AF45: =SUM(C45:F45) -> -8.772 | AG45: =SUM(G45:J45) -> 0 | AH45: =SUM(K45:N45) -> 0 | AI45: =SUM(O45:R45) -> -0.832 | AJ45: =SUM(P45:S45) -> -1.331 | AK45: =SUM(S45:V45) -> -3.436 | AL45: =-AK86*($AZ$79) -> -2.23442 | AM45: =-AL86*($AZ$79) -> -2.2232479 | AN45: =-AM86*($AZ$79) -> -2.2121317 | AO45: =-AN86*($AZ$79) -> -2.201071 | AP45: =-AO86*($AZ$79) -> -2.1900656 | AQ45: =-AP86*($AZ$79) -> -2.1791153 | AR45: =-AQ86*($AZ$79) -> -2.1682197 | AS45: =-AR86*($AZ$79) -> -2.1573786 | ... AU45: =-AT86*($AZ$79) -> -2.1358588
B46: Change in FV of Warrant Liabilities | C46: -8.026 | D46: 6.769 | E46: -10.172 | F46: =5.726-SUM(C46:E46) -> 17.155 | G46: 3.276 | H46: 2.112 | I46: -0.019 | J46: =6.554-SUM(G46:I46) -> 1.185 | K46: 5.945 | L46: 1.226 | M46: 6.833 | N46: =13.709-SUM(K46:M46) -> -0.295 | O46: 1.53 | P46: -0.602 | Q46: 0.198 | R46: =-15.116-SUM(O46:Q46) -> -16.242 | S46: 10.387 | T46: -5.679 | U46: -43.473 | V46: =-161.4-SUM(S46:U46) -> -122.635 | W46: -106.474 | X46: 0 | AF46: =SUM(C46:F46) -> 5.726 | AG46: =SUM(G46:J46) -> 6.554 | AH46: =SUM(K46:N46) -> 13.709 | AI46: =SUM(O46:R46) -> -15.116 | AJ46: =SUM(P46:S46) -> -6.259 | AK46: =SUM(S46:V46) -> -161.4 | AL46: 0 | AM46: 0 | AN46: 0 | AO46: 0 | AP46: 0 | AQ46: 0 | AR46: 0 | AS46: 0 | AT46: 0 | AU46: 0
B47: Other Income | C47: -0.177 | D47: -0.084 | E47: -0.06 | F47: =-2.248-1.69-SUM(C47:E47) -> -3.617 | G47: 0.28 | H47: -0.158 | I47: 0.001 | J47: =0.33-SUM(G47:I47) -> 0.207 | K47: 0.104 | L47: 0.859 | M47: -0.069 | N47: =0.931-SUM(K47:M47) -> 0.037 | O47: 1.083 | P47: -0.363 | Q47: 0.217 | R47: =1.077-SUM(O47:Q47) -> 0.14 | S47: -0.701 | T47: -0.628 | U47: 0.018 | V47: =3.375-SUM(S47:U47) -> 4.686 | W47: -0.206 | X47: -0.105 | AF47: =SUM(C47:F47) -> -3.938 | AG47: =SUM(G47:J47) -> 0.33 | AH47: =SUM(K47:N47) -> 0.931 | AI47: =SUM(O47:R47) -> 1.077 | AJ47: =SUM(P47:S47) -> -0.707 | AK47: =SUM(S47:V47) -> 3.375 | AL47: 0 | AM47: 0 | AN47: 0 | AO47: 0 | AP47: 0 | AQ47: 0 | AR47: 0 | AS47: 0 | AT47: 0 | AU47: 0
B48: Pretax Income | C48: =C43+SUM(C44:C47) -> -28.954 | D48: =D43+SUM(D44:D47) -> -20.199 | E48: =E43+SUM(E44:E47) -> -41.147 | F48: =F43+SUM(F44:F47) -> -44.723 | G48: =G43+SUM(G44:G47) -> -44.073 | H48: =H43+SUM(H44:H47) -> -39.425 | I48: =I43+SUM(I44:I47) -> -39.801 | J48: =J43+SUM(J44:J47) -> -37.878 | ... X48: =X43+SUM(X44:X47) -> -8.62 | AF48: =SUM(C48:F48) -> -135.023 | AG48: =SUM(G48:J48) -> -161.177 | AH48: =SUM(K48:N48) -> -139.59 | AI48: =SUM(O48:R48) -> -120.688 | AJ48: =SUM(P48:S48) -> -103.462 | AK48: =SUM(S48:V48) -> -242.132 | AL48: =AL43+SUM(AL44:AL47) -> 42.211512 | AM48: =AM43+SUM(AM44:AM47) -> 42.821252 | AN48: =AN43+SUM(AN44:AN47) -> 48.49459 | AO48: =AO43+SUM(AO44:AO47) -> 94.241565 | AP48: =AP43+SUM(AP44:AP47) -> 143.9733 | AQ48: =AQ43+SUM(AQ44:AQ47) -> 219.74338 | AR48: =AR43+SUM(AR44:AR47) -> 340.15494 | AS48: =AS43+SUM(AS44:AS47) -> 376.88632 | ... AU48: =AU43+SUM(AU44:AU47) -> 770.41938
B49: Taxes | C49: 0.258 | D49: 0.17 | E49: 0.394 | F49: =2.11-SUM(C49:E49) -> 1.288 | G49: 0.314 | H49: 0.154 | I49: 0.439 | J49: =0.847-SUM(G49:I49) -> -0.06 | K49: 0.307 | L49: 0.582 | M49: 0.355 | N49: =0.815-SUM(K49:M49) -> -0.429 | O49: 0.442 | P49: 0.897 | Q49: 0.025 | R49: =2.46-SUM(O49:Q49) -> 1.096 | S49: 0.928 | T49: 0.497 | U49: 0.781 | V49: =4.655-SUM(S49:U49) -> 2.449 | W49: 1.011 | X49: 0.733 | AF49: =SUM(C49:F49) -> 2.11 | AG49: =SUM(G49:J49) -> 0.847 | AH49: =SUM(K49:N49) -> 0.815 | AI49: =SUM(O49:R49) -> 2.46 | AJ49: =SUM(P49:S49) -> 2.946 | AK49: =SUM(S49:V49) -> 4.655 | AL49: =AL48*AL59 -> -0.81151846 | AM49: =AM48*AM59 -> 0.42821252 | AN49: =AN48*AN59 -> 0.9698918 | AO49: =AO48*AO59 -> 2.827247 | AP49: =AP48*AP59 -> 4.319199 | AQ49: =AQ48*AQ59 -> 6.5923013 | AR49: =AR48*AR59 -> 10.204648 | AS49: =AS48*AS59 -> 11.30659 | ... AU49: =AU48*AU59 -> 23.112581
B50: Net Income | C50: =C48-C49 -> -29.212 | D50: =D48-D49 -> -20.369 | E50: =E48-E49 -> -41.541 | F50: =F48-F49 -> -46.011 | G50: =G48-G49 -> -44.387 | H50: =H48-H49 -> -39.579 | I50: =I48-I49 -> -40.24 | J50: =J48-J49 -> -37.818 | ... X50: =X48-X49 -> -9.353 | AF50: =SUM(C50:F50) -> -137.133 | AG50: =SUM(G50:J50) -> -162.024 | AH50: =SUM(K50:N50) -> -140.405 | AI50: =SUM(O50:R50) -> -123.148 | AJ50: =SUM(P50:S50) -> -106.408 | AK50: =SUM(S50:V50) -> -246.787 | AL50: =AL48-AL49 -> 43.02303 | AM50: =AM48-AM49 -> 42.393039 | AN50: =AN48-AN49 -> 47.524698 | AO50: =AO48-AO49 -> 91.414318 | AP50: =AP48-AP49 -> 139.6541 | AQ50: =AQ48-AQ49 -> 213.15107 | AR50: =AR48-AR49 -> 329.95029 | AS50: =AS48-AS49 -> 365.57973 | ... AU50: =AU48-AU49 -> 747.3068 | AV50: =AU50*(1+$BE$63) -> 765.61581 | AW50: =AV50*(1+$BE$63) -> 784.3734 | AX50: =AW50*(1+$BE$63) -> 803.59055 | AY50: =AX50*(1+$BE$63) -> 823.27852 | AZ50: =AY50*(1+$BE$63) -> 843.44884 | BA50: =AZ50*(1+$BE$63) -> 864.11334 | BB50: =BA50*(1+$BE$63) -> 885.28412 | BC50: =BB50*(1+$BE$63) -> 906.97358 | ... CS50: =CR50*(1+$BE$63) -> 2506.6695
B51: SC | C51: 45.722 | D51: 46.2 | E51: 47.137 | F51: 79.61 | G51: 264.088 | H51: 266.212 | I51: 267.947 | J51: 267.126 | K51: 272.347 | L51: 275.053 | M51: 284.197 | N51: 267.126 | O51: 288.268 | P51: 290.364 | Q51: 293.338 | R51: 292.124 | S51: 300.267 | T51: 304.129 | U51: 309.248 | V51: 307.799 | W51: 345.524 | X51: 359.59 | AF51: =AVERAGE(C51:F51) -> 54.66725 | AG51: =AVERAGE(G51:J51) -> 266.34325 | AH51: =AVERAGE(K51:N51) -> 274.68075 | AI51: =AVERAGE(O51:R51) -> 291.0235 | AJ51: =AVERAGE(P51:S51) -> 294.02325 | AK51: =AVERAGE(S51:V51) -> 305.36075
B52: EPS | C52: =C50/C51 -> -0.63890468 | D52: =D50/D51 -> -0.44088745 | E52: =E50/E51 -> -0.88128222 | F52: =F50/F51 -> -0.57795503 | G52: =G50/G51 -> -0.16807655 | H52: =H50/H51 -> -0.14867474 | I52: =I50/I51 -> -0.15017895 | J52: =J50/J51 -> -0.14157364 | ... X52: =X50/X51 -> -0.026010178 | AF52: =AF50/AF51 -> -2.5085037 | AG52: =AG50/AG51 -> -0.60832779 | AH52: =AH50/AH51 -> -0.51115704 | AI52: =AI50/AI51 -> -0.42315483 | AJ52: =AJ50/AJ51 -> -0.36190335 | AK52: =AK50/AK51 -> -0.8081818
B54: Gross Profit Margin | C54: =C39/C37 -> 0.4023125 | D54: =D39/D37 -> 0.34802632 | E54: =E39/E37 -> 0.34350158 | F54: =F39/F37 -> 0.37385445 | G54: =G39/G37 -> 0.41077307 | H54: =H39/H37 -> 0.48394628 | I54: =I39/I37 -> 0.50245473 | J54: =J39/J37 -> 0.54877358 | ... X54: =X39/X37 -> 0.56553959 | AF54: =AF39/AF37 -> 0.36747713 | AG54: =AG39/AG37 -> 0.49138075 | AH54: =AH39/AH37 -> 0.51201993 | AI54: =AI39/AI37 -> 0.57190262 | AJ54: =AJ39/AJ37 -> 0.57837795 | AK54: =AK39/AK37 -> 0.56061728 | AL54: 0.55 | AM54: 0.565 | AN54: 0.575 | AO54: 0.59 | AP54: 0.6 | AQ54: 0.61 | AR54: 0.62 | AS54: 0.63 | AT54: 0.64 | AU54: 0.65
B55: R&D as % of Revenue | C55: =C40/C37 -> 0.3790625 | D55: =D40/D37 -> 0.40894737 | E55: =E40/E37 -> 0.47189274 | F55: =F40/F37 -> 0.73215633 | G55: =G40/G37 -> 0.61720698 | H55: =H40/H37 -> 0.55241736 | I55: =I40/I37 -> 0.55529175 | J55: =J40/J37 -> 0.60058491 | ... X55: =X40/X37 -> 0.30293317 | AF55: =AF40/AF37 -> 0.5082622 | AG55: =AG40/AG37 -> 0.5801046 | AH55: =AH40/AH37 -> 0.52689764 | AI55: =AI40/AI37 -> 0.41328151 | AJ55: =AJ40/AJ37 -> 0.39349181 | AK55: =AK40/AK37 -> 0.34681287 | AL55: 0.35 | AM55: 0.32 | AN55: 0.29 | AO55: 0.256 | AP55: 0.2362 | AQ55: 0.223 | AR55: 0.21 | AS55: 0.2 | AT55: 0.19 | AU55: 0.18
B56: Sales and Marketing as % of Revenue | C56: =C41/C37 -> 0.33290625 | D56: =D41/D37 -> 0.34858553 | E56: =E41/E37 -> 0.39246057 | F56: =F41/F37 -> 0.51822102 | G56: =G41/G37 -> 0.4701995 | H56: =H41/H37 -> 0.40254132 | I56: =I41/I37 -> 0.39 | J56: =J41/J37 -> 0.383 | ... X56: =X41/X37 -> 0.18524455 | AF56: =AF41/AF37 -> 0.40333079 | AG56: =AG41/AG37 -> 0.40805439 | AH56: =AH41/AH37 -> 0.39086957 | AI56: =AI41/AI37 -> 0.31789689 | AJ56: =AJ41/AJ37 -> 0.28974431 | AK56: =AK41/AK37 -> 0.23611436 | AL56: 0.24 | AM56: 0.23 | AN56: 0.22 | AO56: 0.21 | AP56: 0.205 | AQ56: 0.2 | AR56: 0.195 | AS56: 0.19 | AT56: 0.185 | AU56: 0.18
B57: General and Admin as % of Revenue | C57: =C42/C37 -> 0.25984375 | D57: =D42/D37 -> 0.38894737 | E57: =E42/E37 -> 0.37223975 | F57: =F42/F37 -> 0.66665768 | G57: =G42/G37 -> 0.51391521 | H57: =H42/H37 -> 0.4110124 | I57: =I42/I37 -> 0.41503018 | J57: =J42/J37 -> 0.37016981 | ... X57: =X42/X37 -> 0.19376659 | AF57: =AF42/AF37 -> 0.43195122 | AG57: =AG42/AG37 -> 0.42231695 | AH57: =AH42/AH37 -> 0.36256793 | AI57: =AI42/AI37 -> 0.31565876 | AJ57: =AJ42/AJ37 -> 0.31143827 | AK57: =AK42/AK37 -> 0.28633203 | AL57: 0.305 | AM57: 0.285 | AN57: 0.275 | AO57: 0.265 | AP57: 0.255 | AQ57: 0.245 | AR57: 0.235 | AS57: 0.28633203 | AT57: 0.28633203 | AU57: 0.28633203
B58: Operating Profit Margin | C58: =C43/C37 -> -0.5695 | D58: =D43/D37 -> -0.79845395 | E58: =E43/E37 -> -0.89309148 | F58: =F43/F37 -> -1.5431806 | G58: =G43/G37 -> -1.1905486 | H58: =H43/H37 -> -0.88202479 | I58: =I43/I37 -> -0.8578672 | J58: =J43/J37 -> -0.80498113 | ... X58: =X43/X37 -> -0.11640472 | AF58: =AF43/AF37 -> -0.97606707 | AG58: =AG43/AG37 -> -0.91909519 | AH58: =AH43/AH37 -> -0.76831522 | AI58: =AI43/AI37 -> -0.47493453 | AJ58: =AJ43/AJ37 -> -0.41629644 | AK58: =AK43/AK37 -> -0.30864198 | AL58: =AL43/AL37 -> -0.345 | AM58: =AM43/AM37 -> -0.27 | ... AU58: =AU43/AU37 -> 0.0036679662
B59: Effective Tax Rate | C59: =C49/C48 -> -0.0089106859 | D59: =D49/D48 -> -0.0084162582 | E59: =E49/E48 -> -0.0095754247 | F59: =F49/F48 -> -0.028799499 | G59: =G49/G48 -> -0.0071245434 | H59: =H49/H48 -> -0.0039061509 | I59: =I49/I48 -> -0.011029874 | J59: =J49/J48 -> 0.0015840329 | ... X59: =X49/X48 -> -0.085034803 | AF59: =AF49/AF48 -> -0.015626967 | AG59: =AG49/AG48 -> -0.0052550922 | AH59: =AH49/AH48 -> -0.0058385271 | AI59: =AI49/AI48 -> -0.020383137 | AJ59: =AJ49/AJ48 -> -0.028474222 | AK59: =AK49/AK48 -> -0.019225051 | AL59: -0.019225051 | AM59: 0.01 | AN59: 0.02 | AO59: 0.03 | AP59: 0.03 | AQ59: 0.03 | AR59: 0.03 | AS59: 0.03 | AT59: 0.03 | AU59: 0.03
B60: Net Profit Margin | C60: =C50/C37 -> -0.912875 | D60: =D50/D37 -> -0.67003289 | E60: =E50/E37 -> -1.3104416 | F60: =F50/F37 -> -1.2401887 | G60: =G50/G37 -> -1.1069077 | H60: =H50/H37 -> -0.81774793 | I60: =I50/I37 -> -0.80965795 | J60: =J50/J37 -> -0.71354717 | ... X60: =X50/X37 -> -0.080593182 | AF60: =AF50/AF37 -> -1.045221 | AG60: =AG50/AG37 -> -0.84740586 | AH60: =AH50/AH37 -> -0.63589221 | AI60: =AI50/AI37 -> -0.50387889 | AJ60: =AJ50/AJ37 -> -0.42512185 | AK60: =AK50/AK37 -> -0.80177713 | AL60: =AL50/AL37 -> 0.095279734 | AM60: =AM50/AM37 -> 0.067877555 | ... AU60: =AU50/AU37 -> 0.25208783
B62: Cash & CEs | N62: 83.866 | O62: 107.367 | P62: 148.288 | Q62: 138.969 | R62: 118.048 | S62: 133.471 | T62: 181.087 | U62: 443.349 | V62: 229.441 | W62: 368.09 | X62: 415.13 | AI62: =N62 -> 83.866 | AJ62: =R62 -> 118.048 | AK62: =V62 -> 229.441 | AL62: =SUM(AK62:AK64)+AL50 -> 683.75503 | AM62: =AL62+AM50 -> 726.14807 | AN62: =AM62+AN50 -> 773.67277 | AO62: =AN62+AO50 -> 865.08709 | AP62: =AO62+AP50 -> 1004.7412 | AQ62: =AP62+AQ50 -> 1217.8923 | AR62: =AQ62+AR50 -> 1547.8425 | AS62: =AR62+AS50 -> 1913.4223 | AT62: =AS62+AT50 -> 2437.3813 | AU62: =AT62+AU50 -> 3184.6881 | AW62: Invested Capital | AZ62: Avg. (2024-2025) | BB62: Projected ROIC: | BD62: ROIC | BE62: 0.3125
B63: Restricted Cash & CEs | N63: 8.36 | O63: 8.8 | P63: 8.802 | Q63: 6.525 | R63: 6.598 | S63: 6.607 | T63: 6.316 | U63: 0.906 | V63: 0.642 | W63: 0.896 | X63: 1.891 | AI63: =N63 -> 8.36 | AJ63: =R63 -> 6.598 | AK63: =V63 -> 0.642 | AW63: 2025 | AX63: 2026 | AZ63: 2025-2026 | BB63: 2025 | BD63: Terminal | BE63: 0.0245
B64: ST Investments | N64: 215.041 | O64: 168.218 | P64: 101.102 | Q64: 103.255 | R64: 104.027 | S64: 92.624 | T64: 90.45 | U64: 233.975 | V64: 410.649 | W64: 362.745 | X64: 450.288 | AI64: =N64 -> 215.041 | AJ64: =R64 -> 104.027 | AK64: =V64 -> 410.649 | AW64: =SUM(AJ62:AJ67)-AJ71-AJ77+AJ68+AJ70 -> 530.267 | AX64: =SUM(AK62:AK67)-AK71-AK77+AK68+AK70 -> 1032.142 | AZ64: =AVERAGE(AW64:AX64) -> 781.2045 | BB64: =AVERAGE(AL43)*(1-AL59) -> -158.77775 | BD64: RFR (10-year yield) | BE64: 0.0447
B65: A/R | N65: 43.32 | O65: 38.527 | P65: 43.926 | Q65: 38.853 | R65: 55.833 | S65: 74.663 | T65: 51.633 | U65: 46.332 | V65: 83.528 | W65: 61.605 | X65: 59.87 | AI65: =N65 -> 43.32 | AJ65: =R65 -> 55.833 | AK65: =V65 -> 83.528 | BB65: =BB64/AZ64 -> -0.20324736 | BD65: ERP (Avg. market return - (less) RFR) | BE65: =4.75%-BE64 -> 0.0028
B66: Inventories | N66: 0 | O66: 0 | P66: 0 | Q66: 0 | R66: 0 | S66: 0 | T66: 0 | U66: 0 | V66: 6.118 | W66: 9.343 | X66: 8.852 | AI66: =N66 -> 0 | AJ66: =R66 -> 0 | AK66: =V66 -> 6.118 | AW66: Capital Structure | BD66: Equity β (1-year avg.) | BE66: =AZ74 -> 2.9471353
B67: ST Prepaid Expenses | N67: 19.564 | O67: 23.044 | P67: 24.628 | Q67: 13.992 | R67: 17.719 | S67: 17.447 | T67: 25.977 | U67: 29.581 | V67: 44.984 | W67: 46.299 | X67: 62.759 | AI67: =N67 -> 19.564 | AJ67: =R67 -> 17.719 | AK67: =V67 -> 44.984 | AW67: Mkt Cap | AZ67: =Main!C5 -> 6267.7234 | BD67: Discount (Cost of Equity) | BE67: =+BE64+(BE65*BE66) -> 0.052951979
B68: PP&E, net | N68: 113.429 | O68: 111.338 | P68: 113.227 | Q68: 116.92 | R68: 121.749 | S68: 122.473 | T68: 131.288 | U68: 145.084 | V68: 150.573 | W68: 159.145 | X68: 176.09 | AI68: =N68 -> 113.429 | AJ68: =R68 -> 121.749 | AK68: =V68 -> 150.573 | AW68: Debt to Ttl Mkt Cap | AZ68: =Main!C7/(Main!C7+AZ67) -> 0.066744556
B69: LT Capitalized Software | N69: 14.973 | O69: 16.066 | P69: 17.322 | Q69: 18.259 | R69: 18.974 | S69: 19.783 | T69: 20.567 | U69: 21.062 | V69: 21.475 | W69: 20.98 | X69: 22.051 | AI69: =N69 -> 14.973 | AJ69: =R69 -> 18.974 | AK69: =V69 -> 21.475 | AW69: Mkt Equity to Ttl Mkt Cap | AZ69: =AZ67/(AZ67+Main!C7) -> 0.93325544 | BD69: NPV | BE69: =NPV(BE67,AL50:CS50) -> 13685.196
B70: Goodwill | N70: 136.256 | O70: 137.11 | P70: 137.325 | Q70: 137.411 | R70: 136.349 | S70: 138.49 | T70: 138.644 | U70: 138.954 | V70: 143.452 | W70: 143.111 | X70: 142.701 | AI70: =N70 -> 136.256 | AJ70: =R70 -> 136.349 | AK70: =V70 -> 143.452 | AW70: LT Debt / Equity | AZ70: =AK86/AK89 -> 2.3716055 | BD70: SC | BE70: =Main!C4 -> 359.594
B71: Intangible Assets | N71: 32.448 | O71: 31.403 | P71: 30.405 | Q71: 29.231 | R71: 27.452 | S71: 27.76 | T71: 26.624 | U71: 25.537 | V71: 26.633 | W71: 25.156 | X71: 28.431 | AI71: =N71 -> 32.448 | AJ71: =R71 -> 27.452 | AK71: =V71 -> 26.633 | BD71: FV | BE71: =BE69/BE70 -> 38.057355
B72: LT Restricted Cash & CEs | N72: 9.972 | O72: 9.564 | P72: 9.539 | Q72: 4.437 | R72: 5.348 | S72: 5.526 | T72: 5.527 | U72: 5.367 | V72: 5.471 | W72: 6.61 | X72: 6.607 | AI72: =N72 -> 9.972 | AJ72: =R72 -> 5.348 | AK72: =V72 -> 5.471 | AW72: Cost of Equity | BD72: CP | BE72: =Main!C3 -> 17.43
B73: LT Operating Lease Assets | N73: 22.339 | O73: 20.966 | P73: 21.703 | Q73: 20.829 | R73: 19.752 | S73: 17.927 | T73: 16.099 | U73: 13.95 | V73: 14.588 | W73: 39.507 | X73: 48.871 | AI73: =N73 -> 22.339 | AJ73: =R73 -> 19.752 | AK73: =V73 -> 14.588 | AW73: RFR (10-year yield) | AZ73: 0.0447 | BD73: Change Δ | BE73: =BE71/BE72-1 -> 1.1834398 | BF73: =IF(BE73>0,"Upside","Downside") -> Upside
B74: Other LT Assets | N74: 2.429 | O74: 2.199 | P74: =2.084 -> 2.084 | Q74: 2.083 | R74: 1.947 | S74: 1.615 | T74: 2.213 | U74: 1.963 | V74: 8.132 | W74: 7.944 | X74: 7.423 | AI74: =N74 -> 2.429 | AJ74: =R74 -> 1.947 | AK74: =V74 -> 8.132 | AW74: Equity β (1-year avg.) | AZ74: ='Notes | Quant Analysis'!S244 -> 2.9471353 | BD74: {=_xlfn.IFS(BE73>=25%,"Strong Buy",BE73>=10.00001%,"Buy",AND(BE73<=10%,BE73>=-4.9999%),"Hold",AND(BE73<=-5%,BE73>=-14.999999%),"Sell",BE73<=-15%,"Strong Sell")} -> Strong Buy
B75: Ttl Assets | N75: =SUM(N62:N74) -> 701.997 | O75: =SUM(O62:O74) -> 674.602 | P75: =SUM(P62:P74) -> 658.351 | Q75: =SUM(Q62:Q74) -> 630.764 | R75: =SUM(R62:R74) -> 633.796 | S75: =SUM(S62:S74) -> 658.386 | T75: =SUM(T62:T74) -> 696.425 | U75: =SUM(U62:U74) -> 1106.06 | ... X75: =SUM(X62:X74) -> 1430.964 | AI75: =N75 -> 701.997 | AJ75: =R75 -> 633.796 | AK75: =V75 -> 1145.686 | AW75: Market Return(1-year avg.) | AZ75: 0.075
AW76: Cost of Equity | AZ76: =(AZ73+AZ74)*(AZ75-AZ73) -> 0.090652609
B77: A/P | N77: 2.601 | O77: 3.131 | P77: 2.392 | Q77: 3.572 | R77: 2.604 | S77: 4.097 | T77: 11.053 | U77: 3.448 | V77: 10.612 | W77: 9.04 | X77: 10.355 | AI77: =N77 -> 2.601 | AJ77: =R77 -> 2.604 | AK77: =V77 -> 10.612
B78: ST Accrued Liabilities | N78: 44.779 | O78: 43.361 | P78: 56.839 | Q78: 43.67 | R78: 42.6 | S78: 28.823 | T78: 32.443 | U78: 28.652 | V78: 55.874 | W78: 58.539 | X78: 56.078 | AI78: =N78 -> 44.779 | AJ78: =R78 -> 42.6 | AK78: =V78 -> 55.874 | AW78: Cost of Debt
B79: Deferred Revenue | N79: 72.327 | O79: 63.646 | P79: 64.523 | Q79: 66.462 | R79: 82.275 | S79: 108.336 | T79: 148.006 | U79: 145.857 | V79: 220.572 | W79: 230.682 | X79: 281.215 | AI79: =N79 -> 72.327 | AJ79: =R79 -> 82.275 | AK79: =V79 -> 220.572 | AW79: Cost of Debt | AZ79: 0.005
B80: ST Compensation Liabilities | N80: 8.964 | O80: 8.068 | P80: 7.171 | Q80: 6.275 | R80: 5.378 | S80: 4.482 | T80: 3.586 | U80: 2.689 | V80: 1.793 | W80: 0.896 | X80: 0 | AI80: =N80 -> 8.964 | AJ80: =R80 -> 5.378 | AK80: =V80 -> 1.793 | AW80: Tax Rate | AZ80: 0.015
B81: ST Operating Lease Liabilities | N81: 7.978 | O81: 8.175 | P81: 8.755 | Q81: 9.105 | R81: 9.221 | S81: 8.816 | T81: 8.403 | U81: 7.943 | V81: 7.296 | W81: 3.392 | X81: 3.622 | AI81: =N81 -> 7.978 | AJ81: =R81 -> 9.221 | AK81: =V81 -> 7.296 | AW81: After Tax Cost of Debt | AZ81: =AZ79*(1-AZ80) -> 0.004925
B82: ST Public/Private Warrant Liabilities | N82: 0 | O82: 0 | P82: 0 | Q82: 0 | R82: 0 | S82: 0 | T82: 0 | U82: 0 | V82: 173.308 | W82: 0 | X82: 0 | AI82: =N82 -> 0 | AJ82: =R82 -> 0 | AK82: =V82 -> 173.308
B83: LT Deferred Revenues | N83: 5.293 | O83: 13.247 | P83: 11.969 | Q83: 11.23 | R83: 11.182 | S83: 29.676 | T83: 25.013 | U83: 48.332 | V83: 27.522 | W83: 16.24 | X83: 17.364 | AI83: =N83 -> 5.293 | AJ83: =R83 -> 11.182 | AK83: =V83 -> 27.522 | AW83: WACC | AZ83: =(AZ69*AZ76)+(AZ68*AZ81*(1-AZ80)) -> 0.084925827
B84: LT Deferred Hosting Costs | N84: 7.101 | O84: 9.261 | P84: 7.963 | Q84: 6.665 | R84: 5.368 | S84: 7.75 | T84: 6.512 | U84: 5.273 | V84: 4.034 | W84: 3.21 | X84: 1.885 | AI84: =N84 -> 7.101 | AJ84: =R84 -> 5.368 | AK84: =V84 -> 4.034
B85: LT Operating Lease Liabilites | N85: 16.952 | O85: 15.207 | P85: 15.218 | Q85: 13.819 | R85: 12.392 | S85: 10.806 | T85: 9.139 | U85: 7.209 | V85: 8.3 | W85: 37.074 | X85: 46.746 | AI85: =N85 -> 16.952 | AJ85: =R85 -> 12.392 | AK85: =V85 -> 8.3
B86: LT Convertible Notes | N86: 0 | O86: 0 | P86: 0 | Q86: 0 | R86: 0 | S86: 0 | T86: 0 | U86: 446.201 | V86: 446.884 | W86: 447.569 | X86: 448.255 | AI86: =N86 -> 0 | AJ86: =R86 -> 0 | AK86: =V86 -> 446.884 | AL86: =AK86+AL45 -> 444.64958 | AM86: =AL86+AM45 -> 442.42633 | AN86: =AM86+AN45 -> 440.2142 | AO86: =AN86+AO45 -> 438.01313 | AP86: =AO86+AP45 -> 435.82306 | AQ86: =AP86+AQ45 -> 433.64395 | AR86: =AQ86+AR45 -> 431.47573 | AS86: =AR86+AS45 -> 429.31835 | ... AU86: =AT86+AU45 -> 425.0359
B87: Other LT Liabilities | N87: 17.984 | O87: 10.183 | P87: 10.274 | Q87: 5.361 | R87: 21.49 | S87: 10.802 | T87: 16.581 | U87: =56.82+3.601+0.477 -> 60.898 | V87: 1.06 | W87: 1.085 | X87: 1.093 | AI87: =N87 -> 17.984 | AJ87: =R87 -> 21.49 | AK87: =V87 -> 1.06
B88: Ttl Liabilities | N88: =SUM(N77:N87) -> 183.979 | O88: =SUM(O77:O87) -> 174.279 | P88: =SUM(P77:P87) -> 185.104 | Q88: =SUM(Q77:Q87) -> 166.159 | R88: =SUM(R77:R87) -> 192.51 | S88: =SUM(S77:S87) -> 213.588 | T88: =SUM(T77:T87) -> 260.736 | U88: =SUM(U77:U87) -> 756.502 | ... X88: =SUM(X77:X87) -> 866.613 | AI88: =N88 -> 183.979 | AJ88: =R88 -> 192.51 | AK88: =V88 -> 957.255
B89: Ttl SE | N89: 518.018 | O89: 500.325 | P89: 473.247 | Q89: 464.605 | R89: 441.286 | S89: 444.802 | T89: 435.689 | U89: 349.558 | V89: 188.431 | W89: 443.704 | X89: 564.351 | AI89: =N89 -> 518.018 | AJ89: =R89 -> 441.286 | AK89: =V89 -> 188.431
B90: Ttl L + SE | N90: =N88+N89 -> 701.997 | O90: =O88+O89 -> 674.604 | P90: =P88+P89 -> 658.351 | Q90: =Q88+Q89 -> 630.764 | R90: =R88+R89 -> 633.796 | S90: =S88+S89 -> 658.39 | T90: =T88+T89 -> 696.425 | U90: =U88+U89 -> 1106.06 | ... X90: =X88+X89 -> 1430.964 | AI90: =N90 -> 701.997 | AJ90: =R90 -> 633.796 | AK90: =V90 -> 1145.686
B92: Current Ratio | N92: =SUM(N62:N67)/SUM(N77:N82) -> 2.7087721 | O92: =SUM(O62:O67)/SUM(O77:O82) -> 2.7374051 | P92: =SUM(P62:P67)/SUM(P77:P82) -> 2.3392468 | Q92: =SUM(Q62:Q67)/SUM(Q77:Q82) -> 2.3364166 | R92: =SUM(R62:R67)/SUM(R77:R82) -> 2.1271766 | S92: =SUM(S62:S67)/SUM(S77:S82) -> 2.1016085 | T92: =SUM(T62:T67)/SUM(T77:T82) -> 1.7468242 | U92: =SUM(U62:U67)/SUM(U77:U82) -> 3.9988706 | ... X92: =SUM(X62:X67)/SUM(X77:X82) -> 2.8433683 | AI92: =SUM(AI62:AI67)/SUM(AI77:AI82) -> 2.7087721 | AJ92: =SUM(AJ62:AJ67)/SUM(AJ77:AJ82) -> 2.1271766 | AK92: =SUM(AK62:AK67)/SUM(AK77:AK82) -> 1.6516216
B93: Quick Ratio | N93: =(SUM(N62:N67)-N66)/SUM(N77:N82) -> 2.7087721 | O93: =(SUM(O62:O67)-O66)/SUM(O77:O82) -> 2.7374051 | P93: =(SUM(P62:P67)-P66)/SUM(P77:P82) -> 2.3392468 | Q93: =(SUM(Q62:Q67)-Q66)/SUM(Q77:Q82) -> 2.3364166 | R93: =(SUM(R62:R67)-R66)/SUM(R77:R82) -> 2.1271766 | S93: =(SUM(S62:S67)-S66)/SUM(S77:S82) -> 2.1016085 | T93: =(SUM(T62:T67)-T66)/SUM(T77:T82) -> 1.7468242 | U93: =(SUM(U62:U67)-U66)/SUM(U77:U82) -> 3.9988706 | ... X93: =(SUM(X62:X67)-X66)/SUM(X77:X82) -> 2.8181684 | AI93: =(SUM(AI62:AI67)-AI66)/SUM(AI77:AI82) -> 2.7087721 | AJ93: =(SUM(AJ62:AJ67)-AJ66)/SUM(AJ77:AJ82) -> 2.1271766 | AK93: =(SUM(AK62:AK67)-AK66)/SUM(AK77:AK82) -> 1.6385894
B94: Cash Ratio | N94: =(N64+N62)/SUM(N77:N82) -> 2.1874072 | O94: =(O64+O62)/SUM(O77:O82) -> 2.1805889 | P94: =(P64+P62)/SUM(P77:P82) -> 1.7854381 | Q94: =(Q64+Q62)/SUM(Q77:Q82) -> 1.8764835 | R94: =(R64+R62)/SUM(R77:R82) -> 1.5630499 | S94: =(S64+S62)/SUM(S77:S82) -> 1.4628868 | T94: =(T64+T62)/SUM(T77:T82) -> 1.3343932 | U94: =(U64+U62)/SUM(U77:U82) -> 3.591535 | ... X94: =(X64+X62)/SUM(X77:X82) -> 2.4636832 | AI94: =(AI64+AI62)/SUM(AI77:AI82) -> 2.1874072 | AJ94: =(AJ64+AJ62)/SUM(AJ77:AJ82) -> 1.5630499 | AK94: =(AK64+AK62)/SUM(AK77:AK82) -> 1.3634747
B95: Fixed Asset Turnover Ratio | N95: =N37/SUM(N68:N69) -> 0.4587156 | O95: =O37/SUM(O68:O69) -> 0.47408245 | P95: =P37/SUM(P68:P69) -> 0.4680235 | Q95: =Q37/SUM(Q68:Q69) -> 0.4534728 | R95: =R37/SUM(R68:R69) -> 0.43773939 | S95: =S37/SUM(S68:S69) -> 0.46606119 | T95: =T37/SUM(T68:T69) -> 0.48335583 | U95: =U37/SUM(U68:U69) -> 0.48932866 | ... X95: =X37/SUM(X68:X69) -> 0.58570412 | AI95: =AI37/SUM(AI68:AI69) -> 1.9033971 | AJ95: =AJ37/SUM(AJ68:AJ69) -> 1.7786716 | AK95: =AK37/SUM(AK68:AK69) -> 1.7890356
B96: Ttl Asset Turnover Ratio | N96: =N37/N75 -> 0.083903492 | O96: =O37/O75 -> 0.089534274 | P96: =P37/P75 -> 0.092807636 | Q96: =Q37/Q75 -> 0.097183733 | R96: =R37/R75 -> 0.097192156 | S96: =S37/S75 -> 0.1007008 | T96: =T37/T75 -> 0.10539541 | U96: =U37/U75 -> 0.07350415 | ... X96: =X37/X75 -> 0.081100573 | AI96: =AI37/AI75 -> 0.34814964 | AJ96: =AJ37/AJ75 -> 0.39492203 | AK96: =AK37/AK75 -> 0.26866
B97: Inventory Turnover Ratio | N97: =N38/AVERAGE(K66:N66) -> #DIV/0! | O97: =O38/AVERAGE(L66:O66) -> #DIV/0! | P97: =P38/AVERAGE(M66:P66) -> #DIV/0! | Q97: =Q38/AVERAGE(N66:Q66) -> #DIV/0! | R97: =R38/AVERAGE(O66:R66) -> #DIV/0! | S97: =S38/AVERAGE(P66:S66) -> #DIV/0! | T97: =T38/AVERAGE(Q66:T66) -> #DIV/0! | U97: =U38/AVERAGE(R66:U66) -> #DIV/0! | ... X97: =X38/AVERAGE(U66:X66) -> 8.2951507 | AI97: =AI38/AVERAGE(AF66:AI66) -> #DIV/0! | AJ97: =AJ38/AVERAGE(AG66:AJ66) -> #DIV/0! | AK97: =AK38/AVERAGE(AH66:AK66) -> 66.31677
B98: Return on Assets | N98: =N50/N75 -> -0.042789357 | O98: =O50/O75 -> -0.043481935 | P98: =P50/P75 -> -0.058722475 | Q98: =Q50/Q75 -> -0.031782093 | R98: =R50/R75 -> -0.055393218 | S98: =S50/S75 -> -0.019127077 | T98: =T50/T75 -> -0.032419859 | U98: =U50/U75 -> -0.053465454 | ... X98: =X50/X75 -> -0.0065361533 | AI98: =AI50/AI75 -> -0.17542525 | AJ98: =AJ50/AJ75 -> -0.16788998 | AK98: =AK50/AK75 -> -0.21540544
B99: Return on Equity | N99: =N50/N89 -> -0.057986402 | O99: =O50/O89 -> -0.058627892 | P99: =P50/P89 -> -0.081690956 | Q99: =Q50/Q89 -> -0.043148481 | R99: =R50/R89 -> -0.079558382 | S99: =S50/S89 -> -0.028311473 | T99: =T50/T89 -> -0.051821368 | U99: =U50/U89 -> -0.16917364 | ... X99: =X50/X89 -> -0.016573019 | AI99: =AI50/AI89 -> -0.23772919 | AJ99: =AJ50/AJ89 -> -0.2411316 | AK99: =AK50/AK89 -> -1.3096943
B101: Net Income | C101: =C50 -> -29.212 | D101: =D50 -> -20.369 | E101: =E50 -> -41.541 | F101: =F50 -> -46.011 | G101: =G50 -> -44.387 | H101: =H50 -> -39.579 | I101: =I50 -> -40.24 | J101: =J50 -> -37.818 | ... X101: =X50 -> -9.353 | AF101: =AF50 -> -137.133 | AG101: =AG50 -> -162.024 | AH101: =AH50 -> -140.405 | AI101: =AI50 -> -123.148 | AJ101: =AJ50 -> -106.408 | AK101: =AK50 -> -246.787
B102: CFFO | C102: 3.882 | D102: -12.185 | E102: -12.713 | F102: -21.195 | G102: -6.534 | H102: -22.27 | I102: -30.314 | J102: -14.815 | K102: -30.601 | L102: 9.597 | M102: -22.87 | N102: -6.837 | O102: -4.297 | P102: -7.858 | Q102: 4.076 | R102: -6.295 | S102: 17.346 | T102: 67.774 | U102: 28.593 | V102: 20.649 | W102: 15.44 | X102: 52.948 | AF102: =SUM(C102:F102) -> -42.211 | AG102: =SUM(G102:J102) -> -73.933 | AH102: =SUM(K102:N102) -> -50.711 | AI102: =SUM(O102:R102) -> -14.374 | AJ102: =SUM(P102:S102) -> 7.269 | AK102: =SUM(S102:V102) -> 134.362
B103: CapEx, net | C103: -2.614 | D103: -3.308 | E103: -2.807 | F103: -6.202 | G103: -3.506 | H103: -4.274 | I103: -2.965 | J103: -2.015 | K103: -7.075 | L103: -16.632 | M103: -8.645 | N103: -10.058 | O103: -11.356 | P103: -16.621 | Q103: -8.862 | R103: -12.78 | S103: -9.344 | T103: -21.486 | U103: -27.682 | V103: -22.985 | W103: -17.957 | X103: -29.134 | AF103: =SUM(C103:F103) -> -14.931 | AG103: =SUM(G103:J103) -> -12.76 | AH103: =SUM(K103:N103) -> -42.41 | AI103: =SUM(O103:R103) -> -49.619 | AJ103: =SUM(P103:S103) -> -47.607 | AK103: =SUM(S103:V103) -> -81.497
B104: FCF | C104: =C102+C103 -> 1.268 | D104: =D102+D103 -> -15.493 | E104: =E102+E103 -> -15.52 | F104: =F102+F103 -> -27.397 | G104: =G102+G103 -> -10.04 | H104: =H102+H103 -> -26.544 | I104: =I102+I103 -> -33.279 | J104: =J102+J103 -> -16.83 | ... X104: =X102+X103 -> 23.814 | AF104: =SUM(C104:F104) -> -57.142 | AG104: =SUM(G104:J104) -> -86.693 | AH104: =SUM(K104:N104) -> -93.121 | AI104: =SUM(O104:R104) -> -63.993 | AJ104: =SUM(P104:S104) -> -40.338 | AK104: =SUM(S104:V104) -> 52.865
B105: SC | C105: =C51 -> 45.722 | D105: =D51 -> 46.2 | E105: =E51 -> 47.137 | F105: =F51 -> 79.61 | G105: =G51 -> 264.088 | H105: =H51 -> 266.212 | I105: =I51 -> 267.947 | J105: =J51 -> 267.126 | ... X105: =X51 -> 359.59 | AF105: =AF51 -> 54.66725 | AG105: =AG51 -> 266.34325 | AH105: =AH51 -> 274.68075 | AI105: =AI51 -> 291.0235 | AJ105: =AJ51 -> 294.02325 | AK105: =AK51 -> 305.36075
B106: FCF per Share | C106: =C104/C105 -> 0.02773282 | D106: =D104/D105 -> -0.33534632 | E106: =E104/E105 -> -0.32925303 | F106: =F104/F105 -> -0.34414018 | G106: =G104/G105 -> -0.03801763 | H106: =H104/H105 -> -0.099710006 | I106: =I104/I105 -> -0.12419994 | J106: =J104/J105 -> -0.063003976 | ... X106: =X104/X105 -> 0.066225423 | AF106: =SUM(C106:F106) -> -0.98100671 | AG106: =SUM(G106:J106) -> -0.32493155 | AH106: =SUM(K106:N106) -> -0.33805381 | AI106: =SUM(O106:R106) -> -0.22021796 | AJ106: =SUM(P106:S106) -> -0.13926818 | AK106: =SUM(S106:V106) -> 0.17420468
B108: CFFO Margin | C108: =C102/C37 -> 0.1213125 | D108: =D102/D37 -> -0.40082237 | E108: =E102/E37 -> -0.40104101 | F108: =F102/F37 -> -0.5712938 | G108: =G102/G37 -> -0.16294264 | H108: =H102/H37 -> -0.46012397 | I108: =I102/I37 -> -0.60993964 | J108: =J102/J37 -> -0.2795283 | ... X108: =X102/X37 -> 0.45624375
B109: FCF Margin | C109: =C104/C37 -> 0.039625 | D109: =D104/D37 -> -0.50963816 | E109: =E104/E37 -> -0.48958991 | F109: =F104/F37 -> -0.73846361 | G109: =G104/G37 -> -0.25037406 | H109: =H104/H37 -> -0.54842975 | I109: =I104/I37 -> -0.66959759 | J109: =J104/J37 -> -0.31754717 | ... X109: =X104/X37 -> 0.20520112 | AF109: =AF104/AF37 -> -0.43553354 | AG109: =AG104/AG37 -> -0.45341527 | AH109: =AH104/AH37 -> -0.42174366 | AI109: =AI104/AI37 -> -0.26183715 | AJ109: =AJ104/AJ37 -> -0.16115861 | AK109: =AK104/AK37 -> 0.17175114
B110: CapEx as % of Revenue | C110: =-C103/C37 -> 0.0816875 | D110: =-D103/D37 -> 0.10881579 | E110: =-E103/E37 -> 0.088548896 | F110: =-F103/F37 -> 0.16716981 | G110: =-G103/G37 -> 0.087431421 | H110: =-H103/H37 -> 0.088305785 | I110: =-I103/I37 -> 0.059657948 | J110: =-J103/J37 -> 0.038018868 | ... W110: =-W103/W37 -> 0.19062633 | X110: =X103/X37 -> -0.25104264 | AF110: =-AF103/AF37 -> 0.11380335 | AG110: =-AG103/AG37 -> 0.066736402 | AH110: =-AH103/AH37 -> 0.19207428 | AI110: =-AI103/AI37 -> 0.20302373 | AJ110: =-AJ103/AJ37 -> 0.19019976 | AK110: =-AK103/AK37 -> 0.26477258

Sheet Base Case
B1: [Use for Graphing] | C1: Q1 2021 | G1: Q1 2022 | K1: Q1 2023 | O1: Q1 2024 | S1: Q1 2025 | W1: Q1 2026
B2: Quarterly
B3: Revenues | C3: Q1 2021 | D3: Q2 2021 | E3: Q3 2021 | F3: Q4 2021 | G3: Q1 2022 | H3: Q2 2022 | I3: Q3 2022 | J3: Q4 2022 | K3: Q1 2023 | L3: Q2 2023 | M3: Q3 2023 | N3: Q4 2023 | O3: Q1 2024 | P3: Q2 2024 | Q3: Q3 2024 | R3: Q4 2024 | S3: Q1 2025 | T3: Q2 2025 | U3: Q3 2025 | V3: Q4 2025 | W3: Q1 2026 | X3: Q2 2026 | AF3: 2020 | AG3: =AF3+1 -> 2021 | AH3: =AG3+1 -> 2022 | AI3: =AH3+1 -> 2023 | AJ3: =AI3+1 -> 2024 | AK3: =AJ3+1 -> 2025 | AL3: 2026 | AM3: =AL3+1 -> 2027 | AN3: =AM3+1 -> 2028 | AO3: =AN3+1 -> 2029 | AP3: =AO3+1 -> 2030 | AQ3: =AP3+1 -> 2031 | AR3: =AQ3+1 -> 2032 | AS3: =AR3+1 -> 2033 | AT3: =AS3+1 -> 2034 | ... CS3: =CR3+1 -> 2085
B4: Civil Government | O4: 18.049 | P4: 17.179 | Q4: 18.552 | R4: =71.887-SUM(O4:Q4) -> 18.107 | S4: 16.28 | T4: 16.426 | U4: 18.828 | V4: =71.91-SUM(S4:U4) -> 20.376 | W4: 16.169 | X4: 17.498 | AI4: =SUM(O4:R4) -> 71.887 | AJ4: =SUM(P4:S4) -> 70.118 | AK4: =SUM(S4:V4) -> 71.91 | AL4: =AK4*(1+AL9) -> 75.5055 | AM4: =AL4*(1+AM9) -> 80.03583 | AN4: =AM4*(1+AN9) -> 85.638338 | AO4: =AN4*(1+AO9) -> 90.776638 | AP4: =AO4*(1+AP9) -> 95.31547 | AQ4: =AP4*(1+AQ9) -> 99.128089 | AR4: =AQ4*(1+AR9) -> 102.59757 | AS4: =AR4*(1+AS9) -> 105.6755 | ... AU4: =AT4*(1+AU9) -> 110.48373
B5: Commercial | O5: 12.777 | P5: 14.232 | Q5: 14.173 | R5: =56.184-SUM(O5:Q5) -> 15.002 | S5: 13.338 | T5: 15.051 | U5: 13.061 | V5: =55.585-SUM(S5:U5) -> 14.135 | W5: 16.595 | X5: 17.559 | AI5: =SUM(O5:R5) -> 56.184 | AJ5: =SUM(P5:S5) -> 56.745 | AK5: =SUM(S5:V5) -> 55.585 | AL5: =AK5*(1+AL10) -> 67.8137 | AM5: =AL5*(1+AM10) -> 77.307618 | AN5: =AM5*(1+AN10) -> 87.357608 | AO5: =AN5*(1+AO10) -> 97.840521 | AP5: =AO5*(1+AP10) -> 108.60298 | AQ5: =AP5*(1+AQ10) -> 119.46328 | AR5: =AQ5*(1+AR10) -> 130.21497 | AS5: =AR5*(1+AS10) -> 139.33002 | ... AU5: =AT5*(1+AU10) -> 150.68542
B6: Defense & Intelligence | O6: 29.614 | P6: 29.681 | Q6: 28.541 | R6: =116.281-SUM(O6:Q6) -> 28.445 | S6: 36.647 | T6: 41.909 | U6: 49.365 | V6: =180.232-SUM(S6:U6) -> 52.311 | W6: 61.386 | X6: 80.995 | AI6: =SUM(O6:R6) -> 116.281 | AJ6: =SUM(P6:S6) -> 123.314 | AK6: =SUM(S6:V6) -> 180.232 | AL6: =AK6*(1+AL11) -> 279.3596 | AM6: =AL6*(1+AM11) -> 385.51625 | AN6: =AM6*(1+AN11) -> 508.88145 | AO6: =AN6*(1+AO11) -> 646.27944 | AP6: =AO6*(1+AP11) -> 781.99812 | AQ6: =AP6*(1+AQ11) -> 930.57776 | AR6: =AQ6*(1+AR11) -> 1088.776 | AS6: =AR6*(1+AS11) -> 1252.0924 | ... AU6: =AT6*(1+AU11) -> 1570.4995
B7: Ttl Revenues | O7: =SUM(O4:O6) -> 60.44 | P7: =SUM(P4:P6) -> 61.092 | Q7: =SUM(Q4:Q6) -> 61.266 | R7: =SUM(R4:R6) -> 61.554 | S7: =SUM(S4:S6) -> 66.265 | T7: =SUM(T4:T6) -> 73.386 | U7: =SUM(U4:U6) -> 81.254 | V7: =SUM(V4:V6) -> 86.822 | ... X7: =SUM(X4:X6) -> 116.052 | AI7: =SUM(O7:R7) -> 244.352 | AJ7: =SUM(P7:S7) -> 250.177 | AK7: =SUM(S7:V7) -> 307.727 | AL7: =SUM(AL4:AL6) -> 422.6788 | AM7: =SUM(AM4:AM6) -> 542.8597 | AN7: =SUM(AN4:AN6) -> 681.87739 | AO7: =SUM(AO4:AO6) -> 834.8966 | AP7: =SUM(AP4:AP6) -> 985.91657 | AQ7: =SUM(AQ4:AQ6) -> 1149.1691 | AR7: =SUM(AR4:AR6) -> 1321.5885 | AS7: =SUM(AS4:AS6) -> 1497.0979 | ... AU7: =SUM(AU4:AU6) -> 1831.6686
B9: Civil Government Growth Y/y | S9: =S4/O4-1 -> -0.09801097 | T9: =T4/P4-1 -> -0.043832586 | U9: =U4/Q4-1 -> 0.014877102 | V9: =V4/R4-1 -> 0.12531065 | W9: =W4/S4-1 -> -0.0068181818 | X9: =X4/T4-1 -> 0.065262389 | AJ9: =AJ4/AI4-1 -> -0.024608065 | AK9: =AK4/AJ4-1 -> 0.025556918 | AL9: 0.05 | AM9: 0.06 | AN9: 0.07 | AO9: 0.06 | AP9: 0.05 | AQ9: 0.04 | AR9: 0.035 | AS9: 0.03 | AT9: 0.025 | AU9: 0.02
B10: Commercial Growth Y/y | S10: =S5/O5-1 -> 0.04390702 | T10: =T5/P5-1 -> 0.057546374 | U10: =U5/Q5-1 -> -0.078459042 | V10: =V5/R5-1 -> -0.057792294 | W10: =W5/S5-1 -> 0.24418953 | X10: =X5/T5-1 -> 0.16663345 | AJ10: =AJ5/AI5-1 -> 0.0099850491 | AK10: =AK5/AJ5-1 -> -0.02044233 | AL10: 0.22 | AM10: 0.14 | AN10: 0.13 | AO10: 0.12 | AP10: 0.11 | AQ10: 0.1 | AR10: 0.09 | AS10: 0.07 | AT10: 0.05 | AU10: 0.03
B11: Defense & Intelligence Growth Y/y | S11: =S6/O6-1 -> 0.23748903 | T11: =T6/P6-1 -> 0.41198073 | U11: =U6/Q6-1 -> 0.72961704 | V11: =V6/R6-1 -> 0.83902268 | W11: =W6/S6-1 -> 0.67506208 | X11: =X6/T6-1 -> 0.93263977 | AJ11: =AJ6/AI6-1 -> 0.060482796 | AK11: =AK6/AJ6-1 -> 0.46156965 | AL11: 0.55 | AM11: 0.38 | AN11: 0.32 | AO11: 0.27 | AP11: 0.21 | AQ11: 0.19 | AR11: 0.17 | AS11: 0.15 | AT11: 0.13 | AU11: 0.11
B12: Ttl Revenue Growth Y/y | S12: =S7/O7-1 -> 0.096376572 | T12: =T7/P7-1 -> 0.20123748 | U12: =U7/Q7-1 -> 0.32624947 | V12: =V7/R7-1 -> 0.41050135 | W12: =W7/S7-1 -> 0.42081038 | X12: =X7/T7-1 -> 0.58139155 | AJ12: =AJ7/AI7-1 -> 0.023838561 | AK12: =AK7/AJ7-1 -> 0.23003713 | AL12: =AL7/AK7-1 -> 0.37355123 | AM12: =AM7/AL7-1 -> 0.2843315 | AN12: =AN7/AM7-1 -> 0.25608403 | AO12: =AO7/AN7-1 -> 0.22440868 | AP12: =AP7/AO7-1 -> 0.18088464 | AQ12: =AQ7/AP7-1 -> 0.16558456 | ... AU12: =AU7/AT7-1 -> 0.097150305
B14: Civil Government % of Ttl Revenues | O14: =O4/O7 -> 0.29862674 | P14: =P4/P7 -> 0.28119885 | Q14: =Q4/Q7 -> 0.30281069 | R14: =R4/R7 -> 0.29416447 | S14: =S4/S7 -> 0.24568022 | T14: =T4/T7 -> 0.22383016 | U14: =U4/U7 -> 0.23171782 | V14: =V4/V7 -> 0.23468706 | ... X14: =X4/X7 -> 0.15077724 | AI14: =AI4/AI7 -> 0.29419444 | AJ14: =AJ4/AJ7 -> 0.28027357 | AK14: =AK4/AK7 -> 0.23368115
B15: Commercial % of Ttl Revenues | O15: =O5/O7 -> 0.21139974 | P15: =P5/P7 -> 0.23296013 | Q15: =Q5/Q7 -> 0.23133549 | R15: =R5/R7 -> 0.24372096 | S15: =S5/S7 -> 0.20128273 | T15: =T5/T7 -> 0.20509361 | U15: =U5/U7 -> 0.16074286 | V15: =V5/V7 -> 0.16280436 | ... X15: =X5/X7 -> 0.15130286 | AI15: =AI5/AI7 -> 0.22993059 | AJ15: =AJ5/AJ7 -> 0.22681941 | AK15: =AK5/AK7 -> 0.18063088
B16: Defense & Intelligence % of Ttl Revenues | O16: =O6/O7 -> 0.48997353 | P16: =P6/P7 -> 0.48584103 | Q16: =Q6/Q7 -> 0.46585382 | R16: =R6/R7 -> 0.46211457 | S16: =S6/S7 -> 0.55303705 | T16: =T6/T7 -> 0.57107623 | U16: =U6/U7 -> 0.60753932 | V16: =V6/V7 -> 0.60250858 | ... X16: =X6/X7 -> 0.6979199 | AI16: =AI6/AI7 -> 0.47587497 | AJ16: =AJ6/AJ7 -> 0.49290702 | AK16: =AK6/AK7 -> 0.58568796
B18: North America | O18: 32.713 | P18: 30.797 | Q18: 27.038 | R18: =119.35-SUM(O18:Q18) -> 28.802 | S18: 29.533 | T18: 31.093 | U18: 35.148 | V18: =132.01-SUM(S18:U18) -> 36.236 | W18: 37.037 | X18: 39.015 | AI18: =SUM(O18:R18) -> 119.35 | AJ18: =SUM(P18:S18) -> 116.17 | AK18: =SUM(S18:V18) -> 132.01
B19: APAC | O19: 11.142 | P19: 10.298 | Q19: 10.334 | R19: =42.401-SUM(O19:Q19) -> 10.627 | S19: 15.307 | T19: 16.15 | U19: 14.324 | V19: =59.813-SUM(S19:U19) -> 14.032 | W19: 19.307 | X19: 19.094 | AI19: =SUM(O19:R19) -> 42.401 | AJ19: =SUM(P19:S19) -> 46.566 | AK19: =SUM(S19:V19) -> 59.813
B20: Euro, Mid-East & Africa | O20: 13.694 | P20: 17.226 | Q20: 20.011 | R20: =70.085-SUM(O20:Q20) -> 19.154 | S20: 18.849 | T20: 23.467 | U20: 27.613 | V20: =103.674-SUM(S20:U20) -> 33.745 | W20: 35.053 | X20: 55.2 | AI20: =SUM(O20:R20) -> 70.085 | AJ20: =SUM(P20:S20) -> 75.24 | AK20: =SUM(S20:V20) -> 103.674
B21: LATAM | O21: 2.891 | P21: 2.771 | Q21: 3.883 | R21: =12.516-SUM(O21:Q21) -> 2.971 | S21: 2.576 | T21: 2.676 | U21: 4.169 | V21: =12.23-SUM(S21:U21) -> 2.809 | W21: 2.753 | X21: 2.743 | AI21: =SUM(O21:R21) -> 12.516 | AJ21: =SUM(P21:S21) -> 12.201 | AK21: =SUM(S21:V21) -> 12.23
B22: Ttl Revenues | O22: =SUM(O18:O21) -> 60.44 | P22: =SUM(P18:P21) -> 61.092 | Q22: =SUM(Q18:Q21) -> 61.266 | R22: =SUM(R18:R21) -> 61.554 | S22: =SUM(S18:S21) -> 66.265 | T22: =SUM(T18:T21) -> 73.386 | U22: =SUM(U18:U21) -> 81.254 | V22: =SUM(V18:V21) -> 86.822 | ... X22: =SUM(X18:X21) -> 116.052 | AI22: =SUM(O22:R22) -> 244.352 | AJ22: =SUM(P22:S22) -> 250.177 | AK22: =SUM(S22:V22) -> 307.727
B24: North America Growth Y/y | S24: =S18/O18-1 -> -0.097209061 | T24: =T18/P18-1 -> 0.0096113258 | U24: =U18/Q18-1 -> 0.29994822 | V24: =V18/R18-1 -> 0.25810708 | W24: =W18/S18-1 -> 0.25408865 | X24: =X18/T18-1 -> 0.25478403 | AJ24: =AJ18/AI18-1 -> -0.026644323 | AK24: =AK18/AJ18-1 -> 0.1363519
B25: APAC Growth Y/y | S25: =S19/O19-1 -> 0.37381081 | T25: =T19/P19-1 -> 0.56826568 | U25: =U19/Q19-1 -> 0.38610412 | V25: =V19/R19-1 -> 0.32041028 | W25: =W19/S19-1 -> 0.26131835 | X25: =X19/T19-1 -> 0.18229102 | AJ25: =AJ19/AI19-1 -> 0.098228815 | AK25: =AK19/AJ19-1 -> 0.28447795
B26: Euro, Mid-East & Africa Growth Y/y | S26: =S20/O20-1 -> 0.37644224 | T26: =T20/P20-1 -> 0.36230117 | U26: =U20/Q20-1 -> 0.37989106 | V26: =V20/R20-1 -> 0.761773 | W26: =W20/S20-1 -> 0.85967425 | X26: =X20/T20-1 -> 1.3522393 | AJ26: =AJ20/AI20-1 -> 0.073553542 | AK26: =AK20/AJ20-1 -> 0.37791069
B27: LATAM Growth Y/y | S27: =S21/O21-1 -> -0.10895884 | T27: =T21/P21-1 -> -0.034283652 | U27: =U21/Q21-1 -> 0.073654391 | V27: =V21/R21-1 -> -0.054527095 | W27: =W21/S21-1 -> 0.06871118 | X27: =X21/T21-1 -> 0.025037369 | AJ27: =AJ21/AI21-1 -> -0.025167785 | AK27: =AK21/AJ21-1 -> 0.0023768544
B28: Ttl Revenue Growth Y/y | S28: =S22/O22-1 -> 0.096376572 | T28: =T22/P22-1 -> 0.20123748 | U28: =U22/Q22-1 -> 0.32624947 | V28: =V22/R22-1 -> 0.41050135 | W28: =W22/S22-1 -> 0.42081038 | X28: =X22/T22-1 -> 0.58139155 | AJ28: =AJ22/AI22-1 -> 0.023838561 | AK28: =AK22/AJ22-1 -> 0.23003713
B30: North America % of Ttl Revenues | O30: =O18/O22 -> 0.54124752 | P30: =P18/P22 -> 0.50410856 | Q30: =Q18/Q22 -> 0.44132145 | R30: =R18/R22 -> 0.46791435 | S30: =S18/S22 -> 0.44568022 | T30: =T18/T22 -> 0.42369117 | U30: =U18/U22 -> 0.43256947 | V30: =V18/V22 -> 0.41735966 | ... X30: =X18/X22 -> 0.3361855 | AI30: =AI18/AI22 -> 0.48843472 | AJ30: =AJ18/AJ22 -> 0.46435124 | AK30: =AK18/AK22 -> 0.42898413
B31: APAC % of Ttl Revenues | O31: =O19/O22 -> 0.18434811 | P31: =P19/P22 -> 0.16856544 | Q31: =Q19/Q22 -> 0.16867431 | R31: =R19/R22 -> 0.17264516 | S31: =S19/S22 -> 0.23099676 | T31: =T19/T22 -> 0.22006922 | U31: =U19/U22 -> 0.17628671 | V31: =V19/V22 -> 0.16161802 | ... X31: =X19/X22 -> 0.16452969 | AI31: =AI19/AI22 -> 0.17352426 | AJ31: =AJ19/AJ22 -> 0.18613222 | AK31: =AK19/AK22 -> 0.19437033
B32: Euro, Mid-East & Africa % of Ttl Revenues | O32: =O20/O22 -> 0.22657181 | P32: =P20/P22 -> 0.28196818 | Q32: =Q20/Q22 -> 0.32662488 | R32: =R20/R22 -> 0.31117393 | S32: =S20/S22 -> 0.2844488 | T32: =T20/T22 -> 0.31977489 | U32: =U20/U22 -> 0.33983558 | V32: =V20/V22 -> 0.38866877 | ... X32: =X20/X22 -> 0.47564885 | AI32: =AI20/AI22 -> 0.28681983 | AJ32: =AJ20/AJ22 -> 0.30074707 | AK32: =AK20/AK22 -> 0.33690251
B33: LATAM % of Ttl Revenues | O33: =O21/O22 -> 0.047832561 | P33: =P21/P22 -> 0.045357821 | Q33: =Q21/Q22 -> 0.063379362 | R33: =R21/R22 -> 0.048266563 | S33: =S21/S22 -> 0.038874217 | T33: =T21/T22 -> 0.036464721 | U33: =U21/U22 -> 0.051308243 | V33: =V21/V22 -> 0.032353551 | ... X33: =X21/X22 -> 0.023635956 | AI33: =AI21/AI22 -> 0.051221189 | AJ33: =AJ21/AJ22 -> 0.048769471 | AK33: =AK21/AK22 -> 0.039743019
B35: Sales Backlog | O35: 242.392 | P35: 213.5 | Q35: 232.14 | R35: 503.749 | S35: 527.047 | T35: 736.077 | U35: 734.471 | V35: 900.427 | W35: 906.055 | X35: 814.863 | AI35: =AVERAGE(O35:R35) -> 297.94525 | AJ35: =AVERAGE(P35:S35) -> 369.109 | AK35: =AVERAGE(S35:V35) -> 724.5055
B37: Revenues | C37: 32 | D37: 30.4 | E37: 31.7 | F37: 37.1 | G37: 40.1 | H37: 48.4 | I37: 49.7 | J37: 53 | K37: 52.7 | L37: 53.8 | M37: 55.4 | N37: 58.9 | O37: 60.4 | P37: 61.1 | Q37: 61.3 | R37: 61.6 | S37: 66.3 | T37: 73.4 | U37: 81.3 | V37: 86.8 | W37: 94.2 | X37: 116.052 | AF37: =SUM(C37:F37) -> 131.2 | AG37: =SUM(G37:J37) -> 191.2 | AH37: =SUM(K37:N37) -> 220.8 | AI37: =SUM(O37:R37) -> 244.4 | AJ37: =SUM(P37:S37) -> 250.3 | AK37: =SUM(S37:V37) -> 307.8 | AL37: =AL7 -> 422.6788 | AM37: =AM7 -> 542.8597 | AN37: =AN7 -> 681.87739 | AO37: =AO7 -> 834.8966 | AP37: =AP7 -> 985.91657 | AQ37: =AQ7 -> 1149.1691 | AR37: =AR7 -> 1321.5885 | AS37: =AS7 -> 1497.0979 | ... AU37: =AU7 -> 1831.6686
B38: COGS | C38: 19.126 | D38: 19.82 | E38: 20.811 | F38: =82.987-SUM(C38:E38) -> 23.23 | G38: 23.628 | H38: 24.977 | I38: 24.728 | J38: =97.248-SUM(G38:I38) -> 23.915 | K38: 24.556 | L38: 27.469 | M38: 29.35 | N38: =107.746-SUM(K38:M38) -> 26.371 | O38: 28.757 | P38: 28.782 | Q38: 23.749 | R38: =104.627-SUM(O38:Q38) -> 23.339 | S38: 29.662 | T38: 31.118 | U38: 34.67 | V38: =135.242-SUM(S38:U38) -> 39.792 | W38: 43.749 | X38: 50.42 | AF38: =SUM(C38:F38) -> 82.987 | AG38: =SUM(G38:J38) -> 97.248 | AH38: =SUM(K38:N38) -> 107.746 | AI38: =SUM(O38:R38) -> 104.627 | AJ38: =SUM(P38:S38) -> 105.532 | AK38: =SUM(S38:V38) -> 135.242 | AL38: =AL37*(1-AL54) -> 194.43225 | AM38: =AM37*(1-AM54) -> 238.85827 | AN38: =AN37*(1-AN54) -> 293.20728 | AO38: =AO37*(1-AO54) -> 346.48209 | AP38: =AP37*(1-AP54) -> 399.29621 | AQ38: =AQ37*(1-AQ54) -> 453.92181 | AR38: =AR37*(1-AR54) -> 515.41953 | AS38: =AS37*(1-AS54) -> 576.38269 | ... AU38: =AU37*(1-AU54) -> 677.71739
B39: GP | C39: =C37-C38 -> 12.874 | D39: =D37-D38 -> 10.58 | E39: =E37-E38 -> 10.889 | F39: =F37-F38 -> 13.87 | G39: =G37-G38 -> 16.472 | H39: =H37-H38 -> 23.423 | I39: =I37-I38 -> 24.972 | J39: =J37-J38 -> 29.085 | ... X39: =X37-X38 -> 65.632 | AF39: =SUM(C39:F39) -> 48.213 | AG39: =SUM(G39:J39) -> 93.952 | AH39: =SUM(K39:N39) -> 113.054 | AI39: =SUM(O39:R39) -> 139.773 | AJ39: =SUM(P39:S39) -> 144.768 | AK39: =SUM(S39:V39) -> 172.558 | AL39: =AL37*AL54 -> 228.24655 | AM39: =AM37*AM54 -> 304.00143 | AN39: =AN37*AN54 -> 388.67011 | AO39: =AO37*AO54 -> 488.41451 | AP39: =AP37*AP54 -> 586.62036 | AQ39: =AQ37*AQ54 -> 695.24732 | AR39: =AR37*AR54 -> 806.169 | AS39: =AS37*AS54 -> 920.71521 | ... AU39: =AU37*AU54 -> 1153.9512
B40: R&D | C40: 12.13 | D40: 12.432 | E40: 14.959 | F40: =66.684-SUM(C40:E40) -> 27.163 | G40: 24.75 | H40: 26.737 | I40: 27.598 | J40: =110.916-SUM(G40:I40) -> 31.831 | K40: 28.186 | L40: 26.741 | M40: 33.002 | N40: =116.339-SUM(K40:M40) -> 28.41 | O40: 25.589 | P40: 27.25 | Q40: 25.216 | R40: =101.006-SUM(O40:Q40) -> 22.951 | S40: 23.074 | T40: 24.155 | U40: 27.327 | V40: =106.749-SUM(S40:U40) -> 32.193 | W40: 33.42 | X40: 35.156 | AF40: =SUM(C40:F40) -> 66.684 | AG40: =SUM(G40:J40) -> 110.916 | AH40: =SUM(K40:N40) -> 116.339 | AI40: =SUM(O40:R40) -> 101.006 | AJ40: =SUM(P40:S40) -> 98.491 | AK40: =SUM(S40:V40) -> 106.749 | AL40: =AL37*AL55 -> 147.93758 | AM40: =AM37*AM55 -> 179.1437 | AN40: =AN37*AN55 -> 204.56322 | AO40: =AO37*AO55 -> 212.89863 | AP40: =AP37*AP55 -> 241.54956 | AQ40: =AQ37*AQ55 -> 270.05475 | AR40: =AR37*AR55 -> 297.35742 | AS40: =AS37*AS55 -> 321.87605 | ... AU40: =AU37*AU55 -> 338.8587
B41: Sales and Marketing | C41: 10.653 | D41: 10.597 | E41: 12.441 | F41: =52.917-SUM(C41:E41) -> 19.226 | G41: 18.855 | H41: 19.483 | I41: 19.383 | J41: =78.02-SUM(G41:I41) -> 20.299 | K41: 23.125 | L41: 22.31 | M41: 20.774 | N41: =86.304-SUM(K41:M41) -> 20.095 | O41: 21.485 | P41: 23.733 | Q41: 16.795 | R41: =77.694-SUM(O41:Q41) -> 15.681 | S41: 16.314 | T41: 17.574 | U41: 18.783 | V41: =72.676-SUM(S41:U41) -> 20.005 | W41: 22.782 | X41: 21.498 | AF41: =SUM(C41:F41) -> 52.917 | AG41: =SUM(G41:J41) -> 78.02 | AH41: =SUM(K41:N41) -> 86.304 | AI41: =SUM(O41:R41) -> 77.694 | AJ41: =SUM(P41:S41) -> 72.523 | AK41: =SUM(S41:V41) -> 72.676 | AL41: =AL37*AL56 -> 103.55631 | AM41: =AM37*AM56 -> 127.57203 | AN41: =AN37*AN56 -> 150.01303 | AO41: =AO37*AO56 -> 175.32829 | AP41: =AP37*AP56 -> 202.1129 | AQ41: =AQ37*AQ56 -> 229.83383 | AR41: =AR37*AR56 -> 257.70976 | AS41: =AS37*AS56 -> 284.4486 | ... AU41: =AU37*AU56 -> 329.70035
B42: General and Admin | C42: 8.315 | D42: 11.824 | E42: 11.8 | F42: =56.672-SUM(C42:E42) -> 24.733 | G42: 20.608 | H42: 19.893 | I42: 20.627 | J42: =80.747-SUM(G42:I42) -> 19.619 | K42: 21.528 | L42: 20.521 | M42: 20.112 | N42: =80.055-SUM(K42:M42) -> 17.894 | O42: 19.18 | P42: 20.904 | Q42: 18.114 | R42: =77.147-SUM(O42:Q42) -> 18.949 | S42: 19.986 | T42: 18.499 | U42: 18.814 | V42: =88.133-SUM(S42:U42) -> 30.834 | W42: 29.087 | X42: 22.487 | AF42: =SUM(C42:F42) -> 56.672 | AG42: =SUM(G42:J42) -> 80.747 | AH42: =SUM(K42:N42) -> 80.055 | AI42: =SUM(O42:R42) -> 77.147 | AJ42: =SUM(P42:S42) -> 77.953 | AK42: =SUM(S42:V42) -> 88.133 | AL42: =AL37*AL57 -> 131.03043 | AM42: =AM37*AM57 -> 165.57221 | AN42: =AN37*AN57 -> 204.56322 | AO42: =AO37*AO57 -> 246.2945 | AP42: =AP37*AP57 -> 285.91581 | AQ42: =AQ37*AQ57 -> 327.5132 | AR42: =AR37*AR57 -> 370.04479 | AS42: =AS37*AS57 -> 411.70192 | ... AU42: =AU37*AU57 -> 514.69888
B43: Operating Income | C43: =C39-SUM(C40:C42) -> -18.224 | D43: =D39-SUM(D40:D42) -> -24.273 | E43: =E39-SUM(E40:E42) -> -28.311 | F43: =F39-SUM(F40:F42) -> -57.252 | G43: =G39-SUM(G40:G42) -> -47.741 | H43: =H39-SUM(H40:H42) -> -42.69 | I43: =I39-SUM(I40:I42) -> -42.636 | J43: =J39-SUM(J40:J42) -> -42.664 | ... X43: =X39-SUM(X40:X42) -> -13.509 | AF43: =SUM(C43:F43) -> -128.06 | AG43: =SUM(G43:J43) -> -175.731 | AH43: =SUM(K43:N43) -> -169.644 | AI43: =SUM(O43:R43) -> -116.074 | AJ43: =SUM(P43:S43) -> -104.199 | AK43: =SUM(S43:V43) -> -95 | AL43: =AL39-SUM(AL40:AL42) -> -154.27776 | AM43: =AM39-SUM(AM40:AM42) -> -168.28651 | AN43: =AN39-SUM(AN40:AN42) -> -170.46935 | AO43: =AO39-SUM(AO40:AO42) -> -146.1069 | AP43: =AP39-SUM(AP40:AP42) -> -142.9579 | AQ43: =AQ39-SUM(AQ40:AQ42) -> -132.15445 | AR43: =AR39-SUM(AR40:AR42) -> -118.94297 | AS43: =AS39-SUM(AS40:AS42) -> -97.311363 | ... AU43: =AU39-SUM(AU40:AU42) -> -29.306698
B44: Interest Income | C44: 0 | D44: 0 | E44: 0.008 | F44: =0.021-SUM(C44:E44) -> 0.013 | G44: 0.112 | H44: 1.311 | I44: 2.853 | J44: =7.67-SUM(G44:I44) -> 3.394 | K44: 4.506 | L44: 3.802 | M44: 3.445 | N44: =15.414-SUM(K44:M44) -> 3.661 | O44: 3.107 | P44: 2.771 | Q44: 2.414 | R44: =10.257-SUM(O44:Q44) -> 1.965 | S44: 1.884 | T44: 2.172 | U44: 4.414 | V44: =14.329-SUM(S44:U44) -> 5.859 | W44: 5.153 | X44: 6.433 | AF44: =SUM(C44:F44) -> 0.021 | AG44: =SUM(G44:J44) -> 7.67 | AH44: =SUM(K44:N44) -> 15.414 | AI44: =SUM(O44:R44) -> 10.257 | AJ44: =SUM(P44:S44) -> 9.034 | AK44: =SUM(S44:V44) -> 14.329 | AL44: =SUM(AK62:AK64)*($BE$62) -> 190.61777 | AM44: =SUM(AL62:AL64)*($BE$62) -> 200.95925 | AN44: =SUM(AM62:AM63)*($BE$62) -> 210.19213 | AO44: =SUM(AN62:AN63)*($BE$62) -> 221.56608 | AP44: =SUM(AO62:AO63)*($BE$62) -> 243.77937 | AQ44: =SUM(AP62:AP63)*($BE$62) -> 273.68633 | AR44: =SUM(AQ62:AQ63)*($BE$62) -> 315.9408 | AS44: =SUM(AR62:AR63)*($BE$62) -> 375.01692 | AT44: =SUM(AS62:AS63)*($BE$62) -> 458.56849 | AU44: =SUM(AT62:AT63)*($BE$62) -> 575.70332
B45: Interest Expense | C45: -2.527 | D45: -2.611 | E45: -2.612 | F45: =-8.772-SUM(C45:E45) -> -1.022 | G45: 0 | H45: 0 | I45: 0 | J45: =0-SUM(G45:I45) -> 0 | K45: 0 | L45: 0 | M45: 0 | N45: =0-SUM(K45:M45) -> 0 | O45: 0 | P45: 0 | Q45: -0.277 | R45: =-0.832-SUM(O45:Q45) -> -0.555 | S45: -0.499 | T45: 0 | U45: -1.02 | V45: =-3.436-SUM(S45:U45) -> -1.917 | W45: -1.446 | X45: -1.439 | AF45: =SUM(C45:F45) -> -8.772 | AG45: =SUM(G45:J45) -> 0 | AH45: =SUM(K45:N45) -> 0 | AI45: =SUM(O45:R45) -> -0.832 | AJ45: =SUM(P45:S45) -> -1.331 | AK45: =SUM(S45:V45) -> -3.436 | AL45: =-AK86*($AZ$79) -> -2.23442 | AM45: =-AL86*($AZ$79) -> -2.2232479 | AN45: =-AM86*($AZ$79) -> -2.2121317 | AO45: =-AN86*($AZ$79) -> -2.201071 | AP45: =-AO86*($AZ$79) -> -2.1900656 | AQ45: =-AP86*($AZ$79) -> -2.1791153 | AR45: =-AQ86*($AZ$79) -> -2.1682197 | AS45: =-AR86*($AZ$79) -> -2.1573786 | ... AU45: =-AT86*($AZ$79) -> -2.1358588
B46: Change in FV of Warrant Liabilities | C46: -8.026 | D46: 6.769 | E46: -10.172 | F46: =5.726-SUM(C46:E46) -> 17.155 | G46: 3.276 | H46: 2.112 | I46: -0.019 | J46: =6.554-SUM(G46:I46) -> 1.185 | K46: 5.945 | L46: 1.226 | M46: 6.833 | N46: =13.709-SUM(K46:M46) -> -0.295 | O46: 1.53 | P46: -0.602 | Q46: 0.198 | R46: =-15.116-SUM(O46:Q46) -> -16.242 | S46: 10.387 | T46: -5.679 | U46: -43.473 | V46: =-161.4-SUM(S46:U46) -> -122.635 | W46: -106.474 | X46: 0 | AF46: =SUM(C46:F46) -> 5.726 | AG46: =SUM(G46:J46) -> 6.554 | AH46: =SUM(K46:N46) -> 13.709 | AI46: =SUM(O46:R46) -> -15.116 | AJ46: =SUM(P46:S46) -> -6.259 | AK46: =SUM(S46:V46) -> -161.4 | AL46: 0 | AM46: 0 | AN46: 0 | AO46: 0 | AP46: 0 | AQ46: 0 | AR46: 0 | AS46: 0 | AT46: 0 | AU46: 0
B47: Other Income | C47: -0.177 | D47: -0.084 | E47: -0.06 | F47: =-2.248-1.69-SUM(C47:E47) -> -3.617 | G47: 0.28 | H47: -0.158 | I47: 0.001 | J47: =0.33-SUM(G47:I47) -> 0.207 | K47: 0.104 | L47: 0.859 | M47: -0.069 | N47: =0.931-SUM(K47:M47) -> 0.037 | O47: 1.083 | P47: -0.363 | Q47: 0.217 | R47: =1.077-SUM(O47:Q47) -> 0.14 | S47: -0.701 | T47: -0.628 | U47: 0.018 | V47: =3.375-SUM(S47:U47) -> 4.686 | W47: -0.206 | X47: -0.105 | AF47: =SUM(C47:F47) -> -3.938 | AG47: =SUM(G47:J47) -> 0.33 | AH47: =SUM(K47:N47) -> 0.931 | AI47: =SUM(O47:R47) -> 1.077 | AJ47: =SUM(P47:S47) -> -0.707 | AK47: =SUM(S47:V47) -> 3.375 | AL47: 0 | AM47: 0 | AN47: 0 | AO47: 0 | AP47: 0 | AQ47: 0 | AR47: 0 | AS47: 0 | AT47: 0 | AU47: 0
B48: Pretax Income | C48: =C43+SUM(C44:C47) -> -28.954 | D48: =D43+SUM(D44:D47) -> -20.199 | E48: =E43+SUM(E44:E47) -> -41.147 | F48: =F43+SUM(F44:F47) -> -44.723 | G48: =G43+SUM(G44:G47) -> -44.073 | H48: =H43+SUM(H44:H47) -> -39.425 | I48: =I43+SUM(I44:I47) -> -39.801 | J48: =J43+SUM(J44:J47) -> -37.878 | ... X48: =X43+SUM(X44:X47) -> -8.62 | AF48: =SUM(C48:F48) -> -135.023 | AG48: =SUM(G48:J48) -> -161.177 | AH48: =SUM(K48:N48) -> -139.59 | AI48: =SUM(O48:R48) -> -120.688 | AJ48: =SUM(P48:S48) -> -103.462 | AK48: =SUM(S48:V48) -> -242.132 | AL48: =AL43+SUM(AL44:AL47) -> 34.105588 | AM48: =AM43+SUM(AM44:AM47) -> 30.449494 | AN48: =AN43+SUM(AN44:AN47) -> 37.510647 | AO48: =AO43+SUM(AO44:AO47) -> 73.258109 | AP48: =AP43+SUM(AP44:AP47) -> 98.6314 | AQ48: =AQ43+SUM(AQ44:AQ47) -> 139.35276 | AR48: =AR43+SUM(AR44:AR47) -> 194.82961 | AS48: =AS43+SUM(AS44:AS47) -> 275.54818 | ... AU48: =AU43+SUM(AU44:AU47) -> 544.26076
B49: Taxes | C49: 0.258 | D49: 0.17 | E49: 0.394 | F49: =2.11-SUM(C49:E49) -> 1.288 | G49: 0.314 | H49: 0.154 | I49: 0.439 | J49: =0.847-SUM(G49:I49) -> -0.06 | K49: 0.307 | L49: 0.582 | M49: 0.355 | N49: =0.815-SUM(K49:M49) -> -0.429 | O49: 0.442 | P49: 0.897 | Q49: 0.025 | R49: =2.46-SUM(O49:Q49) -> 1.096 | S49: 0.928 | T49: 0.497 | U49: 0.781 | V49: =4.655-SUM(S49:U49) -> 2.449 | W49: 1.011 | X49: 0.733 | AF49: =SUM(C49:F49) -> 2.11 | AG49: =SUM(G49:J49) -> 0.847 | AH49: =SUM(K49:N49) -> 0.815 | AI49: =SUM(O49:R49) -> 2.46 | AJ49: =SUM(P49:S49) -> 2.946 | AK49: =SUM(S49:V49) -> 4.655 | AL49: =AL48*AL59 -> -0.65568166 | AM49: =AM48*AM59 -> -0.58539307 | AN49: =AN48*AN59 -> -0.72114409 | AO49: =AO48*AO59 -> -1.4083909 | AP49: =AP48*AP59 -> -1.8961937 | AQ49: =AQ48*AQ59 -> -2.6790639 | AR49: =AR48*AR59 -> -3.7456091 | AS49: =AS48*AS59 -> -5.2974278 | ... AU49: =AU48*AU59 -> -10.463441
B50: Net Income | C50: =C48-C49 -> -29.212 | D50: =D48-D49 -> -20.369 | E50: =E48-E49 -> -41.541 | F50: =F48-F49 -> -46.011 | G50: =G48-G49 -> -44.387 | H50: =H48-H49 -> -39.579 | I50: =I48-I49 -> -40.24 | J50: =J48-J49 -> -37.818 | ... X50: =X48-X49 -> -9.353 | AF50: =SUM(C50:F50) -> -137.133 | AG50: =SUM(G50:J50) -> -162.024 | AH50: =SUM(K50:N50) -> -140.405 | AI50: =SUM(O50:R50) -> -123.148 | AJ50: =SUM(P50:S50) -> -106.408 | AK50: =SUM(S50:V50) -> -246.787 | AL50: =AL48-AL49 -> 34.76127 | AM50: =AM48-AM49 -> 31.034887 | AN50: =AN48-AN49 -> 38.231791 | AO50: =AO48-AO49 -> 74.6665 | AP50: =AP48-AP49 -> 100.52759 | AQ50: =AQ48-AQ49 -> 142.03183 | AR50: =AR48-AR49 -> 198.57522 | AS50: =AS48-AS49 -> 280.84561 | ... AU50: =AU48-AU49 -> 554.7242 | AV50: =AU50*(1+$BE$63) -> 567.2055 | AW50: =AV50*(1+$BE$63) -> 579.96762 | AX50: =AW50*(1+$BE$63) -> 593.01689 | AY50: =AX50*(1+$BE$63) -> 606.35977 | AZ50: =AY50*(1+$BE$63) -> 620.00287 | BA50: =AZ50*(1+$BE$63) -> 633.95293 | BB50: =BA50*(1+$BE$63) -> 648.21688 | BC50: =BB50*(1+$BE$63) -> 662.80176 | ... CS50: =CR50*(1+$BE$63) -> 1687.4968
B51: SC | C51: 45.722 | D51: 46.2 | E51: 47.137 | F51: 79.61 | G51: 264.088 | H51: 266.212 | I51: 267.947 | J51: 267.126 | K51: 272.347 | L51: 275.053 | M51: 284.197 | N51: 267.126 | O51: 288.268 | P51: 290.364 | Q51: 293.338 | R51: 292.124 | S51: 300.267 | T51: 304.129 | U51: 309.248 | V51: 307.799 | W51: 345.524 | X51: 359.59 | AF51: =AVERAGE(C51:F51) -> 54.66725 | AG51: =AVERAGE(G51:J51) -> 266.34325 | AH51: =AVERAGE(K51:N51) -> 274.68075 | AI51: =AVERAGE(O51:R51) -> 291.0235 | AJ51: =AVERAGE(P51:S51) -> 294.02325 | AK51: =AVERAGE(S51:V51) -> 305.36075
B52: EPS | C52: =C50/C51 -> -0.63890468 | D52: =D50/D51 -> -0.44088745 | E52: =E50/E51 -> -0.88128222 | F52: =F50/F51 -> -0.57795503 | G52: =G50/G51 -> -0.16807655 | H52: =H50/H51 -> -0.14867474 | I52: =I50/I51 -> -0.15017895 | J52: =J50/J51 -> -0.14157364 | ... X52: =X50/X51 -> -0.026010178 | AF52: =AF50/AF51 -> -2.5085037 | AG52: =AG50/AG51 -> -0.60832779 | AH52: =AH50/AH51 -> -0.51115704 | AI52: =AI50/AI51 -> -0.42315483 | AJ52: =AJ50/AJ51 -> -0.36190335 | AK52: =AK50/AK51 -> -0.8081818
B54: Gross Profit Margin | C54: =C39/C37 -> 0.4023125 | D54: =D39/D37 -> 0.34802632 | E54: =E39/E37 -> 0.34350158 | F54: =F39/F37 -> 0.37385445 | G54: =G39/G37 -> 0.41077307 | H54: =H39/H37 -> 0.48394628 | I54: =I39/I37 -> 0.50245473 | J54: =J39/J37 -> 0.54877358 | ... X54: =X39/X37 -> 0.56553959 | AF54: =AF39/AF37 -> 0.36747713 | AG54: =AG39/AG37 -> 0.49138075 | AH54: =AH39/AH37 -> 0.51201993 | AI54: =AI39/AI37 -> 0.57190262 | AJ54: =AJ39/AJ37 -> 0.57837795 | AK54: =AK39/AK37 -> 0.56061728 | AL54: 0.54 | AM54: 0.56 | AN54: 0.57 | AO54: 0.585 | AP54: 0.595 | AQ54: 0.605 | AR54: 0.61 | AS54: 0.615 | AT54: 0.625 | AU54: 0.63
B55: R&D as % of Revenue | C55: =C40/C37 -> 0.3790625 | D55: =D40/D37 -> 0.40894737 | E55: =E40/E37 -> 0.47189274 | F55: =F40/F37 -> 0.73215633 | G55: =G40/G37 -> 0.61720698 | H55: =H40/H37 -> 0.55241736 | I55: =I40/I37 -> 0.55529175 | J55: =J40/J37 -> 0.60058491 | ... X55: =X40/X37 -> 0.30293317 | AF55: =AF40/AF37 -> 0.5082622 | AG55: =AG40/AG37 -> 0.5801046 | AH55: =AH40/AH37 -> 0.52689764 | AI55: =AI40/AI37 -> 0.41328151 | AJ55: =AJ40/AJ37 -> 0.39349181 | AK55: =AK40/AK37 -> 0.34681287 | AL55: 0.35 | AM55: 0.33 | AN55: 0.3 | AO55: 0.255 | AP55: 0.245 | AQ55: 0.235 | AR55: 0.225 | AS55: 0.215 | AT55: 0.2 | AU55: 0.185
B56: Sales and Marketing as % of Revenue | C56: =C41/C37 -> 0.33290625 | D56: =D41/D37 -> 0.34858553 | E56: =E41/E37 -> 0.39246057 | F56: =F41/F37 -> 0.51822102 | G56: =G41/G37 -> 0.4701995 | H56: =H41/H37 -> 0.40254132 | I56: =I41/I37 -> 0.39 | J56: =J41/J37 -> 0.383 | ... X56: =X41/X37 -> 0.18524455 | AF56: =AF41/AF37 -> 0.40333079 | AG56: =AG41/AG37 -> 0.40805439 | AH56: =AH41/AH37 -> 0.39086957 | AI56: =AI41/AI37 -> 0.31789689 | AJ56: =AJ41/AJ37 -> 0.28974431 | AK56: =AK41/AK37 -> 0.23611436 | AL56: 0.245 | AM56: 0.235 | AN56: 0.22 | AO56: 0.21 | AP56: 0.205 | AQ56: 0.2 | AR56: 0.195 | AS56: 0.19 | AT56: 0.185 | AU56: 0.18
B57: General and Admin as % of Revenue | C57: =C42/C37 -> 0.25984375 | D57: =D42/D37 -> 0.38894737 | E57: =E42/E37 -> 0.37223975 | F57: =F42/F37 -> 0.66665768 | G57: =G42/G37 -> 0.51391521 | H57: =H42/H37 -> 0.4110124 | I57: =I42/I37 -> 0.41503018 | J57: =J42/J37 -> 0.37016981 | ... X57: =X42/X37 -> 0.19376659 | AF57: =AF42/AF37 -> 0.43195122 | AG57: =AG42/AG37 -> 0.42231695 | AH57: =AH42/AH37 -> 0.36256793 | AI57: =AI42/AI37 -> 0.31565876 | AJ57: =AJ42/AJ37 -> 0.31143827 | AK57: =AK42/AK37 -> 0.28633203 | AL57: 0.31 | AM57: 0.305 | AN57: 0.3 | AO57: 0.295 | AP57: 0.29 | AQ57: 0.285 | AR57: 0.28 | AS57: 0.275 | AT57: 0.282 | AU57: 0.281
B58: Operating Profit Margin | C58: =C43/C37 -> -0.5695 | D58: =D43/D37 -> -0.79845395 | E58: =E43/E37 -> -0.89309148 | F58: =F43/F37 -> -1.5431806 | G58: =G43/G37 -> -1.1905486 | H58: =H43/H37 -> -0.88202479 | I58: =I43/I37 -> -0.8578672 | J58: =J43/J37 -> -0.80498113 | ... X58: =X43/X37 -> -0.11640472 | AF58: =AF43/AF37 -> -0.97606707 | AG58: =AG43/AG37 -> -0.91909519 | AH58: =AH43/AH37 -> -0.76831522 | AI58: =AI43/AI37 -> -0.47493453 | AJ58: =AJ43/AJ37 -> -0.41629644 | AK58: =AK43/AK37 -> -0.30864198 | AL58: =AL43/AL37 -> -0.365 | AM58: =AM43/AM37 -> -0.31 | ... AU58: =AU43/AU37 -> -0.016
B59: Effective Tax Rate | C59: =C49/C48 -> -0.0089106859 | D59: =D49/D48 -> -0.0084162582 | E59: =E49/E48 -> -0.0095754247 | F59: =F49/F48 -> -0.028799499 | G59: =G49/G48 -> -0.0071245434 | H59: =H49/H48 -> -0.0039061509 | I59: =I49/I48 -> -0.011029874 | J59: =J49/J48 -> 0.0015840329 | ... X59: =X49/X48 -> -0.085034803 | AF59: =AF49/AF48 -> -0.015626967 | AG59: =AG49/AG48 -> -0.0052550922 | AH59: =AH49/AH48 -> -0.0058385271 | AI59: =AI49/AI48 -> -0.020383137 | AJ59: =AJ49/AJ48 -> -0.028474222 | AK59: =AK49/AK48 -> -0.019225051 | AL59: -0.019225051 | AM59: -0.019225051 | AN59: -0.019225051 | AO59: -0.019225051 | AP59: -0.019225051 | AQ59: -0.019225051 | AR59: -0.019225051 | AS59: -0.019225051 | AT59: -0.019225051 | AU59: -0.019225051
B60: Net Profit Margin | C60: =C50/C37 -> -0.912875 | D60: =D50/D37 -> -0.67003289 | E60: =E50/E37 -> -1.3104416 | F60: =F50/F37 -> -1.2401887 | G60: =G50/G37 -> -1.1069077 | H60: =H50/H37 -> -0.81774793 | I60: =I50/I37 -> -0.80965795 | J60: =J50/J37 -> -0.71354717 | ... X60: =X50/X37 -> -0.080593182 | AF60: =AF50/AF37 -> -1.045221 | AG60: =AG50/AG37 -> -0.84740586 | AH60: =AH50/AH37 -> -0.63589221 | AI60: =AI50/AI37 -> -0.50387889 | AJ60: =AJ50/AJ37 -> -0.42512185 | AK60: =AK50/AK37 -> -0.80177713 | AL60: =AL50/AL37 -> 0.082240391 | AM60: =AM50/AM37 -> 0.05716926 | ... AU60: =AU50/AU37 -> 0.30285184
B62: Cash & CEs | N62: 83.866 | O62: 107.367 | P62: 148.288 | Q62: 138.969 | R62: 118.048 | S62: 133.471 | T62: 181.087 | U62: 443.349 | V62: 229.441 | W62: 368.09 | X62: 415.13 | AI62: =N62 -> 83.866 | AJ62: =R62 -> 118.048 | AK62: =V62 -> 229.441 | AL62: =SUM(AK62:AK64)+AL50 -> 675.49327 | AM62: =AL62+AM50 -> 706.52816 | AN62: =AM62+AN50 -> 744.75995 | AO62: =AN62+AO50 -> 819.42645 | AP62: =AO62+AP50 -> 919.95404 | AQ62: =AP62+AQ50 -> 1061.9859 | AR62: =AQ62+AR50 -> 1260.5611 | AS62: =AR62+AS50 -> 1541.4067 | AT62: =AS62+AT50 -> 1935.1372 | AU62: =AT62+AU50 -> 2489.8614 | AW62: Invested Capital | AZ62: Avg. (2024-2025) | BB62: Projected ROIC: | BD62: ROIC | BE62: 0.2975
B63: Restricted Cash & CEs | N63: 8.36 | O63: 8.8 | P63: 8.802 | Q63: 6.525 | R63: 6.598 | S63: 6.607 | T63: 6.316 | U63: 0.906 | V63: 0.642 | W63: 0.896 | X63: 1.891 | AI63: =N63 -> 8.36 | AJ63: =R63 -> 6.598 | AK63: =V63 -> 0.642 | AW63: 2025 | AX63: 2026 | AZ63: 2025-2026 | BB63: 2025 | BD63: Terminal | BE63: 0.0225
B64: ST Investments | N64: 215.041 | O64: 168.218 | P64: 101.102 | Q64: 103.255 | R64: 104.027 | S64: 92.624 | T64: 90.45 | U64: 233.975 | V64: 410.649 | W64: 362.745 | X64: 450.288 | AI64: =N64 -> 215.041 | AJ64: =R64 -> 104.027 | AK64: =V64 -> 410.649 | AW64: =SUM(AJ62:AJ67)-AJ71-AJ77+AJ68+AJ70 -> 530.267 | AX64: =SUM(AK62:AK67)-AK71-AK77+AK68+AK70 -> 1032.142 | AZ64: =AVERAGE(AW64:AX64) -> 781.2045 | BB64: =AVERAGE(AL43)*(1-AL59) -> -157.24376 | BD64: RFR (10-year yield) | BE64: 0.0447
B65: A/R | N65: 43.32 | O65: 38.527 | P65: 43.926 | Q65: 38.853 | R65: 55.833 | S65: 74.663 | T65: 51.633 | U65: 46.332 | V65: 83.528 | W65: 61.605 | X65: 59.87 | AI65: =N65 -> 43.32 | AJ65: =R65 -> 55.833 | AK65: =V65 -> 83.528 | BB65: =BB64/AZ64 -> -0.20128374 | BD65: ERP (Avg. market return - (less) RFR) | BE65: =4.6%-BE64 -> 0.0013
B66: Inventories | N66: 0 | O66: 0 | P66: 0 | Q66: 0 | R66: 0 | S66: 0 | T66: 0 | U66: 0 | V66: 6.118 | W66: 9.343 | X66: 8.852 | AI66: =N66 -> 0 | AJ66: =R66 -> 0 | AK66: =V66 -> 6.118 | AW66: Capital Structure | BD66: Equity β (1-year avg.) | BE66: =AZ74 -> 2.9471353
B67: ST Prepaid Expenses | N67: 19.564 | O67: 23.044 | P67: 24.628 | Q67: 13.992 | R67: 17.719 | S67: 17.447 | T67: 25.977 | U67: 29.581 | V67: 44.984 | W67: 46.299 | X67: 62.759 | AI67: =N67 -> 19.564 | AJ67: =R67 -> 17.719 | AK67: =V67 -> 44.984 | AW67: Mkt Cap | AZ67: =Main!C5 -> 6267.7234 | BD67: Discount (Cost of Equity) | BE67: =+BE64+(BE65*BE66) -> 0.048531276
B68: PP&E, net | N68: 113.429 | O68: 111.338 | P68: 113.227 | Q68: 116.92 | R68: 121.749 | S68: 122.473 | T68: 131.288 | U68: 145.084 | V68: 150.573 | W68: 159.145 | X68: 176.09 | AI68: =N68 -> 113.429 | AJ68: =R68 -> 121.749 | AK68: =V68 -> 150.573 | AW68: Debt to Ttl Mkt Cap | AZ68: =Main!C7/(Main!C7+AZ67) -> 0.066744556
B69: LT Capitalized Software | N69: 14.973 | O69: 16.066 | P69: 17.322 | Q69: 18.259 | R69: 18.974 | S69: 19.783 | T69: 20.567 | U69: 21.062 | V69: 21.475 | W69: 20.98 | X69: 22.051 | AI69: =N69 -> 14.973 | AJ69: =R69 -> 18.974 | AK69: =V69 -> 21.475 | AW69: Mkt Equity to Ttl Mkt Cap | AZ69: =AZ67/(AZ67+Main!C7) -> 0.93325544 | BD69: NPV | BE69: =NPV(BE67,AL50:CS50) -> 10985.517
B70: Goodwill | N70: 136.256 | O70: 137.11 | P70: 137.325 | Q70: 137.411 | R70: 136.349 | S70: 138.49 | T70: 138.644 | U70: 138.954 | V70: 143.452 | W70: 143.111 | X70: 142.701 | AI70: =N70 -> 136.256 | AJ70: =R70 -> 136.349 | AK70: =V70 -> 143.452 | AW70: LT Debt / Equity | AZ70: =AK86/AK89 -> 2.3716055 | BD70: SC | BE70: =Main!C4 -> 359.594
B71: Intangible Assets | N71: 32.448 | O71: 31.403 | P71: 30.405 | Q71: 29.231 | R71: 27.452 | S71: 27.76 | T71: 26.624 | U71: 25.537 | V71: 26.633 | W71: 25.156 | X71: 28.431 | AI71: =N71 -> 32.448 | AJ71: =R71 -> 27.452 | AK71: =V71 -> 26.633 | BD71: FV | BE71: =BE69/BE70 -> 30.549778
B72: LT Restricted Cash & CEs | N72: 9.972 | O72: 9.564 | P72: 9.539 | Q72: 4.437 | R72: 5.348 | S72: 5.526 | T72: 5.527 | U72: 5.367 | V72: 5.471 | W72: 6.61 | X72: 6.607 | AI72: =N72 -> 9.972 | AJ72: =R72 -> 5.348 | AK72: =V72 -> 5.471 | AW72: Cost of Equity | BD72: CP | BE72: =Main!C3 -> 17.43
B73: LT Operating Lease Assets | N73: 22.339 | O73: 20.966 | P73: 21.703 | Q73: 20.829 | R73: 19.752 | S73: 17.927 | T73: 16.099 | U73: 13.95 | V73: 14.588 | W73: 39.507 | X73: 48.871 | AI73: =N73 -> 22.339 | AJ73: =R73 -> 19.752 | AK73: =V73 -> 14.588 | AW73: RFR (10-year yield) | AZ73: 0.0447 | BD73: Change Δ | BE73: =BE71/BE72-1 -> 0.75271246 | BF73: =IF(BE73>0,"Upside","Downside") -> Upside
B74: Other LT Assets | N74: 2.429 | O74: 2.199 | P74: =2.084 -> 2.084 | Q74: 2.083 | R74: 1.947 | S74: 1.615 | T74: 2.213 | U74: 1.963 | V74: 8.132 | W74: 7.944 | X74: 7.423 | AI74: =N74 -> 2.429 | AJ74: =R74 -> 1.947 | AK74: =V74 -> 8.132 | AW74: Equity β (1-year avg.) | AZ74: ='Notes | Quant Analysis'!S244 -> 2.9471353 | BD74: {=_xlfn.IFS(BE73>=25%,"Strong Buy",BE73>=10.00001%,"Buy",AND(BE73<=10%,BE73>=-4.9999%),"Hold",AND(BE73<=-5%,BE73>=-14.999999%),"Sell",BE73<=-15%,"Strong Sell")} -> Strong Buy
B75: Ttl Assets | N75: =SUM(N62:N74) -> 701.997 | O75: =SUM(O62:O74) -> 674.602 | P75: =SUM(P62:P74) -> 658.351 | Q75: =SUM(Q62:Q74) -> 630.764 | R75: =SUM(R62:R74) -> 633.796 | S75: =SUM(S62:S74) -> 658.386 | T75: =SUM(T62:T74) -> 696.425 | U75: =SUM(U62:U74) -> 1106.06 | ... X75: =SUM(X62:X74) -> 1430.964 | AI75: =N75 -> 701.997 | AJ75: =R75 -> 633.796 | AK75: =V75 -> 1145.686 | AW75: Market Return(1-year avg.) | AZ75: 0.075
AW76: Cost of Equity | AZ76: =(AZ73+AZ74)*(AZ75-AZ73) -> 0.090652609
B77: A/P | N77: 2.601 | O77: 3.131 | P77: 2.392 | Q77: 3.572 | R77: 2.604 | S77: 4.097 | T77: 11.053 | U77: 3.448 | V77: 10.612 | W77: 9.04 | X77: 10.355 | AI77: =N77 -> 2.601 | AJ77: =R77 -> 2.604 | AK77: =V77 -> 10.612
B78: ST Accrued Liabilities | N78: 44.779 | O78: 43.361 | P78: 56.839 | Q78: 43.67 | R78: 42.6 | S78: 28.823 | T78: 32.443 | U78: 28.652 | V78: 55.874 | W78: 58.539 | X78: 56.078 | AI78: =N78 -> 44.779 | AJ78: =R78 -> 42.6 | AK78: =V78 -> 55.874 | AW78: Cost of Debt
B79: Deferred Revenue | N79: 72.327 | O79: 63.646 | P79: 64.523 | Q79: 66.462 | R79: 82.275 | S79: 108.336 | T79: 148.006 | U79: 145.857 | V79: 220.572 | W79: 230.682 | X79: 281.215 | AI79: =N79 -> 72.327 | AJ79: =R79 -> 82.275 | AK79: =V79 -> 220.572 | AW79: Cost of Debt | AZ79: 0.005
B80: ST Compensation Liabilities | N80: 8.964 | O80: 8.068 | P80: 7.171 | Q80: 6.275 | R80: 5.378 | S80: 4.482 | T80: 3.586 | U80: 2.689 | V80: 1.793 | W80: 0.896 | X80: 0 | AI80: =N80 -> 8.964 | AJ80: =R80 -> 5.378 | AK80: =V80 -> 1.793 | AW80: Tax Rate | AZ80: 0.015
B81: ST Operating Lease Liabilities | N81: 7.978 | O81: 8.175 | P81: 8.755 | Q81: 9.105 | R81: 9.221 | S81: 8.816 | T81: 8.403 | U81: 7.943 | V81: 7.296 | W81: 3.392 | X81: 3.622 | AI81: =N81 -> 7.978 | AJ81: =R81 -> 9.221 | AK81: =V81 -> 7.296 | AW81: After Tax Cost of Debt | AZ81: =AZ79*(1-AZ80) -> 0.004925
B82: ST Public/Private Warrant Liabilities | N82: 0 | O82: 0 | P82: 0 | Q82: 0 | R82: 0 | S82: 0 | T82: 0 | U82: 0 | V82: 173.308 | W82: 0 | X82: 0 | AI82: =N82 -> 0 | AJ82: =R82 -> 0 | AK82: =V82 -> 173.308
B83: LT Deferred Revenues | N83: 5.293 | O83: 13.247 | P83: 11.969 | Q83: 11.23 | R83: 11.182 | S83: 29.676 | T83: 25.013 | U83: 48.332 | V83: 27.522 | W83: 16.24 | X83: 17.364 | AI83: =N83 -> 5.293 | AJ83: =R83 -> 11.182 | AK83: =V83 -> 27.522 | AW83: WACC | AZ83: =(AZ69*AZ76)+(AZ68*AZ81*(1-AZ80)) -> 0.084925827
B84: LT Deferred Hosting Costs | N84: 7.101 | O84: 9.261 | P84: 7.963 | Q84: 6.665 | R84: 5.368 | S84: 7.75 | T84: 6.512 | U84: 5.273 | V84: 4.034 | W84: 3.21 | X84: 1.885 | AI84: =N84 -> 7.101 | AJ84: =R84 -> 5.368 | AK84: =V84 -> 4.034
B85: LT Operating Lease Liabilites | N85: 16.952 | O85: 15.207 | P85: 15.218 | Q85: 13.819 | R85: 12.392 | S85: 10.806 | T85: 9.139 | U85: 7.209 | V85: 8.3 | W85: 37.074 | X85: 46.746 | AI85: =N85 -> 16.952 | AJ85: =R85 -> 12.392 | AK85: =V85 -> 8.3
B86: LT Convertible Notes | N86: 0 | O86: 0 | P86: 0 | Q86: 0 | R86: 0 | S86: 0 | T86: 0 | U86: 446.201 | V86: 446.884 | W86: 447.569 | X86: 448.255 | AI86: =N86 -> 0 | AJ86: =R86 -> 0 | AK86: =V86 -> 446.884 | AL86: =AK86+AL45 -> 444.64958 | AM86: =AL86+AM45 -> 442.42633 | AN86: =AM86+AN45 -> 440.2142 | AO86: =AN86+AO45 -> 438.01313 | AP86: =AO86+AP45 -> 435.82306 | AQ86: =AP86+AQ45 -> 433.64395 | AR86: =AQ86+AR45 -> 431.47573 | AS86: =AR86+AS45 -> 429.31835 | ... AU86: =AT86+AU45 -> 425.0359
B87: Other LT Liabilities | N87: 17.984 | O87: 10.183 | P87: 10.274 | Q87: 5.361 | R87: 21.49 | S87: 10.802 | T87: 16.581 | U87: =56.82+3.601+0.477 -> 60.898 | V87: 1.06 | W87: 1.085 | X87: 1.093 | AI87: =N87 -> 17.984 | AJ87: =R87 -> 21.49 | AK87: =V87 -> 1.06
B88: Ttl Liabilities | N88: =SUM(N77:N87) -> 183.979 | O88: =SUM(O77:O87) -> 174.279 | P88: =SUM(P77:P87) -> 185.104 | Q88: =SUM(Q77:Q87) -> 166.159 | R88: =SUM(R77:R87) -> 192.51 | S88: =SUM(S77:S87) -> 213.588 | T88: =SUM(T77:T87) -> 260.736 | U88: =SUM(U77:U87) -> 756.502 | ... X88: =SUM(X77:X87) -> 866.613 | AI88: =N88 -> 183.979 | AJ88: =R88 -> 192.51 | AK88: =V88 -> 957.255
B89: Ttl SE | N89: 518.018 | O89: 500.325 | P89: 473.247 | Q89: 464.605 | R89: 441.286 | S89: 444.802 | T89: 435.689 | U89: 349.558 | V89: 188.431 | W89: 443.704 | X89: 564.351 | AI89: =N89 -> 518.018 | AJ89: =R89 -> 441.286 | AK89: =V89 -> 188.431
B90: Ttl L + SE | N90: =N88+N89 -> 701.997 | O90: =O88+O89 -> 674.604 | P90: =P88+P89 -> 658.351 | Q90: =Q88+Q89 -> 630.764 | R90: =R88+R89 -> 633.796 | S90: =S88+S89 -> 658.39 | T90: =T88+T89 -> 696.425 | U90: =U88+U89 -> 1106.06 | ... X90: =X88+X89 -> 1430.964 | AI90: =N90 -> 701.997 | AJ90: =R90 -> 633.796 | AK90: =V90 -> 1145.686
B92: Current Ratio | N92: =SUM(N62:N67)/SUM(N77:N82) -> 2.7087721 | O92: =SUM(O62:O67)/SUM(O77:O82) -> 2.7374051 | P92: =SUM(P62:P67)/SUM(P77:P82) -> 2.3392468 | Q92: =SUM(Q62:Q67)/SUM(Q77:Q82) -> 2.3364166 | R92: =SUM(R62:R67)/SUM(R77:R82) -> 2.1271766 | S92: =SUM(S62:S67)/SUM(S77:S82) -> 2.1016085 | T92: =SUM(T62:T67)/SUM(T77:T82) -> 1.7468242 | U92: =SUM(U62:U67)/SUM(U77:U82) -> 3.9988706 | ... X92: =SUM(X62:X67)/SUM(X77:X82) -> 2.8433683 | AI92: =SUM(AI62:AI67)/SUM(AI77:AI82) -> 2.7087721 | AJ92: =SUM(AJ62:AJ67)/SUM(AJ77:AJ82) -> 2.1271766 | AK92: =SUM(AK62:AK67)/SUM(AK77:AK82) -> 1.6516216
B93: Quick Ratio | N93: =(SUM(N62:N67)-N66)/SUM(N77:N82) -> 2.7087721 | O93: =(SUM(O62:O67)-O66)/SUM(O77:O82) -> 2.7374051 | P93: =(SUM(P62:P67)-P66)/SUM(P77:P82) -> 2.3392468 | Q93: =(SUM(Q62:Q67)-Q66)/SUM(Q77:Q82) -> 2.3364166 | R93: =(SUM(R62:R67)-R66)/SUM(R77:R82) -> 2.1271766 | S93: =(SUM(S62:S67)-S66)/SUM(S77:S82) -> 2.1016085 | T93: =(SUM(T62:T67)-T66)/SUM(T77:T82) -> 1.7468242 | U93: =(SUM(U62:U67)-U66)/SUM(U77:U82) -> 3.9988706 | ... X93: =(SUM(X62:X67)-X66)/SUM(X77:X82) -> 2.8181684 | AI93: =(SUM(AI62:AI67)-AI66)/SUM(AI77:AI82) -> 2.7087721 | AJ93: =(SUM(AJ62:AJ67)-AJ66)/SUM(AJ77:AJ82) -> 2.1271766 | AK93: =(SUM(AK62:AK67)-AK66)/SUM(AK77:AK82) -> 1.6385894
B94: Cash Ratio | N94: =(N64+N62)/SUM(N77:N82) -> 2.1874072 | O94: =(O64+O62)/SUM(O77:O82) -> 2.1805889 | P94: =(P64+P62)/SUM(P77:P82) -> 1.7854381 | Q94: =(Q64+Q62)/SUM(Q77:Q82) -> 1.8764835 | R94: =(R64+R62)/SUM(R77:R82) -> 1.5630499 | S94: =(S64+S62)/SUM(S77:S82) -> 1.4628868 | T94: =(T64+T62)/SUM(T77:T82) -> 1.3343932 | U94: =(U64+U62)/SUM(U77:U82) -> 3.591535 | ... X94: =(X64+X62)/SUM(X77:X82) -> 2.4636832 | AI94: =(AI64+AI62)/SUM(AI77:AI82) -> 2.1874072 | AJ94: =(AJ64+AJ62)/SUM(AJ77:AJ82) -> 1.5630499 | AK94: =(AK64+AK62)/SUM(AK77:AK82) -> 1.3634747
B95: Fixed Asset Turnover Ratio | N95: =N37/SUM(N68:N69) -> 0.4587156 | O95: =O37/SUM(O68:O69) -> 0.47408245 | P95: =P37/SUM(P68:P69) -> 0.4680235 | Q95: =Q37/SUM(Q68:Q69) -> 0.4534728 | R95: =R37/SUM(R68:R69) -> 0.43773939 | S95: =S37/SUM(S68:S69) -> 0.46606119 | T95: =T37/SUM(T68:T69) -> 0.48335583 | U95: =U37/SUM(U68:U69) -> 0.48932866 | ... X95: =X37/SUM(X68:X69) -> 0.58570412 | AI95: =AI37/SUM(AI68:AI69) -> 1.9033971 | AJ95: =AJ37/SUM(AJ68:AJ69) -> 1.7786716 | AK95: =AK37/SUM(AK68:AK69) -> 1.7890356
B96: Ttl Asset Turnover Ratio | N96: =N37/N75 -> 0.083903492 | O96: =O37/O75 -> 0.089534274 | P96: =P37/P75 -> 0.092807636 | Q96: =Q37/Q75 -> 0.097183733 | R96: =R37/R75 -> 0.097192156 | S96: =S37/S75 -> 0.1007008 | T96: =T37/T75 -> 0.10539541 | U96: =U37/U75 -> 0.07350415 | ... X96: =X37/X75 -> 0.081100573 | AI96: =AI37/AI75 -> 0.34814964 | AJ96: =AJ37/AJ75 -> 0.39492203 | AK96: =AK37/AK75 -> 0.26866
B97: Inventory Turnover Ratio | N97: =N38/AVERAGE(K66:N66) -> #DIV/0! | O97: =O38/AVERAGE(L66:O66) -> #DIV/0! | P97: =P38/AVERAGE(M66:P66) -> #DIV/0! | Q97: =Q38/AVERAGE(N66:Q66) -> #DIV/0! | R97: =R38/AVERAGE(O66:R66) -> #DIV/0! | S97: =S38/AVERAGE(P66:S66) -> #DIV/0! | T97: =T38/AVERAGE(Q66:T66) -> #DIV/0! | U97: =U38/AVERAGE(R66:U66) -> #DIV/0! | ... X97: =X38/AVERAGE(U66:X66) -> 8.2951507 | AI97: =AI38/AVERAGE(AF66:AI66) -> #DIV/0! | AJ97: =AJ38/AVERAGE(AG66:AJ66) -> #DIV/0! | AK97: =AK38/AVERAGE(AH66:AK66) -> 66.31677
B98: Return on Assets | N98: =N50/N75 -> -0.042789357 | O98: =O50/O75 -> -0.043481935 | P98: =P50/P75 -> -0.058722475 | Q98: =Q50/Q75 -> -0.031782093 | R98: =R50/R75 -> -0.055393218 | S98: =S50/S75 -> -0.019127077 | T98: =T50/T75 -> -0.032419859 | U98: =U50/U75 -> -0.053465454 | ... X98: =X50/X75 -> -0.0065361533 | AI98: =AI50/AI75 -> -0.17542525 | AJ98: =AJ50/AJ75 -> -0.16788998 | AK98: =AK50/AK75 -> -0.21540544
B99: Return on Equity | N99: =N50/N89 -> -0.057986402 | O99: =O50/O89 -> -0.058627892 | P99: =P50/P89 -> -0.081690956 | Q99: =Q50/Q89 -> -0.043148481 | R99: =R50/R89 -> -0.079558382 | S99: =S50/S89 -> -0.028311473 | T99: =T50/T89 -> -0.051821368 | U99: =U50/U89 -> -0.16917364 | ... X99: =X50/X89 -> -0.016573019 | AI99: =AI50/AI89 -> -0.23772919 | AJ99: =AJ50/AJ89 -> -0.2411316 | AK99: =AK50/AK89 -> -1.3096943
B101: CFFO | C101: -29.3 | D101: -20.4 | E101: -41.5 | F101: -46 | G101: -44.4 | H101: -39.5 | I101: -40.2 | J101: -37.8 | K101: -34.4 | L101: -38 | M101: -38 | N101: -30.1 | O101: -29.3 | P101: -38.7 | Q101: -20.1 | R101: -35.2 | S101: -12.6 | T101: -22.6 | U101: -59.2 | V101: -152.5 | W101: -138.9 | X101: -138.9 | AF101: =SUM(C101:F101) -> -137.2 | AG101: =SUM(G101:J101) -> -161.9 | AH101: =SUM(K101:N101) -> -140.5 | AI101: =SUM(O101:R101) -> -123.3 | AJ101: =SUM(P101:S101) -> -106.6 | AK101: =SUM(S101:V101) -> -246.9
B102: CapEx, net | C102: -2.6 | D102: -3.3 | E102: -2.8 | F102: -6.2 | G102: -3.5 | H102: -4.3 | I102: -3 | J102: -2 | K102: -7.1 | L102: -16.6 | M102: -8.6 | N102: -10.1 | O102: -11.4 | P102: -16.6 | Q102: -8.9 | R102: -12.8 | S102: -9.3 | T102: -21.5 | U102: -27.7 | V102: -23 | W102: -18 | X102: -18 | AF102: =SUM(C102:F102) -> -14.9 | AG102: =SUM(G102:J102) -> -12.8 | AH102: =SUM(K102:N102) -> -42.4 | AI102: =SUM(O102:R102) -> -49.7 | AJ102: =SUM(P102:S102) -> -47.6 | AK102: =SUM(S102:V102) -> -81.5
B103: FCF | C103: =C101+C102 -> -31.9 | D103: =D101+D102 -> -23.7 | E103: =E101+E102 -> -44.3 | F103: =F101+F102 -> -52.2 | G103: =G101+G102 -> -47.9 | H103: =H101+H102 -> -43.8 | I103: =I101+I102 -> -43.2 | J103: =J101+J102 -> -39.8 | ... X103: =X101+X102 -> -156.9 | AF103: =SUM(C103:F103) -> -152.1 | AG103: =SUM(G103:J103) -> -174.7 | AH103: =SUM(K103:N103) -> -182.9 | AI103: =SUM(O103:R103) -> -173 | AJ103: =SUM(P103:S103) -> -154.2 | AK103: =SUM(S103:V103) -> -328.4
B104: SC | C104: =C51 -> 45.722 | D104: =D51 -> 46.2 | E104: =E51 -> 47.137 | F104: =F51 -> 79.61 | G104: =G51 -> 264.088 | H104: =H51 -> 266.212 | I104: =I51 -> 267.947 | J104: =J51 -> 267.126 | ... X104: =X51 -> 359.59 | AF104: =AF51 -> 54.66725 | AG104: =AG51 -> 266.34325 | AH104: =AH51 -> 274.68075 | AI104: =AI51 -> 291.0235 | AJ104: =AJ51 -> 294.02325 | AK104: =AK51 -> 305.36075
B105: FCF per Share | C105: =C103/C104 -> -0.69769476 | D105: =D103/D104 -> -0.51298701 | E105: =E103/E104 -> -0.93981373 | F105: =F103/F104 -> -0.65569652 | G105: =G103/G104 -> -0.18137893 | H105: =H103/H104 -> -0.16453052 | I105: =I103/I104 -> -0.16122591 | J105: =J103/J104 -> -0.14899336 | ... X105: =X103/X104 -> -0.43633027 | AF105: =SUM(C105:F105) -> -2.806192 | AG105: =SUM(G105:J105) -> -0.65612873 | AH105: =SUM(K105:N105) -> -0.66534788 | AI105: =SUM(O105:R105) -> -0.59481452 | AJ105: =SUM(P105:S105) -> -0.52656154 | AK105: =SUM(S105:V105) -> -1.0691209
B107: FCF Margin | C107: =C103/C37 -> -0.996875 | D107: =D103/D37 -> -0.77960526 | E107: =E103/E37 -> -1.3974763 | F107: =F103/F37 -> -1.4070081 | G107: =G103/G37 -> -1.1945137 | H107: =H103/H37 -> -0.90495868 | I107: =I103/I37 -> -0.86921529 | J107: =J103/J37 -> -0.7509434 | ... X107: =X103/X37 -> -1.3519801 | AF107: =AF103/AF37 -> -1.1592988 | AG107: =AG103/AG37 -> -0.91370293 | AH107: =AH103/AH37 -> -0.82835145 | AI107: =AI103/AI37 -> -0.70785597 | AJ107: =AJ103/AJ37 -> -0.61606073 | AK107: =AK103/AK37 -> -1.0669266
B108: CapEx as % of Revenue | C108: =-C102/C37 -> 0.08125 | D108: =-D102/D37 -> 0.10855263 | E108: =-E102/E37 -> 0.088328076 | F108: =-F102/F37 -> 0.1671159 | G108: =-G102/G37 -> 0.087281796 | H108: =-H102/H37 -> 0.088842975 | I108: =-I102/I37 -> 0.060362173 | J108: =-J102/J37 -> 0.037735849 | ... X108: =-X102/X37 -> 0.15510288 | AF108: =-AF102/AF37 -> 0.11356707 | AG108: =-AG102/AG37 -> 0.066945607 | AH108: =-AH102/AH37 -> 0.19202899 | AI108: =-AI102/AI37 -> 0.20335516 | AJ108: =-AJ102/AJ37 -> 0.19017179 | AK108: =-AK102/AK37 -> 0.26478233

Sheet Notes | Quant Analysis
CI1: 0
P2: Employee Scope: | AL2: General Notes/Observations (Updated Q1'26)
Q29: Notes: | R29: [X]
R30: [Y]
R31: [Z]
AL32: Financial Stmts. Notes/Observations (Updated Q1'26)
P33: Institutional Ownership Snapshot Q1'26 | AL33: Revenues:
Q62: Notes: | R62: As of Q1'26 Google is a majority shareholder, owning 11% of The Company's outstanding equity
R63: [Y]
R64: [Z]
P66: Revenue Breakdown by Segment | AL66: Earnings Scope:
Q98: Notes: | R98: [X]
R99: [Y]
R100: [Z]
P102: Revenue Breakdown by Segment | AL102: Balance Sheet Scope:
Q134: Notes: | R134: [X]
R135: [Y] | AL135: [Equity Preformance Compared to Peers]
R136: [Z]
P138: Q/q Total Revenues, Net Income, FCF
Q167: Notes: | R167: [X]
R168: [Y]
R169: [Z]
P171: Y/y Total Revenues, Net Income, FCF
Q200: Notes: | R200: [X]
R201: [Y]
R202: [Z]
A217: VOO Historical Returns | I217: PL Historical Returns
A218: 1003 Trading Days (From: 6/22/22 - 6/22/62) | I218: 1003 Trading Days (From: 6/22/22 - 6/22/62)
A219: Close | B219: High | C219: Low | D219: Open | E219: Volume | F219: UTC Date | G219: Change | I219: Close | J219: High | K219: Low | L219: Open | M219: Volume | N219: UTC Date | O219: Change
A220: 686.1 | B220: 691.5 | C220: 685 | D220: 689.17 | E220: 13326373 | F220: Mon, 22 Jun 2026 00:00:00 GMT | G220: =A220/D220-1 -> -0.0044546338 | I220: 28.77 | J220: 29.135 | K220: 26.71 | L220: 27.96 | M220: 15178414 | N220: Mon, 22 Jun 2026 00:00:00 GMT | O220: =I220/L220-1 -> 0.028969957
A221: 688.11 | B221: 689.7 | C221: 685.7 | D221: 689.3 | E221: 17717272 | F221: Thu, 18 Jun 2026 00:00:00 GMT | G221: =A221/D221-1 -> -0.0017263891 | I221: 28.23 | J221: 29 | K221: 26.33 | L221: 28.65 | M221: 17151428 | N221: Thu, 18 Jun 2026 00:00:00 GMT | O221: =I221/L221-1 -> -0.014659686
A222: 681.41 | B222: 691.53 | C222: 679.64 | D222: 690.76 | E222: 14960955 | F222: Wed, 17 Jun 2026 00:00:00 GMT | G222: =A222/D222-1 -> -0.013535816 | I222: 28.22 | J222: 29.35 | K222: 28.08 | L222: 28.39 | M222: 10639760 | N222: Wed, 17 Jun 2026 00:00:00 GMT | O222: =I222/L222-1 -> -0.005988024
A223: 689.75 | B223: 694.57 | C223: 689.44 | D223: 693.83 | E223: 13283627 | F223: Tue, 16 Jun 2026 00:00:00 GMT | G223: =A223/D223-1 -> -0.005880403 | I223: 28.21 | J223: 31.25 | K223: 27.0442 | L223: 30.02 | M223: 23141671 | N223: Tue, 16 Jun 2026 00:00:00 GMT | O223: =I223/L223-1 -> -0.060293138
A224: 693.83 | B224: 695.75 | C224: 691.26 | D224: 691.3 | E224: 14017150 | F224: Mon, 15 Jun 2026 00:00:00 GMT | G224: =A224/D224-1 -> 0.0036597714 | I224: 30.58 | J224: 32.14 | K224: 30.11 | L224: 32.08 | M224: 14745534 | N224: Mon, 15 Jun 2026 00:00:00 GMT | O224: =I224/L224-1 -> -0.046758105
A225: 681.95 | B225: 684.4387 | C225: 675.81 | D225: 681.075 | E225: 6296298.6 | F225: Fri, 12 Jun 2026 00:00:00 GMT | G225: =A225/D225-1 -> 0.0012847337 | I225: 31.15 | J225: 34.15 | K225: 29.77 | L225: 33.89 | M225: 19504823 | N225: Fri, 12 Jun 2026 00:00:00 GMT | O225: =I225/L225-1 -> -0.080849808
A226: 678.23 | B226: 680.38 | C226: 666 | D226: 670.1 | E226: 19868903 | F226: Thu, 11 Jun 2026 00:00:00 GMT | G226: =A226/D226-1 -> 0.012132518 | I226: 34.17 | J226: 34.32 | K226: 30.42 | L226: 31.5 | M226: 15976294 | N226: Thu, 11 Jun 2026 00:00:00 GMT | O226: =I226/L226-1 -> 0.084761905
A227: 667.05 | B227: 678.875 | C227: 666.88 | D227: 674.315 | E227: 16308606 | F227: Wed, 10 Jun 2026 00:00:00 GMT | G227: =A227/D227-1 -> -0.010773896 | I227: 30.72 | J227: 31.8 | K227: 30.2 | L227: 30.89 | M227: 11044013 | N227: Wed, 10 Jun 2026 00:00:00 GMT | O227: =I227/L227-1 -> -0.0055033992
A228: 677.7 | B228: 686.76 | C228: 664.3201 | D228: 683.71 | E228: 13784137 | F228: Tue, 09 Jun 2026 00:00:00 GMT | G228: =A228/D228-1 -> -0.0087902766 | I228: 31.17 | J228: 34.37 | K228: 29.32 | L228: 33.42 | M228: 22105339 | N228: Tue, 09 Jun 2026 00:00:00 GMT | O228: =I228/L228-1 -> -0.067324955
A229: 679.68 | B229: 685.29 | C229: 678.7 | D229: 683.47 | E229: 8744745.5 | F229: Mon, 08 Jun 2026 00:00:00 GMT | G229: =A229/D229-1 -> -0.0055452324 | I229: 32.74 | J229: 34.04 | K229: 31.33 | L229: 34.01 | M229: 20005204 | N229: Mon, 08 Jun 2026 00:00:00 GMT | O229: =I229/L229-1 -> -0.037341958
A230: 678 | B230: 692.18 | C230: 676.25 | D230: 691.71 | E230: 10689226 | F230: Fri, 05 Jun 2026 00:00:00 GMT | G230: =A230/D230-1 -> -0.019820445 | I230: 32.22 | J230: 39.18 | K230: 31.66 | L230: 38.3 | M230: 40356016 | N230: Fri, 05 Jun 2026 00:00:00 GMT | O230: =I230/L230-1 -> -0.15874674
A231: 696.06 | B231: 697.2 | C231: 690.9 | D231: 691.49 | E231: 6574889.5 | F231: Thu, 04 Jun 2026 00:00:00 GMT | G231: =A231/D231-1 -> 0.006608917 | I231: 43.53 | J231: 45.165 | K231: 41.3 | L231: 43.23 | M231: 17737570 | N231: Thu, 04 Jun 2026 00:00:00 GMT | O231: =I231/L231-1 -> 0.0069396253
... A237: 689.96 | B237: 690.78 | C237: 687.92 | D237: 690.36 | E237: 7335366 | F237: Wed, 27 May 2026 00:00:00 GMT | G237: =A237/D237-1 -> -0.00057940785 | I237: 50.48 | J237: 50.98 | K237: 47.11 | L237: 50.1 | M237: 15352438 | N237: Wed, 27 May 2026 00:00:00 GMT | O237: =I237/L237-1 -> 0.0075848303
A238: 690.01 | B238: 691.5105 | C238: 688.08 | D238: 689.65 | E238: 6602813 | F238: Tue, 26 May 2026 00:00:00 GMT | G238: =A238/D238-1 -> 0.00052200392 | I238: 48.32 | J238: 51.13 | K238: 45.86 | L238: 47.695 | M238: 16813953 | N238: Tue, 26 May 2026 00:00:00 GMT | O238: =I238/L238-1 -> 0.013104099 | R238: Min | S238: =MIN(O220:O1222) -> -0.20179372
A239: 685.55 | B239: 688.58 | C239: 684.4799 | D239: 686.1 | E239: 4263727.4 | F239: Fri, 22 May 2026 00:00:00 GMT | G239: =A239/D239-1 -> -0.00080163242 | I239: 44.35 | J239: 45.2658 | K239: 43.1001 | L239: 43.35 | M239: 9761458 | N239: Fri, 22 May 2026 00:00:00 GMT | O239: =I239/L239-1 -> 0.023068051 | R239: Max | S239: =MAX(O220:O1222) -> 0.25373134
A240: 682.84 | B240: 684.825 | C240: 677.62 | D240: 679.08 | E240: 7288934.5 | F240: Thu, 21 May 2026 00:00:00 GMT | G240: =A240/D240-1 -> 0.0055369029 | I240: 42.48 | J240: 44 | K240: 41.04 | L240: 42.066 | M240: 7143277.4 | N240: Thu, 21 May 2026 00:00:00 GMT | O240: =I240/L240-1 -> 0.0098416774 | R240: Mean μ | S240: =AVERAGE(O220:O1222) -> 5.4308195e-06
A241: 681.57 | B241: 682 | C241: 674.7401 | D241: 676.32 | E241: 5437520.5 | F241: Wed, 20 May 2026 00:00:00 GMT | G241: =A241/D241-1 -> 0.0077625976 | I241: 42.66 | J241: 43.55 | K241: 40.67 | L241: 42.4 | M241: 8080839.1 | N241: Wed, 20 May 2026 00:00:00 GMT | O241: =I241/L241-1 -> 0.0061320755 | R241: Median | S241: =MEDIAN(O220:O1222) -> -0.00075949367
A242: 674.59 | B242: 678.15 | C242: 672.55 | D242: 675.56 | E242: 5595102.2 | F242: Tue, 19 May 2026 00:00:00 GMT | G242: =A242/D242-1 -> -0.0014358458 | I242: 41.59 | J242: 41.75 | K242: 38.02 | L242: 40.93 | M242: 8748798.8 | N242: Tue, 19 May 2026 00:00:00 GMT | O242: =I242/L242-1 -> 0.016125092 | R242: SD σ | S242: =_xlfn.STDEV.P(O220:O1222) -> 0.04272725
A243: 678.91 | B243: 681.61 | C243: 674.25 | D243: 680.18 | E243: 7548004.3 | F243: Mon, 18 May 2026 00:00:00 GMT | G243: =A243/D243-1 -> -0.0018671528 | I243: 41.61 | J243: 45.78 | K243: 40.26 | L243: 43.28 | M243: 11396073 | N243: Mon, 18 May 2026 00:00:00 GMT | O243: =I243/L243-1 -> -0.038585952 | R243: 3σ 1-Day Δ: ± | S243: =3*S242 -> 0.12818175 | U243: <- Sharpe Ratio (Risk Adjusted Return)
A244: 679.44 | B244: 683.52 | C244: 678.441 | D244: 682.04 | E244: 6403309.8 | F244: Fri, 15 May 2026 00:00:00 GMT | G244: =A244/D244-1 -> -0.0038120931 | I244: 41.62 | J244: 43.18 | K244: 40.54 | L244: 42.07 | M244: 8732818.7 | N244: Fri, 15 May 2026 00:00:00 GMT | O244: =I244/L244-1 -> -0.010696458 | R244: β (1-year avg.) | S244: =_xlfn.COVARIANCE.P(O220:O468,G220:G468)/_xlfn.VAR.P(G220:G468) -> 2.9471353 | U244: <- Sortino Ratio (Downside Risk Adjusted Return)
A245: 687.73 | B245: 689.1 | C245: 683.66 | D245: 683.74 | E245: 5337833.8 | F245: Thu, 14 May 2026 00:00:00 GMT | G245: =A245/D245-1 -> 0.0058355515 | I245: 43.04 | J245: 43.45 | K245: 39.6003 | L245: 40.63 | M245: 7970064.7 | N245: Thu, 14 May 2026 00:00:00 GMT | O245: =I245/L245-1 -> 0.059315777
A246: 682.41 | B246: 683.91 | C246: 676.2 | D246: 678.9 | E246: 4882510.4 | F246: Wed, 13 May 2026 00:00:00 GMT | G246: =A246/D246-1 -> 0.0051701281 | I246: 40.74 | J246: 42.2 | K246: 38.85 | L246: 42.18 | M246: 8620143.6 | N246: Wed, 13 May 2026 00:00:00 GMT | O246: =I246/L246-1 -> -0.034139403 | Q246: n = | R246: 1014
A247: 678.67 | B247: 679.26 | C247: 672.8 | D247: 677.47 | E247: 6020032.1 | F247: Tue, 12 May 2026 00:00:00 GMT | G247: =A247/D247-1 -> 0.0017712961 | I247: 40.68 | J247: 41.88 | K247: 38.26 | L247: 40.09 | M247: 8897065.7 | N247: Tue, 12 May 2026 00:00:00 GMT | O247: =I247/L247-1 -> 0.014716887 | Q247: Histogram Data | T247: Distribution Overlay | X247: SD Lines
A248: 679.52 | B248: 681.06 | C248: 677.08 | D248: 677.08 | E248: 5660494.5 | F248: Mon, 11 May 2026 00:00:00 GMT | G248: =A248/D248-1 -> 0.00360371 | I248: 41.84 | J248: 43.12 | K248: 38.1 | L248: 38.65 | M248: 12107823 | N248: Mon, 11 May 2026 00:00:00 GMT | O248: =I248/L248-1 -> 0.082535576 | Q248: Bin | R248: Frequency | T248: (X) 1-Day Δ | U248: (Y) Pop. Density | X248: X | Y248: Y
A249: 678.04 | B249: 678.53 | C249: 675.37 | D249: 675.7 | E249: 4309792.4 | F249: Fri, 08 May 2026 00:00:00 GMT | G249: =A249/D249-1 -> 0.0034630753 | I249: 39.04 | J249: 39.85 | K249: 35.8 | L249: 36.4 | M249: 12836829 | N249: Fri, 08 May 2026 00:00:00 GMT | O249: =I249/L249-1 -> 0.072527473 | Q249: -0.135 | R249: 5 | T249: =T250-0.0025 -> -0.145 | U249: =_xlfn.NORM.DIST(T249,$S$240,$S$242,FALSE) -> 0.029458411 | W249: Mean | X249: =S240 -> 5.4308195e-06 | Y249: 0
A250: 672.54 | B250: 676.7601 | C250: 670.92 | D250: 675.82 | E250: 6049366.8 | F250: Thu, 07 May 2026 00:00:00 GMT | G250: =A250/D250-1 -> -0.0048533633 | I250: 35.24 | J250: 40.92 | K250: 34.93 | L250: 39.52 | M250: 10367449 | N250: Thu, 07 May 2026 00:00:00 GMT | O250: =I250/L250-1 -> -0.1082996 | Q250: -0.1325 | R250: 1 | T250: =T251-0.0025 -> -0.1425 | U250: =_xlfn.NORM.DIST(T250,$S$240,$S$242,FALSE) -> 0.035867732 | X250: =S240 -> 5.4308195e-06 | Y250: 9.5
A251: 674.66 | B251: 675.34 | C251: 669.15 | D251: 669.45 | E251: 6397545.8 | F251: Wed, 06 May 2026 00:00:00 GMT | G251: =A251/D251-1 -> 0.007782508 | I251: 39.69 | J251: 39.76 | K251: 35.51 | L251: 36.995 | M251: 7469800.8 | N251: Wed, 06 May 2026 00:00:00 GMT | O251: =I251/L251-1 -> 0.072847682 | Q251: -0.13 | R251: 0 | T251: =T252-0.0025 -> -0.14 | U251: =_xlfn.NORM.DIST(T251,$S$240,$S$242,FALSE) -> 0.043522287 | W251: -3σ | X251: =($S$242*-3)+$S$240 -> -0.12817632 | Y251: 0
A252: 665.3 | B252: 666.55 | C252: 663.33 | D252: 663.58 | E252: 4947610.8 | F252: Tue, 05 May 2026 00:00:00 GMT | G252: =A252/D252-1 -> 0.002592001 | I252: 37.13 | J252: 39.43 | K252: 35.95 | L252: 39.2 | M252: 8276453.6 | N252: Tue, 05 May 2026 00:00:00 GMT | O252: =I252/L252-1 -> -0.052806122 | Q252: -0.1275 | R252: 0 | T252: =T253-0.0025 -> -0.1375 | U252: =_xlfn.NORM.DIST(T252,$S$240,$S$242,FALSE) -> 0.052629918 | X252: =($S$242*-3)+$S$240 -> -0.12817632 | Y252: 1
A253: 660.12 | B253: 663.85 | C253: 657.39 | D253: 661.99 | E253: 5927455.9 | F253: Mon, 04 May 2026 00:00:00 GMT | G253: =A253/D253-1 -> -0.0028248161 | I253: 38.54 | J253: 39.27 | K253: 35.82 | L253: 37.04 | M253: 8478269.9 | N253: Mon, 04 May 2026 00:00:00 GMT | O253: =I253/L253-1 -> 0.04049676 | Q253: -0.125 | R253: 2 | T253: =T254-0.0025 -> -0.135 | U253: =_xlfn.NORM.DIST(T253,$S$240,$S$242,FALSE) -> 0.063425935 | W253: -2σ | X253: =($S$242*-2)+$S$240 -> -0.08544907 | Y253: 0
A254: 662.52 | B254: 666.415 | C254: 662.38 | D254: 663.09 | E254: 4934232.2 | F254: Fri, 01 May 2026 00:00:00 GMT | G254: =A254/D254-1 -> -0.00085961182 | I254: 36.9 | J254: 37.285 | K254: 34.8406 | L254: 36.745 | M254: 8967098.5 | N254: Fri, 01 May 2026 00:00:00 GMT | O254: =I254/L254-1 -> 0.004218261 | Q254: -0.1225 | R254: 0 | T254: =T255-0.0025 -> -0.1325 | U254: =_xlfn.NORM.DIST(T254,$S$240,$S$242,FALSE) -> 0.076175314 | X254: =($S$242*-2)+$S$240 -> -0.08544907 | Y254: 2
A255: 660.58 | B255: 661.77 | C255: 653.145 | D255: 657 | E255: 5902689.6 | F255: Thu, 30 Apr 2026 00:00:00 GMT | G255: =A255/D255-1 -> 0.0054490107 | I255: 36.97 | J255: 36.97 | K255: 34.3067 | L255: 34.53 | M255: 8013392 | N255: Thu, 30 Apr 2026 00:00:00 GMT | O255: =I255/L255-1 -> 0.070663191 | Q255: -0.12 | R255: 0 | T255: =T256-0.0025 -> -0.13 | U255: =_xlfn.NORM.DIST(T255,$S$240,$S$242,FALSE) -> 0.091174801 | W255: -1σ | X255: =($S$242*-1)+$S$240 -> -0.042721819 | Y255: 0
A256: 654.24 | B256: 654.7237 | C256: 651.26 | D256: 653.62 | E256: 6203101.4 | F256: Wed, 29 Apr 2026 00:00:00 GMT | G256: =A256/D256-1 -> 0.00094856339 | I256: 34.08 | J256: 35 | K256: 32.57 | L256: 34.38 | M256: 6836085.1 | N256: Wed, 29 Apr 2026 00:00:00 GMT | O256: =I256/L256-1 -> -0.0087260035 | Q256: -0.1175 | R256: 1 | T256: =T257-0.0025 -> -0.1275 | U256: =_xlfn.NORM.DIST(T256,$S$240,$S$242,FALSE) -> 0.10875484 | X256: =($S$242*-1)+$S$240 -> -0.042721819 | Y256: 5.5
A257: 654.26 | B257: 655.39 | C257: 652.01 | D257: 654.41 | E257: 5509669.8 | F257: Tue, 28 Apr 2026 00:00:00 GMT | G257: =A257/D257-1 -> -0.0002292141 | I257: 35.03 | J257: 35.305 | K257: 33.734 | L257: 34.6 | M257: 6065920.4 | N257: Tue, 28 Apr 2026 00:00:00 GMT | O257: =I257/L257-1 -> 0.012427746 | Q257: -0.115 | R257: 0 | T257: =T258-0.0025 -> -0.125 | U257: =_xlfn.NORM.DIST(T257,$S$240,$S$242,FALSE) -> 0.12928125 | W257: 1σ | X257: =($S$242*1)+$S$240 -> 0.042732681 | Y257: 0
A258: 657.5 | B258: 657.9 | C258: 654.84 | D258: 655.67 | E258: 5282297.3 | F258: Mon, 27 Apr 2026 00:00:00 GMT | G258: =A258/D258-1 -> 0.0027910382 | I258: 35.45 | J258: 36.23 | K258: 33.63 | L258: 35.47 | M258: 7716352.4 | N258: Mon, 27 Apr 2026 00:00:00 GMT | O258: =I258/L258-1 -> -0.00056385678 | Q258: -0.1125 | R258: 0 | T258: =T259-0.0025 -> -0.1225 | U258: =_xlfn.NORM.DIST(T258,$S$240,$S$242,FALSE) -> 0.15315659 | X258: =($S$242*1)+$S$240 -> 0.042732681 | Y258: 5.5
A259: 656.42 | B259: 656.82 | C259: 651.8202 | D259: 653.4 | E259: 4722997.4 | F259: Fri, 24 Apr 2026 00:00:00 GMT | G259: =A259/D259-1 -> 0.0046219773 | I259: 35.44 | J259: 39.5 | K259: 35.13 | L259: 39.11 | M259: 10407668 | N259: Fri, 24 Apr 2026 00:00:00 GMT | O259: =I259/L259-1 -> -0.093837893 | Q259: -0.11 | R259: 2 | T259: =T260-0.0025 -> -0.12 | U259: =_xlfn.NORM.DIST(T259,$S$240,$S$242,FALSE) -> 0.18082107 | W259: 2σ | X259: =($S$242*2)+$S$240 -> 0.085459931 | Y259: 0
A260: 651.26 | B260: 654.9 | C260: 645.66 | D260: 652.23 | E260: 6016793.5 | F260: Thu, 23 Apr 2026 00:00:00 GMT | G260: =A260/D260-1 -> -0.0014872054 | I260: 38.29 | J260: 40 | K260: 36.33 | L260: 39.33 | M260: 11884235 | N260: Thu, 23 Apr 2026 00:00:00 GMT | O260: =I260/L260-1 -> -0.026442919 | Q260: -0.1075 | R260: 1 | T260: =T261-0.0025 -> -0.1175 | U260: =_xlfn.NORM.DIST(T260,$S$240,$S$242,FALSE) -> 0.21275294 | X260: =($S$242*2)+$S$240 -> 0.085459931 | Y260: 2
A261: 653.9 | B261: 654.19 | C261: 651.09 | D261: 651.98 | E261: 4491871.3 | F261: Wed, 22 Apr 2026 00:00:00 GMT | G261: =A261/D261-1 -> 0.0029448756 | I261: 39.47 | J261: 41.71 | K261: 38.28 | L261: 39.5 | M261: 12057105 | N261: Wed, 22 Apr 2026 00:00:00 GMT | O261: =I261/L261-1 -> -0.00075949367 | Q261: -0.105 | R261: 0 | T261: =T262-0.0025 -> -0.115 | U261: =_xlfn.NORM.DIST(T261,$S$240,$S$242,FALSE) -> 0.24946826 | W261: 3σ | X261: =($S$242*3)+$S$240 -> 0.12818718 | Y261: 0
A262: 647.25 | B262: 653.86 | C262: 645.9404 | D262: 652.94 | E262: 8457026.3 | F262: Tue, 21 Apr 2026 00:00:00 GMT | G262: =A262/D262-1 -> -0.0087144301 | I262: 38.03 | J262: 39.53 | K262: 37.52 | L262: 38.22 | M262: 10220649 | N262: Tue, 21 Apr 2026 00:00:00 GMT | O262: =I262/L262-1 -> -0.0049712193 | Q262: -0.1025 | R262: 0 | T262: =T263-0.0025 -> -0.1125 | U262: =_xlfn.NORM.DIST(T262,$S$240,$S$242,FALSE) -> 0.29151991 | X262: =($S$242*3)+$S$240 -> 0.12818718 | Y262: 1
A263: 651.54 | B263: 652.6 | C263: 649.17 | D263: 651.62 | E263: 6350549.2 | F263: Mon, 20 Apr 2026 00:00:00 GMT | G263: =A263/D263-1 -> -0.00012277094 | I263: 37.5 | J263: 39.91 | K263: 36.93 | L263: 39.15 | M263: 8852181.8 | N263: Mon, 20 Apr 2026 00:00:00 GMT | O263: =I263/L263-1 -> -0.042145594 | Q263: -0.1 | R263: 0 | T263: =T264-0.0025 -> -0.11 | U263: =_xlfn.NORM.DIST(T263,$S$240,$S$242,FALSE) -> 0.33949575
A264: 652.78 | B264: 654.88 | C264: 648.86 | D264: 649.18 | E264: 7783977.6 | F264: Fri, 17 Apr 2026 00:00:00 GMT | G264: =A264/D264-1 -> 0.0055454573 | I264: 38.48 | J264: 40.23 | K264: 37.84 | L264: 39.14 | M264: 11680043 | N264: Fri, 17 Apr 2026 00:00:00 GMT | O264: =I264/L264-1 -> -0.016862545 | Q264: -0.0975 | R264: 3 | T264: =T265-0.0025 -> -0.1075 | U264: =_xlfn.NORM.DIST(T264,$S$240,$S$242,FALSE) -> 0.39401582
A265: 644.86 | B265: 646.07 | C265: 642.15 | D265: 644.51 | E265: 5858046.5 | F265: Thu, 16 Apr 2026 00:00:00 GMT | G265: =A265/D265-1 -> 0.00054304821 | I265: 39.89 | J265: 40.23 | K265: 34.925 | L265: 34.98 | M265: 19468426 | N265: Thu, 16 Apr 2026 00:00:00 GMT | O265: =I265/L265-1 -> 0.14036592 | Q265: -0.095 | R265: 2 | T265: =T266-0.0025 -> -0.105 | U265: =_xlfn.NORM.DIST(T265,$S$240,$S$242,FALSE) -> 0.45572847
A266: 643.45 | B266: 643.79 | C266: 638.23 | D266: 639.19 | E266: 5050447.7 | F266: Wed, 15 Apr 2026 00:00:00 GMT | G266: =A266/D266-1 -> 0.006664685 | I266: 34.41 | J266: 35.17 | K266: 32.81 | L266: 34.42 | M266: 10894204 | N266: Wed, 15 Apr 2026 00:00:00 GMT | O266: =I266/L266-1 -> -0.00029052876 | Q266: -0.0925 | R266: 4 | T266: =T267-0.0025 -> -0.1025 | U266: =_xlfn.NORM.DIST(T266,$S$240,$S$242,FALSE) -> 0.52530539
A267: 638.35 | B267: 638.52 | C267: 632.22 | D267: 632.225 | E267: 4998949.1 | F267: Tue, 14 Apr 2026 00:00:00 GMT | G267: =A267/D267-1 -> 0.0096880066 | I267: 33.93 | J267: 36.448 | K267: 31.88 | L267: 35.59 | M267: 16257982 | N267: Tue, 14 Apr 2026 00:00:00 GMT | O267: =I267/L267-1 -> -0.046642315 | Q267: -0.09 | R267: 2 | T267: =T268-0.0025 -> -0.1 | U267: =_xlfn.NORM.DIST(T267,$S$240,$S$242,FALSE) -> 0.60343536
A268: 630.72 | B268: 630.9 | C268: 621.98 | D268: 622.75 | E268: 5100917.9 | F268: Mon, 13 Apr 2026 00:00:00 GMT | G268: =A268/D268-1 -> 0.012798073 | I268: 34.32 | J268: 35.485 | K268: 32.7201 | L268: 34.23 | M268: 11878432 | N268: Mon, 13 Apr 2026 00:00:00 GMT | O268: =I268/L268-1 -> 0.0026292726 | Q268: -0.0875 | R268: 1 | T268: =T269-0.0025 -> -0.0975 | U268: =_xlfn.NORM.DIST(T268,$S$240,$S$242,FALSE) -> 0.69081671
A269: 624.6 | B269: 626.99 | C269: 623.72 | D269: 626.325 | E269: 4574295 | F269: Fri, 10 Apr 2026 00:00:00 GMT | G269: =A269/D269-1 -> -0.0027541612 | I269: 34.67 | J269: 36.39 | K269: 33.95 | L269: 34.88 | M269: 9362650.2 | N269: Fri, 10 Apr 2026 00:00:00 GMT | O269: =I269/L269-1 -> -0.0060206422 | Q269: -0.085 | R269: 2 | T269: =T270-0.0025 -> -0.095 | U269: =_xlfn.NORM.DIST(T269,$S$240,$S$242,FALSE) -> 0.78814861
A270: 625.02 | B270: 626.17 | C270: 619.4 | D270: 620.34 | E270: 5470297.5 | F270: Thu, 09 Apr 2026 00:00:00 GMT | G270: =A270/D270-1 -> 0.0075442499 | I270: 34.23 | J270: 37.17 | K270: 33.94 | L270: 36.5 | M270: 11225178 | N270: Thu, 09 Apr 2026 00:00:00 GMT | O270: =I270/L270-1 -> -0.062191781 | Q270: -0.0825 | R270: 2 | T270: =T271-0.0025 -> -0.0925 | U270: =_xlfn.NORM.DIST(T270,$S$240,$S$242,FALSE) -> 0.89612086
A271: 621.34 | B271: 622.49 | C271: 617.3 | D271: 621.795 | E271: 9765573.6 | F271: Wed, 08 Apr 2026 00:00:00 GMT | G271: =A271/D271-1 -> -0.00073175243 | I271: 36.55 | J271: 38.21 | K271: 35.44 | L271: 36.9 | M271: 16073285 | N271: Wed, 08 Apr 2026 00:00:00 GMT | O271: =I271/L271-1 -> -0.0094850949 | Q271: -0.08 | R271: 2 | T271: =T272-0.0025 -> -0.09 | U271: =_xlfn.NORM.DIST(T271,$S$240,$S$242,FALSE) -> 1.0154026
A272: 606.04 | B272: 606.31 | C272: 598.5 | D272: 603.58 | E272: 6146308 | F272: Tue, 07 Apr 2026 00:00:00 GMT | G272: =A272/D272-1 -> 0.0040756818 | I272: 35.17 | J272: 35.8 | K272: 32.77 | L272: 35.38 | M272: 13076903 | N272: Tue, 07 Apr 2026 00:00:00 GMT | O272: =I272/L272-1 -> -0.0059355568 | Q272: -0.0775 | R272: 4 | T272: =T273-0.0025 -> -0.0875 | U272: =_xlfn.NORM.DIST(T272,$S$240,$S$242,FALSE) -> 1.1466295
A273: 605.67 | B273: 606.44 | C273: 602.61 | D273: 602.92 | E273: 6282638.2 | F273: Mon, 06 Apr 2026 00:00:00 GMT | G273: =A273/D273-1 -> 0.0045611358 | I273: 35.02 | J273: 36.29 | K273: 34.21 | L273: 35.92 | M273: 12502655 | N273: Mon, 06 Apr 2026 00:00:00 GMT | O273: =I273/L273-1 -> -0.025055679 | Q273: -0.075 | R273: 3 | T273: =T274-0.0025 -> -0.085 | U273: =_xlfn.NORM.DIST(T273,$S$240,$S$242,FALSE) -> 1.2903905
A274: 602.99 | B274: 604.79 | C274: 593.032 | D274: 594.23 | E274: 12739516 | F274: Thu, 02 Apr 2026 00:00:00 GMT | G274: =A274/D274-1 -> 0.014741767 | I274: 35.88 | J274: 36.04 | K274: 29.44 | L274: 29.44 | M274: 25265919 | N274: Thu, 02 Apr 2026 00:00:00 GMT | O274: =I274/L274-1 -> 0.21875 | Q274: -0.0725 | R274: 5 | T274: =T275-0.0025 -> -0.0825 | U274: =_xlfn.NORM.DIST(T274,$S$240,$S$242,FALSE) -> 1.4472129
... A306: 627.99 | B306: 629.93 | C306: 621.51 | D306: 625.54 | E306: 8039425 | F306: Tue, 17 Feb 2026 00:00:00 GMT | G306: =A306/D306-1 -> 0.003916616 | I306: 22.21 | J306: 22.7899 | K306: 21.5 | L306: 22 | M306: 5521178 | N306: Tue, 17 Feb 2026 00:00:00 GMT | O306: =I306/L306-1 -> 0.0095454545 | Q306: 0.0075 | R306: 18 | T306: =T307-0.0025 -> -0.0025 | U306: =_xlfn.NORM.DIST(T306,$S$240,$S$242,FALSE) -> 9.3209137
A307: 626.89 | B307: 631.17 | C307: 623.115 | D307: 626.93 | E307: 9248752 | F307: Fri, 13 Feb 2026 00:00:00 GMT | G307: =A307/D307-1 -> -6.3802976e-05 | I307: 22.42 | J307: 22.93 | K307: 21.1285 | L307: 21.5 | M307: 6446423 | N307: Fri, 13 Feb 2026 00:00:00 GMT | O307: =I307/L307-1 -> 0.042790698 | Q307: 0.01 | R307: 37 | T307: 0 | U307: =_xlfn.NORM.DIST(T307,$S$240,$S$242,FALSE) -> 9.3369518
A308: 626.49 | B308: 639.52 | C308: 625.76 | D308: 638.51 | E308: 8866872 | F308: Thu, 12 Feb 2026 00:00:00 GMT | G308: =A308/D308-1 -> -0.018825077 | I308: 21.3 | J308: 21.91 | K308: 19.98 | L308: 21.57 | M308: 13315667 | N308: Thu, 12 Feb 2026 00:00:00 GMT | O308: =I308/L308-1 -> -0.012517385 | Q308: 0.0125 | R308: 21 | T308: =T307+0.0025 -> 0.0025 | U308: =_xlfn.NORM.DIST(T308,$S$240,$S$242,FALSE) -> 9.3210523
A309: 636.35 | B309: 641.15 | C309: 633.84 | D309: 640.49 | E309: 5317092 | F309: Wed, 11 Feb 2026 00:00:00 GMT | G309: =A309/D309-1 -> -0.0064638012 | I309: 21.65 | J309: 23.525 | K309: 20.91 | L309: 23.525 | M309: 7993775 | N309: Wed, 11 Feb 2026 00:00:00 GMT | O309: =I309/L309-1 -> -0.079702444 | Q309: 0.015 | R309: 27 | T309: =T308+0.0025 -> 0.005 | U309: =_xlfn.NORM.DIST(T309,$S$240,$S$242,FALSE) -> 9.2733781
A310: 636.44 | B310: 640.62 | C310: 636.08 | D310: 639.14 | E310: 13619951 | F310: Tue, 10 Feb 2026 00:00:00 GMT | G310: =A310/D310-1 -> -0.0042244266 | I310: 22.79 | J310: 23.98 | K310: 22.71 | L310: 23.87 | M310: 7584708 | N310: Tue, 10 Feb 2026 00:00:00 GMT | O310: =I310/L310-1 -> -0.045245078 | Q310: 0.0175 | R310: 32 | T310: =T309+0.0025 -> 0.0075 | U310: =_xlfn.NORM.DIST(T310,$S$240,$S$242,FALSE) -> 9.1944166
A311: 638.23 | B311: 639.99 | C311: 633.11 | D311: 634.07 | E311: 8885179 | F311: Mon, 09 Feb 2026 00:00:00 GMT | G311: =A311/D311-1 -> 0.0065607898 | I311: 24.02 | J311: 24.095 | K311: 21.65 | L311: 21.96 | M311: 10567276 | N311: Mon, 09 Feb 2026 00:00:00 GMT | O311: =I311/L311-1 -> 0.093806922 | Q311: 0.02 | R311: 21 | T311: =T310+0.0025 -> 0.01 | U311: =_xlfn.NORM.DIST(T311,$S$240,$S$242,FALSE) -> 9.0849719
A312: 635.24 | B312: 636.72 | C312: 626.2 | D312: 626.72 | E312: 12959420 | F312: Fri, 06 Feb 2026 00:00:00 GMT | G312: =A312/D312-1 -> 0.013594588 | I312: 22.26 | J312: 22.28 | K312: 20.81 | L312: 21.04 | M312: 9412809 | N312: Fri, 06 Feb 2026 00:00:00 GMT | O312: =I312/L312-1 -> 0.057984791 | Q312: 0.0225 | R312: 19 | T312: =T311+0.0025 -> 0.0125 | U312: =_xlfn.NORM.DIST(T312,$S$240,$S$242,FALSE) -> 8.9461502
A313: 623.1 | B313: 628.75 | C313: 621.5 | D313: 626.24 | E313: 11506981 | F313: Thu, 05 Feb 2026 00:00:00 GMT | G313: =A313/D313-1 -> -0.0050140521 | I313: 20.43 | J313: 21.542 | K313: 20.15 | L313: 21 | M313: 11082687 | N313: Thu, 05 Feb 2026 00:00:00 GMT | O313: =I313/L313-1 -> -0.027142857 | Q313: 0.025 | R313: 25 | T313: =T312+0.0025 -> 0.015 | U313: =_xlfn.NORM.DIST(T313,$S$240,$S$242,FALSE) -> 8.7793423
A314: 630.91 | B314: 635.92 | C314: 627 | D314: 634.93 | E314: 11228241 | F314: Wed, 04 Feb 2026 00:00:00 GMT | G314: =A314/D314-1 -> -0.0063314066 | I314: 21.77 | J314: 24 | K314: 20.59 | L314: 24 | M314: 12162902 | N314: Wed, 04 Feb 2026 00:00:00 GMT | O314: =I314/L314-1 -> -0.092916667 | Q314: 0.0275 | R314: 12 | T314: =T313+0.0025 -> 0.0175 | U314: =_xlfn.NORM.DIST(T314,$S$240,$S$242,FALSE) -> 8.5861994
A315: 634.15 | B315: 641 | C315: 629.105 | D315: 640.33 | E315: 9644195 | F315: Tue, 03 Feb 2026 00:00:00 GMT | G315: =A315/D315-1 -> -0.0096512736 | I315: 23.95 | J315: 23.9868 | K315: 22.91 | L315: 23.98 | M315: 9573272 | N315: Tue, 03 Feb 2026 00:00:00 GMT | O315: =I315/L315-1 -> -0.0012510425 | Q315: 0.03 | R315: 17 | T315: =T314+0.0025 -> 0.02 | U315: =_xlfn.NORM.DIST(T315,$S$240,$S$242,FALSE) -> 8.3686066
A316: 639.68 | B316: 640.96 | C316: 634.07 | D316: 634.18 | E316: 9124531 | F316: Mon, 02 Feb 2026 00:00:00 GMT | G316: =A316/D316-1 -> 0.0086726166 | I316: 22.85 | J316: 25.772 | K316: 22.465 | L316: 24.89 | M316: 14876944 | N316: Mon, 02 Feb 2026 00:00:00 GMT | O316: =I316/L316-1 -> -0.081960627 | Q316: 0.0325 | R316: 19 | T316: =T315+0.0025 -> 0.0225 | U316: =_xlfn.NORM.DIST(T316,$S$240,$S$242,FALSE) -> 8.1286519
A317: 636.22 | B317: 638.45 | C317: 631.95 | D317: 636.25 | E317: 6519552 | F317: Fri, 30 Jan 2026 00:00:00 GMT | G317: =A317/D317-1 -> -4.7151277e-05 | I317: 24.97 | J317: 27.25 | K317: 24.445 | L317: 25.715 | M317: 15421065 | N317: Fri, 30 Jan 2026 00:00:00 GMT | O317: =I317/L317-1 -> -0.028971417 | Q317: 0.035 | R317: 15 | T317: =T316+0.0025 -> 0.025 | U317: =_xlfn.NORM.DIST(T317,$S$240,$S$242,FALSE) -> 7.8685932
A318: 638.27 | B318: 641.04 | C318: 629.82 | D318: 640.43 | E318: 8485857 | F318: Thu, 29 Jan 2026 00:00:00 GMT | G318: =A318/D318-1 -> -0.0033727339 | I318: 26.35 | J318: 27.7 | K318: 25.55 | L318: 27.7 | M318: 10387135 | N318: Thu, 29 Jan 2026 00:00:00 GMT | O318: =I318/L318-1 -> -0.048736462 | Q318: 0.0375 | R318: 14 | T318: =T317+0.0025 -> 0.0275 | U318: =_xlfn.NORM.DIST(T318,$S$240,$S$242,FALSE) -> 7.5908228
A319: 639.6 | B319: 641.81 | C319: 638.22 | D319: 641.05 | E319: 5488373 | F319: Wed, 28 Jan 2026 00:00:00 GMT | G319: =A319/D319-1 -> -0.002261914 | I319: 27.88 | J319: 28.4 | K319: 26.81 | L319: 28.05 | M319: 12700109 | N319: Wed, 28 Jan 2026 00:00:00 GMT | O319: =I319/L319-1 -> -0.0060606061 | Q319: 0.04 | R319: 10 | T319: =T318+0.0025 -> 0.03 | U319: =_xlfn.NORM.DIST(T319,$S$240,$S$242,FALSE) -> 7.2978312
... A357: 626.58 | B357: 628.77 | C357: 624.62 | D357: 627.01 | E357: 5256797 | F357: Tue, 02 Dec 2025 00:00:00 GMT | G357: =A357/D357-1 -> -0.00068579448 | I357: 11.77 | J357: 12.26 | K357: 11.665 | L357: 11.88 | M357: 5614604 | N357: Tue, 02 Dec 2025 00:00:00 GMT | O357: =I357/L357-1 -> -0.0092592593 | Q357: 0.135 | R357: 0 | T357: =T356+0.0025 -> 0.125 | U357: =_xlfn.NORM.DIST(T357,$S$240,$S$242,FALSE) -> 0.12937743
A358: 625.52 | B358: 628.01 | C358: 624.1 | D358: 624.17 | E358: 8381362 | F358: Mon, 01 Dec 2025 00:00:00 GMT | G358: =A358/D358-1 -> 0.0021628723 | I358: 11.7 | J358: 11.82 | K358: 11.4 | L358: 11.6 | M358: 4969861 | N358: Mon, 01 Dec 2025 00:00:00 GMT | O358: =I358/L358-1 -> 0.0086206897 | Q358: More | R358: 7 | T358: =T357+0.0025 -> 0.1275 | U358: =_xlfn.NORM.DIST(T358,$S$240,$S$242,FALSE) -> 0.10883737
A359: 628.41 | B359: 628.63 | C359: 625.705 | D359: 626.025 | E359: 2949167 | F359: Fri, 28 Nov 2025 00:00:00 GMT | G359: =A359/D359-1 -> 0.003809752 | I359: 11.9 | J359: 12.01 | K359: 11.716 | L359: 11.91 | M359: 2033951 | N359: Fri, 28 Nov 2025 00:00:00 GMT | O359: =I359/L359-1 -> -0.00083963056 | T359: =T358+0.0025 -> 0.13 | U359: =_xlfn.NORM.DIST(T359,$S$240,$S$242,FALSE) -> 0.091245347
A360: 624.95 | B360: 626.81 | C360: 622.26 | D360: 623.06 | E360: 5292533 | F360: Wed, 26 Nov 2025 00:00:00 GMT | G360: =A360/D360-1 -> 0.0030334157 | I360: 11.72 | J360: 12.02 | K360: 11.63 | L360: 11.77 | M360: 4680600 | N360: Wed, 26 Nov 2025 00:00:00 GMT | O360: =I360/L360-1 -> -0.0042480884 | T360: =T359+0.0025 -> 0.1325 | U360: =_xlfn.NORM.DIST(T360,$S$240,$S$242,FALSE) -> 0.076235388
A361: 620.66 | B361: 621.75 | C361: 610.99 | D361: 614.78 | E361: 7289905 | F361: Tue, 25 Nov 2025 00:00:00 GMT | G361: =A361/D361-1 -> 0.009564397 | I361: 11.73 | J361: 11.8686 | K361: 11.26 | L361: 11.51 | M361: 4516360 | N361: Tue, 25 Nov 2025 00:00:00 GMT | O361: =I361/L361-1 -> 0.019113814 | T361: =T360+0.0025 -> 0.135 | U361: =_xlfn.NORM.DIST(T361,$S$240,$S$242,FALSE) -> 0.063476899
A362: 614.94 | B362: 616.09 | C362: 608.305 | D362: 609.28 | E362: 6218559 | F362: Mon, 24 Nov 2025 00:00:00 GMT | G362: =A362/D362-1 -> 0.0092896534 | I362: 11.54 | J362: 11.655 | K362: 11.26 | L362: 11.35 | M362: 6076696 | N362: Mon, 24 Nov 2025 00:00:00 GMT | O362: =I362/L362-1 -> 0.016740088 | T362: =T361+0.0025 -> 0.1375 | U362: =_xlfn.NORM.DIST(T362,$S$240,$S$242,FALSE) -> 0.052672991
A363: 605.93 | B363: 611.01 | C363: 598.38 | D363: 602.25 | E363: 9789866 | F363: Fri, 21 Nov 2025 00:00:00 GMT | G363: =A363/D363-1 -> 0.0061104193 | I363: 11.16 | J363: 11.5 | K363: 10.52 | L363: 11.24 | M363: 11238581 | N363: Fri, 21 Nov 2025 00:00:00 GMT | O363: =I363/L363-1 -> -0.0071174377 | T363: =T362+0.0025 -> 0.14 | U363: =_xlfn.NORM.DIST(T363,$S$240,$S$242,FALSE) -> 0.043558553
...

Sheet Product Lines

Sheet Management

Sheet Table Formatting
B2: [Bold Title] | G2: [Bold Title]
B3: Line Titles | G3: <-- General
B4: Line Titles | G4: <-- Info
B5: Line Titles | G5: <-- General
B6: Line Titles | G6: <-- Info
B7: Line Titles | G7: <-- General
B8: Line Titles | G8: <-- Info
