Workbook

Sheet Main
A1: Master
B2: PODD
B3: Price | C3: 133.93 | D3: 10/14/2026
B4: SO | C4: 96.298 | D4: Q2'26
B5: MC | C5: =C3*C4 -> 12897.191
B6: Cash | C6: 534.9 | D6: Q2'26
B7: Debt | C7: =18.9+929.5 -> 948.4 | D7: Q2'26
B8: EV | C8: =C5-C6+C7 -> 13310.691
B10: Insulet Corporation (PODD)
B12: Founder(s): John Brooks, Amparo Diaz, and Duane DeSisto | G12: Registered Exchange: NASDAQ | M12: Resources:
B13: Founded: 2000 | G13: Address: 100 Nagog Park, Acton, MA 01720 U.S. | M13: SEC filings | P13: https://www.sec.gov/edgar/browse/?CIK=1145197&owner=exclude
B14: Headquarters: Acton, MA | G14: Investor Relations Contact: | M14: Company Homepage | P14: https://www.insulet.com/
B15: Current CEO: Ashley McEvoy | G15: Investors Relation Department | N15: Company IR Page | Q15: https://investor.insulet.com/overview/default.aspx
B16: Employees: 5,700 | G16: Phone: | H16: (978) 600 - 7000 | J16: Email: | M16: Earnings Calls | P16: https://seekingalpha.com/symbol/PODD/earnings/transcripts
B17: Industry: Medical Devices | M17: Equity Analysis | P17: https://stockanalysis.com/stocks/podd/company/
B18: Sector: Healthcare | M18: MacroTrends | P18: https://www.macrotrends.net/stocks/charts/PODD/insulet/income-statement?freq=A
B19: IPO: May 15, 2007 | M19: ROIC, WACC | P19: https://www.gurufocus.com/term/wacc/PODD
B20: Fiscal Year: [January - December] | M20: Godel Terminal | P20: https://app.godelterminal.com/
A22: Company Overview:
B23: Insulet Corporation develops, manufactures, and sells insulin delivery systems for people with insulin-dependent diabetes in the United States and internationally
B24: The Company offers Omnipod platform products comprising Omnipod 5 automated insulin delivery system, which includes a proprietary AID algorithm embedded in the pod that integrates with a third-party continuous glucose monitor to obtain glucose values through wireless Bluetooth communication
C25: The Company also offers Omnipod DASH insulin management system that features a Bluetooth enabled pod that is controlled by a smartphone-like personal diabetes manager with a color touch screen user interface
C26: It also provides pods for Amgen for use in the Neulasta Onpro kit, which is a delivery system to help reduce the risk of infection after intense chemotherapy
B27: The Company sells its products to end-users through the pharmacy channel; and independent distributors
B28: Insulet Corporation was incorporated in 2000 and is headquartered in Acton, Massachusetts
A30: Business Segments and Geographical Info:

Sheet Model
B1: [Use for Graphing] | AM1: Q1 2020 | AQ1: Q1 2021 | AU1: Q1 2022 | AY1: Q1 2023 | BC1: Q1 2024 | BG1: Q1 2025 | BK1: Q1 2026
B2: Quarterly
B3: Revenues | C3: {="Q"&MOD(_xlfn.SEQUENCE(1,64)-1,4)+1&" "&(2011+INT((_xlfn.SEQUENCE(1,64)-1)/4))} -> Q1 2011 | D3: Q2 2011 | E3: Q3 2011 | F3: Q4 2011 | G3: Q1 2012 | H3: Q2 2012 | I3: Q3 2012 | J3: Q4 2012 | K3: Q1 2013 | L3: Q2 2013 | M3: Q3 2013 | N3: Q4 2013 | O3: Q1 2014 | P3: Q2 2014 | Q3: Q3 2014 | R3: Q4 2014 | S3: Q1 2015 | T3: Q2 2015 | U3: Q3 2015 | V3: Q4 2015 | W3: Q1 2016 | X3: Q2 2016 | Y3: Q3 2016 | Z3: Q4 2016 | AA3: Q1 2017 | AB3: Q2 2017 | AC3: Q3 2017 | AD3: Q4 2017 | AE3: Q1 2018 | AF3: Q2 2018 | AG3: Q3 2018 | AH3: Q4 2018 | AI3: Q1 2019 | AJ3: Q2 2019 | AK3: Q3 2019 | AL3: Q4 2019 | AM3: Q1 2020 | AN3: Q2 2020 | AO3: Q3 2020 | AP3: Q4 2020 | AQ3: Q1 2021 | AR3: Q2 2021 | AS3: Q3 2021 | AT3: Q4 2021 | AU3: Q1 2022 | AV3: Q2 2022 | AW3: Q3 2022 | AX3: Q4 2022 | AY3: Q1 2023 | AZ3: Q2 2023 | BA3: Q3 2023 | BB3: Q4 2023 | BC3: Q1 2024 | BD3: Q2 2024 | BE3: Q3 2024 | BF3: Q4 2024 | BG3: Q1 2025 | BH3: Q2 2025 | BI3: Q3 2025 | BJ3: Q4 2025 | BK3: Q1 2026 | BL3: Q2 2026 | BM3: Q3 2026 | BN3: Q4 2026 | BS3: 2011 | BT3: =BS3+1 -> 2012 | BU3: =BT3+1 -> 2013 | BV3: =BU3+1 -> 2014 | BW3: =BV3+1 -> 2015 | BX3: =BW3+1 -> 2016 | BY3: =BX3+1 -> 2017 | BZ3: =BY3+1 -> 2018 | CA3: =BZ3+1 -> 2019 | ... EO3: =EN3+1 -> 2085
B4: Omnipod Products | AQ4: 233.2 | AR4: 242.1 | AS4: 260.3 | AT4: =1011.4-SUM(AQ4:AS4) -> 275.8 | AU4: 269.5 | AV4: 285.8 | AW4: 326.1 | AX4: =1247.8-SUM(AU4:AW4) -> 366.4 | AY4: 357.6 | AZ4: 380.5 | BA4: 422 | BB4: =1661.1-SUM(AY4:BA4) -> 501 | BC4: 433 | BD4: 480.4 | BE4: 533.5 | BF4: =2032.7-SUM(BC4:BE4) -> 585.8 | BG4: 554 | BH4: 639 | BI4: 699.2 | BJ4: =2674-SUM(BG4:BI4) -> 781.8 | BK4: 758.4 | BL4: 795.9 | CC4: =SUM(AQ4:AT4) -> 1011.4 | CD4: =SUM(AU4:AX4) -> 1247.8 | CE4: =SUM(AY4:BB4) -> 1661.1 | CF4: =SUM(BC4:BF4) -> 2032.7 | CG4: =SUM(BG4:BJ4) -> 2674 | CH4: =CG4*(1+CH8) -> 3262.28 | CI4: =CH4*(1+CI8) -> 3718.9992 | CJ4: =CI4*(1+CJ8) -> 4128.0891 | CK4: =CJ4*(1+CK8) -> 4499.6171 | CL4: =CK4*(1+CL8) -> 4859.5865 | CM4: =CL4*(1+CM8) -> 5199.7576 | CN4: =CM4*(1+CN8) -> 5511.743 | CO4: =CN4*(1+CO8) -> 5787.3302 | ... CQ4: =CP4*(1+CQ8) -> 6199.3881
B5: Drug Delivery | AQ5: 19.1 | AR5: 21.1 | AS5: 15.3 | AT5: =87.4-SUM(AQ5:AS5) -> 31.9 | AU5: 25.9 | AV5: 13.6 | AW5: 14.7 | AX5: =57.5-SUM(AU5:AW5) -> 3.3 | AY5: 0.5 | AZ5: 16 | BA5: 10.7 | BB5: =36-SUM(AY5:BA5) -> 8.8 | BC5: 8.7 | BD5: 8.1 | BE5: 10.3 | BF5: =38.9-SUM(BC5:BE5) -> 11.8 | BG5: 14.9 | BH5: 10.2 | BI5: 7.1 | BJ5: =34.1-SUM(BG5:BI5) -> 1.9 | BK5: 3.3 | BL5: 5.8 | CC5: =SUM(AQ5:AT5) -> 87.4 | CD5: =SUM(AU5:AX5) -> 57.5 | CE5: =SUM(AY5:BB5) -> 36 | CF5: =SUM(BC5:BF5) -> 38.9 | CG5: =SUM(BG5:BJ5) -> 34.1 | CH5: =CG5*(1+CH9) -> 13.64 | CI5: =CH5*(1+CI9) -> 10.912 | CJ5: =CI5*(1+CJ9) -> 8.7296 | CK5: =CJ5*(1+CK9) -> 9.60256 | CL5: =CK5*(1+CL9) -> 10.178714 | CM5: =CL5*(1+CM9) -> 10.585862 | CN5: =CM5*(1+CN9) -> 10.956367 | CO5: =CN5*(1+CO9) -> 11.285058 | ... CQ5: =CP5*(1+CQ9) -> 11.798528
B6: Ttl Revenues | AQ6: =SUM(AQ4:AQ5) -> 252.3 | AR6: =SUM(AR4:AR5) -> 263.2 | AS6: =SUM(AS4:AS5) -> 275.6 | AT6: =SUM(AT4:AT5) -> 307.7 | AU6: =SUM(AU4:AU5) -> 295.4 | AV6: =SUM(AV4:AV5) -> 299.4 | AW6: =SUM(AW4:AW5) -> 340.8 | AX6: =SUM(AX4:AX5) -> 369.7 | ... BL6: =SUM(BL4:BL5) -> 801.7 | CC6: =SUM(AQ6:AT6) -> 1098.8 | CD6: =SUM(AU6:AX6) -> 1305.3 | CE6: =SUM(AY6:BB6) -> 1697.1 | CF6: =SUM(BC6:BF6) -> 2071.6 | CG6: =SUM(BG6:BJ6) -> 2708.1 | CH6: =SUM(CH4:CH5) -> 3275.92 | CI6: =SUM(CI4:CI5) -> 3729.9112 | CJ6: =SUM(CJ4:CJ5) -> 4136.8187 | CK6: =SUM(CK4:CK5) -> 4509.2197 | CL6: =SUM(CL4:CL5) -> 4869.7652 | CM6: =SUM(CM4:CM5) -> 5210.3434 | CN6: =SUM(CN4:CN5) -> 5522.6994 | CO6: =SUM(CO4:CO5) -> 5798.6152 | ... CQ6: =SUM(CQ4:CQ5) -> 6211.1866
B8: Omnipod Products Growth Y/y | AU8: =AU4/AQ4-1 -> 0.15566038 | AV8: =AV4/AR4-1 -> 0.18050392 | AW8: =AW4/AS4-1 -> 0.25278525 | AX8: =AX4/AT4-1 -> 0.32849891 | AY8: =AY4/AU4-1 -> 0.32690167 | AZ8: =AZ4/AV4-1 -> 0.33135059 | BA8: =BA4/AW4-1 -> 0.29408157 | BB8: =BB4/AX4-1 -> 0.36735808 | ... BL8: =BL4/BH4-1 -> 0.24553991 | CD8: =CD4/CC4-1 -> 0.23373542 | CE8: =CE4/CD4-1 -> 0.33122295 | CF8: =CF4/CE4-1 -> 0.22370718 | CG8: =CG4/CF4-1 -> 0.31549171 | CH8: 0.22 | CI8: 0.14 | CJ8: 0.11 | CK8: 0.09 | CL8: 0.08 | CM8: 0.07 | CN8: 0.06 | CO8: 0.05 | CP8: 0.04 | CQ8: 0.03
B9: Drug Delivery Growth Y/y | AU9: =AU5/AQ5-1 -> 0.35602094 | AV9: =AV5/AR5-1 -> -0.35545024 | AW9: =AW5/AS5-1 -> -0.039215686 | AX9: =AX5/AT5-1 -> -0.89655172 | AY9: =AY5/AU5-1 -> -0.98069498 | AZ9: =AZ5/AV5-1 -> 0.17647059 | BA9: =BA5/AW5-1 -> -0.27210884 | BB9: =BB5/AX5-1 -> 1.6666667 | ... BL9: =BL5/BH5-1 -> -0.43137255 | CD9: =CD5/CC5-1 -> -0.34210526 | CE9: =CE5/CD5-1 -> -0.37391304 | CF9: =CF5/CE5-1 -> 0.080555556 | CG9: =CG5/CF5-1 -> -0.12339332 | CH9: -0.6 | CI9: -0.2 | CJ9: -0.2 | CK9: 0.1 | CL9: 0.06 | CM9: 0.04 | CN9: 0.035 | CO9: 0.03 | CP9: 0.025 | CQ9: 0.02
B10: Ttl Revenue Growth Y/y | AU10: =AU6/AQ6-1 -> 0.17082838 | AV10: =AV6/AR6-1 -> 0.13753799 | AW10: =AW6/AS6-1 -> 0.23657475 | AX10: =AX6/AT6-1 -> 0.20149496 | AY10: =AY6/AU6-1 -> 0.21225457 | AZ10: =AZ6/AV6-1 -> 0.3243153 | BA10: =BA6/AW6-1 -> 0.26965962 | BB10: =BB6/AX6-1 -> 0.37895591 | ... BL10: =BL6/BH6-1 -> 0.2349045 | CD10: =CD6/CC6-1 -> 0.18793229 | CE10: =CE6/CD6-1 -> 0.30016088 | CF10: =CF6/CE6-1 -> 0.22067056 | CG10: =CG6/CF6-1 -> 0.30725043 | CH10: =CH6/CG6-1 -> 0.20967468 | CI10: =CI6/CH6-1 -> 0.13858434 | CJ10: =CJ6/CI6-1 -> 0.10909308 | CK10: =CK6/CJ6-1 -> 0.090021102 | ... CQ10: =CQ6/CP6-1 -> 0.029980819
B12: Omnipod Products % of Revenues | AQ12: =AQ4/AQ6 -> 0.92429647 | AR12: =AR4/AR6 -> 0.91983283 | AS12: =AS4/AS6 -> 0.94448476 | AT12: =AT4/AT6 -> 0.89632759 | AU12: =AU4/AU6 -> 0.91232227 | AV12: =AV4/AV6 -> 0.95457582 | AW12: =AW4/AW6 -> 0.9568662 | AX12: =AX4/AX6 -> 0.99107384 | ... BL12: =BL4/BL6 -> 0.99276537 | CC12: =CC4/CC6 -> 0.92045868 | CD12: =CD4/CD6 -> 0.95594882 | CE12: =CE4/CE6 -> 0.97878734 | CF12: =CF4/CF6 -> 0.98122224 | CG12: =CG4/CG6 -> 0.98740815
B13: Drug Delivery % of Revenues | AQ13: =AQ5/AQ6 -> 0.075703528 | AR13: =AR5/AR6 -> 0.080167173 | AS13: =AS5/AS6 -> 0.055515239 | AT13: =AT5/AT6 -> 0.10367241 | AU13: =AU5/AU6 -> 0.087677725 | AV13: =AV5/AV6 -> 0.045424182 | AW13: =AW5/AW6 -> 0.043133803 | AX13: =AX5/AX6 -> 0.0089261563 | ... BL13: =BL5/BL6 -> 0.0072346264 | CC13: =CC5/CC6 -> 0.079541318 | CD13: =CD5/CD6 -> 0.044051176 | CE13: =CE5/CE6 -> 0.021212657 | CF13: =CF5/CF6 -> 0.018777756 | CG13: =CG5/CG6 -> 0.012591854
B15: U.S. | BK15: 469.3 | BL15: 470.3
B16: Malaysia | BK16: 224.7 | BL16: 234.1
B17: Other | BK17: 136.4 | BL17: 154.2
B18: Ttl Revenues | BK18: =SUM(BK15:BK17) -> 830.4 | BL18: =SUM(BL15:BL17) -> 858.6
B20: U.S. Growth Y/y
B21: Malaysia Growth Y/y
B22: Other Growth Y/y
B23: Ttl Revenues Growth Y/y
B25: U.S. % of Revenues | BK25: =BK15/BK18 -> 0.56514933 | BL25: =BL15/BL18 -> 0.54775215
B26: Malaysia % of Revenues | BK26: =BK16/BK18 -> 0.27059249 | BL26: =BL16/BL18 -> 0.27265316
B27: Other % of Revenues | BK27: =BK17/BK18 -> 0.16425819 | BL27: =BL17/BL18 -> 0.17959469
B29: Revenues | C29: 28.258 | D29: 32.211 | E29: 44.594 | F29: 47.192 | G29: 47.754 | H29: 51.035 | I29: 54.752 | J29: 57.828 | K29: 57.356 | L29: 60.092 | M29: 61.103 | N29: 68.533 | O29: 69.161 | P29: 72.013 | Q29: 74.985 | R29: 15.162 | S29: 48.148 | T29: 60.551 | U29: 71.393 | V29: 83.801 | W29: 81.213 | X29: 87.33 | Y29: 94.871 | Z29: 103.575 | AA29: 101.713 | AB29: 109.756 | AC29: 121.775 | AD29: 130.556 | AE29: 123.578 | AF29: 124.262 | AG29: 151.076 | AH29: 164.884 | AI29: 159.6 | AJ29: 177.1 | AK29: 192.1 | AL29: 209.4 | AM29: 198 | AN29: 226.3 | AO29: 234 | AP29: 246.1 | AQ29: 252.3 | AR29: 263.2 | AS29: 275.6 | AT29: 307.7 | AU29: =AU6 -> 295.4 | AV29: =AV6 -> 299.4 | AW29: =AW6 -> 340.8 | AX29: =AX6 -> 369.7 | AY29: =AY6 -> 358.1 | AZ29: =AZ6 -> 396.5 | BA29: =BA6 -> 432.7 | BB29: =BB6 -> 509.8 | ... BL29: =BL6 -> 801.7 | BS29: =SUM(C29:F29) -> 152.255 | BT29: =SUM(G29:J29) -> 211.369 | BU29: =SUM(K29:N29) -> 247.084 | BV29: =SUM(O29:R29) -> 231.321 | BW29: =SUM(S29:V29) -> 263.893 | BX29: =SUM(W29:Z29) -> 366.989 | BY29: =SUM(AA29:AD29) -> 463.8 | BZ29: =SUM(AE29:AH29) -> 563.8 | CA29: =SUM(AI29:AL29) -> 738.2 | CB29: =SUM(AM29:AP29) -> 904.4 | CC29: =SUM(AQ29:AT29) -> 1098.8 | CD29: =SUM(AU29:AX29) -> 1305.3 | CE29: =SUM(AY29:BB29) -> 1697.1 | CF29: =SUM(BC29:BF29) -> 2071.6 | CG29: =SUM(BG29:BJ29) -> 2708.1 | CH29: =CH6 -> 3275.92 | CI29: =CI6 -> 3729.9112 | CJ29: =CJ6 -> 4136.8187 | CK29: =CK6 -> 4509.2197 | CL29: =CL6 -> 4869.7652 | CM29: =CM6 -> 5210.3434 | CN29: =CN6 -> 5522.6994 | CO29: =CO6 -> 5798.6152 | ... CQ29: =CQ6 -> 6211.1866
B30: COGS | C30: 14.725 | D30: 17.673 | E30: 26.033 | F30: 27.112 | G30: 27.458 | H30: 28.704 | I30: 30.362 | J30: 32.509 | K30: 32.201 | L30: 33.259 | M30: 33.708 | N30: 35.515 | O30: 36.353 | P30: 36.248 | Q30: 36.943 | R30: -5.349 | S30: 18.955 | T30: 30.036 | U30: 39.823 | V30: 41.808 | W30: 37.162 | X30: 36.873 | Y30: 39.23 | Z30: 42.638 | AA30: 42.315 | AB30: 45.117 | AC30: 48.151 | AD30: 51.017 | AE30: 47.763 | AF30: 42.19 | AG30: 49.107 | AH30: 54.54 | AI30: 52.9 | AJ30: 60.7 | AK30: 69 | AL30: 75.3 | AM30: 71.1 | AN30: 83.8 | AO30: 82.2 | AP30: 85 | AQ30: 84.8 | AR30: 80.5 | AS30: 86.9 | AT30: 94.5 | AU30: 85.7 | AV30: 109.1 | AW30: 152.5 | AX30: =499.7-SUM(AU30:AW30) -> 152.4 | AY30: 117.6 | AZ30: 131.6 | BA30: 139.4 | BB30: =537.2-SUM(AY30:BA30) -> 148.6 | BC30: 134.9 | BD30: 157.6 | BE30: 166.8 | BF30: =625.9-SUM(BC30:BE30) -> 166.6 | BG30: 159.9 | BH30: 196.9 | BI30: 196.2 | BJ30: =768.2-SUM(BG30:BI30) -> 215.2 | BK30: 232.7 | BL30: 239.1 | BS30: =SUM(C30:F30) -> 85.543 | BT30: =SUM(G30:J30) -> 119.033 | BU30: =SUM(K30:N30) -> 134.683 | BV30: =SUM(O30:R30) -> 104.195 | BW30: =SUM(S30:V30) -> 130.622 | BX30: =SUM(W30:Z30) -> 155.903 | BY30: =SUM(AA30:AD30) -> 186.6 | BZ30: =SUM(AE30:AH30) -> 193.6 | CA30: =SUM(AI30:AL30) -> 257.9 | CB30: =SUM(AM30:AP30) -> 322.1 | CC30: =SUM(AQ30:AT30) -> 346.7 | CD30: =SUM(AU30:AX30) -> 499.7 | CE30: =SUM(AY30:BB30) -> 537.2 | CF30: =SUM(BC30:BF30) -> 625.9 | CG30: =SUM(BG30:BJ30) -> 768.2 | CH30: =CH29*(1-CH45) -> 929.27209 | CI30: =CI29*(1-CI45) -> 1100.3238 | CJ30: =CJ29*(1-CJ45) -> 1261.7297 | CK30: =CK29*(1-CK45) -> 1352.7659 | CL30: =CL29*(1-CL45) -> 1448.7552 | CM30: =CM29*(1-CM45) -> 1537.0513 | CN30: =CN29*(1-CN45) -> 1615.3896 | CO30: =CO29*(1-CO45) -> 1681.5984 | ... CQ30: =CQ29*(1-CQ45) -> 1801.2441
B31: GP | C31: =C29-C30 -> 13.533 | D31: =D29-D30 -> 14.538 | E31: =E29-E30 -> 18.561 | F31: =F29-F30 -> 20.08 | G31: =G29-G30 -> 20.296 | H31: =H29-H30 -> 22.331 | I31: =I29-I30 -> 24.39 | J31: =J29-J30 -> 25.319 | ... BL31: =BL29-BL30 -> 562.6 | BS31: =SUM(C31:F31) -> 66.712 | BT31: =SUM(G31:J31) -> 92.336 | BU31: =SUM(K31:N31) -> 112.401 | BV31: =SUM(O31:R31) -> 127.126 | BW31: =SUM(S31:V31) -> 133.271 | BX31: =SUM(W31:Z31) -> 211.086 | BY31: =SUM(AA31:AD31) -> 277.2 | BZ31: =SUM(AE31:AH31) -> 370.2 | CA31: =SUM(AI31:AL31) -> 480.3 | CB31: =SUM(AM31:AP31) -> 582.3 | CC31: =SUM(AQ31:AT31) -> 752.1 | CD31: =SUM(AU31:AX31) -> 805.6 | CE31: =SUM(AY31:BB31) -> 1159.9 | CF31: =SUM(BC31:BF31) -> 1445.7 | CG31: =SUM(BG31:BJ31) -> 1939.9 | CH31: =CH29*CH45 -> 2346.6479 | CI31: =CI29*CI45 -> 2629.5874 | CJ31: =CJ29*CJ45 -> 2875.089 | CK31: =CK29*CK45 -> 3156.4538 | CL31: =CL29*CL45 -> 3421.0101 | CM31: =CM29*CM45 -> 3673.2921 | CN31: =CN29*CN45 -> 3907.3098 | CO31: =CO29*CO45 -> 4117.0168 | ... CQ31: =CQ29*CQ45 -> 4409.9425
B32: R&D | C32: 4.589 | D32: 6.832 | E32: 4.638 | F32: 5.804 | G32: 5.432 | H32: 6.521 | I32: 6.559 | J32: 5.847 | K32: 4.396 | L32: 5.174 | M32: 5.771 | N32: 6.424 | O32: 6.779 | P32: 6.677 | Q32: 7.158 | R32: 7.286 | S32: 8.207 | T32: 12.069 | U32: 10.035 | V32: 12.897 | W32: 12.989 | X32: 12.953 | Y32: 13.734 | Z32: 16.034 | AA32: 17.5 | AB32: 18.029 | AC32: 20.141 | AD32: 20.03 | AE32: 20.267 | AF32: 18.801 | AG32: 22.336 | AH32: 33.396 | AI32: 32.5 | AJ32: 33 | AK32: 31.3 | AL32: 35.5 | AM32: 35.5 | AN32: 34.2 | AO32: 38.8 | AP32: 38.3 | AQ32: 40.7 | AR32: 40.1 | AS32: 37.5 | AT32: 41.8 | AU32: 43.1 | AV32: 42.6 | AW32: 45 | AX32: =180.2-SUM(AU32:AW32) -> 49.5 | AY32: 50.1 | AZ32: 55.1 | BA32: 57.8 | BB32: =205-SUM(AY32:BA32) -> 42 | BC32: 50.2 | BD32: 53.9 | BE32: 54.9 | BF32: =219.6-SUM(BC32:BE32) -> 60.6 | BG32: 59.6 | BH32: 73.4 | BI32: 77.2 | BJ32: =301.1-SUM(BG32:BI32) -> 90.9 | BK32: 89.7 | BL32: 88.1 | BS32: =SUM(C32:F32) -> 21.863 | BT32: =SUM(G32:J32) -> 24.359 | BU32: =SUM(K32:N32) -> 21.765 | BV32: =SUM(O32:R32) -> 27.9 | BW32: =SUM(S32:V32) -> 43.208 | BX32: =SUM(W32:Z32) -> 55.71 | BY32: =SUM(AA32:AD32) -> 75.7 | BZ32: =SUM(AE32:AH32) -> 94.8 | CA32: =SUM(AI32:AL32) -> 132.3 | CB32: =SUM(AM32:AP32) -> 146.8 | CC32: =SUM(AQ32:AT32) -> 160.1 | CD32: =SUM(AU32:AX32) -> 180.2 | CE32: =SUM(AY32:BB32) -> 205 | CF32: =SUM(BC32:BF32) -> 219.6 | CG32: =SUM(BG32:BJ32) -> 301.1 | CH32: =CH29*CH46 -> 364.23305 | CI32: =CI29*CI46 -> 428.93979 | CJ32: =CJ29*CJ46 -> 486.0762 | CK32: =CK29*CK46 -> 518.56026 | CL32: =CL29*CL46 -> 547.84859 | CM32: =CM29*CM46 -> 573.13778 | CN32: =CN29*CN46 -> 601.97423 | CO32: =CO29*CO46 -> 626.25044 | ... CQ32: =CQ29*CQ46 -> 658.38578
B33: SG&A | C33: 16.217 | D33: 22.621 | E33: 23.691 | F33: 24.787 | G33: 25.759 | H33: 26.329 | I33: 26.302 | J33: 25.558 | K33: 26.965 | L33: 27.481 | M33: 38.937 | N33: 26.388 | O33: 27.915 | P33: 34.368 | Q33: 33.76 | R33: 12.057 | S33: 28.252 | T33: 32.505 | U33: 36.33 | V33: 41.712 | W33: 38.761 | X33: 38.792 | Y33: 39.489 | Z33: 49.038 | AA33: 47.206 | AB33: 49.968 | AC33: 51.436 | AD33: 60.29 | AE33: 55.548 | AF33: 58.946 | AG33: 72.768 | AH33: 60.738 | AI33: 66.9 | AJ33: 75.8 | AK33: 74.8 | AL33: 80.5 | AM33: 83.9 | AN33: 80.8 | AO33: 89.2 | AP33: 130.1 | AQ33: 110.5 | AR33: 116.3 | AS33: 117.5 | AT33: 121.7 | AU33: 128.7 | AV33: 174.4 | AW33: 140.4 | AX33: =587.8-SUM(AU33:AW33) -> 144.3 | AY33: 162.7 | AZ33: 178.7 | BA33: 180.7 | BB33: =734.8-SUM(AY33:BA33) -> 212.7 | BC33: 199.7 | BD33: 222.4 | BE33: 234.1 | BF33: =917.2-SUM(BC33:BE33) -> 261 | BG33: 260.7 | BH33: 257.7 | BI33: 315.2 | BJ33: =1165-SUM(BG33:BI33) -> 331.4 | BK33: 317.2 | BL33: 344.8 | BS33: =SUM(C33:F33) -> 87.316 | BT33: =SUM(G33:J33) -> 103.948 | BU33: =SUM(K33:N33) -> 119.771 | BV33: =SUM(O33:R33) -> 108.1 | BW33: =SUM(S33:V33) -> 138.799 | BX33: =SUM(W33:Z33) -> 166.08 | BY33: =SUM(AA33:AD33) -> 208.9 | BZ33: =SUM(AE33:AH33) -> 248 | CA33: =SUM(AI33:AL33) -> 298 | CB33: =SUM(AM33:AP33) -> 384 | CC33: =SUM(AQ33:AT33) -> 466 | CD33: =SUM(AU33:AX33) -> 587.8 | CE33: =SUM(AY33:BB33) -> 734.8 | CF33: =SUM(BC33:BF33) -> 917.2 | CG33: =SUM(BG33:BJ33) -> 1165 | CH33: =CH29*CH47 -> 1409.271 | CI33: =CI29*CI47 -> 1566.5627 | CJ33: =CJ29*CJ47 -> 1716.7798 | CK33: =CK29*CK47 -> 1860.0531 | CL33: =CL29*CL47 -> 1996.6037 | CM33: =CM29*CM47 -> 2123.2149 | CN33: =CN29*CN47 -> 2236.6932 | CO33: =CO29*CO47 -> 2333.9426 | ... CQ33: =CQ29*CQ47 -> 2484.4746
B34: OI | C34: =C31-SUM(C32:C33) -> -7.273 | D34: =D31-SUM(D32:D33) -> -14.915 | E34: =E31-SUM(E32:E33) -> -9.768 | F34: =F31-SUM(F32:F33) -> -10.511 | G34: =G31-SUM(G32:G33) -> -10.895 | H34: =H31-SUM(H32:H33) -> -10.519 | I34: =I31-SUM(I32:I33) -> -8.471 | J34: =J31-SUM(J32:J33) -> -6.086 | ... BL34: =BL31-SUM(BL32:BL33) -> 129.7 | BS34: =SUM(C34:F34) -> -42.467 | BT34: =SUM(G34:J34) -> -35.971 | BU34: =SUM(K34:N34) -> -29.135 | BV34: =SUM(O34:R34) -> -8.874 | BW34: =SUM(S34:V34) -> -48.736 | BX34: =SUM(W34:Z34) -> -10.704 | BY34: =SUM(AA34:AD34) -> -7.4 | BZ34: =SUM(AE34:AH34) -> 27.4 | CA34: =SUM(AI34:AL34) -> 50 | CB34: =SUM(AM34:AP34) -> 51.5 | CC34: =SUM(AQ34:AT34) -> 126 | CD34: =SUM(AU34:AX34) -> 37.6 | CE34: =SUM(AY34:BB34) -> 220.1 | CF34: =SUM(BC34:BF34) -> 308.9 | CG34: =SUM(BG34:BJ34) -> 473.8 | CH34: =CH31-SUM(CH32:CH33) -> 573.14386 | CI34: =CI31-SUM(CI32:CI33) -> 634.0849 | CJ34: =CJ31-SUM(CJ32:CJ33) -> 672.23304 | CK34: =CK31-SUM(CK32:CK33) -> 777.8404 | CL34: =CL31-SUM(CL32:CL33) -> 876.55774 | CM34: =CM31-SUM(CM32:CM33) -> 976.93939 | CN34: =CN31-SUM(CN32:CN33) -> 1068.6423 | CO34: =CO31-SUM(CO32:CO33) -> 1156.8237 | ... CQ34: =CQ31-SUM(CQ32:CQ33) -> 1267.0821
B35: Interest Expenses | C35: 0 | D35: 0 | E35: 0 | F35: 0 | G35: 0 | H35: 0 | I35: 0 | J35: 0 | K35: 0 | L35: 0 | M35: 0 | N35: 0 | O35: 0 | P35: 0 | Q35: 0 | R35: 0 | S35: 0 | T35: 0 | U35: 0 | V35: 0 | W35: 0 | X35: 0 | Y35: 0 | Z35: 0 | AA35: 0 | AB35: 0 | AC35: 0 | AD35: 0 | AE35: 0 | AF35: 0 | AG35: 0 | AH35: 0 | AI35: 0 | AJ35: 0 | AK35: 0 | AL35: 0 | AM35: 0 | AN35: 0 | AO35: 0 | AP35: 0 | AQ35: 0 | AR35: 0 | AS35: 0 | AT35: 0 | AU35: -8.9 | AV35: -8.3 | AW35: -6.8 | AX35: =-26.7-SUM(AU35:AW35) -> -2.7 | AY35: -9.4 | AZ35: -9.7 | BA35: -10.4 | BB35: =-36.2-SUM(AY35:BA35) -> -6.7 | BC35: -10.7 | BD35: -11 | BE35: -12.4 | BF35: =-42.7-SUM(BC35:BE35) -> -8.6 | BG35: -9.2 | BH35: -19.6 | BI35: -15.6 | BJ35: =-59.4-SUM(BG35:BI35) -> -15 | BK35: -14.7 | BL35: -13.5 | BS35: =SUM(C35:F35) -> 0 | BT35: =SUM(G35:J35) -> 0 | BU35: =SUM(K35:N35) -> 0 | BV35: =SUM(O35:R35) -> 0 | BW35: =SUM(S35:V35) -> 0 | BX35: =SUM(W35:Z35) -> 0 | BY35: =SUM(AA35:AD35) -> 0 | BZ35: =SUM(AE35:AH35) -> 0 | CA35: =SUM(AI35:AL35) -> 0 | CB35: =SUM(AM35:AP35) -> 0 | CC35: =SUM(AQ35:AT35) -> 0 | CD35: =SUM(AU35:AX35) -> -26.7 | CE35: =SUM(AY35:BB35) -> -36.2 | CF35: =SUM(BC35:BF35) -> -42.7 | CG35: =SUM(BG35:BJ35) -> -59.4 | CH35: =CG65*(-$CV$69) -> -104.7995 | CI35: =CH65*(-$CV$69) -> -97.987533 | CJ35: =CI65*(-$CV$69) -> -91.618343 | CK35: =CJ65*(-$CV$69) -> -85.663151 | CL35: =CK65*(-$CV$69) -> -80.095046 | CM35: =CL65*(-$CV$69) -> -74.888868 | CN35: =CM65*(-$CV$69) -> -70.021091 | CO35: =CN65*(-$CV$69) -> -65.46972 | ... CQ35: =CP65*(-$CV$69) -> -57.235266
B36: Interest Income | C36: 0 | D36: 0 | E36: 0 | F36: 0 | G36: 0 | H36: 0 | I36: 0 | J36: 0 | K36: 0 | L36: 0 | M36: 0 | N36: 0 | O36: 0 | P36: 0 | Q36: 0 | R36: 0 | S36: 0 | T36: 0 | U36: 0 | V36: 0 | W36: 0 | X36: 0 | Y36: 0 | Z36: 0 | AA36: 0 | AB36: 0 | AC36: 0 | AD36: 0 | AE36: 0 | AF36: 0 | AG36: 0 | AH36: 0 | AI36: 0 | AJ36: 0 | AK36: 0 | AL36: 0 | AM36: 0 | AN36: 0 | AO36: 0 | AP36: 0 | AQ36: 0 | AR36: 0 | AS36: 0 | AT36: 0 | AU36: 0 | AV36: 0 | AW36: 0 | AX36: =0-SUM(AU36:AW36) -> 0 | AY36: 6.5 | AZ36: 7.3 | BA36: 8.6 | BB36: =28.6-SUM(AY36:BA36) -> 6.2 | BC36: 9.4 | BD36: 9.3 | BE36: 10.5 | BF36: =39.5-SUM(BC36:BE36) -> 10.3 | BG36: 10.3 | BH36: 10.1 | BI36: 8.6 | BJ36: =34.7-SUM(BG36:BI36) -> 5.7 | BK36: 4.9 | BL36: 3.6 | BS36: =SUM(C36:F36) -> 0 | BT36: =SUM(G36:J36) -> 0 | BU36: =SUM(K36:N36) -> 0 | BV36: =SUM(O36:R36) -> 0 | BW36: =SUM(S36:V36) -> 0 | BX36: =SUM(W36:Z36) -> 0 | BY36: =SUM(AA36:AD36) -> 0 | BZ36: =SUM(AE36:AH36) -> 0 | CA36: =SUM(AI36:AL36) -> 0 | CB36: =SUM(AM36:AP36) -> 0 | CC36: =SUM(AQ36:AT36) -> 0 | CD36: =SUM(AU36:AX36) -> 0 | CE36: =SUM(AY36:BB36) -> 28.6 | CF36: =SUM(BC36:BF36) -> 39.5 | CG36: =SUM(BG36:BJ36) -> 34.7 | CH36: =CG52*$DA$52 -> 141.141 | CI36: =CH52*$DA$52 -> 194.10528 | CJ36: =CI52*$DA$52 -> 257.55989 | CK36: =CJ52*$DA$52 -> 330.39726 | CL36: =CK52*$DA$52 -> 419.25898 | CM36: =CL52*$DA$52 -> 524.9052 | CN36: =CM52*$DA$52 -> 648.90765 | CO36: =CN52*$DA$52 -> 792.07791 | ... CQ36: =CP52*$DA$52 -> 1139.0774
B37: Loss on Extinguishment of Debt | C37: 0 | D37: 0 | E37: 0 | F37: 0 | G37: 0 | H37: 0 | I37: 0 | J37: 0 | K37: 0 | L37: 0 | M37: 0 | N37: 0 | O37: 0 | P37: 0 | Q37: 0 | R37: 0 | S37: 0 | T37: 0 | U37: 0 | V37: 0 | W37: 0 | X37: 0 | Y37: 0 | Z37: 0 | AA37: 0 | AB37: 0 | AC37: 0 | AD37: 0 | AE37: 0 | AF37: 0 | AG37: 0 | AH37: 0 | AI37: 0 | AJ37: 0 | AK37: 0 | AL37: 0 | AM37: 0 | AN37: 0 | AO37: 0 | AP37: 0 | AQ37: 0 | AR37: 0 | AS37: 0 | AT37: 0 | AU37: 0 | AV37: 0 | AW37: 0 | AX37: =0-SUM(AU37:AW37) -> 0 | AY37: 0 | AZ37: 0 | BA37: 0 | BB37: =0-SUM(AY37:BA37) -> 0 | BC37: 0 | BD37: 0 | BE37: 0 | BF37: =0-SUM(BC37:BE37) -> 0 | BG37: -39.5 | BH37: -84.4 | BI37: 0 | BJ37: =-123.9-SUM(BG37:BI37) -> 0 | BK37: 0 | BL37: 0 | BS37: =SUM(C37:F37) -> 0 | BT37: =SUM(G37:J37) -> 0 | BU37: =SUM(K37:N37) -> 0 | BV37: =SUM(O37:R37) -> 0 | BW37: =SUM(S37:V37) -> 0 | BX37: =SUM(W37:Z37) -> 0 | BY37: =SUM(AA37:AD37) -> 0 | BZ37: =SUM(AE37:AH37) -> 0 | CA37: =SUM(AI37:AL37) -> 0 | CB37: =SUM(AM37:AP37) -> 0 | CC37: =SUM(AQ37:AT37) -> 0 | CD37: =SUM(AU37:AX37) -> 0 | CE37: =SUM(AY37:BB37) -> 0 | CF37: =SUM(BC37:BF37) -> 0 | CG37: =SUM(BG37:BJ37) -> -123.9 | CH37: 0 | CI37: 0 | CJ37: 0 | CK37: 0 | CL37: 0 | CM37: 0 | CN37: 0 | CO37: 0 | CP37: 0 | CQ37: 0
B38: Other Income | C38: -2.575 | D38: -4.508 | E38: -3.794 | F38: -3.699 | G38: -3.839 | H38: -3.888 | I38: -3.918 | J38: -4.039 | K38: -4.328 | L38: -4.579 | M38: -3.972 | N38: -2.86 | O38: -4.193 | P38: -23.779 | Q38: -7.948 | R38: -3.083 | S38: -3.152 | T38: -3.193 | U38: -3.146 | V38: -3.163 | W38: -2.926 | X38: -2.998 | Y38: -5.369 | Z38: -4.821 | AA38: -4.573 | AB38: -4.308 | AC38: -4.153 | AD38: -6.166 | AE38: -6.236 | AF38: -5.604 | AG38: -5.012 | AH38: -5.348 | AI38: -2.6 | AJ38: -5.7 | AK38: -15.9 | AL38: -11.3 | AM38: -10.1 | AN38: -10.1 | AO38: -10.4 | AP38: -11.2 | AQ38: -16 | AR38: -54.7 | AS38: -18.5 | AT38: -16.3 | AU38: 0.3 | AV38: -1.1 | AW38: -1.8 | AX38: =-1.1-SUM(AU38:AW38) -> 1.5 | AY38: -0.2 | AZ38: -0.2 | BA38: 0.7 | BB38: =2.2-SUM(AY38:BA38) -> 1.9 | BC38: -0.7 | BD38: -1.8 | BE38: -3.4 | BF38: =-5.5-SUM(BC38:BE38) -> 0.4 | BG38: -2.2 | BH38: 1.1 | BI38: 12.1 | BJ38: =14.3-SUM(BG38:BI38) -> 3.3 | BK38: 0.7 | BL38: -1.1 | BS38: =SUM(C38:F38) -> -14.576 | BT38: =SUM(G38:J38) -> -15.684 | BU38: =SUM(K38:N38) -> -15.739 | BV38: =SUM(O38:R38) -> -39.003 | BW38: =SUM(S38:V38) -> -12.654 | BX38: =SUM(W38:Z38) -> -16.114 | BY38: =SUM(AA38:AD38) -> -19.2 | BZ38: =SUM(AE38:AH38) -> -22.2 | CA38: =SUM(AI38:AL38) -> -35.5 | CB38: =SUM(AM38:AP38) -> -41.8 | CC38: =SUM(AQ38:AT38) -> -105.5 | CD38: =SUM(AU38:AX38) -> -1.1 | CE38: =SUM(AY38:BB38) -> 2.2 | CF38: =SUM(BC38:BF38) -> -5.5 | CG38: =SUM(BG38:BJ38) -> 14.3 | CH38: 0 | CI38: 0 | CJ38: 0 | CK38: 0 | CL38: 0 | CM38: 0 | CN38: 0 | CO38: 0 | CP38: 0 | CQ38: 0
B39: Pretax Income | C39: =C34+SUM(C35:C38) -> -9.848 | D39: =D34+SUM(D35:D38) -> -19.423 | E39: =E34+SUM(E35:E38) -> -13.562 | F39: =F34+SUM(F35:F38) -> -14.21 | G39: =G34+SUM(G35:G38) -> -14.734 | H39: =H34+SUM(H35:H38) -> -14.407 | I39: =I34+SUM(I35:I38) -> -12.389 | J39: =J34+SUM(J35:J38) -> -10.125 | ... BL39: =BL34+SUM(BL35:BL38) -> 118.7 | BS39: =SUM(C39:F39) -> -57.043 | BT39: =SUM(G39:J39) -> -51.655 | BU39: =SUM(K39:N39) -> -44.874 | BV39: =SUM(O39:R39) -> -47.877 | BW39: =SUM(S39:V39) -> -61.39 | BX39: =SUM(W39:Z39) -> -26.818 | BY39: =SUM(AA39:AD39) -> -26.6 | BZ39: =SUM(AE39:AH39) -> 5.2 | CA39: =SUM(AI39:AL39) -> 14.5 | CB39: =SUM(AM39:AP39) -> 9.7 | CC39: =SUM(AQ39:AT39) -> 20.5 | CD39: =SUM(AU39:AX39) -> 9.8 | CE39: =SUM(AY39:BB39) -> 214.7 | CF39: =SUM(BC39:BF39) -> 300.2 | CG39: =SUM(BG39:BJ39) -> 339.5 | CH39: =CH34+SUM(CH35:CH38) -> 609.48536 | CI39: =CI34+SUM(CI35:CI38) -> 730.20265 | CJ39: =CJ34+SUM(CJ35:CJ38) -> 838.17459 | CK39: =CK34+SUM(CK35:CK38) -> 1022.5745 | CL39: =CL34+SUM(CL35:CL38) -> 1215.7217 | CM39: =CM34+SUM(CM35:CM38) -> 1426.9557 | CN39: =CN34+SUM(CN35:CN38) -> 1647.5289 | CO39: =CO34+SUM(CO35:CO38) -> 1883.4319 | ... CQ39: =CQ34+SUM(CQ35:CQ38) -> 2348.9242
B40: Taxes | C40: 0 | D40: -11.339 | E40: 0 | F40: 0 | G40: 0.046 | H40: 0.069 | I40: 0.028 | J40: 0.069 | K40: 0.131 | L40: 0.118 | M40: 0.005 | N40: -0.154 | O40: 0.065 | P40: 0.052 | Q40: 0.021 | R40: -0.078 | S40: 0.024 | T40: 0.015 | U40: 0.044 | V40: 0.129 | W40: 0.1 | X40: 0.1 | Y40: 0.1 | Z40: 0.092 | AA40: 0.096 | AB40: 0.101 | AC40: 0.1 | AD40: -0.097 | AE40: 0.333 | AF40: 0.412 | AG40: 0.194 | AH40: 0.961 | AI40: 0.3 | AJ40: 0.5 | AK40: 0.3 | AL40: 1.8 | AM40: -0.5 | AN40: 3 | AO40: 1.8 | AP40: -1.4 | AQ40: 0.3 | AR40: -3.4 | AS40: 2.6 | AT40: 4.2 | AU40: 1.5 | AV40: -1.1 | AW40: -0.5 | AX40: =5.2-SUM(AU40:AW40) -> 5.3 | AY40: -0.8 | AZ40: -1.2 | BA40: -1.7 | BB40: =8.4-SUM(AY40:BA40) -> 12.1 | BC40: -3.4 | BD40: 137.5 | BE40: -5.4 | BF40: =-118.1-SUM(BC40:BE40) -> -246.8 | BG40: 12.7 | BH40: 5.9 | BI40: 35.2 | BJ40: =92.4-SUM(BG40:BI40) -> 38.6 | BK40: 21.9 | BL40: 23.7 | BS40: =SUM(C40:F40) -> -11.339 | BT40: =SUM(G40:J40) -> 0.212 | BU40: =SUM(K40:N40) -> 0.1 | BV40: =SUM(O40:R40) -> 0.06 | BW40: =SUM(S40:V40) -> 0.212 | BX40: =SUM(W40:Z40) -> 0.392 | BY40: =SUM(AA40:AD40) -> 0.2 | BZ40: =SUM(AE40:AH40) -> 1.9 | CA40: =SUM(AI40:AL40) -> 2.9 | CB40: =SUM(AM40:AP40) -> 2.9 | CC40: =SUM(AQ40:AT40) -> 3.7 | CD40: =SUM(AU40:AX40) -> 5.2 | CE40: =SUM(AY40:BB40) -> 8.4 | CF40: =SUM(BC40:BF40) -> -118.1 | CG40: =SUM(BG40:BJ40) -> 92.4 | CH40: =CH39*CH49 -> 127.99193 | CI40: =CI39*CI49 -> 153.34256 | CJ40: =CJ39*CJ49 -> 176.01666 | CK40: =CK39*CK49 -> 214.74065 | CL40: =CL39*CL49 -> 255.30155 | CM40: =CM39*CM49 -> 299.6607 | CN40: =CN39*CN49 -> 345.98107 | CO40: =CO39*CO49 -> 395.5207 | ... CQ40: =CQ39*CQ49 -> 493.27408
B41: Net Income | C41: =C39-C40 -> -9.848 | D41: =D39-D40 -> -8.084 | E41: =E39-E40 -> -13.562 | F41: =F39-F40 -> -14.21 | G41: =G39-G40 -> -14.78 | H41: =H39-H40 -> -14.476 | I41: =I39-I40 -> -12.417 | J41: =J39-J40 -> -10.194 | ... BL41: =BL39-BL40 -> 95 | BS41: =SUM(C41:F41) -> -45.704 | BT41: =SUM(G41:J41) -> -51.867 | BU41: =SUM(K41:N41) -> -44.974 | BV41: =SUM(O41:R41) -> -47.937 | BW41: =SUM(S41:V41) -> -61.602 | BX41: =SUM(W41:Z41) -> -27.21 | BY41: =SUM(AA41:AD41) -> -26.8 | BZ41: =SUM(AE41:AH41) -> 3.3 | CA41: =SUM(AI41:AL41) -> 11.6 | CB41: =SUM(AM41:AP41) -> 6.8 | CC41: =SUM(AQ41:AT41) -> 16.8 | CD41: =SUM(AU41:AX41) -> 4.6 | CE41: =SUM(AY41:BB41) -> 206.3 | CF41: =SUM(BC41:BF41) -> 418.3 | CG41: =SUM(BG41:BJ41) -> 247.1 | CH41: =CH39-CH40 -> 481.49344 | CI41: =CI39-CI40 -> 576.86009 | CJ41: =CJ39-CJ40 -> 662.15792 | CK41: =CK39-CK40 -> 807.83386 | CL41: =CL39-CL40 -> 960.42013 | CM41: =CM39-CM40 -> 1127.295 | CN41: =CN39-CN40 -> 1301.5478 | CO41: =CO39-CO40 -> 1487.9112 | ... CQ41: =CQ39-CQ40 -> 1855.6501 | CR41: =CQ41*(1+$DA$53) -> 1874.2066 | CS41: =CR41*(1+$DA$53) -> 1892.9487 | CT41: =CS41*(1+$DA$53) -> 1911.8782 | CU41: =CT41*(1+$DA$53) -> 1930.9969 | CV41: =CU41*(1+$DA$53) -> 1950.3069 | CW41: =CV41*(1+$DA$53) -> 1969.81 | CX41: =CW41*(1+$DA$53) -> 1989.5081 | CY41: =CX41*(1+$DA$53) -> 2009.4032 | ... EO41: =EN41*(1+$DA$53) -> 3051.8612
B42: SC | C42: 45.58 | D42: 46.38 | E42: 47.32 | F42: 47.42 | G42: 47.61 | H42: 47.82 | I42: 48.04 | J42: 48.22 | K42: 53.05 | L42: 53.83 | M42: 54.46 | N42: 54.68 | O42: 55.09 | P42: 55.43 | Q42: 55.82 | R42: 56.17 | S42: 56.5 | T42: 56.81 | U42: 56.9 | V42: 56.93 | W42: 57.03 | X42: 57.2 | Y42: 57.34 | Z42: 57.44 | AA42: 57.69 | AB42: 57.98 | AC42: 58.1 | AD42: 58.24 | AE42: 58.48 | AF42: 58.83 | AG42: 59.02 | AH42: 59.1 | AI42: 59.36 | AJ42: 59.85 | AK42: 60.74 | AL42: 62.4 | AM42: 62.88 | AN42: 64.37 | AO42: 65.72 | AP42: 65.95 | AQ42: 66.11 | AR42: 66.7 | AS42: 68.87 | AT42: 69.07 | AU42: 69.25 | AV42: 69.36 | AW42: 69.42 | AX42: 69.47 | AY42: 69.58 | AZ42: 69.74 | BA42: 69.82 | BB42: 69.86 | BC42: 69.96 | BD42: 70.06 | BE42: 70.12 | BF42: 70.27 | BG42: 70.272 | BH42: 70.37 | BI42: 70.367 | BJ42: 70.25 | BK42: 69.98 | BL42: 69.3 | BS42: =AVERAGE(C42:F42) -> 46.675 | BT42: =AVERAGE(G42:J42) -> 47.9225 | BU42: =AVERAGE(K42:N42) -> 54.005 | BV42: =AVERAGE(O42:R42) -> 55.6275 | BW42: =AVERAGE(S42:V42) -> 56.785 | BX42: =AVERAGE(W42:Z42) -> 57.2525 | BY42: =AVERAGE(AA42:AD42) -> 58.0025 | BZ42: =AVERAGE(AE42:AH42) -> 58.8575 | CA42: =AVERAGE(AI42:AL42) -> 60.5875 | CB42: =AVERAGE(AM42:AP42) -> 64.73 | CC42: =AVERAGE(AQ42:AT42) -> 67.6875 | CD42: =AVERAGE(AU42:AX42) -> 69.375 | CE42: =AVERAGE(AY42:BB42) -> 69.75 | CF42: =AVERAGE(BC42:BF42) -> 70.1025 | CG42: =AVERAGE(BG42:BJ42) -> 70.31475
B43: EPS | C43: =C41/C42 -> -0.21605968 | D43: =D41/D42 -> -0.17429927 | E43: =E41/E42 -> -0.28660186 | F43: =F41/F42 -> -0.29966259 | G43: =G41/G42 -> -0.31043898 | H43: =H41/H42 -> -0.30271853 | I43: =I41/I42 -> -0.25847211 | J43: =J41/J42 -> -0.21140606 | ... BL43: =BL41/BL42 -> 1.3708514 | BS43: =SUM(C43:F43) -> -0.97662339 | BT43: =SUM(G43:J43) -> -1.0830357 | BU43: =SUM(K43:N43) -> -0.83309792 | BV43: =SUM(O43:R43) -> -0.863701 | BW43: =SUM(S43:V43) -> -1.0842689 | BX43: =SUM(W43:Z43) -> -0.47546706 | BY43: =SUM(AA43:AD43) -> -0.46248735 | BZ43: =SUM(AE43:AH43) -> 0.054565887 | CA43: =SUM(AI43:AL43) -> 0.1908149 | CB43: =SUM(AM43:AP43) -> 0.1075288 | CC43: =SUM(AQ43:AT43) -> 0.23090032 | CD43: =SUM(AU43:AX43) -> 0.066634013 | CE43: =SUM(AY43:BB43) -> 2.9556979 | CF43: =SUM(BC43:BF43) -> 5.9554265 | CG43: =SUM(BG43:BJ43) -> 3.5146604
B45: Gross Profit Margin | C45: =C31/C29 -> 0.47890863 | D45: =D31/D29 -> 0.4513365 | E45: =E31/E29 -> 0.41622191 | F45: =F31/F29 -> 0.42549585 | G45: =G31/G29 -> 0.42501152 | H45: =H31/H29 -> 0.43756246 | I45: =I31/I29 -> 0.44546318 | J45: =J31/J29 -> 0.43783288 | ... BL45: =BL31/BL29 -> 0.70175876 | BS45: =BS31/BS29 -> 0.43815967 | BT45: =BT31/BT29 -> 0.43684741 | BU45: =BU31/BU29 -> 0.45491007 | BV45: =BV31/BV29 -> 0.54956532 | BW45: =BW31/BW29 -> 0.50501908 | BX45: =BX31/BX29 -> 0.57518345 | BY45: =BY31/BY29 -> 0.59767141 | BZ45: =BZ31/BZ29 -> 0.65661582 | ... CG45: =CG31/CG29 -> 0.71633248 | CH45: 0.71633248 | CI45: 0.705 | CJ45: 0.695 | CK45: 0.7 | CL45: 0.7025 | CM45: 0.705 | CN45: 0.7075 | CO45: 0.71 | CP45: 0.71 | CQ45: 0.71
B46: R&D as % of Revenue | C46: =C32/C29 -> 0.16239649 | D46: =D32/D29 -> 0.21210146 | E46: =E32/E29 -> 0.10400502 | F46: =F32/F29 -> 0.12298695 | G46: =G32/G29 -> 0.11374963 | H46: =H32/H29 -> 0.12777506 | I46: =I32/I29 -> 0.11979471 | J46: =J32/J29 -> 0.10111019 | ... BL46: =BL32/BL29 -> 0.10989148 | BS46: =BS32/BS29 -> 0.14359463 | BT46: =BT32/BT29 -> 0.11524396 | BU46: =BU32/BU29 -> 0.088087452 | BV46: =BV32/BV29 -> 0.12061162 | BW46: =BW32/BW29 -> 0.16373303 | BX46: =BX32/BX29 -> 0.15180292 | BY46: =BY32/BY29 -> 0.1632169 | BZ46: =BZ32/BZ29 -> 0.16814473 | ... CG46: =CG32/CG29 -> 0.11118496 | CH46: 0.11118496 | CI46: 0.115 | CJ46: 0.1175 | CK46: 0.115 | CL46: 0.1125 | CM46: 0.11 | CN46: 0.109 | CO46: 0.108 | CP46: 0.107 | CQ46: 0.106
B47: SG&A as % of Revenue | C47: =C33/C29 -> 0.57389058 | D47: =D33/D29 -> 0.70227562 | E47: =E33/E29 -> 0.53125981 | F47: =F33/F29 -> 0.52523733 | G47: =G33/G29 -> 0.53941031 | H47: =H33/H29 -> 0.51590085 | I47: =I33/I29 -> 0.48038428 | J47: =J33/J29 -> 0.44196583 | ... BL47: =BL33/BL29 -> 0.43008607 | BS47: =BS33/BS29 -> 0.57348527 | BT47: =BT33/BT29 -> 0.49178451 | BU47: =BU33/BU29 -> 0.48473798 | BV47: =BV33/BV29 -> 0.46731598 | BW47: =BW33/BW29 -> 0.52596696 | BX47: =BX33/BX29 -> 0.45254762 | BY47: =BY33/BY29 -> 0.45040966 | BZ47: =BZ33/BZ29 -> 0.4398723 | ... CG47: =CG33/CG29 -> 0.43019091 | CH47: 0.43019091 | CI47: 0.42 | CJ47: 0.415 | CK47: 0.4125 | CL47: 0.41 | CM47: 0.4075 | CN47: 0.405 | CO47: 0.4025 | CP47: 0.4015 | CQ47: 0.4
B48: Operating Profit Margin | C48: =C34/C29 -> -0.25737844 | D48: =D34/D29 -> -0.46304058 | E48: =E34/E29 -> -0.21904292 | F48: =F34/F29 -> -0.22272843 | G48: =G34/G29 -> -0.22814843 | H48: =H34/H29 -> -0.20611345 | I48: =I34/I29 -> -0.15471581 | J48: =J34/J29 -> -0.10524313 | ... BL48: =BL34/BL29 -> 0.16178121 | BS48: =BS34/BS29 -> -0.27892023 | BT48: =BT34/BT29 -> -0.17018106 | BU48: =BU34/BU29 -> -0.11791536 | BV48: =BV34/BV29 -> -0.038362276 | BW48: =BW34/BW29 -> -0.18468091 | BX48: =BX34/BX29 -> -0.029167087 | BY48: =BY34/BY29 -> -0.015955153 | BZ48: =BZ34/BZ29 -> 0.048598794 | ... CQ48: =CQ34/CQ29 -> 0.204
B49: Effective Tax Rate | C49: =C40/C39 -> 0 | D49: =D40/D39 -> 0.58379241 | E49: =E40/E39 -> 0 | F49: =F40/F39 -> 0 | G49: =G40/G39 -> -0.0031220307 | H49: =H40/H39 -> -0.0047893385 | I49: =I40/I39 -> -0.0022600694 | J49: =J40/J39 -> -0.0068148148 | ... BL49: =BL40/BL39 -> 0.19966302 | BS49: =BS40/BS39 -> 0.19877987 | BT49: =BT40/BT39 -> -0.0041041526 | BU49: =BU40/BU39 -> -0.0022284619 | BV49: =BV40/BV39 -> -0.0012532114 | BW49: =BW40/BW39 -> -0.0034533312 | BX49: =BX40/BX39 -> -0.014617048 | BY49: =BY40/BY39 -> -0.007518797 | BZ49: =BZ40/BZ39 -> 0.36538462 | ... CG49: =CG40/CG39 -> 0.27216495 | CH49: 0.21 | CI49: 0.21 | CJ49: 0.21 | CK49: 0.21 | CL49: 0.21 | CM49: 0.21 | CN49: 0.21 | CO49: 0.21 | CP49: 0.21 | CQ49: 0.21
B50: Net Profit Margin | C50: =C41/C29 -> -0.34850308 | D50: =D41/D29 -> -0.25097017 | E50: =E41/E29 -> -0.30412163 | F50: =F41/F29 -> -0.30111036 | G50: =G41/G29 -> -0.30950287 | H50: =H41/H29 -> -0.28364848 | I50: =I41/I29 -> -0.22678624 | J50: =J41/J29 -> -0.17628139 | ... BL50: =BL41/BL29 -> 0.11849819 | BS50: =BS41/BS29 -> -0.30018062 | BT50: =BT41/BT29 -> -0.24538603 | BU50: =BU41/BU29 -> -0.18201907 | BV50: =BV41/BV29 -> -0.20723151 | BW50: =BW41/BW29 -> -0.23343552 | BX50: =BX41/BX29 -> -0.074143912 | BY50: =BY41/BY29 -> -0.057783527 | BZ50: =BZ41/BZ29 -> 0.0058531394 | ... CQ50: =CQ41/CQ29 -> 0.29875936
B52: Cash & CEs | BB52: 704.2 | BC52: 751.2 | BD52: 821 | BE52: 902.6 | BF52: 953.4 | BG52: 1283.1 | BH52: 1121.6 | BI52: 757.4 | BJ52: 716.1 | BK52: 480.4 | BL52: 534.9 | CE52: =BB52 -> 704.2 | CF52: =BF52 -> 953.4 | CG52: =BG52 -> 1283.1 | CH52: =CG52+CH41 -> 1764.5934 | CI52: =CH52+CI41 -> 2341.4535 | CJ52: =CI52+CJ41 -> 3003.6115 | CK52: =CJ52+CK41 -> 3811.4453 | CL52: =CK52+CL41 -> 4771.8654 | CM52: =CL52+CM41 -> 5899.1605 | CN52: =CM52+CN41 -> 7200.7083 | CO52: =CN52+CO41 -> 8688.6195 | ... CQ52: =CP52+CQ41 -> 12210.899 | CS52: Invested Capital | CV52: Avg. (2024-2025) | CX52: Projected ROIC: | CZ52: ROIC | DA52: 0.11
B53: A/R | BB53: =240.2+119.5 -> 359.7 | BC53: =234.1+86.4 -> 320.5 | BD53: =249+99.6 -> 348.6 | BE53: =261.7+113.9 -> 375.6 | BF53: =252.5+113 -> 365.5 | BG53: =283.1+119.2 -> 402.3 | BH53: =306.4+138.1 -> 444.5 | BI53: =306.5+155.7 -> 462.2 | BJ53: 516.9 | BK53: 544.7 | BL53: 588.7 | CE53: =BB53 -> 359.7 | CF53: =BF53 -> 365.5 | CG53: =BG53 -> 402.3 | CS53: 2024 | CT53: 2025 | CV53: 2024-2025 | CX53: 2025 | CZ53: Terminal | DA53: 0.01
B54: Inventories | BB54: 402.6 | BC54: 430.6 | BD54: 430.9 | BE54: 444.9 | BF54: 430.4 | BG54: 440.8 | BH54: 446.9 | BI54: 446.3 | BJ54: 452.6 | BK54: 462.5 | BL54: 484.8 | CE54: =BB54 -> 402.6 | CF54: =BF54 -> 430.4 | CG54: =BG54 -> 440.8 | CS54: =SUM(CF52:CF55)-CF62+CF56+CF58+CF57 -> 2744.7 | CT54: =SUM(CG52:CG55)-CG62+CG56+CG58+CG57 -> 3140.8 | CV54: =AVERAGE(CS54:CT54) -> 2942.75 | CX54: =AVERAGE(CH34)*(1-CH49) -> 452.78365 | CZ54: RFR (10-year yield) | DA54: =CV63 -> 0.0512
B55: Other ST Expenses | BB55: 116.4 | BC55: 116.1 | BD55: 148.3 | BE55: 137.8 | BF55: =50.6+91.5 -> 142.1 | BG55: 202.2 | BH55: 266.7 | BI55: =72.6+120.8 -> 193.4 | BJ55: 228.3 | BK55: 221.9 | BL55: 240.6 | CE55: =BB55 -> 116.4 | CF55: =BF55 -> 142.1 | CG55: =BG55 -> 202.2 | CX55: =CX54/CV54 -> 0.15386412 | CZ55: ERP (Avg. market return - (less) RFR) | DA55: =12.5%-DA54 -> 0.0738
B56: PP&E | BB56: 664.9 | BC56: 667.7 | BD56: 677.9 | BE56: 702.9 | BF56: 723.1 | BG56: 718.7 | BH56: 720.4 | BI56: 724.1 | BJ56: 819.5 | BK56: 830.4 | BL56: 858.6 | CE56: =BB56 -> 664.9 | CF56: =BF56 -> 723.1 | CG56: =BG56 -> 718.7 | CS56: Capital Structure | CZ56: Equity β (1-year avg.) | DA56: ='Notes | Quant Analysis'!S206 -> 0.45014704
B57: Intangibles | BB57: 98.7 | BC57: 98.5 | BD57: 98.5 | BE57: 99.6 | BF57: 98.5 | BG57: 99.8 | BH57: 102.3 | BI57: 105.1 | BJ57: 117.2 | BK57: 115.1 | BL57: 115.1 | CE57: =BB57 -> 98.7 | CF57: =BF57 -> 98.5 | CG57: =BG57 -> 99.8 | CS57: Mkt Cap | CV57: =Main!C5 -> 12897.191 | CZ57: Discount (Cost of Equity) | DA57: =+DA54+(DA55*DA56) -> 0.084420851
B58: Goodwill | BB58: 51.7 | BC58: 51.7 | BD58: 51.7 | BE58: 51.7 | BF58: 51.5 | BG58: 51.5 | BH58: 51.7 | BI58: 51.6 | BJ58: 51.6 | BK58: 51.6 | BL58: 51.6 | CE58: =BB58 -> 51.7 | CF58: =BF58 -> 51.5 | CG58: =BG58 -> 51.5 | CS58: Debt to Ttl Mkt Cap | CV58: =Main!C7/(Main!C7+CV57) -> 0.068498339
B59: Other LT Assets | BB59: =1.8+188.2 -> 190 | BC59: 187.7 | BD59: =141.1+163.6 -> 304.7 | BE59: =144.4+165.9 -> 310.3 | BF59: =141.8+181.6 -> 323.4 | BG59: 318.9 | BH59: 315.1 | BI59: =100.9+188.3 -> 289.2 | BJ59: 288.3 | BK59: 280.6 | BL59: 290.8 | CE59: =BB59 -> 190 | CF59: =BF59 -> 323.4 | CG59: =BG59 -> 318.9 | CS59: Mkt Equity to Ttl Mkt Cap | CV59: =CV57/(CV57+Main!C7) -> 0.93150166 | CZ59: NPV | DA59: =NPV(DA57,CH41:EE41) -> 17062.72
B60: Ttl Assets | BB60: =SUM(BB52:BB59) -> 2588.2 | BC60: =SUM(BC52:BC59) -> 2624 | BD60: =SUM(BD52:BD59) -> 2881.6 | BE60: =SUM(BE52:BE59) -> 3025.4 | BF60: =SUM(BF52:BF59) -> 3087.9 | BG60: =SUM(BG52:BG59) -> 3517.3 | BH60: =SUM(BH52:BH59) -> 3469.2 | BI60: =SUM(BI52:BI59) -> 3029.3 | ... BL60: =SUM(BL52:BL59) -> 3165.1 | CE60: =BB60 -> 2588.2 | CF60: =BF60 -> 3087.9 | CG60: =BG60 -> 3517.3 | CS60: LT Debt / Equity | CV60: =CG65/CG68 -> 1.2116179 | CZ60: SC | DA60: =Main!C4 -> 96.298
CZ61: FV | DA61: =DA59/DA60 -> 177.18665
B62: A/P | BB62: 19.2 | BC62: 75.9 | BD62: 76.8 | BE62: 40.3 | BF62: 19.8 | BG62: 57.6 | BH62: 96.1 | BI62: 48.2 | BJ62: 75 | BK62: 149.8 | BL62: 123.3 | CE62: =BB62 -> 19.2 | CF62: =BF62 -> 19.8 | CG62: =BG62 -> 57.6 | CS62: Cost of Equity | CZ62: CP | DA62: =Main!C3 -> 133.93
B63: ST Expenses & Other Liabilities | BB63: =373.7+8.9 -> 382.6 | BC63: =308.6+9 -> 317.6 | BD63: =365+6.3 -> 371.3 | BE63: =414.2+9.7 -> 423.9 | BF63: =423.9+1 -> 424.9 | BG63: =378.6+1.1 -> 379.7 | BH63: 453.4 | BI63: =518.7+0.9 -> 519.6 | BJ63: 586.7 | BK63: 519 | BL63: 602 | CE63: =BB63 -> 382.6 | CF63: =BF63 -> 424.9 | CG63: =BG63 -> 379.7 | CS63: RFR (10-year yield) | CV63: 0.0512 | CZ63: Change Δ | DA63: =DA61/DA62-1 -> 0.32297955 | DB63: =IF(DA63>0,"Upside","Downside") -> Upside
B64: ST Debt | BB64: 49.4 | BC64: 38.9 | BD64: 37.9 | BE64: 42 | BF64: 83.8 | BG64: 83.1 | BH64: 460.7 | BI64: 79.9 | BJ64: 18.4 | BK64: 18.6 | BL64: 18.9 | CE64: =BB64 -> 49.4 | CF64: =BF64 -> 83.8 | CG64: =BG64 -> 83.1 | CS64: Equity β (1-year avg.) | CV64: ='Notes | Quant Analysis'!S206 -> 0.45014704 | CZ64: {=_xlfn.IFS(DA63>=25%,"Strong Buy",DA63>=10.00001%,"Buy",AND(DA63<=10%,DA63>=-4.9999%),"Hold",AND(DA63<=-5%,DA63>=-14.999999%),"Sell",DA63<=-15%,"Strong Sell")} -> Strong Buy
B65: LT Debt | BB65: 1366.4 | BC65: 1362.6 | BD65: 1359.9 | BE65: 1356.3 | BF65: 1296.1 | BG65: 1612.3 | BH65: 939 | BI65: 934.9 | BJ65: 930.8 | BK65: 929.5 | BL65: 929.5 | CE65: =BB65 -> 1366.4 | CF65: =BF65 -> 1296.1 | CG65: =BG65 -> 1612.3 | CH65: =CG65+CH35 -> 1507.5005 | CI65: =CH65+CI35 -> 1409.513 | CJ65: =CI65+CJ35 -> 1317.8946 | CK65: =CJ65+CK35 -> 1232.2315 | CL65: =CK65+CL35 -> 1152.1364 | CM65: =CL65+CM35 -> 1077.2476 | CN65: =CM65+CN35 -> 1007.2265 | CO65: =CN65+CO35 -> 941.75675 | ... CQ65: =CP65+CQ35 -> 823.30729 | CS65: Market Return(1-year avg.) | CV65: 0.19
B66: Other LT Liabilities | BB66: 37.9 | BC66: 38.3 | BD66: 37.3 | BE66: 44.9 | BF66: 51.7 | BG66: 53.9 | BH66: 57.1 | BI66: 62.6 | BJ66: 64.4 | BK66: 67.7 | BL66: 69.2 | CE66: =BB66 -> 37.9 | CF66: =BF66 -> 51.7 | CG66: =BG66 -> 53.9 | CS66: Cost of Equity | CV66: =(CV63+CV64)*(CV65-CV63) -> 0.069586969
B67: Ttl Liabilities | BB67: =SUM(BB62:BB66) -> 1855.5 | BC67: =SUM(BC62:BC66) -> 1833.3 | BD67: =SUM(BD62:BD66) -> 1883.2 | BE67: =SUM(BE62:BE66) -> 1907.4 | BF67: =SUM(BF62:BF66) -> 1876.3 | BG67: =SUM(BG62:BG66) -> 2186.6 | BH67: =SUM(BH62:BH66) -> 2006.3 | BI67: =SUM(BI62:BI66) -> 1645.2 | ... BL67: =SUM(BL62:BL66) -> 1742.9 | CE67: =BB67 -> 1855.5 | CF67: =BF67 -> 1876.3 | CG67: =BG67 -> 2186.6
B68: Ttl SE | BB68: 732.7 | BC68: 790.7 | BD68: 998.4 | BE68: 1118 | BF68: 1211.6 | BG68: 1330.7 | BH68: 1462.9 | BI68: 1384.1 | BJ68: 1515.2 | BK68: 1302.6 | BL68: 1422.2 | CE68: =BB68 -> 732.7 | CF68: =BF68 -> 1211.6 | CG68: =BG68 -> 1330.7 | CS68: Cost of Debt
B69: Ttl L + SE | BB69: =BB67+BB68 -> 2588.2 | BC69: =BC67+BC68 -> 2624 | BD69: =BD67+BD68 -> 2881.6 | BE69: =BE67+BE68 -> 3025.4 | BF69: =BF67+BF68 -> 3087.9 | BG69: =BG67+BG68 -> 3517.3 | BH69: =BH67+BH68 -> 3469.2 | BI69: =BI67+BI68 -> 3029.3 | ... BL69: =BL67+BL68 -> 3165.1 | CE69: =BB69 -> 2588.2 | CF69: =BF69 -> 3087.9 | CG69: =BG69 -> 3517.3 | CS69: Cost of Debt | CV69: 0.065
CS70: Tax Rate | CV70: 0.23
B71: Current Ratio | BB71: =SUM(BB52:BB55)/SUM(BB62:BB64) -> 3.5082004 | BC71: =SUM(BC52:BC55)/SUM(BC62:BC64) -> 3.7428307 | BD71: =SUM(BD52:BD55)/SUM(BD62:BD64) -> 3.5983539 | BE71: =SUM(BE52:BE55)/SUM(BE62:BE64) -> 3.6762149 | BF71: =SUM(BF52:BF55)/SUM(BF62:BF64) -> 3.5788079 | BG71: =SUM(BG52:BG55)/SUM(BG62:BG64) -> 4.4742506 | BH71: =SUM(BH52:BH55)/SUM(BH62:BH64) -> 2.2566818 | BI71: =SUM(BI52:BI55)/SUM(BI62:BI64) -> 2.8706191 | ... BL71: =SUM(BL52:BL55)/SUM(BL62:BL64) -> 2.4845472 | CE71: =SUM(CE52:CE55)/SUM(CE62:CE64) -> 3.5082004 | CF71: =SUM(CF52:CF55)/SUM(CF62:CF64) -> 3.5788079 | CG71: =SUM(CG52:CG55)/SUM(CG62:CG64) -> 4.4742506 | CS71: After Tax Cost of Debt | CV71: =CV69*(1-CV70) -> 0.05005
B72: Quick Ratio | BB72: =(SUM(BB52:BB55)-BB54)/SUM(BB62:BB64) -> 2.6159131 | BC72: =(SUM(BC52:BC55)-BC54)/SUM(BC62:BC64) -> 2.7469935 | BD72: =(SUM(BD52:BD55)-BD54)/SUM(BD62:BD64) -> 2.7117284 | BE72: =(SUM(BE52:BE55)-BE54)/SUM(BE62:BE64) -> 2.7973133 | BF72: =(SUM(BF52:BF55)-BF54)/SUM(BF62:BF64) -> 2.7644276 | BG72: =(SUM(BG52:BG55)-BG54)/SUM(BG62:BG64) -> 3.6272098 | BH72: =(SUM(BH52:BH55)-BH54)/SUM(BH62:BH64) -> 1.8142942 | BI72: =(SUM(BI52:BI55)-BI54)/SUM(BI62:BI64) -> 2.1815655 | ... BL72: =(SUM(BL52:BL55)-BL54)/SUM(BL62:BL64) -> 1.8331094 | CE72: =(SUM(CE52:CE55)-CE54)/SUM(CE62:CE64) -> 2.6159131 | CF72: =(SUM(CF52:CF55)-CF54)/SUM(CF62:CF64) -> 2.7644276 | CG72: =(SUM(CG52:CG55)-CG54)/SUM(CG62:CG64) -> 3.6272098
B73: Cash Ratio | BB73: =SUM(BB52)/SUM(BB62:BB64) -> 1.560727 | BC73: =SUM(BC52)/SUM(BC62:BC64) -> 1.7372803 | BD73: =SUM(BD52)/SUM(BD62:BD64) -> 1.6893004 | BE73: =SUM(BE52)/SUM(BE62:BE64) -> 1.7830897 | BF73: =SUM(BF52)/SUM(BF62:BF64) -> 1.8039735 | BG73: =SUM(BG52)/SUM(BG62:BG64) -> 2.4656034 | BH73: =SUM(BH52)/SUM(BH62:BH64) -> 1.1102752 | BI73: =SUM(BI52)/SUM(BI62:BI64) -> 1.1693685 | ... BL73: =SUM(BL52)/SUM(BL62:BL64) -> 0.7187584 | CE73: =SUM(CE52)/SUM(CE62:CE64) -> 1.560727 | CF73: =SUM(CF52)/SUM(CF62:CF64) -> 1.8039735 | CG73: =SUM(CG52)/SUM(CG62:CG64) -> 2.4656034 | CS73: WACC | CV73: =(CV59*CV66)+(CV58*CV71*(1-CV70)) -> 0.0674602
B74: Fixed Asset Turnover Ratio | BB74: =BB29/SUM(BB56) -> 0.76673184 | BC74: =BC29/SUM(BC56) -> 0.66152464 | BD74: =BD29/SUM(BD56) -> 0.72060776 | BE74: =BE29/SUM(BE56) -> 0.77365201 | BF74: =BF29/SUM(BF56) -> 0.82644171 | BG74: =BG29/SUM(BG56) -> 0.79156811 | BH74: =BH29/SUM(BH56) -> 0.90116602 | BI74: =BI29/SUM(BI56) -> 0.97541776 | ... BL74: =BL29/SUM(BL56) -> 0.93372933 | CE74: =CE29/SUM(CE56) -> 2.5524139 | CF74: =CF29/SUM(CF56) -> 2.8648873 | CG74: =CG29/SUM(CG56) -> 3.7680534
B75: Ttl Asset Turnover Ratio | BB75: =BB29/BB60 -> 0.19697087 | BC75: =BC29/BC60 -> 0.16833079 | BD75: =BD29/BD60 -> 0.16952388 | BE75: =BE29/BE60 -> 0.17974483 | BF75: =BF29/BF60 -> 0.19352958 | BG75: =BG29/BG60 -> 0.16174338 | BH75: =BH29/BH60 -> 0.18713248 | BI75: =BI29/BI60 -> 0.23315617 | ... BL75: =BL29/BL60 -> 0.25329373 | CE75: =CE29/CE60 -> 0.65570667 | CF75: =CF29/CF60 -> 0.67087665 | CG75: =CG29/CG60 -> 0.76993717
B76: Inventory Turnover Ratio | BB76: =BB28/AVERAGE(AY54:BB54) -> 0 | BC76: =BC28/AVERAGE(AZ54:BC54) -> 0 | BD76: =BD28/AVERAGE(BA54:BD54) -> 0 | BE76: =BE28/AVERAGE(BB54:BE54) -> 0 | BF76: =BF28/AVERAGE(BC54:BF54) -> 0 | BG76: =BG28/AVERAGE(BD54:BG54) -> 0 | BH76: =BH28/AVERAGE(BE54:BH54) -> 0 | BI76: =BI28/AVERAGE(BF54:BI54) -> 0 | ... BL76: =BL28/AVERAGE(BI54:BL54) -> 0 | CE76: =CE28/AVERAGE(CB54:CE54) -> 0 | CF76: =CF28/AVERAGE(CC54:CF54) -> 0 | CG76: =CG28/AVERAGE(CD54:CG54) -> 0
B77: Return on Assets | BB77: =BB41/BB60 -> 0.037014141 | BC77: =BC41/BC60 -> 0.022217988 | BD77: =BD41/BD60 -> -0.029983343 | BE77: =BE41/BE60 -> 0.029120116 | BF77: =BF41/BF60 -> 0.11603355 | BG77: =BG41/BG60 -> 0.010064538 | BH77: =BH41/BH60 -> 0.0064856451 | BI77: =BI41/BI60 -> 0.028917572 | ... BL77: =BL41/BL60 -> 0.030014849 | CE77: =CE41/CE60 -> 0.079707905 | CF77: =CF41/CF60 -> 0.13546423 | CG77: =CG41/CG60 -> 0.070252751
B78: Return on Equity | BB78: =BB41/BB68 -> 0.13074928 | BC78: =BC41/BC68 -> 0.073732136 | BD78: =BD41/BD68 -> -0.086538462 | BE78: =BE41/BE68 -> 0.078801431 | BF78: =BF41/BF68 -> 0.29572466 | BG78: =BG41/BG68 -> 0.02660254 | BH78: =BH41/BH68 -> 0.015380409 | BI78: =BI41/BI68 -> 0.063290225 | ... BL78: =BL41/BL68 -> 0.066797919 | CE78: =CE41/CE68 -> 0.28156135 | CF78: =CF41/CF68 -> 0.34524596 | CG78: =CG41/CG68 -> 0.18569174
B80: Net Income | C80: =C41 -> -9.848 | D80: =D41 -> -8.084 | E80: =E41 -> -13.562 | F80: =F41 -> -14.21 | G80: =G41 -> -14.78 | H80: =H41 -> -14.476 | I80: =I41 -> -12.417 | J80: =J41 -> -10.194 | ... BL80: =BL41 -> 95 | BS80: =BS41 -> -45.704 | BT80: =BT41 -> -51.867 | BU80: =BU41 -> -44.974 | BV80: =BV41 -> -47.937 | BW80: =BW41 -> -61.602 | BX80: =BX41 -> -27.21 | BY80: =BY41 -> -26.8 | BZ80: =BZ41 -> 3.3 | ... CG80: =CG41 -> 247.1
B81: CFFO | C81: -7.866 | D81: -9.082 | E81: -0.836 | F81: -7.668 | G81: -8.903 | H81: -11.114 | I81: -3.449 | J81: -5.593 | K81: -1.2 | L81: 4.372 | M81: 3.694 | N81: -3.518 | O81: -1.017 | P81: 0.508 | Q81: 4.822 | R81: 4.604 | S81: -3.488 | T81: 0.785 | U81: 8.746 | V81: -18.595 | W81: -10.517 | X81: 3.681 | Y81: 2.677 | Z81: 20.07 | AA81: -21.835 | AB81: 17.964 | AC81: 23.278 | AD81: 21.893 | AE81: -4.266 | AF81: -6.129 | AG81: 15.855 | AH81: 30.44 | AI81: 6.5 | AJ81: 13.9 | AK81: 31.1 | AL81: 46.9 | AM81: -3.6 | AN81: 26.4 | AO81: 44.2 | AP81: 17 | AQ81: -35 | AR81: 18.2 | AS81: -25.8 | AT81: -25.5 | AU81: -13.7 | AV81: 25.3 | AW81: 56.7 | AX81: 50.7 | AY81: 0.5 | AZ81: 44 | BA81: 56.8 | BB81: 44.5 | BC81: 87.6 | BD81: 86.9 | BE81: 108.1 | BF81: 147.8 | BG81: 63.9 | BH81: 196.4 | BI81: 125.7 | BJ81: 183.3 | BK81: 113.8 | BL81: 88.5 | BS81: =SUM(C81:F81) -> -25.452 | BT81: =SUM(G81:J81) -> -29.059 | BU81: =SUM(K81:N81) -> 3.348 | BV81: =SUM(O81:R81) -> 8.917 | BW81: =SUM(S81:V81) -> -12.552 | BX81: =SUM(W81:Z81) -> 15.911 | BY81: =SUM(AA81:AD81) -> 41.3 | BZ81: =SUM(AE81:AH81) -> 35.9 | CA81: =SUM(AI81:AL81) -> 98.4 | CB81: =SUM(AM81:AP81) -> 84 | CC81: =SUM(AQ81:AT81) -> -68.1 | CD81: =SUM(AU81:AX81) -> 119 | CE81: =SUM(AY81:BB81) -> 145.8 | CF81: =SUM(BC81:BF81) -> 430.4 | CG81: =SUM(BG81:BJ81) -> 569.3
B82: CapEx, net | C82: -2.897 | D82: -2.663 | E82: -3.278 | F82: -2.276 | G82: -1.699 | H82: -2.55 | I82: -4.687 | J82: -2.055 | K82: -1.069 | L82: -1.626 | M82: -1.822 | N82: -2.79 | O82: -2.157 | P82: -3.588 | Q82: -3.108 | R82: -2.633 | S82: -4.346 | T82: -0.255 | U82: -2.525 | V82: -3.482 | W82: -3.16 | X82: -2.745 | Y82: -13.3 | Z82: -2.91 | AA82: -25.679 | AB82: -13.389 | AC82: -8.745 | AD82: -25.987 | AE82: -35.374 | AF82: -52.356 | AG82: -37.125 | AH82: -32.545 | AI82: -44.4 | AJ82: -47.5 | AK82: -22.7 | AL82: -49.1 | AM82: -26.9 | AN82: -24.8 | AO82: -26.5 | AP82: -88.3 | AQ82: -32.9 | AR82: -19.9 | AS82: -27.3 | AT82: -42.6 | AU82: -15.9 | AV82: -19.1 | AW82: -33.9 | AX82: -66.9 | AY82: -12 | AZ82: -18.1 | BA82: -22.4 | BB82: -31.6 | BC82: -24 | BD82: -24.9 | BE82: -29.1 | BF82: -56 | BG82: -15.7 | BH82: -23.2 | BI82: -31.1 | BJ82: -140.8 | BK82: -27.8 | BL82: -37.3 | BS82: =SUM(C82:F82) -> -11.114 | BT82: =SUM(G82:J82) -> -10.991 | BU82: =SUM(K82:N82) -> -7.307 | BV82: =SUM(O82:R82) -> -11.486 | BW82: =SUM(S82:V82) -> -10.608 | BX82: =SUM(W82:Z82) -> -22.115 | BY82: =SUM(AA82:AD82) -> -73.8 | BZ82: =SUM(AE82:AH82) -> -157.4 | CA82: =SUM(AI82:AL82) -> -163.7 | CB82: =SUM(AM82:AP82) -> -166.5 | CC82: =SUM(AQ82:AT82) -> -122.7 | CD82: =SUM(AU82:AX82) -> -135.8 | CE82: =SUM(AY82:BB82) -> -84.1 | CF82: =SUM(BC82:BF82) -> -134 | CG82: =SUM(BG82:BJ82) -> -210.8
B83: FCF | C83: =C81+C82 -> -10.763 | D83: =D81+D82 -> -11.745 | E83: =E81+E82 -> -4.114 | F83: =F81+F82 -> -9.944 | G83: =G81+G82 -> -10.602 | H83: =H81+H82 -> -13.664 | I83: =I81+I82 -> -8.136 | J83: =J81+J82 -> -7.648 | ... BL83: =BL81+BL82 -> 51.2 | BS83: =SUM(C83:F83) -> -36.566 | BT83: =SUM(G83:J83) -> -40.05 | BU83: =SUM(K83:N83) -> -3.959 | BV83: =SUM(O83:R83) -> -2.569 | BW83: =SUM(S83:V83) -> -23.16 | BX83: =SUM(W83:Z83) -> -6.204 | BY83: =SUM(AA83:AD83) -> -32.5 | BZ83: =SUM(AE83:AH83) -> -121.5 | CA83: =SUM(AI83:AL83) -> -65.3 | CB83: =SUM(AM83:AP83) -> -82.5 | CC83: =SUM(AQ83:AT83) -> -190.8 | CD83: =SUM(AU83:AX83) -> -16.8 | CE83: =SUM(AY83:BB83) -> 61.7 | CF83: =SUM(BC83:BF83) -> 296.4 | CG83: =SUM(BG83:BJ83) -> 358.5
B84: SC | C84: =C42 -> 45.58 | D84: =D42 -> 46.38 | E84: =E42 -> 47.32 | F84: =F42 -> 47.42 | G84: =G42 -> 47.61 | H84: =H42 -> 47.82 | I84: =I42 -> 48.04 | J84: =J42 -> 48.22 | ... BL84: =BL42 -> 69.3 | BS84: =BS42 -> 46.675 | BT84: =BT42 -> 47.9225 | BU84: =BU42 -> 54.005 | BV84: =BV42 -> 55.6275 | BW84: =BW42 -> 56.785 | BX84: =BX42 -> 57.2525 | BY84: =BY42 -> 58.0025 | BZ84: =BZ42 -> 58.8575 | ... CG84: =CG42 -> 70.31475
B85: FCF per Share | C85: =C83/C84 -> -0.23613427 | D85: =D83/D84 -> -0.25323415 | E85: =E83/E84 -> -0.086939983 | F85: =F83/F84 -> -0.20970055 | G85: =G83/G84 -> -0.22268431 | H85: =H83/H84 -> -0.28573818 | I85: =I83/I84 -> -0.16935887 | J85: =J83/J84 -> -0.15860639 | ... BL85: =BL83/BL84 -> 0.73881674 | BS85: =SUM(C85:F85) -> -0.78600895 | BT85: =SUM(G85:J85) -> -0.83638775 | BU85: =SUM(K85:N85) -> -0.072746779 | BV85: =SUM(O85:R85) -> -0.047384644 | BW85: =SUM(S85:V85) -> -0.40778539 | BX85: =SUM(W85:Z85) -> -0.10997433 | BY85: =SUM(AA85:AD85) -> -0.56486006 | BZ85: =SUM(AE85:AH85) -> -2.0679781 | CA85: =SUM(AI85:AL85) -> -1.0968426 | CB85: =SUM(AM85:AP85) -> -1.2719922 | CC85: =SUM(AQ85:AT85) -> -2.8095375 | CD85: =SUM(AU85:AX85) -> -0.2428067 | CE85: =SUM(AY85:BB85) -> 0.88345256 | CF85: =SUM(BC85:BF85) -> 4.2270763 | CG85: =SUM(BG85:BJ85) -> 5.0965447
B87: CFFO Margin | C87: =C81/C29 -> -0.27836365 | D87: =D81/D29 -> -0.28195337 | E87: =E81/E29 -> -0.018746917 | F87: =F81/F29 -> -0.16248517 | G87: =G81/G29 -> -0.18643464 | H87: =H81/H29 -> -0.21777212 | I87: =I81/I29 -> -0.062993133 | J87: =J81/J29 -> -0.096717853 | ... BL87: =BL81/BL29 -> 0.11039042 | BS87: =BS81/BS29 -> -0.16716692 | BT87: =BT81/BT29 -> -0.13747995 | BU87: =BU81/BU29 -> 0.013550048 | BV87: =BV81/BV29 -> 0.038548165 | BW87: =BW81/BW29 -> -0.047564733 | BX87: =BX81/BX29 -> 0.043355523 | BY87: =BY81/BY29 -> 0.089047003 | BZ87: =BZ81/BZ29 -> 0.063675062 | ... CG87: =CG81/CG29 -> 0.21022119
B88: FCF Margin | C88: =C83/C29 -> -0.38088329 | D88: =D83/D29 -> -0.36462699 | E88: =E83/E29 -> -0.092254563 | F88: =F83/F29 -> -0.21071368 | G88: =G83/G29 -> -0.22201282 | H88: =H83/H29 -> -0.26773783 | I88: =I83/I29 -> -0.14859731 | J88: =J83/J29 -> -0.13225427 | ... BL88: =BL83/BL29 -> 0.063864288 | BS88: =BS83/BS29 -> -0.24016288 | BT88: =BT83/BT29 -> -0.18947906 | BU88: =BU83/BU29 -> -0.016022891 | BV88: =BV83/BV29 -> -0.011105779 | BW88: =BW83/BW29 -> -0.087762843 | BX88: =BX83/BX29 -> -0.016905139 | BY88: =BY83/BY29 -> -0.070073307 | BZ88: =BZ83/BZ29 -> -0.21550195 | ... CG88: =CG83/CG29 -> 0.13238064
B89: CapEx as % of Revenue | C89: =C82/C29 -> -0.10251964 | D89: =D82/D29 -> -0.082673621 | E89: =E82/E29 -> -0.073507647 | F89: =F82/F29 -> -0.048228513 | G89: =G82/G29 -> -0.035578171 | H89: =H82/H29 -> -0.04996571 | I89: =I82/I29 -> -0.085604179 | J89: =J82/J29 -> -0.035536418 | ... BL89: =BL82/BL29 -> -0.046526132 | BS89: =BS82/BS29 -> -0.072995961 | BT89: =BT82/BT29 -> -0.051999111 | BU89: =BU82/BU29 -> -0.029572939 | BV89: =BV82/BV29 -> -0.049653944 | BW89: =BW82/BW29 -> -0.040198111 | BX89: =BX82/BX29 -> -0.060260662 | BY89: =BY82/BY29 -> -0.15912031 | BZ89: =BZ82/BZ29 -> -0.27917701 | ... CG89: =CG82/CG29 -> -0.077840552

Sheet Notes | Quant Analysis
CL1: 0
P2: Employee Scope: | AO2: General Notes/Observations
Q32: Notes: | R32: [X]
R33: [Y]
R34: [Z]
AO35: Financial Stmts. Notes/Observations
P36: Institutional Ownership Snapshot | AO36: Revenues:
Q65: Notes: | R65: [X]
R66: [Y]
R67: [Z]
P69: Revenue Breakdown by Segment | AO69: Earnings Scope:
Q101: Notes: | R101: [X]
R102: [Y]
R103: [Z]
P105: Q/q Total Revenues, Net Income, FCF | AO105: Balance Sheet Scope:
Q134: Notes: | R134: [X]
R135: [Y]
R136: [Z]
P138: Y/y Total Revenues, Net Income, FCF | AO138: [Equity Preformance Compared to Peers]
Q167: Notes: | R167: [X]
R168: [Y]
R169: [Z]
A184: VOO Historical Returns | I184: PODD Historical Returns
A185: 1003 Trading Days? (From: 10/11/2022 - 10/11/2026) | I185: 1003 Trading Days? (From: 10/11/2022 - 10/11/2026)
A186: Close | B186: High | C186: Low | D186: Open | E186: Volume | F186: UTC Date | G186: Change | I186: Close | J186: High | K186: Low | L186: Open | M186: Volume | N186: UTC Date | O186: Change
A187: 715.59 | B187: 716.435 | C187: 712.54 | D187: 713.54 | E187: 4345835.7 | F187: Fri, 09 Oct 2026 00:00:00 GMT | G187: =A187/D187-1 -> 0.0028729994 | I187: 135.28 | J187: 137.17 | K187: 133.72 | L187: 134.19 | M187: 865360.2 | N187: Fri, 09 Oct 2026 00:00:00 GMT | O187: =I187/L187-1 -> 0.0081228109
A188: 711.28 | B188: 714.27 | C188: 708.16 | D188: 712.25 | E188: 4763330.7 | F188: Thu, 08 Oct 2026 00:00:00 GMT | G188: =A188/D188-1 -> -0.0013618814 | I188: 134.47 | J188: 134.6 | K188: 132.855 | L188: 133.96 | M188: 1557440.6 | N188: Thu, 08 Oct 2026 00:00:00 GMT | O188: =I188/L188-1 -> 0.0038071066
A189: 714.34 | B189: 715.055 | C189: 711.06 | D189: 713.06 | E189: 4675948.1 | F189: Wed, 07 Oct 2026 00:00:00 GMT | G189: =A189/D189-1 -> 0.0017950804 | I189: 134.36 | J189: 137.1 | K189: 133.33 | L189: 134.94 | M189: 1032906.1 | N189: Wed, 07 Oct 2026 00:00:00 GMT | O189: =I189/L189-1 -> -0.0042982066
A190: 716.2 | B190: 718.47 | C190: 715.09 | D190: 715.21 | E190: 4568431.3 | F190: Tue, 06 Oct 2026 00:00:00 GMT | G190: =A190/D190-1 -> 0.0013842088 | I190: 134.73 | J190: 136.16 | K190: 133.725 | L190: 135.77 | M190: 1712375.2 | N190: Tue, 06 Oct 2026 00:00:00 GMT | O190: =I190/L190-1 -> -0.0076600133
A191: 712.32 | B191: 713.8583 | C191: 707.42 | D191: 707.44 | E191: 6172916.9 | F191: Mon, 05 Oct 2026 00:00:00 GMT | G191: =A191/D191-1 -> 0.0068981115 | I191: 135.62 | J191: 135.81 | K191: 131.225 | L191: 131.69 | M191: 1940340.7 | N191: Mon, 05 Oct 2026 00:00:00 GMT | O191: =I191/L191-1 -> 0.029842813
A192: 707.54 | B192: 710.2 | C192: 705.12 | D192: 708.31 | E192: 6612533.1 | F192: Fri, 02 Oct 2026 00:00:00 GMT | G192: =A192/D192-1 -> -0.0010870946 | I192: 131.69 | J192: 132.53 | K192: 128.01 | L192: 131.825 | M192: 3060814.4 | N192: Fri, 02 Oct 2026 00:00:00 GMT | O192: =I192/L192-1 -> -0.001024085
A193: 702.35 | B193: 703.725 | C193: 697.47 | D193: 702.555 | E193: 8433749.3 | F193: Thu, 01 Oct 2026 00:00:00 GMT | G193: =A193/D193-1 -> -0.0002917921 | I193: 130.79 | J193: 132.015 | K193: 128.745 | L193: 131.78 | M193: 3257419.9 | N193: Thu, 01 Oct 2026 00:00:00 GMT | O193: =I193/L193-1 -> -0.0075125209
A194: 700.86 | B194: 707.2 | C194: 700.56 | D194: 704.58 | E194: 9876125.1 | F194: Wed, 30 Sep 2026 00:00:00 GMT | G194: =A194/D194-1 -> -0.0052797411 | I194: 130.47 | J194: 133.145 | K194: 130.1 | L194: 132.93 | M194: 1416042.3 | N194: Wed, 30 Sep 2026 00:00:00 GMT | O194: =I194/L194-1 -> -0.018505981
A195: 702.46 | B195: 705 | C195: 700.74 | D195: 704.82 | E195: 7643258.6 | F195: Tue, 29 Sep 2026 00:00:00 GMT | G195: =A195/D195-1 -> -0.0033483726 | I195: 132.84 | J195: 133.49 | K195: 130.8 | L195: 132.58 | M195: 1366136.6 | N195: Tue, 29 Sep 2026 00:00:00 GMT | O195: =I195/L195-1 -> 0.0019610801
A196: 703.61 | B196: 707.33 | C196: 701.97 | D196: 706.29 | E196: 8539385.2 | F196: Mon, 28 Sep 2026 00:00:00 GMT | G196: =A196/D196-1 -> -0.0037944754 | I196: 133.11 | J196: 135.4 | K196: 130.385 | L196: 134.44 | M196: 1724759.4 | N196: Mon, 28 Sep 2026 00:00:00 GMT | O196: =I196/L196-1 -> -0.009892889
A197: 708.9674 | B197: 709.82021 | C197: 704.36423 | D197: 706.62343 | E197: 5482247.9 | F197: Fri, 25 Sep 2026 00:00:00 GMT | G197: =A197/D197-1 -> 0.0033171475 | I197: 136.13 | J197: 138.06 | K197: 134.48 | L197: 135.78 | M197: 1055965.7 | N197: Fri, 25 Sep 2026 00:00:00 GMT | O197: =I197/L197-1 -> 0.0025776992
A198: 705.17714 | B198: 706.76805 | C198: 701.54548 | D198: 702.26463 | E198: 9443878 | F198: Thu, 24 Sep 2026 00:00:00 GMT | G198: =A198/D198-1 -> 0.0041473149 | I198: 135.78 | J198: 139.3511 | K198: 134.5501 | L198: 136.8 | M198: 1085511.9 | N198: Thu, 24 Sep 2026 00:00:00 GMT | O198: =I198/L198-1 -> -0.0074561404
A199: 705.78558 | B199: 710.55332 | C199: 704.55215 | D199: 710.30895 | E199: 13844442 | F199: Wed, 23 Sep 2026 00:00:00 GMT | G199: =A199/D199-1 -> -0.0063681746 | I199: 136.49 | J199: 139.82 | K199: 134.73 | L199: 139.07 | M199: 1021320.7 | N199: Wed, 23 Sep 2026 00:00:00 GMT | O199: =I199/L199-1 -> -0.018551808
A200: 710.9523 | B200: 712.4684 | C200: 710.15435 | D200: 711.45102 | E200: 20783008 | F200: Tue, 22 Sep 2026 00:00:00 GMT | G200: =A200/D200-1 -> -0.00070098699 | I200: 139.38 | J200: 142.0425 | K200: 137.6 | L200: 141.93 | M200: 1246949.4 | N200: Tue, 22 Sep 2026 00:00:00 GMT | O200: =I200/L200-1 -> -0.017966603 | R200: Min | S200: =MIN(O187:O1189) -> -0.11815276
A201: 710.9523 | B201: 712.24398 | C201: 704.14979 | D201: 704.3792 | E201: 8882600.7 | F201: Mon, 21 Sep 2026 00:00:00 GMT | G201: =A201/D201-1 -> 0.0093317662 | I201: 140.53 | J201: 141.49 | K201: 138.59 | L201: 140.6 | M201: 1335831.6 | N201: Mon, 21 Sep 2026 00:00:00 GMT | O201: =I201/L201-1 -> -0.00049786629 | R201: Max | S201: =MAX(O187:O1189) -> 0.085451862
A202: 699.9805 | B202: 700.38945 | C202: 696.70891 | D202: 699.78102 | E202: 9618703.4 | F202: Fri, 18 Sep 2026 00:00:00 GMT | G202: =A202/D202-1 -> 0.00028507084 | I202: 140.6 | J202: 142.17 | K202: 139.96 | L202: 141.25 | M202: 2506360.6 | N202: Fri, 18 Sep 2026 00:00:00 GMT | O202: =I202/L202-1 -> -0.0046017699 | R202: Mean μ | S202: =AVERAGE(O187:O1189) -> -0.00095086782
A203: 699.23243 | B203: 700.08025 | C203: 696.81863 | D203: 699.80096 | E203: 9928828.2 | F203: Thu, 17 Sep 2026 00:00:00 GMT | G203: =A203/D203-1 -> -0.00081242873 | I203: 141.55 | J203: 141.8 | K203: 138.51 | L203: 140.38 | M203: 1197295.8 | N203: Thu, 17 Sep 2026 00:00:00 GMT | O203: =I203/L203-1 -> 0.0083345206 | R203: Median | S203: =MEDIAN(O187:O1189) -> -0.00038705137
A204: 691.4624 | B204: 698.30481 | C204: 687.27317 | D204: 696.37976 | E204: 14204833 | F204: Wed, 16 Sep 2026 00:00:00 GMT | G204: =A204/D204-1 -> -0.0070613174 | I204: 140.6 | J204: 143.45 | K204: 138.11 | L204: 138.86 | M204: 1347087.2 | N204: Wed, 16 Sep 2026 00:00:00 GMT | O204: =I204/L204-1 -> 0.012530606 | R204: SD σ | S204: =_xlfn.STDEV.P(O187:O1189) -> 0.021151738
A205: 694.41481 | B205: 697.14779 | C205: 693.30766 | D205: 696.97822 | E205: 9682716.1 | F205: Tue, 15 Sep 2026 00:00:00 GMT | G205: =A205/D205-1 -> -0.0036778912 | I205: 139.24 | J205: 140.28 | K205: 136.16 | L205: 137.59 | M205: 1495909.2 | N205: Tue, 15 Sep 2026 00:00:00 GMT | O205: =I205/L205-1 -> 0.011992151 | R205: 3σ 1-Day Δ: ± | S205: =3*S204 -> 0.063455215 | U205: <- Sharpe Ratio (Risk Adjusted Return)
A206: 697.50686 | B206: 700.05032 | C206: 694.93348 | D206: 695.99076 | E206: 6793476.4 | F206: Mon, 14 Sep 2026 00:00:00 GMT | G206: =A206/D206-1 -> 0.002178337 | I206: 137.8 | J206: 137.9801 | K206: 131.61 | L206: 134.23 | M206: 2342898.7 | N206: Mon, 14 Sep 2026 00:00:00 GMT | O206: =I206/L206-1 -> 0.026596141 | R206: β (1-year avg.) | S206: =_xlfn.COVARIANCE.P(O187:O437,G187:G437)/_xlfn.VAR.P(G187:G437) -> 0.45014704 | U206: <- Sortino Ratio (Downside Risk Adjusted Return)
A207: 700.7585 | B207: 702.68894 | C207: 700.13012 | D207: 701.19738 | E207: 5812878.2 | F207: Fri, 11 Sep 2026 00:00:00 GMT | G207: =A207/D207-1 -> -0.00062588905 | I207: 131.96 | J207: 135.575 | K207: 131.24 | L207: 135.4 | M207: 1747977.9 | N207: Fri, 11 Sep 2026 00:00:00 GMT | O207: =I207/L207-1 -> -0.025406204
A208: 694.86366 | B208: 696.84855 | C208: 693.7586 | D208: 694.99332 | E208: 18360495 | F208: Thu, 10 Sep 2026 00:00:00 GMT | G208: =A208/D208-1 -> -0.00018657252 | I208: 134.68 | J208: 138.66 | K208: 134.11 | L208: 136.74 | M208: 1866957.8 | N208: Thu, 10 Sep 2026 00:00:00 GMT | O208: =I208/L208-1 -> -0.015065087 | Q208: n = | R208: 1003
A209: 699.07284 | B209: 700.90812 | C209: 697.69139 | D209: 700.54904 | E209: 4311927.8 | F209: Wed, 09 Sep 2026 00:00:00 GMT | G209: =A209/D209-1 -> -0.0021072115 | I209: 137.92 | J209: 142.6919 | K209: 137.25 | L209: 140.26 | M209: 2058782.8 | N209: Wed, 09 Sep 2026 00:00:00 GMT | O209: =I209/L209-1 -> -0.016683302 | Q209: Histogram Data | T209: Distribution Overlay | X209: SD Lines
A210: 702.26463 | B210: 705.69581 | C210: 701.56643 | D210: 705.16717 | E210: 7847677 | F210: Tue, 08 Sep 2026 00:00:00 GMT | G210: =A210/D210-1 -> -0.0041160995 | I210: 142.28 | J210: 147.39 | K210: 139.27 | L210: 147.39 | M210: 2232006.8 | N210: Tue, 08 Sep 2026 00:00:00 GMT | O210: =I210/L210-1 -> -0.034669923 | Q210: Bin | R210: Frequency | T210: (X) 1-Day Δ | U210: (Y) Pop. Density | X210: X | Y210: Y
A211: 706.19453 | B211: 708.62827 | C211: 705.08737 | D211: 707.90014 | E211: 6833680.7 | F211: Fri, 04 Sep 2026 00:00:00 GMT | G211: =A211/D211-1 -> -0.0024094009 | I211: 147.48 | J211: 150.56 | K211: 145.42 | L211: 149.32 | M211: 1058435.2 | N211: Fri, 04 Sep 2026 00:00:00 GMT | O211: =I211/L211-1 -> -0.012322529 | Q211: -0.07 | R211: 7 | T211: =T212-0.0025 -> -0.075 | U211: =_xlfn.NORM.DIST(T211,$S$202,$S$204,FALSE) -> 0.041135155 | W211: Mean | X211: =S202 -> -0.00095086782 | Y211: 0
A212: 708.89758 | B212: 709.69054 | C212: 703.70094 | D212: 704.01014 | E212: 8616616.4 | F212: Thu, 03 Sep 2026 00:00:00 GMT | G212: =A212/D212-1 -> 0.0069422799 | I212: 150.58 | J212: 150.99 | K212: 145.16 | L212: 148.14 | M212: 1157659.2 | N212: Thu, 03 Sep 2026 00:00:00 GMT | O212: =I212/L212-1 -> 0.016470906 | Q212: -0.0675 | R212: 0 | T212: =T213-0.0025 -> -0.0725 | U212: =_xlfn.NORM.DIST(T212,$S$202,$S$204,FALSE) -> 0.061784757 | X212: =S202 -> -0.00095086782 | Y212: 19
A213: 701.60632 | B213: 702.72345 | C213: 698.38461 | D213: 699.05289 | E213: 7724754.5 | F213: Wed, 02 Sep 2026 00:00:00 GMT | G213: =A213/D213-1 -> 0.0036527074 | I213: 148.14 | J213: 151.5 | K213: 147.21 | L213: 148 | M213: 1093126.2 | N213: Wed, 02 Sep 2026 00:00:00 GMT | O213: =I213/L213-1 -> 0.00094594595 | Q213: -0.065 | R213: 2 | T213: =T214-0.0025 -> -0.07 | U213: =_xlfn.NORM.DIST(T213,$S$202,$S$204,FALSE) -> 0.091512954 | W213: -3σ | X213: =($S$204*-3)+$S$202 -> -0.064406083 | Y213: 0
A214: 698.48435 | B214: 701.10761 | C214: 696.34964 | D214: 698.65391 | E214: 6503580 | F214: Tue, 01 Sep 2026 00:00:00 GMT | G214: =A214/D214-1 -> -0.00024270112 | I214: 148.38 | J214: 151.16 | K214: 146.81 | L214: 149.79 | M214: 1288263.2 | N214: Tue, 01 Sep 2026 00:00:00 GMT | O214: =I214/L214-1 -> -0.0094131784 | Q214: -0.0625 | R214: 1 | T214: =T215-0.0025 -> -0.0675 | U214: =_xlfn.NORM.DIST(T214,$S$202,$S$204,FALSE) -> 0.13366473 | X214: =($S$204*-3)+$S$202 -> -0.064406083 | Y214: 2
A215: 703.08253 | B215: 704.12984 | C215: 701.15748 | D215: 703.55132 | E215: 5756351.9 | F215: Mon, 31 Aug 2026 00:00:00 GMT | G215: =A215/D215-1 -> -0.00066632641 | I215: 148.66 | J215: 149.68 | K215: 142.005 | L215: 142.93 | M215: 6635039.9 | N215: Mon, 31 Aug 2026 00:00:00 GMT | O215: =I215/L215-1 -> 0.040089554 | Q215: -0.06 | R215: 0 | T215: =T216-0.0025 -> -0.065 | U215: =_xlfn.NORM.DIST(T215,$S$202,$S$204,FALSE) -> 0.19252366 | W215: -2σ | X215: =($S$204*-2)+$S$202 -> -0.043254344 | Y215: 0
A216: 705.4265 | B216: 710.84178 | C216: 704.44902 | D216: 707.57099 | E216: 8105322.5 | F216: Fri, 28 Aug 2026 00:00:00 GMT | G216: =A216/D216-1 -> -0.0030307729 | I216: 145.13 | J216: 146.67 | K216: 143.805 | L216: 144.2 | M216: 1043384.4 | N216: Fri, 28 Aug 2026 00:00:00 GMT | O216: =I216/L216-1 -> 0.0064493759 | Q216: -0.0575 | R216: 1 | T216: =T217-0.0025 -> -0.0625 | U216: =_xlfn.NORM.DIST(T216,$S$202,$S$204,FALSE) -> 0.27345408 | X216: =($S$204*-2)+$S$202 -> -0.043254344 | Y216: 4
A217: 706.93263 | B217: 708.13454 | C217: 703.40211 | D217: 704.57868 | E217: 6773106.6 | F217: Thu, 27 Aug 2026 00:00:00 GMT | G217: =A217/D217-1 -> 0.0033409306 | I217: 143.41 | J217: 144.6 | K217: 140.98 | L217: 142.96 | M217: 1338314.9 | N217: Thu, 27 Aug 2026 00:00:00 GMT | O217: =I217/L217-1 -> 0.0031477336 | Q217: -0.055 | R217: 3 | T217: =T218-0.0025 -> -0.06 | U217: =_xlfn.NORM.DIST(T217,$S$202,$S$204,FALSE) -> 0.38301673 | W217: -1σ | X217: =($S$204*-1)+$S$202 -> -0.022102606 | Y217: 0
A218: 702.3943 | B218: 703.51143 | C218: 700.42935 | D218: 701.09763 | E218: 7176219.4 | F218: Wed, 26 Aug 2026 00:00:00 GMT | G218: =A218/D218-1 -> 0.0018494807 | I218: 143.38 | J218: 144.64 | K218: 141.23 | L218: 141.27 | M218: 1423995.7 | N218: Wed, 26 Aug 2026 00:00:00 GMT | O218: =I218/L218-1 -> 0.014935938 | Q218: -0.0525 | R218: 3 | T218: =T219-0.0025 -> -0.0575 | U218: =_xlfn.NORM.DIST(T218,$S$202,$S$204,FALSE) -> 0.52903462 | X218: =($S$204*-1)+$S$202 -> -0.022102606 | Y218: 13
A219: 702.21476 | B219: 703.02797 | C219: 699.65135 | D219: 702.47908 | E219: 4335609.9 | F219: Tue, 25 Aug 2026 00:00:00 GMT | G219: =A219/D219-1 -> -0.00037626813 | I219: 143.05 | J219: 146.095 | K219: 141.78 | L219: 145.28 | M219: 1925455.4 | N219: Tue, 25 Aug 2026 00:00:00 GMT | O219: =I219/L219-1 -> -0.01534967 | Q219: -0.05 | R219: 4 | T219: =T220-0.0025 -> -0.055 | U219: =_xlfn.NORM.DIST(T219,$S$202,$S$204,FALSE) -> 0.72058211 | W219: 1σ | X219: =($S$204*1)+$S$202 -> 0.02020087 | Y219: 0
A220: 700.03038 | B220: 701.58628 | C220: 698.73371 | D220: 701.16745 | E220: 7757366.3 | F220: Mon, 24 Aug 2026 00:00:00 GMT | G220: =A220/D220-1 -> -0.0016216908 | I220: 145.42 | J220: 151.75 | K220: 145.15 | L220: 151.17 | M220: 1568557.6 | N220: Mon, 24 Aug 2026 00:00:00 GMT | O220: =I220/L220-1 -> -0.038036647 | Q220: -0.0475 | R220: 2 | T220: =T221-0.0025 -> -0.0525 | U220: =_xlfn.NORM.DIST(T220,$S$202,$S$204,FALSE) -> 0.96786744 | X220: =($S$204*1)+$S$202 -> 0.02020087 | Y220: 13
A221: 701.90555 | B221: 703.9902 | C221: 700.63881 | D221: 702.26463 | E221: 10705589 | F221: Fri, 21 Aug 2026 00:00:00 GMT | G221: =A221/D221-1 -> -0.0005113128 | I221: 148.16 | J221: 150.2 | K221: 145.035 | L221: 146.87 | M221: 895453.89 | N221: Fri, 21 Aug 2026 00:00:00 GMT | O221: =I221/L221-1 -> 0.0087832777 | Q221: -0.045 | R221: 4 | T221: =T222-0.0025 -> -0.05 | U221: =_xlfn.NORM.DIST(T221,$S$202,$S$204,FALSE) -> 1.2819802 | W221: 2σ | X221: =($S$204*2)+$S$202 -> 0.041352609 | Y221: 0
A222: 699.21248 | B222: 704.26948 | C222: 698.67596 | D222: 702.24468 | E222: 8480360 | F222: Thu, 20 Aug 2026 00:00:00 GMT | G222: =A222/D222-1 -> -0.0043178752 | I222: 146.87 | J222: 152.685 | K222: 146.67 | L222: 151.74 | M222: 1212723.2 | N222: Thu, 20 Aug 2026 00:00:00 GMT | O222: =I222/L222-1 -> -0.032094372 | Q222: -0.0425 | R222: 6 | T222: =T223-0.0025 -> -0.0475 | U222: =_xlfn.NORM.DIST(T222,$S$202,$S$204,FALSE) -> 1.6744792 | X222: =($S$204*2)+$S$202 -> 0.041352609 | Y222: 4
A223: 705.09735 | B223: 708.27917 | C223: 704.28444 | D223: 706.37407 | E223: 7039831.7 | F223: Wed, 19 Aug 2026 00:00:00 GMT | G223: =A223/D223-1 -> -0.0018074246 | I223: 151.51 | J223: 155.17 | K223: 147.955 | L223: 148 | M223: 1311497.2 | N223: Wed, 19 Aug 2026 00:00:00 GMT | O223: =I223/L223-1 -> 0.023716216 | Q223: -0.04 | R223: 6 | T223: =T224-0.0025 -> -0.045 | U223: =_xlfn.NORM.DIST(T223,$S$202,$S$204,FALSE) -> 2.1568068 | W223: 3σ | X223: =($S$204*3)+$S$202 -> 0.062504347 | Y223: 0
A224: 703.59122 | B224: 705.53622 | C224: 703.15235 | D224: 704.79812 | E224: 5292120.7 | F224: Tue, 18 Aug 2026 00:00:00 GMT | G224: =A224/D224-1 -> -0.0017124015 | I224: 148.03 | J224: 149.335 | K224: 139.45 | L224: 139.91 | M224: 1622404.1 | N224: Tue, 18 Aug 2026 00:00:00 GMT | O224: =I224/L224-1 -> 0.05803731 | Q224: -0.0375 | R224: 5 | T224: =T225-0.0025 -> -0.0425 | U224: =_xlfn.NORM.DIST(T224,$S$202,$S$204,FALSE) -> 2.739528 | X224: =($S$204*3)+$S$202 -> 0.062504347 | Y224: 2
A225: 708.44873 | B225: 712.21405 | C225: 708.27917 | D225: 711.67045 | E225: 5759776.8 | F225: Mon, 17 Aug 2026 00:00:00 GMT | G225: =A225/D225-1 -> -0.0045269797 | I225: 139.7 | J225: 142.13 | K225: 138.275 | L225: 141.32 | M225: 1948953.9 | N225: Mon, 17 Aug 2026 00:00:00 GMT | O225: =I225/L225-1 -> -0.011463346 | Q225: -0.035 | R225: 10 | T225: =T226-0.0025 -> -0.04 | U225: =_xlfn.NORM.DIST(T225,$S$202,$S$204,FALSE) -> 3.4314153
A226: 711.78017 | B226: 714.05432 | C226: 710.97225 | D226: 713.79499 | E226: 4224899.3 | F226: Fri, 14 Aug 2026 00:00:00 GMT | G226: =A226/D226-1 -> -0.0028226877 | I226: 143.34 | J226: 147.1707 | K226: 143.02 | L226: 146.98 | M226: 779900.8 | N226: Fri, 14 Aug 2026 00:00:00 GMT | O226: =I226/L226-1 -> -0.024765274 | Q226: -0.0325 | R226: 8 | T226: =T227-0.0025 -> -0.0375 | U226: =_xlfn.NORM.DIST(T226,$S$202,$S$204,FALSE) -> 4.2384185
A227: 713.11673 | B227: 714.55304 | C227: 709.78031 | D227: 710.47353 | E227: 4562935.4 | F227: Thu, 13 Aug 2026 00:00:00 GMT | G227: =A227/D227-1 -> 0.0037203426 | I227: 146.44 | J227: 146.825 | K227: 143.12 | L227: 145.06 | M227: 1360928.3 | N227: Thu, 13 Aug 2026 00:00:00 GMT | O227: =I227/L227-1 -> 0.0095133048 | Q227: -0.03 | R227: 12 | T227: =T228-0.0025 -> -0.035 | U227: =_xlfn.NORM.DIST(T227,$S$202,$S$204,FALSE) -> 5.1625873
A228: 708.34899 | B228: 710.43363 | C228: 707.11217 | D228: 710.29399 | E228: 4883810.5 | F228: Wed, 12 Aug 2026 00:00:00 GMT | G228: =A228/D228-1 -> -0.0027383025 | I228: 145.06 | J228: 145.59 | K228: 138.7 | L228: 142 | M228: 1570747.1 | N228: Wed, 12 Aug 2026 00:00:00 GMT | O228: =I228/L228-1 -> 0.021549296 | Q228: -0.0275 | R228: 15 | T228: =T229-0.0025 -> -0.0325 | U228: =_xlfn.NORM.DIST(T228,$S$202,$S$204,FALSE) -> 6.2010326
A229: 706.60348 | B229: 710.1743 | C229: 705.18712 | D229: 710.1344 | E229: 5023320.7 | F229: Tue, 11 Aug 2026 00:00:00 GMT | G229: =A229/D229-1 -> -0.0049721894 | I229: 144.7 | J229: 145.16 | K229: 141 | L229: 142.45 | M229: 1249505.4 | N229: Tue, 11 Aug 2026 00:00:00 GMT | O229: =I229/L229-1 -> 0.015795016 | Q229: -0.025 | R229: 11 | T229: =T230-0.0025 -> -0.03 | U229: =_xlfn.NORM.DIST(T229,$S$202,$S$204,FALSE) -> 7.3450313
A230: 708.82776 | B230: 710.61097 | C230: 707.68071 | D230: 708.48863 | E230: 6675037.2 | F230: Mon, 10 Aug 2026 00:00:00 GMT | G230: =A230/D230-1 -> 0.00047866425 | I230: 142.85 | J230: 143.94 | K230: 140.34 | L230: 140.55 | M230: 1505013 | N230: Mon, 10 Aug 2026 00:00:00 GMT | O230: =I230/L230-1 -> 0.016364283 | Q230: -0.0225 | R230: 16 | T230: =T231-0.0025 -> -0.0275 | U230: =_xlfn.NORM.DIST(T230,$S$202,$S$204,FALSE) -> 8.5793879
A231: 708.88761 | B231: 709.54591 | C231: 705.62599 | D231: 706.91268 | E231: 4665094.1 | F231: Fri, 07 Aug 2026 00:00:00 GMT | G231: =A231/D231-1 -> 0.0027937296 | I231: 141.17 | J231: 142.22 | K231: 136.46 | L231: 138 | M231: 1591344.9 | N231: Fri, 07 Aug 2026 00:00:00 GMT | O231: =I231/L231-1 -> 0.022971014 | Q231: -0.02 | R231: 21 | T231: =T232-0.0025 -> -0.025 | U231: =_xlfn.NORM.DIST(T231,$S$202,$S$204,FALSE) -> 9.8821623
A232: 704.58866 | B232: 707.64271 | C232: 703.62114 | D232: 706.11473 | E232: 4680742.7 | F232: Thu, 06 Aug 2026 00:00:00 GMT | G232: =A232/D232-1 -> -0.0021612306 | I232: 139.3 | J232: 139.48 | K232: 130.11 | L232: 130.9 | M232: 3249442.3 | N232: Thu, 06 Aug 2026 00:00:00 GMT | O232: =I232/L232-1 -> 0.064171123 | Q232: -0.0175 | R232: 23 | T232: =T233-0.0025 -> -0.0225 | U232: =_xlfn.NORM.DIST(T232,$S$202,$S$204,FALSE) -> 11.224854
A233: 705.78558 | B233: 712.32876 | C233: 705.5063 | D233: 711.31137 | E233: 5200806.9 | F233: Wed, 05 Aug 2026 00:00:00 GMT | G233: =A233/D233-1 -> -0.0077684606 | I233: 133.26 | J233: 138.41 | K233: 126.4 | L233: 128 | M233: 7145732.9 | N233: Wed, 05 Aug 2026 00:00:00 GMT | O233: =I233/L233-1 -> 0.04109375 | Q233: -0.015 | R233: 43 | T233: =T234-0.0025 -> -0.02 | U233: =_xlfn.NORM.DIST(T233,$S$202,$S$204,FALSE) -> 12.573101
A234: 707.16204 | B234: 709.0854 | C234: 697.27745 | D234: 697.36722 | E234: 6527590.6 | F234: Tue, 04 Aug 2026 00:00:00 GMT | G234: =A234/D234-1 -> 0.014045426 | I234: 166.82 | J234: 170.99 | K234: 164.31 | L234: 166.34 | M234: 1748114.7 | N234: Tue, 04 Aug 2026 00:00:00 GMT | O234: =I234/L234-1 -> 0.0028856559 | Q234: -0.0125 | R234: 39 | T234: =T235-0.0025 -> -0.0175 | U234: =_xlfn.NORM.DIST(T234,$S$202,$S$204,FALSE) -> 13.887919
A235: 694.6143 | B235: 695.52197 | C235: 686.84427 | D235: 687.06371 | E235: 7262939.6 | F235: Mon, 03 Aug 2026 00:00:00 GMT | G235: =A235/D235-1 -> 0.010989649 | I235: 169.7 | J235: 172.105 | K235: 166.655 | L235: 168.56 | M235: 1408002.9 | N235: Mon, 03 Aug 2026 00:00:00 GMT | O235: =I235/L235-1 -> 0.0067631704 | Q235: -0.01 | R235: 41 | T235: =T236-0.0025 -> -0.015 | U235: =_xlfn.NORM.DIST(T235,$S$202,$S$204,FALSE) -> 15.127423
A236: 684.8893 | B236: 686.58494 | C236: 676.32133 | D236: 682.74481 | E236: 7681264.4 | F236: Fri, 31 Jul 2026 00:00:00 GMT | G236: =A236/D236-1 -> 0.0031409788 | I236: 165.35 | J236: 168.36 | K236: 162.425 | L236: 164.57 | M236: 1313819 | N236: Fri, 31 Jul 2026 00:00:00 GMT | O236: =I236/L236-1 -> 0.0047396245 | Q236: -0.0075 | R236: 55 | T236: =T237-0.0025 -> -0.0125 | U236: =_xlfn.NORM.DIST(T236,$S$202,$S$204,FALSE) -> 16.248967
... A240: 677.56812 | B240: 683.48202 | C240: 674.6606 | D240: 682.93433 | E240: 5221145.8 | F240: Mon, 27 Jul 2026 00:00:00 GMT | G240: =A240/D240-1 -> -0.0078575706 | I240: 165 | J240: 168.77 | K240: 164 | L240: 165.62 | M240: 1115213 | N240: Mon, 27 Jul 2026 00:00:00 GMT | O240: =I240/L240-1 -> -0.0037435092 | Q240: 0.0025 | R240: 54 | T240: =T241-0.0025 -> -0.0025 | U240: =_xlfn.NORM.DIST(T240,$S$202,$S$204,FALSE) -> 18.810452
A241: 677.39856 | B241: 681.79725 | C241: 675.96225 | D241: 677.05943 | E241: 6302969 | F241: Fri, 24 Jul 2026 00:00:00 GMT | G241: =A241/D241-1 -> 0.00050088391 | I241: 163.26 | J241: 164.33 | K241: 158.31 | L241: 159.21 | M241: 1147569.3 | N241: Fri, 24 Jul 2026 00:00:00 GMT | O241: =I241/L241-1 -> 0.025438101 | Q241: 0.005 | R241: 56 | T241: 0 | U241: =_xlfn.NORM.DIST(T241,$S$202,$S$204,FALSE) -> 18.84192
A242: 676.86992 | B242: 680.79931 | C242: 674.02224 | D242: 677.80751 | E242: 4955511.7 | F242: Thu, 23 Jul 2026 00:00:00 GMT | G242: =A242/D242-1 -> -0.0013832683 | I242: 158.38 | J242: 160.29 | K242: 157.56 | L242: 159.47 | M242: 1141136.3 | N242: Thu, 23 Jul 2026 00:00:00 GMT | O242: =I242/L242-1 -> -0.0068351414 | Q242: 0.0075 | R242: 69 | T242: =T241+0.0025 -> 0.0025 | U242: =_xlfn.NORM.DIST(T242,$S$202,$S$204,FALSE) -> 18.611618
A243: 685.26833 | B243: 687.63225 | C243: 684.26091 | D243: 684.53022 | E243: 3357712.5 | F243: Wed, 22 Jul 2026 00:00:00 GMT | G243: =A243/D243-1 -> 0.0010782614 | I243: 158.93 | J243: 165.7 | K243: 157.44 | L243: 165.7 | M243: 1374454.4 | N243: Wed, 22 Jul 2026 00:00:00 GMT | O243: =I243/L243-1 -> -0.04085697 | Q243: 0.01 | R243: 48 | T243: =T242+0.0025 -> 0.005 | U243: =_xlfn.NORM.DIST(T243,$S$202,$S$204,FALSE) -> 18.129094
A244: 686.10617 | B244: 686.71959 | C244: 682.27602 | D244: 684.19109 | E244: 4065141.7 | F244: Tue, 21 Jul 2026 00:00:00 GMT | G244: =A244/D244-1 -> 0.0027990378 | I244: 163.72 | J244: 165.79 | K244: 162.62 | L244: 163.28 | M244: 1143996.8 | N244: Tue, 21 Jul 2026 00:00:00 GMT | O244: =I244/L244-1 -> 0.0026947575 | Q244: 0.0125 | R244: 43 | T244: =T243+0.0025 -> 0.0075 | U244: =_xlfn.NORM.DIST(T244,$S$202,$S$204,FALSE) -> 17.414103
A245: 680.46068 | B245: 686.43533 | C245: 679.82233 | D245: 684.90925 | E245: 5335667 | F245: Mon, 20 Jul 2026 00:00:00 GMT | G245: =A245/D245-1 -> -0.0064951141 | I245: 167.37 | J245: 168.25 | K245: 161.9 | L245: 164.13 | M245: 1652180.4 | N245: Mon, 20 Jul 2026 00:00:00 GMT | O245: =I245/L245-1 -> 0.01974045 | Q245: 0.015 | R245: 41 | T245: =T244+0.0025 -> 0.01 | U245: =_xlfn.NORM.DIST(T245,$S$202,$S$204,FALSE) -> 16.495259
A246: 681.41822 | B246: 685.10405 | C246: 679.17399 | D246: 680.37092 | E246: 5642108.9 | F246: Fri, 17 Jul 2026 00:00:00 GMT | G246: =A246/D246-1 -> 0.0015393186 | I246: 164.06 | J246: 165.54 | K246: 159.0064 | L246: 162.25 | M246: 1395466.1 | N246: Fri, 17 Jul 2026 00:00:00 GMT | O246: =I246/L246-1 -> 0.011155624 | Q246: 0.0175 | R246: 30 | T246: =T245+0.0025 -> 0.0125 | U246: =_xlfn.NORM.DIST(T246,$S$202,$S$204,FALSE) -> 15.408139
A247: 688.37035 | B247: 691.77161 | C247: 685.6673 | D247: 690.20563 | E247: 4734752 | F247: Thu, 16 Jul 2026 00:00:00 GMT | G247: =A247/D247-1 -> -0.0026590364 | I247: 164.43 | J247: 169.85 | K247: 161.135 | L247: 161.135 | M247: 1497110.6 | N247: Thu, 16 Jul 2026 00:00:00 GMT | O247: =I247/L247-1 -> 0.020448692 | Q247: 0.02 | R247: 24 | T247: =T246+0.0025 -> 0.015 | U247: =_xlfn.NORM.DIST(T247,$S$202,$S$204,FALSE) -> 14.193002
A248: 692.02097 | B248: 692.71917 | C248: 687.81179 | D248: 691.49232 | E248: 4120626 | F248: Wed, 15 Jul 2026 00:00:00 GMT | G248: =A248/D248-1 -> 0.00076449291 | I248: 159.28 | J248: 163.78 | K248: 156.78 | L248: 158.375 | M248: 1331199.8 | N248: Wed, 15 Jul 2026 00:00:00 GMT | O248: =I248/L248-1 -> 0.0057142857 | Q248: 0.0225 | R248: 19 | T248: =T247+0.0025 -> 0.0175 | U248: =_xlfn.NORM.DIST(T248,$S$202,$S$204,FALSE) -> 12.892329
A249: 689.32789 | B249: 690.62456 | C249: 686.43533 | D249: 688.44017 | E249: 4581789 | F249: Tue, 14 Jul 2026 00:00:00 GMT | G249: =A249/D249-1 -> 0.0012894626 | I249: 159.12 | J249: 160.1 | K249: 153.84 | L249: 158.8 | M249: 1942091.4 | N249: Tue, 14 Jul 2026 00:00:00 GMT | O249: =I249/L249-1 -> 0.0020151134 | Q249: 0.025 | R249: 23 | T249: =T248+0.0025 -> 0.02 | U249: =_xlfn.NORM.DIST(T249,$S$202,$S$204,FALSE) -> 11.548392
A250: 686.73456 | B250: 691.18312 | C250: 685.77702 | D250: 689.82661 | E250: 6604827.4 | F250: Mon, 13 Jul 2026 00:00:00 GMT | G250: =A250/D250-1 -> -0.0044823597 | I250: 162.06 | J250: 164.45 | K250: 161.23 | L250: 161.48 | M250: 1616672.2 | N250: Mon, 13 Jul 2026 00:00:00 GMT | O250: =I250/L250-1 -> 0.0035917761 | Q250: 0.0275 | R250: 16 | T250: =T249+0.0025 -> 0.0225 | U250: =_xlfn.NORM.DIST(T250,$S$202,$S$204,FALSE) -> 10.201045
A251: 692.08081 | B251: 692.54961 | C251: 685.86679 | D251: 689.4775 | E251: 4678890.4 | F251: Fri, 10 Jul 2026 00:00:00 GMT | G251: =A251/D251-1 -> 0.0037757685 | I251: 161.28 | J251: 161.82 | K251: 158.3 | L251: 159.21 | M251: 723083.97 | N251: Fri, 10 Jul 2026 00:00:00 GMT | O251: =I251/L251-1 -> 0.013001696 | Q251: 0.03 | R251: 12 | T251: =T250+0.0025 -> 0.025 | U251: =_xlfn.NORM.DIST(T251,$S$202,$S$204,FALSE) -> 8.8858884
A252: 688.91894 | B252: 689.41387 | C252: 683.53279 | D252: 685.18853 | E252: 6412322.8 | F252: Thu, 09 Jul 2026 00:00:00 GMT | G252: =A252/D252-1 -> 0.0054443555 | I252: 158.29 | J252: 158.63 | K252: 152.78 | L252: 156.4 | M252: 1069923.9 | N252: Thu, 09 Jul 2026 00:00:00 GMT | O252: =I252/L252-1 -> 0.012084399 | Q252: 0.0325 | R252: 11 | T252: =T251+0.0025 -> 0.0275 | U252: =_xlfn.NORM.DIST(T252,$S$202,$S$204,FALSE) -> 7.6329086
A253: 683.50286 | B253: 684.08138 | C253: 677.98704 | D253: 681.3484 | E253: 4817716.3 | F253: Wed, 08 Jul 2026 00:00:00 GMT | G253: =A253/D253-1 -> 0.0031620553 | I253: 157.46 | J253: 160.48 | K253: 156.8 | L253: 160.48 | M253: 976821.77 | N253: Wed, 08 Jul 2026 00:00:00 GMT | O253: =I253/L253-1 -> -0.018818544 | Q253: 0.035 | R253: 7 | T253: =T252+0.0025 -> 0.03 | U253: =_xlfn.NORM.DIST(T253,$S$202,$S$204,FALSE) -> 6.4656515
... A267: 685.98352 | B267: 690.7772 | C267: 685.67521 | D267: 690.04124 | E267: 13356562 | F267: Tue, 16 Jun 2026 00:00:00 GMT | G267: =A267/D267-1 -> -0.005880403 | I267: 147.69 | J267: 150.89 | K267: 146.3332 | L267: 149.69 | M267: 914158.43 | N267: Tue, 16 Jun 2026 00:00:00 GMT | O267: =I267/L267-1 -> -0.013360946 | Q267: 0.07 | R267: 1 | T267: =T266+0.0025 -> 0.065 | U267: =_xlfn.NORM.DIST(T267,$S$202,$S$204,FALSE) -> 0.14604651
A268: 690.04124 | B268: 691.95075 | C268: 687.48527 | D268: 687.52505 | E268: 14094113 | F268: Mon, 15 Jun 2026 00:00:00 GMT | G268: =A268/D268-1 -> 0.0036597714 | I268: 148.14 | J268: 150.58 | K268: 147.4601 | L268: 149.23 | M268: 1041094.3 | N268: Mon, 15 Jun 2026 00:00:00 GMT | O268: =I268/L268-1 -> -0.0073041614 | Q268: More | R268: 1 | T268: =T267+0.0025 -> 0.0675 | U268: =_xlfn.NORM.DIST(T268,$S$202,$S$204,FALSE) -> 0.10032491
A269: 678.22611 | B269: 680.70122 | C269: 672.11964 | D269: 677.35589 | E269: 6330869.3 | F269: Fri, 12 Jun 2026 00:00:00 GMT | G269: =A269/D269-1 -> 0.0012847337 | I269: 149.7 | J269: 150.6 | K269: 145.1431 | L269: 149.605 | M269: 992588.28 | N269: Fri, 12 Jun 2026 00:00:00 GMT | O269: =I269/L269-1 -> 0.00063500551 | T269: =T268+0.0025 -> 0.07 | U269: =_xlfn.NORM.DIST(T269,$S$202,$S$204,FALSE) -> 0.067960945
A270: 674.52642 | B270: 676.66468 | C270: 662.36321 | D270: 666.44082 | E270: 19977996 | F270: Thu, 11 Jun 2026 00:00:00 GMT | G270: =A270/D270-1 -> 0.012132518 | I270: 149.19 | J270: 150.86 | K270: 147.34 | L270: 150.03 | M270: 1501319 | N270: Thu, 11 Jun 2026 00:00:00 GMT | O270: =I270/L270-1 -> -0.0055988802 | T270: =T269+0.0025 -> 0.0725 | U270: =_xlfn.NORM.DIST(T270,$S$202,$S$204,FALSE) -> 0.045398664
A271: 663.40747 | B271: 675.1679 | C271: 663.2384 | D271: 670.6328 | E271: 16398151 | F271: Wed, 10 Jun 2026 00:00:00 GMT | G271: =A271/D271-1 -> -0.010773896 | I271: 150.71 | J271: 161.35 | K271: 149.285 | L271: 159 | M271: 1390135.2 | N271: Wed, 10 Jun 2026 00:00:00 GMT | O271: =I271/L271-1 -> -0.052138365 | T271: =T270+0.0025 -> 0.075 | U271: =_xlfn.NORM.DIST(T271,$S$202,$S$204,FALSE) -> 0.029906098
A272: 673.99932 | B272: 683.00984 | C272: 660.69248 | D272: 679.9765 | E272: 13859821 | F272: Tue, 09 Jun 2026 00:00:00 GMT | G272: =A272/D272-1 -> -0.0087902766 | I272: 159.61 | J272: 160.87 | K272: 149.17 | L272: 150.93 | M272: 1819631.7 | N272: Tue, 09 Jun 2026 00:00:00 GMT | O272: =I272/L272-1 -> 0.057510104
A273: 675.9685 | B273: 681.54787 | C273: 674.99386 | D273: 679.73781 | E273: 8792759.6 | F273: Mon, 08 Jun 2026 00:00:00 GMT | G273: =A273/D273-1 -> -0.0055452324 | I273: 151.51 | J273: 153.57 | K273: 150 | L273: 151.975 | M273: 1217337.9 | N273: Mon, 08 Jun 2026 00:00:00 GMT | O273: =I273/L273-1 -> -0.0030597138
A274: 674.29768 | B274: 688.40025 | C274: 672.55723 | D274: 687.93281 | E274: 10747917 | F274: Fri, 05 Jun 2026 00:00:00 GMT | G274: =A274/D274-1 -> -0.019820445 | I274: 153.22 | J274: 154.71 | K274: 149.21 | L274: 149.23 | M274: 2306324 | N274: Fri, 05 Jun 2026 00:00:00 GMT | O274: =I274/L274-1 -> 0.026737251
A275: 692.25906 | B275: 693.39283 | C275: 687.12724 | D275: 687.71401 | E275: 6610989.8 | F275: Thu, 04 Jun 2026 00:00:00 GMT | G275: =A275/D275-1 -> 0.006608917 | I275: 146.41 | J275: 151.145 | K275: 144.2701 | L275: 146.98 | M275: 1408320.8 | N275: Thu, 04 Jun 2026 00:00:00 GMT | O275: =I275/L275-1 -> -0.0038780787
A276: 689.5738 | B276: 693.84028 | C276: 689.06659 | D276: 693.27349 | E276: 5914876.3 | F276: Wed, 03 Jun 2026 00:00:00 GMT | G276: =A276/D276-1 -> -0.0053365467 | I276: 143.3 | J276: 145.335 | K276: 141.45 | L276: 144.47 | M276: 1140274.4 | N276: Wed, 03 Jun 2026 00:00:00 GMT | O276: =I276/L276-1 -> -0.0080985672
A277: 694.44705 | B277: 695.33219 | C277: 691.98059 | D277: 692.25906 | E277: 4724193.7 | F277: Tue, 02 Jun 2026 00:00:00 GMT | G277: =A277/D277-1 -> 0.0031606471 | I277: 142.43 | J277: 147.225 | K277: 141.06 | L277: 145.65 | M277: 1104354.5 | N277: Tue, 02 Jun 2026 00:00:00 GMT | O277: =I277/L277-1 -> -0.022107793
...

Sheet Product Lines

Sheet Economics

Sheet Management

Sheet Table Formatting
B2: [Bold Title] | G2: [Bold Title]
B3: Line Titles | G3: <-- General
B4: Line Titles | G4: <-- Info
B5: Line Titles | G5: <-- General
B6: Line Titles | G6: <-- Info
B7: Line Titles | G7: <-- General
B8: Line Titles | G8: <-- Info
