Workbook

Sheet Main
A1: Master
A2: Capital Structure Snapshot:
B4: PYPL
B5: Price | C5: 57.8 | D5: 1/10/2025
B6: SO | C6: 935.65 | D6: Q3'25
B7: MC | C7: =C5*C6 -> 54080.57
B8: Cash | C8: =8995+1760 -> 10755 | D8: Q3'25
B9: Debt | C9: 11276 | D9: Q3'25
B10: EV | C10: =C7-C8+C9 -> 54601.57
B12: Paypal (PYPL)
B14: Founder(s): Peter Thiel, Max Levchin, Luke Nosek, Ken Howery, Yu Pan, Elon Musk | J14: Registered Exchange: | Q14: Resources:
B15: Founded: 1998 | J15: Address: | K15: 2211 North First Street San Jose, CA 95131 U.S. | Q15: SEC filings | T15: https://www.sec.gov/edgar/browse/?CIK=1633917&owner=exclude
B16: Headquarters: San Jose, CA | J16: Investor Relations Contact: | Q16: Paypal Homepage | T16: https://www.paypal.com/us/home
B17: Current CEO: James Alexander Chriss (Joined Sep 27, 2023) | J17: Investors Relation Department | R17: Paypal IR Page | U17: https://investor.pypl.com/home/
B18: Employees: 24,400 | J18: Phone: | K18: (408) 967 - 7000 | M18: Email: | Q18: Earnings Calls | T18: https://seekingalpha.com/symbol/PYPL/earnings/transcripts
B19: Industry: FinTech / Credit Services | Q19: Equity Analysis | T19: https://stockanalysis.com/stocks/pypl/
B20: Sector: Financials | Q20: Godel Terminal | T20: https://app.godelterminal.com/
B21: IPO: Feb 15, 2002 -- ~$800M valuation (bought by eBay for $1.5B in stock: Oct, 3,2002)
B22: Active Users: 432M
A24: Company Overview:
B25: PayPal Holdings, Inc. operates a scaled financial technology platform that enables digital payments on behalf of both merchants and consumers worldwide
C26: It generates most revenue from transaction fees on total payment volume (TPV), with additional contribution from value‑added services such as merchant solutions, credit products, and partnerships
B27: The Company's payments platform allows consumers to send and receive payments in approximately 200 markets and in approximately 100 currencies, withdraw funds to their bank accounts in 56 currencies, and hold balances in their PayPal accounts in 25 currencies
A35: Product Lines:
B36: The Business provides payment solutions under the PayPal, PayPal Credit, Braintree, Venmo, Xoom, Zettle, Hyperwallet, Honey, and Paidy names.
B37: PayPal: | C37: PayPal is The Company's core digital payment platform that connects consumers and merchants with a secure and convenient way to transact online, in-store, and across borders.
D38: PayPal supports a "digital wallet" and allows for multiple payment methods including Visa, Mastercard, Discover, American Express, traditional bank accounts or direct PayPal account debits
D39: The Company facilitates withdraws to bank accounts in 56 currencies and balance holding in 25 currencies. Cross-boarder transactions are approximately 25% of PayPal's TPV
D40: PayPal account presents users with a gateway to Buy-Now Pay-Later products
B41: PayPal Credit: | C41: PayPal Credit is a digital, reusable line of credit that functions similarly to a credit card but without a physical card.
D42: Revolving credit line that is automatically integrated into the user's PayPal account upon approval
D43: Minimum beginning credit line of $250, which increases or decreases based on periodic account reviews
D44: PayPal Credit allows users to send money online, but a 2.9% + $0.30 fee applies for this feature
B45: Braintree: | C45: Braintree is a robust payment gateway and processor that offers comprehensive payment solutions for enterprises
D46: Allows for businesses to digitally process transactions through various payment methods including major credit/debit cards, digital wallets (PayPal, Apple Pay, Google Pay), and local payment options
D47: Offers additional transaction security for consumers and merchants.
D48: Supports subscription-based businesses with easy-to-manage recurring payment schedules
D49: Offers solutions for seamless mobile payment integration
D50: Transparent pricing model with a standard rate of 2.59% + $0.49 per transaction for most payment types
B51: Venmo: | C51: Venmo is a mobile payments app/platform (owned and operated by PayPal) that specializes in peer-to-peer money transfers and payments
D52: Facilitates quick and secure money transfers between individuals, commonly used for splitting bills, sharing expenses, or reimbursing friends and family
D53: Can be used for purchases with authorized merchants via the Venmo app, in-store QR codes, or Venmo Mastercard Debit Card
D54: Venmo had 68.3 million active users in the U.S. in 2024, projected to grow to 72.9 million in 2025. User base is younger, with over 83% falling between 18-34 age bracket
D55: P2P transactions are free if funded through a bank account or Venmo balance but incur a 3% fee when funded via credit cards
B56: Xoom: | C56: Xoom is a digital money transfer service (owned and operated by PayPal) that specializes in fast, secure, and convenient international and domestic money transfers.
D57: Designed to help users send money, pay bills, reload mobile phones, and transfer funds globally
D58: Transfers can be made to bank accounts, debit cards, mobile wallets, or for cash pickup at agent locations.
D59: Fees vary based on factors such as the transfer amount, destination country, payment method, and delivery method
D60: Xoom applies a markup (4-6%) on the mid-market exchange rate for currency conversion, which is common among money transfer services
B61: Hyperwallet: | C61: Hyperwallet is a global payout platform designed to facilitate mass payments for businesses of various sizes across multiple industries.
D62: Enables payouts to 200+ markets in 50+ currencies; supports funding in 28 currencies directly via bank transfer
D63: Offers diverse payout options including: Bank deposits, PayPal and Venmo transfers, Prepaid cards (physical and virtual), Checks, Cash pickup, eGift cards
D64: Enterprise product: primary target users include small, medium and, large enterprises
C65: Hyperwallet aims to streamline the global payout process, reduce cross-border payout costs, and provide businesses with a comprehensive solution for managing complex international payments while ensuring regulatory compliance.
B66: Honey: | C66: PayPal Honey is a free browser extension and mobile app designed to help users save money and earn rewards while shopping online. (17 million members). PayPal acquired Honey in January 2020 for approximately $4 billion.
D67: Searches for and applies the best available coupon codes at checkout on over 30,000 popular websites
D68: Users can earn PayPal Rewards points on eligible purchases; Points can be redeemed for cash in your PayPal account or gift cards
D69: Compares prices across different Amazon sellers, factoring in shipping costs and Prime status
C70: PayPal Honey aims to simplify the online shopping experience by automatically finding deals, applying coupons, and offering cash back opportunities, all while integrating with PayPal's broader suite of financial services.
B71: Paidy: | C71: Japanese buy now, pay later platform. (Over 6 million registered users). PayPal acquired Paidy in September 2021 for approximately $2.7 billion.
D72: Allows Japanese shoppers to make online purchases and pay for them monthly in a consolidated bill. Offers payment options including paying the following month or using a 3-Pay (BNPL) installment plan.
D73: Paidy uses proprietary technology to score creditworthiness and underwrite transactions
D74: PayPal generates revenues through its Paidy platform through transaction fees, late fee charges, interest on installment plans, currency conversion fees and interest on customer funds
B75: As of December 31, 2024, The Company's platforms boast 434 million active accounts (consumers and merchants) across approximately 200 markets.
A77: Revenue Overview:
B78: Transaction Fees from payment processing: | F78: Transaction fees: ~90.5% of total revenue
B79: The Business primarily earns revenues by charging fees for completing payment transactions for customers and other payment-related services, which are typically based on the volume of activity processed on the payment platforms.
B80: Total Payment Volume (TPV) is a KPI for The Business that provides insight into the businesses current operating scale and growth trajectory. Payment processing is the revenue driver
C81: Payment processing is spread across a multitude of subsidiary platforms (listed above)
B82: Value Added Services and other revenue: | G82: VAS and other revenues: ~9.5% of total revenue
C83: The Business also earns revenue by providing other value added services, primarily comprised of partnerships deals/agreements, and interest and fees collected by The Business from consumer and merchant credit products.
D84: PayPal manages a consumer and commercial loan portfolio (PayPal credit/personal loans and commercial working capital loans)
D85: Strategic partnerships integrate PayPal payment processing solutions with other existing networks (Amazon Checkout, Shopify Payments, Global Payments partnership, Fiserv integration, etc.)
C86: The Business also generates revenues from currency conversion, for instant transfers from user PayPal or Venmo account to their bank account or debit card, and facilitating the purchase and sale of cryptocurrencies.
D87: PayPal charges a currency conversion fee of 3-4% when users need to convert between different currencies (Cross-Currency/Border Transactions)
D88: The Business facilitates the buying and selling of cryptocurrencies, using a fee structure based on the customer's transaction size. Additionally, The Company applies a spread of ~ 0.5% on cryptocurrency purchases and sales
C89: The Business also earns interest revenues on certain underlying customer balances, referral fees, subscription fees, and gateway services.
D90: The company earns interest on funds held in customer accounts
D91: PayPal earns recurring revenue from subscription-based services and gateway fees. Merchants integrate PayPal's payment solutions directly into their e-commerce platforms, paying a fee for the service
D92: PayPal collects referral fees through browser plug-in Honey, as well as through more traditional methods such as partnership agreements from integrating PayPal tools into other networks

Sheet Model
B1: [Use for Graphing] | W1: Q1 2020 | AA1: Q1 2021 | AE1: Q1 2022 | AI1: Q1 2023 | AM1: Q1 2024 | AQ1: Q1 2025 | AU1: Q1 2026
B2: Quarterly
B3: Revenues | C3: Q1 2015 | D3: Q2 2015 | E3: Q3 2015 | F3: Q4 2015 | G3: Q1 2016 | H3: Q2 2016 | I3: Q3 2016 | J3: Q4 2016 | K3: Q1 2017 | L3: Q2 2017 | M3: Q3 2017 | N3: Q4 2017 | O3: Q1 2018 | P3: Q2 2018 | Q3: Q3 2018 | R3: Q4 2018 | S3: Q1 2019 | T3: Q2 2019 | U3: Q3 2019 | V3: Q4 2019 | W3: Q1 2020 | X3: Q2 2020 | Y3: Q3 2020 | Z3: Q4 2020 | AA3: Q1 2021 | AB3: Q2 2021 | AC3: Q3 2021 | AD3: Q4 2021 | AE3: Q1 2022 | AF3: Q2 2022 | AG3: Q3 2022 | AH3: Q4 2022 | AI3: Q1 2023 | AJ3: Q2 2023 | AK3: Q3 2023 | AL3: Q4 2023 | AM3: Q1 2024 | AN3: Q2 2024 | AO3: Q3 2024 | AP3: Q4 2024 | AQ3: Q1 2025 | AR3: Q2 2025 | AS3: Q3 2025 | AT3: Q4 2025 | AU3: Q1 2026 | AV3: Q2 2026 | AW3: Q3 2026 | AX3: Q4 2026 | AY3: Q1 2027 | AZ3: Q2 2027 | BA3: Q3 2027 | BB3: Q4 2027 | BG3: 2015 | BH3: =BG3+1 -> 2016 | BI3: =BH3+1 -> 2017 | BJ3: =BI3+1 -> 2018 | BK3: =BJ3+1 -> 2019 | BL3: =BK3+1 -> 2020 | BM3: =BL3+1 -> 2021 | BN3: =BM3+1 -> 2022 | BO3: =BN3+1 -> 2023 | ... DX3: =DW3+1 -> 2084
B4: Transaction Revenues | W4: 4215 | X4: 4945 | Y4: 5076 | Z4: =19918-SUM(W4:Y4) -> 5682 | AA4: 5621 | AB4: 5797 | AC4: 5607 | AD4: =23402-SUM(AA4:AC4) -> 6377 | AE4: 5998 | AF4: 6272 | AG4: 6234 | AH4: =25206-SUM(AE4:AG4) -> 6702 | AI4: 6364 | AJ4: 6556 | AK4: 6654 | AL4: =26857-SUM(AI4:AK4) -> 7283 | AM4: 7034 | AN4: 7153 | AO4: 7067 | AP4: =28842-SUM(AM4:AO4) -> 7588 | AQ4: 7016 | AR4: 7441 | AS4: 7522 | BL4: =SUM(W4:Z4) -> 19918 | BM4: =SUM(AA4:AD4) -> 23402 | BN4: =SUM(AE4:AH4) -> 25206 | BO4: =SUM(Model!AI4:AL4) -> 26857 | BP4: =SUM(Model!AM4:AP4) -> 28842 | BQ4: =BP4*(1+BQ8) -> 30067.785 | BR4: =BQ4*(1+BR8) -> 31390.768 | BS4: =BR4*(1+BS8) -> 32803.352 | BT4: =BS4*(1+BT8) -> 34312.306 | BU4: =BT4*(1+BU8) -> 35924.985 | BV4: =BU4*(1+BV8) -> 37649.384 | BW4: =BV4*(1+BW8) -> 39494.204 | BX4: =BW4*(1+BX8) -> 41468.914 | ... BZ4: =BY4*(1+BZ8) -> 45719.478
B5: Revenues from other VASs | W5: 403 | X5: 316 | Y5: 383 | Z5: =1536-SUM(W5:Y5) -> 434 | AA5: 412 | AB5: 441 | AC5: 575 | AD5: =1969-SUM(AA5:AC5) -> 541 | AE5: 485 | AF5: 534 | AG5: 612 | AH5: =2312-SUM(AE5:AG5) -> 681 | AI5: 676 | AJ5: 731 | AK5: 764 | AL5: =2914-SUM(AI5:AK5) -> 743 | AM5: 665 | AN5: 732 | AO5: 780 | AP5: =2955-SUM(AM5:AO5) -> 778 | AQ5: 775 | AR5: 847 | AS5: 895 | BL5: =SUM(W5:Z5) -> 1536 | BM5: =SUM(AA5:AD5) -> 1969 | BN5: =SUM(AE5:AH5) -> 2312 | BO5: =SUM(Model!AI5:AL5) -> 2914 | BP5: =SUM(Model!AM5:AP5) -> 2955 | BQ5: =BP5*(1+BQ9) -> 3353.925 | BR5: =BQ5*(1+BR9) -> 3957.6315 | BS5: =BR5*(1+BS9) -> 4749.1578 | BT5: =BS5*(1+BT9) -> 5556.5146 | BU5: =BT5*(1+BU9) -> 6334.4267 | BV5: =BU5*(1+BV9) -> 7094.5579 | BW5: =BV5*(1+BW9) -> 7804.0137 | BX5: =BW5*(1+BX9) -> 8506.3749 | ... BZ5: =BY5*(1+BZ9) -> 9829.9668
B6: Ttl Revenues | W6: =SUM(W4:W5) -> 4618 | X6: =SUM(X4:X5) -> 5261 | Y6: =SUM(Y4:Y5) -> 5459 | Z6: =SUM(Z4:Z5) -> 6116 | AA6: =SUM(AA4:AA5) -> 6033 | AB6: =SUM(AB4:AB5) -> 6238 | AC6: =SUM(AC4:AC5) -> 6182 | AD6: =SUM(AD4:AD5) -> 6918 | ... AS6: =SUM(AS4:AS5) -> 8417 | BL6: =SUM(W6:Z6) -> 21454 | BM6: =SUM(AA6:AD6) -> 25371 | BN6: =SUM(AE6:AH6) -> 27518 | BO6: =SUM(Model!AI6:AL6) -> 29771 | BP6: =SUM(Model!AM6:AP6) -> 31797 | BQ6: =SUM(BQ4:BQ5) -> 33421.71 | BR6: =SUM(BR4:BR5) -> 35348.399 | BS6: =SUM(BS4:BS5) -> 37552.51 | BT6: =SUM(BT4:BT5) -> 39868.821 | BU6: =SUM(BU4:BU5) -> 42259.411 | BV6: =SUM(BV4:BV5) -> 44743.942 | BW6: =SUM(BW4:BW5) -> 47298.217 | BX6: =SUM(BX4:BX5) -> 49975.289 | ... BZ6: =SUM(BZ4:BZ5) -> 55549.444
B8: Transaction Revenue Growth Y/y | AA8: =AA4/W4-1 -> 0.33357058 | AB8: =AB4/X4-1 -> 0.17229525 | AC8: =AC4/Y4-1 -> 0.10460993 | AD8: =AD4/Z4-1 -> 0.12231609 | AE8: =AE4/AA4-1 -> 0.067069916 | AF8: =AF4/AB4-1 -> 0.081938934 | AG8: =AG4/AC4-1 -> 0.11182451 | AH8: =AH4/AD4-1 -> 0.050964403 | ... AS8: =AS4/AO4-1 -> 0.064383755 | BM8: =BM4/BL4-1 -> 0.17491716 | BN8: =BN4/BM4-1 -> 0.077087428 | BO8: =BO4/BN4-1 -> 0.065500278 | BP8: =BP4/BO4-1 -> 0.073909968 | BQ8: 0.0425 | BR8: 0.044 | BS8: 0.045 | BT8: 0.046 | BU8: 0.047 | BV8: 0.048 | BW8: 0.049 | BX8: 0.05 | BY8: 0.05 | BZ8: 0.05
B9: VAS Revenue Growth Y/y | AA9: =AA5/W5-1 -> 0.022332506 | AB9: =AB5/X5-1 -> 0.39556962 | AC9: =AC5/Y5-1 -> 0.50130548 | AD9: =AD5/Z5-1 -> 0.24654378 | AE9: =AE5/AA5-1 -> 0.17718447 | AF9: =AF5/AB5-1 -> 0.21088435 | AG9: =AG5/AC5-1 -> 0.064347826 | AH9: =AH5/AD5-1 -> 0.25878004 | ... AS9: =AS5/AO5-1 -> 0.1474359 | BM9: =BM5/BL5-1 -> 0.28190104 | BN9: =BN5/BM5-1 -> 0.1742001 | BO9: =BO5/BN5-1 -> 0.26038062 | BP9: =BP5/BO5-1 -> 0.014070007 | BQ9: 0.135 | BR9: 0.18 | BS9: 0.2 | BT9: 0.17 | BU9: 0.14 | BV9: 0.12 | BW9: 0.1 | BX9: 0.09 | BY9: 0.08 | BZ9: 0.07
B10: Total Revenue Growth Y/y | AA10: =AA6/W6-1 -> 0.3064097 | AB10: =AB6/X6-1 -> 0.18570614 | AC10: =AC6/Y6-1 -> 0.13244184 | AD10: =AD6/Z6-1 -> 0.13113146 | AE10: =AE6/AA6-1 -> 0.074589756 | AF10: =AF6/AB6-1 -> 0.091054825 | AG10: =AG6/AC6-1 -> 0.10740861 | AH10: =AH6/AD6-1 -> 0.067215958 | ... AS10: =AS6/AO6-1 -> 0.072639225 | BM10: =BM6/BL6-1 -> 0.18257668 | BN10: =BN6/BM6-1 -> 0.084624177 | BO10: =BO6/BN6-1 -> 0.081873683 | BP10: =BP6/BO6-1 -> 0.068052803 | BQ10: =BQ6/BP6-1 -> 0.05109633 | BR10: =BR6/BQ6-1 -> 0.05764783 | BS10: =BS6/BR6-1 -> 0.062353908 | BT10: =BT6/BS6-1 -> 0.061681923 | ... BZ10: =BZ6/BY6-1 -> 0.05348455
B12: Transcation % of Ttl Revenues | W12: =W4/W6 -> 0.91273278 | X12: =X4/X6 -> 0.93993537 | Y12: =Y4/Y6 -> 0.92984063 | Z12: =Z4/Z6 -> 0.92903859 | AA12: =AA4/AA6 -> 0.93170893 | AB12: =AB4/AB6 -> 0.92930426 | AC12: =AC4/AC6 -> 0.90698803 | AD12: =AD4/AD6 -> 0.92179821 | ... AS12: =AS4/AS6 -> 0.89366758 | BL12: =BL4/BL6 -> 0.92840496 | BM12: =BM4/BM6 -> 0.92239171 | BN12: =BN4/BN6 -> 0.91598227 | BO12: =BO4/BO6 -> 0.90211951 | BP12: =BP4/BP6 -> 0.9070667 | BQ12: =BQ4/BQ6 -> 0.89964831 | BR12: =BR4/BR6 -> 0.8880393 | BS12: =BS4/BS6 -> 0.87353288 | ... BZ12: =BZ4/BZ6 -> 0.82304113
B13: VASs % of Ttl Revenues | W13: =W5/W6 -> 0.087267215 | X13: =X5/X6 -> 0.060064626 | Y13: =Y5/Y6 -> 0.07015937 | Z13: =Z5/Z6 -> 0.070961413 | AA13: =AA5/AA6 -> 0.068291066 | AB13: =AB5/AB6 -> 0.070695736 | AC13: =AC5/AC6 -> 0.09301197 | AD13: =AD5/AD6 -> 0.078201792 | ... AS13: =AS5/AS6 -> 0.10633242 | BL13: =BL5/BL6 -> 0.071595041 | BM13: =BM5/BM6 -> 0.077608293 | BN13: =BN5/BN6 -> 0.084017734 | BO13: =BO5/BO6 -> 0.097880488 | BP13: =BP5/BP6 -> 0.092933296 | BQ13: =BQ5/BQ6 -> 0.10035169 | BR13: =BR5/BR6 -> 0.1119607 | BS13: =BS5/BS6 -> 0.12646712 | ... BZ13: =BZ5/BZ6 -> 0.17695887
B15: U.S. | W15: 2469 | X15: 2651 | Y15: 2820 | Z15: =11013-SUM(W15:Y15) -> 3073 | AA15: 3063 | AB15: 3272 | AC15: 3476 | AD15: =13712-SUM(AA15:AC15) -> 3901 | AE15: 3671 | AF15: 3863 | AG15: 3978 | AH15: =15807-SUM(AE15:AG15) -> 4295 | AI15: 4147 | AJ15: 4210 | AK15: 4257 | AL15: =17253-SUM(AI15:AK15) -> 4639 | AM15: 4467 | AN15: 4550 | AO15: 4518 | AP15: =18267-SUM(AM15:AO15) -> 4732 | AQ15: 4463 | AR15: 4709 | AS15: 4753 | BL15: =SUM(W15:Z15) -> 11013 | BM15: =SUM(AA15:AD15) -> 13712 | BN15: =SUM(AE15:AH15) -> 15807 | BO15: =SUM(Model!AI15:AL15) -> 17253 | BP15: =SUM(Model!AM15:AP15) -> 18267
B16: International | W16: =478+1671 -> 2149 | X16: =586+2024 -> 2610 | Y16: =606+2033 -> 2639 | Z16: =2340+8101-SUM(W16:Y16) -> 3043 | AA16: =625+2345 -> 2970 | AB16: =587+2379 -> 2966 | AC16: =529+2177 -> 2706 | AD16: =2340+9319-SUM(AA16:AC16) -> 3017 | AE16: 2812 | AF16: 2943 | AG16: 2868 | AH16: =2071+9640-SUM(AE16:AG16) -> 3088 | AI16: 2893 | AJ16: 3077 | AK16: 3161 | AL16: =12518-SUM(AI16:AK16) -> 3387 | AM16: 3232 | AN16: 3335 | AO16: 3329 | AP16: =13530-SUM(AM16:AO16) -> 3634 | AQ16: 3328 | AR16: 3579 | AS16: 3664 | BL16: =SUM(W16:Z16) -> 10441 | BM16: =SUM(AA16:AD16) -> 11659 | BN16: =SUM(AE16:AH16) -> 11711 | BO16: =SUM(Model!AI16:AL16) -> 12518 | BP16: =SUM(Model!AM16:AP16) -> 13530
B17: Ttl Revenues | W17: =W16+W15 -> 4618 | X17: =X16+X15 -> 5261 | Y17: =Y16+Y15 -> 5459 | Z17: =Z16+Z15 -> 6116 | AA17: =AA16+AA15 -> 6033 | AB17: =AB16+AB15 -> 6238 | AC17: =AC16+AC15 -> 6182 | AD17: =AD16+AD15 -> 6918 | ... AS17: =AS16+AS15 -> 8417 | BL17: =SUM(W17:Z17) -> 21454 | BM17: =SUM(AA17:AD17) -> 25371 | BN17: =SUM(AE17:AH17) -> 27518 | BO17: =SUM(Model!AI17:AL17) -> 29771 | BP17: =SUM(Model!AM17:AP17) -> 31797
B19: U.S. Revenue Growth Y/y | AA19: =AA15/W15-1 -> 0.24058323 | AB19: =AB15/X15-1 -> 0.23425123 | AC19: =AC15/Y15-1 -> 0.23262411 | AD19: =AD15/Z15-1 -> 0.26944354 | AE19: =AE15/AA15-1 -> 0.1984982 | AF19: =AF15/AB15-1 -> 0.18062347 | AG19: =AG15/AC15-1 -> 0.14441887 | AH19: =AH15/AD15-1 -> 0.10099974 | ... AS19: =AS15/AO15-1 -> 0.052014166 | BM19: =BM15/BL15-1 -> 0.245074 | BN19: =BN15/BM15-1 -> 0.15278588 | BO19: =BO15/BN15-1 -> 0.091478459 | BP19: =BP15/BO15-1 -> 0.058772387
B20: International Revenue Growth Y/y | AA20: =AA16/W16-1 -> 0.38203816 | AB20: =AB16/X16-1 -> 0.13639847 | AC20: =AC16/Y16-1 -> 0.025388405 | AD20: =AD16/Z16-1 -> -0.0085441998 | AE20: =AE16/AA16-1 -> -0.053198653 | AF20: =AF16/AB16-1 -> -0.0077545516 | AG20: =AG16/AC16-1 -> 0.059866962 | AH20: =AH16/AD16-1 -> 0.023533311 | ... AS20: =AS16/AO16-1 -> 0.10063082 | BM20: =BM16/BL16-1 -> 0.11665549 | BN20: =BN16/BM16-1 -> 0.0044600738 | BO20: =BO16/BN16-1 -> 0.068909572 | BP20: =BP16/BO16-1 -> 0.080843585
B21: Ttl Revenue Growth Y/y | AA21: =AA17/W17-1 -> 0.3064097 | AB21: =AB17/X17-1 -> 0.18570614 | AC21: =AC17/Y17-1 -> 0.13244184 | AD21: =AD17/Z17-1 -> 0.13113146 | AE21: =AE17/AA17-1 -> 0.074589756 | AF21: =AF17/AB17-1 -> 0.091054825 | AG21: =AG17/AC17-1 -> 0.10740861 | AH21: =AH17/AD17-1 -> 0.067215958 | ... AS21: =AS17/AO17-1 -> 0.072639225 | BM21: =BM17/BL17-1 -> 0.18257668 | BN21: =BN17/BM17-1 -> 0.084624177 | BO21: =BO17/BN17-1 -> 0.081873683 | BP21: =BP17/BO17-1 -> 0.068052803
B23: U.S. % of Ttl Revenues | W23: =W15/W17 -> 0.53464703 | X23: =X15/X17 -> 0.5038966 | Y23: =Y15/Y17 -> 0.51657813 | Z23: =Z15/Z17 -> 0.50245258 | AA23: =AA15/AA17 -> 0.50770761 | AB23: =AB15/AB17 -> 0.52452709 | AC23: =AC15/AC17 -> 0.56227758 | AD23: =AD15/AD17 -> 0.5638913 | ... AS23: =AS15/AS17 -> 0.56469051 | BL23: =BL15/BL17 -> 0.51333085 | BM23: =BM15/BM17 -> 0.54045958 | BN23: =BN15/BN17 -> 0.57442401 | BO23: =BO15/BO17 -> 0.5795237 | BP23: =BP15/BP17 -> 0.57448816
B24: International % of Ttl Revenues | W24: =W16/W17 -> 0.46535297 | X24: =X16/X17 -> 0.4961034 | Y24: =Y16/Y17 -> 0.48342187 | Z24: =Z16/Z17 -> 0.49754742 | AA24: =AA16/AA17 -> 0.49229239 | AB24: =AB16/AB17 -> 0.47547291 | AC24: =AC16/AC17 -> 0.43772242 | AD24: =AD16/AD17 -> 0.4361087 | ... AS24: =AS16/AS17 -> 0.43530949 | BL24: =BL16/BL17 -> 0.48666915 | BM24: =BM16/BM17 -> 0.45954042 | BN24: =BN16/BN17 -> 0.42557599 | BO24: =BO16/BO17 -> 0.4204763 | BP24: =BP16/BP17 -> 0.42551184
B26: Ttl Active Users | AD26: 428 | AE26: 429 | AF26: 429 | AG26: 432 | AH26: 435 | AI26: 433 | AJ26: 431 | AK26: 428 | AL26: 426 | AM26: 427 | AN26: 429 | AO26: 432 | AP26: 434 | AQ26: 432 | AR26: 438 | AS26: 432 | BN26: =AVERAGE(AE26:AH26) -> 431.25 | BO26: =AVERAGE(Model!AI26:AL26) -> 429.5 | BP26: =AVERAGE(Model!AM26:AP26) -> 430.5
B27: TPV | BL27: $936 B | BM27: $1.25 T | BN27: $1.36 T | BO27: $1.53 T | BP27: $1.68 T
B29: Revenues | C29: 2137 | D29: 2297 | E29: 2258 | F29: 2556 | G29: 2544 | H29: 2650 | I29: 2667 | J29: 2981 | K29: 2975 | L29: 3136 | M29: 3239 | N29: 3744 | O29: 3685 | P29: 3857 | Q29: 3683 | R29: 4226 | S29: 4128 | T29: 4305 | U29: 4378 | V29: 4961 | W29: =W6 -> 4618 | X29: =X6 -> 5261 | Y29: =Y6 -> 5459 | Z29: =Z6 -> 6116 | AA29: =AA6 -> 6033 | AB29: =AB6 -> 6238 | AC29: =AC6 -> 6182 | AD29: =AD6 -> 6918 | ... AS29: =AS6 -> 8417 | AT29: 8850 | AU29: 8280 | AV29: 8530 | AW29: 8630 | AX29: 9210 | AY29: 8940 | AZ29: 8970 | BA29: 9020 | BG29: =SUM(C29:F29) -> 9248 | BH29: =SUM(G29:J29) -> 10842 | BI29: =SUM(K29:N29) -> 13094 | BJ29: =SUM(O29:R29) -> 15451 | BK29: =SUM(S29:V29) -> 17772 | BL29: =SUM(W29:Z29) -> 21454 | BM29: =SUM(AA29:AD29) -> 25371 | BN29: =SUM(AE29:AH29) -> 27518 | BO29: =SUM(AI29:AL29) -> 29771 | BP29: =SUM(AM29:AP29) -> 31797 | BQ29: =BQ6 -> 33421.71 | BR29: =BR6 -> 35348.399 | BS29: =BS6 -> 37552.51 | BT29: =BT6 -> 39868.821 | BU29: =BU6 -> 42259.411 | BV29: =BV6 -> 44743.942 | BW29: =BW6 -> 47298.217 | BX29: =BX6 -> 49975.289 | ... BZ29: =BZ6 -> 55549.444
B30: Transaction Expenses | W30: 1739 | X30: 1843 | Y30: 2022 | Z30: =7934-SUM(W30:Y30) -> 2330 | AA30: 2275 | AB30: 2524 | AC30: 2564 | AD30: =10315-SUM(AA30:AC30) -> 2952 | AE30: 2817 | AF30: 3044 | AG30: 2988 | AH30: =12173-SUM(AE30:AG30) -> 3324 | AI30: 3283 | AJ30: 3541 | AK30: 3603 | AL30: =14385-SUM(AI30:AK30) -> 3958 | AM30: 3917 | AN30: 3942 | AO30: 3841 | AP30: =15697-SUM(AM30:AO30) -> 3997 | AQ30: 3704 | AR30: 3968 | AS30: 4063 | BG30: =SUM(C30:F30) -> 0 | BH30: =SUM(G30:J30) -> 0 | BI30: =SUM(K30:N30) -> 0 | BJ30: =SUM(O30:R30) -> 0 | BK30: =SUM(S30:V30) -> 0 | BL30: =SUM(W30:Z30) -> 7934 | BM30: =SUM(AA30:AD30) -> 10315 | BN30: =SUM(AE30:AH30) -> 12173 | BO30: =SUM(AI30:AL30) -> 14385 | BP30: =SUM(AM30:AP30) -> 15697 | BQ30: =BQ29*BQ45 -> 16042.421 | BR30: =BR29*BR45 -> 17143.974 | BS30: =BS29*BS45 -> 18400.73 | BT30: =BT29*BT45 -> 19735.066 | BU30: =BU29*BU45 -> 21129.706 | BV30: =BV29*BV45 -> 22819.41 | BW30: =BW29*BW45 -> 24595.073 | BX30: =BX29*BX45 -> 26486.903 | ... BZ30: =BZ29*BZ45 -> 30552.194
B31: Transaction & Credit Losses | W31: 591 | X31: 440 | Y31: 344 | Z31: =1741-SUM(W31:Y31) -> 366 | AA31: 273 | AB31: 169 | AC31: 268 | AD31: =1060-SUM(AA31:AC31) -> 350 | AE31: 369 | AF31: 448 | AG31: 367 | AH31: =1572-SUM(AE31:AG31) -> 388 | AI31: 442 | AJ31: 398 | AK31: 446 | AL31: =1682-SUM(AI31:AK31) -> 396 | AM31: 321 | AN31: 335 | AO31: 352 | AP31: =1442-SUM(AM31:AO31) -> 434 | AQ31: 371 | AR31: 476 | AS31: 483 | BG31: =SUM(C31:F31) -> 0 | BH31: =SUM(G31:J31) -> 0 | BI31: =SUM(K31:N31) -> 0 | BJ31: =SUM(O31:R31) -> 0 | BK31: =SUM(S31:V31) -> 0 | BL31: =SUM(W31:Z31) -> 1741 | BM31: =SUM(AA31:AD31) -> 1060 | BN31: =SUM(AE31:AH31) -> 1572 | BO31: =SUM(AI31:AL31) -> 1682 | BP31: =SUM(AM31:AP31) -> 1442 | BQ31: =BQ29*BQ46 -> 1771.3506 | BR31: =BR29*BR46 -> 1944.1619 | BS31: =BS29*BS46 -> 2253.1506 | BT31: =BT29*BT46 -> 1993.441 | BU31: =BU29*BU46 -> 1916.4723 | BV31: =BV29*BV46 -> 1901.6175 | BW31: =BW29*BW46 -> 1986.5251 | BX31: =BX29*BX46 -> 2048.9868 | ... BZ31: =BZ29*BZ46 -> 2221.9778
B32: Customer Support & Op. Expenses | W32: 399 | X32: 423 | Y32: 449 | Z32: =1778-SUM(W32:Y32) -> 507 | AA32: 518 | AB32: 521 | AC32: 504 | AD32: =2075-SUM(AA32:AC32) -> 532 | AE32: 534 | AF32: 536 | AG32: 509 | AH32: =2120-SUM(AE32:AG32) -> 541 | AI32: 488 | AJ32: 492 | AK32: 474 | AL32: =1919-SUM(AI32:AK32) -> 465 | AM32: 454 | AN32: 436 | AO32: 427 | AP32: =1768-SUM(AM32:AO32) -> 451 | AQ32: 398 | AR32: 413 | AS32: 447 | BG32: =SUM(C32:F32) -> 0 | BH32: =SUM(G32:J32) -> 0 | BI32: =SUM(K32:N32) -> 0 | BJ32: =SUM(O32:R32) -> 0 | BK32: =SUM(S32:V32) -> 0 | BL32: =SUM(W32:Z32) -> 1778 | BM32: =SUM(AA32:AD32) -> 2075 | BN32: =SUM(AE32:AH32) -> 2120 | BO32: =SUM(AI32:AL32) -> 1919 | BP32: =SUM(AM32:AP32) -> 1768 | BQ32: =BQ29*BQ48 -> 3141.6407 | BR32: =BR29*BR48 -> 3358.0979 | BS32: =BS29*BS48 -> 3680.146 | BT32: =BT29*BT48 -> 4066.6197 | BU32: =BU29*BU48 -> 4437.2382 | BV32: =BV29*BV48 -> 4698.1139 | BW32: =BW29*BW48 -> 4966.3128 | BX32: =BX29*BX48 -> 5247.4053 | ... BZ32: =BZ29*BZ48 -> 5832.6917
B33: Sales & Marketing Expenses | C33: 217 | D33: 215 | E33: 216 | F33: 273 | G33: 231 | H33: 261 | I33: 261 | J33: 275 | K33: 305 | L33: 282 | M33: 293 | N33: 510 | O33: 500 | P33: 503 | Q33: 405 | R33: 442 | S33: 492 | T33: 417 | U33: 401 | V33: 401 | W33: 371 | X33: 414 | Y33: 471 | Z33: =1861-SUM(W33:Y33) -> 605 | AA33: 602 | AB33: 628 | AC33: 549 | AD33: =2445-SUM(AA33:AC33) -> 666 | AE33: 594 | AF33: 595 | AG33: 544 | AH33: =2257-SUM(AE33:AG33) -> 524 | AI33: 436 | AJ33: 465 | AK33: 442 | AL33: =1809-SUM(AI33:AK33) -> 466 | AM33: 421 | AN33: 446 | AO33: 508 | AP33: =2001-SUM(AM33:AO33) -> 626 | AQ33: 488 | AR33: 583 | AS33: 521 | BG33: =SUM(C33:F33) -> 921 | BH33: =SUM(G33:J33) -> 1028 | BI33: =SUM(K33:N33) -> 1390 | BJ33: =SUM(O33:R33) -> 1850 | BK33: =SUM(S33:V33) -> 1711 | BL33: =SUM(W33:Z33) -> 1861 | BM33: =SUM(AA33:AD33) -> 2445 | BN33: =SUM(AE33:AH33) -> 2257 | BO33: =SUM(AI33:AL33) -> 1809 | BP33: =SUM(AM33:AP33) -> 2001 | BQ33: 0 | BR33: 0 | BS33: 0 | BT33: 0 | BU33: 0 | BV33: 0 | BW33: 0 | BX33: 0 | BY33: 0 | BZ33: 0
B34: R&D Expenses | C34: 185 | D34: 202 | E34: 197 | F34: 208 | G34: 195 | H34: 209 | I34: 215 | J34: 215 | K34: 214 | L34: 232 | M34: 240 | N34: 1054 | O34: 448 | P34: 441 | Q34: 452 | R34: 490 | S34: 511 | T34: 483 | U34: 533 | V34: 558 | W34: 605 | X34: 631 | Y34: 674 | Z34: =2642-SUM(W34:Y34) -> 732 | AA34: 741 | AB34: 746 | AC34: 755 | AD34: =3038-SUM(AA34:AC34) -> 796 | AE34: 815 | AF34: 815 | AG34: 801 | AH34: =3253-SUM(AE34:AG34) -> 822 | AI34: 721 | AJ34: 743 | AK34: 739 | AL34: =2973-SUM(AI34:AK34) -> 770 | AM34: 742 | AN34: 718 | AO34: 746 | AP34: =2979-SUM(AM34:AO34) -> 773 | AQ34: 731 | AR34: 767 | AS34: 801 | BG34: =SUM(C34:F34) -> 792 | BH34: =SUM(G34:J34) -> 834 | BI34: =SUM(K34:N34) -> 1740 | BJ34: =SUM(O34:R34) -> 1831 | BK34: =SUM(S34:V34) -> 2085 | BL34: =SUM(W34:Z34) -> 2642 | BM34: =SUM(AA34:AD34) -> 3038 | BN34: =SUM(AE34:AH34) -> 3253 | BO34: =SUM(AI34:AL34) -> 2973 | BP34: =SUM(AM34:AP34) -> 2979 | BQ34: =BQ29*BQ48 -> 3141.6407 | BR34: =BR29*BR48 -> 3358.0979 | BS34: =BS29*BS48 -> 3680.146 | BT34: =BT29*BT48 -> 4066.6197 | BU34: =BU29*BU48 -> 4437.2382 | BV34: =BV29*BV48 -> 4698.1139 | BW34: =BW29*BW48 -> 4966.3128 | BX34: =BX29*BX48 -> 5247.4053 | ... BZ34: =BZ29*BZ48 -> 5832.6917
B35: G&A Expenses | C35: =1815-SUM(C33:C34) -> 1413 | D35: =1899-SUM(D33:D34) -> 1482 | E35: =1928-SUM(E33:E34) -> 1515 | F35: =2145-SUM(F33:F34) -> 1664 | G35: =2137-SUM(G33:G34) -> 1711 | H35: =2279-SUM(H33:H34) -> 1809 | I35: =2319-SUM(I33:I34) -> 1843 | J35: =2521-SUM(J33:J34) -> 2031 | K35: =2544-SUM(K33:K34) -> 2025 | L35: =2706-SUM(L33:L34) -> 2192 | M35: =2816-SUM(M33:M34) -> 2283 | N35: =2901-SUM(N33:N34) -> 1337 | O35: =3151-SUM(O33:O34) -> 2203 | P35: =3285-SUM(P33:P34) -> 2341 | Q35: =3193-SUM(Q33:Q34) -> 2336 | R35: =3628-SUM(R33:R34) -> 2696 | S35: =3610-SUM(S33:S34) -> 2607 | T35: =3600-SUM(T33:T34) -> 2700 | U35: =3681-SUM(U33:U34) -> 2747 | V35: =4162-SUM(V33:V34) -> 3203 | W35: 486 | X35: 512 | Y35: 503 | Z35: =2070-SUM(W35:Y35) -> 569 | AA35: 524 | AB35: 522 | AC35: 498 | AD35: =2114-SUM(AA35:AC35) -> 570 | AE35: 607 | AF35: 514 | AG35: 463 | AH35: =2099-SUM(AE35:AG35) -> 515 | AI35: 507 | AJ35: 491 | AK35: 507 | AL35: =2059-SUM(AI35:AK35) -> 554 | AM35: 464 | AN35: 570 | AO35: 519 | AP35: =2147-SUM(AM35:AO35) -> 594 | AQ35: 503 | AR35: 461 | AS35: 513 | BG35: =SUM(C35:F35) -> 6074 | BH35: =SUM(G35:J35) -> 7394 | BI35: =SUM(K35:N35) -> 7837 | BJ35: =SUM(O35:R35) -> 9576 | BK35: =SUM(S35:V35) -> 11257 | BL35: =SUM(W35:Z35) -> 2070 | BM35: =SUM(AA35:AD35) -> 2114 | BN35: =SUM(AE35:AH35) -> 2099 | BO35: =SUM(AI35:AL35) -> 2059 | BP35: =SUM(AM35:AP35) -> 2147 | BQ35: =BQ29*BQ49 -> 4144.292 | BR35: =BR29*BR49 -> 4418.5499 | BS35: =BS29*BS49 -> 4506.3012 | BT35: =BT29*BT49 -> 4704.5209 | BU35: =BU29*BU49 -> 4859.8323 | BV35: =BV29*BV49 -> 5145.5533 | BW35: =BW29*BW49 -> 5321.0495 | BX35: =BX29*BX49 -> 5497.2818 | ... BZ35: =BZ29*BZ49 -> 5554.9444
B36: Restructuring & Other Expenses | W36: 29 | X36: 47 | Y36: 19 | Z36: =139-SUM(W36:Y36) -> 44 | AA36: 58 | AB36: 1 | AC36: 1 | AD36: =62-SUM(AA36:AC36) -> 2 | AE36: 36 | AF36: 90 | AG36: 56 | AH36: =207-SUM(AE36:AG36) -> 25 | AI36: 164 | AJ36: 24 | AK36: 39 | AL36: =-84-SUM(AI36:AK36) -> -311 | AM36: 212 | AN36: 113 | AO36: 63 | AP36: =438-SUM(AM36:AO36) -> 50 | AQ36: 66 | AR36: 116 | AS36: 69 | BG36: =SUM(C36:F36) -> 0 | BH36: =SUM(G36:J36) -> 0 | BI36: =SUM(K36:N36) -> 0 | BJ36: =SUM(O36:R36) -> 0 | BK36: =SUM(S36:V36) -> 0 | BL36: =SUM(W36:Z36) -> 139 | BM36: =SUM(AA36:AD36) -> 62 | BN36: =SUM(AE36:AH36) -> 207 | BO36: =SUM(AI36:AL36) -> -84 | BP36: =SUM(AM36:AP36) -> 438 | BQ36: 0 | BR36: 0 | BS36: 0 | BT36: 0 | BU36: 0 | BV36: 0 | BW36: 0 | BX36: 0 | BY36: 0 | BZ36: 0
B37: Operating Income | C37: =C29-SUM(C30:C36) -> 322 | D37: =D29-SUM(D30:D36) -> 398 | E37: =E29-SUM(E30:E36) -> 330 | F37: =F29-SUM(F30:F36) -> 411 | G37: =G29-SUM(G30:G36) -> 407 | H37: =H29-SUM(H30:H36) -> 371 | I37: =I29-SUM(I30:I36) -> 348 | J37: =J29-SUM(J30:J36) -> 460 | ... AS37: =AS29-SUM(AS30:AS36) -> 1520 | BG37: =SUM(C37:F37) -> 1461 | BH37: =SUM(G37:J37) -> 1586 | BI37: =SUM(K37:N37) -> 2127 | BJ37: =SUM(O37:R37) -> 2194 | BK37: =SUM(S37:V37) -> 2719 | BL37: =SUM(W37:Z37) -> 3289 | BM37: =SUM(AA37:AD37) -> 4262 | BN37: =SUM(AE37:AH37) -> 3837 | BO37: =SUM(AI37:AL37) -> 5028 | BP37: =SUM(AM37:AP37) -> 5325 | BQ37: =BQ29-SUM(BQ30:BQ36) -> 5180.3651 | BR37: =BR29-SUM(BR30:BR36) -> 5125.5179 | BS37: =BS29-SUM(BS30:BS36) -> 5032.0363 | BT37: =BT29-SUM(BT30:BT36) -> 5302.5532 | BU37: =BU29-SUM(BU30:BU36) -> 5478.9246 | BV37: =BV29-SUM(BV30:BV36) -> 5481.1329 | BW37: =BW29-SUM(BW30:BW36) -> 5462.9441 | BX37: =BX29-SUM(BX30:BX36) -> 5447.3065 | ... BZ37: =BZ29-SUM(BZ30:BZ36) -> 5554.9444
B38: Other Income/(Expenses), net | C38: -1 | D38: 1 | E38: 20 | F38: 7 | G38: 15 | H38: 9 | I38: 12 | J38: 9 | K38: 7 | L38: 17 | M38: 28 | N38: 21 | O38: 14 | P38: 37 | Q38: 43 | R38: 88 | S38: 199 | T38: 238 | U38: -213 | V38: 55 | W38: -135 | X38: 848 | Y38: 167 | Z38: =1776-SUM(W38:Y38) -> 896 | AA38: -170 | AB38: 229 | AC38: 122 | AD38: =-163-SUM(AA38:AC38) -> -344 | AE38: -82 | AF38: -715 | AG38: 460 | AH38: =-471-SUM(AE38:AG38) -> -134 | AI38: 75 | AJ38: 170 | AK38: 73 | AL38: =383-SUM(AI38:AK38) -> 65 | AM38: 41 | AN38: 74 | AO38: -80 | AP38: =4-SUM(AM38:AO38) -> -31 | AQ38: 73 | AR38: 25 | AS38: 13 | BG38: =SUM(C38:F38) -> 27 | BH38: =SUM(G38:J38) -> 45 | BI38: =SUM(K38:N38) -> 73 | BJ38: =SUM(O38:R38) -> 182 | BK38: =SUM(S38:V38) -> 279 | BL38: =SUM(W38:Z38) -> 1776 | BM38: =SUM(AA38:AD38) -> -163 | BN38: =SUM(AE38:AH38) -> -471 | BO38: =SUM(AI38:AL38) -> 383 | BP38: =SUM(AM38:AP38) -> 4 | BQ38: =BP54*$BZ$56 -> 387.099 | BR38: =BQ54*$BZ$56 -> 654.15355 | BS38: =BR54*$BZ$56 -> 932.06905 | BT38: =BS54*$BZ$56 -> 1220.6125 | BU38: =BT54*$BZ$56 -> 1536.2032 | BV38: =BU54*$BZ$56 -> 1875.5951 | BW38: =BV54*$BZ$56 -> 2231.5136 | BX38: =BW54*$BZ$56 -> 2603.7715 | ... BZ38: =BY54*$BZ$56 -> 3418.7121
B39: Pretax Income | C39: =C37+C38 -> 321 | D39: =D37+D38 -> 399 | E39: =E37+E38 -> 350 | F39: =F37+F38 -> 418 | G39: =G37+G38 -> 422 | H39: =H37+H38 -> 380 | I39: =I37+I38 -> 360 | J39: =J37+J38 -> 469 | ... AS39: =AS37+AS38 -> 1533 | BG39: =SUM(C39:F39) -> 1488 | BH39: =SUM(G39:J39) -> 1631 | BI39: =SUM(K39:N39) -> 2200 | BJ39: =SUM(O39:R39) -> 2376 | BK39: =SUM(S39:V39) -> 2998 | BL39: =SUM(W39:Z39) -> 5065 | BM39: =SUM(AA39:AD39) -> 4099 | BN39: =SUM(AE39:AH39) -> 3366 | BO39: =SUM(AI39:AL39) -> 5411 | BP39: =SUM(AM39:AP39) -> 5329 | BQ39: =BQ37+BQ38 -> 5567.4641 | BR39: =BR37+BR38 -> 5779.6714 | BS39: =BS37+BS38 -> 5964.1054 | BT39: =BT37+BT38 -> 6523.1656 | BU39: =BU37+BU38 -> 7015.1279 | BV39: =BV37+BV38 -> 7356.728 | BW39: =BW37+BW38 -> 7694.4577 | BX39: =BX37+BX38 -> 8051.078 | ... BZ39: =BZ37+BZ38 -> 8973.6566
B40: Taxes | C40: 66 | D40: 94 | E40: 49 | F40: 51 | G40: 57 | H40: 57 | I40: 37 | J40: 79 | K40: 54 | L40: 36 | M40: 71 | N40: 244 | O40: 37 | P40: 83 | Q40: 97 | R40: 102 | S40: 50 | T40: 120 | U40: 22 | V40: 347 | W40: 179 | X40: 269 | Y40: 123 | Z40: =863-SUM(W40:Y40) -> 292 | AA40: -225 | AB40: 172 | AC40: 78 | AD40: =-70-SUM(AA40:AC40) -> -95 | AE40: 120 | AF40: 390 | AG40: 248 | AH40: =947-SUM(AE40:AG40) -> 189 | AI40: 279 | AJ40: 274 | AK40: 221 | AL40: =1165-SUM(AI40:AK40) -> 391 | AM40: 321 | AN40: 271 | AO40: 301 | AP40: =1182-SUM(AM40:AO40) -> 289 | AQ40: 316 | AR40: 268 | AS40: 285 | BG40: =SUM(C40:F40) -> 260 | BH40: =SUM(G40:J40) -> 230 | BI40: =SUM(K40:N40) -> 405 | BJ40: =SUM(O40:R40) -> 319 | BK40: =SUM(S40:V40) -> 539 | BL40: =SUM(W40:Z40) -> 863 | BM40: =SUM(AA40:AD40) -> -70 | BN40: =SUM(AE40:AH40) -> 947 | BO40: =SUM(AI40:AL40) -> 1165 | BP40: =SUM(AM40:AP40) -> 1182 | BQ40: =BQ39*BQ51 -> 1041.1158 | BR40: =BR39*BR51 -> 1069.2392 | BS40: =BS39*BS51 -> 1073.539 | BT40: =BT39*BT51 -> 1174.1698 | BU40: =BU39*BU51 -> 1262.723 | BV40: =BV39*BV51 -> 1324.211 | BW40: =BW39*BW51 -> 1385.0024 | BX40: =BX39*BX51 -> 1449.194 | ... BZ40: =BZ39*BZ51 -> 1615.2582
B41: Net Income | C41: =C39-C40 -> 255 | D41: =D39-D40 -> 305 | E41: =E39-E40 -> 301 | F41: =F39-F40 -> 367 | G41: =G39-G40 -> 365 | H41: =H39-H40 -> 323 | I41: =I39-I40 -> 323 | J41: =J39-J40 -> 390 | ... AS41: =AS39-AS40 -> 1248 | AT41: 1290 | AU41: 1150 | AV41: 1200 | AW41: 1250 | AX41: 1380 | AY41: 1280 | AZ41: 1340 | BA41: 1360 | BG41: =SUM(C41:F41) -> 1228 | BH41: =SUM(G41:J41) -> 1401 | BI41: =SUM(K41:N41) -> 1795 | BJ41: =SUM(O41:R41) -> 2057 | BK41: =SUM(S41:V41) -> 2459 | BL41: =SUM(W41:Z41) -> 4202 | BM41: =SUM(AA41:AD41) -> 4169 | BN41: =SUM(AE41:AH41) -> 2419 | BO41: =SUM(AI41:AL41) -> 4246 | BP41: =SUM(AM41:AP41) -> 4147 | BQ41: =BQ39-BQ40 -> 4526.3483 | BR41: =BR39-BR40 -> 4710.4322 | BS41: =BS39-BS40 -> 4890.5664 | BT41: =BT39-BT40 -> 5348.9958 | BU41: =BU39-BU40 -> 5752.4048 | BV41: =BV39-BV40 -> 6032.5169 | BW41: =BW39-BW40 -> 6309.4553 | BX41: =BX39-BX40 -> 6601.8839 | ... BZ41: =BZ39-BZ40 -> 7358.3984 | CA41: =BZ41*(1+$BZ$57) -> 7450.3784 | CB41: =CA41*(1+$BZ$57) -> 7543.5081 | CC41: =CB41*(1+$BZ$57) -> 7637.8019 | CD41: =CC41*(1+$BZ$57) -> 7733.2745 | CE41: =CD41*(1+$BZ$57) -> 7829.9404 | CF41: =CE41*(1+$BZ$57) -> 7927.8147 | CG41: =CF41*(1+$BZ$57) -> 8026.9123 | CH41: =CG41*(1+$BZ$57) -> 8127.2487 | ... DX41: =DW41*(1+$BZ$57) -> 13694.144
B42: SC | C42: 1218 | D42: 1218 | E42: 1221 | F42: 1222 | G42: 1216 | H42: 1210 | I42: 1207 | J42: 1210 | K42: 1203 | L42: 1202 | M42: 1202 | N42: 1203 | O42: 1192 | P42: 1187 | Q42: 1181 | R42: 1184 | S42: 1171 | T42: 1175 | U42: 1175 | V42: 1174 | W42: 1185 | X42: 1184 | Y42: 1190 | Z42: 1174 | AA42: 1190 | AB42: 1186 | AC42: 1187 | AD42: 1174 | AE42: 1163 | AF42: 1158 | AG42: 1157 | AH42: 1131 | AI42: 1134 | AJ42: 1114 | AK42: 1098 | AL42: 1071 | AM42: 1072 | AN42: 1047 | AO42: 1024 | AP42: 989 | AQ42: 986 | AR42: 969 | AS42: 950 | AT42: =AT41/AT43 -> 962.68657 | AU42: =AU41/AU43 -> 884.61538 | AV42: =AV41/AV43 -> 857.14286 | AW42: =AW41/AW43 -> 850.34014 | AX42: =AX41/AX43 -> 971.83099 | AY42: =AY41/AY43 -> 831.16883 | AZ42: =AZ41/AZ43 -> 858.97436 | BA42: =BA41/BA43 -> 814.37126 | BG42: =AVERAGE(C42:F42) -> 1219.75 | BH42: =AVERAGE(G42:J42) -> 1210.75 | BI42: =AVERAGE(K42:N42) -> 1202.5 | BJ42: =AVERAGE(O42:R42) -> 1186 | BK42: =AVERAGE(S42:V42) -> 1173.75 | BL42: =AVERAGE(W42:Z42) -> 1183.25 | BM42: =AVERAGE(AA42:AD42) -> 1184.25 | BN42: =AVERAGE(AE42:AH42) -> 1152.25 | BO42: =AVERAGE(AI42:AL42) -> 1104.25 | BP42: =AVERAGE(AM42:AP42) -> 1033
B43: EPS | C43: =C41/C42 -> 0.20935961 | D43: =D41/D42 -> 0.25041051 | E43: =E41/E42 -> 0.24651925 | F43: =F41/F42 -> 0.30032733 | G43: =G41/G42 -> 0.30016447 | H43: =H41/H42 -> 0.26694215 | I43: =I41/I42 -> 0.26760563 | J43: =J41/J42 -> 0.32231405 | ... AS43: =AS41/AS42 -> 1.3136842 | AT43: 1.34 | AU43: 1.3 | AV43: 1.4 | AW43: 1.47 | AX43: 1.42 | AY43: 1.54 | AZ43: 1.56 | BA43: 1.67 | BG43: =SUM(C43:F43) -> 1.0066167 | BH43: =SUM(G43:J43) -> 1.1570263 | BI43: =SUM(K43:N43) -> 1.4926501 | BJ43: =SUM(O43:R43) -> 1.7342471 | BK43: =SUM(S43:V43) -> 2.0950726 | BL43: =SUM(W43:Z43) -> 3.555852 | BM43: =SUM(AA43:AD43) -> 3.5181992 | BN43: =SUM(AE43:AH43) -> 2.1070362 | BO43: =SUM(AI43:AL43) -> 3.8627753 | BP43: =SUM(AM43:AP43) -> 4.0255184
B45: Transaction Expenses % of Revenue | W45: =W30/W29 -> 0.37656994 | X45: =X30/X29 -> 0.35031363 | Y45: =Y30/Y29 -> 0.37039751 | Z45: =Z30/Z29 -> 0.38096795 | AA45: =AA30/AA29 -> 0.37709266 | AB45: =AB30/AB29 -> 0.40461686 | AC45: =AC30/AC29 -> 0.41475251 | AD45: =AD30/AD29 -> 0.42671292 | ... AS45: =AS30/AS29 -> 0.48271356 | BL45: =BL30/BL29 -> 0.36981449 | BM45: =BM30/BM29 -> 0.40656655 | BN45: =BN30/BN29 -> 0.442365 | BO45: =BO30/BO29 -> 0.48318834 | BP45: =BP30/BP29 -> 0.49366292 | BQ45: 0.48 | BR45: 0.485 | BS45: 0.49 | BT45: 0.495 | BU45: 0.5 | BV45: 0.51 | BW45: 0.52 | BX45: 0.53 | BY45: 0.54 | BZ45: 0.55
B46: Transaction & Credit Losses % of Revenue | W46: =W31/W29 -> 0.12797748 | X46: =X31/X29 -> 0.08363429 | Y46: =Y31/Y29 -> 0.063015204 | Z46: =Z31/Z29 -> 0.059843035 | AA46: =AA31/AA29 -> 0.045251119 | AB46: =AB31/AB29 -> 0.027092017 | AC46: =AC31/AC29 -> 0.043351666 | AD46: =AD31/AD29 -> 0.050592657 | ... AS46: =AS31/AS29 -> 0.057383866 | BL46: =BL31/BL29 -> 0.081150368 | BM46: =BM31/BM29 -> 0.041779985 | BN46: =BN31/BN29 -> 0.057126245 | BO46: =BO31/BO29 -> 0.056497934 | BP46: =BP31/BP29 -> 0.04535019 | BQ46: 0.053 | BR46: 0.055 | BS46: 0.06 | BT46: 0.05 | BU46: 0.04535019 | BV46: 0.0425 | BW46: 0.042 | BX46: 0.041 | BY46: 0.04 | BZ46: 0.04
B47: Customer Support & Op. Expenses % of Revenue | W47: =W32/W29 -> 0.086401039 | X47: =X32/X29 -> 0.080402965 | Y47: =Y32/Y29 -> 0.082249496 | Z47: =Z32/Z29 -> 0.082897319 | AA47: =AA32/AA29 -> 0.085861097 | AB47: =AB32/AB29 -> 0.083520359 | AC47: =AC32/AC29 -> 0.081527014 | AD47: =AD32/AD29 -> 0.076900838 | ... AS47: =AS32/AS29 -> 0.053106808 | BL47: =BL32/BL29 -> 0.082874988 | BM47: =BM32/BM29 -> 0.081786291 | BN47: =BN32/BN29 -> 0.077040483 | BO47: =BO32/BO29 -> 0.064458701 | BP47: =BP32/BP29 -> 0.05560273 | BQ47: 0.052 | BR47: 0.05 | BS47: 0.049 | BT47: 0.048 | BU47: 0.047 | BV47: 0.046 | BW47: 0.045 | BX47: 0.045 | BY47: 0.045 | BZ47: 0.045
B48: R&D as % of Revenue | C48: =C34/C29 -> 0.086569958 | D48: =D34/D29 -> 0.087940792 | E48: =E34/E29 -> 0.08724535 | F48: =F34/F29 -> 0.081377152 | G48: =G34/G29 -> 0.076650943 | H48: =H34/H29 -> 0.078867925 | I48: =I34/I29 -> 0.080614923 | J48: =J34/J29 -> 0.072123449 | ... AS48: =AS34/AS29 -> 0.095164548 | BL48: =BL34/BL29 -> 0.1231472 | BM48: =BM34/BM29 -> 0.11974301 | BN48: =BN34/BN29 -> 0.11821353 | BO48: =BO34/BO29 -> 0.099862282 | BP48: =BP34/BP29 -> 0.093688084 | BQ48: 0.094 | BR48: 0.095 | BS48: 0.098 | BT48: 0.102 | BU48: 0.105 | BV48: 0.105 | BW48: 0.105 | BX48: 0.105 | BY48: 0.105 | BZ48: 0.105
B49: SG&A as % of Revenue | C49: =(C35+C33)/C29 -> 0.76275152 | D49: =(D35+D33)/D29 -> 0.73878973 | E49: =(E35+E33)/E29 -> 0.76660762 | F49: =(F35+F33)/F29 -> 0.75782473 | G49: =(G35+G33)/G29 -> 0.76336478 | H49: =(H35+H33)/H29 -> 0.78113208 | I49: =(I35+I33)/I29 -> 0.78890139 | J49: =(J35+J33)/J29 -> 0.77356592 | ... AS49: =(AS35+AS33)/AS29 -> 0.12284662 | BL49: =(BL35+BL33)/BL29 -> 0.18322923 | BM49: =(BM35+BM33)/BM29 -> 0.17969335 | BN49: =(BN35+BN33)/BN29 -> 0.15829639 | BO49: =(BO35+BO33)/BO29 -> 0.12992509 | BP49: =(BP35+BP33)/BP29 -> 0.13045256 | BQ49: 0.124 | BR49: 0.125 | BS49: 0.12 | BT49: 0.118 | BU49: 0.115 | BV49: 0.115 | BW49: 0.1125 | BX49: 0.11 | BY49: 0.1 | BZ49: 0.1
B50: Operating Profit Margin | C50: =C37/C29 -> 0.15067852 | D50: =D37/D29 -> 0.17326948 | E50: =E37/E29 -> 0.14614703 | F50: =F37/F29 -> 0.16079812 | G50: =G37/G29 -> 0.15998428 | H50: =H37/H29 -> 0.14 | I50: =I37/I29 -> 0.13048369 | J50: =J37/J29 -> 0.15431063 | ... AS50: =AS37/AS29 -> 0.18058691 | BL50: =BL37/BL29 -> 0.15330475 | BM50: =BM37/BM29 -> 0.16798707 | BN50: =BN37/BN29 -> 0.13943601 | BO50: =BO37/BO29 -> 0.16888919 | BP50: =BP37/BP29 -> 0.16746863 | BQ50: 0.165 | BR50: =BR37/BR29 -> 0.145 | BS50: =BS37/BS29 -> 0.134 | BT50: =BT37/BT29 -> 0.133 | BU50: =BU37/BU29 -> 0.12964981 | BV50: =BV37/BV29 -> 0.1225 | BW50: =BW37/BW29 -> 0.1155 | BX50: =BX37/BX29 -> 0.109 | BY50: =BY37/BY29 -> 0.11 | BZ50: =BZ37/BZ29 -> 0.1
B51: Effective Tax Rate | C51: =C40/C39 -> 0.20560748 | D51: =D40/D39 -> 0.23558897 | E51: =E40/E39 -> 0.14 | F51: =F40/F39 -> 0.12200957 | G51: =G40/G39 -> 0.13507109 | H51: =H40/H39 -> 0.15 | I51: =I40/I39 -> 0.10277778 | J51: =J40/J39 -> 0.1684435 | ... AS51: =AS40/AS39 -> 0.18590998 | BL51: =BL40/BL39 -> 0.170385 | BM51: =BM40/BM39 -> -0.017077336 | BN51: =BN40/BN39 -> 0.28134284 | BO51: =BO40/BO39 -> 0.21530216 | BP51: =BP40/BP39 -> 0.22180522 | BQ51: 0.187 | BR51: 0.185 | BS51: 0.18 | BT51: 0.18 | BU51: 0.18 | BV51: 0.18 | BW51: 0.18 | BX51: 0.18 | BY51: 0.18 | BZ51: 0.18
B52: Net Profit Margin | C52: =C41/C29 -> 0.11932616 | D52: =D41/D29 -> 0.13278189 | E52: =E41/E29 -> 0.13330381 | F52: =F41/F29 -> 0.14358372 | G52: =G41/G29 -> 0.14347484 | H52: =H41/H29 -> 0.12188679 | I52: =I41/I29 -> 0.12110986 | J52: =J41/J29 -> 0.13082858 | ... AS52: =AS41/AS29 -> 0.14827136 | BL52: =BL41/BL29 -> 0.19586091 | BM52: =BM41/BM29 -> 0.16432147 | BN52: =BN41/BN29 -> 0.087906098 | BO52: =BO41/BO29 -> 0.14262201 | BP52: =BP41/BP29 -> 0.13042111 | BQ52: =BQ41/BQ29 -> 0.13543138 | BR52: =BR41/BR29 -> 0.1332573 | BS52: =BS41/BS29 -> 0.13023274 | ... BZ52: =BZ41/BZ29 -> 0.13246574
B54: Cash & CEs | AD54: 4794 | AE54: 5717 | AF54: 5745 | AG54: 7782 | AH54: 7776 | AI54: 7101 | AJ54: 5504 | AK54: 6816 | AL54: 9081 | AM54: 9693 | AN54: 7701 | AO54: 7272 | AP54: 6561 | AQ54: 7449 | AR54: 6688 | AS54: 8995 | BM54: 4794 | BN54: 7776 | BO54: 9081 | BP54: 6561 | BQ54: =BP54+BQ41 -> 11087.348 | BR54: =BQ54+BR41 -> 15797.78 | BS54: =BR54+BS41 -> 20688.347 | BT54: =BS54+BT41 -> 26037.343 | BU54: =BT54+BU41 -> 31789.748 | BV54: =BU54+BV41 -> 37822.264 | BW54: =BV54+BW41 -> 44131.72 | BX54: =BW54+BX41 -> 50733.604 | ... BZ54: =BY54+BZ41 -> 65302.672
B55: ST Investments | AD55: 8289 | AE55: 7369 | AF55: 6650 | AG55: 5510 | AH55: 3092 | AI55: 3559 | AJ55: 4398 | AK55: 4731 | AL55: 4979 | AM55: 4625 | AN55: 5915 | AO55: 4647 | AP55: 4262 | AQ55: 3762 | AR55: 3320 | AS55: 1760 | BM55: 8289 | BN55: 3092 | BO55: 4979 | BP55: 4262
B56: AR, net | AD56: 577 | AE56: 674 | AF56: 693 | AG56: 736 | AH56: 963 | AI56: 967 | AJ56: 928 | AK56: 988 | AL56: 1069 | AM56: 1108 | AN56: 987 | AO56: 1038 | AP56: 984 | AQ56: 1082 | AR56: 1099 | AS56: 973 | BM56: 577 | BN56: 963 | BO56: 1069 | BP56: 984 | BR56: Projected ROIC: | BU56: Invested Capital | BW56: AVG Invested Capital | BY56: ROIC | BZ56: 0.059
B57: Loans & Interest Receivable | AD57: 0 | AE57: 0 | AF57: 0 | AG57: 0 | AH57: 0 | AI57: 0 | AJ57: 1903 | AK57: 2165 | AL57: 563 | AM57: 307 | AN57: 369 | AO57: 471 | AP57: 541 | AQ57: 714 | AR57: 817 | AS57: 1404 | BM57: 0 | BN57: 0 | BO57: 563 | BP57: 541 | BR57: 2025 | BT57: 2023 | BU57: 2024 | BW57: 2023-2024 | BY57: Terminal | BZ57: 0.0125
B58: Loans & Interest Receivable, net | AD58: 2769 | AE58: 2731 | AF58: 3283 | AG58: 3713 | AH58: 7431 | AI58: 7495 | AJ58: 5547 | AK58: 5066 | AL58: 5433 | AM58: 5202 | AN58: 5319 | AO58: 6003 | AP58: 6422 | AQ58: 6511 | AR58: 6938 | AS58: 6396 | BM58: 2769 | BN58: 7431 | BO58: 5433 | BP58: 6422 | BR58: =AVERAGE(BQ37)*(1-BQ51) -> 4211.6368 | BT58: =SUM(BO54:BO59)-BO68+BO62+BO64+BO63 -> 72972 | BU58: =SUM(BP54:BP59)-BP68+BP62+BP64+BP63 -> 68885 | BW58: =AVERAGE(BT58:BU58) -> 70928.5 | BY58: RFR (10-year yield) | BZ58: 0.03985
B59: Funds Receivable & Customer Accounts | AD59: 33418 | AE59: 35623 | AF59: 35670 | AG59: 35104 | AH59: 36264 | AI59: 35276 | AJ59: 33643 | AK59: 34641 | AL59: 38935 | AM59: 38353 | AN59: 38727 | AO59: 39182 | AP59: 37671 | AQ59: 39205 | AR59: 38923 | AS59: 38668 | BM59: 33418 | BN59: 36264 | BO59: 38935 | BP59: 37671 | BR59: =BR58/BW58 -> 0.059378625 | BY59: ERP (Avg. market return - (less) RFR) | BZ59: =13.1%-BZ58 -> 0.09115
B60: Prepaid Expenses & Other Current | AD60: 1148 | AE60: 1318 | AF60: 1190 | AG60: 1285 | AH60: 1898 | AI60: 2162 | AJ60: 2202 | AK60: 2228 | AL60: 2509 | AM60: 4418 | AN60: 3954 | AO60: 4060 | AP60: 4651 | AQ60: 1888 | AR60: 2094 | AS60: 1980 | BM60: 1148 | BN60: 1898 | BO60: 2509 | BP60: 4651 | BY60: Equity β (1-year avg.) | BZ60: 0.49
B61: LT Investments | AD61: 6089 | AE61: 5994 | AF61: 6968 | AG61: 6753 | AH61: 5018 | AI61: 4632 | AJ61: 4543 | AK61: 3855 | AL61: 3273 | AM61: 3409 | AN61: 4653 | AO61: 4282 | AP61: 4583 | AQ61: 4613 | AR61: 3645 | AS61: 3601 | BM61: 6089 | BN61: 5018 | BO61: 3273 | BP61: 4583 | BY61: Discount (Cost of Equity) | BZ61: =+BZ58+(BZ59*BZ60) -> 0.0845135
B62: PP&E | AD62: 1807 | AE62: 1806 | AF62: 1848 | AG62: 1900 | AH62: 1730 | AI62: 1633 | AJ62: 1589 | AK62: 1529 | AL62: 1488 | AM62: 1426 | AN62: 1459 | AO62: 1496 | AP62: 1508 | AQ62: 1537 | AR62: 1625 | AS62: 1656 | BM62: 1807 | BN62: 1730 | BO62: 1488 | BP62: 1508
B63: Goodwill | AD63: 9135 | AE63: 9117 | AF63: 9564 | AG63: 9550 | AH63: 11209 | AI63: 11195 | AJ63: 11067 | AK63: 10935 | AL63: 11026 | AM63: 10916 | AN63: 10816 | AO63: 10996 | AP63: 10837 | AQ63: 10910 | AR63: 10976 | AS63: 10941 | BM63: 9135 | BN63: 11209 | BO63: 11026 | BP63: 10837 | BY63: NPV | BZ63: =NPV(BZ61,BQ41:DX41) -> 81672.8
B64: Intangibles | AD64: 1048 | AE64: 938 | AF64: 920 | AG64: 808 | AH64: 788 | AI64: 730 | AJ64: 640 | AK64: 564 | AL64: 537 | AM64: 465 | AN64: 403 | AO64: 393 | AP64: 326 | AQ64: 296 | AR64: 271 | AS64: 226 | BM64: 1048 | BN64: 788 | BO64: 537 | BP64: 326 | BY64: SC | BZ64: =Main!C6 -> 935.65 | CA64: Q2'25
B65: Other Assets | AD65: 1305 | AE65: 1230 | AF65: 1285 | AG65: 1393 | AH65: 2455 | AI65: 2436 | AJ65: 2615 | AK65: 2922 | AL65: 3273 | AM65: 3425 | AN65: 3713 | AO65: 3671 | AP65: 3265 | AQ65: 3307 | AR65: 3381 | AS65: 3201 | BM65: 1305 | BN65: 2455 | BO65: 3273 | BP65: 3265 | BY65: FV | BZ65: =BZ63/BZ64 -> 87.289905
B66: Total Assets | AD66: =SUM(AD54:AD65) -> 70379 | AE66: =SUM(AE54:AE65) -> 72517 | AF66: =SUM(AF54:AF65) -> 73816 | AG66: =SUM(AG54:AG65) -> 74534 | AH66: =SUM(AH54:AH65) -> 78624 | AI66: =SUM(AI54:AI65) -> 77186 | AJ66: =SUM(AJ54:AJ65) -> 74579 | AK66: =SUM(AK54:AK65) -> 76440 | ... AS66: =SUM(AS54:AS65) -> 79801 | BM66: =SUM(BM54:BM65) -> 70379 | BN66: =SUM(BN54:BN65) -> 78624 | BO66: =SUM(BO54:BO65) -> 82166 | BP66: =SUM(BP54:BP65) -> 81611 | BY66: CP | BZ66: =Main!C5 -> 57.8
BY67: Change Δ | BZ67: =BZ65/BZ66-1 -> 0.51020597 | CA67: =IF(BZ67>0,"Upside","Downside") -> Upside
B68: AP | AD68: 252 | AE68: 191 | AF68: 260 | AG68: 186 | AH68: 126 | AI68: 142 | AJ68: 137 | AK68: 131 | AL68: 139 | AM68: 108 | AN68: 133 | AO68: 165 | AP68: 227 | AQ68: 175 | AR68: 221 | AS68: 208 | BM68: 252 | BN68: 126 | BO68: 139 | BP68: 227 | BY68: {=_xlfn.IFS(BZ67>=25%,"Strong Buy",BZ67>=10.00001%,"Buy",AND(BZ67<=10%,BZ67>=-4.9999%),"Hold",AND(BZ67<=-5%,BZ67>=-14.999999%),"Sell",BZ67<=-15%,"Strong Sell")} -> Strong Buy
B69: Funds Payable & Amts Due to Customers | AD69: 35418 | AE69: 38323 | AF69: 38370 | AG69: 37804 | AH69: 40014 | AI69: 39026 | AJ69: 37393 | AK69: 38641 | AL69: 41935 | AM69: 41353 | AN69: 41727 | AO69: 41182 | AP69: 39671 | AQ69: 41205 | AR69: 40923 | AS69: 40668 | BM69: 35418 | BN69: 40014 | BO69: 41935 | BP69: 39671
B70: Accrued Expenses & Other Current Liab. | AD70: =2648+129 -> 2777 | AE70: =2731+95 -> 2826 | AF70: =2489+149 -> 2638 | AG70: =3554+151 -> 3705 | AH70: =4055+813 -> 4868 | AI70: =4164+577 -> 4741 | AJ70: =3433+791 -> 4224 | AK70: =3533+1137 -> 4670 | AL70: 6392 | AM70: 8385 | AN70: 8853 | AO70: 8921 | AP70: 8478 | AQ70: 5242 | AR70: 3906 | AS70: 4048 | BM70: =2648+129 -> 2777 | BN70: =4055+813 -> 4868 | BO70: 6392 | BP70: 8478
B71: Other LT Liabilities | AD71: 2930 | AE71: 2794 | AF71: 2698 | AG71: 2800 | AH71: 2925 | AI71: 2938 | AJ71: 2615 | AK71: 2618 | AL71: 2973 | AM71: 3116 | AN71: 2954 | AO71: 3093 | AP71: 2939 | AQ71: 2981 | AR71: 3230 | AS71: 3403 | BM71: 2930 | BN71: 2925 | BO71: 2973 | BP71: 2939
B72: LT Debt | AD72: 8939 | AE72: 8942 | AF72: 8945 | AG72: 7949 | AH72: 10417 | AI72: 10481 | AJ72: 10549 | AK72: 10640 | AL72: 9676 | AM72: 9683 | AN72: 9727 | AO72: 9976 | AP72: 9879 | AQ72: 11417 | AR72: 11296 | AS72: 11276 | BM72: 8939 | BN72: 10417 | BO72: 9676 | BP72: 9879
B73: Total Liabilities | AD73: =SUM(AD68:AD72) -> 50316 | AE73: =SUM(AE68:AE72) -> 53076 | AF73: =SUM(AF68:AF72) -> 52911 | AG73: =SUM(AG68:AG72) -> 52444 | AH73: =SUM(AH68:AH72) -> 58350 | AI73: =SUM(AI68:AI72) -> 57328 | AJ73: =SUM(AJ68:AJ72) -> 54918 | AK73: =SUM(AK68:AK72) -> 56700 | ... AS73: =SUM(AS68:AS72) -> 59603 | BM73: =SUM(BM68:BM72) -> 50316 | BN73: =SUM(BN68:BN72) -> 58350 | BO73: =SUM(BO68:BO72) -> 61115 | BP73: =SUM(BP68:BP72) -> 61194
B74: SE | AD74: 20063 | AE74: 19441 | AF74: 20905 | AG74: 22090 | AH74: 20274 | AI74: 19858 | AJ74: 19661 | AK74: 19740 | AL74: 21051 | AM74: 20702 | AN74: 20622 | AO74: 20174 | AP74: 20417 | AQ74: 20254 | AR74: 20201 | AS74: 20198 | BM74: 20063 | BN74: 20274 | BO74: 21051 | BP74: 20417
B75: Ttl L + SE | AD75: =AD74+AD73 -> 70379 | AE75: =AE74+AE73 -> 72517 | AF75: =AF74+AF73 -> 73816 | AG75: =AG74+AG73 -> 74534 | AH75: =AH74+AH73 -> 78624 | AI75: =AI74+AI73 -> 77186 | AJ75: =AJ74+AJ73 -> 74579 | AK75: =AK74+AK73 -> 76440 | ... AS75: =AS74+AS73 -> 79801 | BM75: =BM74+BM73 -> 70379 | BN75: =BN74+BN73 -> 78624 | BO75: =BO74+BO73 -> 82166 | BP75: =BP74+BP73 -> 81611
B77: Current Ratio | AD77: =SUM(AD54:AD60)/SUM(AD68:AD70) -> 1.3263714 | AE77: =SUM(AE54:AE60)/SUM(AE68:AE70) -> 1.2925012 | AF77: =SUM(AF54:AF60)/SUM(AF68:AF70) -> 1.2898856 | AG77: =SUM(AG54:AG60)/SUM(AG68:AG70) -> 1.2982372 | AH77: =SUM(AH54:AH60)/SUM(AH68:AH70) -> 1.2758621 | AI77: =SUM(AI54:AI60)/SUM(AI68:AI70) -> 1.2881186 | AJ77: =SUM(AJ54:AJ60)/SUM(AJ68:AJ70) -> 1.296283 | AK77: =SUM(AK54:AK60)/SUM(AK68:AK70) -> 1.3036923 | ... AS77: =SUM(AS54:AS60)/SUM(AS68:AS70) -> 1.3395067 | BM77: =SUM(BM54:BM60)/SUM(BM68:BM70) -> 1.3263714 | BN77: =SUM(BN54:BN60)/SUM(BN68:BN70) -> 1.2758621 | BO77: =SUM(BO54:BO60)/SUM(BO68:BO70) -> 1.2909875 | BP77: =SUM(BP54:BP60)/SUM(BP68:BP70) -> 1.2628576
B78: Quick Ratio | AD78: =SUM(AD54:AD60)/SUM(AD68:AD70) -> 1.3263714 | AE78: =SUM(AE54:AE60)/SUM(AE68:AE70) -> 1.2925012 | AF78: =SUM(AF54:AF60)/SUM(AF68:AF70) -> 1.2898856 | AG78: =SUM(AG54:AG60)/SUM(AG68:AG70) -> 1.2982372 | AH78: =SUM(AH54:AH60)/SUM(AH68:AH70) -> 1.2758621 | AI78: =SUM(AI54:AI60)/SUM(AI68:AI70) -> 1.2881186 | AJ78: =SUM(AJ54:AJ60)/SUM(AJ68:AJ70) -> 1.296283 | AK78: =SUM(AK54:AK60)/SUM(AK68:AK70) -> 1.3036923 | ... AS78: =SUM(AS54:AS60)/SUM(AS68:AS70) -> 1.3395067 | BM78: =SUM(BM54:BM60)/SUM(BM68:BM70) -> 1.3263714 | BN78: =SUM(BN54:BN60)/SUM(BN68:BN70) -> 1.2758621 | BO78: =SUM(BO54:BO60)/SUM(BO68:BO70) -> 1.2909875 | BP78: =SUM(BP54:BP60)/SUM(BP68:BP70) -> 1.2628576
B79: Cash Ratio | AD79: =(SUM(AD54:AD55)+SUM(AD59))/(SUM(AD68:AD70)) -> 1.2094832 | AE79: =(SUM(AE54:AE55)+SUM(AE59))/(SUM(AE68:AE70)) -> 1.1782535 | AF79: =(SUM(AF54:AF55)+SUM(AF59))/(SUM(AF68:AF70)) -> 1.1647039 | AG79: =(SUM(AG54:AG55)+SUM(AG59))/(SUM(AG68:AG70)) -> 1.1607147 | AH79: =(SUM(AH54:AH55)+SUM(AH59))/(SUM(AH68:AH70)) -> 1.0471916 | AI79: =(SUM(AI54:AI55)+SUM(AI59))/(SUM(AI68:AI70)) -> 1.0461637 | AJ79: =(SUM(AJ54:AJ55)+SUM(AJ59))/(SUM(AJ68:AJ70)) -> 1.0428941 | AK79: =(SUM(AK54:AK55)+SUM(AK59))/(SUM(AK68:AK70)) -> 1.0632107 | ... AS79: =(SUM(AS54:AS55)+SUM(AS59))/(SUM(AS68:AS70)) -> 1.1001469 | BM79: =(SUM(BM54:BM55)+SUM(BM59))/(SUM(BM68:BM70)) -> 1.2094832 | BN79: =(SUM(BN54:BN55)+SUM(BN59))/(SUM(BN68:BN70)) -> 1.0471916 | BO79: =(SUM(BO54:BO55)+SUM(BO59))/(SUM(BO68:BO70)) -> 1.093447 | BP79: =(SUM(BP54:BP55)+SUM(BP59))/(SUM(BP68:BP70)) -> 1.0024392
B80: Ttl Asset Turnover | AD80: =AD6/AD66 -> 0.098296367 | AE80: =AE6/AE66 -> 0.089399727 | AF80: =AF6/AF66 -> 0.092202233 | AG80: =AG6/AG66 -> 0.091850699 | AH80: =AH6/AH66 -> 0.093902625 | AI80: =AI6/AI66 -> 0.09120825 | AJ80: =AJ6/AJ66 -> 0.09770847 | AK80: =AK6/AK66 -> 0.097043433 | ... AS80: =AS6/AS66 -> 0.10547487 | BM80: =BM6/BM66 -> 0.36049106 | BN80: =BN6/BN66 -> 0.34999491 | BO80: =BO6/BO66 -> 0.36232748 | BP80: =BP6/BP66 -> 0.3896166
B81: Return on Assets | AD81: =AD41/AD75 -> 0.011381236 | AE81: =AE41/AE75 -> 0.0070190438 | AF81: =AF41/AF75 -> -0.0046195947 | AG81: =AG41/AG75 -> 0.017844205 | AH81: =AH41/AH75 -> 0.01171398 | AI81: =AI41/AI75 -> 0.010299795 | AJ81: =AJ41/AJ75 -> 0.01379745 | AK81: =AK41/AK75 -> 0.013343799 | ... AS81: =AS41/AS75 -> 0.015638902 | BM81: =BM41/BM75 -> 0.05923642 | BN81: =BN41/BN75 -> 0.030766687 | BO81: =BO41/BO75 -> 0.051675876 | BP81: =BP41/BP75 -> 0.050814228
B82: Return on Equity | AD82: =AD41/AD74 -> 0.039924239 | AE82: =AE41/AE74 -> 0.026181781 | AF82: =AF41/AF74 -> -0.016311887 | AG82: =AG41/AG74 -> 0.060208239 | AH82: =AH41/AH74 -> 0.045427641 | AI82: =AI41/AI74 -> 0.040034243 | AJ82: =AJ41/AJ74 -> 0.052337114 | AK82: =AK41/AK74 -> 0.051671733 | ... AS82: =AS41/AS74 -> 0.061788296 | BM82: =BM41/BM74 -> 0.20779544 | BN82: =BN41/BN74 -> 0.11931538 | BO82: =BO41/BO74 -> 0.20170063 | BP82: =BP41/BP74 -> 0.20311505
B84: Net Income | W84: =W41 -> 84 | X84: =X41 -> 1530 | Y84: =Y41 -> 1021 | Z84: =Z41 -> 1567 | AA84: =AA41 -> 1097 | AB84: =AB41 -> 1184 | AC84: =AC41 -> 1087 | AD84: =AD41 -> 801 | ... AS84: =AS41 -> 1248 | BL84: =SUM(Model!C80:F80) -> 0 | BM84: =SUM(Model!G80:J80) -> 0 | BN84: =SUM(Model!K80:N80) -> 0 | BO84: =SUM(Model!O80:R80) -> 0 | BP84: =SUM(Model!S80:V80) -> 0
B85: Transaction & Credit Losses | W85: 591 | X85: =1031-W85 -> 440 | Y85: =1184-SUM(W85:X85) -> 153 | Z85: =1741-SUM(W85:Y85) -> 557 | AA85: 273 | AB85: =442-AA85 -> 169 | AC85: =710-SUM(AA85:AB85) -> 268 | AD85: =1572-SUM(AA85:AC85) -> 862 | AE85: 369 | AF85: =817-AE85 -> 448 | AG85: =1184-SUM(AE85:AF85) -> 367 | AH85: =1572-SUM(AE85:AG85) -> 388 | AI85: 442 | AJ85: =840-AI85 -> 398 | AK85: =1286-SUM(AI85:AJ85) -> 446 | AL85: =1682-SUM(AI85:AK85) -> 396 | AM85: 321 | AN85: =656-AM85 -> 335 | AO85: =1008-SUM(AM85:AN85) -> 352 | AP85: =1442-SUM(AM85:AO85) -> 434 | AQ85: 371 | AR85: 371 | AS85: 371 | BL85: =SUM(Model!C81:F81) -> 0 | BM85: =SUM(Model!G81:J81) -> 0 | BN85: =SUM(Model!K81:N81) -> 0 | BO85: =SUM(Model!O81:R81) -> 0 | BP85: =SUM(Model!S81:V81) -> 0
B86: Dep. and Am. | W86: 293 | X86: =590-W86 -> 297 | Y86: =1184-SUM(W86:X86) -> 594 | Z86: =1189-SUM(W86:Y86) -> 5 | AA86: 300 | AB86: =616-AA86 -> 316 | AC86: =939-SUM(AA86:AB86) -> 323 | AD86: =1317-SUM(AA86:AC86) -> 378 | AE86: 328 | AF86: =661-AE86 -> 333 | AG86: =991-SUM(AE86:AF86) -> 330 | AH86: =1317-SUM(AE86:AG86) -> 326 | AI86: 270 | AJ86: =539-AI86 -> 269 | AK86: =809-SUM(AI86:AJ86) -> 270 | AL86: =1072-SUM(AI86:AK86) -> 263 | AM86: 265 | AN86: =528-AM86 -> 263 | AO86: =783-SUM(AM86:AN86) -> 255 | AP86: =1032-SUM(AM86:AO86) -> 249 | AQ86: 245 | AR86: 245 | AS86: 245 | BL86: =SUM(Model!C82:F82) -> 0 | BM86: =SUM(Model!G82:J82) -> 0 | BN86: =SUM(Model!K82:N82) -> 0 | BO86: =SUM(Model!O82:R82) -> 0 | BP86: =SUM(Model!S82:V82) -> 0
A87: Adding SBC Back in | B87: SBC | W87: 283 | X87: =635-W87 -> 352 | Y87: =1184-SUM(W87:X87) -> 549 | Z87: =1376-SUM(W87:Y87) -> 192 | AA87: 368 | AB87: =758-AA87 -> 390 | AC87: =1058-SUM(AA87:AB87) -> 300 | AD87: =1261-SUM(AA87:AC87) -> 203 | AE87: 429 | AF87: =741-AE87 -> 312 | AG87: =967-SUM(AE87:AF87) -> 226 | AH87: =1261-SUM(AE87:AG87) -> 294 | AI87: 345 | AJ87: =708-AI87 -> 363 | AK87: =1087-SUM(AI87:AJ87) -> 379 | AL87: =1475-SUM(AI87:AK87) -> 388 | AM87: 365 | AN87: =663-AM87 -> 298 | AO87: =947-SUM(AM87:AN87) -> 284 | AP87: =1230-SUM(AM87:AO87) -> 283 | AQ87: 249 | AR87: 249 | AS87: 249 | BL87: =SUM(Model!C83:F83) -> 0 | BM87: =SUM(Model!G83:J83) -> 0 | BN87: =SUM(Model!K83:N83) -> 0 | BO87: =SUM(Model!O83:R83) -> 0 | BP87: =SUM(Model!S83:V83) -> 0
B88: Deffered Income Taxes | W88: -79 | X88: =31-W88 -> 110 | Y88: =1184-SUM(W88:X88) -> 1153 | Z88: =165-SUM(W88:Y88) -> -1019 | AA88: 0 | AB88: =--103-AA88 -> 103 | AC88: =-175-SUM(AA88:AB88) -> -278 | AD88: =-811-SUM(AA88:AC88) -> -636 | AE88: -16 | AF88: =-457-AE88 -> -441 | AG88: =-538-SUM(AE88:AF88) -> -81 | AH88: =-811-SUM(AE88:AG88) -> -273 | AI88: -67 | AJ88: =-146-AI88 -> -79 | AK88: =-439-SUM(AI88:AJ88) -> -293 | AL88: =-668-SUM(AI88:AK88) -> -229 | AM88: 52 | AN88: =29-AM88 -> -23 | AO88: =8-SUM(AM88:AN88) -> -21 | AP88: =231-SUM(AM88:AO88) -> 223 | AQ88: -6 | AR88: -6 | AS88: -6 | BL88: =SUM(Model!C84:F84) -> 0 | BM88: =SUM(Model!G84:J84) -> 0 | BN88: =SUM(Model!K84:N84) -> 0 | BO88: =SUM(Model!O84:R84) -> 0 | BP88: =SUM(Model!S84:V84) -> 0
B89: Net (Gain) Loss on Strategic Investments | W89: 124 | X89: =-764-W89 -> -888 | Y89: =-973-SUM(W89:X89) -> -209 | Z89: =-1914-SUM(W89:Y89) -> -941 | AA89: 120 | AB89: =-163-AA89 -> -283 | AC89: =-336-SUM(AA89:AB89) -> -173 | AD89: =304-SUM(AA89:AC89) -> 640 | AE89: -14 | AF89: =658-AE89 -> 672 | AG89: =163-SUM(AE89:AF89) -> -495 | AH89: =304-SUM(AE89:AG89) -> 141 | AI89: -48 | AJ89: =-181-AI89 -> -133 | AK89: =-205-SUM(AI89:AJ89) -> -24 | AL89: =-201-SUM(AI89:AK89) -> 4 | AM89: 49 | AN89: =55-AM89 -> 6 | AO89: =226-SUM(AM89:AN89) -> 171 | AP89: =285-SUM(AM89:AO89) -> 59 | AQ89: -48 | AR89: -48 | AS89: -48 | BL89: =SUM(Model!C85:F85) -> 0 | BM89: =SUM(Model!G85:J85) -> 0 | BN89: =SUM(Model!K85:N85) -> 0 | BO89: =SUM(Model!O85:R85) -> 0 | BP89: =SUM(Model!S85:V85) -> 0
B90: Gain on Divestiture | W90: 0 | X90: 0 | Y90: 0 | Z90: 0 | AA90: 0 | AB90: 0 | AC90: 0 | AD90: 0 | AE90: 0 | AF90: 0 | AG90: 0 | AH90: 0 | AI90: 0 | AJ90: 0 | AK90: 0 | AL90: -356 | AM90: 0 | AN90: 0 | AO90: 0 | AP90: 0 | AQ90: 0 | AR90: 0 | AS90: 0 | BL90: =SUM(Model!C86:F86) -> 0 | BM90: =SUM(Model!G86:J86) -> 0 | BN90: =SUM(Model!K86:N86) -> 0 | BO90: =SUM(Model!O86:R86) -> 0 | BP90: =SUM(Model!S86:V86) -> 0
B91: Accretion of Discounts on Investments | W91: 0 | X91: 0 | Y91: 0 | Z91: 0 | AA91: 0 | AB91: 0 | AC91: 0 | AD91: 0 | AE91: 0 | AF91: 0 | AG91: 0 | AH91: =-70-SUM(AE91:AG91) -> -70 | AI91: -69 | AJ91: =-162-AI91 -> -93 | AK91: =-265-SUM(AI91:AJ91) -> -103 | AL91: =-367-SUM(AI91:AK91) -> -102 | AM91: -75 | AN91: =-197-AM91 -> -122 | AO91: =-290-SUM(AM91:AN91) -> -93 | AP91: =-335-SUM(AM91:AO91) -> -45 | AQ91: -30 | AR91: -30 | AS91: -30 | BL91: =SUM(Model!C87:F87) -> 0 | BM91: =SUM(Model!G87:J87) -> 0 | BN91: =SUM(Model!K87:N87) -> 0 | BO91: =SUM(Model!O87:R87) -> 0 | BP91: =SUM(Model!S87:V87) -> 0
B92: Adjustments to Loans & Int. Recieveable | W92: 0 | X92: 0 | Y92: 0 | Z92: 0 | AA92: 0 | AB92: 0 | AC92: 0 | AD92: 0 | AE92: 0 | AF92: 0 | AG92: 0 | AH92: 0 | AI92: 0 | AJ92: =34-AI92 -> 34 | AK92: =49-SUM(AI92:AJ92) -> 15 | AL92: =53-SUM(AI92:AK92) -> 4 | AM92: 37 | AN92: =64-AM92 -> 27 | AO92: =92-SUM(AM92:AN92) -> 28 | AP92: =125-SUM(AM92:AO92) -> 33 | AQ92: 25 | AR92: 25 | AS92: 25 | BL92: =SUM(Model!C88:F88) -> 0 | BM92: =SUM(Model!G88:J88) -> 0 | BN92: =SUM(Model!K88:N88) -> 0 | BO92: =SUM(Model!O88:R88) -> 0 | BP92: =SUM(Model!S88:V88) -> 0
B93: Other | W93: -5 | X93: =-2-W93 -> 3 | Y93: =10-SUM(W93:X93) -> 12 | Z93: =47-SUM(W93:Y93) -> 37 | AA93: 51 | AB93: =-2-AA93 -> -53 | AC93: =92-SUM(AA93:AB93) -> 94 | AD93: =100-SUM(AA93:AC93) -> 8 | AE93: 65 | AF93: =295-AE93 -> 230 | AG93: =514-SUM(AE93:AF93) -> 219 | AH93: =275-SUM(AE93:AG93) -> -239 | AI93: -23 | AJ93: =-114-AI93 -> -91 | AK93: =-2-SUM(AI93:AJ93) -> 112 | AL93: =-104-SUM(AI93:AK93) -> -102 | AM93: 13 | AN93: =-42-AM93 -> -55 | AO93: =-138-SUM(AM93:AN93) -> -96 | AP93: =-3-SUM(AM93:AO93) -> 135 | AQ93: -73 | AR93: -73 | AS93: -73 | BL93: =SUM(Model!C89:F89) -> 0 | BM93: =SUM(Model!G89:J89) -> 0 | BN93: =SUM(Model!K89:N89) -> 0 | BO93: =SUM(Model!O89:R89) -> 0 | BP93: =SUM(Model!S89:V89) -> 0
B94: Originations of Loans Recieveable | W94: 0 | X94: 0 | Y94: 0 | Z94: 0 | AA94: 0 | AB94: 0 | AC94: 0 | AD94: 0 | AE94: 0 | AF94: 0 | AG94: 0 | AH94: 0 | AI94: 0 | AJ94: =-1521-AI94 -> -1521 | AK94: =-5705-SUM(AI94:AJ94) -> -4184 | AL94: =-11470-SUM(AI94:AK94) -> -5765 | AM94: -5345 | AN94: =-11065-AM94 -> -5720 | AO94: =-17173-SUM(AM94:AN94) -> -6108 | AP94: =-24498-SUM(AM94:AO94) -> -7325 | AQ94: -6629 | AR94: -6629 | AS94: -6629 | BL94: =SUM(Model!C90:F90) -> 0 | BM94: =SUM(Model!G90:J90) -> 0 | BN94: =SUM(Model!K90:N90) -> 0 | BO94: =SUM(Model!O90:R90) -> 0 | BP94: =SUM(Model!S90:V90) -> 0
B95: Proceeds from Repayments | W95: 0 | X95: 0 | Y95: 0 | Z95: 0 | AA95: 0 | AB95: 0 | AC95: 0 | AD95: 0 | AE95: 0 | AF95: 0 | AG95: 0 | AH95: 0 | AI95: 0 | AJ95: =302-AI95 -> 302 | AK95: =3676-SUM(AI95:AJ95) -> 3374 | AL95: =10795-SUM(AI95:AK95) -> 7119 | AM95: 5232 | AN95: =11175-AM95 -> 5943 | AO95: =17159-SUM(AM95:AN95) -> 5984 | AP95: =24352-SUM(AM95:AO95) -> 7193 | AQ95: 6445 | AR95: 6445 | AS95: 6445 | BL95: =SUM(Model!C91:F91) -> 0 | BM95: =SUM(Model!G91:J91) -> 0 | BN95: =SUM(Model!K91:N91) -> 0 | BO95: =SUM(Model!O91:R91) -> 0 | BP95: =SUM(Model!S91:V91) -> 0
B96: WC | W96: =77-21+51+21 -> 128 | X96: =47-48+114-55-W96 -> -70 | Y96: =1184-SUM(W96:X96) -> 1126 | Z96: =-100-1120-171-4-230+1038-SUM(W96:Y96) -> -1771 | AA96: =-97-34-33-287 -> -451 | AB96: =47-48+114-55-AA96 -> 509 | AC96: =-155-50+18-892-SUM(AA96:AB96) -> -1137 | AD96: =-222-1178+486-31+73+199-SUM(AA96:AC96) -> 406 | AE96: =-50-29+17-391 -> -453 | AF96: =-67-27+86-408-AE96 -> 37 | AG96: =-89-55+109-522-SUM(AE96:AF96) -> -141 | AH96: =-163-1230+118-35+856-SUM(AE96:AG96) -> 103 | AI96: =-3+3-475 -> -475 | AJ96: =36-12-1177-AI96 -> -678 | AK96: =-35-6-865-SUM(AI96:AJ96) -> 247 | AL96: =-114-1188+203+7-222-SUM(AI96:AK96) -> -408 | AM96: =-39-22+176 -> 115 | AN96: =82-11-511-AM96 -> -555 | AO96: =31+24-647-SUM(AM96:AN96) -> -152 | AP96: =85-1131-8+83+413-SUM(AM96:AO96) -> 34 | AQ96: =-98-52-526 -> -676 | AR96: =-98-52-526 -> -676 | AS96: =-98-52-526 -> -676 | BL96: =SUM(Model!C92:F92) -> 0 | BM96: =SUM(Model!G92:J92) -> 0 | BN96: =SUM(Model!K92:N92) -> 0 | BO96: =SUM(Model!O92:R92) -> 0 | BP96: =SUM(Model!S92:V92) -> 0
B97: CFFO | W97: =W84+SUM(W85:W96) -> 1419 | X97: =X84+SUM(X85:X96) -> 1774 | Y97: =Y84+SUM(Y85:Y96) -> 4399 | Z97: =Z84+SUM(Z85:Z96) -> -1373 | AA97: =AA84+SUM(AA85:AA96) -> 1758 | AB97: =AB84+SUM(AB85:AB96) -> 2335 | AC97: =AC84+SUM(AC85:AC96) -> 484 | AD97: =AD84+SUM(AD85:AD96) -> 2662 | ... AS97: =AS84+SUM(AS85:AS96) -> 1121 | BL97: =SUM(Model!C93:F93) -> 0 | BM97: =SUM(AA97:AD97) -> 7239 | BN97: =SUM(Model!K93:N93) -> 0 | BO97: =SUM(Model!O93:R93) -> 0 | BP97: =SUM(Model!S93:V93) -> 0
B99: Net Income | C99: =C41 -> 255 | D99: =D41 -> 305 | E99: =E41 -> 301 | F99: =F41 -> 367 | G99: =G41 -> 365 | H99: =H41 -> 323 | I99: =I41 -> 323 | J99: =J41 -> 390 | ... BA99: =BA41 -> 1360 | BG99: =SUM(C99:F99) -> 1228 | BH99: =SUM(G99:J99) -> 1401 | BI99: =SUM(K99:N99) -> 1795 | BJ99: =SUM(O99:R99) -> 2057 | BK99: =SUM(S99:V99) -> 2459 | BL99: =SUM(W99:Z99) -> 4202 | BM99: =SUM(AA99:AD99) -> 4169 | BN99: =SUM(AE99:AH99) -> 2419 | BO99: =SUM(AI99:AL99) -> 4246 | BP99: =SUM(AM99:AP99) -> 4147
B100: CFFO | C100: 544 | D100: 622 | E100: 652 | F100: 728 | G100: 738 | H100: 696 | I100: 801 | J100: 923 | K100: 751 | L100: 921 | M100: 1006 | N100: -147 | O100: -349 | P100: 28 | Q100: 4670 | R100: 1131 | S100: 1027 | T100: 1174 | U100: 1096 | V100: 774 | W100: 1421 | X100: 1772 | Y100: 1314 | Z100: 1712 | AA100: =AA97 -> 1758 | AB100: 1306 | AC100: 1513 | AD100: 1220 | AE100: =AE97 -> 1217 | AF100: =AF97 -> 1250 | AG100: =AG97 -> 1755 | AH100: =AH97 -> 1591 | AI100: =AI97 -> 1170 | AJ100: =AJ97 -> -200 | AK100: =AK97 -> 1259 | AL100: =AL97 -> 2614 | ... AQ100: =AQ97 -> 1160 | AR100: =2058-AQ100 -> 898 | AS100: =4032-SUM(AQ100:AR100) -> 1974 | AT100: 2190 | AU100: 1760 | AV100: 1900 | AW100: 1990 | AX100: 1840 | AY100: 1920 | AZ100: 1940 | BA100: 1950 | BG100: =SUM(C100:F100) -> 2546 | BH100: =SUM(G100:J100) -> 3158 | BI100: =SUM(K100:N100) -> 2531 | BJ100: =SUM(O100:R100) -> 5480 | BK100: =SUM(S100:V100) -> 4071 | BL100: =SUM(W100:Z100) -> 6219 | BM100: =SUM(AA100:AD100) -> 5797 | BN100: =SUM(AE100:AH100) -> 5813 | BO100: =SUM(AI100:AL100) -> 4843 | BP100: =SUM(AM100:AP100) -> 7450
B101: CapEx, Net | C101: -194 | D101: -220 | E101: -118 | F101: -164 | G101: -133 | H101: -201 | I101: -183 | J101: -152 | K101: -148 | L101: -174 | M101: -165 | N101: -180 | O101: -178 | P101: -198 | Q101: -223 | R101: -224 | S101: -218 | T101: -139 | U101: -156 | V101: -174 | W101: =-206+119 -> -87 | X101: =-399+120-W101 -> -192 | Y101: =-640+120-SUM(W101:X101) -> -241 | Z101: =-866+120-SUM(W101:Y101) -> -226 | AA101: -221 | AB101: =-468+1-AA101 -> -246 | AC101: =-695+3-SUM(AA101:AB101) -> -225 | AD101: =-908+5-SUM(AA101:AC101) -> -211 | AE101: =-191+3 -> -188 | AF101: =-366+5-AE101 -> -173 | AG101: =-548+5-SUM(AE101:AF101) -> -182 | AH101: =-706+5-SUM(AE101:AG101) -> -158 | AI101: =-170+1 -> -169 | AJ101: =-320+40-AI101 -> -111 | AK101: =-478+44-SUM(AI101:AJ101) -> -154 | AL101: =-623+45-SUM(AI101:AK101) -> -144 | AM101: -154 | AN101: =-311-AM101 -> -157 | AO101: =-480-SUM(AM101:AN101) -> -169 | AP101: =-683+1-SUM(AM101:AO101) -> -202 | AQ101: =-196+2 -> -194 | AR101: =-402-AQ101 -> -208 | AS101: =-658-AR101 -> -450 | AT101: -325 | AU101: -285 | AV101: -295 | AW101: -305 | AX101: -325 | AY101: -335 | AZ101: -340 | BA101: -355 | BG101: =SUM(C101:F101) -> -696 | BH101: =SUM(G101:J101) -> -669 | BI101: =SUM(K101:N101) -> -667 | BJ101: =SUM(O101:R101) -> -823 | BK101: -704 | BL101: =SUM(W101:Z101) -> -746 | BM101: -908 | BN101: -706 | BO101: -623 | BP101: -683
B102: FCF | C102: =C100+C101 -> 350 | D102: =D100+D101 -> 402 | E102: =E100+E101 -> 534 | F102: =F100+F101 -> 564 | G102: =G100+G101 -> 605 | H102: =H100+H101 -> 495 | I102: =I100+I101 -> 618 | J102: =J100+J101 -> 771 | ... BA102: =BA100+BA101 -> 1595 | BG102: =BG100+BG101 -> 1850 | BH102: =BH100+BH101 -> 2489 | BI102: =BI100+BI101 -> 1864 | BJ102: =BJ100+BJ101 -> 4657 | BK102: =BK100+BK101 -> 3367 | BL102: =BL100+BL101 -> 5473 | BM102: =BM100+BM101 -> 4889 | BN102: =BN100+BN101 -> 5107 | ... BP102: =BP100+BP101 -> 6767
B103: Share Count | C103: =C42 -> 1218 | D103: =D42 -> 1218 | E103: =E42 -> 1221 | F103: =F42 -> 1222 | G103: =G42 -> 1216 | H103: =H42 -> 1210 | I103: =I42 -> 1207 | J103: =J42 -> 1210 | ... AS103: =AS42 -> 950 | BG103: =AVERAGE(C103:F103) -> 1219.75 | BH103: =AVERAGE(G103:J103) -> 1210.75 | BI103: =AVERAGE(K103:N103) -> 1202.5 | BJ103: =AVERAGE(O103:R103) -> 1186 | BK103: =AVERAGE(S103:V103) -> 1173.75 | BL103: =AVERAGE(W103:Z103) -> 1183.25 | BM103: =AVERAGE(AA103:AD103) -> 1184.25 | BN103: =AVERAGE(AE103:AH103) -> 1152.25 | BO103: =AVERAGE(AI103:AL103) -> 1104.25 | BP103: =AVERAGE(AM103:AP103) -> 1033
B104: FCF Per Share | C104: =C102/C103 -> 0.28735632 | D104: =D102/D103 -> 0.33004926 | E104: =E102/E103 -> 0.43734644 | F104: =F102/F103 -> 0.46153846 | G104: =G102/G103 -> 0.49753289 | H104: =H102/H103 -> 0.40909091 | I104: =I102/I103 -> 0.51201326 | J104: =J102/J103 -> 0.63719008 | ... AS104: =AS102/AS103 -> 1.6042105 | BG104: =SUM(C104:F104) -> 1.5162905 | BH104: =SUM(G104:J104) -> 2.0558271 | BI104: =SUM(K104:N104) -> 1.5505579 | BJ104: =SUM(O104:R104) -> 3.946168 | BK104: =SUM(S104:V104) -> 2.8827868 | BL104: =BL102/BL103 -> 4.6253962 | BM104: =BM102/BM103 -> 4.1283513 | BN104: =BN102/BN103 -> 4.4321979 | BO104: =BO102/BO103 -> 3.8215984 | BP104: =BP102/BP103 -> 6.5508228

Sheet Notes | Quant Analysis
CA1: 0
H2: Employee Scope: | AD2: General Notes/Observations (Updated Q1'25)
AD4: TPV is the sole most important "macro" figure for PayPal. PayPal's revenues are directly correlated with TPV --> a focus of management should be on network access/boosting conversion rates
AE5: BNPL services allow for a greater sum of users to access "credit" and make transactions they otherwise may have held off on --> increases TPV --> must analyze consumer credit risks to ensure recollection of loaned funds
AE6: User growth has stagnated for the last couple of years; TPV is still growing faster than GDP… check against inflation/money supply growth
AF7: 60% of 2025 Coachella tickets were purchased using BNPL services… LMAOO
AD9: Operating income margin will be important to track very closely for short term modeling
AE10: Operating margin better tracks the true operating performance on a Q/q basis ex 1 time cash inflows from other incomes and divestments
AD12: A brief observation I had while scoping out the balance sheet was in regards to the refinancing of $1.5 billion in bonds terming out in 2025
AE13: The notes terming out were issued before the FED hiking cycle beginning Mar. '22, having effective interest rates below 2%
AE14: The newly issued notes have effective interest rates between 4.5-5%, a 2-3x increase in borrowing costs
AD15: 2025 is expected to see a disproportionately large wave of corporate debt refinancing from the 2020-2021 low rate era. Refinancing will happen at a much higher rate across the board.
AE16: From a macro perspective -> watching credit spreads, default rates and credit revaluations will be important to monitor throughout the year
AE17: Looking at the CME tool, 3 FED cuts are currently priced in for year end overnight lending rates between 3.5-3.75%
AD19: My model is relatively conservative with most future projected figures, except for operating margin (which I believe will see some decent expansion over FY '25 due to Braintree contract renegotiations). I believe PayPal is a decent long around the ($55-65) range and have an initial price target of ~$85… could be an incredible value trap though as there are a few challenges I feel will be difficult for the firm to overcome.
AD20: The Company's valuation multiples is discounted in comparison to peers... the firm has anemic user growth, and is continuing to spend on expensive marketing campaigns, all while competing firms continue to seize market share in virtually every category PayPal operates in
AD21: PayPal operates in many high value markets including:
AE22: Operating a traditional payment network/CC offerings (competing with V, MA, and AXP)
AE23: Digital wallets (competing with AAPL, GOOG, XYZ, Zelle)
AE24: BNPL (competing with AFRM, XYZ and Klarna)
AE25: E-Commerce payment processing (competing with XYY, ADYEY, SHOP)
I32: Notes: | J32: [X]
J33: [Y]
J34: [Z]
AD35: Financial Stmts. Notes/Observations (Updated Q1'25)
H36: Institutional Ownership Snapshot (4/14/2025) | AD36: Revenues:
I64: Notes: | J64: [X]
J65: [Y]
J66: [Z]
H68: Revenue Breakdown by Segment | AD68: Earnings Scope:
I100: Notes: | J100: [X]
J101: [Y]
J102: [Z]
H104: Q/q Total Revenues, Net Income, FCF | AD104: Balance Sheet Scope:
I133: Notes: | J133: [X]
J134: [Y]
J135: [Z]
H137: Y/y Total Revenues, Net Income, FCF | AD137: [Equity Preformance Compared to Peers]
I166: Notes: | J166: [X]
J167: [Y]
J168: [Z]
H170: [PYPL] Historical Return Histogram (Date Built)
I199: Comparing this 3 sigma figure to the recorded Min/Max… we observe a "relatively normal" return distribution
I200: You could hypothetically lever up 20x on a PayPal position and remain in the clear/unliquidated from a 1-day 3 σ move…
J201: Will PayPal's day-to-day EQ returns be more volatile going forward? Hahaha, lever up 20x… FAFO
J203: Min | K203: =MIN(G249:G2006) -> -0.093684651
J204: Max | K204: =MAX(G249:G2006) -> 0.12846303
J205: Mean μ | K205: =AVERAGE(G249:G2006) -> -3.3941718e-05
J206: Median | K206: =MEDIAN(G249:G2006) -> 0.00055201649
J207: SD σ | K207: =_xlfn.STDEV.P(G249:G2006) -> 0.020378289
J208: 3σ 1-Day Δ: ± | K208: =3*K207 -> 0.061134866 | M208: <- Sharpe Ratio (Risk Adjusted Return)
J209: β (1-year avg.) | K209: 1.45 | M209: <- Sortino Ratio (Downside Risk Adjusted Return)
I211: n = | J211: 1758
I212: Histogram Data | L212: Distribution Overlay | P212: SD Lines
I213: Bin | J213: Frequency | L213: (X) 1-Day Δ | M213: (Y) Pop. Density | P213: X | Q213: Y
I214: -0.0625 | J214: 0 | L214: -0.065 | M214: =_xlfn.NORM.DIST(L214,$K$205,$K$207,FALSE) -> 0.12156126 | O214: Mean | P214: =K205 -> -3.3941718e-05 | Q214: 0
I215: -0.06 | J215: 0 | L215: -0.0625 | M215: =_xlfn.NORM.DIST(L215,$K$205,$K$207,FALSE) -> 0.17839428 | P215: =K205 -> -3.3941718e-05 | Q215: 20
I216: -0.0575 | J216: 5 | L216: -0.06 | M216: =_xlfn.NORM.DIST(L216,$K$205,$K$207,FALSE) -> 0.25788757 | O216: -3σ | P216: =($K$207*-3)+$K$205 -> -0.061168807 | Q216: 0
I217: -0.055 | J217: 4 | L217: -0.0575 | M217: =_xlfn.NORM.DIST(L217,$K$205,$K$207,FALSE) -> 0.36723464 | P217: =($K$207*-3)+$K$205 -> -0.061168807 | Q217: 2
I218: -0.0525 | J218: 3 | L218: -0.055 | M218: =_xlfn.NORM.DIST(L218,$K$205,$K$207,FALSE) -> 0.51513447 | O218: -2σ | P218: =($K$207*-2)+$K$205 -> -0.040790519 | Q218: 0
I219: -0.05 | J219: 8 | L219: -0.0525 | M219: =_xlfn.NORM.DIST(L219,$K$205,$K$207,FALSE) -> 0.71180548 | P219: =($K$207*-2)+$K$205 -> -0.040790519 | Q219: 4
I220: -0.0475 | J220: 2 | L220: -0.05 | M220: =_xlfn.NORM.DIST(L220,$K$205,$K$207,FALSE) -> 0.96887063 | O220: -1σ | P220: =($K$207*-1)+$K$205 -> -0.02041223 | Q220: 0
I221: -0.045 | J221: 10 | L221: -0.0475 | M221: =_xlfn.NORM.DIST(L221,$K$205,$K$207,FALSE) -> 1.2990743 | P221: =($K$207*-1)+$K$205 -> -0.02041223 | Q221: 11
I222: -0.0425 | J222: 10 | L222: -0.045 | M222: =_xlfn.NORM.DIST(L222,$K$205,$K$207,FALSE) -> 1.7157972 | O222: 1σ | P222: =($K$207*1)+$K$205 -> 0.020344347 | Q222: 0
I223: -0.04 | J223: 9 | L223: -0.0425 | M223: =_xlfn.NORM.DIST(L223,$K$205,$K$207,FALSE) -> 2.2323468 | P223: =($K$207*1)+$K$205 -> 0.020344347 | Q223: 11
I224: -0.0375 | J224: 12 | L224: -0.04 | M224: =_xlfn.NORM.DIST(L224,$K$205,$K$207,FALSE) -> 2.8610214 | O224: 2σ | P224: =($K$207*2)+$K$205 -> 0.040722635 | Q224: 0
I225: -0.035 | J225: 16 | L225: -0.0375 | M225: =_xlfn.NORM.DIST(L225,$K$205,$K$207,FALSE) -> 3.6119714 | P225: =($K$207*2)+$K$205 -> 0.040722635 | Q225: 4
I226: -0.0325 | J226: 16 | L226: -0.035 | M226: =_xlfn.NORM.DIST(L226,$K$205,$K$207,FALSE) -> 4.491912 | O226: 3σ | P226: =($K$207*3)+$K$205 -> 0.061100924 | Q226: 0
I227: -0.03 | J227: 26 | L227: -0.0325 | M227: =_xlfn.NORM.DIST(L227,$K$205,$K$207,FALSE) -> 5.5027772 | P227: =($K$207*3)+$K$205 -> 0.061100924 | Q227: 2
I228: -0.0275 | J228: 21 | L228: -0.03 | M228: =_xlfn.NORM.DIST(L228,$K$205,$K$207,FALSE) -> 6.6404325
I229: -0.025 | J229: 30 | L229: -0.0275 | M229: =_xlfn.NORM.DIST(L229,$K$205,$K$207,FALSE) -> 7.8935896
I230: -0.0225 | J230: 30 | L230: -0.025 | M230: =_xlfn.NORM.DIST(L230,$K$205,$K$207,FALSE) -> 9.2430748
I231: -0.02 | J231: 57 | L231: -0.0225 | M231: =_xlfn.NORM.DIST(L231,$K$205,$K$207,FALSE) -> 10.661594
I232: -0.0175 | J232: 36 | L232: -0.02 | M232: =_xlfn.NORM.DIST(L232,$K$205,$K$207,FALSE) -> 12.114111
I233: -0.015 | J233: 52 | L233: -0.0175 | M233: =_xlfn.NORM.DIST(L233,$K$205,$K$207,FALSE) -> 13.558908
I234: -0.0125 | J234: 62 | L234: -0.015 | M234: =_xlfn.NORM.DIST(L234,$K$205,$K$207,FALSE) -> 14.949327
I235: -0.01 | J235: 75 | L235: -0.0125 | M235: =_xlfn.NORM.DIST(L235,$K$205,$K$207,FALSE) -> 16.236121
I236: -0.0075 | J236: 73 | L236: -0.01 | M236: =_xlfn.NORM.DIST(L236,$K$205,$K$207,FALSE) -> 17.370275
I237: -0.005 | J237: 101 | L237: -0.0075 | M237: =_xlfn.NORM.DIST(L237,$K$205,$K$207,FALSE) -> 18.306058
I238: -0.0025 | J238: 95 | L238: -0.005 | M238: =_xlfn.NORM.DIST(L238,$K$205,$K$207,FALSE) -> 19.004075
I239: 3.5561831e-17 | J239: 96 | L239: -0.0025 | M239: =_xlfn.NORM.DIST(L239,$K$205,$K$207,FALSE) -> 19.434008
... I246: 0.0175 | J246: 57 | L246: 0.015 | M246: =_xlfn.NORM.DIST(L246,$K$205,$K$207,FALSE) -> 14.912716
A247: 1758 Trading Days (From: 5/26/18-5/26/25) | I247: 0.02 | J247: 55 | L247: 0.0175 | M247: =_xlfn.NORM.DIST(L247,$K$205,$K$207,FALSE) -> 13.520176
A248: Close | B248: High | C248: Low | D248: Open | E248: Volume | F248: UTC Date | G248: Change | I248: 0.0225 | J248: 35 | L248: 0.02 | M248: =_xlfn.NORM.DIST(L248,$K$205,$K$207,FALSE) -> 12.074571
A249: 69.85 | B249: 70.14 | C249: 69.41 | D249: 69.46 | E249: 7683598 | F249: Fri, 23 May 2025 00:00:00 GMT | G249: =A249/D249-1 -> 0.0056147423 | I249: 0.025 | J249: 31 | L249: 0.0225 | M249: =_xlfn.NORM.DIST(L249,$K$205,$K$207,FALSE) -> 10.622453
A250: 71.45 | B250: 71.985 | C250: 71.2801 | D250: 71.475 | E250: 6451026 | F250: Thu, 22 May 2025 00:00:00 GMT | G250: =A250/D250-1 -> -0.00034977265 | I250: 0.0275 | J250: 25 | L250: 0.025 | M250: =_xlfn.NORM.DIST(L250,$K$205,$K$207,FALSE) -> 9.2053786
A251: 71.65 | B251: 73.2042 | C251: 71.505 | D251: 72.2 | E251: 8094345 | F251: Wed, 21 May 2025 00:00:00 GMT | G251: =A251/D251-1 -> -0.0076177285 | I251: 0.03 | J251: 19 | L251: 0.0275 | M251: =_xlfn.NORM.DIST(L251,$K$205,$K$207,FALSE) -> 7.858185
A252: 72.61 | B252: 72.78 | C252: 71.74 | D252: 71.89 | E252: 8403163 | F252: Tue, 20 May 2025 00:00:00 GMT | G252: =A252/D252-1 -> 0.010015301 | I252: 0.0325 | J252: 17 | L252: 0.03 | M252: =_xlfn.NORM.DIST(L252,$K$205,$K$207,FALSE) -> 6.6079476
A253: 72.32 | B253: 72.54 | C253: 71.11 | D253: 71.16 | E253: 7434931 | F253: Mon, 19 May 2025 00:00:00 GMT | G253: =A253/D253-1 -> 0.016301293 | I253: 0.035 | J253: 12 | L253: 0.0325 | M253: =_xlfn.NORM.DIST(L253,$K$205,$K$207,FALSE) -> 5.4736204
A254: 72.18 | B254: 72.22 | C254: 71.08 | D254: 71.47 | E254: 8717851 | F254: Fri, 16 May 2025 00:00:00 GMT | G254: =A254/D254-1 -> 0.0099342381 | I254: 0.0375 | J254: 20 | L254: 0.035 | M254: =_xlfn.NORM.DIST(L254,$K$205,$K$207,FALSE) -> 4.4662857
A255: 71.57 | B255: 72.67 | C255: 71.44 | D255: 72.34 | E255: 8116475 | F255: Thu, 15 May 2025 00:00:00 GMT | G255: =A255/D255-1 -> -0.01064418 | I255: 0.04 | J255: 9 | L255: 0.0375 | M255: =_xlfn.NORM.DIST(L255,$K$205,$K$207,FALSE) -> 3.5898978
A256: 72.68 | B256: 73.34 | C256: 72.2403 | D256: 72.66 | E256: 7724048 | F256: Wed, 14 May 2025 00:00:00 GMT | G256: =A256/D256-1 -> 0.00027525461 | I256: 0.0425 | J256: 9 | L256: 0.04 | M256: =_xlfn.NORM.DIST(L256,$K$205,$K$207,FALSE) -> 2.8423752
A257: 72.29 | B257: 72.65 | C257: 71.89 | D257: 72.41 | E257: 8076183 | F257: Tue, 13 May 2025 00:00:00 GMT | G257: =A257/D257-1 -> -0.0016572297 | I257: 0.045 | J257: 8 | L257: 0.0425 | M257: =_xlfn.NORM.DIST(L257,$K$205,$K$207,FALSE) -> 2.2168917
A258: 72.31 | B258: 74.15 | C258: 71.85 | D258: 72.97 | E258: 12513047 | F258: Mon, 12 May 2025 00:00:00 GMT | G258: =A258/D258-1 -> -0.0090448129 | I258: 0.0475 | J258: 6 | L258: 0.045 | M258: =_xlfn.NORM.DIST(L258,$K$205,$K$207,FALSE) -> 1.7032221
A259: 70.26 | B259: 71.32 | C259: 70.01 | D259: 70.87 | E259: 7470489 | F259: Fri, 09 May 2025 00:00:00 GMT | G259: =A259/D259-1 -> -0.0086073092 | I259: 0.05 | J259: 5 | L259: 0.0475 | M259: =_xlfn.NORM.DIST(L259,$K$205,$K$207,FALSE) -> 1.2890265
A260: 70.48 | B260: 70.946 | C260: 69.3 | D260: 69.3 | E260: 11791492 | F260: Thu, 08 May 2025 00:00:00 GMT | G260: =A260/D260-1 -> 0.017027417 | I260: 0.0525 | J260: 3 | L260: 0.05 | M260: =_xlfn.NORM.DIST(L260,$K$205,$K$207,FALSE) -> 0.96098401
... A264: 67.24 | B264: 67.76 | C264: 65.98 | D264: 66.135 | E264: 10081506 | F264: Fri, 02 May 2025 00:00:00 GMT | G264: =A264/D264-1 -> 0.016708248 | I264: 0.0625 | J264: 1 | L264: 0.06 | M264: =_xlfn.NORM.DIST(L264,$K$205,$K$207,FALSE) -> 0.25537058
A265: 65.41 | B265: 66.12 | C265: 64.85 | D265: 65.62 | E265: 10072972 | F265: Thu, 01 May 2025 00:00:00 GMT | G265: =A265/D265-1 -> -0.0032002438 | I265: More | J265: 10 | L265: 0.0625 | M265: =_xlfn.NORM.DIST(L265,$K$205,$K$207,FALSE) -> 0.17658097
A266: 65.84 | B266: 65.99 | C266: 63.54 | D266: 65.155 | E266: 10293798 | F266: Wed, 30 Apr 2025 00:00:00 GMT | G266: =A266/D266-1 -> 0.010513391 | L266: 0.065 | M266: =_xlfn.NORM.DIST(L266,$K$205,$K$207,FALSE) -> 0.12027647
A267: 66.32 | B267: 67.43 | C267: 64.36 | D267: 66.37 | E267: 19706804 | F267: Tue, 29 Apr 2025 00:00:00 GMT | G267: =A267/D267-1 -> -0.00075335242
...

Sheet Product Lines

Sheet Management

Sheet Table Formatting
B2: [Bold Title] | G2: [Bold Title]
B3: Line Titles | G3: <-- General
B4: Line Titles | G4: <-- Info
B5: Line Titles | G5: <-- General
B6: Line Titles | G6: <-- Info
B7: Line Titles | G7: <-- General
B8: Line Titles | G8: <-- Info
