Workbook

Sheet Main
B2: RTX
B3: Price | C3: 192.23 | D3: 10/21/2026
B4: SO | C4: 1347.758 | D4: Q3'26
B5: MC | C5: =C3*C4 -> 259079.52
B6: Cash | C6: 9173 | D6: Q3'26
B7: Debt | C7: =210+5679+31490 -> 37379 | D7: Q3'26
B8: EV | C8: =C5-C6+C7 -> 287285.52
B10: RTX Corporation (RTX)
B12: Founder(s): Vannevar Bush, Laurence K. Marshall, Charles G. Smith | F12: Registered Exchange: NYSE | N12: Resources:
B13: Founded: 1922 | F13: Address: 1000 Wilson Boulevard, Arlington, VA 22209 U.S. | N13: SEC filings | Q13: https://www.sec.gov/edgar/browse/?CIK=101829&owner=exclude
B14: Headquarters: Arlington, VA | F14: Investor Relations Contact: | N14: Company Homepage | Q14: https://www.rtx.com/
B15: Current CEO: Christopher Calio | F15: Investors Relation Department | O15: Company IR Page | R15: https://investors.rtx.com/#Investors
B16: Employees: 180,000 | F16: Phone: | G16: (781) 522 - 3000 | I16: Email: | N16: Earnings Calls | Q16: https://seekingalpha.com/symbol/RTX/earnings/transcripts
B17: Industry: Aerospace & Defense | N17: Equity Analysis | Q17: https://stockanalysis.com/stocks/rtx/company/
B18: Sector: Industrials | N18: MacroTrends | Q18: https://www.macrotrends.net/stocks/charts/RTX/rtx/income-statement
B19: IPO: September 15, 1952 | N19: ROIC, WACC | Q19: https://www.gurufocus.com/term/wacc/RTX
B20: Fiscal Year: [January - December] | N20: Godel Terminal | Q20: https://app.godelterminal.com/
A22: Company Overview:
B23: RTX Corporation, an aerospace and defense company, provides systems and services for commercial, military, and government customers worldwide
B24: The Company operates through three segments: Collins Aerospace (Collins), Pratt & Whitney, and Raytheon
C25: The Collins segment offers aerospace and defense products, and aftermarket services for civil and military aircraft manufacturers and commercial airlines, as well as regional, business, and general aviation, defense, and commercial space operations
D26: This segment designs, manufactures, and supplies electric power generation and management and distribution, environmental control, flight control, air data and aircraft sensing, engine control, and engine nacelle systems, as well as engine components
D27: cabin interiors, including seating, oxygen, food and beverage preparation, storage and galley, lavatory, and wastewater management systems; connected aviation solutions and services; and systems solutions for connected battlespace, test and training range systems, crew escape systems, and simulation and training
D28: It also provides spare parts, overhaul and repair, engineering and technical support, training and fleet management solutions, and asset and information management services
C29: The Pratt & Whitney segment supplies aircraft engines for commercial, military, business jet, and general aviation customers; and produces, sells, and services military and commercial auxiliary power units, as well as offers fleet management and aftermarket maintenance, repair, and overhaul services
C30: The Raytheon segment provides defensive and offensive threat detection, tracking, and mitigation capabilities for government and commercial customers
D31: This segment offers sensors, mission orchestration and satellite control products, and software. The company was formerly known as Raytheon Technologies Corporation and changed its name to RTX Corporation in July 2023
B32: RTX Corporation was incorporated in 1934 and is headquartered in Arlington, Virginia
A34: Business Segments and Geographical Info:
B35: [Begin researching fundamentals / core business … begin with SEC filings, but expand and use all public resources available]

Sheet Model
B1: [Use for Graphing] | AI1: Q1 2020 | AM1: Q1 2021 | AQ1: Q1 2022 | AU1: Q1 2023 | AY1: Q1 2024 | BC1: Q1 2025 | BG1: Q1 2026
B2: Quarterly
B3: Revenues | C3: {="Q"&MOD(_xlfn.SEQUENCE(1,60)-1,4)+1&" "&(2012+INT((_xlfn.SEQUENCE(1,60)-1)/4))} -> Q1 2012 | D3: Q2 2012 | E3: Q3 2012 | F3: Q4 2012 | G3: Q1 2013 | H3: Q2 2013 | I3: Q3 2013 | J3: Q4 2013 | K3: Q1 2014 | L3: Q2 2014 | M3: Q3 2014 | N3: Q4 2014 | O3: Q1 2015 | P3: Q2 2015 | Q3: Q3 2015 | R3: Q4 2015 | S3: Q1 2016 | T3: Q2 2016 | U3: Q3 2016 | V3: Q4 2016 | W3: Q1 2017 | X3: Q2 2017 | Y3: Q3 2017 | Z3: Q4 2017 | AA3: Q1 2018 | AB3: Q2 2018 | AC3: Q3 2018 | AD3: Q4 2018 | AE3: Q1 2019 | AF3: Q2 2019 | AG3: Q3 2019 | AH3: Q4 2019 | AI3: Q1 2020 | AJ3: Q2 2020 | AK3: Q3 2020 | AL3: Q4 2020 | AM3: Q1 2021 | AN3: Q2 2021 | AO3: Q3 2021 | AP3: Q4 2021 | AQ3: Q1 2022 | AR3: Q2 2022 | AS3: Q3 2022 | AT3: Q4 2022 | AU3: Q1 2023 | AV3: Q2 2023 | AW3: Q3 2023 | AX3: Q4 2023 | AY3: Q1 2024 | AZ3: Q2 2024 | BA3: Q3 2024 | BB3: Q4 2024 | BC3: Q1 2025 | BD3: Q2 2025 | BE3: Q3 2025 | BF3: Q4 2025 | BG3: Q1 2026 | BH3: Q2 2026 | BI3: Q3 2026 | BJ3: Q4 2026 | BS3: 2012 | BT3: =BS3+1 -> 2013 | BU3: =BT3+1 -> 2014 | BV3: =BU3+1 -> 2015 | BW3: =BV3+1 -> 2016 | BX3: =BW3+1 -> 2017 | BY3: =BX3+1 -> 2018 | BZ3: =BY3+1 -> 2019 | CA3: =BZ3+1 -> 2020 | ... EN3: =EM3+1 -> 2085
B4: Collins Aerospace | AM4: 4370 | AN4: 4545 | AO4: 4592 | AP4: =18449-SUM(AM4:AO4) -> 4942 | AQ4: 4824 | AR4: 5011 | AS4: 5718 | AT4: =20597-SUM(AQ4:AS4) -> 5044 | AU4: 6120 | AV4: 6384 | AW4: 6629 | AX4: =26253-SUM(AU4:AW4) -> 7120 | AY4: 6673 | AZ4: 6999 | BA4: 7075 | BB4: =28284-SUM(AY4:BA4) -> 7537 | BC4: 7217 | BD4: 7622 | BE4: 7621 | BF4: =30196-SUM(BC4:BE4) -> 7736 | BG4: 7602 | BH4: 8210 | BI4: 8382 | CB4: =SUM(AM4:AP4) -> 18449 | CC4: =SUM(AQ4:AT4) -> 20597 | CD4: =SUM(AU4:AX4) -> 26253 | CE4: =SUM(AY4:BB4) -> 28284 | CF4: =SUM(BC4:BF4) -> 30196 | CG4: =CF4*(1+CG10) -> 32460.7 | CH4: =CG4*(1+CH10) -> 35382.163 | CI4: =CH4*(1+CI10) -> 39097.29 | CJ4: =CI4*(1+CJ10) -> 42811.533 | CK4: =CJ4*(1+CK10) -> 46236.455 | CL4: =CK4*(1+CL10) -> 49010.643 | CM4: =CL4*(1+CM10) -> 51706.228 | CN4: =CM4*(1+CN10) -> 54291.539 | ... CP4: =CO4*(1+CP10) -> 59004.045
B5: Pratt & Whitney | AM5: 4030 | AN5: 4280 | AO5: 4725 | AP5: =18150-SUM(AM5:AO5) -> 5115 | AQ5: 4529 | AR5: 4969 | AS5: 5380 | AT5: =20530-SUM(AQ5:AS5) -> 5652 | AU5: 5230 | AV5: 5701 | AW5: 926 | AX5: =18296-SUM(AU5:AW5) -> 6439 | AY5: 6456 | AZ5: 6802 | BA5: 7239 | BB5: =28066-SUM(AY5:BA5) -> 7569 | BC5: 7366 | BD5: 7631 | BE5: 8423 | BF5: =32916-SUM(BC5:BE5) -> 9496 | BG5: 8173 | BH5: 8889 | BI5: 9231 | CB5: =SUM(AM5:AP5) -> 18150 | CC5: =SUM(AQ5:AT5) -> 20530 | CD5: =SUM(AU5:AX5) -> 18296 | CE5: =SUM(AY5:BB5) -> 28066 | CF5: =SUM(BC5:BF5) -> 32916 | CG5: =CF5*(1+CG11) -> 37030.5 | CH5: =CG5*(1+CH11) -> 42214.77 | CI5: =CH5*(1+CI11) -> 48546.986 | CJ5: =CI5*(1+CJ11) -> 54858.094 | CK5: =CJ5*(1+CK11) -> 60892.484 | CL5: =CK5*(1+CL11) -> 66372.807 | CM5: =CL5*(1+CM11) -> 71018.904 | CN5: =CM5*(1+CN11) -> 75280.038 | ... CP5: =CO5*(1+CP11) -> 82205.802
B6: Raytheon Intelligence & Space + Missiles & Defense | AM6: =3765+3793 -> 7558 | AN6: =3805+3985 -> 7790 | AO6: =3740+3902 -> 7642 | AP6: =15180+15539-SUM(AM6:AO6) -> 7729 | AQ6: =3572+3527 -> 7099 | AR6: =3570+3558 -> 7128 | AS6: 6308 | AT6: =14312+14863-SUM(AQ6:AS6) -> 8640 | AU6: 6292 | AV6: 6700 | AW6: 6472 | AX6: =26350-SUM(AU6:AW6) -> 6886 | AY6: 6659 | AZ6: 6511 | BA6: 6386 | BB6: =26713-SUM(AY6:BA6) -> 7157 | BC6: 6340 | BD6: 7001 | BE6: 7045 | BF6: =28043-SUM(BC6:BE6) -> 7657 | BG6: 6945 | BH6: 8269 | BI6: 8031 | CB6: =SUM(AM6:AP6) -> 30719 | CC6: =SUM(AQ6:AT6) -> 29175 | CD6: =SUM(AU6:AX6) -> 26350 | CE6: =SUM(AY6:BB6) -> 26713 | CF6: =SUM(BC6:BF6) -> 28043 | CG6: =CF6*(1+CG12) -> 31688.59 | CH6: =CG6*(1+CH12) -> 36441.878 | CI6: =CH6*(1+CI12) -> 40450.485 | CJ6: =CI6*(1+CJ12) -> 44091.029 | CK6: =CJ6*(1+CK12) -> 47618.311 | CL6: =CK6*(1+CL12) -> 49999.227 | CM6: =CL6*(1+CM12) -> 51499.203 | CN6: =CM6*(1+CN12) -> 52529.188 | ... CP6: =CO6*(1+CP12) -> 54250.175
B7: Intersegment Eliminations | AM7: -707 | AN7: -735 | AO7: -746 | AP7: =-2930-SUM(AM7:AO7) -> -742 | AQ7: -736 | AR7: -794 | AS7: -455 | AT7: =-3228-SUM(AQ7:AS7) -> -1243 | AU7: -428 | AV7: -470 | AW7: -563 | AX7: =-1979-SUM(AU7:AW7) -> -518 | AY7: -483 | AZ7: -591 | BA7: -611 | BB7: =-2325-SUM(AY7:BA7) -> -640 | BC7: -617 | BD7: -673 | BE7: -611 | BF7: =-2552-SUM(BC7:BE7) -> -651 | BG7: -644 | BH7: -660 | BI7: -679 | CB7: =SUM(AM7:AP7) -> -2930 | CC7: =SUM(AQ7:AT7) -> -3228 | CD7: =SUM(AU7:AX7) -> -1979 | CE7: =SUM(AY7:BB7) -> -2325 | CF7: =SUM(BC7:BF7) -> -2552 | CG7: =CF7*(1+CG13) -> -2603.04 | CH7: =CG7*(1+CH13) -> -2707.1616 | CI7: =CH7*(1+CI13) -> -2815.4481 | CJ7: =CI7*(1+CJ13) -> -2871.757 | CK7: =CJ7*(1+CK13) -> -2929.1922 | CL7: =CK7*(1+CL13) -> -2987.776 | CM7: =CL7*(1+CM13) -> -3047.5315 | CN7: =CM7*(1+CN13) -> -3108.4822 | ... CP7: =CO7*(1+CP13) -> -3234.0648
B8: Ttl Revenues | AM8: =SUM(AM4:AM7) -> 15251 | AN8: =SUM(AN4:AN7) -> 15880 | AO8: =SUM(AO4:AO7) -> 16213 | AP8: =SUM(AP4:AP7) -> 17044 | AQ8: =SUM(AQ4:AQ7) -> 15716 | AR8: =SUM(AR4:AR7) -> 16314 | AS8: =SUM(AS4:AS7) -> 16951 | AT8: =SUM(AT4:AT7) -> 18093 | ... BI8: =SUM(BI4:BI7) -> 24965 | CB8: =SUM(AM8:AP8) -> 64388 | CC8: =SUM(AQ8:AT8) -> 67074 | CD8: =SUM(AU8:AX8) -> 68920 | CE8: =SUM(AY8:BB8) -> 80738 | CF8: =SUM(BC8:BF8) -> 88603 | CG8: =SUM(CG4:CG7) -> 98576.75 | CH8: =SUM(CH4:CH7) -> 111331.65 | CI8: =SUM(CI4:CI7) -> 125279.31 | CJ8: =SUM(CJ4:CJ7) -> 138888.9 | CK8: =SUM(CK4:CK7) -> 151818.06 | CL8: =SUM(CL4:CL7) -> 162394.9 | CM8: =SUM(CM4:CM7) -> 171176.8 | CN8: =SUM(CN4:CN7) -> 178992.28 | ... CP8: =SUM(CP4:CP7) -> 192225.96
B10: Collins Aerospace Growth Y/y | AQ10: =AQ4/AM4-1 -> 0.10389016 | AR10: =AR4/AN4-1 -> 0.10253025 | AS10: =AS4/AO4-1 -> 0.24520906 | AT10: =AT4/AP4-1 -> 0.020639417 | AU10: =AU4/AQ4-1 -> 0.26865672 | AV10: =AV4/AR4-1 -> 0.27399721 | AW10: =AW4/AS4-1 -> 0.15932144 | AX10: =AX4/AT4-1 -> 0.41157811 | ... BI10: =BI4/BE4-1 -> 0.099855662 | CC10: =CC4/CB4-1 -> 0.11642907 | CD10: =CD4/CC4-1 -> 0.2746031 | CE10: =CE4/CD4-1 -> 0.077362587 | CF10: =CF4/CE4-1 -> 0.067600057 | CG10: 0.075 | CH10: 0.09 | CI10: 0.105 | CJ10: 0.095 | CK10: 0.08 | CL10: 0.06 | CM10: 0.055 | CN10: 0.05 | CO10: 0.045 | CP10: 0.04
B11: Pratt & Whitney Growth Y/y | AQ11: =AQ5/AM5-1 -> 0.12382134 | AR11: =AR5/AN5-1 -> 0.16098131 | AS11: =AS5/AO5-1 -> 0.13862434 | AT11: =AT5/AP5-1 -> 0.10498534 | AU11: =AU5/AQ5-1 -> 0.1547803 | AV11: =AV5/AR5-1 -> 0.14731334 | AW11: =AW5/AS5-1 -> -0.82788104 | AX11: =AX5/AT5-1 -> 0.13924275 | ... BI11: =BI5/BE5-1 -> 0.095927817 | CC11: =CC5/CB5-1 -> 0.13112948 | CD11: =CD5/CC5-1 -> -0.10881637 | CE11: =CE5/CD5-1 -> 0.5339965 | CF11: =CF5/CE5-1 -> 0.17280696 | CG11: 0.125 | CH11: 0.14 | CI11: 0.15 | CJ11: 0.13 | CK11: 0.11 | CL11: 0.09 | CM11: 0.07 | CN11: 0.06 | CO11: 0.05 | CP11: 0.04
B12: Raytheon Growth Y/y | AQ12: =AQ6/AM6-1 -> -0.060730352 | AR12: =AR6/AN6-1 -> -0.084980745 | AS12: =AS6/AO6-1 -> -0.17456163 | AT12: =AT6/AP6-1 -> 0.11786777 | AU12: =AU6/AQ6-1 -> -0.11367798 | AV12: =AV6/AR6-1 -> -0.060044893 | AW12: =AW6/AS6-1 -> 0.025998732 | AX12: =AX6/AT6-1 -> -0.20300926 | ... BI12: =BI6/BE6-1 -> 0.13995742 | CC12: =CC6/CB6-1 -> -0.050262053 | CD12: =CD6/CC6-1 -> -0.096829477 | CE12: =CE6/CD6-1 -> 0.013776091 | CF12: =CF6/CE6-1 -> 0.049788492 | CG12: 0.13 | CH12: 0.15 | CI12: 0.11 | CJ12: 0.09 | CK12: 0.08 | CL12: 0.05 | CM12: 0.03 | CN12: 0.02 | CO12: 0.0175 | CP12: 0.015
B13: Intersegment Eliminations | AQ13: =AQ7/AM7-1 -> 0.041018388 | AR13: =AR7/AN7-1 -> 0.080272109 | AS13: =AS7/AO7-1 -> -0.39008043 | AT13: =AT7/AP7-1 -> 0.67520216 | AU13: =AU7/AQ7-1 -> -0.41847826 | AV13: =AV7/AR7-1 -> -0.40806045 | AW13: =AW7/AS7-1 -> 0.23736264 | AX13: =AX7/AT7-1 -> -0.58326629 | ... BI13: =BI7/BE7-1 -> 0.11129296 | CC13: =CC7/CB7-1 -> 0.10170648 | CD13: =CD7/CC7-1 -> -0.38692689 | CE13: =CE7/CD7-1 -> 0.17483578 | CF13: =CF7/CE7-1 -> 0.097634409 | CG13: 0.02 | CH13: 0.04 | CI13: 0.04 | CJ13: 0.02 | CK13: 0.02 | CL13: 0.02 | CM13: 0.02 | CN13: 0.02 | CO13: 0.02 | CP13: 0.02
B14: Ttl Revenue Growth Y/y | AQ14: =AQ8/AM8-1 -> 0.030489804 | AR14: =AR8/AN8-1 -> 0.027329975 | AS14: =AS8/AO8-1 -> 0.045519028 | AT14: =AT8/AP8-1 -> 0.061546585 | AU14: =AU8/AQ8-1 -> 0.095316875 | AV14: =AV8/AR8-1 -> 0.12265539 | AW14: =AW8/AS8-1 -> -0.20571058 | AX14: =AX8/AT8-1 -> 0.10136517 | ... BI14: =BI8/BE8-1 -> 0.11064152 | CC14: =CC8/CB8-1 -> 0.041715848 | CD14: =CD8/CC8-1 -> 0.027521842 | CE14: =CE8/CD8-1 -> 0.17147417 | CF14: =CF8/CE8-1 -> 0.097413857 | CG14: =CG8/CF8-1 -> 0.11256673 | CH14: =CH8/CG8-1 -> 0.12939055 | CI14: =CI8/CH8-1 -> 0.1252803 | CJ14: =CJ8/CI8-1 -> 0.10863394 | ... CP14: =CP8/CO8-1 -> 0.033159077
B16: Collins Aerospace % of Ttl Revenues | AM16: =AM4/AM8 -> 0.28653859 | AN16: =AN4/AN8 -> 0.28620907 | AO16: =AO4/AO8 -> 0.28322951 | AP16: =AP4/AP8 -> 0.28995541 | AQ16: =AQ4/AQ8 -> 0.30694833 | AR16: =AR4/AR8 -> 0.30715949 | AS16: =AS4/AS8 -> 0.33732523 | AT16: =AT4/AT8 -> 0.27878185 | ... BI16: =BI4/BI8 -> 0.33575005 | CB16: =CB4/CB8 -> 0.28652855 | CC16: =CC4/CC8 -> 0.30707875 | CD16: =CD4/CD8 -> 0.38091991 | CE16: =CE4/CE8 -> 0.35031831 | CF16: =CF4/CF8 -> 0.3408011
B17: Pratt & Whitney % of Ttl Revenues | AM17: =AM5/AM8 -> 0.26424497 | AN17: =AN5/AN8 -> 0.26952141 | AO17: =AO5/AO8 -> 0.2914328 | AP17: =AP5/AP8 -> 0.30010561 | AQ17: =AQ5/AQ8 -> 0.28817765 | AR17: =AR5/AR8 -> 0.30458502 | AS17: =AS5/AS8 -> 0.3173854 | AT17: =AT5/AT8 -> 0.31238601 | ... BI17: =BI5/BI8 -> 0.36975766 | CB17: =CB5/CB8 -> 0.28188482 | CC17: =CC5/CC8 -> 0.30607985 | CD17: =CD5/CD8 -> 0.26546721 | CE17: =CE5/CE8 -> 0.34761822 | CF17: =CF5/CF8 -> 0.37149984
B18: Raytheon % of Ttl Revenues | AM18: =AM6/AM8 -> 0.49557406 | AN18: =AN6/AN8 -> 0.49055416 | AO18: =AO6/AO8 -> 0.47135015 | AP18: =AP6/AP8 -> 0.45347336 | AQ18: =AQ6/AQ8 -> 0.45170527 | AR18: =AR6/AR8 -> 0.43692534 | AS18: =AS6/AS8 -> 0.37213144 | AT18: =AT6/AT8 -> 0.47753275 | ... BI18: =BI6/BI8 -> 0.32169037 | CB18: =CB6/CB8 -> 0.477092 | CC18: =CC6/CC8 -> 0.43496735 | CD18: =CD6/CD8 -> 0.38232734 | CE18: =CE6/CE8 -> 0.33086031 | CF18: =CF6/CF8 -> 0.3165017
B20: U.S. | AM20: 9730 | AN20: 9871 | AO20: 10096 | AP20: =40011-SUM(AM20:AO20) -> 10314 | AQ20: 9730 | AR20: 10185 | AS20: 10422 | AT20: =41190-SUM(AQ20:AS20) -> 10853 | AU20: 10548 | AV20: 11227 | AW20: 11155 | AX20: =44881-SUM(AU20:AW20) -> 11951 | AY20: 11361 | AZ20: 11625 | BA20: 11411 | BB20: =46087-SUM(AY20:BA20) -> 11690 | BC20: 11266 | BD20: 11737 | BE20: 11734 | BF20: =47291-SUM(BC20:BE20) -> 12554 | BG20: 11913 | BH20: 13093 | BI20: 13241 | CB20: =SUM(AM20:AP20) -> 40011 | CC20: =SUM(AQ20:AT20) -> 41190 | CD20: =SUM(AU20:AX20) -> 44881 | CE20: =SUM(AY20:BB20) -> 46087 | CF20: =SUM(BC20:BF20) -> 47291
B21: Europe | AM21: 2147 | AN21: 2316 | AO21: 2408 | AP21: =9598-SUM(AM21:AO21) -> 2727 | AQ21: 2572 | AR21: 2678 | AS21: 2663 | AT21: =11111-SUM(AQ21:AS21) -> 3198 | AU21: 2990 | AV21: 3286 | AW21: 3514 | AX21: =13501-SUM(AU21:AW21) -> 3711 | AY21: 3833 | AZ21: 3589 | BA21: 4120 | BB21: =15975-SUM(AY21:BA21) -> 4433 | BC21: 4413 | BD21: 4205 | BE21: 5225 | BF21: =18799-SUM(BC21:BE21) -> 4956 | BG21: 4882 | BH21: 5350 | BI21: 5670 | CB21: =SUM(AM21:AP21) -> 9598 | CC21: =SUM(AQ21:AT21) -> 11111 | CD21: =SUM(AU21:AX21) -> 13501 | CE21: =SUM(AY21:BB21) -> 15975 | CF21: =SUM(BC21:BF21) -> 18799
B22: APAC | AM22: 1772 | AN22: 2002 | AO22: 2006 | AP22: =7969-SUM(AM22:AO22) -> 2189 | AQ22: 1857 | AR22: 1808 | AS22: 2160 | AT22: =8057-SUM(AQ22:AS22) -> 2232 | AU22: 2050 | AV22: 2109 | AW22: 2414 | AX22: =9049-SUM(AU22:AW22) -> 2476 | AY22: 2427 | AZ22: 2661 | BA22: 2789 | BB22: =10893-SUM(AY22:BA22) -> 3016 | BC22: 2592 | BD22: 3410 | BE22: 3567 | BF22: =13782-SUM(BC22:BE22) -> 4213 | BG22: 2804 | BH22: 3656 | BI22: 3521 | CB22: =SUM(AM22:AP22) -> 7969 | CC22: =SUM(AQ22:AT22) -> 8057 | CD22: =SUM(AU22:AX22) -> 9049 | CE22: =SUM(AY22:BB22) -> 10893 | CF22: =SUM(BC22:BF22) -> 13782
B23: Mid-East | AM23: 992 | AN23: 1167 | AO23: 1140 | AP23: =4379-SUM(AM23:AO23) -> 1080 | AQ23: 829 | AR23: 869 | AS23: 978 | AT23: =3599-SUM(AQ23:AS23) -> 923 | AU23: 763 | AV23: 851 | AW23: 824 | AX23: =3237-SUM(AU23:AW23) -> 799 | AY23: 849 | AZ23: 791 | BA23: 628 | BB23: =3458-SUM(AY23:BA23) -> 1190 | BC23: 848 | BD23: 904 | BE23: 732 | BF23: =3621-SUM(BC23:BE23) -> 1137 | BG23: 930 | BH23: 1042 | BI23: 975 | CB23: =SUM(AM23:AP23) -> 4379 | CC23: =SUM(AQ23:AT23) -> 3599 | CD23: =SUM(AU23:AX23) -> 3237 | CE23: =SUM(AY23:BB23) -> 3458 | CF23: =SUM(BC23:BF23) -> 3621
B24: Other regions | AM24: 610 | AN24: 524 | AO24: 563 | AP24: =2431-SUM(AM24:AO24) -> 734 | AQ24: 728 | AR24: 774 | AS24: 728 | AT24: =3117-SUM(AQ24:AS24) -> 887 | AU24: 863 | AV24: 842 | AW24: 958 | AX24: =3653-SUM(AU24:AW24) -> 990 | AY24: 835 | AZ24: 1055 | BA24: 1141 | BB24: =4325-SUM(AY24:BA24) -> 1294 | BC24: 1187 | BD24: 1325 | BE24: 1220 | BF24: =5110-SUM(BC24:BE24) -> 1378 | BG24: 1547 | BH24: 1567 | BI24: 1558 | CB24: =SUM(AM24:AP24) -> 2431 | CC24: =SUM(AQ24:AT24) -> 3117 | CD24: =SUM(AU24:AX24) -> 3653 | CE24: =SUM(AY24:BB24) -> 4325 | CF24: =SUM(BC24:BF24) -> 5110
B25: Ttl Revenues | AM25: =SUM(AM20:AM24) -> 15251 | AN25: =SUM(AN20:AN24) -> 15880 | AO25: =SUM(AO20:AO24) -> 16213 | AP25: =SUM(AP20:AP24) -> 17044 | AQ25: =SUM(AQ20:AQ24) -> 15716 | AR25: =SUM(AR20:AR24) -> 16314 | AS25: =SUM(AS20:AS24) -> 16951 | AT25: =SUM(AT20:AT24) -> 18093 | ... AV25: =SUM(AV20:AV24) -> 18315 | AW25: =SUM(AW19:AW24)-5401 -> 13464 | AX25: =SUM(AX20:AX24) -> 19927 | AY25: =SUM(AY20:AY24) -> 19305 | AZ25: =SUM(AZ20:AZ24) -> 19721 | BA25: =SUM(BA20:BA24) -> 20089 | BB25: =SUM(BB20:BB24) -> 21623 | BC25: =SUM(BC20:BC24) -> 20306 | BD25: =SUM(BD20:BD24) -> 21581 | BE25: =SUM(BE20:BE24) -> 22478 | ... BI25: =SUM(BI20:BI24) -> 24965 | CB25: =SUM(AM25:AP25) -> 64388 | CC25: =SUM(AQ25:AT25) -> 67074 | CD25: =SUM(AU25:AX25) -> 68920 | CE25: =SUM(AY25:BB25) -> 80738 | CF25: =SUM(BC25:BF25) -> 88603
B27: U.S. Growth Y/y | AQ27: =AQ20/AM20-1 -> 0 | AR27: =AR20/AN20-1 -> 0.031810354 | AS27: =AS20/AO20-1 -> 0.032290016 | AT27: =AT20/AP20-1 -> 0.052259065 | AU27: =AU20/AQ20-1 -> 0.084069887 | AV27: =AV20/AR20-1 -> 0.10230731 | AW27: =AW20/AS20-1 -> 0.07033199 | AX27: =AX20/AT20-1 -> 0.10117018 | ... BI27: =BI20/BE20-1 -> 0.1284302 | CC27: =CC20/CB20-1 -> 0.029466897 | CD27: =CD20/CC20-1 -> 0.089609128 | CE27: =CE20/CD20-1 -> 0.026871059 | CF27: =CF20/CE20-1 -> 0.026124504
B28: Europe Growth Y/y | AQ28: =AQ21/AM21-1 -> 0.19795063 | AR28: =AR21/AN21-1 -> 0.15630397 | AS28: =AS21/AO21-1 -> 0.10589701 | AT28: =AT21/AP21-1 -> 0.17271727 | AU28: =AU21/AQ21-1 -> 0.16251944 | AV28: =AV21/AR21-1 -> 0.2270351 | AW28: =AW21/AS21-1 -> 0.3195644 | AX28: =AX21/AT21-1 -> 0.16041276 | ... BI28: =BI21/BE21-1 -> 0.085167464 | CC28: =CC21/CB21-1 -> 0.15763701 | CD28: =CD21/CC21-1 -> 0.21510215 | CE28: =CE21/CD21-1 -> 0.18324569 | CF28: =CF21/CE21-1 -> 0.17677621
B29: APAC Growth Y/y | AQ29: =AQ22/AM22-1 -> 0.047968397 | AR29: =AR22/AN22-1 -> -0.096903097 | AS29: =AS22/AO22-1 -> 0.076769691 | AT29: =AT22/AP22-1 -> 0.019643673 | AU29: =AU22/AQ22-1 -> 0.10393107 | AV29: =AV22/AR22-1 -> 0.1664823 | AW29: =AW22/AS22-1 -> 0.11759259 | AX29: =AX22/AT22-1 -> 0.109319 | ... BI29: =BI22/BE22-1 -> -0.012895991 | CC29: =CC22/CB22-1 -> 0.011042791 | CD29: =CD22/CC22-1 -> 0.12312275 | CE29: =CE22/CD22-1 -> 0.20377942 | CF29: =CF22/CE22-1 -> 0.26521619
B30: Mid-East Growth Y/y | AQ30: =AQ23/AM23-1 -> -0.16431452 | AR30: =AR23/AN23-1 -> -0.25535561 | AS30: =AS23/AO23-1 -> -0.14210526 | AT30: =AT23/AP23-1 -> -0.14537037 | AU30: =AU23/AQ23-1 -> -0.079613993 | AV30: =AV23/AR23-1 -> -0.020713464 | AW30: =AW23/AS23-1 -> -0.15746421 | AX30: =AX23/AT23-1 -> -0.13434453 | ... BI30: =BI23/BE23-1 -> 0.33196721 | CC30: =CC23/CB23-1 -> -0.17812286 | CD30: =CD23/CC23-1 -> -0.1005835 | CE30: =CE23/CD23-1 -> 0.068273092 | CF30: =CF23/CE23-1 -> 0.047137073
B31: Other regions Growth Y/y | AQ31: =AQ24/AM24-1 -> 0.19344262 | AR31: =AR24/AN24-1 -> 0.47709924 | AS31: =AS24/AO24-1 -> 0.29307282 | AT31: =AT24/AP24-1 -> 0.20844687 | AU31: =AU24/AQ24-1 -> 0.18543956 | AV31: =AV24/AR24-1 -> 0.087855297 | AW31: =AW24/AS24-1 -> 0.31593407 | AX31: =AX24/AT24-1 -> 0.11612176 | ... BI31: =BI24/BE24-1 -> 0.27704918 | CC31: =CC24/CB24-1 -> 0.2821884 | CD31: =CD24/CC24-1 -> 0.17196022 | CE31: =CE24/CD24-1 -> 0.18395839 | CF31: =CF24/CE24-1 -> 0.18150289
B32: Ttl Revenue Growth | AQ32: =AQ25/AM25-1 -> 0.030489804 | AR32: =AR25/AN25-1 -> 0.027329975 | AS32: =AS25/AO25-1 -> 0.045519028 | AT32: =AT25/AP25-1 -> 0.061546585 | AU32: =AU25/AQ25-1 -> 0.095316875 | AV32: =AV25/AR25-1 -> 0.12265539 | AW32: =AW25/AS25-1 -> -0.20571058 | AX32: =AX25/AT25-1 -> 0.10136517 | ... BI32: =BI25/BE25-1 -> 0.11064152 | CC32: =CC25/CB25-1 -> 0.041715848 | CD32: =CD25/CC25-1 -> 0.027521842 | CE32: =CE25/CD25-1 -> 0.17147417 | CF32: =CF25/CE25-1 -> 0.097413857
B34: U.S. % of Revenues | AM34: =AM20/AM25 -> 0.63799095 | AN34: =AN20/AN25 -> 0.6215995 | AO34: =AO20/AO25 -> 0.62271017 | AP34: =AP20/AP25 -> 0.60513964 | AQ34: =AQ20/AQ25 -> 0.61911428 | AR34: =AR20/AR25 -> 0.62431041 | AS34: =AS20/AS25 -> 0.61483098 | AT34: =AT20/AT25 -> 0.59984524 | ... BI34: =BI20/BI25 -> 0.53038254 | CB34: =CB20/CB25 -> 0.62140461 | CC34: =CC20/CC25 -> 0.61409786 | CD34: =CD20/CD25 -> 0.65120429 | CE34: =CE20/CE25 -> 0.57082167 | CF34: =CF20/CF25 -> 0.53374039
B35: Europe % of Revenues | AM35: =AM21/AM25 -> 0.14077765 | AN35: =AN21/AN25 -> 0.14584383 | AO35: =AO21/AO25 -> 0.14852279 | AP35: =AP21/AP25 -> 0.15999765 | AQ35: =AQ21/AQ25 -> 0.16365487 | AR35: =AR21/AR25 -> 0.16415349 | AS35: =AS21/AS25 -> 0.15709988 | AT35: =AT21/AT25 -> 0.17675344 | ... BI35: =BI21/BI25 -> 0.22711797 | CB35: =CB21/CB25 -> 0.14906504 | CC35: =CC21/CC25 -> 0.16565286 | CD35: =CD21/CD25 -> 0.19589379 | CE35: =CE21/CE25 -> 0.19786222 | CF35: =CF21/CF25 -> 0.21217115
B36: APAC % of Revenues | AM36: =AM22/AM25 -> 0.1161891 | AN36: =AN22/AN25 -> 0.12607053 | AO36: =AO22/AO25 -> 0.12372787 | AP36: =AP22/AP25 -> 0.12843229 | AQ36: =AQ22/AQ25 -> 0.11815984 | AR36: =AR22/AR25 -> 0.11082506 | AS36: =AS22/AS25 -> 0.12742611 | AT36: =AT22/AT25 -> 0.12336263 | ... BI36: =BI22/BI25 -> 0.14103745 | CB36: =CB22/CB25 -> 0.1237653 | CC36: =CC22/CC25 -> 0.12012106 | CD36: =CD22/CD25 -> 0.13129716 | CE36: =CE22/CE25 -> 0.13491788 | CF36: =CF22/CF25 -> 0.15554778
B37: Mid-East % of Revenues | AM37: =AM23/AM25 -> 0.065044915 | AN37: =AN23/AN25 -> 0.073488665 | AO37: =AO23/AO25 -> 0.070313946 | AP37: =AP23/AP25 -> 0.063365407 | AQ37: =AQ23/AQ25 -> 0.052748791 | AR37: =AR23/AR25 -> 0.053267133 | AS37: =AS23/AS25 -> 0.057695711 | AT37: =AT23/AT25 -> 0.051014204 | ... BI37: =BI23/BI25 -> 0.039054677 | CB37: =CB23/CB25 -> 0.068009567 | CC37: =CC23/CC25 -> 0.053657155 | CD37: =CD23/CD25 -> 0.046967499 | CE37: =CE23/CE25 -> 0.042829894 | CF37: =CF23/CF25 -> 0.040867691
B38: Other regions % of Revenues | AM38: =AM24/AM25 -> 0.039997377 | AN38: =AN24/AN25 -> 0.032997481 | AO38: =AO24/AO25 -> 0.034725221 | AP38: =AP24/AP25 -> 0.043065008 | AQ38: =AQ24/AQ25 -> 0.046322219 | AR38: =AR24/AR25 -> 0.047443913 | AS38: =AS24/AS25 -> 0.042947319 | AT38: =AT24/AT25 -> 0.049024485 | ... BI38: =BI24/BI25 -> 0.06240737 | CB38: =CB24/CB25 -> 0.037755482 | CC38: =CC24/CC25 -> 0.046471062 | CD38: =CD24/CD25 -> 0.053003482 | CE38: =CE24/CE25 -> 0.053568332 | CF38: =CF24/CF25 -> 0.057672991
B40: Revenues | C40: 12416 | D40: 13807 | E40: 15042 | F40: 16443 | G40: 14399 | H40: 16006 | I40: 15462 | J40: 10733 | K40: 14745 | L40: 17191 | M40: 14613 | N40: 11351 | O40: 13320 | P40: 14690 | Q40: 13788 | R40: 14300 | S40: 13357 | T40: 14874 | U40: 14354 | V40: 14659 | W40: 13815 | X40: 15280 | Y40: 15062 | Z40: 15680 | AA40: 15242 | AB40: 16705 | AC40: 16510 | AD40: -13756 | AE40: 18365 | AF40: 11329 | AG40: 11373 | AH40: 4282 | AI40: 18210 | AJ40: 14277 | AK40: 14747 | AL40: 16583 | AM40: =AM8 -> 15251 | AN40: =AN8 -> 15880 | AO40: =AO8 -> 16213 | AP40: =AP8 -> 17044 | AQ40: =AQ8 -> 15716 | AR40: =AR8 -> 16314 | AS40: =AS8 -> 16951 | AT40: =AT8 -> 18093 | ... BI40: =BI8 -> 24965 | BS40: =SUM(C40:F40) -> 57708 | BT40: =SUM(G40:J40) -> 56600 | BU40: =SUM(K40:N40) -> 57900 | BV40: =SUM(O40:R40) -> 56098 | BW40: =SUM(S40:V40) -> 57244 | BX40: =SUM(W40:Z40) -> 59837 | BY40: =SUM(AA40:AD40) -> 34701 | BZ40: =SUM(AE40:AH40) -> 45349 | CA40: =SUM(AI40:AL40) -> 63817 | CB40: =SUM(AM40:AP40) -> 64388 | CC40: =SUM(AQ40:AT40) -> 67074 | CD40: =SUM(AU40:AX40) -> 68920 | CE40: =SUM(AY40:BB40) -> 80738 | CF40: =SUM(BC40:BF40) -> 88603 | CG40: =CG8 -> 98576.75 | CH40: =CH8 -> 111331.65 | CI40: =CI8 -> 125279.31 | CJ40: =CJ8 -> 138888.9 | CK40: =CK8 -> 151818.06 | CL40: =CL8 -> 162394.9 | CM40: =CM8 -> 171176.8 | CN40: =CN8 -> 178992.28 | ... CP40: =CP8 -> 192225.96
B41: COGS | C41: 8930 | D41: 9934 | E41: 11003 | F41: 12286 | G41: 10465 | H41: 11552 | I41: 11020 | J41: 7431 | K41: 10690 | L41: 12931 | M41: 10165 | N41: 7112 | O41: 9506 | P41: 10472 | Q41: 9800 | R41: 10653 | S41: 9654 | T41: 10741 | U41: 10342 | V41: 10734 | W41: 10136 | X41: 11164 | Y41: 11106 | Z41: 11795 | AA41: 11280 | AB41: 12422 | AC41: 12536 | AD41: -8773 | AE41: 13707 | AF41: 8554 | AG41: 8509 | AH41: 3828 | AI41: 8572 | AJ41: 12214 | AK41: 13004 | AL41: 14266 | AM41: =9974+2563 -> 12537 | AN41: =9997+2658 -> 12655 | AO41: =10296+2793 -> 13089 | AP41: =41095+10802-SUM(AM41:AO41) -> 13616 | AQ41: =9820+2740 -> 12560 | AR41: =10040+2816 -> 12856 | AS41: =10493+2971 -> 13464 | AT41: =41927+11479-SUM(AQ41:AS41) -> 14526 | AU41: =10700+2945 -> 13645 | AV41: =11089+3429 -> 14518 | AW41: =9289+3461 -> 12750 | AX41: =43425+13406-SUM(AU41:AW41) -> 15918 | AY41: =12216+3528 -> 15744 | AZ41: =12625+3516 -> 16141 | BA41: =12336+3719 -> 16055 | BB41: =50768+14560-SUM(AY41:BA41) -> 17388 | BC41: =12283+3907 -> 16190 | BD41: =12989+4216 -> 17205 | BE41: =13593+4305 -> 17898 | BF41: =53780+17034-SUM(BC41:BE41) -> 19521 | BG41: =13000+4482 -> 17482 | BH41: =14802+4773 -> 19575 | BI41: 19160 | BS41: =SUM(C41:F41) -> 42153 | BT41: =SUM(G41:J41) -> 40468 | BU41: =SUM(K41:N41) -> 40898 | BV41: =SUM(O41:R41) -> 40431 | BW41: =SUM(S41:V41) -> 41471 | BX41: =SUM(W41:Z41) -> 44201 | BY41: =SUM(AA41:AD41) -> 27465 | BZ41: =SUM(AE41:AH41) -> 34598 | CA41: =SUM(AI41:AL41) -> 48056 | CB41: =SUM(AM41:AP41) -> 51897 | CC41: =SUM(AQ41:AT41) -> 53406 | CD41: =SUM(AU41:AX41) -> 56831 | CE41: =SUM(AY41:BB41) -> 65328 | CF41: =SUM(BC41:BF41) -> 70814 | CG41: =CG40*(1-CG57) -> 77875.633 | CH41: =CH40*(1-CH57) -> 87673.674 | CI41: =CI40*(1-CI57) -> 98344.26 | CJ41: =CJ40*(1-CJ57) -> 108333.34 | CK41: =CK40*(1-CK57) -> 118266.27 | CL41: =CL40*(1-CL57) -> 126343.23 | CM41: =CM40*(1-CM57) -> 133004.38 | CN41: =CN40*(1-CN57) -> 138898.01 | ... CP41: =CP40*(1-CP57) -> 148975.12
B42: GP | C42: =C40-C41 -> 3486 | D42: =D40-D41 -> 3873 | E42: =E40-E41 -> 4039 | F42: =F40-F41 -> 4157 | G42: =G40-G41 -> 3934 | H42: =H40-H41 -> 4454 | I42: =I40-I41 -> 4442 | J42: =J40-J41 -> 3302 | ... BI42: =BI40-BI41 -> 5805 | BS42: =SUM(C42:F42) -> 15555 | BT42: =SUM(G42:J42) -> 16132 | BU42: =SUM(K42:N42) -> 17002 | BV42: =SUM(O42:R42) -> 15667 | BW42: =SUM(S42:V42) -> 15773 | BX42: =SUM(W42:Z42) -> 15636 | BY42: =SUM(AA42:AD42) -> 7236 | BZ42: =SUM(AE42:AH42) -> 10751 | CA42: =SUM(AI42:AL42) -> 15761 | CB42: =SUM(AM42:AP42) -> 12491 | CC42: =SUM(AQ42:AT42) -> 13668 | CD42: =SUM(AU42:AX42) -> 12089 | CE42: =SUM(AY42:BB42) -> 15410 | CF42: =SUM(BC42:BF42) -> 17789 | CG42: =CG40-CG41 -> 20701.117 | CH42: =CH40-CH41 -> 23657.976 | CI42: =CI40-CI41 -> 26935.052 | CJ42: =CJ40-CJ41 -> 30555.558 | CK42: =CK40-CK41 -> 33551.791 | CL42: =CL40-CL41 -> 36051.668 | CM42: =CM40-CM41 -> 38172.427 | CN42: =CN40-CN41 -> 40094.271 | ... CP42: =CP40-CP41 -> 43250.84
B43: R&D | C43: 544 | D43: 525 | E43: 590 | F43: 712 | G43: 610 | H43: 631 | I43: 630 | J43: 471 | K43: 624 | L43: 666 | M43: 640 | N43: 545 | O43: 564 | P43: 558 | Q43: 546 | R43: 611 | S43: 541 | T43: 588 | U43: 582 | V43: 665 | W43: 586 | X43: 619 | Y43: 592 | Z43: 630 | AA43: 554 | AB43: 589 | AC43: 586 | AD43: 149 | AE43: 728 | AF43: 605 | AG43: 592 | AH43: 527 | AI43: 535 | AJ43: 695 | AK43: 642 | AL43: 710 | AM43: 589 | AN43: 657 | AO43: 676 | AP43: =2711-SUM(AM43:AO43) -> 789 | AQ43: 635 | AR43: 698 | AS43: 662 | AT43: =2711-SUM(AQ43:AS43) -> 716 | AU43: 607 | AV43: 729 | AW43: 712 | AX43: =2805-SUM(AU43:AW43) -> 757 | AY43: 669 | AZ43: 706 | BA43: 751 | BB43: =2934-SUM(AY43:BA43) -> 808 | BC43: 637 | BD43: 697 | BE43: 684 | BF43: =2807-SUM(BC43:BE43) -> 789 | BG43: 627 | BH43: 726 | BI43: 711 | BS43: =SUM(C43:F43) -> 2371 | BT43: =SUM(G43:J43) -> 2342 | BU43: =SUM(K43:N43) -> 2475 | BV43: =SUM(O43:R43) -> 2279 | BW43: =SUM(S43:V43) -> 2376 | BX43: =SUM(W43:Z43) -> 2427 | BY43: =SUM(AA43:AD43) -> 1878 | BZ43: =SUM(AE43:AH43) -> 2452 | CA43: =SUM(AI43:AL43) -> 2582 | CB43: =SUM(AM43:AP43) -> 2711 | CC43: =SUM(AQ43:AT43) -> 2711 | CD43: =SUM(AU43:AX43) -> 2805 | CE43: =SUM(AY43:BB43) -> 2934 | CF43: =SUM(BC43:BF43) -> 2807 | CG43: =CG40*CG58 -> 2760.149 | CH43: =CH40*CH58 -> 3228.6178 | CI43: =CI40*CI58 -> 3758.3794 | CJ43: =CJ40*CJ58 -> 4305.5558 | CK43: =CK40*CK58 -> 4858.1779 | CL43: =CL40*CL58 -> 5196.6368 | CM43: =CM40*CM58 -> 5306.4809 | CN43: =CN40*CN58 -> 5369.7685 | ... CP43: =CP40*CP58 -> 5382.3268
B44: SG&A | C44: 1529 | D44: 1509 | E44: 1619 | F44: 1795 | G44: 1627 | H44: 1737 | I44: 1633 | J44: 1367 | K44: 1596 | L44: 1623 | M44: 1501 | N44: 1452 | O44: 1476 | P44: 1426 | Q44: 1359 | R44: 1836 | S44: 1363 | T44: 1451 | U44: 1390 | V44: 1754 | W44: 1537 | X44: 1590 | Y44: 1582 | Z44: 1720 | AA44: 1711 | AB44: 1759 | AC44: 1681 | AD44: -2287 | AE44: 1997 | AF44: 902 | AG44: 902 | AH44: -90 | AI44: 977 | AJ44: 1811 | AK44: 1401 | AL44: 1351 | AM44: 1220 | AN44: 1368 | AO44: 1229 | AP44: =5663-SUM(AM44:AO44) -> 1846 | AQ44: 1469 | AR44: 1424 | AS44: 1351 | AT44: =5663-SUM(AQ44:AS44) -> 1419 | AU44: 1363 | AV44: 1600 | AW44: 1401 | AX44: =5809-SUM(AU44:AW44) -> 1445 | AY44: 1394 | AZ44: 1449 | BA44: 1389 | BB44: =5806-SUM(AY44:BA44) -> 1574 | BC44: 1448 | BD44: 1573 | BE44: 1436 | BF44: =6095-SUM(BC44:BE44) -> 1638 | BG44: 1476 | BH44: 1658 | BI44: 1918 | BS44: =SUM(C44:F44) -> 6452 | BT44: =SUM(G44:J44) -> 6364 | BU44: =SUM(K44:N44) -> 6172 | BV44: =SUM(O44:R44) -> 6097 | BW44: =SUM(S44:V44) -> 5958 | BX44: =SUM(W44:Z44) -> 6429 | BY44: =SUM(AA44:AD44) -> 2864 | BZ44: =SUM(AE44:AH44) -> 3711 | CA44: =SUM(AI44:AL44) -> 5540 | CB44: =SUM(AM44:AP44) -> 5663 | CC44: =SUM(AQ44:AT44) -> 5663 | CD44: =SUM(AU44:AX44) -> 5809 | CE44: =SUM(AY44:BB44) -> 5806 | CF44: =SUM(BC44:BF44) -> 6095 | CG44: =CG40*CG59 -> 6604.6423 | CH44: =CH40*CH59 -> 7793.2155 | CI44: =CI40*CI59 -> 9020.1105 | CJ44: =CJ40*CJ59 -> 9722.2229 | CK44: =CK40*CK59 -> 10247.719 | CL44: =CL40*CL59 -> 10555.669 | CM44: =CM40*CM59 -> 10698.55 | CN44: =CN40*CN59 -> 11097.522 | ... CP44: =CP40*CP59 -> 11533.557
B45: Other (Income), net | C45: -300 | D45: -340 | E45: -211 | F45: -101 | G45: -309 | H45: -421 | I45: -187 | J45: -206 | K45: -263 | L45: -384 | M45: -305 | N45: -286 | O45: -408 | P45: -181 | Q45: -219 | R45: 808 | S45: -146 | T45: -243 | U45: -211 | V45: -182 | W45: -588 | X45: -257 | Y45: -250 | Z45: -263 | AA45: -231 | AB45: -941 | AC45: -131 | AD45: 920 | AE45: -112 | AF45: -118 | AG45: -60 | AH45: -36 | AI45: -19 | AJ45: 3101 | AK45: -734 | AL45: -50 | AM45: -108 | AN45: -82 | AO45: -124 | AP45: =1000-SUM(AM45:AO45) -> 1314 | AQ45: -28 | AR45: -17 | AS45: -46 | AT45: =-120-SUM(AQ45:AS45) -> -29 | AU45: -88 | AV45: -25 | AW45: -3 | AX45: =-86-SUM(AU45:AW45) -> 30 | AY45: -372 | AZ45: 896 | BA45: -134 | BB45: =132-SUM(AY45:BA45) -> -258 | BC45: -4 | BD45: -40 | BE45: -63 | BF45: =-413-SUM(BC45:BE45) -> -306 | BG45: -64 | BH45: -62 | BI45: -161 | BS45: =SUM(C45:F45) -> -952 | BT45: =SUM(G45:J45) -> -1123 | BU45: =SUM(K45:N45) -> -1238 | BV45: =SUM(O45:R45) -> 0 | BW45: =SUM(S45:V45) -> -782 | BX45: =SUM(W45:Z45) -> -1358 | BY45: =SUM(AA45:AD45) -> -383 | BZ45: =SUM(AE45:AH45) -> -326 | CA45: =SUM(AI45:AL45) -> 2298 | CB45: =SUM(AM45:AP45) -> 1000 | CC45: =SUM(AQ45:AT45) -> -120 | CD45: =SUM(AU45:AX45) -> -86 | CE45: =SUM(AY45:BB45) -> 132 | CF45: =SUM(BC45:BF45) -> -413 | CG45: =CG40*CG60 -> -295.73025 | CH45: =CH40*CH60 -> -333.99495 | CI45: =CI40*CI60 -> -375.83794 | CJ45: =CJ40*CJ60 -> -416.66669 | CK45: =CK40*CK60 -> -455.45417 | CL45: =CL40*CL60 -> -487.1847 | CM45: =CM40*CM60 -> -513.53041 | CN45: =CN40*CN60 -> -536.97685 | ... CP45: =CP40*CP60 -> -576.67787
B46: OI | C46: =C42-SUM(C43:C45) -> 1713 | D46: =D42-SUM(D43:D45) -> 2179 | E46: =E42-SUM(E43:E45) -> 2041 | F46: =F42-SUM(F43:F45) -> 1751 | G46: =G42-SUM(G43:G45) -> 2006 | H46: =H42-SUM(H43:H45) -> 2507 | I46: =I42-SUM(I43:I45) -> 2366 | J46: =J42-SUM(J43:J45) -> 1670 | ... BI46: =BI42-SUM(BI43:BI45) -> 3337 | BS46: =SUM(C46:F46) -> 7684 | BT46: =SUM(G46:J46) -> 8549 | BU46: =SUM(K46:N46) -> 9593 | BV46: =SUM(O46:R46) -> 7291 | BW46: =SUM(S46:V46) -> 8221 | BX46: =SUM(W46:Z46) -> 8138 | BY46: =SUM(AA46:AD46) -> 2877 | BZ46: =SUM(AE46:AH46) -> 4914 | CA46: =SUM(AI46:AL46) -> 5341 | CB46: =SUM(AM46:AP46) -> 3117 | CC46: =SUM(AQ46:AT46) -> 5414 | CD46: =SUM(AU46:AX46) -> 3561 | CE46: =SUM(AY46:BB46) -> 6538 | CF46: =SUM(BC46:BF46) -> 9300 | CG46: =CG42-SUM(CG43:CG45) -> 11632.056 | CH46: =CH42-SUM(CH43:CH45) -> 12970.137 | CI46: =CI42-SUM(CI43:CI45) -> 14532.4 | CJ46: =CJ42-SUM(CJ43:CJ45) -> 16944.446 | CK46: =CK42-SUM(CK43:CK45) -> 18901.348 | CL46: =CL42-SUM(CL43:CL45) -> 20786.547 | CM46: =CM42-SUM(CM43:CM45) -> 22680.927 | CN46: =CN42-SUM(CN43:CN45) -> 24163.958 | ... CP46: =CP42-SUM(CP43:CP45) -> 26911.634
B47: Other Income | C47: -129 | D47: -168 | E47: -216 | F47: -260 | G47: -236 | H47: -217 | I47: -226 | J47: -216 | K47: -225 | L47: -206 | M47: -185 | N47: -265 | O47: -217 | P47: -217 | Q47: -184 | R47: -206 | S47: -223 | T47: -225 | U47: -225 | V47: -415 | W47: -90 | X47: -100 | Y47: -92 | Z47: -93 | AA47: -38 | AB47: -42 | AC47: -70 | AD47: -223 | AE47: -223 | AF47: -152 | AG47: -113 | AH47: -274 | AI47: -164 | AJ47: -98 | AK47: -97 | AL47: -105 | AM47: -491 | AN47: -490 | AO47: -491 | AP47: =1000-SUM(AM47:AO47) -> 2472 | AQ47: -480 | AR47: -474 | AS47: -468 | AT47: =-1889-SUM(AQ47:AS47) -> -467 | AU47: -444 | AV47: -447 | AW47: -443 | AX47: =-1780-SUM(AU47:AW47) -> -446 | AY47: -386 | AZ47: -374 | BA47: -374 | BB47: =-1518-SUM(AY47:BA47) -> -384 | BC47: -366 | BD47: -351 | BE47: -364 | BF47: =-1182-SUM(BC47:BE47) -> -101 | BG47: -355 | BH47: -348 | BI47: -345 | BS47: =SUM(C47:F47) -> -773 | BT47: =SUM(G47:J47) -> -895 | BU47: =SUM(K47:N47) -> -881 | BV47: =SUM(O47:R47) -> -824 | BW47: =SUM(S47:V47) -> -1088 | BX47: =SUM(W47:Z47) -> -375 | BY47: =SUM(AA47:AD47) -> -373 | BZ47: =SUM(AE47:AH47) -> -762 | CA47: =SUM(AI47:AL47) -> -464 | CB47: =SUM(AM47:AP47) -> 1000 | CC47: =SUM(AQ47:AT47) -> -1889 | CD47: =SUM(AU47:AX47) -> -1780 | CE47: =SUM(AY47:BB47) -> -1518 | CF47: =SUM(BC47:BF47) -> -1182 | CG47: =CF65*(-$CZ$65) -> -322.3125 | CH47: =CG65*(-$CZ$65) -> -839.2822 | CI47: =CH65*(-$CZ$65) -> -1465.2997 | CJ47: =CI65*(-$CZ$65) -> -2202.4672 | CK47: =CJ65*(-$CZ$65) -> -3096.9134 | CL47: =CK65*(-$CZ$65) -> -4135.6339 | CM47: =CL65*(-$CZ$65) -> -5320.2337 | CN47: =CM65*(-$CZ$65) -> -6656.416 | ... CP47: =CO65*(-$CZ$65) -> -9734.0722
B48: Interest Expense | C48: 0 | D48: 0 | E48: 0 | F48: 0 | G48: 0 | H48: 0 | I48: 0 | J48: 0 | K48: 0 | L48: 0 | M48: 0 | N48: 0 | O48: 0 | P48: 0 | Q48: 0 | R48: 0 | S48: 0 | T48: 0 | U48: 0 | V48: 0 | W48: 0 | X48: 0 | Y48: 0 | Z48: 0 | AA48: 0 | AB48: 0 | AC48: 0 | AD48: 0 | AE48: 0 | AF48: 0 | AG48: 0 | AH48: 0 | AI48: 0 | AJ48: 0 | AK48: 0 | AL48: 0 | AM48: 346 | AN48: 342 | AO48: 358 | AP48: =1000-SUM(AM48:AO48) -> -46 | AQ48: 318 | AR48: 329 | AS48: 311 | AT48: =1276-SUM(AQ48:AS48) -> 318 | AU48: 315 | AV48: 333 | AW48: 369 | AX48: =1505-SUM(AU48:AW48) -> 488 | AY48: 405 | AZ48: 475 | BA48: 496 | BB48: =1862-SUM(AY48:BA48) -> 486 | BC48: 443 | BD48: 457 | BE48: 449 | BF48: =1749-SUM(BC48:BE48) -> 400 | BG48: 390 | BH48: 417 | BI48: 381 | BS48: =SUM(C48:F48) -> 0 | BT48: =SUM(G48:J48) -> 0 | BU48: =SUM(K48:N48) -> 0 | BV48: =SUM(O48:R48) -> 0 | BW48: =SUM(S48:V48) -> 0 | BX48: =SUM(W48:Z48) -> 0 | BY48: =SUM(AA48:AD48) -> 0 | BZ48: =SUM(AE48:AH48) -> 0 | CA48: =SUM(AI48:AL48) -> 0 | CB48: =SUM(AM48:AP48) -> 1000 | CC48: =SUM(AQ48:AT48) -> 1276 | CD48: =SUM(AU48:AX48) -> 1505 | CE48: =SUM(AY48:BB48) -> 1862 | CF48: =SUM(BC48:BF48) -> 1749 | CG48: =CF84*$CU$82 -> 1988.688 | CH48: =CG84*$CU$82 -> 1885.2762 | CI48: =CH84*$CU$82 -> 1787.2419 | CJ48: =CI84*$CU$82 -> 1694.3053 | CK48: =CJ84*$CU$82 -> 1606.2014 | CL48: =CK84*$CU$82 -> 1522.6789 | CM48: =CL84*$CU$82 -> 1443.4996 | CN48: =CM84*$CU$82 -> 1368.4377 | ... CP48: =CO84*$CU$82 -> 1229.8204
B49: Pretax Income | C49: =C46-SUM(C47:C48) -> 1842 | D49: =D46-SUM(D47:D48) -> 2347 | E49: =E46-SUM(E47:E48) -> 2257 | F49: =F46-SUM(F47:F48) -> 2011 | G49: =G46-SUM(G47:G48) -> 2242 | H49: =H46-SUM(H47:H48) -> 2724 | I49: =I46-SUM(I47:I48) -> 2592 | J49: =J46-SUM(J47:J48) -> 1886 | ... BI49: =BI46-SUM(BI47:BI48) -> 3301 | BS49: =SUM(C49:F49) -> 8457 | BT49: =SUM(G49:J49) -> 9444 | BU49: =SUM(K49:N49) -> 10474 | BV49: =SUM(O49:R49) -> 8115 | BW49: =SUM(S49:V49) -> 9309 | BX49: =SUM(W49:Z49) -> 8513 | BY49: =SUM(AA49:AD49) -> 3250 | BZ49: =SUM(AE49:AH49) -> 5676 | CA49: =SUM(AI49:AL49) -> 5805 | CB49: =SUM(AM49:AP49) -> 1117 | CC49: =SUM(AQ49:AT49) -> 6027 | CD49: =SUM(AU49:AX49) -> 3836 | CE49: =SUM(AY49:BB49) -> 6194 | CF49: =SUM(BC49:BF49) -> 8733 | CG49: =CG46-SUM(CG47:CG48) -> 9965.681 | CH49: =CH46-SUM(CH47:CH48) -> 11924.143 | CI49: =CI46-SUM(CI47:CI48) -> 14210.458 | CJ49: =CJ46-SUM(CJ47:CJ48) -> 17452.608 | CK49: =CK46-SUM(CK47:CK48) -> 20392.06 | CL49: =CL46-SUM(CL47:CL48) -> 23399.502 | CM49: =CM46-SUM(CM47:CM48) -> 26557.661 | CN49: =CN46-SUM(CN47:CN48) -> 29451.937 | ... CP49: =CP46-SUM(CP47:CP48) -> 35415.886
B50: Taxes | C50: 320 | D50: 453 | E50: 484 | F50: 454 | G50: 418 | H50: 645 | I50: 614 | J50: 322 | K50: 567 | L50: 359 | M50: 575 | N50: 743 | O50: 530 | P50: 626 | Q50: 592 | R50: 363 | S50: 469 | T50: 587 | U50: 492 | V50: 149 | W50: 586 | X50: 532 | Y50: 506 | Z50: 1219 | AA50: 522 | AB50: 695 | AC50: 419 | AD50: -538 | AE50: 397 | AF50: 6 | AG50: 306 | AH50: -288 | AI50: 639 | AJ50: -38 | AK50: 152 | AL50: -178 | AM50: 345 | AN50: 342 | AO50: 3 | AP50: =1000-SUM(AM50:AO50) -> 310 | AQ50: 116 | AR50: 160 | AS50: 282 | AT50: =700-SUM(AQ50:AS50) -> 142 | AU50: 335 | AV50: 248 | AW50: -389 | AX50: =456-SUM(AU50:AW50) -> 262 | AY50: 108 | AZ50: 253 | BA50: 371 | BB50: =1181-SUM(AY50:BA50) -> 449 | BC50: 333 | BD50: 315 | BE50: 432 | BF50: =1664-SUM(BC50:BE50) -> 584 | BG50: 363 | BH50: 493 | BI50: 593 | BS50: =SUM(C50:F50) -> 1711 | BT50: =SUM(G50:J50) -> 1999 | BU50: =SUM(K50:N50) -> 2244 | BV50: =SUM(O50:R50) -> 2111 | BW50: =SUM(S50:V50) -> 1697 | BX50: =SUM(W50:Z50) -> 2843 | BY50: =SUM(AA50:AD50) -> 1098 | BZ50: =SUM(AE50:AH50) -> 421 | CA50: =SUM(AI50:AL50) -> 575 | CB50: =SUM(AM50:AP50) -> 1000 | CC50: =SUM(AQ50:AT50) -> 700 | CD50: =SUM(AU50:AX50) -> 456 | CE50: =SUM(AY50:BB50) -> 1181 | CF50: =SUM(BC50:BF50) -> 1664 | CG50: =CG49*CG62 -> 1694.1658 | CH50: =CH49*CH62 -> 1907.8629 | CI50: =CI49*CI62 -> 2415.7779 | CJ50: =CJ49*CJ62 -> 3141.4694 | CK50: =CK49*CK62 -> 3772.5311 | CL50: =CL49*CL62 -> 4445.9054 | CM50: =CM49*CM62 -> 5178.7438 | CN50: =CN49*CN62 -> 5890.3873 | ... CP50: =CP49*CP62 -> 7791.4949
B51: Net Income | C51: =C49-C50 -> 1522 | D51: =D49-D50 -> 1894 | E51: =E49-E50 -> 1773 | F51: =F49-F50 -> 1557 | G51: =G49-G50 -> 1824 | H51: =H49-H50 -> 2079 | I51: =I49-I50 -> 1978 | J51: =J49-J50 -> 1564 | ... BI51: =BI49-BI50 -> 2708 | BS51: =SUM(C51:F51) -> 6746 | BT51: =SUM(G51:J51) -> 7445 | BU51: =SUM(K51:N51) -> 8230 | BV51: =SUM(O51:R51) -> 6004 | BW51: =SUM(S51:V51) -> 7612 | BX51: =SUM(W51:Z51) -> 5670 | BY51: =SUM(AA51:AD51) -> 2152 | BZ51: =SUM(AE51:AH51) -> 5255 | CA51: =SUM(AI51:AL51) -> 5230 | CB51: =SUM(AM51:AP51) -> 117 | CC51: =SUM(AQ51:AT51) -> 5327 | CD51: =SUM(AU51:AX51) -> 3380 | CE51: =SUM(AY51:BB51) -> 5013 | CF51: =SUM(BC51:BF51) -> 7069 | CG51: =CG49-CG50 -> 8271.5152 | CH51: =CH49-CH50 -> 10016.28 | CI51: =CI49-CI50 -> 11794.68 | CJ51: =CJ49-CJ50 -> 14311.138 | CK51: =CK49-CK50 -> 16619.529 | CL51: =CL49-CL50 -> 18953.597 | CM51: =CM49-CM50 -> 21378.917 | CN51: =CN49-CN50 -> 23561.549 | ... CP51: =CP49-CP50 -> 27624.391 | CQ51: =CP51*(1+$CZ$66) -> 27762.513 | CR51: =CQ51*(1+$CZ$66) -> 27901.325 | CS51: =CR51*(1+$CZ$66) -> 28040.832 | CT51: =CS51*(1+$CZ$66) -> 28181.036 | CU51: =CT51*(1+$CZ$66) -> 28321.941 | CV51: =CU51*(1+$CZ$66) -> 28463.551 | CW51: =CV51*(1+$CZ$66) -> 28605.869 | CX51: =CW51*(1+$CZ$66) -> 28748.898 | ... EN51: =EM51*(1+$CZ$66) -> 35448.332
B52: Non-controlling Interest | C52: 0 | D52: 0 | E52: 0 | F52: 0 | G52: 0 | H52: 0 | I52: 0 | J52: 0 | K52: 0 | L52: 0 | M52: 0 | N52: 0 | O52: 0 | P52: 0 | Q52: 0 | R52: 0 | S52: 0 | T52: 0 | U52: 0 | V52: 0 | W52: 0 | X52: 0 | Y52: 0 | Z52: 0 | AA52: 0 | AB52: 0 | AC52: 0 | AD52: 0 | AE52: 0 | AF52: 0 | AG52: 0 | AH52: 0 | AI52: 0 | AJ52: 0 | AK52: 0 | AL52: 0 | AM52: 41 | AN52: 48 | AO52: 73 | AP52: =1000-SUM(AM52:AO52) -> 838 | AQ52: 23 | AR52: 34 | AS52: 8 | AT52: =111-SUM(AQ52:AS52) -> 46 | AU52: 55 | AV52: 32 | AW52: 51 | AX52: =185-SUM(AU52:AW52) -> 47 | AY52: 34 | AZ52: 64 | BA52: 63 | BB52: =239-SUM(AY52:BA52) -> 78 | BC52: 90 | BD52: 68 | BE52: 88 | BF52: =337-SUM(BC52:BE52) -> 91 | BG52: 98 | BH52: 110 | BI52: 125 | BS52: =SUM(C52:F52) -> 0 | BT52: =SUM(G52:J52) -> 0 | BU52: =SUM(K52:N52) -> 0 | BV52: =SUM(O52:R52) -> 0 | BW52: =SUM(S52:V52) -> 0 | BX52: =SUM(W52:Z52) -> 0 | BY52: =SUM(AA52:AD52) -> 0 | BZ52: =SUM(AE52:AH52) -> 0 | CA52: =SUM(AI52:AL52) -> 0 | CB52: =SUM(AM52:AP52) -> 1000 | CC52: =SUM(AQ52:AT52) -> 111 | CD52: =SUM(AU52:AX52) -> 185 | CE52: =SUM(AY52:BB52) -> 239 | CF52: =SUM(BC52:BF52) -> 337
B53: Net Income to RTX | C53: =C51-C52 -> 1522 | D53: =D51-D52 -> 1894 | E53: =E51-E52 -> 1773 | F53: =F51-F52 -> 1557 | G53: =G51-G52 -> 1824 | H53: =H51-H52 -> 2079 | I53: =I51-I52 -> 1978 | J53: =J51-J52 -> 1564 | ... BI53: =BI51-BI52 -> 2583 | BS53: =SUM(C53:F53) -> 6746 | BT53: =SUM(G53:J53) -> 7445 | BU53: =SUM(K53:N53) -> 8230 | BV53: =SUM(O53:R53) -> 6004 | BW53: =SUM(S53:V53) -> 7612 | BX53: =SUM(W53:Z53) -> 5670 | BY53: =SUM(AA53:AD53) -> 2152 | BZ53: =SUM(AE53:AH53) -> 5255 | CA53: =SUM(AI53:AL53) -> 5230 | CB53: =SUM(AM53:AP53) -> -883 | CC53: =SUM(AQ53:AT53) -> 5216 | CD53: =SUM(AU53:AX53) -> 3195 | CE53: =SUM(AY53:BB53) -> 4774 | CF53: =SUM(BC53:BF53) -> 6732
B54: SC | C54: 891 | D54: 893 | E54: 896 | F54: 895 | G54: 901 | H54: 901 | I54: 901 | J54: 901 | K54: 901 | L54: 900 | M54: 900 | N54: 898 | O54: 890 | P54: 877 | Q54: 876 | R54: 873 | S54: 825 | T54: 825 | U54: 822 | V54: 818 | W54: 794 | X54: 789 | Y54: 788 | Z54: 790 | AA54: 790 | AB54: 791 | AC54: 791 | AD54: 800 | AE54: 853 | AF54: 854 | AG54: 855 | AH54: 855 | AI54: 858 | AJ54: 1504 | AK54: 1509 | AL54: 1511 | AM54: 1507 | AN54: 1505 | AO54: 1497 | AP54: 1492 | AQ54: 1488 | AR54: 1476 | AS54: 1470 | AT54: 1468 | AU54: 1463 | AV54: 1462 | AW54: 1448 | AX54: 1347 | AY54: 1326 | AZ54: 1327 | BA54: 1330 | BB54: 1332 | BC54: 1335 | BD54: 1336 | BE54: 1342 | BF54: 1342 | BG54: 1349 | BH54: 1347.8 | BI54: 1352.2 | BS54: =AVERAGE(C54:F54) -> 893.75 | BT54: =AVERAGE(G54:J54) -> 901 | BU54: =AVERAGE(K54:N54) -> 899.75 | BV54: =AVERAGE(O54:R54) -> 879 | BW54: =AVERAGE(S54:V54) -> 822.5 | BX54: =AVERAGE(W54:Z54) -> 790.25 | BY54: =AVERAGE(AA54:AD54) -> 793 | BZ54: =AVERAGE(AE54:AH54) -> 854.25 | CA54: =AVERAGE(AI54:AL54) -> 1345.5 | CB54: =AVERAGE(AM54:AP54) -> 1500.25 | CC54: =AVERAGE(AQ54:AT54) -> 1475.5 | CD54: =AVERAGE(AU54:AX54) -> 1430 | CE54: =AVERAGE(AY54:BB54) -> 1328.75 | CF54: =AVERAGE(BC54:BF54) -> 1338.75
B55: EPS | C55: =C53/C54 -> 1.708193 | D55: =D53/D54 -> 2.1209406 | E55: =E53/E54 -> 1.9787946 | F55: =F53/F54 -> 1.7396648 | G55: =G53/G54 -> 2.0244173 | H55: =H53/H54 -> 2.3074362 | I55: =I53/I54 -> 2.1953385 | J55: =J53/J54 -> 1.7358491 | ... BI55: =BI53/BI54 -> 1.9102204 | BS55: =SUM(C55:F55) -> 7.5475931 | BT55: =SUM(G55:J55) -> 8.2630411 | BU55: =SUM(K55:N55) -> 9.147352 | BV55: =SUM(O55:R55) -> 6.8186304 | BW55: =SUM(S55:V55) -> 9.2557117 | BX55: =SUM(W55:Z55) -> 7.1746829 | BY55: =SUM(AA55:AD55) -> 2.765642 | BZ55: =SUM(AE55:AH55) -> 6.1534278 | CA55: =SUM(AI55:AL55) -> 7.3144043 | CB55: =SUM(AM55:AP55) -> -0.60612838 | CC55: =SUM(AQ55:AT55) -> 3.5369345 | CD55: =SUM(AU55:AX55) -> 2.2614611 | CE55: =SUM(AY55:BB55) -> 3.5918655 | CF55: =SUM(BC55:BF55) -> 5.0279361
B57: Gross Profit Margin | C57: =C42/C40 -> 0.28076675 | D57: =D42/D40 -> 0.28050989 | E57: =E42/E40 -> 0.26851483 | F57: =F42/F40 -> 0.25281275 | G57: =G42/G40 -> 0.27321342 | H57: =H42/H40 -> 0.27827065 | I57: =I42/I40 -> 0.28728496 | J57: =J42/J40 -> 0.30764931 | ... BI57: =BI42/BI40 -> 0.23252554 | BS57: =BS42/BS40 -> 0.26954668 | BT57: =BT42/BT40 -> 0.28501767 | BU57: =BU42/BU40 -> 0.29364421 | BV57: =BV42/BV40 -> 0.27927912 | BW57: =BW42/BW40 -> 0.27553979 | BX57: =BX42/BX40 -> 0.26130989 | BY57: =BY42/BY40 -> 0.20852425 | BZ57: =BZ42/BZ40 -> 0.23707248 | ... CF57: =CF42/CF40 -> 0.20077198 | CG57: 0.21 | CH57: 0.2125 | CI57: 0.215 | CJ57: 0.22 | CK57: 0.221 | CL57: 0.222 | CM57: 0.223 | CN57: 0.224 | CO57: 0.225 | CP57: 0.225
B58: R&D as % of Revenue | C58: =C43/C40 -> 0.043814433 | D58: =D43/D40 -> 0.038024191 | E58: =E43/E40 -> 0.039223508 | F58: =F43/F40 -> 0.043301101 | G58: =G43/G40 -> 0.042364053 | H58: =H43/H40 -> 0.039422716 | I58: =I43/I40 -> 0.040745052 | J58: =J43/J40 -> 0.04388335 | ... BI58: =BI43/BI40 -> 0.028479872 | BS58: =BS43/BS40 -> 0.041086158 | BT58: =BT43/BT40 -> 0.041378092 | BU58: =BU43/BU40 -> 0.042746114 | BV58: =BV43/BV40 -> 0.040625334 | BW58: =BW43/BW40 -> 0.041506533 | BX58: =BX43/BX40 -> 0.040560189 | BY58: =BY43/BY40 -> 0.054119478 | BZ58: =BZ43/BZ40 -> 0.054069549 | ... CF58: =CF43/CF40 -> 0.031680643 | CG58: 0.028 | CH58: 0.029 | CI58: 0.03 | CJ58: 0.031 | CK58: 0.032 | CL58: 0.032 | CM58: 0.031 | CN58: 0.03 | CO58: 0.029 | CP58: 0.028
B59: SG&A as % of Revenue | C59: =C44/C40 -> 0.12314755 | D59: =D44/D40 -> 0.10929239 | E59: =E44/E40 -> 0.10763196 | F59: =F44/F40 -> 0.10916499 | G59: =G44/G40 -> 0.11299396 | H59: =H44/H40 -> 0.1085218 | I59: =I44/I40 -> 0.10561376 | J59: =J44/J40 -> 0.1273642 | ... BI59: =BI44/BI40 -> 0.076827559 | BS59: =BS44/BS40 -> 0.11180426 | BT59: =BT44/BT40 -> 0.11243816 | BU59: =BU44/BU40 -> 0.10659758 | BV59: =BV44/BV40 -> 0.1086848 | BW59: =BW44/BW40 -> 0.10408078 | BX59: =BX44/BX40 -> 0.10744188 | BY59: =BY44/BY40 -> 0.082533645 | BZ59: =BZ44/BZ40 -> 0.081832014 | ... CF59: =CF44/CF40 -> 0.068789996 | CG59: 0.067 | CH59: 0.07 | CI59: 0.072 | CJ59: 0.07 | CK59: 0.0675 | CL59: 0.065 | CM59: 0.0625 | CN59: 0.062 | CO59: 0.061 | CP59: 0.06
B60: Other as % of Revenue | C60: =C45/C40 -> -0.024162371 | D60: =D45/D40 -> -0.02462519 | E60: =E45/E40 -> -0.01402739 | F60: =F45/F40 -> -0.0061424314 | G60: =G45/G40 -> -0.021459824 | H60: =H45/H40 -> -0.026302637 | I60: =I45/I40 -> -0.012094166 | J60: =J45/J40 -> -0.019193143 | ... BI60: =BI45/BI40 -> -0.0064490286 | BS60: =BS45/BS40 -> -0.016496846 | BT60: =BT45/BT40 -> -0.019840989 | BU60: =BU45/BU40 -> -0.021381693 | BV60: =BV45/BV40 -> 0 | BW60: =BW45/BW40 -> -0.01366082 | BX60: =BX45/BX40 -> -0.022694988 | BY60: =BY45/BY40 -> -0.011037146 | BZ60: =BZ45/BZ40 -> -0.0071886921 | ... CF60: =CF45/CF40 -> -0.0046612417 | CG60: -0.003 | CH60: -0.003 | CI60: -0.003 | CJ60: -0.003 | CK60: -0.003 | CL60: -0.003 | CM60: -0.003 | CN60: -0.003 | CO60: -0.003 | CP60: -0.003
B61: Operating Margin | C61: =C46/C40 -> 0.13796714 | D61: =D46/D40 -> 0.1578185 | E61: =E46/E40 -> 0.13568674 | F61: =F46/F40 -> 0.10648908 | G61: =G46/G40 -> 0.13931523 | H61: =H46/H40 -> 0.15662876 | I61: =I46/I40 -> 0.15302031 | J61: =J46/J40 -> 0.15559489 | ... BI61: =BI46/BI40 -> 0.13366713 | BS61: =BS46/BS40 -> 0.13315312 | BT61: =BT46/BT40 -> 0.1510424 | BU61: =BU46/BU40 -> 0.16568221 | BV61: =BV46/BV40 -> 0.12996898 | BW61: =BW46/BW40 -> 0.1436133 | BX61: =BX46/BX40 -> 0.13600281 | BY61: =BY46/BY40 -> 0.082908274 | BZ61: =BZ46/BZ40 -> 0.10835961 | ... CP61: =CP46/CP40 -> 0.14
B62: Effective Tax Rate | C62: =C50/C49 -> 0.17372421 | D62: =D50/D49 -> 0.19301236 | E62: =E50/E49 -> 0.21444395 | F62: =F50/F49 -> 0.22575833 | G62: =G50/G49 -> 0.18644068 | H62: =H50/H49 -> 0.23678414 | I62: =I50/I49 -> 0.23688272 | J62: =J50/J49 -> 0.17073171 | ... BI62: =BI50/BI49 -> 0.17964253 | BS62: =BS50/BS49 -> 0.20231761 | BT62: =BT50/BT49 -> 0.21166878 | BU62: =BU50/BU49 -> 0.2142448 | BV62: =BV50/BV49 -> 0.26013555 | BW62: =BW50/BW49 -> 0.1822967 | BX62: =BX50/BX49 -> 0.33395983 | BY62: =BY50/BY49 -> 0.33784615 | BZ62: =BZ50/BZ49 -> 0.074171952 | ... CF62: =CF50/CF49 -> 0.19054162 | CG62: 0.17 | CH62: 0.16 | CI62: 0.17 | CJ62: 0.18 | CK62: 0.185 | CL62: 0.19 | CM62: 0.195 | CN62: 0.2 | CO62: 0.21 | CP62: 0.22
B63: Net Profit Margin | C63: =C51/C40 -> 0.12258376 | D63: =D51/D40 -> 0.13717679 | E63: =E51/E40 -> 0.11786996 | F63: =F51/F40 -> 0.09469075 | G63: =G51/G40 -> 0.12667546 | H63: =H51/H40 -> 0.12988879 | I63: =I51/I40 -> 0.12792653 | J63: =J51/J40 -> 0.14571881 | ... BI63: =BI51/BI40 -> 0.10847186 | BS63: =BS51/BS40 -> 0.11689887 | BT63: =BT51/BT40 -> 0.1315371 | BU63: =BU51/BU40 -> 0.14214162 | BV63: =BV51/BV40 -> 0.10702699 | BW63: =BW51/BW40 -> 0.13297463 | BX63: =BX51/BX40 -> 0.094757424 | BY63: =BY51/BY40 -> 0.062015504 | BZ63: =BZ51/BZ40 -> 0.11587907 | ... CP63: =CP51/CP40 -> 0.14370791
B65: Cash & CEs | AX65: 6587 | AY65: 5607 | AZ65: 6011 | BA65: 6682 | BB65: 5578 | BC65: 5157 | BD65: 4782 | BE65: 5966 | BF65: 7435 | BG65: 6818 | BH65: 8305 | BI65: 9173 | CD65: =AX65 -> 6587 | CE65: =BB65 -> 5578 | CF65: =BC65 -> 5157 | CG65: =CF65+CG51 -> 13428.515 | CH65: =CG65+CH51 -> 23444.796 | CI65: =CH65+CI51 -> 35239.476 | CJ65: =CI65+CJ51 -> 49550.614 | CK65: =CJ65+CK51 -> 66170.143 | CL65: =CK65+CL51 -> 85123.74 | CM65: =CL65+CM51 -> 106502.66 | CN65: =CM65+CN51 -> 130064.21 | ... CP65: =CO65+CP51 -> 183369.55 | CR65: Invested Capital | CU65: Avg. (2024-2025) | CW65: Projected ROIC: | CY65: ROIC | CZ65: 0.0625
B66: A/R | AX66: 10838 | AY66: 10280 | AZ66: 10252 | BA66: 10097 | BB66: 10976 | BC66: 11426 | BD66: 12385 | BE66: 12837 | BF66: 14701 | BG66: 12945 | BH66: 13942 | BI66: 14681 | CD66: =AX66 -> 10838 | CE66: =BB66 -> 10976 | CF66: =BC66 -> 11426 | CR66: 2024 | CS66: 2025 | CU66: 2024-2025 | CW66: 2025 | CY66: Terminal | CZ66: 0.005
B67: Contract Assets | AX67: 12139 | AY67: 13104 | AZ67: 13581 | BA67: 14684 | BB67: 14570 | BC67: 15241 | BD67: 15686 | BE67: 16604 | BF67: 17092 | BG67: 18070 | BH67: 18980 | BI67: 18701 | CD67: =AX67 -> 12139 | CE67: =BB67 -> 14570 | CF67: =BC67 -> 15241 | CR67: =SUM(CE65:CE69)-SUM(CE79)+CE71+CE74+CE73 -> 140557 | CS67: =SUM(CF65:CF69)-SUM(CF79)+CF71+CF74+CF73 -> 141768 | CU67: =AVERAGE(CR67:CS67) -> 141162.5 | CW67: =CG46*(1-CG62) -> 9654.6069 | CY67: RFR (10-year yield) | CZ67: 0.0499
B68: Inventories | AX68: 11777 | AY68: 12386 | AZ68: 13047 | BA68: 13465 | BB68: 12768 | BC68: 13618 | BD68: 14012 | BE68: 13806 | BF68: 13364 | BG68: 14153 | BH68: 14409 | BI68: 14953 | CD68: =AX68 -> 11777 | CE68: =BB68 -> 12768 | CF68: =BC68 -> 13618 | CW68: =CW67/CU67 -> 0.068393567 | CY68: ERP (Avg. market return - (less) RFR) | CZ68: =9.25%-CZ67 -> 0.0426
B69: Other ST Assets | AX69: 7076 | AY69: 6646 | AZ69: 6334 | BA69: 6836 | BB69: 7241 | BC69: 7474 | BD69: 7792 | BE69: 7905 | BF69: 7740 | BG69: 8023 | BH69: 8276 | BI69: 8561 | CD69: =AX69 -> 7076 | CE69: =BB69 -> 7241 | CF69: =BC69 -> 7474 | CR69: Capital Structure | CY69: Equity β (1-year avg.) | CZ69: ='Notes | Quant Analysis'!S244 -> 0.48869047
B70: LT Customer Financing Assets | AX70: 2392 | AY70: 2359 | AZ70: 2320 | BA70: 2306 | BB70: 2246 | BC70: 2135 | BD70: 2104 | BE70: 2071 | BF70: 2132 | BG70: 2041 | BH70: 1902 | BI70: 1880 | CD70: =AX70 -> 2392 | CE70: =BB70 -> 2246 | CF70: =BC70 -> 2135 | CR70: Mkt Cap | CU70: =Main!C5 -> 259079.52 | CY70: Discount (Cost of Equity) | CZ70: =+CZ67+(CZ68*CZ69) -> 0.070718214
B71: PP&E, net | AX71: 15748 | AY71: 15638 | AZ71: 15693 | BA71: 15886 | BB71: 16089 | BC71: 16135 | BD71: 16205 | BE71: 16325 | BF71: 16868 | BG71: 16842 | BH71: 16965 | BI71: 17235 | CD71: =AX71 -> 15748 | CE71: =BB71 -> 16089 | CF71: =BC71 -> 16135 | CR71: Debt to Ttl Mkt Cap | CU71: =Main!C7/(Main!C7+CU70) -> 0.12608509
B72: LT Operating Lease Assets | AX72: 1638 | AY72: 1639 | AZ72: 1664 | BA72: 1846 | BB72: 1864 | BC72: 1899 | BD72: 1869 | BE72: 1899 | BF72: 1887 | BG72: 1773 | BH72: 1727 | BI72: 1770 | CD72: =AX72 -> 1638 | CE72: =BB72 -> 1864 | CF72: =BC72 -> 1899 | CR72: Mkt Equity to Ttl Mkt Cap | CU72: =CU70/(CU70+Main!C7) -> 0.87391491 | CY72: NPV | CZ72: =NPV(CZ70,CG51:EO51) -> 320401.37
B73: Goodwill | AX73: 53699 | AY73: 53644 | AZ73: 53347 | BA73: 53759 | BB73: 52789 | BC73: 53045 | BD73: 53327 | BE73: 53311 | BF73: 53343 | BG73: 53276 | BH73: 52928 | BI73: 52969 | CD73: =AX73 -> 53699 | CE73: =BB73 -> 52789 | CF73: =BC73 -> 53045 | CR73: LT Debt / Equity | CU73: =CF84/CF89 -> 0.60375095 | CY73: SC | CZ73: =Main!C4 -> 1347.758
B74: Intangibles | AX74: 35399 | AY74: 34960 | AZ74: 34503 | BA74: 34159 | BB74: 33443 | BC74: 33116 | BD74: 32748 | BE74: 32260 | BF74: 31845 | BG74: 31482 | BH74: 31043 | BI74: 30652 | CD74: =AX74 -> 35399 | CE74: =BB74 -> 33443 | CF74: =BC74 -> 33116 | CY74: FV | CZ74: =CZ72/CZ73 -> 237.72915
B75: Other LT Assets | AX75: 4576 | AY75: 3924 | AZ75: 4417 | BA75: 5102 | BB75: 5297 | BC75: 5618 | BD75: 6229 | BE75: 5688 | BF75: 4672 | BG75: 5008 | BH75: 5495 | BI75: 6021 | CD75: =AX75 -> 4576 | CE75: =BB75 -> 5297 | CF75: =BC75 -> 5618 | CR75: Cost of Equity | CY75: CP | CZ75: =Main!C3 -> 192.23
B76: Ttl Assets | AX76: =SUM(AX65:AX75) -> 161869 | AY76: =SUM(AY65:AY75) -> 160187 | AZ76: =SUM(AZ65:AZ75) -> 161169 | BA76: =SUM(BA65:BA75) -> 164822 | BB76: =SUM(BB65:BB75) -> 162861 | BC76: =SUM(BC65:BC75) -> 164864 | BD76: =SUM(BD65:BD75) -> 167139 | BE76: =SUM(BE65:BE75) -> 168672 | ... BI76: =SUM(BI65:BI75) -> 176596 | CD76: =AX76 -> 161869 | CE76: =BB76 -> 162861 | CF76: =BC76 -> 164864 | CR76: RFR (10-year yield) | CU76: 0.0517 | CY76: Change Δ | CZ76: =CZ74/CZ75-1 -> 0.23669123 | DA76: =IF(CZ76>0,"Upside","Downside") -> Upside
CR77: Equity β (1-year avg.) | CU77: ='Notes | Quant Analysis'!S244 -> 0.48869047 | CY77: {=_xlfn.IFS(CZ76>=25%,"Strong Buy",CZ76>=10.00001%,"Buy",AND(CZ76<=10%,CZ76>=-4.9999%),"Hold",AND(CZ76<=-5%,CZ76>=-14.999999%),"Sell",CZ76<=-15%,"Strong Sell")} -> Buy
B78: ST Debt | AX78: 189 | AY78: 166 | AZ78: 231 | BA78: 220 | BB78: 183 | BC78: 212 | BD78: 1635 | BE78: 215 | BF78: 204 | BG78: 226 | BH78: 229 | BI78: 210 | CD78: =AX78 -> 189 | CE78: =BB78 -> 183 | CF78: =BC78 -> 212 | CR78: Market Return(1-year avg.) | CU78: 0.17
B79: A/P | AX79: 10698 | AY79: 10522 | AZ79: 10939 | BA79: 11834 | BB79: 12897 | BC79: 13444 | BD79: 13433 | BE79: 14552 | BF79: 15895 | BG79: 15979 | BH79: 16998 | BI79: 17803 | CD79: =AX79 -> 10698 | CE79: =BB79 -> 12897 | CF79: =BC79 -> 13444 | CR79: Cost of Equity | CU79: =(CU76+CU77)*(CU78-CU76) -> 0.063928193
B80: ST Employee Comp | AX80: 2491 | AY80: 1862 | AZ80: 2065 | BA80: 2673 | BB80: 2620 | BC80: 1867 | BD80: 2133 | BE80: 2937 | BF80: 3308 | BG80: 2004 | BH80: 2356 | BI80: 3155 | CD80: =AX80 -> 2491 | CE80: =BB80 -> 2620 | CF80: =BC80 -> 1867
B81: Other ST Liabilities | AX81: 14917 | AY81: 15006 | AZ81: 17048 | BA81: 15971 | BB81: 14831 | BC81: 15219 | BD81: 15861 | BE81: 14835 | BF81: 14350 | BG81: 14217 | BH81: 15695 | BI81: 14801 | CD81: =AX81 -> 14917 | CE81: =BB81 -> 14831 | CF81: =BC81 -> 15219 | CR81: Cost of Debt
B82: Contract Liabilities | AX82: 17183 | AY82: 17119 | AZ82: 17665 | BA82: 18436 | BB82: 18616 | BC82: 19038 | BD82: 19186 | BE82: 20111 | BF82: 21615 | BG82: 21940 | BH82: 22671 | BI82: 21550 | CD82: =AX82 -> 17183 | CE82: =BB82 -> 18616 | CF82: =BC82 -> 19038 | CR82: Cost of Debt | CU82: 0.052
B83: Current Portion of LT Debt | AX83: 1283 | AY83: 344 | AZ83: 1617 | BA83: 3113 | BB83: 2352 | BC83: 2844 | BD83: 2084 | BE83: 584 | BF83: 3412 | BG83: 4213 | BH83: 5296 | BI83: 5679 | CD83: =AX83 -> 1283 | CE83: =BB83 -> 2352 | CF83: =BC83 -> 2844 | CR83: Tax Rate | CU83: 0.17
B84: LT Debt | AX84: 42355 | AY84: 42334 | AZ84: 40303 | BA84: 38823 | BB84: 38726 | BC84: 38244 | BD84: 38259 | BE84: 38260 | BF84: 34288 | BG84: 32974 | BH84: 31858 | BI84: 31490 | CD84: =AX84 -> 42355 | CE84: =BB84 -> 38726 | CF84: =BC84 -> 38244 | CG84: =CF84-CG48 -> 36255.312 | CH84: =CG84-CH48 -> 34370.036 | CI84: =CH84-CI48 -> 32582.794 | CJ84: =CI84-CJ48 -> 30888.489 | CK84: =CJ84-CK48 -> 29282.287 | CL84: =CK84-CL48 -> 27759.608 | CM84: =CL84-CM48 -> 26316.109 | CN84: =CM84-CN48 -> 24947.671 | ... CP84: =CO84-CP48 -> 22420.572 | CR84: After Tax Cost of Debt | CU84: =CU82*(1-CU83) -> 0.04316
B85: LT Operating Lease Liabilities | AX85: 1412 | AY85: 1410 | AZ85: 1415 | BA85: 1592 | BB85: 1632 | BC85: 1646 | BD85: 1617 | BE85: 1650 | BF85: 1602 | BG85: 1522 | BH85: 1473 | BI85: 1495 | CD85: =AX85 -> 1412 | CE85: =BB85 -> 1632 | CF85: =BC85 -> 1646
B86: LT Employee Comp Liabilities | AX86: 2385 | AY86: 2320 | AZ86: 2264 | BA86: 2230 | BB86: 2104 | BC86: 2060 | BD86: 2038 | BE86: 1981 | BF86: 2067 | BG86: 2015 | BH86: 1956 | BI86: 1913 | CD86: =AX86 -> 2385 | CE86: =BB86 -> 2104 | CF86: =BC86 -> 2060 | CR86: WACC | CU86: =(CU72*CU79)+(CU71*CU84*(1-CU83)) -> 0.060384522
B87: Other LT Liabilities | AX87: 7511 | AY87: 6967 | AZ87: 6941 | BA87: 7071 | BB87: 6942 | BC87: 6946 | BD87: 6646 | BE87: 7154 | BF87: 7200 | BG87: 7307 | BH87: 7296 | BI87: 7508 | CD87: =AX87 -> 7511 | CE87: =BB87 -> 6942 | CF87: =BC87 -> 6946
B88: Ttl Liabilities | AX88: =SUM(AX78:AX87) -> 100424 | AY88: =SUM(AY78:AY87) -> 98050 | AZ88: =SUM(AZ78:AZ87) -> 100488 | BA88: =SUM(BA78:BA87) -> 101963 | BB88: =SUM(BB78:BB87) -> 100903 | BC88: =SUM(BC78:BC87) -> 101520 | BD88: =SUM(BD78:BD87) -> 102892 | BE88: =SUM(BE78:BE87) -> 102279 | ... BI88: =SUM(BI78:BI87) -> 105604 | CD88: =AX88 -> 100424 | CE88: =BB88 -> 100903 | CF88: =BC88 -> 101520
B89: Ttl SE | AX89: =35+61410 -> 61445 | AY89: =37+62100 -> 62137 | AZ89: =31+60650 -> 60681 | BA89: =33+62826 -> 62859 | BB89: =35+61923 -> 61958 | BC89: =37+63307 -> 63344 | BD89: =41+64206 -> 64247 | BE89: =34+66359 -> 66393 | BF89: =36+67102 -> 67138 | BG89: =67997+37 -> 68034 | BH89: =28+68116 -> 68144 | BI89: 70992 | CD89: =AX89 -> 61445 | CE89: =BB89 -> 61958 | CF89: =BC89 -> 63344
B90: Ttl L + SE | AX90: =AX88+AX89 -> 161869 | AY90: =AY88+AY89 -> 160187 | AZ90: =AZ88+AZ89 -> 161169 | BA90: =BA88+BA89 -> 164822 | BB90: =BB88+BB89 -> 162861 | BC90: =BC88+BC89 -> 164864 | BD90: =BD88+BD89 -> 167139 | BE90: =BE88+BE89 -> 168672 | ... BI90: =BI88+BI89 -> 176596 | CD90: =AX90 -> 161869 | CE90: =BB90 -> 162861 | CF90: =BC90 -> 164864
B92: Current Ratio | AX92: =SUM(AX65:AX69)/SUM(AX78:AX83) -> 1.0354141 | AY92: =SUM(AY65:AY69)/SUM(AY78:AY83) -> 1.0667274 | AZ92: =SUM(AZ65:AZ69)/SUM(AZ78:AZ83) -> 0.99314032 | BA92: =SUM(BA65:BA69)/SUM(BA78:BA83) -> 0.99075545 | BB92: =SUM(BB65:BB69)/SUM(BB78:BB83) -> 0.99289307 | BC92: =SUM(BC65:BC69)/SUM(BC78:BC83) -> 1.0055488 | BD92: =SUM(BD65:BD69)/SUM(BD78:BD83) -> 1.0059817 | BE92: =SUM(BE65:BE69)/SUM(BE78:BE83) -> 1.0729609 | ... BI92: =SUM(BI65:BI69)/SUM(BI78:BI83) -> 1.0454287 | CD92: =SUM(CD65:CD69)/SUM(CD78:CD83) -> 1.0354141 | CE92: =SUM(CE65:CE69)/SUM(CE78:CE83) -> 0.99289307 | CF92: =SUM(CF65:CF69)/SUM(CF78:CF83) -> 1.0055488
B93: Quick Ratio | AX93: =(SUM(AX65:AX69)-AX68)/SUM(AX78:AX83) -> 0.78355895 | AY93: =(SUM(AY65:AY69)-AY68)/SUM(AY78:AY83) -> 0.7915991 | AZ93: =(SUM(AZ65:AZ69)-AZ68)/SUM(AZ78:AZ83) -> 0.72991022 | BA93: =(SUM(BA65:BA69)-BA68)/SUM(BA78:BA83) -> 0.7330373 | BB93: =(SUM(BB65:BB69)-BB68)/SUM(BB78:BB83) -> 0.74496592 | BC93: =(SUM(BC65:BC69)-BC68)/SUM(BC78:BC83) -> 0.74676953 | BD93: =(SUM(BD65:BD69)-BD68)/SUM(BD78:BD83) -> 0.74808584 | BE93: =(SUM(BE65:BE69)-BE68)/SUM(BE78:BE83) -> 0.81361536 | ... BI93: =(SUM(BI65:BI69)-BI68)/SUM(BI78:BI83) -> 0.80882306 | CD93: =(SUM(CD65:CD69)-CD68)/SUM(CD78:CD83) -> 0.78355895 | CE93: =(SUM(CE65:CE69)-CE68)/SUM(CE78:CE83) -> 0.74496592 | CF93: =(SUM(CF65:CF69)-CF68)/SUM(CF78:CF83) -> 0.74676953
B94: Cash Ratio | AX94: =SUM(AX65)/SUM(AX78:AX83) -> 0.14086525 | AY94: =SUM(AY65)/SUM(AY78:AY83) -> 0.12454741 | AZ94: =SUM(AZ65)/SUM(AZ78:AZ83) -> 0.12127509 | BA94: =SUM(BA65)/SUM(BA78:BA83) -> 0.12789251 | BB94: =SUM(BB65)/SUM(BB78:BB83) -> 0.10831278 | BC94: =SUM(BC65)/SUM(BC78:BC83) -> 0.097997112 | BD94: =SUM(BD65)/SUM(BD78:BD83) -> 0.08801443 | BE94: =SUM(BE65)/SUM(BE78:BE83) -> 0.11207123 | ... BI94: =SUM(BI65)/SUM(BI78:BI83) -> 0.145147 | CD94: =SUM(CD65)/SUM(CD78:CD83) -> 0.14086525 | CE94: =SUM(CE65)/SUM(CE78:CE83) -> 0.10831278 | CF94: =SUM(CF65)/SUM(CF78:CF83) -> 0.097997112
B95: Fixed Asset Turnover Ratio | AX95: =AX40/AVERAGE(AU71:AX71) -> 1.265367 | AY95: =AY40/AVERAGE(AV71:AY71) -> 1.2301663 | AZ95: =AZ40/AVERAGE(AW71:AZ71) -> 1.256675 | BA95: =BA40/AVERAGE(AX71:BA71) -> 1.2762011 | BB95: =BB40/AVERAGE(AY71:BB71) -> 1.3662528 | BC95: =BC40/AVERAGE(AZ71:BC71) -> 1.2730436 | BD95: =BD40/AVERAGE(BA71:BD71) -> 1.3422063 | BE95: =BE40/AVERAGE(BB71:BE71) -> 1.3885165 | ... BI95: =BI40/AVERAGE(BF71:BI71) -> 1.4704756 | CD95: =CD40/AVERAGE(CA71:CD71) -> 4.3764288 | CE95: =CE40/AVERAGE(CB71:CE71) -> 5.0719603 | CF95: =CF40/AVERAGE(CC71:CF71) -> 5.5409197
B96: Ttl Asset Turnover Ratio | AX96: =AX40/AX90 -> 0.12310572 | AY96: =AY40/AY90 -> 0.1205154 | AZ96: =AZ40/AZ90 -> 0.12236224 | BA96: =BA40/BA90 -> 0.121883 | BB96: =BB40/BB90 -> 0.13276966 | BC96: =BC40/BC90 -> 0.12316819 | BD96: =BD40/BD90 -> 0.12912007 | BE96: =BE40/BE90 -> 0.13326456 | ... BI96: =BI40/BI90 -> 0.14136787 | CD96: =CD40/CD90 -> 0.4257764 | CE96: =CE40/CE90 -> 0.49574791 | CF96: =CF40/CF90 -> 0.53743085
B97: Inventory Turnover Ratio | AX97: =AX41/AVERAGE(AU68:AX68) -> 1.3516176 | AY97: =AY41/AVERAGE(AV68:AY68) -> 1.3031494 | AZ97: =AZ41/AVERAGE(AW68:AZ68) -> 1.3013437 | BA97: =BA41/AVERAGE(AX68:BA68) -> 1.2672916 | BB97: =BB41/AVERAGE(AY68:BB68) -> 1.3461851 | BC97: =BC41/AVERAGE(AZ68:BC68) -> 1.2242429 | BD97: =BD41/AVERAGE(BA68:BD68) -> 1.277686 | BE97: =BE41/AVERAGE(BB68:BE68) -> 1.3207881 | ... BI97: =BI41/AVERAGE(BF68:BI68) -> 1.3474217 | CD97: =CD41/AVERAGE(CA68:CD68) -> 4.8255923 | CE97: =CE41/AVERAGE(CB68:CE68) -> 5.3231208 | CF97: =CF41/AVERAGE(CC68:CF68) -> 5.5667007
B98: Return on Assets | AX98: =AX51/AX90 -> 0.0090999512 | AY98: =AY51/AY90 -> 0.010881033 | AZ98: =AZ51/AZ90 -> 0.0010858168 | BA98: =BA51/BA90 -> 0.0093130771 | BB98: =BB51/BB90 -> 0.0095787205 | BC98: =BC51/BC90 -> 0.0098566091 | BD98: =BD51/BD90 -> 0.010320751 | BE98: =BE51/BE90 -> 0.011892905 | ... BI98: =BI51/BI90 -> 0.015334436 | CD98: =CD51/CD90 -> 0.020881083 | CE98: =CE51/CE90 -> 0.03078085 | CF98: =CF51/CF90 -> 0.042877766
B99: Return on Equity | AX99: =AX51/AX89 -> 0.023972658 | AY99: =AY51/AY89 -> 0.02805092 | AZ99: =AZ51/AZ89 -> 0.002883934 | BA99: =BA51/BA89 -> 0.024419733 | BB99: =BB51/BB89 -> 0.025178347 | BC99: =BC51/BC89 -> 0.025653574 | BD99: =BD51/BD89 -> 0.026849503 | BE99: =BE51/BE89 -> 0.030214029 | ... BI99: =BI51/BI89 -> 0.038145143 | CD99: =CD51/CD89 -> 0.055008544 | CE99: =CE51/CE89 -> 0.080909648 | CF99: =CF51/CF89 -> 0.11159699
B101: Net Income | C101: =C51 -> 1522 | D101: =D51 -> 1894 | E101: =E51 -> 1773 | F101: =F51 -> 1557 | G101: =G51 -> 1824 | H101: =H51 -> 2079 | I101: =I51 -> 1978 | J101: =J51 -> 1564 | ... BI101: =BI51 -> 2708 | BS101: =SUM(C101:F101) -> 6746 | BT101: =SUM(G101:J101) -> 7445 | BU101: =SUM(K101:N101) -> 8230 | BV101: =SUM(O101:R101) -> 6004 | BW101: =SUM(S101:V101) -> 7612 | BX101: =SUM(W101:Z101) -> 5670 | BY101: =SUM(AA101:AD101) -> 2152 | BZ101: =SUM(AE101:AH101) -> 5255 | CA101: =SUM(AI101:AL101) -> 5230 | CB101: =SUM(AM101:AP101) -> 117 | CC101: =SUM(AQ101:AT101) -> 5327 | CD101: =SUM(AU101:AX101) -> 3380 | CE101: =SUM(AY101:BB101) -> 5013 | CF101: =SUM(BC101:BF101) -> 7069
B102: CFFO | C102: 1323 | D102: 1703 | E102: 1625 | F102: 12284 | G102: 1409 | H102: 1939 | I102: 1543 | J102: 2423 | K102: 1335 | L102: 1742 | M102: 1945 | N102: 1957 | O102: 1646 | P102: 1376 | Q102: 1022 | R102: 2711 | S102: 798 | T102: 1808 | U102: 1961 | V102: 1845 | W102: 993 | X102: 2146 | Y102: -29 | Z102: 2521 | AA102: 453 | AB102: 2102 | AC102: 1762 | AD102: -1647 | AE102: 1500 | AF102: 1269 | AG102: 1727 | AH102: 1325 | AI102: 1132 | AJ102: 210 | AK102: 1622 | AL102: 1370 | AM102: 723 | AN102: 1326 | AO102: 1932 | AP102: 3161 | AQ102: 476 | AR102: 1286 | AS102: 778 | AT102: 4628 | AU102: -863 | AV102: 719 | AW102: 3316 | AX102: 4711 | AY102: 342 | AZ102: 2733 | BA102: 2523 | BB102: 1561 | BC102: 1305 | BD102: 458 | BE102: 4639 | BF102: 4165 | BG102: 1855 | BH102: 3547 | BI102: 2868 | BS102: =SUM(C102:F102) -> 16935 | BT102: =SUM(G102:J102) -> 7314 | BU102: =SUM(K102:N102) -> 6979 | BV102: =SUM(O102:R102) -> 6755 | BW102: =SUM(S102:V102) -> 6412 | BX102: =SUM(W102:Z102) -> 5631 | BY102: =SUM(AA102:AD102) -> 2670 | BZ102: =SUM(AE102:AH102) -> 5821 | CA102: =SUM(AI102:AL102) -> 4334 | CB102: =SUM(AM102:AP102) -> 7142 | CC102: =SUM(AQ102:AT102) -> 7168 | CD102: =SUM(AU102:AX102) -> 7883 | CE102: =SUM(AY102:BB102) -> 7159 | CF102: =SUM(BC102:BF102) -> 10567
B103: CapEx, net | C103: -187 | D103: -244 | E103: -317 | F103: -641 | G103: -295 | H103: -369 | I103: -383 | J103: -522 | K103: -333 | L103: -406 | M103: -324 | N103: -531 | O103: -323 | P103: -331 | Q103: -390 | R103: -608 | S103: -286 | T103: -363 | U103: -394 | V103: -656 | W103: -325 | X103: -446 | Y103: -443 | Z103: -800 | AA103: -337 | AB103: -372 | AC103: -413 | AD103: -345 | AE103: -363 | AF103: -315 | AG103: -444 | AH103: -746 | AI103: -325 | AJ103: -458 | AK103: -389 | AL103: -623 | AM103: -387 | AN103: -360 | AO103: -433 | AP103: -954 | AQ103: -439 | AR103: -479 | AS103: -515 | AT103: -855 | AU103: -520 | AV103: -526 | AW103: -564 | AX103: -805 | AY103: -467 | AZ103: -537 | BA103: -552 | BB103: -1069 | BC103: -513 | BD103: -530 | BE103: -614 | BF103: -970 | BG103: -546 | BH103: -669 | BI103: -749 | BS103: =SUM(C103:F103) -> -1389 | BT103: =SUM(G103:J103) -> -1569 | BU103: =SUM(K103:N103) -> -1594 | BV103: =SUM(O103:R103) -> -1652 | BW103: =SUM(S103:V103) -> -1699 | BX103: =SUM(W103:Z103) -> -2014 | BY103: =SUM(AA103:AD103) -> -1467 | BZ103: =SUM(AE103:AH103) -> -1868 | CA103: =SUM(AI103:AL103) -> -1795 | CB103: =SUM(AM103:AP103) -> -2134 | CC103: =SUM(AQ103:AT103) -> -2288 | CD103: =SUM(AU103:AX103) -> -2415 | CE103: =SUM(AY103:BB103) -> -2625 | CF103: =SUM(BC103:BF103) -> -2627
B104: FCF | C104: =C102+C103 -> 1136 | D104: =D102+D103 -> 1459 | E104: =E102+E103 -> 1308 | F104: =F102+F103 -> 11643 | G104: =G102+G103 -> 1114 | H104: =H102+H103 -> 1570 | I104: =I102+I103 -> 1160 | J104: =J102+J103 -> 1901 | ... BI104: =BI102+BI103 -> 2119 | BS104: =SUM(C104:F104) -> 15546 | BT104: =SUM(G104:J104) -> 5745 | BU104: =SUM(K104:N104) -> 5385 | BV104: =SUM(O104:R104) -> 5103 | BW104: =SUM(S104:V104) -> 4713 | BX104: =SUM(W104:Z104) -> 3617 | BY104: =SUM(AA104:AD104) -> 1203 | BZ104: =SUM(AE104:AH104) -> 3953 | CA104: =SUM(AI104:AL104) -> 2539 | CB104: =SUM(AM104:AP104) -> 5008 | CC104: =SUM(AQ104:AT104) -> 4880 | CD104: =SUM(AU104:AX104) -> 5468 | CE104: =SUM(AY104:BB104) -> 4534 | CF104: =SUM(BC104:BF104) -> 7940
B105: SC | C105: =C54 -> 891 | D105: =D54 -> 893 | E105: =E54 -> 896 | F105: =F54 -> 895 | G105: =G54 -> 901 | H105: =H54 -> 901 | I105: =I54 -> 901 | J105: =J54 -> 901 | ... BI105: =BI54 -> 1352.2 | BS105: =BS54 -> 893.75 | BT105: =BT54 -> 901 | BU105: =BU54 -> 899.75 | BV105: =BV54 -> 879 | BW105: =BW54 -> 822.5 | BX105: =BX54 -> 790.25 | BY105: =BY54 -> 793 | BZ105: =BZ54 -> 854.25 | ... CF105: =CF54 -> 1338.75
B106: FCF per Share | C106: =C104/C105 -> 1.2749719 | D106: =D104/D105 -> 1.6338186 | E106: =E104/E105 -> 1.4598214 | F106: =F104/F105 -> 13.008939 | G106: =G104/G105 -> 1.236404 | H106: =H104/H105 -> 1.7425083 | I106: =I104/I105 -> 1.2874584 | J106: =J104/J105 -> 2.1098779 | ... BI106: =BI104/BI105 -> 1.5670759 | BS106: =SUM(C106:F106) -> 17.377551 | BT106: =SUM(G106:J106) -> 6.3762486 | BU106: =SUM(K106:N106) -> 5.9856265 | BV106: =SUM(O106:R106) -> 5.8084749 | BW106: =SUM(S106:V106) -> 5.7319925 | BX106: =SUM(W106:Z106) -> 4.5754322 | BY106: =SUM(AA106:AD106) -> 1.5493765 | BZ106: =SUM(AE106:AH106) -> 4.6278164 | CA106: =SUM(AI106:AL106) -> 2.0871378 | CB106: =SUM(AM106:AP106) -> 3.3453785 | CC106: =SUM(AQ106:AT106) -> 3.3206886 | CD106: =SUM(AU106:AX106) -> 3.9870229 | CE106: =SUM(AY106:BB106) -> 3.4119164 | CF106: =SUM(BC106:BF106) -> 5.919396
B108: CFFO Margin | C108: =C102/C40 -> 0.10655606 | D108: =D102/D40 -> 0.12334323 | E108: =E102/E40 -> 0.10803085 | F108: =F102/F40 -> 0.74706562 | G108: =G102/G40 -> 0.097854018 | H108: =H102/H40 -> 0.12114207 | I108: =I102/I40 -> 0.099793041 | J108: =J102/J40 -> 0.22575235 | ... BI108: =BI102/BI40 -> 0.11488083 | BS108: =BS102/BS40 -> 0.29346018 | BT108: =BT102/BT40 -> 0.12922261 | BU108: =BU102/BU40 -> 0.12053541 | BV108: =BV102/BV40 -> 0.12041428 | BW108: =BW102/BW40 -> 0.11201174 | BX108: =BX102/BX40 -> 0.094105654 | BY108: =BY102/BY40 -> 0.076943028 | BZ108: =BZ102/BZ40 -> 0.12836005 | ... CF108: =CF102/CF40 -> 0.11926233
B109: FCF Margin | C109: =C104/C40 -> 0.091494845 | D109: =D104/D40 -> 0.10567104 | E109: =E104/E40 -> 0.086956522 | F109: =F104/F40 -> 0.70808247 | G109: =G104/G40 -> 0.077366484 | H109: =H104/H40 -> 0.098088217 | I109: =I104/I40 -> 0.075022636 | J109: =J104/J40 -> 0.1771173 | ... BI109: =BI104/BI40 -> 0.08487883 | BS109: =BS104/BS40 -> 0.26939073 | BT109: =BT104/BT40 -> 0.10150177 | BU109: =BU104/BU40 -> 0.093005181 | BV109: =BV104/BV40 -> 0.09096581 | BW109: =BW104/BW40 -> 0.082331773 | BX109: =BX104/BX40 -> 0.060447549 | BY109: =BY104/BY40 -> 0.034667589 | BZ109: =BZ104/BZ40 -> 0.087168405 | ... CF109: =CF104/CF40 -> 0.089613219
B110: CapEx as % of Revenue | C110: =C103/C40 -> -0.015061211 | D110: =D103/D40 -> -0.017672195 | E110: =E103/E40 -> -0.021074325 | F110: =F103/F40 -> -0.038983154 | G110: =G103/G40 -> -0.020487534 | H110: =H103/H40 -> -0.023053855 | I110: =I103/I40 -> -0.024770405 | J110: =J103/J40 -> -0.048635051 | ... BI110: =BI103/BI40 -> -0.030002003 | BS110: =BS103/BS40 -> -0.024069453 | BT110: =BT103/BT40 -> -0.027720848 | BU110: =BU103/BU40 -> -0.027530225 | BV110: =BV103/BV40 -> -0.029448465 | BW110: =BW103/BW40 -> -0.029679966 | BX110: =BX103/BX40 -> -0.033658105 | BY110: =BY103/BY40 -> -0.042275439 | BZ110: =BZ103/BZ40 -> -0.041191647 | ... CF110: =CF103/CF40 -> -0.029649109

Sheet Notes | Quant Analysis
CK1: 0
P2: Employee Scope: | AN2: General Notes/Observations
Q33: Notes: | R33: [X]
R34: [Y]
R35: [Z]
AN36: Financial Stmts. Notes/Observations
P37: Institutional Ownership | AN37: Revenues:
Q67: Notes: | R67: [X]
R68: [Y]
R69: [Z]
P71: Revenue Breakdown by Segment | AN71: Earnings Scope:
Q103: Notes: | R103: [X]
R104: [Y]
R105: [Z]
P107: Revenue Breakdown by Geography | AN107: Balance Sheet Scope:
Q139: Notes: | R139: [X]
R140: [Y] | AN140: [Equity Preformance Compared to Peers]
R141: [Z]
P143: Q/q Total Revenues, Net Income, FCF
Q172: Notes: | R172: [X]
R173: [Y]
R174: [Z]
P176: Y/y Total Revenues, Net Income, FCF
Q205: Notes: | R205: [X]
R206: [Y]
R207: [Z]
A222: VOO Historical Returns | I222: RTX Historical Returns
A223: 1506 Trading Days? (From: 9/19/2020 - 9/19/2026) | I223: 1506 Trading Days? (From: 9/19/2020 - 9/19/2026)
A224: Close | B224: High | C224: Low | D224: Open | E224: Volume | F224: UTC Date | G224: Change | I224: Close | J224: High | K224: Low | L224: Open | M224: Volume | N224: UTC Date | O224: Change
A225: 701.78 | B225: 702.19 | C225: 698.5 | D225: 701.58 | E225: 9594039.2 | F225: Fri, 18 Sep 2026 00:00:00 GMT | G225: =A225/D225-1 -> 0.00028507084 | I225: 194 | J225: 194 | K225: 191.175 | L225: 193 | M225: 9843426.5 | N225: Fri, 18 Sep 2026 00:00:00 GMT | O225: =I225/L225-1 -> 0.0051813472
A226: 701.03 | B226: 701.88 | C226: 698.61 | D226: 701.6 | E226: 9903368.8 | F226: Thu, 17 Sep 2026 00:00:00 GMT | G226: =A226/D226-1 -> -0.00081242873 | I226: 193.54 | J226: 197.5 | K226: 191.84 | L226: 197.5 | M226: 3549581.7 | N226: Thu, 17 Sep 2026 00:00:00 GMT | O226: =I226/L226-1 -> -0.020050633
A227: 693.24 | B227: 700.1 | C227: 689.04 | D227: 698.17 | E227: 14168409 | F227: Wed, 16 Sep 2026 00:00:00 GMT | G227: =A227/D227-1 -> -0.0070613174 | I227: 196.83 | J227: 197.67 | K227: 194.78 | L227: 195.39 | M227: 3485674.5 | N227: Wed, 16 Sep 2026 00:00:00 GMT | O227: =I227/L227-1 -> 0.0073698756
A228: 696.2 | B228: 698.94 | C228: 695.09 | D228: 698.77 | E228: 9657887.8 | F228: Tue, 15 Sep 2026 00:00:00 GMT | G228: =A228/D228-1 -> -0.0036778912 | I228: 195.5 | J228: 197.205 | K228: 193.05 | L228: 196.73 | M228: 4729145.5 | N228: Tue, 15 Sep 2026 00:00:00 GMT | O228: =I228/L228-1 -> -0.0062522239
A229: 699.3 | B229: 701.85 | C229: 696.72 | D229: 697.78 | E229: 6776056.6 | F229: Mon, 14 Sep 2026 00:00:00 GMT | G229: =A229/D229-1 -> 0.002178337 | I229: 195.34 | J229: 196.5 | K229: 194.01 | L229: 196.4 | M229: 3568413 | N229: Mon, 14 Sep 2026 00:00:00 GMT | O229: =I229/L229-1 -> -0.0053971487
A230: 702.56 | B230: 704.4954 | C230: 701.93 | D230: 703 | E230: 5797972.9 | F230: Fri, 11 Sep 2026 00:00:00 GMT | G230: =A230/D230-1 -> -0.00062588905 | I230: 197.68 | J230: 200.38 | K230: 196.31 | L230: 199.57 | M230: 3680583.8 | N230: Fri, 11 Sep 2026 00:00:00 GMT | O230: =I230/L230-1 -> -0.0094703613
A231: 696.65 | B231: 698.64 | C231: 695.5421 | D231: 696.78 | E231: 18313415 | F231: Thu, 10 Sep 2026 00:00:00 GMT | G231: =A231/D231-1 -> -0.00018657252 | I231: 198.12 | J231: 198.86 | K231: 196.6801 | L231: 198.03 | M231: 2651871 | N231: Thu, 10 Sep 2026 00:00:00 GMT | O231: =I231/L231-1 -> 0.00045447659
A232: 700.87 | B232: 702.71 | C232: 699.485 | D232: 702.35 | E232: 4300871.2 | F232: Wed, 09 Sep 2026 00:00:00 GMT | G232: =A232/D232-1 -> -0.0021072115 | I232: 197.55 | J232: 199.56 | K232: 196.8 | L232: 198.92 | M232: 3319425.7 | N232: Wed, 09 Sep 2026 00:00:00 GMT | O232: =I232/L232-1 -> -0.0068871908
A233: 704.07 | B233: 707.51 | C233: 703.37 | D233: 706.98 | E233: 7827554 | F233: Tue, 08 Sep 2026 00:00:00 GMT | G233: =A233/D233-1 -> -0.0041160995 | I233: 198.81 | J233: 201.75 | K233: 198.13 | L233: 199.73 | M233: 3627291.7 | N233: Tue, 08 Sep 2026 00:00:00 GMT | O233: =I233/L233-1 -> -0.0046062184
A234: 708.01 | B234: 710.45 | C234: 706.9 | D234: 709.72 | E234: 6816157.9 | F234: Fri, 04 Sep 2026 00:00:00 GMT | G234: =A234/D234-1 -> -0.0024094009 | I234: 200.79 | J234: 201.6357 | K234: 199.04 | L234: 200.77 | M234: 2803336.8 | N234: Fri, 04 Sep 2026 00:00:00 GMT | O234: =I234/L234-1 -> 9.9616477e-05
A235: 710.72 | B235: 711.515 | C235: 705.51 | D235: 705.82 | E235: 8594521.7 | F235: Thu, 03 Sep 2026 00:00:00 GMT | G235: =A235/D235-1 -> 0.0069422799 | I235: 202.13 | J235: 202.665 | K235: 200.1 | L235: 202 | M235: 3706634 | N235: Thu, 03 Sep 2026 00:00:00 GMT | O235: =I235/L235-1 -> 0.00064356436
A236: 703.41 | B236: 704.53 | C236: 700.18 | D236: 700.85 | E236: 7704946.8 | F236: Wed, 02 Sep 2026 00:00:00 GMT | G236: =A236/D236-1 -> 0.0036527074 | I236: 200.78 | J236: 206.88 | K236: 200.31 | L236: 206.88 | M236: 4662376.1 | N236: Wed, 02 Sep 2026 00:00:00 GMT | O236: =I236/L236-1 -> -0.029485692
A237: 700.28 | B237: 702.91 | C237: 698.1398 | D237: 700.45 | E237: 6486903.6 | F237: Tue, 01 Sep 2026 00:00:00 GMT | G237: =A237/D237-1 -> -0.00024270112 | I237: 205.16 | J237: 211.31 | K237: 204.17 | L237: 208.51 | M237: 3087938.7 | N237: Tue, 01 Sep 2026 00:00:00 GMT | O237: =I237/L237-1 -> -0.016066376
A238: 704.89 | B238: 705.94 | C238: 702.96 | D238: 705.36 | E238: 5741591.5 | F238: Mon, 31 Aug 2026 00:00:00 GMT | G238: =A238/D238-1 -> -0.00066632641 | I238: 207.73 | J238: 211.24 | K238: 207.69 | L238: 210.23 | M238: 3962328.9 | N238: Mon, 31 Aug 2026 00:00:00 GMT | O238: =I238/L238-1 -> -0.011891738 | R238: Min | S238: =MIN(O225:O1730) -> -0.067857143
A239: 707.24 | B239: 712.6692 | C239: 706.26 | D239: 709.39 | E239: 8084538.9 | F239: Fri, 28 Aug 2026 00:00:00 GMT | G239: =A239/D239-1 -> -0.0030307729 | I239: 211.71 | J239: 213.5 | K239: 210.7 | L239: 212.73 | M239: 2314857.6 | N239: Fri, 28 Aug 2026 00:00:00 GMT | O239: =I239/L239-1 -> -0.0047948103 | R239: Max | S239: =MAX(O225:O1730) -> 0.079062342
A240: 708.75 | B240: 709.955 | C240: 705.2104 | D240: 706.39 | E240: 6755739 | F240: Thu, 27 Aug 2026 00:00:00 GMT | G240: =A240/D240-1 -> 0.0033409306 | I240: 212.08 | J240: 212.52 | K240: 209.825 | L240: 211.34 | M240: 3849925.7 | N240: Thu, 27 Aug 2026 00:00:00 GMT | O240: =I240/L240-1 -> 0.0035014668 | R240: Mean μ | S240: =AVERAGE(O225:O1730) -> 0.00010616547
A241: 704.2 | B241: 705.32 | C241: 702.23 | D241: 702.9 | E241: 7157818.2 | F241: Wed, 26 Aug 2026 00:00:00 GMT | G241: =A241/D241-1 -> 0.0018494807 | I241: 211.99 | J241: 213.1 | K241: 209.2897 | L241: 210.4 | M241: 3791748.3 | N241: Wed, 26 Aug 2026 00:00:00 GMT | O241: =I241/L241-1 -> 0.0075570342 | R241: Median | S241: =MEDIAN(O225:O1730) -> 6.5647567e-05
A242: 704.02 | B242: 704.8353 | C242: 701.45 | D242: 704.285 | E242: 4324492.6 | F242: Tue, 25 Aug 2026 00:00:00 GMT | G242: =A242/D242-1 -> -0.00037626813 | I242: 210.28 | J242: 210.65 | K242: 207.44 | L242: 210.36 | M242: 4894904.2 | N242: Tue, 25 Aug 2026 00:00:00 GMT | O242: =I242/L242-1 -> -0.00038030044 | R242: SD σ | S242: =_xlfn.STDEV.P(O225:O1730) -> 0.012937452
A243: 701.83 | B243: 703.3899 | C243: 700.53 | D243: 702.97 | E243: 7737475 | F243: Mon, 24 Aug 2026 00:00:00 GMT | G243: =A243/D243-1 -> -0.0016216908 | I243: 209.22 | J243: 210.8894 | K243: 207.7461 | L243: 210 | M243: 3839606.5 | N243: Mon, 24 Aug 2026 00:00:00 GMT | O243: =I243/L243-1 -> -0.0037142857 | R243: 3σ 1-Day Δ: ± | S243: =3*S242 -> 0.038812356 | U243: <- Sharpe Ratio (Risk Adjusted Return)
A244: 703.71 | B244: 705.8 | C244: 702.44 | D244: 704.07 | E244: 10678137 | F244: Fri, 21 Aug 2026 00:00:00 GMT | G244: =A244/D244-1 -> -0.0005113128 | I244: 209.91 | J244: 213.52 | K244: 209.85 | L244: 213.36 | M244: 4777141.4 | N244: Fri, 21 Aug 2026 00:00:00 GMT | O244: =I244/L244-1 -> -0.016169854 | R244: β (1-year avg.) | S244: =_xlfn.COVARIANCE.P(O225:O473,G225:G473)/_xlfn.VAR.P(G225:G473) -> 0.48869047 | U244: <- Sortino Ratio (Downside Risk Adjusted Return)
A245: 701.01 | B245: 706.08 | C245: 700.4721 | D245: 704.05 | E245: 8458614.7 | F245: Thu, 20 Aug 2026 00:00:00 GMT | G245: =A245/D245-1 -> -0.0043178752 | I245: 212.29 | J245: 220.49 | K245: 212.16 | L245: 218.97 | M245: 4931795.4 | N245: Thu, 20 Aug 2026 00:00:00 GMT | O245: =I245/L245-1 -> -0.030506462
A246: 706.91 | B246: 710.1 | C246: 706.095 | D246: 708.19 | E246: 7021780.3 | F246: Wed, 19 Aug 2026 00:00:00 GMT | G246: =A246/D246-1 -> -0.0018074246 | I246: 220.35 | J246: 226.41 | K246: 220.22 | L246: 225.93 | M246: 6227052 | N246: Wed, 19 Aug 2026 00:00:00 GMT | O246: =I246/L246-1 -> -0.024697915 | Q246: n = | R246: 1014
A247: 705.4 | B247: 707.35 | C247: 704.96 | D247: 706.61 | E247: 5278550.7 | F247: Tue, 18 Aug 2026 00:00:00 GMT | G247: =A247/D247-1 -> -0.0017124015 | I247: 225.49 | J247: 226.09 | K247: 222.3 | L247: 222.76 | M247: 5972477.6 | N247: Tue, 18 Aug 2026 00:00:00 GMT | O247: =I247/L247-1 -> 0.012255342 | Q247: Histogram Data | T247: Distribution Overlay | X247: SD Lines
A248: 710.27 | B248: 714.045 | C248: 710.1 | D248: 713.5 | E248: 5745007.7 | F248: Mon, 17 Aug 2026 00:00:00 GMT | G248: =A248/D248-1 -> -0.0045269797 | I248: 221.64 | J248: 224.61 | K248: 221.6 | L248: 222.92 | M248: 5187626.9 | N248: Mon, 17 Aug 2026 00:00:00 GMT | O248: =I248/L248-1 -> -0.0057419702 | Q248: Bin | R248: Frequency | T248: (X) 1-Day Δ | U248: (Y) Pop. Density | X248: X | Y248: Y
A249: 713.61 | B249: 715.89 | C249: 712.8 | D249: 715.63 | E249: 4214065.8 | F249: Fri, 14 Aug 2026 00:00:00 GMT | G249: =A249/D249-1 -> -0.0028226877 | I249: 222.97 | J249: 223.07 | K249: 219.975 | L249: 222 | M249: 2856069.5 | N249: Fri, 14 Aug 2026 00:00:00 GMT | O249: =I249/L249-1 -> 0.0043693694 | Q249: -0.045 | R249: 3 | T249: =T250-0.001 -> -0.05 | U249: =_xlfn.NORM.DIST(T249,$S$240,$S$242,FALSE) -> 0.017056934 | W249: Mean | X249: =S240 -> 0.00010616547 | Y249: 0
A250: 714.95 | B250: 716.39 | C250: 711.605 | D250: 712.3 | E250: 4551235.2 | F250: Thu, 13 Aug 2026 00:00:00 GMT | G250: =A250/D250-1 -> 0.0037203426 | I250: 219.75 | J250: 223.25835 | K250: 218.14533 | L250: 222.7301 | M250: 3239381.5 | N250: Thu, 13 Aug 2026 00:00:00 GMT | O250: =I250/L250-1 -> -0.013379872 | Q250: -0.044 | R250: 0 | T250: =T251-0.001 -> -0.049 | U250: =_xlfn.NORM.DIST(T250,$S$240,$S$242,FALSE) -> 0.022941086 | X250: =S240 -> 0.00010616547 | Y250: 30.5
A251: 710.17 | B251: 712.26 | C251: 708.93 | D251: 712.12 | E251: 4871287.5 | F251: Wed, 12 Aug 2026 00:00:00 GMT | G251: =A251/D251-1 -> -0.0027383025 | I251: 222.02245 | J251: 222.80984 | K251: 218.74334 | L251: 221.88291 | M251: 3885417.8 | N251: Wed, 12 Aug 2026 00:00:00 GMT | O251: =I251/L251-1 -> 0.00062887431 | Q251: -0.043 | R251: 2 | T251: =T252-0.001 -> -0.048 | U251: =_xlfn.NORM.DIST(T251,$S$240,$S$242,FALSE) -> 0.030671308 | W251: -3σ | X251: =($S$242*-3)+$S$240 -> -0.038706191 | Y251: 0
A252: 708.42 | B252: 712 | C252: 707 | D252: 711.96 | E252: 5010440 | F252: Tue, 11 Aug 2026 00:00:00 GMT | G252: =A252/D252-1 -> -0.0049721894 | I252: 223.11881 | J252: 224.59391 | K252: 221.60384 | L252: 223.25835 | M252: 2834129.7 | N252: Tue, 11 Aug 2026 00:00:00 GMT | O252: =I252/L252-1 -> -0.000625 | Q252: -0.042 | R252: 1 | T252: =T253-0.001 -> -0.047 | U252: =_xlfn.NORM.DIST(T252,$S$240,$S$242,FALSE) -> 0.04076204 | X252: =($S$242*-3)+$S$240 -> -0.038706191 | Y252: 1
A253: 710.65 | B253: 712.4378 | C253: 709.5 | D253: 710.31 | E253: 6657921.2 | F253: Mon, 10 Aug 2026 00:00:00 GMT | G253: =A253/D253-1 -> 0.00047866425 | I253: 223.37795 | J253: 226.1328 | K253: 222.56066 | L253: 223.63709 | M253: 3258688.9 | N253: Mon, 10 Aug 2026 00:00:00 GMT | O253: =I253/L253-1 -> -0.0011587486 | Q253: -0.041 | R253: 2 | T253: =T254-0.001 -> -0.046 | U253: =_xlfn.NORM.DIST(T253,$S$240,$S$242,FALSE) -> 0.053849891 | W253: -2σ | X253: =($S$242*-2)+$S$240 -> -0.025768739 | Y253: 0
A254: 710.71 | B254: 711.37 | C254: 707.44 | D254: 708.73 | E254: 4653131.9 | F254: Fri, 07 Aug 2026 00:00:00 GMT | G254: =A254/D254-1 -> 0.0027937296 | I254: 222.29156 | J254: 223.56244 | K254: 219.76993 | L254: 221.79321 | M254: 4992125 | N254: Fri, 07 Aug 2026 00:00:00 GMT | O254: =I254/L254-1 -> 0.0022468881 | Q254: -0.04 | R254: 1 | T254: =T255-0.001 -> -0.045 | U254: =_xlfn.NORM.DIST(T254,$S$240,$S$242,FALSE) -> 0.070716222 | X254: =($S$242*-2)+$S$240 -> -0.025768739 | Y254: 5
A255: 706.4 | B255: 709.4619 | C255: 705.43 | D255: 707.93 | E255: 4668740.4 | F255: Thu, 06 Aug 2026 00:00:00 GMT | G255: =A255/D255-1 -> -0.0021612306 | I255: 222.51083 | J255: 224.90288 | K255: 219.75 | L255: 223.46267 | M255: 5993391.1 | N255: Thu, 06 Aug 2026 00:00:00 GMT | O255: =I255/L255-1 -> -0.0042594947 | Q255: -0.039 | R255: 0 | T255: =T256-0.001 -> -0.044 | U255: =_xlfn.NORM.DIST(T255,$S$240,$S$242,FALSE) -> 0.092312088 | W255: -1σ | X255: =($S$242*-1)+$S$240 -> -0.012831287 | Y255: 0
A256: 707.6 | B256: 714.16 | C256: 707.32 | D256: 713.14 | E256: 5187471.1 | F256: Wed, 05 Aug 2026 00:00:00 GMT | G256: =A256/D256-1 -> -0.0077684606 | I256: 221.57394 | J256: 222.07727 | K256: 218.17025 | L256: 219.27159 | M256: 4280136.1 | N256: Wed, 05 Aug 2026 00:00:00 GMT | O256: =I256/L256-1 -> 0.0105 | Q256: -0.038 | R256: 2 | T256: =T257-0.001 -> -0.043 | U256: =_xlfn.NORM.DIST(T256,$S$240,$S$242,FALSE) -> 0.11978526 | X256: =($S$242*-1)+$S$240 -> -0.012831287 | Y256: 15
A257: 708.98 | B257: 710.9083 | C257: 699.07 | D257: 699.16 | E257: 6510852.7 | F257: Tue, 04 Aug 2026 00:00:00 GMT | G257: =A257/D257-1 -> 0.014045426 | I257: 217.20844 | J257: 217.87622 | K257: 213.81472 | L257: 216.66026 | M257: 6319866 | N257: Tue, 04 Aug 2026 00:00:00 GMT | O257: =I257/L257-1 -> 0.0025301316 | Q257: -0.037 | R257: 1 | T257: =T258-0.001 -> -0.042 | U257: =_xlfn.NORM.DIST(T257,$S$240,$S$242,FALSE) -> 0.15450891 | W257: 1σ | X257: =($S$242*1)+$S$240 -> 0.013043618 | Y257: 0
A258: 696.4 | B258: 697.31 | C258: 688.61 | D258: 688.83 | E258: 7244316 | F258: Mon, 03 Aug 2026 00:00:00 GMT | G258: =A258/D258-1 -> 0.010989649 | I258: 215.93268 | J258: 217.40778 | K258: 213.71006 | L258: 215.85295 | M258: 3805799.1 | N258: Mon, 03 Aug 2026 00:00:00 GMT | O258: =I258/L258-1 -> 0.00036939558 | Q258: -0.036 | R258: 3 | T258: =T259-0.001 -> -0.041 | U258: =_xlfn.NORM.DIST(T258,$S$240,$S$242,FALSE) -> 0.19811117 | X258: =($S$242*1)+$S$240 -> 0.013043618 | Y258: 15
A259: 686.65 | B259: 688.35 | C259: 678.06 | D259: 684.5 | E259: 7661568.2 | F259: Fri, 31 Jul 2026 00:00:00 GMT | G259: =A259/D259-1 -> 0.0031409788 | I259: 214.50742 | J259: 215.10543 | K259: 211.33296 | L259: 212.64361 | M259: 3417869.1 | N259: Fri, 31 Jul 2026 00:00:00 GMT | O259: =I259/L259-1 -> 0.0087649402 | Q259: -0.035 | R259: 3 | T259: =T260-0.001 -> -0.04 | U259: =_xlfn.NORM.DIST(T259,$S$240,$S$242,FALSE) -> 0.25250483 | W259: 2σ | X259: =($S$242*2)+$S$240 -> 0.02598107 | Y259: 0
A260: 681.79 | B260: 682.4363 | C260: 675.21 | D260: 676.54 | E260: 6009104.5 | F260: Thu, 30 Jul 2026 00:00:00 GMT | G260: =A260/D260-1 -> 0.0077600733 | I260: 213.6702 | J260: 213.92934 | K260: 208.69672 | L260: 213.7898 | M260: 5236753.3 | N260: Thu, 30 Jul 2026 00:00:00 GMT | O260: =I260/L260-1 -> -0.00055944056 | Q260: -0.034 | R260: 1 | T260: =T261-0.001 -> -0.039 | U260: =_xlfn.NORM.DIST(T260,$S$240,$S$242,FALSE) -> 0.31991582 | X260: =($S$242*2)+$S$240 -> 0.02598107 | Y260: 5
A261: 670.63 | B261: 682.63 | C261: 670.155 | D261: 680.12 | E261: 7845443.5 | F261: Wed, 29 Jul 2026 00:00:00 GMT | G261: =A261/D261-1 -> -0.01395342 | I261: 214.53732 | J261: 219.8397 | K261: 214.29811 | L261: 219.27159 | M261: 8236967.8 | N261: Wed, 29 Jul 2026 00:00:00 GMT | O261: =I261/L261-1 -> -0.021590909 | Q261: -0.033 | R261: 1 | T261: =T262-0.001 -> -0.038 | U261: =_xlfn.NORM.DIST(T261,$S$240,$S$242,FALSE) -> 0.40290908 | W261: 3σ | X261: =($S$242*3)+$S$240 -> 0.038918522 | Y261: 0
A262: 680.96 | B262: 682.755 | C262: 676.4801 | D262: 679.45 | E262: 5021080 | F262: Tue, 28 Jul 2026 00:00:00 GMT | G262: =A262/D262-1 -> 0.0022223858 | I262: 217.85629 | J262: 220.60715 | K262: 215.18516 | L262: 220.25831 | M262: 7752956.1 | N262: Tue, 28 Jul 2026 00:00:00 GMT | O262: =I262/L262-1 -> -0.010905471 | Q262: -0.032 | R262: 5 | T262: =T263-0.001 -> -0.037 | U262: =_xlfn.NORM.DIST(T262,$S$240,$S$242,FALSE) -> 0.50441001 | X262: =($S$242*3)+$S$240 -> 0.038918522 | Y262: 1
A263: 679.31 | B263: 685.2391 | C263: 676.395 | D263: 684.69 | E263: 5207757.8 | F263: Mon, 27 Jul 2026 00:00:00 GMT | G263: =A263/D263-1 -> -0.0078575706 | I263: 217.69682 | J263: 219.6603 | K263: 213.09182 | L263: 213.71006 | M263: 8210299 | N263: Mon, 27 Jul 2026 00:00:00 GMT | O263: =I263/L263-1 -> 0.018654976 | Q263: -0.031 | R263: 0 | T263: =T264-0.001 -> -0.036 | U263: =_xlfn.NORM.DIST(T263,$S$240,$S$242,FALSE) -> 0.62771952
A264: 679.14 | B264: 683.55 | C264: 677.7 | D264: 678.8 | E264: 6286807 | F264: Fri, 24 Jul 2026 00:00:00 GMT | G264: =A264/D264-1 -> 0.00050088391 | I264: 212.08546 | J264: 214.17841 | K264: 208.56725 | L264: 210.13195 | M264: 5894163.9 | N264: Fri, 24 Jul 2026 00:00:00 GMT | O264: =I264/L264-1 -> 0.0092965897 | Q264: -0.03 | R264: 5 | T264: =T265-0.001 -> -0.035 | U264: =_xlfn.NORM.DIST(T264,$S$240,$S$242,FALSE) -> 0.77652041
A265: 678.61 | B265: 682.5495 | C265: 675.755 | D265: 679.55 | E265: 4942804.8 | F265: Thu, 23 Jul 2026 00:00:00 GMT | G265: =A265/D265-1 -> -0.0013832683 | I265: 208.46748 | J265: 212.78314 | K265: 201.8395 | L265: 204.32125 | M265: 9906081.7 | N265: Thu, 23 Jul 2026 00:00:00 GMT | O265: =I265/L265-1 -> 0.020292683 | Q265: -0.029 | R265: 3 | T265: =T266-0.001 -> -0.034 | U265: =_xlfn.NORM.DIST(T265,$S$240,$S$242,FALSE) -> 0.95487258
A266: 687.03 | B266: 689.4 | C266: 686.02 | D266: 686.29 | E266: 3349102.7 | F266: Wed, 22 Jul 2026 00:00:00 GMT | G266: =A266/D266-1 -> 0.0010782614 | I266: 194.23476 | J266: 196.69648 | K266: 193.13591 | L266: 195.25138 | M266: 5158758 | N266: Wed, 22 Jul 2026 00:00:00 GMT | O266: =I266/L266-1 -> -0.0052067381 | Q266: -0.028 | R266: 3 | T266: =T267-0.001 -> -0.033 | U266: =_xlfn.NORM.DIST(T266,$S$240,$S$242,FALSE) -> 1.1671946
A267: 687.87 | B267: 688.485 | C267: 684.03 | D267: 685.95 | E267: 4054717.9 | F267: Tue, 21 Jul 2026 00:00:00 GMT | G267: =A267/D267-1 -> 0.0027990378 | I267: 193.02877 | J267: 196.48738 | K267: 189.39085 | L267: 193.35767 | M267: 3452643.3 | N267: Tue, 21 Jul 2026 00:00:00 GMT | O267: =I267/L267-1 -> -0.0017010309 | Q267: -0.027 | R267: 2 | T267: =T268-0.001 -> -0.032 | U267: =_xlfn.NORM.DIST(T267,$S$240,$S$242,FALSE) -> 1.4182292
A268: 682.21 | B268: 688.2 | C268: 681.57 | D268: 686.67 | E268: 5321985.3 | F268: Mon, 20 Jul 2026 00:00:00 GMT | G268: =A268/D268-1 -> -0.0064951141 | I268: 193.79622 | J268: 196.88595 | K268: 193.45734 | L268: 193.98559 | M268: 4606182.9 | N268: Mon, 20 Jul 2026 00:00:00 GMT | O268: =I268/L268-1 -> -0.00097621127 | Q268: -0.026 | R268: 6 | T268: =T269-0.001 -> -0.031 | U268: =_xlfn.NORM.DIST(T268,$S$240,$S$242,FALSE) -> 1.7129902
A269: 683.17 | B269: 686.8653 | C269: 680.92 | D269: 682.12 | E269: 5627641.4 | F269: Fri, 17 Jul 2026 00:00:00 GMT | G269: =A269/D269-1 -> 0.0015393186 | I269: 192.8693 | J269: 197.78297 | K269: 192.33108 | L269: 194.73311 | M269: 4183303.6 | N269: Fri, 17 Jul 2026 00:00:00 GMT | O269: =I269/L269-1 -> -0.0095710922 | Q269: -0.025 | R269: 4 | T269: =T270-0.001 -> -0.03 | U269: =_xlfn.NORM.DIST(T269,$S$240,$S$242,FALSE) -> 2.056689
A270: 690.14 | B270: 693.55 | C270: 687.43 | D270: 691.98 | E270: 4722611.2 | F270: Thu, 16 Jul 2026 00:00:00 GMT | G270: =A270/D270-1 -> -0.0026590364 | I270: 193.71648 | J270: 196.06867 | K270: 192.21148 | L270: 195.01218 | M270: 3519451.7 | N270: Thu, 16 Jul 2026 00:00:00 GMT | O270: =I270/L270-1 -> -0.0066441787 | Q270: -0.024 | R270: 6 | T270: =T271-0.001 -> -0.029 | U270: =_xlfn.NORM.DIST(T270,$S$240,$S$242,FALSE) -> 2.4546392
A271: 693.8 | B271: 694.5 | C271: 689.58 | D271: 693.27 | E271: 4110059.9 | F271: Wed, 15 Jul 2026 00:00:00 GMT | G271: =A271/D271-1 -> 0.00076449291 | I271: 195.24142 | J271: 195.63013 | K271: 192.50052 | L271: 194.36931 | M271: 3550952.3 | N271: Wed, 15 Jul 2026 00:00:00 GMT | O271: =I271/L271-1 -> 0.0044868343 | Q271: -0.023 | R271: 3 | T271: =T272-0.001 -> -0.028 | U271: =_xlfn.NORM.DIST(T271,$S$240,$S$242,FALSE) -> 2.9121385
A272: 691.1 | B272: 692.4 | C272: 688.2 | D272: 690.21 | E272: 4570040.4 | F272: Tue, 14 Jul 2026 00:00:00 GMT | G272: =A272/D272-1 -> 0.0012894626 | I272: 192.74969 | J272: 197.84277 | K272: 192.74969 | L272: 195.72979 | M272: 4258120 | N272: Tue, 14 Jul 2026 00:00:00 GMT | O272: =I272/L272-1 -> -0.015225583 | Q272: -0.022 | R272: 6 | T272: =T273-0.001 -> -0.027 | U272: =_xlfn.NORM.DIST(T272,$S$240,$S$242,FALSE) -> 3.4343274
A273: 688.5 | B273: 692.96 | C273: 687.54 | D273: 691.6 | E273: 6587891.4 | F273: Mon, 13 Jul 2026 00:00:00 GMT | G273: =A273/D273-1 -> -0.0044823597 | I273: 195.73976 | J273: 197.03207 | K273: 194.57862 | L273: 195.7896 | M273: 3617510.8 | N273: Mon, 13 Jul 2026 00:00:00 GMT | O273: =I273/L273-1 -> -0.00025453065 | Q273: -0.021 | R273: 8 | T273: =T274-0.001 -> -0.026 | U273: =_xlfn.NORM.DIST(T273,$S$240,$S$242,FALSE) -> 4.0260267
A274: 693.86 | B274: 694.33 | C274: 687.63 | D274: 691.25 | E274: 4666892.9 | F274: Fri, 10 Jul 2026 00:00:00 GMT | G274: =A274/D274-1 -> 0.0037757685 | I274: 195.28128 | J274: 196.03628 | K274: 191.95234 | L274: 194.36433 | M274: 2829509.5 | N274: Fri, 10 Jul 2026 00:00:00 GMT | O274: =I274/L274-1 -> 0.0047177068 | Q274: -0.02 | R274: 13 | T274: =T275-0.001 -> -0.025 | U274: =_xlfn.NORM.DIST(T274,$S$240,$S$242,FALSE) -> 4.6915561
... A298: 694.03871 | B298: 695.17539 | C298: 688.89369 | D298: 689.48198 | E298: 6594038 | F298: Thu, 04 Jun 2026 00:00:00 GMT | G298: =A298/D298-1 -> 0.006608917 | I298: 178.81598 | J298: 179.82264 | K298: 175.61063 | L298: 175.95548 | M298: 4500890.7 | N298: Thu, 04 Jun 2026 00:00:00 GMT | O298: =I298/L298-1 -> 0.016256939 | Q298: 0.004 | R298: 57 | T298: =T299-0.001 -> -0.001 | U298: =_xlfn.NORM.DIST(T298,$S$240,$S$242,FALSE) -> 30.723725
A299: 691.34655 | B299: 695.62399 | C299: 690.83803 | D299: 695.05574 | E299: 5899709.5 | F299: Wed, 03 Jun 2026 00:00:00 GMT | G299: =A299/D299-1 -> -0.0053365467 | I299: 171.97869 | J299: 175.83588 | K299: 171.97869 | L299: 172.43717 | M299: 4248594.7 | N299: Wed, 03 Jun 2026 00:00:00 GMT | O299: =I299/L299-1 -> -0.0026588058 | Q299: 0.005 | R299: 57 | T299: 0 | U299: =_xlfn.NORM.DIST(T299,$S$240,$S$242,FALSE) -> 30.835194
A300: 696.23232 | B300: 697.11973 | C300: 693.75952 | D300: 694.03871 | E300: 4712080 | F300: Tue, 02 Jun 2026 00:00:00 GMT | G300: =A300/D300-1 -> 0.0031606471 | I300: 173.68303 | J300: 175.1681 | K300: 172.41724 | L300: 173.31426 | M300: 4385568.6 | N300: Tue, 02 Jun 2026 00:00:00 GMT | O300: =I300/L300-1 -> 0.0021277819 | Q300: 0.006 | R300: 46 | T300: =T299+0.001 -> 0.001 | U300: =_xlfn.NORM.DIST(T300,$S$240,$S$242,FALSE) -> 30.762725
A301: 695.2751 | B301: 697.02999 | C301: 691.92486 | D301: 692.52312 | E301: 9977807.5 | F301: Mon, 01 Jun 2026 00:00:00 GMT | G301: =A301/D301-1 -> 0.0039738532 | I301: 173.83254 | J301: 178.09827 | K301: 173.55346 | L301: 176.8525 | M301: 5488129.4 | N301: Mon, 01 Jun 2026 00:00:00 GMT | O301: =I301/L301-1 -> -0.017076195 | Q301: 0.007 | R301: 50 | T301: =T300+0.001 -> 0.002 | U301: =_xlfn.NORM.DIST(T301,$S$240,$S$242,FALSE) -> 30.507613
A302: 693.47036 | B302: 694.97598 | C302: 691.87501 | D302: 692.98178 | E302: 5053895.6 | F302: Fri, 29 May 2026 00:00:00 GMT | G302: =A302/D302-1 -> 0.00070503597 | I302: 179.06515 | J302: 179.5037 | K302: 175.45714 | L302: 178.31764 | M302: 8747363.8 | N302: Fri, 29 May 2026 00:00:00 GMT | O302: =I302/L302-1 -> 0.0041920519 | Q302: 0.008 | R302: 41 | T302: =T301+0.001 -> 0.003 | U302: =_xlfn.NORM.DIST(T302,$S$240,$S$242,FALSE) -> 30.074398
A303: 691.89495 | B303: 692.27385 | C303: 686.84964 | D303: 687.757 | E303: 8469446.4 | F303: Thu, 28 May 2026 00:00:00 GMT | G303: =A303/D303-1 -> 0.0060165855 | I303: 178.36747 | J303: 180.9489 | K303: 176.15482 | L303: 176.21462 | M303: 5806604 | N303: Thu, 28 May 2026 00:00:00 GMT | O303: =I303/L303-1 -> 0.012217195 | Q303: 0.009 | R303: 33 | T303: =T302+0.001 -> 0.004 | U303: =_xlfn.NORM.DIST(T303,$S$240,$S$242,FALSE) -> 29.470735
A304: 687.95642 | B304: 688.77404 | C304: 685.92234 | D304: 688.35526 | E304: 7356729.2 | F304: Wed, 27 May 2026 00:00:00 GMT | G304: =A304/D304-1 -> -0.00057940785 | I304: 176.00532 | J304: 178.20591 | K304: 175.12395 | L304: 177.89903 | M304: 4511333.3 | N304: Wed, 27 May 2026 00:00:00 GMT | O304: =I304/L304-1 -> -0.010644854 | Q304: 0.01 | R304: 44 | T304: =T303+0.001 -> 0.005 | U304: =_xlfn.NORM.DIST(T304,$S$240,$S$242,FALSE) -> 28.707165
A305: 688.00627 | B305: 689.50242 | C305: 686.08188 | D305: 687.64732 | E305: 6622042.8 | F305: Tue, 26 May 2026 00:00:00 GMT | G305: =A305/D305-1 -> 0.00052200392 | I305: 178.37744 | J305: 178.61664 | K305: 175.48704 | L305: 177.41065 | M305: 5519352.5 | N305: Tue, 26 May 2026 00:00:00 GMT | O305: =I305/L305-1 -> 0.0054494382 | Q305: 0.011 | R305: 39 | T305: =T304+0.001 -> 0.006 | U305: =_xlfn.NORM.DIST(T305,$S$240,$S$242,FALSE) -> 27.796808
A306: 683.55923 | B306: 686.58043 | C306: 682.49223 | D306: 684.10763 | E306: 4276144.9 | F306: Fri, 22 May 2026 00:00:00 GMT | G306: =A306/D306-1 -> -0.00080163242 | I306: 176.42393 | J306: 177.01197 | K306: 174.67972 | L306: 176.15482 | M306: 4092671.7 | N306: Fri, 22 May 2026 00:00:00 GMT | O306: =I306/L306-1 -> 0.0015276678 | Q306: 0.012 | R306: 30 | T306: =T305+0.001 -> 0.007 | U306: =_xlfn.NORM.DIST(T306,$S$240,$S$242,FALSE) -> 26.754994
A307: 680.8571 | B307: 682.83633 | C307: 675.65225 | D307: 677.10801 | E307: 7310162.6 | F307: Thu, 21 May 2026 00:00:00 GMT | G307: =A307/D307-1 -> 0.0055369029 | I307: 174.66975 | J307: 175.86082 | K307: 171.99978 | L307: 173.2901 | M307: 3595915.9 | N307: Thu, 21 May 2026 00:00:00 GMT | O307: =I307/L307-1 -> 0.0079615098 | Q307: 0.013 | R307: 16 | T307: =T306+0.001 -> 0.008 | U307: =_xlfn.NORM.DIST(T307,$S$240,$S$242,FALSE) -> 25.598829
A308: 679.59078 | B308: 680.01953 | C308: 672.78072 | D308: 674.35603 | E308: 5453356.5 | F308: Wed, 20 May 2026 00:00:00 GMT | G308: =A308/D308-1 -> 0.0077625976 | I308: 173.54817 | J308: 174.84841 | K308: 171.71194 | L308: 174.16355 | M308: 6630832.6 | N308: Wed, 20 May 2026 00:00:00 GMT | O308: =I308/L308-1 -> -0.0035333675 | Q308: 0.014 | R308: 21 | T308: =T307+0.001 -> 0.009 | U308: =_xlfn.NORM.DIST(T308,$S$240,$S$242,FALSE) -> 24.346729
A309: 672.63105 | B309: 676.18071 | C309: 670.59698 | D309: 673.59824 | E309: 5611397.2 | F309: Tue, 19 May 2026 00:00:00 GMT | G309: =A309/D309-1 -> -0.0014358458 | I309: 173.19085 | J309: 175.68216 | K309: 173.0767 | L309: 174.97745 | M309: 5513352.5 | N309: Tue, 19 May 2026 00:00:00 GMT | O309: =I309/L309-1 -> -0.010210449 | Q309: 0.015 | R309: 19 | T309: =T308+0.001 -> 0.01 | U309: =_xlfn.NORM.DIST(T309,$S$240,$S$242,FALSE) -> 23.017941
A310: 676.93851 | B310: 679.63067 | C310: 672.29204 | D310: 678.20482 | E310: 7569986.9 | F310: Mon, 18 May 2026 00:00:00 GMT | G310: =A310/D310-1 -> -0.0018671528 | I310: 174.63998 | J310: 174.77894 | K310: 169.72683 | L310: 170.40177 | M310: 5327973.6 | N310: Mon, 18 May 2026 00:00:00 GMT | O310: =I310/L310-1 -> 0.024871855 | Q310: 0.016 | R310: 16 | T310: =T309+0.001 -> 0.011 | U310: =_xlfn.NORM.DIST(T310,$S$240,$S$242,FALSE) -> 21.632046
A311: 677.46697 | B311: 681.53512 | C311: 676.47087 | D311: 680.05942 | E311: 6421958.6 | F311: Fri, 15 May 2026 00:00:00 GMT | G311: =A311/D311-1 -> -0.0038120931 | I311: 169.90549 | J311: 174.66975 | K311: 169.50847 | L311: 174.21318 | M311: 6775910.4 | N311: Fri, 15 May 2026 00:00:00 GMT | O311: =I311/L311-1 -> -0.024726527 | Q311: 0.017 | R311: 13 | T311: =T310+0.001 -> 0.012 | U311: =_xlfn.NORM.DIST(T311,$S$240,$S$242,FALSE) -> 20.208499
... A339: 604.28012 | B339: 604.54933 | C339: 596.76201 | D339: 601.82726 | E339: 6164208.3 | F339: Tue, 07 Apr 2026 00:00:00 GMT | G339: =A339/D339-1 -> 0.0040756818 | I339: 196.4464 | J339: 196.67469 | K339: 194.05435 | L339: 195.9402 | M339: 3041064.1 | N339: Tue, 07 Apr 2026 00:00:00 GMT | O339: =I339/L339-1 -> 0.0025834558 | Q339: 0.045 | R339: 0 | T339: =T338+0.001 -> 0.04 | U339: =_xlfn.NORM.DIST(T339,$S$240,$S$242,FALSE) -> 0.26564832
A340: 603.91119 | B340: 604.67895 | C340: 600.86008 | D340: 601.16918 | E340: 6300935.5 | F340: Mon, 06 Apr 2026 00:00:00 GMT | G340: =A340/D340-1 -> 0.0045611358 | I340: 196.93275 | J340: 197.15112 | K340: 193.54814 | L340: 194.76402 | M340: 2308241.5 | N340: Mon, 06 Apr 2026 00:00:00 GMT | O340: =I340/L340-1 -> 0.011135176 | Q340: More | R340: 5 | T340: =T339+0.001 -> 0.041 | U340: =_xlfn.NORM.DIST(T340,$S$240,$S$242,FALSE) -> 0.2086879
A341: 601.23897 | B341: 603.03375 | C341: 591.30989 | D341: 592.50441 | E341: 12776618 | F341: Thu, 02 Apr 2026 00:00:00 GMT | G341: =A341/D341-1 -> 0.014741767 | I341: 194.74913 | J341: 195.96998 | K341: 192.18834 | L341: 193.62755 | M341: 4101903.9 | N341: Thu, 02 Apr 2026 00:00:00 GMT | O341: =I341/L341-1 -> 0.0057924954 | T341: =T340+0.001 -> 0.042 | U341: =_xlfn.NORM.DIST(T341,$S$240,$S$242,FALSE) -> 0.16296441
A342: 600.55098 | B342: 603.59212 | C342: 598.52687 | D342: 599.31458 | E342: 11314501 | F342: Wed, 01 Apr 2026 00:00:00 GMT | G342: =A342/D342-1 -> 0.002063022 | I342: 193.27023 | J342: 195.17593 | K342: 192.10894 | L342: 193.02209 | M342: 4154412.5 | N342: Wed, 01 Apr 2026 00:00:00 GMT | O342: =I342/L342-1 -> 0.0012855453 | T342: =T341+0.001 -> 0.043 | U342: =_xlfn.NORM.DIST(T342,$S$240,$S$242,FALSE) -> 0.12650089
A343: 595.81477 | B343: 597.11099 | C343: 584.79686 | D343: 585.64439 | E343: 12375375 | F343: Tue, 31 Mar 2026 00:00:00 GMT | G343: =A343/D343-1 -> 0.017366136 | I343: 191.46378 | J343: 191.99976 | K343: 186.18339 | L343: 187.73177 | M343: 5352520.2 | N343: Tue, 31 Mar 2026 00:00:00 GMT | O343: =I343/L343-1 -> 0.019879454 | T343: =T342+0.001 -> 0.044 | U343: =_xlfn.NORM.DIST(T343,$S$240,$S$242,FALSE) -> 0.09761121
A344: 579.24303 | B344: 586.96056 | C344: 576.78021 | D344: 586.68137 | E344: 11776669 | F344: Mon, 30 Mar 2026 00:00:00 GMT | G344: =A344/D344-1 -> -0.012678666 | I344: 185.75659 | J344: 191.56303 | K344: 184.18835 | L344: 191.05683 | M344: 5056405.9 | N344: Mon, 30 Mar 2026 00:00:00 GMT | O344: =I344/L344-1 -> -0.027741701 | T344: =T343+0.001 -> 0.045 | U344: =_xlfn.NORM.DIST(T344,$S$240,$S$242,FALSE) -> 0.074870565
A345: 581.26714 | B345: 589.11428 | C345: 580.33984 | D345: 588.96472 | E345: 11637657 | F345: Fri, 27 Mar 2026 00:00:00 GMT | G345: =A345/D345-1 -> -0.013069682 | I345: 188.29753 | J345: 191.67221 | K345: 188.04939 | L345: 190.97743 | M345: 3833404.5 | N345: Fri, 27 Mar 2026 00:00:00 GMT | O345: =I345/L345-1 -> -0.014032535 | T345: =T344+0.001 -> 0.046 | U345: =_xlfn.NORM.DIST(T345,$S$240,$S$242,FALSE) -> 0.057085765
...

Sheet Product Lines

Sheet Management

Sheet Table Formatting
B2: [Bold Title] | G2: [Bold Title]
B3: Line Titles | G3: <-- General
B4: Line Titles | G4: <-- Info
B5: Line Titles | G5: <-- General
B6: Line Titles | G6: <-- Info
B7: Line Titles | G7: <-- General
B8: Line Titles | G8: <-- Info
