Workbook

Sheet Main
B2: SHOP
B3: Price | C3: 168.81 | D3: 10/22/2026
B4: SO | C4: 1295.22 | D4: Q2'26
B5: MC | C5: =C3*C4 -> 218646.09
B6: Cash | C6: =1656+3291 -> 4947 | D6: Q2'26
B7: Debt | C7: 0 | D7: Q2'26
B8: EV | C8: =C5-C6+C7 -> 213699.09
B10: Shopify Inc. (SHOP)
B12: Founder(s): Tobias Lutke, Daniel Weinand and Scott Lake | F12: Registered Exchange: NASDAQ | N12: Resources:
B13: Founded: 2004 | F13: Address: 151 O'Connor Street, Ottawa, ON Canada | N13: SEC filings | Q13: https://www.sec.gov/edgar/browse/?CIK=1594805&owner=exclude
B14: Headquarters: Ottawa, ON | F14: Investor Relations Contact: | N14: Company Homepage | Q14: https://www.shopify.com/
B15: Current CEO: Tobias Lutke | F15: Investors Relation Department | O15: Company IR Page | R15: https://www.shopify.com/investors
B16: Employees: 7,600 | F16: Phone: | G16: (613) 241 - 2828 | I16: Email: | N16: Earnings Calls | Q16: https://app.godelterminal.com/
B17: Industry: Software Services | N17: Equity Analysis | Q17: https://stockanalysis.com/stocks/shop/company/
B18: Sector: Technology | N18: MacroTrends | Q18: https://www.macrotrends.net/stocks/charts/SHOP/shopify/income-statement
B19: IPO: May, 21 2015 -- $1.27B valuation | N19: ROIC, WACC | Q19: https://www.gurufocus.com/term/wacc/SHOP
B20: Fiscal Year: [January - December] | N20: Godel Terminal | Q20: https://app.godelterminal.com/
A22: Company Overview:
B23: Shopify Inc., a commerce technology company, provides tools to start, scale, market, and run a business of various sizes in Canada, the United States, Europe, the Middle East, Africa, the Asia Pacific, and Latin America
B24: The Company offers Shopify platform that enables merchants to manage products and inventory, process orders and payments, fulfill and ship orders, build customer relationships, source products, leverage analytics, and reporting and access financing for running their business
C25: Supports partner businesses across all of their sales channels, including web and mobile storefronts, physical retail locations, social media storefronts, and marketplaces
B26: It also provides Shopify Payments, a fully integrated payment processing service that allows merchants to accept and process payment cards online and offline
C27: In addition, the company engages in the sale of themes and apps; shipping labels through Shopify Shipping; point-of-sale hardware, advertising on the Shopify App Store … and Shop Campaigns for buyer acquisitions, as well as registration of domain names
B28: Shopify Inc. was incorporated in 2004 and is based in Ottawa, Canada
C29: The Company was formerly known as Jaded Pixel Technologies Inc. and changed its name to Shopify Inc. in November 2011
A33: Business Segments and Geographical Info:
B34: [Begin researching fundamentals / core business … begin with SEC filings, but expand and use all public resources available]

Sheet Model
B1: [Use for Graphing] | C1: Q1 2024 | G1: Q1 2025 | K1: Q1 2026
B2: Quarterly
B3: Revenues | C3: Q1 2024 | D3: Q2 2024 | E3: Q3 2024 | F3: Q4 2024 | G3: Q1 2025 | H3: Q2 2025 | I3: Q3 2025 | J3: Q4 2025 | K3: Q1 2026 | L3: Q2 2026 | M3: Q3 2026 | N3: Q4 2026 | W3: 2024 | X3: 2025 | Y3: =X3+1 -> 2026 | Z3: =Y3+1 -> 2027 | AA3: =Z3+1 -> 2028 | AB3: =AA3+1 -> 2029 | AC3: =AB3+1 -> 2030 | AD3: =AC3+1 -> 2031 | AE3: =AD3+1 -> 2032 | AF3: =AE3+1 -> 2033 | ... CF3: =CE3+1 -> 2085
B4: U.S. | C4: 1198 | D4: 1323 | E4: 1377 | F4: =5708-SUM(C4:E4) -> 1810 | G4: 1499 | H4: 1703 | I4: 1783 | J4: =7331-SUM(G4:I4) -> 2346 | K4: 2001 | L4: 2283 | M4: 2283 | W4: =SUM(C4:F4) -> 5708 | X4: =SUM(G4:J4) -> 7331 | Y4: =X4*(1+Y11) -> 9823.54 | Z4: =Y4*(1+Z11) -> 12967.073 | AA4: =Z4*(1+AA11) -> 16857.195 | AB4: =AA4*(1+AB11) -> 21408.637 | AC4: =AB4*(1+AC11) -> 26760.796 | AD4: =AC4*(1+AD11) -> 32915.78 | AE4: =AD4*(1+AE11) -> 39828.093 | AF4: =AE4*(1+AF11) -> 47395.431 | ... AH4: =AG4*(1+AH11) -> 64325.079
B5: Canada | C5: 99 | D5: 114 | E5: 119 | F5: =483-SUM(C5:E5) -> 151 | G5: 119 | H5: 133 | I5: 138 | J5: =567-SUM(G5:I5) -> 177 | K5: 147 | L5: 171 | M5: 171 | W5: =SUM(C5:F5) -> 483 | X5: =SUM(G5:J5) -> 567 | Y5: =X5*(1+Y12) -> 714.42 | Z5: =Y5*(1+Z12) -> 878.7366 | AA5: =Z5*(1+AA12) -> 1072.0587 | AB5: =AA5*(1+AB12) -> 1286.4704 | AC5: =AB5*(1+AC12) -> 1518.0351 | AD5: =AC5*(1+AD12) -> 1760.9207 | AE5: =AD5*(1+AE12) -> 1989.8403 | AF5: =AE5*(1+AF12) -> 2188.8244 | ... AH5: =AG5*(1+AH12) -> 2505.7661
B6: Europe | C6: 354 | D6: 381 | E6: 418 | F6: =1707-SUM(C6:E6) -> 554 | G6: 461 | H6: 554 | I6: 615 | J6: =2426-SUM(G6:I6) -> 796 | K6: 653 | L6: 721 | M6: 721 | W6: =SUM(C6:F6) -> 1707 | X6: =SUM(G6:J6) -> 2426 | Y6: =X6*(1+Y13) -> 3347.88 | Z6: =Y6*(1+Z13) -> 4653.5532 | AA6: =Z6*(1+AA13) -> 6096.1547 | AB6: =AA6*(1+AB13) -> 7681.1549 | AC6: =AB6*(1+AC13) -> 9294.1974 | AD6: =AC6*(1+AD13) -> 10967.153 | AE6: =AD6*(1+AE13) -> 12612.226 | AF6: =AE6*(1+AF13) -> 14251.815 | ... AH6: =AG6*(1+AH13) -> 17243.271
B7: APAC | C7: 189 | D7: 203 | E7: 223 | F7: =885-SUM(C7:E7) -> 270 | G7: 240 | H7: 265 | I7: 282 | J7: =1128-SUM(G7:I7) -> 341 | K7: 312 | L7: 346 | M7: 346 | W7: =SUM(C7:F7) -> 885 | X7: =SUM(G7:J7) -> 1128 | Y7: =X7*(1+Y14) -> 1477.68 | Z7: =Y7*(1+Z14) -> 1965.3144 | AA7: =Z7*(1+AA14) -> 2495.9493 | AB7: =AA7*(1+AB14) -> 3094.9771 | AC7: =AB7*(1+AC14) -> 3744.9223 | AD7: =AC7*(1+AD14) -> 4419.0083 | AE7: =AD7*(1+AE14) -> 5081.8596 | AF7: =AE7*(1+AF14) -> 5691.6827 | ... AH7: =AG7*(1+AH14) -> 6761.7191
B8: Rest of World | C8: 21 | D8: 24 | E8: 25 | F8: =97-SUM(C8:E8) -> 27 | G8: 41 | H8: 25 | I8: 26 | J8: =104-SUM(G8:I8) -> 12 | K8: 57 | L8: 62 | M8: 62 | W8: =SUM(C8:F8) -> 97 | X8: =SUM(G8:J8) -> 104 | Y8: =X8*(1+Y15) -> 202.8 | Z8: =Y8*(1+Z15) -> 275.808 | AA8: =Z8*(1+AA15) -> 353.03424 | AB8: =AA8*(1+AB15) -> 425.40626 | AC8: =AB8*(1+AC15) -> 495.59829 | AD8: =AC8*(1+AD15) -> 562.50406 | AE8: =AD8*(1+AE15) -> 618.75447 | AF8: =AE8*(1+AF15) -> 668.25482 | ... AH8: =AG8*(1+AH15) -> 736.68412
B9: Ttl Revenues | C9: =SUM(C4:C8) -> 1861 | D9: =SUM(D4:D8) -> 2045 | E9: =SUM(E4:E8) -> 2162 | F9: =SUM(F4:F8) -> 2812 | G9: =SUM(G4:G8) -> 2360 | H9: =SUM(H4:H8) -> 2680 | I9: =SUM(I4:I8) -> 2844 | J9: =SUM(J4:J8) -> 3672 | ... M9: =SUM(M4:M8) -> 3583 | W9: =SUM(C9:F9) -> 8880 | X9: =SUM(G9:J9) -> 11556 | Y9: =SUM(Y4:Y8) -> 15566.32 | Z9: =SUM(Z4:Z8) -> 20740.485 | AA9: =SUM(AA4:AA8) -> 26874.392 | AB9: =SUM(AB4:AB8) -> 33896.646 | AC9: =SUM(AC4:AC8) -> 41813.55 | AD9: =SUM(AD4:AD8) -> 50625.366 | AE9: =SUM(AE4:AE8) -> 60130.774 | AF9: =SUM(AF4:AF8) -> 70196.008 | ... AH9: =SUM(AH4:AH8) -> 91572.52
B11: U.S. Growth Y/y | G11: =G4/C4-1 -> 0.25125209 | H11: =H4/D4-1 -> 0.287226 | I11: =I4/E4-1 -> 0.29484386 | J11: =J4/F4-1 -> 0.2961326 | K11: =K4/G4-1 -> 0.33488993 | L11: =L4/H4-1 -> 0.34057546 | M11: =M4/I4-1 -> 0.28042625 | X11: =X4/W4-1 -> 0.28433777 | Y11: 0.34 | Z11: 0.32 | AA11: 0.3 | AB11: 0.27 | AC11: 0.25 | AD11: 0.23 | AE11: 0.21 | AF11: 0.19 | AG11: 0.17 | AH11: 0.16
B12: Canada Growth Y/y | G12: =G5/C5-1 -> 0.2020202 | H12: =H5/D5-1 -> 0.16666667 | I12: =I5/E5-1 -> 0.15966387 | J12: =J5/F5-1 -> 0.17218543 | K12: =K5/G5-1 -> 0.23529412 | L12: =L5/H5-1 -> 0.28571429 | M12: =M5/I5-1 -> 0.23913043 | X12: =X5/W5-1 -> 0.17391304 | Y12: 0.26 | Z12: 0.23 | AA12: 0.22 | AB12: 0.2 | AC12: 0.18 | AD12: 0.16 | AE12: 0.13 | AF12: 0.1 | AG12: 0.08 | AH12: 0.06
B13: Europe Growth Y/y | G13: =G6/C6-1 -> 0.30225989 | H13: =H6/D6-1 -> 0.45406824 | I13: =I6/E6-1 -> 0.47129187 | J13: =J6/F6-1 -> 0.4368231 | K13: =K6/G6-1 -> 0.4164859 | L13: =L6/H6-1 -> 0.30144404 | M13: =M6/I6-1 -> 0.17235772 | X13: =X6/W6-1 -> 0.4212068 | Y13: 0.38 | Z13: 0.39 | AA13: 0.31 | AB13: 0.26 | AC13: 0.21 | AD13: 0.18 | AE13: 0.15 | AF13: 0.13 | AG13: 0.11 | AH13: 0.09
B14: APAC Growth Y/y | G14: =G7/C7-1 -> 0.26984127 | H14: =H7/D7-1 -> 0.30541872 | I14: =I7/E7-1 -> 0.26457399 | J14: =J7/F7-1 -> 0.26296296 | K14: =K7/G7-1 -> 0.3 | L14: =L7/H7-1 -> 0.30566038 | M14: =M7/I7-1 -> 0.22695035 | X14: =X7/W7-1 -> 0.27457627 | Y14: 0.31 | Z14: 0.33 | AA14: 0.27 | AB14: 0.24 | AC14: 0.21 | AD14: 0.18 | AE14: 0.15 | AF14: 0.12 | AG14: 0.1 | AH14: 0.08
B15: Rest of World Growth Y/y | G15: =G8/C8-1 -> 0.95238095 | H15: =H8/D8-1 -> 0.041666667 | I15: =I8/E8-1 -> 0.04 | J15: =J8/F8-1 -> -0.55555556 | K15: =K8/G8-1 -> 0.3902439 | L15: =L8/H8-1 -> 1.48 | M15: =M8/I8-1 -> 1.3846154 | X15: =X8/W8-1 -> 0.072164948 | Y15: 0.95 | Z15: 0.36 | AA15: 0.28 | AB15: 0.205 | AC15: 0.165 | AD15: 0.135 | AE15: 0.1 | AF15: 0.08 | AG15: 0.06 | AH15: 0.04
B16: Ttl Revenue Growth Y/y | G16: =G9/C9-1 -> 0.26813541 | H16: =H9/D9-1 -> 0.31051345 | I16: =I9/E9-1 -> 0.31544866 | J16: =J9/F9-1 -> 0.30583215 | K16: =K9/G9-1 -> 0.34322034 | L16: =L9/H9-1 -> 0.3369403 | M16: =M9/I9-1 -> 0.25984529 | X16: =X9/W9-1 -> 0.30135135 | Y16: =Y9/X9-1 -> 0.34703358 | Z16: =Z9/Y9-1 -> 0.33239488 | AA16: =AA9/Z9-1 -> 0.29574557 | AB16: =AB9/AA9-1 -> 0.2612991 | AC16: =AC9/AB9-1 -> 0.23356009 | AD16: =AD9/AC9-1 -> 0.21074069 | AE16: =AE9/AD9-1 -> 0.18775979 | ... AH16: =AH9/AG9-1 -> 0.13606077
B18: U.S. % of Ttl Revenues | C18: =C4/C9 -> 0.64373992 | D18: =D4/D9 -> 0.64694377 | E18: =E4/E9 -> 0.63691027 | F18: =F4/F9 -> 0.64366999 | G18: =G4/G9 -> 0.63516949 | H18: =H4/H9 -> 0.63544776 | I18: =I4/I9 -> 0.6269339 | J18: =J4/J9 -> 0.63888889 | ... M18: =M4/M9 -> 0.63717555 | W18: =W4/W9 -> 0.64279279 | X18: =X4/X9 -> 0.63438906
B19: Canada % of Ttl Revenues | C19: =C5/C9 -> 0.053197206 | D19: =D5/D9 -> 0.055745721 | E19: =E5/E9 -> 0.055041628 | F19: =F5/F9 -> 0.053698435 | G19: =G5/G9 -> 0.050423729 | H19: =H5/H9 -> 0.049626866 | I19: =I5/I9 -> 0.048523207 | J19: =J5/J9 -> 0.048202614 | ... M19: =M5/M9 -> 0.04772537 | W19: =W5/W9 -> 0.054391892 | X19: =X5/X9 -> 0.049065421
B20: Europe % of Ttl Revenues | C20: =C6/C9 -> 0.19022031 | D20: =D6/D9 -> 0.18630807 | E20: =E6/E9 -> 0.1933395 | F20: =F6/F9 -> 0.1970128 | G20: =G6/G9 -> 0.19533898 | H20: =H6/H9 -> 0.20671642 | I20: =I6/I9 -> 0.21624473 | J20: =J6/J9 -> 0.2167756 | ... M20: =M6/M9 -> 0.20122802 | W20: =W6/W9 -> 0.19222973 | X20: =X6/X9 -> 0.20993423
B21: APAC % of Ttl Revenues | C21: =C7/C9 -> 0.1015583 | D21: =D7/D9 -> 0.099266504 | E21: =E7/E9 -> 0.10314524 | F21: =F7/F9 -> 0.09601707 | G21: =G7/G9 -> 0.10169492 | H21: =H7/H9 -> 0.098880597 | I21: =I7/I9 -> 0.099156118 | J21: =J7/J9 -> 0.092864924 | ... M21: =M7/M9 -> 0.096567123 | W21: =W7/W9 -> 0.099662162 | X21: =X7/X9 -> 0.09761163
B22: Rest of World % of Ttl Revenues | C22: =C8/C9 -> 0.011284256 | D22: =D8/D9 -> 0.011735941 | E22: =E8/E9 -> 0.011563367 | F22: =F8/F9 -> 0.009601707 | G22: =G8/G9 -> 0.017372881 | H22: =H8/H9 -> 0.0093283582 | I22: =I8/I9 -> 0.0091420534 | J22: =J8/J9 -> 0.0032679739 | ... M22: =M8/M9 -> 0.017303935 | W22: =W8/W9 -> 0.010923423 | X22: =X8/X9 -> 0.0089996539
B24: Subscription Revenue | C24: 511 | D24: 563 | E24: 610 | F24: =2350-SUM(C24:E24) -> 666 | G24: 620 | H24: 656 | I24: 699 | J24: =2752-SUM(G24:I24) -> 777 | K24: 750 | L24: 802 | M24: 802 | W24: =SUM(C24:F24) -> 2350 | X24: =SUM(G24:J24) -> 2752
B25: Merchant Revenue | C25: 1350 | D25: 1482 | E25: 1552 | F25: =6530-SUM(C25:E25) -> 2146 | G25: 1740 | H25: 2024 | I25: 2145 | J25: =8804-SUM(G25:I25) -> 2895 | K25: 2420 | L25: 2781 | M25: 2781 | W25: =SUM(C25:F25) -> 6530 | X25: =SUM(G25:J25) -> 8804
B26: Ttl Revenues | C26: =SUM(C24:C25) -> 1861 | D26: =SUM(D24:D25) -> 2045 | E26: =SUM(E24:E25) -> 2162 | F26: =SUM(F24:F25) -> 2812 | G26: =SUM(G24:G25) -> 2360 | H26: =SUM(H24:H25) -> 2680 | I26: =SUM(I24:I25) -> 2844 | J26: =SUM(J24:J25) -> 3672 | ... M26: =SUM(M24:M25) -> 3583 | W26: =SUM(C26:F26) -> 8880 | X26: =SUM(G26:J26) -> 11556
B28: Subscription Costs | C28: 95 | D28: 97 | E28: 108 | F28: =434-SUM(C28:E28) -> 134 | G28: 123 | H28: 121 | I28: 128 | J28: =520-SUM(G28:I28) -> 148 | K28: 148 | L28: 163 | M28: 163 | W28: =SUM(C28:F28) -> 434 | X28: =SUM(G28:J28) -> 520
B29: Merchant Costs | C29: 809 | D29: 903 | E29: 936 | F29: =3974-SUM(C29:E29) -> 1326 | G29: 1068 | H29: 1257 | I29: 1325 | J29: =5481-SUM(G29:I29) -> 1831 | K29: 1476 | L29: 1712 | M29: 1712 | W29: =SUM(C29:F29) -> 3974 | X29: =SUM(G29:J29) -> 5481
B30: Ttl Costs | C30: =SUM(C28:C29) -> 904 | D30: =SUM(D28:D29) -> 1000 | E30: =SUM(E28:E29) -> 1044 | F30: =SUM(F28:F29) -> 1460 | G30: =SUM(G28:G29) -> 1191 | H30: =SUM(H28:H29) -> 1378 | I30: =SUM(I28:I29) -> 1453 | J30: =SUM(J28:J29) -> 1979 | ... M30: =SUM(M28:M29) -> 1875 | W30: =SUM(C30:F30) -> 4408 | X30: =SUM(G30:J30) -> 6001
B32: Revenues | C32: =C9 -> 1861 | D32: =D9 -> 2045 | E32: =E9 -> 2162 | F32: =F9 -> 2812 | G32: =G9 -> 2360 | H32: =H9 -> 2680 | I32: =I9 -> 2844 | J32: =J9 -> 3672 | ... M32: =M9 -> 3583 | W32: =SUM(C32:F32) -> 8880 | X32: =SUM(G32:J32) -> 11556 | Y32: =Y9 -> 15566.32 | Z32: =Z9 -> 20740.485 | AA32: =AA9 -> 26874.392 | AB32: =AB9 -> 33896.646 | AC32: =AC9 -> 41813.55 | AD32: =AD9 -> 50625.366 | AE32: =AE9 -> 60130.774 | AF32: =AF9 -> 70196.008 | ... AH32: =AH9 -> 91572.52
B33: COGS | C33: =C30 -> 904 | D33: =D30 -> 1000 | E33: =E30 -> 1044 | F33: =F30 -> 1460 | G33: =G30 -> 1191 | H33: =H30 -> 1378 | I33: =I30 -> 1453 | J33: =J30 -> 1979 | ... M33: =M30 -> 1875 | W33: =SUM(C33:F33) -> 4408 | X33: =SUM(G33:J33) -> 6001 | Y33: =Y32*(1-Y51) -> 8083.5485 | Z33: =Z32*(1-Z51) -> 10577.647 | AA33: =AA32*(1-AA51) -> 13437.196 | AB33: =AB32*(1-AB51) -> 16778.84 | AC33: =AC32*(1-AC51) -> 20488.639 | AD33: =AD32*(1-AD51) -> 24679.866 | AE33: =AE32*(1-AE51) -> 29163.425 | AF33: =AF32*(1-AF51) -> 33869.574 | ... AH33: =AH32*(1-AH51) -> 43954.81
B34: GP | C34: =C32-C33 -> 957 | D34: =D32-D33 -> 1045 | E34: =E32-E33 -> 1118 | F34: =F32-F33 -> 1352 | G34: =G32-G33 -> 1169 | H34: =H32-H33 -> 1302 | I34: =I32-I33 -> 1391 | J34: =J32-J33 -> 1693 | ... M34: =M32-M33 -> 1708 | W34: =SUM(C34:F34) -> 4472 | X34: =SUM(G34:J34) -> 5555 | Y34: =Y32*Y51 -> 7482.7715 | Z34: =Z32*Z51 -> 10162.838 | AA34: =AA32*AA51 -> 13437.196 | AB34: =AB32*AB51 -> 17117.806 | AC34: =AC32*AC51 -> 21324.91 | AD34: =AD32*AD51 -> 25945.5 | AE34: =AE32*AE51 -> 30967.348 | AF34: =AF32*AF51 -> 36326.434 | ... AH34: =AH32*AH51 -> 47617.71
B35: Sales & Marketing | C35: 361 | D35: 353 | E35: 331 | F35: =1393-SUM(C35:E35) -> 348 | G35: 405 | H35: 415 | I35: 410 | J35: =1663-SUM(G35:I35) -> 433 | K35: 496 | L35: 498 | M35: 498 | W35: =SUM(C35:F35) -> 1393 | X35: =SUM(G35:J35) -> 1663 | Y35: =Y32*Y52 -> 2240.1168 | Z35: =Z32*Z52 -> 2841.4464 | AA35: =AA32*AA52 -> 3547.4197 | AB35: =AB32*AB52 -> 4304.874 | AC35: =AC32*AC52 -> 5226.6937 | AD35: =AD32*AD52 -> 6277.5453 | AE35: =AE32*AE52 -> 7396.0852 | AF35: =AF32*AF52 -> 8563.913 | ... AH35: =AH32*AH52 -> 10988.702
B36: R&D | C36: 335 | D36: 349 | E36: 332 | F36: =1367-SUM(C36:E36) -> 351 | G36: 377 | H36: 394 | I36: 375 | J36: =1536-SUM(G36:I36) -> 390 | K36: 437 | L36: 445 | M36: 445 | W36: =SUM(C36:F36) -> 1367 | X36: =SUM(G36:J36) -> 1536 | Y36: =Y32*Y53 -> 2117.0195 | Z36: =Z32*Z53 -> 2799.9655 | AA36: =AA32*AA53 -> 3547.4197 | AB36: =AB32*AB53 -> 4372.6673 | AC36: =AC32*AC53 -> 5310.3208 | AD36: =AD32*AD53 -> 6328.1707 | AE36: =AE32*AE53 -> 7215.6928 | AF36: =AF32*AF53 -> 8072.541 | ... AH36: =AH32*AH53 -> 9615.1146
B37: General & Administrative | C37: 124 | D37: 60 | E37: 114 | F37: =410-SUM(C37:E37) -> 112 | G37: 109 | H37: 122 | I37: 115 | J37: =471-SUM(G37:I37) -> 125 | K37: 115 | L37: 136 | M37: 136 | W37: =SUM(C37:F37) -> 410 | X37: =SUM(G37:J37) -> 471 | Y37: =Y32*Y54 -> 634.45281 | Z37: =Z32*Z54 -> 788.13843 | AA37: =AA32*AA54 -> 967.47809 | AB37: =AB32*AB54 -> 1186.3826 | AC37: =AC32*AC54 -> 1463.4742 | AD37: =AD32*AD54 -> 1771.8878 | AE37: =AE32*AE54 -> 2104.5771 | AF37: =AF32*AF54 -> 2456.8603 | ... AH37: =AH32*AH54 -> 3205.0382
B38: Transaction & Loan Losses | C38: 51 | D38: 42 | E38: 58 | F38: =227-SUM(C38:E38) -> 76 | G38: 75 | H38: 80 | I38: 148 | J38: =417-SUM(G38:I38) -> 114 | K38: 116 | L38: 141 | M38: 141 | W38: =SUM(C38:F38) -> 227 | X38: =SUM(G38:J38) -> 417 | Y38: =Y32*Y55 -> 561.713 | Z38: =Z32*Z55 -> 705.17649 | AA38: =AA32*AA55 -> 886.85492 | AB38: =AB32*AB55 -> 1084.6927 | AC38: =AC32*AC55 -> 1296.22 | AD38: =AD32*AD55 -> 1518.761 | AE38: =AE32*AE55 -> 1803.9232 | AF38: =AF32*AF55 -> 2105.8803 | ... AH38: =AH32*AH55 -> 2747.1756
B39: Operating Income | C39: =C34-SUM(C35:C38) -> 86 | D39: =D34-SUM(D35:D38) -> 241 | E39: =E34-SUM(E35:E38) -> 283 | F39: =F34-SUM(F35:F38) -> 465 | G39: =G34-SUM(G35:G38) -> 203 | H39: =H34-SUM(H35:H38) -> 291 | I39: =I34-SUM(I35:I38) -> 343 | J39: =J34-SUM(J35:J38) -> 631 | ... M39: =M34-SUM(M35:M38) -> 488 | W39: =SUM(C39:F39) -> 1075 | X39: =SUM(G39:J39) -> 1468 | Y39: =Y34-SUM(Y35:Y38) -> 1929.4693 | Z39: =Z34-SUM(Z35:Z38) -> 3028.1108 | AA39: =AA34-SUM(AA35:AA38) -> 4488.0234 | AB39: =AB34-SUM(AB35:AB38) -> 6169.1895 | AC39: =AC34-SUM(AC35:AC38) -> 8028.2015 | AD39: =AD34-SUM(AD35:AD38) -> 10049.135 | AE39: =AE34-SUM(AE35:AE38) -> 12447.07 | AF39: =AF34-SUM(AF35:AF38) -> 15127.24 | ... AH39: =AH34-SUM(AH35:AH38) -> 21061.68
B40: Interest Income | C40: 79 | D40: 80 | E40: 77 | F40: =308-SUM(C40:E40) -> 72 | G40: 65 | H40: 106 | I40: 81 | J40: =331-SUM(G40:I40) -> 79 | K40: 75 | L40: 1228 | M40: 1228 | W40: =SUM(C40:F40) -> 308 | X40: =SUM(G40:J40) -> 331 | Y40: =X60*($AR$60) -> 374.6625 | Z40: =Y60*($AR$60) -> 978.11463 | AA40: =Z60*($AR$60) -> 2075.9206 | AB40: =AA60*($AR$60) -> 3906.4404 | AC40: =AB60*($AR$60) -> 6740.7151 | AD40: =AC60*($AR$60) -> 10913.119 | AE40: =AD60*($AR$60) -> 16860.634 | AF40: =AE60*($AR$60) -> 25211.498 | ... AH40: =AG60*($AR$60) -> 52438.314
B41: Net Realized G/L on Equity Inv | C41: -373 | D41: 3 | E41: 0 | F41: =3-SUM(C41:E41) -> 373 | G41: 0 | H41: 1 | I41: 0 | J41: =33-SUM(G41:I41) -> 32 | K41: 3 | L41: 59 | M41: 59 | W41: =SUM(C41:F41) -> 3 | X41: =SUM(G41:J41) -> 33 | Y41: 0 | Z41: 0 | AA41: 0 | AB41: 0 | AC41: 0 | AD41: 0 | AE41: 0 | AF41: 0 | AG41: 0 | AH41: 0
B42: Net Unealized G/L on Equity Inv | C42: 0 | D42: -79 | E42: 512 | F42: =988-SUM(C42:E42) -> 555 | G42: -1021 | H42: 681 | I42: -62 | J42: =-186-SUM(G42:I42) -> 216 | K42: -1064 | L42: 0 | M42: 0 | W42: =SUM(C42:F42) -> 988 | X42: =SUM(G42:J42) -> -186 | Y42: 0 | Z42: 0 | AA42: 0 | AB42: 0 | AC42: 0 | AD42: 0 | AE42: 0 | AF42: 0 | AG42: 0 | AH42: 0
B43: Net G/L on Equity Method Inv | C43: -44 | D43: -44 | E43: -28 | F43: =-138-SUM(C43:E43) -> -22 | G43: -23 | H43: -24 | I43: -21 | J43: =-40-SUM(G43:I43) -> 28 | K43: -21 | L43: 0 | M43: 0 | W43: =SUM(C43:F43) -> -138 | X43: =SUM(G43:J43) -> -40 | Y43: 0 | Z43: 0 | AA43: 0 | AB43: 0 | AC43: 0 | AD43: 0 | AE43: 0 | AF43: 0 | AG43: 0 | AH43: 0
B44: ForEx G/L | C44: -4 | D44: 2 | E44: 16 | F44: =-8-SUM(C44:E44) -> -22 | G44: 6 | H44: 24 | I44: -33 | J44: =-123+26-SUM(G44:I44) -> -94 | K44: -9 | L44: 0 | M44: 0 | W44: =SUM(C44:F44) -> -8 | X44: =SUM(G44:J44) -> -97 | Y44: 0 | Z44: 0 | AA44: 0 | AB44: 0 | AC44: 0 | AD44: 0 | AE44: 0 | AF44: 0 | AG44: 0 | AH44: 0
B45: Pretax Income | C45: =C39+SUM(C40:C44) -> -256 | D45: =D39+SUM(D40:D44) -> 203 | E45: =E39+SUM(E40:E44) -> 860 | F45: =F39+SUM(F40:F44) -> 1421 | G45: =G39+SUM(G40:G44) -> -770 | H45: =H39+SUM(H40:H44) -> 1079 | I45: =I39+SUM(I40:I44) -> 308 | J45: =J39+SUM(J40:J44) -> 892 | ... M45: =M39+SUM(M40:M44) -> 1775 | W45: =SUM(C45:F45) -> 2228 | X45: =SUM(G45:J45) -> 1509 | Y45: =Y39+Y40 -> 2304.1318 | Z45: =Z39+Z40 -> 4006.2254 | AA45: =AA39+AA40 -> 6563.9439 | AB45: =AB39+AB40 -> 10075.63 | AC45: =AC39+AC40 -> 14768.917 | AD45: =AD39+AD40 -> 20962.254 | AE45: =AE39+AE40 -> 29307.704 | AF45: =AF39+AF40 -> 40338.738 | ... AH45: =AH39+AH40 -> 73499.994
B46: Taxes | C46: -17 | D46: -32 | E46: -32 | F46: =-209-SUM(C46:E46) -> -128 | G46: 88 | H46: -173 | I46: -44 | J46: =-278-SUM(G46:I46) -> -149 | K46: 53 | L46: -273 | M46: -273 | W46: =SUM(C46:F46) -> -209 | X46: =SUM(G46:J46) -> -278 | Y46: =Y45*Y57 -> 184.33055 | Z46: =Z45*Z57 -> 520.80931 | AA46: =AA45*AA57 -> 984.59159 | AB46: =AB45*AB57 -> 1612.1008 | AC46: =AC45*AC57 -> 2436.8712 | AD46: =AD45*AD57 -> 3563.5831 | AE46: =AE45*AE57 -> 5128.8483 | AF46: =AF45*AF57 -> 7260.9728 | ... AH46: =AH45*AH57 -> 13229.999
B47: Net Income | C47: =C45+C46 -> -273 | D47: =D45+D46 -> 171 | E47: =E45+E46 -> 828 | F47: =F45+F46 -> 1293 | G47: =G45+G46 -> -682 | H47: =H45+H46 -> 906 | I47: =I45+I46 -> 264 | J47: =J45+J46 -> 743 | ... M47: =M45+M46 -> 1502 | W47: =SUM(C47:F47) -> 2019 | X47: =SUM(G47:J47) -> 1231 | Y47: =Y45+Y46 -> 2488.4624 | Z47: =Z45+Z46 -> 4527.0347 | AA47: =AA45+AA46 -> 7548.5355 | AB47: =AB45+AB46 -> 11687.731 | AC47: =AC45+AC46 -> 17205.788 | AD47: =AD45+AD46 -> 24525.837 | AE47: =AE45+AE46 -> 34436.553 | AF47: =AF45+AF46 -> 47599.711 | ... AH47: =AH45+AH46 -> 86729.992 | AI47: =AH47*(1+$AR$61) -> 88768.147 | AJ47: =AI47*(1+$AR$61) -> 90854.199 | AK47: =AJ47*(1+$AR$61) -> 92989.272 | AL47: =AK47*(1+$AR$61) -> 95174.52 | AM47: =AL47*(1+$AR$61) -> 97411.121 | AN47: =AM47*(1+$AR$61) -> 99700.283 | AO47: =AN47*(1+$AR$61) -> 102043.24 | AP47: =AO47*(1+$AR$61) -> 104441.26 | ... CF47: =CE47*(1+$AR$61) -> 277052.23
B48: SC | C48: 1287.376 | D48: 1288.9 | E48: 1290.585 | F48: 1289.812 | G48: 1295.377 | H48: 1297.74 | I48: 1300.069 | J48: 1298.955 | K48: 1303.35 | L48: 1295.22 | M48: 1295.22 | W48: =AVERAGE(C48:F48) -> 1289.1682 | X48: =AVERAGE(G48:J48) -> 1298.0352
B49: EPS | C49: =C47/C48 -> -0.21205926 | D49: =D47/D48 -> 0.13267127 | E49: =E47/E48 -> 0.64156952 | F49: =F47/F48 -> 1.0024717 | G49: =G47/G48 -> -0.52648766 | H49: =H47/H48 -> 0.69813676 | I49: =I47/I48 -> 0.20306614 | J49: =J47/J48 -> 0.57199826 | ... M49: =M47/M48 -> 1.1596486 | W49: =SUM(C49:F49) -> 1.5646532 | X49: =SUM(G49:J49) -> 0.94671351
B51: Gross Profit Margin | C51: =C34/C32 -> 0.51423966 | D51: =D34/D32 -> 0.51100244 | E51: =E34/E32 -> 0.51711378 | F51: =F34/F32 -> 0.48079659 | G51: =G34/G32 -> 0.49533898 | H51: =H34/H32 -> 0.4858209 | I51: =I34/I32 -> 0.48909986 | J51: =J34/J32 -> 0.46105664 | ... M51: =M34/M32 -> 0.47669551 | W51: =W34/W32 -> 0.5036036 | X51: =X34/X32 -> 0.48070267 | Y51: 0.48070267 | Z51: 0.49 | AA51: 0.5 | AB51: 0.505 | AC51: 0.51 | AD51: 0.5125 | AE51: 0.515 | AF51: 0.5175 | AG51: 0.52 | AH51: 0.52
B52: S&M as % of Revenue | C52: =C35/C32 -> 0.19398173 | D52: =D35/D32 -> 0.17261614 | E52: =E35/E32 -> 0.15309898 | F52: =F35/F32 -> 0.12375533 | G52: =G35/G32 -> 0.17161017 | H52: =H35/H32 -> 0.15485075 | I52: =I35/I32 -> 0.14416315 | J52: =J35/J32 -> 0.11791939 | ... M52: =M35/M32 -> 0.13898967 | W52: =W35/W32 -> 0.15686937 | X52: =X35/X32 -> 0.14390793 | Y52: 0.14390793 | Z52: 0.137 | AA52: 0.132 | AB52: 0.127 | AC52: 0.125 | AD52: 0.124 | AE52: 0.123 | AF52: 0.122 | AG52: 0.121 | AH52: 0.12
B53: R&D as % of Revenue | C53: =C36/C32 -> 0.18001075 | D53: =D36/D32 -> 0.17066015 | E53: =E36/E32 -> 0.15356152 | F53: =F36/F32 -> 0.12482219 | G53: =G36/G32 -> 0.15974576 | H53: =H36/H32 -> 0.14701493 | I53: =I36/I32 -> 0.13185654 | J53: =J36/J32 -> 0.10620915 | ... M53: =M36/M32 -> 0.1241976 | W53: =W36/W32 -> 0.15394144 | X53: =X36/X32 -> 0.13291796 | Y53: 0.136 | Z53: 0.135 | AA53: 0.132 | AB53: 0.129 | AC53: 0.127 | AD53: 0.125 | AE53: 0.12 | AF53: 0.115 | AG53: 0.11 | AH53: 0.105
B54: G&A as % of Revenue | C54: =C37/C32 -> 0.066630844 | D54: =D37/D32 -> 0.029339853 | E54: =E37/E32 -> 0.052728955 | F54: =F37/F32 -> 0.039829303 | G54: =G37/G32 -> 0.046186441 | H54: =H37/H32 -> 0.045522388 | I54: =I37/I32 -> 0.040436006 | J54: =J37/J32 -> 0.034041394 | ... M54: =M37/M32 -> 0.037957019 | W54: =W37/W32 -> 0.046171171 | X54: =X37/X32 -> 0.040758048 | Y54: 0.040758048 | Z54: 0.038 | AA54: 0.036 | AB54: 0.035 | AC54: 0.035 | AD54: 0.035 | AE54: 0.035 | AF54: 0.035 | AG54: 0.035 | AH54: 0.035
B55: Loss as % of Revenue | C55: =C38/C32 -> 0.027404621 | D55: =D38/D32 -> 0.020537897 | E55: =E38/E32 -> 0.026827012 | F55: =F38/F32 -> 0.027027027 | G55: =G38/G32 -> 0.031779661 | H55: =H38/H32 -> 0.029850746 | I55: =I38/I32 -> 0.052039381 | J55: =J38/J32 -> 0.031045752 | ... M55: =M38/M32 -> 0.039352498 | W55: =W38/W32 -> 0.025563063 | X55: =X38/X32 -> 0.036085151 | Y55: 0.036085151 | Z55: 0.034 | AA55: 0.033 | AB55: 0.032 | AC55: 0.031 | AD55: 0.03 | AE55: 0.03 | AF55: 0.03 | AG55: 0.03 | AH55: 0.03
B56: Operating Profit Margin | C56: =C39/C32 -> 0.046211714 | D56: =D39/D32 -> 0.11784841 | E56: =E39/E32 -> 0.13089732 | F56: =F39/F32 -> 0.16536273 | G56: =G39/G32 -> 0.086016949 | H56: =H39/H32 -> 0.10858209 | I56: =I39/I32 -> 0.12060478 | J56: =J39/J32 -> 0.17184096 | ... M56: =M39/M32 -> 0.13619872 | W56: =W39/W32 -> 0.12105856 | X56: =X39/X32 -> 0.12703358 | Y56: =Y39/Y32 -> 0.12395154 | Z56: =Z39/Z32 -> 0.146 | AA56: =AA39/AA32 -> 0.167 | AB56: =AB39/AB32 -> 0.182 | AC56: =AC39/AC32 -> 0.192 | AD56: =AD39/AD32 -> 0.1985 | ... AH56: =AH39/AH32 -> 0.23
B57: Effective Tax Rate | C57: =C46/C45 -> 0.06640625 | D57: =D46/D45 -> -0.15763547 | E57: =E46/E45 -> -0.037209302 | F57: =F46/F45 -> -0.09007741 | G57: =G46/G45 -> -0.11428571 | H57: =H46/H45 -> -0.16033364 | I57: =I46/I45 -> -0.14285714 | J57: =J46/J45 -> -0.16704036 | ... M57: =M46/M45 -> -0.15380282 | W57: =W46/W45 -> -0.093806104 | X57: =X46/X45 -> -0.18422797 | Y57: 0.08 | Z57: 0.13 | AA57: 0.15 | AB57: 0.16 | AC57: 0.165 | AD57: 0.17 | AE57: 0.175 | AF57: 0.18 | AG57: 0.18 | AH57: 0.18
B58: Net Profit Margin | C58: =C47/C32 -> -0.14669533 | D58: =D47/D32 -> 0.083618582 | E58: =E47/E32 -> 0.38297872 | F58: =F47/F32 -> 0.45981508 | G58: =G47/G32 -> -0.28898305 | H58: =H47/H32 -> 0.3380597 | I58: =I47/I32 -> 0.092827004 | J58: =J47/J32 -> 0.20234205 | ... M58: =M47/M32 -> 0.41920179 | W58: =W47/W32 -> 0.22736486 | X58: =X47/X32 -> 0.10652475 | Y58: =Y47/Y32 -> 0.15986196 | Z58: =Z47/Z32 -> 0.21827044 | AA58: =AA47/AA32 -> 0.2808821 | AB58: =AB47/AB32 -> 0.34480493 | AC58: =AC47/AC32 -> 0.41148833 | AD58: =AD47/AD32 -> 0.48445748 | ... AH58: =AH47/AH32 -> 0.94711811
B60: Cash & CEs | F60: 1498 | G60: 1309 | H60: 1542 | I60: 2414 | J60: 1545 | K60: 1848 | L60: 1656 | M60: 1656 | W60: =F60 -> 1498 | X60: =J60 -> 1545 | Y60: =X60+Y47 -> 4033.4624 | Z60: =Y60+Z47 -> 8560.4971 | AA60: =Z60+AA47 -> 16109.033 | AB60: =AA60+AB47 -> 27796.763 | AC60: =AB60+AC47 -> 45002.551 | AD60: =AC60+AD47 -> 69528.388 | AE60: =AD60+AE47 -> 103964.94 | AF60: =AE60+AF47 -> 151564.65 | ... AH60: =AG60+AH47 -> 302970.46 | AJ60: Invested Capital | AM60: Avg. (2024-2025) | AO60: Projected ROIC: | AQ60: ROIC | AR60: 0.2425
B61: Marketable Securities | F61: 3981 | G61: 4205 | H61: 4278 | I61: 3935 | J61: 4233 | K61: 3895 | L61: 3291 | M61: 3291 | W61: =F61 -> 3981 | X61: =J61 -> 4233 | AJ61: 2024 | AK61: 2025 | AM61: 2024-2025 | AO61: 2025 | AQ61: Terminal | AR61: 0.0235
B62: A/R | F62: 342 | G62: 297 | H62: 350 | I62: 396 | J62: 500 | K62: 449 | L62: 466 | M62: 466 | W62: =F62 -> 342 | X62: =J62 -> 500 | AJ62: =SUM(W60:W64)-SUM(W76:W78)+W65+W73+W67 -> 6737 | AK62: =SUM(X60:X64)-SUM(X76:X78)+X65+X73+X67 -> 7478 | AM62: =AVERAGE(AJ62:AK62) -> 7107.5 | AO62: =X40*(1-X54) -> 317.50909 | AQ62: RFR (10-year yield) | AR62: =AM71 -> 0.0517
B63: ST Loans & Merchant Cash Advances | F63: 1224 | G63: 1392 | H63: 1597 | I63: 1733 | J63: 1784 | K63: 2097 | L63: 2184 | M63: 2184 | W63: =F63 -> 1224 | X63: =J63 -> 1784 | AO63: =AO62/AM62 -> 0.0446724 | AQ63: ERP (Avg. market return - (less) RFR) | AR63: =10.35%-AR62 -> 0.0518
B64: Other ST Assets | F64: 209 | G64: 242 | H64: 234 | I64: 227 | J64: 234 | K64: 206 | L64: 219 | M64: 219 | W64: =F64 -> 209 | X64: =J64 -> 234 | AJ64: Capital Structure | AQ64: Equity β (1-year avg.) | AR64: ='Notes | Quant Analysis'!S207 -> 2.2109453
B65: PP&E | F65: 47 | G65: 46 | H65: 46 | I65: 51 | J65: 53 | K65: 54 | L65: 53 | M65: 53 | W65: =F65 -> 47 | X65: =J65 -> 53 | AJ65: Mkt Cap | AM65: =Main!C5 -> 218646.09 | AQ65: Discount (Cost of Equity) | AR65: =+AR62+(AR63*AR64) -> 0.16622696
B66: LT Operating Lease Assets | F66: 93 | G66: 105 | H66: 97 | I66: 94 | J66: 88 | K66: 84 | L66: 90 | M66: 90 | W66: =F66 -> 93 | X66: =J66 -> 88 | AJ66: Debt to Ttl Mkt Cap | AM66: =Main!C7/(Main!C7+AM65) -> 0
B67: Intangible Assets | F67: 22 | G67: 39 | H67: 36 | I67: 33 | J67: 30 | K67: 28 | L67: 27 | M67: 27 | W67: =F67 -> 22 | X67: =J67 -> 30 | AJ67: Mkt Equity to Ttl Mkt Cap | AM67: =AM65/(AM65+Main!C7) -> 1 | AQ67: NPV | AR67: =NPV(AR65,Y47:CG47) -> 228191.75
B68: LT Deferred Tax Assets | F68: 37 | G68: 98 | H68: 31 | I68: 29 | J68: 33 | K68: 117 | L68: 30 | M68: 30 | W68: =F68 -> 37 | X68: =J68 -> 33 | AJ68: LT Debt / Equity | AM68: =X79/X85 -> 0 | AQ68: SC | AR68: =Main!C4 -> 1295.22
B69: Other LT Assets | F69: 21 | G69: 23 | H69: 28 | I69: 23 | J69: 39 | K69: 30 | L69: 25 | M69: 25 | W69: =F69 -> 21 | X69: =J69 -> 39 | AQ69: FV | AR69: =AR67/AR68 -> 176.17991
B70: LT Investments | F70: 709 | G70: 894 | H70: 831 | I70: 676 | J70: 975 | K70: 708 | L70: 525 | M70: 525 | W70: =F70 -> 709 | X70: =J70 -> 975 | AJ70: Cost of Equity | AQ70: CP | AR70: =Main!C3 -> 168.81
B71: LT Equity Investments | F71: 4647 | G71: 3640 | H71: 4405 | I71: 4363 | J71: 4582 | K71: 3533 | L71: 4854 | M71: 4854 | W71: =F71 -> 4647 | X71: =J71 -> 4582 | AJ71: RFR (10-year yield) | AM71: 0.0517 | AQ71: Change Δ | AR71: =AR69/AR70-1 -> 0.043658043 | AS71: =IF(AR71>0,"Upside","Downside") -> Upside
B72: LT Equity Method Investments | F72: 642 | G72: 619 | H72: 595 | I72: 574 | J72: 602 | K72: 581 | L72: 559 | M72: 559 | W72: =F72 -> 642 | X72: =J72 -> 602 | AJ72: Equity β (1-year avg.) | AM72: ='Notes | Quant Analysis'!S207 -> 2.2109453 | AQ72: {=_xlfn.IFS(AR71>=25%,"Strong Buy",AR71>=10.00001%,"Buy",AND(AR71<=10%,AR71>=-4.9999%),"Hold",AND(AR71<=-5%,AR71>=-14.999999%),"Sell",AR71<=-15%,"Strong Sell")} -> Hold
B73: Goodwill | F73: 452 | G73: 491 | H73: 491 | I73: 491 | J73: 491 | K73: 491 | L73: 491 | M73: 491 | W73: =F73 -> 452 | X73: =J73 -> 491 | AJ73: Market Return(1-year avg.) | AM73: 0.1457
B74: Ttl Assets | F74: =SUM(F60:F73) -> 13924 | G74: =SUM(G60:G73) -> 13400 | H74: =SUM(H60:H73) -> 14561 | I74: =SUM(I60:I73) -> 15039 | J74: =SUM(J60:J73) -> 15189 | K74: =SUM(K60:K73) -> 14121 | L74: =SUM(L60:L73) -> 14470 | M74: =SUM(M60:M73) -> 14470 | W74: =F74 -> 13924 | X74: =J74 -> 15189 | AJ74: Cost of Equity | AM74: =(AM71+AM72)*(AM73-AM71) -> 0.21268865
B76: A/P | F76: 737 | G76: 776 | H76: 841 | I76: 974 | J76: 1075 | K76: 1034 | L76: 1115 | M76: 1115 | W76: =F76 -> 737 | X76: =J76 -> 1075 | AJ76: Cost of Debt
B77: ST Deferred Revenue | F77: 283 | G77: 295 | H77: 298 | I77: 300 | J77: 300 | K77: 321 | L77: 335 | M77: 335 | W77: =F77 -> 283 | X77: =J77 -> 300 | AJ77: Cost of Debt | AM77: 0
B78: ST Operating Lease Liabilities | F78: 18 | G78: 19 | H78: 20 | I78: 19 | J78: 17 | K78: 16 | L78: 10 | M78: 10 | W78: =F78 -> 18 | X78: =J78 -> 17 | AJ78: Tax Rate | AM78: 0.23
B79: Convertible Notes | F79: 918 | G79: 919 | H79: 919 | I79: 920 | J79: 0 | K79: 0 | L79: 79 | M79: 79 | W79: =F79 -> 918 | X79: =J79 -> 0 | AJ79: After Tax Cost of Debt | AM79: =AM77*(1-AM78) -> 0
B80: LT Deferred Revenue | F80: 147 | G80: 135 | H80: 123 | I80: 110 | J80: 98 | K80: 86 | L80: 168 | M80: 168 | W80: =F80 -> 147 | X80: =J80 -> 98
B81: Operating Lease Liabilities | F81: 190 | G81: 200 | H81: 200 | I81: 176 | J81: 171 | K81: 163 | L81: 79 | M81: 79 | W81: =F81 -> 190 | X81: =J81 -> 171 | AJ81: WACC | AM81: =(AM67*AM74)+(AM66*AM79*(1-AM78)) -> 0.21268865
B82: LT Deferred Tax Liabilities | F82: 73 | G82: 5 | H82: 36 | I82: 29 | J82: 55 | K82: 0 | L82: 0 | M82: 0 | W82: =F82 -> 73 | X82: =J82 -> 55
B83: Ttl Liabilities | F83: =SUM(F76:F82) -> 2366 | G83: =SUM(G76:G82) -> 2349 | H83: =SUM(H76:H82) -> 2437 | I83: =SUM(I76:I82) -> 2528 | J83: =SUM(J76:J82) -> 1716 | K83: =SUM(K76:K82) -> 1620 | L83: =SUM(L76:L82) -> 1786 | M83: =SUM(M76:M82) -> 1786 | W83: =F83 -> 2366 | X83: =J83 -> 1716
B84: Ttl SE | F84: 11558 | G84: 11051 | H84: 12124 | I84: 12511 | J84: 13473 | K84: 12501 | L84: 12684 | M84: 12684 | W84: =F84 -> 11558 | X84: =J84 -> 13473
B85: Ttl L + SE | F85: =F83+F84 -> 13924 | G85: =G83+G84 -> 13400 | H85: =H83+H84 -> 14561 | I85: =I83+I84 -> 15039 | J85: =J83+J84 -> 15189 | K85: =K83+K84 -> 14121 | L85: =L83+L84 -> 14470 | M85: =M83+M84 -> 14470 | W85: =F85 -> 13924 | X85: =J85 -> 15189
B87: Current Ratio
B88: Quick Ratio
B89: Cash Ratio
B90: Fixed Asset Turnover Ratio
B91: Ttl Asset Turnover Ratio
B92: Inventory Turnover Ratio
B93: Return on Assets
B94: Return on Equity
B96: Net Income | C96: =C47 -> -273 | D96: =D47 -> 171 | E96: =E47 -> 828 | F96: =F47 -> 1293 | G96: =G47 -> -682 | H96: =H47 -> 906 | I96: =I47 -> 264 | J96: =J47 -> 743 | ... M96: =M47 -> 1502 | W96: =SUM(C96:F96) -> 2019 | X96: =SUM(G96:J96) -> 1231
B97: CFFO | C97: 238 | D97: 340 | E97: 423 | F97: 615 | G97: 367 | H97: 428 | I97: 513 | J97: 725 | K97: 481 | L97: 481 | M97: 481 | W97: =SUM(C97:F97) -> 1616 | X97: =SUM(G97:J97) -> 2033
B98: CapEx, net | C98: -6 | D98: -7 | E98: -2 | F98: -4 | G98: -4 | H98: -6 | I98: -6 | J98: -10 | K98: -5 | L98: -5 | M98: -5 | W98: =SUM(C98:F98) -> -19 | X98: =SUM(G98:J98) -> -26
B99: FCF | C99: =C97+C98 -> 232 | D99: =D97+D98 -> 333 | E99: =E97+E98 -> 421 | F99: =F97+F98 -> 611 | G99: =G97+G98 -> 363 | H99: =H97+H98 -> 422 | I99: =I97+I98 -> 507 | J99: =J97+J98 -> 715 | ... M99: =M97+M98 -> 476 | W99: =SUM(C99:F99) -> 1597 | X99: =SUM(G99:J99) -> 2007
B100: SC | C100: =C48 -> 1287.376 | D100: =D48 -> 1288.9 | E100: =E48 -> 1290.585 | F100: =F48 -> 1289.812 | G100: =G48 -> 1295.377 | H100: =H48 -> 1297.74 | I100: =I48 -> 1300.069 | J100: =J48 -> 1298.955 | ... M100: =M48 -> 1295.22 | W100: =AVERAGE(C100:F100) -> 1289.1682 | X100: =AVERAGE(G100:J100) -> 1298.0352
B101: FCF per Share | C101: =C99/C100 -> 0.18021153 | D101: =D99/D100 -> 0.25835984 | E101: =E99/E100 -> 0.32620866 | F101: =F99/F100 -> 0.47371245 | G101: =G99/G100 -> 0.2802273 | H101: =H99/H100 -> 0.3251807 | I101: =I99/I100 -> 0.3899793 | J101: =J99/J100 -> 0.55044247 | ... M101: =M99/M100 -> 0.36750513 | W101: =SUM(C101:F101) -> 1.2384925 | X101: =SUM(G101:J101) -> 1.5458298
B103: CFFO Margin | C103: =C97/C32 -> 0.12788823 | D103: =D97/D32 -> 0.16625917 | E103: =E97/E32 -> 0.19565217 | F103: =F97/F32 -> 0.21870555 | G103: =G97/G32 -> 0.15550847 | H103: =H97/H32 -> 0.15970149 | I103: =I97/I32 -> 0.18037975 | J103: =J97/J32 -> 0.19744009 | ... M103: =M97/M32 -> 0.13424505 | W103: =W97/W32 -> 0.18198198 | X103: =X97/X32 -> 0.17592593
B104: FCF Margin | C104: =C99/C32 -> 0.12466416 | D104: =D99/D32 -> 0.16283619 | E104: =E99/E32 -> 0.1947271 | F104: =F99/F32 -> 0.21728307 | G104: =G99/G32 -> 0.15381356 | H104: =H99/H32 -> 0.15746269 | I104: =I99/I32 -> 0.17827004 | J104: =J99/J32 -> 0.19471678 | ... M104: =M99/M32 -> 0.13284957 | W104: =W99/W32 -> 0.17984234 | X104: =X99/X32 -> 0.17367601
B105: CapEx as % of Revenue | C105: =C98/C32 -> -0.0032240731 | D105: =D98/D32 -> -0.0034229829 | E105: =E98/E32 -> -0.00092506938 | F105: =F98/F32 -> -0.0014224751 | G105: =G98/G32 -> -0.0016949153 | H105: =H98/H32 -> -0.002238806 | I105: =I98/I32 -> -0.0021097046 | J105: =J98/J32 -> -0.0027233115 | ... M105: =M98/M32 -> -0.0013954786 | W105: =W98/W32 -> -0.0021396396 | X105: =X98/X32 -> -0.0022499135

Sheet Notes | Quant Analysis
CI1: 0
P2: Employee Scope: | AL2: General Notes/Observations
Q32: Notes: | R32: [X]
R33: [Y]
R34: [Z]
AL35: Financial Stmts. Notes/Observations
P36: Institutional Ownership Snapshot Q2'25 | AL36: Revenues:
Q66: Notes: | R66: [X]
R67: [Y]
R68: [Z]
P70: Revenue Breakdown by Segment (Build graph for this section if applicable…. See example below) | AL70: Earnings Scope:
Q102: Notes: | R102: [X]
R103: [Y]
R104: [Z]
P106: Q/q Total Revenues, Net Income, FCF | AL106: Balance Sheet Scope:
Q135: Notes: | R135: [X]
R136: [Y]
R137: [Z]
P139: Y/y Total Revenues, Net Income, FCF | AL139: [Equity Preformance Compared to Peers]
Q168: Notes: | R168: [X]
R169: [Y]
R170: [Z]
A185: VOO Historical Returns
A186: 251 Trading Days? (From: 8/1/2025 - 8/1/2026) | I186: 251 Trading Days? (From: 8/1/2025 - 8/1/2026)
A187: Close | B187: High | C187: Low | D187: Open | E187: Volume | F187: UTC Date | G187: Change | I187: Close | J187: High | K187: Low | L187: Open | M187: Volume | N187: UTC Date | O187: Change
A188: 686.65 | B188: 688.35 | C188: 678.06 | D188: 684.5 | E188: 7661568.2 | F188: Fri, 31 Jul 2026 00:00:00 GMT | G188: =A188/D188-1 -> 0.0031409788 | I188: 117.15 | J188: 122.25 | K188: 115.27 | L188: 120.93 | M188: 12043764 | N188: Fri, 31 Jul 2026 00:00:00 GMT | O188: =I188/L188-1 -> -0.031257752
A189: 681.79 | B189: 682.4363 | C189: 675.21 | D189: 676.54 | E189: 6009104.5 | F189: Thu, 30 Jul 2026 00:00:00 GMT | G189: =A189/D189-1 -> 0.0077600733 | I189: 122.4 | J189: 126.61 | K189: 122.29 | L189: 126.315 | M189: 10314840 | N189: Thu, 30 Jul 2026 00:00:00 GMT | O189: =I189/L189-1 -> -0.030993944
A190: 670.63 | B190: 682.63 | C190: 670.155 | D190: 680.12 | E190: 7845443.5 | F190: Wed, 29 Jul 2026 00:00:00 GMT | G190: =A190/D190-1 -> -0.01395342 | I190: 129.17 | J190: 133.73 | K190: 128.22 | L190: 129.045 | M190: 7304206.9 | N190: Wed, 29 Jul 2026 00:00:00 GMT | O190: =I190/L190-1 -> 0.00096865435
A191: 680.96 | B191: 682.755 | C191: 676.4801 | D191: 679.45 | E191: 5021080 | F191: Tue, 28 Jul 2026 00:00:00 GMT | G191: =A191/D191-1 -> 0.0022223858 | I191: 130.28 | J191: 133.99 | K191: 127.87 | L191: 128.29 | M191: 9553143.2 | N191: Tue, 28 Jul 2026 00:00:00 GMT | O191: =I191/L191-1 -> 0.015511731
A192: 679.31 | B192: 685.2391 | C192: 676.395 | D192: 684.69 | E192: 5207757.8 | F192: Mon, 27 Jul 2026 00:00:00 GMT | G192: =A192/D192-1 -> -0.0078575706 | I192: 126.88 | J192: 126.91 | K192: 117.81 | L192: 118.195 | M192: 10161838 | N192: Mon, 27 Jul 2026 00:00:00 GMT | O192: =I192/L192-1 -> 0.073480266
A193: 679.14 | B193: 683.55 | C193: 677.7 | D193: 678.8 | E193: 6286807 | F193: Fri, 24 Jul 2026 00:00:00 GMT | G193: =A193/D193-1 -> 0.00050088391 | I193: 113.75 | J193: 114.6 | K193: 111.26 | L193: 112.99 | M193: 6998804.4 | N193: Fri, 24 Jul 2026 00:00:00 GMT | O193: =I193/L193-1 -> 0.006726259
A194: 678.61 | B194: 682.5495 | C194: 675.755 | D194: 679.55 | E194: 4942804.8 | F194: Thu, 23 Jul 2026 00:00:00 GMT | G194: =A194/D194-1 -> -0.0013832683 | I194: 112 | J194: 117.91 | K194: 111.055 | L194: 117.44 | M194: 10236843 | N194: Thu, 23 Jul 2026 00:00:00 GMT | O194: =I194/L194-1 -> -0.046321526
A195: 687.03 | B195: 689.4 | C195: 686.02 | D195: 686.29 | E195: 3349102.7 | F195: Wed, 22 Jul 2026 00:00:00 GMT | G195: =A195/D195-1 -> 0.0010782614 | I195: 118.42 | J195: 123.425 | K195: 116.621 | L195: 122.95 | M195: 7679815.6 | N195: Wed, 22 Jul 2026 00:00:00 GMT | O195: =I195/L195-1 -> -0.036844246
A196: 687.87 | B196: 688.485 | C196: 684.03 | D196: 685.95 | E196: 4054717.9 | F196: Tue, 21 Jul 2026 00:00:00 GMT | G196: =A196/D196-1 -> 0.0027990378 | I196: 123.03 | J196: 124.29 | K196: 119.25 | L196: 121.21 | M196: 6551861.5 | N196: Tue, 21 Jul 2026 00:00:00 GMT | O196: =I196/L196-1 -> 0.015015263
A197: 682.21 | B197: 688.2 | C197: 681.57 | D197: 686.67 | E197: 5321985.3 | F197: Mon, 20 Jul 2026 00:00:00 GMT | G197: =A197/D197-1 -> -0.0064951141 | I197: 124.48 | J197: 128.26 | K197: 123.45 | L197: 124.23 | M197: 7312521.2 | N197: Mon, 20 Jul 2026 00:00:00 GMT | O197: =I197/L197-1 -> 0.0020123964
A198: 683.17 | B198: 686.8653 | C198: 680.92 | D198: 682.12 | E198: 5627641.4 | F198: Fri, 17 Jul 2026 00:00:00 GMT | G198: =A198/D198-1 -> 0.0015393186 | I198: 123.56 | J198: 124.6 | K198: 121.11 | L198: 124.6 | M198: 6312592.5 | N198: Fri, 17 Jul 2026 00:00:00 GMT | O198: =I198/L198-1 -> -0.0083467095
A199: 690.14 | B199: 693.55 | C199: 687.43 | D199: 691.98 | E199: 4722611.2 | F199: Thu, 16 Jul 2026 00:00:00 GMT | G199: =A199/D199-1 -> -0.0026590364 | I199: 125.06 | J199: 127.89 | K199: 121.78 | L199: 124.6 | M199: 7302620.4 | N199: Thu, 16 Jul 2026 00:00:00 GMT | O199: =I199/L199-1 -> 0.0036918138
A200: 693.8 | B200: 694.5 | C200: 689.58 | D200: 693.27 | E200: 4110059.9 | F200: Wed, 15 Jul 2026 00:00:00 GMT | G200: =A200/D200-1 -> 0.00076449291 | I200: 123.55 | J200: 127.59 | K200: 120.87 | L200: 126.45 | M200: 8182482 | N200: Wed, 15 Jul 2026 00:00:00 GMT | O200: =I200/L200-1 -> -0.022933966
A201: 691.1 | B201: 692.4 | C201: 688.2 | D201: 690.21 | E201: 4570040.4 | F201: Tue, 14 Jul 2026 00:00:00 GMT | G201: =A201/D201-1 -> 0.0012894626 | I201: 125.68 | J201: 126.11 | K201: 120 | L201: 121.63 | M201: 4727877.2 | N201: Tue, 14 Jul 2026 00:00:00 GMT | O201: =I201/L201-1 -> 0.033297706 | R201: Min | S201: =MIN(O188:O438) -> -0.14535637
A202: 688.5 | B202: 692.96 | C202: 687.54 | D202: 691.6 | E202: 6587891.4 | F202: Mon, 13 Jul 2026 00:00:00 GMT | G202: =A202/D202-1 -> -0.0044823597 | I202: 124.74 | J202: 126.7 | K202: 121.7 | L202: 124.63 | M202: 6576280.4 | N202: Mon, 13 Jul 2026 00:00:00 GMT | O202: =I202/L202-1 -> 0.00088261253 | R202: Max | S202: =MAX(O188:O438) -> 0.076364923
A203: 693.86 | B203: 694.33 | C203: 687.63 | D203: 691.25 | E203: 4666892.9 | F203: Fri, 10 Jul 2026 00:00:00 GMT | G203: =A203/D203-1 -> 0.0037757685 | I203: 122.54 | J203: 130.75 | K203: 122.3 | L203: 126.765 | M203: 5358760.3 | N203: Fri, 10 Jul 2026 00:00:00 GMT | O203: =I203/L203-1 -> -0.033329389 | R203: Mean μ | S203: =AVERAGE(O188:O438) -> 0.00011080396
A204: 690.69 | B204: 691.1862 | C204: 685.29 | D204: 686.95 | E204: 6395880.4 | F204: Thu, 09 Jul 2026 00:00:00 GMT | G204: =A204/D204-1 -> 0.0054443555 | I204: 123.17 | J204: 123.22 | K204: 116.71 | L204: 117.25 | M204: 5872204.4 | N204: Thu, 09 Jul 2026 00:00:00 GMT | O204: =I204/L204-1 -> 0.050490405 | R204: Median | S204: =MEDIAN(O188:O438) -> -0.00027164071
A205: 685.26 | B205: 685.84 | C205: 679.73 | D205: 683.1 | E205: 4805362.7 | F205: Wed, 08 Jul 2026 00:00:00 GMT | G205: =A205/D205-1 -> 0.0031620553 | I205: 119.22 | J205: 120.94 | K205: 115.17 | L205: 120.93 | M205: 5507901.3 | N205: Wed, 08 Jul 2026 00:00:00 GMT | O205: =I205/L205-1 -> -0.014140412 | R205: SD σ | S205: =_xlfn.STDEV.P(O188:O438) -> 0.030781942
A206: 687.08 | B206: 690.24 | C206: 684.989 | D206: 689.58 | E206: 4816042.5 | F206: Tue, 07 Jul 2026 00:00:00 GMT | G206: =A206/D206-1 -> -0.0036253952 | I206: 121.88 | J206: 125.94 | K206: 121.47 | L206: 122.84 | M206: 10065823 | N206: Tue, 07 Jul 2026 00:00:00 GMT | O206: =I206/L206-1 -> -0.007815044 | R206: 3σ 1-Day Δ: ± | S206: =3*S205 -> 0.092345825 | U206: <- Sharpe Ratio (Risk Adjusted Return)
A207: 690.62 | B207: 691.575 | C207: 687 | D207: 688.11 | E207: 5575659.2 | F207: Mon, 06 Jul 2026 00:00:00 GMT | G207: =A207/D207-1 -> 0.0036476726 | I207: 120.14 | J207: 121.54 | K207: 115.71 | L207: 118.96 | M207: 7258857.8 | N207: Mon, 06 Jul 2026 00:00:00 GMT | O207: =I207/L207-1 -> 0.0099193006 | R207: β (1-year avg.) | S207: =_xlfn.COVARIANCE.P(O188:O436,G188:G436)/_xlfn.VAR.P(G188:G436) -> 2.2109453 | U207: <- Sortino Ratio (Downside Risk Adjusted Return)
A208: 684.84 | B208: 690.5 | C208: 680.215 | D208: 686.98 | E208: 6980816.8 | F208: Thu, 02 Jul 2026 00:00:00 GMT | G208: =A208/D208-1 -> -0.0031150834 | I208: 119.46 | J208: 121.3 | K208: 118.42 | L208: 119.05 | M208: 6631413.9 | N208: Thu, 02 Jul 2026 00:00:00 GMT | O208: =I208/L208-1 -> 0.0034439311
A209: 685.46 | B209: 688.83 | C209: 682.3 | D209: 684.73 | E209: 8627875 | F209: Wed, 01 Jul 2026 00:00:00 GMT | G209: =A209/D209-1 -> 0.0010661137 | I209: 121.63 | J209: 123.7 | K209: 117.325 | L209: 117.325 | M209: 8295889.7 | N209: Wed, 01 Jul 2026 00:00:00 GMT | O209: =I209/L209-1 -> 0.036692947 | Q209: n = | R209: 251
A210: 686.81 | B210: 687.529 | C210: 680.99 | D210: 681.32 | E210: 9853712.9 | F210: Tue, 30 Jun 2026 00:00:00 GMT | G210: =A210/D210-1 -> 0.0080578876 | I210: 114.18 | J210: 116 | K210: 112 | L210: 113 | M210: 6467826.4 | N210: Tue, 30 Jun 2026 00:00:00 GMT | O210: =I210/L210-1 -> 0.010442478 | Q210: Histogram Data | T210: Distribution Overlay | X210: SD Lines
A211: 681.01 | B211: 681.565 | C211: 672.93 | D211: 677.01 | E211: 5649228.8 | F211: Mon, 29 Jun 2026 00:00:00 GMT | G211: =A211/D211-1 -> 0.0059083322 | I211: 114.21 | J211: 120.62 | K211: 113.99 | L211: 118.38 | M211: 9688149 | N211: Mon, 29 Jun 2026 00:00:00 GMT | O211: =I211/L211-1 -> -0.035225545 | Q211: Bin | R211: Frequency | T211: (X) 1-Day Δ | U211: (Y) Pop. Density | X211: X | Y211: Y
A212: 670.26 | B212: 676.955 | C212: 668.1 | D212: 669.96 | E212: 5935648.6 | F212: Fri, 26 Jun 2026 00:00:00 GMT | G212: =A212/D212-1 -> 0.00044778793 | I212: 116.86 | J212: 117.87 | K212: 112.1 | L212: 112.595 | M212: 9721542.2 | N212: Fri, 26 Jun 2026 00:00:00 GMT | O212: =I212/L212-1 -> 0.037879124 | Q212: -0.1 | R212: 1 | T212: =T213-0.0025 -> -0.1 | U212: =_xlfn.NORM.DIST(T212,$S$203,$S$205,FALSE) -> 0.065434788 | W212: Mean | X212: =S203 -> 0.00011080396 | Y212: 0
A213: 673.7478 | B213: 679.56087 | C213: 670.62689 | D213: 679.16203 | E213: 23355606 | F213: Thu, 25 Jun 2026 00:00:00 GMT | G213: =A213/D213-1 -> -0.0079719294 | I213: 111.62 | J213: 115.69 | K213: 111.325 | L213: 113.4 | M213: 7807277.5 | N213: Thu, 25 Jun 2026 00:00:00 GMT | O213: =I213/L213-1 -> -0.015696649 | Q213: -0.0975 | R213: 0 | T213: =T214-0.0025 -> -0.0975 | U213: =_xlfn.NORM.DIST(T213,$S$203,$S$205,FALSE) -> 0.084935556 | X213: =S203 -> 0.00011080396 | Y213: 13
A214: 673.72786 | B214: 680.08933 | C214: 671.72369 | D214: 675.71208 | E214: 9593615.8 | F214: Wed, 24 Jun 2026 00:00:00 GMT | G214: =A214/D214-1 -> -0.0029364892 | I214: 114.17 | J214: 114.49 | K214: 106.72 | L214: 106.87 | M214: 19813657 | N214: Wed, 24 Jun 2026 00:00:00 GMT | O214: =I214/L214-1 -> 0.068307289 | Q214: -0.095 | R214: 0 | T214: =T215-0.0025 -> -0.095 | U214: =_xlfn.NORM.DIST(T214,$S$203,$S$205,FALSE) -> 0.1095231 | W214: -3σ | X214: =($S$205*-3)+$S$203 -> -0.092235021 | Y214: 0
A215: 674.37597 | B215: 679.74912 | C215: 673.0598 | D215: 674.39093 | E215: 17263981 | F215: Tue, 23 Jun 2026 00:00:00 GMT | G215: =A215/D215-1 -> -2.2177703e-05 | I215: 107.68 | J215: 110.02 | K215: 106.99 | L215: 107.855 | M215: 10546149 | N215: Tue, 23 Jun 2026 00:00:00 GMT | O215: =I215/L215-1 -> -0.0016225488 | Q215: -0.0925 | R215: 0 | T215: =T216-0.0025 -> -0.0925 | U215: =_xlfn.NORM.DIST(T215,$S$203,$S$205,FALSE) -> 0.14029986 | X215: =($S$205*-3)+$S$203 -> -0.092235021 | Y215: 0.2
A216: 684.10763 | B216: 689.49195 | C216: 683.01082 | D216: 687.16871 | E216: 13365185 | F216: Mon, 22 Jun 2026 00:00:00 GMT | G216: =A216/D216-1 -> -0.0044546338 | I216: 107.98 | J216: 111.58 | K216: 106 | L216: 106.75 | M216: 8324641.9 | N216: Mon, 22 Jun 2026 00:00:00 GMT | O216: =I216/L216-1 -> 0.011522248 | Q216: -0.09 | R216: 1 | T216: =T217-0.0025 -> -0.09 | U216: =_xlfn.NORM.DIST(T216,$S$203,$S$205,FALSE) -> 0.17854353 | W216: -2σ | X216: =($S$205*-2)+$S$203 -> -0.061453079 | Y216: 0
A217: 686.11179 | B217: 687.69717 | C217: 683.70879 | D217: 687.29834 | E217: 17768872 | F217: Thu, 18 Jun 2026 00:00:00 GMT | G217: =A217/D217-1 -> -0.0017263891 | I217: 108.85 | J217: 109.66 | K217: 106.14 | L217: 107.79 | M217: 9827409.9 | N217: Thu, 18 Jun 2026 00:00:00 GMT | O217: =I217/L217-1 -> 0.0098339364 | Q217: -0.0875 | R217: 0 | T217: =T218-0.0025 -> -0.0875 | U217: =_xlfn.NORM.DIST(T217,$S$203,$S$205,FALSE) -> 0.22571807 | X217: =($S$205*-2)+$S$203 -> -0.061453079 | Y217: 2
A218: 679.43125 | B218: 689.52186 | C218: 677.66639 | D218: 688.7541 | E218: 15004527 | F218: Wed, 17 Jun 2026 00:00:00 GMT | G218: =A218/D218-1 -> -0.013535816 | I218: 108.09 | J218: 114.07 | K218: 107.76 | L218: 112.4 | M218: 8375989.6 | N218: Wed, 17 Jun 2026 00:00:00 GMT | O218: =I218/L218-1 -> -0.038345196 | Q218: -0.085 | R218: 0 | T218: =T219-0.0025 -> -0.085 | U218: =_xlfn.NORM.DIST(T218,$S$203,$S$205,FALSE) -> 0.28348095 | W218: -1σ | X218: =($S$205*-1)+$S$203 -> -0.030671138 | Y218: 0
A219: 687.74703 | B219: 692.55303 | C219: 687.43793 | D219: 691.81518 | E219: 13322314 | F219: Tue, 16 Jun 2026 00:00:00 GMT | G219: =A219/D219-1 -> -0.005880403 | I219: 113.23 | J219: 114.58 | K219: 111.595 | L219: 111.98 | M219: 5015760.1 | N219: Tue, 16 Jun 2026 00:00:00 GMT | O219: =I219/L219-1 -> 0.011162708 | Q219: -0.0825 | R219: 1 | T219: =T220-0.0025 -> -0.0825 | U219: =_xlfn.NORM.DIST(T219,$S$203,$S$205,FALSE) -> 0.35368512 | X219: =($S$205*-1)+$S$203 -> -0.030671138 | Y219: 8
A220: 691.81518 | B220: 693.72961 | C220: 689.25264 | D220: 689.29253 | E220: 14057973 | F220: Mon, 15 Jun 2026 00:00:00 GMT | G220: =A220/D220-1 -> 0.0036597714 | I220: 112.49 | J220: 115.315 | K220: 110.2 | L220: 110.9 | M220: 6737783.1 | N220: Mon, 15 Jun 2026 00:00:00 GMT | O220: =I220/L220-1 -> 0.014337241 | Q220: -0.08 | R220: 0 | T220: =T221-0.0025 -> -0.08 | U220: =_xlfn.NORM.DIST(T220,$S$203,$S$205,FALSE) -> 0.43837425 | W220: 1σ | X220: =($S$205*1)+$S$203 -> 0.030892746 | Y220: 0
A221: 679.96968 | B221: 682.45115 | C221: 673.84751 | D221: 679.09722 | E221: 6314635.8 | F221: Fri, 12 Jun 2026 00:00:00 GMT | G221: =A221/D221-1 -> 0.0012847337 | I221: 108.24 | J221: 111.03 | K221: 106.98 | L221: 110.1 | M221: 8707990.3 | N221: Fri, 12 Jun 2026 00:00:00 GMT | O221: =I221/L221-1 -> -0.016893733 | Q221: -0.0775 | R221: 1 | T221: =T222-0.0025 -> -0.0775 | U221: =_xlfn.NORM.DIST(T221,$S$203,$S$205,FALSE) -> 0.53976986 | X221: =($S$205*1)+$S$203 -> 0.030892746 | Y221: 8
A222: 676.26048 | B222: 678.40424 | C222: 664.066 | D222: 668.15409 | E222: 19926769 | F222: Thu, 11 Jun 2026 00:00:00 GMT | G222: =A222/D222-1 -> 0.012132518 | I222: 110.47 | J222: 110.57 | K222: 104.11 | L222: 106.9 | M222: 8018926.8 | N222: Thu, 11 Jun 2026 00:00:00 GMT | O222: =I222/L222-1 -> 0.033395697 | Q222: -0.075 | R222: 0 | T222: =T223-0.0025 -> -0.075 | U222: =_xlfn.NORM.DIST(T222,$S$203,$S$205,FALSE) -> 0.66024872 | W222: 2σ | X222: =($S$205*2)+$S$203 -> 0.061674687 | Y222: 0
A223: 665.11295 | B223: 676.90361 | C223: 664.94344 | D223: 672.35685 | E223: 16356103 | F223: Wed, 10 Jun 2026 00:00:00 GMT | G223: =A223/D223-1 -> -0.010773896 | I223: 108.2 | J223: 110.25 | K223: 106.4 | L223: 108.6 | M223: 7304284.5 | N223: Wed, 10 Jun 2026 00:00:00 GMT | O223: =I223/L223-1 -> -0.0036832413 | Q223: -0.0725 | R223: 1 | T223: =T224-0.0025 -> -0.0725 | U223: =_xlfn.NORM.DIST(T223,$S$203,$S$205,FALSE) -> 0.80230935 | X223: =($S$205*2)+$S$203 -> 0.061674687 | Y223: 2
A224: 675.73202 | B224: 684.76571 | C224: 662.39098 | D224: 681.72457 | E224: 13824282 | F224: Tue, 09 Jun 2026 00:00:00 GMT | G224: =A224/D224-1 -> -0.0087902766 | I224: 110.42 | J224: 116.96 | K224: 107.19 | L224: 111 | M224: 7805019.1 | N224: Tue, 09 Jun 2026 00:00:00 GMT | O224: =I224/L224-1 -> -0.0052252252 | Q224: -0.07 | R224: 0 | T224: =T225-0.0025 -> -0.07 | U224: =_xlfn.NORM.DIST(T224,$S$203,$S$205,FALSE) -> 0.96852644 | W224: 3σ | X224: =($S$205*3)+$S$203 -> 0.092456629 | Y224: 0
A225: 677.70627 | B225: 683.29998 | C225: 676.72912 | D225: 681.48527 | E225: 8770213.3 | F225: Mon, 08 Jun 2026 00:00:00 GMT | G225: =A225/D225-1 -> -0.0055452324 | I225: 110.78 | J225: 114.88 | K225: 110.52 | L225: 113.58 | M225: 6945929.6 | N225: Mon, 08 Jun 2026 00:00:00 GMT | O225: =I225/L225-1 -> -0.024652228 | Q225: -0.0675 | R225: 0 | T225: =T226-0.0025 -> -0.0675 | U225: =_xlfn.NORM.DIST(T225,$S$203,$S$205,FALSE) -> 1.1614926 | X225: =($S$205*3)+$S$203 -> 0.092456629 | Y225: 0.2
A226: 676.03115 | B226: 690.16997 | C226: 674.28623 | D226: 689.70134 | E226: 10720357 | F226: Fri, 05 Jun 2026 00:00:00 GMT | G226: =A226/D226-1 -> -0.019820445 | I226: 109.54 | J226: 115.9 | K226: 108.29 | L226: 114.5 | M226: 7940731.3 | N226: Fri, 05 Jun 2026 00:00:00 GMT | O226: =I226/L226-1 -> -0.043318777 | Q226: -0.065 | R226: 2 | T226: =T227-0.0025 -> -0.065 | U226: =_xlfn.NORM.DIST(T226,$S$203,$S$205,FALSE) -> 1.3837473
A227: 694.03871 | B227: 695.17539 | C227: 688.89369 | D227: 689.48198 | E227: 6594038 | F227: Thu, 04 Jun 2026 00:00:00 GMT | G227: =A227/D227-1 -> 0.006608917 | I227: 116.04 | J227: 117.77 | K227: 114.3346 | L227: 115.875 | M227: 7037415.5 | N227: Thu, 04 Jun 2026 00:00:00 GMT | O227: =I227/L227-1 -> 0.0014239482 | Q227: -0.0625 | R227: 1 | T227: =T228-0.0025 -> -0.0625 | U227: =_xlfn.NORM.DIST(T227,$S$203,$S$205,FALSE) -> 1.6376928
A228: 691.34655 | B228: 695.62399 | C228: 690.83803 | D228: 695.05574 | E228: 5899709.5 | F228: Wed, 03 Jun 2026 00:00:00 GMT | G228: =A228/D228-1 -> -0.0053365467 | I228: 112.94 | J228: 115.26 | K228: 112.5 | L228: 114.61 | M228: 7404148.8 | N228: Wed, 03 Jun 2026 00:00:00 GMT | O228: =I228/L228-1 -> -0.014571154 | Q228: -0.06 | R228: 0 | T228: =T229-0.0025 -> -0.06 | U228: =_xlfn.NORM.DIST(T228,$S$203,$S$205,FALSE) -> 1.9254997
A229: 696.23232 | B229: 697.11973 | C229: 693.75952 | D229: 694.03871 | E229: 4712080 | F229: Tue, 02 Jun 2026 00:00:00 GMT | G229: =A229/D229-1 -> 0.0031606471 | I229: 117.01 | J229: 121.53 | K229: 115.535 | L229: 120.455 | M229: 9024535.3 | N229: Tue, 02 Jun 2026 00:00:00 GMT | O229: =I229/L229-1 -> -0.028599892 | Q229: -0.0575 | R229: 0 | T229: =T230-0.0025 -> -0.0575 | U229: =_xlfn.NORM.DIST(T229,$S$203,$S$205,FALSE) -> 2.2490018
A230: 695.2751 | B230: 697.02999 | C230: 691.92486 | D230: 692.52312 | E230: 9977807.5 | F230: Mon, 01 Jun 2026 00:00:00 GMT | G230: =A230/D230-1 -> 0.0039738532 | I230: 124.12 | J230: 124.625 | K230: 119.055 | L230: 120.25 | M230: 10538707 | N230: Mon, 01 Jun 2026 00:00:00 GMT | O230: =I230/L230-1 -> 0.032182952 | Q230: -0.055 | R230: 0 | T230: =T231-0.0025 -> -0.055 | U230: =_xlfn.NORM.DIST(T230,$S$203,$S$205,FALSE) -> 2.6095854
A231: 693.47036 | B231: 694.97598 | C231: 691.87501 | D231: 692.98178 | E231: 5053895.6 | F231: Fri, 29 May 2026 00:00:00 GMT | G231: =A231/D231-1 -> 0.00070503597 | I231: 118.71 | J231: 119.84 | K231: 113.45 | L231: 116.382 | M231: 11548730 | N231: Fri, 29 May 2026 00:00:00 GMT | O231: =I231/L231-1 -> 0.020003093 | Q231: -0.0525 | R231: 1 | T231: =T232-0.0025 -> -0.0525 | U231: =_xlfn.NORM.DIST(T231,$S$203,$S$205,FALSE) -> 3.0080743
A232: 691.89495 | B232: 692.27385 | C232: 686.84964 | D232: 687.757 | E232: 8469446.4 | F232: Thu, 28 May 2026 00:00:00 GMT | G232: =A232/D232-1 -> 0.0060165855 | I232: 115.03 | J232: 115.25 | K232: 106.96 | L232: 107.185 | M232: 14132227 | N232: Thu, 28 May 2026 00:00:00 GMT | O232: =I232/L232-1 -> 0.073191211 | Q232: -0.05 | R232: 0 | T232: =T233-0.0025 -> -0.05 | U232: =_xlfn.NORM.DIST(T232,$S$203,$S$205,FALSE) -> 3.444617
A233: 687.95642 | B233: 688.77404 | C233: 685.92234 | D233: 688.35526 | E233: 7356729.2 | F233: Wed, 27 May 2026 00:00:00 GMT | G233: =A233/D233-1 -> -0.00057940785 | I233: 106.6 | J233: 109.1 | K233: 103.825 | L233: 103.98 | M233: 8211035.3 | N233: Wed, 27 May 2026 00:00:00 GMT | O233: =I233/L233-1 -> 0.025197153 | Q233: -0.0475 | R233: 2 | T233: =T234-0.0025 -> -0.0475 | U233: =_xlfn.NORM.DIST(T233,$S$203,$S$205,FALSE) -> 3.9185797
A234: 688.00627 | B234: 689.50242 | C234: 686.08188 | D234: 687.64732 | E234: 6622042.8 | F234: Tue, 26 May 2026 00:00:00 GMT | G234: =A234/D234-1 -> 0.00052200392 | I234: 104.9 | J234: 105.1 | K234: 102.32 | L234: 103.23 | M234: 7912458.5 | N234: Tue, 26 May 2026 00:00:00 GMT | O234: =I234/L234-1 -> 0.016177468 | Q234: -0.045 | R234: 3 | T234: =T235-0.0025 -> -0.045 | U234: =_xlfn.NORM.DIST(T234,$S$203,$S$205,FALSE) -> 4.4284502
A235: 683.55923 | B235: 686.58043 | C235: 682.49223 | D235: 684.10763 | E235: 4276144.9 | F235: Fri, 22 May 2026 00:00:00 GMT | G235: =A235/D235-1 -> -0.00080163242 | I235: 103 | J235: 107.85 | K235: 102.98 | L235: 105.81 | M235: 10431078 | N235: Fri, 22 May 2026 00:00:00 GMT | O235: =I235/L235-1 -> -0.026557036 | Q235: -0.0425 | R235: 3 | T235: =T236-0.0025 -> -0.0425 | U235: =_xlfn.NORM.DIST(T235,$S$203,$S$205,FALSE) -> 4.9717604
A236: 680.8571 | B236: 682.83633 | C236: 675.65225 | D236: 677.10801 | E236: 7310162.6 | F236: Thu, 21 May 2026 00:00:00 GMT | G236: =A236/D236-1 -> 0.0055369029 | I236: 104.86 | J236: 106.42 | K236: 101.655 | L236: 103.24 | M236: 6925634.6 | N236: Thu, 21 May 2026 00:00:00 GMT | O236: =I236/L236-1 -> 0.015691592 | Q236: -0.04 | R236: 2 | T236: =T237-0.0025 -> -0.04 | U236: =_xlfn.NORM.DIST(T236,$S$203,$S$205,FALSE) -> 5.5450308
A237: 679.59078 | B237: 680.01953 | C237: 672.78072 | D237: 674.35603 | E237: 5453356.5 | F237: Wed, 20 May 2026 00:00:00 GMT | G237: =A237/D237-1 -> 0.0077625976 | I237: 105.01 | J237: 105.12 | K237: 99.231 | L237: 100.19 | M237: 8074999.6 | N237: Wed, 20 May 2026 00:00:00 GMT | O237: =I237/L237-1 -> 0.048108594 | Q237: -0.0375 | R237: 3 | T237: =T238-0.0025 -> -0.0375 | U237: =_xlfn.NORM.DIST(T237,$S$203,$S$205,FALSE) -> 6.1437435
... A251: 658.66174 | B251: 659.84828 | C251: 651.24833 | D251: 655.09213 | E251: 5919880.4 | F251: Thu, 30 Apr 2026 00:00:00 GMT | G251: =A251/D251-1 -> 0.0054490107 | I251: 121.13 | J251: 122.58 | K251: 118.35 | L251: 120.79 | M251: 6633004 | N251: Thu, 30 Apr 2026 00:00:00 GMT | O251: =I251/L251-1 -> 0.0028148025 | Q251: -0.0025 | R251: 10 | T251: =T252-0.0025 -> -0.0025 | U251: =_xlfn.NORM.DIST(T251,$S$203,$S$205,FALSE) -> 12.913737
A252: 652.34015 | B252: 652.82244 | C252: 649.3688 | D252: 651.72195 | E252: 6221167.1 | F252: Wed, 29 Apr 2026 00:00:00 GMT | G252: =A252/D252-1 -> 0.00094856339 | I252: 121.26 | J252: 122.0325 | K252: 119.42 | L252: 121.14 | M252: 5053389.8 | N252: Wed, 29 Apr 2026 00:00:00 GMT | O252: =I252/L252-1 -> 0.0009905894 | Q252: 0 | R252: 12 | T252: 0 | U252: =_xlfn.NORM.DIST(T252,$S$203,$S$205,FALSE) -> 12.960186
A253: 652.36009 | B253: 653.48681 | C253: 650.11662 | D253: 652.50965 | E253: 5525716 | F253: Tue, 28 Apr 2026 00:00:00 GMT | G253: =A253/D253-1 -> -0.0002292141 | I253: 122.05 | J253: 127.31 | K253: 121.98 | L253: 123.69 | M253: 4814702.4 | N253: Tue, 28 Apr 2026 00:00:00 GMT | O253: =I253/L253-1 -> -0.013258954 | Q253: 0.0025 | R253: 12 | T253: =T252+0.0025 -> 0.0025 | U253: =_xlfn.NORM.DIST(T253,$S$203,$S$205,FALSE) -> 12.92129
A254: 655.59068 | B254: 655.98952 | C254: 652.9384 | D254: 653.76599 | E254: 5297681.3 | F254: Mon, 27 Apr 2026 00:00:00 GMT | G254: =A254/D254-1 -> 0.0027910382 | I254: 124.23 | J254: 126.2282 | K254: 123.09 | L254: 124.405 | M254: 3871174.3 | N254: Mon, 27 Apr 2026 00:00:00 GMT | O254: =I254/L254-1 -> -0.0014066959 | Q254: 0.005 | R254: 9 | T254: =T253+0.0025 -> 0.005 | U254: =_xlfn.NORM.DIST(T254,$S$203,$S$205,FALSE) -> 12.797816
A255: 654.51382 | B255: 654.91265 | C255: 649.92737 | D255: 651.50259 | E255: 4736752.5 | F255: Fri, 24 Apr 2026 00:00:00 GMT | G255: =A255/D255-1 -> 0.0046219773 | I255: 125.83 | J255: 126.46 | K255: 121.66 | L255: 124.5 | M255: 8290803.9 | N255: Fri, 24 Apr 2026 00:00:00 GMT | O255: =I255/L255-1 -> 0.010682731 | Q255: 0.0075 | R255: 7 | T255: =T254+0.0025 -> 0.0075 | U255: =_xlfn.NORM.DIST(T255,$S$203,$S$205,FALSE) -> 12.592188
A256: 649.3688 | B256: 652.99823 | C256: 643.78506 | D256: 650.33598 | E256: 6034316.6 | F256: Thu, 23 Apr 2026 00:00:00 GMT | G256: =A256/D256-1 -> -0.0014872054 | I256: 124.23 | J256: 130.3 | K256: 121.7301 | L256: 130 | M256: 7419992.3 | N256: Thu, 23 Apr 2026 00:00:00 GMT | O256: =I256/L256-1 -> -0.044384615 | Q256: 0.01 | R256: 10 | T256: =T255+0.0025 -> 0.01 | U256: =_xlfn.NORM.DIST(T256,$S$203,$S$205,FALSE) -> 12.308408
A257: 652.00113 | B257: 652.29029 | C257: 649.19929 | D257: 650.08671 | E257: 4504953.3 | F257: Wed, 22 Apr 2026 00:00:00 GMT | G257: =A257/D257-1 -> 0.0029448756 | I257: 131.96 | J257: 133.77 | K257: 131.25 | L257: 133.39 | M257: 5604966.4 | N257: Wed, 22 Apr 2026 00:00:00 GMT | O257: =I257/L257-1 -> -0.010720444 | Q257: 0.0125 | R257: 10 | T257: =T256+0.0025 -> 0.0125 | U257: =_xlfn.NORM.DIST(T257,$S$203,$S$205,FALSE) -> 11.951926
A258: 645.37045 | B258: 651.96125 | C258: 644.06465 | D258: 651.04392 | E258: 8481656.3 | F258: Tue, 21 Apr 2026 00:00:00 GMT | G258: =A258/D258-1 -> -0.0087144301 | I258: 131.13 | J258: 137.3 | K258: 130.86 | L258: 135.215 | M258: 6860771.9 | N258: Tue, 21 Apr 2026 00:00:00 GMT | O258: =I258/L258-1 -> -0.030211145 | Q258: 0.015 | R258: 2 | T258: =T257+0.0025 -> 0.015 | U258: =_xlfn.NORM.DIST(T258,$S$203,$S$205,FALSE) -> 11.529468
A259: 649.64799 | B259: 650.70491 | C259: 647.28487 | D259: 649.72776 | E259: 6369044.3 | F259: Mon, 20 Apr 2026 00:00:00 GMT | G259: =A259/D259-1 -> -0.00012277094 | I259: 135.14 | J259: 135.33 | K259: 129.56 | L259: 130.05 | M259: 5607038.4 | N259: Mon, 20 Apr 2026 00:00:00 GMT | O259: =I259/L259-1 -> 0.039138793 | Q259: 0.0175 | R259: 8 | T259: =T258+0.0025 -> 0.0175 | U259: =_xlfn.NORM.DIST(T259,$S$203,$S$205,FALSE) -> 11.048822
A260: 650.88439 | B260: 652.97829 | C260: 646.97577 | D260: 647.29484 | E260: 7806647.4 | F260: Fri, 17 Apr 2026 00:00:00 GMT | G260: =A260/D260-1 -> 0.0055454573 | I260: 131.15 | J260: 133.32 | K260: 129.825 | L260: 130.14 | M260: 8465085.5 | N260: Fri, 17 Apr 2026 00:00:00 GMT | O260: =I260/L260-1 -> 0.0077608729 | Q260: 0.02 | R260: 2 | T260: =T259+0.0025 -> 0.02 | U260: =_xlfn.NORM.DIST(T260,$S$203,$S$205,FALSE) -> 10.518602
A261: 642.98739 | B261: 644.19387 | C261: 640.28526 | D261: 642.6384 | E261: 5875107.3 | F261: Thu, 16 Apr 2026 00:00:00 GMT | G261: =A261/D261-1 -> 0.00054304821 | I261: 126.94 | J261: 130.69 | K261: 125.84 | L261: 130.15 | M261: 6306399.8 | N261: Thu, 16 Apr 2026 00:00:00 GMT | O261: =I261/L261-1 -> -0.024663849 | Q261: 0.0225 | R261: 10 | T261: =T260+0.0025 -> 0.0225 | U261: =_xlfn.NORM.DIST(T261,$S$203,$S$205,FALSE) -> 9.9479917
A262: 641.58148 | B262: 641.92049 | C262: 636.37664 | D262: 637.33385 | E262: 5065156.5 | F262: Wed, 15 Apr 2026 00:00:00 GMT | G262: =A262/D262-1 -> 0.006664685 | I262: 127.41 | J262: 127.7 | K262: 118.23 | L262: 119.1 | M262: 9131130.4 | N262: Wed, 15 Apr 2026 00:00:00 GMT | O262: =I262/L262-1 -> 0.0697733 | Q262: 0.025 | R262: 1 | T262: =T261+0.0025 -> 0.025 | U262: =_xlfn.NORM.DIST(T262,$S$203,$S$205,FALSE) -> 9.3464817
A263: 636.49629 | B263: 636.6658 | C263: 630.38409 | D263: 630.38908 | E263: 5013507.9 | F263: Tue, 14 Apr 2026 00:00:00 GMT | G263: =A263/D263-1 -> 0.0096880066 | I263: 117.64 | J263: 119.115 | K263: 115.56 | L263: 116.97 | M263: 8928276.6 | N263: Tue, 14 Apr 2026 00:00:00 GMT | O263: =I263/L263-1 -> 0.0057279644 | Q263: 0.0275 | R263: 6 | T263: =T262+0.0025 -> 0.0275 | U263: =_xlfn.NORM.DIST(T263,$S$203,$S$205,FALSE) -> 8.7236101
A264: 628.88845 | B264: 629.06792 | C264: 620.17383 | D264: 620.94159 | E264: 5115773.6 | F264: Mon, 13 Apr 2026 00:00:00 GMT | G264: =A264/D264-1 -> 0.012798073 | I264: 114.97 | J264: 115.68 | K264: 109.32 | L264: 109.45 | M264: 10095151 | N264: Mon, 13 Apr 2026 00:00:00 GMT | O264: =I264/L264-1 -> 0.050433988 | Q264: 0.03 | R264: 3 | T264: =T263+0.0025 -> 0.03 | U264: =_xlfn.NORM.DIST(T264,$S$203,$S$205,FALSE) -> 8.0887178
... A292: 621.93935 | B292: 623.99684 | C292: 612.1588 | D292: 617.05901 | E292: 17858757 | F292: Tue, 03 Mar 2026 00:00:00 GMT | G292: =A292/D292-1 -> 0.0079090221 | I292: 121.87 | J292: 122.03 | K292: 112.4478 | L292: 114.945 | M292: 11915489 | N292: Tue, 03 Mar 2026 00:00:00 GMT | O292: =I292/L292-1 -> 0.060246205 | Q292: 0.1 | R292: 0 | T292: =T291+0.0025 -> 0.1 | U292: =_xlfn.NORM.DIST(T292,$S$203,$S$205,FALSE) -> 0.066983215
A293: 627.46575 | B293: 629.51331 | C293: 619.83216 | D293: 620.41362 | E293: 9196640.1 | F293: Mon, 02 Mar 2026 00:00:00 GMT | G293: =A293/D293-1 -> 0.011366822 | I293: 119.38 | J293: 120.24 | K293: 114.37 | L293: 115.8 | M293: 8139670.4 | N293: Mon, 02 Mar 2026 00:00:00 GMT | O293: =I293/L293-1 -> 0.030915371 | Q293: More | R293: 0
A294: 627.2272 | B294: 627.87328 | C294: 623.15198 | D294: 624.44412 | E294: 10491519 | F294: Fri, 27 Feb 2026 00:00:00 GMT | G294: =A294/D294-1 -> 0.0044568955 | I294: 120.73 | J294: 123.925 | K294: 118.56 | L294: 123.475 | M294: 9773941.5 | N294: Fri, 27 Feb 2026 00:00:00 GMT | O294: =I294/L294-1 -> -0.022231221
A295: 630.11962 | B295: 633.91654 | C295: 625.62693 | D295: 633.79727 | E295: 9465251.1 | F295: Thu, 26 Feb 2026 00:00:00 GMT | G295: =A295/D295-1 -> -0.0058025563 | I295: 125.94 | J295: 126 | K295: 120.75 | L295: 121.49 | M295: 11976295 | N295: Thu, 26 Feb 2026 00:00:00 GMT | O295: =I295/L295-1 -> 0.036628529
A296: 633.67799 | B296: 634.14515 | C296: 630.90485 | D296: 630.93467 | E296: 12065850 | F296: Wed, 25 Feb 2026 00:00:00 GMT | G296: =A296/D296-1 -> 0.0043480316 | I296: 120.31 | J296: 123.77 | K296: 117.6401 | L296: 117.955 | M296: 10120395 | N296: Wed, 25 Feb 2026 00:00:00 GMT | O296: =I296/L296-1 -> 0.019965241
A297: 628.39013 | B297: 629.26482 | C297: 621.62128 | D297: 623.36071 | E297: 6934297.7 | F297: Tue, 24 Feb 2026 00:00:00 GMT | G297: =A297/D297-1 -> 0.0080682452 | I297: 116.93 | J297: 120.28 | K297: 115.7 | L297: 117 | M297: 11120838 | N297: Tue, 24 Feb 2026 00:00:00 GMT | O297: =I297/L297-1 -> -0.0005982906
A298: 623.83781 | B298: 630.77563 | C298: 621.96917 | D298: 628.78772 | E298: 10883526 | F298: Mon, 23 Feb 2026 00:00:00 GMT | G298: =A298/D298-1 -> -0.0078721487 | I298: 117.28 | J298: 124.4 | K298: 115.88 | L298: 123.935 | M298: 12529266 | N298: Mon, 23 Feb 2026 00:00:00 GMT | O298: =I298/L298-1 -> -0.053697503
A299: 630.1892 | B299: 630.74582 | C299: 623.24143 | D299: 623.68871 | E299: 7493334.3 | F299: Fri, 20 Feb 2026 00:00:00 GMT | G299: =A299/D299-1 -> 0.010422643 | I299: 126.2 | J299: 131.01 | K299: 120.736 | L299: 122.26 | M299: 14548006 | N299: Fri, 20 Feb 2026 00:00:00 GMT | O299: =I299/L299-1 -> 0.032226403
A300: 625.72633 | B300: 627.26696 | C300: 623.02276 | D300: 625.14983 | E300: 5201993.9 | F300: Thu, 19 Feb 2026 00:00:00 GMT | G300: =A300/D300-1 -> 0.00092217187 | I300: 123.8 | J300: 124.65 | K300: 119.62 | L300: 120.13 | M300: 12218011 | N300: Thu, 19 Feb 2026 00:00:00 GMT | O300: =I300/L300-1 -> 0.030550237
A301: 627.33654 | B301: 629.97053 | C301: 624.20557 | D301: 625.30887 | E301: 9566979.5 | F301: Wed, 18 Feb 2026 00:00:00 GMT | G301: =A301/D301-1 -> 0.0032426762 | I301: 121.64 | J301: 124.73 | K301: 112.49 | L301: 113.01 | M301: 18689967 | N301: Wed, 18 Feb 2026 00:00:00 GMT | O301: =I301/L301-1 -> 0.076364923
A302: 624.19563 | B302: 626.12391 | C302: 617.75479 | D302: 621.76044 | E302: 8088295.1 | F302: Tue, 17 Feb 2026 00:00:00 GMT | G302: =A302/D302-1 -> 0.003916616 | I302: 113.54 | J302: 116.63 | K302: 110.91 | L302: 112.5 | M302: 14545616 | N302: Tue, 17 Feb 2026 00:00:00 GMT | O302: =I302/L302-1 -> 0.0092444444
...

Sheet Product Lines

Sheet Management

Sheet Table Formatting
B2: [Bold Title] | G2: [Bold Title]
B3: Line Titles | G3: <-- General
B4: Line Titles | G4: <-- Info
B5: Line Titles | G5: <-- General
B6: Line Titles | G6: <-- Info
B7: Line Titles | G7: <-- General
B8: Line Titles | G8: <-- Info
