Workbook

Sheet Main
A2: Capital Structure Snapshot:
B4: SRPT
B5: Price | C5: 23.73 | D5: 1/10/2026
B6: SO | C6: 104.787 | D6: Q3'25
B7: MC | C7: =C5*C6 -> 2486.5955
B8: Cash | C8: =510.59+289.54+195.52 -> 995.65 | D8: Q3'25 | O8: Resources:
B9: Debt | C9: ='Bull Case (20%)'!X65 -> 1139.458 | D9: Q3'25 | O9: SEC Filings | R9: https://www.sec.gov/edgar/browse/?CIK=873303&owner=exclude
B10: EV | C10: =C7-C8+C9 -> 2630.4035 | O10: Sarepta Homepage | R10: https://www.sarepta.com/
P11: Sarepta IR Page | S11: https://investorrelations.sarepta.com/
B12: Sarepta, Therapeutics Inc. (SRPT) | O12: Earnings Calls | R12: https://seekingalpha.com/symbol/SRPT/sec-filings
O13: Equity Analysis | R13: https://stockanalysis.com/stocks/srpt/company/
B14: Founder(s): James Summerton & Dwight Weller | H14: Registered Exchange: NASDAQ | O14: MacroTrends | R14: https://www.macrotrends.net/stocks/charts/SRPT/sarepta-therapeutics/income-statement?freq=A
B15: Founded: 1980 | H15: Address: | I15: 215 First Street, Suite 415, Cambridge, MA 02142 | O15: ROIC/WACC | R15: https://www.gurufocus.com/term/wacc/SRPT
B16: Headquarters: Cambridge, MA | H16: Investor Relations Contact: | O16: Godel Terminal | R16: https://app.godelterminal.com/
B17: Current CEO: Douglas Ingram | H17: Investors Relation Department | O17: Pharsight Patent Search | R17: https://pharsight.greyb.com/drug/exondys-51-patent-expiration
B18: Employees: 1,372 (Q4'24) | H18: Phone: | I18: (617) 274-4000 | K18: Email: | L18: investors@sarepta.com | P18: Vyondys 53 | S18: https://pharsight.greyb.com/drug/vyondys-53-patent-expiration
B19: Industry: BioTech | P19: Amondys 45 Scope | S19: https://pharsight.greyb.com/drug/amondys-45-patent-expiration
B20: Sector: Healthcare | P20: Exondys 51 | S20: https://pharsight.greyb.com/drug/exondys-51-patent-expiration
B21: IPO: June 3rd, 1997 -- ~$600M valuation | O21: Duchenne Info | R21: https://cureduchenne.org/about/what-is-duchenne/
A23: Company Overview:
B24: Sarepta Therapeutics, Inc., a commercial-stage biopharmaceutical company, focuses on the discovery and development of RNA-targeted therapeutics, gene therapies, and other genetic therapeutic modalities for the treatment of rare diseases
C25: It offers EXONDYS 51 injection to treat Duchenne muscular dystrophy (Duchenne) in patients with confirmed mutation of the dystrophin gene that is amenable to exon 51 skipping
C26: VYONDYS 53 for the treatment of Duchenne in patients with confirmed mutation of the dystrophin gene that is amenable to exon 53 skipping
C27: AMONDYS 45, for the treatment of Duchenne in patients with confirmed mutation of the dystrophin gene that is amenable to exon 45 skipping
C28: ELEVIDYS, an adeno-associated virus based gene therapy for the treatment of ambulatory pediatric patients with Duchenne with a confirmed mutation in the Duchenne gene
C29: The company is also developing SRP-9003, a limb-girdle muscular dystrophies gene therapy program
B30: It has collaboration and license agreements with:
C31: F. Hoffman-La Roche Ltd
C32: Arrowhead Pharmaceuticals, Inc.
C33: University of Western Australia
C34: Catalent Maryland, Inc.
C35: Nationwide Children’s Hospital
C36: Dyno Therapeutics
C37: Hansa Biopharma
C38: Duke University
C39: Genethon
B40: The Company was incorporated in 1980 and is headquartered in Cambridge, Massachusetts
B41: The Company's current portfolio seeks to address Duchenne muscular dystrophy (DMD), a rare, progressive genetic disorder that primarily affects boys
C42: By the age of 12, many are reliant on wheelchairs due to muscle degeneration and also encounter social isolation
C43: The condition complicates even the simplest daily activities and, as it progresses, critically affects the heart and respiratory muscles
C44: Duchenne is classified under muscular dystrophies, genetic diseases marked by muscle weakness, with Duchenne being notably the most severe due to the absence of dystrophin, a protein essential for muscle integrity
C45: Research into the genetic underpinnings of Duchenne has been ongoing since the dystrophin gene’s identification in 1986
C46: CureDuchenne is committed to improving the lives of everyone affected through accelerating research to find a cure, improving care and empowering the our community
B47: The Company's research and therapies are focused on exon skipping approaches (Denoted in the drugs name)
B48: Prevalence:
B49: More than 900 patients globally have received Elevidys for Duchenne muscular dystrophy as of June 2025, including both clinical trial participants and commercial recipients
G51: Total Sales | I51: Bull Case: | M51: Base Case: | Q51: Bear Case:
B52: United States: | D52: 15000 | E52: Cases | I52: 17,500 Patients | M52: 12,000 Patients | Q52: 5,000 Patients
B53: Globally: | D53: 300000 | E53: Cases | I53: $38B (Elevidys + PMOs by 2044) | M53: $22B (Elevidys + PMOs by 2038) | Q53: $16B (Elevidys + PMOs (by 2038)
B54: Even with strong demand, the total addressable market is small, and uptake is constrained by payer coverage, regulatory approvals, and the ability of healthcare systems to absorb such high-cost therapies
A56: Business Segments:
B57: PMOs Offerings
B58: EXONDYS 51 (eteplirsen), VYONDYS 53 (golodirsen), and AMONDYS 45 (casimersen) are synthetic antisense oligonucleotide therapies offered by The Company, which use PMO (phosphorodiamidate morpholino oligomer) technology to treat Duchenne muscular dystrophy (DMD)
C59: These drugs work by binding to specific exons in the dystrophin gene’s pre-mRNA and promoting exon skipping during RNA splicing
C60: This process enables the production of a shorter, but partially functional, dystrophin protein in patients with certain genetic mutations, helping to slow disease progression and improve muscle function
B61: PMO (phosphorodiamidate morpholino oligomer) are a type of synthetic molecule where the natural ribose sugar in DNA/RNA is replaced with a morpholine ring, and the phosphate linkage is replaced with a phosphorodiamidate linkage
C62: This structure makes PMOs uncharged and highly resistant to degradation, allowing them to bind to RNA and modulate gene expression
B63: Drug: | G63: FDA 510(k) Approval Date | K63: Generic Name: | N63: Mechanism:
C64: EXONDYS 51 | H64: 9/19/2016 | K64: Eteplirsen | N64: Exon 51 skipping
C65: VYONDYS 53 | H65: 12/12/2019 | K65: Golodirsen | N65: Exon 53 skipping
C66: AMONDYS 45 | H66: 2/25/2021 | K66: Casimersen | N66: Exon 45 skipping
B67: NCE-1 date:
C68: NCE-1 is the earliest point when generic competition might begin, provided a challenge to the patent is successful
C69: EXONDYS 51 | F69: Since the approval date for Exondys 51 is 19 September, 2016, its NCE-1 date is estimated to be 19 September, 2020
C70: VYONDYS 53 | F70: Since the approval date for Vyondys 53 is 12 December, 2019, its NCE-1 date is estimated to be 13 December, 2023
C71: AMONDYS 45 | F71: Since the approval date for Amondys 45 is 25 February, 2021, its NCE-1 date is estimated to be 25 February, 2025
B72: EXONDYS 51 (eteplirsen), VYONDYS 53 (golodirsen), and AMONDYS 45 (casimersen) are all protected by patents and regulatory exclusivities, which delay the entry of generic versions into the market
C73: While IP protection will fall away, entry into the DMD space is constrained by several other barriers that are not typically present in small molecule drug businesses
B74: The Company currently leads the market for PMO-based exon-skipping therapies, but several companies are developing or advancing competing antisense oligonucleotide (PMO and next-generation) therapies targeting Duchenne muscular dystrophy
B75: Pricing:
C76: EXONDYS 51 | F76: The price for EXONDYS 51 is weight-based and can exceed $1 million per patient per year … a typical pediatric dose (based on 20 kg body weight) is estimated at around $300,000 per year, but for heavier patients, the annual cost can be much higher, often cited in the range of $1.3 million per year on average
C77: VYONDYS 53 | F77: Like EXONDYS 51, VYONDYS 53 is also dosed by weight and has a similar annual cost structure, with payer costs averaging around $1.3 million per year
C78: AMONDYS 45 | F78: AMONDYS 45 follows the same pricing model as the other two drugs, with treatment for a 20 kg child costing about $300,000 per year, and average costs for older/heavier patients reaching $1.3 million per year
C79: Pricing for these drugs is weight-based … treatment costs can be anywhere between $300K - $1.3M annually
D80: All three drugs are among the most expensive therapies on the market, reflecting their complexity, rarity of the disease, and lack of generic alternatives
D81: Actual patient cost may vary based on weight, insurance coverage, and negotiated discounts
B82: Key Potential and Emerging Competitors:
C83: Avidity Biosciences
D84: Lead candidate: Delpacibart zotadirsen (del-zota), an antibody-PMO conjugate targeting exon 44 skipping
D85: Technology: Combines a PMO with an antibody to enhance delivery to muscle, aiming for improved efficacy over traditional PMOs
D86: Status: In phase 1/2 clinical trials; has shown promising early results, including increased dystrophin production and exon skipping
C87: Dyne Therapeutics
D88: Lead candidate: DYNE-251, designed for exon 51 skipping (the same target as EXONDYS 51)
D89: Technology: Uses proprietary delivery technology to improve PMO uptake in muscle
D90: Status: Ongoing clinical trials with new long-term data reported in 2025
B91: Other Notable Programs:
C92: Wave Life Sciences
D93: Pipeline: Developing next-generation stereopure oligonucleotides for DMD, aiming to improve potency and durability over current PMO drugs
C94: Nippon Shinyaku
D95: Offering: Viltepso (viltolarsen), an exon 53-skipping PMO, is approved in Japan and the US, directly competing with Sarepta’s VYONDYS 53
C96: NS Pharma
D97: Offering: Also markets viltolarsen in the US
C98: Dyne Therapeutics and others:
D99: Several firms are developing preclinical or early clinical exon-skipping therapies using novel delivery systems or modifications to the PMO backbone
B101: Elevidys | D101: FDA 510(k) Approval: 6/20/2024 | H101: Seeks to treat DMD in all patients 4 years or older | N101: Price: $3.2M for single infusion treatment
B102: Elevidys (delandistrogene moxeparvovec-rokl) is the first (and as of 2025, only) gene therapy approved to treat Duchenne muscular dystrophy (DMD) in both ambulatory and non-ambulatory patients aged 4 and older, marking a historic milestone in DMD treatment
C103: Unlike PMO therapies that modify RNA splicing to partially restore dystrophin production, Elevidys delivers a new gene directly to muscle cells, enabling them to produce micro-dystrophin—a shortened but functional version of the dystrophin protein that DMD patients lack
C104: Elevidys is administered as a single intravenous infusion, offering the potential for long-lasting or even permanent benefit, compared to the ongoing, regular dosing required for PMO therapies
B105: Elevidys uses an engineered adeno-associated virus (AAV) to carry the micro-dystrophin gene into muscle cells throughout the body
C106: Once inside, the new gene is expressed, allowing muscle cells to produce micro-dystrophin, which helps stabilize and protect muscle fibers from damage
...

Sheet Bull Case (20%)
C1: Q1 2020 | G1: Q1 2021 | K1: Q1 2022 | O1: Q1 2023 | S1: Q1 2024 | W1: Q1 2025 | AA1: Q1 2026
B2: Quarterly
B3: Revenues | C3: Q1 2020 | D3: Q2 2020 | E3: Q3 2020 | F3: Q4 2020 | G3: Q1 2021 | H3: Q2 2021 | I3: Q3 2021 | J3: Q4 2021 | K3: Q1 2022 | L3: Q2 2022 | M3: Q3 2022 | N3: Q4 2022 | O3: Q1 2023 | P3: Q2 2023 | Q3: Q3 2023 | R3: Q4 2023 | S3: Q1 2024 | T3: Q2 2024 | U3: Q3 2024 | V3: Q4 2024 | W3: Q1 2025 | X3: Q2 2025 | Y3: Q3 2025 | Z3: Q4 2025 | AA3: Q1 2026 | AB3: Q2 2026 | AC3: Q3 2026 | AD3: Q4 2026 | AM3: 2020 | AN3: =AM3+1 -> 2021 | AO3: =AN3+1 -> 2022 | AP3: =AO3+1 -> 2023 | AQ3: =AP3+1 -> 2024 | AR3: =AQ3+1 -> 2025 | AS3: =AR3+1 -> 2026 | AT3: =AS3+1 -> 2027 | AU3: =AT3+1 -> 2028 | ... CY3: =CX3+1 -> 2084
B4: PMO Products | C4: 100.448 | D4: 111.34 | E4: 121.429 | F4: =455.865-SUM(C4:E4) -> 122.648 | G4: 124.926 | H4: 141.839 | I4: 166.911 | J4: =612.401-SUM(G4:I4) -> 178.725 | K4: 188.825 | L4: 211.237 | M4: 207.774 | N4: =843.769-SUM(K4:M4) -> 235.933 | O4: 231.495 | P4: 238.988 | Q4: 240.21 | R4: =944.52-SUM(O4:Q4) -> 233.827 | S4: 225.548 | T4: 238.827 | U4: 248.788 | V4: =967.169-SUM(S4:U4) -> 254.006 | W4: 236.538 | X4: 231.272 | Y4: 238.545 | Z4: =V4*(1+Z14) -> 266.7063 | AA4: =W4*(1+AA14) -> 275.09369 | AB4: =X4*(1+AB14) -> 280.07039 | AC4: =Y4*(1+AC14) -> 218.50722 | AD4: =Z4*(1+AD14) -> 283.5088 | AM4: =SUM(C4:F4) -> 455.865 | AN4: =SUM(G4:J4) -> 612.401 | AO4: =SUM(K4:N4) -> 843.769 | AP4: =SUM(O4:R4) -> 944.52 | AQ4: =SUM(S4:V4) -> 967.169 | AR4: =AQ4*(1+AR14) -> 1010.6916 | AS4: =AR4*(1+AS14) -> 1041.0124 | AT4: =AS4*(1+AT14) -> 1061.8326 | AU4: =AT4*(1+AU14) -> 1008.741 | AV4: =AU4*(1+AV14) -> 933.0854 | AW4: =AV4*(1+AW14) -> 839.77686 | AX4: =AW4*(1+AX14) -> 671.82149 | AY4: =AX4*(1+AY14) -> 537.45719 | ... BA4: =AZ4*(1+BA14) -> 343.9726
B5: ELEVIDYS | C5: 0 | D5: 0 | E5: 0 | F5: 0 | G5: 0 | H5: 0 | I5: 0 | J5: 0 | K5: 0 | L5: 0 | M5: 0 | N5: 0 | O5: 0 | P5: 0 | Q5: 69.108 | R5: =200.356-SUM(O5:Q5) -> 131.248 | S5: 133.936 | T5: 121.72 | U5: 180.983 | V5: =820.791-SUM(S5:U5) -> 384.152 | W5: 374.895 | X5: 281.851 | Y5: 131.49 | Z5: =V5*(1+Z15) -> 111.40408 | AA5: =W5*(1+AA15) -> 104.9706 | AB5: =X5*(1+AB15) -> 98.64785 | AC5: =Y5*(1+AC15) -> 89.4132 | AD5: =Z5*(1+AD15) -> 77.982856 | AM5: =SUM(C5:F5) -> 0 | AN5: =SUM(G5:J5) -> 0 | AO5: =SUM(K5:N5) -> 0 | AP5: =SUM(O5:R5) -> 200.356 | AQ5: =SUM(S5:V5) -> 820.791 | AR5: =AQ5*(1+AR15) -> 906.97406 | AS5: =AR5*(1+AS15) -> 634.88184 | AT5: =AS5*(1+AT15) -> 571.39365 | AU5: =AT5*(1+AU15) -> 514.25429 | AV5: =AU5*(1+AV15) -> 462.82886 | AW5: =AV5*(1+AW15) -> 416.54597 | AX5: =AW5*(1+AX15) -> 374.89138 | AY5: =AX5*(1+AY15) -> 356.14681 | ... BA5: =AZ5*(1+BA15) -> 321.42249
B6: Product Revenues | C6: =SUM(C4:C5) -> 100.448 | D6: =SUM(D4:D5) -> 111.34 | E6: =SUM(E4:E5) -> 121.429 | F6: =SUM(F4:F5) -> 122.648 | G6: =SUM(G4:G5) -> 124.926 | H6: =SUM(H4:H5) -> 141.839 | I6: =SUM(I4:I5) -> 166.911 | J6: =SUM(J4:J5) -> 178.725 | ... AD6: =SUM(AD4:AD5) -> 361.49165 | AM6: =SUM(C6:F6) -> 455.865 | AN6: =SUM(G6:J6) -> 612.401 | AO6: =SUM(K6:N6) -> 843.769 | AP6: =SUM(O6:R6) -> 1144.876 | AQ6: =SUM(S6:V6) -> 1787.96 | AR6: =SUM(AR4:AR5) -> 1917.6657 | AS6: =SUM(AS4:AS5) -> 1675.8942 | AT6: =SUM(AT4:AT5) -> 1633.2263 | AU6: =SUM(AU4:AU5) -> 1522.9953 | AV6: =SUM(AV4:AV5) -> 1395.9143 | AW6: =SUM(AW4:AW5) -> 1256.3228 | AX6: =SUM(AX4:AX5) -> 1046.7129 | AY6: =SUM(AY4:AY5) -> 893.604 | ... BA6: =SUM(BA4:BA5) -> 665.3951
B7: Collaboration Revenues | C7: 0 | D7: 0 | E7: 0 | F7: 0 | G7: 0 | H7: 0 | I7: 0 | J7: 0 | K7: 0 | L7: 0 | M7: 0 | N7: 0 | O7: 0 | P7: 0 | Q7: 0 | R7: 0 | S7: 48 | T7: 0 | U7: 0 | V7: =48-SUM(S7:U7) -> 0 | W7: 112 | X7: 63.5 | Y7: 0 | AM7: =SUM(C7:F7) -> 0 | AN7: =SUM(G7:J7) -> 0 | AO7: =SUM(K7:N7) -> 0 | AP7: =SUM(O7:R7) -> 0 | AQ7: =SUM(S7:V7) -> 48
B8: Contract Manufacturing | C8: 0 | D8: 0 | E8: 0 | F8: 0 | G8: 0 | H8: 0 | I8: 0 | J8: 0 | K8: 0 | L8: 0 | M8: 0 | N8: 0 | O8: 0 | P8: 0 | Q8: 0 | R8: =9.216-SUM(O8:Q8) -> 9.216 | S8: 5.8 | T8: 2.38 | U8: 27.89 | V8: =49.038-SUM(S8:U8) -> 12.968 | W8: 17.379 | X8: 27.02 | Y8: 18.7 | AM8: =SUM(C8:F8) -> 0 | AN8: =SUM(G8:J8) -> 0 | AO8: =SUM(K8:N8) -> 0 | AP8: =SUM(O8:R8) -> 9.216 | AQ8: =SUM(S8:V8) -> 49.038
B9: Royalty Revenues | C9: 0 | D9: 0 | E9: 0 | F9: 0 | G9: 0 | H9: 0 | I9: 0 | J9: 0 | K9: 0 | L9: 0 | M9: 0 | N9: 0 | O9: 0 | P9: 0 | Q9: 0 | R9: 0 | S9: 0.173 | T9: 0 | U9: 9.51 | V9: =16.981-SUM(S9:U9) -> 7.298 | W9: 4.05 | X9: 7.445 | Y9: 10.608 | AM9: =SUM(C9:F9) -> 0 | AN9: =SUM(G9:J9) -> 0 | AO9: =SUM(K9:N9) -> 0 | AP9: =SUM(O9:R9) -> 0 | AQ9: =SUM(S9:V9) -> 16.981
B10: Amortization of PO | C10: 13.226 | D10: 26.019 | E10: 22.495 | F10: =84.234-SUM(C10:E10) -> 22.494 | G10: 22.005 | H10: 22.25 | I10: 22.459 | J10: =89.444-SUM(G10:I10) -> 22.73 | K10: 22.005 | L10: 22.3 | M10: 22.5 | N10: =89.244-SUM(K10:M10) -> 22.439 | O10: 22 | P10: 22.25 | Q10: 22.49 | R10: =89.244-SUM(O10:Q10) -> 22.504 | S10: 0 | T10: 0 | U10: 0 | V10: =0-SUM(S10:U10) -> 0 | W10: 0 | X10: 0 | Y10: 0 | AM10: =SUM(C10:F10) -> 84.234 | AN10: =SUM(G10:J10) -> 89.444 | AO10: =SUM(K10:N10) -> 89.244 | AP10: =SUM(O10:R10) -> 89.244 | AQ10: =SUM(S10:V10) -> 0
B11: Collaboration and Other Revenues | C11: =SUM(C7:C10) -> 13.226 | D11: =SUM(D7:D10) -> 26.019 | E11: =SUM(E7:E10) -> 22.495 | F11: =SUM(F7:F10) -> 22.494 | G11: =SUM(G7:G10) -> 22.005 | H11: =SUM(H7:H10) -> 22.25 | I11: =SUM(I7:I10) -> 22.459 | J11: =SUM(J7:J10) -> 22.73 | ... Y11: =SUM(Y7:Y10) -> 29.308 | Z11: =V11*(1+Z16) -> 35.4655 | AA11: =W11*(1+AA16) -> 30.68867 | AB11: =X11*(1+AB16) -> 24.49125 | AC11: =Y11*(1+AC16) -> 8.20624 | AD11: =Z11*(1+AD16) -> 21.2793 | AM11: =AM10 -> 84.234 | AN11: =AN10 -> 89.444 | AO11: =SUM(K11:N11) -> 89.244 | AP11: =SUM(O11:R11) -> 98.46 | AQ11: =SUM(S11:V11) -> 114.019 | AR11: =AQ11*(1+AR16) -> 293.02883 | AS11: =AR11*(1+AS16) -> 84.978361 | AT11: =AS11*(1+AT16) -> 89.227279 | AU11: =AT11*(1+AU16) -> 93.688643 | AV11: =AU11*(1+AV16) -> 97.436188 | AW11: =AV11*(1+AW16) -> 101.33364 | AX11: =AW11*(1+AX16) -> 104.37364 | AY11: =AX11*(1+AY16) -> 107.50485 | ... BA11: =AZ11*(1+BA16) -> 111.84805
B12: Ttl Revenues | C12: =C6+C11 -> 113.674 | D12: =D11+D6 -> 137.359 | E12: =E6+E11 -> 143.924 | F12: =F6+F11 -> 145.142 | G12: =G6+G11 -> 146.931 | H12: =H6+H11 -> 164.089 | I12: =I6+I11 -> 189.37 | J12: =J6+J11 -> 201.455 | K12: =K6+K11 -> 210.83 | L12: =L6+L11 -> 233.537 | ... AD12: =AD6+AD11 -> 382.77095 | AM12: =AM6+AM11 -> 540.099 | AN12: =AN6+AN11 -> 701.845 | AO12: =SUM(K12:N12) -> 933.013 | AP12: =SUM(O12:R12) -> 1243.336 | AQ12: =SUM(S12:V12) -> 1901.979 | AR12: =AR6+AR11 -> 2210.6945 | AS12: =AS6+AS11 -> 1760.8726 | AT12: =AT6+AT11 -> 1722.4535 | AU12: =AU6+AU11 -> 1616.6839 | AV12: =AV6+AV11 -> 1493.3504 | AW12: =AW6+AW11 -> 1357.6565 | AX12: =AX6+AX11 -> 1151.0865 | AY12: =AY6+AY11 -> 1001.1089 | ... BA12: =BA6+BA11 -> 777.24315
B14: PMO Products Growth Y/y | G14: =G4/C4-1 -> 0.24368828 | H14: =H4/D4-1 -> 0.27392671 | I14: =I4/E4-1 -> 0.37455633 | J14: =J4/F4-1 -> 0.45721903 | K14: =K4/G4-1 -> 0.5114948 | L14: =L4/H4-1 -> 0.48927305 | M14: =M4/I4-1 -> 0.2448191 | N14: =N4/J4-1 -> 0.32008952 | ... X14: =X4/T4-1 -> -0.031633777 | Y14: 0.04 | Z14: 0.05 | AA14: 0.163 | AB14: 0.211 | AC14: -0.084 | AD14: 0.063 | AN14: =AN4/AM4-1 -> 0.34338236 | AO14: =AO4/AN4-1 -> 0.37780474 | AP14: =AP4/AO4-1 -> 0.1194059 | AQ14: =AQ4/AP4-1 -> 0.023979376 | AR14: 0.045 | AS14: 0.03 | AT14: 0.02 | AU14: -0.05 | AV14: -0.075 | AW14: -0.1 | AX14: -0.2 | AY14: -0.2 | AZ14: -0.2 | BA14: -0.2
B15: ELEVIDYS Growth Y/y | U15: =U5/Q5-1 -> 1.618843 | V15: =V5/R5-1 -> 1.926917 | W15: =W5/S5-1 -> 1.7990607 | X15: =X5/T5-1 -> 1.3155685 | Y15: 0.48 | Z15: -0.71 | AA15: -0.72 | AB15: -0.65 | AC15: -0.32 | AD15: -0.3 | AQ15: =AQ5/AP5-1 -> 3.0966629 | AR15: 0.105 | AS15: -0.3 | AT15: -0.1 | AU15: -0.1 | AV15: -0.1 | AW15: -0.1 | AX15: -0.1 | AY15: -0.05 | AZ15: -0.05 | BA15: -0.05
B16: Other Growth Y/y | G16: =G11/C11-1 -> 0.66376834 | H16: =H11/D11-1 -> -0.14485568 | I16: =I11/E11-1 -> -0.0016003556 | J16: =J11/F11-1 -> 0.010491687 | K16: =K11/G11-1 -> 0 | L16: =L11/H11-1 -> 0.002247191 | M16: =M11/I11-1 -> 0.0018255488 | N16: =N11/J11-1 -> -0.012802464 | ... X16: =X11/T11-1 -> 40.161765 | Y16: 1.15 | Z16: 0.75 | AA16: -0.77 | AB16: -0.75 | AC16: -0.72 | AD16: -0.4 | AN16: =AN11/AM11-1 -> 0.061851509 | AO16: =AO11/AN11-1 -> -0.002236036 | AP16: =AP11/AO11-1 -> 0.10326745 | AQ16: =AQ11/AP11-1 -> 0.15802356 | AR16: 1.57 | AS16: -0.71 | AT16: 0.05 | AU16: 0.05 | AV16: 0.04 | AW16: 0.04 | AX16: 0.03 | AY16: 0.03 | AZ16: 0.02 | BA16: 0.02
B17: Ttl Revenue Growth Y/y | G17: =G6/C6-1 -> 0.24368828 | H17: =H6/D6-1 -> 0.27392671 | I17: =I6/E6-1 -> 0.37455633 | J17: =J6/F6-1 -> 0.45721903 | K17: =K6/G6-1 -> 0.5114948 | L17: =L6/H6-1 -> 0.48927305 | M17: =M6/I6-1 -> 0.2448191 | N17: =N6/J6-1 -> 0.32008952 | ... AD17: =AD6/Z6-1 -> -0.043952052 | AN17: =AN12/AM12-1 -> 0.29947473 | AO17: =AO12/AN12-1 -> 0.32937187 | AP17: =AP12/AO12-1 -> 0.33260308 | AQ17: =AQ12/AP12-1 -> 0.52973854 | AR17: =AR12/AQ12-1 -> 0.16231278 | AS17: =AS12/AR12-1 -> -0.2034754 | AT17: =AT12/AS12-1 -> -0.021818171 | AU17: =AU12/AT12-1 -> -0.061406377 | ... BA17: =BA12/AZ12-1 -> -0.11471708
B19: PMO % of Ttl Revenues | C19: =C4/C12 -> 0.88364974 | D19: =D4/D12 -> 0.81057666 | E19: =E4/E12 -> 0.84370223 | F19: =F4/F12 -> 0.84502074 | G19: =G4/G12 -> 0.85023582 | H19: =H4/H12 -> 0.86440285 | I19: =I4/I12 -> 0.88140149 | J19: =J4/J12 -> 0.88717083 | ... AD19: =AD4/AD12 -> 0.74067479 | AM19: =AM4/AM6 -> 1 | AN19: =AN4/AN6 -> 1 | AO19: =AO4/AO6 -> 1 | AP19: =AP4/AP6 -> 0.82499764 | AQ19: =AQ4/AQ6 -> 0.54093436 | AR19: =AR4/AR6 -> 0.52704266 | AS19: =AS4/AS6 -> 0.6211683 | AT19: =AT4/AT6 -> 0.65014421 | ... BA19: =BA4/BA6 -> 0.5169449
B20: ELEVIDYS % of Ttl Revenues | Q20: =Q5/Q12 -> 0.20827708 | R20: =R5/R12 -> 0.3307703 | S20: =S5/S12 -> 0.32394179 | T20: =T5/T12 -> 0.33538425 | U20: =U5/U12 -> 0.38740204 | V20: =V5/V12 -> 0.58344167 | W20: =W5/W12 -> 0.503308 | X20: =X5/X12 -> 0.46122817 | ... AD20: =AD5/AD12 -> 0.20373243 | AM20: =AM5/AM6 -> 0 | AN20: =AN5/AN6 -> 0 | AO20: =AO5/AO6 -> 0 | AP20: =AP5/AP6 -> 0.17500236 | AQ20: =AQ5/AQ6 -> 0.45906564 | AR20: =AR5/AR6 -> 0.47295734 | AS20: =AS5/AS6 -> 0.3788317 | AT20: =AT5/AT6 -> 0.34985579 | ... BA20: =BA5/BA6 -> 0.4830551
B21: Other % of Ttl Revenues | C21: =C11/C12 -> 0.11635026 | D21: =D11/D12 -> 0.18942334 | E21: =E11/E12 -> 0.15629777 | F21: =F11/F12 -> 0.15497926 | G21: =G11/G12 -> 0.14976418 | H21: =H11/H12 -> 0.13559715 | I21: =I11/I12 -> 0.11859851 | J21: =J11/J12 -> 0.11282917 | ... AD21: =AD11/AD12 -> 0.055592776
B23: Revenues | C23: =C12 -> 113.674 | D23: =D12 -> 137.359 | E23: =E12 -> 143.924 | F23: =F12 -> 145.142 | G23: =G12 -> 146.931 | H23: =H12 -> 164.089 | I23: =I12 -> 189.37 | J23: =J12 -> 201.455 | ... AD23: =AD12 -> 382.77095 | AM23: =SUM(C23:F23) -> 540.099 | AN23: =SUM(G23:J23) -> 701.845 | AO23: =SUM(K23:N23) -> 933.013 | AP23: =SUM(O23:R23) -> 1243.336 | AQ23: =SUM(S23:V23) -> 1901.979 | AR23: =AR12 -> 2210.6945 | AS23: =AS12 -> 1760.8726 | AT23: =AT12 -> 1722.4535 | AU23: =AU12 -> 1616.6839 | AV23: =AV12 -> 1493.3504 | AW23: =AW12 -> 1357.6565 | AX23: =AX12 -> 1151.0865 | AY23: =AY12 -> 1001.1089 | ... BA23: =BA12 -> 777.24315
B24: COGS | C24: 12.622 | D24: 13.341 | E24: 15.015 | F24: =63.382-SUM(C24:E24) -> 22.404 | G24: 22.346 | H24: 19.515 | I24: 23.44 | J24: =97.049-SUM(G24:I24) -> 31.748 | K24: 31.443 | L24: 37.795 | M24: 39.952 | N24: =139.989-SUM(K24:M24) -> 30.799 | O24: 35.017 | P24: 34.124 | Q24: 37.026 | R24: =150.343-SUM(O24:Q24) -> 44.176 | S24: 50.559 | T24: 44.54 | U24: 91.691 | V24: =319.099-SUM(S24:U24) -> 132.309 | W24: 137.56 | X24: 152.558 | Y24: 150.775 | Z24: =Z23*(1-Z39) -> 82.715176 | AA24: =AA23*(1-AA39) -> 78.043063 | AB24: =AB23*(1-AB39) -> 72.577709 | AC24: =AC23*(1-AC39) -> 53.741532 | AD24: =AD23*(1-AD39) -> 65.071062 | AM24: =SUM(C24:F24) -> 63.382 | AN24: =SUM(G24:J24) -> 97.049 | AO24: =SUM(K24:N24) -> 139.989 | AP24: =SUM(O24:R24) -> 150.343 | AQ24: =SUM(S24:V24) -> 319.099 | AR24: =AR23*(1-AR39) -> 530.56668 | AS24: =AS23*(1-AS39) -> 334.56578 | AT24: =AT23*(1-AT39) -> 249.75576 | AU24: =AU23*(1-AU39) -> 226.33575 | AV24: =AV23*(1-AV39) -> 209.06906 | AW24: =AW23*(1-AW39) -> 190.07191 | AX24: =AX23*(1-AX39) -> 161.15211 | AY24: =AY23*(1-AY39) -> 140.15524 | ... BA24: =BA23*(1-BA39) -> 108.81404
B25: GP | C25: =C23-C24 -> 101.052 | D25: =D23-D24 -> 124.018 | E25: =E23-E24 -> 128.909 | F25: =F23-F24 -> 122.738 | G25: =G23-G24 -> 124.585 | H25: =H23-H24 -> 144.574 | I25: =I23-I24 -> 165.93 | J25: =J23-J24 -> 169.707 | ... Y25: =Y23-Y24 -> 248.568 | Z25: =Z23*Z39 -> 330.8607 | AA25: =AA23*AA39 -> 332.7099 | AB25: =AB23*AB39 -> 330.63178 | AC25: =AC23*AC39 -> 262.38513 | AD25: =AD23*AD39 -> 317.69989 | AM25: =SUM(C25:F25) -> 476.717 | AN25: =SUM(G25:J25) -> 604.796 | AO25: =SUM(K25:N25) -> 793.024 | AP25: =SUM(O25:R25) -> 1092.993 | AQ25: =SUM(S25:V25) -> 1582.88 | AR25: =AR23-AR24 -> 1680.1278 | AS25: =AS23-AS24 -> 1426.3068 | AT25: =AT23-AT24 -> 1472.6978 | AU25: =AU23-AU24 -> 1390.3482 | AV25: =AV23-AV24 -> 1284.2814 | AW25: =AW23-AW24 -> 1167.5846 | AX25: =AX23-AX24 -> 989.9344 | AY25: =AY23-AY24 -> 860.95361 | ... BA25: =BA23-BA24 -> 668.42911
B26: R&D | C26: 136.144 | D26: 188.522 | E26: 190.438 | F26: =722.343-SUM(C26:E26) -> 207.239 | G26: 195.149 | H26: 239.622 | I26: 139.115 | J26: =771.182-SUM(G26:I26) -> 197.296 | K26: 194.25 | L26: 252.329 | M26: 216.7 | N26: =877.09-SUM(K26:M26) -> 213.811 | O26: 245.679 | P26: 241.89 | Q26: 194.301 | R26: =877.387-SUM(O26:Q26) -> 195.517 | S26: 200.396 | T26: 179.69 | U26: 224.483 | V26: =804.522-SUM(S26:U26) -> 199.953 | W26: 773.448 | X26: 204.392 | Y26: 218.89 | Z26: =Z23*Z40 -> 138.32967 | AA26: =AA23*AA40 -> 137.38548 | AB26: =AB23*AB40 -> 134.8624 | AC26: =AC23*AC40 -> 105.73561 | AD26: =AD23*AD40 -> 128.02628 | AM26: =SUM(C26:F26) -> 722.343 | AN26: =SUM(G26:J26) -> 771.182 | AO26: =SUM(K26:N26) -> 877.09 | AP26: =SUM(O26:R26) -> 877.387 | AQ26: =SUM(S26:V26) -> 804.522 | AR26: =AR23*AR40 -> 1348.5236 | AS26: =AS23*AS40 -> 968.4799 | AT26: =AT23*AT40 -> 723.43048 | AU26: =AU23*AU40 -> 517.33885 | AV26: =AV23*AV40 -> 418.13812 | AW26: =AW23*AW40 -> 339.41412 | AX26: =AX23*AX40 -> 276.26076 | AY26: =AY23*AY40 -> 240.26612 | ... BA26: =BA23*BA40 -> 186.53835
B27: SG&A | C27: 82.768 | D27: 73.688 | E27: 75.373 | F27: =317.875-SUM(C27:E27) -> 86.046 | G27: 71.131 | H27: 72.347 | I27: 61.127 | J27: =282.66-SUM(G27:I27) -> 78.055 | K27: 71.84 | L27: 154.316 | M27: 104.787 | N27: =451.421-SUM(K27:M27) -> 120.478 | O27: 110.714 | P27: 118.56 | Q27: 120.893 | R27: =481.871-SUM(O27:Q27) -> 131.704 | S27: 127.003 | T27: 138.796 | U27: 128.2 | V27: =557.87-SUM(S27:U27) -> 163.871 | W27: 133.629 | X27: 137.897 | Y27: 91.89 | Z27: =Z23*Z41 -> 93.326776 | AA27: =AA23*AA41 -> 92.689762 | AB27: =AB23*AB41 -> 90.987516 | AC27: =AC23*AC41 -> 71.336564 | AD27: =AD23*AD41 -> 86.375393 | AM27: =SUM(C27:F27) -> 317.875 | AN27: =SUM(G27:J27) -> 282.66 | AO27: =SUM(K27:N27) -> 451.421 | AP27: =SUM(O27:R27) -> 481.871 | AQ27: =SUM(S27:V27) -> 557.87 | AR27: =AR23*AR41 -> 541.62015 | AS27: =AS23*AS41 -> 343.37015 | AT27: =AT23*AT41 -> 331.57231 | AU27: =AU23*AU41 -> 307.16994 | AV27: =AV23*AV41 -> 276.26983 | AW27: =AW23*AW41 -> 247.77231 | AX27: =AX23*AX41 -> 207.19557 | AY27: =AY23*AY41 -> 180.19959 | ... BA27: =BA23*BA41 -> 139.90377
B28: Settlement and Liscence | C28: 0 | D28: 0 | E28: 0 | F28: =0-SUM(C28:E28) -> 0 | G28: 10 | H28: 0 | I28: 0 | J28: =10-SUM(G28:I28) -> 0 | K28: 0 | L28: 0 | M28: 0 | N28: =0-SUM(K28:M28) -> 0 | O28: 0 | P28: 0 | Q28: =0-SUM(N28:P28) -> 0 | R28: =0-SUM(O28:Q28) -> 0 | S28: =0-SUM(P28:R28) -> 0 | T28: =0-SUM(Q28:S28) -> 0 | U28: 0 | V28: 0 | W28: 0 | X28: 0 | Y28: 40.51 | Z28: 0 | AA28: 0 | AB28: 0 | AC28: 0 | AD28: 0 | AM28: =SUM(C28:F28) -> 0 | AN28: =SUM(G28:J28) -> 10 | AO28: =SUM(K28:N28) -> 0 | AP28: =SUM(O28:R28) -> 0 | AQ28: =SUM(S28:V28) -> 0 | AR28: 0 | AS28: 0 | AT28: 0 | AU28: 0 | AV28: 0 | AW28: 0 | AX28: 0 | AY28: 0 | AZ28: 0 | BA28: 0
B29: Amortization of In-Liscensed Rights | C29: 0.166 | D29: 0.165 | E29: 0.166 | F29: =0.662-SUM(C29:E29) -> 0.165 | G29: 0.17 | H29: 0.179 | I29: 0.178 | J29: =0.706-SUM(G29:I29) -> 0.179 | K29: 0.178 | L29: 0.179 | M29: 0.178 | N29: =0.71-SUM(K29:M29) -> 0.175 | O29: 0.178 | P29: 0.179 | Q29: 0.439 | R29: =1.559-SUM(O29:Q29) -> 0.763 | S29: 0.601 | T29: 0.601 | U29: 0.6 | V29: =2.405-SUM(S29:U29) -> 0.603 | W29: 0.6 | X29: 0.667 | Y29: 0.677 | Z29: 0 | AA29: 0 | AB29: 0 | AC29: 0 | AD29: 0 | AM29: =SUM(C29:F29) -> 0.662 | AN29: =SUM(G29:J29) -> 0.706 | AO29: =SUM(K29:N29) -> 0.71 | AP29: =SUM(O29:R29) -> 1.559 | AQ29: =SUM(S29:V29) -> 2.405 | AR29: =AQ29*1 -> 2.405 | AS29: =AR29*1.05 -> 2.52525 | AT29: =AS29*1.05 -> 2.6515125 | AU29: =AT29*1.05 -> 2.7840881 | AV29: =AU29*1.05 -> 2.9232925 | AW29: =AV29*1.05 -> 3.0694572 | AX29: =AW29*1.05 -> 3.22293 | AY29: =AX29*1.05 -> 3.3840765 | AZ29: =AY29*1.05 -> 3.5532803 | BA29: =AZ29*1.05 -> 3.7309444
B30: Operating Income | C30: =C25-SUM(C26:C29) -> -118.026 | D30: =D25-SUM(D26:D29) -> -138.357 | E30: =E25-SUM(E26:E29) -> -137.068 | F30: =F25-SUM(F26:F29) -> -170.712 | G30: =G25-SUM(G26:G29) -> -151.865 | H30: =H25-SUM(H26:H29) -> -167.574 | I30: =I25-SUM(I26:I29) -> -34.49 | J30: =J25-SUM(J26:J29) -> -105.823 | ... AD30: =AD25-SUM(AD26:AD29) -> 103.29822 | AM30: =SUM(C30:F30) -> -564.163 | AN30: =SUM(G30:J30) -> -459.752 | AO30: =SUM(K30:N30) -> -536.197 | AP30: =SUM(O30:R30) -> -267.824 | AQ30: =SUM(S30:V30) -> 218.083 | AR30: =AR25-SUM(AR26:AR29) -> -212.42098 | AS30: =AS25-SUM(AS26:AS29) -> 111.93147 | AT30: =AT25-SUM(AT26:AT29) -> 415.04347 | AU30: =AU25-SUM(AU26:AU29) -> 563.05528 | AV30: =AV25-SUM(AV26:AV29) -> 586.95013 | AW30: =AW25-SUM(AW26:AW29) -> 577.32868 | AX30: =AX25-SUM(AX26:AX29) -> 503.25513 | AY30: =AY25-SUM(AY26:AY29) -> 437.10382 | ... BA30: =BA25-SUM(BA26:BA29) -> 338.25604
B31: Other Income (Expenses) | C31: -7.42 | D31: 0 | E31: -45 | F31: =-51.971-SUM(C31:E31) -> 0.449 | G31: -15.528 | H31: 102 | I31: -20.649 | J31: =-68.43-SUM(G31:I31) -> -134.253 | K31: -17.26 | L31: 0 | M31: =6.7-125.44 -> -118.74 | N31: =-125.441+6.7-SUM(K31:M31) -> 17.259 | O31: 12.7 | P31: 16.934 | Q31: -12.33 | R31: =33.055-SUM(O31:Q31) -> 15.751 | S31: 6.54 | T31: 14.278 | U31: 11.81 | V31: =42.693-SUM(S31:U31) -> 10.065 | W31: -83.132 | X31: 38.06 | Y31: -138.61 | Z31: =Y46*(0.06) -> 36.7842 | AA31: =Z46*(0.06) -> 43.474832 | AB31: =AA46*(0.06) -> 50.663419 | AC31: =AB46*(0.06) -> 58.311327 | AD31: =AC46*(0.06) -> 65.377642 | AM31: =SUM(C31:F31) -> -51.971 | AN31: =SUM(G31:J31) -> -68.43 | AO31: =SUM(K31:N31) -> -118.741 | AP31: =SUM(O31:R31) -> 33.055 | AQ31: =SUM(S31:V31) -> 42.693 | AR31: -35 | AS31: =AR46*($BA$48) -> 87.986157 | AT31: =AS46*($BA$48) -> 106.89836 | AU31: =AT46*($BA$48) -> 155.15189 | AV31: =AU46*($BA$48) -> 220.77807 | AW31: =AV46*($BA$48) -> 294.58423 | AX31: =AW46*($BA$48) -> 374.25527 | AY31: =AX46*($BA$48) -> 454.43779 | AZ31: =AY46*($BA$48) -> 535.9024 | BA31: =AZ46*($BA$48) -> 619.84419
B32: Gain on, Income | C32: 108.069 | D32: -12.447 | E32: -14.335 | F32: =108.1-45-SUM(C32:E32) -> -18.187 | G32: 0 | H32: -16.185 | I32: 7.2 | J32: =102+7.2-SUM(G32:I32) -> 118.185 | K32: 0 | L32: -16.961 | M32: -6.33 | N32: =-35.021-SUM(K32:M32) -> -11.73 | O32: -387.32 | P32: 102 | Q32: 0 | R32: =-387.329+102-SUM(O32:Q32) -> -0.009 | S32: 0 | T32: 0 | U32: 0 | V32: =0-SUM(S32:U32) -> 0 | W32: 0 | X32: 0 | Y32: 47.95 | Z32: 0 | AA32: 0 | AB32: 0 | AC32: 0 | AD32: 0 | AM32: =SUM(C32:F32) -> 63.1 | AN32: =SUM(G32:J32) -> 109.2 | AO32: =SUM(K32:N32) -> -35.021 | AP32: =SUM(O32:R32) -> -285.329 | AQ32: =SUM(S32:V32) -> 0 | AR32: 0 | AS32: 0 | AT32: 0 | AU32: 0 | AV32: 0 | AW32: 0 | AX32: 0 | AY32: 0 | AZ32: 0 | BA32: 0
B33: Pretax Income | C33: =C30+SUM(C31:C32) -> -17.377 | D33: =D30+SUM(D31:D32) -> -150.804 | E33: =E30+SUM(E31:E32) -> -196.403 | F33: =F30+SUM(F31:F32) -> -188.45 | G33: =G30+SUM(G31:G32) -> -167.393 | H33: =H30+SUM(H31:H32) -> -81.759 | I33: =I30+SUM(I31:I32) -> -47.939 | J33: =J30+SUM(J31:J32) -> -121.891 | ... AD33: =AD30+SUM(AD31:AD32) -> 168.67586 | AM33: =SUM(C33:F33) -> -553.034 | AN33: =SUM(G33:J33) -> -418.982 | AO33: =SUM(K33:N33) -> -689.959 | AP33: =SUM(O33:R33) -> -520.098 | AQ33: =SUM(S33:V33) -> 260.776 | AR33: =AR30+SUM(AR31:AR32) -> -247.42098 | AS33: =AS30+SUM(AS31:AS32) -> 199.91762 | AT33: =AT30+SUM(AT31:AT32) -> 521.94183 | AU33: =AU30+SUM(AU31:AU32) -> 718.20716 | AV33: =AV30+SUM(AV31:AV32) -> 807.7282 | AW33: =AW30+SUM(AW31:AW32) -> 871.91291 | AX33: =AX30+SUM(AX31:AX32) -> 877.51041 | AY33: =AY30+SUM(AY31:AY32) -> 891.5416 | ... BA33: =BA30+SUM(BA31:BA32) -> 958.10023
B34: Taxes | C34: 0.115 | D34: 0.2 | E34: 0.096 | F34: =1.063-SUM(C34:E34) -> 0.652 | G34: -0.143 | H34: -0.35 | I34: 0.237 | J34: =-0.168-SUM(G34:I34) -> 0.088 | K34: 0.879 | L34: 3.388 | M34: 1.32 | N34: =13.525-SUM(K34:M34) -> 7.938 | O34: 4.045 | P34: 9.355 | Q34: 7.763 | R34: =15.879-SUM(O34:Q34) -> -5.284 | S34: 5.329 | T34: 7.117 | U34: 0.395 | V34: =25.535-SUM(S34:U34) -> 12.694 | W34: 63.99 | X34: -43.25 | Y34: -14.1 | Z34: =Z33*Z43 -> 24.477922 | AA34: =AA33*AA43 -> 26.299708 | AB34: =AB33*AB43 -> 27.980151 | AC34: =AC33*AC43 -> 25.852371 | AD34: =AD33*AD43 -> 30.361656 | AM34: =SUM(C34:F34) -> 1.063 | AN34: =SUM(G34:J34) -> -0.168 | AO34: =SUM(K34:N34) -> 13.525 | AP34: =SUM(O34:R34) -> 15.879 | AQ34: =SUM(S34:V34) -> 25.535 | AR34: =AR33*AR43 -> 37.113146 | AS34: =AS33*AS43 -> 23.990115 | AT34: =AT33*AT43 -> 73.071857 | AU34: =AU33*AU43 -> 107.73107 | AV34: =AV33*AV43 -> 121.15923 | AW34: =AW33*AW43 -> 130.78694 | AX34: =AX33*AX43 -> 131.62656 | AY34: =AY33*AY43 -> 133.73124 | ... BA34: =BA33*BA43 -> 143.71503
B35: Net Income | C35: =C33-C34 -> -17.492 | D35: =D33-D34 -> -151.004 | E35: =E33-E34 -> -196.499 | F35: =F33-F34 -> -189.102 | G35: =G33-G34 -> -167.25 | H35: =H33-H34 -> -81.409 | I35: =I33-I34 -> -48.176 | J35: =J33-J34 -> -121.979 | K35: =K33-K34 -> -105.02 | L35: =L33-L34+-2.2 -> -233.631 | M35: =M33-M34-0.72 -> -258.453 | N35: =N33-N34 -> -109.3 | O35: =O33-O34 -> -516.758 | P35: =P33-P34 -> -23.936 | Q35: =Q33-Q34 -> -40.944 | R35: =R33-R34 -> 45.661 | S35: =S33-S34-1.6 -> 34.509 | T35: =T33-T34 -> 6.461 | U35: =U33-U34 -> 33.612 | V35: =V33-V34 -> 159.059 | W35: =W33-W34 -> -447.497 | X35: =X33-X34 -> 196.884 | Y35: =Y33-Y34 -> -179.959 | Z35: =Z33-Z34 -> 111.51054 | AA35: =AA33-AA34 -> 119.80978 | ... AD35: =AD33-AD34 -> 138.31421 | AM35: =SUM(C35:F35) -> -554.097 | AN35: =SUM(G35:J35) -> -418.814 | AO35: =SUM(K35:N35) -> -706.404 | AP35: =SUM(O35:R35) -> -535.977 | AQ35: =SUM(S35:V35) -> 233.641 | AR35: =AR33-AR34 -> -284.53412 | AS35: =AS33-AS34 -> 175.92751 | AT35: =AT33-AT34 -> 448.86998 | AU35: =AU33-AU34 -> 610.47609 | AV35: =AV33-AV34 -> 686.56897 | AW35: =AW33-AW34 -> 741.12598 | AX35: =AX33-AX34 -> 745.88385 | AY35: =AY33-AY34 -> 757.81036 | ... BA35: =BA33-BA34 -> 814.38519 | BB35: =BA35*(1+$BA$49) -> 749.23438 | BC35: =BB35*(1+$BA$49) -> 689.29563 | BD35: =BC35*(1+$BA$49) -> 634.15198 | BE35: =BD35*(1+$BA$49) -> 583.41982 | BF35: =BE35*(1+$BA$49) -> 536.74623 | BG35: =BF35*(1+$BA$49) -> 493.80654 | BH35: =BG35*(1+$BA$49) -> 454.30201 | BI35: =BH35*(1+$BA$49) -> 417.95785 | ... BK35: =BJ35*(1+$BA$49) -> 353.75953
B36: SC | C36: 76.432 | D36: 77.968 | E36: 78.501 | F36: 77.77 | G36: 79.454 | H36: 79.746 | I36: 79.88 | J36: 87.12 | K36: 87.253 | L36: 87.511 | M36: 87.62 | N36: 87.981 | O36: 88.186 | P36: 88.743 | Q36: 88.889 | R36: 92.398 | S36: 93.99 | T36: 94.618 | U36: 95.39 | V36: 97.032 | W36: 97.362 | X36: 98.005 | Y36: 100.23 | AM36: =AVERAGE(C36:F36) -> 77.66775 | AN36: =AVERAGE(G36:J36) -> 81.55 | AO36: =AVERAGE(K36:N36) -> 87.59125 | AP36: =AVERAGE(O36:R36) -> 89.554 | AQ36: =AVERAGE(S36:V36) -> 95.2575
B37: EPS | C37: =C35/C36 -> -0.22885702 | D37: =D35/D36 -> -1.9367433 | E37: =E35/E36 -> -2.5031401 | F37: =F35/F36 -> -2.4315546 | G37: =G35/G36 -> -2.1049916 | H37: =H35/H36 -> -1.0208537 | I37: =I35/I36 -> -0.60310466 | J37: =(J35/J36) -> -1.4001263 | K37: =K35/K36 -> -1.2036262 | L37: =L35/L36 -> -2.6697329 | M37: =M35/M36 -> -2.9497033 | N37: =N35/N36 -> -1.2423137 | O37: =O35/O36 -> -5.8598644 | P37: =P35/P36 -> -0.26972268 | Q37: =Q35/Q36 -> -0.46061942 | R37: =R35/R36 -> 0.49417736 | ... Y37: =Y35/Y36 -> -1.7954604 | AM37: =SUM(C37:F37) -> -7.100295 | AN37: =SUM(G37:J37) -> -5.1290762 | AO37: =SUM(K37:N37) -> -8.0653761 | AP37: =SUM(O37:R37) -> -6.0960291 | AQ37: =SUM(S37:V37) -> 2.4270479
B39: Gross Profit Margin | C39: =C25/C23 -> 0.88896318 | D39: =D25/D23 -> 0.90287495 | E39: =E25/E23 -> 0.89567411 | F39: =F25/F23 -> 0.84564082 | G39: =G25/G23 -> 0.84791501 | H39: =H25/H23 -> 0.88107064 | I39: =I25/I23 -> 0.87622115 | J39: =J25/J23 -> 0.84240649 | ... Y39: =Y25/Y23 -> 0.62244236 | Z39: 0.8 | AA39: 0.81 | AB39: 0.82 | AC39: 0.83 | AD39: 0.83 | AM39: =AM25/AM23 -> 0.88264744 | AN39: =AN25/AN23 -> 0.86172303 | AO39: =AO25/AO23 -> 0.84996029 | AP39: =AP25/AP23 -> 0.87908096 | AQ39: =AQ25/AQ23 -> 0.83222791 | AR39: 0.76 | AS39: 0.81 | AT39: 0.855 | AU39: 0.86 | AV39: 0.86 | AW39: 0.86 | AX39: 0.86 | AY39: 0.86 | AZ39: 0.86 | BA39: 0.86
B40: R&D as % of Revenue | C40: =C26/C23 -> 1.1976705 | D40: =D26/D23 -> 1.3724765 | E40: =E26/E23 -> 1.3231845 | F40: =F26/F23 -> 1.4278362 | G40: =G26/G23 -> 1.3281676 | H40: =H26/H23 -> 1.4603173 | I40: =I26/I23 -> 0.73462006 | J40: =J26/J23 -> 0.97935519 | ... Y40: =Y26/Y23 -> 0.5481253 | Z40: 0.33447229 | AA40: 0.33447229 | AB40: 0.33447229 | AC40: 0.33447229 | AD40: 0.33447229 | AM40: =AM26/AM23 -> 1.337427 | AN40: =AN26/AN23 -> 1.0987925 | AO40: =AO26/AO23 -> 0.94006193 | AP40: =AP26/AP23 -> 0.70567168 | AQ40: =AQ26/AQ23 -> 0.42299205 | AR40: 0.61 | AS40: 0.55 | AT40: 0.42 | AU40: 0.32 | AV40: 0.28 | AW40: 0.25 | AX40: 0.24 | AY40: 0.24 | AZ40: 0.24 | BA40: 0.24
B41: SG&A as % of Revenue | C41: =C27/C23 -> 0.72811725 | D41: =D27/D23 -> 0.53646285 | E41: =E27/E23 -> 0.52370001 | F41: =F27/F23 -> 0.59284012 | G41: =G27/G23 -> 0.48411159 | H41: =H27/H23 -> 0.44090097 | I41: =I27/I23 -> 0.32279136 | J41: =J27/J23 -> 0.38745626 | ... Y41: =Y27/Y23 -> 0.23010294 | Z41: 0.22565817 | AA41: 0.22565817 | AB41: 0.22565817 | AC41: 0.22565817 | AD41: 0.22565817 | AM41: =AM27/AM23 -> 0.58854951 | AN41: =AN27/AN23 -> 0.4027385 | AO41: =AO27/AO23 -> 0.48383141 | AP41: =AP27/AP23 -> 0.38756298 | AQ41: =AQ27/AQ23 -> 0.29331028 | AR41: 0.245 | AS41: 0.195 | AT41: 0.1925 | AU41: 0.19 | AV41: 0.185 | AW41: 0.1825 | AX41: 0.18 | AY41: 0.18 | AZ41: 0.18 | BA41: 0.18
B42: Operating Profit Margin | C42: =C30/C23 -> -1.0382849 | D42: =D30/D23 -> -1.0072656 | E42: =E30/E23 -> -0.95236375 | F42: =F30/F23 -> -1.1761723 | G42: =G30/G23 -> -1.0335804 | H42: =H30/H23 -> -1.0212385 | I42: =I30/I23 -> -0.18213022 | J42: =J30/J23 -> -0.52529349 | ... AD42: =AD30/AD23 -> 0.26986954 | AM42: =AM30/AM23 -> -1.0445548 | AN42: =AN30/AN23 -> -0.65506202 | AO42: =AO30/AO23 -> -0.57469403 | AP42: =AP30/AP23 -> -0.21540758 | AQ42: =AQ30/AQ23 -> 0.1146611 | AR42: =AR30/AR23 -> -0.096087893 | AS42: =AS30/AS23 -> 0.06356591 | AT42: =AT30/AT23 -> 0.24096062 | ... BA42: =BA30/BA23 -> 0.43519977
B43: Effective Tax Rate | C43: =-C34/C33 -> 0.0066179433 | D43: =-D34/D33 -> 0.0013262248 | E43: =-E34/E33 -> 0.0004887909 | F43: =-F34/F33 -> 0.0034598037 | G43: =-G34/G33 -> -0.00085427706 | H43: =-H34/H33 -> -0.0042808743 | I43: =-I34/I33 -> 0.0049437827 | J43: =-J34/J33 -> 0.0007219565 | ... Q43: =-Q34/Q33 -> 0.23395919 | R43: =R34/R33 -> -0.13086658 | S43: =S34/S33 -> 0.12860177 | T43: =T34/T33 -> 0.52415672 | U43: =U34/U33 -> 0.011615256 | V43: =V34/V33 -> 0.073908462 | W43: =-W34/W33 -> 0.16685484 | X43: =X34/X33 -> -0.28151321 | Y43: =Y34/Y33 -> 0.072658315 | Z43: 0.18 | AA43: 0.18 | AB43: 0.18 | AC43: 0.18 | AD43: 0.18 | AM43: =-AM34/AM33 -> 0.0019221241 | AN43: =-AN34/AN33 -> -0.00040097188 | AO43: =-AO34/AO33 -> 0.019602614 | AP43: =-AP34/AP33 -> 0.030530785 | AQ43: =-AQ34/AQ33 -> -0.097919287 | AR43: -0.15 | AS43: 0.12 | AT43: 0.14 | AU43: 0.15 | AV43: 0.15 | AW43: 0.15 | AX43: 0.15 | AY43: 0.15 | AZ43: 0.15 | BA43: 0.15
B44: Net Profit Margin | C44: =C35/C23 -> -0.15387864 | D44: =D35/D23 -> -1.0993382 | E44: =E35/E23 -> -1.365297 | F44: =F35/F23 -> -1.3028758 | G44: =G35/G23 -> -1.1382894 | H44: =H35/H23 -> -0.4961271 | I44: =I35/I23 -> -0.25440144 | J44: =J35/J23 -> -0.60549006 | ... Y44: =Y35/Y23 -> -0.45063767 | Z44: 0.322186 | AA44: 0.322186 | AB44: 0.322186 | AC44: 0.322186 | AD44: 0.322186 | AM44: =AM35/AM23 -> -1.0259175 | AN44: =AN35/AN23 -> -0.5967329 | AO44: =AO35/AO23 -> -0.75712128 | AP44: =AP35/AP23 -> -0.43107977 | AQ44: =AQ35/AQ23 -> 0.122841 | AR44: =AR35/AR23 -> -0.12870803 | AS44: =AS35/AS23 -> 0.099909279 | AT44: =AT35/AT23 -> 0.26059918 | ... BA44: =BA35/BA23 -> 1.0477869
B46: Cash & CEs | F46: 1502.64 | G46: 1481.83 | H46: 1697.27 | I46: 1599.113 | J46: 2115.869 | K46: 1233.877 | L46: 868.565 | M46: 1038.62 | N46: 966.77 | O46: 871.668 | P46: 851.929 | Q46: 541.932 | R46: 428.43 | S46: 427.29 | T46: 383.622 | U46: 197.855 | V46: 1103.01 | W46: 240.867 | X46: 510.598 | Y46: 613.07 | Z46: =Y46+Z35 -> 724.58054 | AA46: =Z46+AA35 -> 844.39032 | AB46: =AA46+AB35 -> 971.85545 | AC46: =AB46+AC35 -> 1089.6274 | AD46: =AC46+AD35 -> 1227.9416 | AM46: =F46 -> 1502.64 | AN46: =J46 -> 2115.869 | AO46: =N46 -> 966.77 | AP46: =R46 -> 428.43 | AQ46: =V46 -> 1103.01 | AR46: =AQ46+AR35 -> 818.47588 | AS46: =AR46+AS35 -> 994.40338 | AT46: =AS46+AT35 -> 1443.2734 | AU46: =AT46+AU35 -> 2053.7495 | AV46: =AU46+AV35 -> 2740.3184 | AW46: =AV46+AW35 -> 3481.4444 | AX46: =AW46+AX35 -> 4227.3282 | AY46: =AX46+AY35 -> 4985.1386 | ... BA46: =AZ46+BA35 -> 6580.3777
B47: ST Investments | F47: 435.923 | G47: 255.997 | H47: 30 | I47: 0 | J47: 0 | K47: 779.548 | L47: 1059.454 | M47: 1033.86 | N47: 1022.597 | O47: 1010.42 | P47: 1008.786 | Q47: 1191.61 | R47: 1247.82 | S47: 963.453 | T47: 1076.85 | U47: 1000.534 | V47: 251.782 | W47: 281.895 | X47: 289.541 | Y47: 237.916 | AM47: =F47 -> 435.923 | AN47: =J47 -> 0 | AO47: =N47 -> 1022.597 | AP47: =R47 -> 1247.82 | AQ47: =V47 -> 251.782
B48: A/R | F48: 101.34 | G48: 118.203 | H48: 127.52 | I48: 149.787 | J48: 152.99 | K48: 178.194 | L48: 203.854 | M48: 201.509 | N48: 214.628 | O48: 223.836 | P48: 236.808 | Q48: 318.855 | R48: 400.32 | S48: 378.806 | T48: 359.997 | U48: 434.524 | V48: 601.988 | W48: 659.371 | X48: 527.295 | Y48: 395.73 | AM48: =F48 -> 101.34 | AN48: =J48 -> 152.99 | AO48: =N48 -> 214.628 | AP48: =R48 -> 400.32 | AQ48: =V48 -> 601.988 | AS48: Projected ROIC: | AV48: Invested Capital | AX48: AVG Invested Capital | AZ48: ROIC | BA48: 0.1075
B49: Inventories | F49: 231.961 | G49: 240.333 | H49: 268.756 | I49: 288.469 | J49: 186.212 | K49: 198.997 | L49: 208.095 | M49: 221.192 | N49: 203.968 | O49: 202.67 | P49: 226.876 | Q49: 244.011 | R49: 322.85 | S49: 373.53 | T49: 485.795 | U49: 565.924 | V49: 749.96 | W49: 941.432 | X49: 994 | Y49: 1077.16 | AM49: =F49 -> 231.961 | AN49: =J49 -> 186.212 | AO49: =N49 -> 203.968 | AP49: =R49 -> 322.85 | AQ49: =V49 -> 749.96 | AS49: 2026 | AU49: 2023 | AV49: 2024 | AX49: 2023-2024 | AZ49: Terminal | BA49: -0.08
B50: Manufacturing Prepaids | F50: 0 | G50: 0 | H50: 0 | I50: 0 | J50: 0 | K50: 0 | L50: 0 | M50: 0 | N50: 0 | O50: 0 | P50: 0 | Q50: 0 | R50: 0 | S50: 238.821 | T50: 302.627 | U50: 321.055 | V50: 276.62 | W50: 203.49 | X50: 207.92 | Y50: 206.06 | AM50: =F50 -> 0 | AN50: =J50 -> 0 | AO50: =N50 -> 0 | AP50: =R50 -> 0 | AQ50: =V50 -> 276.62 | AS50: =AVERAGE(AS30)*(1-AS43) -> 98.49969 | AU50: =SUM(AP46:AP49)-AP60+AP52 -> 2461.652 | AV50: =SUM(AQ46:AQ49)-AQ60+AQ52 -> 2832.634 | AX50: =AVERAGE(AU50:AV50) -> 2647.143 | AZ50: RFR (10-year yield) | BA50: 0.0416
B51: Other ST Assets | F51: 213.324 | G51: 174.98 | H51: 141.666 | I51: 147.941 | J51: 149.028 | K51: 140.33 | L51: 129.332 | M51: 130.744 | N51: 149.891 | O51: 179.769 | P51: 148.215 | Q51: 154.441 | R51: 179.89 | S51: 82.965 | T51: 74.74 | U51: 165.477 | V51: 90.461 | W51: 105.478 | X51: 127.59 | Y51: 192.34 | AM51: =F51 -> 213.324 | AN51: =J51 -> 149.028 | AO51: =N51 -> 149.891 | AP51: =R51 -> 179.89 | AQ51: =V51 -> 90.461 | AS51: =AS50/AX50 -> 0.037209811 | AZ51: ERP (Avg. market return - (less) RFR) | BA51: =9.5%-BA50 -> 0.0534
B52: PP&E | F52: 190.43 | G52: 203.107 | H52: 203.33 | I52: 199.249 | J52: 191.156 | K52: 187.248 | L52: 183.292 | M52: 181.005 | N52: 180.037 | O52: 182.86 | P52: 188.874 | Q52: 212.367 | R52: 227.15 | S52: 249.302 | T52: 276.2 | U52: 305.788 | V52: 340.336 | W52: 360.587 | X52: 371.857 | Y52: 358.93 | AM52: =F52 -> 190.43 | AN52: =J52 -> 191.156 | AO52: =N52 -> 180.037 | AP52: =R52 -> 227.15 | AQ52: =V52 -> 340.336 | AZ52: Equity β (1-year avg.) | BA52: 0.56
B53: Right-to-use assets | F53: 13.628 | G53: 14.124 | H53: 14.105 | I53: 14.204 | J53: 14.239 | K53: 13.328 | L53: 13.062 | M53: 13.057 | N53: 7.578 | O53: 62.016 | P53: 134.728 | Q53: 133.454 | R53: 129.95 | S53: 126.269 | T53: 124 | U53: 140.898 | V53: 148.31 | W53: 147.063 | X53: 143.041 | Y53: 139.16 | AM53: =F53 -> 13.628 | AN53: =J53 -> 14.239 | AO53: =N53 -> 7.578 | AP53: =R53 -> 129.95 | AQ53: =V53 -> 148.31 | AZ53: Discount (Cost of Equity) | BA53: =+BA50+(BA51*BA52) -> 0.071504
B54: Non-current Inventories | F54: 91.761 | G54: 65.068 | H54: 72.868 | I54: 72.663 | J54: 45.531 | K54: 45.982 | L54: 46.999 | M54: 43.034 | N54: 64.954 | O54: 164.144 | P54: 166.635 | Q54: 176.112 | R54: 191.36 | S54: 207.542 | T54: 204.69 | U54: 202.55 | V54: 187.986 | W54: 181.158 | X54: 194.668 | Y54: 198.6 | AM54: =F54 -> 91.761 | AN54: =J54 -> 45.531 | AO54: =N54 -> 64.954 | AP54: =R54 -> 191.36 | AQ54: =V54 -> 187.986
B55: Strategic Investments | F55: 0 | G55: 0 | H55: 0 | I55: 0 | J55: 0 | K55: 0 | L55: 0 | M55: 0 | N55: 0 | O55: 0 | P55: 0 | Q55: 0 | R55: 0 | S55: 0 | T55: 0 | U55: 0 | V55: 0 | W55: 154.37 | X55: 195.522 | Y55: 0 | AM55: =F55 -> 0 | AN55: =J55 -> 0 | AO55: =N55 -> 0 | AP55: =R55 -> 0 | AQ55: =V55 -> 0 | AZ55: NPV | BA55: =NPV(BA53,AR35:CO35) -> 5354.2826
B56: LT Investments | F56: 0 | G56: 0 | H56: 0 | I56: 0 | J56: 0 | K56: 0 | L56: 0 | M56: 0 | N56: 0 | O56: 0 | P56: 0 | Q56: 0 | R56: 0 | S56: 0 | T56: 0 | U56: 181.77 | V56: 133.163 | W56: 109.125 | X56: 34.604 | Y56: 1.04 | AM56: =F56 -> 0 | AN56: =J56 -> 0 | AO56: =N56 -> 0 | AP56: =R56 -> 0 | AQ56: =V56 -> 133.163 | AZ56: SC | BA56: =Main!C6 -> 104.787
B57: Other LT Assets | F57: 203.703 | G57: 211.584 | H57: 203.553 | I57: 190.792 | J57: 292.949 | K57: 278.649 | L57: 284.2 | M57: 293.124 | N57: 317.936 | O57: 162.387 | P57: 163.039 | Q57: 136.925 | R57: 136.87 | S57: 176.407 | T57: 135.72 | U57: 83.559 | V57: 79.915 | W57: 80.551 | X57: 83.137 | Y57: 73.38 | AM57: =F57 -> 203.703 | AN57: =J57 -> 292.949 | AO57: =N57 -> 317.936 | AP57: =R57 -> 136.87 | AQ57: =V57 -> 79.915 | AZ57: FV | BA57: =BA55/BA56 -> 51.096821
B58: Ttl Assets | F58: =SUM(F46:F57) -> 2984.71 | G58: =SUM(G46:G57) -> 2765.226 | H58: =SUM(H46:H57) -> 2759.068 | I58: =SUM(I46:I57) -> 2662.218 | J58: =SUM(J46:J57) -> 3147.974 | K58: =SUM(K46:K57) -> 3056.153 | L58: =SUM(L46:L57) -> 2996.853 | M58: =SUM(M46:M57) -> 3156.145 | ... Y58: =SUM(Y46:Y57) -> 3493.386 | AM58: =F58 -> 2984.71 | AN58: =J58 -> 3147.974 | AO58: =N58 -> 3128.359 | AP58: =R58 -> 3264.64 | AQ58: =V58 -> 3963.531 | AZ58: CP | BA58: =Main!C5 -> 23.73
AZ59: Change Δ | BA59: =BA57/BA58-1 -> 1.1532584 | BB59: =IF(BA59>0,"Upside","Downside") -> Upside
B60: A/P | F60: 111.09 | G60: 76.651 | H60: 76.68 | I60: 44.163 | J60: 76.741 | K60: 54.007 | L60: 56.207 | M60: 118.461 | N60: 95.875 | O60: 106.71 | P60: 109.796 | Q60: 87.948 | R60: 164.918 | S60: 91.536 | T60: 107.417 | U60: 118.774 | V60: 214.442 | W60: 156.105 | X60: 136.702 | Y60: 94.015 | AM60: =F60 -> 111.09 | AN60: =J60 -> 76.741 | AO60: =N60 -> 95.875 | AP60: =R60 -> 164.918 | AQ60: =V60 -> 214.442 | AZ60: {=_xlfn.IFS(BA59>=25%,"Strong Buy",BA59>=10.00001%,"Buy",AND(BA59<=10%,BA59>=-4.9999%),"Hold",AND(BA59<=-5%,BA59>=-14.999999%),"Sell",BA59<=-15%,"Strong Sell")} -> Strong Buy
B61: Accrued Expenses, current | F61: 193.55 | G61: 180.636 | H61: 240.141 | I61: 221.009 | J61: 271.697 | K61: 293.908 | L61: 383.699 | M61: 368.998 | N61: 418.99 | O61: 345.55 | P61: 326.877 | Q61: 322.35 | R61: 314.997 | S61: 283.317 | T61: 350.404 | U61: 344.83 | V61: 373.5 | W61: 391.65 | X61: 377.399 | Y61: 295.79 | AM61: =F61 -> 193.55 | AN61: =J61 -> 271.697 | AO61: =N61 -> 418.99 | AP61: =R61 -> 314.997 | AQ61: =V61 -> 373.5
B62: Deffered Revenues, current | F62: 89.244 | G62: 89.244 | H62: 89.244 | I62: 89.244 | J62: 89.244 | K62: 89.244 | L62: 89.244 | M62: 89.244 | N62: 89.244 | O62: 67.239 | P62: 44.989 | Q62: 22.494 | R62: 50.416 | S62: 112 | T62: 122.036 | U62: 127 | V62: 130.256 | W62: 44.859 | X62: 395.431 | Y62: 485.449 | AM62: =F62 -> 89.244 | AN62: =J62 -> 89.244 | AO62: =N62 -> 89.244 | AP62: =R62 -> 50.416 | AQ62: =V62 -> 130.256
B63: Other ST Liabilities | F63: 22.139 | G63: 18.205 | H63: 18.956 | I63: 19.02 | J63: 15.051 | K63: 17.803 | L63: 16.416 | M63: 26.213 | N63: 15.489 | O63: 17.381 | P63: 16.992 | Q63: 17.951 | R63: 17.845 | S63: 16.27 | T63: 17.12 | U63: 17.289 | V63: 13.473 | W63: 12.974 | X63: 10.416 | Y63: =36+10.16 -> 46.16 | AM63: =F63 -> 22.139 | AN63: =J63 -> 15.051 | AO63: =N63 -> 15.489 | AP63: =R63 -> 17.845 | AQ63: =V63 -> 13.473
B64: Current Portion of Debt | F64: 0 | G64: 0 | H64: 0 | I64: 0 | J64: 0 | K64: 0 | L64: 0 | M64: 0 | N64: 0 | O64: 0 | P64: 0 | Q64: 0 | R64: 105.483 | S64: 105.586 | T64: 91.505 | U64: 91.595 | V64: 0 | W64: 0 | X64: 0 | Y64: 0 | AM64: =F64 -> 0 | AN64: =J64 -> 0 | AO64: =N64 -> 0 | AP64: =R64 -> 105.483 | AQ64: =V64 -> 0
B65: LT Debt | F65: 992.493 | G65: 1091.11 | H65: 1092.985 | I65: 1094.912 | J65: 1096.876 | K65: 1098.84 | L65: 1100.873 | M65: 1542.77 | N65: 1544.29 | O65: 1234.284 | P65: 1235.51 | Q65: 1236.755 | R65: 1132.515 | S65: 1133.66 | T65: 1134.81 | U65: 1135.965 | V65: 1137.12 | W65: 1138.28 | X65: 1139.458 | Y65: 1035.146 | AM65: =F65 -> 992.493 | AN65: =J65 -> 1096.876 | AO65: =N65 -> 1544.29 | AP65: =R65 -> 1132.515 | AQ65: =V65 -> 1137.12
B66: LT Lease Liabilities | F66: 80.36 | G66: 60.675 | H66: 65.285 | I66: 63.42 | J66: 41.512 | K66: 38.62 | L66: 39.368 | M66: 35.229 | N66: 57.578 | O66: 53.931 | P66: 129.17 | Q66: 134.752 | R66: 140.96 | S66: 140.1 | T66: 143.601 | U66: 170 | V66: 192.473 | W66: 205.46 | X66: 214.419 | Y66: 215.042 | AM66: =F66 -> 80.36 | AN66: =J66 -> 41.512 | AO66: =N66 -> 57.578 | AP66: =R66 -> 140.96 | AQ66: =V66 -> 192.473
B67: Deffered LT Revenues | F67: 663.488 | G67: 641.483 | H67: 619.233 | I67: 596.73 | J67: 574.244 | K67: 552.239 | L67: 529.989 | M67: 507.494 | N67: 485 | O67: 485 | P67: 485 | Q67: 485 | R67: 437 | S67: 325 | T67: 325 | U67: 325 | V67: 325 | W67: 325 | X67: 0 | Y67: 0 | AM67: =F67 -> 663.488 | AN67: =J67 -> 574.244 | AO67: =N67 -> 485 | AP67: =R67 -> 437 | AQ67: =V67 -> 325
B68: Contingent Consideration | F68: 50.8 | G68: 50.8 | H68: 50.8 | I68: 43.6 | J68: 43.6 | K68: 43.6 | L68: 43.6 | M68: 36.9 | N68: 36.9 | O68: 36.9 | P68: 36.1 | Q68: 38.1 | R68: 38.1 | S68: 48.2 | T68: 48.2 | U68: 47.4 | V68: 47.4 | W68: 47.4 | X68: 47.4 | Y68: 0.3 | AM68: =F68 -> 50.8 | AN68: =J68 -> 43.6 | AO68: =N68 -> 36.9 | AP68: =R68 -> 38.1 | AQ68: =V68 -> 47.4
B69: Other LT Liabilities | F69: 19.785 | G69: 20.984 | H69: 20.64 | I69: 20.569 | J69: 11 | K69: 11 | L69: 11 | M69: 0 | N69: 0.042 | O69: 0.038 | P69: 0.038 | Q69: 0 | R69: 3 | S69: 7.522 | T69: 7.087 | U69: 1 | V69: 1.75 | W69: 0.927 | X69: 1.2 | Y69: 1.404 | AM69: =F69 -> 19.785 | AN69: =J69 -> 11 | AO69: =N69 -> 0.042 | AP69: =R69 -> 3 | AQ69: =V69 -> 1.75
B70: Ttl Liabilities | F70: =SUM(F60:F69) -> 2222.949 | G70: =SUM(G60:G69) -> 2229.788 | H70: =SUM(H60:H69) -> 2273.964 | I70: =SUM(I60:I69) -> 2192.667 | J70: =SUM(J60:J69) -> 2219.965 | K70: =SUM(K60:K69) -> 2199.261 | L70: =SUM(L60:L69) -> 2270.396 | M70: =SUM(M60:M69) -> 2725.309 | ... Y70: =SUM(Y60:Y69) -> 2173.306 | AM70: =F70 -> 2222.949 | AN70: =J70 -> 2219.965 | AO70: =N70 -> 2743.408 | AP70: =R70 -> 2405.234 | AQ70: =V70 -> 2435.414
B71: SE | F71: 761.759 | G71: 535.445 | H71: 485.1 | I71: 469.52 | J71: 928.009 | K71: 856.886 | L71: 726.457 | M71: 430.84 | N71: 384.95 | O71: 712.749 | P71: 741.411 | Q71: 764.357 | R71: 859.337 | S71: 961.192 | T71: 1077.06 | U71: 1221.071 | V71: 1527.742 | W71: 1142.723 | X71: 1357.38 | Y71: 1320.12 | AM71: =F71 -> 761.759 | AN71: =J71 -> 928.009 | AO71: =N71 -> 384.95 | AP71: =R71 -> 859.337 | AQ71: =V71 -> 1527.742
B72: Total L + SE | F72: =F70+F71 -> 2984.708 | G72: =G70+G71 -> 2765.233 | H72: =H70+H71 -> 2759.064 | I72: =I70+I71 -> 2662.187 | J72: =J70+J71 -> 3147.974 | K72: =K70+K71 -> 3056.147 | L72: =L70+L71 -> 2996.853 | M72: =M70+M71 -> 3156.149 | ... Y72: =Y70+Y71 -> 3493.426 | AM72: =F72 -> 2984.708 | AN72: =J72 -> 3147.974 | AO72: =N72 -> 3128.358 | AP72: =R72 -> 3264.571 | AQ72: =V72 -> 3963.156
B74: Current Ratio | F74: =SUM(F46:F51)/SUM(F60:F64) -> 5.9736793 | G74: =SUM(G46:G51)/SUM(G60:G64) -> 6.2273617 | H74: =SUM(H46:H51)/SUM(H60:H64) -> 5.3296472 | I74: =SUM(I46:I51)/SUM(I60:I64) -> 5.8518997 | J74: =SUM(J46:J51)/SUM(J60:J64) -> 5.7519531 | K74: =SUM(K46:K51)/SUM(K60:K64) -> 5.5629833 | L74: =SUM(L46:L51)/SUM(L60:L64) -> 4.5261252 | M74: =SUM(M46:M51)/SUM(M60:M64) -> 4.3553745 | ... Y74: =SUM(Y46:Y51)/SUM(Y60:Y64) -> 2.9544548 | AM74: =SUM(AM46:AM51)/SUM(AM60:AM64) -> 5.9736793 | AN74: =SUM(AN46:AN51)/SUM(AN60:AN64) -> 5.7519531 | AO74: =SUM(AO46:AO51)/SUM(AO60:AO64) -> 4.1282477 | AP74: =SUM(AP46:AP51)/SUM(AP60:AP64) -> 3.9459565 | AQ74: =SUM(AQ46:AQ51)/SUM(AQ60:AQ64) -> 4.2010972
B75: Quick Ratio | F75: =(SUM(F46:F51)-F49)/SUM(F60:F64) -> 5.4161116 | G75: =(SUM(G46:G51)-G49)/SUM(G60:G64) -> 5.5684385 | H75: =(SUM(H46:H51)-H49)/SUM(H60:H64) -> 4.6973114 | I75: =(SUM(I46:I51)-I49)/SUM(I60:I64) -> 5.0794273 | J75: =(SUM(J46:J51)-J49)/SUM(J60:J64) -> 5.3406467 | K75: =(SUM(K46:K51)-K49)/SUM(K60:K64) -> 5.1255907 | L75: =(SUM(L46:L51)-L49)/SUM(L60:L64) -> 4.1446956 | M75: =(SUM(M46:M51)-M49)/SUM(M60:M64) -> 3.9885042 | ... Y75: =(SUM(Y46:Y51)-Y49)/SUM(Y60:Y64) -> 1.7854254 | AM75: =(SUM(AM46:AM51)-AM49)/SUM(AM60:AM64) -> 5.4161116 | AN75: =(SUM(AN46:AN51)-AN49)/SUM(AN60:AN64) -> 5.3406467 | AO75: =(SUM(AO46:AO51)-AO49)/SUM(AO60:AO64) -> 3.7990536 | AP75: =(SUM(AP46:AP51)-AP49)/SUM(AP60:AP64) -> 3.4520446 | AQ75: =(SUM(AQ46:AQ51)-AQ49)/SUM(AQ60:AQ64) -> 3.176101
B76: Cash Ratio | F76: =F46/SUM(F60:F64) -> 3.6119157 | G76: =G46/SUM(G60:G64) -> 4.0627468 | H76: =H46/SUM(H60:H64) -> 3.9933792 | I76: =I46/SUM(I60:I64) -> 4.2821608 | J76: =J46/SUM(J60:J64) -> 4.6735471 | K76: =K46/SUM(K60:K64) -> 2.7120441 | L76: =L46/SUM(L60:L64) -> 1.5920439 | M76: =M46/SUM(M60:M64) -> 1.7226612 | ... Y76: =Y46/SUM(Y60:Y64) -> 0.66535781 | AM76: =AM46/SUM(AM60:AM64) -> 3.6119157 | AN76: =AN46/SUM(AN60:AN64) -> 4.6735471 | AO76: =AO46/SUM(AO60:AO64) -> 1.5603181 | AP76: =AP46/SUM(AP60:AP64) -> 0.65543349 | AQ76: =AQ46/SUM(AQ60:AQ64) -> 1.5075218
B77: Ttl Asset Turnover | F77: =F23/F72 -> 0.048628543 | G77: =G23/G72 -> 0.053135125 | H77: =H23/H72 -> 0.059472705 | I77: =I23/I72 -> 0.071133245 | J77: =J23/J72 -> 0.063995128 | K77: =K23/K72 -> 0.068985556 | L77: =L23/L72 -> 0.077927413 | M77: =M23/M72 -> 0.072960434 | ... Y77: =Y23/Y72 -> 0.11431271 | AM77: =AM23/AM72 -> 0.18095539 | AN77: =AN23/AN72 -> 0.22295133 | AO77: =AO23/AO72 -> 0.29824368 | AP77: =AP23/AP72 -> 0.38085739 | AQ77: =AQ23/AQ72 -> 0.47991525
B78: Inventory Turnover Ratio | F78: =F24/AVERAGE(C49:F49) -> 0.096585202 | G78: =G24/AVERAGE(D49:G49) -> 0.094627499 | H78: =H24/AVERAGE(E49:H49) -> 0.079002766 | I78: =I24/AVERAGE(F49:I49) -> 0.091071656 | J78: =J24/AVERAGE(G49:J49) -> 0.12908708 | K78: =K24/AVERAGE(H49:K49) -> 0.13345444 | L78: =L24/AVERAGE(I49:L49) -> 0.17145002 | M78: =M24/AVERAGE(J49:M49) -> 0.19620477 | ... Y78: =Y24/AVERAGE(V49:Y49) -> 0.16029014 | AM78: =AM24/AVERAGE(AJ49:AM49) -> 0.27324421 | AN78: =AN24/AVERAGE(AK49:AN49) -> 0.46415718 | AO78: =AO24/AVERAGE(AL49:AO49) -> 0.67503508 | AP78: =AP24/AVERAGE(AM49:AP49) -> 0.63637855 | AQ78: =AQ24/AVERAGE(AN49:AQ49) -> 0.87245709
B79: Return on Assets | F79: =F35/F72 -> -0.063356952 | G79: =G35/G72 -> -0.060483149 | H79: =H35/H72 -> -0.029506021 | I79: =I35/I72 -> -0.0180964 | J79: =J35/J72 -> -0.038748414 | K79: =K35/K72 -> -0.03436353 | L79: =L35/L72 -> -0.077958779 | M79: =M35/M72 -> -0.081888719 | ... Y79: =Y35/Y72 -> -0.051513614 | AM79: =AM35/AM72 -> -0.1856453 | AN79: =AN35/AN72 -> -0.13304239 | AO79: =AO35/AO72 -> -0.22580664 | AP79: =AP35/AP72 -> -0.16417992 | AQ79: =AQ35/AQ72 -> 0.058953269
B80: Return on Equity | F80: =F35/F71 -> -0.24824387 | G80: =G35/G71 -> -0.31235701 | H80: =H35/H71 -> -0.16781901 | I80: =I35/I71 -> -0.10260692 | J80: =J35/J71 -> -0.13144161 | K80: =K35/K71 -> -0.12256006 | L80: =L35/L71 -> -0.32160334 | M80: =M35/M71 -> -0.59988163 | ... Y80: =Y35/Y71 -> -0.13632018 | AM80: =AM35/AM71 -> -0.72739147 | AN80: =AN35/AN71 -> -0.45130381 | AO80: =AO35/AO71 -> -1.8350539 | AP80: =AP35/AP71 -> -0.62370991 | AQ80: =AQ35/AQ71 -> 0.15293224
B82: Net Income | C82: =C35 -> -17.492 | D82: =D35 -> -151.004 | E82: =E35 -> -196.499 | F82: =F35 -> -189.102 | G82: =G35 -> -167.25 | H82: =H35 -> -81.409 | I82: =I35 -> -48.176 | J82: =J35 -> -121.979 | ... Y82: =Y35 -> -179.959 | AM82: =SUM(C82:F82) -> -554.097 | AN82: =SUM(G82:J82) -> -418.814 | AO82: =SUM(K82:N82) -> -706.404 | AP82: =SUM(O82:R82) -> -535.977 | AQ82: =SUM(S82:V82) -> 233.641 | AR82: =AR35 -> -284.53412 | AS82: =AS35 -> 175.92751 | AT82: =AT35 -> 448.86998 | AU82: =AU35 -> 610.47609 | AV82: =AV35 -> 686.56897 | AW82: =AW35 -> 741.12598 | AX82: =AX35 -> 745.88385 | AY82: =AY35 -> 757.81036 | ... BA82: =BA35 -> 814.38519
B83: CFFO | C83: 627.8 | D83: -107.6 | E83: -283.2 | F83: -129.5 | G83: -180.4 | H83: -109.5 | I83: -124 | J83: -29.3 | K83: -101.2 | L83: -66.8 | M83: -65 | N83: -92.4 | O83: -209.4 | P83: -122.2 | Q83: -115.9 | R83: -53.5 | S83: -241.1 | T83: 14.9 | U83: -70.7 | V83: 92 | W83: -583.4 | X83: =-322.1-W83 -> 261.3 | Y83: -14.6 | AM83: =SUM(C83:F83) -> 107.5 | AN83: =SUM(G83:J83) -> -443.2 | AO83: =SUM(K83:N83) -> -325.4 | AP83: =SUM(O83:R83) -> -501 | AQ83: =SUM(S83:V83) -> -204.9
B84: CapEx, net | C84: -9.1 | D84: -19.2 | E84: -25.3 | F84: -28.6 | G84: -21.1 | H84: -5.9 | I84: -9.2 | J84: -2.2 | K84: -5.6 | L84: -9.1 | M84: -8.2 | N84: -8 | O84: -9.5 | P84: -17.9 | Q84: -29.7 | R84: -19 | S84: -32.4 | T84: -29.2 | U84: -37.3 | V84: -38.1 | W84: -43.7 | X84: =-75.44-W84 -> -31.74 | Y84: -22.9 | AM84: =SUM(C84:F84) -> -82.2 | AN84: =SUM(G84:J84) -> -38.4 | AO84: =SUM(K84:N84) -> -30.9 | AP84: =SUM(O84:R84) -> -76.1 | AQ84: =SUM(S84:V84) -> -137
B85: FCF | C85: =C83+C84 -> 618.7 | D85: =D83+D84 -> -126.8 | E85: =E83+E84 -> -308.5 | F85: =F83+F84 -> -158.1 | G85: =G83+G84 -> -201.5 | H85: =H83+H84 -> -115.4 | I85: =I83+I84 -> -133.2 | J85: =J83+J84 -> -31.5 | ... Y85: =Y83+Y84 -> -37.5 | AM85: =SUM(C85:F85) -> 25.3 | AN85: =SUM(G85:J85) -> -481.6 | AO85: =SUM(K85:N85) -> -356.3 | AP85: =SUM(O85:R85) -> -577.1 | AQ85: =SUM(S85:V85) -> -341.9
B86: SC | C86: =C36 -> 76.432 | D86: =D36 -> 77.968 | E86: =E36 -> 78.501 | F86: =F36 -> 77.77 | G86: =G36 -> 79.454 | H86: =H36 -> 79.746 | I86: =I36 -> 79.88 | J86: =J36 -> 87.12 | ... Y86: =Y36 -> 100.23 | AM86: =AM36 -> 77.66775 | AN86: =AN36 -> 81.55 | AO86: =AO36 -> 87.59125 | AP86: =AP36 -> 89.554 | AQ86: =AQ36 -> 95.2575
B87: FCF per Share | C87: =C85/C86 -> 8.0947771 | D87: =D85/D86 -> -1.6263082 | E87: =E85/E86 -> -3.9298862 | F87: =F85/F86 -> -2.0329176 | G87: =G85/G86 -> -2.5360586 | H87: =H85/H86 -> -1.4470945 | I87: =I85/I86 -> -1.6675013 | J87: =J85/J86 -> -0.36157025 | ... Y87: =Y85/Y86 -> -0.37413948 | AM87: =SUM(C87:F87) -> 0.50566501 | AN87: =SUM(G87:J87) -> -6.0122246 | AO87: =SUM(K87:N87) -> -4.0679274 | AP87: =SUM(O87:R87) -> -6.4836165 | AQ87: =SUM(S87:V87) -> -3.6377254
B89: FCF/Revenue | C89: =C85/C23 -> 5.4427574 | D89: =D85/D23 -> -0.92312844 | E89: =E85/E23 -> -2.1434924 | F89: =F85/F23 -> -1.0892781 | G89: =G85/G23 -> -1.371392 | H89: =H85/H23 -> -0.70327688 | I89: =I85/I23 -> -0.70338491 | J89: =J85/J23 -> -0.15636246 | ... Y89: =Y85/Y23 -> -0.093904238

Sheet Base Case (50%)
C1: Q1 2020 | G1: Q1 2021 | K1: Q1 2022 | O1: Q1 2023 | S1: Q1 2024 | W1: Q1 2025
B2: Quarterly
B3: Revenues | C3: Q1 2020 | D3: Q2 2020 | E3: Q3 2020 | F3: Q4 2020 | G3: Q1 2021 | H3: Q2 2021 | I3: Q3 2021 | J3: Q4 2021 | K3: Q1 2022 | L3: Q2 2022 | M3: Q3 2022 | N3: Q4 2022 | O3: Q1 2023 | P3: Q2 2023 | Q3: Q3 2023 | R3: Q4 2023 | S3: Q1 2024 | T3: Q2 2024 | U3: Q3 2024 | V3: Q4 2024 | W3: Q1 2025 | X3: Q2 2025 | Y3: Q3 2025 | Z3: Q4 2025 | AA3: Q1 2026 | AB3: Q2 2026 | AC3: Q3 2026 | AD3: Q4 2026 | AM3: 2020 | AN3: =AM3+1 -> 2021 | AO3: =AN3+1 -> 2022 | AP3: =AO3+1 -> 2023 | AQ3: =AP3+1 -> 2024 | AR3: =AQ3+1 -> 2025 | AS3: =AR3+1 -> 2026 | AT3: =AS3+1 -> 2027 | AU3: =AT3+1 -> 2028 | ... CY3: =CX3+1 -> 2084
B4: PMO Products | C4: 100.448 | D4: 111.34 | E4: 121.429 | F4: =455.865-SUM(C4:E4) -> 122.648 | G4: 124.926 | H4: 141.839 | I4: 166.911 | J4: =612.401-SUM(G4:I4) -> 178.725 | K4: 188.825 | L4: 211.237 | M4: 207.774 | N4: =843.769-SUM(K4:M4) -> 235.933 | O4: 231.495 | P4: 238.988 | Q4: 240.21 | R4: =944.52-SUM(O4:Q4) -> 233.827 | S4: 225.548 | T4: 238.827 | U4: 248.788 | V4: =967.169-SUM(S4:U4) -> 254.006 | W4: 236.538 | X4: 231.272 | Y4: 238.545 | Z4: 240 | AA4: 255 | AB4: 260 | AC4: 270 | AD4: 275 | AM4: =SUM(C4:F4) -> 455.865 | AN4: =SUM(G4:J4) -> 612.401 | AO4: =SUM(K4:N4) -> 843.769 | AP4: =SUM(O4:R4) -> 944.52 | AQ4: =SUM(S4:V4) -> 967.169 | AR4: =AQ4*(1+AR14) -> 1010.6916 | AS4: =AR4*(1+AS14) -> 909.62244 | AT4: =AS4*(1+AT14) -> 955.10357 | AU4: =AT4*(1+AU14) -> 993.30771 | AV4: =AU4*(1+AV14) -> 1028.0735 | AW4: =AV4*(1+AW14) -> 1058.9157 | AX4: =AW4*(1+AX14) -> 1085.3886 | AY4: =AX4*(1+AY14) -> 1107.0963 | ... BA4: =AZ4*(1+BA14) -> 1134.9398
B5: ELEVIDYS | C5: 0 | D5: 0 | E5: 0 | F5: 0 | G5: 0 | H5: 0 | I5: 0 | J5: 0 | K5: 0 | L5: 0 | M5: 0 | N5: 0 | O5: 0 | P5: 0 | Q5: 69.108 | R5: =200.356-SUM(O5:Q5) -> 131.248 | S5: 133.936 | T5: 121.72 | U5: 180.983 | V5: =820.791-SUM(S5:U5) -> 384.152 | W5: 374.895 | X5: 281.851 | Y5: 131.49 | Z5: 160 | AA5: 175 | AB5: 170 | AC5: 160 | AD5: 150 | AM5: =SUM(C5:F5) -> 0 | AN5: =SUM(G5:J5) -> 0 | AO5: =SUM(K5:N5) -> 0 | AP5: =SUM(O5:R5) -> 200.356 | AQ5: =SUM(S5:V5) -> 820.791 | AR5: =AQ5*(1+AR15) -> 878.24637 | AS5: =AR5*(1+AS15) -> 601.59876 | AT5: =AS5*(1+AT15) -> 421.11913 | AU5: =AT5*(1+AU15) -> 357.95126 | AV5: =AU5*(1+AV15) -> 322.15614 | AW5: =AV5*(1+AW15) -> 289.94052 | AX5: =AW5*(1+AX15) -> 260.94647 | AY5: =AX5*(1+AY15) -> 247.89915 | ... BA5: =AZ5*(1+BA15) -> 223.72898
B6: Product Revenues | C6: =SUM(C4:C5) -> 100.448 | D6: =SUM(D4:D5) -> 111.34 | E6: =SUM(E4:E5) -> 121.429 | F6: =SUM(F4:F5) -> 122.648 | G6: =SUM(G4:G5) -> 124.926 | H6: =SUM(H4:H5) -> 141.839 | I6: =SUM(I4:I5) -> 166.911 | J6: =SUM(J4:J5) -> 178.725 | ... AD6: =SUM(AD4:AD5) -> 425 | AM6: =SUM(C6:F6) -> 455.865 | AN6: =SUM(G6:J6) -> 612.401 | AO6: =SUM(K6:N6) -> 843.769 | AP6: =SUM(O6:R6) -> 1144.876 | AQ6: =SUM(S6:V6) -> 1787.96 | AR6: =SUM(AR4:AR5) -> 1888.938 | AS6: =SUM(AS4:AS5) -> 1511.2212 | AT6: =SUM(AT4:AT5) -> 1376.2227 | AU6: =SUM(AU4:AU5) -> 1351.259 | AV6: =SUM(AV4:AV5) -> 1350.2296 | AW6: =SUM(AW4:AW5) -> 1348.8562 | AX6: =SUM(AX4:AX5) -> 1346.335 | AY6: =SUM(AY4:AY5) -> 1354.9955 | ... BA6: =SUM(BA4:BA5) -> 1358.6688
B7: Collaboration Revenues | C7: 0 | D7: 0 | E7: 0 | F7: 0 | G7: 0 | H7: 0 | I7: 0 | J7: 0 | K7: 0 | L7: 0 | M7: 0 | N7: 0 | O7: 0 | P7: 0 | Q7: 0 | R7: 0 | S7: 48 | T7: 0 | U7: 0 | V7: =48-SUM(S7:U7) -> 0 | W7: 112 | X7: 63.5 | Y7: 0 | AM7: =SUM(C7:F7) -> 0 | AN7: =SUM(G7:J7) -> 0 | AO7: =SUM(K7:N7) -> 0 | AP7: =SUM(O7:R7) -> 0 | AQ7: =SUM(S7:V7) -> 48
B8: Contract Manufacturing | C8: 0 | D8: 0 | E8: 0 | F8: 0 | G8: 0 | H8: 0 | I8: 0 | J8: 0 | K8: 0 | L8: 0 | M8: 0 | N8: 0 | O8: 0 | P8: 0 | Q8: 0 | R8: =9.216-SUM(O8:Q8) -> 9.216 | S8: 5.8 | T8: 2.38 | U8: 27.89 | V8: =49.038-SUM(S8:U8) -> 12.968 | W8: 17.379 | X8: 27.02 | Y8: 18.7 | AM8: =SUM(C8:F8) -> 0 | AN8: =SUM(G8:J8) -> 0 | AO8: =SUM(K8:N8) -> 0 | AP8: =SUM(O8:R8) -> 9.216 | AQ8: =SUM(S8:V8) -> 49.038
B9: Royalty Revenues | C9: 0 | D9: 0 | E9: 0 | F9: 0 | G9: 0 | H9: 0 | I9: 0 | J9: 0 | K9: 0 | L9: 0 | M9: 0 | N9: 0 | O9: 0 | P9: 0 | Q9: 0 | R9: 0 | S9: 0.173 | T9: 0 | U9: 9.51 | V9: =16.981-SUM(S9:U9) -> 7.298 | W9: 4.05 | X9: 7.445 | Y9: 10.608 | AM9: =SUM(C9:F9) -> 0 | AN9: =SUM(G9:J9) -> 0 | AO9: =SUM(K9:N9) -> 0 | AP9: =SUM(O9:R9) -> 0 | AQ9: =SUM(S9:V9) -> 16.981
B10: Amortization of PO | C10: 13.226 | D10: 26.019 | E10: 22.495 | F10: =84.234-SUM(C10:E10) -> 22.494 | G10: 22.005 | H10: 22.25 | I10: 22.459 | J10: =89.444-SUM(G10:I10) -> 22.73 | K10: 22.005 | L10: 22.3 | M10: 22.5 | N10: =89.244-SUM(K10:M10) -> 22.439 | O10: 22 | P10: 22.25 | Q10: 22.49 | R10: =89.244-SUM(O10:Q10) -> 22.504 | S10: 0 | T10: 0 | U10: 0 | V10: =0-SUM(S10:U10) -> 0 | W10: 0 | X10: 0 | Y10: 0 | AM10: =SUM(C10:F10) -> 84.234 | AN10: =SUM(G10:J10) -> 89.444 | AO10: =SUM(K10:N10) -> 89.244 | AP10: =SUM(O10:R10) -> 89.244 | AQ10: =SUM(S10:V10) -> 0
B11: Collaboration and Other Revenues | C11: =SUM(C7:C10) -> 13.226 | D11: =SUM(D7:D10) -> 26.019 | E11: =SUM(E7:E10) -> 22.495 | F11: =SUM(F7:F10) -> 22.494 | G11: =SUM(G7:G10) -> 22.005 | H11: =SUM(H7:H10) -> 22.25 | I11: =SUM(I7:I10) -> 22.459 | J11: =SUM(J7:J10) -> 22.73 | ... Y11: =SUM(Y7:Y10) -> 29.308 | AM11: =AM10 -> 84.234 | AN11: =AN10 -> 89.444 | AO11: =SUM(K11:N11) -> 89.244 | AP11: =SUM(O11:R11) -> 98.46 | AQ11: =SUM(S11:V11) -> 114.019 | AR11: =AQ11*(1+AR16) -> 285.0475 | AS11: =AR11*(1+AS16) -> 128.27138 | AT11: =AS11*(1+AT16) -> 121.85781 | AU11: =AT11*(1+AU16) -> 125.51354 | AV11: =AU11*(1+AV16) -> 128.96516 | AW11: =AV11*(1+AW16) -> 132.18929 | AX11: =AW11*(1+AX16) -> 135.16355 | AY11: =AX11*(1+AY16) -> 137.191 | ... BA11: =AZ11*(1+BA16) -> 139.25573
B12: Ttl Revenues | C12: =C6+C11 -> 113.674 | D12: =D11+D6 -> 137.359 | E12: =E6+E11 -> 143.924 | F12: =F6+F11 -> 145.142 | G12: =G6+G11 -> 146.931 | H12: =H6+H11 -> 164.089 | I12: =I6+I11 -> 189.37 | J12: =J6+J11 -> 201.455 | K12: =K6+K11 -> 210.83 | L12: =L6+L11 -> 233.537 | ... AD12: =AD6+AD11 -> 425 | AM12: =AM6+AM11 -> 540.099 | AN12: =AN6+AN11 -> 701.845 | AO12: =SUM(K12:N12) -> 933.013 | AP12: =SUM(O12:R12) -> 1243.336 | AQ12: =SUM(S12:V12) -> 1901.979 | AR12: =AR6+AR11 -> 2173.9855 | AS12: =AS6+AS11 -> 1639.4926 | AT12: =AT6+AT11 -> 1498.0805 | AU12: =AU6+AU11 -> 1476.7725 | AV12: =AV6+AV11 -> 1479.1948 | AW12: =AW6+AW11 -> 1481.0455 | AX12: =AX6+AX11 -> 1481.4986 | AY12: =AY6+AY11 -> 1492.1865 | ... BA12: =BA6+BA11 -> 1497.9245
B14: PMO Products Growth Y/y | G14: =G4/C4-1 -> 0.24368828 | H14: =H4/D4-1 -> 0.27392671 | I14: =I4/E4-1 -> 0.37455633 | J14: =J4/F4-1 -> 0.45721903 | K14: =K4/G4-1 -> 0.5114948 | L14: =L4/H4-1 -> 0.48927305 | M14: =M4/I4-1 -> 0.2448191 | N14: =N4/J4-1 -> 0.32008952 | ... X14: =X4/T4-1 -> -0.031633777 | Y14: 0.04 | Z14: =Z4/V4-1 -> -0.05514043 | AA14: =AA4/W4-1 -> 0.078050884 | AB14: =AB4/X4-1 -> 0.12421737 | AC14: =AC4/Y4-1 -> 0.13186191 | AD14: =AD4/Z4-1 -> 0.14583333 | AN14: =AN4/AM4-1 -> 0.34338236 | AO14: =AO4/AN4-1 -> 0.37780474 | AP14: =AP4/AO4-1 -> 0.1194059 | AQ14: =AQ4/AP4-1 -> 0.023979376 | AR14: 0.045 | AS14: -0.1 | AT14: 0.05 | AU14: 0.04 | AV14: 0.035 | AW14: 0.03 | AX14: 0.025 | AY14: 0.02 | AZ14: 0.015 | BA14: 0.01
B15: ELEVIDYS Growth Y/y | U15: =U5/Q5-1 -> 1.618843 | V15: =V5/R5-1 -> 1.926917 | W15: =W5/S5-1 -> 1.7990607 | X15: =X5/T5-1 -> 1.3155685 | Y15: 0.48 | Z15: =Z5/V5-1 -> -0.5834982 | AA15: =AA5/W5-1 -> -0.53320263 | AB15: =AB5/X5-1 -> -0.39684443 | AC15: =AC5/Y5-1 -> 0.21682257 | AD15: =AD5/Z5-1 -> -0.0625 | AQ15: =AQ5/AP5-1 -> 3.0966629 | AR15: 0.07 | AS15: -0.315 | AT15: -0.3 | AU15: -0.15 | AV15: -0.1 | AW15: -0.1 | AX15: -0.1 | AY15: -0.05 | AZ15: -0.05 | BA15: -0.05
B16: Other Growth Y/y | G16: =G11/C11-1 -> 0.66376834 | H16: =H11/D11-1 -> -0.14485568 | I16: =I11/E11-1 -> -0.0016003556 | J16: =J11/F11-1 -> 0.010491687 | K16: =K11/G11-1 -> 0 | L16: =L11/H11-1 -> 0.002247191 | M16: =M11/I11-1 -> 0.0018255488 | N16: =N11/J11-1 -> -0.012802464 | ... X16: =X11/T11-1 -> 40.161765 | Y16: 1.15 | AN16: =AN11/AM11-1 -> 0.061851509 | AO16: =AO11/AN11-1 -> -0.002236036 | AP16: =AP11/AO11-1 -> 0.10326745 | AQ16: =AQ11/AP11-1 -> 0.15802356 | AR16: 1.5 | AS16: -0.55 | AT16: -0.05 | AU16: 0.03 | AV16: 0.0275 | AW16: 0.025 | AX16: 0.0225 | AY16: 0.015 | AZ16: 0.01 | BA16: 0.005
B17: Ttl Revenue Growth Y/y | G17: =G6/C6-1 -> 0.24368828 | H17: =H6/D6-1 -> 0.27392671 | I17: =I6/E6-1 -> 0.37455633 | J17: =J6/F6-1 -> 0.45721903 | K17: =K6/G6-1 -> 0.5114948 | L17: =L6/H6-1 -> 0.48927305 | M17: =M6/I6-1 -> 0.2448191 | N17: =N6/J6-1 -> 0.32008952 | ... Y17: =Y6/U6-1 -> -0.13899495 | Z17: =Z12/V12-1 -> -0.39248873 | AA17: =AA12/W12-1 -> -0.42271186 | AB17: =AB12/X12-1 -> -0.29633703 | AC17: =AC12/Y12-1 -> 0.076768592 | AD17: =AD12/Z12-1 -> 0.0625 | AN17: =AN12/AM12-1 -> 0.29947473 | AO17: =AO12/AN12-1 -> 0.32937187 | AP17: =AP12/AO12-1 -> 0.33260308 | AQ17: =AQ12/AP12-1 -> 0.52973854 | AR17: =AR12/AQ12-1 -> 0.14301234 | AS17: =AS12/AR12-1 -> -0.24585854 | AT17: =AT12/AS12-1 -> -0.086253562 | AU17: =AU12/AT12-1 -> -0.01422353 | ... BA17: =BA12/AZ12-1 -> 0.00010324214
B19: PMO % of Ttl Revenues | C19: =C4/C12 -> 0.88364974 | D19: =D4/D12 -> 0.81057666 | E19: =E4/E12 -> 0.84370223 | F19: =F4/F12 -> 0.84502074 | G19: =G4/G12 -> 0.85023582 | H19: =H4/H12 -> 0.86440285 | I19: =I4/I12 -> 0.88140149 | J19: =J4/J12 -> 0.88717083 | ... Y19: =Y4/Y12 -> 0.59734364 | AM19: =AM4/AM6 -> 1 | AN19: =AN4/AN6 -> 1 | AO19: =AO4/AO6 -> 1 | AP19: =AP4/AP6 -> 0.82499764 | AQ19: =AQ4/AQ6 -> 0.54093436 | AR19: =AR4/AR12 -> 0.46490265 | AS19: =AS4/AS12 -> 0.55481949 | AT19: =AT4/AT12 -> 0.63755156 | AU19: =AU4/AU12 -> 0.67262066 | AV19: =AV4/AV12 -> 0.69502238 | AW19: =AW4/AW12 -> 0.7149785 | AX19: =AX4/AX12 -> 0.73262882 | AY19: =AY4/AY12 -> 0.74192894 | ... BA19: =BA4/BA12 -> 0.7576749
B20: ELEVIDYS % of Ttl Revenues | Q20: =Q5/Q12 -> 0.20827708 | R20: =R5/R12 -> 0.3307703 | S20: =S5/S12 -> 0.32394179 | T20: =T5/T12 -> 0.33538425 | U20: =U5/U12 -> 0.38740204 | V20: =V5/V12 -> 0.58344167 | W20: =W5/W12 -> 0.503308 | X20: =X5/X12 -> 0.46122817 | Y20: =Y5/Y12 -> 0.32926582 | AM20: =AM5/AM6 -> 0 | AN20: =AN5/AN6 -> 0 | AO20: =AO5/AO6 -> 0 | AP20: =AP5/AP6 -> 0.17500236 | AQ20: =AQ5/AQ6 -> 0.45906564 | AR20: =AR5/AR12 -> 0.40397987 | AS20: =AS5/AS12 -> 0.36694205 | AT20: =AT5/AT12 -> 0.28110581 | AU20: =AU5/AU12 -> 0.24238755 | AV20: =AV5/AV12 -> 0.21779156 | AW20: =AW5/AW12 -> 0.19576747 | AX20: =AX5/AX12 -> 0.17613683 | AY20: =AY5/AY12 -> 0.16613148 | ... BA20: =BA5/BA12 -> 0.14935931
B21: Other % of Ttl Revenues | C21: =C11/C12 -> 0.11635026 | D21: =D11/D12 -> 0.18942334 | E21: =E11/E12 -> 0.15629777 | F21: =F11/F12 -> 0.15497926 | G21: =G11/G12 -> 0.14976418 | H21: =H11/H12 -> 0.13559715 | I21: =I11/I12 -> 0.11859851 | J21: =J11/J12 -> 0.11282917 | ... Y21: =Y11/Y12 -> 0.073390544
B23: Revenues | C23: =C12 -> 113.674 | D23: =D12 -> 137.359 | E23: =E12 -> 143.924 | F23: =F12 -> 145.142 | G23: =G12 -> 146.931 | H23: =H12 -> 164.089 | I23: =I12 -> 189.37 | J23: =J12 -> 201.455 | ... Y23: =Y12 -> 399.343 | AM23: =SUM(C23:F23) -> 540.099 | AN23: =SUM(G23:J23) -> 701.845 | AO23: =SUM(K23:N23) -> 933.013 | AP23: =SUM(O23:R23) -> 1243.336 | AQ23: =SUM(S23:V23) -> 1901.979 | AR23: =AR12 -> 2173.9855 | AS23: =AS12 -> 1639.4926 | AT23: =AT12 -> 1498.0805 | AU23: =AU12 -> 1476.7725 | AV23: =AV12 -> 1479.1948 | AW23: =AW12 -> 1481.0455 | AX23: =AX12 -> 1481.4986 | AY23: =AY12 -> 1492.1865 | ... BA23: =BA12 -> 1497.9245
B24: COGS | C24: 12.622 | D24: 13.341 | E24: 15.015 | F24: =63.382-SUM(C24:E24) -> 22.404 | G24: 22.346 | H24: 19.515 | I24: 23.44 | J24: =97.049-SUM(G24:I24) -> 31.748 | K24: 31.443 | L24: 37.795 | M24: 39.952 | N24: =139.989-SUM(K24:M24) -> 30.799 | O24: 35.017 | P24: 34.124 | Q24: 37.026 | R24: =150.343-SUM(O24:Q24) -> 44.176 | S24: 50.559 | T24: 44.54 | U24: 91.691 | V24: =319.099-SUM(S24:U24) -> 132.309 | W24: 137.56 | X24: 152.558 | Y24: 150.775 | AM24: =SUM(C24:F24) -> 63.382 | AN24: =SUM(G24:J24) -> 97.049 | AO24: =SUM(K24:N24) -> 139.989 | AP24: =SUM(O24:R24) -> 150.343 | AQ24: =SUM(S24:V24) -> 319.099 | AR24: =AR23*(1-AR39) -> 521.75651 | AS24: =AS23*(1-AS39) -> 360.68837 | AT24: =AT23*(1-AT39) -> 314.59691 | AU24: =AU23*(1-AU39) -> 302.73837 | AV24: =AV23*(1-AV39) -> 295.83896 | AW24: =AW23*(1-AW39) -> 288.80387 | AX24: =AX23*(1-AX39) -> 281.48473 | AY24: =AY23*(1-AY39) -> 283.51543 | ... BA24: =BA23*(1-BA39) -> 284.60566
B25: GP | C25: =C23-C24 -> 101.052 | D25: =D23-D24 -> 124.018 | E25: =E23-E24 -> 128.909 | F25: =F23-F24 -> 122.738 | G25: =G23-G24 -> 124.585 | H25: =H23-H24 -> 144.574 | I25: =I23-I24 -> 165.93 | J25: =J23-J24 -> 169.707 | ... Y25: =Y23-Y24 -> 248.568 | AM25: =SUM(C25:F25) -> 476.717 | AN25: =SUM(G25:J25) -> 604.796 | AO25: =SUM(K25:N25) -> 793.024 | AP25: =SUM(O25:R25) -> 1092.993 | AQ25: =SUM(S25:V25) -> 1582.88 | AR25: =AR23-AR24 -> 1652.229 | AS25: =AS23-AS24 -> 1278.8042 | AT25: =AT23-AT24 -> 1183.4836 | AU25: =AU23-AU24 -> 1174.0341 | AV25: =AV23-AV24 -> 1183.3558 | AW25: =AW23-AW24 -> 1192.2416 | AX25: =AX23-AX24 -> 1200.0139 | AY25: =AY23-AY24 -> 1208.6711 | ... BA25: =BA23-BA24 -> 1213.3189
B26: R&D | C26: 136.144 | D26: 188.522 | E26: 190.438 | F26: =722.343-SUM(C26:E26) -> 207.239 | G26: 195.149 | H26: 239.622 | I26: 139.115 | J26: =771.182-SUM(G26:I26) -> 197.296 | K26: 194.25 | L26: 252.329 | M26: 216.7 | N26: =877.09-SUM(K26:M26) -> 213.811 | O26: 245.679 | P26: 241.89 | Q26: 194.301 | R26: =877.387-SUM(O26:Q26) -> 195.517 | S26: 200.396 | T26: 179.69 | U26: 224.483 | V26: =804.522-SUM(S26:U26) -> 199.953 | W26: 773.448 | X26: 204.392 | Y26: 218.89 | AM26: =SUM(C26:F26) -> 722.343 | AN26: =SUM(G26:J26) -> 771.182 | AO26: =SUM(K26:N26) -> 877.09 | AP26: =SUM(O26:R26) -> 877.387 | AQ26: =SUM(S26:V26) -> 804.522 | AR26: =AR23*AR40 -> 1391.3507 | AS26: =AS23*AS40 -> 901.72092 | AT26: =AT23*AT40 -> 479.38576 | AU26: =AU23*AU40 -> 443.03175 | AV26: =AV23*AV40 -> 414.17454 | AW26: =AW23*AW40 -> 399.88228 | AX26: =AX23*AX40 -> 385.18964 | AY26: =AY23*AY40 -> 373.04662 | ... BA26: =BA23*BA40 -> 359.50189
B27: SG&A | C27: 82.768 | D27: 73.688 | E27: 75.373 | F27: =317.875-SUM(C27:E27) -> 86.046 | G27: 71.131 | H27: 72.347 | I27: 61.127 | J27: =282.66-SUM(G27:I27) -> 78.055 | K27: 71.84 | L27: 154.316 | M27: 104.787 | N27: =451.421-SUM(K27:M27) -> 120.478 | O27: 110.714 | P27: 118.56 | Q27: 120.893 | R27: =481.871-SUM(O27:Q27) -> 131.704 | S27: 127.003 | T27: 138.796 | U27: 128.2 | V27: =557.87-SUM(S27:U27) -> 163.871 | W27: 133.629 | X27: 137.897 | Y27: 91.89 | AM27: =SUM(C27:F27) -> 317.875 | AN27: =SUM(G27:J27) -> 282.66 | AO27: =SUM(K27:N27) -> 451.421 | AP27: =SUM(O27:R27) -> 481.871 | AQ27: =SUM(S27:V27) -> 557.87 | AR27: =AR23*AR41 -> 500.01666 | AS27: =AS23*AS41 -> 327.89852 | AT27: =AT23*AT41 -> 292.1257 | AU27: =AU23*AU41 -> 280.58678 | AV27: =AV23*AV41 -> 273.65103 | AW27: =AW23*AW41 -> 266.58819 | AX27: =AX23*AX41 -> 266.66975 | AY27: =AY23*AY41 -> 268.59357 | ... BA27: =BA23*BA41 -> 269.62642
B28: Settlement and Liscence | C28: 0 | D28: 0 | E28: 0 | F28: =0-SUM(C28:E28) -> 0 | G28: 10 | H28: 0 | I28: 0 | J28: =10-SUM(G28:I28) -> 0 | K28: 0 | L28: 0 | M28: 0 | N28: =0-SUM(K28:M28) -> 0 | O28: 0 | P28: 0 | Q28: =0-SUM(N28:P28) -> 0 | R28: =0-SUM(O28:Q28) -> 0 | S28: =0-SUM(P28:R28) -> 0 | T28: =0-SUM(Q28:S28) -> 0 | U28: 0 | V28: 0 | W28: 0 | X28: 0 | Y28: 40.51 | AM28: =SUM(C28:F28) -> 0 | AN28: =SUM(G28:J28) -> 10 | AO28: =SUM(K28:N28) -> 0 | AP28: =SUM(O28:R28) -> 0 | AQ28: =SUM(S28:V28) -> 0 | AR28: 0 | AS28: 0 | AT28: 0 | AU28: 0 | AV28: 0 | AW28: 0 | AX28: 0 | AY28: 0 | AZ28: 0 | BA28: 0
B29: Amortization of In-Liscensed Rights | C29: 0.166 | D29: 0.165 | E29: 0.166 | F29: =0.662-SUM(C29:E29) -> 0.165 | G29: 0.17 | H29: 0.179 | I29: 0.178 | J29: =0.706-SUM(G29:I29) -> 0.179 | K29: 0.178 | L29: 0.179 | M29: 0.178 | N29: =0.71-SUM(K29:M29) -> 0.175 | O29: 0.178 | P29: 0.179 | Q29: 0.439 | R29: =1.559-SUM(O29:Q29) -> 0.763 | S29: 0.601 | T29: 0.601 | U29: 0.6 | V29: =2.405-SUM(S29:U29) -> 0.603 | W29: 0.6 | X29: 0.667 | Y29: 0.677 | AM29: =SUM(C29:F29) -> 0.662 | AN29: =SUM(G29:J29) -> 0.706 | AO29: =SUM(K29:N29) -> 0.71 | AP29: =SUM(O29:R29) -> 1.559 | AQ29: =SUM(S29:V29) -> 2.405 | AR29: 0 | AS29: 0 | AT29: 0 | AU29: 0 | AV29: 0 | AW29: 0 | AX29: 0 | AY29: 0 | AZ29: 0 | BA29: 0
B30: Operating Income | C30: =C25-SUM(C26:C29) -> -118.026 | D30: =D25-SUM(D26:D29) -> -138.357 | E30: =E25-SUM(E26:E29) -> -137.068 | F30: =F25-SUM(F26:F29) -> -170.712 | G30: =G25-SUM(G26:G29) -> -151.865 | H30: =H25-SUM(H26:H29) -> -167.574 | I30: =I25-SUM(I26:I29) -> -34.49 | J30: =J25-SUM(J26:J29) -> -105.823 | ... Y30: =Y25-SUM(Y26:Y29) -> -103.399 | AM30: =SUM(C30:F30) -> -564.163 | AN30: =SUM(G30:J30) -> -459.752 | AO30: =SUM(K30:N30) -> -536.197 | AP30: =SUM(O30:R30) -> -267.824 | AQ30: =SUM(S30:V30) -> 218.083 | AR30: =AR25-SUM(AR26:AR29) -> -239.1384 | AS30: =AS25-SUM(AS26:AS29) -> 49.184777 | AT30: =AT25-SUM(AT26:AT29) -> 411.97214 | AU30: =AU25-SUM(AU26:AU29) -> 450.41562 | AV30: =AV25-SUM(AV26:AV29) -> 495.53025 | AW30: =AW25-SUM(AW26:AW29) -> 525.77115 | AX30: =AX25-SUM(AX26:AX29) -> 548.15448 | AY30: =AY25-SUM(AY26:AY29) -> 567.03087 | ... BA30: =BA25-SUM(BA26:BA29) -> 584.19057
B31: Other Income (Expenses) | C31: -7.42 | D31: 0 | E31: -45 | F31: =-51.971-SUM(C31:E31) -> 0.449 | G31: -15.528 | H31: 102 | I31: -20.649 | J31: =-68.43-SUM(G31:I31) -> -134.253 | K31: -17.26 | L31: 0 | M31: =6.7-125.44 -> -118.74 | N31: =-125.441+6.7-SUM(K31:M31) -> 17.259 | O31: 12.7 | P31: 16.934 | Q31: -12.33 | R31: =33.055-SUM(O31:Q31) -> 15.751 | S31: 6.54 | T31: 14.278 | U31: 11.81 | V31: =42.693-SUM(S31:U31) -> 10.065 | W31: -83.132 | X31: 38.06 | Y31: -138.61 | AM31: =SUM(C31:F31) -> -51.971 | AN31: =SUM(G31:J31) -> -68.43 | AO31: =SUM(K31:N31) -> -118.741 | AP31: =SUM(O31:R31) -> 33.055 | AQ31: =SUM(S31:V31) -> 42.693 | AR31: 40 | AS31: =AR46*($BA$48) -> 53.634881 | AT31: =AS31*1.04 -> 55.780276 | AU31: =AT31*1.04 -> 58.011487 | AV31: =AU31*1.04 -> 60.331946 | AW31: =AV31*1.04 -> 62.745224 | AX31: =AW31*1.04 -> 65.255033 | AY31: =AX31*1.04 -> 67.865235 | AZ31: =AY31*1.04 -> 70.579844 | BA31: =AZ31*1.04 -> 73.403038
B32: Gain on, Income | C32: 108.069 | D32: -12.447 | E32: -14.335 | F32: =108.1-45-SUM(C32:E32) -> -18.187 | G32: 0 | H32: -16.185 | I32: 7.2 | J32: =102+7.2-SUM(G32:I32) -> 118.185 | K32: 0 | L32: -16.961 | M32: -6.33 | N32: =-35.021-SUM(K32:M32) -> -11.73 | O32: -387.32 | P32: 102 | Q32: 0 | R32: =-387.329+102-SUM(O32:Q32) -> -0.009 | S32: 0 | T32: 0 | U32: 0 | V32: =0-SUM(S32:U32) -> 0 | W32: 0 | X32: 0 | Y32: 47.95 | AM32: =SUM(C32:F32) -> 63.1 | AN32: =SUM(G32:J32) -> 109.2 | AO32: =SUM(K32:N32) -> -35.021 | AP32: =SUM(O32:R32) -> -285.329 | AQ32: =SUM(S32:V32) -> 0 | AR32: 0 | AS32: 0 | AT32: 0 | AU32: 0 | AV32: 0 | AW32: 0 | AX32: 0 | AY32: 0 | AZ32: 0 | BA32: 0
B33: Pretax Income | C33: =C30+SUM(C31:C32) -> -17.377 | D33: =D30+SUM(D31:D32) -> -150.804 | E33: =E30+SUM(E31:E32) -> -196.403 | F33: =F30+SUM(F31:F32) -> -188.45 | G33: =G30+SUM(G31:G32) -> -167.393 | H33: =H30+SUM(H31:H32) -> -81.759 | I33: =I30+SUM(I31:I32) -> -47.939 | J33: =J30+SUM(J31:J32) -> -121.891 | ... Y33: =Y30+SUM(Y31:Y32) -> -194.059 | AM33: =SUM(C33:F33) -> -553.034 | AN33: =SUM(G33:J33) -> -418.982 | AO33: =SUM(K33:N33) -> -689.959 | AP33: =SUM(O33:R33) -> -520.098 | AQ33: =SUM(S33:V33) -> 260.776 | AR33: =AR30+SUM(AR31:AR32) -> -199.1384 | AS33: =AS30+SUM(AS31:AS32) -> 102.81966 | AT33: =AT30+SUM(AT31:AT32) -> 467.75242 | AU33: =AU30+SUM(AU31:AU32) -> 508.4271 | AV33: =AV30+SUM(AV31:AV32) -> 555.8622 | AW33: =AW30+SUM(AW31:AW32) -> 588.51638 | AX33: =AX30+SUM(AX31:AX32) -> 613.40951 | AY33: =AY30+SUM(AY31:AY32) -> 634.8961 | ... BA33: =BA30+SUM(BA31:BA32) -> 657.5936
B34: Taxes | C34: 0.115 | D34: 0.2 | E34: 0.096 | F34: =1.063-SUM(C34:E34) -> 0.652 | G34: -0.143 | H34: -0.35 | I34: 0.237 | J34: =-0.168-SUM(G34:I34) -> 0.088 | K34: 0.879 | L34: 3.388 | M34: 1.32 | N34: =13.525-SUM(K34:M34) -> 7.938 | O34: 4.045 | P34: 9.355 | Q34: 7.763 | R34: =15.879-SUM(O34:Q34) -> -5.284 | S34: 5.329 | T34: 7.117 | U34: 0.395 | V34: =25.535-SUM(S34:U34) -> 12.694 | W34: 63.99 | X34: -43.25 | Y34: -14.1 | AM34: =SUM(C34:F34) -> 1.063 | AN34: =SUM(G34:J34) -> -0.168 | AO34: =SUM(K34:N34) -> 13.525 | AP34: =SUM(O34:R34) -> 15.879 | AQ34: =SUM(S34:V34) -> 25.535 | AR34: =AR33*AR43 -> 9.9569201 | AS34: =AS33*AS43 -> 8.2255727 | AT34: =AT33*AT43 -> 46.775242 | AU34: =AU33*AU43 -> 50.84271 | AV34: =AV33*AV43 -> 55.58622 | AW34: =AW33*AW43 -> 58.851638 | AX34: =AX33*AX43 -> 61.340951 | AY34: =AY33*AY43 -> 63.48961 | ... BA34: =BA33*BA43 -> 65.75936
B35: Net Income | C35: =C33-C34 -> -17.492 | D35: =D33-D34 -> -151.004 | E35: =E33-E34 -> -196.499 | F35: =F33-F34 -> -189.102 | G35: =G33-G34 -> -167.25 | H35: =H33-H34 -> -81.409 | I35: =I33-I34 -> -48.176 | J35: =J33-J34 -> -121.979 | K35: =K33-K34 -> -105.02 | L35: =L33-L34+-2.2 -> -233.631 | M35: =M33-M34-0.72 -> -258.453 | N35: =N33-N34 -> -109.3 | O35: =O33-O34 -> -516.758 | P35: =P33-P34 -> -23.936 | Q35: =Q33-Q34 -> -40.944 | R35: =R33-R34 -> 45.661 | S35: =S33-S34-1.6 -> 34.509 | T35: =T33-T34 -> 6.461 | U35: =U33-U34 -> 33.612 | V35: =V33-V34 -> 159.059 | W35: =W33-W34 -> -447.497 | X35: =X33-X34 -> 196.884 | Y35: =Y33-Y34 -> -179.959 | AM35: =SUM(C35:F35) -> -554.097 | AN35: =SUM(G35:J35) -> -418.814 | AO35: =SUM(K35:N35) -> -706.404 | AP35: =SUM(O35:R35) -> -535.977 | AQ35: =SUM(S35:V35) -> 233.641 | AR35: =AR33-AR34 -> -209.09532 | AS35: =AS33-AS34 -> 94.594085 | AT35: =AT33-AT34 -> 420.97717 | AU35: =AU33-AU34 -> 457.58439 | AV35: =AV33-AV34 -> 500.27598 | AW35: =AW33-AW34 -> 529.66474 | AX35: =AX33-AX34 -> 552.06856 | AY35: =AY33-AY34 -> 571.40649 | ... BA35: =BA33-BA34 -> 591.83424 | BB35: =BA35*(1+$BA$49) -> 532.65082 | BC35: =BB35*(1+$BA$49) -> 479.38574 | BD35: =BC35*(1+$BA$49) -> 431.44716 | BE35: =BD35*(1+$BA$49) -> 388.30245
B36: SC | C36: 76.432 | D36: 77.968 | E36: 78.501 | F36: 77.77 | G36: 79.454 | H36: 79.746 | I36: 79.88 | J36: 87.12 | K36: 87.253 | L36: 87.511 | M36: 87.62 | N36: 87.981 | O36: 88.186 | P36: 88.743 | Q36: 88.889 | R36: 92.398 | S36: 93.99 | T36: 94.618 | U36: 95.39 | V36: 97.032 | W36: 97.362 | X36: 98.005 | Y36: 100.23 | AM36: =AVERAGE(C36:F36) -> 77.66775 | AN36: =AVERAGE(G36:J36) -> 81.55 | AO36: =AVERAGE(K36:N36) -> 87.59125 | AP36: =AVERAGE(O36:R36) -> 89.554 | AQ36: =AVERAGE(S36:V36) -> 95.2575
B37: EPS | C37: =C35/C36 -> -0.22885702 | D37: =D35/D36 -> -1.9367433 | E37: =E35/E36 -> -2.5031401 | F37: =F35/F36 -> -2.4315546 | G37: =G35/G36 -> -2.1049916 | H37: =H35/H36 -> -1.0208537 | I37: =I35/I36 -> -0.60310466 | J37: =(J35/J36) -> -1.4001263 | K37: =K35/K36 -> -1.2036262 | L37: =L35/L36 -> -2.6697329 | M37: =M35/M36 -> -2.9497033 | N37: =N35/N36 -> -1.2423137 | O37: =O35/O36 -> -5.8598644 | P37: =P35/P36 -> -0.26972268 | Q37: =Q35/Q36 -> -0.46061942 | R37: =R35/R36 -> 0.49417736 | ... Y37: =Y35/Y36 -> -1.7954604 | AM37: =SUM(C37:F37) -> -7.100295 | AN37: =SUM(G37:J37) -> -5.1290762 | AO37: =SUM(K37:N37) -> -8.0653761 | AP37: =SUM(O37:R37) -> -6.0960291 | AQ37: =SUM(S37:V37) -> 2.4270479
B39: Gross Profit Margin | C39: =C25/C23 -> 0.88896318 | D39: =D25/D23 -> 0.90287495 | E39: =E25/E23 -> 0.89567411 | F39: =F25/F23 -> 0.84564082 | G39: =G25/G23 -> 0.84791501 | H39: =H25/H23 -> 0.88107064 | I39: =I25/I23 -> 0.87622115 | J39: =J25/J23 -> 0.84240649 | ... Y39: =Y25/Y23 -> 0.62244236 | AM39: =AM25/AM23 -> 0.88264744 | AN39: =AN25/AN23 -> 0.86172303 | AO39: =AO25/AO23 -> 0.84996029 | AP39: =AP25/AP23 -> 0.87908096 | AQ39: =AQ25/AQ23 -> 0.83222791 | AR39: 0.76 | AS39: 0.78 | AT39: 0.79 | AU39: 0.795 | AV39: 0.8 | AW39: 0.805 | AX39: 0.81 | AY39: 0.81 | AZ39: 0.81 | BA39: 0.81
B40: R&D as % of Revenue | C40: =C26/C23 -> 1.1976705 | D40: =D26/D23 -> 1.3724765 | E40: =E26/E23 -> 1.3231845 | F40: =F26/F23 -> 1.4278362 | G40: =G26/G23 -> 1.3281676 | H40: =H26/H23 -> 1.4603173 | I40: =I26/I23 -> 0.73462006 | J40: =J26/J23 -> 0.97935519 | ... Y40: =Y26/Y23 -> 0.5481253 | AM40: =AM26/AM23 -> 1.337427 | AN40: =AN26/AN23 -> 1.0987925 | AO40: =AO26/AO23 -> 0.94006193 | AP40: =AP26/AP23 -> 0.70567168 | AQ40: =AQ26/AQ23 -> 0.42299205 | AR40: 0.64 | AS40: 0.55 | AT40: 0.32 | AU40: 0.3 | AV40: 0.28 | AW40: 0.27 | AX40: 0.26 | AY40: 0.25 | AZ40: 0.245 | BA40: 0.24
B41: SG&A as % of Revenue | C41: =C27/C23 -> 0.72811725 | D41: =D27/D23 -> 0.53646285 | E41: =E27/E23 -> 0.52370001 | F41: =F27/F23 -> 0.59284012 | G41: =G27/G23 -> 0.48411159 | H41: =H27/H23 -> 0.44090097 | I41: =I27/I23 -> 0.32279136 | J41: =J27/J23 -> 0.38745626 | ... Y41: =Y27/Y23 -> 0.23010294 | AM41: =AM27/AM23 -> 0.58854951 | AN41: =AN27/AN23 -> 0.4027385 | AO41: =AO27/AO23 -> 0.48383141 | AP41: =AP27/AP23 -> 0.38756298 | AQ41: =AQ27/AQ23 -> 0.29331028 | AR41: 0.23 | AS41: 0.2 | AT41: 0.195 | AU41: 0.19 | AV41: 0.185 | AW41: 0.18 | AX41: 0.18 | AY41: 0.18 | AZ41: 0.18 | BA41: 0.18
B42: Operating Profit Margin | C42: =C30/C23 -> -1.0382849 | D42: =D30/D23 -> -1.0072656 | E42: =E30/E23 -> -0.95236375 | F42: =F30/F23 -> -1.1761723 | G42: =G30/G23 -> -1.0335804 | H42: =H30/H23 -> -1.0212385 | I42: =I30/I23 -> -0.18213022 | J42: =J30/J23 -> -0.52529349 | ... Y42: =Y30/Y23 -> -0.25892278 | AM42: =AM30/AM23 -> -1.0445548 | AN42: =AN30/AN23 -> -0.65506202 | AO42: =AO30/AO23 -> -0.57469403 | AP42: =AP30/AP23 -> -0.21540758 | AQ42: =AQ30/AQ23 -> 0.1146611 | AR42: =AR30/AR23 -> -0.11 | AS42: =AS30/AS23 -> 0.03 | AT42: =AT30/AT23 -> 0.275 | ... BA42: =BA30/BA23 -> 0.39
B43: Effective Tax Rate | C43: =-C34/C33 -> 0.0066179433 | D43: =-D34/D33 -> 0.0013262248 | E43: =-E34/E33 -> 0.0004887909 | F43: =-F34/F33 -> 0.0034598037 | G43: =-G34/G33 -> -0.00085427706 | H43: =-H34/H33 -> -0.0042808743 | I43: =-I34/I33 -> 0.0049437827 | J43: =-J34/J33 -> 0.0007219565 | ... Q43: =-Q34/Q33 -> 0.23395919 | R43: =R34/R33 -> -0.13086658 | S43: =S34/S33 -> 0.12860177 | T43: =T34/T33 -> 0.52415672 | U43: =U34/U33 -> 0.011615256 | V43: =V34/V33 -> 0.073908462 | W43: =-W34/W33 -> 0.16685484 | X43: =X34/X33 -> -0.28151321 | Y43: =Y34/Y33 -> 0.072658315 | AM43: =-AM34/AM33 -> 0.0019221241 | AN43: =-AN34/AN33 -> -0.00040097188 | AO43: =-AO34/AO33 -> 0.019602614 | AP43: =-AP34/AP33 -> 0.030530785 | AQ43: =-AQ34/AQ33 -> -0.097919287 | AR43: -0.05 | AS43: 0.08 | AT43: 0.1 | AU43: 0.1 | AV43: 0.1 | AW43: 0.1 | AX43: 0.1 | AY43: 0.1 | AZ43: 0.1 | BA43: 0.1
B44: Net Profit Margin | C44: =C35/C23 -> -0.15387864 | D44: =D35/D23 -> -1.0993382 | E44: =E35/E23 -> -1.365297 | F44: =F35/F23 -> -1.3028758 | G44: =G35/G23 -> -1.1382894 | H44: =H35/H23 -> -0.4961271 | I44: =I35/I23 -> -0.25440144 | J44: =J35/J23 -> -0.60549006 | ... Y44: =Y35/Y23 -> -0.45063767 | AM44: =AM35/AM23 -> -1.0259175 | AN44: =AN35/AN23 -> -0.5967329 | AO44: =AO35/AO23 -> -0.75712128 | AP44: =AP35/AP23 -> -0.43107977 | AQ44: =AQ35/AQ23 -> 0.122841 | AR44: =AR35/AR23 -> -0.096180644 | AS44: =AS35/AS23 -> 0.057697172 | AT44: =AT35/AT23 -> 0.28101105 | ... BA44: =BA35/BA23 -> 0.39510285
B46: Cash & CEs | F46: 1502.64 | G46: 1481.83 | H46: 1697.27 | I46: 1599.113 | J46: 2115.869 | K46: 1233.877 | L46: 868.565 | M46: 1038.62 | N46: 966.77 | O46: 871.668 | P46: 851.929 | Q46: 541.932 | R46: 428.43 | S46: 427.29 | T46: 383.622 | U46: 197.855 | V46: 1103.01 | W46: 240.867 | X46: 510.598 | Y46: 613.07 | AM46: =F46 -> 1502.64 | AN46: =J46 -> 2115.869 | AO46: =N46 -> 966.77 | AP46: =R46 -> 428.43 | AQ46: =V46 -> 1103.01 | AR46: =AR35+AQ46 -> 893.91468 | AS46: =AS35+AR46 -> 988.50876 | AT46: =AT35+AS46 -> 1409.4859 | AU46: =AU35+AT46 -> 1867.0703 | AV46: =AV35+AU46 -> 2367.3463 | AW46: =AW35+AV46 -> 2897.011 | AX46: =AX35+AW46 -> 3449.0796 | AY46: =AY35+AX46 -> 4020.4861 | ... BA46: =BA35+AZ46 -> 5194.8195
B47: ST Investments | F47: 435.923 | G47: 255.997 | H47: 30 | I47: 0 | J47: 0 | K47: 779.548 | L47: 1059.454 | M47: 1033.86 | N47: 1022.597 | O47: 1010.42 | P47: 1008.786 | Q47: 1191.61 | R47: 1247.82 | S47: 963.453 | T47: 1076.85 | U47: 1000.534 | V47: 251.782 | W47: 281.895 | X47: 289.541 | Y47: 237.916 | AM47: =F47 -> 435.923 | AN47: =J47 -> 0 | AO47: =N47 -> 1022.597 | AP47: =R47 -> 1247.82 | AQ47: =V47 -> 251.782
B48: A/R | F48: 101.34 | G48: 118.203 | H48: 127.52 | I48: 149.787 | J48: 152.99 | K48: 178.194 | L48: 203.854 | M48: 201.509 | N48: 214.628 | O48: 223.836 | P48: 236.808 | Q48: 318.855 | R48: 400.32 | S48: 378.806 | T48: 359.997 | U48: 434.524 | V48: 601.988 | W48: 659.371 | X48: 527.295 | Y48: 395.73 | AM48: =F48 -> 101.34 | AN48: =J48 -> 152.99 | AO48: =N48 -> 214.628 | AP48: =R48 -> 400.32 | AQ48: =V48 -> 601.988 | AS48: Projected ROIC: | AV48: Invested Capital | AX48: AVG Invested Capital | AZ48: ROIC | BA48: 0.06
B49: Inventories | F49: 231.961 | G49: 240.333 | H49: 268.756 | I49: 288.469 | J49: 186.212 | K49: 198.997 | L49: 208.095 | M49: 221.192 | N49: 203.968 | O49: 202.67 | P49: 226.876 | Q49: 244.011 | R49: 322.85 | S49: 373.53 | T49: 485.795 | U49: 565.924 | V49: 749.96 | W49: 941.432 | X49: 994 | Y49: 1077.16 | AM49: =F49 -> 231.961 | AN49: =J49 -> 186.212 | AO49: =N49 -> 203.968 | AP49: =R49 -> 322.85 | AQ49: =V49 -> 749.96 | AS49: 2026 | AU49: 2023 | AV49: 2024 | AX49: 2023-2024 | AZ49: Terminal | BA49: -0.1
B50: Manufacturing Prepaids | F50: 0 | G50: 0 | H50: 0 | I50: 0 | J50: 0 | K50: 0 | L50: 0 | M50: 0 | N50: 0 | O50: 0 | P50: 0 | Q50: 0 | R50: 0 | S50: 238.821 | T50: 302.627 | U50: 321.055 | V50: 276.62 | W50: 203.49 | X50: 207.92 | Y50: 206.06 | AM50: =F50 -> 0 | AN50: =J50 -> 0 | AO50: =N50 -> 0 | AP50: =R50 -> 0 | AQ50: =V50 -> 276.62 | AS50: =AVERAGE(AS30)*(1-AS43) -> 45.249995 | AU50: =SUM(AP46:AP49)-AP60+AP52 -> 2461.652 | AV50: =SUM(AQ46:AQ49)-AQ60+AQ52 -> 2832.634 | AX50: =AVERAGE(AU50:AV50) -> 2647.143 | AZ50: RFR (10-year yield) | BA50: ='Bull Case (20%)'!BA50 -> 0.0416
B51: Other ST Assets | F51: 213.324 | G51: 174.98 | H51: 141.666 | I51: 147.941 | J51: 149.028 | K51: 140.33 | L51: 129.332 | M51: 130.744 | N51: 149.891 | O51: 179.769 | P51: 148.215 | Q51: 154.441 | R51: 179.89 | S51: 82.965 | T51: 74.74 | U51: 165.477 | V51: 90.461 | W51: 105.478 | X51: 127.59 | Y51: 192.34 | AM51: =F51 -> 213.324 | AN51: =J51 -> 149.028 | AO51: =N51 -> 149.891 | AP51: =R51 -> 179.89 | AQ51: =V51 -> 90.461 | AS51: =AS50/AX50 -> 0.017093899 | AZ51: ERP (Avg. market return - (less) RFR) | BA51: =9.75%-BA50 -> 0.0559
B52: PP&E | F52: 190.43 | G52: 203.107 | H52: 203.33 | I52: 199.249 | J52: 191.156 | K52: 187.248 | L52: 183.292 | M52: 181.005 | N52: 180.037 | O52: 182.86 | P52: 188.874 | Q52: 212.367 | R52: 227.15 | S52: 249.302 | T52: 276.2 | U52: 305.788 | V52: 340.336 | W52: 360.587 | X52: 371.857 | Y52: 358.93 | AM52: =F52 -> 190.43 | AN52: =J52 -> 191.156 | AO52: =N52 -> 180.037 | AP52: =R52 -> 227.15 | AQ52: =V52 -> 340.336 | AZ52: Equity β (1-year avg.) | BA52: 0.56
B53: Right-to-use assets | F53: 13.628 | G53: 14.124 | H53: 14.105 | I53: 14.204 | J53: 14.239 | K53: 13.328 | L53: 13.062 | M53: 13.057 | N53: 7.578 | O53: 62.016 | P53: 134.728 | Q53: 133.454 | R53: 129.95 | S53: 126.269 | T53: 124 | U53: 140.898 | V53: 148.31 | W53: 147.063 | X53: 143.041 | Y53: 139.16 | AM53: =F53 -> 13.628 | AN53: =J53 -> 14.239 | AO53: =N53 -> 7.578 | AP53: =R53 -> 129.95 | AQ53: =V53 -> 148.31 | AZ53: Discount (Cost of Equity) | BA53: =+BA50+(BA51*BA52) -> 0.072904
B54: Non-current Inventories | F54: 91.761 | G54: 65.068 | H54: 72.868 | I54: 72.663 | J54: 45.531 | K54: 45.982 | L54: 46.999 | M54: 43.034 | N54: 64.954 | O54: 164.144 | P54: 166.635 | Q54: 176.112 | R54: 191.36 | S54: 207.542 | T54: 204.69 | U54: 202.55 | V54: 187.986 | W54: 181.158 | X54: 194.668 | Y54: 198.6 | AM54: =F54 -> 91.761 | AN54: =J54 -> 45.531 | AO54: =N54 -> 64.954 | AP54: =R54 -> 191.36 | AQ54: =V54 -> 187.986
B55: Strategic Investments | F55: 0 | G55: 0 | H55: 0 | I55: 0 | J55: 0 | K55: 0 | L55: 0 | M55: 0 | N55: 0 | O55: 0 | P55: 0 | Q55: 0 | R55: 0 | S55: 0 | T55: 0 | U55: 0 | V55: 0 | W55: 154.37 | X55: 195.522 | Y55: 0 | AM55: =F55 -> 0 | AN55: =J55 -> 0 | AO55: =N55 -> 0 | AP55: =R55 -> 0 | AQ55: =V55 -> 0 | AZ55: NPV | BA55: =NPV(BA53,AR35:CO35) -> 3306.8828
B56: LT Investments | F56: 0 | G56: 0 | H56: 0 | I56: 0 | J56: 0 | K56: 0 | L56: 0 | M56: 0 | N56: 0 | O56: 0 | P56: 0 | Q56: 0 | R56: 0 | S56: 0 | T56: 0 | U56: 181.77 | V56: 133.163 | W56: 109.125 | X56: 34.604 | Y56: 1.04 | AM56: =F56 -> 0 | AN56: =J56 -> 0 | AO56: =N56 -> 0 | AP56: =R56 -> 0 | AQ56: =V56 -> 133.163 | AZ56: SC | BA56: =Main!C6 -> 104.787
B57: Other LT Assets | F57: 203.703 | G57: 211.584 | H57: 203.553 | I57: 190.792 | J57: 292.949 | K57: 278.649 | L57: 284.2 | M57: 293.124 | N57: 317.936 | O57: 162.387 | P57: 163.039 | Q57: 136.925 | R57: 136.87 | S57: 176.407 | T57: 135.72 | U57: 83.559 | V57: 79.915 | W57: 80.551 | X57: 83.137 | Y57: 73.38 | AM57: =F57 -> 203.703 | AN57: =J57 -> 292.949 | AO57: =N57 -> 317.936 | AP57: =R57 -> 136.87 | AQ57: =V57 -> 79.915 | AZ57: FV | BA57: =BA55/BA56 -> 31.55814
B58: Ttl Assets | F58: =SUM(F46:F57) -> 2984.71 | G58: =SUM(G46:G57) -> 2765.226 | H58: =SUM(H46:H57) -> 2759.068 | I58: =SUM(I46:I57) -> 2662.218 | J58: =SUM(J46:J57) -> 3147.974 | K58: =SUM(K46:K57) -> 3056.153 | L58: =SUM(L46:L57) -> 2996.853 | M58: =SUM(M46:M57) -> 3156.145 | ... Y58: =SUM(Y46:Y57) -> 3493.386 | AM58: =F58 -> 2984.71 | AN58: =J58 -> 3147.974 | AO58: =N58 -> 3128.359 | AP58: =R58 -> 3264.64 | AQ58: =V58 -> 3963.531 | AZ58: CP | BA58: =Main!C5 -> 23.73
AZ59: Change Δ | BA59: =BA57/BA58-1 -> 0.32988368 | BB59: =IF(BA59>0,"Upside","Downside") -> Upside
B60: A/P | F60: 111.09 | G60: 76.651 | H60: 76.68 | I60: 44.163 | J60: 76.741 | K60: 54.007 | L60: 56.207 | M60: 118.461 | N60: 95.875 | O60: 106.71 | P60: 109.796 | Q60: 87.948 | R60: 164.918 | S60: 91.536 | T60: 107.417 | U60: 118.774 | V60: 214.442 | W60: 156.105 | X60: 136.702 | Y60: 94.015 | AM60: =F60 -> 111.09 | AN60: =J60 -> 76.741 | AO60: =N60 -> 95.875 | AP60: =R60 -> 164.918 | AQ60: =V60 -> 214.442 | AZ60: {=_xlfn.IFS(BA59>=25%,"Strong Buy",BA59>=10.00001%,"Buy",AND(BA59<=10%,BA59>=-4.9999%),"Hold",AND(BA59<=-5%,BA59>=-14.999999%),"Sell",BA59<=-15%,"Strong Sell")} -> Strong Buy
B61: Accrued Expenses, current | F61: 193.55 | G61: 180.636 | H61: 240.141 | I61: 221.009 | J61: 271.697 | K61: 293.908 | L61: 383.699 | M61: 368.998 | N61: 418.99 | O61: 345.55 | P61: 326.877 | Q61: 322.35 | R61: 314.997 | S61: 283.317 | T61: 350.404 | U61: 344.83 | V61: 373.5 | W61: 391.65 | X61: 377.399 | Y61: 295.79 | AM61: =F61 -> 193.55 | AN61: =J61 -> 271.697 | AO61: =N61 -> 418.99 | AP61: =R61 -> 314.997 | AQ61: =V61 -> 373.5
B62: Deffered Revenues, current | F62: 89.244 | G62: 89.244 | H62: 89.244 | I62: 89.244 | J62: 89.244 | K62: 89.244 | L62: 89.244 | M62: 89.244 | N62: 89.244 | O62: 67.239 | P62: 44.989 | Q62: 22.494 | R62: 50.416 | S62: 112 | T62: 122.036 | U62: 127 | V62: 130.256 | W62: 44.859 | X62: 395.431 | Y62: 485.449 | AM62: =F62 -> 89.244 | AN62: =J62 -> 89.244 | AO62: =N62 -> 89.244 | AP62: =R62 -> 50.416 | AQ62: =V62 -> 130.256
B63: Other ST Liabilities | F63: 22.139 | G63: 18.205 | H63: 18.956 | I63: 19.02 | J63: 15.051 | K63: 17.803 | L63: 16.416 | M63: 26.213 | N63: 15.489 | O63: 17.381 | P63: 16.992 | Q63: 17.951 | R63: 17.845 | S63: 16.27 | T63: 17.12 | U63: 17.289 | V63: 13.473 | W63: 12.974 | X63: 10.416 | Y63: =36+10.16 -> 46.16 | AM63: =F63 -> 22.139 | AN63: =J63 -> 15.051 | AO63: =N63 -> 15.489 | AP63: =R63 -> 17.845 | AQ63: =V63 -> 13.473
B64: Current Portion of Debt | F64: 0 | G64: 0 | H64: 0 | I64: 0 | J64: 0 | K64: 0 | L64: 0 | M64: 0 | N64: 0 | O64: 0 | P64: 0 | Q64: 0 | R64: 105.483 | S64: 105.586 | T64: 91.505 | U64: 91.595 | V64: 0 | W64: 0 | X64: 0 | Y64: 0 | AM64: =F64 -> 0 | AN64: =J64 -> 0 | AO64: =N64 -> 0 | AP64: =R64 -> 105.483 | AQ64: =V64 -> 0
B65: LT Debt | F65: 992.493 | G65: 1091.11 | H65: 1092.985 | I65: 1094.912 | J65: 1096.876 | K65: 1098.84 | L65: 1100.873 | M65: 1542.77 | N65: 1544.29 | O65: 1234.284 | P65: 1235.51 | Q65: 1236.755 | R65: 1132.515 | S65: 1133.66 | T65: 1134.81 | U65: 1135.965 | V65: 1137.12 | W65: 1138.28 | X65: 1139.458 | Y65: 1035.146 | AM65: =F65 -> 992.493 | AN65: =J65 -> 1096.876 | AO65: =N65 -> 1544.29 | AP65: =R65 -> 1132.515 | AQ65: =V65 -> 1137.12
B66: LT Lease Liabilities | F66: 80.36 | G66: 60.675 | H66: 65.285 | I66: 63.42 | J66: 41.512 | K66: 38.62 | L66: 39.368 | M66: 35.229 | N66: 57.578 | O66: 53.931 | P66: 129.17 | Q66: 134.752 | R66: 140.96 | S66: 140.1 | T66: 143.601 | U66: 170 | V66: 192.473 | W66: 205.46 | X66: 214.419 | Y66: 215.042 | AM66: =F66 -> 80.36 | AN66: =J66 -> 41.512 | AO66: =N66 -> 57.578 | AP66: =R66 -> 140.96 | AQ66: =V66 -> 192.473
B67: Deffered LT Revenues | F67: 663.488 | G67: 641.483 | H67: 619.233 | I67: 596.73 | J67: 574.244 | K67: 552.239 | L67: 529.989 | M67: 507.494 | N67: 485 | O67: 485 | P67: 485 | Q67: 485 | R67: 437 | S67: 325 | T67: 325 | U67: 325 | V67: 325 | W67: 325 | X67: 0 | Y67: 0 | AM67: =F67 -> 663.488 | AN67: =J67 -> 574.244 | AO67: =N67 -> 485 | AP67: =R67 -> 437 | AQ67: =V67 -> 325
B68: Contingent Consideration | F68: 50.8 | G68: 50.8 | H68: 50.8 | I68: 43.6 | J68: 43.6 | K68: 43.6 | L68: 43.6 | M68: 36.9 | N68: 36.9 | O68: 36.9 | P68: 36.1 | Q68: 38.1 | R68: 38.1 | S68: 48.2 | T68: 48.2 | U68: 47.4 | V68: 47.4 | W68: 47.4 | X68: 47.4 | Y68: 0.3 | AM68: =F68 -> 50.8 | AN68: =J68 -> 43.6 | AO68: =N68 -> 36.9 | AP68: =R68 -> 38.1 | AQ68: =V68 -> 47.4
B69: Other LT Liabilities | F69: 19.785 | G69: 20.984 | H69: 20.64 | I69: 20.569 | J69: 11 | K69: 11 | L69: 11 | M69: 0 | N69: 0.042 | O69: 0.038 | P69: 0.038 | Q69: 0 | R69: 3 | S69: 7.522 | T69: 7.087 | U69: 1 | V69: 1.75 | W69: 0.927 | X69: 1.2 | Y69: 1.404 | AM69: =F69 -> 19.785 | AN69: =J69 -> 11 | AO69: =N69 -> 0.042 | AP69: =R69 -> 3 | AQ69: =V69 -> 1.75
B70: Ttl Liabilities | F70: =SUM(F60:F69) -> 2222.949 | G70: =SUM(G60:G69) -> 2229.788 | H70: =SUM(H60:H69) -> 2273.964 | I70: =SUM(I60:I69) -> 2192.667 | J70: =SUM(J60:J69) -> 2219.965 | K70: =SUM(K60:K69) -> 2199.261 | L70: =SUM(L60:L69) -> 2270.396 | M70: =SUM(M60:M69) -> 2725.309 | ... Y70: =SUM(Y60:Y69) -> 2173.306 | AM70: =F70 -> 2222.949 | AN70: =J70 -> 2219.965 | AO70: =N70 -> 2743.408 | AP70: =R70 -> 2405.234 | AQ70: =V70 -> 2435.414
B71: SE | F71: 761.759 | G71: 535.445 | H71: 485.1 | I71: 469.52 | J71: 928.009 | K71: 856.886 | L71: 726.457 | M71: 430.84 | N71: 384.95 | O71: 712.749 | P71: 741.411 | Q71: 764.357 | R71: 859.337 | S71: 961.192 | T71: 1077.06 | U71: 1221.071 | V71: 1527.742 | W71: 1142.723 | X71: 1357.38 | Y71: 1320.12 | AM71: =F71 -> 761.759 | AN71: =J71 -> 928.009 | AO71: =N71 -> 384.95 | AP71: =R71 -> 859.337 | AQ71: =V71 -> 1527.742
B72: Total L + SE | F72: =F70+F71 -> 2984.708 | G72: =G70+G71 -> 2765.233 | H72: =H70+H71 -> 2759.064 | I72: =I70+I71 -> 2662.187 | J72: =J70+J71 -> 3147.974 | K72: =K70+K71 -> 3056.147 | L72: =L70+L71 -> 2996.853 | M72: =M70+M71 -> 3156.149 | ... Y72: =Y70+Y71 -> 3493.426 | AM72: =F72 -> 2984.708 | AN72: =J72 -> 3147.974 | AO72: =N72 -> 3128.358 | AP72: =R72 -> 3264.571 | AQ72: =V72 -> 3963.156
B74: Current Ratio | F74: =SUM(F46:F51)/SUM(F60:F64) -> 5.9736793 | G74: =SUM(G46:G51)/SUM(G60:G64) -> 6.2273617 | H74: =SUM(H46:H51)/SUM(H60:H64) -> 5.3296472 | I74: =SUM(I46:I51)/SUM(I60:I64) -> 5.8518997 | J74: =SUM(J46:J51)/SUM(J60:J64) -> 5.7519531 | K74: =SUM(K46:K51)/SUM(K60:K64) -> 5.5629833 | L74: =SUM(L46:L51)/SUM(L60:L64) -> 4.5261252 | M74: =SUM(M46:M51)/SUM(M60:M64) -> 4.3553745 | ... Y74: =SUM(Y46:Y51)/SUM(Y60:Y64) -> 2.9544548 | AM74: =SUM(AM46:AM51)/SUM(AM60:AM64) -> 5.9736793 | AN74: =SUM(AN46:AN51)/SUM(AN60:AN64) -> 5.7519531 | AO74: =SUM(AO46:AO51)/SUM(AO60:AO64) -> 4.1282477 | AP74: =SUM(AP46:AP51)/SUM(AP60:AP64) -> 3.9459565 | AQ74: =SUM(AQ46:AQ51)/SUM(AQ60:AQ64) -> 4.2010972
B75: Quick Ratio | F75: =(SUM(F46:F51)-F49)/SUM(F60:F64) -> 5.4161116 | G75: =(SUM(G46:G51)-G49)/SUM(G60:G64) -> 5.5684385 | H75: =(SUM(H46:H51)-H49)/SUM(H60:H64) -> 4.6973114 | I75: =(SUM(I46:I51)-I49)/SUM(I60:I64) -> 5.0794273 | J75: =(SUM(J46:J51)-J49)/SUM(J60:J64) -> 5.3406467 | K75: =(SUM(K46:K51)-K49)/SUM(K60:K64) -> 5.1255907 | L75: =(SUM(L46:L51)-L49)/SUM(L60:L64) -> 4.1446956 | M75: =(SUM(M46:M51)-M49)/SUM(M60:M64) -> 3.9885042 | ... Y75: =(SUM(Y46:Y51)-Y49)/SUM(Y60:Y64) -> 1.7854254 | AM75: =(SUM(AM46:AM51)-AM49)/SUM(AM60:AM64) -> 5.4161116 | AN75: =(SUM(AN46:AN51)-AN49)/SUM(AN60:AN64) -> 5.3406467 | AO75: =(SUM(AO46:AO51)-AO49)/SUM(AO60:AO64) -> 3.7990536 | AP75: =(SUM(AP46:AP51)-AP49)/SUM(AP60:AP64) -> 3.4520446 | AQ75: =(SUM(AQ46:AQ51)-AQ49)/SUM(AQ60:AQ64) -> 3.176101
B76: Cash Ratio | F76: =F46/SUM(F60:F64) -> 3.6119157 | G76: =G46/SUM(G60:G64) -> 4.0627468 | H76: =H46/SUM(H60:H64) -> 3.9933792 | I76: =I46/SUM(I60:I64) -> 4.2821608 | J76: =J46/SUM(J60:J64) -> 4.6735471 | K76: =K46/SUM(K60:K64) -> 2.7120441 | L76: =L46/SUM(L60:L64) -> 1.5920439 | M76: =M46/SUM(M60:M64) -> 1.7226612 | ... Y76: =Y46/SUM(Y60:Y64) -> 0.66535781 | AM76: =AM46/SUM(AM60:AM64) -> 3.6119157 | AN76: =AN46/SUM(AN60:AN64) -> 4.6735471 | AO76: =AO46/SUM(AO60:AO64) -> 1.5603181 | AP76: =AP46/SUM(AP60:AP64) -> 0.65543349 | AQ76: =AQ46/SUM(AQ60:AQ64) -> 1.5075218
B77: Ttl Asset Turnover | F77: =F23/F72 -> 0.048628543 | G77: =G23/G72 -> 0.053135125 | H77: =H23/H72 -> 0.059472705 | I77: =I23/I72 -> 0.071133245 | J77: =J23/J72 -> 0.063995128 | K77: =K23/K72 -> 0.068985556 | L77: =L23/L72 -> 0.077927413 | M77: =M23/M72 -> 0.072960434 | ... Y77: =Y23/Y72 -> 0.11431271 | AM77: =AM23/AM72 -> 0.18095539 | AN77: =AN23/AN72 -> 0.22295133 | AO77: =AO23/AO72 -> 0.29824368 | AP77: =AP23/AP72 -> 0.38085739 | AQ77: =AQ23/AQ72 -> 0.47991525
B78: Inventory Turnover Ratio | F78: =F24/AVERAGE(C49:F49) -> 0.096585202 | G78: =G24/AVERAGE(D49:G49) -> 0.094627499 | H78: =H24/AVERAGE(E49:H49) -> 0.079002766 | I78: =I24/AVERAGE(F49:I49) -> 0.091071656 | J78: =J24/AVERAGE(G49:J49) -> 0.12908708 | K78: =K24/AVERAGE(H49:K49) -> 0.13345444 | L78: =L24/AVERAGE(I49:L49) -> 0.17145002 | M78: =M24/AVERAGE(J49:M49) -> 0.19620477 | ... Y78: =Y24/AVERAGE(V49:Y49) -> 0.16029014 | AM78: =AM24/AVERAGE(AJ49:AM49) -> 0.27324421 | AN78: =AN24/AVERAGE(AK49:AN49) -> 0.46415718 | AO78: =AO24/AVERAGE(AL49:AO49) -> 0.67503508 | AP78: =AP24/AVERAGE(AM49:AP49) -> 0.63637855 | AQ78: =AQ24/AVERAGE(AN49:AQ49) -> 0.87245709
B79: Return on Assets | F79: =F35/F72 -> -0.063356952 | G79: =G35/G72 -> -0.060483149 | H79: =H35/H72 -> -0.029506021 | I79: =I35/I72 -> -0.0180964 | J79: =J35/J72 -> -0.038748414 | K79: =K35/K72 -> -0.03436353 | L79: =L35/L72 -> -0.077958779 | M79: =M35/M72 -> -0.081888719 | ... Y79: =Y35/Y72 -> -0.051513614 | AM79: =AM35/AM72 -> -0.1856453 | AN79: =AN35/AN72 -> -0.13304239 | AO79: =AO35/AO72 -> -0.22580664 | AP79: =AP35/AP72 -> -0.16417992 | AQ79: =AQ35/AQ72 -> 0.058953269
B80: Return on Equity | F80: =F35/F71 -> -0.24824387 | G80: =G35/G71 -> -0.31235701 | H80: =H35/H71 -> -0.16781901 | I80: =I35/I71 -> -0.10260692 | J80: =J35/J71 -> -0.13144161 | K80: =K35/K71 -> -0.12256006 | L80: =L35/L71 -> -0.32160334 | M80: =M35/M71 -> -0.59988163 | ... Y80: =Y35/Y71 -> -0.13632018 | AM80: =AM35/AM71 -> -0.72739147 | AN80: =AN35/AN71 -> -0.45130381 | AO80: =AO35/AO71 -> -1.8350539 | AP80: =AP35/AP71 -> -0.62370991 | AQ80: =AQ35/AQ71 -> 0.15293224
B82: Net Income | C82: =C35 -> -17.492 | D82: =D35 -> -151.004 | E82: =E35 -> -196.499 | F82: =F35 -> -189.102 | G82: =G35 -> -167.25 | H82: =H35 -> -81.409 | I82: =I35 -> -48.176 | J82: =J35 -> -121.979 | ... Y82: =Y35 -> -179.959 | AM82: =SUM(C82:F82) -> -554.097 | AN82: =SUM(G82:J82) -> -418.814 | AO82: =SUM(K82:N82) -> -706.404 | AP82: =SUM(O82:R82) -> -535.977 | AQ82: =SUM(S82:V82) -> 233.641
B83: CFFO | C83: 627.8 | D83: -107.6 | E83: -283.2 | F83: -129.5 | G83: -180.4 | H83: -109.5 | I83: -124 | J83: -29.3 | K83: -101.2 | L83: -66.8 | M83: -65 | N83: -92.4 | O83: -209.4 | P83: -122.2 | Q83: -115.9 | R83: -53.5 | S83: -241.1 | T83: 14.9 | U83: -70.7 | V83: 92 | W83: -583.4 | X83: =-322.1-W83 -> 261.3 | Y83: -14.6 | AM83: =SUM(C83:F83) -> 107.5 | AN83: =SUM(G83:J83) -> -443.2 | AO83: =SUM(K83:N83) -> -325.4 | AP83: =SUM(O83:R83) -> -501 | AQ83: =SUM(S83:V83) -> -204.9
B84: CapEx, net | C84: -9.1 | D84: -19.2 | E84: -25.3 | F84: -28.6 | G84: -21.1 | H84: -5.9 | I84: -9.2 | J84: -2.2 | K84: -5.6 | L84: -9.1 | M84: -8.2 | N84: -8 | O84: -9.5 | P84: -17.9 | Q84: -29.7 | R84: -19 | S84: -32.4 | T84: -29.2 | U84: -37.3 | V84: -38.1 | W84: -43.7 | X84: =-75.44-W84 -> -31.74 | Y84: -22.9 | AM84: =SUM(C84:F84) -> -82.2 | AN84: =SUM(G84:J84) -> -38.4 | AO84: =SUM(K84:N84) -> -30.9 | AP84: =SUM(O84:R84) -> -76.1 | AQ84: =SUM(S84:V84) -> -137
B85: FCF | C85: =C83+C84 -> 618.7 | D85: =D83+D84 -> -126.8 | E85: =E83+E84 -> -308.5 | F85: =F83+F84 -> -158.1 | G85: =G83+G84 -> -201.5 | H85: =H83+H84 -> -115.4 | I85: =I83+I84 -> -133.2 | J85: =J83+J84 -> -31.5 | ... Y85: =Y83+Y84 -> -37.5 | AM85: =SUM(C85:F85) -> 25.3 | AN85: =SUM(G85:J85) -> -481.6 | AO85: =SUM(K85:N85) -> -356.3 | AP85: =SUM(O85:R85) -> -577.1 | AQ85: =SUM(S85:V85) -> -341.9
B86: SC | C86: =C36 -> 76.432 | D86: =D36 -> 77.968 | E86: =E36 -> 78.501 | F86: =F36 -> 77.77 | G86: =G36 -> 79.454 | H86: =H36 -> 79.746 | I86: =I36 -> 79.88 | J86: =J36 -> 87.12 | ... Y86: =Y36 -> 100.23 | AM86: =AM36 -> 77.66775 | AN86: =AN36 -> 81.55 | AO86: =AO36 -> 87.59125 | AP86: =AP36 -> 89.554 | AQ86: =AQ36 -> 95.2575
B87: FCF per Share | C87: =C85/C86 -> 8.0947771 | D87: =D85/D86 -> -1.6263082 | E87: =E85/E86 -> -3.9298862 | F87: =F85/F86 -> -2.0329176 | G87: =G85/G86 -> -2.5360586 | H87: =H85/H86 -> -1.4470945 | I87: =I85/I86 -> -1.6675013 | J87: =J85/J86 -> -0.36157025 | ... Y87: =Y85/Y86 -> -0.37413948 | AM87: =SUM(C87:F87) -> 0.50566501 | AN87: =SUM(G87:J87) -> -6.0122246 | AO87: =SUM(K87:N87) -> -4.0679274 | AP87: =SUM(O87:R87) -> -6.4836165 | AQ87: =SUM(S87:V87) -> -3.6377254
B89: FCF/Revenue | C89: =C85/C23 -> 5.4427574 | D89: =D85/D23 -> -0.92312844 | E89: =E85/E23 -> -2.1434924 | F89: =F85/F23 -> -1.0892781 | G89: =G85/G23 -> -1.371392 | H89: =H85/H23 -> -0.70327688 | I89: =I85/I23 -> -0.70338491 | J89: =J85/J23 -> -0.15636246 | ... Y89: =Y85/Y23 -> -0.093904238

Sheet Bear Case (30%)
C1: Q1 2020 | G1: Q1 2021 | K1: Q1 2022 | O1: Q1 2023 | S1: Q1 2024 | W1: Q1 2025
B2: Quarterly
B3: Revenues | C3: Q1 2020 | D3: Q2 2020 | E3: Q3 2020 | F3: Q4 2020 | G3: Q1 2021 | H3: Q2 2021 | I3: Q3 2021 | J3: Q4 2021 | K3: Q1 2022 | L3: Q2 2022 | M3: Q3 2022 | N3: Q4 2022 | O3: Q1 2023 | P3: Q2 2023 | Q3: Q3 2023 | R3: Q4 2023 | S3: Q1 2024 | T3: Q2 2024 | U3: Q3 2024 | V3: Q4 2024 | W3: Q1 2025 | X3: Q2 2025 | Y3: Q3 2025 | Z3: Q4 2025 | AA3: Q1 2026 | AB3: Q2 2026 | AC3: Q3 2026 | AD3: Q4 2026 | AM3: 2020 | AN3: =AM3+1 -> 2021 | AO3: =AN3+1 -> 2022 | AP3: =AO3+1 -> 2023 | AQ3: =AP3+1 -> 2024 | AR3: =AQ3+1 -> 2025 | AS3: =AR3+1 -> 2026 | AT3: =AS3+1 -> 2027 | AU3: =AT3+1 -> 2028 | ... CY3: =CX3+1 -> 2084
B4: PMO Products | C4: 100.448 | D4: 111.34 | E4: 121.429 | F4: =455.865-SUM(C4:E4) -> 122.648 | G4: 124.926 | H4: 141.839 | I4: 166.911 | J4: =612.401-SUM(G4:I4) -> 178.725 | K4: 188.825 | L4: 211.237 | M4: 207.774 | N4: =843.769-SUM(K4:M4) -> 235.933 | O4: 231.495 | P4: 238.988 | Q4: 240.21 | R4: =944.52-SUM(O4:Q4) -> 233.827 | S4: 225.548 | T4: 238.827 | U4: 248.788 | V4: =967.169-SUM(S4:U4) -> 254.006 | W4: 236.538 | X4: 231.272 | Y4: 238.545 | Z4: 270 | AA4: 275 | AB4: 278 | AC4: 280 | AD4: 282 | AM4: =SUM(C4:F4) -> 455.865 | AN4: =SUM(G4:J4) -> 612.401 | AO4: =SUM(K4:N4) -> 843.769 | AP4: =SUM(O4:R4) -> 944.52 | AQ4: =SUM(S4:V4) -> 967.169 | AR4: =AQ4*(1+AR14) -> 1005.8558 | AS4: =AR4*(1+AS14) -> 955.56297 | AT4: =AS4*(1+AT14) -> 926.89608 | AU4: =AT4*(1+AU14) -> 954.70297 | AV4: =AU4*(1+AV14) -> 973.79702 | AW4: =AV4*(1+AW14) -> 964.05905 | AX4: =AW4*(1+AX14) -> 944.77787 | AY4: =AX4*(1+AY14) -> 897.53898 | ... BA4: =AZ4*(1+BA14) -> 767.39583
B5: ELEVIDYS | C5: 0 | D5: 0 | E5: 0 | F5: 0 | G5: 0 | H5: 0 | I5: 0 | J5: 0 | K5: 0 | L5: 0 | M5: 0 | N5: 0 | O5: 0 | P5: 0 | Q5: 69.108 | R5: =200.356-SUM(O5:Q5) -> 131.248 | S5: 133.936 | T5: 121.72 | U5: 180.983 | V5: =820.791-SUM(S5:U5) -> 384.152 | W5: 374.895 | X5: 281.851 | Y5: 131.49 | Z5: 145 | AA5: 150 | AB5: 150 | AC5: 150 | AD5: 140 | AM5: =SUM(C5:F5) -> 0 | AN5: =SUM(G5:J5) -> 0 | AO5: =SUM(K5:N5) -> 0 | AP5: =SUM(O5:R5) -> 200.356 | AQ5: =SUM(S5:V5) -> 820.791 | AR5: =AQ5*(1+AR15) -> 861.83055 | AS5: =AR5*(1+AS15) -> 474.0068 | AT5: =AS5*(1+AT15) -> 0
B6: Product Revenues | C6: =SUM(C4:C5) -> 100.448 | D6: =SUM(D4:D5) -> 111.34 | E6: =SUM(E4:E5) -> 121.429 | F6: =SUM(F4:F5) -> 122.648 | G6: =SUM(G4:G5) -> 124.926 | H6: =SUM(H4:H5) -> 141.839 | I6: =SUM(I4:I5) -> 166.911 | J6: =SUM(J4:J5) -> 178.725 | ... AD6: =SUM(AD4:AD5) -> 422 | AM6: =SUM(C6:F6) -> 455.865 | AN6: =SUM(G6:J6) -> 612.401 | AO6: =SUM(K6:N6) -> 843.769 | AP6: =SUM(O6:R6) -> 1144.876 | AQ6: =SUM(S6:V6) -> 1787.96 | AR6: =SUM(AR4:AR5) -> 1867.6863 | AS6: =SUM(AS4:AS5) -> 1429.5698 | AT6: =SUM(AT4:AT5) -> 926.89608 | AU6: =SUM(AU4:AU5) -> 954.70297 | AV6: =SUM(AV4:AV5) -> 973.79702 | AW6: =SUM(AW4:AW5) -> 964.05905 | AX6: =SUM(AX4:AX5) -> 944.77787 | AY6: =SUM(AY4:AY5) -> 897.53898 | ... BA6: =SUM(BA4:BA5) -> 767.39583
B7: Collaboration Revenues | C7: 0 | D7: 0 | E7: 0 | F7: 0 | G7: 0 | H7: 0 | I7: 0 | J7: 0 | K7: 0 | L7: 0 | M7: 0 | N7: 0 | O7: 0 | P7: 0 | Q7: 0 | R7: 0 | S7: 48 | T7: 0 | U7: 0 | V7: =48-SUM(S7:U7) -> 0 | W7: 112 | X7: 63.5 | Y7: 0 | AM7: =SUM(C7:F7) -> 0 | AN7: =SUM(G7:J7) -> 0 | AO7: =SUM(K7:N7) -> 0 | AP7: =SUM(O7:R7) -> 0 | AQ7: =SUM(S7:V7) -> 48
B8: Contract Manufacturing | C8: 0 | D8: 0 | E8: 0 | F8: 0 | G8: 0 | H8: 0 | I8: 0 | J8: 0 | K8: 0 | L8: 0 | M8: 0 | N8: 0 | O8: 0 | P8: 0 | Q8: 0 | R8: =9.216-SUM(O8:Q8) -> 9.216 | S8: 5.8 | T8: 2.38 | U8: 27.89 | V8: =49.038-SUM(S8:U8) -> 12.968 | W8: 17.379 | X8: 27.02 | Y8: 18.7 | AM8: =SUM(C8:F8) -> 0 | AN8: =SUM(G8:J8) -> 0 | AO8: =SUM(K8:N8) -> 0 | AP8: =SUM(O8:R8) -> 9.216 | AQ8: =SUM(S8:V8) -> 49.038
B9: Royalty Revenues | C9: 0 | D9: 0 | E9: 0 | F9: 0 | G9: 0 | H9: 0 | I9: 0 | J9: 0 | K9: 0 | L9: 0 | M9: 0 | N9: 0 | O9: 0 | P9: 0 | Q9: 0 | R9: 0 | S9: 0.173 | T9: 0 | U9: 9.51 | V9: =16.981-SUM(S9:U9) -> 7.298 | W9: 4.05 | X9: 7.445 | Y9: 10.608 | AM9: =SUM(C9:F9) -> 0 | AN9: =SUM(G9:J9) -> 0 | AO9: =SUM(K9:N9) -> 0 | AP9: =SUM(O9:R9) -> 0 | AQ9: =SUM(S9:V9) -> 16.981
B10: Amortization of PO | C10: 13.226 | D10: 26.019 | E10: 22.495 | F10: =84.234-SUM(C10:E10) -> 22.494 | G10: 22.005 | H10: 22.25 | I10: 22.459 | J10: =89.444-SUM(G10:I10) -> 22.73 | K10: 22.005 | L10: 22.3 | M10: 22.5 | N10: =89.244-SUM(K10:M10) -> 22.439 | O10: 22 | P10: 22.25 | Q10: 22.49 | R10: =89.244-SUM(O10:Q10) -> 22.504 | S10: 0 | T10: 0 | U10: 0 | V10: =0-SUM(S10:U10) -> 0 | W10: 0 | X10: 0 | Y10: 0 | AM10: =SUM(C10:F10) -> 84.234 | AN10: =SUM(G10:J10) -> 89.444 | AO10: =SUM(K10:N10) -> 89.244 | AP10: =SUM(O10:R10) -> 89.244 | AQ10: =SUM(S10:V10) -> 0
B11: Collaboration and Other Revenues | C11: =SUM(C7:C10) -> 13.226 | D11: =SUM(D7:D10) -> 26.019 | E11: =SUM(E7:E10) -> 22.495 | F11: =SUM(F7:F10) -> 22.494 | G11: =SUM(G7:G10) -> 22.005 | H11: =SUM(H7:H10) -> 22.25 | I11: =SUM(I7:I10) -> 22.459 | J11: =SUM(J7:J10) -> 22.73 | ... Y11: =SUM(Y7:Y10) -> 29.308 | AM11: =AM10 -> 84.234 | AN11: =AN10 -> 89.444 | AO11: =SUM(K11:N11) -> 89.244 | AP11: =SUM(O11:R11) -> 98.46 | AQ11: =SUM(S11:V11) -> 114.019 | AR11: =AQ11*(1+AR16) -> 279.34655 | AS11: =AR11*(1+AS16) -> 203.92298 | AT11: =AS11*(1+AT16) -> 152.94224 | AU11: =AT11*(1+AU16) -> 145.29512 | AV11: =AU11*(1+AV16) -> 149.65398 | AW11: =AV11*(1+AW16) -> 152.64706 | AX11: =AW11*(1+AX16) -> 154.17353 | AY11: =AX11*(1+AY16) -> 155.71526 | ... BA11: =AZ11*(1+BA16) -> 158.84514
B12: Ttl Revenues | C12: =C6+C11 -> 113.674 | D12: =D11+D6 -> 137.359 | E12: =E6+E11 -> 143.924 | F12: =F6+F11 -> 145.142 | G12: =G6+G11 -> 146.931 | H12: =H6+H11 -> 164.089 | I12: =I6+I11 -> 189.37 | J12: =J6+J11 -> 201.455 | K12: =K6+K11 -> 210.83 | L12: =L6+L11 -> 233.537 | ... Y12: =Y6+Y11 -> 399.343 | Z12: =SUM(Z4:Z5) -> 415 | AA12: =SUM(AA4:AA5) -> 425 | AB12: =SUM(AB4:AB5) -> 428 | AC12: =SUM(AC4:AC5) -> 430 | AD12: =SUM(AD4:AD5) -> 422 | AM12: =SUM(C12:F12) -> 540.099 | AN12: =SUM(G12:J12) -> 701.845 | AO12: =SUM(K12:N12) -> 933.013 | AP12: =SUM(O12:R12) -> 1243.336 | AQ12: =SUM(S12:V12) -> 1901.979 | AR12: =AR6+AR11 -> 2147.0329 | AS12: =SUM(AS4:AS5) -> 1429.5698 | AT12: =SUM(AT4:AT5) -> 926.89608 | AU12: =SUM(AU4:AU5) -> 954.70297 | AV12: =SUM(AV4:AV5) -> 973.79702 | AW12: =SUM(AW4:AW5) -> 964.05905 | AX12: =SUM(AX4:AX5) -> 944.77787 | AY12: =SUM(AY4:AY5) -> 897.53898 | AZ12: =SUM(AZ4:AZ5) -> 852.66203 | BA12: =SUM(BA4:BA5) -> 767.39583
B14: PMO Products Growth Y/y | G14: =G4/C4-1 -> 0.24368828 | H14: =H4/D4-1 -> 0.27392671 | I14: =I4/E4-1 -> 0.37455633 | J14: =J4/F4-1 -> 0.45721903 | K14: =K4/G4-1 -> 0.5114948 | L14: =L4/H4-1 -> 0.48927305 | M14: =M4/I4-1 -> 0.2448191 | N14: =N4/J4-1 -> 0.32008952 | ... X14: =X4/T4-1 -> -0.031633777 | Y14: 0.04 | Z14: =Z4/V4-1 -> 0.062967017 | AA14: =AA4/W4-1 -> 0.16260389 | AB14: =AB4/X4-1 -> 0.20204781 | AC14: =AC4/Y4-1 -> 0.17378272 | AD14: =AD4/Z4-1 -> 0.044444444 | AN14: =AN4/AM4-1 -> 0.34338236 | AO14: =AO4/AN4-1 -> 0.37780474 | AP14: =AP4/AO4-1 -> 0.1194059 | AQ14: =AQ4/AP4-1 -> 0.023979376 | AR14: 0.04 | AS14: -0.05 | AT14: -0.03 | AU14: 0.03 | AV14: 0.02 | AW14: -0.01 | AX14: -0.02 | AY14: -0.05 | AZ14: -0.05 | BA14: -0.1
B15: ELEVIDYS Growth Y/y | U15: =U5/Q5-1 -> 1.618843 | V15: =V5/R5-1 -> 1.926917 | W15: =W5/S5-1 -> 1.7990607 | X15: =X5/T5-1 -> 1.3155685 | Y15: 0.48 | Z15: =Z5/V5-1 -> -0.62254524 | AA15: =AA5/W5-1 -> -0.59988797 | AB15: =AB5/X5-1 -> -0.46780391 | AC15: =AC5/Y5-1 -> 0.14077116 | AD15: =AD5/Z5-1 -> -0.034482759 | AQ15: =AQ5/AP5-1 -> 3.0966629 | AR15: 0.05 | AS15: -0.45 | AT15: -1 | AU15: 0 | AV15: 0 | AW15: 0 | AX15: 0 | AY15: 0 | AZ15: 0 | BA15: 0
B16: Other Growth Y/y | G16: =G11/C11-1 -> 0.66376834 | H16: =H11/D11-1 -> -0.14485568 | I16: =I11/E11-1 -> -0.0016003556 | J16: =J11/F11-1 -> 0.010491687 | K16: =K11/G11-1 -> 0 | L16: =L11/H11-1 -> 0.002247191 | M16: =M11/I11-1 -> 0.0018255488 | N16: =N11/J11-1 -> -0.012802464 | ... X16: =X11/T11-1 -> 40.161765 | Y16: 1.15 | AN16: =AN12/AM12-1 -> 0.29947473 | AO16: =AO12/AN12-1 -> 0.32937187 | AP16: =AP12/AO12-1 -> 0.33260308 | AQ16: =AQ12/AP12-1 -> 0.52973854 | AR16: 1.45 | AS16: -0.27 | AT16: -0.25 | AU16: -0.05 | AV16: 0.03 | AW16: 0.02 | AX16: 0.01 | AY16: 0.01 | AZ16: 0.01 | BA16: 0.01
B17: Ttl Revenue Growth Y/y | G17: =G6/C6-1 -> 0.24368828 | H17: =H6/D6-1 -> 0.27392671 | I17: =I6/E6-1 -> 0.37455633 | J17: =J6/F6-1 -> 0.45721903 | K17: =K6/G6-1 -> 0.5114948 | L17: =L6/H6-1 -> 0.48927305 | M17: =M6/I6-1 -> 0.2448191 | N17: =N6/J6-1 -> 0.32008952 | ... Y17: =Y6/U6-1 -> -0.13899495 | Z17: =Z12/V12-1 -> -0.36970706 | AA17: =AA12/W12-1 -> -0.42942451 | AB17: =AB12/X12-1 -> -0.29960988 | AC17: =AC12/Y12-1 -> 0.076768592 | AD17: =AD12/Z12-1 -> 0.01686747
B19: PMO % of Ttl Revenues | C19: =C4/C12 -> 0.88364974 | D19: =D4/D12 -> 0.81057666 | E19: =E4/E12 -> 0.84370223 | F19: =F4/F12 -> 0.84502074 | G19: =G4/G12 -> 0.85023582 | H19: =H4/H12 -> 0.86440285 | I19: =I4/I12 -> 0.88140149 | J19: =J4/J12 -> 0.88717083 | ... AD19: =AD4/AD12 -> 0.66824645 | AM19: =AM4/AM12 -> 0.8440397 | AN19: =AN4/AN12 -> 0.87255876 | AO19: =AO4/AO12 -> 0.9043486 | AP19: =AP4/AP12 -> 0.75966593 | AQ19: =AQ4/AQ12 -> 0.50850667 | AR19: =AR4/AR12 -> 0.46848643 | AS19: =AS4/AS12 -> 0.66842696 | AT19: =AT4/AT12 -> 1 | ... BA19: =BA4/BA12 -> 1
B20: ELEVIDYS % of Ttl Revenues | Q20: =Q5/Q12 -> 0.20827708 | R20: =R5/R12 -> 0.3307703 | S20: =S5/S12 -> 0.32394179 | T20: =T5/T12 -> 0.33538425 | U20: =U5/U12 -> 0.38740204 | V20: =V5/V12 -> 0.58344167 | W20: =W5/W12 -> 0.503308 | X20: =X5/X12 -> 0.46122817 | ... AD20: =AD5/AD12 -> 0.33175355 | AM20: =AM5/AM12 -> 0 | AN20: =AN5/AN12 -> 0 | AO20: =AO5/AO12 -> 0 | AP20: =AP5/AP12 -> 0.16114389 | AQ20: =AQ5/AQ12 -> 0.43154577 | AR20: =AR5/AR12 -> 0.40140538 | AS20: =AS5/AS12 -> 0.33157304 | AT20: =AT5/AT12 -> 0 | ... BA20: =BA5/BA12 -> 0
B21: Other % of Ttl Revenues | C21: =C11/C12 -> 0.11635026 | D21: =D11/D12 -> 0.18942334 | E21: =E11/E12 -> 0.15629777 | F21: =F11/F12 -> 0.15497926 | G21: =G11/G12 -> 0.14976418 | H21: =H11/H12 -> 0.13559715 | I21: =I11/I12 -> 0.11859851 | J21: =J11/J12 -> 0.11282917 | ... Y21: =Y11/Y12 -> 0.073390544
B23: Revenues | C23: =C12 -> 113.674 | D23: =D12 -> 137.359 | E23: =E12 -> 143.924 | F23: =F12 -> 145.142 | G23: =G12 -> 146.931 | H23: =H12 -> 164.089 | I23: =I12 -> 189.37 | J23: =J12 -> 201.455 | ... Y23: =Y12 -> 399.343 | AM23: =SUM(C23:F23) -> 540.099 | AN23: =SUM(G23:J23) -> 701.845 | AO23: =SUM(K23:N23) -> 933.013 | AP23: =SUM(O23:R23) -> 1243.336 | AQ23: =SUM(S23:V23) -> 1901.979 | AR23: =AR12 -> 2147.0329 | AS23: =AS12 -> 1429.5698 | AT23: =AT12 -> 926.89608 | AU23: =AU12 -> 954.70297 | AV23: =AV12 -> 973.79702 | AW23: =AW12 -> 964.05905 | AX23: =AX12 -> 944.77787 | AY23: =AY12 -> 897.53898 | ... BA23: =BA12 -> 767.39583
B24: COGS | C24: 12.622 | D24: 13.341 | E24: 15.015 | F24: =63.382-SUM(C24:E24) -> 22.404 | G24: 22.346 | H24: 19.515 | I24: 23.44 | J24: =97.049-SUM(G24:I24) -> 31.748 | K24: 31.443 | L24: 37.795 | M24: 39.952 | N24: =139.989-SUM(K24:M24) -> 30.799 | O24: 35.017 | P24: 34.124 | Q24: 37.026 | R24: =150.343-SUM(O24:Q24) -> 44.176 | S24: 50.559 | T24: 44.54 | U24: 91.691 | V24: =319.099-SUM(S24:U24) -> 132.309 | W24: 137.56 | X24: 152.558 | Y24: 150.775 | AM24: =SUM(C24:F24) -> 63.382 | AN24: =SUM(G24:J24) -> 97.049 | AO24: =SUM(K24:N24) -> 139.989 | AP24: =SUM(O24:R24) -> 150.343 | AQ24: =SUM(S24:V24) -> 319.099 | AR24: =AR23*(1-AR39) -> 343.52526 | AS24: =AS23*(1-AS39) -> 228.73116 | AT24: =AT23*(1-AT39) -> 148.30337 | AU24: =AU23*(1-AU39) -> 152.75247 | AV24: =AV23*(1-AV39) -> 155.80752 | AW24: =AW23*(1-AW39) -> 154.24945 | AX24: =AX23*(1-AX39) -> 151.16446 | AY24: =AY23*(1-AY39) -> 143.60624 | ... BA24: =BA23*(1-BA39) -> 122.78333
B25: GP | C25: =C23-C24 -> 101.052 | D25: =D23-D24 -> 124.018 | E25: =E23-E24 -> 128.909 | F25: =F23-F24 -> 122.738 | G25: =G23-G24 -> 124.585 | H25: =H23-H24 -> 144.574 | I25: =I23-I24 -> 165.93 | J25: =J23-J24 -> 169.707 | ... Y25: =Y23-Y24 -> 248.568 | AM25: =SUM(C25:F25) -> 476.717 | AN25: =SUM(G25:J25) -> 604.796 | AO25: =SUM(K25:N25) -> 793.024 | AP25: =SUM(O25:R25) -> 1092.993 | AQ25: =SUM(S25:V25) -> 1582.88 | AR25: =AR23-AR24 -> 1803.5076 | AS25: =AS23-AS24 -> 1200.8386 | AT25: =AT23-AT24 -> 778.59271 | AU25: =AU23-AU24 -> 801.95049 | AV25: =AV23-AV24 -> 817.9895 | AW25: =AW23-AW24 -> 809.80961 | AX25: =AX23-AX24 -> 793.61341 | AY25: =AY23-AY24 -> 753.93274 | ... BA25: =BA23-BA24 -> 644.6125
B26: R&D | C26: 136.144 | D26: 188.522 | E26: 190.438 | F26: =722.343-SUM(C26:E26) -> 207.239 | G26: 195.149 | H26: 239.622 | I26: 139.115 | J26: =771.182-SUM(G26:I26) -> 197.296 | K26: 194.25 | L26: 252.329 | M26: 216.7 | N26: =877.09-SUM(K26:M26) -> 213.811 | O26: 245.679 | P26: 241.89 | Q26: 194.301 | R26: =877.387-SUM(O26:Q26) -> 195.517 | S26: 200.396 | T26: 179.69 | U26: 224.483 | V26: =804.522-SUM(S26:U26) -> 199.953 | W26: 773.448 | X26: 204.392 | Y26: 218.89 | AM26: =SUM(C26:F26) -> 722.343 | AN26: =SUM(G26:J26) -> 771.182 | AO26: =SUM(K26:N26) -> 877.09 | AP26: =SUM(O26:R26) -> 877.387 | AQ26: =SUM(S26:V26) -> 804.522 | AR26: =AR23*AR40 -> 1642.4801 | AS26: =AS23*AS40 -> 786.26338 | AT26: =AT23*AT40 -> 370.75843 | AU26: =AU23*AU40 -> 334.14604 | AV26: =AV23*AV40 -> 438.20866 | AW26: =AW23*AW40 -> 409.7251 | AX26: =AX23*AX40 -> 377.91115 | AY26: =AY23*AY40 -> 336.57712 | ... BA26: =BA23*BA40 -> 268.58854
B27: SG&A | C27: 82.768 | D27: 73.688 | E27: 75.373 | F27: =317.875-SUM(C27:E27) -> 86.046 | G27: 71.131 | H27: 72.347 | I27: 61.127 | J27: =282.66-SUM(G27:I27) -> 78.055 | K27: 71.84 | L27: 154.316 | M27: 104.787 | N27: =451.421-SUM(K27:M27) -> 120.478 | O27: 110.714 | P27: 118.56 | Q27: 120.893 | R27: =481.871-SUM(O27:Q27) -> 131.704 | S27: 127.003 | T27: 138.796 | U27: 128.2 | V27: =557.87-SUM(S27:U27) -> 163.871 | W27: 133.629 | X27: 137.897 | Y27: 91.89 | AM27: =SUM(C27:F27) -> 317.875 | AN27: =SUM(G27:J27) -> 282.66 | AO27: =SUM(K27:N27) -> 451.421 | AP27: =SUM(O27:R27) -> 481.871 | AQ27: =SUM(S27:V27) -> 557.87 | AR27: =AR23*AR41 -> 558.22854 | AS27: =AS23*AS41 -> 364.54029 | AT27: =AT23*AT41 -> 231.72402 | AU27: =AU23*AU41 -> 233.90223 | AV27: =AV23*AV41 -> 233.71129 | AW27: =AW23*AW41 -> 221.73358 | AX27: =AX23*AX41 -> 207.85113 | AY27: =AY23*AY41 -> 188.48319 | ... BA27: =BA23*BA41 -> 157.31614
B28: Settlement and Liscence | C28: 0 | D28: 0 | E28: 0 | F28: =0-SUM(C28:E28) -> 0 | G28: 10 | H28: 0 | I28: 0 | J28: =10-SUM(G28:I28) -> 0 | K28: 0 | L28: 0 | M28: 0 | N28: =0-SUM(K28:M28) -> 0 | O28: 0 | P28: 0 | Q28: =0-SUM(N28:P28) -> 0 | R28: =0-SUM(O28:Q28) -> 0 | S28: =0-SUM(P28:R28) -> 0 | T28: =0-SUM(Q28:S28) -> 0 | U28: 0 | V28: 0 | W28: 0 | X28: 0 | Y28: 40.51 | AM28: =SUM(C28:F28) -> 0 | AN28: =SUM(G28:J28) -> 10 | AO28: =SUM(K28:N28) -> 0 | AP28: =SUM(O28:R28) -> 0 | AQ28: =SUM(S28:V28) -> 0 | AR28: 0 | AS28: 0 | AT28: 0 | AU28: 0 | AV28: 0 | AW28: 0 | AX28: 0 | AY28: 0 | AZ28: 0 | BA28: 0
B29: Amortization of In-Liscensed Rights | C29: 0.166 | D29: 0.165 | E29: 0.166 | F29: =0.662-SUM(C29:E29) -> 0.165 | G29: 0.17 | H29: 0.179 | I29: 0.178 | J29: =0.706-SUM(G29:I29) -> 0.179 | K29: 0.178 | L29: 0.179 | M29: 0.178 | N29: =0.71-SUM(K29:M29) -> 0.175 | O29: 0.178 | P29: 0.179 | Q29: 0.439 | R29: =1.559-SUM(O29:Q29) -> 0.763 | S29: 0.601 | T29: 0.601 | U29: 0.6 | V29: =2.405-SUM(S29:U29) -> 0.603 | W29: 0.6 | X29: 0.667 | Y29: 0.677 | AM29: =SUM(C29:F29) -> 0.662 | AN29: =SUM(G29:J29) -> 0.706 | AO29: =SUM(K29:N29) -> 0.71 | AP29: =SUM(O29:R29) -> 1.559 | AQ29: =SUM(S29:V29) -> 2.405 | AR29: =AQ29*1 -> 2.405 | AS29: =AR29*1.05 -> 2.52525 | AT29: =AS29*1.05 -> 2.6515125 | AU29: =AT29*1.05 -> 2.7840881 | AV29: =AU29*1.05 -> 2.9232925 | AW29: =AV29*1.05 -> 3.0694572 | AX29: =AW29*1.05 -> 3.22293 | AY29: =AX29*1.05 -> 3.3840765 | AZ29: =AY29*1.05 -> 3.5532803 | BA29: =AZ29*1.05 -> 3.7309444
B30: Operating Income | C30: =C25-SUM(C26:C29) -> -118.026 | D30: =D25-SUM(D26:D29) -> -138.357 | E30: =E25-SUM(E26:E29) -> -137.068 | F30: =F25-SUM(F26:F29) -> -170.712 | G30: =G25-SUM(G26:G29) -> -151.865 | H30: =H25-SUM(H26:H29) -> -167.574 | I30: =I25-SUM(I26:I29) -> -34.49 | J30: =J25-SUM(J26:J29) -> -105.823 | ... Y30: =Y25-SUM(Y26:Y29) -> -103.399 | AM30: =SUM(C30:F30) -> -564.163 | AN30: =SUM(G30:J30) -> -459.752 | AO30: =SUM(K30:N30) -> -536.197 | AP30: =SUM(O30:R30) -> -267.824 | AQ30: =SUM(S30:V30) -> 218.083 | AR30: =AR25-SUM(AR26:AR29) -> -399.60608 | AS30: =AS25-SUM(AS26:AS29) -> 47.509692 | AT30: =AT25-SUM(AT26:AT29) -> 173.45874 | AU30: =AU25-SUM(AU26:AU29) -> 231.11814 | AV30: =AV25-SUM(AV26:AV29) -> 143.14626 | AW30: =AW25-SUM(AW26:AW29) -> 175.28147 | AX30: =AX25-SUM(AX26:AX29) -> 204.6282 | AY30: =AY25-SUM(AY26:AY29) -> 225.48836 | ... BA30: =BA25-SUM(BA26:BA29) -> 214.97687
B31: Other Income (Expenses) | C31: -7.42 | D31: 0 | E31: -45 | F31: =-51.971-SUM(C31:E31) -> 0.449 | G31: -15.528 | H31: 102 | I31: -20.649 | J31: =-68.43-SUM(G31:I31) -> -134.253 | K31: -17.26 | L31: 0 | M31: =6.7-125.44 -> -118.74 | N31: =-125.441+6.7-SUM(K31:M31) -> 17.259 | O31: 12.7 | P31: 16.934 | Q31: -12.33 | R31: =33.055-SUM(O31:Q31) -> 15.751 | S31: 6.54 | T31: 14.278 | U31: 11.81 | V31: =42.693-SUM(S31:U31) -> 10.065 | W31: -83.132 | X31: 38.06 | Y31: -138.61 | AM31: =SUM(C31:F31) -> -51.971 | AN31: =SUM(G31:J31) -> -68.43 | AO31: =SUM(K31:N31) -> -118.741 | AP31: =SUM(O31:R31) -> 33.055 | AQ31: =SUM(S31:V31) -> 42.693 | AR31: -35 | AS31: =AR46*($BA$48) -> 25.171575 | AT31: =AS31*1.04 -> 26.178438 | AU31: =AT31*1.04 -> 27.225575 | AV31: =AU31*1.04 -> 28.314598 | AW31: =AV31*1.04 -> 29.447182 | AX31: =AW31*1.04 -> 30.62507 | AY31: =AX31*1.04 -> 31.850073 | AZ31: =AY31*1.04 -> 33.124075 | BA31: =AZ31*1.04 -> 34.449038
B32: Gain on, Income | C32: 108.069 | D32: -12.447 | E32: -14.335 | F32: =108.1-45-SUM(C32:E32) -> -18.187 | G32: 0 | H32: -16.185 | I32: 7.2 | J32: =102+7.2-SUM(G32:I32) -> 118.185 | K32: 0 | L32: -16.961 | M32: -6.33 | N32: =-35.021-SUM(K32:M32) -> -11.73 | O32: -387.32 | P32: 102 | Q32: 0 | R32: =-387.329+102-SUM(O32:Q32) -> -0.009 | S32: 0 | T32: 0 | U32: 0 | V32: =0-SUM(S32:U32) -> 0 | W32: 0 | X32: 0 | Y32: 47.95 | AM32: =SUM(C32:F32) -> 63.1 | AN32: =SUM(G32:J32) -> 109.2 | AO32: =SUM(K32:N32) -> -35.021 | AP32: =SUM(O32:R32) -> -285.329 | AQ32: =SUM(S32:V32) -> 0 | AR32: 0 | AS32: 0 | AT32: 0 | AU32: 0 | AV32: 0 | AW32: 0 | AX32: 0 | AY32: 0 | AZ32: 0 | BA32: 0
B33: Pretax Income | C33: =C30+SUM(C31:C32) -> -17.377 | D33: =D30+SUM(D31:D32) -> -150.804 | E33: =E30+SUM(E31:E32) -> -196.403 | F33: =F30+SUM(F31:F32) -> -188.45 | G33: =G30+SUM(G31:G32) -> -167.393 | H33: =H30+SUM(H31:H32) -> -81.759 | I33: =I30+SUM(I31:I32) -> -47.939 | J33: =J30+SUM(J31:J32) -> -121.891 | ... Y33: =Y30+SUM(Y31:Y32) -> -194.059 | AM33: =SUM(C33:F33) -> -553.034 | AN33: =SUM(G33:J33) -> -418.982 | AO33: =SUM(K33:N33) -> -689.959 | AP33: =SUM(O33:R33) -> -520.098 | AQ33: =SUM(S33:V33) -> 260.776 | AR33: =AR30+SUM(AR31:AR32) -> -434.60608 | AS33: =AS30+SUM(AS31:AS32) -> 72.681267 | AT33: =AT30+SUM(AT31:AT32) -> 199.63718 | AU33: =AU30+SUM(AU31:AU32) -> 258.34371 | AV33: =AV30+SUM(AV31:AV32) -> 171.46086 | AW33: =AW30+SUM(AW31:AW32) -> 204.72865 | AX33: =AX30+SUM(AX31:AX32) -> 235.25327 | AY33: =AY30+SUM(AY31:AY32) -> 257.33844 | ... BA33: =BA30+SUM(BA31:BA32) -> 249.4259
B34: Taxes | C34: 0.115 | D34: 0.2 | E34: 0.096 | F34: =1.063-SUM(C34:E34) -> 0.652 | G34: -0.143 | H34: -0.35 | I34: 0.237 | J34: =-0.168-SUM(G34:I34) -> 0.088 | K34: 0.879 | L34: 3.388 | M34: 1.32 | N34: =13.525-SUM(K34:M34) -> 7.938 | O34: 4.045 | P34: 9.355 | Q34: 7.763 | R34: =15.879-SUM(O34:Q34) -> -5.284 | S34: 5.329 | T34: 7.117 | U34: 0.395 | V34: =25.535-SUM(S34:U34) -> 12.694 | W34: 63.99 | X34: -43.25 | Y34: -14.1 | AM34: =SUM(C34:F34) -> 1.063 | AN34: =SUM(G34:J34) -> -0.168 | AO34: =SUM(K34:N34) -> 13.525 | AP34: =SUM(O34:R34) -> 15.879 | AQ34: =SUM(S34:V34) -> 25.535 | AR34: =AR33*AR43 -> 39.114547 | AS34: =AS33*AS43 -> -8.721752 | AT34: =AT33*AT43 -> 41.923808 | AU34: =AU33*AU43 -> 54.25218 | AV34: =AV33*AV43 -> 36.006781 | AW34: =AW33*AW43 -> 42.993017 | AX34: =AX33*AX43 -> 49.403187 | AY34: =AY33*AY43 -> 54.041072 | ... BA34: =BA33*BA43 -> 52.37944
B35: Net Income | C35: =C33-C34 -> -17.492 | D35: =D33-D34 -> -151.004 | E35: =E33-E34 -> -196.499 | F35: =F33-F34 -> -189.102 | G35: =G33-G34 -> -167.25 | H35: =H33-H34 -> -81.409 | I35: =I33-I34 -> -48.176 | J35: =J33-J34 -> -121.979 | K35: =K33-K34 -> -105.02 | L35: =L33-L34+-2.2 -> -233.631 | M35: =M33-M34-0.72 -> -258.453 | N35: =N33-N34 -> -109.3 | O35: =O33-O34 -> -516.758 | P35: =P33-P34 -> -23.936 | Q35: =Q33-Q34 -> -40.944 | R35: =R33-R34 -> 45.661 | S35: =S33-S34-1.6 -> 34.509 | T35: =T33-T34 -> 6.461 | U35: =U33-U34 -> 33.612 | V35: =V33-V34 -> 159.059 | W35: =W33-W34 -> -447.497 | X35: =X33-X34 -> 196.884 | Y35: =Y33-Y34 -> -179.959 | AM35: =SUM(C35:F35) -> -554.097 | AN35: =SUM(G35:J35) -> -418.814 | AO35: =SUM(K35:N35) -> -706.404 | AP35: =SUM(O35:R35) -> -535.977 | AQ35: =SUM(S35:V35) -> 233.641 | AR35: =AR33-AR34 -> -473.72063 | AS35: =AS33-AS34 -> 81.403019 | AT35: =AT33-AT34 -> 157.71337 | AU35: =AU33-AU34 -> 204.09153 | AV35: =AV33-AV34 -> 135.45408 | AW35: =AW33-AW34 -> 161.73563 | AX35: =AX33-AX34 -> 185.85008 | AY35: =AY33-AY34 -> 203.29736 | ... BA35: =BA33-BA34 -> 197.04646 | BB35: =BA35*(1+$BA$49) -> 173.40089 | BC35: =BB35*(1+$BA$49) -> 152.59278 | BD35: =BC35*(1+$BA$49) -> 134.28165 | BE35: =BD35*(1+$BA$49) -> 118.16785
B36: SC | C36: 76.432 | D36: 77.968 | E36: 78.501 | F36: 77.77 | G36: 79.454 | H36: 79.746 | I36: 79.88 | J36: 87.12 | K36: 87.253 | L36: 87.511 | M36: 87.62 | N36: 87.981 | O36: 88.186 | P36: 88.743 | Q36: 88.889 | R36: 92.398 | S36: 93.99 | T36: 94.618 | U36: 95.39 | V36: 97.032 | W36: 97.362 | X36: 98.005 | Y36: 100.23 | AM36: =AVERAGE(C36:F36) -> 77.66775 | AN36: =AVERAGE(G36:J36) -> 81.55 | AO36: =AVERAGE(K36:N36) -> 87.59125 | AP36: =AVERAGE(O36:R36) -> 89.554 | AQ36: =AVERAGE(S36:V36) -> 95.2575
B37: EPS | C37: =C35/C36 -> -0.22885702 | D37: =D35/D36 -> -1.9367433 | E37: =E35/E36 -> -2.5031401 | F37: =F35/F36 -> -2.4315546 | G37: =G35/G36 -> -2.1049916 | H37: =H35/H36 -> -1.0208537 | I37: =I35/I36 -> -0.60310466 | J37: =(J35/J36) -> -1.4001263 | K37: =K35/K36 -> -1.2036262 | L37: =L35/L36 -> -2.6697329 | M37: =M35/M36 -> -2.9497033 | N37: =N35/N36 -> -1.2423137 | O37: =O35/O36 -> -5.8598644 | P37: =P35/P36 -> -0.26972268 | Q37: =Q35/Q36 -> -0.46061942 | R37: =R35/R36 -> 0.49417736 | ... Y37: =Y35/Y36 -> -1.7954604 | AM37: =SUM(C37:F37) -> -7.100295 | AN37: =SUM(G37:J37) -> -5.1290762 | AO37: =SUM(K37:N37) -> -8.0653761 | AP37: =SUM(O37:R37) -> -6.0960291 | AQ37: =SUM(S37:V37) -> 2.4270479
B39: Gross Profit Margin | C39: =C25/C23 -> 0.88896318 | D39: =D25/D23 -> 0.90287495 | E39: =E25/E23 -> 0.89567411 | F39: =F25/F23 -> 0.84564082 | G39: =G25/G23 -> 0.84791501 | H39: =H25/H23 -> 0.88107064 | I39: =I25/I23 -> 0.87622115 | J39: =J25/J23 -> 0.84240649 | ... Y39: =Y25/Y23 -> 0.62244236 | AM39: =AM25/AM23 -> 0.88264744 | AN39: =AN25/AN23 -> 0.86172303 | AO39: =AO25/AO23 -> 0.84996029 | AP39: =AP25/AP23 -> 0.87908096 | AQ39: =AQ25/AQ23 -> 0.83222791 | AR39: 0.84 | AS39: 0.84 | AT39: 0.84 | AU39: 0.84 | AV39: 0.84 | AW39: 0.84 | AX39: 0.84 | AY39: 0.84 | AZ39: 0.84 | BA39: 0.84
B40: R&D as % of Revenue | C40: =C26/C23 -> 1.1976705 | D40: =D26/D23 -> 1.3724765 | E40: =E26/E23 -> 1.3231845 | F40: =F26/F23 -> 1.4278362 | G40: =G26/G23 -> 1.3281676 | H40: =H26/H23 -> 1.4603173 | I40: =I26/I23 -> 0.73462006 | J40: =J26/J23 -> 0.97935519 | ... Y40: =Y26/Y23 -> 0.5481253 | AM40: =AM26/AM23 -> 1.337427 | AN40: =AN26/AN23 -> 1.0987925 | AO40: =AO26/AO23 -> 0.94006193 | AP40: =AP26/AP23 -> 0.70567168 | AQ40: =AQ26/AQ23 -> 0.42299205 | AR40: 0.765 | AS40: 0.55 | AT40: 0.4 | AU40: 0.35 | AV40: 0.45 | AW40: 0.425 | AX40: 0.4 | AY40: 0.375 | AZ40: 0.35 | BA40: 0.35
B41: SG&A as % of Revenue | C41: =C27/C23 -> 0.72811725 | D41: =D27/D23 -> 0.53646285 | E41: =E27/E23 -> 0.52370001 | F41: =F27/F23 -> 0.59284012 | G41: =G27/G23 -> 0.48411159 | H41: =H27/H23 -> 0.44090097 | I41: =I27/I23 -> 0.32279136 | J41: =J27/J23 -> 0.38745626 | ... Y41: =Y27/Y23 -> 0.23010294 | AM41: =AM27/AM23 -> 0.58854951 | AN41: =AN27/AN23 -> 0.4027385 | AO41: =AO27/AO23 -> 0.48383141 | AP41: =AP27/AP23 -> 0.38756298 | AQ41: =AQ27/AQ23 -> 0.29331028 | AR41: 0.26 | AS41: 0.255 | AT41: 0.25 | AU41: 0.245 | AV41: 0.24 | AW41: 0.23 | AX41: 0.22 | AY41: 0.21 | AZ41: 0.2075 | BA41: 0.205
B42: Operating Profit Margin | C42: =C30/C23 -> -1.0382849 | D42: =D30/D23 -> -1.0072656 | E42: =E30/E23 -> -0.95236375 | F42: =F30/F23 -> -1.1761723 | G42: =G30/G23 -> -1.0335804 | H42: =H30/H23 -> -1.0212385 | I42: =I30/I23 -> -0.18213022 | J42: =J30/J23 -> -0.52529349 | ... Y42: =Y30/Y23 -> -0.25892278 | AM42: =AM30/AM23 -> -1.0445548 | AN42: =AN30/AN23 -> -0.65506202 | AO42: =AO30/AO23 -> -0.57469403 | AP42: =AP30/AP23 -> -0.21540758 | AQ42: =AQ30/AQ23 -> 0.1146611 | AR42: =AR30/AR23 -> -0.18612015 | AS42: =AS30/AS23 -> 0.033233559 | AT42: =AT30/AT23 -> 0.18713936 | ... BA42: =BA30/BA23 -> 0.28013817
B43: Effective Tax Rate | C43: =-C34/C33 -> 0.0066179433 | D43: =-D34/D33 -> 0.0013262248 | E43: =-E34/E33 -> 0.0004887909 | F43: =-F34/F33 -> 0.0034598037 | G43: =-G34/G33 -> -0.00085427706 | H43: =-H34/H33 -> -0.0042808743 | I43: =-I34/I33 -> 0.0049437827 | J43: =-J34/J33 -> 0.0007219565 | ... Q43: =-Q34/Q33 -> 0.23395919 | R43: =R34/R33 -> -0.13086658 | S43: =S34/S33 -> 0.12860177 | T43: =T34/T33 -> 0.52415672 | U43: =U34/U33 -> 0.011615256 | V43: =V34/V33 -> 0.073908462 | W43: =-W34/W33 -> 0.16685484 | X43: =X34/X33 -> -0.28151321 | Y43: =Y34/Y33 -> 0.072658315 | AM43: =-AM34/AM33 -> 0.0019221241 | AN43: =-AN34/AN33 -> -0.00040097188 | AO43: =-AO34/AO33 -> 0.019602614 | AP43: =-AP34/AP33 -> 0.030530785 | AQ43: =-AQ34/AQ33 -> -0.097919287 | AR43: -0.09 | AS43: -0.12 | AT43: 0.21 | AU43: 0.21 | AV43: 0.21 | AW43: 0.21 | AX43: 0.21 | AY43: 0.21 | AZ43: 0.21 | BA43: 0.21
B44: Net Profit Margin | C44: =C35/C23 -> -0.15387864 | D44: =D35/D23 -> -1.0993382 | E44: =E35/E23 -> -1.365297 | F44: =F35/F23 -> -1.3028758 | G44: =G35/G23 -> -1.1382894 | H44: =H35/H23 -> -0.4961271 | I44: =I35/I23 -> -0.25440144 | J44: =J35/J23 -> -0.60549006 | ... Y44: =Y35/Y23 -> -0.45063767 | AM44: =AM35/AM23 -> -1.0259175 | AN44: =AN35/AN23 -> -0.5967329 | AO44: =AO35/AO23 -> -0.75712128 | AP44: =AP35/AP23 -> -0.43107977 | AQ44: =AQ35/AQ23 -> 0.122841 | AR44: =AR35/AR23 -> -0.22063967 | AS44: =AS35/AS23 -> 0.05694232 | AT44: =AT35/AT23 -> 0.17015216 | ... BA44: =BA35/BA23 -> 0.25677292
B46: Cash & CEs | F46: 1502.64 | G46: 1481.83 | H46: 1697.27 | I46: 1599.113 | J46: 2115.869 | K46: 1233.877 | L46: 868.565 | M46: 1038.62 | N46: 966.77 | O46: 871.668 | P46: 851.929 | Q46: 541.932 | R46: 428.43 | S46: 427.29 | T46: 383.622 | U46: 197.855 | V46: 1103.01 | W46: 240.867 | X46: 510.598 | Y46: 613.07 | AM46: =F46 -> 1502.64 | AN46: =J46 -> 2115.869 | AO46: =N46 -> 966.77 | AP46: =R46 -> 428.43 | AQ46: =V46 -> 1103.01 | AR46: =AR35+AQ46 -> 629.28937 | AS46: =AS35+AR46 -> 710.69239 | AT46: =AT35+AS46 -> 868.40577 | AU46: =AU35+AT46 -> 1072.4973 | AV46: =AV35+AU46 -> 1207.9514 | AW46: =AW35+AV46 -> 1369.687 | AX46: =AX35+AW46 -> 1555.5371 | AY46: =AY35+AX46 -> 1758.8345 | ... BA46: =BA35+AZ46 -> 2169.5347
B47: ST Investments | F47: 435.923 | G47: 255.997 | H47: 30 | I47: 0 | J47: 0 | K47: 779.548 | L47: 1059.454 | M47: 1033.86 | N47: 1022.597 | O47: 1010.42 | P47: 1008.786 | Q47: 1191.61 | R47: 1247.82 | S47: 963.453 | T47: 1076.85 | U47: 1000.534 | V47: 251.782 | W47: 281.895 | X47: 289.541 | Y47: 237.916 | AM47: =F47 -> 435.923 | AN47: =J47 -> 0 | AO47: =N47 -> 1022.597 | AP47: =R47 -> 1247.82 | AQ47: =V47 -> 251.782
B48: A/R | F48: 101.34 | G48: 118.203 | H48: 127.52 | I48: 149.787 | J48: 152.99 | K48: 178.194 | L48: 203.854 | M48: 201.509 | N48: 214.628 | O48: 223.836 | P48: 236.808 | Q48: 318.855 | R48: 400.32 | S48: 378.806 | T48: 359.997 | U48: 434.524 | V48: 601.988 | W48: 659.371 | X48: 527.295 | Y48: 395.73 | AM48: =F48 -> 101.34 | AN48: =J48 -> 152.99 | AO48: =N48 -> 214.628 | AP48: =R48 -> 400.32 | AQ48: =V48 -> 601.988 | AS48: Projected ROIC: | AV48: Invested Capital | AX48: AVG Invested Capital | AZ48: ROIC | BA48: 0.04
B49: Inventories | F49: 231.961 | G49: 240.333 | H49: 268.756 | I49: 288.469 | J49: 186.212 | K49: 198.997 | L49: 208.095 | M49: 221.192 | N49: 203.968 | O49: 202.67 | P49: 226.876 | Q49: 244.011 | R49: 322.85 | S49: 373.53 | T49: 485.795 | U49: 565.924 | V49: 749.96 | W49: 941.432 | X49: 994 | Y49: 1077.16 | AM49: =F49 -> 231.961 | AN49: =J49 -> 186.212 | AO49: =N49 -> 203.968 | AP49: =R49 -> 322.85 | AQ49: =V49 -> 749.96 | AS49: 2025 | AU49: 2023 | AV49: 2024 | AX49: 2023-2024 | AZ49: Terminal | BA49: -0.12
B50: Manufacturing Prepaids | F50: 0 | G50: 0 | H50: 0 | I50: 0 | J50: 0 | K50: 0 | L50: 0 | M50: 0 | N50: 0 | O50: 0 | P50: 0 | Q50: 0 | R50: 0 | S50: 238.821 | T50: 302.627 | U50: 321.055 | V50: 276.62 | W50: 203.49 | X50: 207.92 | Y50: 206.06 | AM50: =F50 -> 0 | AN50: =J50 -> 0 | AO50: =N50 -> 0 | AP50: =R50 -> 0 | AQ50: =V50 -> 276.62 | AS50: =AVERAGE(AR30)*(1-AR43) -> -435.57063 | AU50: =SUM(AP46:AP49)-AP60+AP52 -> 2461.652 | AV50: =SUM(AQ46:AQ49)-AQ60+AQ52 -> 2832.634 | AX50: =AVERAGE(AU50:AV50) -> 2647.143 | AZ50: RFR (10-year yield) | BA50: ='Bull Case (20%)'!BA50 -> 0.0416
B51: Other ST Assets | F51: 213.324 | G51: 174.98 | H51: 141.666 | I51: 147.941 | J51: 149.028 | K51: 140.33 | L51: 129.332 | M51: 130.744 | N51: 149.891 | O51: 179.769 | P51: 148.215 | Q51: 154.441 | R51: 179.89 | S51: 82.965 | T51: 74.74 | U51: 165.477 | V51: 90.461 | W51: 105.478 | X51: 127.59 | Y51: 192.34 | AM51: =F51 -> 213.324 | AN51: =J51 -> 149.028 | AO51: =N51 -> 149.891 | AP51: =R51 -> 179.89 | AQ51: =V51 -> 90.461 | AS51: =AS50/AX50 -> -0.16454367 | AZ51: ERP (Avg. market return - (less) RFR) | BA51: =10%-BA50 -> 0.0584
B52: PP&E | F52: 190.43 | G52: 203.107 | H52: 203.33 | I52: 199.249 | J52: 191.156 | K52: 187.248 | L52: 183.292 | M52: 181.005 | N52: 180.037 | O52: 182.86 | P52: 188.874 | Q52: 212.367 | R52: 227.15 | S52: 249.302 | T52: 276.2 | U52: 305.788 | V52: 340.336 | W52: 360.587 | X52: 371.857 | Y52: 358.93 | AM52: =F52 -> 190.43 | AN52: =J52 -> 191.156 | AO52: =N52 -> 180.037 | AP52: =R52 -> 227.15 | AQ52: =V52 -> 340.336 | AZ52: Equity β (1-year avg.) | BA52: 0.56
B53: Right-to-use assets | F53: 13.628 | G53: 14.124 | H53: 14.105 | I53: 14.204 | J53: 14.239 | K53: 13.328 | L53: 13.062 | M53: 13.057 | N53: 7.578 | O53: 62.016 | P53: 134.728 | Q53: 133.454 | R53: 129.95 | S53: 126.269 | T53: 124 | U53: 140.898 | V53: 148.31 | W53: 147.063 | X53: 143.041 | Y53: 139.16 | AM53: =F53 -> 13.628 | AN53: =J53 -> 14.239 | AO53: =N53 -> 7.578 | AP53: =R53 -> 129.95 | AQ53: =V53 -> 148.31 | AZ53: Discount (Cost of Equity) | BA53: =+BA50+(BA51*BA52) -> 0.074304
B54: Non-current Inventories | F54: 91.761 | G54: 65.068 | H54: 72.868 | I54: 72.663 | J54: 45.531 | K54: 45.982 | L54: 46.999 | M54: 43.034 | N54: 64.954 | O54: 164.144 | P54: 166.635 | Q54: 176.112 | R54: 191.36 | S54: 207.542 | T54: 204.69 | U54: 202.55 | V54: 187.986 | W54: 181.158 | X54: 194.668 | Y54: 198.6 | AM54: =F54 -> 91.761 | AN54: =J54 -> 45.531 | AO54: =N54 -> 64.954 | AP54: =R54 -> 191.36 | AQ54: =V54 -> 187.986
B55: Strategic Investments | F55: 0 | G55: 0 | H55: 0 | I55: 0 | J55: 0 | K55: 0 | L55: 0 | M55: 0 | N55: 0 | O55: 0 | P55: 0 | Q55: 0 | R55: 0 | S55: 0 | T55: 0 | U55: 0 | V55: 0 | W55: 154.37 | X55: 195.522 | Y55: 0 | AM55: =F55 -> 0 | AN55: =J55 -> 0 | AO55: =N55 -> 0 | AP55: =R55 -> 0 | AQ55: =V55 -> 0 | AZ55: NPV | BA55: =NPV(BA53,AR35:CO35) -> 784.89094
B56: LT Investments | F56: 0 | G56: 0 | H56: 0 | I56: 0 | J56: 0 | K56: 0 | L56: 0 | M56: 0 | N56: 0 | O56: 0 | P56: 0 | Q56: 0 | R56: 0 | S56: 0 | T56: 0 | U56: 181.77 | V56: 133.163 | W56: 109.125 | X56: 34.604 | Y56: 1.04 | AM56: =F56 -> 0 | AN56: =J56 -> 0 | AO56: =N56 -> 0 | AP56: =R56 -> 0 | AQ56: =V56 -> 133.163 | AZ56: SC | BA56: =Main!C6 -> 104.787
B57: Other LT Assets | F57: 203.703 | G57: 211.584 | H57: 203.553 | I57: 190.792 | J57: 292.949 | K57: 278.649 | L57: 284.2 | M57: 293.124 | N57: 317.936 | O57: 162.387 | P57: 163.039 | Q57: 136.925 | R57: 136.87 | S57: 176.407 | T57: 135.72 | U57: 83.559 | V57: 79.915 | W57: 80.551 | X57: 83.137 | Y57: 73.38 | AM57: =F57 -> 203.703 | AN57: =J57 -> 292.949 | AO57: =N57 -> 317.936 | AP57: =R57 -> 136.87 | AQ57: =V57 -> 79.915 | AZ57: FV | BA57: =BA55/BA56 -> 7.4903465
B58: Ttl Assets | F58: =SUM(F46:F57) -> 2984.71 | G58: =SUM(G46:G57) -> 2765.226 | H58: =SUM(H46:H57) -> 2759.068 | I58: =SUM(I46:I57) -> 2662.218 | J58: =SUM(J46:J57) -> 3147.974 | K58: =SUM(K46:K57) -> 3056.153 | L58: =SUM(L46:L57) -> 2996.853 | M58: =SUM(M46:M57) -> 3156.145 | ... Y58: =SUM(Y46:Y57) -> 3493.386 | AM58: =F58 -> 2984.71 | AN58: =J58 -> 3147.974 | AO58: =N58 -> 3128.359 | AP58: =R58 -> 3264.64 | AQ58: =V58 -> 3963.531 | AZ58: CP | BA58: =Main!C5 -> 23.73
AZ59: Change Δ | BA59: =BA57/BA58-1 -> -0.68435118 | BB59: =IF(BA59>0,"Upside","Downside") -> Downside
B60: A/P | F60: 111.09 | G60: 76.651 | H60: 76.68 | I60: 44.163 | J60: 76.741 | K60: 54.007 | L60: 56.207 | M60: 118.461 | N60: 95.875 | O60: 106.71 | P60: 109.796 | Q60: 87.948 | R60: 164.918 | S60: 91.536 | T60: 107.417 | U60: 118.774 | V60: 214.442 | W60: 156.105 | X60: 136.702 | Y60: 94.015 | AM60: =F60 -> 111.09 | AN60: =J60 -> 76.741 | AO60: =N60 -> 95.875 | AP60: =R60 -> 164.918 | AQ60: =V60 -> 214.442 | AZ60: {=_xlfn.IFS(BA59>=25%,"Strong Buy",BA59>=10.00001%,"Buy",AND(BA59<=10%,BA59>=-4.9999%),"Hold",AND(BA59<=-5%,BA59>=-14.999999%),"Sell",BA59<=-15%,"Strong Sell")} -> Strong Sell
B61: Accrued Expenses, current | F61: 193.55 | G61: 180.636 | H61: 240.141 | I61: 221.009 | J61: 271.697 | K61: 293.908 | L61: 383.699 | M61: 368.998 | N61: 418.99 | O61: 345.55 | P61: 326.877 | Q61: 322.35 | R61: 314.997 | S61: 283.317 | T61: 350.404 | U61: 344.83 | V61: 373.5 | W61: 391.65 | X61: 377.399 | Y61: 295.79 | AM61: =F61 -> 193.55 | AN61: =J61 -> 271.697 | AO61: =N61 -> 418.99 | AP61: =R61 -> 314.997 | AQ61: =V61 -> 373.5
B62: Deffered Revenues, current | F62: 89.244 | G62: 89.244 | H62: 89.244 | I62: 89.244 | J62: 89.244 | K62: 89.244 | L62: 89.244 | M62: 89.244 | N62: 89.244 | O62: 67.239 | P62: 44.989 | Q62: 22.494 | R62: 50.416 | S62: 112 | T62: 122.036 | U62: 127 | V62: 130.256 | W62: 44.859 | X62: 395.431 | Y62: 485.449 | AM62: =F62 -> 89.244 | AN62: =J62 -> 89.244 | AO62: =N62 -> 89.244 | AP62: =R62 -> 50.416 | AQ62: =V62 -> 130.256
B63: Other ST Liabilities | F63: 22.139 | G63: 18.205 | H63: 18.956 | I63: 19.02 | J63: 15.051 | K63: 17.803 | L63: 16.416 | M63: 26.213 | N63: 15.489 | O63: 17.381 | P63: 16.992 | Q63: 17.951 | R63: 17.845 | S63: 16.27 | T63: 17.12 | U63: 17.289 | V63: 13.473 | W63: 12.974 | X63: 10.416 | Y63: =36+10.16 -> 46.16 | AM63: =F63 -> 22.139 | AN63: =J63 -> 15.051 | AO63: =N63 -> 15.489 | AP63: =R63 -> 17.845 | AQ63: =V63 -> 13.473
B64: Current Portion of Debt | F64: 0 | G64: 0 | H64: 0 | I64: 0 | J64: 0 | K64: 0 | L64: 0 | M64: 0 | N64: 0 | O64: 0 | P64: 0 | Q64: 0 | R64: 105.483 | S64: 105.586 | T64: 91.505 | U64: 91.595 | V64: 0 | W64: 0 | X64: 0 | Y64: 0 | AM64: =F64 -> 0 | AN64: =J64 -> 0 | AO64: =N64 -> 0 | AP64: =R64 -> 105.483 | AQ64: =V64 -> 0
B65: LT Debt | F65: 992.493 | G65: 1091.11 | H65: 1092.985 | I65: 1094.912 | J65: 1096.876 | K65: 1098.84 | L65: 1100.873 | M65: 1542.77 | N65: 1544.29 | O65: 1234.284 | P65: 1235.51 | Q65: 1236.755 | R65: 1132.515 | S65: 1133.66 | T65: 1134.81 | U65: 1135.965 | V65: 1137.12 | W65: 1138.28 | X65: 1139.458 | Y65: 1035.146 | AM65: =F65 -> 992.493 | AN65: =J65 -> 1096.876 | AO65: =N65 -> 1544.29 | AP65: =R65 -> 1132.515 | AQ65: =V65 -> 1137.12
B66: LT Lease Liabilities | F66: 80.36 | G66: 60.675 | H66: 65.285 | I66: 63.42 | J66: 41.512 | K66: 38.62 | L66: 39.368 | M66: 35.229 | N66: 57.578 | O66: 53.931 | P66: 129.17 | Q66: 134.752 | R66: 140.96 | S66: 140.1 | T66: 143.601 | U66: 170 | V66: 192.473 | W66: 205.46 | X66: 214.419 | Y66: 215.042 | AM66: =F66 -> 80.36 | AN66: =J66 -> 41.512 | AO66: =N66 -> 57.578 | AP66: =R66 -> 140.96 | AQ66: =V66 -> 192.473
B67: Deffered LT Revenues | F67: 663.488 | G67: 641.483 | H67: 619.233 | I67: 596.73 | J67: 574.244 | K67: 552.239 | L67: 529.989 | M67: 507.494 | N67: 485 | O67: 485 | P67: 485 | Q67: 485 | R67: 437 | S67: 325 | T67: 325 | U67: 325 | V67: 325 | W67: 325 | X67: 0 | Y67: 0 | AM67: =F67 -> 663.488 | AN67: =J67 -> 574.244 | AO67: =N67 -> 485 | AP67: =R67 -> 437 | AQ67: =V67 -> 325
B68: Contingent Consideration | F68: 50.8 | G68: 50.8 | H68: 50.8 | I68: 43.6 | J68: 43.6 | K68: 43.6 | L68: 43.6 | M68: 36.9 | N68: 36.9 | O68: 36.9 | P68: 36.1 | Q68: 38.1 | R68: 38.1 | S68: 48.2 | T68: 48.2 | U68: 47.4 | V68: 47.4 | W68: 47.4 | X68: 47.4 | Y68: 0.3 | AM68: =F68 -> 50.8 | AN68: =J68 -> 43.6 | AO68: =N68 -> 36.9 | AP68: =R68 -> 38.1 | AQ68: =V68 -> 47.4
B69: Other LT Liabilities | F69: 19.785 | G69: 20.984 | H69: 20.64 | I69: 20.569 | J69: 11 | K69: 11 | L69: 11 | M69: 0 | N69: 0.042 | O69: 0.038 | P69: 0.038 | Q69: 0 | R69: 3 | S69: 7.522 | T69: 7.087 | U69: 1 | V69: 1.75 | W69: 0.927 | X69: 1.2 | Y69: 1.404 | AM69: =F69 -> 19.785 | AN69: =J69 -> 11 | AO69: =N69 -> 0.042 | AP69: =R69 -> 3 | AQ69: =V69 -> 1.75
B70: Ttl Liabilities | F70: =SUM(F60:F69) -> 2222.949 | G70: =SUM(G60:G69) -> 2229.788 | H70: =SUM(H60:H69) -> 2273.964 | I70: =SUM(I60:I69) -> 2192.667 | J70: =SUM(J60:J69) -> 2219.965 | K70: =SUM(K60:K69) -> 2199.261 | L70: =SUM(L60:L69) -> 2270.396 | M70: =SUM(M60:M69) -> 2725.309 | ... Y70: =SUM(Y60:Y69) -> 2173.306 | AM70: =F70 -> 2222.949 | AN70: =J70 -> 2219.965 | AO70: =N70 -> 2743.408 | AP70: =R70 -> 2405.234 | AQ70: =V70 -> 2435.414
B71: SE | F71: 761.759 | G71: 535.445 | H71: 485.1 | I71: 469.52 | J71: 928.009 | K71: 856.886 | L71: 726.457 | M71: 430.84 | N71: 384.95 | O71: 712.749 | P71: 741.411 | Q71: 764.357 | R71: 859.337 | S71: 961.192 | T71: 1077.06 | U71: 1221.071 | V71: 1527.742 | W71: 1142.723 | X71: 1357.38 | Y71: 1320.12 | AM71: =F71 -> 761.759 | AN71: =J71 -> 928.009 | AO71: =N71 -> 384.95 | AP71: =R71 -> 859.337 | AQ71: =V71 -> 1527.742
B72: Total L + SE | F72: =F70+F71 -> 2984.708 | G72: =G70+G71 -> 2765.233 | H72: =H70+H71 -> 2759.064 | I72: =I70+I71 -> 2662.187 | J72: =J70+J71 -> 3147.974 | K72: =K70+K71 -> 3056.147 | L72: =L70+L71 -> 2996.853 | M72: =M70+M71 -> 3156.149 | ... Y72: =Y70+Y71 -> 3493.426 | AM72: =F72 -> 2984.708 | AN72: =J72 -> 3147.974 | AO72: =N72 -> 3128.358 | AP72: =R72 -> 3264.571 | AQ72: =V72 -> 3963.156
B74: Current Ratio | F74: =SUM(F46:F51)/SUM(F60:F64) -> 5.9736793 | G74: =SUM(G46:G51)/SUM(G60:G64) -> 6.2273617 | H74: =SUM(H46:H51)/SUM(H60:H64) -> 5.3296472 | I74: =SUM(I46:I51)/SUM(I60:I64) -> 5.8518997 | J74: =SUM(J46:J51)/SUM(J60:J64) -> 5.7519531 | K74: =SUM(K46:K51)/SUM(K60:K64) -> 5.5629833 | L74: =SUM(L46:L51)/SUM(L60:L64) -> 4.5261252 | M74: =SUM(M46:M51)/SUM(M60:M64) -> 4.3553745 | ... Y74: =SUM(Y46:Y51)/SUM(Y60:Y64) -> 2.9544548 | AM74: =SUM(AM46:AM51)/SUM(AM60:AM64) -> 5.9736793 | AN74: =SUM(AN46:AN51)/SUM(AN60:AN64) -> 5.7519531 | AO74: =SUM(AO46:AO51)/SUM(AO60:AO64) -> 4.1282477 | AP74: =SUM(AP46:AP51)/SUM(AP60:AP64) -> 3.9459565 | AQ74: =SUM(AQ46:AQ51)/SUM(AQ60:AQ64) -> 4.2010972
B75: Quick Ratio | F75: =(SUM(F46:F51)-F49)/SUM(F60:F64) -> 5.4161116 | G75: =(SUM(G46:G51)-G49)/SUM(G60:G64) -> 5.5684385 | H75: =(SUM(H46:H51)-H49)/SUM(H60:H64) -> 4.6973114 | I75: =(SUM(I46:I51)-I49)/SUM(I60:I64) -> 5.0794273 | J75: =(SUM(J46:J51)-J49)/SUM(J60:J64) -> 5.3406467 | K75: =(SUM(K46:K51)-K49)/SUM(K60:K64) -> 5.1255907 | L75: =(SUM(L46:L51)-L49)/SUM(L60:L64) -> 4.1446956 | M75: =(SUM(M46:M51)-M49)/SUM(M60:M64) -> 3.9885042 | ... Y75: =(SUM(Y46:Y51)-Y49)/SUM(Y60:Y64) -> 1.7854254 | AM75: =(SUM(AM46:AM51)-AM49)/SUM(AM60:AM64) -> 5.4161116 | AN75: =(SUM(AN46:AN51)-AN49)/SUM(AN60:AN64) -> 5.3406467 | AO75: =(SUM(AO46:AO51)-AO49)/SUM(AO60:AO64) -> 3.7990536 | AP75: =(SUM(AP46:AP51)-AP49)/SUM(AP60:AP64) -> 3.4520446 | AQ75: =(SUM(AQ46:AQ51)-AQ49)/SUM(AQ60:AQ64) -> 3.176101
B76: Cash Ratio | F76: =F46/SUM(F60:F64) -> 3.6119157 | G76: =G46/SUM(G60:G64) -> 4.0627468 | H76: =H46/SUM(H60:H64) -> 3.9933792 | I76: =I46/SUM(I60:I64) -> 4.2821608 | J76: =J46/SUM(J60:J64) -> 4.6735471 | K76: =K46/SUM(K60:K64) -> 2.7120441 | L76: =L46/SUM(L60:L64) -> 1.5920439 | M76: =M46/SUM(M60:M64) -> 1.7226612 | ... Y76: =Y46/SUM(Y60:Y64) -> 0.66535781 | AM76: =AM46/SUM(AM60:AM64) -> 3.6119157 | AN76: =AN46/SUM(AN60:AN64) -> 4.6735471 | AO76: =AO46/SUM(AO60:AO64) -> 1.5603181 | AP76: =AP46/SUM(AP60:AP64) -> 0.65543349 | AQ76: =AQ46/SUM(AQ60:AQ64) -> 1.5075218
B77: Ttl Asset Turnover | F77: =F23/F72 -> 0.048628543 | G77: =G23/G72 -> 0.053135125 | H77: =H23/H72 -> 0.059472705 | I77: =I23/I72 -> 0.071133245 | J77: =J23/J72 -> 0.063995128 | K77: =K23/K72 -> 0.068985556 | L77: =L23/L72 -> 0.077927413 | M77: =M23/M72 -> 0.072960434 | ... Y77: =Y23/Y72 -> 0.11431271 | AM77: =AM23/AM72 -> 0.18095539 | AN77: =AN23/AN72 -> 0.22295133 | AO77: =AO23/AO72 -> 0.29824368 | AP77: =AP23/AP72 -> 0.38085739 | AQ77: =AQ23/AQ72 -> 0.47991525
B78: Inventory Turnover Ratio | F78: =F24/AVERAGE(C49:F49) -> 0.096585202 | G78: =G24/AVERAGE(D49:G49) -> 0.094627499 | H78: =H24/AVERAGE(E49:H49) -> 0.079002766 | I78: =I24/AVERAGE(F49:I49) -> 0.091071656 | J78: =J24/AVERAGE(G49:J49) -> 0.12908708 | K78: =K24/AVERAGE(H49:K49) -> 0.13345444 | L78: =L24/AVERAGE(I49:L49) -> 0.17145002 | M78: =M24/AVERAGE(J49:M49) -> 0.19620477 | ... Y78: =Y24/AVERAGE(V49:Y49) -> 0.16029014 | AM78: =AM24/AVERAGE(AJ49:AM49) -> 0.27324421 | AN78: =AN24/AVERAGE(AK49:AN49) -> 0.46415718 | AO78: =AO24/AVERAGE(AL49:AO49) -> 0.67503508 | AP78: =AP24/AVERAGE(AM49:AP49) -> 0.63637855 | AQ78: =AQ24/AVERAGE(AN49:AQ49) -> 0.87245709
B79: Return on Assets | F79: =F35/F72 -> -0.063356952 | G79: =G35/G72 -> -0.060483149 | H79: =H35/H72 -> -0.029506021 | I79: =I35/I72 -> -0.0180964 | J79: =J35/J72 -> -0.038748414 | K79: =K35/K72 -> -0.03436353 | L79: =L35/L72 -> -0.077958779 | M79: =M35/M72 -> -0.081888719 | ... Y79: =Y35/Y72 -> -0.051513614 | AM79: =AM35/AM72 -> -0.1856453 | AN79: =AN35/AN72 -> -0.13304239 | AO79: =AO35/AO72 -> -0.22580664 | AP79: =AP35/AP72 -> -0.16417992 | AQ79: =AQ35/AQ72 -> 0.058953269
B80: Return on Equity | F80: =F35/F71 -> -0.24824387 | G80: =G35/G71 -> -0.31235701 | H80: =H35/H71 -> -0.16781901 | I80: =I35/I71 -> -0.10260692 | J80: =J35/J71 -> -0.13144161 | K80: =K35/K71 -> -0.12256006 | L80: =L35/L71 -> -0.32160334 | M80: =M35/M71 -> -0.59988163 | ... Y80: =Y35/Y71 -> -0.13632018 | AM80: =AM35/AM71 -> -0.72739147 | AN80: =AN35/AN71 -> -0.45130381 | AO80: =AO35/AO71 -> -1.8350539 | AP80: =AP35/AP71 -> -0.62370991 | AQ80: =AQ35/AQ71 -> 0.15293224
B82: Net Income | C82: =C35 -> -17.492 | D82: =D35 -> -151.004 | E82: =E35 -> -196.499 | F82: =F35 -> -189.102 | G82: =G35 -> -167.25 | H82: =H35 -> -81.409 | I82: =I35 -> -48.176 | J82: =J35 -> -121.979 | ... Y82: =Y35 -> -179.959 | AM82: =SUM(C82:F82) -> -554.097 | AN82: =SUM(G82:J82) -> -418.814 | AO82: =SUM(K82:N82) -> -706.404 | AP82: =SUM(O82:R82) -> -535.977 | AQ82: =SUM(S82:V82) -> 233.641
B83: CFFO | C83: 627.8 | D83: -107.6 | E83: -283.2 | F83: -129.5 | G83: -180.4 | H83: -109.5 | I83: -124 | J83: -29.3 | K83: -101.2 | L83: -66.8 | M83: -65 | N83: -92.4 | O83: -209.4 | P83: -122.2 | Q83: -115.9 | R83: -53.5 | S83: -241.1 | T83: 14.9 | U83: -70.7 | V83: 92 | W83: -583.4 | X83: =-322.1-W83 -> 261.3 | Y83: -14.6 | AM83: =SUM(C83:F83) -> 107.5 | AN83: =SUM(G83:J83) -> -443.2 | AO83: =SUM(K83:N83) -> -325.4 | AP83: =SUM(O83:R83) -> -501 | AQ83: =SUM(S83:V83) -> -204.9
B84: CapEx, net | C84: -9.1 | D84: -19.2 | E84: -25.3 | F84: -28.6 | G84: -21.1 | H84: -5.9 | I84: -9.2 | J84: -2.2 | K84: -5.6 | L84: -9.1 | M84: -8.2 | N84: -8 | O84: -9.5 | P84: -17.9 | Q84: -29.7 | R84: -19 | S84: -32.4 | T84: -29.2 | U84: -37.3 | V84: -38.1 | W84: -43.7 | X84: =-75.44-W84 -> -31.74 | Y84: -22.9 | AM84: =SUM(C84:F84) -> -82.2 | AN84: =SUM(G84:J84) -> -38.4 | AO84: =SUM(K84:N84) -> -30.9 | AP84: =SUM(O84:R84) -> -76.1 | AQ84: =SUM(S84:V84) -> -137
B85: FCF | C85: =C83+C84 -> 618.7 | D85: =D83+D84 -> -126.8 | E85: =E83+E84 -> -308.5 | F85: =F83+F84 -> -158.1 | G85: =G83+G84 -> -201.5 | H85: =H83+H84 -> -115.4 | I85: =I83+I84 -> -133.2 | J85: =J83+J84 -> -31.5 | ... Y85: =Y83+Y84 -> -37.5 | AM85: =SUM(C85:F85) -> 25.3 | AN85: =SUM(G85:J85) -> -481.6 | AO85: =SUM(K85:N85) -> -356.3 | AP85: =SUM(O85:R85) -> -577.1 | AQ85: =SUM(S85:V85) -> -341.9
B86: SC | C86: =C36 -> 76.432 | D86: =D36 -> 77.968 | E86: =E36 -> 78.501 | F86: =F36 -> 77.77 | G86: =G36 -> 79.454 | H86: =H36 -> 79.746 | I86: =I36 -> 79.88 | J86: =J36 -> 87.12 | ... Y86: =Y36 -> 100.23 | AM86: =AM36 -> 77.66775 | AN86: =AN36 -> 81.55 | AO86: =AO36 -> 87.59125 | AP86: =AP36 -> 89.554 | AQ86: =AQ36 -> 95.2575
B87: FCF per Share | C87: =C85/C86 -> 8.0947771 | D87: =D85/D86 -> -1.6263082 | E87: =E85/E86 -> -3.9298862 | F87: =F85/F86 -> -2.0329176 | G87: =G85/G86 -> -2.5360586 | H87: =H85/H86 -> -1.4470945 | I87: =I85/I86 -> -1.6675013 | J87: =J85/J86 -> -0.36157025 | ... Y87: =Y85/Y86 -> -0.37413948 | AM87: =SUM(C87:F87) -> 0.50566501 | AN87: =SUM(G87:J87) -> -6.0122246 | AO87: =SUM(K87:N87) -> -4.0679274 | AP87: =SUM(O87:R87) -> -6.4836165 | AQ87: =SUM(S87:V87) -> -3.6377254
B89: FCF/Revenue | C89: =C85/C23 -> 5.4427574 | D89: =D85/D23 -> -0.92312844 | E89: =E85/E23 -> -2.1434924 | F89: =F85/F23 -> -1.0892781 | G89: =G85/G23 -> -1.371392 | H89: =H85/H23 -> -0.70327688 | I89: =I85/I23 -> -0.70338491 | J89: =J85/J23 -> -0.15636246 | ... Y89: =Y85/Y23 -> -0.093904238

Sheet Notes | Quant Analysis
CA1: 0
H2: Employee Scope: | AC2: General Notes/Observations (Updated Q1'25)
I27: Notes: | J27: [X]
J28: [Y]
J29: [Z]
H31: Institutional Ownership Snapshot (6/16/2025)
AC32: Financial Stmts. Notes/Observations (Updated Q1'25)
AC33: Revenues:
I59: Notes: | J59: [X]
J60: [Y]
J61: [Z]
AD62: Bull Case:
H63: Revenue Breakdown by Segment (Build graph for this section if applicable…. See example below) | AE63: Elevidys goes through short term hiccups with second patient death and pause on non-ambulatory patients until Q1'26
AE64: PMO business remains stable for the next two years as Elevidys gets into the market and health care providers are able to collect higher quality patient outcome data
AF65: High R&D spend on clinical trails and research in the short term, but efficacy is ultimately proven, and patient outcomes are positive … take dominant share of DMD market
AE66: PMO business phases out in the LT as HCP's and insurance companies feel comfortable providing Elevidys … Elevydis maintains dominance in the gene therapy space
AC79: Earnings Scope:
I95: Notes: | J95: [X]
J96: [Y]
J97: [Z]
H99: Q/q Total Revenues, Net Income, FCF
I128: Notes: | J128: [X]
J129: [Y]
J130: [Z]
H132: Y/y Total Revenues, Net Income, FCF | AC132: Balance Sheet Scope:
I161: Notes: | J161: [X]
J162: [Y]
J163: [Z]
H165: SRPT Historical Return Histogram (Date Built)
A183: 1255 Trading Days? (From: 6/17/20 - 6/17/25) | AC183: [Equity Preformance Compared to Peers]
A184: Close | B184: High | C184: Low | D184: Open | E184: Volume | F184: UTC Date | G184: Change
A185: 20.94 | B185: 21.5499 | C185: 18.3001 | D185: 21.26 | E185: 43041864 | F185: Mon, 16 Jun 2025 00:00:00 GMT | G185: =A185/D185-1 -> -0.01505174
A186: 36.18 | B186: 38.09 | C186: 35.77 | D186: 37.05 | E186: 3233810 | F186: Fri, 13 Jun 2025 00:00:00 GMT | G186: =A186/D186-1 -> -0.023481781
A187: 37.31 | B187: 37.84 | C187: 36.8 | D187: 37.6 | E187: 3199528 | F187: Thu, 12 Jun 2025 00:00:00 GMT | G187: =A187/D187-1 -> -0.007712766
A188: 37.81 | B188: 39.6359 | C188: 37.76 | D188: 39.305 | E188: 2367951 | F188: Wed, 11 Jun 2025 00:00:00 GMT | G188: =A188/D188-1 -> -0.038035873
A189: 39.07 | B189: 40.9 | C189: 38.95 | D189: 40 | E189: 3397782 | F189: Tue, 10 Jun 2025 00:00:00 GMT | G189: =A189/D189-1 -> -0.02325
A190: 39.71 | B190: 43.9156 | C190: 39.4105 | D190: 43.795 | E190: 5629632 | F190: Mon, 09 Jun 2025 00:00:00 GMT | G190: =A190/D190-1 -> -0.093275488
A191: 43.01 | B191: 43.54 | C191: 40.45 | D191: 40.45 | E191: 4851881 | F191: Fri, 06 Jun 2025 00:00:00 GMT | G191: =A191/D191-1 -> 0.06328801
A192: 39.21 | B192: 40.49 | C192: 37.91 | D192: 39.54 | E192: 2864373 | F192: Thu, 05 Jun 2025 00:00:00 GMT | G192: =A192/D192-1 -> -0.0083459788
A193: 39.54 | B193: 40.28 | C193: 38.635 | D193: 39.05 | E193: 2338059 | F193: Wed, 04 Jun 2025 00:00:00 GMT | G193: =A193/D193-1 -> 0.012548015
A194: 38.87 | B194: 39.12 | C194: 37.1503 | D194: 37.72 | E194: 2211270 | F194: Tue, 03 Jun 2025 00:00:00 GMT | G194: =A194/D194-1 -> 0.030487805 | I194: Notes: | J194: [X]
A195: 37.74 | B195: 39.01 | C195: 37.07 | D195: 37.85 | E195: 2210050 | F195: Mon, 02 Jun 2025 00:00:00 GMT | G195: =A195/D195-1 -> -0.0029062087 | J195: [Y]
A196: 37.6 | B196: 38.15 | C196: 36.96 | D196: 38.05 | E196: 3093450 | F196: Fri, 30 May 2025 00:00:00 GMT | G196: =A196/D196-1 -> -0.011826544 | J196: [Z]
A197: 39.99 | B197: 40.7 | C197: 37.145 | D197: 38.02 | E197: 4912564 | F197: Tue, 20 May 2025 00:00:00 GMT | G197: =A197/D197-1 -> 0.051814834
A198: 37.94 | B198: 38.36 | C198: 35.85 | D198: 35.99 | E198: 3664098 | F198: Mon, 19 May 2025 00:00:00 GMT | G198: =A198/D198-1 -> 0.054181717 | J198: Min | K198: =MIN(G185:G428) -> -0.25705205
A199: 36.43 | B199: 36.72 | C199: 35.25 | D199: 35.64 | E199: 4052764 | F199: Fri, 16 May 2025 00:00:00 GMT | G199: =A199/D199-1 -> 0.022166105 | J199: Max | K199: =MAX(G185:G428) -> 0.14624099
A200: 35.27 | B200: 35.7 | C200: 34.1 | D200: 35.7 | E200: 3896257 | F200: Thu, 15 May 2025 00:00:00 GMT | G200: =A200/D200-1 -> -0.012044818 | J200: Mean μ | K200: =AVERAGE(G185:G428) -> -0.0032638118
A201: 35.74 | B201: 37.4167 | C201: 35.5612 | D201: 36.25 | E201: 5227734 | F201: Wed, 14 May 2025 00:00:00 GMT | G201: =A201/D201-1 -> -0.014068966 | J201: Median | K201: =MEDIAN(G185:G428) -> -0.0028354551
A202: 36.2 | B202: 37.32 | C202: 34.9 | D202: 36.57 | E202: 5670168 | F202: Tue, 13 May 2025 00:00:00 GMT | G202: =A202/D202-1 -> -0.010117583 | J202: SD σ | K202: =_xlfn.STDEV.P(G185:G428) -> 0.032636891
A203: 36.37 | B203: 39.2144 | C203: 36.21 | D203: 37.7 | E203: 8369292 | F203: Mon, 12 May 2025 00:00:00 GMT | G203: =A203/D203-1 -> -0.035278515 | J203: 3σ 1-Day Δ: ± | K203: =3*K202 -> 0.097910674 | M203: <- Sharpe Ratio (Risk Adjusted Return)
A204: 36.27 | B204: 39.66 | C204: 35.9324 | D204: 37.32 | E204: 6625629 | F204: Fri, 09 May 2025 00:00:00 GMT | G204: =A204/D204-1 -> -0.028135048 | J204: β (1-year avg.) | K204: 0.6 | M204: <- Sortino Ratio (Downside Risk Adjusted Return)
A205: 36.52 | B205: 38.03 | C205: 35.46 | D205: 37.26 | E205: 9244275 | F205: Thu, 08 May 2025 00:00:00 GMT | G205: =A205/D205-1 -> -0.01986044
A206: 36.72 | B206: 40 | C206: 36.585 | D206: 39.99 | E206: 20751470 | F206: Wed, 07 May 2025 00:00:00 GMT | G206: =A206/D206-1 -> -0.081770443
A207: 46.75 | B207: 63.9199 | C207: 46.52 | D207: 62.925 | E207: 15763443 | F207: Tue, 06 May 2025 00:00:00 GMT | G207: =A207/D207-1 -> -0.25705205 | I207: n = | J207: 1255
A208: 63.66 | B208: 64.8 | C208: 63.12 | D208: 63.41 | E208: 2092060 | F208: Mon, 05 May 2025 00:00:00 GMT | G208: =A208/D208-1 -> 0.0039425958 | I208: Histogram Data | L208: Distribution Overlay | P208: SD Lines
A209: 63.51 | B209: 64.3 | C209: 63.0187 | D209: 63.5 | E209: 1396031 | F209: Fri, 02 May 2025 00:00:00 GMT | G209: =A209/D209-1 -> 0.00015748031 | I209: Bin | J209: Frequency | L209: (X) 1-Day Δ | M209: (Y) Pop. Density | P209: X | Q209: Y
A210: 62.78 | B210: 64 | C210: 60.5301 | D210: 62.45 | E210: 1360542 | F210: Thu, 01 May 2025 00:00:00 GMT | G210: =A210/D210-1 -> 0.0052842274 | I210: -0.1 | J210: 0 | L210: -0.1025 | M210: =_xlfn.NORM.DIST(L210,$K$200,$K$202,FALSE) -> 0.12011649 | O210: Mean | P210: =K200 -> -0.0032638118 | Q210: 0
A211: 62.4 | B211: 62.51 | C211: 59.6169 | D211: 59.98 | E211: 1577083 | F211: Wed, 30 Apr 2025 00:00:00 GMT | G211: =A211/D211-1 -> 0.040346782 | I211: -0.0975 | J211: 1 | L211: -0.1 | M211: =_xlfn.NORM.DIST(L211,$K$200,$K$202,FALSE) -> 0.15117538 | P211: =K200 -> -0.0032638118 | Q211: 20
A212: 60.85 | B212: 62.1326 | C212: 60.55 | D212: 61.37 | E212: 1995899 | F212: Tue, 29 Apr 2025 00:00:00 GMT | G212: =A212/D212-1 -> -0.0084731954 | I212: -0.095 | J212: 0 | L212: -0.0975 | M212: =_xlfn.NORM.DIST(L212,$K$200,$K$202,FALSE) -> 0.18915211 | O212: -3σ | P212: =($K$202*-3)+$K$200 -> -0.10117449 | Q212: 0
A213: 61.51 | B213: 62.47 | C213: 60.18 | D213: 60.59 | E213: 1155727 | F213: Mon, 28 Apr 2025 00:00:00 GMT | G213: =A213/D213-1 -> 0.015184024 | I213: -0.0925 | J213: 2 | L213: -0.095 | M213: =_xlfn.NORM.DIST(L213,$K$200,$K$202,FALSE) -> 0.23528435 | P213: =($K$202*-3)+$K$200 -> -0.10117449 | Q213: 2
A214: 60.44 | B214: 61.9241 | C214: 59.96 | D214: 61.68 | E214: 1312947 | F214: Fri, 25 Apr 2025 00:00:00 GMT | G214: =A214/D214-1 -> -0.020103761 | I214: -0.09 | J214: 1 | L214: -0.0925 | M214: =_xlfn.NORM.DIST(L214,$K$200,$K$202,FALSE) -> 0.29095553 | O214: -2σ | P214: =($K$202*-2)+$K$200 -> -0.068537595 | Q214: 0
A215: 61.76 | B215: 61.91 | C215: 58.76 | D215: 59.63 | E215: 1562239 | F215: Thu, 24 Apr 2025 00:00:00 GMT | G215: =A215/D215-1 -> 0.035720275 | I215: -0.0875 | J215: 0 | L215: -0.09 | M215: =_xlfn.NORM.DIST(L215,$K$200,$K$202,FALSE) -> 0.35769421 | P215: =($K$202*-2)+$K$200 -> -0.068537595 | Q215: 5
A216: 59.49 | B216: 62.78 | C216: 59.06 | D216: 61.65 | E216: 1930012 | F216: Wed, 23 Apr 2025 00:00:00 GMT | G216: =A216/D216-1 -> -0.035036496 | I216: -0.085 | J216: 1 | L216: -0.0875 | M216: =_xlfn.NORM.DIST(L216,$K$200,$K$202,FALSE) -> 0.43716857 | O216: -1σ | P216: =($K$202*-1)+$K$200 -> -0.035900703 | Q216: 0
A217: 59.31 | B217: 59.33 | C217: 55.52 | D217: 55.66 | E217: 2509219 | F217: Tue, 22 Apr 2025 00:00:00 GMT | G217: =A217/D217-1 -> 0.065576716 | I217: -0.0825 | J217: 1 | L217: -0.085 | M217: =_xlfn.NORM.DIST(L217,$K$200,$K$202,FALSE) -> 0.53117505 | P217: =($K$202*-1)+$K$200 -> -0.035900703 | Q217: 10
A218: 55.23 | B218: 56.11 | C218: 52.8 | D218: 53.4 | E218: 1467400 | F218: Mon, 21 Apr 2025 00:00:00 GMT | G218: =A218/D218-1 -> 0.034269663 | I218: -0.08 | J218: 2 | L218: -0.0825 | M218: =_xlfn.NORM.DIST(L218,$K$200,$K$202,FALSE) -> 0.64162036 | O218: 1σ | P218: =($K$202*1)+$K$200 -> 0.02937308 | Q218: 0
A219: 53.79 | B219: 55.49 | C219: 53.5575 | D219: 53.7 | E219: 1912279 | F219: Thu, 17 Apr 2025 00:00:00 GMT | G219: =A219/D219-1 -> 0.0016759777 | I219: -0.0775 | J219: 1 | L219: -0.08 | M219: =_xlfn.NORM.DIST(L219,$K$200,$K$202,FALSE) -> 0.77049588 | P219: =($K$202*1)+$K$200 -> 0.02937308 | Q219: 10
A220: 53.94 | B220: 55.01 | C220: 53.02 | D220: 54.59 | E220: 1440158 | F220: Wed, 16 Apr 2025 00:00:00 GMT | G220: =A220/D220-1 -> -0.011906943 | I220: -0.075 | J220: 0 | L220: -0.0775 | M220: =_xlfn.NORM.DIST(L220,$K$200,$K$202,FALSE) -> 0.9198441 | O220: 2σ | P220: =($K$202*2)+$K$200 -> 0.062009971 | Q220: 0
A221: 54.42 | B221: 56.34 | C221: 53.23 | D221: 54.09 | E221: 2215742 | F221: Tue, 15 Apr 2025 00:00:00 GMT | G221: =A221/D221-1 -> 0.0061009429 | I221: -0.0725 | J221: 0 | L221: -0.075 | M221: =_xlfn.NORM.DIST(L221,$K$200,$K$202,FALSE) -> 1.0917165 | P221: =($K$202*2)+$K$200 -> 0.062009971 | Q221: 5
A222: 54.63 | B222: 54.64 | C222: 51.39 | D222: 53.34 | E222: 2310611 | F222: Mon, 14 Apr 2025 00:00:00 GMT | G222: =A222/D222-1 -> 0.024184477 | I222: -0.07 | J222: 0 | L222: -0.0725 | M222: =_xlfn.NORM.DIST(L222,$K$200,$K$202,FALSE) -> 1.2881226 | O222: 3σ | P222: =($K$202*3)+$K$200 -> 0.094646862 | Q222: 0
A223: 51.03 | B223: 51.8 | C223: 49.085 | D223: 51.22 | E223: 4036734 | F223: Fri, 11 Apr 2025 00:00:00 GMT | G223: =A223/D223-1 -> -0.0037094885 | I223: -0.0675 | J223: 0 | L223: -0.07 | M223: =_xlfn.NORM.DIST(L223,$K$200,$K$202,FALSE) -> 1.5109715 | P223: =($K$202*3)+$K$200 -> 0.094646862 | Q223: 2
A224: 50.31 | B224: 54.465 | C224: 49.86 | D224: 53.34 | E224: 2905054 | F224: Thu, 10 Apr 2025 00:00:00 GMT | G224: =A224/D224-1 -> -0.056805399 | I224: -0.065 | J224: 1 | L224: -0.0675 | M224: =_xlfn.NORM.DIST(L224,$K$200,$K$202,FALSE) -> 1.7620048
A225: 55.65 | B225: 57.7 | C225: 48.01 | D225: 48.55 | E225: 4270638 | F225: Wed, 09 Apr 2025 00:00:00 GMT | G225: =A225/D225-1 -> 0.14624099 | I225: -0.0625 | J225: 3 | L225: -0.065 | M225: =_xlfn.NORM.DIST(L225,$K$200,$K$202,FALSE) -> 2.0427236
A226: 49.3 | B226: 55.36 | C226: 48.94 | D226: 53.99 | E226: 3550239 | F226: Tue, 08 Apr 2025 00:00:00 GMT | G226: =A226/D226-1 -> -0.086867939 | I226: -0.06 | J226: 4 | L226: -0.0625 | M226: =_xlfn.NORM.DIST(L226,$K$200,$K$202,FALSE) -> 2.3543111
A227: 52.4 | B227: 55.17 | C227: 50.6095 | D227: 51.59 | E227: 4155802 | F227: Mon, 07 Apr 2025 00:00:00 GMT | G227: =A227/D227-1 -> 0.015700717 | I227: -0.0575 | J227: 5 | L227: -0.06 | M227: =_xlfn.NORM.DIST(L227,$K$200,$K$202,FALSE) -> 2.6975519
A228: 54.43 | B228: 59.45 | C228: 54.26 | D228: 59.215 | E228: 4577350 | F228: Fri, 04 Apr 2025 00:00:00 GMT | G228: =A228/D228-1 -> -0.080807228 | I228: -0.055 | J228: 2 | L228: -0.0575 | M228: =_xlfn.NORM.DIST(L228,$K$200,$K$202,FALSE) -> 3.0727519
A229: 58.61 | B229: 60.24 | C229: 57.1399 | D229: 57.22 | E229: 3759773 | F229: Thu, 03 Apr 2025 00:00:00 GMT | G229: =A229/D229-1 -> 0.024292206 | I229: -0.0525 | J229: 4 | L229: -0.055 | M229: =_xlfn.NORM.DIST(L229,$K$200,$K$202,FALSE) -> 3.4796608
A230: 62.47 | B230: 64.225 | C230: 60.7 | D230: 61.69 | E230: 3804942 | F230: Wed, 02 Apr 2025 00:00:00 GMT | G230: =A230/D230-1 -> 0.012643864 | I230: -0.05 | J230: 6 | L230: -0.0525 | M230: =_xlfn.NORM.DIST(L230,$K$200,$K$202,FALSE) -> 3.9174011
A231: 61.91 | B231: 65.69 | C231: 61.525 | D231: 64.37 | E231: 3549418 | F231: Tue, 01 Apr 2025 00:00:00 GMT | G231: =A231/D231-1 -> -0.038216561 | I231: -0.0475 | J231: 4 | L231: -0.05 | M231: =_xlfn.NORM.DIST(L231,$K$200,$K$202,FALSE) -> 4.3844073
A232: 63.82 | B232: 67.47 | C232: 62.5 | D232: 65.9 | E232: 4635376 | F232: Mon, 31 Mar 2025 00:00:00 GMT | G232: =A232/D232-1 -> -0.031562974 | I232: -0.045 | J232: 8 | L232: -0.0475 | M232: =_xlfn.NORM.DIST(L232,$K$200,$K$202,FALSE) -> 4.8783782
A233: 70.41 | B233: 72.05 | C233: 69.805 | D233: 71.88 | E233: 984550 | F233: Fri, 28 Mar 2025 00:00:00 GMT | G233: =A233/D233-1 -> -0.020450751 | I233: -0.0425 | J233: 9 | L233: -0.045 | M233: =_xlfn.NORM.DIST(L233,$K$200,$K$202,FALSE) -> 5.3962463
A234: 71.81 | B234: 73.95 | C234: 71.25 | D234: 72.98 | E234: 1364994 | F234: Thu, 27 Mar 2025 00:00:00 GMT | G234: =A234/D234-1 -> -0.01603179 | I234: -0.04 | J234: 4 | L234: -0.0425 | M234: =_xlfn.NORM.DIST(L234,$K$200,$K$202,FALSE) -> 5.9341673
A235: 72.88 | B235: 74.4 | C235: 70.91 | D235: 73.88 | E235: 1387471 | F235: Wed, 26 Mar 2025 00:00:00 GMT | G235: =A235/D235-1 -> -0.013535463 | I235: -0.0375 | J235: 11 | L235: -0.04 | M235: =_xlfn.NORM.DIST(L235,$K$200,$K$202,FALSE) -> 6.4875322
... A290: 126.29 | B290: 127.285 | C290: 124.54 | D290: 124.54 | E290: 397586 | F290: Fri, 03 Jan 2025 00:00:00 GMT | G290: =A290/D290-1 -> 0.01405171 | I290: 0.1 | J290: 0 | L290: 0.0975 | M290: =_xlfn.NORM.DIST(L290,$K$200,$K$202,FALSE) -> 0.10406812
A291: 124.09 | B291: 126.8866 | C291: 121.28 | D291: 122.72 | E291: 593051 | F291: Thu, 02 Jan 2025 00:00:00 GMT | G291: =A291/D291-1 -> 0.011163625 | I291: More | J291: 6 | L291: 0.1 | M291: =_xlfn.NORM.DIST(L291,$K$200,$K$202,FALSE) -> 0.081909428
A292: 121.59 | B292: 122.795 | C292: 120.29 | D292: 121.67 | E292: 379087 | F292: Tue, 31 Dec 2024 00:00:00 GMT | G292: =A292/D292-1 -> -0.00065751623 | L292: 0.1025 | M292: =_xlfn.NORM.DIST(L292,$K$200,$K$202,FALSE) -> 0.064091702
A293: 121.19 | B293: 121.63 | C293: 119.26 | D293: 120.21 | E293: 444800 | F293: Mon, 30 Dec 2024 00:00:00 GMT | G293: =A293/D293-1 -> 0.0081524
A294: 121.5 | B294: 123.574 | C294: 120.83 | D294: 122.24 | E294: 478250 | F294: Fri, 27 Dec 2024 00:00:00 GMT | G294: =A294/D294-1 -> -0.0060536649
A295: 123.37 | B295: 123.9 | C295: 120.74 | D295: 120.82 | E295: 392803 | F295: Thu, 26 Dec 2024 00:00:00 GMT | G295: =A295/D295-1 -> 0.021105777
A296: 121.9 | B296: 122.1808 | C296: 120 | D296: 120.21 | E296: 204864 | F296: Tue, 24 Dec 2024 00:00:00 GMT | G296: =A296/D296-1 -> 0.014058731
A297: 120.66 | B297: 121.065 | C297: 117.395 | D297: 119 | E297: 509527 | F297: Mon, 23 Dec 2024 00:00:00 GMT | G297: =A297/D297-1 -> 0.01394958
A298: 118.97 | B298: 121 | C298: 118.56 | D298: 119.59 | E298: 1952948 | F298: Fri, 20 Dec 2024 00:00:00 GMT | G298: =A298/D298-1 -> -0.00518438
A299: 119.47 | B299: 122.5 | C299: 117.97 | D299: 120.53 | E299: 1031269 | F299: Thu, 19 Dec 2024 00:00:00 GMT | G299: =A299/D299-1 -> -0.008794491
A300: 120.25 | B300: 126.04 | C300: 119.84 | D300: 126.04 | E300: 942784 | F300: Wed, 18 Dec 2024 00:00:00 GMT | G300: =A300/D300-1 -> -0.045937798
A301: 125.76 | B301: 127.87 | C301: 124.9006 | D301: 125.1 | E301: 566207 | F301: Tue, 17 Dec 2024 00:00:00 GMT | G301: =A301/D301-1 -> 0.0052757794
A302: 126.79 | B302: 128.73 | C302: 123 | D302: 123.455 | E302: 741421 | F302: Mon, 16 Dec 2024 00:00:00 GMT | G302: =A302/D302-1 -> 0.027013892
A303: 123.71 | B303: 125.91 | C303: 122.12 | D303: 123.19 | E303: 730761 | F303: Fri, 13 Dec 2024 00:00:00 GMT | G303: =A303/D303-1 -> 0.0042211218
A304: 124.47 | B304: 126.72 | C304: 123.74 | D304: 125.39 | E304: 739839 | F304: Thu, 12 Dec 2024 00:00:00 GMT | G304: =A304/D304-1 -> -0.0073371082
... A1433: 163.42 | B1433: 164.87 | C1433: 160 | D1433: 161.71 | E1433: 1071048 | F1433: Wed, 17 Jun 2020 00:00:00 GMT | G1433: =A1433/D1433-1 -> 0.010574485

Sheet Product Lines

Sheet IP
B2: https://pharsight.greyb.com/company/sarepta-theraps-inc-drug-patent-portfolio

Sheet Management

Sheet Table 
B2: [Bold Title] | G2: [Bold Title]
B3: Line Titles | G3: <-- General
B4: Line Titles | G4: <-- Info
B5: Line Titles | G5: <-- General
B6: Line Titles | G6: <-- Info
B7: Line Titles | G7: <-- General
B8: Line Titles | G8: <-- Info
