Workbook

Sheet Main
A1: Master
A2: Capital Structure Snapshot:
B4: TFX
B5: Price | C5: 125.12 | D5: 2/20/2026
B6: SO | C6: 42.372 | D6: Q2'26
B7: MC | C7: =C5*C6 -> 5301.5846
B8: Cash | C8: 300.159 | D8: Q2'26
B9: Debt | C9: =87.5+2720.509 -> 2808.009 | D9: Q2'26
B10: EV | C10: =C7-C8+C9 -> 7809.4346
B12: Teleflex Inc. (TFX)
B14: Founder(s): Morse Smith | F14: Registered Exchange: NYSE | N14: Resources:
B15: Founded: 1943 | F15: Address: 550 East Swedesford Rd. Wayne, PA | N15: SEC filings | Q15: https://www.sec.gov/edgar/browse/?CIK=96943&owner=exclude
B16: Headquarters: Wayne, PA | F16: Investor Relations Contact: | N16: Teleflex Homepage | Q16: https://www.teleflex.com/usa/en/
B17: Current CEO: Liam Kelly | F17: Investors Relation Department | O17: Teleflex Product Page | R17: https://www.teleflexvascular.com/
B18: Employees: 14,100 | F18: Phone: | G18: 1 (610) 948-2836 | I18: Email: | J18: investor.relations@teleflex.com | O18: Teleflex IR Page | R18: https://investors.teleflex.com/home/default.aspx
B19: Industry: Med-Tech and Supplies | N19: Earnings Calls | Q19: https://seekingalpha.com/symbol/TFX/earnings/transcripts
B20: Sector: Healthcare | N20: Equity Analysis | Q20: https://stockanalysis.com/stocks/tfx/company/
B21: IPO: Feb. 18, 1988 | N21: MacroTrends | Q21: https://www.macrotrends.net/stocks/charts/ISRG/intuitive-surgical/cash-flow-statement?q=
B22: Fiscal Year: [January - December] | N22: ROIC, WACC | Q22: https://www.gurufocus.com/term/wacc/TFX
N23: Godel Terminal | Q23: https://app.godelterminal.com/
A24: Company Overview:
B25: Teleflex is a global medical technology company specializing in the design, development, manufacturing, and supply of single-use medical devices primarily used by hospitals and healthcare providers for diagnostic and therapeutic procedures in critical care and surgical settings worldwide
C26: Its products are marketed worldwide to hospitals and healthcare providers through a direct sales force and distributors
C27: The Company focuses on achieving sustainable and profitable growth by expanding its product portfolio through new product development, technology investments, geographic expansion, operational efficiencies, and strategic acquisitions or partnerships
D28: Teleflex’s operational strategy emphasizes innovation, low-cost manufacturing, and broad market reach to enhance patient outcomes and provider efficiencies globally
C29: The Company’s portfolio consists mainly of Class I and II medical devices, many of which require FDA 510(k) clearance, allowing for quicker and less costly market entry compared to Class III devices
B30: The Company is currently focused on restructuring through the separation of its Urology, Acute Care, and OEM businesses into a new publicly traded company, referred to by management as "NewCo."
C31: This strategic move aims to streamline operations and enhance management focus … “RemainCo” will concentrate on high-growth hospital-focused markets
C32: The remaining company (RemainCo) will integrate the recently acquired Biotronik Vascular Intervention business and concentrate on high-growth hospital-focused markets such as vascular access, interventional, and surgical procedures performed in critical care settings like intensive care units and catheter labs
D33: This restructuring aims to streamline operations, sharpen management focus, and drive profitability and innovation in core categories such as vascular access, interventional cardiology, and surgical products
B34: Teleflex was incorporated in 1943 and is headquartered in Wayne, Pennsylvania
A36: History:
B37: Teleflex was founded in 1943 as a manufacturer of precision mechanical push/pull controls for military aircraft
C38: From this original single market, single product orientation, The Company expanded and evolved through entries into new businesses, development of new products, introduction of products into new geographic or end-markets and acquisitions and dispositions of businesses
C39: Throughout The Company's history, management has continually focused on providing innovative, technology-driven, specialty-engineered products that help customers meet their business requirements
B40: Beginning in 2007, Managers significantly restructured the composition of The Company's portfolio of businesses, expanding its presence in the medical device industry, while spinning off all all other businesses, which served the aerospace, automotive, industrial and marine markets
C41: Following the divestitures of the marine business and cargo container and systems businesses in 2011, The Company became exclusively a medical device business
B42: In 2017, The Company completed two large scale acquisitions: NeoTract, Inc. ("NeoTract") and Vascular Solutions, Inc. (“Vascular Solutions”)
C43: NeoTract was a medical device company that developed and commercialized the UroLift System, a minimally invasive medical device for treating lower urinary tract symptoms due to benign prostatic hyperplasia, or BPH
C44: Vascular Solutions was a medical device company that developed and marketed clinical products for use in minimally invasive coronary and peripheral vascular procedures
B45: In 2021, The Company divested certain product lines within the global respiratory product portfolio to Medline Industries, Inc. (“Medline”) (the "Respiratory business divestiture")
C46: The initial phase of the Respiratory business divestiture was completed on June 28, 2021
C47: The second and final phase of the Respiratory business divestiture was completed in December 2023 with the transfer of certain additional manufacturing assets to Medline
B48: On February 27, 2025, Managers announced an intention to create a new, independently traded public company … "NewCo"
C49: "NewCo" will comprise of the Urology (consisting of our Interventional Urology and Urology product categories), Acute Care (consisting of Respiratory product category, the majority of the Anesthesia segment certain products within the Interventional Access and Surgical product categories) and OEM business segments
C50: While Teleflex is proceeding with the spin-off of certain segments into a new publicly traded entity (“NewCo”), The Company's Vascular Access product category, most products within the Interventional Access and Surgical businesses and the Vascular Intervention business expected to be acquired from BIOTRONIK will remain with Teleflex
C51: Managers continue to execute a footprint realignment and other restructuring programs designed to improve efficiencies in The Company's manufacturing and distribution facilities and, to a lesser extent, our sales and marketing and research and development organizations
A53: Business Segments and Geographical Info:
B54: The Company generally serves three end-markets: hospitals and healthcare providers, medical device manufacturers and home care
C55: These markets are affected by a number of factors, including demographics, utilization and reimbursement patterns
B56: The Company's Vascular Access product portfolio encompasses devices designed to support a variety of critical care therapies and other medical applications, with an emphasis on reducing vascular-related complications
B57: Vascular Access products are comprised of Arrow branded catheters, catheter navigation and tip positioning systems, and intraosseous bone access systems
C58: The Company's catheters are designed to support a wide array of clinical procedures, including the administration of intravenous therapies, the measurement of blood pressure, and the collection of blood samples, all through a single puncture site
D59: Many of these catheters are equipped with antimicrobial and anti-thrombogenic protection technologies, which have been demonstrated to reduce the risk of catheter related bloodstream infections, microbial colonization, and thrombus formation on catheter surfaces
C60: The Company's intraosseous access systems are designed for the delivery of medications and fluids in situations where intravenous access is challenging or not feasible
D61: These systems are particularly effective in emergency, urgent or medically critical scenarios and are suitable for use in both hospital and pre-hospital settings. Key products in this line include the EZ-IO Intraosseous Vascular Access System and the Arrow FAST1 Sternal Intraosseous Infusion System
B62: The Company also offers Vascular Intervention products that facilitate a variety of applications to diagnose and deliver treatment of coronary and peripheral vascular disease
C63: These products primarily consist of a diverse portfolio of coronary catheters, structural heart support devices, peripheral intervention products, and mechanical circulatory support platforms used by interventional cardiologists, interventional radiologists and vascular surgeons
C64: Clinical benefits of our products include increased vein and artery access, post-procedure closure, and increased support during complex medical procedures
C65: Additionally, The Company offers Arrow branded intra-aortic balloon pumps and catheters, Guideliner, Turnpike, and Trapliner catheters, the Manta Vascular Closure, and Arrow Oncontrol devices
B66: The Company provides Anesthesia products, such as airway, pain management and hemostatic product lines that support hospital, emergency medicine and military channels
C67: The airway management products and related devices are designed to enable use of standard and advanced anesthesia techniques in both pre-hospital emergency and hospital settings
D68: key products include laryngoscopes, supraglottic airways, endotracheal tubes and atomization devices, which are branded under our LMA, Rusch and MAD trade names
C69: Pain management product line includes epidurals, catheters and disposable pain pumps for regional anesthesia, designed to improve patients’ post-operative pain experience, which are branded under our Arrow trade name
C70: Hemostatic products accelerate the body's natural clotting cascade and are used in trauma situations where bleeding is difficult to control
D71: The portfolio consists of external hemostats used by first responders, interventional products used in the catheter lab, and trauma products used by trauma surgeons, which are branded under our QuikClot trade name
C72: A majority of the Anesthesia business will be spun off in "NewCo"
B73: The Company offers Surgical products consists of single-use and reusable devices designed for use in a variety of surgical procedures
C74: These products primarily consist of metal and polymer ligating clips, and fascial closure surgical systems that are used in laparoscopic surgical procedures, percutaneous surgical systems, a powered bariatric stapler, and other surgical instruments used in Ear, Nose and Throat and Cardio-Vascular and Thoracic procedures
C75: Significant surgical brands include Weck, MiniLap, Pleur-Evac, Deknatel, KMedic, Pilling and Titan SGS
B76: The Company also offers Interventional Urology products includes the UroLift System, a minimally invasive technology for treating lower urinary tract symptoms due to benign prostatic hyperplasia, or BPH
C77: The UroLift System involves the placement of permanent implants, typically through a transurethral outpatient procedure, that holds the prostate lobes apart to relieve compression on the urethra without cutting, heating or removing prostate tissue
C78: In 2023, Managers expanded the Interventional Urology portfolio with the acquisition of Palette Life Sciences AB (“Palette”), which adds a portfolio of hyaluronic acid gel-based products primarily utilized in the treatment of urological diseases, including Barrigel, a rectal spacing product used in connection with radiation therapy treatment of prostate cancer
D79: The Company's Interventional Urology product portfolio is most heavily weighted in the Americas segment
C80: Interventional Urology business will be spun off in "NewCo"
B81: Respiratory products are used in a variety of care settings and primarily consist of humidification and oxygen therapy products
C82: This product category previously included aerosol therapy, spirometry and ventilation management products, as well as certain other oxygen therapy products, all of which were included in the Respiratory business divestiture
C83: Respiratory business will be spun off in "NewCo"
B84: Urology products provides bladder management for patients in the hospital and individuals in the home care markets
C85: The product portfolio consists principally of a wide range of catheters (including Foley and intermittent), urine collectors, bladder management services, catheterization accessories, and products for operative endourology, which are marketed under the Teleflex and Rusch brand names
D86: The Company's Urology product portfolio is most heavily weighted in our EMEA segment
C87: Urology business will be spun off in "NewCo"
B88: The OEM product category designs, manufactures and supplies devices and instruments for other medical device manufacturers
C89: The Company's OEM portfolio includes the TFX Medical OEM, TFX OEM, Deknatel and HPC Medical brands, provides custom extrusions, micro-diameter film-cast tubing, diagnostic and interventional catheters, balloons and balloon catheters, film-insulated fine wire, coated mandrel wire, conductors, sheath/dilator introducers, specialized sutures and performance fibers, bioabsorbable sutures, yarns and resins
D90: The Company's OEM product portfolio is presented within the Americas segment
B91: Most of The Company's products are sold to hospitals or healthcare providers on orders calling for delivery within a few days or weeks, with longer order times for products sold to medical device manufacturers
C92: A backlog of orders is not indicative of revenues to be anticipated in any future 12-month period
A94: Competition
B95: The medical device industry is highly competitive
C96: Teleflex competes with many companies, ranging from small start-up enterprises to companies that are larger and more established than us and have access to significantly greater financial resources
C97: Furthermore, extensive product research and development and rapid technological advances characterize the market in which we compete
C98: The Company must continue to develop and acquire new products and technologies for our businesses to remain competitive
C99: Managers believe that The Company competes primarily on the basis of clinical superiority and innovative features that enhance patient benefit, product reliability, performance, customer and sales support, and cost-effectiveness
A101: Sales and Marketing:
B102: The Company's product sales are made directly to hospitals, healthcare providers, distributors and to original equipment manufacturers of medical devices through our own sales forces, independent representatives and independent distributor networks
A104: Patents and Trademarks:
B105: The Company owns a portfolio of patents, patents pending and trademarks … The Company also licenses various patents and trademarks
C106: Patents for individual products extend for varying periods based upon the date of patent filing or grant and the legal term of patents in the various countries where patent protection is obtained
C107: Trademark rights may potentially extend for longer periods of time and are dependent upon national laws and use of the marks
C108: All product names throughout this document are trademarks owned by, or licensed to, The Company or its subsidiaries
...

Sheet Bull Case
B1: [Use for Graphing] | AQ1: Q1 2020 | AU1: Q1 2021 | AY1: Q1 2022 | BC1: Q1 2023 | BG1: Q1 2024 | BK1: Q1 2025 | BO1: Q1 2026
B2: Quarterly
B3: Revenues | C3: Q1 2010 | D3: Q2 2010 | E3: Q3 2010 | F3: Q4 2010 | G3: Q1 2011 | H3: Q2 2011 | I3: Q3 2011 | J3: Q4 2011 | K3: Q1 2012 | L3: Q2 2012 | M3: Q3 2012 | N3: Q4 2012 | O3: Q1 2013 | P3: Q2 2013 | Q3: Q3 2013 | R3: Q4 2013 | S3: Q1 2014 | T3: Q2 2014 | U3: Q3 2014 | V3: Q4 2014 | W3: Q1 2015 | X3: Q2 2015 | Y3: Q3 2015 | Z3: Q4 2015 | AA3: Q1 2016 | AB3: Q2 2016 | AC3: Q3 2016 | AD3: Q4 2016 | AE3: Q1 2017 | AF3: Q2 2017 | AG3: Q3 2017 | AH3: Q4 2017 | AI3: Q1 2018 | AJ3: Q2 2018 | AK3: Q3 2018 | AL3: Q4 2018 | AM3: Q1 2019 | AN3: Q2 2019 | AO3: Q3 2019 | AP3: Q4 2019 | AQ3: Q1 2020 | AR3: Q2 2020 | AS3: Q3 2020 | AT3: Q4 2020 | AU3: Q1 2021 | AV3: Q2 2021 | AW3: Q3 2021 | AX3: Q4 2021 | AY3: Q1 2022 | AZ3: Q2 2022 | BA3: Q3 2022 | BB3: Q4 2022 | BC3: Q1 2023 | BD3: Q2 2023 | BE3: Q3 2023 | BF3: Q4 2023 | BG3: Q1 2024 | BH3: Q2 2024 | BI3: Q3 2024 | BJ3: Q4 2024 | BK3: Q1 2025 | BL3: Q2 2025 | BM3: Q3 2025 | BN3: Q4 2025 | BO3: Q1 2026 | BP3: Q2 2026 | BQ3: Q3 2026 | BR3: Q4 2026 | BW3: 2010 | BX3: =BW3+1 -> 2011 | BY3: =BX3+1 -> 2012 | BZ3: =BY3+1 -> 2013 | CA3: =BZ3+1 -> 2014 | CB3: =CA3+1 -> 2015 | CC3: =CB3+1 -> 2016 | CD3: =CC3+1 -> 2017 | CE3: =CD3+1 -> 2018 | ... ES3: =ER3+1 -> 2084
B4: Vascular Access | AQ4: 150.25 | AR4: 164.958 | AS4: 160.05 | AT4: =657.703-SUM(AQ4:AS4) -> 182.445 | AU4: 163.97 | AV4: 167.73 | AW4: 175.47 | AX4: =700.24-SUM(AU4:AW4) -> 193.07 | AY4: 166.13 | AZ4: 163.9 | BA4: 167.14 | BB4: =683.612-SUM(AY4:BA4) -> 186.442 | BC4: 177.65 | BD4: 173.785 | BE4: 169.91 | BF4: =708.04-SUM(BC4:BE4) -> 186.695 | BG4: 181.35 | BH4: 181.1 | BI4: 180.89 | BJ4: =732.67-SUM(BG4:BI4) -> 189.33 | BK4: 182.36 | BL4: 185.53 | BM4: 191.02 | BO4: 236.812 | BP4: 246.337 | CG4: =SUM(AQ4:AT4) -> 657.703 | CH4: =SUM(AU4:AX4) -> 700.24 | CI4: =SUM(AY4:BB4) -> 683.612 | CJ4: =SUM(BC4:BF4) -> 708.04 | CK4: =SUM(BG4:BJ4) -> 732.67 | CL4: =CK4*(1+CL13) -> 752.81843 | CM4: =CL4*(1+CM13) -> 779.16707 | CN4: =CM4*(1+CN13) -> 810.33375 | CO4: =CN4*(1+CO13) -> 844.36777 | CP4: =CO4*(1+CP13) -> 878.14248 | CQ4: =CP4*(1+CQ13) -> 911.5119 | CR4: =CQ4*(1+CR13) -> 944.32632 | CS4: =CR4*(1+CS13) -> 976.43342 | ... CU4: =CT4*(1+CU13) -> 1037.9097
B5: Interventional Cardiology | AQ5: 99.93 | AR5: 82.594 | AS5: 93.18 | AT5: =382.43-SUM(AQ5:AS5) -> 106.726 | AU5: 96.173 | AV5: 112.08 | AW5: 104.304 | AX5: =427.5-SUM(AU5:AW5) -> 114.943 | AY5: 96.85 | AZ5: 114.34 | BA5: 97.6 | BB5: =445.01-SUM(AY5:BA5) -> 136.22 | BC5: 116.89 | BD5: 124.78 | BE5: 134.089 | BF5: =511.434-SUM(BC5:BE5) -> 135.675 | BG5: 134.665 | BH5: 141.15 | BI5: 149.86 | BJ5: =586.05-SUM(BG5:BI5) -> 160.375 | BK5: 137.55 | BL5: 170.01 | BM5: 266.41 | BO5: 204.656 | BP5: 211.874 | CG5: =SUM(AQ5:AT5) -> 382.43 | CH5: =SUM(AU5:AX5) -> 427.5 | CI5: =SUM(AY5:BB5) -> 445.01 | CJ5: =SUM(BC5:BF5) -> 511.434 | CK5: =SUM(BG5:BJ5) -> 586.05 | CL5: =CK5*(1+CL14) -> 785.307 | CM5: =CL5*(1+CM14) -> 973.78068 | CN5: =CM5*(1+CN14) -> 1129.5856 | CO5: =CN5*(1+CO14) -> 1287.7276 | CP5: =CO5*(1+CP14) -> 1442.2549 | CQ5: =CP5*(1+CQ14) -> 1586.4804 | CR5: =CQ5*(1+CR14) -> 1729.2636 | CS5: =CR5*(1+CS14) -> 1867.6047 | ... CU5: =CT5*(1+CU14) -> 2118.2372
B6: Anesthesia | AQ6: 75.7 | AR6: 64.867 | AS6: 75.64 | AT6: =302.293-SUM(AQ5:AS5) -> 26.589 | AU6: 84.85 | AV6: 95.42 | AW6: 97.07 | AX6: =380.14-SUM(AU6:AW6) -> 102.8 | AY6: 86.95 | AZ6: 104.695 | BA6: 108.73 | BB6: =388.89-SUM(AY6:BA6) -> 88.515 | BC6: 93.33 | BD6: 100.84 | BE6: 97.61 | BF6: =389.957-SUM(BC6:BE6) -> 98.177 | BG6: 96.352 | BH6: 102.49 | BI6: 101.15 | BJ6: =395.28-SUM(BG6:BI6) -> 95.288 | BK6: 86.59 | BL6: 96.38 | BM6: 101.44 | BO6: 0 | BP6: 0 | CG6: =SUM(AQ6:AT6) -> 242.796 | CH6: =SUM(AU6:AX6) -> 380.14 | CI6: =SUM(AW6:BB6) -> 588.76 | CJ6: =SUM(AW6:BF6) -> 978.717 | CK6: =SUM(BG6:BJ6) -> 395.28 | CL6: =CK6*(1+CL15) -> 379.4688 | CM6: =CL6*(1+CM15) -> 246.65472 | CN6: =CM6*(1+CN15) -> 0 | CO6: =CN6*(1+CO15) -> 0 | CP6: =CO6*(1+CP15) -> 0 | CQ6: =CP6*(1+CQ15) -> 0 | CR6: =CQ6*(1+CR15) -> 0 | CS6: =CR6*(1+CS15) -> 0 | ... CU6: =CT6*(1+CU15) -> 0
B7: Surgical | AQ7: 75.432 | AR7: 67.275 | AS7: 82.22 | AT7: =317.2-SUM(AQ7:AS7) -> 92.273 | AU7: 80.386 | AV7: 98.18 | AW7: 92.83 | AX7: =377.75-SUM(AU7:AW7) -> 106.354 | AY7: 89.7 | AZ7: 99.64 | BA7: 93.12 | BB7: =392.91-SUM(AY7:BA7) -> 110.45 | BC7: 99.02 | BD7: 105.95 | BE7: 112.8 | BF7: =427.359-SUM(BC7:BE7) -> 109.589 | BG7: 105.52 | BH7: 111.3 | BI7: 111.746 | BJ7: =450.48-SUM(BG7:BI7) -> 121.914 | BK7: 105.78 | BL7: 114.04 | BM7: 122.87 | BO7: 106.794 | BP7: 112.121 | CG7: =SUM(AQ7:AT7) -> 317.2 | CH7: =SUM(AU7:AX7) -> 377.75 | CI7: =SUM(AY7:BB7) -> 392.91 | CJ7: =SUM(BC7:BF7) -> 427.359 | CK7: =SUM(BG7:BJ7) -> 450.48 | CL7: =CK7*(1+CL16) -> 477.5088 | CM7: =CL7*(1+CM16) -> 515.7095 | CN7: =CM7*(1+CN16) -> 551.80917 | CO7: =CN7*(1+CO16) -> 584.91772 | CP7: =CO7*(1+CP16) -> 617.08819 | CQ7: =CP7*(1+CQ16) -> 647.9426 | CR7: =CQ7*(1+CR16) -> 677.10002 | CS7: =CR7*(1+CS16) -> 704.18402 | ... CU7: =CT7*(1+CU16) -> 761.64544
B8: Interventional Urology | AQ8: 74.19 | AR8: 40.09 | AS8: 81.77 | AT8: =290.02-SUM(AQ8:AS8) -> 93.97 | AU8: 73.36 | AV8: 92.24 | AW8: 83.107 | AX8: =341.66-SUM(AU8:AW8) -> 92.953 | AY8: 74.89 | AZ8: 79.81 | BA8: 78.969 | BB8: =322.83-SUM(AY8:BA8) -> 89.161 | BC8: 75.37 | BD8: 77.81 | BE8: 73.622 | BF8: =319.785-SUM(BC8:BE8) -> 92.983 | BG8: 79.74 | BH8: 83.1 | BI8: 83.39 | BJ8: =331.092-SUM(BG8:BI8) -> 84.862 | BK8: 70.96 | BL8: 76.38 | BM8: 71.77 | BO8: 0 | BP8: 0 | CG8: =SUM(AQ8:AT8) -> 290.02 | CH8: =SUM(AU8:AX8) -> 341.66 | CI8: =SUM(AY8:BB8) -> 322.83 | CJ8: =SUM(BC8:BF8) -> 319.785 | CK8: =SUM(BG8:BJ8) -> 331.092 | CL8: =CK8*(1+CL17) -> 281.4282 | CM8: =CL8*(1+CM17) -> 140.7141 | CN8: =CM8*(1+CN17) -> 0 | CO8: =CN8*(1+CO17) -> 0 | CP8: =CO8*(1+CP17) -> 0 | CQ8: =CP8*(1+CQ17) -> 0 | CR8: =CQ8*(1+CR17) -> 0 | CS8: =CR8*(1+CS17) -> 0 | ... CU8: =CT8*(1+CU17) -> 0
B9: OEM | AQ9: 63.389 | AR9: 55.832 | AS9: 49.399 | AT9: =220.246-SUM(AQ9:AS9) -> 51.626 | AU9: 53.48 | AV9: 60.95 | AW9: 64.08 | AX9: =245.681-SUM(AU9:AW9) -> 67.171 | AY9: 57.656 | AZ9: 70 | BA9: 71.28 | BB9: =272.624-SUM(AY9:BA9) -> 73.688 | BC9: 76.99 | BD9: 84.12 | BE9: 82.309 | BF9: =326.008-SUM(BC9:BE9) -> 82.589 | BG9: 87.69 | BH9: 88.82 | BI9: 82.55 | BJ9: =344.51-SUM(BG9:BI9) -> 85.45 | BK9: 63.88 | BL9: 78.67 | BM9: 80.41 | BO9: 0 | BP9: 0 | CG9: =SUM(AQ9:AT9) -> 220.246 | CH9: =SUM(AU9:AX9) -> 245.681 | CI9: =SUM(AY9:BB9) -> 272.624 | CJ9: =SUM(BC9:BF9) -> 326.008 | CK9: =SUM(BG9:BJ9) -> 344.51 | CL9: =CK9*(1+CL18) -> 294.55605 | CM9: =CL9*(1+CM18) -> 265.10044 | CN9: =CM9*(1+CN18) -> 0 | CO9: =CN9*(1+CO18) -> 0 | CP9: =CO9*(1+CP18) -> 0 | CQ9: =CP9*(1+CQ18) -> 0 | CR9: =CQ9*(1+CR18) -> 0 | CS9: =CR9*(1+CS18) -> 0 | ... CU9: =CT9*(1+CU18) -> 0
B10: Other | AQ10: 91.73 | AR10: 91.414 | AS10: 86.02 | AT10: =367.25-SUM(AQ10:AS10) -> 98.086 | AU10: 81.683 | AV10: 86.84 | AW10: 83.37 | AX10: =336.585-SUM(AU10:AW10) -> 84.692 | AY10: 69.512 | AZ10: 72.13 | BA10: 69.9 | BB10: =285.148-SUM(AY10:BA10) -> 73.606 | BC10: 71.65 | BD10: 75.95 | BE10: 76.033 | BF10: =291.902-SUM(BC10:BE10) -> 68.269 | BG10: 52.51 | BH10: 41.7 | BI10: 54.76 | BJ10: =207.222-SUM(BG10:BI10) -> 58.252 | BK10: 53.6 | BL10: 59.84 | BM10: 79.07 | BO10: 0 | BP10: 0 | CG10: =SUM(AQ10:AT10) -> 367.25 | CH10: =SUM(AU10:AX10) -> 336.585 | CI10: =SUM(AY10:BB10) -> 285.148 | CJ10: =SUM(BC10:BF10) -> 291.902 | CK10: =SUM(BG10:BJ10) -> 207.222 | CL10: =CK10*(1+CL19) -> 261.09972 | CM10: =CL10*(1+CM19) -> 266.32171 | CN10: =CM10*(1+CN19) -> 271.64815 | CO10: =CN10*(1+CO19) -> 277.08111 | CP10: =CO10*(1+CP19) -> 282.62273 | CQ10: =CP10*(1+CQ19) -> 288.27519 | CR10: =CQ10*(1+CR19) -> 294.04069 | CS10: =CR10*(1+CS19) -> 299.92151 | ... CU10: =CT10*(1+CU19) -> 312.03834
B11: Ttl Revenues | AQ11: =SUM(AQ4:AQ10) -> 630.621 | AR11: =SUM(AR4:AR10) -> 567.03 | AS11: =SUM(AS4:AS10) -> 628.279 | AT11: =SUM(AT4:AT10) -> 651.715 | AU11: =SUM(AU4:AU10) -> 633.902 | AV11: =SUM(AV4:AV10) -> 713.44 | AW11: =SUM(AW4:AW10) -> 700.231 | AX11: =SUM(AX4:AX10) -> 761.983 | ... BM11: =SUM(BM4:BM10) -> 912.99 | BO11: =SUM(BO4:BO10) -> 548.262 | BP11: =SUM(BP4:BP10) -> 570.332 | CG11: =SUM(AQ11:AT11) -> 2477.645 | CH11: =SUM(AU11:AX11) -> 2809.556 | CI11: =SUM(AY11:BB11) -> 2791.024 | CJ11: =SUM(BC11:BF11) -> 2974.485 | CK11: =SUM(BG11:BJ11) -> 3047.304 | CL11: =SUM(CL4:CL10) -> 3232.187 | CM11: =SUM(CM4:CM10) -> 3187.4482 | CN11: =SUM(CN4:CN10) -> 2763.3767 | CO11: =SUM(CO4:CO10) -> 2994.0942 | CP11: =SUM(CP4:CP10) -> 3220.1083 | CQ11: =SUM(CQ4:CQ10) -> 3434.2101 | CR11: =SUM(CR4:CR10) -> 3644.7306 | CS11: =SUM(CS4:CS10) -> 3848.1436 | ... CU11: =SUM(CU4:CU10) -> 4229.8307
B13: Vascular Access Growth Y/y | AU13: =AU4/AQ4-1 -> 0.091314476 | AV13: =AV4/AR4-1 -> 0.016804277 | AW13: =AW4/AS4-1 -> 0.096344892 | AX13: =AX4/AT4-1 -> 0.058236729 | AY13: =AY4/AU4-1 -> 0.013173141 | AZ13: =AZ4/AV4-1 -> -0.022834317 | BA13: =BA4/AW4-1 -> -0.047472502 | BB13: =BB4/AX4-1 -> -0.034329518 | ... BM13: =BM4/BI4-1 -> 0.056000885 | BO13: =BO4/BK4-1 -> 0.29859618 | BP13: =BP4/BL4-1 -> 0.32774753 | CH13: =CH4/CG4-1 -> 0.064675089 | CI13: =CI4/CH4-1 -> -0.023746144 | CJ13: =CJ4/CI4-1 -> 0.03573372 | CK13: =CK4/CJ4-1 -> 0.03478617 | CL13: 0.0275 | CM13: 0.035 | CN13: 0.04 | CO13: 0.042 | CP13: 0.04 | CQ13: 0.038 | CR13: 0.036 | CS13: 0.034 | CT13: 0.032 | CU13: 0.03
B14: Vascular Intervention Growth Y/y | AU14: =AU5/AQ5-1 -> -0.037596317 | AV14: =AV5/AR5-1 -> 0.3569993 | AW14: =AW5/AS5-1 -> 0.11938184 | AX14: =AX5/AT5-1 -> 0.076991548 | AY14: =AY5/AU5-1 -> 0.0070393978 | AZ14: =AZ5/AV5-1 -> 0.020164168 | BA14: =BA5/AW5-1 -> -0.064273662 | BB14: =BB5/AX5-1 -> 0.18510914 | ... BM14: =BM5/BI5-1 -> 0.77772588 | BO14: =BO5/BK5-1 -> 0.48786623 | BP14: =BP5/BL5-1 -> 0.24624434 | CH14: =CH5/CG5-1 -> 0.11785163 | CI14: =CI5/CH5-1 -> 0.040959064 | CJ14: =CJ5/CI5-1 -> 0.14926406 | CK14: =CK5/CJ5-1 -> 0.14589566 | CL14: 0.34 | CM14: 0.24 | CN14: 0.16 | CO14: 0.14 | CP14: 0.12 | CQ14: 0.1 | CR14: 0.09 | CS14: 0.08 | CT14: 0.07 | CU14: 0.06
B15: Anesthesia Growth Y/y | AU15: =AU6/AQ6-1 -> 0.12087186 | AV15: =AV6/AR6-1 -> 0.47100991 | AW15: =AW6/AS6-1 -> 0.28331571 | AX15: =AX6/AT6-1 -> 2.8662605 | AY15: =AY6/AU6-1 -> 0.024749558 | AZ15: =AZ6/AV6-1 -> 0.097201844 | BA15: =BA6/AW6-1 -> 0.1201195 | BB15: =BB6/AX6-1 -> -0.13895914 | ... BM15: =BM6/BI6-1 -> 0.0028670292 | BO15: =BO6/BK6-1 -> -1 | BP15: =BP6/BL6-1 -> -1 | CH15: =CH6/CG6-1 -> 0.56567654 | CI15: =CI6/CH6-1 -> 0.54879781 | CJ15: =CJ6/CI6-1 -> 0.6623361 | CK15: =CK6/CJ6-1 -> -0.59612431 | CL15: -0.04 | CM15: -0.35 | CN15: -1 | CO15: 0 | CP15: 0 | CQ15: 0 | CR15: 0 | CS15: 0 | CT15: 0 | CU15: 0
B16: Surgical Growth Y/y | AU16: =AU7/AQ7-1 -> 0.065675045 | AV16: =AV7/AR7-1 -> 0.45938313 | AW16: =AW7/AS7-1 -> 0.12904403 | AX16: =AX7/AT7-1 -> 0.15260152 | AY16: =AY7/AU7-1 -> 0.11586595 | AZ16: =AZ7/AV7-1 -> 0.014870646 | BA16: =BA7/AW7-1 -> 0.0031239901 | BB16: =BB7/AX7-1 -> 0.038512891 | ... BM16: =BM7/BI7-1 -> 0.099547187 | BO16: =BO7/BK7-1 -> 0.0095859331 | BP16: =BP7/BL7-1 -> -0.016827429 | CH16: =CH7/CG7-1 -> 0.19088903 | CI16: =CI7/CH7-1 -> 0.040132363 | CJ16: =CJ7/CI7-1 -> 0.087676567 | CK16: =CK7/CJ7-1 -> 0.054102055 | CL16: 0.06 | CM16: 0.08 | CN16: 0.07 | CO16: 0.06 | CP16: 0.055 | CQ16: 0.05 | CR16: 0.045 | CS16: 0.04 | CT16: 0.04 | CU16: 0.04
B17: Interventional Urology Growth Y/y | AU17: =AU8/AQ8-1 -> -0.011187492 | AV17: =AV8/AR8-1 -> 1.3008231 | AW17: =AW8/AS8-1 -> 0.01635074 | AX17: =AX8/AT8-1 -> -0.010822603 | AY17: =AY8/AU8-1 -> 0.020856052 | AZ17: =AZ8/AV8-1 -> -0.13475716 | BA17: =BA8/AW8-1 -> -0.049791233 | BB17: =BB8/AX8-1 -> -0.04079481 | ... BM17: =BM8/BI8-1 -> -0.13934525 | BO17: =BO8/BK8-1 -> -1 | BP17: =BP8/BL8-1 -> -1 | CH17: =CH8/CG8-1 -> 0.17805669 | CI17: =CI8/CH8-1 -> -0.055113271 | CJ17: =CJ8/CI8-1 -> -0.0094322089 | CK17: =CK8/CJ8-1 -> 0.035358131 | CL17: -0.15 | CM17: -0.5 | CN17: -1 | CO17: 0 | CP17: 0 | CQ17: 0 | CR17: 0 | CS17: 0 | CT17: 0 | CU17: 0
B18: OEM Growth Y/y | AU18: =AU9/AQ9-1 -> -0.1563205 | AV18: =AV9/AR9-1 -> 0.091667861 | AW18: =AW9/AS9-1 -> 0.29719225 | AX18: =AX9/AT9-1 -> 0.30110797 | AY18: =AY9/AU9-1 -> 0.078085266 | AZ18: =AZ9/AV9-1 -> 0.14848236 | BA18: =BA9/AW9-1 -> 0.11235955 | BB18: =BB9/AX9-1 -> 0.097021036 | ... BM18: =BM9/BI9-1 -> -0.025923683 | BO18: =BO9/BK9-1 -> -1 | BP18: =BP9/BL9-1 -> -1 | CH18: =CH9/CG9-1 -> 0.1154845 | CI18: =CI9/CH9-1 -> 0.1096666 | CJ18: =CJ9/CI9-1 -> 0.19581548 | CK18: =CK9/CJ9-1 -> 0.056753209 | CL18: -0.145 | CM18: -0.1 | CN18: -1 | CO18: 0 | CP18: 0 | CQ18: 0 | CR18: 0 | CS18: 0 | CT18: 0 | CU18: 0
B19: Other Growth Y/y | AU19: =AU10/AQ10-1 -> -0.10952796 | AV19: =AV10/AR10-1 -> -0.0500361 | AW19: =AW10/AS10-1 -> -0.030806789 | AX19: =AX10/AT10-1 -> -0.13655364 | AY19: =AY10/AU10-1 -> -0.14900285 | AZ19: =AZ10/AV10-1 -> -0.16939199 | BA19: =BA10/AW10-1 -> -0.16156891 | BB19: =BB10/AX10-1 -> -0.13089784 | ... BM19: =BM10/BI10-1 -> 0.44393718 | BO19: =BO10/BK10-1 -> -1 | BP19: =BP10/BL10-1 -> -1 | CH19: =CH10/CG10-1 -> -0.083498979 | CI19: =CI10/CH10-1 -> -0.15282024 | CJ19: =CJ10/CI10-1 -> 0.023685946 | CK19: =CK10/CJ10-1 -> -0.29009736 | CL19: 0.26 | CM19: 0.02 | CN19: 0.02 | CO19: 0.02 | CP19: 0.02 | CQ19: 0.02 | CR19: 0.02 | CS19: 0.02 | CT19: 0.02 | CU19: 0.02
B20: Ttl Revenues Growth Y/y | AU20: =AU11/AQ11-1 -> 0.005202808 | AV20: =AV11/AR11-1 -> 0.25820503 | AW20: =AW11/AS11-1 -> 0.11452237 | AX20: =AX11/AT11-1 -> 0.16919666 | AY20: =AY11/AU11-1 -> 0.012282656 | AZ20: =AZ11/AV11-1 -> -0.012509812 | BA20: =BA11/AW11-1 -> -0.019267927 | BB20: =BB11/AX11-1 -> -0.0051195368 | ... BM20: =BM11/BI11-1 -> 0.19447214 | BO20: =BO11/BK11-1 -> -0.21757335 | BP20: =BP11/BL11-1 -> -0.26960108 | CH20: =CH11/CG11-1 -> 0.13396229 | CI20: =CI11/CH11-1 -> -0.00659606 | CJ20: =CJ11/CI11-1 -> 0.065732505 | CK20: =CK11/CJ11-1 -> 0.024481213 | CL20: =CL11/CK11-1 -> 0.060671005 | CM20: =CM11/CL11-1 -> -0.013841638 | CN20: =CN11/CM11-1 -> -0.13304422 | CO20: =CO11/CN11-1 -> 0.083491157 | ... CU20: =CU11/CT11-1 -> 0.045877809
B22: Vascular Access % of Ttl Revenues | AQ22: =AQ4/AQ11 -> 0.23825721 | AR22: =AR4/AR11 -> 0.29091582 | AS22: =AS4/AS11 -> 0.25474351 | AT22: =AT4/AT11 -> 0.27994599 | AU22: =AU4/AU11 -> 0.25866774 | AV22: =AV4/AV11 -> 0.23510036 | AW22: =AW4/AW11 -> 0.25058873 | AX22: =AX4/AX11 -> 0.25337836 | ... BM22: =BM4/BM11 -> 0.20922464 | BO22: =BO4/BO11 -> 0.43193218 | BP22: =BP4/BP11 -> 0.4319186 | CG22: =CG4/CG11 -> 0.2654549 | CH22: =CH4/CH11 -> 0.24923511 | CI22: =CI4/CI11 -> 0.24493233 | CJ22: =CJ4/CJ11 -> 0.23803785 | CK22: =CK4/CK11 -> 0.2404322
B23: Interventional % of Ttl Revenues | AQ23: =AQ5/AQ11 -> 0.15846285 | AR23: =AR5/AR11 -> 0.14566072 | AS23: =AS5/AS11 -> 0.14830991 | AT23: =AT5/AT11 -> 0.16376177 | AU23: =AU5/AU11 -> 0.15171588 | AV23: =AV5/AV11 -> 0.157098 | AW23: =AW5/AW11 -> 0.14895656 | AX23: =AX5/AX11 -> 0.1508472 | ... BM23: =BM5/BM11 -> 0.29179947 | BO23: =BO5/BO11 -> 0.37328139 | BP23: =BP5/BP11 -> 0.37149239 | CG23: =CG5/CG11 -> 0.15435222 | CH23: =CH5/CH11 -> 0.15215927 | CI23: =CI5/CI11 -> 0.15944327 | CJ23: =CJ5/CJ11 -> 0.17194035 | CK23: =CK5/CK11 -> 0.19231754
B24: Anesthesia % of Ttl Revenues | AQ24: =AQ6/AQ11 -> 0.1200404 | AR24: =AR6/AR11 -> 0.11439783 | AS24: =AS6/AS11 -> 0.12039237 | AT24: =AT6/AT11 -> 0.040798509 | AU24: =AU6/AU11 -> 0.1338535 | AV24: =AV6/AV11 -> 0.13374636 | AW24: =AW6/AW11 -> 0.13862568 | AX24: =AX6/AX11 -> 0.13491115 | ... BM24: =BM6/BM11 -> 0.11110746 | BO24: =BO6/BO11 -> 0 | BP24: =BP6/BP11 -> 0 | CG24: =CG6/CG11 -> 0.097994668 | CH24: =CH6/CH11 -> 0.13530252 | CI24: =CI6/CI11 -> 0.21094767 | CJ24: =CJ6/CJ11 -> 0.32903746 | CK24: =CK6/CK11 -> 0.12971466
B25: Surgical % of Ttl Revenues | AQ25: =AQ7/AQ11 -> 0.11961543 | AR25: =AR7/AR11 -> 0.11864452 | AS25: =AS7/AS11 -> 0.13086543 | AT25: =AT7/AT11 -> 0.1415849 | AU25: =AU7/AU11 -> 0.1268114 | AV25: =AV7/AV11 -> 0.13761494 | AW25: =AW7/AW11 -> 0.13257054 | AX25: =AX7/AX11 -> 0.13957529 | ... BM25: =BM7/BM11 -> 0.13457979 | BO25: =BO7/BO11 -> 0.19478643 | BP25: =BP7/BP11 -> 0.196589 | CG25: =CG7/CG11 -> 0.1280248 | CH25: =CH7/CH11 -> 0.13445185 | CI25: =CI7/CI11 -> 0.14077629 | CJ25: =CJ7/CJ11 -> 0.14367496 | CK25: =CK7/CK11 -> 0.14782903
B26: Interventional Urology % of Ttl Revenues | AQ26: =AQ8/AQ11 -> 0.11764594 | AR26: =AR8/AR11 -> 0.070701727 | AS26: =AS8/AS11 -> 0.13014919 | AT26: =AT8/AT11 -> 0.14418879 | AU26: =AU8/AU11 -> 0.11572767 | AV26: =AV8/AV11 -> 0.12928908 | AW26: =AW8/AW11 -> 0.11868512 | AX26: =AX8/AX11 -> 0.12198829 | ... BM26: =BM8/BM11 -> 0.078609842 | BO26: =BO8/BO11 -> 0 | BP26: =BP8/BP11 -> 0 | CG26: =CG8/CG11 -> 0.1170547 | CH26: =CH8/CH11 -> 0.1216064 | CI26: =CI8/CI11 -> 0.11566722 | CJ26: =CJ8/CJ11 -> 0.10750937 | CK26: =CK8/CK11 -> 0.10865079
B27: OEM % of Ttl Revenues | AQ27: =AQ9/AQ11 -> 0.10051838 | AR27: =AR9/AR11 -> 0.098463926 | AS27: =AS9/AS11 -> 0.078625897 | AT27: =AT9/AT11 -> 0.079215608 | AU27: =AU9/AU11 -> 0.084366353 | AV27: =AV9/AV11 -> 0.08543115 | AW27: =AW9/AW11 -> 0.091512658 | AX27: =AX9/AX11 -> 0.088152885 | ... BM27: =BM9/BM11 -> 0.088073254 | BO27: =BO9/BO11 -> 0 | BP27: =BP9/BP11 -> 0 | CG27: =CG9/CG11 -> 0.088893284 | CH27: =CH9/CH11 -> 0.087444778 | CI27: =CI9/CI11 -> 0.097678845 | CJ27: =CJ9/CJ11 -> 0.10960149 | CK27: =CK9/CK11 -> 0.11305403
B28: Other % of Ttl Revenues | AQ28: =AQ10/AQ11 -> 0.14545979 | AR28: =AR10/AR11 -> 0.16121546 | AS28: =AS10/AS11 -> 0.1369137 | AT28: =AT10/AT11 -> 0.15050444 | AU28: =AU10/AU11 -> 0.12885746 | AV28: =AV10/AV11 -> 0.12172012 | AW28: =AW10/AW11 -> 0.11906071 | AX28: =AX10/AX11 -> 0.11114684 | ... BM28: =BM10/BM11 -> 0.086605549 | BO28: =BO10/BO11 -> 0 | BP28: =BP10/BP11 -> 0 | CG28: =CG10/CG11 -> 0.14822543 | CH28: =CH10/CH11 -> 0.11980007 | CI28: =CI10/CI11 -> 0.10216609 | CJ28: =CJ10/CJ11 -> 0.098135307 | CK28: =CK10/CK11 -> 0.068001748
B30: U.S. Revenues | BC30: =411.86+76.99 -> 488.85 | BD30: =424.64+84.128 -> 508.768 | BE30: =428.206+82.309 -> 510.515 | BF30: =2041.4-SUM(BC30:BE30) -> 533.267 | BG30: 494 | BH30: 515.6 | BI30: =433.3+82.6 -> 515.9 | BJ30: =2066.3-SUM(BG30:BI30) -> 540.8 | BK30: 475.7 | BL30: 525.7 | BM30: 555.9 | BN30: =1279.197-SUM(BK30:BM30) -> -278.103 | BO30: 332.653 | BP30: 348.838 | CJ30: =SUM(BC30:BF30) -> 2041.4 | CK30: =SUM(BG30:BJ30) -> 2066.3
B31: EMEA Revenues | BC31: 143.34 | BD31: 147.809 | BE31: 142.723 | BF31: =586.2-SUM(BC31:BE31) -> 152.328 | BG31: 159.6 | BH31: 147.1 | BI31: 150.22 | BJ31: =618-SUM(BG31:BI31) -> 161.08 | BK31: 151.2 | BL31: 166.2 | BM31: 234.24 | BN31: =472.411-SUM(BK31:BM31) -> -79.229 | BO31: 146.678 | BP31: 145.531 | CJ31: =SUM(BC31:BF31) -> 586.2 | CK31: =SUM(BG31:BJ31) -> 618
B32: Asia Revenues | BC32: 78.731 | BD32: 86.678 | BE32: 93.151 | BF32: =346.9-SUM(BC32:BE32) -> 88.34 | BG32: 84.2 | BH32: 87 | BI32: 98.26 | BJ32: =363-SUM(BG32:BI32) -> 93.54 | BK32: 73.8 | BL32: 89 | BM32: 122.87 | BN32: =241.105-SUM(BK32:BM32) -> -44.565 | BO32: 68.93 | BP32: 75.963 | CJ32: =SUM(BC32:BF32) -> 346.9 | CK32: =SUM(BG32:BJ32) -> 363
B33: Ttl Revenues | BC33: =SUM(BC30:BC32) -> 710.921 | BD33: =SUM(BD30:BD32) -> 743.255 | BE33: =SUM(BE30:BE32) -> 746.389 | BF33: =SUM(BF30:BF32) -> 773.935 | BG33: =SUM(BG30:BG32) -> 737.8 | BH33: =SUM(BH30:BH32) -> 749.7 | BI33: =SUM(BI30:BI32) -> 764.38 | BJ33: =SUM(BJ30:BJ32) -> 795.42 | ... BP33: =SUM(BP30:BP32) -> 570.332 | CJ33: =SUM(BC33:BF33) -> 2974.5 | CK33: =SUM(BG33:BJ33) -> 3047.3
B35: U.S. Revenues Growth Y/y | BG35: =BG30/BC30-1 -> 0.010534929 | BH35: =BH30/BD30-1 -> 0.013428518 | BI35: =BI30/BE30-1 -> 0.010548172 | BJ35: =BJ30/BF30-1 -> 0.014126132 | BK35: =BK30/BG30-1 -> -0.037044534 | BL35: =BL30/BH30-1 -> 0.019588829 | BM35: =BM30/BI30-1 -> 0.077534406 | BN35: =BN30/BJ30-1 -> -1.5142437 | ... BP35: =BP30/BL30-1 -> -0.33643142 | CK35: =CK30/CJ30-1 -> 0.012197512
B36: EMEA Revenues Growth Y/y | BG36: =BG31/BC31-1 -> 0.11343658 | BH36: =BH31/BD31-1 -> -0.0047967309 | BI36: =BI31/BE31-1 -> 0.052528324 | BJ36: =BJ31/BF31-1 -> 0.057454966 | BK36: =BK31/BG31-1 -> -0.052631579 | BL36: =BL31/BH31-1 -> 0.12984364 | BM36: =BM31/BI31-1 -> 0.55931301 | BN36: =BN31/BJ31-1 -> -1.4918612 | ... BP36: =BP31/BL31-1 -> -0.12436221 | CK36: =CK31/CJ31-1 -> 0.054247697
B37: Asia Revenues Growth Y/y | BG37: =BG32/BC32-1 -> 0.069464379 | BH37: =BH32/BD32-1 -> 0.0037148988 | BI37: =BI32/BE32-1 -> 0.054846432 | BJ37: =BJ32/BF32-1 -> 0.058863482 | BK37: =BK32/BG32-1 -> -0.12351544 | BL37: =BL32/BH32-1 -> 0.022988506 | BM37: =BM32/BI32-1 -> 0.25045797 | BN37: =BN32/BJ32-1 -> -1.4764272 | ... BP37: =BP32/BL32-1 -> -0.14648315 | CK37: =CK32/CJ32-1 -> 0.046411069
B38: Ttl Revenues Growth Y/y | BG38: =BG33/BC33-1 -> 0.037808702 | BH38: =BH33/BD33-1 -> 0.0086713174 | BI38: =BI33/BE33-1 -> 0.024104053 | BJ38: =BJ33/BF33-1 -> 0.027760729 | BK38: =BK33/BG33-1 -> -0.05028463 | BL38: =BL33/BH33-1 -> 0.041616647 | BM38: =BM33/BI33-1 -> 0.19444517 | BN38: =BN33/BJ33-1 -> -1.5052639 | ... BP38: =BP33/BL33-1 -> -0.26964784 | CK38: =CK33/CJ33-1 -> 0.024474702
B40: U.S. Revenues % of Revenues | BC40: =BC30/BC33 -> 0.68762915 | BD40: =BD30/BD33 -> 0.68451339 | BE40: =BE30/BE33 -> 0.6839798 | BF40: =BF30/BF33 -> 0.68903332 | BG40: =BG30/BG33 -> 0.66955815 | BH40: =BH30/BH33 -> 0.68774176 | BI40: =BI30/BI33 -> 0.67492608 | BJ40: =BJ30/BJ33 -> 0.67989238 | ... BP40: =BP30/BP33 -> 0.61164024 | CJ40: =CJ30/CJ33 -> 0.68630022 | CK40: =CK30/CK33 -> 0.67807567
B41: EMEA Revenues % of Revenues | BC41: =BC31/BC33 -> 0.20162578 | BD41: =BD31/BD33 -> 0.19886715 | BE41: =BE31/BE33 -> 0.19121798 | BF41: =BF31/BF33 -> 0.19682273 | BG41: =BG31/BG33 -> 0.21631879 | BH41: =BH31/BH33 -> 0.19621182 | BI41: =BI31/BI33 -> 0.19652529 | BJ41: =BJ31/BJ33 -> 0.20250937 | ... BP41: =BP31/BP33 -> 0.25516892 | CJ41: =CJ31/CJ33 -> 0.19707514 | CK41: =CK31/CK33 -> 0.20280248
B42: Asia Revenues % of Revenues | BC42: =BC32/BC33 -> 0.11074508 | BD42: =BD32/BD33 -> 0.11661946 | BE42: =BE32/BE33 -> 0.12480221 | BF42: =BF32/BF33 -> 0.11414395 | BG42: =BG32/BG33 -> 0.11412307 | BH42: =BH32/BH33 -> 0.11604642 | BI42: =BI32/BI33 -> 0.12854863 | BJ42: =BJ32/BJ33 -> 0.11759825 | ... BP42: =BP32/BP33 -> 0.13319084 | CJ42: =CJ32/CJ33 -> 0.11662464 | CK42: =CK32/CK33 -> 0.11912185
B44: Revenues | C44: 367.3 | D44: 358.4 | E44: 345 | F44: 326.9 | G44: 354 | H44: 381.2 | I44: 362.7 | J44: 394.6 | K44: 380.6 | L44: 383.3 | M44: 368.1 | N44: 419.1 | O44: 411.9 | P44: 420.1 | Q44: 413.8 | R44: 450.5 | S44: 438.5 | T44: 468.1 | U44: 457.2 | V44: 476 | W44: 429.4 | X44: 452 | Y44: 443.7 | Z44: 484.5 | AA44: 424.9 | AB44: 473.6 | AC44: 455.6 | AD44: 513.9 | AE44: 487.9 | AF44: 528.6 | AG44: 534.7 | AH44: 595.1 | AI44: 587.2 | AJ44: 609.9 | AK44: 609.7 | AL44: 641.6 | AM44: 613.6 | AN44: 652.5 | AO44: 648.3 | AP44: 681 | AQ44: =AQ11 -> 630.621 | AR44: =AR11 -> 567.03 | AS44: =AS11 -> 628.279 | AT44: =AT11 -> 651.715 | AU44: =AU11 -> 633.902 | AV44: =AV11 -> 713.44 | AW44: =AW11 -> 700.231 | AX44: =AX11 -> 761.983 | ... BM44: =BM11 -> 912.99 | BN44: 530 | BO44: =BO33 -> 548.261 | BP44: =BP33 -> 570.332 | BW44: =SUM(C44:F44) -> 1397.6 | BX44: =SUM(G44:J44) -> 1492.5 | BY44: =SUM(K44:N44) -> 1551.1 | BZ44: =SUM(O44:R44) -> 1696.3 | CA44: =SUM(S44:V44) -> 1839.8 | CB44: =SUM(W44:Z44) -> 1809.6 | CC44: =SUM(AA44:AD44) -> 1868 | CD44: =SUM(AE44:AH44) -> 2146.3 | CE44: =SUM(AI44:AL44) -> 2448.4 | CF44: =SUM(AM44:AP44) -> 2595.4 | CG44: =SUM(AQ44:AT44) -> 2477.645 | CH44: =SUM(AU44:AX44) -> 2809.556 | CI44: =SUM(AY44:BB44) -> 2791.024 | CJ44: =SUM(BC44:BF44) -> 2974.485 | CK44: =SUM(BG44:BJ44) -> 3047.304 | CL44: =CL11 -> 3232.187 | CM44: =CM11 -> 3187.4482 | CN44: =CN11 -> 2763.3767 | CO44: =CO11 -> 2994.0942 | CP44: =CP11 -> 3220.1083 | CQ44: =CQ11 -> 3434.2101 | CR44: =CR11 -> 3644.7306 | CS44: =CS11 -> 3848.1436 | ... CU44: =CU11 -> 4229.8307
B45: COGS | C45: 190.4 | D45: 184.1 | E45: 178.5 | F45: 165.8 | G45: 189.5 | H45: 199.8 | I45: 187.1 | J45: 207.3 | K45: 196.5 | L45: 199 | M45: 187.5 | N45: 219.9 | O45: 211.4 | P45: 210.6 | Q45: 209.8 | R45: 225.6 | S45: 217.4 | T45: 224 | U45: 221 | V45: 235 | W45: 206.8 | X45: 218.8 | Y45: 215.5 | Z45: 224.2 | AA45: 199.7 | AB45: 217.2 | AC45: 214 | AD45: 240.9 | AE45: 232.3 | AF45: 238.3 | AG45: 239.5 | AH45: 264.4 | AI45: 256 | AJ45: 265.1 | AK45: 267.1 | AL45: 357.4 | AM45: 289.6 | AN45: 300.3 | AO45: 293.2 | AP45: 303.2 | AQ45: 297.018 | AR45: 288.66 | AS45: 298.977 | AT45: =1212.28-SUM(AQ45:AS45) -> 327.625 | AU45: 289.398 | AV45: 315.917 | AW45: 312.464 | AX45: =1259.961-SUM(AU45:AW45) -> 342.182 | AY45: 295.48 | AZ45: 315.709 | BA45: 312.833 | BB45: =1259.95-SUM(AY45:BA45) -> 335.928 | BC45: 319.55 | BD45: 335.436 | BE45: 330.07 | BF45: =1327.55-SUM(BC45:BE45) -> 342.494 | BG45: 321.715 | BH45: 333.23 | BI45: 334.203 | BJ45: =1344.64-SUM(BG45:BI45) -> 355.492 | BK45: 311.23 | BL45: 349.804 | BM45: 461.37 | BN45: =871.959-SUM(BK45:BM45) -> -250.445 | BO45: 240.836 | BP45: 238.625 | BW45: =SUM(C45:F45) -> 718.8 | BX45: =SUM(G45:J45) -> 783.7 | BY45: =SUM(K45:N45) -> 802.9 | BZ45: =SUM(O45:R45) -> 857.4 | CA45: =SUM(S45:V45) -> 897.4 | CB45: =SUM(W45:Z45) -> 865.3 | CC45: =SUM(AA45:AD45) -> 871.8 | CD45: =SUM(AE45:AH45) -> 974.5 | CE45: =SUM(AI45:AL45) -> 1145.6 | CF45: =SUM(AM45:AP45) -> 1186.3 | CG45: =SUM(AQ45:AT45) -> 1212.28 | CH45: =SUM(AU45:AX45) -> 1259.961 | CI45: =SUM(AY45:BB45) -> 1259.95 | CJ45: =SUM(BC45:BF45) -> 1327.55 | CK45: =SUM(BG45:BJ45) -> 1344.64 | CL45: =CL44*(1-CL63) -> 1422.1623 | CM45: =CM44*(1-CM63) -> 1386.54 | CN45: =CN44*(1-CN63) -> 1188.252 | CO45: =CO44*(1-CO63) -> 1287.4605 | CP45: =CP44*(1-CP63) -> 1384.6466 | CQ45: =CQ44*(1-CQ63) -> 1476.7103 | CR45: =CR44*(1-CR63) -> 1567.2342 | CS45: =CS44*(1-CS63) -> 1654.7018 | ... CU45: =CU44*(1-CU63) -> 1818.8272
B46: GP | C46: =C44-C45 -> 176.9 | D46: =D44-D45 -> 174.3 | E46: =E44-E45 -> 166.5 | F46: =F44-F45 -> 161.1 | G46: =G44-G45 -> 164.5 | H46: =H44-H45 -> 181.4 | I46: =I44-I45 -> 175.6 | J46: =J44-J45 -> 187.3 | ... BP46: =BP44-BP45 -> 331.707 | BW46: =SUM(C46:F46) -> 678.8 | BX46: =SUM(G46:J46) -> 708.8 | BY46: =SUM(K46:N46) -> 748.2 | BZ46: =SUM(O46:R46) -> 838.9 | CA46: =SUM(S46:V46) -> 942.4 | CB46: =SUM(W46:Z46) -> 944.3 | CC46: =SUM(AA46:AD46) -> 996.2 | CD46: =SUM(AE46:AH46) -> 1171.8 | CE46: =SUM(AI46:AL46) -> 1302.8 | CF46: =SUM(AM46:AP46) -> 1409.1 | CG46: =SUM(AQ46:AT46) -> 1265.365 | CH46: =SUM(AU46:AX46) -> 1549.595 | CI46: =SUM(AY46:BB46) -> 1531.074 | CJ46: =SUM(BC46:BF46) -> 1646.935 | CK46: =SUM(BG46:BJ46) -> 1702.664 | CL46: =CL44-CL45 -> 1810.0247 | CM46: =CM44-CM45 -> 1800.9083 | CN46: =CN44-CN45 -> 1575.1247 | CO46: =CO44-CO45 -> 1706.6337 | CP46: =CP44-CP45 -> 1835.4617 | CQ46: =CQ44-CQ45 -> 1957.4997 | CR46: =CR44-CR45 -> 2077.4965 | CS46: =CS44-CS45 -> 2193.4419 | ... CU46: =CU44-CU45 -> 2411.0035
B47: SG&A | C47: 100.6 | D47: 99.8 | E47: 101.5 | F47: 101.8 | G47: 103.2 | H47: 109.8 | I47: 101.6 | J47: 109.3 | K47: 112.1 | L47: 106 | M47: 114.9 | N47: 121.5 | O47: 127 | P47: 116.3 | Q47: 115.2 | R47: 143.8 | S47: 140.3 | T47: 146.8 | U47: 138.3 | V47: 153.3 | W47: 139.7 | X47: 142.2 | Y47: 138.8 | Z47: 148.2 | AA47: 136.3 | AB47: 143 | AC47: 139.8 | AD47: 144.2 | AE47: 164 | AF47: 158.9 | AG47: 163.8 | AH47: 213.3 | AI47: 215.3 | AJ47: 229.9 | AK47: 214.9 | AL47: 136.9 | AM47: 206.9 | AN47: 215.5 | AO47: 209.3 | AP47: 220.1 | AQ47: 147.796 | AR47: 191.193 | AS47: 171.67 | AT47: =743.568-SUM(AQ47:AS47) -> 232.909 | AU47: 203.148 | AV47: 224 | AW47: 205.194 | AX47: =860.08-SUM(AU47:AW47) -> 227.738 | AY47: 203.932 | AZ47: 216.825 | BA47: 209.6 | BB47: =863.748-SUM(AY47:BA47) -> 233.391 | BC47: 232.716 | BD47: 223.306 | BE47: 213.194 | BF47: =929.867-SUM(BC47:BE47) -> 260.651 | BG47: 242.83 | BH47: 250.631 | BI47: 247.257 | BJ47: =995.27-SUM(BG47:BI47) -> 254.552 | BK47: 222.71 | BL47: 215.08 | BM47: 281.76 | BN47: =720.169-SUM(BK47:BM47) -> 0.619 | BO47: 226.012 | BP47: 213.515 | BW47: =SUM(C47:F47) -> 403.7 | BX47: =SUM(G47:J47) -> 423.9 | BY47: =SUM(K47:N47) -> 454.5 | BZ47: =SUM(O47:R47) -> 502.3 | CA47: =SUM(S47:V47) -> 578.7 | CB47: =SUM(W47:Z47) -> 568.9 | CC47: =SUM(AA47:AD47) -> 563.3 | CD47: =SUM(AE47:AH47) -> 700 | CE47: =SUM(AI47:AL47) -> 797 | CF47: =SUM(AM47:AP47) -> 851.8 | CG47: =SUM(AQ47:AT47) -> 743.568 | CH47: =SUM(AU47:AX47) -> 860.08 | CI47: =SUM(AY47:BB47) -> 863.748 | CJ47: =SUM(BC47:BF47) -> 929.867 | CK47: =SUM(BG47:BJ47) -> 995.27 | CL47: =CL44*CL65 -> 985.81703 | CM47: =CM44*CM65 -> 1067.7952 | CN47: =CN44*CN65 -> 884.28053 | CO47: =CO44*CO65 -> 943.13966 | CP47: =CP44*CP65 -> 998.23357 | CQ47: =CQ44*CQ65 -> 1047.4341 | CR47: =CR44*CR65 -> 1093.4192 | CS47: =CS44*CS65 -> 1144.8227 | ... CU47: =CU44*CU65 -> 1247.8
B48: R&D | C48: 9.3 | D48: 10.3 | E48: 10.2 | F48: 12.6 | G48: 11 | H48: 12.5 | I48: 12.1 | J48: 13.5 | K48: 11.6 | L48: 13.6 | M48: 14.8 | N48: 16.4 | O48: 15 | P48: 16.5 | Q48: 15.6 | R48: 17.9 | S48: 14.1 | T48: 14.9 | U48: 14.8 | V48: 17.2 | W48: 12.9 | X48: 13.4 | Y48: 12.6 | Z48: 13.2 | AA48: 12.6 | AB48: 15 | AC48: 15.1 | AD48: 15.7 | AE48: 17.9 | AF48: 20.3 | AG48: 21 | AH48: 25.5 | AI48: 26 | AJ48: 26 | AK48: 26.4 | AL48: 27.8 | AM48: 27.3 | AN48: 27.5 | AO48: 28 | AP48: 30.8 | AQ48: 27.396 | AR48: 29.36 | AS48: 29.21 | AT48: =119.747-SUM(AQ48:AS48) -> 33.781 | AU48: 29.94 | AV48: 33.283 | AW48: 31.816 | AX48: =130.84-SUM(AU48:AW48) -> 35.801 | AY48: 36.36 | AZ48: 36.93 | BA48: 37.77 | BB48: =153.819-SUM(AY48:BA48) -> 42.759 | BC48: 41.469 | BD48: 39.448 | BE48: 37.576 | BF48: =154.35-SUM(BC48:BE48) -> 35.857 | BG48: 37.29 | BH48: 41.094 | BI48: 38.726 | BJ48: =161.67-SUM(BG48:BI48) -> 44.56 | BK48: 36.404 | BL48: 38.521 | BM48: 57.22 | BN48: =144.781-SUM(BK48:BM48) -> 12.636 | BO48: 44.386 | BP48: 45.122 | BW48: =SUM(C48:F48) -> 42.4 | BX48: =SUM(G48:J48) -> 49.1 | BY48: =SUM(K48:N48) -> 56.4 | BZ48: =SUM(O48:R48) -> 65 | CA48: =SUM(S48:V48) -> 61 | CB48: =SUM(W48:Z48) -> 52.1 | CC48: =SUM(AA48:AD48) -> 58.4 | CD48: =SUM(AE48:AH48) -> 84.7 | CE48: =SUM(AI48:AL48) -> 106.2 | CF48: =SUM(AM48:AP48) -> 113.6 | CG48: =SUM(AQ48:AT48) -> 119.747 | CH48: =SUM(AU48:AX48) -> 130.84 | CI48: =SUM(AY48:BB48) -> 153.819 | CJ48: =SUM(BC48:BF48) -> 154.35 | CK48: =SUM(BG48:BJ48) -> 161.67 | CL48: =CL44*CL64 -> 177.77028 | CM48: =CM44*CM64 -> 172.1222 | CN48: =CN44*CN64 -> 146.45896 | CO48: =CO44*CO64 -> 155.6929 | CP48: =CP44*CP64 -> 164.22552 | CQ48: =CQ44*CQ64 -> 171.7105 | CR48: =CR44*CR64 -> 182.23653 | CS48: =CS44*CS64 -> 192.40718 | ... CU48: =CU44*CU64 -> 211.49153
B49: Pension Settlement Charge | C49: 0 | D49: 0 | E49: 0 | F49: 0 | G49: 0 | H49: 0 | I49: 0 | J49: 0 | K49: 0 | L49: 0 | M49: 0 | N49: 0 | O49: 0 | P49: 0 | Q49: 0 | R49: 0 | S49: 0 | T49: 0 | U49: 0 | V49: 0 | W49: 0 | X49: 0 | Y49: 0 | Z49: 0 | AA49: 0 | AB49: 0 | AC49: 0 | AD49: 0 | AE49: 0 | AF49: 0 | AG49: 0 | AH49: 0 | AI49: 0 | AJ49: 0 | AK49: 0 | AL49: 0 | AM49: 0 | AN49: 0 | AO49: 0 | AP49: 0 | AQ49: 0 | AR49: 0 | AS49: 0 | AT49: =0-SUM(AQ49:AS49) -> 0 | AU49: 0 | AV49: 0 | AW49: 0 | AX49: =0-SUM(AU49:AW49) -> 0 | AY49: 0 | AZ49: 0 | BA49: 0 | BB49: =0-SUM(AY49:BA49) -> 0 | BC49: 0 | BD49: 0 | BE49: 0 | BF49: =45.244-SUM(BC49:BE49) -> 45.244 | BG49: 138.139 | BH49: 0 | BI49: -5.407 | BJ49: =132.73-SUM(BG49:BI49) -> -0.002 | BK49: 0 | BL49: 0 | BM49: 0 | BN49: =0-SUM(BK49:BM49) -> 0 | BO49: 0 | BP49: 0 | BW49: =SUM(C49:F49) -> 0 | BX49: =SUM(G49:J49) -> 0 | BY49: =SUM(K49:N49) -> 0 | BZ49: =SUM(O49:R49) -> 0 | CA49: =SUM(S49:V49) -> 0 | CB49: =SUM(W49:Z49) -> 0 | CC49: =SUM(AA49:AD49) -> 0 | CD49: =SUM(AE49:AH49) -> 0 | CE49: =SUM(AI49:AL49) -> 0 | CF49: =SUM(AM49:AP49) -> 0 | CG49: =SUM(AQ49:AT49) -> 0 | CH49: =SUM(AU49:AX49) -> 0 | CI49: =SUM(AY49:BB49) -> 0 | CJ49: =SUM(BC49:BF49) -> 45.244 | CK49: =SUM(BG49:BJ49) -> 132.73 | CL49: 0 | CM49: 0 | CN49: 0 | CO49: 0 | CP49: 0 | CQ49: 0 | CR49: 0 | CS49: 0 | CT49: 0 | CU49: 0
B50: Goodwill Impairment | C50: 0.4 | D50: 0 | E50: 1.3 | F50: 0.6 | G50: 0.6 | H50: 3.2 | I50: 0 | J50: 2.4 | K50: 330.8 | L50: 0 | M50: 1 | N50: 2.9 | O50: 9.1 | P50: 12.9 | Q50: 7.2 | R50: 9.1 | S50: 7.7 | T50: 7.6 | U50: 1.2 | V50: 1.3 | W50: 4.4 | X50: 0.6 | Y50: 0.2 | Z50: 2.2 | AA50: 8.8 | AB50: 0 | AC50: 0.2 | AD50: 46.1 | AE50: 12.9 | AF50: 0.9 | AG50: 0 | AH50: 1 | AI50: 3.1 | AJ50: 55.4 | AK50: 19.2 | AL50: 0.2 | AM50: 14.6 | AN50: 1.7 | AO50: 0.2 | AP50: 0 | AQ50: 0 | AR50: 0 | AS50: 0 | AT50: =0-SUM(AQ50:AS50) -> 0 | AU50: 0 | AV50: 0 | AW50: 0 | AX50: =0-SUM(AU50:AW50) -> 0 | AY50: 0 | AZ50: 0 | BA50: 0 | BB50: =0-SUM(AY50:BA50) -> 0 | BC50: 0 | BD50: 0 | BE50: 0 | BF50: =0-SUM(BC50:BE50) -> 0 | BG50: 0 | BH50: 0 | BI50: 0 | BJ50: =240-SUM(BG50:BI50) -> 240 | BK50: 0 | BL50: 0 | BM50: 403.92 | BN50: =0-SUM(BK50:BM50) -> -403.92 | BO50: 0 | BP50: 0 | BW50: =SUM(C50:F50) -> 2.3 | BX50: =SUM(G50:J50) -> 6.2 | BY50: =SUM(K50:N50) -> 334.7 | BZ50: =SUM(O50:R50) -> 38.3 | CA50: =SUM(S50:V50) -> 17.8 | CB50: =SUM(W50:Z50) -> 7.4 | CC50: =SUM(AA50:AD50) -> 55.1 | CD50: =SUM(AE50:AH50) -> 14.8 | CE50: =SUM(AI50:AL50) -> 77.9 | CF50: =SUM(AM50:AP50) -> 16.5 | CG50: =SUM(AQ50:AT50) -> 0 | CH50: =SUM(AU50:AX50) -> 0 | CI50: =SUM(AY50:BB50) -> 0 | CJ50: =SUM(BC50:BF50) -> 0 | CK50: =SUM(BG50:BJ50) -> 240 | CL50: 0 | CM50: 0 | CN50: 0 | CO50: 0 | CP50: 0 | CQ50: 0 | CR50: 0 | CS50: 0 | CT50: 0 | CU50: 0
B51: Restructuring Charge | C51: 0 | D51: 0 | E51: 0 | F51: 0 | G51: 0 | H51: 0 | I51: 0 | J51: 0 | K51: 0 | L51: 0 | M51: 0 | N51: 0 | O51: 0 | P51: 0 | Q51: 0 | R51: 0 | S51: 0 | T51: 0 | U51: 0 | V51: 0 | W51: 0 | X51: 0 | Y51: 0 | Z51: 0 | AA51: 0 | AB51: 0 | AC51: 0 | AD51: 0 | AE51: 0 | AF51: 0 | AG51: 0 | AH51: 0 | AI51: 0 | AJ51: 0 | AK51: 0 | AL51: 0 | AM51: 0 | AN51: 0 | AO51: 0 | AP51: 0 | AQ51: 1.346 | AR51: 19.005 | AS51: -3.659 | AT51: =38.491-SUM(AQ51:AS51) -> 21.799 | AU51: 7.998 | AV51: 11.494 | AW51: 0.959 | AX51: =21.738-SUM(AU51:AW51) -> 1.287 | AY51: 2.405 | AZ51: -0.083 | BA51: 0.628 | BB51: =20.299-SUM(AY51:BA51) -> 17.349 | BC51: 2.22 | BD51: 1.5 | BE51: 0.231 | BF51: =15.604-SUM(BC51:BE51) -> 11.653 | BG51: 2.659 | BH51: 7.855 | BI51: 0.285 | BJ51: =21.991-SUM(BG51:BI51) -> 11.192 | BK51: 4.755 | BL51: 22.17 | BM51: 117.62 | BN51: =21.991-SUM(BK51:BM51) -> -122.554 | BO51: 16.845 | BP51: 0.246 | BW51: =SUM(C51:F51) -> 0 | BX51: =SUM(G51:J51) -> 0 | BY51: =SUM(K51:N51) -> 0 | BZ51: =SUM(O51:R51) -> 0 | CA51: =SUM(S51:V51) -> 0 | CB51: =SUM(W51:Z51) -> 0 | CC51: =SUM(AA51:AD51) -> 0 | CD51: =SUM(AE51:AH51) -> 0 | CE51: =SUM(AI51:AL51) -> 0 | CF51: =SUM(AM51:AP51) -> 0 | CG51: =SUM(AQ51:AT51) -> 38.491 | CH51: =SUM(AU51:AX51) -> 21.738 | CI51: =SUM(AY51:BB51) -> 20.299 | CJ51: =SUM(BC51:BF51) -> 15.604 | CK51: =SUM(BG51:BJ51) -> 21.991 | CL51: 50 | CM51: 20 | CN51: 0 | CO51: 0 | CP51: 0 | CQ51: 0 | CR51: 0 | CS51: 0 | CT51: 0 | CU51: 0
B52: Gain of Sale of Assets | C52: 0 | D52: 0 | E52: 0 | F52: 0 | G52: 0 | H52: 0 | I52: 0 | J52: 0 | K52: 0 | L52: 0 | M52: 0 | N52: 0 | O52: 0 | P52: 0 | Q52: 0 | R52: 0 | S52: 0 | T52: 0 | U52: 0 | V52: 0 | W52: 0 | X52: 0 | Y52: 0 | Z52: 0 | AA52: 0 | AB52: 0 | AC52: 0 | AD52: 0 | AE52: 0 | AF52: 0 | AG52: 0 | AH52: 0 | AI52: 0 | AJ52: 0 | AK52: 0 | AL52: 0 | AM52: 0 | AN52: 0 | AO52: 0 | AP52: 0 | AQ52: 0 | AR52: 0 | AS52: 0 | AT52: =0-SUM(AQ52:AS52) -> 0 | AU52: 0 | AV52: 0 | AW52: -91.157 | AX52: =-91.157-SUM(AU52:AW52) -> 0 | AY52: 0 | AZ52: 0 | BA52: -6.5 | BB52: =-6.5-SUM(AY52:BA52) -> 0 | BC52: 0 | BD52: 0 | BE52: 0 | BF52: =-4.448-SUM(BC52:BE52) -> -4.448 | BG52: 0 | BH52: 0 | BI52: 0 | BJ52: =0-SUM(BG52:BI52) -> 0 | BK52: 0 | BL52: 0 | BM52: 0 | BN52: =0-SUM(BK52:BM52) -> 0 | BO52: 0 | BP52: 0 | BW52: =SUM(C52:F52) -> 0 | BX52: =SUM(G52:J52) -> 0 | BY52: =SUM(K52:N52) -> 0 | BZ52: =SUM(O52:R52) -> 0 | CA52: =SUM(S52:V52) -> 0 | CB52: =SUM(W52:Z52) -> 0 | CC52: =SUM(AA52:AD52) -> 0 | CD52: =SUM(AE52:AH52) -> 0 | CE52: =SUM(AI52:AL52) -> 0 | CF52: =SUM(AM52:AP52) -> 0 | CG52: =SUM(AQ52:AT52) -> 0 | CH52: =SUM(AU52:AX52) -> -91.157 | CI52: =SUM(AY52:BB52) -> -6.5 | CJ52: =SUM(BC52:BF52) -> -4.448 | CK52: =SUM(BG52:BJ52) -> 0 | CL52: 0 | CM52: 0 | CN52: 0 | CO52: 0 | CP52: 0 | CQ52: 0 | CR52: 0 | CS52: 0 | CT52: 0 | CU52: 0
B53: OI | C53: =C46-SUM(C47:C52) -> 66.6 | D53: =D46-SUM(D47:D52) -> 64.2 | E53: =E46-SUM(E47:E52) -> 53.5 | F53: =F46-SUM(F47:F52) -> 46.1 | G53: =G46-SUM(G47:G52) -> 49.7 | H53: =H46-SUM(H47:H52) -> 55.9 | I53: =I46-SUM(I47:I52) -> 61.9 | J53: =J46-SUM(J47:J52) -> 62.1 | ... BP53: =BP46-SUM(BP47:BP52) -> 72.824 | BW53: =SUM(C53:F53) -> 230.4 | BX53: =SUM(G53:J53) -> 229.6 | BY53: =SUM(K53:N53) -> -97.4 | BZ53: =SUM(O53:R53) -> 233.3 | CA53: =SUM(S53:V53) -> 284.9 | CB53: =SUM(W53:Z53) -> 315.9 | CC53: =SUM(AA53:AD53) -> 319.4 | CD53: =SUM(AE53:AH53) -> 372.3 | CE53: =SUM(AI53:AL53) -> 321.7 | CF53: =SUM(AM53:AP53) -> 427.2 | CG53: =SUM(AQ53:AT53) -> 363.559 | CH53: =SUM(AU53:AX53) -> 628.094 | CI53: =SUM(AY53:BB53) -> 499.708 | CJ53: =SUM(BC53:BF53) -> 506.318 | CK53: =SUM(BG53:BJ53) -> 151.003 | CL53: =CL46-SUM(CL47:CL52) -> 596.4374 | CM53: =CM46-SUM(CM47:CM52) -> 540.99089 | CN53: =CN46-SUM(CN47:CN52) -> 544.3852 | CO53: =CO46-SUM(CO47:CO52) -> 607.80112 | CP53: =CP46-SUM(CP47:CP52) -> 673.00263 | CQ53: =CQ46-SUM(CQ47:CQ52) -> 738.35516 | CR53: =CR46-SUM(CR47:CR52) -> 801.84074 | CS53: =CS46-SUM(CS47:CS52) -> 856.21196 | ... CU53: =CU46-SUM(CU47:CU52) -> 951.7119
B54: Interest Expense | C54: -18.8 | D54: -19.4 | E54: -50.2 | F54: -37.3 | G54: -30.6 | H54: -16.3 | I54: -18.9 | J54: -19.2 | K54: -17.7 | L54: -17.7 | M54: -18.2 | N54: -14.4 | O54: -14 | P54: -14.3 | Q54: -15.1 | R54: -14.2 | S54: -15.2 | T54: -15.9 | U54: -17 | V54: -16.6 | W54: -17 | X54: -26.5 | Y54: -14.2 | Z54: -13.6 | AA54: -13.7 | AB54: -31 | AC54: -12.8 | AD54: -16.2 | AE54: -23.1 | AF54: -19.7 | AG54: -21 | AH54: -23.5 | AI54: -25.7 | AJ54: -26.5 | AK54: -26.9 | AL54: -23.1 | AM54: -22.4 | AN54: -20.3 | AO54: -19.1 | AP54: -25.6 | AQ54: 15.439 | AR54: 15.682 | AS54: 16.65 | AT54: =66.494-SUM(AQ54:AS54) -> 18.723 | AU54: 16.798 | AV54: 16.171 | AW54: 11.989 | AX54: =56.969-SUM(AU54:AW54) -> 12.011 | AY54: 10.418 | AZ54: 11.419 | BA54: 13.375 | BB54: =54.264-SUM(AY54:BA54) -> 19.052 | BC54: 18.337 | BD54: 17.76 | BE54: 23.192 | BF54: =85.082-SUM(BC54:BE54) -> 25.793 | BG54: 22.683 | BH54: 21.168 | BI54: 21.058 | BJ54: =83.544-SUM(BG54:BI54) -> 18.635 | BK54: 18.544 | BL54: 21.708 | BM54: 31.84 | BN54: =83.544-SUM(BK54:BM54) -> 11.452 | BO54: 25.718 | BP54: 27.953 | BW54: =SUM(C54:F54) -> -125.7 | BX54: =SUM(G54:J54) -> -85 | BY54: =SUM(K54:N54) -> -68 | BZ54: =SUM(O54:R54) -> -57.6 | CA54: =SUM(S54:V54) -> -64.7 | CB54: =SUM(W54:Z54) -> -71.3 | CC54: =SUM(AA54:AD54) -> -73.7 | CD54: =SUM(AE54:AH54) -> -87.3 | CE54: =SUM(AI54:AL54) -> -102.2 | CF54: =SUM(AM54:AP54) -> -87.4 | CG54: =SUM(AQ54:AT54) -> 66.494 | CH54: =SUM(AU54:AX54) -> 56.969 | CI54: =SUM(AY54:BB54) -> 54.264 | CJ54: =SUM(BC54:BF54) -> 85.082 | CK54: =SUM(BG54:BJ54) -> 83.544 | CL54: =-$CK$93*5.5% -> -85.57285 | CM54: =-$CK$93*5.5% -> -85.57285 | CN54: =-$CK$93*5.5% -> -85.57285 | CO54: =-$CK$93*5.5% -> -85.57285 | CP54: =-$CK$93*5.5% -> -85.57285 | CQ54: =-$CK$93*5.5% -> -85.57285 | CR54: =-$CK$93*5.5% -> -85.57285 | CS54: =-$CK$93*5.5% -> -85.57285 | ... CU54: =-$CK$93*5.5% -> -85.57285
B55: Interest Income | C55: 0 | D55: 0 | E55: 0 | F55: 0 | G55: 0 | H55: 0 | I55: 0 | J55: 0 | K55: 0 | L55: 0 | M55: 0 | N55: 0 | O55: 0 | P55: 0 | Q55: 0 | R55: 0 | S55: 0 | T55: 0 | U55: 0 | V55: 0 | W55: 0 | X55: 0 | Y55: 0 | Z55: 0 | AA55: 0 | AB55: 0 | AC55: 0 | AD55: 0 | AE55: 0 | AF55: 0 | AG55: 0 | AH55: 0 | AI55: 0 | AJ55: 0 | AK55: 0 | AL55: 0 | AM55: 0 | AN55: 0 | AO55: 0 | AP55: 0 | AQ55: -0.579 | AR55: -0.163 | AS55: -0.214 | AT55: =-1.158-SUM(AQ55:AS55) -> -0.202 | AU55: -0.659 | AV55: -0.232 | AW55: -0.215 | AX55: =-1.328-SUM(AU55:AW55) -> -0.222 | AY55: -0.22 | AZ55: -0.229 | BA55: 0.126 | BB55: =-0.912-SUM(AY55:BA55) -> -0.589 | BC55: -0.843 | BD55: -1.15 | BE55: -7.487 | BF55: =-12.78-SUM(BC55:BE55) -> -3.3 | BG55: -1.66 | BH55: -1.787 | BI55: -2.298 | BJ55: =-8.009-SUM(BG55:BI55) -> -2.264 | BK55: -1.917 | BL55: -1.6 | BM55: -2.16 | BN55: =-8.009-SUM(BK55:BM55) -> -2.332 | BO55: -1.708 | BP55: -1.416 | BW55: =SUM(C55:F55) -> 0 | BX55: =SUM(G55:J55) -> 0 | BY55: =SUM(K55:N55) -> 0 | BZ55: =SUM(O55:R55) -> 0 | CA55: =SUM(S55:V55) -> 0 | CB55: =SUM(W55:Z55) -> 0 | CC55: =SUM(AA55:AD55) -> 0 | CD55: =SUM(AE55:AH55) -> 0 | CE55: =SUM(AI55:AL55) -> 0 | CF55: =SUM(AM55:AP55) -> 0 | CG55: =SUM(AQ55:AT55) -> -1.158 | CH55: =SUM(AU55:AX55) -> -1.328 | CI55: =SUM(AY55:BB55) -> -0.912 | CJ55: =SUM(BC55:BF55) -> -12.78 | CK55: =SUM(BG55:BJ55) -> -8.009 | CL55: =CK70*$CU$72 -> 21.47332 | CM55: =CL55*(1+$CU$72) -> 23.062346 | CN55: =CM55*(1+$CU$72) -> 24.768959 | CO55: =CN55*(1+$CU$72) -> 26.601862 | CP55: =CO55*(1+$CU$72) -> 28.5704 | CQ55: =CP55*(1+$CU$72) -> 30.68461 | CR55: =CQ55*(1+$CU$72) -> 32.955271 | CS55: =CR55*(1+$CU$72) -> 35.393961 | CT55: =CS55*(1+$CU$72) -> 38.013114 | CU55: =CT55*(1+$CU$72) -> 40.826084
B56: Loss on Extinguishment of Debt | C56: 0 | D56: 0 | E56: 0 | F56: 0 | G56: 0 | H56: 0 | I56: 0 | J56: 0 | K56: 0 | L56: 0 | M56: 0 | N56: 0 | O56: 0 | P56: 0 | Q56: 0 | R56: 0 | S56: 0 | T56: 0 | U56: 0 | V56: 0 | W56: 0 | X56: 0 | Y56: 0 | Z56: 0 | AA56: 0 | AB56: 0 | AC56: 0 | AD56: 0 | AE56: 0 | AF56: 0 | AG56: 0 | AH56: 0 | AI56: 0 | AJ56: 0 | AK56: 0 | AL56: 0 | AM56: 0 | AN56: 0 | AO56: 0 | AP56: 0 | AQ56: 0 | AR56: 0 | AS56: 0 | AT56: =0-SUM(AQ56:AS56) -> 0 | AU56: 0 | AV56: 12.986 | AW56: 0 | AX56: =-12.986-SUM(AU56:AW56) -> -25.972 | AY56: 0 | AZ56: 0 | BA56: 0 | BB56: =0.454-SUM(AY56:BA56) -> 0.454 | BC56: 0 | BD56: 0 | BE56: 0 | BF56: =0-SUM(BC56:BE56) -> 0 | BG56: 0 | BH56: 0 | BI56: 0 | BJ56: =0-SUM(BG56:BI56) -> 0 | BK56: 0 | BL56: 0 | BM56: 0 | BN56: =0-SUM(BK56:BM56) -> 0 | BO56: 0 | BP56: 1.15 | BW56: =SUM(C56:F56) -> 0 | BX56: =SUM(G56:J56) -> 0 | BY56: =SUM(K56:N56) -> 0 | BZ56: =SUM(O56:R56) -> 0 | CA56: =SUM(S56:V56) -> 0 | CB56: =SUM(W56:Z56) -> 0 | CC56: =SUM(AA56:AD56) -> 0 | CD56: =SUM(AE56:AH56) -> 0 | CE56: =SUM(AI56:AL56) -> 0 | CF56: =SUM(AM56:AP56) -> 0 | CG56: =SUM(AQ56:AT56) -> 0 | CH56: =SUM(AU56:AX56) -> -12.986 | CI56: =SUM(AY56:BB56) -> 0.454 | CJ56: =SUM(BC56:BF56) -> 0 | CK56: =SUM(BG56:BJ56) -> 0 | CL56: 0 | CM56: 0 | CN56: 0 | CO56: 0 | CP56: 0 | CQ56: 0 | CR56: 0 | CS56: 0 | CT56: 0 | CU56: 0
B57: Pretax Income | C57: =C53+C54 -> 47.8 | D57: =D53+D54 -> 44.8 | E57: =E53+E54 -> 3.3 | F57: =F53+F54 -> 8.8 | G57: =G53+G54 -> 19.1 | H57: =H53+H54 -> 39.6 | I57: =I53+I54 -> 43 | J57: =J53+J54 -> 42.9 | ... AP57: =AP53+AP54 -> 101.3 | AQ57: =AQ53-SUM(AQ54:AQ56) -> 142.205 | AR57: =AR53-SUM(AR54:AR56) -> 23.293 | AS57: =AS53-SUM(AS54:AS56) -> 115.645 | AT57: =AT53-SUM(AT54:AT56) -> 17.08 | AU57: =AU53-SUM(AU54:AU56) -> 87.279 | AV57: =AV53-SUM(AV54:AV56) -> 99.821 | AW57: =AW53-SUM(AW54:AW56) -> 229.181 | AX57: =AX53-SUM(AX54:AX56) -> 169.158 | ... BP57: =BP53-SUM(BP54:BP56) -> 45.137 | BW57: =SUM(C57:F57) -> 104.7 | BX57: =SUM(G57:J57) -> 144.6 | BY57: =SUM(K57:N57) -> -165.4 | BZ57: =SUM(O57:R57) -> 175.7 | CA57: =SUM(S57:V57) -> 220.2 | CB57: =SUM(W57:Z57) -> 244.6 | CC57: =SUM(AA57:AD57) -> 245.7 | CD57: =SUM(AE57:AH57) -> 285 | CE57: =SUM(AI57:AL57) -> 219.5 | CF57: =SUM(AM57:AP57) -> 339.8 | CG57: =SUM(AQ57:AT57) -> 298.223 | CH57: =SUM(AU57:AX57) -> 585.439 | CI57: =SUM(AY57:BB57) -> 445.902 | CJ57: =SUM(BC57:BF57) -> 434.016 | CK57: =SUM(BG57:BJ57) -> 75.468 | CL57: =CL53+SUM(CL54:CL56) -> 532.33787 | CM57: =CM53+SUM(CM54:CM56) -> 478.48038 | CN57: =CN53+SUM(CN54:CN56) -> 483.58131 | CO57: =CO53+SUM(CO54:CO56) -> 548.83013 | CP57: =CP53+SUM(CP54:CP56) -> 616.00018 | CQ57: =CQ53+SUM(CQ54:CQ56) -> 683.46692 | CR57: =CR53+SUM(CR54:CR56) -> 749.22316 | CS57: =CS53+SUM(CS54:CS56) -> 806.03307 | ... CU57: =CU53+SUM(CU54:CU56) -> 906.96514
B58: Taxes | C58: 14.2 | D58: 12.4 | E58: -7.7 | F58: -2.1 | G58: 4.9 | H58: 8.4 | I58: 10.1 | J58: 2.3 | K58: -4 | L58: -0.3 | M58: 7.2 | N58: 13.5 | O58: 7.7 | P58: 6.1 | Q58: 5.2 | R58: 4.6 | S58: 8.5 | T58: 10 | U58: 9.7 | V58: 0.4 | W58: 9.3 | X58: 5.3 | Y58: 0.8 | Z58: -7.6 | AA58: 2.6 | AB58: 8 | AC58: 7.5 | AD58: -10.1 | AE58: -2.7 | AF58: 12.1 | AG58: 10 | AH58: 110.2 | AI58: 6.2 | AJ58: 9.6 | AK58: -1.3 | AL58: 8.7 | AM58: 11 | AN58: 3.8 | AO58: -130.4 | AP58: -6.5 | AQ58: 11.074 | AR58: 11.848 | AS58: -0.951 | AT58: =21.93-SUM(AQ58:AS58) -> -0.041 | AU58: 12.428 | AV58: 16.412 | AW58: 29.69 | AX58: =74.349-SUM(AU58:AW58) -> 15.819 | AY58: 15.973 | AZ58: 18.412 | BA58: 17.315 | BB58: =83-SUM(AY58:BA58) -> 31.3 | BC58: 20.184 | BD58: 15.53 | BE58: 11.935 | BF58: =76.44-SUM(BC58:BE58) -> 28.791 | BG58: -41.551 | BH58: 17.332 | BI58: 19.633 | BJ58: =5.316-SUM(BG58:BI58) -> 9.902 | BK58: =13.83 -> 13.83 | BL58: 12.662 | BM58: -29.69 | BN58: =5.316-SUM(BK58:BM58) -> 8.514 | BO58: 1.011 | BP58: 3.375 | BW58: =SUM(C58:F58) -> 16.8 | BX58: =SUM(G58:J58) -> 25.7 | BY58: =SUM(K58:N58) -> 16.4 | BZ58: =SUM(O58:R58) -> 23.6 | CA58: =SUM(S58:V58) -> 28.6 | CB58: =SUM(W58:Z58) -> 7.8 | CC58: =SUM(AA58:AD58) -> 8 | CD58: =SUM(AE58:AH58) -> 129.6 | CE58: =SUM(AI58:AL58) -> 23.2 | CF58: =SUM(AM58:AP58) -> -122.1 | CG58: =SUM(AQ58:AT58) -> 21.93 | CH58: =SUM(AU58:AX58) -> 74.349 | CI58: =SUM(AY58:BB58) -> 83 | CJ58: =SUM(BC58:BF58) -> 76.44 | CK58: =SUM(BG58:BJ58) -> 5.316 | CL58: =CL57*CL67 -> 63.880544 | CM58: =CM57*CM67 -> 71.772058 | CN58: =CN57*CN67 -> 77.37301 | CO58: =CO57*CO67 -> 87.812821 | CP58: =CP57*CP67 -> 98.560029 | CQ58: =CQ57*CQ67 -> 109.35471 | CR58: =CR57*CR67 -> 119.87571 | CS58: =CS57*CS67 -> 128.96529 | ... CU58: =CU57*CU67 -> 145.11442
B59: NI | C59: =C57-C58 -> 33.6 | D59: =D57-D58 -> 32.4 | E59: =E57-E58 -> 11 | F59: =F57-F58 -> 10.9 | G59: =G57-G58 -> 14.2 | H59: =H57-H58 -> 31.2 | I59: =I57-I58 -> 32.9 | J59: =J57-J58 -> 40.6 | ... AQ59: =AQ57-AQ58 -> 131.131 | AR59: =AR57-AR58+0.013 -> 11.458 | AS59: =AS57-AS58-0.018 -> 116.578 | AT59: =AT57-AT58 -> 17.121 | AU59: =AU57-AU58 -> 74.851 | AV59: =AV57-AV58-0.035 -> 83.374 | AW59: =AW57-AW58-0.325 -> 199.166 | AX59: =AX57-AX58 -> 153.339 | AY59: =AY57-AY58-0.226 -> 77.114 | AZ59: =AZ57-AZ58-0.041 -> 105.491 | BA59: =BA57-BA58 -> 101.592 | BB59: =BB57-BB58 -> 78.438 | BC59: =BC57-BC58-0.548 -> 76.719 | BD59: =BD57-BD58-0.08 -> 111.325 | BE59: =BE57-BE58-0.53 -> 137.132 | BF59: =BF57-BF58-1.24 -> 30.002 | BG59: =BG57-BG58-0.452 -> 15.27 | BH59: =BH57-BH58 -> 80.137 | BI59: =BI57-BI58 -> 110.889 | BJ59: =BJ57-BJ58 -> -136.596 | BK59: =BK57-BK58-0.1 -> 95.064 | BL59: =BL57-BL58 -> 122.505 | BM59: =BM57-BM58 -> -408.89 | BN59: =BN57-BN58 -> 1276.03 | BO59: =BO57-BO58-3.316 -> -8.155 | BP59: =BP57-BP58 -> 41.762 | BW59: =SUM(C59:F59) -> 87.9 | BX59: =SUM(G59:J59) -> 118.9 | BY59: =SUM(K59:N59) -> -181.8 | BZ59: =SUM(O59:R59) -> 152.1 | CA59: =SUM(S59:V59) -> 191.6 | CB59: =SUM(W59:Z59) -> 236.8 | CC59: =SUM(AA59:AD59) -> 237.7 | CD59: =SUM(AE59:AH59) -> 155.4 | CE59: =SUM(AI59:AL59) -> 196.3 | CF59: =SUM(AM59:AP59) -> 461.9 | CG59: =SUM(AQ59:AT59) -> 276.288 | CH59: =SUM(AU59:AX59) -> 510.73 | CI59: =SUM(AY59:BB59) -> 362.635 | CJ59: =SUM(BC59:BF59) -> 355.178 | CK59: =SUM(BG59:BJ59) -> 69.7 | CL59: =CL57-CL58 -> 468.45732 | CM59: =CM57-CM58 -> 406.70833 | CN59: =CN57-CN58 -> 406.2083 | CO59: =CO57-CO58 -> 461.01731 | CP59: =CP57-CP58 -> 517.44015 | CQ59: =CQ57-CQ58 -> 574.11221 | CR59: =CR57-CR58 -> 629.34746 | CS59: =CS57-CS58 -> 677.06778 | ... CU59: =CU57-CU58 -> 761.85071 | CV59: =CU59*(1+$CU$73) -> 769.46922 | CW59: =CV59*(1+$CU$73) -> 777.16391 | CX59: =CW59*(1+$CU$73) -> 784.93555 | CY59: =CX59*(1+$CU$73) -> 792.78491 | CZ59: =CY59*(1+$CU$73) -> 800.71276 | DA59: =CZ59*(1+$CU$73) -> 808.71989 | DB59: =DA59*(1+$CU$73) -> 816.80708 | DC59: =DB59*(1+$CU$73) -> 824.97516 | ... ES59: =ER59*(1+$CU$73) -> 1252.9639
B60: SC | C60: 40 | D60: 40 | E60: 40 | F60: 40 | G60: 40 | H60: 41 | I60: 41 | J60: 41 | K60: 41 | L60: 41 | M60: 41 | N60: 41 | O60: 41 | P60: 41 | Q60: 41 | R60: 41 | S60: 41 | T60: 41 | U60: 41 | V60: 41 | W60: 41 | X60: 42 | Y60: 42 | Z60: 42 | AA60: 42 | AB60: 44 | AC60: 44 | AD60: 43 | AE60: 45 | AF60: 45 | AG60: 45 | AH60: 45 | AI60: 45 | AJ60: 46 | AK60: 46 | AL60: 46 | AM60: 46 | AN60: 46 | AO60: 46 | AP60: 46 | AQ60: 46.382 | AR60: 46.442 | AS60: 46.53 | AT60: 335.324 | AU60: 46.698 | AV60: 46.741 | AW60: 46.81 | AX60: 46.77 | AY60: 46.876 | AZ60: 46.901 | BA60: 46.906 | BB60: 46.898 | BC60: 46.949 | BD60: 46.981 | BE60: 46.992 | BF60: 46.981 | BG60: 47.068 | BH60: 47.151 | BI60: 46.724 | BJ60: 46.837 | BK60: 45.782 | BL60: 44.269 | BM60: 44.237 | BN60: 46.837 | BO60: 44.257 | BP60: 43.56 | BW60: =AVERAGE(C60:F60) -> 40 | BX60: =AVERAGE(G60:J60) -> 40.75 | BY60: =AVERAGE(K60:N60) -> 41 | BZ60: =AVERAGE(O60:R60) -> 41 | CA60: =AVERAGE(S60:V60) -> 41 | CB60: =AVERAGE(W60:Z60) -> 41.75 | CC60: =AVERAGE(AA60:AD60) -> 43.25 | CD60: =AVERAGE(AE60:AH60) -> 45 | CE60: =AVERAGE(AI60:AL60) -> 45.75 | CF60: =AVERAGE(AM60:AP60) -> 46 | CG60: =AVERAGE(AQ60:AT60) -> 118.6695 | CH60: =AVERAGE(AU60:AX60) -> 46.75475 | CI60: =AVERAGE(AY60:BB60) -> 46.89525 | CJ60: =AVERAGE(BC60:BF60) -> 46.97575 | CK60: =AVERAGE(BG60:BJ60) -> 46.945
B61: EPS | C61: =C59/C60 -> 0.84 | D61: =D59/D60 -> 0.81 | E61: =E59/E60 -> 0.275 | F61: =F59/F60 -> 0.2725 | G61: =G59/G60 -> 0.355 | H61: =H59/H60 -> 0.76097561 | I61: =I59/I60 -> 0.80243902 | J61: =J59/J60 -> 0.9902439 | ... BP61: =BP59/BP60 -> 0.9587236 | BW61: =SUM(C61:F61) -> 2.1975 | BX61: =SUM(G61:J61) -> 2.9086585 | BY61: =SUM(K61:N61) -> -4.4341463 | BZ61: =SUM(O61:R61) -> 3.7097561 | CA61: =SUM(S61:V61) -> 4.6731707 | CB61: =SUM(W61:Z61) -> 5.6609175 | CC61: =SUM(AA61:AD61) -> 5.4898721 | CD61: =SUM(AE61:AH61) -> 3.4533333 | CE61: =SUM(AI61:AL61) -> 4.293913 | CF61: =SUM(AM61:AP61) -> 10.041304 | CG61: =SUM(AQ61:AT61) -> 5.6304077 | CH61: =SUM(AU61:AX61) -> 10.919969 | CI61: =SUM(AY61:BB61) -> 7.7326777 | CJ61: =SUM(BC61:BF61) -> 7.5604647 | CK61: =SUM(BG61:BJ61) -> 1.4808713
B63: Gross Profit Margin | C63: =C46/C44 -> 0.48162265 | D63: =D46/D44 -> 0.48632812 | E63: =E46/E44 -> 0.4826087 | F63: =F46/F44 -> 0.49281126 | G63: =G46/G44 -> 0.46468927 | H63: =H46/H44 -> 0.47586569 | I63: =I46/I44 -> 0.48414668 | J63: =J46/J44 -> 0.47465788 | ... BP63: =BP46/BP44 -> 0.58160335 | BW63: =BW46/BW44 -> 0.48568975 | BX63: =BX46/BX44 -> 0.47490787 | BY63: =BY46/BY44 -> 0.48236735 | BZ63: =BZ46/BZ44 -> 0.49454696 | CA63: =CA46/CA44 -> 0.51222959 | CB63: =CB46/CB44 -> 0.52182803 | CC63: =CC46/CC44 -> 0.53329764 | CD63: =CD46/CD44 -> 0.54596282 | ... CK63: =CK46/CK44 -> 0.55874439 | CL63: 0.56 | CM63: 0.565 | CN63: 0.57 | CO63: 0.57 | CP63: 0.57 | CQ63: 0.57 | CR63: 0.57 | CS63: 0.57 | CT63: 0.57 | CU63: 0.57
B64: R&D as % of Revenue | C64: =C48/C44 -> 0.025319902 | D64: =D48/D44 -> 0.028738839 | E64: =E48/E44 -> 0.029565217 | F64: =F48/F44 -> 0.038543897 | G64: =G48/G44 -> 0.031073446 | H64: =H48/H44 -> 0.032791186 | I64: =I48/I44 -> 0.033360904 | J64: =J48/J44 -> 0.03421186 | ... BP64: =BP48/BP44 -> 0.079115322 | BW64: =BW48/BW44 -> 0.030337722 | BX64: =BX48/BX44 -> 0.032897822 | BY64: =BY48/BY44 -> 0.036361292 | BZ64: =BZ48/BZ44 -> 0.038318694 | CA64: =CA48/CA44 -> 0.033155778 | CB64: =CB48/CB44 -> 0.028790893 | CC64: =CC48/CC44 -> 0.031263383 | CD64: =CD48/CD44 -> 0.039463262 | ... CK64: =CK48/CK44 -> 0.053053453 | CL64: 0.055 | CM64: 0.054 | CN64: 0.053 | CO64: 0.052 | CP64: 0.051 | CQ64: 0.05 | CR64: 0.05 | CS64: 0.05 | CT64: 0.05 | CU64: 0.05
B65: SG&A as % of Revenue | C65: =C47/C44 -> 0.27389055 | D65: =D47/D44 -> 0.27845982 | E65: =E47/E44 -> 0.2942029 | F65: =F47/F44 -> 0.31141022 | G65: =G47/G44 -> 0.29152542 | H65: =H47/H44 -> 0.28803778 | I65: =I47/I44 -> 0.28012131 | J65: =J47/J44 -> 0.27698936 | ... BP65: =BP47/BP44 -> 0.37436967 | BW65: =BW47/BW44 -> 0.28885232 | BX65: =BX47/BX44 -> 0.2840201 | BY65: =BY47/BY44 -> 0.29301786 | BZ65: =BZ47/BZ44 -> 0.29611507 | CA65: =CA47/CA44 -> 0.31454506 | CB65: =CB47/CB44 -> 0.31437887 | CC65: =CC47/CC44 -> 0.30155246 | CD65: =CD47/CD44 -> 0.32614266 | ... CK65: =CK47/CK44 -> 0.32660673 | CL65: 0.305 | CM65: 0.335 | CN65: 0.32 | CO65: 0.315 | CP65: 0.31 | CQ65: 0.305 | CR65: 0.3 | CS65: 0.2975 | CT65: 0.295 | CU65: 0.295
B66: Operating Profit Margin | C66: =C53/C44 -> 0.18132317 | D66: =D53/D44 -> 0.17912946 | E66: =E53/E44 -> 0.15507246 | F66: =F53/F44 -> 0.14102172 | G66: =G53/G44 -> 0.14039548 | H66: =H53/H44 -> 0.14664218 | I66: =I53/I44 -> 0.17066446 | J66: =J53/J44 -> 0.15737456 | ... BP66: =BP53/BP44 -> 0.12768703 | BW66: =BW53/BW44 -> 0.16485404 | BX66: =BX53/BX44 -> 0.15383585 | BY66: =BY53/BY44 -> -0.062794146 | BZ66: =BZ53/BZ44 -> 0.13753463 | CA66: =CA53/CA44 -> 0.15485379 | CB66: =CB53/CB44 -> 0.17456897 | CC66: =CC53/CC44 -> 0.17098501 | CD66: =CD53/CD44 -> 0.17346131 | ... CU66: =CU53/CU44 -> 0.225
B67: Effective Tax Rate | C67: =C58/C57 -> 0.29707113 | D67: =D58/D57 -> 0.27678571 | E67: =E58/E57 -> -2.3333333 | F67: =F58/F57 -> -0.23863636 | G67: =G58/G57 -> 0.2565445 | H67: =H58/H57 -> 0.21212121 | I67: =I58/I57 -> 0.23488372 | J67: =J58/J57 -> 0.053613054 | ... BP67: =BP58/BP57 -> 0.07477236 | BW67: =BW58/BW57 -> 0.16045845 | BX67: =BX58/BX57 -> 0.17773167 | BY67: =BY58/BY57 -> -0.099153567 | BZ67: =BZ58/BZ57 -> 0.13431986 | CA67: =CA58/CA57 -> 0.12988193 | CB67: =CB58/CB57 -> 0.031888798 | CC67: =CC58/CC57 -> 0.032560033 | CD67: =CD58/CD57 -> 0.45473684 | ... CK67: =CK58/CK57 -> 0.070440452 | CL67: 0.12 | CM67: 0.15 | CN67: 0.16 | CO67: 0.16 | CP67: 0.16 | CQ67: 0.16 | CR67: 0.16 | CS67: 0.16 | CT67: 0.16 | CU67: 0.16
B68: Net Profit Margin | C68: =C59/C44 -> 0.091478356 | D68: =D59/D44 -> 0.090401786 | E68: =E59/E44 -> 0.031884058 | F68: =F59/F44 -> 0.03334353 | G68: =G59/G44 -> 0.040112994 | H68: =H59/H44 -> 0.0818468 | I68: =I59/I44 -> 0.090708575 | J68: =J59/J44 -> 0.102889 | ... BP68: =BP59/BP44 -> 0.073224017 | BW68: =BW59/BW44 -> 0.062893532 | BX68: =BX59/BX44 -> 0.079664992 | BY68: =BY59/BY44 -> -0.11720714 | BZ68: =BZ59/BZ44 -> 0.089665743 | CA68: =CA59/CA44 -> 0.10414175 | CB68: =CB59/CB44 -> 0.13085765 | CC68: =CC59/CC44 -> 0.12724839 | CD68: =CD59/CD44 -> 0.072403671 | ... CU68: =CU59/CU44 -> 0.18011376
B70: Cash & CEs | AT70: 375.88 | AU70: 324.63 | AV70: 361.78 | AW70: 481.16 | AX70: 445.08 | AY70: 466.656 | AZ70: 308.121 | BA70: 397.25 | BB70: 292.03 | BC70: 264.13 | BD70: 250.816 | BE70: 881.49 | BF70: 222.848 | BG70: 237.42 | BH70: 238.56 | BI70: 243.24 | BJ70: 290.18 | BK70: 284.122 | BL70: 253.69 | BM70: 353.997 | BN70: 378.564 | BO70: 309.411 | BP70: 300.159 | CG70: =AT70 -> 375.88 | CH70: =AX70 -> 445.08 | CI70: =BB70 -> 292.03 | CJ70: =BF70 -> 222.848 | CK70: =BJ70 -> 290.18 | CL70: =CK70+CL59 -> 758.63732 | CM70: =CL70+CM59+1200 -> 2365.3457 | CN70: =CM70+CN59 -> 2771.554 | CO70: =CN70+CO59 -> 3232.5713 | CP70: =CO70+CP59 -> 3750.0114 | CQ70: =CP70+CQ59 -> 4324.1236 | CR70: =CQ70+CR59 -> 4953.4711 | CS70: =CR70+CS59 -> 5630.5389 | CT70: =CS70+CT59 -> 6354.959 | CU70: =CT70+CU59 -> 7116.8098
B71: A/R | AT71: 395.071 | AU71: 401.11 | AV71: 414.19 | AW71: 399.74 | AX71: 383.56 | AY71: 407.159 | AZ71: 415.29 | BA71: 391.25 | BB71: 408.83 | BC71: 410.02 | BD71: 429.309 | BE71: 425.19 | BF71: 443.467 | BG71: 448.53 | BH71: 448.89 | BI71: 470.25 | BJ71: 459.49 | BK71: 464.52 | BL71: 513.81 | BM71: 592.65 | BN71: 345.583 | BO71: 365.526 | BP71: 364.609 | CG71: =AT71 -> 395.071 | CH71: =AX71 -> 383.56 | CI71: =BB71 -> 408.83 | CJ71: =BF71 -> 443.467 | CK71: =BJ71 -> 459.49
B72: Inventories | AT72: 513.19 | AU72: 512.3 | AV72: 490.3 | AW72: 484.34 | AX72: 477.64 | AY72: 491.422 | AZ72: 510.53 | BA72: 530.08 | BB72: 578.507 | BC72: 614.1 | BD72: 631.555 | BE72: 625.075 | BF72: 626.216 | BG72: 627.86 | BH72: 636.9 | BI72: 639.93 | BJ72: 600.13 | BK72: 643.97 | BL72: 693.68 | BM72: 802.46 | BN72: 404.395 | BO72: 380.861 | BP72: 351.912 | CG72: =AT72 -> 513.19 | CH72: =AX72 -> 477.64 | CI72: =BB72 -> 578.507 | CJ72: =BF72 -> 626.216 | CK72: =BJ72 -> 600.13 | CM72: Invested Capital | CP72: Avg. (2023-2024) | CR72: Projected ROIC: | CT72: ROIC | CU72: 0.074
B73: ST Prepaid Expenses | AT73: 115.43 | AU73: 121.87 | AV73: 116.818 | AW73: 123.776 | AX73: 117.277 | AY73: 123.87 | AZ73: 112.595 | BA73: 113.916 | BB73: 125.084 | BC73: 134.94 | BD73: 120.19 | BE73: 138.65 | BF73: 107.47 | BG73: 111.62 | BH73: 94.82 | BI73: 116.92 | BJ73: 117.85 | BK73: 141.6 | BL73: 199 | BM73: 154.6 | BN73: 150.678 | BO73: 149.808 | BP73: 148.222 | CG73: =AT73 -> 115.43 | CH73: =AX73 -> 117.277 | CI73: =BB73 -> 125.084 | CJ73: =BF73 -> 107.47 | CK73: =BJ73 -> 117.85 | CM73: 2023 | CN73: 2024 | CP73: 2023-2024 | CR73: 2024 | CT73: Terminal | CU73: 0.01
B74: ST Prepaid Taxes | AT74: 22.84 | AU74: 18.87 | AV74: 27.18 | AW74: 52.8 | AX74: 5.545 | AY74: 5.092 | AZ74: 38.8 | BA74: 26.868 | BB74: 6.524 | BC74: 4.84 | BD74: 13.929 | BE74: 26.84 | BF74: 7.404 | BG74: 8.163 | BH74: 18.89 | BI74: 28.94 | BJ74: 3.4 | BK74: 4.69 | BL74: 63.66 | BM74: 82.26 | BN74: 19.566 | BO74: 16.793 | BP74: 36.458 | CG74: =AT74 -> 22.84 | CH74: =AX74 -> 5.545 | CI74: =BB74 -> 6.524 | CJ74: =BF74 -> 7.404 | CK74: =BJ74 -> 3.4 | CM74: =SUM(CJ70:CJ75)-CJ86+CJ76+CJ79+CJ78 -> 7171.088 | CN74: =SUM(CK70:CK75)-CK86+CK76+CK79+CK78 -> 6733.88 | CP74: =AVERAGE(CM74:CN74) -> 6952.484 | CR74: =AVERAGE(CL53)*(1-CL67) -> 524.86491 | CT74: RFR (10-year yield) | CU74: 0.0416
B75: Current Assets Held-For-Sale | AT75: 0 | AU75: 0 | AV75: 26.936 | AW75: 0 | AX75: 0 | AY75: 0 | AZ75: 0 | BA75: 0 | BB75: 0 | BC75: 0 | BD75: 0 | BE75: 0 | BF75: 0 | BG75: 0 | BH75: 0 | BI75: 0 | BJ75: 0 | BK75: 0 | BL75: 0 | BM75: 0 | BN75: 639.552 | BO75: 637.271 | BP75: 674.516 | CG75: =AT75 -> 0 | CH75: =AX75 -> 0 | CI75: =BB75 -> 0 | CJ75: =BF75 -> 0 | CK75: =BJ75 -> 0 | CR75: =CR74/CP74 -> 0.075493149 | CT75: ERP (Avg. market return - (less) RFR) | CU75: =9.95%-CU74 -> 0.0579
B76: PP&E | AT76: 473.912 | AU76: 467.64 | AV76: 449.75 | AW76: 446.318 | AX76: 443.75 | AY76: 436.02 | AZ76: 429.37 | BA76: 422.355 | BB76: 447.205 | BC76: 458.86 | BD76: 464.609 | BE76: 464.467 | BF76: 479.913 | BG76: 485.535 | BH76: 491.99 | BI76: 512.224 | BJ76: 502.85 | BK76: 518.916 | BL76: 548.961 | BM76: 700.586 | BN76: 498.281 | BO76: 476.955 | BP76: 475.637 | CG76: =AT76 -> 473.912 | CH76: =AX76 -> 443.75 | CI76: =BB76 -> 447.205 | CJ76: =BF76 -> 479.913 | CK76: =BJ76 -> 502.85 | CM76: Capital Structure | CT76: Equity β (1-year avg.) | CU76: ='Notes | Quant Analysis'!K204 -> 1.08
B77: Operating Lease Assets | AT77: 100.63 | AU77: 94.55 | AV77: 115.11 | AW77: 129.99 | AX77: 129.65 | AY77: 124.39 | AZ77: 118.62 | BA77: 112.04 | BB77: 131.211 | BC77: 126.77 | BD77: 123.215 | BE77: 123.6 | BF77: 123.52 | BG77: 112.56 | BH77: 112.01 | BI77: 112.89 | BJ77: 108.9 | BK77: 108.34 | BL77: 99.09 | BM77: 107.05 | BN77: 91.817 | BO77: 84.912 | BP77: 77.158 | CG77: =AT77 -> 100.63 | CH77: =AX77 -> 129.65 | CI77: =BB77 -> 131.211 | CJ77: =BF77 -> 123.52 | CK77: =BJ77 -> 108.9 | CM77: Mkt Cap | CP77: =Main!C7 -> 5301.5846 | CT77: Discount (Cost of Equity) | CU77: =+CU74+(CU75*CU76) -> 0.104132
B78: Goodwill | AT78: 2585.966 | AU78: 2565.87 | AV78: 2537.43 | AW78: 2522.95 | AX78: 2504.202 | AY78: 2492.72 | AZ78: 2461.083 | BA78: 2415.29 | BB78: 2536.73 | BC78: 2547.84 | BD78: 2546.13 | BE78: 2528.305 | BF78: 2914.05 | BG78: 2898.343 | BH78: 2892.62 | BI78: 2918.56 | BJ78: 2632.31 | BK78: 2651.88 | BL78: 2694.1 | BM78: 2537.77 | BN78: 2305.05 | BO78: 2297.447 | BP78: 2292.435 | CG78: =AT78 -> 2585.966 | CH78: =AX78 -> 2504.202 | CI78: =BB78 -> 2536.73 | CJ78: =BF78 -> 2914.05 | CK78: =BJ78 -> 2632.31 | CM78: Debt to Ttl Mkt Cap | CP78: =Main!C9/(Main!C9+CP77) -> 0.34625767
B79: Intangible Assets | AT79: 2519.74 | AU79: 2470.244 | AV79: 2381.32 | AW79: 2337.24 | AX79: 2289.06 | AY79: 2243.55 | AZ79: 2226.87 | BA79: 2176.25 | BB79: 2306.16 | BC79: 2269.53 | BD79: 2227.947 | BE79: 2180.53 | BF79: 2501.96 | BG79: 2429.46 | BH79: 2379.91 | BI79: 2325.1 | BJ79: 2268.7 | BK79: 2226.14 | BL79: 2184.3 | BM79: 2410.4 | BN79: 1524.15 | BO79: 1485.885 | BP79: 1448.669 | CG79: =AT79 -> 2519.74 | CH79: =AX79 -> 2289.06 | CI79: =BB79 -> 2306.16 | CJ79: =BF79 -> 2501.96 | CK79: =BJ79 -> 2268.7 | CM79: Mkt Equity to Ttl Mkt Cap | CP79: =CP77/(CP77+Main!C9) -> 0.65374233 | CT79: NPV | CU79: =NPV(CU77,CL59:EI59) -> 6152.7486
B80: Deffered Tax Assets | AT80: 8.073 | AU80: 8.045 | AV80: 8.44 | AW80: 8.425 | AX80: 6.82 | AY80: 6.791 | AZ80: 6.243 | BA80: 5.762 | BB80: 6.402 | BC80: 6.479 | BD80: 6.278 | BE80: 6.167 | BF80: 6.74 | BG80: 6.588 | BH80: 6.424 | BI80: 6.779 | BJ80: 11.374 | BK80: 11.773 | BL80: 12.86 | BM80: 13.509 | BN80: 12.593 | BO80: 12.206 | BP80: 12.642 | CG80: =AT80 -> 8.073 | CH80: =AX80 -> 6.82 | CI80: =BB80 -> 6.402 | CJ80: =BF80 -> 6.74 | CK80: =BJ80 -> 11.374 | CM80: LT Debt / Equity | CP80: =CK93/CK100 -> 0.36368248 | CT80: SC | CU80: =Main!C6 -> 42.372
B81: Other LT Assets | AT81: 41.802 | AU81: 42.87 | AV81: 41.66 | AW81: 53.3 | AX81: 69.104 | AY81: 75.622 | AZ81: 104.308 | BA81: 166.98 | BB81: 89.36 | BC81: 80.38 | BD81: 81.747 | BE81: 93.28 | BF81: 98.943 | BG81: 111.828 | BH81: 120.577 | BI81: 111.42 | BJ81: 102.624 | BK81: 107.317 | BL81: 112.06 | BM81: 116.626 | BN81: 112.984 | BO81: 113.557 | BP81: 120.31 | CG81: =AT81 -> 41.802 | CH81: =AX81 -> 69.104 | CI81: =BB81 -> 89.36 | CJ81: =BF81 -> 98.943 | CK81: =BJ81 -> 102.624 | CT81: FV | CU81: =CU79/CU80 -> 145.20789
B82: LT Assets Held-For-Sale | AT82: 0 | AU82: 0 | AV82: 95.426 | AW82: 0 | AX82: 0 | AY82: 0 | AZ82: 0 | BA82: 0 | BB82: 0 | BC82: 0 | BD82: 0 | BE82: 0 | BF82: 0 | BG82: 0 | BH82: 0 | BI82: 0 | BJ82: 0 | BK82: 0 | BL82: 0 | BM82: 0 | BN82: 464.026 | BO82: 452.37 | BP82: 484.051 | CG82: =AT82 -> 0 | CH82: =AX82 -> 0 | CI82: =BB82 -> 0 | CJ82: =BF82 -> 0 | CK82: =BJ82 -> 0 | CM82: Cost of Equity | CT82: CP | CU82: =Main!C5 -> 125.12
B83: Ttl Assets | AT83: =SUM(AT70:AT81) -> 7152.534 | AU83: =SUM(AU70:AU81) -> 7027.999 | AV83: =SUM(AV70:AV82) -> 7066.34 | AW83: =SUM(AW70:AW82) -> 7040.039 | AX83: =SUM(AX70:AX81) -> 6871.688 | AY83: =SUM(AY70:AY81) -> 6873.292 | AZ83: =SUM(AZ70:AZ81) -> 6731.83 | BA83: =SUM(BA70:BA81) -> 6758.041 | BB83: =SUM(BB70:BB81) -> 6928.043 | BC83: =SUM(BC70:BC81) -> 6917.889 | BD83: =SUM(BD70:BD81) -> 6895.725 | BE83: =SUM(BE70:BE81) -> 7493.594 | ... BM83: =SUM(BM70:BM81) -> 7871.908 | BN83: =SUM(BN70:BN82) -> 6947.239 | BO83: =SUM(BO70:BO82) -> 6783.002 | BP83: =SUM(BP70:BP82) -> 6786.778 | CG83: =AT83 -> 7152.534 | CH83: =AX83 -> 6871.688 | CI83: =BB83 -> 6928.043 | CJ83: =BF83 -> 7532.531 | CK83: =BJ83 -> 7097.808 | CM83: RFR (10-year yield) | CP83: 0.0516 | CT83: Change Δ | CU83: =CU81/CU82-1 -> 0.16054898 | CV83: =IF(CU83>0,"Upside","Downside") -> Upside
CM84: Equity β (1-year avg.) | CP84: ='Notes | Quant Analysis'!K204 -> 1.08 | CT84: {=_xlfn.IFS(CU83>=25%,"Strong Buy",CU83>=10.00001%,"Buy",AND(CU83<=10%,CU83>=-4.9999%),"Hold",AND(CU83<=-5%,CU83>=-14.999999%),"Sell",CU83<=-15%,"Strong Sell")} -> Buy
B85: Current Debt | AT85: 100.5 | AU85: 83.75 | AV85: 92.5 | AW85: 101.25 | AX85: 110 | AY85: 110 | AZ85: 110 | BA85: 114.37 | BB85: 87.5 | BC85: 87.5 | BD85: 87.5 | BE85: 87.5 | BF85: 87.5 | BG85: 90.625 | BH85: 93.75 | BI85: 96.87 | BJ85: 100 | BK85: 100 | BL85: 100 | BM85: 100 | BN85: 100 | BO85: 103.125 | BP85: 87.5 | CG85: =AT85 -> 100.5 | CH85: =AX85 -> 110 | CI85: =BB85 -> 87.5 | CJ85: =BF85 -> 87.5 | CK85: =BJ85 -> 100 | CM85: Market Return(1-year avg.) | CP85: 0.17
B86: A/P | AT86: 102.52 | AU86: 101.34 | AV86: 106.56 | AW86: 104.139 | AX86: 118.236 | AY86: 117.464 | AZ86: 121.418 | BA86: 121.5 | BB86: 126.807 | BC86: 136.239 | BD86: 142.08 | BE86: 130.686 | BF86: 132.24 | BG86: 115.945 | BH86: 113.45 | BI86: 119.25 | BJ86: 141.03 | BK86: 143.037 | BL86: 157.55 | BM86: 165.9 | BN86: 130.201 | BO86: 143.627 | BP86: 143.292 | CG86: =AT86 -> 102.52 | CH86: =AX86 -> 118.236 | CI86: =BB86 -> 126.807 | CJ86: =BF86 -> 132.24 | CK86: =BJ86 -> 141.03 | CM86: Cost of Equity | CP86: =(CP83+CP84)*(CP85-CP83) -> 0.13398144
B87: Accrued ST Expenses | AT87: 136.276 | AU87: 134.311 | AV87: 138.28 | AW87: 127.116 | AX87: 163.44 | AY87: 158.945 | AZ87: 151.715 | BA87: 140.86 | BB87: 140.644 | BC87: 123.45 | BD87: 127.86 | BE87: 133.067 | BF87: 146.88 | BG87: 136.614 | BH87: 153.4 | BI87: 157.78 | BJ87: 143.16 | BK87: 150.85 | BL87: 157.17 | BM87: 147.05 | BN87: 117.35 | BO87: 118.423 | BP87: 134.17 | CG87: =AT87 -> 136.276 | CH87: =AX87 -> 163.44 | CI87: =BB87 -> 140.644 | CJ87: =BF87 -> 146.88 | CK87: =BJ87 -> 143.16
B88: Payroll & Benefit Liabilities | AT88: 122.366 | AU88: 100.38 | AV88: 121.82 | AW88: 133.523 | AX88: 143.65 | AY88: 102.407 | AZ88: 114.38 | BA88: 121.59 | BB88: 133.092 | BC88: 102.08 | BD88: 106.177 | BE88: 127.1 | BF88: 146.535 | BG88: 106.055 | BH88: 113.112 | BI88: 142.619 | BJ88: 151.26 | BK88: 108.9 | BL88: 114.16 | BM88: 167.73 | BN88: 124.769 | BO88: 103.345 | BP88: 110.214 | CG88: =AT88 -> 122.366 | CH88: =AX88 -> 143.65 | CI88: =BB88 -> 133.092 | CJ88: =BF88 -> 146.535 | CK88: =BJ88 -> 151.26 | CM88: Cost of Debt
B89: Accrued Interest Liabilities | AT89: 7.135 | AU89: 23.4 | AV89: 5.5 | AW89: 15.757 | AX89: 5.209 | AY89: 16.808 | AZ89: 4.751 | BA89: 15.87 | BB89: 5.332 | BC89: 16.86 | BD89: 5.793 | BE89: 17.428 | BF89: 5.583 | BG89: 16.99 | BH89: 5.77 | BI89: 16.657 | BJ89: 5.33 | BK89: 17.02 | BL89: 5.63 | BM89: 16.766 | BN89: 5.404 | BO89: 16.478 | BP89: 3.558 | CG89: =AT89 -> 7.135 | CH89: =AX89 -> 5.209 | CI89: =BB89 -> 5.332 | CJ89: =BF89 -> 5.583 | CK89: =BJ89 -> 5.33 | CM89: Cost of Debt | CP89: 0.065
B90: Taxes Payable | AT90: 17.36 | AU90: 14.83 | AV90: 14.836 | AW90: 17.185 | AX90: 83.943 | AY90: 88.451 | AZ90: 52.174 | BA90: 41.32 | BB90: 24.736 | BC90: 30.17 | BD90: 20.18 | BE90: 24.375 | BF90: 41.45 | BG90: 48.905 | BH90: 19.731 | BI90: 18.68 | BJ90: 41.31 | BK90: 49.78 | BL90: 22.494 | BM90: 12.97 | BN90: 18.787 | BO90: 11.824 | BP90: 17.787 | CG90: =AT90 -> 17.36 | CH90: =AX90 -> 83.943 | CI90: =BB90 -> 24.736 | CJ90: =BF90 -> 41.45 | CK90: =BJ90 -> 41.31 | CM90: Tax Rate | CP90: 0.14
B91: Other ST Liabilities | AT91: 53.869 | AU91: 50.04 | AV91: 46.26 | AW91: 63.24 | AX91: 55.633 | AY91: 62.125 | AZ91: 56.004 | BA91: 55.407 | BB91: 63.38 | BC91: 79.403 | BD91: 65.85 | BE91: 65.26 | BF91: 46.547 | BG91: 55.87 | BH91: 57.53 | BI91: 66.88 | BJ91: 67.24 | BK91: 103.31 | BL91: 159.119 | BM91: 162.6 | BN91: 137.195 | BO91: =103.929 -> 103.929 | BP91: 88.364 | CG91: =AT91 -> 53.869 | CH91: =AX91 -> 55.633 | CI91: =BB91 -> 63.38 | CJ91: =BF91 -> 46.547 | CK91: =BJ91 -> 67.24 | CM91: After Tax Cost of Debt | CP91: =CP89*(1-CP90) -> 0.0559
B92: ST Liabilities Held-For-Sale | AT92: 0 | AU92: 0 | AV92: 1.056 | AW92: 0 | AX92: 0 | AY92: 0 | AZ92: 0 | BA92: 0 | BB92: 0 | BC92: 0 | BD92: 0 | BE92: 0 | BF92: 0 | BG92: 0 | BH92: 0 | BI92: 0 | BJ92: 0 | BK92: 0 | BL92: 0 | BM92: 0 | BN92: 128.32 | BO92: 127.298 | BP92: 135.494 | CG92: =AT92 -> 0 | CH92: =AX92 -> 0 | CI92: =BB92 -> 0 | CJ92: =BF92 -> 0 | CK92: =BJ92 -> 0
B93: LT Debt | AT93: 2377.88 | AU93: 2295.43 | AV93: 2215.66 | AW93: 1948.666 | AX93: 1740.1 | AY93: 1740.778 | AZ93: 1605.95 | BA93: 1593.5 | BB93: 1624.02 | BC93: 1549.47 | BD93: 1470.67 | BE93: 1950.123 | BF93: 1727.57 | BG93: 1667.896 | BH93: 1624.22 | BI93: 1661.54 | BJ93: 1555.87 | BK93: 1807.321 | BL93: 1801.64 | BM93: 2571.5 | BN93: 2541.449 | BO93: 2514.268 | BP93: 2720.509 | CG93: =AT93 -> 2377.88 | CH93: =AX93 -> 1740.1 | CI93: =BB93 -> 1624.02 | CJ93: =BF93 -> 1727.57 | CK93: =BJ93 -> 1555.87 | CM93: WACC | CP93: =(CP79*CP86)+(CP78*CP91*(1-CP90)) -> 0.10423533
B94: LT Tax Liabilities | AT94: 484.67 | AU94: 482.48 | AV94: 483.269 | AW94: 479.105 | AX94: 370.12 | AY94: 369.73 | AZ94: 379.93 | BA94: 387.333 | BB94: 388.88 | BC94: 388.18 | BD94: 385.11 | BE94: 389.08 | BF94: 456.08 | BG94: 456.36 | BH94: 453.02 | BI94: 445.84 | BJ94: 391.066 | BK94: 385.67 | BL94: 373.955 | BM94: 423.65 | BN94: 183.749 | BO94: 169.429 | BP94: 146.141 | CG94: =AT94 -> 484.67 | CH94: =AX94 -> 370.12 | CI94: =BB94 -> 388.88 | CJ94: =BF94 -> 456.08 | CK94: =BJ94 -> 391.066
B95: Pension Benefits | AT95: 74.499 | AU95: 57.118 | AV95: 51.179 | AW95: 49.843 | AX95: 45.18 | AY95: 43.42 | AZ95: 42.09 | BA95: 40.34 | BB95: 31.394 | BC95: 30.92 | BD95: 30.686 | BE95: 30.05 | BF95: 23.989 | BG95: 23.17 | BH95: 23.026 | BI95: 23.548 | BJ95: 20.18 | BK95: 20.3 | BL95: 21.485 | BM95: 32.808 | BN95: 3.536 | BO95: 3.831 | BP95: 3.802 | CG95: =AT95 -> 74.499 | CH95: =AX95 -> 45.18 | CI95: =BB95 -> 31.394 | CJ95: =BF95 -> 23.989 | CK95: =BJ95 -> 20.18
B96: LT Liability for Uncertain Taxes | AT96: 10.127 | AU96: 9.987 | AV96: 10.078 | AW96: 10.078 | AX96: 8.646 | AY96: 8.61 | AZ96: 8.543 | BA96: 9 | BB96: 5.8 | BC96: 6.464 | BD96: 6.53 | BE96: 6.545 | BF96: 3.37 | BG96: 3.288 | BH96: 3.271 | BI96: 3.369 | BJ96: 1.83 | BK96: 1.896 | BL96: 1.96 | BM96: 4.592 | BN96: 84.21 | BO96: 68.32 | BP96: 64.54 | CG96: =AT96 -> 10.127 | CH96: =AX96 -> 8.646 | CI96: =BB96 -> 5.8 | CJ96: =BF96 -> 3.37 | CK96: =BJ96 -> 1.83
B97: LT Operating Lease Liabilities | AT97: 86.09 | AU97: 79.403 | AV97: 101.302 | AW97: 114.777 | AX97: 116.03 | AY97: 109.59 | AZ97: 104.702 | BA97: 99.6 | BB97: 120.43 | BC97: 115.83 | BD97: 112.229 | BE97: 111.81 | BF97: 111.3 | BG97: 104.37 | BH97: 102.572 | BI97: 102.938 | BJ97: 99.15 | BK97: 97.661 | BL97: 93.506 | BM97: 97.65 | BN97: 194.532 | BO97: 162.507 | BP97: 174.899 | CG97: =AT97 -> 86.09 | CH97: =AX97 -> 116.03 | CI97: =BB97 -> 120.43 | CJ97: =BF97 -> 111.3 | CK97: =BJ97 -> 99.15
B98: Other LT Liabilities | AT98: 242.78 | AU98: 219.75 | AV98: 211.94 | AW98: 217.411 | AX98: 156.76 | AY98: 149.42 | AZ98: 127.44 | BA98: 122.188 | BB98: 154.05 | BC98: 141.07 | BD98: 119.948 | BE98: 106.555 | BF98: 162.502 | BG98: 148.6 | BH98: 120.05 | BI98: 148.57 | BJ98: 102.307 | BK98: 79.365 | BL98: 123.644 | BM98: 146.838 | BN98: 52.969 | BO98: 52.162 | BP98: 51.974 | CG98: =AT98 -> 242.78 | CH98: =AX98 -> 156.76 | CI98: =BB98 -> 154.05 | CJ98: =BF98 -> 162.502 | CK98: =BJ98 -> 102.307
B99: Ttl Liabilities | AT99: =SUM(AT85:AT98) -> 3816.072 | AU99: =SUM(AU85:AU98) -> 3652.219 | AV99: =SUM(AV85:AV98) -> 3600.24 | AW99: =SUM(AW85:AW98) -> 3382.09 | AX99: =SUM(AX85:AX98) -> 3116.947 | AY99: =SUM(AY85:AY98) -> 3077.748 | AZ99: =SUM(AZ85:AZ98) -> 2879.097 | BA99: =SUM(BA85:BA98) -> 2862.878 | ... BP99: =SUM(BP85:BP98) -> 3882.244 | CG99: =AT99 -> 3816.072 | CH99: =AX99 -> 3116.947 | CI99: =BB99 -> 2906.065 | CJ99: =BF99 -> 3091.546 | CK99: =BJ99 -> 2819.733
B100: SE | AT100: 3336.457 | AU100: 3375.79 | AV100: 3466.1 | AW100: 3657.87 | AX100: 3754.74 | AY100: 3795.53 | AZ100: 3852.73 | BA100: 3895.16 | BB100: 4021.96 | BC100: 4110.25 | BD100: 4215.09 | BE100: 4314.048 | BF100: 4440.988 | BG100: 4503.21 | BH100: 4558.719 | BI100: 4481.717 | BJ100: 4278.1 | BK100: 4095.16 | BL100: 4242.86 | BM100: 3821.86 | BN100: 3124.768 | BO100: 3084.436 | BP100: 2904.534 | CG100: =AT100 -> 3336.457 | CH100: =AX100 -> 3754.74 | CI100: =BB100 -> 4021.96 | CJ100: =BF100 -> 4440.988 | CK100: =BJ100 -> 4278.1
B101: Ttl L + SE | AT101: =AT99+AT100 -> 7152.529 | AU101: =AU99+AU100 -> 7028.009 | AV101: =AV99+AV100 -> 7066.34 | AW101: =AW99+AW100 -> 7039.96 | AX101: =AX99+AX100 -> 6871.687 | AY101: =AY99+AY100 -> 6873.278 | AZ101: =AZ99+AZ100 -> 6731.827 | BA101: =BA99+BA100 -> 6758.038 | ... BP101: =BP99+BP100 -> 6786.778 | CG101: =AT101 -> 7152.529 | CH101: =AX101 -> 6871.687 | CI101: =BB101 -> 6928.025 | CJ101: =BF101 -> 7532.534 | CK101: =BJ101 -> 7097.833
B103: Current Ratio | AT103: =SUM(AT70:AT75)/SUM(AT85:AT92) -> 2.6339676 | AU103: =SUM(AU70:AU75)/SUM(AU85:AU92) -> 2.7138614 | AV103: =SUM(AV70:AV75)/SUM(AV85:AV92) -> 2.7281155 | AW103: =SUM(AW70:AW75)/SUM(AW85:AW92) -> 2.7424201 | AX103: =SUM(AX70:AX75)/SUM(AX85:AX92) -> 2.1012776 | AY103: =SUM(AY70:AY75)/SUM(AY85:AY92) -> 2.2770482 | AZ103: =SUM(AZ70:AZ75)/SUM(AZ85:AZ92) -> 2.2693982 | BA103: =SUM(BA70:BA75)/SUM(BA85:BA92) -> 2.388809 | ... BP103: =SUM(BP70:BP75)/SUM(BP85:BP92) -> 2.6040126 | CG103: =SUM(CG70:CG75)/SUM(CG85:CG92) -> 2.6339676 | CH103: =SUM(CH70:CH75)/SUM(CH85:CH92) -> 2.1012776 | CI103: =SUM(CI70:CI75)/SUM(CI85:CI92) -> 2.4264778 | CJ103: =SUM(CJ70:CJ75)/SUM(CJ85:CJ92) -> 2.3196371 | CK103: =SUM(CK70:CK75)/SUM(CK85:CK92) -> 2.265489
B104: Quick Ratio | AT104: =(SUM(AT70:AT75)-AT72)/SUM(AT85:AT92) -> 1.6836615 | AU104: =(SUM(AU70:AU75)-AU72)/SUM(AU85:AU92) -> 1.7054981 | AV104: =(SUM(AV70:AV75)-AV72)/SUM(AV85:AV92) -> 1.797423 | AW104: =(SUM(AW70:AW75)-AW72)/SUM(AW85:AW92) -> 1.8809271 | AX104: =(SUM(AX70:AX75)-AX72)/SUM(AX85:AX92) -> 1.3989805 | AY104: =(SUM(AY70:AY75)-AY72)/SUM(AY85:AY92) -> 1.5281576 | AZ104: =(SUM(AZ70:AZ75)-AZ72)/SUM(AZ85:AZ92) -> 1.4330698 | BA104: =(SUM(BA70:BA75)-BA72)/SUM(BA85:BA92) -> 1.5211297 | ... BP104: =(SUM(BP70:BP75)-BP72)/SUM(BP85:BP92) -> 2.1155031 | CG104: =(SUM(CG70:CG75)-CG72)/SUM(CG85:CG92) -> 1.6836615 | CH104: =(SUM(CH70:CH75)-CH72)/SUM(CH85:CH92) -> 1.3989805 | CI104: =(SUM(CI70:CI75)-CI72)/SUM(CI85:CI92) -> 1.4316094 | CJ104: =(SUM(CJ70:CJ75)-CJ72)/SUM(CJ85:CJ92) -> 1.2875292 | CK104: =(SUM(CK70:CK75)-CK72)/SUM(CK85:CK92) -> 1.3412595
B105: Cash Ratio | AT105: =AT70/SUM(AT85:AT92) -> 0.69604056 | AU105: =AU70/SUM(AU85:AU92) -> 0.63897128 | AV105: =AV70/SUM(AV85:AV92) -> 0.68673455 | AW105: =AW70/SUM(AW85:AW92) -> 0.85583679 | AX105: =AX70/SUM(AX85:AX92) -> 0.65442259 | AY105: =AY70/SUM(AY85:AY92) -> 0.71114904 | AZ105: =AZ70/SUM(AZ85:AZ92) -> 0.50475066 | BA105: =BA70/SUM(BA85:BA92) -> 0.650252 | ... BP105: =BP70/SUM(BP85:BP92) -> 0.41666817 | CG105: =CG70/SUM(CG85:CG92) -> 0.69604056 | CH105: =CH70/SUM(CH85:CH92) -> 0.65442259 | CI105: =CI70/SUM(CI85:CI92) -> 0.50220898 | CJ105: =CJ70/SUM(CJ85:CJ92) -> 0.3672905 | CK105: =CK70/SUM(CK85:CK92) -> 0.44689141
B106: Ttl Asset Turnover | AT106: =AT44/AT83 -> 0.091116659 | AU106: =AU44/AU83 -> 0.090196655 | AV106: =AV44/AV83 -> 0.10096316 | AW106: =AW44/AW83 -> 0.09946408 | AX106: =AX44/AX83 -> 0.11088731 | AY106: =AY44/AY83 -> 0.09335963 | AZ106: =AZ44/AZ83 -> 0.10465431 | BA106: =BA44/BA83 -> 0.10161806 | ... BP106: =BP44/BP83 -> 0.084035753 | CG106: =CG44/CG83 -> 0.34640101 | CH106: =CH44/CH83 -> 0.40885966 | CI106: =CI44/CI83 -> 0.40285893 | CJ106: =CJ44/CJ83 -> 0.3948852 | CK106: =CK44/CK83 -> 0.42933029
B107: Inventory Turnover Ratio | AT107: =AT45/(AVERAGE(AQ72:AT72)) -> 0.63840878 | AU107: =AU45/(AVERAGE(AR72:AU72)) -> 0.56440921 | AV107: =AV45/(AVERAGE(AS72:AV72)) -> 0.62525218 | AW107: =AW45/(AVERAGE(AT72:AW72)) -> 0.62488738 | AX107: =AX45/(AVERAGE(AU72:AX72)) -> 0.6967026 | AY107: =AY45/(AVERAGE(AV72:AY72)) -> 0.60807675 | AZ107: =AZ45/(AVERAGE(AW72:AZ72)) -> 0.64301412 | BA107: =BA45/(AVERAGE(AX72:BA72)) -> 0.62265484 | ... BP107: =BP45/(AVERAGE(BM72:BP72)) -> 0.49210467 | CG107: =CG45/(AVERAGE(CD72:CG72)) -> 2.362244 | CH107: =CH45/(AVERAGE(CE72:CH72)) -> 2.5432435 | CI107: =CI45/(AVERAGE(CF72:CI72)) -> 2.4085649 | CJ107: =CJ45/(AVERAGE(CG72:CJ72)) -> 2.4186162 | CK107: =CK45/(AVERAGE(CH72:CK72)) -> 2.356441
B108: Return on Assets | AT108: =AT59/AT101 -> 0.0023936988 | AU108: =AU59/AU101 -> 0.010650385 | AV108: =AV59/AV101 -> 0.011798753 | AW108: =AW59/AW101 -> 0.028290786 | AX108: =AX59/AX101 -> 0.022314608 | AY108: =AY59/AY101 -> 0.011219392 | AZ108: =AZ59/AZ101 -> 0.015670486 | BA108: =BA59/BA101 -> 0.015032765 | ... BP108: =BP59/BP101 -> 0.0061534354 | CG108: =CG59/CG101 -> 0.038628015 | CH108: =CH59/CH101 -> 0.074323816 | CI108: =CI59/CI101 -> 0.0523432 | CJ108: =CJ59/CJ101 -> 0.047152525 | CK108: =CK59/CK101 -> 0.0098198986
B109: Return on Equity | AT109: =AT59/AT100 -> 0.0051314913 | AU109: =AU59/AU100 -> 0.022172884 | AV109: =AV59/AV100 -> 0.024054124 | AW109: =AW59/AW100 -> 0.054448627 | AX109: =AX59/AX100 -> 0.04083878 | AY109: =AY59/AY100 -> 0.020317057 | AZ109: =AZ59/AZ100 -> 0.027380844 | BA109: =BA59/BA100 -> 0.026081599 | ... BP109: =BP59/BP100 -> 0.01437821 | CG109: =CG59/CG100 -> 0.0828088 | CH109: =CH59/CH100 -> 0.13602273 | CI109: =CI59/CI100 -> 0.090163751 | CJ109: =CJ59/CJ100 -> 0.079977248 | CK109: =CK59/CK100 -> 0.016292279
...

Sheet Base Case
B1: [Use for Graphing] | AQ1: Q1 2020 | AU1: Q1 2021 | AY1: Q1 2022 | BC1: Q1 2023 | BG1: Q1 2024 | BK1: Q1 2025 | BO1: Q1 2026
B2: Quarterly
B3: Revenues | C3: Q1 2010 | D3: Q2 2010 | E3: Q3 2010 | F3: Q4 2010 | G3: Q1 2011 | H3: Q2 2011 | I3: Q3 2011 | J3: Q4 2011 | K3: Q1 2012 | L3: Q2 2012 | M3: Q3 2012 | N3: Q4 2012 | O3: Q1 2013 | P3: Q2 2013 | Q3: Q3 2013 | R3: Q4 2013 | S3: Q1 2014 | T3: Q2 2014 | U3: Q3 2014 | V3: Q4 2014 | W3: Q1 2015 | X3: Q2 2015 | Y3: Q3 2015 | Z3: Q4 2015 | AA3: Q1 2016 | AB3: Q2 2016 | AC3: Q3 2016 | AD3: Q4 2016 | AE3: Q1 2017 | AF3: Q2 2017 | AG3: Q3 2017 | AH3: Q4 2017 | AI3: Q1 2018 | AJ3: Q2 2018 | AK3: Q3 2018 | AL3: Q4 2018 | AM3: Q1 2019 | AN3: Q2 2019 | AO3: Q3 2019 | AP3: Q4 2019 | AQ3: Q1 2020 | AR3: Q2 2020 | AS3: Q3 2020 | AT3: Q4 2020 | AU3: Q1 2021 | AV3: Q2 2021 | AW3: Q3 2021 | AX3: Q4 2021 | AY3: Q1 2022 | AZ3: Q2 2022 | BA3: Q3 2022 | BB3: Q4 2022 | BC3: Q1 2023 | BD3: Q2 2023 | BE3: Q3 2023 | BF3: Q4 2023 | BG3: Q1 2024 | BH3: Q2 2024 | BI3: Q3 2024 | BJ3: Q4 2024 | BK3: Q1 2025 | BL3: Q2 2025 | BM3: Q3 2025 | BN3: Q4 2025 | BO3: Q1 2026 | BP3: Q2 2026 | BQ3: Q3 2026 | BR3: Q4 2026 | CA3: 2010 | CB3: =CA3+1 -> 2011 | CC3: =CB3+1 -> 2012 | CD3: =CC3+1 -> 2013 | CE3: =CD3+1 -> 2014 | CF3: =CE3+1 -> 2015 | CG3: =CF3+1 -> 2016 | CH3: =CG3+1 -> 2017 | CI3: =CH3+1 -> 2018 | ... EW3: =EV3+1 -> 2084
B4: Vascular Access | AQ4: 150.25 | AR4: 164.958 | AS4: 160.05 | AT4: =657.703-SUM(AQ4:AS4) -> 182.445 | AU4: 163.97 | AV4: 167.73 | AW4: 175.47 | AX4: =700.24-SUM(AU4:AW4) -> 193.07 | AY4: 166.13 | AZ4: 163.9 | BA4: 167.14 | BB4: =683.612-SUM(AY4:BA4) -> 186.442 | BC4: 177.65 | BD4: 173.785 | BE4: 169.91 | BF4: =708.04-SUM(BC4:BE4) -> 186.695 | BG4: 181.35 | BH4: 181.1 | BI4: 180.89 | BJ4: =732.67-SUM(BG4:BI4) -> 189.33 | BK4: 182.36 | BL4: 185.53 | BM4: 191.02 | BO4: 236.812 | BP4: 246.337 | CK4: =SUM(AQ4:AT4) -> 657.703 | CL4: =SUM(AU4:AX4) -> 700.24 | CM4: =SUM(AY4:BB4) -> 683.612 | CN4: =SUM(BC4:BF4) -> 708.04 | CO4: =SUM(BG4:BJ4) -> 732.67 | CP4: =CO4*(1+CP13) -> 752.81843 | CQ4: =CP4*(1+CQ13) -> 779.16707 | CR4: =CQ4*(1+CR13) -> 804.49 | CS4: =CR4*(1+CS13) -> 828.6247 | CT4: =CS4*(1+CT13) -> 853.48344 | CU4: =CT4*(1+CU13) -> 879.08794 | CV4: =CU4*(1+CV13) -> 905.46058 | CW4: =CV4*(1+CW13) -> 932.6244 | ... CY4: =CX4*(1+CY13) -> 989.42123
B5: Interventional Cardiology | AQ5: 99.93 | AR5: 82.594 | AS5: 93.18 | AT5: =382.43-SUM(AQ5:AS5) -> 106.726 | AU5: 96.173 | AV5: 112.08 | AW5: 104.304 | AX5: =427.5-SUM(AU5:AW5) -> 114.943 | AY5: 96.85 | AZ5: 114.34 | BA5: 97.6 | BB5: =445.01-SUM(AY5:BA5) -> 136.22 | BC5: 116.89 | BD5: 124.78 | BE5: 134.089 | BF5: =511.434-SUM(BC5:BE5) -> 135.675 | BG5: 134.665 | BH5: 141.15 | BI5: 149.86 | BJ5: =586.05-SUM(BG5:BI5) -> 160.375 | BK5: 137.55 | BL5: 170.01 | BM5: 266.41 | BO5: 204.656 | BP5: 211.874 | CK5: =SUM(AQ5:AT5) -> 382.43 | CL5: =SUM(AU5:AX5) -> 427.5 | CM5: =SUM(AY5:BB5) -> 445.01 | CN5: =SUM(BC5:BF5) -> 511.434 | CO5: =SUM(BG5:BJ5) -> 586.05 | CP5: =CO5*(1+CP14) -> 791.1675 | CQ5: =CP5*(1+CQ14) -> 957.31268 | CR5: =CQ5*(1+CR14) -> 1120.0558 | CS5: =CR5*(1+CS14) -> 1276.8636 | CT5: =CS5*(1+CT14) -> 1417.3186 | CU5: =CT5*(1+CU14) -> 1544.8773 | CV5: =CU5*(1+CV14) -> 1668.4675 | CW5: =CV5*(1+CW14) -> 1785.2602 | ... CY5: =CX5*(1+CY14) -> 1986.9946
B6: Anesthesia | AQ6: 75.7 | AR6: 64.867 | AS6: 75.64 | AT6: =302.293-SUM(AQ5:AS5) -> 26.589 | AU6: 84.85 | AV6: 95.42 | AW6: 97.07 | AX6: =380.14-SUM(AU6:AW6) -> 102.8 | AY6: 86.95 | AZ6: 104.695 | BA6: 108.73 | BB6: =388.89-SUM(AY6:BA6) -> 88.515 | BC6: 93.33 | BD6: 100.84 | BE6: 97.61 | BF6: =389.957-SUM(BC6:BE6) -> 98.177 | BG6: 96.352 | BH6: 102.49 | BI6: 101.15 | BJ6: =395.28-SUM(BG6:BI6) -> 95.288 | BK6: 86.59 | BL6: 96.38 | BM6: 101.44 | BO6: 0 | BP6: 0 | CK6: =SUM(AQ6:AT6) -> 242.796 | CL6: =SUM(AU6:AX6) -> 380.14 | CM6: =SUM(AW6:BB6) -> 588.76 | CN6: =SUM(AW6:BF6) -> 978.717 | CO6: =SUM(BG6:BJ6) -> 395.28 | CP6: =CO6*(1+CP15) -> 379.4688 | CQ6: =CP6*(1+CQ15) -> 0 | CR6: =CQ6*(1+CR15) -> 0 | CS6: =CR6*(1+CS15) -> 0 | CT6: =CS6*(1+CT15) -> 0 | CU6: =CT6*(1+CU15) -> 0 | CV6: =CU6*(1+CV15) -> 0 | CW6: =CV6*(1+CW15) -> 0 | ... CY6: =CX6*(1+CY15) -> 0
B7: Surgical | AQ7: 75.432 | AR7: 67.275 | AS7: 82.22 | AT7: =317.2-SUM(AQ7:AS7) -> 92.273 | AU7: 80.386 | AV7: 98.18 | AW7: 92.83 | AX7: =377.75-SUM(AU7:AW7) -> 106.354 | AY7: 89.7 | AZ7: 99.64 | BA7: 93.12 | BB7: =392.91-SUM(AY7:BA7) -> 110.45 | BC7: 99.02 | BD7: 105.95 | BE7: 112.8 | BF7: =427.359-SUM(BC7:BE7) -> 109.589 | BG7: 105.52 | BH7: 111.3 | BI7: 111.746 | BJ7: =450.48-SUM(BG7:BI7) -> 121.914 | BK7: 105.78 | BL7: 114.04 | BM7: 122.87 | BO7: 106.794 | BP7: 112.121 | CK7: =SUM(AQ7:AT7) -> 317.2 | CL7: =SUM(AU7:AX7) -> 377.75 | CM7: =SUM(AY7:BB7) -> 392.91 | CN7: =SUM(BC7:BF7) -> 427.359 | CO7: =SUM(BG7:BJ7) -> 450.48 | CP7: =CO7*(1+CP16) -> 477.5088 | CQ7: =CP7*(1+CQ16) -> 510.93442 | CR7: =CQ7*(1+CR16) -> 551.80917 | CS7: =CR7*(1+CS16) -> 584.91772 | CT7: =CS7*(1+CT16) -> 614.16361 | CU7: =CT7*(1+CU16) -> 641.80097 | CV7: =CU7*(1+CV16) -> 667.47301 | CW7: =CV7*(1+CW16) -> 690.83456 | ... CY7: =CX7*(1+CY16) -> 734.68529
B8: Interventional Urology | AQ8: 74.19 | AR8: 40.09 | AS8: 81.77 | AT8: =290.02-SUM(AQ8:AS8) -> 93.97 | AU8: 73.36 | AV8: 92.24 | AW8: 83.107 | AX8: =341.66-SUM(AU8:AW8) -> 92.953 | AY8: 74.89 | AZ8: 79.81 | BA8: 78.969 | BB8: =322.83-SUM(AY8:BA8) -> 89.161 | BC8: 75.37 | BD8: 77.81 | BE8: 73.622 | BF8: =319.785-SUM(BC8:BE8) -> 92.983 | BG8: 79.74 | BH8: 83.1 | BI8: 83.39 | BJ8: =331.092-SUM(BG8:BI8) -> 84.862 | BK8: 70.96 | BL8: 76.38 | BM8: 71.77 | BO8: 0 | BP8: 0 | CK8: =SUM(AQ8:AT8) -> 290.02 | CL8: =SUM(AU8:AX8) -> 341.66 | CM8: =SUM(AY8:BB8) -> 322.83 | CN8: =SUM(BC8:BF8) -> 319.785 | CO8: =SUM(BG8:BJ8) -> 331.092 | CP8: =CO8*(1+CP17) -> 314.5374 | CQ8: =CP8*(1+CQ17) -> 0 | CR8: =CQ8*(1+CR17) -> 0 | CS8: =CR8*(1+CS17) -> 0 | CT8: =CS8*(1+CT17) -> 0 | CU8: =CT8*(1+CU17) -> 0 | CV8: =CU8*(1+CV17) -> 0 | CW8: =CV8*(1+CW17) -> 0 | ... CY8: =CX8*(1+CY17) -> 0
B9: OEM | AQ9: 63.389 | AR9: 55.832 | AS9: 49.399 | AT9: =220.246-SUM(AQ9:AS9) -> 51.626 | AU9: 53.48 | AV9: 60.95 | AW9: 64.08 | AX9: =245.681-SUM(AU9:AW9) -> 67.171 | AY9: 57.656 | AZ9: 70 | BA9: 71.28 | BB9: =272.624-SUM(AY9:BA9) -> 73.688 | BC9: 76.99 | BD9: 84.12 | BE9: 82.309 | BF9: =326.008-SUM(BC9:BE9) -> 82.589 | BG9: 87.69 | BH9: 88.82 | BI9: 82.55 | BJ9: =344.51-SUM(BG9:BI9) -> 85.45 | BK9: 63.88 | BL9: 78.67 | BM9: 80.41 | BO9: 0 | BP9: 0 | CK9: =SUM(AQ9:AT9) -> 220.246 | CL9: =SUM(AU9:AX9) -> 245.681 | CM9: =SUM(AY9:BB9) -> 272.624 | CN9: =SUM(BC9:BF9) -> 326.008 | CO9: =SUM(BG9:BJ9) -> 344.51 | CP9: =CO9*(1+CP18) -> 310.059 | CQ9: =CP9*(1+CQ18) -> 0 | CR9: =CQ9*(1+CR18) -> 0 | CS9: =CR9*(1+CS18) -> 0 | CT9: =CS9*(1+CT18) -> 0 | CU9: =CT9*(1+CU18) -> 0 | CV9: =CU9*(1+CV18) -> 0 | CW9: =CV9*(1+CW18) -> 0 | ... CY9: =CX9*(1+CY18) -> 0
B10: Other | AQ10: 91.73 | AR10: 91.414 | AS10: 86.02 | AT10: =367.25-SUM(AQ10:AS10) -> 98.086 | AU10: 81.683 | AV10: 86.84 | AW10: 83.37 | AX10: =336.585-SUM(AU10:AW10) -> 84.692 | AY10: 69.512 | AZ10: 72.13 | BA10: 69.9 | BB10: =285.148-SUM(AY10:BA10) -> 73.606 | BC10: 71.65 | BD10: 75.95 | BE10: 76.033 | BF10: =291.902-SUM(BC10:BE10) -> 68.269 | BG10: 52.51 | BH10: 41.7 | BI10: 54.76 | BJ10: =207.222-SUM(BG10:BI10) -> 58.252 | BK10: 53.6 | BL10: 59.84 | BM10: 79.07 | BO10: 0 | BP10: 0 | CK10: =SUM(AQ10:AT10) -> 367.25 | CL10: =SUM(AU10:AX10) -> 336.585 | CM10: =SUM(AY10:BB10) -> 285.148 | CN10: =SUM(BC10:BF10) -> 291.902 | CO10: =SUM(BG10:BJ10) -> 207.222 | CP10: =CO10*(1+CP19) -> 211.36644 | CQ10: =CP10*(1+CQ19) -> 215.59377 | CR10: =CQ10*(1+CR19) -> 219.90564 | CS10: =CR10*(1+CS19) -> 224.30376 | CT10: =CS10*(1+CT19) -> 228.78983 | CU10: =CT10*(1+CU19) -> 233.36563 | CV10: =CU10*(1+CV19) -> 238.03294 | CW10: =CV10*(1+CW19) -> 242.7936 | ... CY10: =CX10*(1+CY19) -> 252.60246
B11: Ttl Revenues | AQ11: =SUM(AQ4:AQ10) -> 630.621 | AR11: =SUM(AR4:AR10) -> 567.03 | AS11: =SUM(AS4:AS10) -> 628.279 | AT11: =SUM(AT4:AT10) -> 651.715 | AU11: =SUM(AU4:AU10) -> 633.902 | AV11: =SUM(AV4:AV10) -> 713.44 | AW11: =SUM(AW4:AW10) -> 700.231 | AX11: =SUM(AX4:AX10) -> 761.983 | ... BM11: =SUM(BM4:BM10) -> 912.99 | BO11: =SUM(BO4:BO10) -> 548.262 | BP11: =SUM(BP4:BP10) -> 570.332 | CK11: =SUM(AQ11:AT11) -> 2477.645 | CL11: =SUM(AU11:AX11) -> 2809.556 | CM11: =SUM(AY11:BB11) -> 2791.024 | CN11: =SUM(BC11:BF11) -> 2974.485 | CO11: =SUM(BG11:BJ11) -> 3047.304 | CP11: =SUM(CP4:CP10) -> 3236.9264 | CQ11: =SUM(CQ4:CQ10) -> 2463.0079 | CR11: =SUM(CR4:CR10) -> 2696.2606 | CS11: =SUM(CS4:CS10) -> 2914.7098 | CT11: =SUM(CT4:CT10) -> 3113.7555 | CU11: =SUM(CU4:CU10) -> 3299.1319 | CV11: =SUM(CV4:CV10) -> 3479.434 | CW11: =SUM(CW4:CW10) -> 3651.5128 | ... CY11: =SUM(CY4:CY10) -> 3963.7036
B13: Vascular Access Growth Y/y | AU13: =AU4/AQ4-1 -> 0.091314476 | AV13: =AV4/AR4-1 -> 0.016804277 | AW13: =AW4/AS4-1 -> 0.096344892 | AX13: =AX4/AT4-1 -> 0.058236729 | AY13: =AY4/AU4-1 -> 0.013173141 | AZ13: =AZ4/AV4-1 -> -0.022834317 | BA13: =BA4/AW4-1 -> -0.047472502 | BB13: =BB4/AX4-1 -> -0.034329518 | ... BM13: =BM4/BI4-1 -> 0.056000885 | BO13: =BO4/BK4-1 -> 0.29859618 | BP13: =BP4/BL4-1 -> 0.32774753 | CL13: =CL4/CK4-1 -> 0.064675089 | CM13: =CM4/CL4-1 -> -0.023746144 | CN13: =CN4/CM4-1 -> 0.03573372 | CO13: =CO4/CN4-1 -> 0.03478617 | CP13: 0.0275 | CQ13: 0.035 | CR13: 0.0325 | CS13: 0.03 | CT13: 0.03 | CU13: 0.03 | CV13: 0.03 | CW13: 0.03 | CX13: 0.03 | CY13: 0.03
B14: Vascular Intervention Growth Y/y | AU14: =AU5/AQ5-1 -> -0.037596317 | AV14: =AV5/AR5-1 -> 0.3569993 | AW14: =AW5/AS5-1 -> 0.11938184 | AX14: =AX5/AT5-1 -> 0.076991548 | AY14: =AY5/AU5-1 -> 0.0070393978 | AZ14: =AZ5/AV5-1 -> 0.020164168 | BA14: =BA5/AW5-1 -> -0.064273662 | BB14: =BB5/AX5-1 -> 0.18510914 | ... BM14: =BM5/BI5-1 -> 0.77772588 | BO14: =BO5/BK5-1 -> 0.48786623 | BP14: =BP5/BL5-1 -> 0.24624434 | CL14: =CL5/CK5-1 -> 0.11785163 | CM14: =CM5/CL5-1 -> 0.040959064 | CN14: =CN5/CM5-1 -> 0.14926406 | CO14: =CO5/CN5-1 -> 0.14589566 | CP14: 0.35 | CQ14: 0.21 | CR14: 0.17 | CS14: 0.14 | CT14: 0.11 | CU14: 0.09 | CV14: 0.08 | CW14: 0.07 | CX14: 0.06 | CY14: 0.05
B15: Anesthesia Growth Y/y | AU15: =AU6/AQ6-1 -> 0.12087186 | AV15: =AV6/AR6-1 -> 0.47100991 | AW15: =AW6/AS6-1 -> 0.28331571 | AX15: =AX6/AT6-1 -> 2.8662605 | AY15: =AY6/AU6-1 -> 0.024749558 | AZ15: =AZ6/AV6-1 -> 0.097201844 | BA15: =BA6/AW6-1 -> 0.1201195 | BB15: =BB6/AX6-1 -> -0.13895914 | ... BM15: =BM6/BI6-1 -> 0.0028670292 | BO15: =BO6/BK6-1 -> -1 | BP15: =BP6/BL6-1 -> -1 | CL15: =CL6/CK6-1 -> 0.56567654 | CM15: =CM6/CL6-1 -> 0.54879781 | CN15: =CN6/CM6-1 -> 0.6623361 | CO15: =CO6/CN6-1 -> -0.59612431 | CP15: -0.04 | CQ15: -1 | CR15: -1 | CS15: 0 | CT15: 0 | CU15: 0 | CV15: 0 | CW15: 0 | CX15: 0 | CY15: 0
B16: Surgical Growth Y/y | AU16: =AU7/AQ7-1 -> 0.065675045 | AV16: =AV7/AR7-1 -> 0.45938313 | AW16: =AW7/AS7-1 -> 0.12904403 | AX16: =AX7/AT7-1 -> 0.15260152 | AY16: =AY7/AU7-1 -> 0.11586595 | AZ16: =AZ7/AV7-1 -> 0.014870646 | BA16: =BA7/AW7-1 -> 0.0031239901 | BB16: =BB7/AX7-1 -> 0.038512891 | ... BM16: =BM7/BI7-1 -> 0.099547187 | BO16: =BO7/BK7-1 -> 0.0095859331 | BP16: =BP7/BL7-1 -> -0.016827429 | CL16: =CL7/CK7-1 -> 0.19088903 | CM16: =CM7/CL7-1 -> 0.040132363 | CN16: =CN7/CM7-1 -> 0.087676567 | CO16: =CO7/CN7-1 -> 0.054102055 | CP16: 0.06 | CQ16: 0.07 | CR16: 0.08 | CS16: 0.06 | CT16: 0.05 | CU16: 0.045 | CV16: 0.04 | CW16: 0.035 | CX16: 0.0325 | CY16: 0.03
B17: Interventional Urology Growth Y/y | AU17: =AU8/AQ8-1 -> -0.011187492 | AV17: =AV8/AR8-1 -> 1.3008231 | AW17: =AW8/AS8-1 -> 0.01635074 | AX17: =AX8/AT8-1 -> -0.010822603 | AY17: =AY8/AU8-1 -> 0.020856052 | AZ17: =AZ8/AV8-1 -> -0.13475716 | BA17: =BA8/AW8-1 -> -0.049791233 | BB17: =BB8/AX8-1 -> -0.04079481 | ... BM17: =BM8/BI8-1 -> -0.13934525 | BO17: =BO8/BK8-1 -> -1 | BP17: =BP8/BL8-1 -> -1 | CL17: =CL8/CK8-1 -> 0.17805669 | CM17: =CM8/CL8-1 -> -0.055113271 | CN17: =CN8/CM8-1 -> -0.0094322089 | CO17: =CO8/CN8-1 -> 0.035358131 | CP17: -0.05 | CQ17: -1 | CR17: -1 | CS17: 0 | CT17: 0 | CU17: 0 | CV17: 0 | CW17: 0 | CX17: 0 | CY17: 0
B18: OEM Growth Y/y | AU18: =AU9/AQ9-1 -> -0.1563205 | AV18: =AV9/AR9-1 -> 0.091667861 | AW18: =AW9/AS9-1 -> 0.29719225 | AX18: =AX9/AT9-1 -> 0.30110797 | AY18: =AY9/AU9-1 -> 0.078085266 | AZ18: =AZ9/AV9-1 -> 0.14848236 | BA18: =BA9/AW9-1 -> 0.11235955 | BB18: =BB9/AX9-1 -> 0.097021036 | ... BM18: =BM9/BI9-1 -> -0.025923683 | BO18: =BO9/BK9-1 -> -1 | BP18: =BP9/BL9-1 -> -1 | CL18: =CL9/CK9-1 -> 0.1154845 | CM18: =CM9/CL9-1 -> 0.1096666 | CN18: =CN9/CM9-1 -> 0.19581548 | CO18: =CO9/CN9-1 -> 0.056753209 | CP18: -0.1 | CQ18: -1 | CR18: -1 | CS18: 0 | CT18: 0 | CU18: 0 | CV18: 0 | CW18: 0 | CX18: 0 | CY18: 0
B19: Other Growth Y/y | AU19: =AU10/AQ10-1 -> -0.10952796 | AV19: =AV10/AR10-1 -> -0.0500361 | AW19: =AW10/AS10-1 -> -0.030806789 | AX19: =AX10/AT10-1 -> -0.13655364 | AY19: =AY10/AU10-1 -> -0.14900285 | AZ19: =AZ10/AV10-1 -> -0.16939199 | BA19: =BA10/AW10-1 -> -0.16156891 | BB19: =BB10/AX10-1 -> -0.13089784 | ... BM19: =BM10/BI10-1 -> 0.44393718 | BO19: =BO10/BK10-1 -> -1 | BP19: =BP10/BL10-1 -> -1 | CL19: =CL10/CK10-1 -> -0.083498979 | CM19: =CM10/CL10-1 -> -0.15282024 | CN19: =CN10/CM10-1 -> 0.023685946 | CO19: =CO10/CN10-1 -> -0.29009736 | CP19: 0.02 | CQ19: 0.02 | CR19: 0.02 | CS19: 0.02 | CT19: 0.02 | CU19: 0.02 | CV19: 0.02 | CW19: 0.02 | CX19: 0.02 | CY19: 0.02
B20: Ttl Revenues Growth Y/y | AU20: =AU11/AQ11-1 -> 0.005202808 | AV20: =AV11/AR11-1 -> 0.25820503 | AW20: =AW11/AS11-1 -> 0.11452237 | AX20: =AX11/AT11-1 -> 0.16919666 | AY20: =AY11/AU11-1 -> 0.012282656 | AZ20: =AZ11/AV11-1 -> -0.012509812 | BA20: =BA11/AW11-1 -> -0.019267927 | BB20: =BB11/AX11-1 -> -0.0051195368 | ... BM20: =BM11/BI11-1 -> 0.19447214 | BO20: =BO11/BK11-1 -> -0.21757335 | BP20: =BP11/BL11-1 -> -0.26960108 | CL20: =CL11/CK11-1 -> 0.13396229 | CM20: =CM11/CL11-1 -> -0.00659606 | CN20: =CN11/CM11-1 -> 0.065732505 | CO20: =CO11/CN11-1 -> 0.024481213 | CP20: =CP11/CO11-1 -> 0.062226271 | CQ20: =CQ11/CP11-1 -> -0.23909053 | CR20: =CR11/CQ11-1 -> 0.09470238 | CS20: =CS11/CR11-1 -> 0.081019311 | ... CY20: =CY11/CX11-1 -> 0.039274203
B22: Vascular Access % of Ttl Revenues | AQ22: =AQ4/AQ11 -> 0.23825721 | AR22: =AR4/AR11 -> 0.29091582 | AS22: =AS4/AS11 -> 0.25474351 | AT22: =AT4/AT11 -> 0.27994599 | AU22: =AU4/AU11 -> 0.25866774 | AV22: =AV4/AV11 -> 0.23510036 | AW22: =AW4/AW11 -> 0.25058873 | AX22: =AX4/AX11 -> 0.25337836 | ... BM22: =BM4/BM11 -> 0.20922464 | BO22: =BO4/BO11 -> 0.43193218 | BP22: =BP4/BP11 -> 0.4319186 | CK22: =CK4/CK11 -> 0.2654549 | CL22: =CL4/CL11 -> 0.24923511 | CM22: =CM4/CM11 -> 0.24493233 | CN22: =CN4/CN11 -> 0.23803785 | CO22: =CO4/CO11 -> 0.2404322
B23: Interventional % of Ttl Revenues | AQ23: =AQ5/AQ11 -> 0.15846285 | AR23: =AR5/AR11 -> 0.14566072 | AS23: =AS5/AS11 -> 0.14830991 | AT23: =AT5/AT11 -> 0.16376177 | AU23: =AU5/AU11 -> 0.15171588 | AV23: =AV5/AV11 -> 0.157098 | AW23: =AW5/AW11 -> 0.14895656 | AX23: =AX5/AX11 -> 0.1508472 | ... BM23: =BM5/BM11 -> 0.29179947 | BO23: =BO5/BO11 -> 0.37328139 | BP23: =BP5/BP11 -> 0.37149239 | CK23: =CK5/CK11 -> 0.15435222 | CL23: =CL5/CL11 -> 0.15215927 | CM23: =CM5/CM11 -> 0.15944327 | CN23: =CN5/CN11 -> 0.17194035 | CO23: =CO5/CO11 -> 0.19231754
B24: Anesthesia % of Ttl Revenues | AQ24: =AQ6/AQ11 -> 0.1200404 | AR24: =AR6/AR11 -> 0.11439783 | AS24: =AS6/AS11 -> 0.12039237 | AT24: =AT6/AT11 -> 0.040798509 | AU24: =AU6/AU11 -> 0.1338535 | AV24: =AV6/AV11 -> 0.13374636 | AW24: =AW6/AW11 -> 0.13862568 | AX24: =AX6/AX11 -> 0.13491115 | ... BM24: =BM6/BM11 -> 0.11110746 | BO24: =BO6/BO11 -> 0 | BP24: =BP6/BP11 -> 0 | CK24: =CK6/CK11 -> 0.097994668 | CL24: =CL6/CL11 -> 0.13530252 | CM24: =CM6/CM11 -> 0.21094767 | CN24: =CN6/CN11 -> 0.32903746 | CO24: =CO6/CO11 -> 0.12971466
B25: Surgical % of Ttl Revenues | AQ25: =AQ7/AQ11 -> 0.11961543 | AR25: =AR7/AR11 -> 0.11864452 | AS25: =AS7/AS11 -> 0.13086543 | AT25: =AT7/AT11 -> 0.1415849 | AU25: =AU7/AU11 -> 0.1268114 | AV25: =AV7/AV11 -> 0.13761494 | AW25: =AW7/AW11 -> 0.13257054 | AX25: =AX7/AX11 -> 0.13957529 | ... BM25: =BM7/BM11 -> 0.13457979 | BO25: =BO7/BO11 -> 0.19478643 | BP25: =BP7/BP11 -> 0.196589 | CK25: =CK7/CK11 -> 0.1280248 | CL25: =CL7/CL11 -> 0.13445185 | CM25: =CM7/CM11 -> 0.14077629 | CN25: =CN7/CN11 -> 0.14367496 | CO25: =CO7/CO11 -> 0.14782903
B26: Interventional Urology % of Ttl Revenues | AQ26: =AQ8/AQ11 -> 0.11764594 | AR26: =AR8/AR11 -> 0.070701727 | AS26: =AS8/AS11 -> 0.13014919 | AT26: =AT8/AT11 -> 0.14418879 | AU26: =AU8/AU11 -> 0.11572767 | AV26: =AV8/AV11 -> 0.12928908 | AW26: =AW8/AW11 -> 0.11868512 | AX26: =AX8/AX11 -> 0.12198829 | ... BM26: =BM8/BM11 -> 0.078609842 | BO26: =BO8/BO11 -> 0 | BP26: =BP8/BP11 -> 0 | CK26: =CK8/CK11 -> 0.1170547 | CL26: =CL8/CL11 -> 0.1216064 | CM26: =CM8/CM11 -> 0.11566722 | CN26: =CN8/CN11 -> 0.10750937 | CO26: =CO8/CO11 -> 0.10865079
B27: OEM % of Ttl Revenues | AQ27: =AQ9/AQ11 -> 0.10051838 | AR27: =AR9/AR11 -> 0.098463926 | AS27: =AS9/AS11 -> 0.078625897 | AT27: =AT9/AT11 -> 0.079215608 | AU27: =AU9/AU11 -> 0.084366353 | AV27: =AV9/AV11 -> 0.08543115 | AW27: =AW9/AW11 -> 0.091512658 | AX27: =AX9/AX11 -> 0.088152885 | ... BM27: =BM9/BM11 -> 0.088073254 | BO27: =BO9/BO11 -> 0 | BP27: =BP9/BP11 -> 0 | CK27: =CK9/CK11 -> 0.088893284 | CL27: =CL9/CL11 -> 0.087444778 | CM27: =CM9/CM11 -> 0.097678845 | CN27: =CN9/CN11 -> 0.10960149 | CO27: =CO9/CO11 -> 0.11305403
B28: Other % of Ttl Revenues | AQ28: =AQ10/AQ11 -> 0.14545979 | AR28: =AR10/AR11 -> 0.16121546 | AS28: =AS10/AS11 -> 0.1369137 | AT28: =AT10/AT11 -> 0.15050444 | AU28: =AU10/AU11 -> 0.12885746 | AV28: =AV10/AV11 -> 0.12172012 | AW28: =AW10/AW11 -> 0.11906071 | AX28: =AX10/AX11 -> 0.11114684 | ... BM28: =BM10/BM11 -> 0.086605549 | BO28: =BO10/BO11 -> 0 | BP28: =BP10/BP11 -> 0 | CK28: =CK10/CK11 -> 0.14822543 | CL28: =CL10/CL11 -> 0.11980007 | CM28: =CM10/CM11 -> 0.10216609 | CN28: =CN10/CN11 -> 0.098135307 | CO28: =CO10/CO11 -> 0.068001748
B30: U.S. Revenues | BC30: =411.86+76.99 -> 488.85 | BD30: =424.64+84.128 -> 508.768 | BE30: =428.206+82.309 -> 510.515 | BF30: =2041.4-SUM(BC30:BE30) -> 533.267 | BG30: 494 | BH30: 515.6 | BI30: =433.3+82.6 -> 515.9 | BJ30: =2066.3-SUM(BG30:BI30) -> 540.8 | BK30: 475.7 | BL30: 525.7 | BM30: 555.9 | BN30: =1279.197-SUM(BK30:BM30) -> -278.103 | BO30: 332.653 | BP30: 348.838 | CN30: =SUM(BC30:BF30) -> 2041.4 | CO30: =SUM(BG30:BJ30) -> 2066.3
B31: EMEA Revenues | BC31: 143.34 | BD31: 147.809 | BE31: 142.723 | BF31: =586.2-SUM(BC31:BE31) -> 152.328 | BG31: 159.6 | BH31: 147.1 | BI31: 150.22 | BJ31: =618-SUM(BG31:BI31) -> 161.08 | BK31: 151.2 | BL31: 166.2 | BM31: 234.24 | BN31: =472.411-SUM(BK31:BM31) -> -79.229 | BO31: 146.678 | BP31: 145.531 | CN31: =SUM(BC31:BF31) -> 586.2 | CO31: =SUM(BG31:BJ31) -> 618
B32: Asia Revenues | BC32: 78.731 | BD32: 86.678 | BE32: 93.151 | BF32: =346.9-SUM(BC32:BE32) -> 88.34 | BG32: 84.2 | BH32: 87 | BI32: 98.26 | BJ32: =363-SUM(BG32:BI32) -> 93.54 | BK32: 73.8 | BL32: 89 | BM32: 122.87 | BN32: =241.105-SUM(BK32:BM32) -> -44.565 | BO32: 68.93 | BP32: 75.963 | CN32: =SUM(BC32:BF32) -> 346.9 | CO32: =SUM(BG32:BJ32) -> 363
B33: Ttl Revenues | BC33: =SUM(BC30:BC32) -> 710.921 | BD33: =SUM(BD30:BD32) -> 743.255 | BE33: =SUM(BE30:BE32) -> 746.389 | BF33: =SUM(BF30:BF32) -> 773.935 | BG33: =SUM(BG30:BG32) -> 737.8 | BH33: =SUM(BH30:BH32) -> 749.7 | BI33: =SUM(BI30:BI32) -> 764.38 | BJ33: =SUM(BJ30:BJ32) -> 795.42 | ... BP33: =SUM(BP30:BP32) -> 570.332 | CN33: =SUM(BC33:BF33) -> 2974.5 | CO33: =SUM(BG33:BJ33) -> 3047.3
B35: U.S. Revenues Growth Y/y | BG35: =BG30/BC30-1 -> 0.010534929 | BH35: =BH30/BD30-1 -> 0.013428518 | BI35: =BI30/BE30-1 -> 0.010548172 | BJ35: =BJ30/BF30-1 -> 0.014126132 | BK35: =BK30/BG30-1 -> -0.037044534 | BL35: =BL30/BH30-1 -> 0.019588829 | BM35: =BM30/BI30-1 -> 0.077534406 | BN35: =BN30/BJ30-1 -> -1.5142437 | ... BP35: =BP30/BL30-1 -> -0.33643142 | CO35: =CO30/CN30-1 -> 0.012197512
B36: EMEA Revenues Growth Y/y | BG36: =BG31/BC31-1 -> 0.11343658 | BH36: =BH31/BD31-1 -> -0.0047967309 | BI36: =BI31/BE31-1 -> 0.052528324 | BJ36: =BJ31/BF31-1 -> 0.057454966 | BK36: =BK31/BG31-1 -> -0.052631579 | BL36: =BL31/BH31-1 -> 0.12984364 | BM36: =BM31/BI31-1 -> 0.55931301 | BN36: =BN31/BJ31-1 -> -1.4918612 | ... BP36: =BP31/BL31-1 -> -0.12436221 | CO36: =CO31/CN31-1 -> 0.054247697
B37: Asia Revenues Growth Y/y | BG37: =BG32/BC32-1 -> 0.069464379 | BH37: =BH32/BD32-1 -> 0.0037148988 | BI37: =BI32/BE32-1 -> 0.054846432 | BJ37: =BJ32/BF32-1 -> 0.058863482 | BK37: =BK32/BG32-1 -> -0.12351544 | BL37: =BL32/BH32-1 -> 0.022988506 | BM37: =BM32/BI32-1 -> 0.25045797 | BN37: =BN32/BJ32-1 -> -1.4764272 | ... BP37: =BP32/BL32-1 -> -0.14648315 | CO37: =CO32/CN32-1 -> 0.046411069
B38: Ttl Revenues Growth Y/y | BG38: =BG33/BC33-1 -> 0.037808702 | BH38: =BH33/BD33-1 -> 0.0086713174 | BI38: =BI33/BE33-1 -> 0.024104053 | BJ38: =BJ33/BF33-1 -> 0.027760729 | BK38: =BK33/BG33-1 -> -0.05028463 | BL38: =BL33/BH33-1 -> 0.041616647 | BM38: =BM33/BI33-1 -> 0.19444517 | BN38: =BN33/BJ33-1 -> -1.5052639 | ... BP38: =BP33/BL33-1 -> -0.26964784 | CO38: =CO33/CN33-1 -> 0.024474702
B40: U.S. Revenues % of Revenues | BC40: =BC30/BC33 -> 0.68762915 | BD40: =BD30/BD33 -> 0.68451339 | BE40: =BE30/BE33 -> 0.6839798 | BF40: =BF30/BF33 -> 0.68903332 | BG40: =BG30/BG33 -> 0.66955815 | BH40: =BH30/BH33 -> 0.68774176 | BI40: =BI30/BI33 -> 0.67492608 | BJ40: =BJ30/BJ33 -> 0.67989238 | ... BP40: =BP30/BP33 -> 0.61164024 | CN40: =CN30/CN33 -> 0.68630022 | CO40: =CO30/CO33 -> 0.67807567
B41: EMEA Revenues % of Revenues | BC41: =BC31/BC33 -> 0.20162578 | BD41: =BD31/BD33 -> 0.19886715 | BE41: =BE31/BE33 -> 0.19121798 | BF41: =BF31/BF33 -> 0.19682273 | BG41: =BG31/BG33 -> 0.21631879 | BH41: =BH31/BH33 -> 0.19621182 | BI41: =BI31/BI33 -> 0.19652529 | BJ41: =BJ31/BJ33 -> 0.20250937 | ... BP41: =BP31/BP33 -> 0.25516892 | CN41: =CN31/CN33 -> 0.19707514 | CO41: =CO31/CO33 -> 0.20280248
B42: Asia Revenues % of Revenues | BC42: =BC32/BC33 -> 0.11074508 | BD42: =BD32/BD33 -> 0.11661946 | BE42: =BE32/BE33 -> 0.12480221 | BF42: =BF32/BF33 -> 0.11414395 | BG42: =BG32/BG33 -> 0.11412307 | BH42: =BH32/BH33 -> 0.11604642 | BI42: =BI32/BI33 -> 0.12854863 | BJ42: =BJ32/BJ33 -> 0.11759825 | ... BP42: =BP32/BP33 -> 0.13319084 | CN42: =CN32/CN33 -> 0.11662464 | CO42: =CO32/CO33 -> 0.11912185
B44: Revenues | C44: 367.3 | D44: 358.4 | E44: 345 | F44: 326.9 | G44: 354 | H44: 381.2 | I44: 362.7 | J44: 394.6 | K44: 380.6 | L44: 383.3 | M44: 368.1 | N44: 419.1 | O44: 411.9 | P44: 420.1 | Q44: 413.8 | R44: 450.5 | S44: 438.5 | T44: 468.1 | U44: 457.2 | V44: 476 | W44: 429.4 | X44: 452 | Y44: 443.7 | Z44: 484.5 | AA44: 424.9 | AB44: 473.6 | AC44: 455.6 | AD44: 513.9 | AE44: 487.9 | AF44: 528.6 | AG44: 534.7 | AH44: 595.1 | AI44: 587.2 | AJ44: 609.9 | AK44: 609.7 | AL44: 641.6 | AM44: 613.6 | AN44: 652.5 | AO44: 648.3 | AP44: 681 | AQ44: =AQ11 -> 630.621 | AR44: =AR11 -> 567.03 | AS44: =AS11 -> 628.279 | AT44: =AT11 -> 651.715 | AU44: =AU11 -> 633.902 | AV44: =AV11 -> 713.44 | AW44: =AW11 -> 700.231 | AX44: =AX11 -> 761.983 | ... BM44: =BM11 -> 912.99 | BN44: 500 | BO44: =BO33 -> 548.261 | BP44: =BP33 -> 570.332 | CA44: =SUM(C44:F44) -> 1397.6 | CB44: =SUM(G44:J44) -> 1492.5 | CC44: =SUM(K44:N44) -> 1551.1 | CD44: =SUM(O44:R44) -> 1696.3 | CE44: =SUM(S44:V44) -> 1839.8 | CF44: =SUM(W44:Z44) -> 1809.6 | CG44: =SUM(AA44:AD44) -> 1868 | CH44: =SUM(AE44:AH44) -> 2146.3 | CI44: =SUM(AI44:AL44) -> 2448.4 | CJ44: =SUM(AM44:AP44) -> 2595.4 | CK44: =SUM(AQ44:AT44) -> 2477.645 | CL44: =SUM(AU44:AX44) -> 2809.556 | CM44: =SUM(AY44:BB44) -> 2791.024 | CN44: =SUM(BC44:BF44) -> 2974.485 | CO44: =SUM(BG44:BJ44) -> 3047.304 | CP44: =CP11 -> 3236.9264 | CQ44: =CQ11 -> 2463.0079 | CR44: =CR11 -> 2696.2606 | CS44: =CS11 -> 2914.7098 | CT44: =CT11 -> 3113.7555 | CU44: =CU11 -> 3299.1319 | CV44: =CV11 -> 3479.434 | CW44: =CW11 -> 3651.5128 | ... CY44: =CY11 -> 3963.7036
B45: COGS | C45: 190.4 | D45: 184.1 | E45: 178.5 | F45: 165.8 | G45: 189.5 | H45: 199.8 | I45: 187.1 | J45: 207.3 | K45: 196.5 | L45: 199 | M45: 187.5 | N45: 219.9 | O45: 211.4 | P45: 210.6 | Q45: 209.8 | R45: 225.6 | S45: 217.4 | T45: 224 | U45: 221 | V45: 235 | W45: 206.8 | X45: 218.8 | Y45: 215.5 | Z45: 224.2 | AA45: 199.7 | AB45: 217.2 | AC45: 214 | AD45: 240.9 | AE45: 232.3 | AF45: 238.3 | AG45: 239.5 | AH45: 264.4 | AI45: 256 | AJ45: 265.1 | AK45: 267.1 | AL45: 357.4 | AM45: 289.6 | AN45: 300.3 | AO45: 293.2 | AP45: 303.2 | AQ45: 297.018 | AR45: 288.66 | AS45: 298.977 | AT45: =1212.28-SUM(AQ45:AS45) -> 327.625 | AU45: 289.398 | AV45: 315.917 | AW45: 312.464 | AX45: =1259.961-SUM(AU45:AW45) -> 342.182 | AY45: 295.48 | AZ45: 315.709 | BA45: 312.833 | BB45: =1259.95-SUM(AY45:BA45) -> 335.928 | BC45: 319.55 | BD45: 335.436 | BE45: 330.07 | BF45: =1327.55-SUM(BC45:BE45) -> 342.494 | BG45: 321.715 | BH45: 333.23 | BI45: 334.203 | BJ45: =1344.64-SUM(BG45:BI45) -> 355.492 | BK45: 311.23 | BL45: 349.804 | BM45: 461.37 | BN45: 225 | BO45: 240.836 | BP45: 238.625 | CA45: =SUM(C45:F45) -> 718.8 | CB45: =SUM(G45:J45) -> 783.7 | CC45: =SUM(K45:N45) -> 802.9 | CD45: =SUM(O45:R45) -> 857.4 | CE45: =SUM(S45:V45) -> 897.4 | CF45: =SUM(W45:Z45) -> 865.3 | CG45: =SUM(AA45:AD45) -> 871.8 | CH45: =SUM(AE45:AH45) -> 974.5 | CI45: =SUM(AI45:AL45) -> 1145.6 | CJ45: =SUM(AM45:AP45) -> 1186.3 | CK45: =SUM(AQ45:AT45) -> 1212.28 | CL45: =SUM(AU45:AX45) -> 1259.961 | CM45: =SUM(AY45:BB45) -> 1259.95 | CN45: =SUM(BC45:BF45) -> 1327.55 | CO45: =SUM(BG45:BJ45) -> 1344.64 | CP45: =CP44*(1-CP63) -> 1424.2476 | CQ45: =CQ44*(1-CQ63) -> 1077.566 | CR45: =CR44*(1-CR63) -> 1172.8734 | CS45: =CS44*(1-CS63) -> 1267.8988 | CT45: =CT44*(1-CT63) -> 1354.4837 | CU45: =CU44*(1-CU63) -> 1435.1224 | CV45: =CV44*(1-CV63) -> 1513.5538 | CW45: =CW44*(1-CW63) -> 1588.4081 | ... CY45: =CY44*(1-CY63) -> 1724.2111
B46: GP | C46: =C44-C45 -> 176.9 | D46: =D44-D45 -> 174.3 | E46: =E44-E45 -> 166.5 | F46: =F44-F45 -> 161.1 | G46: =G44-G45 -> 164.5 | H46: =H44-H45 -> 181.4 | I46: =I44-I45 -> 175.6 | J46: =J44-J45 -> 187.3 | ... BP46: =BP44-BP45 -> 331.707 | CA46: =SUM(C46:F46) -> 678.8 | CB46: =SUM(G46:J46) -> 708.8 | CC46: =SUM(K46:N46) -> 748.2 | CD46: =SUM(O46:R46) -> 838.9 | CE46: =SUM(S46:V46) -> 942.4 | CF46: =SUM(W46:Z46) -> 944.3 | CG46: =SUM(AA46:AD46) -> 996.2 | CH46: =SUM(AE46:AH46) -> 1171.8 | CI46: =SUM(AI46:AL46) -> 1302.8 | CJ46: =SUM(AM46:AP46) -> 1409.1 | CK46: =SUM(AQ46:AT46) -> 1265.365 | CL46: =SUM(AU46:AX46) -> 1549.595 | CM46: =SUM(AY46:BB46) -> 1531.074 | CN46: =SUM(BC46:BF46) -> 1646.935 | CO46: =SUM(BG46:BJ46) -> 1702.664 | CP46: =CP44-CP45 -> 1812.6788 | CQ46: =CQ44-CQ45 -> 1385.442 | CR46: =CR44-CR45 -> 1523.3873 | CS46: =CS44-CS45 -> 1646.811 | CT46: =CT44-CT45 -> 1759.2719 | CU46: =CU44-CU45 -> 1864.0095 | CV46: =CV44-CV45 -> 1965.8802 | CW46: =CW44-CW45 -> 2063.1047 | ... CY46: =CY44-CY45 -> 2239.4925
B47: SG&A | C47: 100.6 | D47: 99.8 | E47: 101.5 | F47: 101.8 | G47: 103.2 | H47: 109.8 | I47: 101.6 | J47: 109.3 | K47: 112.1 | L47: 106 | M47: 114.9 | N47: 121.5 | O47: 127 | P47: 116.3 | Q47: 115.2 | R47: 143.8 | S47: 140.3 | T47: 146.8 | U47: 138.3 | V47: 153.3 | W47: 139.7 | X47: 142.2 | Y47: 138.8 | Z47: 148.2 | AA47: 136.3 | AB47: 143 | AC47: 139.8 | AD47: 144.2 | AE47: 164 | AF47: 158.9 | AG47: 163.8 | AH47: 213.3 | AI47: 215.3 | AJ47: 229.9 | AK47: 214.9 | AL47: 136.9 | AM47: 206.9 | AN47: 215.5 | AO47: 209.3 | AP47: 220.1 | AQ47: 147.796 | AR47: 191.193 | AS47: 171.67 | AT47: =743.568-SUM(AQ47:AS47) -> 232.909 | AU47: 203.148 | AV47: 224 | AW47: 205.194 | AX47: =860.08-SUM(AU47:AW47) -> 227.738 | AY47: 203.932 | AZ47: 216.825 | BA47: 209.6 | BB47: =863.748-SUM(AY47:BA47) -> 233.391 | BC47: 232.716 | BD47: 223.306 | BE47: 213.194 | BF47: =929.867-SUM(BC47:BE47) -> 260.651 | BG47: 242.83 | BH47: 250.631 | BI47: 247.257 | BJ47: =995.27-SUM(BG47:BI47) -> 254.552 | BK47: 222.71 | BL47: 215.08 | BM47: 281.76 | BN47: =720.169-SUM(BK47:BM47) -> 0.619 | BO47: 226.012 | BP47: 213.515 | CA47: =SUM(C47:F47) -> 403.7 | CB47: =SUM(G47:J47) -> 423.9 | CC47: =SUM(K47:N47) -> 454.5 | CD47: =SUM(O47:R47) -> 502.3 | CE47: =SUM(S47:V47) -> 578.7 | CF47: =SUM(W47:Z47) -> 568.9 | CG47: =SUM(AA47:AD47) -> 563.3 | CH47: =SUM(AE47:AH47) -> 700 | CI47: =SUM(AI47:AL47) -> 797 | CJ47: =SUM(AM47:AP47) -> 851.8 | CK47: =SUM(AQ47:AT47) -> 743.568 | CL47: =SUM(AU47:AX47) -> 860.08 | CM47: =SUM(AY47:BB47) -> 863.748 | CN47: =SUM(BC47:BF47) -> 929.867 | CO47: =SUM(BG47:BJ47) -> 995.27 | CP47: =CP44*CP65 -> 987.26254 | CQ47: =CQ44*CQ65 -> 812.79262 | CR47: =CR44*CR65 -> 903.24732 | CS47: =CS44*CS65 -> 961.85424 | CT47: =CT44*CT65 -> 996.40177 | CU47: =CU44*CU65 -> 1022.7309 | CV47: =CV44*CV65 -> 1061.2274 | CW47: =CW44*CW65 -> 1095.4538 | ... CY47: =CY44*CY65 -> 1169.2926
B48: R&D | C48: 9.3 | D48: 10.3 | E48: 10.2 | F48: 12.6 | G48: 11 | H48: 12.5 | I48: 12.1 | J48: 13.5 | K48: 11.6 | L48: 13.6 | M48: 14.8 | N48: 16.4 | O48: 15 | P48: 16.5 | Q48: 15.6 | R48: 17.9 | S48: 14.1 | T48: 14.9 | U48: 14.8 | V48: 17.2 | W48: 12.9 | X48: 13.4 | Y48: 12.6 | Z48: 13.2 | AA48: 12.6 | AB48: 15 | AC48: 15.1 | AD48: 15.7 | AE48: 17.9 | AF48: 20.3 | AG48: 21 | AH48: 25.5 | AI48: 26 | AJ48: 26 | AK48: 26.4 | AL48: 27.8 | AM48: 27.3 | AN48: 27.5 | AO48: 28 | AP48: 30.8 | AQ48: 27.396 | AR48: 29.36 | AS48: 29.21 | AT48: =119.747-SUM(AQ48:AS48) -> 33.781 | AU48: 29.94 | AV48: 33.283 | AW48: 31.816 | AX48: =130.84-SUM(AU48:AW48) -> 35.801 | AY48: 36.36 | AZ48: 36.93 | BA48: 37.77 | BB48: =153.819-SUM(AY48:BA48) -> 42.759 | BC48: 41.469 | BD48: 39.448 | BE48: 37.576 | BF48: =154.35-SUM(BC48:BE48) -> 35.857 | BG48: 37.29 | BH48: 41.094 | BI48: 38.726 | BJ48: =161.67-SUM(BG48:BI48) -> 44.56 | BK48: 36.404 | BL48: 38.521 | BM48: 57.22 | BN48: =144.781-SUM(BK48:BM48) -> 12.636 | BO48: 44.386 | BP48: 45.122 | CA48: =SUM(C48:F48) -> 42.4 | CB48: =SUM(G48:J48) -> 49.1 | CC48: =SUM(K48:N48) -> 56.4 | CD48: =SUM(O48:R48) -> 65 | CE48: =SUM(S48:V48) -> 61 | CF48: =SUM(W48:Z48) -> 52.1 | CG48: =SUM(AA48:AD48) -> 58.4 | CH48: =SUM(AE48:AH48) -> 84.7 | CI48: =SUM(AI48:AL48) -> 106.2 | CJ48: =SUM(AM48:AP48) -> 113.6 | CK48: =SUM(AQ48:AT48) -> 119.747 | CL48: =SUM(AU48:AX48) -> 130.84 | CM48: =SUM(AY48:BB48) -> 153.819 | CN48: =SUM(BC48:BF48) -> 154.35 | CO48: =SUM(BG48:BJ48) -> 161.67 | CP48: =CP44*CP64 -> 168.32017 | CQ48: =CQ44*CQ64 -> 133.00243 | CR48: =CR44*CR64 -> 148.29434 | CS48: =CS44*CS64 -> 163.22375 | CT48: =CT44*CT64 -> 177.48406 | CU48: =CU44*CU64 -> 188.05052 | CV48: =CV44*CV64 -> 198.32774 | CW48: =CW44*CW64 -> 208.13623 | ... CY48: =CY44*CY64 -> 198.18518
B49: Pension Settlement Charge | C49: 0 | D49: 0 | E49: 0 | F49: 0 | G49: 0 | H49: 0 | I49: 0 | J49: 0 | K49: 0 | L49: 0 | M49: 0 | N49: 0 | O49: 0 | P49: 0 | Q49: 0 | R49: 0 | S49: 0 | T49: 0 | U49: 0 | V49: 0 | W49: 0 | X49: 0 | Y49: 0 | Z49: 0 | AA49: 0 | AB49: 0 | AC49: 0 | AD49: 0 | AE49: 0 | AF49: 0 | AG49: 0 | AH49: 0 | AI49: 0 | AJ49: 0 | AK49: 0 | AL49: 0 | AM49: 0 | AN49: 0 | AO49: 0 | AP49: 0 | AQ49: 0 | AR49: 0 | AS49: 0 | AT49: =0-SUM(AQ49:AS49) -> 0 | AU49: 0 | AV49: 0 | AW49: 0 | AX49: =0-SUM(AU49:AW49) -> 0 | AY49: 0 | AZ49: 0 | BA49: 0 | BB49: =0-SUM(AY49:BA49) -> 0 | BC49: 0 | BD49: 0 | BE49: 0 | BF49: =45.244-SUM(BC49:BE49) -> 45.244 | BG49: 138.139 | BH49: 0 | BI49: -5.407 | BJ49: =132.73-SUM(BG49:BI49) -> -0.002 | BK49: 0 | BL49: 0 | BM49: 0 | BN49: =0-SUM(BK49:BM49) -> 0 | BO49: 0 | BP49: 0 | CA49: =SUM(C49:F49) -> 0 | CB49: =SUM(G49:J49) -> 0 | CC49: =SUM(K49:N49) -> 0 | CD49: =SUM(O49:R49) -> 0 | CE49: =SUM(S49:V49) -> 0 | CF49: =SUM(W49:Z49) -> 0 | CG49: =SUM(AA49:AD49) -> 0 | CH49: =SUM(AE49:AH49) -> 0 | CI49: =SUM(AI49:AL49) -> 0 | CJ49: =SUM(AM49:AP49) -> 0 | CK49: =SUM(AQ49:AT49) -> 0 | CL49: =SUM(AU49:AX49) -> 0 | CM49: =SUM(AY49:BB49) -> 0 | CN49: =SUM(BC49:BF49) -> 45.244 | CO49: =SUM(BG49:BJ49) -> 132.73 | CP49: 0 | CQ49: 0 | CR49: 0 | CS49: 0 | CT49: 0 | CU49: 0 | CV49: 0 | CW49: 0 | CX49: 0 | CY49: 0
B50: Goodwill Impairment | C50: 0.4 | D50: 0 | E50: 1.3 | F50: 0.6 | G50: 0.6 | H50: 3.2 | I50: 0 | J50: 2.4 | K50: 330.8 | L50: 0 | M50: 1 | N50: 2.9 | O50: 9.1 | P50: 12.9 | Q50: 7.2 | R50: 9.1 | S50: 7.7 | T50: 7.6 | U50: 1.2 | V50: 1.3 | W50: 4.4 | X50: 0.6 | Y50: 0.2 | Z50: 2.2 | AA50: 8.8 | AB50: 0 | AC50: 0.2 | AD50: 46.1 | AE50: 12.9 | AF50: 0.9 | AG50: 0 | AH50: 1 | AI50: 3.1 | AJ50: 55.4 | AK50: 19.2 | AL50: 0.2 | AM50: 14.6 | AN50: 1.7 | AO50: 0.2 | AP50: 0 | AQ50: 0 | AR50: 0 | AS50: 0 | AT50: =0-SUM(AQ50:AS50) -> 0 | AU50: 0 | AV50: 0 | AW50: 0 | AX50: =0-SUM(AU50:AW50) -> 0 | AY50: 0 | AZ50: 0 | BA50: 0 | BB50: =0-SUM(AY50:BA50) -> 0 | BC50: 0 | BD50: 0 | BE50: 0 | BF50: =0-SUM(BC50:BE50) -> 0 | BG50: 0 | BH50: 0 | BI50: 0 | BJ50: =240-SUM(BG50:BI50) -> 240 | BK50: 0 | BL50: 0 | BM50: 403.92 | BN50: =403.9-SUM(BK50:BM50) -> -0.02 | BO50: 0 | BP50: 0 | CA50: =SUM(C50:F50) -> 2.3 | CB50: =SUM(G50:J50) -> 6.2 | CC50: =SUM(K50:N50) -> 334.7 | CD50: =SUM(O50:R50) -> 38.3 | CE50: =SUM(S50:V50) -> 17.8 | CF50: =SUM(W50:Z50) -> 7.4 | CG50: =SUM(AA50:AD50) -> 55.1 | CH50: =SUM(AE50:AH50) -> 14.8 | CI50: =SUM(AI50:AL50) -> 77.9 | CJ50: =SUM(AM50:AP50) -> 16.5 | CK50: =SUM(AQ50:AT50) -> 0 | CL50: =SUM(AU50:AX50) -> 0 | CM50: =SUM(AY50:BB50) -> 0 | CN50: =SUM(BC50:BF50) -> 0 | CO50: =SUM(BG50:BJ50) -> 240 | CP50: 0 | CQ50: 0 | CR50: 0 | CS50: 0 | CT50: 0 | CU50: 0 | CV50: 0 | CW50: 0 | CX50: 0 | CY50: 0
B51: Restructuring Charge | C51: 0 | D51: 0 | E51: 0 | F51: 0 | G51: 0 | H51: 0 | I51: 0 | J51: 0 | K51: 0 | L51: 0 | M51: 0 | N51: 0 | O51: 0 | P51: 0 | Q51: 0 | R51: 0 | S51: 0 | T51: 0 | U51: 0 | V51: 0 | W51: 0 | X51: 0 | Y51: 0 | Z51: 0 | AA51: 0 | AB51: 0 | AC51: 0 | AD51: 0 | AE51: 0 | AF51: 0 | AG51: 0 | AH51: 0 | AI51: 0 | AJ51: 0 | AK51: 0 | AL51: 0 | AM51: 0 | AN51: 0 | AO51: 0 | AP51: 0 | AQ51: 1.346 | AR51: 19.005 | AS51: -3.659 | AT51: =38.491-SUM(AQ51:AS51) -> 21.799 | AU51: 7.998 | AV51: 11.494 | AW51: 0.959 | AX51: =21.738-SUM(AU51:AW51) -> 1.287 | AY51: 2.405 | AZ51: -0.083 | BA51: 0.628 | BB51: =20.299-SUM(AY51:BA51) -> 17.349 | BC51: 2.22 | BD51: 1.5 | BE51: 0.231 | BF51: =15.604-SUM(BC51:BE51) -> 11.653 | BG51: 2.659 | BH51: 7.855 | BI51: 0.285 | BJ51: =21.991-SUM(BG51:BI51) -> 11.192 | BK51: 4.755 | BL51: 22.17 | BM51: 117.62 | BN51: =21.991-SUM(BK51:BM51) -> -122.554 | BO51: 16.845 | BP51: 0.246 | CA51: =SUM(C51:F51) -> 0 | CB51: =SUM(G51:J51) -> 0 | CC51: =SUM(K51:N51) -> 0 | CD51: =SUM(O51:R51) -> 0 | CE51: =SUM(S51:V51) -> 0 | CF51: =SUM(W51:Z51) -> 0 | CG51: =SUM(AA51:AD51) -> 0 | CH51: =SUM(AE51:AH51) -> 0 | CI51: =SUM(AI51:AL51) -> 0 | CJ51: =SUM(AM51:AP51) -> 0 | CK51: =SUM(AQ51:AT51) -> 38.491 | CL51: =SUM(AU51:AX51) -> 21.738 | CM51: =SUM(AY51:BB51) -> 20.299 | CN51: =SUM(BC51:BF51) -> 15.604 | CO51: =SUM(BG51:BJ51) -> 21.991 | CP51: 40 | CQ51: 20 | CR51: 0 | CS51: 0 | CT51: 0 | CU51: 0 | CV51: 0 | CW51: 0 | CX51: 0 | CY51: 0
B52: Gain of Sale of Assets | C52: 0 | D52: 0 | E52: 0 | F52: 0 | G52: 0 | H52: 0 | I52: 0 | J52: 0 | K52: 0 | L52: 0 | M52: 0 | N52: 0 | O52: 0 | P52: 0 | Q52: 0 | R52: 0 | S52: 0 | T52: 0 | U52: 0 | V52: 0 | W52: 0 | X52: 0 | Y52: 0 | Z52: 0 | AA52: 0 | AB52: 0 | AC52: 0 | AD52: 0 | AE52: 0 | AF52: 0 | AG52: 0 | AH52: 0 | AI52: 0 | AJ52: 0 | AK52: 0 | AL52: 0 | AM52: 0 | AN52: 0 | AO52: 0 | AP52: 0 | AQ52: 0 | AR52: 0 | AS52: 0 | AT52: =0-SUM(AQ52:AS52) -> 0 | AU52: 0 | AV52: 0 | AW52: -91.157 | AX52: =-91.157-SUM(AU52:AW52) -> 0 | AY52: 0 | AZ52: 0 | BA52: -6.5 | BB52: =-6.5-SUM(AY52:BA52) -> 0 | BC52: 0 | BD52: 0 | BE52: 0 | BF52: =-4.448-SUM(BC52:BE52) -> -4.448 | BG52: 0 | BH52: 0 | BI52: 0 | BJ52: =0-SUM(BG52:BI52) -> 0 | BK52: 0 | BL52: 0 | BM52: 0 | BN52: =0-SUM(BK52:BM52) -> 0 | BO52: 0 | BP52: 0 | CA52: =SUM(C52:F52) -> 0 | CB52: =SUM(G52:J52) -> 0 | CC52: =SUM(K52:N52) -> 0 | CD52: =SUM(O52:R52) -> 0 | CE52: =SUM(S52:V52) -> 0 | CF52: =SUM(W52:Z52) -> 0 | CG52: =SUM(AA52:AD52) -> 0 | CH52: =SUM(AE52:AH52) -> 0 | CI52: =SUM(AI52:AL52) -> 0 | CJ52: =SUM(AM52:AP52) -> 0 | CK52: =SUM(AQ52:AT52) -> 0 | CL52: =SUM(AU52:AX52) -> -91.157 | CM52: =SUM(AY52:BB52) -> -6.5 | CN52: =SUM(BC52:BF52) -> -4.448 | CO52: =SUM(BG52:BJ52) -> 0 | CP52: 0 | CQ52: 0 | CR52: 0 | CS52: 0 | CT52: 0 | CU52: 0 | CV52: 0 | CW52: 0 | CX52: 0 | CY52: 0
B53: OI | C53: =C46-SUM(C47:C52) -> 66.6 | D53: =D46-SUM(D47:D52) -> 64.2 | E53: =E46-SUM(E47:E52) -> 53.5 | F53: =F46-SUM(F47:F52) -> 46.1 | G53: =G46-SUM(G47:G52) -> 49.7 | H53: =H46-SUM(H47:H52) -> 55.9 | I53: =I46-SUM(I47:I52) -> 61.9 | J53: =J46-SUM(J47:J52) -> 62.1 | ... BP53: =BP46-SUM(BP47:BP52) -> 72.824 | CA53: =SUM(C53:F53) -> 230.4 | CB53: =SUM(G53:J53) -> 229.6 | CC53: =SUM(K53:N53) -> -97.4 | CD53: =SUM(O53:R53) -> 233.3 | CE53: =SUM(S53:V53) -> 284.9 | CF53: =SUM(W53:Z53) -> 315.9 | CG53: =SUM(AA53:AD53) -> 319.4 | CH53: =SUM(AE53:AH53) -> 372.3 | CI53: =SUM(AI53:AL53) -> 321.7 | CJ53: =SUM(AM53:AP53) -> 427.2 | CK53: =SUM(AQ53:AT53) -> 363.559 | CL53: =SUM(AU53:AX53) -> 628.094 | CM53: =SUM(AY53:BB53) -> 499.708 | CN53: =SUM(BC53:BF53) -> 506.318 | CO53: =SUM(BG53:BJ53) -> 151.003 | CP53: =CP46-SUM(CP47:CP52) -> 617.09605 | CQ53: =CQ46-SUM(CQ47:CQ52) -> 419.64692 | CR53: =CR46-SUM(CR47:CR52) -> 471.84561 | CS53: =CS46-SUM(CS47:CS52) -> 521.73306 | CT53: =CT46-SUM(CT47:CT52) -> 585.38604 | CU53: =CU46-SUM(CU47:CU52) -> 653.22811 | CV53: =CV46-SUM(CV47:CV52) -> 706.32511 | CW53: =CW46-SUM(CW47:CW52) -> 759.51466 | ... CY53: =CY46-SUM(CY47:CY52) -> 872.0148
B54: Interest Expense | C54: -18.8 | D54: -19.4 | E54: -50.2 | F54: -37.3 | G54: -30.6 | H54: -16.3 | I54: -18.9 | J54: -19.2 | K54: -17.7 | L54: -17.7 | M54: -18.2 | N54: -14.4 | O54: -14 | P54: -14.3 | Q54: -15.1 | R54: -14.2 | S54: -15.2 | T54: -15.9 | U54: -17 | V54: -16.6 | W54: -17 | X54: -26.5 | Y54: -14.2 | Z54: -13.6 | AA54: -13.7 | AB54: -31 | AC54: -12.8 | AD54: -16.2 | AE54: -23.1 | AF54: -19.7 | AG54: -21 | AH54: -23.5 | AI54: -25.7 | AJ54: -26.5 | AK54: -26.9 | AL54: -23.1 | AM54: -22.4 | AN54: -20.3 | AO54: -19.1 | AP54: -25.6 | AQ54: 15.439 | AR54: 15.682 | AS54: 16.65 | AT54: =66.494-SUM(AQ54:AS54) -> 18.723 | AU54: 16.798 | AV54: 16.171 | AW54: 11.989 | AX54: =56.969-SUM(AU54:AW54) -> 12.011 | AY54: 10.418 | AZ54: 11.419 | BA54: 13.375 | BB54: =54.264-SUM(AY54:BA54) -> 19.052 | BC54: 18.337 | BD54: 17.76 | BE54: 23.192 | BF54: =85.082-SUM(BC54:BE54) -> 25.793 | BG54: 22.683 | BH54: 21.168 | BI54: 21.058 | BJ54: =83.544-SUM(BG54:BI54) -> 18.635 | BK54: 18.544 | BL54: 21.708 | BM54: 31.84 | BN54: =83.544-SUM(BK54:BM54) -> 11.452 | BO54: 25.718 | BP54: 27.953 | CA54: =SUM(C54:F54) -> -125.7 | CB54: =SUM(G54:J54) -> -85 | CC54: =SUM(K54:N54) -> -68 | CD54: =SUM(O54:R54) -> -57.6 | CE54: =SUM(S54:V54) -> -64.7 | CF54: =SUM(W54:Z54) -> -71.3 | CG54: =SUM(AA54:AD54) -> -73.7 | CH54: =SUM(AE54:AH54) -> -87.3 | CI54: =SUM(AI54:AL54) -> -102.2 | CJ54: =SUM(AM54:AP54) -> -87.4 | CK54: =SUM(AQ54:AT54) -> 66.494 | CL54: =SUM(AU54:AX54) -> 56.969 | CM54: =SUM(AY54:BB54) -> 54.264 | CN54: =SUM(BC54:BF54) -> 85.082 | CO54: =SUM(BG54:BJ54) -> 83.544 | CP54: =-$CO$93*5.5% -> -85.57285 | CQ54: =-$CO$93*5.5% -> -85.57285 | CR54: =-$CO$93*5.5% -> -85.57285 | CS54: =-$CO$93*5.5% -> -85.57285 | CT54: =-$CO$93*5.5% -> -85.57285 | CU54: =-$CO$93*5.5% -> -85.57285 | CV54: =-$CO$93*5.5% -> -85.57285 | CW54: =-$CO$93*5.5% -> -85.57285 | ... CY54: =-$CO$93*5.5% -> -85.57285
B55: Interest Income | C55: 0 | D55: 0 | E55: 0 | F55: 0 | G55: 0 | H55: 0 | I55: 0 | J55: 0 | K55: 0 | L55: 0 | M55: 0 | N55: 0 | O55: 0 | P55: 0 | Q55: 0 | R55: 0 | S55: 0 | T55: 0 | U55: 0 | V55: 0 | W55: 0 | X55: 0 | Y55: 0 | Z55: 0 | AA55: 0 | AB55: 0 | AC55: 0 | AD55: 0 | AE55: 0 | AF55: 0 | AG55: 0 | AH55: 0 | AI55: 0 | AJ55: 0 | AK55: 0 | AL55: 0 | AM55: 0 | AN55: 0 | AO55: 0 | AP55: 0 | AQ55: -0.579 | AR55: -0.163 | AS55: -0.214 | AT55: =-1.158-SUM(AQ55:AS55) -> -0.202 | AU55: -0.659 | AV55: -0.232 | AW55: -0.215 | AX55: =-1.328-SUM(AU55:AW55) -> -0.222 | AY55: -0.22 | AZ55: -0.229 | BA55: 0.126 | BB55: =-0.912-SUM(AY55:BA55) -> -0.589 | BC55: -0.843 | BD55: -1.15 | BE55: -7.487 | BF55: =-12.78-SUM(BC55:BE55) -> -3.3 | BG55: -1.66 | BH55: -1.787 | BI55: -2.298 | BJ55: =-8.009-SUM(BG55:BI55) -> -2.264 | BK55: -1.917 | BL55: -1.6 | BM55: -2.16 | BN55: =-8.009-SUM(BK55:BM55) -> -2.332 | BO55: -1.708 | BP55: -1.416 | CA55: =SUM(C55:F55) -> 0 | CB55: =SUM(G55:J55) -> 0 | CC55: =SUM(K55:N55) -> 0 | CD55: =SUM(O55:R55) -> 0 | CE55: =SUM(S55:V55) -> 0 | CF55: =SUM(W55:Z55) -> 0 | CG55: =SUM(AA55:AD55) -> 0 | CH55: =SUM(AE55:AH55) -> 0 | CI55: =SUM(AI55:AL55) -> 0 | CJ55: =SUM(AM55:AP55) -> 0 | CK55: =SUM(AQ55:AT55) -> -1.158 | CL55: =SUM(AU55:AX55) -> -1.328 | CM55: =SUM(AY55:BB55) -> -0.912 | CN55: =SUM(BC55:BF55) -> -12.78 | CO55: =SUM(BG55:BJ55) -> -8.009 | CP55: =CO70*$CY$72 -> 20.89296 | CQ55: =CP55*(1+$CY$72) -> 22.397253 | CR55: =CQ55*(1+$CY$72) -> 24.009855 | CS55: =CR55*(1+$CY$72) -> 25.738565 | CT55: =CS55*(1+$CY$72) -> 27.591742 | CU55: =CT55*(1+$CY$72) -> 29.578347 | CV55: =CU55*(1+$CY$72) -> 31.707988 | CW55: =CV55*(1+$CY$72) -> 33.990963 | CX55: =CW55*(1+$CY$72) -> 36.438312 | CY55: =CX55*(1+$CY$72) -> 39.061871
B56: Loss on Extinguishment of Debt | C56: 0 | D56: 0 | E56: 0 | F56: 0 | G56: 0 | H56: 0 | I56: 0 | J56: 0 | K56: 0 | L56: 0 | M56: 0 | N56: 0 | O56: 0 | P56: 0 | Q56: 0 | R56: 0 | S56: 0 | T56: 0 | U56: 0 | V56: 0 | W56: 0 | X56: 0 | Y56: 0 | Z56: 0 | AA56: 0 | AB56: 0 | AC56: 0 | AD56: 0 | AE56: 0 | AF56: 0 | AG56: 0 | AH56: 0 | AI56: 0 | AJ56: 0 | AK56: 0 | AL56: 0 | AM56: 0 | AN56: 0 | AO56: 0 | AP56: 0 | AQ56: 0 | AR56: 0 | AS56: 0 | AT56: =0-SUM(AQ56:AS56) -> 0 | AU56: 0 | AV56: 12.986 | AW56: 0 | AX56: =-12.986-SUM(AU56:AW56) -> -25.972 | AY56: 0 | AZ56: 0 | BA56: 0 | BB56: =0.454-SUM(AY56:BA56) -> 0.454 | BC56: 0 | BD56: 0 | BE56: 0 | BF56: =0-SUM(BC56:BE56) -> 0 | BG56: 0 | BH56: 0 | BI56: 0 | BJ56: =0-SUM(BG56:BI56) -> 0 | BK56: 0 | BL56: 0 | BM56: 0 | BN56: =0-SUM(BK56:BM56) -> 0 | BO56: 0 | BP56: 1.15 | CA56: =SUM(C56:F56) -> 0 | CB56: =SUM(G56:J56) -> 0 | CC56: =SUM(K56:N56) -> 0 | CD56: =SUM(O56:R56) -> 0 | CE56: =SUM(S56:V56) -> 0 | CF56: =SUM(W56:Z56) -> 0 | CG56: =SUM(AA56:AD56) -> 0 | CH56: =SUM(AE56:AH56) -> 0 | CI56: =SUM(AI56:AL56) -> 0 | CJ56: =SUM(AM56:AP56) -> 0 | CK56: =SUM(AQ56:AT56) -> 0 | CL56: =SUM(AU56:AX56) -> -12.986 | CM56: =SUM(AY56:BB56) -> 0.454 | CN56: =SUM(BC56:BF56) -> 0 | CO56: =SUM(BG56:BJ56) -> 0 | CP56: 0 | CQ56: 0 | CR56: 0 | CS56: 0 | CT56: 0 | CU56: 0 | CV56: 0 | CW56: 0 | CX56: 0 | CY56: 0
B57: Pretax Income | C57: =C53+C54 -> 47.8 | D57: =D53+D54 -> 44.8 | E57: =E53+E54 -> 3.3 | F57: =F53+F54 -> 8.8 | G57: =G53+G54 -> 19.1 | H57: =H53+H54 -> 39.6 | I57: =I53+I54 -> 43 | J57: =J53+J54 -> 42.9 | ... AP57: =AP53+AP54 -> 101.3 | AQ57: =AQ53-SUM(AQ54:AQ56) -> 142.205 | AR57: =AR53-SUM(AR54:AR56) -> 23.293 | AS57: =AS53-SUM(AS54:AS56) -> 115.645 | AT57: =AT53-SUM(AT54:AT56) -> 17.08 | AU57: =AU53-SUM(AU54:AU56) -> 87.279 | AV57: =AV53-SUM(AV54:AV56) -> 99.821 | AW57: =AW53-SUM(AW54:AW56) -> 229.181 | AX57: =AX53-SUM(AX54:AX56) -> 169.158 | ... BP57: =BP53-SUM(BP54:BP56) -> 45.137 | CA57: =SUM(C57:F57) -> 104.7 | CB57: =SUM(G57:J57) -> 144.6 | CC57: =SUM(K57:N57) -> -165.4 | CD57: =SUM(O57:R57) -> 175.7 | CE57: =SUM(S57:V57) -> 220.2 | CF57: =SUM(W57:Z57) -> 244.6 | CG57: =SUM(AA57:AD57) -> 245.7 | CH57: =SUM(AE57:AH57) -> 285 | CI57: =SUM(AI57:AL57) -> 219.5 | CJ57: =SUM(AM57:AP57) -> 339.8 | CK57: =SUM(AQ57:AT57) -> 298.223 | CL57: =SUM(AU57:AX57) -> 585.439 | CM57: =SUM(AY57:BB57) -> 445.902 | CN57: =SUM(BC57:BF57) -> 434.016 | CO57: =SUM(BG57:BJ57) -> 75.468 | CP57: =CP53+SUM(CP54:CP56) -> 552.41616 | CQ57: =CQ53+SUM(CQ54:CQ56) -> 356.47132 | CR57: =CR53+SUM(CR54:CR56) -> 410.28262 | CS57: =CS53+SUM(CS54:CS56) -> 461.89877 | CT57: =CT53+SUM(CT54:CT56) -> 527.40493 | CU57: =CU53+SUM(CU54:CU56) -> 597.23361 | CV57: =CV53+SUM(CV54:CV56) -> 652.46025 | CW57: =CW53+SUM(CW54:CW56) -> 707.93278 | ... CY57: =CY53+SUM(CY54:CY56) -> 825.50382
B58: Taxes | C58: 14.2 | D58: 12.4 | E58: -7.7 | F58: -2.1 | G58: 4.9 | H58: 8.4 | I58: 10.1 | J58: 2.3 | K58: -4 | L58: -0.3 | M58: 7.2 | N58: 13.5 | O58: 7.7 | P58: 6.1 | Q58: 5.2 | R58: 4.6 | S58: 8.5 | T58: 10 | U58: 9.7 | V58: 0.4 | W58: 9.3 | X58: 5.3 | Y58: 0.8 | Z58: -7.6 | AA58: 2.6 | AB58: 8 | AC58: 7.5 | AD58: -10.1 | AE58: -2.7 | AF58: 12.1 | AG58: 10 | AH58: 110.2 | AI58: 6.2 | AJ58: 9.6 | AK58: -1.3 | AL58: 8.7 | AM58: 11 | AN58: 3.8 | AO58: -130.4 | AP58: -6.5 | AQ58: 11.074 | AR58: 11.848 | AS58: -0.951 | AT58: =21.93-SUM(AQ58:AS58) -> -0.041 | AU58: 12.428 | AV58: 16.412 | AW58: 29.69 | AX58: =74.349-SUM(AU58:AW58) -> 15.819 | AY58: 15.973 | AZ58: 18.412 | BA58: 17.315 | BB58: =83-SUM(AY58:BA58) -> 31.3 | BC58: 20.184 | BD58: 15.53 | BE58: 11.935 | BF58: =76.44-SUM(BC58:BE58) -> 28.791 | BG58: -41.551 | BH58: 17.332 | BI58: 19.633 | BJ58: =5.316-SUM(BG58:BI58) -> 9.902 | BK58: =13.83 -> 13.83 | BL58: 12.662 | BM58: -29.69 | BN58: =5.316-SUM(BK58:BM58) -> 8.514 | BO58: 1.011 | BP58: 3.375 | CA58: =SUM(C58:F58) -> 16.8 | CB58: =SUM(G58:J58) -> 25.7 | CC58: =SUM(K58:N58) -> 16.4 | CD58: =SUM(O58:R58) -> 23.6 | CE58: =SUM(S58:V58) -> 28.6 | CF58: =SUM(W58:Z58) -> 7.8 | CG58: =SUM(AA58:AD58) -> 8 | CH58: =SUM(AE58:AH58) -> 129.6 | CI58: =SUM(AI58:AL58) -> 23.2 | CJ58: =SUM(AM58:AP58) -> -122.1 | CK58: =SUM(AQ58:AT58) -> 21.93 | CL58: =SUM(AU58:AX58) -> 74.349 | CM58: =SUM(AY58:BB58) -> 83 | CN58: =SUM(BC58:BF58) -> 76.44 | CO58: =SUM(BG58:BJ58) -> 5.316 | CP58: =CP57*CP67 -> 66.289939 | CQ58: =CQ57*CQ67 -> 46.341271 | CR58: =CR57*CR67 -> 61.542393 | CS58: =CS57*CS67 -> 69.284816 | CT58: =CT57*CT67 -> 79.11074 | CU58: =CU57*CU67 -> 89.585041 | CV58: =CV57*CV67 -> 97.869037 | CW58: =CW57*CW67 -> 106.18992 | ... CY58: =CY57*CY67 -> 123.82557
B59: NI | C59: =C57-C58 -> 33.6 | D59: =D57-D58 -> 32.4 | E59: =E57-E58 -> 11 | F59: =F57-F58 -> 10.9 | G59: =G57-G58 -> 14.2 | H59: =H57-H58 -> 31.2 | I59: =I57-I58 -> 32.9 | J59: =J57-J58 -> 40.6 | ... AQ59: =AQ57-AQ58 -> 131.131 | AR59: =AR57-AR58+0.013 -> 11.458 | AS59: =AS57-AS58-0.018 -> 116.578 | AT59: =AT57-AT58 -> 17.121 | AU59: =AU57-AU58 -> 74.851 | AV59: =AV57-AV58-0.035 -> 83.374 | AW59: =AW57-AW58-0.325 -> 199.166 | AX59: =AX57-AX58 -> 153.339 | AY59: =AY57-AY58-0.226 -> 77.114 | AZ59: =AZ57-AZ58-0.041 -> 105.491 | BA59: =BA57-BA58 -> 101.592 | BB59: =BB57-BB58 -> 78.438 | BC59: =BC57-BC58-0.548 -> 76.719 | BD59: =BD57-BD58-0.08 -> 111.325 | BE59: =BE57-BE58-0.53 -> 137.132 | BF59: =BF57-BF58-1.24 -> 30.002 | BG59: =BG57-BG58-0.452 -> 15.27 | BH59: =BH57-BH58 -> 80.137 | BI59: =BI57-BI58 -> 110.889 | BJ59: =BJ57-BJ58 -> -136.596 | BK59: =BK57-BK58-0.1 -> 95.064 | BL59: =BL57-BL58 -> 122.505 | BM59: =BM57-BM58 -> -408.89 | BN59: =BN57-BN58 -> 366.685 | BO59: =BO57-BO58-3.316 -> -8.155 | BP59: =BP57-BP58 -> 41.762 | CA59: =SUM(C59:F59) -> 87.9 | CB59: =SUM(G59:J59) -> 118.9 | CC59: =SUM(K59:N59) -> -181.8 | CD59: =SUM(O59:R59) -> 152.1 | CE59: =SUM(S59:V59) -> 191.6 | CF59: =SUM(W59:Z59) -> 236.8 | CG59: =SUM(AA59:AD59) -> 237.7 | CH59: =SUM(AE59:AH59) -> 155.4 | CI59: =SUM(AI59:AL59) -> 196.3 | CJ59: =SUM(AM59:AP59) -> 461.9 | CK59: =SUM(AQ59:AT59) -> 276.288 | CL59: =SUM(AU59:AX59) -> 510.73 | CM59: =SUM(AY59:BB59) -> 362.635 | CN59: =SUM(BC59:BF59) -> 355.178 | CO59: =SUM(BG59:BJ59) -> 69.7 | CP59: =CP57-CP58 -> 486.12622 | CQ59: =CQ57-CQ58 -> 310.13005 | CR59: =CR57-CR58 -> 348.74023 | CS59: =CS57-CS58 -> 392.61396 | CT59: =CT57-CT58 -> 448.29419 | CU59: =CU57-CU58 -> 507.64857 | CV59: =CV57-CV58 -> 554.59121 | CW59: =CW57-CW58 -> 601.74286 | ... CY59: =CY57-CY58 -> 701.67824 | CZ59: =CY59*(1+$CY$73) -> 708.69503 | DA59: =CZ59*(1+$CY$73) -> 715.78198 | DB59: =DA59*(1+$CY$73) -> 722.9398 | DC59: =DB59*(1+$CY$73) -> 730.16919 | DD59: =DC59*(1+$CY$73) -> 737.47089 | DE59: =DD59*(1+$CY$73) -> 744.8456 | DF59: =DE59*(1+$CY$73) -> 752.29405 | DG59: =DF59*(1+$CY$73) -> 759.81699 | ... EW59: =EV59*(1+$CY$73) -> 1154.0024
B60: SC | C60: 40 | D60: 40 | E60: 40 | F60: 40 | G60: 40 | H60: 41 | I60: 41 | J60: 41 | K60: 41 | L60: 41 | M60: 41 | N60: 41 | O60: 41 | P60: 41 | Q60: 41 | R60: 41 | S60: 41 | T60: 41 | U60: 41 | V60: 41 | W60: 41 | X60: 42 | Y60: 42 | Z60: 42 | AA60: 42 | AB60: 44 | AC60: 44 | AD60: 43 | AE60: 45 | AF60: 45 | AG60: 45 | AH60: 45 | AI60: 45 | AJ60: 46 | AK60: 46 | AL60: 46 | AM60: 46 | AN60: 46 | AO60: 46 | AP60: 46 | AQ60: 46.382 | AR60: 46.442 | AS60: 46.53 | AT60: 335.324 | AU60: 46.698 | AV60: 46.741 | AW60: 46.81 | AX60: 46.77 | AY60: 46.876 | AZ60: 46.901 | BA60: 46.906 | BB60: 46.898 | BC60: 46.949 | BD60: 46.981 | BE60: 46.992 | BF60: 46.981 | BG60: 47.068 | BH60: 47.151 | BI60: 46.724 | BJ60: 46.837 | BK60: 45.782 | BL60: 44.269 | BM60: 44.237 | BN60: 46.837 | BO60: 44.257 | BP60: 43.56 | CA60: =AVERAGE(C60:F60) -> 40 | CB60: =AVERAGE(G60:J60) -> 40.75 | CC60: =AVERAGE(K60:N60) -> 41 | CD60: =AVERAGE(O60:R60) -> 41 | CE60: =AVERAGE(S60:V60) -> 41 | CF60: =AVERAGE(W60:Z60) -> 41.75 | CG60: =AVERAGE(AA60:AD60) -> 43.25 | CH60: =AVERAGE(AE60:AH60) -> 45 | CI60: =AVERAGE(AI60:AL60) -> 45.75 | CJ60: =AVERAGE(AM60:AP60) -> 46 | CK60: =AVERAGE(AQ60:AT60) -> 118.6695 | CL60: =AVERAGE(AU60:AX60) -> 46.75475 | CM60: =AVERAGE(AY60:BB60) -> 46.89525 | CN60: =AVERAGE(BC60:BF60) -> 46.97575 | CO60: =AVERAGE(BG60:BJ60) -> 46.945
B61: EPS | C61: =C59/C60 -> 0.84 | D61: =D59/D60 -> 0.81 | E61: =E59/E60 -> 0.275 | F61: =F59/F60 -> 0.2725 | G61: =G59/G60 -> 0.355 | H61: =H59/H60 -> 0.76097561 | I61: =I59/I60 -> 0.80243902 | J61: =J59/J60 -> 0.9902439 | ... BP61: =BP59/BP60 -> 0.9587236 | CA61: =SUM(C61:F61) -> 2.1975 | CB61: =SUM(G61:J61) -> 2.9086585 | CC61: =SUM(K61:N61) -> -4.4341463 | CD61: =SUM(O61:R61) -> 3.7097561 | CE61: =SUM(S61:V61) -> 4.6731707 | CF61: =SUM(W61:Z61) -> 5.6609175 | CG61: =SUM(AA61:AD61) -> 5.4898721 | CH61: =SUM(AE61:AH61) -> 3.4533333 | CI61: =SUM(AI61:AL61) -> 4.293913 | CJ61: =SUM(AM61:AP61) -> 10.041304 | CK61: =SUM(AQ61:AT61) -> 5.6304077 | CL61: =SUM(AU61:AX61) -> 10.919969 | CM61: =SUM(AY61:BB61) -> 7.7326777 | CN61: =SUM(BC61:BF61) -> 7.5604647 | CO61: =SUM(BG61:BJ61) -> 1.4808713
B63: Gross Profit Margin | C63: =C46/C44 -> 0.48162265 | D63: =D46/D44 -> 0.48632812 | E63: =E46/E44 -> 0.4826087 | F63: =F46/F44 -> 0.49281126 | G63: =G46/G44 -> 0.46468927 | H63: =H46/H44 -> 0.47586569 | I63: =I46/I44 -> 0.48414668 | J63: =J46/J44 -> 0.47465788 | ... BP63: =BP46/BP44 -> 0.58160335 | CA63: =CA46/CA44 -> 0.48568975 | CB63: =CB46/CB44 -> 0.47490787 | CC63: =CC46/CC44 -> 0.48236735 | CD63: =CD46/CD44 -> 0.49454696 | CE63: =CE46/CE44 -> 0.51222959 | CF63: =CF46/CF44 -> 0.52182803 | CG63: =CG46/CG44 -> 0.53329764 | CH63: =CH46/CH44 -> 0.54596282 | ... CO63: =CO46/CO44 -> 0.55874439 | CP63: 0.56 | CQ63: 0.5625 | CR63: 0.565 | CS63: 0.565 | CT63: 0.565 | CU63: 0.565 | CV63: 0.565 | CW63: 0.565 | CX63: 0.565 | CY63: 0.565
B64: R&D as % of Revenue | C64: =C48/C44 -> 0.025319902 | D64: =D48/D44 -> 0.028738839 | E64: =E48/E44 -> 0.029565217 | F64: =F48/F44 -> 0.038543897 | G64: =G48/G44 -> 0.031073446 | H64: =H48/H44 -> 0.032791186 | I64: =I48/I44 -> 0.033360904 | J64: =J48/J44 -> 0.03421186 | ... BP64: =BP48/BP44 -> 0.079115322 | CA64: =CA48/CA44 -> 0.030337722 | CB64: =CB48/CB44 -> 0.032897822 | CC64: =CC48/CC44 -> 0.036361292 | CD64: =CD48/CD44 -> 0.038318694 | CE64: =CE48/CE44 -> 0.033155778 | CF64: =CF48/CF44 -> 0.028790893 | CG64: =CG48/CG44 -> 0.031263383 | CH64: =CH48/CH44 -> 0.039463262 | ... CO64: =CO48/CO44 -> 0.053053453 | CP64: 0.052 | CQ64: 0.054 | CR64: 0.055 | CS64: 0.056 | CT64: 0.057 | CU64: 0.057 | CV64: 0.057 | CW64: 0.057 | CX64: 0.057 | CY64: 0.05
B65: SG&A as % of Revenue | C65: =C47/C44 -> 0.27389055 | D65: =D47/D44 -> 0.27845982 | E65: =E47/E44 -> 0.2942029 | F65: =F47/F44 -> 0.31141022 | G65: =G47/G44 -> 0.29152542 | H65: =H47/H44 -> 0.28803778 | I65: =I47/I44 -> 0.28012131 | J65: =J47/J44 -> 0.27698936 | ... BP65: =BP47/BP44 -> 0.37436967 | CA65: =CA47/CA44 -> 0.28885232 | CB65: =CB47/CB44 -> 0.2840201 | CC65: =CC47/CC44 -> 0.29301786 | CD65: =CD47/CD44 -> 0.29611507 | CE65: =CE47/CE44 -> 0.31454506 | CF65: =CF47/CF44 -> 0.31437887 | CG65: =CG47/CG44 -> 0.30155246 | CH65: =CH47/CH44 -> 0.32614266 | ... CO65: =CO47/CO44 -> 0.32660673 | CP65: 0.305 | CQ65: 0.33 | CR65: 0.335 | CS65: 0.33 | CT65: 0.32 | CU65: 0.31 | CV65: 0.305 | CW65: 0.3 | CX65: 0.2975 | CY65: 0.295
B66: Operating Profit Margin | C66: =C53/C44 -> 0.18132317 | D66: =D53/D44 -> 0.17912946 | E66: =E53/E44 -> 0.15507246 | F66: =F53/F44 -> 0.14102172 | G66: =G53/G44 -> 0.14039548 | H66: =H53/H44 -> 0.14664218 | I66: =I53/I44 -> 0.17066446 | J66: =J53/J44 -> 0.15737456 | ... BP66: =BP53/BP44 -> 0.12768703 | CA66: =CA53/CA44 -> 0.16485404 | CB66: =CB53/CB44 -> 0.15383585 | CC66: =CC53/CC44 -> -0.062794146 | CD66: =CD53/CD44 -> 0.13753463 | CE66: =CE53/CE44 -> 0.15485379 | CF66: =CF53/CF44 -> 0.17456897 | CG66: =CG53/CG44 -> 0.17098501 | CH66: =CH53/CH44 -> 0.17346131 | ... CY66: =CY53/CY44 -> 0.22
B67: Effective Tax Rate | C67: =C58/C57 -> 0.29707113 | D67: =D58/D57 -> 0.27678571 | E67: =E58/E57 -> -2.3333333 | F67: =F58/F57 -> -0.23863636 | G67: =G58/G57 -> 0.2565445 | H67: =H58/H57 -> 0.21212121 | I67: =I58/I57 -> 0.23488372 | J67: =J58/J57 -> 0.053613054 | ... BP67: =BP58/BP57 -> 0.07477236 | CA67: =CA58/CA57 -> 0.16045845 | CB67: =CB58/CB57 -> 0.17773167 | CC67: =CC58/CC57 -> -0.099153567 | CD67: =CD58/CD57 -> 0.13431986 | CE67: =CE58/CE57 -> 0.12988193 | CF67: =CF58/CF57 -> 0.031888798 | CG67: =CG58/CG57 -> 0.032560033 | CH67: =CH58/CH57 -> 0.45473684 | ... CO67: =CO58/CO57 -> 0.070440452 | CP67: 0.12 | CQ67: 0.13 | CR67: 0.15 | CS67: 0.15 | CT67: 0.15 | CU67: 0.15 | CV67: 0.15 | CW67: 0.15 | CX67: 0.15 | CY67: 0.15
B68: Net Profit Margin | C68: =C59/C44 -> 0.091478356 | D68: =D59/D44 -> 0.090401786 | E68: =E59/E44 -> 0.031884058 | F68: =F59/F44 -> 0.03334353 | G68: =G59/G44 -> 0.040112994 | H68: =H59/H44 -> 0.0818468 | I68: =I59/I44 -> 0.090708575 | J68: =J59/J44 -> 0.102889 | ... BP68: =BP59/BP44 -> 0.073224017 | CA68: =CA59/CA44 -> 0.062893532 | CB68: =CB59/CB44 -> 0.079664992 | CC68: =CC59/CC44 -> -0.11720714 | CD68: =CD59/CD44 -> 0.089665743 | CE68: =CE59/CE44 -> 0.10414175 | CF68: =CF59/CF44 -> 0.13085765 | CG68: =CG59/CG44 -> 0.12724839 | CH68: =CH59/CH44 -> 0.072403671 | ... CY68: =CY59/CY44 -> 0.17702591
B70: Cash & CEs | AT70: 375.88 | AU70: 324.63 | AV70: 361.78 | AW70: 481.16 | AX70: 445.08 | AY70: 466.656 | AZ70: 308.121 | BA70: 397.25 | BB70: 292.03 | BC70: 264.13 | BD70: 250.816 | BE70: 881.49 | BF70: 222.848 | BG70: 237.42 | BH70: 238.56 | BI70: 243.24 | BJ70: 290.18 | BK70: 284.122 | BL70: 253.69 | BM70: 353.997 | BN70: 378.564 | BO70: 309.411 | BP70: 300.159 | CK70: =AT70 -> 375.88 | CL70: =AX70 -> 445.08 | CM70: =BB70 -> 292.03 | CN70: =BF70 -> 222.848 | CO70: =BJ70 -> 290.18 | CP70: =CO70+CP59 -> 776.30622 | CQ70: =CP70+CQ59+1200 -> 2286.4363 | CR70: =CQ70+CR59 -> 2635.1765 | CS70: =CR70+CS59 -> 3027.7905 | CT70: =CS70+CT59 -> 3476.0846 | CU70: =CT70+CU59 -> 3983.7332 | CV70: =CU70+CV59 -> 4538.3244 | CW70: =CV70+CW59 -> 5140.0673 | CX70: =CW70+CX59 -> 5780.7077 | CY70: =CX70+CY59 -> 6482.3859
B71: A/R | AT71: 395.071 | AU71: 401.11 | AV71: 414.19 | AW71: 399.74 | AX71: 383.56 | AY71: 407.159 | AZ71: 415.29 | BA71: 391.25 | BB71: 408.83 | BC71: 410.02 | BD71: 429.309 | BE71: 425.19 | BF71: 443.467 | BG71: 448.53 | BH71: 448.89 | BI71: 470.25 | BJ71: 459.49 | BK71: 464.52 | BL71: 513.81 | BM71: 592.65 | BN71: 345.583 | BO71: 365.526 | BP71: 364.609 | CK71: =AT71 -> 395.071 | CL71: =AX71 -> 383.56 | CM71: =BB71 -> 408.83 | CN71: =BF71 -> 443.467 | CO71: =BJ71 -> 459.49
B72: Inventories | AT72: 513.19 | AU72: 512.3 | AV72: 490.3 | AW72: 484.34 | AX72: 477.64 | AY72: 491.422 | AZ72: 510.53 | BA72: 530.08 | BB72: 578.507 | BC72: 614.1 | BD72: 631.555 | BE72: 625.075 | BF72: 626.216 | BG72: 627.86 | BH72: 636.9 | BI72: 639.93 | BJ72: 600.13 | BK72: 643.97 | BL72: 693.68 | BM72: 802.46 | BN72: 404.395 | BO72: 380.861 | BP72: 351.912 | CK72: =AT72 -> 513.19 | CL72: =AX72 -> 477.64 | CM72: =BB72 -> 578.507 | CN72: =BF72 -> 626.216 | CO72: =BJ72 -> 600.13 | CQ72: Projected ROIC: | CT72: Invested Capital | CV72: AVG Invested Capital | CX72: ROIC | CY72: 0.072
B73: ST Prepaid Expenses | AT73: 115.43 | AU73: 121.87 | AV73: 116.818 | AW73: 123.776 | AX73: 117.277 | AY73: 123.87 | AZ73: 112.595 | BA73: 113.916 | BB73: 125.084 | BC73: 134.94 | BD73: 120.19 | BE73: 138.65 | BF73: 107.47 | BG73: 111.62 | BH73: 94.82 | BI73: 116.92 | BJ73: 117.85 | BK73: 141.6 | BL73: 199 | BM73: 154.6 | BN73: 150.678 | BO73: 149.808 | BP73: 148.222 | CK73: =AT73 -> 115.43 | CL73: =AX73 -> 117.277 | CM73: =BB73 -> 125.084 | CN73: =BF73 -> 107.47 | CO73: =BJ73 -> 117.85 | CQ73: 2025 | CS73: 2023 | CT73: 2024 | CV73: 2023-2024 | CX73: Terminal | CY73: 0.01
B74: ST Prepaid Taxes | AT74: 22.84 | AU74: 18.87 | AV74: 27.18 | AW74: 52.8 | AX74: 5.545 | AY74: 5.092 | AZ74: 38.8 | BA74: 26.868 | BB74: 6.524 | BC74: 4.84 | BD74: 13.929 | BE74: 26.84 | BF74: 7.404 | BG74: 8.163 | BH74: 18.89 | BI74: 28.94 | BJ74: 3.4 | BK74: 4.69 | BL74: 63.66 | BM74: 82.26 | BN74: 19.566 | BO74: 16.793 | BP74: 36.458 | CK74: =AT74 -> 22.84 | CL74: =AX74 -> 5.545 | CM74: =BB74 -> 6.524 | CN74: =BF74 -> 7.404 | CO74: =BJ74 -> 3.4 | CQ74: =AVERAGE(CP53)*(1-CP67) -> 543.04453 | CS74: =SUM(CN70:CN75)-CN86+CN76+CN79+CN78 -> 7171.088 | CT74: =SUM(CO70:CO75)-CO86+CO76+CO79+CO78 -> 6733.88 | CV74: =AVERAGE(CS74:CT74) -> 6952.484 | CX74: RFR (10-year yield) | CY74: 0.0434
B75: Current Assets Held-For-Sale | AT75: 0 | AU75: 0 | AV75: 26.936 | AW75: 0 | AX75: 0 | AY75: 0 | AZ75: 0 | BA75: 0 | BB75: 0 | BC75: 0 | BD75: 0 | BE75: 0 | BF75: 0 | BG75: 0 | BH75: 0 | BI75: 0 | BJ75: 0 | BK75: 0 | BL75: 0 | BM75: 0 | BN75: 639.552 | BO75: 637.271 | BP75: 674.516 | CK75: =AT75 -> 0 | CL75: =AX75 -> 0 | CM75: =BB75 -> 0 | CN75: =BF75 -> 0 | CO75: =BJ75 -> 0 | CQ75: =CQ74/CV74 -> 0.078107986 | CX75: ERP (Avg. market return - (less) RFR) | CY75: =9.75%-CY74 -> 0.0541
B76: PP&E | AT76: 473.912 | AU76: 467.64 | AV76: 449.75 | AW76: 446.318 | AX76: 443.75 | AY76: 436.02 | AZ76: 429.37 | BA76: 422.355 | BB76: 447.205 | BC76: 458.86 | BD76: 464.609 | BE76: 464.467 | BF76: 479.913 | BG76: 485.535 | BH76: 491.99 | BI76: 512.224 | BJ76: 502.85 | BK76: 518.916 | BL76: 548.961 | BM76: 700.586 | BN76: 498.281 | BO76: 476.955 | BP76: 475.637 | CK76: =AT76 -> 473.912 | CL76: =AX76 -> 443.75 | CM76: =BB76 -> 447.205 | CN76: =BF76 -> 479.913 | CO76: =BJ76 -> 502.85 | CX76: Equity β (1-year avg.) | CY76: ='Notes | Quant Analysis'!K204 -> 1.08
B77: Operating Lease Assets | AT77: 100.63 | AU77: 94.55 | AV77: 115.11 | AW77: 129.99 | AX77: 129.65 | AY77: 124.39 | AZ77: 118.62 | BA77: 112.04 | BB77: 131.211 | BC77: 126.77 | BD77: 123.215 | BE77: 123.6 | BF77: 123.52 | BG77: 112.56 | BH77: 112.01 | BI77: 112.89 | BJ77: 108.9 | BK77: 108.34 | BL77: 99.09 | BM77: 107.05 | BN77: 91.817 | BO77: 84.912 | BP77: 77.158 | CK77: =AT77 -> 100.63 | CL77: =AX77 -> 129.65 | CM77: =BB77 -> 131.211 | CN77: =BF77 -> 123.52 | CO77: =BJ77 -> 108.9 | CX77: Discount (Cost of Equity) | CY77: =+CY74+(CY75*CY76) -> 0.101828
B78: Goodwill | AT78: 2585.966 | AU78: 2565.87 | AV78: 2537.43 | AW78: 2522.95 | AX78: 2504.202 | AY78: 2492.72 | AZ78: 2461.083 | BA78: 2415.29 | BB78: 2536.73 | BC78: 2547.84 | BD78: 2546.13 | BE78: 2528.305 | BF78: 2914.05 | BG78: 2898.343 | BH78: 2892.62 | BI78: 2918.56 | BJ78: 2632.31 | BK78: 2651.88 | BL78: 2694.1 | BM78: 2537.77 | BN78: 2305.05 | BO78: 2297.447 | BP78: 2292.435 | CK78: =AT78 -> 2585.966 | CL78: =AX78 -> 2504.202 | CM78: =BB78 -> 2536.73 | CN78: =BF78 -> 2914.05 | CO78: =BJ78 -> 2632.31
B79: Intangible Assets | AT79: 2519.74 | AU79: 2470.244 | AV79: 2381.32 | AW79: 2337.24 | AX79: 2289.06 | AY79: 2243.55 | AZ79: 2226.87 | BA79: 2176.25 | BB79: 2306.16 | BC79: 2269.53 | BD79: 2227.947 | BE79: 2180.53 | BF79: 2501.96 | BG79: 2429.46 | BH79: 2379.91 | BI79: 2325.1 | BJ79: 2268.7 | BK79: 2226.14 | BL79: 2184.3 | BM79: 2410.4 | BN79: 1524.15 | BO79: 1485.885 | BP79: 1448.669 | CK79: =AT79 -> 2519.74 | CL79: =AX79 -> 2289.06 | CM79: =BB79 -> 2306.16 | CN79: =BF79 -> 2501.96 | CO79: =BJ79 -> 2268.7 | CX79: NPV | CY79: =NPV(CY77,CP59:EM59) -> 5711.975
B80: Deffered Tax Assets | AT80: 8.073 | AU80: 8.045 | AV80: 8.44 | AW80: 8.425 | AX80: 6.82 | AY80: 6.791 | AZ80: 6.243 | BA80: 5.762 | BB80: 6.402 | BC80: 6.479 | BD80: 6.278 | BE80: 6.167 | BF80: 6.74 | BG80: 6.588 | BH80: 6.424 | BI80: 6.779 | BJ80: 11.374 | BK80: 11.773 | BL80: 12.86 | BM80: 13.509 | BN80: 12.593 | BO80: 12.206 | BP80: 12.642 | CK80: =AT80 -> 8.073 | CL80: =AX80 -> 6.82 | CM80: =BB80 -> 6.402 | CN80: =BF80 -> 6.74 | CO80: =BJ80 -> 11.374 | CX80: SC | CY80: =Main!C6 -> 42.372 | CZ80: Q2'25
B81: Other LT Assets | AT81: 41.802 | AU81: 42.87 | AV81: 41.66 | AW81: 53.3 | AX81: 69.104 | AY81: 75.622 | AZ81: 104.308 | BA81: 166.98 | BB81: 89.36 | BC81: 80.38 | BD81: 81.747 | BE81: 93.28 | BF81: 98.943 | BG81: 111.828 | BH81: 120.577 | BI81: 111.42 | BJ81: 102.624 | BK81: 107.317 | BL81: 112.06 | BM81: 116.626 | BN81: 112.984 | BO81: 113.557 | BP81: 120.31 | CK81: =AT81 -> 41.802 | CL81: =AX81 -> 69.104 | CM81: =BB81 -> 89.36 | CN81: =BF81 -> 98.943 | CO81: =BJ81 -> 102.624 | CX81: FV | CY81: =CY79/CY80 -> 134.80541
B82: LT Assets Held-For-Sale | AT82: 0 | AU82: 0 | AV82: 95.426 | AW82: 0 | AX82: 0 | AY82: 0 | AZ82: 0 | BA82: 0 | BB82: 0 | BC82: 0 | BD82: 0 | BE82: 0 | BF82: 0 | BG82: 0 | BH82: 0 | BI82: 0 | BJ82: 0 | BK82: 0 | BL82: 0 | BM82: 0 | BN82: 464.026 | BO82: 452.37 | BP82: 484.051 | CK82: =AT82 -> 0 | CL82: =AX82 -> 0 | CM82: =BB82 -> 0 | CN82: =BF82 -> 0 | CO82: =BJ82 -> 0 | CX82: CP | CY82: =Main!C5 -> 125.12 | CZ82: 8/25/2025
B83: Ttl Assets | AT83: =SUM(AT70:AT81) -> 7152.534 | AU83: =SUM(AU70:AU81) -> 7027.999 | AV83: =SUM(AV70:AV82) -> 7066.34 | AW83: =SUM(AW70:AW82) -> 7040.039 | AX83: =SUM(AX70:AX81) -> 6871.688 | AY83: =SUM(AY70:AY81) -> 6873.292 | AZ83: =SUM(AZ70:AZ81) -> 6731.83 | BA83: =SUM(BA70:BA81) -> 6758.041 | BB83: =SUM(BB70:BB81) -> 6928.043 | BC83: =SUM(BC70:BC81) -> 6917.889 | BD83: =SUM(BD70:BD81) -> 6895.725 | BE83: =SUM(BE70:BE81) -> 7493.594 | ... BM83: =SUM(BM70:BM81) -> 7871.908 | BN83: =SUM(BN70:BN82) -> 6947.239 | BO83: =SUM(BO70:BO82) -> 6783.002 | BP83: =SUM(BP70:BP82) -> 6786.778 | CK83: =AT83 -> 7152.534 | CL83: =AX83 -> 6871.688 | CM83: =BB83 -> 6928.043 | CN83: =BF83 -> 7532.531 | CO83: =BJ83 -> 7097.808 | CX83: Change Δ | CY83: =CY81/CY82-1 -> 0.077408996 | CZ83: =IF(CY83>0,"Upside","Downside") -> Upside
CX84: {=_xlfn.IFS(CY83>=25%,"Strong Buy",CY83>=10.00001%,"Buy",AND(CY83<=10%,CY83>=-4.9999%),"Hold",AND(CY83<=-5%,CY83>=-14.999999%),"Sell",CY83<=-15%,"Strong Sell")} -> Hold
B85: Current Debt | AT85: 100.5 | AU85: 83.75 | AV85: 92.5 | AW85: 101.25 | AX85: 110 | AY85: 110 | AZ85: 110 | BA85: 114.37 | BB85: 87.5 | BC85: 87.5 | BD85: 87.5 | BE85: 87.5 | BF85: 87.5 | BG85: 90.625 | BH85: 93.75 | BI85: 96.87 | BJ85: 100 | BK85: 100 | BL85: 100 | BM85: 100 | BN85: 100 | BO85: 103.125 | BP85: 87.5 | CK85: =AT85 -> 100.5 | CL85: =AX85 -> 110 | CM85: =BB85 -> 87.5 | CN85: =BF85 -> 87.5 | CO85: =BJ85 -> 100
B86: A/P | AT86: 102.52 | AU86: 101.34 | AV86: 106.56 | AW86: 104.139 | AX86: 118.236 | AY86: 117.464 | AZ86: 121.418 | BA86: 121.5 | BB86: 126.807 | BC86: 136.239 | BD86: 142.08 | BE86: 130.686 | BF86: 132.24 | BG86: 115.945 | BH86: 113.45 | BI86: 119.25 | BJ86: 141.03 | BK86: 143.037 | BL86: 157.55 | BM86: 165.9 | BN86: 130.201 | BO86: 143.627 | BP86: 143.292 | CK86: =AT86 -> 102.52 | CL86: =AX86 -> 118.236 | CM86: =BB86 -> 126.807 | CN86: =BF86 -> 132.24 | CO86: =BJ86 -> 141.03
B87: Accrued ST Expenses | AT87: 136.276 | AU87: 134.311 | AV87: 138.28 | AW87: 127.116 | AX87: 163.44 | AY87: 158.945 | AZ87: 151.715 | BA87: 140.86 | BB87: 140.644 | BC87: 123.45 | BD87: 127.86 | BE87: 133.067 | BF87: 146.88 | BG87: 136.614 | BH87: 153.4 | BI87: 157.78 | BJ87: 143.16 | BK87: 150.85 | BL87: 157.17 | BM87: 147.05 | BN87: 117.35 | BO87: 118.423 | BP87: 134.17 | CK87: =AT87 -> 136.276 | CL87: =AX87 -> 163.44 | CM87: =BB87 -> 140.644 | CN87: =BF87 -> 146.88 | CO87: =BJ87 -> 143.16
B88: Payroll & Benefit Liabilities | AT88: 122.366 | AU88: 100.38 | AV88: 121.82 | AW88: 133.523 | AX88: 143.65 | AY88: 102.407 | AZ88: 114.38 | BA88: 121.59 | BB88: 133.092 | BC88: 102.08 | BD88: 106.177 | BE88: 127.1 | BF88: 146.535 | BG88: 106.055 | BH88: 113.112 | BI88: 142.619 | BJ88: 151.26 | BK88: 108.9 | BL88: 114.16 | BM88: 167.73 | BN88: 124.769 | BO88: 103.345 | BP88: 110.214 | CK88: =AT88 -> 122.366 | CL88: =AX88 -> 143.65 | CM88: =BB88 -> 133.092 | CN88: =BF88 -> 146.535 | CO88: =BJ88 -> 151.26
B89: Accrued Interest Liabilities | AT89: 7.135 | AU89: 23.4 | AV89: 5.5 | AW89: 15.757 | AX89: 5.209 | AY89: 16.808 | AZ89: 4.751 | BA89: 15.87 | BB89: 5.332 | BC89: 16.86 | BD89: 5.793 | BE89: 17.428 | BF89: 5.583 | BG89: 16.99 | BH89: 5.77 | BI89: 16.657 | BJ89: 5.33 | BK89: 17.02 | BL89: 5.63 | BM89: 16.766 | BN89: 5.404 | BO89: 16.478 | BP89: 3.558 | CK89: =AT89 -> 7.135 | CL89: =AX89 -> 5.209 | CM89: =BB89 -> 5.332 | CN89: =BF89 -> 5.583 | CO89: =BJ89 -> 5.33
B90: Taxes Payable | AT90: 17.36 | AU90: 14.83 | AV90: 14.836 | AW90: 17.185 | AX90: 83.943 | AY90: 88.451 | AZ90: 52.174 | BA90: 41.32 | BB90: 24.736 | BC90: 30.17 | BD90: 20.18 | BE90: 24.375 | BF90: 41.45 | BG90: 48.905 | BH90: 19.731 | BI90: 18.68 | BJ90: 41.31 | BK90: 49.78 | BL90: 22.494 | BM90: 12.97 | BN90: 18.787 | BO90: 11.824 | BP90: 17.787 | CK90: =AT90 -> 17.36 | CL90: =AX90 -> 83.943 | CM90: =BB90 -> 24.736 | CN90: =BF90 -> 41.45 | CO90: =BJ90 -> 41.31
B91: Other ST Liabilities | AT91: 53.869 | AU91: 50.04 | AV91: 46.26 | AW91: 63.24 | AX91: 55.633 | AY91: 62.125 | AZ91: 56.004 | BA91: 55.407 | BB91: 63.38 | BC91: 79.403 | BD91: 65.85 | BE91: 65.26 | BF91: 46.547 | BG91: 55.87 | BH91: 57.53 | BI91: 66.88 | BJ91: 67.24 | BK91: 103.31 | BL91: 159.119 | BM91: 162.6 | BN91: 137.195 | BO91: =103.929 -> 103.929 | BP91: 88.364 | CK91: =AT91 -> 53.869 | CL91: =AX91 -> 55.633 | CM91: =BB91 -> 63.38 | CN91: =BF91 -> 46.547 | CO91: =BJ91 -> 67.24
B92: ST Liabilities Held-For-Sale | AT92: 0 | AU92: 0 | AV92: 1.056 | AW92: 0 | AX92: 0 | AY92: 0 | AZ92: 0 | BA92: 0 | BB92: 0 | BC92: 0 | BD92: 0 | BE92: 0 | BF92: 0 | BG92: 0 | BH92: 0 | BI92: 0 | BJ92: 0 | BK92: 0 | BL92: 0 | BM92: 0 | BN92: 128.32 | BO92: 127.298 | BP92: 135.494 | CK92: =AT92 -> 0 | CL92: =AX92 -> 0 | CM92: =BB92 -> 0 | CN92: =BF92 -> 0 | CO92: =BJ92 -> 0
B93: LT Debt | AT93: 2377.88 | AU93: 2295.43 | AV93: 2215.66 | AW93: 1948.666 | AX93: 1740.1 | AY93: 1740.778 | AZ93: 1605.95 | BA93: 1593.5 | BB93: 1624.02 | BC93: 1549.47 | BD93: 1470.67 | BE93: 1950.123 | BF93: 1727.57 | BG93: 1667.896 | BH93: 1624.22 | BI93: 1661.54 | BJ93: 1555.87 | BK93: 1807.321 | BL93: 1801.64 | BM93: 2571.5 | BN93: 2541.449 | BO93: 2514.268 | BP93: 2720.509 | CK93: =AT93 -> 2377.88 | CL93: =AX93 -> 1740.1 | CM93: =BB93 -> 1624.02 | CN93: =BF93 -> 1727.57 | CO93: =BJ93 -> 1555.87
B94: LT Tax Liabilities | AT94: 484.67 | AU94: 482.48 | AV94: 483.269 | AW94: 479.105 | AX94: 370.12 | AY94: 369.73 | AZ94: 379.93 | BA94: 387.333 | BB94: 388.88 | BC94: 388.18 | BD94: 385.11 | BE94: 389.08 | BF94: 456.08 | BG94: 456.36 | BH94: 453.02 | BI94: 445.84 | BJ94: 391.066 | BK94: 385.67 | BL94: 373.955 | BM94: 423.65 | BN94: 183.749 | BO94: 169.429 | BP94: 146.141 | CK94: =AT94 -> 484.67 | CL94: =AX94 -> 370.12 | CM94: =BB94 -> 388.88 | CN94: =BF94 -> 456.08 | CO94: =BJ94 -> 391.066
B95: Pension Benefits | AT95: 74.499 | AU95: 57.118 | AV95: 51.179 | AW95: 49.843 | AX95: 45.18 | AY95: 43.42 | AZ95: 42.09 | BA95: 40.34 | BB95: 31.394 | BC95: 30.92 | BD95: 30.686 | BE95: 30.05 | BF95: 23.989 | BG95: 23.17 | BH95: 23.026 | BI95: 23.548 | BJ95: 20.18 | BK95: 20.3 | BL95: 21.485 | BM95: 32.808 | BN95: 3.536 | BO95: 3.831 | BP95: 3.802 | CK95: =AT95 -> 74.499 | CL95: =AX95 -> 45.18 | CM95: =BB95 -> 31.394 | CN95: =BF95 -> 23.989 | CO95: =BJ95 -> 20.18
B96: LT Liability for Uncertain Taxes | AT96: 10.127 | AU96: 9.987 | AV96: 10.078 | AW96: 10.078 | AX96: 8.646 | AY96: 8.61 | AZ96: 8.543 | BA96: 9 | BB96: 5.8 | BC96: 6.464 | BD96: 6.53 | BE96: 6.545 | BF96: 3.37 | BG96: 3.288 | BH96: 3.271 | BI96: 3.369 | BJ96: 1.83 | BK96: 1.896 | BL96: 1.96 | BM96: 4.592 | BN96: 84.21 | BO96: 68.32 | BP96: 64.54 | CK96: =AT96 -> 10.127 | CL96: =AX96 -> 8.646 | CM96: =BB96 -> 5.8 | CN96: =BF96 -> 3.37 | CO96: =BJ96 -> 1.83
B97: LT Operating Lease Liabilities | AT97: 86.09 | AU97: 79.403 | AV97: 101.302 | AW97: 114.777 | AX97: 116.03 | AY97: 109.59 | AZ97: 104.702 | BA97: 99.6 | BB97: 120.43 | BC97: 115.83 | BD97: 112.229 | BE97: 111.81 | BF97: 111.3 | BG97: 104.37 | BH97: 102.572 | BI97: 102.938 | BJ97: 99.15 | BK97: 97.661 | BL97: 93.506 | BM97: 97.65 | BN97: 194.532 | BO97: 162.507 | BP97: 174.899 | CK97: =AT97 -> 86.09 | CL97: =AX97 -> 116.03 | CM97: =BB97 -> 120.43 | CN97: =BF97 -> 111.3 | CO97: =BJ97 -> 99.15
B98: Other LT Liabilities | AT98: 242.78 | AU98: 219.75 | AV98: 211.94 | AW98: 217.411 | AX98: 156.76 | AY98: 149.42 | AZ98: 127.44 | BA98: 122.188 | BB98: 154.05 | BC98: 141.07 | BD98: 119.948 | BE98: 106.555 | BF98: 162.502 | BG98: 148.6 | BH98: 120.05 | BI98: 148.57 | BJ98: 102.307 | BK98: 79.365 | BL98: 123.644 | BM98: 146.838 | BN98: 52.969 | BO98: 52.162 | BP98: 51.974 | CK98: =AT98 -> 242.78 | CL98: =AX98 -> 156.76 | CM98: =BB98 -> 154.05 | CN98: =BF98 -> 162.502 | CO98: =BJ98 -> 102.307
B99: Ttl Liabilities | AT99: =SUM(AT85:AT98) -> 3816.072 | AU99: =SUM(AU85:AU98) -> 3652.219 | AV99: =SUM(AV85:AV98) -> 3600.24 | AW99: =SUM(AW85:AW98) -> 3382.09 | AX99: =SUM(AX85:AX98) -> 3116.947 | AY99: =SUM(AY85:AY98) -> 3077.748 | AZ99: =SUM(AZ85:AZ98) -> 2879.097 | BA99: =SUM(BA85:BA98) -> 2862.878 | ... BP99: =SUM(BP85:BP98) -> 3882.244 | CK99: =AT99 -> 3816.072 | CL99: =AX99 -> 3116.947 | CM99: =BB99 -> 2906.065 | CN99: =BF99 -> 3091.546 | CO99: =BJ99 -> 2819.733
B100: SE | AT100: 3336.457 | AU100: 3375.79 | AV100: 3466.1 | AW100: 3657.87 | AX100: 3754.74 | AY100: 3795.53 | AZ100: 3852.73 | BA100: 3895.16 | BB100: 4021.96 | BC100: 4110.25 | BD100: 4215.09 | BE100: 4314.048 | BF100: 4440.988 | BG100: 4503.21 | BH100: 4558.719 | BI100: 4481.717 | BJ100: 4278.1 | BK100: 4095.16 | BL100: 4242.86 | BM100: 3821.86 | BN100: 3124.768 | BO100: 3084.436 | BP100: 2904.534 | CK100: =AT100 -> 3336.457 | CL100: =AX100 -> 3754.74 | CM100: =BB100 -> 4021.96 | CN100: =BF100 -> 4440.988 | CO100: =BJ100 -> 4278.1
B101: Ttl L + SE | AT101: =AT99+AT100 -> 7152.529 | AU101: =AU99+AU100 -> 7028.009 | AV101: =AV99+AV100 -> 7066.34 | AW101: =AW99+AW100 -> 7039.96 | AX101: =AX99+AX100 -> 6871.687 | AY101: =AY99+AY100 -> 6873.278 | AZ101: =AZ99+AZ100 -> 6731.827 | BA101: =BA99+BA100 -> 6758.038 | ... BP101: =BP99+BP100 -> 6786.778 | CK101: =AT101 -> 7152.529 | CL101: =AX101 -> 6871.687 | CM101: =BB101 -> 6928.025 | CN101: =BF101 -> 7532.534 | CO101: =BJ101 -> 7097.833
B103: Current Ratio | AT103: =SUM(AT70:AT75)/SUM(AT85:AT92) -> 2.6339676 | AU103: =SUM(AU70:AU75)/SUM(AU85:AU92) -> 2.7138614 | AV103: =SUM(AV70:AV75)/SUM(AV85:AV92) -> 2.7281155 | AW103: =SUM(AW70:AW75)/SUM(AW85:AW92) -> 2.7424201 | AX103: =SUM(AX70:AX75)/SUM(AX85:AX92) -> 2.1012776 | AY103: =SUM(AY70:AY75)/SUM(AY85:AY92) -> 2.2770482 | AZ103: =SUM(AZ70:AZ75)/SUM(AZ85:AZ92) -> 2.2693982 | BA103: =SUM(BA70:BA75)/SUM(BA85:BA92) -> 2.388809 | ... BP103: =SUM(BP70:BP75)/SUM(BP85:BP92) -> 2.6040126 | CK103: =SUM(CK70:CK75)/SUM(CK85:CK92) -> 2.6339676 | CL103: =SUM(CL70:CL75)/SUM(CL85:CL92) -> 2.1012776 | CM103: =SUM(CM70:CM75)/SUM(CM85:CM92) -> 2.4264778 | CN103: =SUM(CN70:CN75)/SUM(CN85:CN92) -> 2.3196371 | CO103: =SUM(CO70:CO75)/SUM(CO85:CO92) -> 2.265489
B104: Quick Ratio | AT104: =(SUM(AT70:AT75)-AT72)/SUM(AT85:AT92) -> 1.6836615 | AU104: =(SUM(AU70:AU75)-AU72)/SUM(AU85:AU92) -> 1.7054981 | AV104: =(SUM(AV70:AV75)-AV72)/SUM(AV85:AV92) -> 1.797423 | AW104: =(SUM(AW70:AW75)-AW72)/SUM(AW85:AW92) -> 1.8809271 | AX104: =(SUM(AX70:AX75)-AX72)/SUM(AX85:AX92) -> 1.3989805 | AY104: =(SUM(AY70:AY75)-AY72)/SUM(AY85:AY92) -> 1.5281576 | AZ104: =(SUM(AZ70:AZ75)-AZ72)/SUM(AZ85:AZ92) -> 1.4330698 | BA104: =(SUM(BA70:BA75)-BA72)/SUM(BA85:BA92) -> 1.5211297 | ... BP104: =(SUM(BP70:BP75)-BP72)/SUM(BP85:BP92) -> 2.1155031 | CK104: =(SUM(CK70:CK75)-CK72)/SUM(CK85:CK92) -> 1.6836615 | CL104: =(SUM(CL70:CL75)-CL72)/SUM(CL85:CL92) -> 1.3989805 | CM104: =(SUM(CM70:CM75)-CM72)/SUM(CM85:CM92) -> 1.4316094 | CN104: =(SUM(CN70:CN75)-CN72)/SUM(CN85:CN92) -> 1.2875292 | CO104: =(SUM(CO70:CO75)-CO72)/SUM(CO85:CO92) -> 1.3412595
B105: Cash Ratio | AT105: =AT70/SUM(AT85:AT92) -> 0.69604056 | AU105: =AU70/SUM(AU85:AU92) -> 0.63897128 | AV105: =AV70/SUM(AV85:AV92) -> 0.68673455 | AW105: =AW70/SUM(AW85:AW92) -> 0.85583679 | AX105: =AX70/SUM(AX85:AX92) -> 0.65442259 | AY105: =AY70/SUM(AY85:AY92) -> 0.71114904 | AZ105: =AZ70/SUM(AZ85:AZ92) -> 0.50475066 | BA105: =BA70/SUM(BA85:BA92) -> 0.650252 | ... BP105: =BP70/SUM(BP85:BP92) -> 0.41666817 | CK105: =CK70/SUM(CK85:CK92) -> 0.69604056 | CL105: =CL70/SUM(CL85:CL92) -> 0.65442259 | CM105: =CM70/SUM(CM85:CM92) -> 0.50220898 | CN105: =CN70/SUM(CN85:CN92) -> 0.3672905 | CO105: =CO70/SUM(CO85:CO92) -> 0.44689141
B106: Ttl Asset Turnover | AT106: =AT44/AT83 -> 0.091116659 | AU106: =AU44/AU83 -> 0.090196655 | AV106: =AV44/AV83 -> 0.10096316 | AW106: =AW44/AW83 -> 0.09946408 | AX106: =AX44/AX83 -> 0.11088731 | AY106: =AY44/AY83 -> 0.09335963 | AZ106: =AZ44/AZ83 -> 0.10465431 | BA106: =BA44/BA83 -> 0.10161806 | ... BP106: =BP44/BP83 -> 0.084035753 | CK106: =CK44/CK83 -> 0.34640101 | CL106: =CL44/CL83 -> 0.40885966 | CM106: =CM44/CM83 -> 0.40285893 | CN106: =CN44/CN83 -> 0.3948852 | CO106: =CO44/CO83 -> 0.42933029
B107: Inventory Turnover Ratio | AT107: =AT45/(AVERAGE(AQ72:AT72)) -> 0.63840878 | AU107: =AU45/(AVERAGE(AR72:AU72)) -> 0.56440921 | AV107: =AV45/(AVERAGE(AS72:AV72)) -> 0.62525218 | AW107: =AW45/(AVERAGE(AT72:AW72)) -> 0.62488738 | AX107: =AX45/(AVERAGE(AU72:AX72)) -> 0.6967026 | AY107: =AY45/(AVERAGE(AV72:AY72)) -> 0.60807675 | AZ107: =AZ45/(AVERAGE(AW72:AZ72)) -> 0.64301412 | BA107: =BA45/(AVERAGE(AX72:BA72)) -> 0.62265484 | ... BP107: =BP45/(AVERAGE(BM72:BP72)) -> 0.49210467 | CK107: =CK45/(AVERAGE(CH72:CK72)) -> 2.362244 | CL107: =CL45/(AVERAGE(CI72:CL72)) -> 2.5432435 | CM107: =CM45/(AVERAGE(CJ72:CM72)) -> 2.4085649 | CN107: =CN45/(AVERAGE(CK72:CN72)) -> 2.4186162 | CO107: =CO45/(AVERAGE(CL72:CO72)) -> 2.356441
B108: Return on Assets | AT108: =AT59/AT101 -> 0.0023936988 | AU108: =AU59/AU101 -> 0.010650385 | AV108: =AV59/AV101 -> 0.011798753 | AW108: =AW59/AW101 -> 0.028290786 | AX108: =AX59/AX101 -> 0.022314608 | AY108: =AY59/AY101 -> 0.011219392 | AZ108: =AZ59/AZ101 -> 0.015670486 | BA108: =BA59/BA101 -> 0.015032765 | ... BP108: =BP59/BP101 -> 0.0061534354 | CK108: =CK59/CK101 -> 0.038628015 | CL108: =CL59/CL101 -> 0.074323816 | CM108: =CM59/CM101 -> 0.0523432 | CN108: =CN59/CN101 -> 0.047152525 | CO108: =CO59/CO101 -> 0.0098198986
B109: Return on Equity | AT109: =AT59/AT100 -> 0.0051314913 | AU109: =AU59/AU100 -> 0.022172884 | AV109: =AV59/AV100 -> 0.024054124 | AW109: =AW59/AW100 -> 0.054448627 | AX109: =AX59/AX100 -> 0.04083878 | AY109: =AY59/AY100 -> 0.020317057 | AZ109: =AZ59/AZ100 -> 0.027380844 | BA109: =BA59/BA100 -> 0.026081599 | ... BP109: =BP59/BP100 -> 0.01437821 | CK109: =CK59/CK100 -> 0.0828088 | CL109: =CL59/CL100 -> 0.13602273 | CM109: =CM59/CM100 -> 0.090163751 | CN109: =CN59/CN100 -> 0.079977248 | CO109: =CO59/CO100 -> 0.016292279
...

Sheet Notes | Quant Analysis
CA1: 0
H2: Employee Scope: | AC2: Teleflex Q2'25 Earnings Scope
I30: Notes: | J30: [X]
J31: [Y]
J32: [Z]
H34: Institutional Ownership Snapshot (7/30/2025) | AC34: General Notes/Observations (Updated Q1'25)
AD35: Acquisition of BIOTRONIK Vascular Intervention business
AE36: On February 24, 2025, Managers executed a definitive agreement to acquire substantially all of the Vascular Intervention business (the “VI Business”) of BIOTRONIK SE & Co. KG ("BIOTRONIK")
AF37: The acquisition will include a broad suite of coronary and peripheral medical devices, such as drug-coated balloons, stents, and balloon catheters, which will complement our interventional product portfolio
AF38: Under the terms of the agreement, we will acquire the VI Business for an initial cash payment of €760 million reduced by certain adjustments as provided in the purchase agreement including certain working capital not transferring and other customary adjustments
AF39: The acquisition is subject to customary closing conditions, including receipt of certain regulatory approvals, and is expected to be completed in the third quarter of 2025
AE40: Concurrent with the execution of the agreement to acquire the VI Business, we entered into an amendment to our Third Amended and Restated Credit Agreement (the “Credit Agreement”), which, among other things, (a) provides for a delayed draw term loan facility in an aggregate principal amount of $500 million, which will be available to be drawn on the date on which we consummate the VI Business acquisition and (b) permits us to borrow up to $550 million under the revolving facility provided for under the Credit Agreement on a limited condition basis on the date on which the VI Business acquisition is consummated
AF41: Borrowings under the delayed draw term loan will bear interest at a rate per annum equal to the applicable margin plus, at our option, either (1) the highest of (i) the “Prime Rate” in the U.S. last quoted by The Wall Street Journal, (ii) 0.50% above the greater of the federal funds rate and the rate comprised of both overnight federal funds and overnight eurodollar transactions denominated in dollars and (iii) 1.00% above the Term SOFR Rate for a one month interest period, plus an applicable margin ranging from 0.125% to 1.00%, in each case subject to adjustments based on our total net leverage ratio or (2) a Term Secured Overnight Financing Rate (“SOFR”) rate (which includes a credit spread adjustment of 10 basis points)
AF42: The applicable margin for borrowings under the delayed draw term loan range from 1.125% to 2.00% for SOFR borrowings and from 0.125% to 1.00% for base-rate borrowings, in each case, depending on, at our election, either (x) our public corporate family rating or (y) our consolidated total net leverage ratio, in each case, based on the most recently ended fiscal quarter. The obligations under the delayed draw term loan will be guaranteed and secured on the same basis as the facilities provided for under the Credit Agreement
AF43: The delayed draw term loan will not amortize and will mature on the earlier of (x) the date that is two years after the date on which such loans are funded and (y) the maturity date for the revolving facility provided for under the Credit Agreement
AE44: In addition to amending our Credit Agreement, we also entered into foreign exchange derivative contracts with an aggregate notional value of €700 million to economically hedge against the foreign currency exposure associated with the cash consideration needed to complete the VI Business acquisition
AE45: We anticipate using the new delayed draw term loan along with revolving credit borrowings under the Credit Agreement and cash on hand to finance the VI Business acquisition
AF46: For the year ended December 31, 2024, The Company incurred transaction costs of $11.5 million in connection with the acquisition, which was recognized in selling, general and administrative expenses in the Consolidated Statement of Income
AF47: The majority of the transaction costs were recognized in the fourth quarter of 2024
AD48: Recently Announced Strategic Actions
AE49: On February 27, 2025, Managers announced intentions to create a new, independently traded public company comprising Urology (consisting of our Interventional Urology and Urology product categories), Acute Care (consisting of our Respiratory product category, the majority of our Anesthesia product category and certain products within our Interventional Access and Surgical product categories) and the OEM businesses
AE50: The Vascular Access product category, most of our products within our Interventional Access and Surgical product categories and the expected acquisition of the VI business will remain with Teleflex
AE51: Managers intend to target the completion of the transaction in the middle of 2026 via a distribution of newly issued shares of the new company to shareholders that is tax-free for U.S. tax purposes
AE52: There can be no guarantees that the proposed separation will be completed on the terms and within the timeframe we announced, or at all
I63: Notes: | J63: [X]
J64: [Y]
J65: [Z]
AC66: Financial Stmts. Notes/Observations (Updated Q1'25)
H67: Revenue Breakdown by Segment | AC67: Revenues:
I99: Notes: | J99: [X]
J100: [Y]
J101: [Z]
H103: Q/q Total Revenues, Net Income, FCF | AC103: Earnings Scope:
I132: Notes: | J132: [X]
J133: [Y]
J134: [Z]
H136: Y/y Total Revenues, Net Income, FCF | AC136: Balance Sheet Scope:
I165: Notes: | J165: [X]
J166: [Y]
J167: [Z]
AC181: [Equity Preformance Compared to Peers]
AD182: Use Godel CMS command
A183: 752 Trading Days? (From: 7/30/2021 - 7/30/2025)
A184: Close | B184: High | C184: Low | D184: Open | E184: Volume | F184: UTC Date | G184: Change
A185: 113.91 | B185: 116.13 | C185: 113.78 | D185: 115.1 | E185: 522319 | F185: Wed, 30 Jul 2025 00:00:00 GMT | G185: =A185/D185-1 -> -0.010338836
A186: 115.49 | B186: 116.21 | C186: 114.5701 | D186: 115.19 | E186: 309568 | F186: Tue, 29 Jul 2025 00:00:00 GMT | G186: =A186/D186-1 -> 0.0026043927
A187: 115.56 | B187: 117.25 | C187: 115.385 | D187: 116.12 | E187: 395730 | F187: Mon, 28 Jul 2025 00:00:00 GMT | G187: =A187/D187-1 -> -0.0048225973
A188: 117.19 | B188: 117.36 | C188: 114.9844 | D188: 116.17 | E188: 326398 | F188: Fri, 25 Jul 2025 00:00:00 GMT | G188: =A188/D188-1 -> 0.0087802359
A189: 116.2 | B189: 118.81 | C189: 116.125 | D189: 117.31 | E189: 541318 | F189: Thu, 24 Jul 2025 00:00:00 GMT | G189: =A189/D189-1 -> -0.0094621089
A190: 117.24 | B190: 117.64 | C190: 115.51 | D190: 116.85 | E190: 651680 | F190: Wed, 23 Jul 2025 00:00:00 GMT | G190: =A190/D190-1 -> 0.0033376123
A191: 115.2 | B191: 115.22 | C191: 108.9 | D191: 110.8 | E191: 670064 | F191: Tue, 22 Jul 2025 00:00:00 GMT | G191: =A191/D191-1 -> 0.039711191
A192: 109.79 | B192: 112.0843 | C192: 109.73 | D192: 111.72 | E192: 703646 | F192: Mon, 21 Jul 2025 00:00:00 GMT | G192: =A192/D192-1 -> -0.017275331
A193: 111.06 | B193: 114.3555 | C193: 110.83 | D193: 114.03 | E193: 845803 | F193: Fri, 18 Jul 2025 00:00:00 GMT | G193: =A193/D193-1 -> -0.026045777
A194: 113.59 | B194: 114 | C194: 112.5 | D194: 112.66 | E194: 543539 | F194: Thu, 17 Jul 2025 00:00:00 GMT | G194: =A194/D194-1 -> 0.0082549263
A195: 113.32 | B195: 114.625 | C195: 112.32 | D195: 114.01 | E195: 683972 | F195: Wed, 16 Jul 2025 00:00:00 GMT | G195: =A195/D195-1 -> -0.0060521007
A196: 113.47 | B196: 116.395 | C196: 113.32 | D196: 116.01 | E196: 685267 | F196: Tue, 15 Jul 2025 00:00:00 GMT | G196: =A196/D196-1 -> -0.021894664
A197: 115.75 | B197: 116.725 | C197: 114.5 | D197: 115.8 | E197: 641744 | F197: Mon, 14 Jul 2025 00:00:00 GMT | G197: =A197/D197-1 -> -0.00043177893
A198: 116.4 | B198: 119.025 | C198: 116.215 | D198: 118.32 | E198: 307857 | F198: Fri, 11 Jul 2025 00:00:00 GMT | G198: =A198/D198-1 -> -0.016227181 | J198: Min | K198: =MIN(G185:G936) -> -0.11111821
A199: 119.94 | B199: 121.75 | C199: 118.21 | D199: 118.41 | E199: 444206 | F199: Thu, 10 Jul 2025 00:00:00 GMT | G199: =A199/D199-1 -> 0.012921206 | J199: Max | K199: =MAX(G185:G936) -> 0.089758283
A200: 118.93 | B200: 120 | C200: 117.83 | D200: 119.29 | E200: 452191 | F200: Wed, 09 Jul 2025 00:00:00 GMT | G200: =A200/D200-1 -> -0.0030178556 | J200: Mean μ | K200: =AVERAGE(G185:G936) -> -0.00031910528
A201: 119.68 | B201: 121.7196 | C201: 116.88 | D201: 116.93 | E201: 632490 | F201: Tue, 08 Jul 2025 00:00:00 GMT | G201: =A201/D201-1 -> 0.023518344 | J201: Median | K201: =MEDIAN(G185:G936) -> 2.8094623e-05
A202: 116.67 | B202: 120 | C202: 116.32 | D202: 119.26 | E202: 457948 | F202: Mon, 07 Jul 2025 00:00:00 GMT | G202: =A202/D202-1 -> -0.021717256 | J202: SD σ | K202: =_xlfn.STDEV.P(G185:G936) -> 0.01662862
A203: 119.9 | B203: 122.39 | C203: 119.79 | D203: 122.16 | E203: 360058 | F203: Thu, 03 Jul 2025 00:00:00 GMT | G203: =A203/D203-1 -> -0.018500327 | J203: 3σ 1-Day Δ: ± | K203: =3*K202 -> 0.04988586 | M203: <- Sharpe Ratio (Risk Adjusted Return)
A204: 121.59 | B204: 122.42 | C204: 120.58 | D204: 122.33 | E204: 532464 | F204: Wed, 02 Jul 2025 00:00:00 GMT | G204: =A204/D204-1 -> -0.0060492112 | J204: β (1-year avg.) | K204: 1.08 | M204: <- Sortino Ratio (Downside Risk Adjusted Return)
A205: 121.83 | B205: 123.965 | C205: 118.09 | D205: 118.77 | E205: 735471 | F205: Tue, 01 Jul 2025 00:00:00 GMT | G205: =A205/D205-1 -> 0.025764082
A206: 118.36 | B206: 120 | C206: 117.41 | D206: 120 | E206: 934722 | F206: Mon, 30 Jun 2025 00:00:00 GMT | G206: =A206/D206-1 -> -0.013666667
A207: 119.47 | B207: 119.99 | C207: 118.31 | D207: 119.11 | E207: 712257 | F207: Fri, 27 Jun 2025 00:00:00 GMT | G207: =A207/D207-1 -> 0.0030224163 | I207: n = | J207: 752
A208: 119.58 | B208: 120.38 | C208: 118.95 | D208: 119.48 | E208: 303574 | F208: Thu, 26 Jun 2025 00:00:00 GMT | G208: =A208/D208-1 -> 0.00083696016 | I208: Histogram Data | L208: Distribution Overlay | P208: SD Lines
A209: 119.15 | B209: 120.32 | C209: 118.68 | D209: 120.02 | E209: 431644 | F209: Wed, 25 Jun 2025 00:00:00 GMT | G209: =A209/D209-1 -> -0.0072487919 | I209: Bin | J209: Frequency | L209: (X) 1-Day Δ | M209: (Y) Pop. Density | P209: X | Q209: Y
A210: 120.1 | B210: 120.27 | C210: 117.525 | D210: 118.59 | E210: 461848 | F210: Tue, 24 Jun 2025 00:00:00 GMT | G210: =A210/D210-1 -> 0.012732945 | I210: -0.05 | J210: 1 | L210: -0.05 | M210: =_xlfn.NORM.DIST(L210,$K$200,$K$202,FALSE) -> 0.27653818 | O210: Mean | P210: =K200 -> -0.00031910528 | Q210: 0
A211: 118.06 | B211: 118.85 | C211: 115.9397 | D211: 117.94 | E211: 447478 | F211: Mon, 23 Jun 2025 00:00:00 GMT | G211: =A211/D211-1 -> 0.0010174665 | I211: -0.0475 | J211: 2 | L211: -0.0475 | M211: =_xlfn.NORM.DIST(L211,$K$200,$K$202,FALSE) -> 0.42847133 | P211: =K200 -> -0.00031910528 | Q211: 25
A212: 118.31 | B212: 118.995 | C212: 116.6 | D212: 118.62 | E212: 1262901 | F212: Fri, 20 Jun 2025 00:00:00 GMT | G212: =A212/D212-1 -> -0.0026133873 | I212: -0.045 | J212: 2 | L212: -0.045 | M212: =_xlfn.NORM.DIST(L212,$K$200,$K$202,FALSE) -> 0.64904086 | O212: -3σ | P212: =($K$202*-3)+$K$200 -> -0.050204965 | Q212: 0
A213: 117.72 | B213: 118.6175 | C213: 117.04 | D213: 117.89 | E213: 556011 | F213: Wed, 18 Jun 2025 00:00:00 GMT | G213: =A213/D213-1 -> -0.0014420222 | I213: -0.0425 | J213: 1 | L213: -0.0425 | M213: =_xlfn.NORM.DIST(L213,$K$200,$K$202,FALSE) -> 0.96118265 | P213: =($K$202*-3)+$K$200 -> -0.050204965 | Q213: 3
A214: 117.53 | B214: 120.8892 | C214: 117.24 | D214: 119.63 | E214: 496923 | F214: Tue, 17 Jun 2025 00:00:00 GMT | G214: =A214/D214-1 -> -0.017554125 | I214: -0.04 | J214: 1 | L214: -0.04 | M214: =_xlfn.NORM.DIST(L214,$K$200,$K$202,FALSE) -> 1.3916288 | O214: -2σ | P214: =($K$202*-2)+$K$200 -> -0.033576345 | Q214: 0
A215: 121.11 | B215: 121.5325 | C215: 119.6196 | D215: 120.38 | E215: 360756 | F215: Mon, 16 Jun 2025 00:00:00 GMT | G215: =A215/D215-1 -> 0.0060641303 | I215: -0.0375 | J215: 1 | L215: -0.0375 | M215: =_xlfn.NORM.DIST(L215,$K$200,$K$202,FALSE) -> 1.9698108 | P215: =($K$202*-2)+$K$200 -> -0.033576345 | Q215: 5
A216: 119.93 | B216: 122.17 | C216: 119.89 | D216: 120.42 | E216: 368994 | F216: Fri, 13 Jun 2025 00:00:00 GMT | G216: =A216/D216-1 -> -0.0040690915 | I216: -0.035 | J216: 1 | L216: -0.035 | M216: =_xlfn.NORM.DIST(L216,$K$200,$K$202,FALSE) -> 2.7258956 | O216: -1σ | P216: =($K$202*-1)+$K$200 -> -0.016947725 | Q216: 0
A217: 122.1 | B217: 122.3499 | C217: 120.72 | D217: 120.72 | E217: 348599 | F217: Thu, 12 Jun 2025 00:00:00 GMT | G217: =A217/D217-1 -> 0.011431412 | I217: -0.0325 | J217: 6 | L217: -0.0325 | M217: =_xlfn.NORM.DIST(L217,$K$200,$K$202,FALSE) -> 3.6878864 | P217: =($K$202*-1)+$K$200 -> -0.016947725 | Q217: 15
A218: 122.47 | B218: 125.99 | C218: 121.41 | D218: 125.78 | E218: 465377 | F218: Wed, 11 Jun 2025 00:00:00 GMT | G218: =A218/D218-1 -> -0.026315789 | I218: -0.03 | J218: 5 | L218: -0.03 | M218: =_xlfn.NORM.DIST(L218,$K$200,$K$202,FALSE) -> 4.8778614 | O218: 1σ | P218: =($K$202*1)+$K$200 -> 0.016309515 | Q218: 0
A219: 125.44 | B219: 126.87 | C219: 123.9 | D219: 125.34 | E219: 565031 | F219: Tue, 10 Jun 2025 00:00:00 GMT | G219: =A219/D219-1 -> 0.0007978299 | I219: -0.0275 | J219: 6 | L219: -0.0275 | M219: =_xlfn.NORM.DIST(L219,$K$200,$K$202,FALSE) -> 6.3076122 | P219: =($K$202*1)+$K$200 -> 0.016309515 | Q219: 15
A220: 123.27 | B220: 124.54 | C220: 121.285 | D220: 123.62 | E220: 433256 | F220: Mon, 09 Jun 2025 00:00:00 GMT | G220: =A220/D220-1 -> -0.0028312571 | I220: -0.025 | J220: 16 | L220: -0.025 | M220: =_xlfn.NORM.DIST(L220,$K$200,$K$202,FALSE) -> 7.9741448 | O220: 2σ | P220: =($K$202*2)+$K$200 -> 0.032938135 | Q220: 0
A221: 122.8 | B221: 123.75 | C221: 122.1 | D221: 122.76 | E221: 361939 | F221: Fri, 06 Jun 2025 00:00:00 GMT | G221: =A221/D221-1 -> 0.00032583904 | I221: -0.0225 | J221: 14 | L221: -0.0225 | M221: =_xlfn.NORM.DIST(L221,$K$200,$K$202,FALSE) -> 9.8556861 | P221: =($K$202*2)+$K$200 -> 0.032938135 | Q221: 5
A222: 122.46 | B222: 124.01 | C222: 121.71 | D222: 123.23 | E222: 501734 | F222: Thu, 05 Jun 2025 00:00:00 GMT | G222: =A222/D222-1 -> -0.0062484785 | I222: -0.02 | J222: 13 | L222: -0.02 | M222: =_xlfn.NORM.DIST(L222,$K$200,$K$202,FALSE) -> 11.908943 | O222: 3σ | P222: =($K$202*3)+$K$200 -> 0.049566755 | Q222: 0
A223: 122.75 | B223: 123.44 | C223: 120.93 | D223: 121.57 | E223: 376076 | F223: Wed, 04 Jun 2025 00:00:00 GMT | G223: =A223/D223-1 -> 0.009706342 | I223: -0.0175 | J223: 25 | L223: -0.0175 | M223: =_xlfn.NORM.DIST(L223,$K$200,$K$202,FALSE) -> 14.06835 | P223: =($K$202*3)+$K$200 -> 0.049566755 | Q223: 3
A224: 121.44 | B224: 122.175 | C224: 118.7 | D224: 119.13 | E224: 514742 | F224: Tue, 03 Jun 2025 00:00:00 GMT | G224: =A224/D224-1 -> 0.019390582 | I224: -0.015 | J224: 22 | L224: -0.015 | M224: =_xlfn.NORM.DIST(L224,$K$200,$K$202,FALSE) -> 16.247881
A225: 119.66 | B225: 122.165 | C225: 119.2 | D225: 121.71 | E225: 538380 | F225: Mon, 02 Jun 2025 00:00:00 GMT | G225: =A225/D225-1 -> -0.016843316 | I225: -0.0125 | J225: 26 | L225: -0.0125 | M225: =_xlfn.NORM.DIST(L225,$K$200,$K$202,FALSE) -> 18.345684
A226: 122.27 | B226: 123.13 | C226: 119.1 | D226: 121.38 | E226: 683820 | F226: Fri, 30 May 2025 00:00:00 GMT | G226: =A226/D226-1 -> 0.0073323447 | I226: -0.01 | J226: 31 | L226: -0.01 | M226: =_xlfn.NORM.DIST(L226,$K$200,$K$202,FALSE) -> 20.251383
A227: 122.53 | B227: 122.91 | C227: 120.95 | D227: 122.27 | E227: 392468 | F227: Thu, 29 May 2025 00:00:00 GMT | G227: =A227/D227-1 -> 0.0021264415 | I227: -0.0075 | J227: 43 | L227: -0.0075 | M227: =_xlfn.NORM.DIST(L227,$K$200,$K$202,FALSE) -> 21.855416
A228: 121.09 | B228: 123.33 | C228: 121.01 | D228: 122.89 | E228: 284817 | F228: Wed, 28 May 2025 00:00:00 GMT | G228: =A228/D228-1 -> -0.014647246 | I228: -0.005 | J228: 45 | L228: -0.005 | M228: =_xlfn.NORM.DIST(L228,$K$200,$K$202,FALSE) -> 23.059351
A229: 122.96 | B229: 123.31 | C229: 121.035 | D229: 122.28 | E229: 393493 | F229: Tue, 27 May 2025 00:00:00 GMT | G229: =A229/D229-1 -> 0.0055610075 | I229: -0.0025 | J229: 54 | L229: -0.0025 | M229: =_xlfn.NORM.DIST(L229,$K$200,$K$202,FALSE) -> 23.78585
A230: 120.78 | B230: 121.54 | C230: 119.08 | D230: 119.08 | E230: 504862 | F230: Fri, 23 May 2025 00:00:00 GMT | G230: =A230/D230-1 -> 0.014276117 | I230: 0 | J230: 59 | L230: 0 | M230: =_xlfn.NORM.DIST(L230,$K$200,$K$202,FALSE) -> 23.986887
A231: 120.94 | B231: 121.625 | C231: 119.6 | D231: 120.88 | E231: 426349 | F231: Thu, 22 May 2025 00:00:00 GMT | G231: =A231/D231-1 -> 0.00049636003 | I231: 0.0025 | J231: 64 | L231: 0.0025 | M231: =_xlfn.NORM.DIST(L231,$K$200,$K$202,FALSE) -> 23.648996
A232: 121.97 | B232: 126.43 | C232: 121.79 | D232: 125.98 | E232: 391174 | F232: Wed, 21 May 2025 00:00:00 GMT | G232: =A232/D232-1 -> -0.031830449 | I232: 0.005 | J232: 52 | L232: 0.005 | M232: =_xlfn.NORM.DIST(L232,$K$200,$K$202,FALSE) -> 22.794766
A233: 126.86 | B233: 128.28 | C233: 126.065 | D233: 127.48 | E233: 327442 | F233: Tue, 20 May 2025 00:00:00 GMT | G233: =A233/D233-1 -> -0.004863508 | I233: 0.0075 | J233: 54 | L233: 0.0075 | M233: =_xlfn.NORM.DIST(L233,$K$200,$K$202,FALSE) -> 21.480341
A234: 127.79 | B234: 128.03934 | C234: 125.86263 | D234: 127.10183 | E234: 394167.95 | F234: Mon, 19 May 2025 00:00:00 GMT | G234: =A234/D234-1 -> 0.0054143126 | I234: 0.01 | J234: 42 | L234: 0.01 | M234: =_xlfn.NORM.DIST(L234,$K$200,$K$202,FALSE) -> 19.789317
A235: 128.94692 | B235: 128.94692 | C235: 125.58427 | D235: 127.19159 | E235: 544254.21 | F235: Fri, 16 May 2025 00:00:00 GMT | G235: =A235/D235-1 -> 0.013800674 | I235: 0.0125 | J235: 34 | L235: 0.0125 | M235: =_xlfn.NORM.DIST(L235,$K$200,$K$202,FALSE) -> 17.823954
... A250: 134.85121 | B250: 134.92103 | C250: 132.71689 | D250: 134.2927 | E250: 680517.79 | F250: Fri, 25 Apr 2025 00:00:00 GMT | G250: =A250/D250-1 -> 0.0041589306 | I250: 0.05 | J250: 1 | L250: 0.05 | M250: =_xlfn.NORM.DIST(L250,$K$200,$K$202,FALSE) -> 0.24639716
A251: 135.30002 | B251: 135.30002 | C251: 132.92633 | D251: 133.30533 | E251: 693616.55 | F251: Thu, 24 Apr 2025 00:00:00 GMT | G251: =A251/D251-1 -> 0.01496334 | I251: More | J251: 5
A252: 132.66702 | B252: 136.96559 | C252: 132.1883 | D252: 134.00347 | E252: 690170.41 | F252: Wed, 23 Apr 2025 00:00:00 GMT | G252: =A252/D252-1 -> -0.0099732063
A253: 131.09122 | B253: 131.46043 | C253: 129.09652 | D253: 130.0839 | E253: 549074 | F253: Tue, 22 Apr 2025 00:00:00 GMT | G253: =A253/D253-1 -> 0.0077436173
A254: 128.80729 | B254: 129.46554 | C254: 125.93992 | D254: 128.23881 | E254: 1035998.1 | F254: Mon, 21 Apr 2025 00:00:00 GMT | G254: =A254/D254-1 -> 0.0044330378
...

Sheet Product Lines
B2: Product Families | F2: Key Product Brands
B3: Vascular Access | C3: Centeral Venous Catheters | F3: Four-Lumen Catheters:
F4: Arrowg+ard Blue Plus Four-Lumen CVC Catheter
F5: Pressure Injectable Arrowg+ard Blue Plus Four-Lumen CVC Catheter
F6: Four-Lumen CVC Catheter
F7: Three-Lumen Catheters:
F8: Arrowg+ard Blue Large-Bore Three-Lumen CVC Catheter
F9: Arrowg+ard Blue Three-Lumen CVC Catheter
F10: Pressure Injectable Arrowg+ard Blue Plus Three-Lumen CVC Catheter
F11: Small Vein Arrowg+ard Blue Three-Lumen CVC Catheter
F12: Three-Lumen CVC Catheter
F13: Three-Lumen CVC Catheter for Femoral Vein Insertion
F14: Two-Lumen Catheters:
F15: Pressure Injectable Arrowg+ard Blue Plus Two-Lumen CVC Catheter
... F31: Vessel Catheterization Set
C32: Arterial | F32: Arterial Catheterization Set
F33: Arterial/Venous Catheterization Set
F34: QuickFlash Radial Artery Catheterization Set
F35: Radial Artery Catheterization Set
F36: Radial Artery Catheterization Set with Integral Needle Protection
D38: PICC | F38: One-Lumen PICC Set
C40: Midline and Peripheral IV | F40: One-Lumen Midline
F41: Pressure Injectable One-Lumen Midline
F42: Pressure Injectable Arrowg+ard Vlue Advance One-Lumen Midline
F43: Twin-Cath 18/20 Two-Lumen Peripheral Catheter
F44: Twin-Cath 20/22 Two-Lumen Peripheral Catheter
F45: Vasonova VPS G4 Cart GCX
D46: Tip Positioning Systems | F46: Vasonova VPS G4 Service/Warranty
F47: Arrow VPS Stylet Bedside Procedure Kit
F48: VPS G4 Device Remote Control
F49: VPS G4 Device Stylet Extention Cable
F50: VPS G4 Interface Case
F51: VPS Device ECG Lead Set (3 Lead) RoHS
D53: Accessory
B55: Interventional Cardiology / Radiology
B71: Anesthesia
B74: Surgical
B77: Interventional Urology
D78: Interventional Urology
D81: Urology
B83: OEM
D84: Military / Federal
B87: Other
D88: Emergency Medicine

Sheet CVC
B2: Four-Lumen Catheters:
C3: Arrowg+ard Blue Plus Four-Lumen CVC Catheter
C4: Pressure Injectable Arrowg+ard Blue Plus Four-Lumen CVC Catheter
C5: Four-Lumen CVC Catheter
B6: Three-Lumen Catheters:
C7: Arrowg+ard Blue Large-Bore Three-Lumen CVC Catheter
C8: Arrowg+ard Blue Three-Lumen CVC Catheter
C9: Pressure Injectable Arrowg+ard Blue Plus Three-Lumen CVC Catheter
C10: Small Vein Arrowg+ard Blue Three-Lumen CVC Catheter
C11: Three-Lumen CVC Catheter
C12: Three-Lumen CVC Catheter for Femoral Vein Insertion
B13: Two-Lumen Catheters:
C14: Pressure Injectable Arrowg+ard Blue Plus Two-Lumen CVC Catheter
C15: Two-Lumen CVC Catheter for Femoral Vein Insertion
C16: Small Vein Arrowg+ard Blue Two-Lumen CVC Catheter
C17: Two-Lumen CVC Catheter
C18: Arrowg+ard Blue Two-Lumen Hemodialysis Catheter
C19: Pediatric Two-Lumen Hemodialysis Catheterization
C20: Two-Lumen Hemodialysis Catheter
C21: Two-Lumen Hemodialysis Curved Catheter Catheter
C22: You-Bend Two-Lumen Hemodialysis Catheter
B23: One-Lumen Catheters:
C24: Arrowg+ard Blue One-Lumen CVC Catheter
C25: One-Lumen CVC Catheter
B26: Specialty & Related Sets:
C27: Central Venous Catheterization Set with Blue FlexTip Catheter
C28: Jugular Puncture Catheter
C29: Vessel Catheterization Set

Sheet Management
B2: Name | E2: Age | H2: Positions and Offices with Company
B3: Liam J. Kelly | E3: 58 | H3: Chairman, President and Chief Executive Officer
B4: Thomas E. Powell | E4: 63 | H4: Executive Vice President and Chief Financial Officer
B5: Cameron P. Hicks | E5: 60 | H5: Corporate Vice President, Human Resources and Communications
B6: Daniel V. Logue | E6: 51 | H6: Corporate Vice President, General Counsel and Secretary
B7: Jay White | E7: 51 | H7: Corporate Vice President and President, Global Commercial
B8: James Winters | E8: 52 | H8: Corporate Vice President, Manufacturing and Supply Chain
B24: Mr. Kelly has been our President and Chief Executive Officer since January 2018 and has been Chairman of our Board of Directors since May 2020

Sheet Table Formatting
B2: [Bold Title] | G2: [Bold Title]
B3: Line Titles | G3: <-- General
B4: Line Titles | G4: <-- Info
B5: Line Titles | G5: <-- General
B6: Line Titles | G6: <-- Info
B7: Line Titles | G7: <-- General
B8: Line Titles | G8: <-- Info
