Workbook

Sheet Main
A1: Master
B2: TMO
B3: Price | C3: 694.02 | D3: 10/21/2026
B4: SO | C4: 370 | D4: Q3'26
B5: MC | C5: =C3*C4 -> 256787.4
B6: Cash | C6: =5461+600 -> 6061 | D6: Q3'26
B7: Debt | C7: =2262+39108 -> 41370 | D7: Q3'26
B8: EV | C8: =C5-C6+C7 -> 292096.4
B10: Thermo Fisher Scientific, Inc. | N10: Resources:
N11: SEC filings | Q11: https://www.sec.gov/edgar/browse/?CIK=97745&owner=exclude
B12: Founder(s): George Hatsopoulos & Peter Nomikos | F12: Registered Exchange: NYSE | N12: Thermofisher Homepage | Q12: https://www.thermofisher.com/us/en/home.html
B13: Founded: 1956 | F13: Address: 168 THIRD AVENUE, WALTHAM, MA, 02451 | O13: TMO IR page | R13: https://ir.thermofisher.com/investors/overview/default.aspx
B14: Headquarters: Waltham, Massachusetts | F14: Investor Relations Contact: | N14: FDA Med Device Reporting's | Q14: https://www.fda.gov/medical-devices
B15: Current CEO: Marc Casper | F15: Investors Relation Department | N15: U.S. Patent Office Search | Q15: https://ppubs.uspto.gov/pubThe Companybapp/static/pages/ppubsbasic.html
B16: Employees: 125,000 | F16: Phone: | G16: (781) 622 - 1000 | I16: Email: | J16: BSXInvestorRelations@bsci.com | N16: MedTech News | Q16: https://www.medtechdive.com/
B17: Sector: Healthcare | N17: Earnings Calls | Q17: https://seekingalpha.com/symbol/BSX/earnings/transcripts
B18: Industry: Medical Devices | N18: Equity Analysis | Q18: https://stockanalysis.com/stocks/tmo/company/
B19: IPO: May 19, 1992 -- $1.6B valuation | N19: MacroTrends | Q19: https://www.macrotrends.net/stocks/charts/BSX/boston-scientific/income-statement?freq=Q
B20: Fiscal Year: [January - December] | N20: ROIC, WACC | Q20: https://www.gurufocus.com/term/wacc/BSX
N21: Godel Terminal | Q21: https://app.godelterminal.com/
A23: Company Overview:
B24: Thermo Fisher Scientific is a life sciences and lab equipment maker that sells scientific instruments, reagents, consumables, and software. It also provides contract drug development, manufacturing, and clinical research services
C25: Brands include Thermo Scientific, Applied Biosystems, Invitrogen, Fisher Scientific, Patheon, and PPD in the North America, Europe, Asia-Pacific, and internationally
B26: The Company’s Life Sciences Solutions segment offers reagents, instruments, and consumables for biological and medical research, discovery and production of drugs and vaccines, as well as diagnosis of infections and diseases
B27: Its Analytical Instruments segment provides instruments, consumables, software, and services for pharmaceutical, biotechnology, academic, government, environmental, and other research and industrial markets, as well as clinical laboratories
B28: The Company’s Specialty Diagnostics segment includes clinical diagnostics offering liquid, ready-to-use, and lyophilized immunodiagnostic reagent kits, as well as calibrators, controls, protein detection assays, and instruments
C29: immunodiagnostics offers develops, manufactures, and markets complete blood test systems to support the clinical diagnosis and monitoring of allergy, asthma, and autoimmune diseases
C30: microbiology offers dehydrated and prepared culture media, collection and transport systems, instrumentation, and consumables; transplant diagnostics products include human leukocyte antigen typing and testing for organ transplant market
C31: healthcare market channel offers consumables, diagnostic kits and reagents, equipment, instruments, solutions, and services
B32: Laboratory Products and Biopharma Services segment provides laboratory products, research and safety market channel, and pharma services and clinical research
B33: The Company offers products and services through a direct sales force, customer-service professionals, electronic commerce, and third-party distributors under Thermo Scientific; Applied Biosystems; Invitrogen; Fisher Scientific; Unity Lab Services; and Patheon and PPD
B34: Thermo Fisher Scientific Inc. was founded in 1956 and is headquartered in Waltham, Massachusetts
A36: Business Segments and Geographical Info:

Sheet Model
B1: [Use for Graphing] | AQ1: Q1 2020 | AU1: Q1 2021 | AY1: Q1 2022 | BC1: Q1 2023 | BG1: Q1 2024 | BK1: Q1 2025 | BO1: Q1 2026
B2: Quarterly
B3: Revenues | C3: {="Q"&MOD(_xlfn.SEQUENCE(1,68)-1,4)+1&" "&(2010+INT((_xlfn.SEQUENCE(1,68)-1)/4))} -> Q1 2010 | D3: Q2 2010 | E3: Q3 2010 | F3: Q4 2010 | G3: Q1 2011 | H3: Q2 2011 | I3: Q3 2011 | J3: Q4 2011 | K3: Q1 2012 | L3: Q2 2012 | M3: Q3 2012 | N3: Q4 2012 | O3: Q1 2013 | P3: Q2 2013 | Q3: Q3 2013 | R3: Q4 2013 | S3: Q1 2014 | T3: Q2 2014 | U3: Q3 2014 | V3: Q4 2014 | W3: Q1 2015 | X3: Q2 2015 | Y3: Q3 2015 | Z3: Q4 2015 | AA3: Q1 2016 | AB3: Q2 2016 | AC3: Q3 2016 | AD3: Q4 2016 | AE3: Q1 2017 | AF3: Q2 2017 | AG3: Q3 2017 | AH3: Q4 2017 | AI3: Q1 2018 | AJ3: Q2 2018 | AK3: Q3 2018 | AL3: Q4 2018 | AM3: Q1 2019 | AN3: Q2 2019 | AO3: Q3 2019 | AP3: Q4 2019 | AQ3: Q1 2020 | AR3: Q2 2020 | AS3: Q3 2020 | AT3: Q4 2020 | AU3: Q1 2021 | AV3: Q2 2021 | AW3: Q3 2021 | AX3: Q4 2021 | AY3: Q1 2022 | AZ3: Q2 2022 | BA3: Q3 2022 | BB3: Q4 2022 | BC3: Q1 2023 | BD3: Q2 2023 | BE3: Q3 2023 | BF3: Q4 2023 | BG3: Q1 2024 | BH3: Q2 2024 | BI3: Q3 2024 | BJ3: Q4 2024 | BK3: Q1 2025 | BL3: Q2 2025 | BM3: Q3 2025 | BN3: Q4 2025 | BO3: Q1 2026 | BP3: Q2 2026 | BQ3: Q3 2026 | BR3: Q4 2026 | CA3: 2010 | CB3: =CA3+1 -> 2011 | CC3: =CB3+1 -> 2012 | CD3: =CC3+1 -> 2013 | CE3: =CD3+1 -> 2014 | CF3: =CE3+1 -> 2015 | CG3: =CF3+1 -> 2016 | CH3: =CG3+1 -> 2017 | CI3: =CH3+1 -> 2018 | ... EX3: =EW3+1 -> 2085
B4: Consumables | AU4: 5964 | AV4: 5372 | AW4: 5544 | AX4: =22608-SUM(AU4:AW4) -> 5728 | AY4: 6110 | AZ4: 4993 | BA4: 4651 | BB4: =20624-SUM(AY4:BA4) -> 4870 | BC4: 4506 | BD4: 4433 | BE4: 4289 | BF4: =17597-SUM(BC4:BE4) -> 4369 | BG4: 4328 | BH4: 4363 | BI4: 4379 | BJ4: =17587-SUM(BG4:BI4) -> 4517 | BK4: 4354 | BL4: 4606 | BM4: 4679 | BN4: =18664-SUM(BK4:BM4) -> 5025 | BO4: 4722 | BP4: 5073 | BQ4: 5132 | CL4: =SUM(AU4:AX4) -> 22608 | CM4: =SUM(AY4:BB4) -> 20624 | CN4: =SUM(BC4:BF4) -> 17597 | CO4: =SUM(BG4:BJ4) -> 17587 | CP4: =SUM(BK4:BN4) -> 18664 | CQ4: =CP4*(1+CQ9) -> 20390.42 | CR4: =CQ4*(1+CR9) -> 22327.51 | CS4: =CR4*(1+CS9) -> 24381.641 | CT4: =CS4*(1+CT9) -> 26454.08 | CU4: =CT4*(1+CU9) -> 28570.407 | CV4: =CU4*(1+CV9) -> 30713.187 | CW4: =CV4*(1+CW9) -> 32709.544 | CX4: =CW4*(1+CX9) -> 34672.117 | ... CZ4: =CY4*(1+CZ9) -> 38408.038
B5: Instruments | AU5: 1892 | AV5: 1842 | AW5: 1816 | AX5: =7753-SUM(AU5:AW5) -> 2203 | AY5: 1907 | AZ5: 2010 | BA5: 1932 | BB5: =7924-SUM(AY5:BA5) -> 2075 | BC5: 1898 | BD5: 1838 | BE5: 1868 | BF5: =7646-SUM(BC5:BE5) -> 2042 | BG5: 1627 | BH5: 1800 | BI5: 1769 | BJ5: =7446-SUM(BG5:BI5) -> 2250 | BK5: 1626 | BL5: 1644 | BM5: 1811 | BN5: =7301-SUM(BK5:BM5) -> 2220 | BO5: 1555 | BP5: 1750 | BQ5: 1840 | CL5: =SUM(AU5:AX5) -> 7753 | CM5: =SUM(AY5:BB5) -> 7924 | CN5: =SUM(BC5:BF5) -> 7646 | CO5: =SUM(BG5:BJ5) -> 7446 | CP5: =SUM(BK5:BN5) -> 7301 | CQ5: =CP5*(1+CQ10) -> 7483.525 | CR5: =CQ5*(1+CR10) -> 7708.0307 | CS5: =CR5*(1+CS10) -> 8016.352 | CT5: =CS5*(1+CT10) -> 8296.9243 | CU5: =CT5*(1+CU10) -> 8545.832 | CV5: =CU5*(1+CV10) -> 8759.4778 | CW5: =CV5*(1+CW10) -> 8956.5661 | CX5: =CW5*(1+CX10) -> 9135.6974 | ... CZ5: =CY5*(1+CZ10) -> 9435.0057
B6: Services | AU6: 2050 | AV6: 2059 | AW6: 1970 | AX6: =8850-SUM(AU6:AW6) -> 2771 | AY6: 3801 | AZ6: 3967 | BA6: 4094 | BB6: =16367-SUM(AY6:BA6) -> 4505 | BC6: 4306 | BD6: 4416 | BE6: 4417 | BF6: =17614-SUM(BC6:BE6) -> 4475 | BG6: 4390 | BH6: 4378 | BI6: 4450 | BJ6: =17845-SUM(BG6:BI6) -> 4627 | BK6: 4384 | BL6: 4605 | BM6: 4633 | BN6: =18592-SUM(BK6:BM6) -> 4970 | BO6: 4728 | BP6: 5171 | BQ6: 5165 | CL6: =SUM(AU6:AX6) -> 8850 | CM6: =SUM(AY6:BB6) -> 16367 | CN6: =SUM(BC6:BF6) -> 17614 | CO6: =SUM(BG6:BJ6) -> 17845 | CP6: =SUM(BK6:BN6) -> 18592 | CQ6: =CP6*(1+CQ11) -> 20404.72 | CR6: =CQ6*(1+CR11) -> 22853.286 | CS6: =CR6*(1+CS11) -> 25824.214 | CT6: =CS6*(1+CT11) -> 28664.877 | CU6: =CT6*(1+CU11) -> 31531.365 | CV6: =CU6*(1+CV11) -> 34369.188 | CW6: =CV6*(1+CW11) -> 37118.723 | CX6: =CW6*(1+CX11) -> 39717.033 | ... CZ6: =CY6*(1+CZ11) -> 44415.558
B7: Ttl Revenue | AU7: =SUM(AU4:AU6) -> 9906 | AV7: =SUM(AV4:AV6) -> 9273 | AW7: =SUM(AW4:AW6) -> 9330 | AX7: =SUM(AX4:AX6) -> 10702 | AY7: =SUM(AY4:AY6) -> 11818 | AZ7: =SUM(AZ4:AZ6) -> 10970 | BA7: =SUM(BA4:BA6) -> 10677 | BB7: =SUM(BB4:BB6) -> 11450 | ... BQ7: =SUM(BQ4:BQ6) -> 12137 | CL7: =SUM(AU7:AX7) -> 39211 | CM7: =SUM(AY7:BB7) -> 44915 | CN7: =SUM(BC7:BF7) -> 42857 | CO7: =SUM(BG7:BJ7) -> 42878 | CP7: =SUM(BK7:BN7) -> 44557 | CQ7: =SUM(CQ4:CQ6) -> 48278.665 | CR7: =SUM(CR4:CR6) -> 52888.827 | CS7: =SUM(CS4:CS6) -> 58222.206 | CT7: =SUM(CT4:CT6) -> 63415.882 | CU7: =SUM(CU4:CU6) -> 68647.604 | CV7: =SUM(CV4:CV6) -> 73841.853 | CW7: =SUM(CW4:CW6) -> 78784.833 | CX7: =SUM(CX4:CX6) -> 83524.848 | ... CZ7: =SUM(CZ4:CZ6) -> 92258.602
B9: Consumables Growth Y/y | AX9: =AX4/AT4-1 -> #DIV/0! | AY9: =AY4/AU4-1 -> 0.024480215 | AZ9: =AZ4/AV4-1 -> -0.070551005 | BA9: =BA4/AW4-1 -> -0.16107504 | BB9: =BB4/AX4-1 -> -0.1497905 | BC9: =BC4/AY4-1 -> -0.26252046 | BD9: =BD4/AZ4-1 -> -0.11215702 | BE9: =BE4/BA4-1 -> -0.077832724 | ... BQ9: =BQ4/BM4-1 -> 0.096815559 | CM9: =CM4/CL4-1 -> -0.087756546 | CN9: =CN4/CM4-1 -> -0.14677075 | CO9: =CO4/CN4-1 -> -0.00056827868 | CP9: =CP4/CO4-1 -> 0.061238415 | CQ9: 0.0925 | CR9: 0.095 | CS9: 0.092 | CT9: 0.085 | CU9: 0.08 | CV9: 0.075 | CW9: 0.065 | CX9: 0.06 | CY9: 0.055 | CZ9: 0.05
B10: Instruments Growth Y/y | AX10: =AX5/AT5-1 -> #DIV/0! | AY10: =AY5/AU5-1 -> 0.0079281184 | AZ10: =AZ5/AV5-1 -> 0.091205212 | BA10: =BA5/AW5-1 -> 0.063876652 | BB10: =BB5/AX5-1 -> -0.058102587 | BC10: =BC5/AY5-1 -> -0.0047194546 | BD10: =BD5/AZ5-1 -> -0.085572139 | BE10: =BE5/BA5-1 -> -0.033126294 | ... BQ10: =BQ5/BM5-1 -> 0.016013252 | CM10: =CM5/CL5-1 -> 0.022055978 | CN10: =CN5/CM5-1 -> -0.035083291 | CO10: =CO5/CN5-1 -> -0.026157468 | CP10: =CP5/CO5-1 -> -0.019473543 | CQ10: 0.025 | CR10: 0.03 | CS10: 0.04 | CT10: 0.035 | CU10: 0.03 | CV10: 0.025 | CW10: 0.0225 | CX10: 0.02 | CY10: 0.0175 | CZ10: 0.015
B11: Services Growth Y/y | AX11: =AX6/AT6-1 -> #DIV/0! | AY11: =AY6/AU6-1 -> 0.85414634 | AZ11: =AZ6/AV6-1 -> 0.92666343 | BA11: =BA6/AW6-1 -> 1.0781726 | BB11: =BB6/AX6-1 -> 0.62576687 | BC11: =BC6/AY6-1 -> 0.13285977 | BD11: =BD6/AZ6-1 -> 0.11318377 | BE11: =BE6/BA6-1 -> 0.078895945 | ... BQ11: =BQ6/BM6-1 -> 0.1148284 | CM11: =CM6/CL6-1 -> 0.84937853 | CN11: =CN6/CM6-1 -> 0.076189894 | CO11: =CO6/CN6-1 -> 0.013114568 | CP11: =CP6/CO6-1 -> 0.041860465 | CQ11: 0.0975 | CR11: 0.12 | CS11: 0.13 | CT11: 0.11 | CU11: 0.1 | CV11: 0.09 | CW11: 0.08 | CX11: 0.07 | CY11: 0.06 | CZ11: 0.055
B12: Ttl Revenue Growth Y/y | AX12: =AX7/AT7-1 -> #DIV/0! | AY12: =AY7/AU7-1 -> 0.19301433 | AZ12: =AZ7/AV7-1 -> 0.18300442 | BA12: =BA7/AW7-1 -> 0.14437299 | BB12: =BB7/AX7-1 -> 0.069893478 | BC12: =BC7/AY7-1 -> -0.093755289 | BD12: =BD7/AZ7-1 -> -0.02579763 | BE12: =BE7/BA7-1 -> -0.0096469046 | ... BQ12: =BQ7/BM7-1 -> 0.091162456 | CM12: =CM7/CL7-1 -> 0.14546938 | CN12: =CN7/CM7-1 -> -0.045819882 | CO12: =CO7/CN7-1 -> 0.00049000163 | CP12: =CP7/CO7-1 -> 0.03915761 | CQ12: =CQ7/CP7-1 -> 0.083525933 | CR12: =CR7/CQ7-1 -> 0.09549067 | CS12: =CS7/CR7-1 -> 0.10084132 | CT12: =CT7/CS7-1 -> 0.089204371 | ... CZ12: =CZ7/CY7-1 -> 0.048694571
B14: Consumables % of Ttl Revenues | AU14: =AU4/AU7 -> 0.60205936 | AV14: =AV4/AV7 -> 0.57931629 | AW14: =AW4/AW7 -> 0.59421222 | AX14: =AX4/AX7 -> 0.53522706 | AY14: =AY4/AY7 -> 0.51700795 | AZ14: =AZ4/AZ7 -> 0.45515041 | BA14: =BA4/BA7 -> 0.43560925 | BB14: =BB4/BB7 -> 0.42532751 | ... BQ14: =BQ4/BQ7 -> 0.42283925 | CL14: =CL4/CL7 -> 0.5765729 | CM14: =CM4/CM7 -> 0.45917845 | CN14: =CN4/CN7 -> 0.41059804 | CO14: =CO4/CO7 -> 0.41016372 | CP14: =CP4/CP7 -> 0.41887919
B15: Instruments % of Ttl Revenues | AU15: =AU5/AU7 -> 0.19099536 | AV15: =AV5/AV7 -> 0.19864122 | AW15: =AW5/AW7 -> 0.19464094 | AX15: =AX5/AX7 -> 0.20584937 | AY15: =AY5/AY7 -> 0.16136402 | AZ15: =AZ5/AZ7 -> 0.18322698 | BA15: =BA5/BA7 -> 0.1809497 | BB15: =BB5/BB7 -> 0.18122271 | ... BQ15: =BQ5/BQ7 -> 0.15160254 | CL15: =CL5/CL7 -> 0.19772513 | CM15: =CM5/CM7 -> 0.17642213 | CN15: =CN5/CN7 -> 0.17840726 | CO15: =CO5/CO7 -> 0.17365549 | CP15: =CP5/CP7 -> 0.16385753
B16: Services % of Ttl Revenues | AU16: =AU6/AU7 -> 0.20694529 | AV16: =AV6/AV7 -> 0.22204249 | AW16: =AW6/AW7 -> 0.21114684 | AX16: =AX6/AX7 -> 0.25892357 | AY16: =AY6/AY7 -> 0.32162803 | AZ16: =AZ6/AZ7 -> 0.36162261 | BA16: =BA6/BA7 -> 0.38344104 | BB16: =BB6/BB7 -> 0.39344978 | ... BQ16: =BQ6/BQ7 -> 0.42555821 | CL16: =CL6/CL7 -> 0.22570197 | CM16: =CM6/CM7 -> 0.36439942 | CN16: =CN6/CN7 -> 0.4109947 | CO16: =CO6/CO7 -> 0.41618079 | CP16: =CP6/CP7 -> 0.41726328
B18: U.S. | AU18: 5101 | AV18: 4529 | AW18: 4662 | AX18: =19659-SUM(AU18:AW18) -> 5367 | AY18: 6323 | AZ18: 6032 | BA18: 5962 | BB18: =24594-SUM(AY18:BA18) -> 6277 | BC18: 5778 | BD18: 5714 | BE18: 5668 | BF18: =22764-SUM(BC18:BE18) -> 5604 | BG18: 5519 | BH18: 5529 | BI18: 5591 | BJ18: =22504-SUM(BG18:BI18) -> 5865 | BK18: 5513 | BL18: 5722 | BM18: 5689 | BN18: =23033-SUM(BK18:BM18) -> 6109 | BO18: 5705 | BP18: 6149 | CL18: =SUM(AU18:AX18) -> 19659 | CM18: =SUM(AY18:BB18) -> 24594 | CN18: =SUM(BC18:BF18) -> 22764 | CO18: =SUM(BG18:BJ18) -> 22504 | CP18: =SUM(BK18:BN18) -> 23033
B19: Euro | AU19: 2785 | AV19: 2695 | AW19: 2557 | AX19: =11134-SUM(AU19:AW19) -> 3097 | AY19: 3050 | AZ19: 2551 | BA19: 2406 | BB19: =10762-SUM(AY19:BA19) -> 2755 | BC19: 2601 | BD19: 2654 | BE19: 2643 | BF19: =10741-SUM(BC19:BE19) -> 2843 | BG19: 2619 | BH19: 2663 | BI19: 2686 | BJ19: =10857-SUM(BG19:BI19) -> 2889 | BK19: 2624 | BL19: 2830 | BM19: 3005 | BN19: =11826-SUM(BK19:BM19) -> 3367 | BO19: 2957 | BP19: 3311 | CL19: =SUM(AU19:AX19) -> 11134 | CM19: =SUM(AY19:BB19) -> 10762 | CN19: =SUM(BC19:BF19) -> 10741 | CO19: =SUM(BG19:BJ19) -> 10857 | CP19: =SUM(BK19:BN19) -> 11826
B20: APAC | AU20: 1709 | AV20: 1749 | AW20: 1836 | AX20: =7218-SUM(AU20:AW20) -> 1924 | AY20: 2064 | AZ20: 2042 | BA20: 1971 | BB20: =8115-SUM(AY20:BA20) -> 2038 | BC20: 1986 | BD20: 1902 | BE20: 1913 | BF20: =7873-SUM(BC20:BE20) -> 2072 | BG20: 1861 | BH20: 1971 | BI20: 1923 | BJ20: =7956-SUM(BG20:BI20) -> 2201 | BK20: 1891 | BL20: 1920 | BM20: 2013 | BN20: =8101-SUM(BK20:BM20) -> 2277 | BO20: 1970 | BP20: 2104 | CL20: =SUM(AU20:AX20) -> 7218 | CM20: =SUM(AY20:BB20) -> 8115 | CN20: =SUM(BC20:BF20) -> 7873 | CO20: =SUM(BG20:BJ20) -> 7956 | CP20: =SUM(BK20:BN20) -> 8101
B21: Other Regions | AU21: 311 | AV21: 300 | AW21: 275 | AX21: =1200-SUM(AU21:AW21) -> 314 | AY21: 381 | AZ21: 345 | BA21: 338 | BB21: =1444-SUM(AY21:BA21) -> 380 | BC21: 345 | BD21: 417 | BE21: 350 | BF21: =1479-SUM(BC21:BE21) -> 367 | BG21: 346 | BH21: 379 | BI21: 397 | BJ21: =1561-SUM(BG21:BI21) -> 439 | BK21: 336 | BL21: 383 | BM21: 415 | BN21: =1597-SUM(BK21:BM21) -> 463 | BO21: 373 | BP21: 430 | BQ21: 12137 | CL21: =SUM(AU21:AX21) -> 1200 | CM21: =SUM(AY21:BB21) -> 1444 | CN21: =SUM(BC21:BF21) -> 1479 | CO21: =SUM(BG21:BJ21) -> 1561 | CP21: =SUM(BK21:BN21) -> 1597
B22: Ttl Revenue | AU22: =SUM(AU18:AU21) -> 9906 | AV22: =SUM(AV18:AV21) -> 9273 | AW22: =SUM(AW18:AW21) -> 9330 | AX22: =SUM(AX18:AX21) -> 10702 | AY22: =SUM(AY18:AY21) -> 11818 | AZ22: =SUM(AZ18:AZ21) -> 10970 | BA22: =SUM(BA18:BA21) -> 10677 | BB22: =SUM(BB18:BB21) -> 11450 | ... BQ22: =SUM(BQ18:BQ21) -> 12137 | CL22: =SUM(AU22:AX22) -> 39211 | CM22: =SUM(AY22:BB22) -> 44915 | CN22: =SUM(BC22:BF22) -> 42857 | CO22: =SUM(BG22:BJ22) -> 42878 | CP22: =SUM(BK22:BN22) -> 44557
B24: U.S. Growth Y/y | AY24: =AY18/AU18-1 -> 0.23956087 | AZ24: =AZ18/AV18-1 -> 0.33186134 | BA24: =BA18/AW18-1 -> 0.27885028 | BB24: =BB18/AX18-1 -> 0.16955469 | BC24: =BC18/AY18-1 -> -0.086193263 | BD24: =BD18/AZ18-1 -> -0.052718833 | BE24: =BE18/BA18-1 -> -0.049312311 | BF24: =BF18/BB18-1 -> -0.10721682 | ... BQ24: =BQ18/BM18-1 -> -1 | CM24: =CM18/CL18-1 -> 0.25103006 | CN24: =CN18/CM18-1 -> -0.074408392 | CO24: =CO18/CN18-1 -> -0.011421543 | CP24: =CP18/CO18-1 -> 0.023506932
B25: Euro Growth Y/y | AY25: =AY19/AU19-1 -> 0.095152603 | AZ25: =AZ19/AV19-1 -> -0.053432282 | BA25: =BA19/AW19-1 -> -0.059053578 | BB25: =BB19/AX19-1 -> -0.11042945 | BC25: =BC19/AY19-1 -> -0.14721311 | BD25: =BD19/AZ19-1 -> 0.040376323 | BE25: =BE19/BA19-1 -> 0.098503741 | BF25: =BF19/BB19-1 -> 0.031941924 | ... BQ25: =BQ19/BM19-1 -> -1 | CM25: =CM19/CL19-1 -> -0.033411173 | CN25: =CN19/CM19-1 -> -0.0019513102 | CO25: =CO19/CN19-1 -> 0.010799739 | CP25: =CP19/CO19-1 -> 0.089251174
B26: APAC Growth Y/y | AY26: =AY20/AU20-1 -> 0.20772382 | AZ26: =AZ20/AV20-1 -> 0.1675243 | BA26: =BA20/AW20-1 -> 0.073529412 | BB26: =BB20/AX20-1 -> 0.059251559 | BC26: =BC20/AY20-1 -> -0.037790698 | BD26: =BD20/AZ20-1 -> -0.068560235 | BE26: =BE20/BA20-1 -> -0.029426687 | BF26: =BF20/BB20-1 -> 0.016683023 | ... BQ26: =BQ20/BM20-1 -> -1 | CM26: =CM20/CL20-1 -> 0.12427265 | CN26: =CN20/CM20-1 -> -0.029821319 | CO26: =CO20/CN20-1 -> 0.01054236 | CP26: =CP20/CO20-1 -> 0.018225239
B27: Other Regions Growth Y/y | AY27: =AY21/AU21-1 -> 0.22508039 | AZ27: =AZ21/AV21-1 -> 0.15 | BA27: =BA21/AW21-1 -> 0.22909091 | BB27: =BB21/AX21-1 -> 0.21019108 | BC27: =BC21/AY21-1 -> -0.094488189 | BD27: =BD21/AZ21-1 -> 0.20869565 | BE27: =BE21/BA21-1 -> 0.035502959 | BF27: =BF21/BB21-1 -> -0.034210526 | ... BQ27: =BQ21/BM21-1 -> 28.245783 | CM27: =CM21/CL21-1 -> 0.20333333 | CN27: =CN21/CM21-1 -> 0.024238227 | CO27: =CO21/CN21-1 -> 0.055442867 | CP27: =CP21/CO21-1 -> 0.02306214
B28: Ttl Revenue Growth Y/y | AY28: =AY22/AU22-1 -> 0.19301433 | AZ28: =AZ22/AV22-1 -> 0.18300442 | BA28: =BA22/AW22-1 -> 0.14437299 | BB28: =BB22/AX22-1 -> 0.069893478 | BC28: =BC22/AY22-1 -> -0.093755289 | BD28: =BD22/AZ22-1 -> -0.02579763 | BE28: =BE22/BA22-1 -> -0.0096469046 | BF28: =BF22/BB22-1 -> -0.049257642 | ... BQ28: =BQ22/BM22-1 -> 0.091260565 | CM28: =CM22/CL22-1 -> 0.14546938 | CN28: =CN22/CM22-1 -> -0.045819882 | CO28: =CO22/CN22-1 -> 0.00049000163 | CP28: =CP22/CO22-1 -> 0.03915761
B30: North America % of Ttl Revenues | AU30: =AU18/AU22 -> 0.51494044 | AV30: =AV18/AV22 -> 0.4884072 | AW30: =AW18/AW22 -> 0.49967846 | AX30: =AX18/AX22 -> 0.50149505 | AY30: =AY18/AY22 -> 0.53503131 | AZ30: =AZ18/AZ22 -> 0.54986326 | BA30: =BA18/BA22 -> 0.55839655 | BB30: =BB18/BB22 -> 0.54820961 | ... BQ30: =BQ18/BQ22 -> 0 | CL30: =CL18/CL22 -> 0.50136441 | CM30: =CM18/CM22 -> 0.54756763 | CN30: =CN18/CN22 -> 0.53116177 | CO30: =CO18/CO22 -> 0.52483791 | CP30: =CP18/CP22 -> 0.51693337
B31: Euro % of Ttl Revenues | AU31: =AU19/AU22 -> 0.28114274 | AV31: =AV19/AV22 -> 0.29062871 | AW31: =AW19/AW22 -> 0.27406217 | AX31: =AX19/AX22 -> 0.28938516 | AY31: =AY19/AY22 -> 0.25808089 | AZ31: =AZ19/AZ22 -> 0.2325433 | BA31: =BA19/BA22 -> 0.2253442 | BB31: =BB19/BB22 -> 0.24061135 | ... BQ31: =BQ19/BQ22 -> 0 | CL31: =CL19/CL22 -> 0.28395093 | CM31: =CM19/CM22 -> 0.23960815 | CN31: =CN19/CN22 -> 0.25062417 | CO31: =CO19/CO22 -> 0.25320677 | CP31: =CP19/CP22 -> 0.26541284
B32: APAC % of Ttl Revenues | AU32: =AU20/AU22 -> 0.1725217 | AV32: =AV20/AV22 -> 0.1886121 | AW32: =AW20/AW22 -> 0.19678457 | AX32: =AX20/AX22 -> 0.17977948 | AY32: =AY20/AY22 -> 0.17464884 | AZ32: =AZ20/AZ22 -> 0.18614403 | BA32: =BA20/BA22 -> 0.18460242 | BB32: =BB20/BB22 -> 0.17799127 | ... BQ32: =BQ20/BQ22 -> 0 | CL32: =CL20/CL22 -> 0.184081 | CM32: =CM20/CM22 -> 0.18067461 | CN32: =CN20/CN22 -> 0.18370395 | CO32: =CO20/CO22 -> 0.1855497 | CP32: =CP20/CP22 -> 0.18181206
B33: Other Regions % of Ttl Revenues | AU33: =AU21/AU22 -> 0.031395114 | AV33: =AV21/AV22 -> 0.03235199 | AW33: =AW21/AW22 -> 0.029474812 | AX33: =AX21/AX22 -> 0.02934031 | AY33: =AY21/AY22 -> 0.032238958 | AZ33: =AZ21/AZ22 -> 0.031449407 | BA33: =BA21/BA22 -> 0.031656832 | BB33: =BB21/BB22 -> 0.033187773 | ... BQ33: =BQ21/BQ22 -> 1 | CL33: =CL21/CL22 -> 0.030603657 | CM33: =CM21/CM22 -> 0.032149616 | CN33: =CN21/CN22 -> 0.034510115 | CO33: =CO21/CO22 -> 0.036405616 | CP33: =CP21/CP22 -> 0.035841731
B35: Bioscience | BK35: 993 | BL35: 1075 | BM35: 1023 | BN35: =4169-SUM(BK35:BM35) -> 1078 | BO35: 981 | BP35: 1060 | CN35: 4238 | CO35: 4192 | CP35: =SUM(BK35:BN35) -> 4169
B36: Genetic Sciences | BK36: 677 | BL36: 679 | BM36: 720 | BN36: =2870-SUM(BK36:BM36) -> 794 | BO36: 655 | BP36: 703 | CN36: 2816 | CO36: 2787 | CP36: =SUM(BK36:BN36) -> 2870
B37: Bioproduction | BK37: 671 | BL37: 745 | BM37: 817 | BN37: =3200-SUM(BK37:BM37) -> 967 | BO37: 893 | BP37: 941 | CN37: 2923 | CO37: 2652 | CP37: =SUM(BK37:BN37) -> 3200
B38: Other | BK38: 0 | BL38: 0 | BM38: 28 | BN38: =136-SUM(BK38:BM38) -> 108 | BO38: 107 | BP38: 112 | CN38: 1 | CO38: 0 | CP38: =SUM(BK38:BN38) -> 136
B39: Life Science Solutions | BK39: =SUM(BK35:BK38) -> 2341 | BL39: =SUM(BL35:BL38) -> 2499 | BM39: =SUM(BM35:BM38) -> 2588 | BN39: =SUM(BN35:BN38) -> 2947 | BO39: =SUM(BO35:BO38) -> 2636 | BP39: =SUM(BP35:BP38) -> 2816 | BQ39: =SUM(BQ35:BQ38) -> 0 | CN39: 9977 | CO39: 9631 | CP39: =SUM(BK39:BN39) -> 10375
B40: Chromatography & Spectrometry | BK40: 773 | BL40: 784 | BM40: 841 | BN40: =3360-SUM(BK40:BM40) -> 962 | BO40: 798 | BP40: 821 | CN40: 3329 | CO40: 3278 | CP40: =SUM(BK40:BN40) -> 3360
B41: Chemical Analysis | BK41: 286 | BL41: 292 | BM41: 320 | BN41: =1237-SUM(BK41:BM41) -> 339 | BO41: 285 | BP41: 318 | CN41: 1371 | CO41: 1315 | CP41: =SUM(BK41:BN41) -> 1237
B42: Electronic Microscopy | BK42: 659 | BL42: 652 | BM42: 732 | BN42: =2957-SUM(BK42:BM42) -> 914 | BO42: 633 | BP42: 707 | CN42: 2564 | CO42: 2870 | CP42: =SUM(BK42:BN42) -> 2957
B43: Analytical Instruments | BK43: =SUM(BK40:BK42) -> 1718 | BL43: =SUM(BL40:BL42) -> 1728 | BM43: =SUM(BM40:BM42) -> 1893 | BN43: =SUM(BN40:BN42) -> 2215 | BO43: =SUM(BO40:BO42) -> 1716 | BP43: =SUM(BP40:BP42) -> 1846 | BQ43: =SUM(BQ40:BQ42) -> 0 | CN43: 7263 | CO43: 7463 | CP43: =SUM(BK43:BN43) -> 7554
B44: Clinical Diagnostics | BK44: 263 | BL44: 276 | BM44: 283 | BN44: =1115-SUM(BK44:BM44) -> 293 | BO44: 271 | BP44: 290 | CN44: 1104 | CO44: 1063 | CP44: =SUM(BK44:BN44) -> 1115
B45: ImmunoDiagnostics | BK45: 217 | BL45: 234 | BM45: 230 | BN45: =912-SUM(BK45:BM45) -> 231 | BO45: 230 | BP45: 248 | CN45: 802 | CO45: 864 | CP45: =SUM(BK45:BN45) -> 912
B46: Microbiology | BK46: 152 | BL46: 159 | BM46: 162 | BN46: =645-SUM(BK46:BM46) -> 172 | BO46: 160 | BP46: 166 | CN46: 618 | CO46: 633 | CP46: =SUM(BK46:BN46) -> 645
B47: Transplant Diagnostics | BK47: 113 | BL47: 124 | BM47: 125 | BN47: =492-SUM(BK47:BM47) -> 130 | BO47: 121 | BP47: 134 | CN47: 393 | CO47: 454 | CP47: =SUM(BK47:BN47) -> 492
B48: Healthcare Channel | BK48: 474 | BL48: 407 | BM48: 444 | BN48: =1788-SUM(BK48:BM48) -> 463 | BO48: 430 | BP48: 442 | CN48: 1712 | CO48: 1764 | CP48: =SUM(BK48:BN48) -> 1788
B49: Elimination of Intrasegment Revenues | BK49: -72 | BL49: -65 | BM49: -70 | BN49: =-275-SUM(BK49:BM49) -> -68 | BO49: -71 | BP49: -75 | CN49: -222 | CO49: -266 | CP49: =SUM(BK49:BN49) -> -275
B50: Specialty Diagnostics | BK50: =SUM(BK44:BK49) -> 1147 | BL50: =SUM(BL44:BL49) -> 1135 | BM50: =SUM(BM44:BM49) -> 1174 | BN50: =SUM(BN44:BN49) -> 1221 | BO50: =SUM(BO44:BO49) -> 1141 | BP50: =SUM(BP44:BP49) -> 1205 | BQ50: =SUM(BQ44:BQ49) -> 0 | CN50: 4405 | CO50: 4512 | CP50: =SUM(BK50:BN50) -> 4677
B51: Lab Products | BK51: 582 | BL51: 601 | BM51: 594 | BN51: =2407-SUM(BK51:BM51) -> 630 | BO51: 569 | BP51: 608 | CN51: 2613 | CO51: 2525 | CP51: =SUM(BK51:BN51) -> 2407
B52: Research & Safety Channel | BK52: 1727 | BL52: 1883 | BM52: 1861 | BN52: =7440-SUM(BK52:BM52) -> 1969 | BO52: 1827 | BP52: 2036 | CN52: 6841 | CO52: 7019 | CP52: =SUM(BK52:BN52) -> 7440
B53: Pharma Services | BK53: 1607 | BL53: 1794 | BM53: 1722 | BN53: =7142-SUM(BK53:BM53) -> 2019 | BO53: 1741 | BP53: 1893 | CN53: 6806 | CO53: 6685 | CP53: =SUM(BK53:BN53) -> 7142
B54: Clinical Research | BK54: 1939 | BL54: 1955 | BM54: 2019 | BN54: =7915-SUM(BK54:BM54) -> 2002 | BO54: 2128 | BP54: 2396 | CN54: 7691 | CO54: 7836 | CP54: =SUM(BK54:BN54) -> 7915
B55: Elimination of Intrasegment Revenues | BK55: -214 | BL55: -238 | BM55: -226 | BN55: =-920-SUM(BK55:BM55) -> -242 | BO55: -229 | BP55: -240 | CN55: -910 | CO55: -907 | CP55: =SUM(BK55:BN55) -> -920
B56: Lab Products & Biopharma Services | BK56: =SUM(BK51:BK55) -> 5641 | BL56: =SUM(BL51:BL55) -> 5995 | BM56: =SUM(BM51:BM55) -> 5970 | BN56: =SUM(BN51:BN55) -> 6378 | BO56: =SUM(BO51:BO55) -> 6036 | BP56: =SUM(BP51:BP55) -> 6693 | BQ56: =SUM(BQ51:BQ55) -> 0 | CN56: 23041 | CO56: 23157 | CP56: =SUM(BK56:BN56) -> 23984
B57: Elimination of Intrasegment Revenues | BK57: -483 | BL57: -502 | BM57: -503 | BN57: =-2034-SUM(BK57:BM57) -> -546 | BO57: -524 | BP57: -565 | BQ57: 12137 | CN57: -1829 | CO57: -1885 | CP57: =SUM(BK57:BN57) -> -2034
B58: Ttl Revenue | BK58: =BK39+BK43+BK50+BK56+BK57 -> 10364 | BL58: =BL39+BL43+BL50+BL56+BL57 -> 10855 | BM58: =BM39+BM43+BM50+BM56+BM57 -> 11122 | BN58: =BN39+BN43+BN50+BN56+BN57 -> 12215 | BO58: =BO39+BO43+BO50+BO56+BO57 -> 11005 | BP58: =BP39+BP43+BP50+BP56+BP57 -> 11995 | BQ58: =BQ39+BQ43+BQ50+BQ56+BQ57 -> 12137 | CN58: 42857 | CO58: 42879 | CP58: =SUM(BK58:BN58) -> 44556
B60: Life Science Solutions Growth Y/y | BO60: =BO39/BK39-1 -> 0.12601452 | BP60: =BP39/BL39-1 -> 0.12685074 | BQ60: =BQ39/BM39-1 -> -1 | CO60: =CO39/CN39-1 -> -0.034679763 | CP60: =CP39/CO39-1 -> 0.077250545
B61: Analytical Instruments Growth Y/y | BO61: =BO43/BK43-1 -> -0.0011641444 | BP61: =BP43/BL43-1 -> 0.068287037 | BQ61: =BQ43/BM43-1 -> -1 | CO61: =CO43/CN43-1 -> 0.027536831 | CP61: =CP43/CO43-1 -> 0.012193488
B62: Specialty Diagnostics Growth Y/y | BO62: =BO50/BK50-1 -> -0.0052310375 | BP62: =BP50/BL50-1 -> 0.061674009 | BQ62: =BQ50/BM50-1 -> -1 | CO62: =CO50/CN50-1 -> 0.024290579 | CP62: =CP50/CO50-1 -> 0.036569149
B63: Lab Products & Biopharma Services Growth Y/y | BO63: =BO56/BK56-1 -> 0.070023046 | BP63: =BP56/BL56-1 -> 0.11643036 | BQ63: =BQ56/BM56-1 -> -1 | CO63: =CO56/CN56-1 -> 0.0050345037 | CP63: =CP56/CO56-1 -> 0.035712743
B64: Ttl Revenue Growth Y/y | BO64: =BO58/BK58-1 -> 0.061848707 | BP64: =BP58/BL58-1 -> 0.10502073 | BQ64: =BQ58/BM58-1 -> 0.091260565 | CO64: =CO58/CN58-1 -> 0.00051333504 | CP64: =CP58/CO58-1 -> 0.039110054
B66: Life Science Solutions % of Ttl Revenues | BK66: =BK39/BK58 -> 0.22587804 | BL66: =BL39/BL58 -> 0.23021649 | BM66: =BM39/BM58 -> 0.23269196 | BN66: =BN39/BN58 -> 0.24126074 | BO66: =BO39/BO58 -> 0.23952749 | BP66: =BP39/BP58 -> 0.23476449 | BQ66: =BQ39/BQ58 -> 0 | CN66: =CN39/CN58 -> 0.23279744 | CO66: =CO39/CO58 -> 0.22460878 | CP66: =CP39/CP58 -> 0.23285304
B67: Analytical Instruments % of Ttl Revenues | BK67: =BK43/BK58 -> 0.16576611 | BL67: =BL43/BL58 -> 0.15918931 | BM67: =BM43/BM58 -> 0.1702032 | BN67: =BN43/BN58 -> 0.18133442 | BO67: =BO43/BO58 -> 0.15592912 | BP67: =BP43/BP58 -> 0.15389746 | BQ67: =BQ43/BQ58 -> 0 | CN67: =CN43/CN58 -> 0.16947056 | CO67: =CO43/CO58 -> 0.1740479 | CP67: =CP43/CP58 -> 0.16953946
B68: Specialty Diagnostics % of Ttl Revenues | BK68: =BK50/BK58 -> 0.11067156 | BL68: =BL50/BL58 -> 0.10456011 | BM68: =BM50/BM58 -> 0.10555655 | BN68: =BN50/BN58 -> 0.099959067 | BO68: =BO50/BO58 -> 0.10368015 | BP68: =BP50/BP58 -> 0.10045852 | BQ68: =BQ50/BQ58 -> 0 | CN68: =CN50/CN58 -> 0.10278368 | CO68: =CO50/CO58 -> 0.10522633 | CP68: =CP50/CP58 -> 0.10496903
B69: Lab Products & Biopharma Services % of Ttl Revenues | BK69: =BK56/BK58 -> 0.54428792 | BL69: =BL56/BL58 -> 0.55228006 | BM69: =BM56/BM58 -> 0.53677396 | BN69: =BN56/BN58 -> 0.5221449 | BO69: =BO56/BO58 -> 0.54847796 | BP69: =BP56/BP58 -> 0.55798249 | BQ69: =BQ56/BQ58 -> 0 | CN69: =CN56/CN58 -> 0.53762513 | CO69: =CO56/CO58 -> 0.54005457 | CP69: =CP56/CP58 -> 0.53828889
B71: Revenues | C71: 2626.9 | D71: 2595.7 | E71: 2628.7 | F71: 2541.8 | G71: 2721.4 | H71: 2854 | I71: 2932.9 | J71: 3050.5 | K71: 3056.8 | L71: 3108.1 | M71: 3085.7 | N71: 3259.3 | O71: 3191.5 | P71: 3240.1 | Q71: 3191.8 | R71: 3466.9 | S71: 3903.5 | T71: 4321.9 | U71: 4171.4 | V71: 4492.8 | W71: 3918.8 | X71: 4270.9 | Y71: 4123.2 | Z71: 4652.1 | AA71: 4294.8 | AB71: 4535.2 | AC71: 4490.9 | AD71: 4953.1 | AE71: 4765 | AF71: 4990 | AG71: 5116 | AH71: 6047 | AI71: 5853 | AJ71: 6078 | AK71: 5920 | AL71: 6507 | AM71: 6125 | AN71: 6316 | AO71: 6272 | AP71: 6829 | AQ71: 6230 | AR71: 6917 | AS71: 8521 | AT71: 10550 | AU71: 9906 | AV71: 9273 | AW71: 9330 | AX71: 10702 | AY71: 11818 | AZ71: 10970 | BA71: 10677 | BB71: 11450 | BC71: 10710 | BD71: 10687 | BE71: 10574 | BF71: 10886 | BG71: 10345 | BH71: 10541 | BI71: 10598 | BJ71: 11395 | BK71: 10364 | BL71: 10855 | BM71: 11122 | BN71: 12215 | BO71: 11005 | BP71: 11994 | BQ71: =BQ58 -> 12137 | CA71: =SUM(C71:F71) -> 10393.1 | CB71: =SUM(G71:J71) -> 11558.8 | CC71: =SUM(K71:N71) -> 12509.9 | CD71: =SUM(O71:R71) -> 13090.3 | CE71: =SUM(S71:V71) -> 16889.6 | CF71: =SUM(W71:Z71) -> 16965 | CG71: =SUM(AA71:AD71) -> 18274 | CH71: =SUM(AE71:AH71) -> 20918 | CI71: =SUM(AI71:AL71) -> 24358 | CJ71: =SUM(AM71:AP71) -> 25542 | CK71: =SUM(AQ71:AT71) -> 32218 | CL71: =SUM(AU71:AX71) -> 39211 | CM71: =SUM(AY71:BB71) -> 44915 | CN71: =SUM(BC71:BF71) -> 42857 | CO71: =SUM(BG71:BJ71) -> 42879 | CP71: =SUM(BK71:BN71) -> 44556 | CQ71: =CQ7 -> 48278.665 | CR71: =CR7 -> 52888.827 | CS71: =CS7 -> 58222.206 | CT71: =CT7 -> 63415.882 | CU71: =CU7 -> 68647.604 | CV71: =CV7 -> 73841.853 | CW71: =CW7 -> 78784.833 | CX71: =CX7 -> 83524.848 | ... CZ71: =CZ7 -> 92258.602
B72: COGS | C72: 1560.5 | D72: 1546.8 | E72: 1567.2 | F72: 1457.1 | G72: 1601.1 | H72: 1693 | I72: 1714 | J72: 1756.7 | K72: 1767.1 | L72: 1786.8 | M72: 1787.3 | N72: 1873.2 | O72: 1855.2 | P72: 1876.9 | Q72: 1843.9 | R72: 1985.2 | S72: 2283.5 | T72: 2475.4 | U72: 2237.8 | V72: 2400.9 | W72: 2096.3 | X72: 2329.1 | Y72: 2239.9 | Z72: 2543.7 | AA72: 2336.9 | AB72: 2456.7 | AC72: 2437 | AD72: 2671.4 | AE72: 2572 | AF72: 2706 | AG72: 2816 | AH72: 3376 | AI72: 3273 | AJ72: 3340 | AK72: 3305 | AL72: 3583 | AM72: 3418 | AN72: 3493 | AO72: 3509 | AP72: 3794 | AQ72: 3490 | AR72: 3540 | AS72: 4190 | AT72: 4994 | AU72: 4697 | AV72: 4749 | AW72: 4679 | AX72: 5448 | AY72: 6354 | AZ72: 6371 | BA72: 6375 | BB72: 6844 | BC72: 6570 | BD72: 6436 | BE72: 6258 | BF72: 6493 | BG72: 6140 | BH72: 6194 | BI72: 6270 | BJ72: 6573 | BK72: 6129 | BL72: 6446 | BM72: 6539 | BN72: 7204 | BO72: 6575 | BP72: 7112 | BQ72: 6945 | CA72: =SUM(C72:F72) -> 6131.6 | CB72: =SUM(G72:J72) -> 6764.8 | CC72: =SUM(K72:N72) -> 7214.4 | CD72: =SUM(O72:R72) -> 7561.2 | CE72: =SUM(S72:V72) -> 9397.6 | CF72: =SUM(W72:Z72) -> 9209 | CG72: =SUM(AA72:AD72) -> 9902 | CH72: =SUM(AE72:AH72) -> 11470 | CI72: =SUM(AI72:AL72) -> 13501 | CJ72: =SUM(AM72:AP72) -> 14214 | CK72: =SUM(AQ72:AT72) -> 16214 | CL72: =SUM(AU72:AX72) -> 19573 | CM72: =SUM(AY72:BB72) -> 25944 | CN72: =SUM(BC72:BF72) -> 25757 | CO72: =SUM(BG72:BJ72) -> 25177 | CP72: =SUM(BK72:BN72) -> 26318 | CQ72: =CQ71*(1-CQ89) -> 28516.876 | CR72: =CR71*(1-CR89) -> 31204.408 | CS72: =CS71*(1-CS89) -> 34059.991 | CT72: =CT71*(1-CT89) -> 36781.211 | CU72: =CU71*(1-CU89) -> 39643.991 | CV72: =CV71*(1-CV89) -> 42459.065 | CW72: =CW71*(1-CW89) -> 45104.317 | CX72: =CX71*(1-CX89) -> 47609.163 | ... CZ72: =CZ71*(1-CZ89) -> 52587.403
B73: GP | C73: =C71-C72 -> 1066.4 | D73: =D71-D72 -> 1048.9 | E73: =E71-E72 -> 1061.5 | F73: =F71-F72 -> 1084.7 | G73: =G71-G72 -> 1120.3 | H73: =H71-H72 -> 1161 | I73: =I71-I72 -> 1218.9 | J73: =J71-J72 -> 1293.8 | ... BQ73: =BQ71-BQ72 -> 5192 | CA73: =SUM(C73:F73) -> 4261.5 | CB73: =SUM(G73:J73) -> 4794 | CC73: =SUM(K73:N73) -> 5295.5 | CD73: =SUM(O73:R73) -> 5529.1 | CE73: =SUM(S73:V73) -> 7492 | CF73: =SUM(W73:Z73) -> 7756 | CG73: =SUM(AA73:AD73) -> 8372 | CH73: =SUM(AE73:AH73) -> 9448 | CI73: =SUM(AI73:AL73) -> 10857 | CJ73: =SUM(AM73:AP73) -> 11328 | CK73: =SUM(AQ73:AT73) -> 16004 | CL73: =SUM(AU73:AX73) -> 19638 | CM73: =SUM(AY73:BB73) -> 18971 | CN73: =SUM(BC73:BF73) -> 17100 | CO73: =SUM(BG73:BJ73) -> 17702 | CP73: =SUM(BK73:BN73) -> 18238 | CQ73: =CQ71*CQ89 -> 19761.789 | CR73: =CR71*CR89 -> 21684.419 | CS73: =CS71*CS89 -> 24162.216 | CT73: =CT71*CT89 -> 26634.67 | CU73: =CU71*CU89 -> 29003.613 | CV73: =CV71*CV89 -> 31382.787 | CW73: =CW71*CW89 -> 33680.516 | CX73: =CX71*CX89 -> 35915.685 | ... CZ73: =CZ71*CZ89 -> 39671.199
B74: SG&A | C74: 698.3 | D74: 673.2 | E74: 677 | F74: 680.3 | G74: 708.7 | H74: 772.9 | I74: 804.5 | J74: 820.4 | K74: 824.3 | L74: 835 | M74: 839 | N74: 856.6 | O74: 829.5 | P74: 869.6 | Q74: 848.5 | R74: 898.7 | S74: 1177 | T74: 1253.8 | U74: 1228.7 | V74: 1236.6 | W74: 1137.4 | X74: 1151 | Y74: 1133.3 | Z74: 1190.3 | AA74: 1212.9 | AB74: 1223.1 | AC74: 1274.6 | AD74: 1260.4 | AE74: 1334 | AF74: 1291 | AG74: 1400 | AH74: 1479 | AI74: 1515 | AJ74: 1542 | AK74: 1490 | AL74: 1510 | AM74: 1528 | AN74: 1565 | AO74: 1539 | AP74: 1512 | AQ74: 1551 | AR74: 1710 | AS74: 1592 | AT74: 2077 | AU74: 1826 | AV74: 1899 | AW74: 2004 | AX74: 2278 | AY74: 2277 | AZ74: 2209 | BA74: 2208 | BB74: 2299 | BC74: 2119 | BD74: 2145 | BE74: 2049 | BF74: 2132 | BG74: 2183 | BH74: 2111 | BI74: 2098 | BJ74: 2203 | BK74: 2078 | BL74: 2140 | BM74: 2162 | BN74: 2352 | BO74: 2181 | BP74: 2333 | BQ74: =1863+519 -> 2382 | CA74: =SUM(C74:F74) -> 2728.8 | CB74: =SUM(G74:J74) -> 3106.5 | CC74: =SUM(K74:N74) -> 3354.9 | CD74: =SUM(O74:R74) -> 3446.3 | CE74: =SUM(S74:V74) -> 4896.1 | CF74: =SUM(W74:Z74) -> 4612 | CG74: =SUM(AA74:AD74) -> 4971 | CH74: =SUM(AE74:AH74) -> 5504 | CI74: =SUM(AI74:AL74) -> 6057 | CJ74: =SUM(AM74:AP74) -> 6144 | CK74: =SUM(AQ74:AT74) -> 6930 | CL74: =SUM(AU74:AX74) -> 8007 | CM74: =SUM(AY74:BB74) -> 8993 | CN74: =SUM(BC74:BF74) -> 8445 | CO74: =SUM(BG74:BJ74) -> 8595 | CP74: =SUM(BK74:BN74) -> 8732 | CQ74: =CQ71*CQ90 -> 9461.5608 | CR74: =CR71*CR90 -> 10365.052 | CS74: =CS71*CS90 -> 11410.277 | CT74: =CT71*CT90 -> 12428.124 | CU74: =CU71*CU90 -> 13453.427 | CV74: =CV71*CV90 -> 14471.386 | CW74: =CW71*CW90 -> 15440.102 | CX74: =CX71*CX90 -> 16369.041 | ... CZ74: =CZ71*CZ90 -> 18080.665
B75: R&D | C75: 66.1 | D75: 69.6 | E75: 71.5 | F75: 77.2 | G75: 74.8 | H75: 83.2 | I75: 86.8 | J75: 95.4 | K75: 91.7 | L75: 94.2 | M75: 92 | N75: 98.5 | O75: 98.2 | P75: 96.7 | Q75: 95.9 | R75: 104.7 | S75: 149.7 | T75: 183.7 | U75: 175.2 | V75: 182.5 | W75: 165.8 | X75: 174.6 | Y75: 171.6 | Z75: 180 | AA75: 176.5 | AB75: 182.4 | AC75: 183.3 | AD75: 211.8 | AE75: 215 | AF75: 222 | AG75: 217 | AH75: 233 | AI75: 234 | AJ75: 242 | AK75: 240 | AL75: 251 | AM75: 248 | AN75: 246 | AO75: 247 | AP75: 262 | AQ75: 245 | AR75: 264 | AS75: 296 | AT75: 376 | AU75: 320 | AV75: 343 | AW75: 351 | AX75: 392 | AY75: 364 | AZ75: 365 | BA75: 351 | BB75: 391 | BC75: 346 | BD75: 345 | BE75: 319 | BF75: 327 | BG75: 331 | BH75: 339 | BI75: 346 | BJ75: 374 | BK75: 342 | BL75: 352 | BM75: 346 | BN75: 357 | BO75: 336 | BP75: 364 | BQ75: 348 | CA75: =SUM(C75:F75) -> 284.4 | CB75: =SUM(G75:J75) -> 340.2 | CC75: =SUM(K75:N75) -> 376.4 | CD75: =SUM(O75:R75) -> 395.5 | CE75: =SUM(S75:V75) -> 691.1 | CF75: =SUM(W75:Z75) -> 692 | CG75: =SUM(AA75:AD75) -> 754 | CH75: =SUM(AE75:AH75) -> 887 | CI75: =SUM(AI75:AL75) -> 967 | CJ75: =SUM(AM75:AP75) -> 1003 | CK75: =SUM(AQ75:AT75) -> 1181 | CL75: =SUM(AU75:AX75) -> 1406 | CM75: =SUM(AY75:BB75) -> 1471 | CN75: =SUM(BC75:BF75) -> 1337 | CO75: =SUM(BG75:BJ75) -> 1390 | CP75: =SUM(BK75:BN75) -> 1397 | CQ75: =CQ71*CQ91 -> 1513.7197 | CR75: =CR71*CR91 -> 1586.6648 | CS75: =CS71*CS91 -> 1746.6662 | CT75: =CT71*CT91 -> 1839.0606 | CU75: =CU71*CU91 -> 1990.7805 | CV75: =CV71*CV91 -> 2067.5719 | CW75: =CW71*CW91 -> 2205.9753 | CX75: =CX71*CX91 -> 2255.1709 | ... CZ75: =CZ71*CZ91 -> 2398.7236
B76: Restructuring & Other | C76: 17.4 | D76: 8.2 | E76: 10.3 | F76: 24.3 | G76: 15.3 | H76: 39.8 | I76: 11.6 | J76: 29.8 | K76: 12.2 | L76: 24.3 | M76: 15.2 | N76: 30.4 | O76: 21.5 | P76: 21.5 | Q76: 11.4 | R76: 23.3 | S76: -582.2 | T76: 60.9 | U76: -110.6 | V76: 33.7 | W76: 32 | X76: 20.4 | Y76: 15.5 | Z76: 48.1 | AA76: 50.6 | AB76: 35.4 | AC76: 54.9 | AD76: 48.1 | AE76: 24 | AF76: 22 | AG76: 49 | AH76: 2 | AI76: 45 | AJ76: 17 | AK76: -27 | AL76: 15 | AM76: 11 | AN76: -484 | AO76: 31 | AP76: 29 | AQ76: 38 | AR76: 12 | AS76: 17 | AT76: 32 | AU76: 14 | AV76: 119 | AW76: 18 | AX76: 46 | AY76: 2 | AZ76: 24 | BA76: 33 | BB76: 55 | BC76: 112 | BD76: 183 | BE76: 84 | BF76: 80 | BG76: 29 | BH76: 77 | BI76: 45 | BJ76: 228 | BK76: 98 | BL76: 82 | BM76: 135 | BN76: 47 | BO76: 49 | BP76: 98 | BQ76: 199 | CA76: =SUM(C76:F76) -> 60.2 | CB76: =SUM(G76:J76) -> 96.5 | CC76: =SUM(K76:N76) -> 82.1 | CD76: =SUM(O76:R76) -> 77.7 | CE76: =SUM(S76:V76) -> -598.2 | CF76: =SUM(W76:Z76) -> 116 | CG76: =SUM(AA76:AD76) -> 189 | CH76: =SUM(AE76:AH76) -> 97 | CI76: =SUM(AI76:AL76) -> 50 | CJ76: =SUM(AM76:AP76) -> -413 | CK76: =SUM(AQ76:AT76) -> 99 | CL76: =SUM(AU76:AX76) -> 197 | CM76: =SUM(AY76:BB76) -> 114 | CN76: =SUM(BC76:BF76) -> 459 | CO76: =SUM(BG76:BJ76) -> 379 | CP76: =SUM(BK76:BN76) -> 362 | CQ76: =CQ71*CQ92 -> 579.34398 | CR76: =CR71*CR92 -> 528.88827 | CS76: =CS71*CS92 -> 523.99986 | CT76: =CT71*CT92 -> 515.22913 | CU76: =CU71*CU92 -> 557.73482 | CV76: =CV71*CV92 -> 599.93605 | CW76: =CW71*CW92 -> 551.49383 | CX76: =CX71*CX92 -> 584.67393 | ... CZ76: =CZ71*CZ92 -> 553.55161
B77: Operating Income | C77: =C73-SUM(C74:C76) -> 284.6 | D77: =D73-SUM(D74:D76) -> 297.9 | E77: =E73-SUM(E74:E76) -> 302.7 | F77: =F73-SUM(F74:F76) -> 302.9 | G77: =G73-SUM(G74:G76) -> 321.5 | H77: =H73-SUM(H74:H76) -> 265.1 | I77: =I73-SUM(I74:I76) -> 316 | J77: =J73-SUM(J74:J76) -> 348.2 | ... BQ77: =BQ73-SUM(BQ74:BQ76) -> 2263 | CA77: =SUM(C77:F77) -> 1188.1 | CB77: =SUM(G77:J77) -> 1250.8 | CC77: =SUM(K77:N77) -> 1482.1 | CD77: =SUM(O77:R77) -> 1609.6 | CE77: =SUM(S77:V77) -> 2503 | CF77: =SUM(W77:Z77) -> 2336 | CG77: =SUM(AA77:AD77) -> 2458 | CH77: =SUM(AE77:AH77) -> 2960 | CI77: =SUM(AI77:AL77) -> 3783 | CJ77: =SUM(AM77:AP77) -> 4594 | CK77: =SUM(AQ77:AT77) -> 7794 | CL77: =SUM(AU77:AX77) -> 10028 | CM77: =SUM(AY77:BB77) -> 8393 | CN77: =SUM(BC77:BF77) -> 6859 | CO77: =SUM(BG77:BJ77) -> 7338 | CP77: =SUM(BK77:BN77) -> 7747 | CQ77: =CQ73-SUM(CQ74:CQ76) -> 8207.165 | CR77: =CR73-SUM(CR74:CR76) -> 9203.8144 | CS77: =CS73-SUM(CS74:CS76) -> 10481.273 | CT77: =CT73-SUM(CT74:CT76) -> 11852.257 | CU77: =CU73-SUM(CU74:CU76) -> 13001.671 | CV77: =CV73-SUM(CV74:CV76) -> 14243.894 | CW77: =CW73-SUM(CW74:CW76) -> 15482.945 | CX77: =CX73-SUM(CX74:CX76) -> 16706.799 | ... CZ77: =CZ73-SUM(CZ74:CZ76) -> 18638.258
B78: Interest Income | C78: 0 | D78: 0 | E78: 0 | F78: 0 | G78: 0 | H78: 0 | I78: 0 | J78: 0 | K78: 0 | L78: 0 | M78: 0 | N78: 0 | O78: 0 | P78: 0 | Q78: 0 | R78: 0 | S78: 0 | T78: 0 | U78: 0 | V78: 0 | W78: 0 | X78: 0 | Y78: 0 | Z78: 0 | AA78: 0 | AB78: 0 | AC78: 0 | AD78: 0 | AE78: 0 | AF78: 0 | AG78: 0 | AH78: 0 | AI78: 0 | AJ78: 0 | AK78: 0 | AL78: 0 | AM78: 0 | AN78: 0 | AO78: 0 | AP78: 0 | AQ78: 0 | AR78: 0 | AS78: 0 | AT78: 0 | AU78: 12 | AV78: 11 | AW78: 9 | AX78: =43-SUM(AU78:AW78) -> 11 | AY78: 18 | AZ78: 36 | BA78: 68 | BB78: =272-SUM(AY78:BA78) -> 150 | BC78: 146 | BD78: 178 | BE78: 246 | BF78: =879-SUM(BC78:BE78) -> 309 | BG78: 279 | BH78: 295 | BI78: 277 | BJ78: =1078-SUM(BG78:BI78) -> 227 | BK78: 203 | BL78: 297 | BM78: 234 | BN78: =993-SUM(BK78:BM78) -> 259 | BO78: 233 | BP78: 207 | BQ78: 252 | CA78: =SUM(C78:F78) -> 0 | CB78: =SUM(G78:J78) -> 0 | CC78: =SUM(K78:N78) -> 0 | CD78: =SUM(O78:R78) -> 0 | CE78: =SUM(S78:V78) -> 0 | CF78: =SUM(W78:Z78) -> 0 | CG78: =SUM(AA78:AD78) -> 0 | CH78: =SUM(AE78:AH78) -> 0 | CI78: =SUM(AI78:AL78) -> 0 | CJ78: =SUM(AM78:AP78) -> 0 | CK78: =SUM(AQ78:AT78) -> 0 | CL78: =SUM(AU78:AX78) -> 43 | CM78: =SUM(AY78:BB78) -> 272 | CN78: =SUM(BC78:BF78) -> 879 | CO78: =SUM(BG78:BJ78) -> 1078 | CP78: =SUM(BK78:BN78) -> 993 | CQ78: =(BP97+BP98)*($DJ$97) -> 355.6 | CR78: =(CQ97)*($DJ$97) -> 908.82741 | CS78: =(CR97)*($DJ$97) -> 1584.9131 | CT78: =(CS97)*($DJ$97) -> 2397.1489 | CU78: =(CT97)*($DJ$97) -> 3377.9805 | CV78: =(CU97)*($DJ$97) -> 4523.2277 | CW78: =(CV97)*($DJ$97) -> 5852.0615 | CX78: =(CW97)*($DJ$97) -> 7377.8813 | CY78: =(CX97)*($DJ$97) -> 9114.1979 | CZ78: =(CY97)*($DJ$97) -> 11058.193
B79: Interest Expenses | C79: 0 | D79: 0 | E79: 0 | F79: 0 | G79: 0 | H79: 0 | I79: 0 | J79: 0 | K79: 0 | L79: 0 | M79: 0 | N79: 0 | O79: 0 | P79: 0 | Q79: 0 | R79: 0 | S79: 0 | T79: 0 | U79: 0 | V79: 0 | W79: 0 | X79: 0 | Y79: 0 | Z79: 0 | AA79: 0 | AB79: 0 | AC79: 0 | AD79: 0 | AE79: 0 | AF79: 0 | AG79: 0 | AH79: 0 | AI79: 0 | AJ79: 0 | AK79: 0 | AL79: 0 | AM79: 0 | AN79: 0 | AO79: 0 | AP79: 0 | AQ79: 0 | AR79: 0 | AS79: 0 | AT79: 0 | AU79: -125 | AV79: -122 | AW79: -128 | AX79: =-536-SUM(AU79:AW79) -> -161 | AY79: -136 | AZ79: -148 | BA79: -173 | BB79: =-726-SUM(AY79:BA79) -> -269 | BC79: -300 | BD79: -326 | BE79: -359 | BF79: =-1375-SUM(BC79:BE79) -> -390 | BG79: -363 | BH79: -354 | BI79: -356 | BJ79: =-1390-SUM(BG79:BI79) -> -317 | BK79: -303 | BL79: -404 | BM79: -347 | BN79: =-1419-SUM(BK79:BM79) -> -365 | BO79: -354 | BP79: -401 | BQ79: -417 | CA79: =SUM(C79:F79) -> 0 | CB79: =SUM(G79:J79) -> 0 | CC79: =SUM(K79:N79) -> 0 | CD79: =SUM(O79:R79) -> 0 | CE79: =SUM(S79:V79) -> 0 | CF79: =SUM(W79:Z79) -> 0 | CG79: =SUM(AA79:AD79) -> 0 | CH79: =SUM(AE79:AH79) -> 0 | CI79: =SUM(AI79:AL79) -> 0 | CJ79: =SUM(AM79:AP79) -> 0 | CK79: =SUM(AQ79:AT79) -> 0 | CL79: =SUM(AU79:AX79) -> -536 | CM79: =SUM(AY79:BB79) -> -726 | CN79: =SUM(BC79:BF79) -> -1375 | CO79: =SUM(BG79:BJ79) -> -1390 | CP79: =SUM(BK79:BN79) -> -1419 | CQ79: =BP116*-($DE$114) -> -1763.145 | CR79: =CQ116*-($DE$114) -> -1332.3085 | CS79: =CR116*-($DE$114) -> -1272.3546 | CT79: =CS116*-($DE$114) -> -1215.0986 | CU79: =CT116*-($DE$114) -> -1160.4192 | CV79: =CU116*-($DE$114) -> -1108.2003 | CW79: =CV116*-($DE$114) -> -1058.3313 | CX79: =CW116*-($DE$114) -> -1010.7064 | CY79: =CX116*-($DE$114) -> -965.22462 | CZ79: =CY116*-($DE$114) -> -921.78951
B80: Other Income | C80: -24.9 | D80: -36.8 | E80: -15.4 | F80: -23.3 | G80: -22.5 | H80: -10.3 | I80: -49.6 | J80: -35.6 | K80: -50.4 | L80: -49.4 | M80: -55.8 | N80: -57.1 | O80: -44.2 | P80: -95.4 | Q80: -73.1 | R80: -77.4 | S80: -101.1 | T80: -111.6 | U80: -101.1 | V80: -102 | W80: -105.3 | X80: -92.2 | Y80: -94.8 | Z80: -107.7 | AA80: -94.9 | AB80: -116.5 | AC80: -113.2 | AD80: -109.4 | AE80: -117 | AF80: -123 | AG80: -154 | AH80: -137 | AI80: -152 | AJ80: -131 | AK80: -102 | AL80: -136 | AM80: -103 | AN80: -103 | AO80: -124 | AP80: -192 | AQ80: -78 | AR80: -138 | AS80: -174 | AT80: -174 | AU80: -183 | AV80: -3 | AW80: 14 | AX80: =-694-SUM(AU80:AW80) -> -522 | AY80: -163 | AZ80: 28 | BA80: -4 | BB80: =-104-SUM(AY80:BA80) -> 35 | BC80: -46 | BD80: 0 | BE80: 14 | BF80: =-65-SUM(BC80:BE80) -> -33 | BG80: 10 | BH80: 5 | BI80: -16 | BJ80: =12-SUM(BG80:BI80) -> 13 | BK80: 3 | BL80: -19 | BM80: -2 | BN80: =-12-SUM(BK80:BM80) -> 6 | BO80: -9 | BP80: 31 | BQ80: -10 | CA80: =SUM(C80:F80) -> -100.4 | CB80: =SUM(G80:J80) -> -118 | CC80: =SUM(K80:N80) -> -212.7 | CD80: =SUM(O80:R80) -> -290.1 | CE80: =SUM(S80:V80) -> -415.8 | CF80: =SUM(W80:Z80) -> -400 | CG80: =SUM(AA80:AD80) -> -434 | CH80: =SUM(AE80:AH80) -> -531 | CI80: =SUM(AI80:AL80) -> -521 | CJ80: =SUM(AM80:AP80) -> -522 | CK80: =SUM(AQ80:AT80) -> -564 | CL80: =SUM(AU80:AX80) -> -694 | CM80: =SUM(AY80:BB80) -> -104 | CN80: =SUM(BC80:BF80) -> -65 | CO80: =SUM(BG80:BJ80) -> 12 | CP80: =SUM(BK80:BN80) -> -12 | CQ80: 0 | CR80: 0 | CS80: 0 | CT80: 0 | CU80: 0 | CV80: 0 | CW80: 0 | CX80: 0 | CY80: 0 | CZ80: 0
B81: Pretax Income | C81: =C77+SUM(C78:C80) -> 259.7 | D81: =D77+SUM(D78:D80) -> 261.1 | E81: =E77+SUM(E78:E80) -> 287.3 | F81: =F77+SUM(F78:F80) -> 279.6 | G81: =G77+SUM(G78:G80) -> 299 | H81: =H77+SUM(H78:H80) -> 254.8 | I81: =I77+SUM(I78:I80) -> 266.4 | J81: =J77+SUM(J78:J80) -> 312.6 | ... BQ81: =BQ77+SUM(BQ78:BQ80) -> 2088 | CA81: =SUM(C81:F81) -> 1087.7 | CB81: =SUM(G81:J81) -> 1132.8 | CC81: =SUM(K81:N81) -> 1269.4 | CD81: =SUM(O81:R81) -> 1319.5 | CE81: =SUM(S81:V81) -> 2087.2 | CF81: =SUM(W81:Z81) -> 1936 | CG81: =SUM(AA81:AD81) -> 2024 | CH81: =SUM(AE81:AH81) -> 2429 | CI81: =SUM(AI81:AL81) -> 3262 | CJ81: =SUM(AM81:AP81) -> 4072 | CK81: =SUM(AQ81:AT81) -> 7230 | CL81: =SUM(AU81:AX81) -> 8841 | CM81: =SUM(AY81:BB81) -> 7835 | CN81: =SUM(BC81:BF81) -> 6298 | CO81: =SUM(BG81:BJ81) -> 7038 | CP81: =SUM(BK81:BN81) -> 7309 | CQ81: =CQ77+SUM(CQ78:CQ80) -> 6799.62 | CR81: =CR77+SUM(CR78:CR80) -> 8780.3334 | CS81: =CS77+SUM(CS78:CS80) -> 10793.831 | CT81: =CT77+SUM(CT78:CT80) -> 13034.307 | CU81: =CU77+SUM(CU78:CU80) -> 15219.232 | CV81: =CV77+SUM(CV78:CV80) -> 17658.921 | CW81: =CW77+SUM(CW78:CW80) -> 20276.676 | CX81: =CX77+SUM(CX78:CX80) -> 23073.974 | ... CZ81: =CZ77+SUM(CZ78:CZ80) -> 28774.662
B82: Taxes | C82: 35.1 | D82: 32.4 | E82: 28.5 | F82: 5.6 | G82: 51.8 | H82: 37.7 | I82: 0.1 | J82: 19.8 | K82: 30.3 | L82: 26 | M82: -3 | N82: -42.3 | O82: 2.1 | P82: 2.4 | Q82: 1.3 | R82: 34.6 | S82: 231.3 | T82: -42 | U82: 69.3 | V82: -66.9 | W82: -3.1 | X82: -8 | Y82: -9.2 | Z82: -23.7 | AA82: 20.7 | AB82: 4.3 | AC82: -45.6 | AD82: 19.6 | AE82: -48 | AF82: 13 | AG82: -54 | AH82: 290 | AI82: 55 | AJ82: 54 | AK82: 101 | AL82: 114 | AM82: 2 | AN82: 274 | AO82: 62 | AP82: 36 | AQ82: 40 | AR82: 97 | AS82: 319 | AT82: 394 | AU82: 416 | AV82: 220 | AW82: 271 | AX82: =1113-SUM(AU82:AW82) -> 206 | AY82: 320 | AZ82: 249 | BA82: 103 | BB82: =703+172-SUM(AY82:BA82) -> 203 | BC82: 71 | BD82: =52+16 -> 68 | BE82: 70 | BF82: =284+59-SUM(BC82:BE82) -> 134 | BG82: =281-23 -> 258 | BH82: =128+84 -> 212 | BI82: 114 | BJ82: =657+42-SUM(BG82:BI82) -> 115 | BK82: 109 | BL82: 90 | BM82: 205 | BN82: =547+41-SUM(BK82:BM82) -> 184 | BO82: 78 | BP82: 182 | BQ82: 361 | CA82: =SUM(C82:F82) -> 101.6 | CB82: =SUM(G82:J82) -> 109.4 | CC82: =SUM(K82:N82) -> 11 | CD82: =SUM(O82:R82) -> 40.4 | CE82: =SUM(S82:V82) -> 191.7 | CF82: =SUM(W82:Z82) -> -44 | CG82: =SUM(AA82:AD82) -> -1 | CH82: =SUM(AE82:AH82) -> 201 | CI82: =SUM(AI82:AL82) -> 324 | CJ82: =SUM(AM82:AP82) -> 374 | CK82: =SUM(AQ82:AT82) -> 850 | CL82: =SUM(AU82:AX82) -> 1113 | CM82: =SUM(AY82:BB82) -> 875 | CN82: =SUM(BC82:BF82) -> 343 | CO82: =SUM(BG82:BJ82) -> 699 | CP82: =SUM(BK82:BN82) -> 588 | CQ82: =CQ81*CQ94 -> 547.02101 | CR82: =CR81*CR94 -> 1053.64 | CS82: =CS81*CS94 -> 1511.1363 | CT82: =CT81*CT94 -> 1824.803 | CU82: =CU81*CU94 -> 2130.6925 | CV82: =CV81*CV94 -> 2472.249 | CW82: =CW81*CW94 -> 2838.7346 | CX82: =CX81*CX94 -> 3230.3564 | ... CZ82: =CZ81*CZ94 -> 4028.4526
B83: Net Income | C83: =C81-C82 -> 224.6 | D83: =D81-D82 -> 228.7 | E83: =E81-E82 -> 258.8 | F83: =F81-F82 -> 274 | G83: =G81-G82 -> 247.2 | H83: =H81-H82 -> 217.1 | I83: =I81-I82 -> 266.3 | J83: =J81-J82 -> 292.8 | ... BQ83: =BQ81-BQ82 -> 1727 | CA83: =SUM(C83:F83) -> 986.1 | CB83: =SUM(G83:J83) -> 1023.4 | CC83: =SUM(K83:N83) -> 1258.4 | CD83: =SUM(O83:R83) -> 1279.1 | CE83: =SUM(S83:V83) -> 1895.5 | CF83: =SUM(W83:Z83) -> 1980 | CG83: =SUM(AA83:AD83) -> 2025 | CH83: =SUM(AE83:AH83) -> 2228 | CI83: =SUM(AI83:AL83) -> 2938 | CJ83: =SUM(AM83:AP83) -> 3698 | CK83: =SUM(AQ83:AT83) -> 6380 | CL83: =SUM(AU83:AX83) -> 7728 | CM83: =SUM(AY83:BB83) -> 6960 | CN83: =SUM(BC83:BF83) -> 5955 | CO83: =SUM(BG83:BJ83) -> 6339 | CP83: =SUM(BK83:BN83) -> 6721 | CQ83: =CQ81-CQ82 -> 6252.599 | CR83: =CR81-CR82 -> 7726.6934 | CS83: =CS81-CS82 -> 9282.6947 | CT83: =CT81-CT82 -> 11209.504 | CU83: =CU81-CU82 -> 13088.539 | CV83: =CV81-CV82 -> 15186.672 | CW83: =CW81-CW82 -> 17437.941 | CX83: =CX81-CX82 -> 19843.618 | ... CZ83: =CZ81-CZ82 -> 24746.209
B84: Non-controlling Int. | C84: 0 | D84: 0 | E84: 0 | F84: 0 | G84: 0 | H84: 0 | I84: 0 | J84: 0 | K84: 0 | L84: 0 | M84: 0 | N84: 0 | O84: 0 | P84: 0 | Q84: 0 | R84: 0 | S84: 0 | T84: 0 | U84: 0 | V84: 0 | W84: 0 | X84: 0 | Y84: 0 | Z84: 0 | AA84: 0 | AB84: 0 | AC84: 0 | AD84: 0 | AE84: 0 | AF84: 0 | AG84: 0 | AH84: 0 | AI84: 0 | AJ84: 0 | AK84: 0 | AL84: 0 | AM84: 0 | AN84: 0 | AO84: 0 | AP84: 0 | AQ84: 0 | AR84: 0 | AS84: 0 | AT84: 0 | AU84: 0 | AV84: 1 | AW84: 0 | AX84: =3-SUM(AU84:AW84) -> 2 | AY84: 5 | AZ84: 4 | BA84: 3 | BB84: =10-SUM(AY84:BA84) -> -2 | BC84: 3 | BD84: 1 | BE84: -20 | BF84: =-40-SUM(BC84:BE84) -> -24 | BG84: 4 | BH84: 6 | BI84: 0 | BJ84: =3-SUM(BG84:BI84) -> -7 | BK84: 4 | BL84: 2 | BM84: 5 | BN84: =17-SUM(BK84:BM84) -> 6 | BO84: 5 | BP84: 5 | BQ84: 6 | CA84: =SUM(C84:F84) -> 0 | CB84: =SUM(G84:J84) -> 0 | CC84: =SUM(K84:N84) -> 0 | CD84: =SUM(O84:R84) -> 0 | CE84: =SUM(S84:V84) -> 0 | CF84: =SUM(W84:Z84) -> 0 | CG84: =SUM(AA84:AD84) -> 0 | CH84: =SUM(AE84:AH84) -> 0 | CI84: =SUM(AI84:AL84) -> 0 | CJ84: =SUM(AM84:AP84) -> 0 | CK84: =SUM(AQ84:AT84) -> 0 | CL84: =SUM(AU84:AX84) -> 3 | CM84: =SUM(AY84:BB84) -> 10 | CN84: =SUM(BC84:BF84) -> -40 | CO84: =SUM(BG84:BJ84) -> 3 | CP84: =SUM(BK84:BN84) -> 17 | CQ84: 0 | CR84: 0 | CS84: 0 | CT84: 0 | CU84: 0 | CV84: 0 | CW84: 0 | CX84: 0 | CY84: 0 | CZ84: 0
B85: Attr. Net Income | C85: =C83-C84 -> 224.6 | D85: =D83-D84 -> 228.7 | E85: =E83-E84 -> 258.8 | F85: =F83-F84 -> 274 | G85: =G83-G84 -> 247.2 | H85: =H83-H84 -> 217.1 | I85: =I83-I84 -> 266.3 | J85: =J83-J84 -> 292.8 | ... BQ85: =BQ83-BQ84 -> 1721 | CA85: =SUM(C85:F85) -> 986.1 | CB85: =SUM(G85:J85) -> 1023.4 | CC85: =SUM(K85:N85) -> 1258.4 | CD85: =SUM(O85:R85) -> 1279.1 | CE85: =SUM(S85:V85) -> 1895.5 | CF85: =SUM(W85:Z85) -> 1980 | CG85: =SUM(AA85:AD85) -> 2025 | CH85: =SUM(AE85:AH85) -> 2228 | CI85: =SUM(AI85:AL85) -> 2938 | CJ85: =SUM(AM85:AP85) -> 3698 | CK85: =SUM(AQ85:AT85) -> 6380 | CL85: =SUM(AU85:AX85) -> 7725 | CM85: =SUM(AY85:BB85) -> 6950 | CN85: =SUM(BC85:BF85) -> 5995 | CO85: =SUM(BG85:BJ85) -> 6336 | CP85: =SUM(BK85:BN85) -> 6704 | CQ85: =CQ83-CQ84 -> 6252.599 | CR85: =CR83-CR84 -> 7726.6934 | CS85: =CS83-CS84 -> 9282.6947 | CT85: =CT83-CT84 -> 11209.504 | CU85: =CU83-CU84 -> 13088.539 | CV85: =CV83-CV84 -> 15186.672 | CW85: =CW83-CW84 -> 17437.941 | CX85: =CX83-CX84 -> 19843.618 | ... CZ85: =CZ83-CZ84 -> 24746.209 | DA85: =CZ85*(1+$DJ$98) -> 25105.029 | DB85: =DA85*(1+$DJ$98) -> 25469.052 | DC85: =DB85*(1+$DJ$98) -> 25838.353 | DD85: =DC85*(1+$DJ$98) -> 26213.009 | DE85: =DD85*(1+$DJ$98) -> 26593.098 | DF85: =DE85*(1+$DJ$98) -> 26978.698 | DG85: =DF85*(1+$DJ$98) -> 27369.889 | DH85: =DG85*(1+$DJ$98) -> 27766.752 | ... EX85: =EW85*(1+$DJ$98) -> 50828.962
B86: SC | C86: 406 | D86: 405 | E86: 396 | F86: 392 | G86: 385 | H86: 376 | I86: 375 | J86: 372 | K86: 370 | L86: 368 | M86: 364 | N86: 362 | O86: 360 | P86: 362 | Q86: 363 | R86: 364 | S86: 390 | T86: 396 | U86: 398 | V86: 400 | W86: 395 | X86: 396 | Y86: 398 | Z86: 400 | AA86: 395 | AB86: 391 | AC86: 392 | AD86: 393 | AE86: 392 | AF86: 387 | AG86: 394 | AH86: 395 | AI86: 396 | AJ86: 397 | AK86: 398 | AL86: 397 | AM86: 396 | AN86: 397 | AO86: 398 | AP86: 396 | AQ86: 394 | AR86: 392 | AS86: 394 | AT86: 396 | AU86: 394 | AV86: 393 | AW86: 394 | AX86: 394 | AY86: 392 | AZ86: 392 | BA86: 392 | BB86: 392 | BC86: 386 | BD86: 386 | BE86: 386 | BF86: 386 | BG86: 382 | BH86: 382 | BI86: 382 | BJ86: 382 | BK86: 378 | BL86: 378 | BM86: 378 | BN86: 376 | BO86: 372 | BP86: 371 | BQ86: 370 | CA86: =AVERAGE(C86:F86) -> 399.75 | CB86: =AVERAGE(G86:J86) -> 377 | CC86: =AVERAGE(K86:N86) -> 366 | CD86: =AVERAGE(O86:R86) -> 362.25 | CE86: =AVERAGE(S86:V86) -> 396 | CF86: =AVERAGE(W86:Z86) -> 397.25 | CG86: =AVERAGE(AA86:AD86) -> 392.75 | CH86: =AVERAGE(AE86:AH86) -> 392 | CI86: =AVERAGE(AI86:AL86) -> 397 | CJ86: =AVERAGE(AM86:AP86) -> 396.75 | CK86: =AVERAGE(AQ86:AT86) -> 394 | CL86: =AVERAGE(AU86:AX86) -> 393.75 | CM86: =AVERAGE(AY86:BB86) -> 392 | CN86: =AVERAGE(BC86:BF86) -> 386 | CO86: =AVERAGE(BG86:BJ86) -> 382 | CP86: =AVERAGE(BK86:BN86) -> 377.5
B87: EPS | C87: =C85/C86 -> 0.55320197 | D87: =D85/D86 -> 0.56469136 | E87: =E85/E86 -> 0.65353535 | F87: =F85/F86 -> 0.69897959 | G87: =G85/G86 -> 0.64207792 | H87: =H85/H86 -> 0.57739362 | I87: =I85/I86 -> 0.71013333 | J87: =J85/J86 -> 0.78709677 | ... BQ87: =BQ85/BQ86 -> 4.6513514 | CA87: =SUM(C87:F87) -> 2.4704083 | CB87: =SUM(G87:J87) -> 2.7167016 | CC87: =SUM(K87:N87) -> 3.4417575 | CD87: =SUM(O87:R87) -> 3.5310318 | CE87: =SUM(S87:V87) -> 4.7865002 | CF87: =SUM(W87:Z87) -> 4.9811021 | CG87: =SUM(AA87:AD87) -> 5.1572886 | CH87: =SUM(AE87:AH87) -> 5.6866937 | CI87: =SUM(AI87:AL87) -> 7.3996995 | CJ87: =SUM(AM87:AP87) -> 9.3216219 | CK87: =SUM(AQ87:AT87) -> 16.175778 | CL87: =SUM(AU87:AX87) -> 19.618405 | CM87: =SUM(AY87:BB87) -> 17.729592 | CN87: =SUM(BC87:BF87) -> 15.531088 | CO87: =SUM(BG87:BJ87) -> 16.586387 | CP87: =SUM(BK87:BN87) -> 17.763101
B89: Gross Profit Margin | C89: =C73/C71 -> 0.40595379 | D89: =D73/D71 -> 0.40409138 | E89: =E73/E71 -> 0.40381177 | F89: =F73/F71 -> 0.42674483 | G89: =G73/G71 -> 0.41166311 | H89: =H73/H71 -> 0.40679748 | I89: =I73/I71 -> 0.41559549 | J89: =J73/J71 -> 0.42412719 | ... BQ89: =BQ73/BQ71 -> 0.42778281 | CA89: =CA73/CA71 -> 0.41003166 | CB89: =CB73/CB71 -> 0.41474894 | CC89: =CC73/CC71 -> 0.42330474 | CD89: =CD73/CD71 -> 0.42238146 | CE89: =CE73/CE71 -> 0.44358659 | CF89: =CF73/CF71 -> 0.45717654 | CG89: =CG73/CG71 -> 0.45813724 | CH89: =CH73/CH71 -> 0.45166842 | ... CP89: =CP73/CP71 -> 0.40932759 | CQ89: 0.40932759 | CR89: 0.41 | CS89: 0.415 | CT89: 0.42 | CU89: 0.4225 | CV89: 0.425 | CW89: 0.4275 | CX89: 0.43 | CY89: 0.43 | CZ89: 0.43
B90: SG&A as % of Revenue | C90: =C74/C71 -> 0.26582664 | D90: =D74/D71 -> 0.25935201 | E90: =E74/E71 -> 0.25754175 | F90: =F74/F71 -> 0.26764498 | G90: =G74/G71 -> 0.26041743 | H90: =H74/H71 -> 0.27081289 | I90: =I74/I71 -> 0.27430189 | J90: =J74/J71 -> 0.26893952 | ... BQ90: =BQ74/BQ71 -> 0.19625937 | CA90: =CA74/CA71 -> 0.26255881 | CB90: =CB74/CB71 -> 0.26875627 | CC90: =CC74/CC71 -> 0.2681796 | CD90: =CD74/CD71 -> 0.26327128 | CE90: =CE74/CE71 -> 0.28988845 | CF90: =CF74/CF71 -> 0.27185382 | CG90: =CG74/CG71 -> 0.27202583 | CH90: =CH74/CH71 -> 0.26312267 | ... CP90: =CP74/CP71 -> 0.19597809 | CQ90: 0.19597809 | CR90: 0.19597809 | CS90: 0.19597809 | CT90: 0.19597809 | CU90: 0.19597809 | CV90: 0.19597809 | CW90: 0.19597809 | CX90: 0.19597809 | CY90: 0.19597809 | CZ90: 0.19597809
B91: R&D as % of Revenue | C91: =C75/C71 -> 0.025162739 | D91: =D75/D71 -> 0.026813576 | E91: =E75/E71 -> 0.027199757 | F91: =F75/F71 -> 0.030372177 | G91: =G75/G71 -> 0.027485853 | H91: =H75/H71 -> 0.029152067 | I91: =I75/I71 -> 0.029595281 | J91: =J75/J71 -> 0.031273562 | ... BQ91: =BQ75/BQ71 -> 0.028672654 | CA91: =CA75/CA71 -> 0.027364309 | CB91: =CB75/CB71 -> 0.029432121 | CC91: =CC75/CC71 -> 0.03008817 | CD91: =CD75/CD71 -> 0.030213211 | CE91: =CE75/CE71 -> 0.040918672 | CF91: =CF75/CF71 -> 0.040789861 | CG91: =CG75/CG71 -> 0.041260808 | CH91: =CH75/CH71 -> 0.042403671 | ... CP91: =CP75/CP71 -> 0.031353802 | CQ91: 0.031353802 | CR91: 0.03 | CS91: 0.03 | CT91: 0.029 | CU91: 0.029 | CV91: 0.028 | CW91: 0.028 | CX91: 0.027 | CY91: 0.027 | CZ91: 0.026
B92: Other Op Ex as % of Revenue | C92: =C76/C71 -> 0.0066237771 | D92: =D76/D71 -> 0.0031590708 | E92: =E76/E71 -> 0.0039182866 | F92: =F76/F71 -> 0.0095601542 | G92: =G76/G71 -> 0.0056221063 | H92: =H76/H71 -> 0.01394534 | I92: =I76/I71 -> 0.0039551297 | J92: =J76/J71 -> 0.0097688903 | ... BQ92: =BQ76/BQ71 -> 0.016396144 | CA92: =CA76/CA71 -> 0.0057923045 | CB92: =CB76/CB71 -> 0.0083486175 | CC92: =CC76/CC71 -> 0.0065628023 | CD92: =CD76/CD71 -> 0.0059356928 | CE92: =CE76/CE71 -> -0.035418246 | CF92: =CF76/CF71 -> 0.0068376068 | CG92: =CG76/CG71 -> 0.010342563 | CH92: =CH76/CH71 -> 0.0046371546 | ... CP92: =CP76/CP71 -> 0.0081246072 | CQ92: 0.012 | CR92: 0.01 | CS92: 0.009 | CT92: 0.0081246072 | CU92: 0.0081246072 | CV92: 0.0081246072 | CW92: 0.007 | CX92: 0.007 | CY92: 0.006 | CZ92: 0.006
B93: Operating Profit Margin | C93: =C77/C71 -> 0.10834063 | D93: =D77/D71 -> 0.11476673 | E93: =E77/E71 -> 0.11515198 | F93: =F77/F71 -> 0.11916752 | G93: =G77/G71 -> 0.11813772 | H93: =H77/H71 -> 0.092887176 | I93: =I77/I71 -> 0.10774319 | J93: =J77/J71 -> 0.11414522 | ... BQ93: =BQ77/BQ71 -> 0.18645464 | CA93: =CA77/CA71 -> 0.11431623 | CB93: =CB77/CB71 -> 0.10821193 | CC93: =CC77/CC71 -> 0.11847417 | CD93: =CD77/CD71 -> 0.12296128 | CE93: =CE77/CE71 -> 0.14819771 | CF93: =CF77/CF71 -> 0.13769525 | CG93: =CG77/CG71 -> 0.13450804 | CH93: =CH77/CH71 -> 0.14150492 | ... CP93: =CP77/CP71 -> 0.17387108 | CQ93: 0.17387108 | CR93: 0.17387108 | CS93: 0.17387108 | CT93: 0.17387108 | CU93: 0.17387108 | CV93: 0.17387108 | CW93: 0.17387108 | CX93: 0.17387108 | CY93: 0.17387108 | CZ93: 0.17387108
B94: Effective Tax Rate | C94: =C82/C81 -> 0.13515595 | D94: =D82/D81 -> 0.12409039 | E94: =E82/E81 -> 0.099199443 | F94: =F82/F81 -> 0.020028612 | G94: =G82/G81 -> 0.17324415 | H94: =H82/H81 -> 0.14795918 | I94: =I82/I81 -> 0.00037537538 | J94: =J82/J81 -> 0.063339731 | ... BQ94: =BQ82/BQ81 -> 0.17289272 | CA94: =CA82/CA81 -> 0.093408109 | CB94: =CB82/CB81 -> 0.096574859 | CC94: =CC82/CC81 -> 0.0086655113 | CD94: =CD82/CD81 -> 0.030617658 | CE94: =CE82/CE81 -> 0.091845535 | CF94: =CF82/CF81 -> -0.022727273 | CG94: =CG82/CG81 -> -0.00049407115 | CH94: =CH82/CH81 -> 0.082750103 | ... CP94: =CP82/CP81 -> 0.080448762 | CQ94: 0.080448762 | CR94: 0.12 | CS94: 0.14 | CT94: 0.14 | CU94: 0.14 | CV94: 0.14 | CW94: 0.14 | CX94: 0.14 | CY94: 0.14 | CZ94: 0.14
B95: Net Profit Margin | C95: =C85/C71 -> 0.085500019 | D95: =D85/D71 -> 0.088107254 | E95: =E85/E71 -> 0.098451706 | F95: =F85/F71 -> 0.10779762 | G95: =G85/G71 -> 0.090835599 | H95: =H85/H71 -> 0.076068676 | I95: =I85/I71 -> 0.090797504 | J95: =J85/J71 -> 0.095984265 | ... BQ95: =BQ85/BQ71 -> 0.14179781 | CA95: =CA85/CA71 -> 0.094880257 | CB95: =CB85/CB71 -> 0.088538603 | CC95: =CC85/CC71 -> 0.10059233 | CD95: =CD85/CD71 -> 0.097713574 | CE95: =CE85/CE71 -> 0.11222883 | CF95: =CF85/CF71 -> 0.11671088 | CG95: =CG85/CG71 -> 0.11081318 | CH95: =CH85/CH71 -> 0.10651114 | ... CP95: =CP85/CP71 -> 0.15046234 | CQ95: 0.15046234 | CR95: 0.15046234 | CS95: 0.15046234 | CT95: 0.15046234 | CU95: 0.15046234 | CV95: 0.15046234 | CW95: 0.15046234 | CX95: 0.15046234 | CY95: 0.15046234 | CZ95: 0.15046234
B97: Cash & CEs | BB97: 8524 | BC97: 3482 | BD97: 3133 | BE97: 6151 | BF97: 8077 | BG97: 5499 | BH97: 7073 | BI97: 4645 | BJ97: 4009 | BK97: 4134 | BL97: 4576 | BM97: 1982 | BN97: 9852 | BO97: 3254 | BP97: 4064 | BQ97: 5641 | CM97: =BB97 -> 8524 | CN97: =BF97 -> 8077 | CO97: =BJ97 -> 4009 | CP97: =BK97 -> 4134 | CQ97: =CP97+CQ85 -> 10386.599 | CR97: =CQ97+CR85 -> 18113.292 | CS97: =CR97+CS85 -> 27395.987 | CT97: =CS97+CT85 -> 38605.491 | CU97: =CT97+CU85 -> 51694.031 | CV97: =CU97+CV85 -> 66880.703 | CW97: =CV97+CW85 -> 84318.644 | CX97: =CW97+CX85 -> 104162.26 | ... CZ97: =CY97+CZ85 -> 151125.55 | DB97: Invested Capital | DE97: Avg. (2024-2025) | DG97: Projected ROIC: | DI97: ROIC | DJ97: 0.0875
B98: ST Investments | BB98: 0 | BC98: 0 | BD98: 0 | BE98: 0 | BF98: 3 | BG98: 1751 | BH98: 1750 | BI98: 2000 | BJ98: 1561 | BK98: 1813 | BL98: 1814 | BM98: 1564 | BN98: 253 | BO98: 2 | BP98: 0 | BQ98: 600 | CM98: =BB98 -> 0 | CN98: =BF98 -> 3 | CO98: =BJ98 -> 1561 | CP98: =BK98 -> 1813 | DB98: 2024 | DC98: 2025 | DE98: 2024-2025 | DG98: 2025 | DI98: Terminal | DJ98: 0.0145
B99: A/R | BB99: 8115 | BC99: 7922 | BD99: 8019 | BE99: 8370 | BF99: 8221 | BG99: 7931 | BH99: 7943 | BI99: 8255 | BJ99: 8191 | BK99: 8455 | BL99: 8594 | BM99: 8911 | BN99: 8900 | BO99: 9204 | BP99: 9451 | BQ99: 9625 | CM99: =BB99 -> 8115 | CN99: =BF99 -> 8221 | CO99: =BJ99 -> 8191 | CP99: =BK99 -> 8455 | DB99: =SUM(CO97:CO100)-CO112+CO104+CO106+CO105 -> 81765 | DC99: =SUM(BP97:BP100)-BP112+BP104+BP106+BP105 -> 95278 | DE99: =AVERAGE(DB99:DC99) -> 88521.5 | DG99: =AVERAGE(CQ77)*(1-CQ94) -> 7546.9087 | DI99: RFR (10-year yield) | DJ99: =DE108 -> 0.0517
B100: Inventories | BB100: 5634 | BC100: 5664 | BD100: 5655 | BE100: 5404 | BF100: 5088 | BG100: 5133 | BH100: 5198 | BI100: 5430 | BJ100: 4978 | BK100: 5224 | BL100: 5559 | BM100: 5745 | BN100: 5425 | BO100: 5496 | BP100: 5627 | BQ100: 5643 | CM100: =BB100 -> 5634 | CN100: =BF100 -> 5088 | CO100: =BJ100 -> 4978 | CP100: =BK100 -> 5224 | DG100: =DG99/DE99 -> 0.085255093 | DI100: ERP (Avg. market return - (less) RFR) | DJ100: =8.95%-DJ99 -> 0.0378
B101: ST Contract Assets | BB101: 1312 | BC101: 1375 | BD101: 1467 | BE101: 1465 | BF101: 1443 | BG101: 1422 | BH101: 1487 | BI101: 1541 | BJ101: 1435 | BK101: 1366 | BL101: 1441 | BM101: 1620 | BN101: 1666 | BO101: 1684 | BP101: 1688 | BQ101: 0 | CM101: =BB101 -> 1312 | CN101: =BF101 -> 1443 | CO101: =BJ101 -> 1435 | CP101: =BK101 -> 1366 | DB101: Capital Structure | DI101: Equity β (1-year avg.) | DJ101: ='Notes | Quant Analysis'!K213 -> 0.76
B102: Other ST Assets | BB102: 1644 | BC102: 1766 | BD102: 1721 | BE102: 1702 | BF102: 1757 | BG102: 1904 | BH102: 2025 | BI102: 1911 | BJ102: 1964 | BK102: 2387 | BL102: 2599 | BM102: 2472 | BN102: 2612 | BO102: 2677 | BP102: 2536 | BQ102: 4285 | CM102: =BB102 -> 1644 | CN102: =BF102 -> 1757 | CO102: =BJ102 -> 1964 | CP102: =BK102 -> 2387 | DB102: Mkt Cap | DE102: =Main!C5 -> 256787.4 | DI102: Discount (Cost of Equity) | DJ102: =+DJ99+(DJ100*DJ101) -> 0.080428
B103: PP&E | BB103: 9280 | BC103: 9354 | BD103: 9292 | BE103: 9167 | BF103: 9448 | BG103: 9324 | BH103: 9282 | BI103: 9412 | BJ103: 9306 | BK103: 9331 | BL103: 9635 | BM103: 10177 | BN103: 10565 | BO103: 10658 | BP103: 10755 | BQ103: 10577 | CM103: =BB103 -> 9280 | CN103: =BF103 -> 9448 | CO103: =BJ103 -> 9306 | CP103: =BK103 -> 9331 | DB103: Debt to Ttl Mkt Cap | DE103: =Main!C7/(Main!C7+DE102) -> 0.13875222
B104: Acquisition Related Intangibles | BB104: 17442 | BC104: 17972 | BD104: 17437 | BE104: 17091 | BF104: 16670 | BG104: 16048 | BH104: 15519 | BI104: 16262 | BJ104: 15533 | BK104: 15323 | BL104: 15148 | BM104: 16242 | BN104: 15838 | BO104: 19146 | BP104: 18606 | BQ104: 18077 | CM104: =BB104 -> 17442 | CN104: =BF104 -> 16670 | CO104: =BJ104 -> 15533 | CP104: =BK104 -> 15323 | DB104: Mkt Equity to Ttl Mkt Cap | DE104: =DE102/(DE102+Main!C7) -> 0.86124778 | DI104: NPV | DJ104: =NPV(DJ102,CQ85:EX85) -> 257896.64
B105: Other Assets | BB105: 4007 | BC105: 3983 | BD105: 4108 | BE105: 4124 | BF105: 3999 | BG105: 4241 | BH105: 4377 | BI105: 4180 | BJ105: 4492 | BK105: 4516 | BL105: 4615 | BM105: 5019 | BN105: 5871 | BO105: 5973 | BP105: 5616 | BQ105: 5701 | CM105: =BB105 -> 4007 | CN105: =BF105 -> 3999 | CO105: =BJ105 -> 4492 | CP105: =BK105 -> 4516 | DB105: LT Debt / Equity | DE105: =CP116/CP119 -> 0.63557347 | DI105: SC | DJ105: =Main!C4 -> 370
B106: Goodwill | BB106: 41196 | BC106: 43140 | BD106: 43273 | BE106: 43583 | BF106: 44020 | BG106: 43843 | BH106: 43843 | BI106: 46726 | BJ106: 45853 | BK106: 46493 | BL106: 47249 | BM106: 49287 | BN106: 49362 | BO106: 55187 | BP106: 54832 | BQ106: 54263 | CM106: =BB106 -> 41196 | CN106: =BF106 -> 44020 | CO106: =BJ106 -> 45853 | CP106: =BK106 -> 46493 | DI106: FV | DJ106: =DJ104/DJ105 -> 697.01794
B107: Ttl Assets | BB107: =SUM(BB97:BB106) -> 97154 | BC107: =SUM(BC97:BC106) -> 94658 | BD107: =SUM(BD97:BD106) -> 94105 | BE107: =SUM(BE97:BE106) -> 97057 | BF107: =SUM(BF97:BF106) -> 98726 | BG107: =SUM(BG97:BG106) -> 97096 | BH107: =SUM(BH97:BH106) -> 98497 | BI107: =SUM(BI97:BI106) -> 100362 | ... BQ107: =SUM(BQ97:BQ106) -> 114412 | CM107: =BB107 -> 97154 | CN107: =BF107 -> 98726 | CO107: =BJ107 -> 97322 | CP107: =BK107 -> 99042 | DB107: Cost of Equity | DI107: CP | DJ107: =Main!C3 -> 694.02
DB108: RFR (10-year yield) | DE108: 0.0517 | DI108: Change Δ | DJ108: =DJ106/DJ107-1 -> 0.0043196676 | DK108: =IF(DJ108>0,"Upside","Downside") -> Upside
B109: ST Debt | BB109: 5579 | BC109: 6122 | BD109: 4814 | BE109: 4795 | BF109: 3609 | BG109: 4451 | BH109: 5121 | BI109: 4116 | BJ109: 2214 | BK109: 2819 | BL109: 2214 | BM109: 3823 | BN109: 3533 | BO109: 3090 | BP109: 3368 | CM109: =BB109 -> 5579 | CN109: =BF109 -> 3609 | CO109: =BJ109 -> 2214 | CP109: =BK109 -> 2819 | DB109: Equity β (1-year avg.) | DE109: ='Notes | Quant Analysis'!K213 -> 0.76 | DI109: {=_xlfn.IFS(DJ108>=25%,"Strong Buy",DJ108>=10.00001%,"Buy",AND(DJ108<=10%,DJ108>=-4.9999%),"Hold",AND(DJ108<=-5%,DJ108>=-14.999999%),"Sell",DJ108<=-15%,"Strong Sell")} -> Hold
B110: A/P | BB110: 3381 | BC110: 2798 | BD110: 2423 | BE110: 2508 | BF110: 2872 | BG110: 2555 | BH110: 2547 | BI110: 2606 | BJ110: 3079 | BK110: 3049 | BL110: 2980 | BM110: 3120 | BN110: 3622 | BO110: 3344 | BP110: 3268 | CM110: =BB110 -> 3381 | CN110: =BF110 -> 2872 | CO110: =BJ110 -> 3079 | CP110: =BK110 -> 3049 | DB110: Market Return(1-year avg.) | DE110: 0.17
B111: Accrued Payroll | BB111: 2095 | BC111: 1307 | BD111: 1310 | BE111: 1460 | BF111: 1596 | BG111: 1314 | BH111: 1495 | BI111: 1823 | BJ111: 1988 | BK111: 1419 | BL111: 1518 | BM111: 1884 | BN111: 1995 | BO111: 1565 | BP111: 1694 | CM111: =BB111 -> 2095 | CN111: =BF111 -> 1596 | CO111: =BJ111 -> 1988 | CP111: =BK111 -> 1419 | DB111: Cost of Equity | DE111: =(DE108+DE109)*(DE110-DE108) -> 0.09602411
...

Sheet Notes | Quant Analysis
CC1: 0
H2: TMO Employee Snapshot (Q4'25) | AF2: General Notes/Observations (Updated Q2'25)
I32: Notes: | J32: [X]
J33: [Y]
J34: [Z]
H36: Institutional Ownership Snapshot (8/24/2026) | AF36: Financial Stmts. Notes/Observations (Updated Q2'25)
AF37: Revenues:
I71: Notes: | J71: [X]
J72: [Y]
J73: [Z]
H75: Revenue Breakdown by Segment (Build graph for this section if applicable…. See example below)
I107: Notes: | J107: [X]
J108: [Y]
J109: [Z]
H111: Total Revenues, Net Income, FCF
I140: Notes: | J140: [X]
J141: [Y]
J142: [Z]
H144: Total Revenues, Net Income, FCF
AF149: Earnings Scope:
I173: Notes: | J173: [X]
J174: [Y]
J175: [Z]
H177: [TMO] Historical Return Histogram
A195: 1256 Trading Days? (From: 9/21/20 - 9/21/25)
A196: Close | B196: High | C196: Low | D196: Open | E196: Volume | F196: UTC Date | G196: Change
A197: 479.58 | B197: 487.99 | C197: 478.0201 | D197: 483.29 | E197: 4244050 | F197: Fri, 19 Sep 2025 00:00:00 GMT | G197: =A197/D197-1 -> -0.0076765503
A198: 481.1 | B198: 482.255 | C198: 473.03 | D198: 477.15 | E198: 1563249 | F198: Thu, 18 Sep 2025 00:00:00 GMT | G198: =A198/D198-1 -> 0.0082783192
A199: 472.64 | B199: 486.57 | C199: 469.14 | D199: 482.96 | E199: 1947751 | F199: Wed, 17 Sep 2025 00:00:00 GMT | G199: =A199/D199-1 -> -0.021368229
A200: 480.74 | B200: 484.59 | C200: 470.05 | D200: 470.27 | E200: 1798297 | F200: Tue, 16 Sep 2025 00:00:00 GMT | G200: =A200/D200-1 -> 0.022263806
A201: 474.46 | B201: 482.94 | C201: 470.74 | D201: 478.78 | E201: 1663465 | F201: Mon, 15 Sep 2025 00:00:00 GMT | G201: =A201/D201-1 -> -0.0090229333
A202: 479.46 | B202: 491.26 | C202: 479.46 | D202: 488.61 | E202: 1538547 | F202: Fri, 12 Sep 2025 00:00:00 GMT | G202: =A202/D202-1 -> -0.018726592
A203: 491.41 | B203: 492 | C203: 480.3575 | D203: 480.575 | E203: 1505086 | F203: Thu, 11 Sep 2025 00:00:00 GMT | G203: =A203/D203-1 -> 0.022545909
A204: 476.54 | B204: 485.8199 | C204: 475.635 | D204: 481.12 | E204: 1442005 | F204: Wed, 10 Sep 2025 00:00:00 GMT | G204: =A204/D204-1 -> -0.0095194546
A205: 482.41 | B205: 489.99 | C205: 481.52 | D205: 486.48 | E205: 1501000 | F205: Tue, 09 Sep 2025 00:00:00 GMT | G205: =A205/D205-1 -> -0.0083662227
A206: 487.65 | B206: 490.065 | C206: 480.95 | D206: 487.77 | E206: 2222973 | F206: Mon, 08 Sep 2025 00:00:00 GMT | G206: =A206/D206-1 -> -0.00024601759
A207: 492.6 | B207: 502 | C207: 489.12 | D207: 490 | E207: 1440451 | F207: Fri, 05 Sep 2025 00:00:00 GMT | G207: =A207/D207-1 -> 0.0053061224 | J207: Min | K207: =MIN(G197:G1452) -> -0.070595797
A208: 489.49 | B208: 490.26 | C208: 471.61 | D208: 482.08 | E208: 1391914 | F208: Thu, 04 Sep 2025 00:00:00 GMT | G208: =A208/D208-1 -> 0.015370893 | J208: Max | K208: =MAX(G197:G1452) -> 0.093866821
A209: 484.55 | B209: 489.54 | C209: 481.53 | D209: 487.03 | E209: 1213141 | F209: Wed, 03 Sep 2025 00:00:00 GMT | G209: =A209/D209-1 -> -0.0050920888 | J209: Mean μ | K209: =AVERAGE(G197:G1452) -> -9.5221812e-05
A210: 487.53 | B210: 492.7 | C210: 479.03 | D210: 489.31 | E210: 1289669 | F210: Tue, 02 Sep 2025 00:00:00 GMT | G210: =A210/D210-1 -> -0.0036377756 | J210: Median | K210: =MEDIAN(G197:G1452) -> -8.5423273e-05
A211: 492.72 | B211: 494.28 | C211: 485.92 | D211: 489.94 | E211: 1220318 | F211: Fri, 29 Aug 2025 00:00:00 GMT | G211: =A211/D211-1 -> 0.0056741642 | J211: SD σ | K211: =_xlfn.STDEV.P(G197:G1452) -> 0.014357925
A212: 489.74 | B212: 491.14 | C212: 483.39 | D212: 487.65 | E212: 1391996 | F212: Thu, 28 Aug 2025 00:00:00 GMT | G212: =A212/D212-1 -> 0.0042858608 | J212: 3σ 1-Day Δ: ± | K212: =3*K211 -> 0.043073776 | M212: <- Shapre Ratio (Risk Adjusted Return)
A213: 488.12 | B213: 490.98 | C213: 482.98 | D213: 486.63 | E213: 1284841 | F213: Wed, 27 Aug 2025 00:00:00 GMT | G213: =A213/D213-1 -> 0.0030618745 | J213: β (1-year avg.) | K213: 0.76 | M213: <- Sortino Ratio (Downside Risk Adjusted Return)
A214: 488.48 | B214: 491.52 | C214: 486.73 | D214: 490.09 | E214: 1330616 | F214: Tue, 26 Aug 2025 00:00:00 GMT | G214: =A214/D214-1 -> -0.0032851109
A215: 490.75 | B215: 499.58 | C215: 489.18 | D215: 499.25 | E215: 1044386 | F215: Mon, 25 Aug 2025 00:00:00 GMT | G215: =A215/D215-1 -> -0.017025538 | I215: n = | J215: 1256
A216: 499.99 | B216: 502.39 | C216: 486.885 | D216: 487.53 | E216: 1759231 | F216: Fri, 22 Aug 2025 00:00:00 GMT | G216: =A216/D216-1 -> 0.025557402 | I216: Histogram Data | L216: Distribution Overlay | P216: SD Lines
A217: 483.76 | B217: 494.78 | C217: 482.81 | D217: 492.44 | E217: 1360656 | F217: Thu, 21 Aug 2025 00:00:00 GMT | G217: =A217/D217-1 -> -0.017626513 | I217: Bin | J217: Frequency | L217: (X) 1-Day Δ | M217: (Y) Pop. Density | P217: X | Q217: Y
A218: 494.81 | B218: 500.37 | C218: 492.755 | D218: 498.77 | E218: 2346221 | F218: Wed, 20 Aug 2025 00:00:00 GMT | G218: =A218/D218-1 -> -0.0079395312 | I218: -0.044 | J218: 8 | L218: -0.045 | M218: =_xlfn.NORM.DIST(L218,$K$209,K211,FALSE) -> 0.20883866 | O218: Mean | P218: =K209 -> -9.5221812e-05 | Q218: 0
A219: 498.29 | B219: 500.93 | C219: 489.89 | D219: 490.92 | E219: 2573296 | F219: Tue, 19 Aug 2025 00:00:00 GMT | G219: =A219/D219-1 -> 0.015012629 | I219: -0.043 | J219: 1 | L219: -0.044 | M219: =_xlfn.NORM.DIST(L219,$K$209,$K$211,FALSE) -> 0.25903477 | P219: =K209 -> -9.5221812e-05 | Q219: 28
A220: 487.54 | B220: 493.24 | C220: 487.14 | D220: 490.13 | E220: 2211081 | F220: Mon, 18 Aug 2025 00:00:00 GMT | G220: =A220/D220-1 -> -0.0052843123 | I220: -0.042 | J220: 2 | L220: -0.043 | M220: =_xlfn.NORM.DIST(L220,$K$209,$K$211,FALSE) -> 0.31974115 | O220: -3σ | P220: =($K$211*-3)+$K$209 -> -0.043168998 | Q220: 0
A221: 489.01 | B221: 491.545 | C221: 486 | D221: 486.73 | E221: 2462473 | F221: Fri, 15 Aug 2025 00:00:00 GMT | G221: =A221/D221-1 -> 0.0046843219 | I221: -0.041 | J221: 0 | L221: -0.042 | M221: =_xlfn.NORM.DIST(L221,$K$209,$K$211,FALSE) -> 0.39276458 | P221: =($K$211*-3)+$K$209 -> -0.043168998 | Q221: 2
A222: 485.04 | B222: 485.9 | C222: 479.24 | D222: 480.74 | E222: 1955358 | F222: Thu, 14 Aug 2025 00:00:00 GMT | G222: =A222/D222-1 -> 0.0089445438 | I222: -0.04 | J222: 0 | L222: -0.041 | M222: =_xlfn.NORM.DIST(L222,$K$209,$K$211,FALSE) -> 0.48013062 | O222: -2σ | P222: =($K$211*-2)+$K$209 -> -0.028811073 | Q222: 0
A223: 484.79 | B223: 486.98 | C223: 478.715 | D223: 480.44 | E223: 2054842 | F223: Wed, 13 Aug 2025 00:00:00 GMT | G223: =A223/D223-1 -> 0.0090542003 | I223: -0.039 | J223: 1 | L223: -0.04 | M223: =_xlfn.NORM.DIST(L223,$K$209,$K$211,FALSE) -> 0.58409005 | P223: =($K$211*-2)+$K$209 -> -0.028811073 | Q223: 4
A224: 477.41 | B224: 478.19 | C224: 460.91 | D224: 460.91 | E224: 2104911 | F224: Tue, 12 Aug 2025 00:00:00 GMT | G224: =A224/D224-1 -> 0.035798746 | I224: -0.038 | J224: 1 | L224: -0.039 | M224: =_xlfn.NORM.DIST(L224,$K$209,$K$211,FALSE) -> 0.70712064 | O224: -1σ | P224: =($K$211*-1)+$K$209 -> -0.014453147 | Q224: 0
A225: 462.39 | B225: 467.695 | C225: 459.33 | D225: 461.79 | E225: 1706673 | F225: Mon, 11 Aug 2025 00:00:00 GMT | G225: =A225/D225-1 -> 0.0012992919 | I225: -0.037 | J225: 1 | L225: -0.038 | M225: =_xlfn.NORM.DIST(L225,$K$209,$K$211,FALSE) -> 0.85192337 | P225: =($K$211*-1)+$K$209 -> -0.014453147 | Q225: 17
A226: 460.72 | B226: 461.72 | C226: 451.435 | D226: 453.49 | E226: 1689920 | F226: Fri, 08 Aug 2025 00:00:00 GMT | G226: =A226/D226-1 -> 0.01594302 | I226: -0.036 | J226: 1 | L226: -0.037 | M226: =_xlfn.NORM.DIST(L226,$K$209,$K$211,FALSE) -> 1.0214118 | O226: 1σ | P226: =($K$211*1)+$K$209 -> 0.014262704 | Q226: 0
A227: 454.74 | B227: 457.09 | C227: 451.17 | D227: 454.86 | E227: 1490175 | F227: Thu, 07 Aug 2025 00:00:00 GMT | G227: =A227/D227-1 -> -0.00026381744 | I227: -0.035 | J227: 3 | L227: -0.036 | M227: =_xlfn.NORM.DIST(L227,$K$209,$K$211,FALSE) -> 1.2186935 | P227: =($K$211*1)+$K$209 -> 0.014262704 | Q227: 17
A228: 448.94 | B228: 466.5 | C228: 446.28 | D228: 465.23 | E228: 2539468 | F228: Wed, 06 Aug 2025 00:00:00 GMT | G228: =A228/D228-1 -> -0.035014939 | I228: -0.034 | J228: 2 | L228: -0.035 | M228: =_xlfn.NORM.DIST(L228,$K$209,$K$211,FALSE) -> 1.447043 | O228: 2σ | P228: =($K$211*2)+$K$209 -> 0.028620629 | Q228: 0
A229: 466.42 | B229: 469.87 | C229: 464.84 | D229: 466.98 | E229: 1992305 | F229: Tue, 05 Aug 2025 00:00:00 GMT | G229: =A229/D229-1 -> -0.0011991948 | I229: -0.033 | J229: 3 | L229: -0.034 | M229: =_xlfn.NORM.DIST(L229,$K$209,$K$211,FALSE) -> 1.7098645 | P229: =($K$211*2)+$K$209 -> 0.028620629 | Q229: 4
A230: 466.57 | B230: 467.765 | C230: 456.54 | D230: 460.1 | E230: 2057405 | F230: Mon, 04 Aug 2025 00:00:00 GMT | G230: =A230/D230-1 -> 0.01406216 | I230: -0.032 | J230: 1 | L230: -0.033 | M230: =_xlfn.NORM.DIST(L230,$K$209,$K$211,FALSE) -> 2.0106443 | O230: 3σ | P230: =($K$211*3)+$K$209 -> 0.042978554 | Q230: 0
A231: 463.04 | B231: 464.1 | C231: 451.45 | D231: 461.03 | E231: 2750829 | F231: Fri, 01 Aug 2025 00:00:00 GMT | G231: =A231/D231-1 -> 0.004359803 | I231: -0.031 | J231: 1 | L231: -0.032 | M231: =_xlfn.NORM.DIST(L231,$K$209,$K$211,FALSE) -> 2.3528926 | P231: =($K$211*3)+$K$209 -> 0.042978554 | Q231: 2
A232: 467.68 | B232: 483.87 | C232: 466.74 | D232: 470.78 | E232: 3408669 | F232: Thu, 31 Jul 2025 00:00:00 GMT | G232: =A232/D232-1 -> -0.0065848167 | I232: -0.03 | J232: 5 | L232: -0.031 | M232: =_xlfn.NORM.DIST(L232,$K$209,$K$211,FALSE) -> 2.740074
A233: 477.28 | B233: 484.88 | C233: 473.65 | D233: 483.98 | E233: 2581694 | F233: Wed, 30 Jul 2025 00:00:00 GMT | G233: =A233/D233-1 -> -0.013843547 | I233: -0.029 | J233: 2 | L233: -0.03 | M233: =_xlfn.NORM.DIST(L233,$K$209,$K$211,FALSE) -> 3.1755267
A234: 482.16 | B234: 488.52 | C234: 480.4101 | D234: 482.24 | E234: 3028330 | F234: Tue, 29 Jul 2025 00:00:00 GMT | G234: =A234/D234-1 -> -0.0001658925 | I234: -0.028 | J234: 1 | L234: -0.029 | M234: =_xlfn.NORM.DIST(L234,$K$209,$K$211,FALSE) -> 3.6623729
A235: 484.96 | B235: 487.11 | C235: 474.87 | D235: 475.44 | E235: 3409832 | F235: Mon, 28 Jul 2025 00:00:00 GMT | G235: =A235/D235-1 -> 0.020023557 | I235: -0.027 | J235: 3 | L235: -0.028 | M235: =_xlfn.NORM.DIST(L235,$K$209,$K$211,FALSE) -> 4.2034189
A236: 478.32 | B236: 483.6 | C236: 474.405 | D236: 479.98 | E236: 4111685 | F236: Fri, 25 Jul 2025 00:00:00 GMT | G236: =A236/D236-1 -> -0.0034584774 | I236: -0.026 | J236: 6 | L236: -0.027 | M236: =_xlfn.NORM.DIST(L236,$K$209,$K$211,FALSE) -> 4.8010484
A237: 475.03 | B237: 484.6 | C237: 465.035 | D237: 466.67 | E237: 6234071 | F237: Thu, 24 Jul 2025 00:00:00 GMT | G237: =A237/D237-1 -> 0.017914158 | I237: -0.025 | J237: 3 | L237: -0.026 | M237: =_xlfn.NORM.DIST(L237,$K$209,$K$211,FALSE) -> 5.4571112
A238: 466.71 | B238: 487.93 | C238: 465.5501 | D238: 473.255 | E238: 8928524 | F238: Wed, 23 Jul 2025 00:00:00 GMT | G238: =A238/D238-1 -> -0.013829754 | I238: -0.024 | J238: 10 | L238: -0.025 | M238: =_xlfn.NORM.DIST(L238,$K$209,$K$211,FALSE) -> 6.1728088
A239: 427.62 | B239: 428.99 | C239: 405.15 | D239: 406.31 | E239: 3665528 | F239: Tue, 22 Jul 2025 00:00:00 GMT | G239: =A239/D239-1 -> 0.052447639 | I239: -0.023 | J239: 6 | L239: -0.024 | M239: =_xlfn.NORM.DIST(L239,$K$209,$K$211,FALSE) -> 6.9485816
A240: 404.94 | B240: 414.995 | C240: 403.36 | D240: 414.94 | E240: 2722938 | F240: Mon, 21 Jul 2025 00:00:00 GMT | G240: =A240/D240-1 -> -0.02409987 | I240: -0.022 | J240: 8 | L240: -0.023 | M240: =_xlfn.NORM.DIST(L240,$K$209,$K$211,FALSE) -> 7.7839997
A241: 414.75 | B241: 427.91 | C241: 411.41 | D241: 425.92 | E241: 2629681 | F241: Fri, 18 Jul 2025 00:00:00 GMT | G241: =A241/D241-1 -> -0.026225582 | I241: -0.021 | J241: 10 | L241: -0.022 | M241: =_xlfn.NORM.DIST(L241,$K$209,$K$211,FALSE) -> 8.6776627
A242: 424.98 | B242: 427 | C242: 413.29 | D242: 415 | E242: 2489763 | F242: Thu, 17 Jul 2025 00:00:00 GMT | G242: =A242/D242-1 -> 0.024048193 | I242: -0.02 | J242: 7 | L242: -0.021 | M242: =_xlfn.NORM.DIST(L242,$K$209,$K$211,FALSE) -> 9.6271121
A243: 416.31 | B243: 420.55 | C243: 413.78 | D243: 418.31 | E243: 2758638 | F243: Wed, 16 Jul 2025 00:00:00 GMT | G243: =A243/D243-1 -> -0.0047811432 | I243: -0.019 | J243: 9 | L243: -0.02 | M243: =_xlfn.NORM.DIST(L243,$K$209,$K$211,FALSE) -> 10.62876
A244: 417.99 | B244: 429 | C244: 417.2 | D244: 428.44 | E244: 2084826 | F244: Tue, 15 Jul 2025 00:00:00 GMT | G244: =A244/D244-1 -> -0.024390813 | I244: -0.018 | J244: 18 | L244: -0.019 | M244: =_xlfn.NORM.DIST(L244,$K$209,$K$211,FALSE) -> 11.677839 | AF244: Balance Sheet Scope:
A245: 425.34 | B245: 430.5 | C245: 422.04 | D245: 429 | E245: 2819144 | F245: Mon, 14 Jul 2025 00:00:00 GMT | G245: =A245/D245-1 -> -0.0085314685 | I245: -0.017 | J245: 7 | L245: -0.018 | M245: =_xlfn.NORM.DIST(L245,$K$209,$K$211,FALSE) -> 12.768376 | AF245: [Godel Snapshot of projected balances (assets, liabilities, equity)]
A246: 434.86 | B246: 436.32 | C246: 425.6501 | D246: 430.245 | E246: 2507609 | F246: Fri, 11 Jul 2025 00:00:00 GMT | G246: =A246/D246-1 -> 0.010726447 | I246: -0.016 | J246: 14 | L246: -0.017 | M246: =_xlfn.NORM.DIST(L246,$K$209,$K$211,FALSE) -> 13.893196
A247: 430.73 | B247: 438.4921 | C247: 418.32 | D247: 420.83 | E247: 2931032 | F247: Thu, 10 Jul 2025 00:00:00 GMT | G247: =A247/D247-1 -> 0.023524939 | I247: -0.015 | J247: 17 | L247: -0.016 | M247: =_xlfn.NORM.DIST(L247,$K$209,$K$211,FALSE) -> 15.043953
A248: 419.88 | B248: 429.39 | C248: 411.88 | D248: 422.2 | E248: 2719807 | F248: Wed, 09 Jul 2025 00:00:00 GMT | G248: =A248/D248-1 -> -0.0054950261 | I248: -0.014 | J248: 14 | L248: -0.015 | M248: =_xlfn.NORM.DIST(L248,$K$209,$K$211,FALSE) -> 16.211197
A249: 426.17 | B249: 433.135 | C249: 418.58 | D249: 418.58 | E249: 2617086 | F249: Tue, 08 Jul 2025 00:00:00 GMT | G249: =A249/D249-1 -> 0.018132734 | I249: -0.013 | J249: 19 | L249: -0.014 | M249: =_xlfn.NORM.DIST(L249,$K$209,$K$211,FALSE) -> 17.384472
A250: 418.7 | B250: 429.32 | C250: 415.42 | D250: 426.56 | E250: 2495788 | F250: Mon, 07 Jul 2025 00:00:00 GMT | G250: =A250/D250-1 -> -0.018426482 | I250: -0.012 | J250: 25 | L250: -0.013 | M250: =_xlfn.NORM.DIST(L250,$K$209,$K$211,FALSE) -> 18.552449
A251: 429.33 | B251: 432.9 | C251: 426.08 | D251: 428.62 | E251: 1359315 | F251: Thu, 03 Jul 2025 00:00:00 GMT | G251: =A251/D251-1 -> 0.0016564789 | I251: -0.011 | J251: 17 | L251: -0.012 | M251: =_xlfn.NORM.DIST(L251,$K$209,$K$211,FALSE) -> 19.703087
A252: 427.76 | B252: 430.46 | C252: 421.75 | D252: 425 | E252: 2663652 | F252: Wed, 02 Jul 2025 00:00:00 GMT | G252: =A252/D252-1 -> 0.0064941176 | I252: -0.01 | J252: 28 | L252: -0.011 | M252: =_xlfn.NORM.DIST(L252,$K$209,$K$211,FALSE) -> 20.823831
A253: 421.47 | B253: 429.1 | C253: 404.85 | D253: 406.29 | E253: 2601748 | F253: Tue, 01 Jul 2025 00:00:00 GMT | G253: =A253/D253-1 -> 0.037362475 | I253: -0.009 | J253: 31 | L253: -0.01 | M253: =_xlfn.NORM.DIST(L253,$K$209,$K$211,FALSE) -> 21.901824
A254: 405.46 | B254: 413.28 | C254: 401.45 | D254: 407.84 | E254: 3905950 | F254: Mon, 30 Jun 2025 00:00:00 GMT | G254: =A254/D254-1 -> -0.0058356218 | I254: -0.008 | J254: 22 | L254: -0.009 | M254: =_xlfn.NORM.DIST(L254,$K$209,$K$211,FALSE) -> 22.92415
A255: 408.28 | B255: 414.4 | C255: 406.95 | D255: 412.395 | E255: 3923072 | F255: Fri, 27 Jun 2025 00:00:00 GMT | G255: =A255/D255-1 -> -0.0099782975 | I255: -0.007 | J255: 32 | L255: -0.008 | M255: =_xlfn.NORM.DIST(L255,$K$209,$K$211,FALSE) -> 23.878086
A256: 412.12 | B256: 415.31 | C256: 409.275 | D256: 409.54 | E256: 2927706 | F256: Thu, 26 Jun 2025 00:00:00 GMT | G256: =A256/D256-1 -> 0.0062997509 | I256: -0.006 | J256: 40 | L256: -0.007 | M256: =_xlfn.NORM.DIST(L256,$K$209,$K$211,FALSE) -> 24.751362
A257: 410.65 | B257: 415 | C257: 398.08 | D257: 402.22 | E257: 3100914 | F257: Wed, 25 Jun 2025 00:00:00 GMT | G257: =A257/D257-1 -> 0.020958679 | I257: -0.005 | J257: 39 | L257: -0.006 | M257: =_xlfn.NORM.DIST(L257,$K$209,$K$211,FALSE) -> 25.532421
... A306: 448.8648 | B306: 450.37324 | C306: 441.54239 | D306: 447.53618 | E306: 2372974.8 | F306: Mon, 14 Apr 2025 00:00:00 GMT | G306: =A306/D306-1 -> 0.00296875 | I306: 0.044 | J306: 2 | L306: 0.043 | M306: =_xlfn.NORM.DIST(L306,$K$209,$K$211,FALSE) -> 0.30728876
A307: 437.69637 | B307: 440.2737 | C307: 419.56517 | D307: 429.54482 | E307: 2660180.1 | F307: Fri, 11 Apr 2025 00:00:00 GMT | G307: =A307/D307-1 -> 0.018977186 | I307: More | J307: 6 | L307: 0.044 | M307: =_xlfn.NORM.DIST(L307,$K$209,$K$211,FALSE) -> 0.24871673
A308: 426.99746 | B308: 448.13555 | C308: 414.88002 | D308: 445.93783 | E308: 3906413.4 | F308: Thu, 10 Apr 2025 00:00:00 GMT | G308: =A308/D308-1 -> -0.042473118 | L308: 0.045 | M308: =_xlfn.NORM.DIST(L308,$K$209,$K$211,FALSE) -> 0.20033491
A309: 453.08043 | B309: 454.5539 | C309: 409.42667 | D309: 414.20072 | E309: 4602444 | F309: Wed, 09 Apr 2025 00:00:00 GMT | G309: =A309/D309-1 -> 0.093866821
A310: 418.87588 | B310: 453.65983 | C310: 412.90207 | D310: 450.6929 | E310: 3933704.6 | F310: Tue, 08 Apr 2025 00:00:00 GMT | G310: =A310/D310-1 -> -0.070595797
A311: 437.41666 | B311: 452.87065 | C311: 410.78427 | D311: 417.33747 | E311: 4080477.6 | F311: Mon, 07 Apr 2025 00:00:00 GMT | G311: =A311/D311-1 -> 0.048112598
A312: 437.45662 | B312: 463.6295 | C312: 436.76734 | D312: 461.01221 | E312: 3898603.3 | F312: Fri, 04 Apr 2025 00:00:00 GMT | G312: =A312/D312-1 -> -0.051095365
A313: 469.54337 | B313: 485.40693 | C313: 467.68529 | D313: 481.39109 | E313: 2816545 | F313: Thu, 03 Apr 2025 00:00:00 GMT | G313: =A313/D313-1 -> -0.024611426
A314: 488.55367 | B314: 490.85128 | C314: 479.10346 | D314: 480.00253 | E314: 2070846 | F314: Wed, 02 Apr 2025 00:00:00 GMT | G314: =A314/D314-1 -> 0.017814776
A315: 482.46997 | B315: 495.99096 | C315: 480.71179 | D315: 495.04694 | E315: 1839542.5 | F315: Tue, 01 Apr 2025 00:00:00 GMT | G315: =A315/D315-1 -> -0.025405602
A316: 497.08482 | B316: 500.1017 | C316: 483.76862 | D316: 495.98596 | E316: 2918844.9 | F316: Mon, 31 Mar 2025 00:00:00 GMT | G316: =A316/D316-1 -> 0.0022155086
A317: 499.64217 | B317: 512.8335 | C317: 498.88296 | D317: 512.07928 | E317: 1789602.8 | F317: Fri, 28 Mar 2025 00:00:00 GMT | G317: =A317/D317-1 -> -0.02428747
A318: 511.15025 | B318: 514.79647 | C318: 507.53399 | D318: 513.45786 | E318: 1251325.5 | F318: Thu, 27 Mar 2025 00:00:00 GMT | G318: =A318/D318-1 -> -0.0044942509
...

Sheet Consumables

Sheet Instruments

Sheet Services

Sheet Management

Sheet Table Formatting
B2: [Bold Title] | G2: [Bold Title]
B3: Line Titles | G3: <-- General
B4: Line Titles | G4: <-- Info
B5: Line Titles | G5: <-- General
B6: Line Titles | G6: <-- Info
B7: Line Titles | G7: <-- General
B8: Line Titles | G8: <-- Info
